{
  "type": "Feature",
  "properties": {
    "gn:admin1_code":"4.0",
    "gn:admin2_code":"1861964.0",
    "gn:asciiname":"Hokkemachi",
    "gn:country_code":"JP",
    "gn:dem":21,
    "gn:feature_class":"P",
    "gn:feature_code":"PPL",
    "gn:name":"Hokkemachi",
    "gn:population":0,
    "gn:timezone":"Asia/Tokyo",
    "iso:country":"JP",
    "name:jpn_x_preferred":[
        "\u5317\u65b9\u753a"
    ],
    "name:jpn_x_variant":[
        "\u307b\u3063\u3051\u307e\u3061"
    ],
    "wof:name":"Hokkemachi",
    "wof:placetype":"locality"
},
  "geometry": {"coordinates":[139.9564,35.73195],"type":"Point"}
}