{
  "type": "Feature",
  "properties": {
    "gn:admin1_code":"27.0",
    "gn:admin2_code":"7418810.0",
    "gn:asciiname":"Wakata",
    "gn:country_code":"JP",
    "gn:dem":37,
    "gn:feature_class":"P",
    "gn:feature_code":"PPL",
    "gn:name":"Wakata",
    "gn:population":0,
    "gn:timezone":"Asia/Tokyo",
    "iso:country":"JP",
    "name:deu_x_preferred":[
        "Wakata"
    ],
    "name:jpn_x_preferred":[
        "\u82e5\u7530"
    ],
    "wof:name":"Wakata",
    "wof:placetype":"locality"
},
  "geometry": {"coordinates":[129.24018999999998,34.22367],"type":"Point"}
}