{
  "type": "Feature",
  "properties": {
    "gn:admin1_code":"19.0",
    "gn:admin2_code":"1859635.0",
    "gn:admin3_code":"14131.0",
    "gn:asciiname":"Ogawacho",
    "gn:country_code":"JP",
    "gn:dem":11,
    "gn:feature_class":"P",
    "gn:feature_code":"PPL",
    "gn:name":"Ogawach\u014d",
    "gn:population":0,
    "gn:timezone":"Asia/Tokyo",
    "iso:country":"JP",
    "name:jpn_x_preferred":[
        "\u5c0f\u5ddd\u753a"
    ],
    "name:und_x_variant":[
        "Ogawach\u014d"
    ],
    "wof:name":"Ogawacho",
    "wof:placetype":"locality"
},
  "geometry": {"coordinates":[139.6979,35.52779],"type":"Point"}
}