{
  "type": "Feature",
  "properties": {
    "gn:admin1_code":"7.0",
    "gn:admin2_code":"1851269.0",
    "gn:admin3_code":"40601.0",
    "gn:asciiname":"Yamashitamachi",
    "gn:country_code":"JP",
    "gn:dem":58,
    "gn:feature_class":"P",
    "gn:feature_code":"PPLL",
    "gn:name":"Yamashitamachi",
    "gn:population":0,
    "gn:timezone":"Asia/Tokyo",
    "iso:country":"JP",
    "name:jpn_x_preferred":[
        "\u5c71\u4e0b\u753a"
    ],
    "wof:name":"Yamashitamachi",
    "wof:placetype":"locality"
},
  "geometry": {"coordinates":[130.84573,33.67120999999999],"type":"Point"}
}