{
  "type": "Feature",
  "properties": {
    "gn:admin1_code":"21.0",
    "gn:admin2_code":"1864973.0",
    "gn:asciiname":"Akamizu",
    "gn:country_code":"JP",
    "gn:dem":490,
    "gn:feature_class":"P",
    "gn:feature_code":"PPL",
    "gn:name":"Akamizu",
    "gn:population":0,
    "gn:timezone":"Asia/Tokyo",
    "iso:country":"JP",
    "name:jpn_x_preferred":[
        "\u8d64\u6c34"
    ],
    "name:jpn_x_variant":[
        "\u3042\u304b\u307f\u305a",
        "\u30a2\u30ab\u30df\u30ba"
    ],
    "wof:name":"Akamizu",
    "wof:placetype":"locality"
},
  "geometry": {"coordinates":[130.99589,32.91701],"type":"Point"}
}