{
  "type": "Feature",
  "properties": {
    "gn:admin1_code":"21.0",
    "gn:admin2_code":"7412705.0",
    "gn:admin3_code":"43484.0",
    "gn:asciiname":"Uchino",
    "gn:country_code":"JP",
    "gn:dem":48,
    "gn:feature_class":"P",
    "gn:feature_code":"PPLL",
    "gn:name":"Uchino",
    "gn:population":0,
    "gn:timezone":"Asia/Tokyo",
    "iso:country":"JP",
    "name:jpn_x_preferred":[
        "\u5185\u91ce"
    ],
    "name:jpn_x_variant":[
        "\u3046\u3061\u306e",
        "\u30a6\u30c1\u30ce"
    ],
    "wof:name":"Uchino",
    "wof:placetype":"locality"
},
  "geometry": {"coordinates":[130.47295,32.24241],"type":"Point"}
}