{
  "type": "Feature",
  "properties": {
    "gn:admin1_code":"24.0",
    "gn:admin2_code":"7447001.0",
    "gn:asciiname":"Komukaihara",
    "gn:country_code":"JP",
    "gn:dem":418,
    "gn:feature_class":"P",
    "gn:feature_code":"PPL",
    "gn:name":"Komukaihara",
    "gn:population":0,
    "gn:timezone":"Asia/Tokyo",
    "iso:country":"JP",
    "name:jpn_x_preferred":[
        "\u5c0f\u5411\u539f"
    ],
    "name:jpn_x_variant":[
        "\u3053\u3080\u304b\u3044\u306f\u3089",
        "\u30b3\u30e0\u30ab\u30a4\u30cf\u30e9"
    ],
    "wof:name":"Komukaihara",
    "wof:placetype":"locality"
},
  "geometry": {"coordinates":[140.64311000000001,38.78458],"type":"Point"}
}