{
  "type": "Feature",
  "properties": {
    "gn:admin1_code":"17",
    "gn:admin2_code":"7391347.0",
    "gn:asciiname":"Sanbonmatsu",
    "gn:country_code":"JP",
    "gn:dem":7,
    "gn:feature_class":"P",
    "gn:feature_code":"PPL",
    "gn:name":"Sanbonmatsu",
    "gn:population":0,
    "gn:timezone":"Asia/Tokyo",
    "iso:country":"JP",
    "name:jpn_x_preferred":[
        "\u4e09\u672c\u677e"
    ],
    "name:und_x_variant":[
        "Sanbommatsu",
        "Sambommatsu",
        "Sanbonmatsu"
    ],
    "wof:name":"Sanbonmatsu",
    "wof:placetype":"locality"
},
  "geometry": {"coordinates":[134.33333000000002,34.25],"type":"Point"}
}