{
  "type": "Feature",
  "properties": {
    "gn:admin1_code":"12.0",
    "gn:admin2_code":"2127415.0",
    "gn:asciiname":"Yubari",
    "gn:country_code":"JP",
    "gn:dem":280,
    "gn:feature_class":"P",
    "gn:feature_code":"PPLA2",
    "gn:name":"Y\u016bbari",
    "gn:population":0,
    "gn:timezone":"Asia/Tokyo",
    "iso:country":"JP",
    "name:ara_x_preferred":[
        "\u064a\u0648\u0628\u0627\u0631\u064a"
    ],
    "name:aze_x_preferred":[
        "Y\u00fcbari"
    ],
    "name:epo_x_preferred":[
        "Jubari"
    ],
    "name:fas_x_preferred":[
        "\u06cc\u0648\u0628\u0627\u0631\u06cc\u060c \u0647\u0648\u06a9\u0627\u06cc\u062f\u0648"
    ],
    "name:ido_x_preferred":[
        "Yubari"
    ],
    "name:jpn_x_preferred":[
        "\u5915\u5f35"
    ],
    "name:jpn_x_variant":[
        "\u5915\u5f35\u5e02"
    ],
    "name:kor_x_preferred":[
        "\uc720\ubc14\ub9ac \uc2dc"
    ],
    "name:mzn_x_preferred":[
        "\u06cc\u0648\u0628\u0627\u0631\u06cc\u060c \u0647\u0648\u06a9\u0627\u06cc\u062f\u0648"
    ],
    "name:nan_x_preferred":[
        "Y\u00fbbari-chh\u012b"
    ],
    "name:nld_x_preferred":[
        "Yubari"
    ],
    "name:por_x_preferred":[
        "Yubari"
    ],
    "name:rus_x_preferred":[
        "\u042e\u0431\u0430\u0440\u0438"
    ],
    "name:tgk_x_preferred":[
        "\u042e\u0431\u0430\u0440\u0438"
    ],
    "name:tgl_x_preferred":[
        "Yubari"
    ],
    "name:tha_x_preferred":[
        "\u0e22\u0e39\u0e1a\u0e30\u0e23\u0e34"
    ],
    "name:ukr_x_preferred":[
        "\u042e\u0431\u0430\u0440\u0456"
    ],
    "name:und_x_variant":[
        "Y\u016bbari"
    ],
    "name:urd_x_preferred":[
        "\u06cc\u0648\u0628\u0631\u06cc\u060c \u06c1\u0648\u06a9\u06cc\u062f\u0648"
    ],
    "name:yue_x_preferred":[
        "\u5915\u5f35\u5e02"
    ],
    "name:zho_x_preferred":[
        "\u5915\u5f35\u5e02"
    ],
    "wof:name":"Yubari",
    "wof:placetype":"locality"
},
  "geometry": {"coordinates":[141.95778000000001,43.03778],"type":"Point"}
}