{
  "type": "Feature",
  "properties": {
    "gn:admin1_code":"21.0",
    "gn:admin2_code":"7413150.0",
    "gn:asciiname":"Harabu",
    "gn:country_code":"JP",
    "gn:dem":43,
    "gn:feature_class":"P",
    "gn:feature_code":"PPLL",
    "gn:name":"Harabu",
    "gn:population":0,
    "gn:timezone":"Asia/Tokyo",
    "iso:country":"JP",
    "name:jpn_x_preferred":[
        "\u539f\u90e8"
    ],
    "name:jpn_x_variant":[
        "\u306f\u3089\u3076",
        "\u30cf\u30e9\u30d6"
    ],
    "wof:name":"Harabu",
    "wof:placetype":"locality"
},
  "geometry": {"coordinates":[130.74393000000001,33.00044],"type":"Point"}
}