{
  "type": "Feature",
  "properties": {
    "gn:country":"JP",
    "gn:fcode":"ADM3",
    "gn:population":0,
    "iso:country":"JP",
    "name:eng_x_preferred":[
        "Kanmaki"
    ],
    "name:eng_x_variant":[
        "Kanmaki-ch\u014d"
    ],
    "name:jpn_x_preferred":[
        "\u4e0a\u7267\u753a"
    ],
    "name:jpn_x_variant":[
        "\u304b\u3093\u307e\u304d\u3061\u3087\u3046"
    ],
    "name:und_x_variant":[
        "Kanmaki Ch\u014d"
    ],
    "qs:name":"Kanmaki-ch\u014d",
    "qs:photos_9r":0,
    "qs:photos_sr":0,
    "qs:pop_sr":"0",
    "wof:name":"Kanmaki",
    "wof:placetype":"localadmin",
    "wof:population":0
},
  "geometry": {"coordinates":[135.71546000000001,34.56549],"type":"Point"}
}