{
  "type": "Feature",
  "properties": {
    "iso:country":"JP",
    "qs:name":"\u6709\u7530\u5ddd\u753a",
    "qs:name_adm0":"\u65e5\u672c",
    "qs:name_adm1":"\u548c\u6b4c\u5c71\u770c",
    "qs:photos":225,
    "qs:photos_1k":46,
    "qs:photos_9k":1,
    "qs:photos_9r":4,
    "qs:photos_all":225,
    "qs:photos_sr":4,
    "qs:placetype":"Town",
    "qs:pop_sr":"0",
    "wof:name":"\u6709\u7530\u5ddd\u753a",
    "wof:placetype":"locality"
},
  "geometry": {"coordinates":[135.44511700000001,34.093326],"type":"Point"}
}