{
  "type": "Feature",
  "properties": {
    "gn:admin1_code":"12.0",
    "gn:admin2_code":"7428089.0",
    "gn:admin3_code":"1631.0",
    "gn:asciiname":"Higashiasahi",
    "gn:country_code":"JP",
    "gn:dem":63,
    "gn:feature_class":"P",
    "gn:feature_code":"PPLL",
    "gn:name":"Higashiasahi",
    "gn:population":0,
    "gn:timezone":"Asia/Tokyo",
    "iso:country":"JP",
    "name:jpn_x_preferred":[
        "\u6771\u65ed"
    ],
    "wof:name":"Higashiasahi",
    "wof:placetype":"locality"
},
  "geometry": {"coordinates":[143.29061000000004,42.94383],"type":"Point"}
}