{
  "type": "Feature",
  "properties": {
    "gn:admin1_code":"2.0",
    "gn:admin2_code":"7443156.0",
    "gn:asciiname":"Mitsukita",
    "gn:country_code":"JP",
    "gn:dem":36,
    "gn:feature_class":"P",
    "gn:feature_code":"PPL",
    "gn:name":"Mitsukita",
    "gn:population":0,
    "gn:timezone":"Asia/Tokyo",
    "iso:country":"JP",
    "name:jpn_x_preferred":[
        "\u4e09\u6728\u7530"
    ],
    "wof:name":"Mitsukita",
    "wof:placetype":"locality"
},
  "geometry": {"coordinates":[140.30938999999998,40.11519000000001],"type":"Point"}
}