{
  "type": "Feature",
  "properties": {
    "gn:admin1_code":"13.0",
    "gn:admin2_code":"1851011.0",
    "gn:asciiname":"Hanayashiki",
    "gn:country_code":"JP",
    "gn:dem":73,
    "gn:feature_class":"P",
    "gn:feature_code":"PPL",
    "gn:name":"Hanayashiki",
    "gn:population":0,
    "gn:timezone":"Asia/Tokyo",
    "iso:country":"JP",
    "name:jpn_x_preferred":[
        "\u82b1\u5c4b\u6577"
    ],
    "wof:name":"Hanayashiki",
    "wof:placetype":"locality"
},
  "geometry": {"coordinates":[135.40223,34.82913],"type":"Point"}
}