{
  "type": "Feature",
  "properties": {
    "gn:admin1_code":"13.0",
    "gn:admin2_code":"1851011.0",
    "gn:asciiname":"Hanayashiki",
    "gn:country_code":"JP",
    "gn:dem":73,
    "gn:feature_class":"P",
    "gn:feature_code":"PPL",
    "gn:name":"Hanayashiki",
    "gn:population":0,
    "gn:timezone":"Asia/Tokyo",
    "iso:country":"JP",
    "name:fra_x_preferred":[
        "Parc Hanayashiki"
    ],
    "name:ita_x_preferred":[
        "Asakusa Hanayashiki"
    ],
    "name:jpn_x_preferred":[
        "\u82b1\u5c4b\u6577"
    ],
    "name:jpn_x_variant":[
        "\u6d45\u8349\u82b1\u3084\u3057\u304d"
    ],
    "name:kor_x_preferred":[
        "\ud558\ub098\uc57c\uc2dc\ud0a4"
    ],
    "name:zho_x_preferred":[
        "\u6d45\u8349\u82b1\u5c4b\u6577"
    ],
    "wof:name":"Hanayashiki",
    "wof:placetype":"locality"
},
  "geometry": {"coordinates":[135.40223,34.82913],"type":"Point"}
}