{
  "type": "Feature",
  "properties": {
    "gn:admin1_code":"19.0",
    "gn:admin2_code":"1859635.0",
    "gn:admin3_code":"14137.0",
    "gn:asciiname":"Nijigaoka",
    "gn:country_code":"JP",
    "gn:dem":54,
    "gn:feature_class":"P",
    "gn:feature_code":"PPL",
    "gn:name":"Nijigaoka",
    "gn:population":0,
    "gn:timezone":"Asia/Tokyo",
    "iso:country":"JP",
    "name:jpn_x_preferred":[
        "\u8679\u30f6\u4e18"
    ],
    "wof:name":"Nijigaoka",
    "wof:placetype":"locality"
},
  "geometry": {"coordinates":[139.52321000000001,35.57946],"type":"Point"}
}