{
  "type": "Feature",
  "properties": {
    "gn:admin1_code":"21.0",
    "gn:admin2_code":"1865358.0",
    "gn:asciiname":"Shinwamachi-otao",
    "gn:country_code":"JP",
    "gn:dem":84,
    "gn:feature_class":"P",
    "gn:feature_code":"PPL",
    "gn:name":"Shinwamachi-\u014dtao",
    "gn:population":0,
    "gn:timezone":"Asia/Tokyo",
    "iso:country":"JP",
    "name:jpn_x_preferred":[
        "\u65b0\u548c\u753a\u5927\u591a\u5c3e"
    ],
    "name:jpn_x_variant":[
        "\u3057\u3093\u308f\u307e\u3061\u304a\u304a\u305f\u304a",
        "\u30b7\u30f3\u30ef\u30de\u30c1\u30aa\u30aa\u30bf\u30aa"
    ],
    "name:und_x_variant":[
        "Shinwamachi-\u014dtao"
    ],
    "wof:name":"Shinwamachi-otao",
    "wof:placetype":"locality"
},
  "geometry": {"coordinates":[130.21066000000002,32.37013],"type":"Point"}
}