{
  "type": "Feature",
  "properties": {
    "gn:admin1_code":"33.0",
    "gn:admin2_code":"8300623.0",
    "gn:asciiname":"Ochicho-kuroiwa",
    "gn:country_code":"JP",
    "gn:dem":20,
    "gn:feature_class":"P",
    "gn:feature_code":"PPL",
    "gn:name":"\u014cchich\u014d-kuroiwa",
    "gn:population":0,
    "gn:timezone":"Asia/Tokyo",
    "iso:country":"JP",
    "name:jpn_x_preferred":[
        "\u76f8\u77e5\u753a\u9ed2\u5ca9"
    ],
    "name:und_x_variant":[
        "\u014cchich\u014d-kuroiwa"
    ],
    "wof:name":"Ochicho-kuroiwa",
    "wof:placetype":"locality"
},
  "geometry": {"coordinates":[130.00462999999999,33.37117],"type":"Point"}
}