{
  "type": "Feature",
  "properties": {
    "gn:admin1_code":"21.0",
    "gn:admin2_code":"1865358.0",
    "gn:asciiname":"Tatsugagoe",
    "gn:country_code":"JP",
    "gn:dem":21,
    "gn:feature_class":"P",
    "gn:feature_code":"PPLL",
    "gn:name":"Tatsugagoe",
    "gn:population":0,
    "gn:timezone":"Asia/Tokyo",
    "iso:country":"JP",
    "name:jpn_x_preferred":[
        "\u8fb0\u30f6\u8d8a"
    ],
    "name:jpn_x_variant":[
        "\u305f\u3064\u304c\u3054\u3048",
        "\u30bf\u30c4\u30ac\u30b4\u30a8"
    ],
    "wof:name":"Tatsugagoe",
    "wof:placetype":"locality"
},
  "geometry": {"coordinates":[130.01886000000002,32.22158],"type":"Point"}
}