{
  "type": "Feature",
  "properties": {
    "gn:admin1_code":"11",
    "gn:admin2_code":"1853990.0",
    "gn:asciiname":"Ichi",
    "gn:country_code":"JP",
    "gn:dem":79,
    "gn:feature_class":"P",
    "gn:feature_code":"PPL",
    "gn:name":"Ichi",
    "gn:population":0,
    "gn:timezone":"Asia/Tokyo",
    "iso:country":"JP",
    "wof:name":"Ichi",
    "wof:placetype":"locality"
},
  "geometry": {"coordinates":[133.15000000000001,34.51667],"type":"Point"}
}