{
  "type": "Feature",
  "properties": {
    "gn:admin1_code":"3.0",
    "gn:admin2_code":"2128302.0",
    "gn:admin3_code":"2441.0",
    "gn:asciiname":"Kuzuhata",
    "gn:country_code":"JP",
    "gn:dem":273,
    "gn:feature_class":"P",
    "gn:feature_code":"PPL",
    "gn:name":"Kuzuhata",
    "gn:population":0,
    "gn:timezone":"Asia/Tokyo",
    "iso:country":"JP",
    "name:jpn_x_preferred":[
        "\u845b\u7551"
    ],
    "name:jpn_x_variant":[
        "\u304f\u305a\u306f\u305f",
        "\u30af\u30ba\u30cf\u30bf"
    ],
    "wof:name":"Kuzuhata",
    "wof:placetype":"locality"
},
  "geometry": {"coordinates":[141.06881000000001,40.38709],"type":"Point"}
}