{
  "type": "Feature",
  "properties": {
    "gn:admin1_code":"43",
    "gn:admin2_code":"1862767.0",
    "gn:admin3_code":"30424.0",
    "gn:asciiname":"Mitogawa",
    "gn:cc2":"JP",
    "gn:country_code":"JP",
    "gn:dem":60,
    "gn:feature_class":"P",
    "gn:feature_code":"PPL",
    "gn:name":"Mitogawa",
    "gn:population":0,
    "gn:timezone":"Asia/Tokyo",
    "iso:country":"JP",
    "name:und_x_variant":[
        "Miokawa",
        "Mitogawa"
    ],
    "wof:name":"Mitogawa",
    "wof:placetype":"locality"
},
  "geometry": {"coordinates":[135.68333000000001,33.55],"type":"Point"}
}