{
  "type": "Feature",
  "properties": {
    "gn:admin1_code":"2.0",
    "gn:admin2_code":"2113122.0",
    "gn:asciiname":"Kamimoroi",
    "gn:country_code":"JP",
    "gn:dem":25,
    "gn:feature_class":"P",
    "gn:feature_code":"PPL",
    "gn:name":"Kamimoroi",
    "gn:population":0,
    "gn:timezone":"Asia/Tokyo",
    "iso:country":"JP",
    "name:jpn_x_preferred":[
        "\u4e0a\u8af8\u4e95"
    ],
    "name:jpn_x_variant":[
        "\u304b\u307f\u3082\u308d\u3044",
        "\u30ab\u30df\u30e2\u30ed\u30a4"
    ],
    "wof:name":"Kamimoroi",
    "wof:placetype":"locality"
},
  "geometry": {"coordinates":[140.24504999999999,39.66518],"type":"Point"}
}