{
  "type": "Feature",
  "properties": {
    "gn:admin1_code":"21.0",
    "gn:admin2_code":"1864973.0",
    "gn:asciiname":"Shimoyokobori",
    "gn:country_code":"JP",
    "gn:dem":777,
    "gn:feature_class":"P",
    "gn:feature_code":"PPLL",
    "gn:name":"Shimoyokobori",
    "gn:population":0,
    "gn:timezone":"Asia/Tokyo",
    "iso:country":"JP",
    "name:jpn_x_preferred":[
        "\u4e0b\u6a2a\u5800"
    ],
    "name:jpn_x_variant":[
        "\u3057\u3082\u3088\u3053\u307c\u308a",
        "\u30b7\u30e2\u30e8\u30b3\u30dc\u30ea"
    ],
    "wof:name":"Shimoyokobori",
    "wof:placetype":"locality"
},
  "geometry": {"coordinates":[131.18709999999999,32.91694],"type":"Point"}
}