{
  "type": "Feature",
  "properties": {
    "gn:admin1_code":"15",
    "gn:admin2_code":"1851337.0",
    "gn:asciiname":"Otanimachi",
    "gn:country_code":"JP",
    "gn:dem":20,
    "gn:feature_class":"P",
    "gn:feature_code":"PPL",
    "gn:name":"\u014ctanimachi",
    "gn:population":0,
    "gn:timezone":"Asia/Tokyo",
    "iso:country":"JP",
    "name:jpn_x_preferred":[
        "\u5927\u8c37\u753a"
    ],
    "name:und_x_variant":[
        "\u014ctanimachi",
        "\u014ctani"
    ],
    "wof:name":"Otanimachi",
    "wof:placetype":"locality"
},
  "geometry": {"coordinates":[137.17259000000001,37.49957],"type":"Point"}
}