{
  "type": "Feature",
  "properties": {
    "gn:admin1_code":"12.0",
    "gn:admin2_code":"2130044.0",
    "gn:admin3_code":"1363.0",
    "gn:asciiname":"Sakanoue",
    "gn:country_code":"JP",
    "gn:dem":64,
    "gn:feature_class":"P",
    "gn:feature_code":"PPL",
    "gn:name":"Sakanoue",
    "gn:population":0,
    "gn:timezone":"Asia/Tokyo",
    "iso:country":"JP",
    "wof:name":"Sakanoue",
    "wof:placetype":"locality"
},
  "geometry": {"coordinates":[140.28756999999999,41.91506],"type":"Point"}
}