{
  "type": "Feature",
  "properties": {
    "gn:admin1_code":"19.0",
    "gn:admin2_code":"1848350.0",
    "gn:admin3_code":"14102.0",
    "gn:asciiname":"Kinkocho",
    "gn:country_code":"JP",
    "gn:dem":12,
    "gn:feature_class":"P",
    "gn:feature_code":"PPL",
    "gn:name":"Kink\u014dch\u014d",
    "gn:population":0,
    "gn:timezone":"Asia/Tokyo",
    "iso:country":"JP",
    "name:jpn_x_preferred":[
        "\u91d1\u6e2f\u753a"
    ],
    "name:jpn_x_variant":[
        "\u304d\u3093\u3053\u3046\u3061\u3087\u3046",
        "\u30ad\u30f3\u30b3\u30a6\u30c1\u30e7\u30a6"
    ],
    "name:und_x_variant":[
        "Kink\u014dch\u014d"
    ],
    "wof:name":"Kinkocho",
    "wof:placetype":"locality"
},
  "geometry": {"coordinates":[139.62638000000001,35.46718],"type":"Point"}
}