{
  "type": "Feature",
  "properties": {
    "gn:admin1_code":"34.0",
    "gn:admin2_code":"1854369.0",
    "gn:asciiname":"Tamukai",
    "gn:country_code":"JP",
    "gn:dem":19,
    "gn:feature_class":"P",
    "gn:feature_code":"PPLL",
    "gn:name":"Tamukai",
    "gn:population":0,
    "gn:timezone":"Asia/Tokyo",
    "iso:country":"JP",
    "name:jpn_x_preferred":[
        "\u7530\u5411"
    ],
    "wof:name":"Tamukai",
    "wof:placetype":"locality"
},
  "geometry": {"coordinates":[139.53036,35.98271],"type":"Point"}
}