{
  "type": "Feature",
  "properties": {
    "gn:admin1_code":"21.0",
    "gn:admin2_code":"1865168.0",
    "gn:asciiname":"Yamato",
    "gn:country_code":"JP",
    "gn:dem":23,
    "gn:feature_class":"P",
    "gn:feature_code":"PPLL",
    "gn:name":"Yamato",
    "gn:population":0,
    "gn:timezone":"Asia/Tokyo",
    "iso:country":"JP",
    "name:jpn_x_preferred":[
        "\u5927\u548c"
    ],
    "name:jpn_x_variant":[
        "\u3084\u307e\u3068",
        "\u30e4\u30de\u30c8"
    ],
    "wof:name":"Yamato",
    "wof:placetype":"locality"
},
  "geometry": {"coordinates":[130.46812,32.97719],"type":"Point"}
}