{
  "type": "Feature",
  "properties": {
    "gn:admin1_code":"21.0",
    "gn:admin2_code":"1865168.0",
    "gn:asciiname":"Yamato",
    "gn:country_code":"JP",
    "gn:dem":23,
    "gn:feature_class":"P",
    "gn:feature_code":"PPLL",
    "gn:name":"Yamato",
    "gn:population":0,
    "gn:timezone":"Asia/Tokyo",
    "iso:country":"JP",
    "name:bul_x_preferred":[
        "\u042f\u043c\u0430\u0442\u043e"
    ],
    "name:ceb_x_preferred":[
        "Yamato"
    ],
    "name:deu_x_preferred":[
        "Yamato"
    ],
    "name:epo_x_preferred":[
        "Yamato"
    ],
    "name:est_x_preferred":[
        "Yamato"
    ],
    "name:fas_x_preferred":[
        "\u06cc\u0627\u0645\u0627\u062a\u0648"
    ],
    "name:fin_x_preferred":[
        "Yamato"
    ],
    "name:fra_x_preferred":[
        "Yamato"
    ],
    "name:glg_x_preferred":[
        "Yamato"
    ],
    "name:hrv_x_preferred":[
        "Yamato"
    ],
    "name:ind_x_preferred":[
        "Yamato"
    ],
    "name:ita_x_preferred":[
        "Yamato"
    ],
    "name:jpn_x_preferred":[
        "\u5927\u548c"
    ],
    "name:jpn_x_variant":[
        "\u3084\u307e\u3068",
        "\u30e4\u30de\u30c8"
    ],
    "name:kor_x_preferred":[
        "\uc57c\ub9c8\ud1a0"
    ],
    "name:nld_x_preferred":[
        "Yamato"
    ],
    "name:nor_x_preferred":[
        "Yamato"
    ],
    "name:pol_x_preferred":[
        "Yamato"
    ],
    "name:por_x_preferred":[
        "Yamato"
    ],
    "name:ron_x_preferred":[
        "Yamato"
    ],
    "name:rus_x_preferred":[
        "\u042f\u043c\u0430\u0442\u043e"
    ],
    "name:spa_x_preferred":[
        "Yamato"
    ],
    "name:srp_x_preferred":[
        "\u0408\u0430\u043c\u0430\u0442\u043e"
    ],
    "name:swe_x_preferred":[
        "Yamato"
    ],
    "name:tha_x_preferred":[
        "\u0e22\u0e30\u0e21\u0e30\u0e42\u0e15\u0e30"
    ],
    "name:ukr_x_preferred":[
        "\u042f\u043c\u0430\u0442\u043e"
    ],
    "name:uzb_x_preferred":[
        "Yamato"
    ],
    "name:vie_x_preferred":[
        "Yamato"
    ],
    "wof:name":"Yamato",
    "wof:placetype":"locality"
},
  "geometry": {"coordinates":[130.46812,32.97719],"type":"Point"}
}