{
  "type": "Feature",
  "properties": {
    "gn:admin1_code":"16.0",
    "gn:admin2_code":"2110604.0",
    "gn:admin3_code":"3366.0",
    "gn:asciiname":"Kawashiri",
    "gn:cc2":"JP",
    "gn:country_code":"JP",
    "gn:dem":222,
    "gn:feature_class":"P",
    "gn:feature_code":"PPL",
    "gn:name":"Kawashiri",
    "gn:population":0,
    "gn:timezone":"Asia/Tokyo",
    "iso:country":"JP",
    "name:jpn_x_preferred":[
        "\u5ddd\u5c3b"
    ],
    "name:und_x_variant":[
        "Kawajiri",
        "Kawashiri"
    ],
    "wof:name":"Kawashiri",
    "wof:placetype":"locality"
},
  "geometry": {"coordinates":[140.78333000000001,39.31667],"type":"Point"}
}