{
  "type": "Feature",
  "properties": {
    "gn:admin1_code":"24.0",
    "gn:admin2_code":"2112261.0",
    "gn:asciiname":"Matsuzaki-shimokanetori",
    "gn:country_code":"JP",
    "gn:dem":103,
    "gn:feature_class":"P",
    "gn:feature_code":"PPL",
    "gn:name":"Matsuzaki-shimokanetori",
    "gn:population":0,
    "gn:timezone":"Asia/Tokyo",
    "iso:country":"JP",
    "name:jpn_x_preferred":[
        "\u677e\u5d0e\u4e0b\u91d1\u53d6"
    ],
    "name:jpn_x_variant":[
        "\u307e\u3064\u3056\u304d\u3057\u3082\u304b\u306d\u3068\u308a",
        "\u30de\u30c4\u30b6\u30ad\u30b7\u30e2\u30ab\u30cd\u30c8\u30ea"
    ],
    "wof:name":"Matsuzaki-shimokanetori",
    "wof:placetype":"locality"
},
  "geometry": {"coordinates":[141.53093000000001,38.8543],"type":"Point"}
}