{
  "type": "Feature",
  "properties": {
    "gn:admin1_code":"7.0",
    "gn:admin2_code":"1848086.0",
    "gn:asciiname":"Sukisako",
    "gn:country_code":"JP",
    "gn:dem":26,
    "gn:feature_class":"P",
    "gn:feature_code":"PPLL",
    "gn:name":"Sukisako",
    "gn:population":0,
    "gn:timezone":"Asia/Tokyo",
    "iso:country":"JP",
    "name:jpn_x_preferred":[
        "\u92e4\u8feb"
    ],
    "wof:name":"Sukisako",
    "wof:placetype":"locality"
},
  "geometry": {"coordinates":[130.93778999999998,33.68151],"type":"Point"}
}