{
  "type": "Feature",
  "properties": {
    "gn:admin1_code":"15.0",
    "gn:admin2_code":"7467839.0",
    "gn:admin3_code":"17461.0",
    "gn:asciiname":"Ikuro",
    "gn:country_code":"JP",
    "gn:dem":141,
    "gn:feature_class":"P",
    "gn:feature_code":"PPL",
    "gn:name":"Ikuro",
    "gn:population":0,
    "gn:timezone":"Asia/Tokyo",
    "iso:country":"JP",
    "name:jpn_x_preferred":[
        "\u4f0a\u4e45\u7559"
    ],
    "wof:name":"Ikuro",
    "wof:placetype":"locality"
},
  "geometry": {"coordinates":[136.98197999999999,37.27877],"type":"Point"}
}