{
  "type": "Feature",
  "properties": {
    "gn:admin1_code":"21.0",
    "gn:admin2_code":"1857206.0",
    "gn:asciiname":"Tsukinoura",
    "gn:country_code":"JP",
    "gn:dem":32,
    "gn:feature_class":"P",
    "gn:feature_code":"PPL",
    "gn:name":"Tsukinoura",
    "gn:population":0,
    "gn:timezone":"Asia/Tokyo",
    "iso:country":"JP",
    "name:jpn_x_preferred":[
        "\u6708\u6d66"
    ],
    "name:jpn_x_variant":[
        "\u3064\u304d\u306e\u3046\u3089",
        "\u30c4\u30ad\u30ce\u30a6\u30e9"
    ],
    "wof:name":"Tsukinoura",
    "wof:placetype":"locality"
},
  "geometry": {"coordinates":[130.38149000000001,32.19016],"type":"Point"}
}