{
  "type": "Feature",
  "properties": {
    "gn:admin1_code":"21.0",
    "gn:admin2_code":"1858418.0",
    "gn:admin3_code":"43104.0",
    "gn:asciiname":"Minamitakae",
    "gn:country_code":"JP",
    "gn:dem":4,
    "gn:feature_class":"P",
    "gn:feature_code":"PPL",
    "gn:name":"Minamitakae",
    "gn:population":0,
    "gn:timezone":"Asia/Tokyo",
    "iso:country":"JP",
    "name:jpn_x_preferred":[
        "\u5357\u9ad8\u6c5f"
    ],
    "name:jpn_x_variant":[
        "\u307f\u306a\u307f\u305f\u304b\u3048",
        "\u30df\u30ca\u30df\u30bf\u30ab\u30a8"
    ],
    "wof:name":"Minamitakae",
    "wof:placetype":"locality"
},
  "geometry": {"coordinates":[130.68618999999998,32.75234],"type":"Point"}
}