{
  "type": "Feature",
  "properties": {
    "gn:admin1_code":"13.0",
    "gn:admin2_code":"1859161.0",
    "gn:admin3_code":"28108.0",
    "gn:asciiname":"Tamondai",
    "gn:country_code":"JP",
    "gn:dem":69,
    "gn:feature_class":"P",
    "gn:feature_code":"PPL",
    "gn:name":"Tamondai",
    "gn:population":0,
    "gn:timezone":"Asia/Tokyo",
    "iso:country":"JP",
    "name:jpn_x_preferred":[
        "\u591a\u805e\u53f0"
    ],
    "wof:name":"Tamondai",
    "wof:placetype":"locality"
},
  "geometry": {"coordinates":[135.04245,34.66176],"type":"Point"}
}