{
  "type": "Feature",
  "properties": {
    "gn:admin1_code":"23.0",
    "gn:admin2_code":"1857496.0",
    "gn:asciiname":"Ureshino-kamodacho",
    "gn:country_code":"JP",
    "gn:dem":32,
    "gn:feature_class":"P",
    "gn:feature_code":"PPL",
    "gn:name":"Ureshino-kamodach\u014d",
    "gn:population":0,
    "gn:timezone":"Asia/Tokyo",
    "iso:country":"JP",
    "name:jpn_x_preferred":[
        "\u5b09\u91ce\u91dc\u751f\u7530\u753a"
    ],
    "name:und_x_variant":[
        "Ureshino-kamodach\u014d"
    ],
    "wof:name":"Ureshino-kamodacho",
    "wof:placetype":"locality"
},
  "geometry": {"coordinates":[136.43421999999998,34.61566],"type":"Point"}
}