{
  "type": "Feature",
  "properties": {
    "gn:admin1_code":"21.0",
    "gn:admin2_code":"1858418.0",
    "gn:admin3_code":"43104.0",
    "gn:asciiname":"Nijitcho",
    "gn:country_code":"JP",
    "gn:dem":-2,
    "gn:feature_class":"P",
    "gn:feature_code":"PPLL",
    "gn:name":"Nijitch\u014d",
    "gn:population":0,
    "gn:timezone":"Asia/Tokyo",
    "iso:country":"JP",
    "name:jpn_x_preferred":[
        "\u5f10\u62fe\u753a"
    ],
    "name:jpn_x_variant":[
        "\u306b\u3058\u3063\u3061\u3087\u3046",
        "\u30cb\u30b8\u30c3\u30c1\u30e7\u30a6"
    ],
    "name:und_x_variant":[
        "Nijitch\u014d"
    ],
    "wof:name":"Nijitcho",
    "wof:placetype":"locality"
},
  "geometry": {"coordinates":[130.62285,32.72323],"type":"Point"}
}