{
  "type": "Feature",
  "properties": {
    "gn:admin1_code":"16.0",
    "gn:admin2_code":"2112822.0",
    "gn:asciiname":"Tokaichi",
    "gn:country_code":"JP",
    "gn:dem":83,
    "gn:feature_class":"P",
    "gn:feature_code":"PPL",
    "gn:name":"T\u014dkaichi",
    "gn:population":0,
    "gn:timezone":"Asia/Tokyo",
    "iso:country":"JP",
    "name:jpn_x_preferred":[
        "\u5341\u65e5\u5e02"
    ],
    "name:jpn_x_variant":[
        "\u3068\u3046\u304b\u3044\u3061",
        "\u30c8\u30a6\u30ab\u30a4\u30c1",
        "\u5341\u65e5\u753a"
    ],
    "name:und_x_variant":[
        "T\u014dkaichi",
        "T\u014dkamachi"
    ],
    "wof:name":"Tokaichi",
    "wof:placetype":"locality"
},
  "geometry": {"coordinates":[141.16364999999999,39.46199],"type":"Point"}
}