{
  "type": "Feature",
  "properties": {
    "gn:admin1_code":"28.0",
    "gn:admin2_code":"1848164.0",
    "gn:admin3_code":"29441.0",
    "gn:asciiname":"Irou",
    "gn:country_code":"JP",
    "gn:dem":310,
    "gn:feature_class":"P",
    "gn:feature_code":"PPL",
    "gn:name":"Irou",
    "gn:population":0,
    "gn:timezone":"Asia/Tokyo",
    "iso:country":"JP",
    "name:jpn_x_preferred":[
        "\u8272\u751f"
    ],
    "wof:name":"Irou",
    "wof:placetype":"locality"
},
  "geometry": {"coordinates":[135.93186,34.40972],"type":"Point"}
}