{
  "type": "Feature",
  "properties": {
    "gn:admin1_code":"37.0",
    "gn:admin2_code":"1864089.0",
    "gn:asciiname":"Hinoki-shinden",
    "gn:country_code":"JP",
    "gn:dem":13,
    "gn:feature_class":"P",
    "gn:feature_code":"PPL",
    "gn:name":"Hinoki-shinden",
    "gn:population":0,
    "gn:timezone":"Asia/Tokyo",
    "iso:country":"JP",
    "name:jpn_x_preferred":[
        "\u6867\u65b0\u7530"
    ],
    "wof:name":"Hinoki-shinden",
    "wof:placetype":"locality"
},
  "geometry": {"coordinates":[138.72951,35.13719],"type":"Point"}
}