{
  "type": "Feature",
  "properties": {
    "gn:admin1_code":"04",
    "gn:admin2_code":"7465521.0",
    "gn:asciiname":"Hongo",
    "gn:country_code":"JP",
    "gn:dem":77,
    "gn:feature_class":"P",
    "gn:feature_code":"PPL",
    "gn:name":"Hong\u014d",
    "gn:population":0,
    "gn:timezone":"Asia/Tokyo",
    "iso:country":"JP",
    "wof:name":"Hongo",
    "wof:placetype":"locality"
},
  "geometry": {"coordinates":[139.8673,34.91237],"type":"Point"}
}