{
  "type": "Feature",
  "properties": {
    "gn:admin1_code":"19.0",
    "gn:admin2_code":"1859635.0",
    "gn:admin3_code":"14133.0",
    "gn:asciiname":"Shinmarukomachi",
    "gn:country_code":"JP",
    "gn:dem":18,
    "gn:feature_class":"P",
    "gn:feature_code":"PPL",
    "gn:name":"Shinmarukomachi",
    "gn:population":0,
    "gn:timezone":"Asia/Tokyo",
    "iso:country":"JP",
    "name:jpn_x_preferred":[
        "\u65b0\u4e38\u5b50\u753a"
    ],
    "wof:name":"Shinmarukomachi",
    "wof:placetype":"locality"
},
  "geometry": {"coordinates":[139.66139999999999,35.58185],"type":"Point"}
}