{
  "type": "Feature",
  "properties": {
    "gn:admin1_code":"3.0",
    "gn:admin2_code":"8534376.0",
    "gn:admin3_code":"2321.0",
    "gn:asciiname":"Hosogadaira",
    "gn:country_code":"JP",
    "gn:dem":180,
    "gn:feature_class":"P",
    "gn:feature_code":"PPLL",
    "gn:name":"Hosogadaira",
    "gn:population":0,
    "gn:timezone":"Asia/Tokyo",
    "iso:country":"JP",
    "name:jpn_x_preferred":[
        "\u7d30\u30f6\u5e73"
    ],
    "name:jpn_x_variant":[
        "\u307b\u305d\u304c\u3060\u3044\u3089",
        "\u30db\u30bd\u30ac\u30c0\u30a4\u30e9"
    ],
    "wof:name":"Hosogadaira",
    "wof:placetype":"locality"
},
  "geometry": {"coordinates":[140.20799,40.69641],"type":"Point"}
}