{
  "type": "Feature",
  "properties": {
    "gn:admin1_code":"7.0",
    "gn:admin2_code":"7407416.0",
    "gn:asciiname":"Furuyashiki",
    "gn:country_code":"JP",
    "gn:dem":248,
    "gn:feature_class":"P",
    "gn:feature_code":"PPLL",
    "gn:name":"Furuyashiki",
    "gn:population":0,
    "gn:timezone":"Asia/Tokyo",
    "iso:country":"JP",
    "name:jpn_x_preferred":[
        "\u53e4\u5c4b\u6577"
    ],
    "wof:name":"Furuyashiki",
    "wof:placetype":"locality"
},
  "geometry": {"coordinates":[130.59365,33.66025],"type":"Point"}
}