{
  "type": "Feature",
  "properties": {
    "iso:country":"JP",
    "qs:name":"\u5c71\u8fba\u753a",
    "qs:name_adm0":"\u65e5\u672c",
    "qs:name_adm1":"\u5c71\u5f62\u770c",
    "qs:photos":38,
    "qs:photos_1k":8,
    "qs:photos_9k":1,
    "qs:photos_9r":2,
    "qs:photos_all":38,
    "qs:photos_sr":2,
    "qs:placetype":"Town",
    "qs:pop_sr":"0",
    "wof:name":"\u5c71\u8fba\u753a",
    "wof:placetype":"locality"
},
  "geometry": {"coordinates":[140.252959,38.253953],"type":"Point"}
}