{
  "type": "Feature",
  "properties": {
    "gn:admin1_code":"4.0",
    "gn:admin2_code":"1859468.0",
    "gn:asciiname":"Kungasaku",
    "gn:country_code":"JP",
    "gn:dem":36,
    "gn:feature_class":"P",
    "gn:feature_code":"PPLL",
    "gn:name":"Kungasaku",
    "gn:population":0,
    "gn:timezone":"Asia/Tokyo",
    "iso:country":"JP",
    "name:jpn_x_preferred":[
        "\u541b\u30f6\u4f5c"
    ],
    "name:jpn_x_variant":[
        "\u304f\u3093\u304c\u3055\u304f",
        "\u30af\u30f3\u30ac\u30b5\u30af"
    ],
    "wof:name":"Kungasaku",
    "wof:placetype":"locality"
},
  "geometry": {"coordinates":[139.94936000000001,35.2953],"type":"Point"}
}