{
  "type": "Feature",
  "properties": {
    "gn:admin1_code":"2.0",
    "gn:admin2_code":"2111935.0",
    "gn:admin3_code":"5363.0",
    "gn:asciiname":"Mikurahana",
    "gn:country_code":"JP",
    "gn:dem":3,
    "gn:feature_class":"P",
    "gn:feature_code":"PPL",
    "gn:name":"Mikurahana",
    "gn:population":0,
    "gn:timezone":"Asia/Tokyo",
    "iso:country":"JP",
    "name:jpn_x_preferred":[
        "\u4e09\u5009\u9f3b"
    ],
    "name:und_x_variant":[
        "Mikura-saki",
        "Mikura-bana",
        "Mitura Bana",
        "Mikura-hana",
        "Mikurahana"
    ],
    "wof:name":"Mikurahana",
    "wof:placetype":"locality"
},
  "geometry": {"coordinates":[140.07372000000001,39.98441],"type":"Point"}
}