{
  "type": "Feature",
  "properties": {
    "gn:admin1_code":"25.0",
    "gn:admin2_code":"1864313.0",
    "gn:asciiname":"Nishinono",
    "gn:country_code":"JP",
    "gn:dem":466,
    "gn:feature_class":"P",
    "gn:feature_code":"PPLL",
    "gn:name":"Nishinono",
    "gn:population":0,
    "gn:timezone":"Asia/Tokyo",
    "iso:country":"JP",
    "name:jpn_x_preferred":[
        "\u897f\u306e\u91ce"
    ],
    "name:jpn_x_variant":[
        "\u306b\u3057\u306e\u306e",
        "\u30cb\u30b7\u30ce\u30ce"
    ],
    "wof:name":"Nishinono",
    "wof:placetype":"locality"
},
  "geometry": {"coordinates":[130.72012000000001,32.05855],"type":"Point"}
}