{
  "type": "Feature",
  "properties": {
    "gn:admin1_code":"7.0",
    "gn:admin2_code":"1851269.0",
    "gn:admin3_code":"40608.0",
    "gn:asciiname":"Kakibaru",
    "gn:country_code":"JP",
    "gn:dem":58,
    "gn:feature_class":"P",
    "gn:feature_code":"PPLL",
    "gn:name":"Kakibaru",
    "gn:population":0,
    "gn:timezone":"Asia/Tokyo",
    "iso:country":"JP",
    "name:jpn_x_preferred":[
        "\u67ff\u539f"
    ],
    "wof:name":"Kakibaru",
    "wof:placetype":"locality"
},
  "geometry": {"coordinates":[130.858,33.6094],"type":"Point"}
}