{
  "type": "Feature",
  "properties": {
    "gn:admin1_code":"3.0",
    "gn:admin2_code":"2129393.0",
    "gn:asciiname":"Ushirodaikumachi",
    "gn:country_code":"JP",
    "gn:dem":48,
    "gn:feature_class":"P",
    "gn:feature_code":"PPL",
    "gn:name":"Ushirodaikumachi",
    "gn:population":0,
    "gn:timezone":"Asia/Tokyo",
    "iso:country":"JP",
    "name:jpn_x_preferred":[
        "\u5f8c\u5927\u5de5\u753a"
    ],
    "name:jpn_x_variant":[
        "\u3046\u3057\u308d\u3060\u3044\u304f\u307e\u3061",
        "\u30a6\u30b7\u30ed\u30c0\u30a4\u30af\u30de\u30c1"
    ],
    "wof:name":"Ushirodaikumachi",
    "wof:placetype":"locality"
},
  "geometry": {"coordinates":[140.58794,40.64437],"type":"Point"}
}