{
  "type": "Feature",
  "properties": {
    "gn:admin1_code":"18.0",
    "gn:admin2_code":"7383999.0",
    "gn:admin3_code":"46490.0",
    "gn:asciiname":"Hassawa",
    "gn:country_code":"JP",
    "gn:dem":176,
    "gn:feature_class":"P",
    "gn:feature_code":"PPLL",
    "gn:name":"Hassawa",
    "gn:population":0,
    "gn:timezone":"Asia/Tokyo",
    "iso:country":"JP",
    "name:jpn_x_preferred":[
        "\u539f\u6ca2"
    ],
    "name:und_x_variant":[
        "Harasawa"
    ],
    "wof:name":"Hassawa",
    "wof:placetype":"locality"
},
  "geometry": {"coordinates":[130.84398000000002,31.17509],"type":"Point"}
}