{
  "type": "Feature",
  "properties": {
    "gn:admin1_code":"4.0",
    "gn:admin2_code":"2112663.0",
    "gn:asciiname":"Araoi",
    "gn:country_code":"JP",
    "gn:dem":10,
    "gn:feature_class":"P",
    "gn:feature_code":"PPL",
    "gn:name":"Araoi",
    "gn:population":0,
    "gn:timezone":"Asia/Tokyo",
    "iso:country":"JP",
    "name:jpn_x_preferred":[
        "\u65b0\u751f"
    ],
    "name:jpn_x_variant":[
        "\u3042\u3089\u304a\u3044",
        "\u30a2\u30e9\u30aa\u30a4"
    ],
    "wof:name":"Araoi",
    "wof:placetype":"locality"
},
  "geometry": {"coordinates":[140.11066,35.4725],"type":"Point"}
}