{
  "type": "Feature",
  "properties": {
    "gn:admin1_code":"21.0",
    "gn:admin2_code":"7412708.0",
    "gn:admin3_code":"43501.0",
    "gn:asciiname":"Kiage",
    "gn:country_code":"JP",
    "gn:dem":135,
    "gn:feature_class":"P",
    "gn:feature_code":"PPLL",
    "gn:name":"Kiage",
    "gn:population":0,
    "gn:timezone":"Asia/Tokyo",
    "iso:country":"JP",
    "name:jpn_x_preferred":[
        "\u6728\u63da"
    ],
    "name:jpn_x_variant":[
        "\u304d\u3042\u3052",
        "\u30ad\u30a2\u30b2"
    ],
    "wof:name":"Kiage",
    "wof:placetype":"locality"
},
  "geometry": {"coordinates":[130.8158,32.18832],"type":"Point"}
}