{
  "type": "Feature",
  "properties": {
    "gn:admin1_code":"14.0",
    "gn:admin2_code":"6950859.0",
    "gn:asciiname":"Oyama-shinden",
    "gn:country_code":"JP",
    "gn:dem":22,
    "gn:feature_class":"P",
    "gn:feature_code":"PPL",
    "gn:name":"\u014cyama-shinden",
    "gn:population":0,
    "gn:timezone":"Asia/Tokyo",
    "iso:country":"JP",
    "name:jpn_x_preferred":[
        "\u5927\u5c71\u65b0\u7530"
    ],
    "name:und_x_variant":[
        "\u014cyama-shinden"
    ],
    "wof:name":"Oyama-shinden",
    "wof:placetype":"locality"
},
  "geometry": {"coordinates":[139.96385000000001,35.9728],"type":"Point"}
}