{
  "type": "Feature",
  "properties": {
    "gn:admin1_code":"21.0",
    "gn:admin2_code":"7412706.0",
    "gn:admin3_code":"43447.0",
    "gn:asciiname":"Utani",
    "gn:country_code":"JP",
    "gn:dem":705,
    "gn:feature_class":"P",
    "gn:feature_code":"PPLL",
    "gn:name":"Utani",
    "gn:population":0,
    "gn:timezone":"Asia/Tokyo",
    "iso:country":"JP",
    "name:jpn_x_preferred":[
        "\u5b87\u8c37"
    ],
    "name:jpn_x_variant":[
        "\u3046\u305f\u306b",
        "\u30a6\u30bf\u30cb"
    ],
    "wof:name":"Utani",
    "wof:placetype":"locality"
},
  "geometry": {"coordinates":[131.12904,32.76911],"type":"Point"}
}