{
  "type": "Feature",
  "properties": {
    "gn:country":"JP",
    "gn:fcode":"ADMD",
    "gn:pop":0,
    "iso:country":"JP",
    "name:eng_x_preferred":[
        "Oji-cho"
    ],
    "name:jpn_x_preferred":[
        "\u738b\u5bfa\u753a"
    ],
    "name:unk_x_variant":[
        "\u014cji-machi"
    ],
    "qs:name":"\u014cji-ch\u014d",
    "qs:photos_9r":0,
    "qs:photos_sr":0,
    "qs:pop_sr":"0",
    "wof:name":"\u014cji-ch\u014d",
    "wof:placetype":"localadmin",
    "wof:population":0
},
  "geometry": {"coordinates":[135.70689999999999,34.59407],"type":"Point"}
}