{
  "type": "Feature",
  "properties": {
    "gn:admin1_code":"21.0",
    "gn:admin2_code":"7412708.0",
    "gn:admin3_code":"43501.0",
    "gn:asciiname":"Muramatsu",
    "gn:country_code":"JP",
    "gn:dem":156,
    "gn:feature_class":"P",
    "gn:feature_code":"PPLL",
    "gn:name":"Muramatsu",
    "gn:population":0,
    "gn:timezone":"Asia/Tokyo",
    "iso:country":"JP",
    "name:jpn_x_preferred":[
        "\u6751\u677e"
    ],
    "name:jpn_x_variant":[
        "\u3080\u3089\u307e\u3064",
        "\u30e0\u30e9\u30de\u30c4"
    ],
    "wof:name":"Muramatsu",
    "wof:placetype":"locality"
},
  "geometry": {"coordinates":[130.82185000000001,32.23702],"type":"Point"}
}