{
  "type": "Feature",
  "properties": {
    "gn:admin1_code":"2.0",
    "gn:admin2_code":"2128783.0",
    "gn:asciiname":"Shimizu",
    "gn:country_code":"JP",
    "gn:dem":55,
    "gn:feature_class":"P",
    "gn:feature_code":"PPL",
    "gn:name":"Shimizu",
    "gn:population":0,
    "gn:timezone":"Asia/Tokyo",
    "iso:country":"JP",
    "name:jpn_x_preferred":[
        "\u6e05\u6c34"
    ],
    "name:jpn_x_variant":[
        "\u3057\u307f\u305a",
        "\u30b7\u30df\u30ba"
    ],
    "wof:name":"Shimizu",
    "wof:placetype":"locality"
},
  "geometry": {"coordinates":[140.55008000000001,40.2824],"type":"Point"}
}