{
  "type": "Feature",
  "properties": {
    "gn:admin1_code":"2.0",
    "gn:admin2_code":"2128783.0",
    "gn:asciiname":"Shimizu",
    "gn:country_code":"JP",
    "gn:dem":55,
    "gn:feature_class":"P",
    "gn:feature_code":"PPL",
    "gn:name":"Shimizu",
    "gn:population":0,
    "gn:timezone":"Asia/Tokyo",
    "iso:country":"JP",
    "name:deu_x_preferred":[
        "Shimizu"
    ],
    "name:fra_x_preferred":[
        "Shimizu"
    ],
    "name:jpn_x_preferred":[
        "\u6e05\u6c34"
    ],
    "name:jpn_x_variant":[
        "\u3057\u307f\u305a",
        "\u30b7\u30df\u30ba"
    ],
    "name:kor_x_preferred":[
        "\uc2dc\ubbf8\uc988"
    ],
    "name:nld_x_preferred":[
        "Thanh Th\u1ee7y"
    ],
    "name:por_x_preferred":[
        "Shimizu"
    ],
    "name:rus_x_preferred":[
        "\u0421\u0438\u043c\u0438\u0434\u0437\u0443"
    ],
    "name:ukr_x_preferred":[
        "\u0421\u0456\u043c\u0456\u0434\u0437\u0443"
    ],
    "name:vie_x_preferred":[
        "Thanh Th\u1ee7y"
    ],
    "wof:name":"Shimizu",
    "wof:placetype":"locality"
},
  "geometry": {"coordinates":[140.55008000000001,40.2824],"type":"Point"}
}