{
  "type": "Feature",
  "properties": {
    "iso:country":"JP",
    "qs:name":"\uff12\u4e01\u76ee",
    "qs:name_adm0":"\u65e5\u672c",
    "qs:name_adm1":"\u5948\u826f\u770c",
    "qs:photos":125,
    "qs:photos_1k":25,
    "qs:photos_9k":1,
    "qs:photos_9r":3,
    "qs:photos_all":125,
    "qs:photos_sr":3,
    "qs:placetype":"Suburb",
    "qs:pop_sr":"0",
    "wof:name":"\uff12\u4e01\u76ee",
    "wof:placetype":"neighbourhood"
},
  "geometry": {"coordinates":[135.784254,34.673593],"type":"Point"}
}