{
  "type": "Feature",
  "properties": {
    "gn:admin1_code":"12.0",
    "gn:admin2_code":"7428078.0",
    "gn:admin3_code":"1662.0",
    "gn:asciiname":"Otahigashi",
    "gn:country_code":"JP",
    "gn:dem":72,
    "gn:feature_class":"P",
    "gn:feature_code":"PPL",
    "gn:name":"\u014ctahigashi",
    "gn:population":0,
    "gn:timezone":"Asia/Tokyo",
    "iso:country":"JP",
    "name:jpn_x_preferred":[
        "\u592a\u7530\u6771"
    ],
    "name:jpn_x_variant":[
        "\u304a\u304a\u305f\u3072\u304c\u3057",
        "\u30aa\u30aa\u30bf\u30d2\u30ac\u30b7"
    ],
    "name:und_x_variant":[
        "\u014ctahigashi"
    ],
    "wof:name":"Otahigashi",
    "wof:placetype":"locality"
},
  "geometry": {"coordinates":[144.81360000000001,43.09072000000001],"type":"Point"}
}