{
  "type": "Feature",
  "properties": {
    "gn:admin1_code":"07",
    "gn:admin2_code":"1848572.0",
    "gn:asciiname":"Okinohatamachi",
    "gn:country_code":"JP",
    "gn:dem":2,
    "gn:feature_class":"P",
    "gn:feature_code":"PPL",
    "gn:name":"Okinohatamachi",
    "gn:population":0,
    "gn:timezone":"Asia/Tokyo",
    "iso:country":"JP",
    "name:jpn_x_preferred":[
        "\u6c96\u7aef\u753a"
    ],
    "name:und_x_variant":[
        "Okinohata",
        "Okinoha",
        "Okinohatamachi"
    ],
    "wof:name":"Okinohatamachi",
    "wof:placetype":"locality"
},
  "geometry": {"coordinates":[130.39219,33.15877],"type":"Point"}
}