{
  "type": "Feature",
  "properties": {
    "gn:admin1_code":"2.0",
    "gn:admin2_code":"2127468.0",
    "gn:admin3_code":"5348.0",
    "gn:asciiname":"Shidobashi",
    "gn:country_code":"JP",
    "gn:dem":52,
    "gn:feature_class":"P",
    "gn:feature_code":"PPLL",
    "gn:name":"Shidobashi",
    "gn:population":0,
    "gn:timezone":"Asia/Tokyo",
    "iso:country":"JP",
    "name:jpn_x_preferred":[
        "\u5fd7\u6238\u6a4b"
    ],
    "wof:name":"Shidobashi",
    "wof:placetype":"locality"
},
  "geometry": {"coordinates":[140.09402,40.13863],"type":"Point"}
}