{
  "type": "Feature",
  "properties": {
    "iso:country":"JP",
    "name:eng_x_preferred":[
        "Hirara Azashimozato"
    ],
    "name:eng_x_variant":[
        "Hirara Hirara Azashimozato",
        "Hirara Azashimozato"
    ],
    "name:jpn_x_preferred":[
        "\u5b57\u4e0b\u91cc"
    ],
    "name:jpn_x_variant":[
        "\u3042\u3056\u3057\u3082\u3056\u3068",
        "\u3072\u3089\u3089 \u3042\u3056\u3057\u3082\u3056\u3068",
        "\u5e73\u826f \u5b57\u4e0b\u91cc"
    ],
    "name:unk_x_variant":[
        "\u5b57\u4e0b\u91cc"
    ],
    "qs:gn_local":0,
    "qs:local_max":975,
    "qs:local_sum":3712,
    "qs:localhoods":19,
    "qs:name":"\u5b57\u4e0b\u91cc",
    "qs:name_adm0":"\u65e5\u672c",
    "qs:name_adm1":"\u6c96\u7e04\u770c",
    "qs:name_en":"Hirara Azashimozato",
    "qs:name_lau":"\u5e73\u826f",
    "qs:name_local":"\u5bae\u53e4\u5cf6\u5e02",
    "qs:photo_max":19,
    "qs:photo_sum":60,
    "qs:placetype":"Suburb",
    "qs:quad_count":8,
    "qs:woe_adm0":23424856,
    "qs:woe_adm1":2345896,
    "qs:woe_adm2":0,
    "qs:woe_lau":1117217,
    "qs:woe_local":28379331,
    "qs:woe_ver":"7.10.0",
    "wof:lang":[
        "jpn"
    ],
    "wof:name":"\u5b57\u4e0b\u91cc",
    "wof:placetype":"neighbourhood"
},
  "geometry": {"coordinates":[125.295708,24.782932],"type":"Point"}
}