{
  "type": "Feature",
  "properties": {
    "gn:admin1_code":"2.0",
    "gn:admin2_code":"2128783.0",
    "gn:asciiname":"Hedaremachi",
    "gn:country_code":"JP",
    "gn:dem":75,
    "gn:feature_class":"P",
    "gn:feature_code":"PPL",
    "gn:name":"Hedaremachi",
    "gn:population":0,
    "gn:timezone":"Asia/Tokyo",
    "iso:country":"JP",
    "name:jpn_x_preferred":[
        "\u90e8\u5782\u753a"
    ],
    "name:jpn_x_variant":[
        "\u3078\u3060\u308c\u307e\u3061",
        "\u30d8\u30c0\u30ec\u30de\u30c1"
    ],
    "wof:name":"Hedaremachi",
    "wof:placetype":"locality"
},
  "geometry": {"coordinates":[140.56686999999999,40.27066],"type":"Point"}
}