{
  "type": "Feature",
  "properties": {
    "gn:admin1_code":"4.0",
    "gn:admin2_code":"2113012.0",
    "gn:admin3_code":"12102.0",
    "gn:asciiname":"Hanamigawa",
    "gn:country_code":"JP",
    "gn:dem":29,
    "gn:feature_class":"P",
    "gn:feature_code":"PPL",
    "gn:name":"Hanamigawa",
    "gn:population":0,
    "gn:timezone":"Asia/Tokyo",
    "iso:country":"JP",
    "name:jpn_x_preferred":[
        "\u82b1\u898b\u5ddd"
    ],
    "name:jpn_x_variant":[
        "\u306f\u306a\u307f\u304c\u308f"
    ],
    "wof:name":"Hanamigawa",
    "wof:placetype":"locality"
},
  "geometry": {"coordinates":[140.09336000000002,35.68855],"type":"Point"}
}