{
  "type": "Feature",
  "properties": {
    "gn:admin1_code":"21.0",
    "gn:admin2_code":"1865358.0",
    "gn:asciiname":"Matsusaki",
    "gn:country_code":"JP",
    "gn:dem":33,
    "gn:feature_class":"P",
    "gn:feature_code":"PPLL",
    "gn:name":"Matsusaki",
    "gn:population":0,
    "gn:timezone":"Asia/Tokyo",
    "iso:country":"JP",
    "name:jpn_x_preferred":[
        "\u677e\u5d0e"
    ],
    "name:jpn_x_variant":[
        "\u307e\u3064\u3055\u304d",
        "\u30de\u30c4\u30b5\u30ad"
    ],
    "wof:name":"Matsusaki",
    "wof:placetype":"locality"
},
  "geometry": {"coordinates":[130.14812000000001,32.32306],"type":"Point"}
}