{
  "type": "Feature",
  "properties": {
    "gn:admin1_code":"21.0",
    "gn:admin2_code":"7412708.0",
    "gn:admin3_code":"43513.0",
    "gn:asciiname":"Matsudani",
    "gn:country_code":"JP",
    "gn:dem":220,
    "gn:feature_class":"P",
    "gn:feature_code":"PPLL",
    "gn:name":"Matsudani",
    "gn:population":0,
    "gn:timezone":"Asia/Tokyo",
    "iso:country":"JP",
    "name:jpn_x_preferred":[
        "\u677e\u8c37"
    ],
    "name:jpn_x_variant":[
        "\u307e\u3064\u3060\u306b",
        "\u30de\u30c4\u30c0\u30cb"
    ],
    "wof:name":"Matsudani",
    "wof:placetype":"locality"
},
  "geometry": {"coordinates":[130.66540000000001,32.2242],"type":"Point"}
}