{
  "type": "Feature",
  "properties": {
    "iso:country":"JP",
    "qs:name":"\u6e05\u702c\u5e02",
    "qs:name_adm0":"\u65e5\u672c",
    "qs:name_adm1":"\u6771\u4eac\u90fd",
    "qs:photos":200,
    "qs:photos_1k":41,
    "qs:photos_9k":5,
    "qs:photos_9r":7,
    "qs:photos_all":1053,
    "qs:photos_sr":4,
    "qs:placetype":"Town",
    "qs:pop_sr":"0",
    "wof:name":"\u6e05\u702c\u5e02",
    "wof:placetype":"locality"
},
  "geometry": {"coordinates":[139.53563600000001,35.785671],"type":"Point"}
}