{
  "type": "Feature",
  "properties": {
    "gn:admin1_code":"44.0",
    "gn:admin2_code":"2110496.0",
    "gn:asciiname":"Kuchitazawa",
    "gn:country_code":"JP",
    "gn:dem":334,
    "gn:feature_class":"P",
    "gn:feature_code":"PPL",
    "gn:name":"Kuchitazawa",
    "gn:population":0,
    "gn:timezone":"Asia/Tokyo",
    "iso:country":"JP",
    "name:jpn_x_preferred":[
        "\u53e3\u7530\u6ca2"
    ],
    "wof:name":"Kuchitazawa",
    "wof:placetype":"locality"
},
  "geometry": {"coordinates":[140.02176,37.90058],"type":"Point"}
}