{
  "type": "Feature",
  "properties": {
    "gn:admin1_code":"26",
    "gn:admin2_code":"1853055.0",
    "gn:asciiname":"Toridemachi",
    "gn:country_code":"JP",
    "gn:dem":682,
    "gn:feature_class":"P",
    "gn:feature_code":"PPL",
    "gn:name":"Toridemachi",
    "gn:population":0,
    "gn:timezone":"Asia/Tokyo",
    "iso:country":"JP",
    "name:jpn_x_preferred":[
        "\u53d6\u51fa\u753a"
    ],
    "name:und_x_variant":[
        "Toridech\u014d",
        "Toridemachi"
    ],
    "wof:name":"Toridemachi",
    "wof:placetype":"locality"
},
  "geometry": {"coordinates":[138.46666999999999,36.21667],"type":"Point"}
}