{
  "type": "Feature",
  "properties": {
    "gn:admin1_code":"18",
    "gn:admin2_code":"7383994.0",
    "gn:asciiname":"Bonotsucho-akime",
    "gn:country_code":"JP",
    "gn:dem":112,
    "gn:feature_class":"P",
    "gn:feature_code":"PPL",
    "gn:name":"B\u014dnotsuch\u014d-akime",
    "gn:population":0,
    "gn:timezone":"Asia/Tokyo",
    "iso:country":"JP",
    "name:jpn_x_preferred":[
        "\u574a\u6d25\u753a\u79cb\u76ee"
    ],
    "name:und_x_variant":[
        "Akinome",
        "Akime",
        "B\u014dnotsuch\u014d-akime"
    ],
    "wof:name":"Bonotsucho-akime",
    "wof:placetype":"locality"
},
  "geometry": {"coordinates":[130.2072,31.35228],"type":"Point"}
}