{
  "type": "Feature",
  "properties": {
    "gn:admin1_code":"27",
    "gn:admin2_code":"7418810.0",
    "gn:asciiname":"Kamitsushimacho-toyo",
    "gn:country_code":"JP",
    "gn:dem":52,
    "gn:feature_class":"P",
    "gn:feature_code":"PPL",
    "gn:name":"Kamitsushimach\u014d-toyo",
    "gn:population":0,
    "gn:timezone":"Asia/Tokyo",
    "iso:country":"JP",
    "name:jpn_x_preferred":[
        "\u4e0a\u5bfe\u99ac\u753a\u8c4a"
    ],
    "name:und_x_variant":[
        "Kamitsushimach\u014d-toyo",
        "Toyo"
    ],
    "wof:name":"Kamitsushimacho-toyo",
    "wof:placetype":"locality"
},
  "geometry": {"coordinates":[129.46666999999999,34.68333],"type":"Point"}
}