{
  "type": "Feature",
  "properties": {
    "gn:admin1_code":"19.0",
    "gn:admin2_code":"7468160.0",
    "gn:admin3_code":"14402.0",
    "gn:asciiname":"Shimizugaoka",
    "gn:country_code":"JP",
    "gn:dem":190,
    "gn:feature_class":"P",
    "gn:feature_code":"PPLL",
    "gn:name":"Shimizugaoka",
    "gn:population":0,
    "gn:timezone":"Asia/Tokyo",
    "iso:country":"JP",
    "name:jpn_x_preferred":[
        "\u6e05\u6c34\u30f6\u4e18"
    ],
    "wof:name":"Shimizugaoka",
    "wof:placetype":"locality"
},
  "geometry": {"coordinates":[139.28451000000001,35.47025],"type":"Point"}
}