{
  "type": "Feature",
  "properties": {
    "gn:admin1_code":"47",
    "gn:admin2_code":"1858371.0",
    "gn:admin3_code":"47301.0",
    "gn:asciiname":"Hanji",
    "gn:country_code":"JP",
    "gn:dem":9,
    "gn:feature_class":"P",
    "gn:feature_code":"PPL",
    "gn:name":"Hanji",
    "gn:population":0,
    "gn:timezone":"Asia/Tokyo",
    "iso:country":"JP",
    "name:ceb_x_preferred":[
        "Hanji"
    ],
    "name:jpn_x_preferred":[
        "\u534a\u5730"
    ],
    "name:jpn_x_variant":[
        "\u306f\u3093\u3062"
    ],
    "name:swe_x_preferred":[
        "Hanji"
    ],
    "name:und_x_variant":[
        "Banchi"
    ],
    "wof:name":"Hanji",
    "wof:placetype":"locality"
},
  "geometry": {"coordinates":[128.16460000000001,26.72649],"type":"Point"}
}