{
  "type": "Feature",
  "properties": {
    "gn:admin1_code":"33.0",
    "gn:admin2_code":"1853274.0",
    "gn:asciiname":"Kubotacho-edo",
    "gn:country_code":"JP",
    "gn:dem":-2,
    "gn:feature_class":"P",
    "gn:feature_code":"PPL",
    "gn:name":"Kubotach\u014d-edo",
    "gn:population":0,
    "gn:timezone":"Asia/Tokyo",
    "iso:country":"JP",
    "name:jpn_x_preferred":[
        "\u4e45\u4fdd\u7530\u753a\u6c5f\u6238"
    ],
    "name:und_x_variant":[
        "Kubotach\u014d-edo"
    ],
    "wof:name":"Kubotacho-edo",
    "wof:placetype":"locality"
},
  "geometry": {"coordinates":[130.23876999999999,33.20551],"type":"Point"}
}