{
  "type": "Feature",
  "properties": {
    "gn:admin1_code":"10.0",
    "gn:admin2_code":"7453747.0",
    "gn:admin3_code":"10421.0",
    "gn:asciiname":"Akaiwa",
    "gn:country_code":"JP",
    "gn:dem":709,
    "gn:feature_class":"P",
    "gn:feature_code":"PPL",
    "gn:name":"Akaiwa",
    "gn:population":0,
    "gn:timezone":"Asia/Tokyo",
    "iso:country":"JP",
    "name:jpn_x_preferred":[
        "\u8d64\u5ca9"
    ],
    "wof:name":"Akaiwa",
    "wof:placetype":"locality"
},
  "geometry": {"coordinates":[138.62795,36.57543],"type":"Point"}
}