{
  "type": "Feature",
  "properties": {
    "gn:admin1_code":"10.0",
    "gn:admin2_code":"7453747.0",
    "gn:admin3_code":"10421.0",
    "gn:asciiname":"Akaiwa",
    "gn:country_code":"JP",
    "gn:dem":709,
    "gn:feature_class":"P",
    "gn:feature_code":"PPL",
    "gn:name":"Akaiwa",
    "gn:population":0,
    "gn:timezone":"Asia/Tokyo",
    "iso:country":"JP",
    "name:ara_x_preferred":[
        "\u0623\u0643\u0627\u064a\u0648\u0627"
    ],
    "name:azb_x_preferred":[
        "\u0622\u06a9\u0627\u06cc\u0648\u0627"
    ],
    "name:ceb_x_preferred":[
        "Akaiwa Shi"
    ],
    "name:deu_x_preferred":[
        "Akaiwa"
    ],
    "name:fas_x_preferred":[
        "\u0622\u06a9\u0627\u06cc\u0648\u0627"
    ],
    "name:fra_x_preferred":[
        "Akaiwa"
    ],
    "name:glg_x_preferred":[
        "Akaiwa"
    ],
    "name:ita_x_preferred":[
        "Akaiwa"
    ],
    "name:jpn_x_preferred":[
        "\u8d64\u5ca9"
    ],
    "name:jpn_x_variant":[
        "\u8d64\u78d0\u5e02"
    ],
    "name:kor_x_preferred":[
        "\uc544\uce74\uc774\uc640\uc2dc"
    ],
    "name:mzn_x_preferred":[
        "\u0622\u06a9\u0627\u06cc\u0648\u0627"
    ],
    "name:nld_x_preferred":[
        "Akaiwa"
    ],
    "name:pol_x_preferred":[
        "Akaiwa"
    ],
    "name:por_x_preferred":[
        "Akaiwa"
    ],
    "name:ron_x_preferred":[
        "Akaiwa"
    ],
    "name:rus_x_preferred":[
        "\u0410\u043a\u0430\u0438\u0432\u0430"
    ],
    "name:swe_x_preferred":[
        "Akaiwa"
    ],
    "name:tgk_x_preferred":[
        "\u0410\u043a\u0430\u0438\u0443\u0430"
    ],
    "name:tgl_x_preferred":[
        "Akaiwa"
    ],
    "name:tur_x_preferred":[
        "Akaiwa"
    ],
    "name:ukr_x_preferred":[
        "\u0410\u043a\u0430\u0457\u0432\u0430"
    ],
    "name:vie_x_preferred":[
        "Akaiwa"
    ],
    "name:war_x_preferred":[
        "Akaiwa"
    ],
    "name:zho_x_preferred":[
        "\u8d64\u78d0\u5e02"
    ],
    "wof:name":"Akaiwa",
    "wof:placetype":"locality"
},
  "geometry": {"coordinates":[138.62795,36.57543],"type":"Point"}
}