{
  "type": "Feature",
  "properties": {
    "gn:admin1_code":"42.0",
    "gn:admin2_code":"7391183.0",
    "gn:asciiname":"Higashinishihara",
    "gn:country_code":"JP",
    "gn:dem":261,
    "gn:feature_class":"P",
    "gn:feature_code":"PPL",
    "gn:name":"Higashinishihara",
    "gn:population":0,
    "gn:timezone":"Asia/Tokyo",
    "iso:country":"JP",
    "name:jpn_x_preferred":[
        "\u6771\u897f\u539f"
    ],
    "wof:name":"Higashinishihara",
    "wof:placetype":"locality"
},
  "geometry": {"coordinates":[136.94587000000001,36.51626],"type":"Point"}
}