{
  "type": "Feature",
  "properties": {
    "iso:country":"JP",
    "name:eng_x_preferred":[
        "Ikegami 4 Chome"
    ],
    "name:eng_x_variant":[
        "Ikegami 4 Choume",
        "Ikegami 4 Chome"
    ],
    "name:jpn_x_preferred":[
        "\uff14\u4e01\u76ee"
    ],
    "name:jpn_x_variant":[
        "\u3044\u3051\u304c\u307f \uff14\u3061\u3087\u3046\u3081",
        "\u6c60\u4e0a \uff14\u4e01\u76ee",
        "\uff14\u3061\u3087\u3046\u3081"
    ],
    "qs:gn_adm0_cc":"JP",
    "qs:gn_local":1850147,
    "qs:local_max":18112,
    "qs:local_sum":895907,
    "qs:localhoods":857,
    "qs:name":"\uff14\u4e01\u76ee",
    "qs:name_adm0":"\u65e5\u672c",
    "qs:name_adm1":"\u6771\u4eac\u90fd",
    "qs:name_adm2":"\u5927\u7530\u533a",
    "qs:name_en":"Ikegami 4 Chome",
    "qs:name_lau":"\u6c60\u4e0a",
    "qs:name_local":"\u6771\u4eac",
    "qs:photo_max":4,
    "qs:photo_sum":4,
    "qs:placetype":"Suburb",
    "qs:quad_count":1,
    "qs:woe_adm0":23424856,
    "qs:woe_adm1":2345889,
    "qs:woe_adm2":15015506,
    "qs:woe_lau":28414276,
    "qs:woe_local":1118370,
    "qs:woe_ver":"7.10.0",
    "wof:lang":[
        "jpn"
    ],
    "wof:name":"\uff14\u4e01\u76ee",
    "wof:placetype":"neighbourhood"
},
  "geometry": {"coordinates":[139.70626799999999,35.571331],"type":"Point"}
}