{
  "type": "Feature",
  "properties": {
    "gn:admin1_code":"21.0",
    "gn:admin2_code":"1858418.0",
    "gn:admin3_code":"43104.0",
    "gn:asciiname":"Hirano",
    "gn:country_code":"JP",
    "gn:dem":7,
    "gn:feature_class":"P",
    "gn:feature_code":"PPLL",
    "gn:name":"Hirano",
    "gn:population":0,
    "gn:timezone":"Asia/Tokyo",
    "iso:country":"JP",
    "name:jpn_x_preferred":[
        "\u5e73\u91ce"
    ],
    "name:jpn_x_variant":[
        "\u3072\u3089\u306e",
        "\u30d2\u30e9\u30ce"
    ],
    "wof:name":"Hirano",
    "wof:placetype":"locality"
},
  "geometry": {"coordinates":[130.74208999999999,32.72446],"type":"Point"}
}