{
  "type": "Feature",
  "properties": {
    "gn:admin1_code":"40.0",
    "gn:admin2_code":"1853655.0",
    "gn:asciiname":"Kitaminemachi",
    "gn:country_code":"JP",
    "gn:dem":25,
    "gn:feature_class":"P",
    "gn:feature_code":"PPL",
    "gn:name":"Kitaminemachi",
    "gn:population":0,
    "gn:timezone":"Asia/Tokyo",
    "iso:country":"JP",
    "name:jpn_x_preferred":[
        "\u5317\u5dba\u753a"
    ],
    "wof:name":"Kitaminemachi",
    "wof:placetype":"locality"
},
  "geometry": {"coordinates":[139.68298999999999,35.58725],"type":"Point"}
}