{
  "type": "Feature",
  "properties": {
    "gn:admin1_code":"4.0",
    "gn:admin2_code":"2112663.0",
    "gn:asciiname":"Yanagawa",
    "gn:country_code":"JP",
    "gn:dem":123,
    "gn:feature_class":"P",
    "gn:feature_code":"PPL",
    "gn:name":"Yanagawa",
    "gn:population":0,
    "gn:timezone":"Asia/Tokyo",
    "iso:country":"JP",
    "name:jpn_x_preferred":[
        "\u67f3\u5ddd"
    ],
    "name:jpn_x_variant":[
        "\u3084\u306a\u304c\u308f",
        "\u30e4\u30ca\u30ac\u30ef"
    ],
    "wof:name":"Yanagawa",
    "wof:placetype":"locality"
},
  "geometry": {"coordinates":[140.13081,35.28842],"type":"Point"}
}