{
  "type": "Feature",
  "properties": {
    "gn:admin1_code":"16.0",
    "gn:admin2_code":"7441804.0",
    "gn:admin3_code":"3301.0",
    "gn:asciiname":"Ashigadaira",
    "gn:country_code":"JP",
    "gn:dem":260,
    "gn:feature_class":"P",
    "gn:feature_code":"PPL",
    "gn:name":"Ashigadaira",
    "gn:population":0,
    "gn:timezone":"Asia/Tokyo",
    "iso:country":"JP",
    "name:jpn_x_preferred":[
        "\u82a6\u30f6\u5e73"
    ],
    "wof:name":"Ashigadaira",
    "wof:placetype":"locality"
},
  "geometry": {"coordinates":[141.00978000000001,39.62293],"type":"Point"}
}