{
  "type": "Feature",
  "properties": {
    "gn:admin1_code":"47",
    "gn:admin2_code":"7415820.0",
    "gn:asciiname":"Funakoshi",
    "gn:country_code":"JP",
    "gn:dem":61,
    "gn:feature_class":"P",
    "gn:feature_code":"PPLL",
    "gn:name":"Funakoshi",
    "gn:population":0,
    "gn:timezone":"Asia/Tokyo",
    "iso:country":"JP",
    "name:jpn_x_preferred":[
        "\u8239\u8d8a"
    ],
    "name:und_x_variant":[
        "Funakushi"
    ],
    "wof:name":"Funakoshi",
    "wof:placetype":"locality"
},
  "geometry": {"coordinates":[127.75397,26.15245],"type":"Point"}
}