{
  "type": "Feature",
  "properties": {
    "iso:country":"JP",
    "qs:name":"\u307f\u306a\u3079\u753a",
    "qs:name_adm0":"\u65e5\u672c",
    "qs:name_adm1":"\u548c\u6b4c\u5c71\u770c",
    "qs:photos":118,
    "qs:photos_1k":24,
    "qs:photos_9k":1,
    "qs:photos_9r":3,
    "qs:photos_all":118,
    "qs:photos_sr":3,
    "qs:placetype":"Town",
    "qs:pop_sr":"0",
    "wof:name":"\u307f\u306a\u3079\u753a",
    "wof:placetype":"locality"
},
  "geometry": {"coordinates":[135.30063949999999,33.768944],"type":"Point"}
}