{
  "type": "Feature",
  "properties": {
    "gn:admin1_code":"3.0",
    "gn:admin2_code":"2127674.0",
    "gn:asciiname":"Toriyazuku",
    "gn:country_code":"JP",
    "gn:dem":182,
    "gn:feature_class":"P",
    "gn:feature_code":"PPL",
    "gn:name":"Toriyazuku",
    "gn:population":0,
    "gn:timezone":"Asia/Tokyo",
    "iso:country":"JP",
    "name:jpn_x_preferred":[
        "\u9ce5\u8c37\u9644"
    ],
    "name:jpn_x_variant":[
        "\u3068\u308a\u3084\u3065\u304f",
        "\u30c8\u30ea\u30e4\u30c5\u30af"
    ],
    "wof:name":"Toriyazuku",
    "wof:placetype":"locality"
},
  "geometry": {"coordinates":[141.06360000000001,40.61621],"type":"Point"}
}