{
  "type": "Feature",
  "properties": {
    "gn:admin1_code":"21.0",
    "gn:admin2_code":"1850744.0",
    "gn:admin3_code":"43369.0",
    "gn:asciiname":"Nagaoda",
    "gn:country_code":"JP",
    "gn:dem":18,
    "gn:feature_class":"P",
    "gn:feature_code":"PPL",
    "gn:name":"Nagaoda",
    "gn:population":0,
    "gn:timezone":"Asia/Tokyo",
    "iso:country":"JP",
    "name:jpn_x_preferred":[
        "\u9577\u5c0f\u7530"
    ],
    "name:jpn_x_variant":[
        "\u306a\u304c\u304a\u3060",
        "\u30ca\u30ac\u30aa\u30c0"
    ],
    "wof:name":"Nagaoda",
    "wof:placetype":"locality"
},
  "geometry": {"coordinates":[130.60312999999999,33.00048],"type":"Point"}
}