{
  "type": "Feature",
  "properties": {
    "iso:country":"JP",
    "name:eng_x_preferred":[
        "Sakahogi Town"
    ],
    "name:jpn_x_preferred":[
        "\u5742\u795d\u753a"
    ],
    "qs:name":"\u5742\u795d\u753a",
    "qs:name_adm0":"\u65e5\u672c",
    "qs:name_adm1":"\u5c90\u961c\u770c",
    "qs:photos":53,
    "qs:photos_1k":11,
    "qs:photos_9k":1,
    "qs:photos_9r":2,
    "qs:photos_all":67,
    "qs:photos_sr":2,
    "qs:placetype":"Town",
    "qs:pop_sr":"0",
    "wof:name":"Sakahogi Town",
    "wof:placetype":"locality"
},
  "geometry": {"coordinates":[136.977844,35.408639],"type":"Point"}
}