{
  "type": "Feature",
  "properties": {
    "gn:admin1_code":"2.0",
    "gn:admin2_code":"2113122.0",
    "gn:asciiname":"Araya-kotobukimachi",
    "gn:country_code":"JP",
    "gn:dem":26,
    "gn:feature_class":"P",
    "gn:feature_code":"PPL",
    "gn:name":"Araya-kotobukimachi",
    "gn:population":0,
    "gn:timezone":"Asia/Tokyo",
    "iso:country":"JP",
    "name:jpn_x_preferred":[
        "\u65b0\u5c4b\u5bff\u753a"
    ],
    "name:jpn_x_variant":[
        "\u3042\u3089\u3084\u3053\u3068\u3076\u304d\u307e\u3061",
        "\u30a2\u30e9\u30e4\u30b3\u30c8\u30d6\u30ad\u30de\u30c1"
    ],
    "wof:name":"Araya-kotobukimachi",
    "wof:placetype":"locality"
},
  "geometry": {"coordinates":[140.07656,39.69756],"type":"Point"}
}