{
  "type": "Feature",
  "properties": {
    "gn:admin1_code":"7.0",
    "gn:admin2_code":"1859306.0",
    "gn:admin3_code":"40107.0",
    "gn:asciiname":"Shii",
    "gn:country_code":"JP",
    "gn:dem":34,
    "gn:feature_class":"P",
    "gn:feature_code":"PPL",
    "gn:name":"Shii",
    "gn:population":0,
    "gn:timezone":"Asia/Tokyo",
    "iso:country":"JP",
    "name:fin_x_preferred":[
        "Shii"
    ],
    "name:jpn_x_preferred":[
        "\u5fd7\u4e95"
    ],
    "wof:name":"Shii",
    "wof:placetype":"locality"
},
  "geometry": {"coordinates":[130.87214,33.81889],"type":"Point"}
}