{
  "type": "Feature",
  "properties": {
    "gn:admin1_code":"21.0",
    "gn:admin2_code":"7413151.0",
    "gn:asciiname":"Nagaura",
    "gn:country_code":"JP",
    "gn:dem":6,
    "gn:feature_class":"P",
    "gn:feature_code":"PPLL",
    "gn:name":"Nagaura",
    "gn:population":0,
    "gn:timezone":"Asia/Tokyo",
    "iso:country":"JP",
    "name:jpn_x_preferred":[
        "\u6c38\u6d66"
    ],
    "name:jpn_x_variant":[
        "\u306a\u304c\u3046\u3089",
        "\u30ca\u30ac\u30a6\u30e9"
    ],
    "wof:name":"Nagaura",
    "wof:placetype":"locality"
},
  "geometry": {"coordinates":[130.41326999999998,32.54415],"type":"Point"}
}