{
  "type": "Feature",
  "properties": {
    "gn:admin1_code":"43.0",
    "gn:admin2_code":"1865121.0",
    "gn:asciiname":"Miyaharacho-takigahara",
    "gn:country_code":"JP",
    "gn:dem":7,
    "gn:feature_class":"P",
    "gn:feature_code":"PPL",
    "gn:name":"Miyaharach\u014d-takigahara",
    "gn:population":0,
    "gn:timezone":"Asia/Tokyo",
    "iso:country":"JP",
    "name:jpn_x_preferred":[
        "\u5bae\u539f\u753a\u6edd\u5ddd\u539f"
    ],
    "name:und_x_variant":[
        "Miyaharach\u014d-takigahara"
    ],
    "wof:name":"Miyaharacho-takigahara",
    "wof:placetype":"locality"
},
  "geometry": {"coordinates":[135.16551999999999,34.08095],"type":"Point"}
}