{
  "type": "Feature",
  "properties": {
    "gn:admin1_code":"37.0",
    "gn:admin2_code":"1864104.0",
    "gn:asciiname":"Nishikicho",
    "gn:country_code":"JP",
    "gn:dem":121,
    "gn:feature_class":"P",
    "gn:feature_code":"PPL",
    "gn:name":"Nishikich\u014d",
    "gn:population":0,
    "gn:timezone":"Asia/Tokyo",
    "iso:country":"JP",
    "name:jpn_x_preferred":[
        "\u9326\u753a"
    ],
    "name:und_x_variant":[
        "Nishikich\u014d"
    ],
    "wof:name":"Nishikicho",
    "wof:placetype":"locality"
},
  "geometry": {"coordinates":[138.61591999999999,35.21989],"type":"Point"}
}