{
  "type": "Feature",
  "properties": {
    "gn:admin1_code":"36",
    "gn:admin2_code":"1863519.0",
    "gn:asciiname":"Tsuchi-hongo",
    "gn:country_code":"JP",
    "gn:dem":14,
    "gn:feature_class":"P",
    "gn:feature_code":"PPL",
    "gn:name":"Tsuchi-hong\u014d",
    "gn:population":0,
    "gn:timezone":"Asia/Tokyo",
    "iso:country":"JP",
    "name:und_x_variant":[
        "Tsuchi-hong\u014d"
    ],
    "wof:name":"Tsuchi-hongo",
    "wof:placetype":"locality"
},
  "geometry": {"coordinates":[132.30000000000001,35.03333],"type":"Point"}
}