{
  "type": "Feature",
  "properties": {
    "gn:admin1_code":"28.0",
    "gn:admin2_code":"1848164.0",
    "gn:admin3_code":"29443.0",
    "gn:asciiname":"Heibara",
    "gn:country_code":"JP",
    "gn:dem":398,
    "gn:feature_class":"P",
    "gn:feature_code":"PPL",
    "gn:name":"Heibara",
    "gn:population":0,
    "gn:timezone":"Asia/Tokyo",
    "iso:country":"JP",
    "name:jpn_x_preferred":[
        "\u5e73\u539f"
    ],
    "wof:name":"Heibara",
    "wof:placetype":"locality"
},
  "geometry": {"coordinates":[135.7799,34.33119],"type":"Point"}
}