{
  "type": "Feature",
  "properties": {
    "gn:admin1_code":"11.0",
    "gn:admin2_code":"8740425.0",
    "gn:asciiname":"Ozuke",
    "gn:country_code":"JP",
    "gn:dem":3,
    "gn:feature_class":"P",
    "gn:feature_code":"PPL",
    "gn:name":"Ozuke",
    "gn:population":0,
    "gn:timezone":"Asia/Tokyo",
    "iso:country":"JP",
    "name:und_x_variant":[
        "Otsuki"
    ],
    "wof:name":"Ozuke",
    "wof:placetype":"locality"
},
  "geometry": {"coordinates":[132.44658999999999,34.17905],"type":"Point"}
}