{
  "type": "Feature",
  "properties": {
    "gn:admin1_code":"21.0",
    "gn:admin2_code":"1864975.0",
    "gn:admin3_code":"43423.0",
    "gn:asciiname":"Nakayuta",
    "gn:country_code":"JP",
    "gn:dem":538,
    "gn:feature_class":"P",
    "gn:feature_code":"PPLL",
    "gn:name":"Nakayuta",
    "gn:population":0,
    "gn:timezone":"Asia/Tokyo",
    "iso:country":"JP",
    "name:jpn_x_preferred":[
        "\u4e2d\u6e6f\u7530"
    ],
    "name:jpn_x_variant":[
        "\u306a\u304b\u3086\u305f",
        "\u30ca\u30ab\u30e6\u30bf"
    ],
    "wof:name":"Nakayuta",
    "wof:placetype":"locality"
},
  "geometry": {"coordinates":[131.03849,33.08462],"type":"Point"}
}