{
  "type": "Feature",
  "properties": {
    "gn:admin1_code":"3.0",
    "gn:admin2_code":"2129754.0",
    "gn:admin3_code":"2408.0",
    "gn:asciiname":"Kirisazaka",
    "gn:country_code":"JP",
    "gn:dem":23,
    "gn:feature_class":"P",
    "gn:feature_code":"PPL",
    "gn:name":"Kirisazaka",
    "gn:population":0,
    "gn:timezone":"Asia/Tokyo",
    "iso:country":"JP",
    "name:jpn_x_preferred":[
        "\u5207\u5de6\u5742"
    ],
    "name:jpn_x_variant":[
        "\u304d\u308a\u3055\u3056\u304b",
        "\u30ad\u30ea\u30b5\u30b6\u30ab"
    ],
    "wof:name":"Kirisazaka",
    "wof:placetype":"locality"
},
  "geometry": {"coordinates":[141.2561,40.82241],"type":"Point"}
}