{
  "type": "Feature",
  "properties": {
    "gn:admin1_code":"3.0",
    "gn:admin2_code":"2130056.0",
    "gn:asciiname":"Shimonakahata",
    "gn:country_code":"JP",
    "gn:dem":14,
    "gn:feature_class":"P",
    "gn:feature_code":"PPL",
    "gn:name":"Shimonakahata",
    "gn:population":0,
    "gn:timezone":"Asia/Tokyo",
    "iso:country":"JP",
    "name:jpn_x_preferred":[
        "\u4e0b\u4e2d\u7551"
    ],
    "name:jpn_x_variant":[
        "\u3057\u3082\u306a\u304b\u306f\u305f",
        "\u30b7\u30e2\u30ca\u30ab\u30cf\u30bf"
    ],
    "wof:name":"Shimonakahata",
    "wof:placetype":"locality"
},
  "geometry": {"coordinates":[140.41367,40.73105],"type":"Point"}
}