{
  "type": "Feature",
  "properties": {
    "gn:admin1_code":"4.0",
    "gn:admin2_code":"7465524.0",
    "gn:asciiname":"Kariya",
    "gn:country_code":"JP",
    "gn:dem":17,
    "gn:feature_class":"P",
    "gn:feature_code":"PPL",
    "gn:name":"Kariya",
    "gn:population":0,
    "gn:timezone":"Asia/Tokyo",
    "iso:country":"JP",
    "name:jpn_x_preferred":[
        "\u5208\u8c37"
    ],
    "name:jpn_x_variant":[
        "\u304b\u308a\u3084",
        "\u30ab\u30ea\u30e4"
    ],
    "wof:name":"Kariya",
    "wof:placetype":"locality"
},
  "geometry": {"coordinates":[140.30941999999999,35.2814],"type":"Point"}
}