{
  "type": "Feature",
  "properties": {
    "gn:admin1_code":"21.0",
    "gn:admin2_code":"1858418.0",
    "gn:admin3_code":"43105.0",
    "gn:asciiname":"Onizuka",
    "gn:country_code":"JP",
    "gn:dem":69,
    "gn:feature_class":"P",
    "gn:feature_code":"PPLL",
    "gn:name":"Onizuka",
    "gn:population":0,
    "gn:timezone":"Asia/Tokyo",
    "iso:country":"JP",
    "name:jpn_x_preferred":[
        "\u9b3c\u585a"
    ],
    "name:jpn_x_variant":[
        "\u304a\u306b\u3065\u304b",
        "\u30aa\u30cb\u30c5\u30ab"
    ],
    "wof:name":"Onizuka",
    "wof:placetype":"locality"
},
  "geometry": {"coordinates":[130.67293000000001,32.87945999999999],"type":"Point"}
}