{
  "type": "Feature",
  "properties": {
    "gn:admin1_code":"21.0",
    "gn:admin2_code":"1865360.0",
    "gn:admin3_code":"43531.0",
    "gn:asciiname":"Ropponmatsu",
    "gn:country_code":"JP",
    "gn:dem":395,
    "gn:feature_class":"P",
    "gn:feature_code":"PPLL",
    "gn:name":"Ropponmatsu",
    "gn:population":0,
    "gn:timezone":"Asia/Tokyo",
    "iso:country":"JP",
    "name:jpn_x_preferred":[
        "\u516d\u672c\u677e"
    ],
    "name:jpn_x_variant":[
        "\u308d\u3063\u307d\u3093\u307e\u3064",
        "\u30ed\u30c3\u30dd\u30f3\u30de\u30c4"
    ],
    "wof:name":"Ropponmatsu",
    "wof:placetype":"locality"
},
  "geometry": {"coordinates":[130.09323000000001,32.43226],"type":"Point"}
}