{
  "type": "Feature",
  "properties": {
    "gn:admin1_code":"47",
    "gn:admin2_code":"1856061.0",
    "gn:asciiname":"Kyoda",
    "gn:country_code":"JP",
    "gn:dem":12,
    "gn:feature_class":"P",
    "gn:feature_code":"PPL",
    "gn:name":"Kyoda",
    "gn:population":0,
    "gn:timezone":"Asia/Tokyo",
    "iso:country":"JP",
    "name:jpn_x_preferred":[
        "\u8a31\u7530"
    ],
    "name:und_x_variant":[
        "Ch\u016bda",
        "Kyota",
        "Chude",
        "Tyota",
        "Ch\u016bta",
        "Chota",
        "Kyoda"
    ],
    "wof:name":"Kyoda",
    "wof:placetype":"locality"
},
  "geometry": {"coordinates":[127.96917000000001,26.54199],"type":"Point"}
}