{
  "type": "Feature",
  "properties": {
    "gn:admin1_code":"3.0",
    "gn:admin2_code":"2127674.0",
    "gn:asciiname":"Chuseri",
    "gn:country_code":"JP",
    "gn:dem":71,
    "gn:feature_class":"P",
    "gn:feature_code":"PPL",
    "gn:name":"Ch\u016bseri",
    "gn:population":0,
    "gn:timezone":"Asia/Tokyo",
    "iso:country":"JP",
    "name:jpn_x_preferred":[
        "\u4e2d\u63ab"
    ],
    "name:jpn_x_variant":[
        "\u3061\u3085\u3046\u305b\u308a",
        "\u30c1\u30e5\u30a6\u30bb\u30ea"
    ],
    "name:und_x_variant":[
        "Ch\u016bseri"
    ],
    "wof:name":"Chuseri",
    "wof:placetype":"locality"
},
  "geometry": {"coordinates":[141.14936,40.59714],"type":"Point"}
}