{
  "type": "Feature",
  "properties": {
    "gn:admin1_code":"8.0",
    "gn:admin2_code":"7451502.0",
    "gn:admin3_code":"7502.0",
    "gn:asciiname":"Okudaira",
    "gn:country_code":"JP",
    "gn:dem":359,
    "gn:feature_class":"P",
    "gn:feature_code":"PPLL",
    "gn:name":"Okudaira",
    "gn:population":0,
    "gn:timezone":"Asia/Tokyo",
    "iso:country":"JP",
    "name:jpn_x_preferred":[
        "\u5965\u5e73"
    ],
    "wof:name":"Okudaira",
    "wof:placetype":"locality"
},
  "geometry": {"coordinates":[140.44996,37.21387],"type":"Point"}
}