{
  "type": "Feature",
  "properties": {
    "gn:admin1_code":"7.0",
    "gn:admin2_code":"1861834.0",
    "gn:asciiname":"Kotoge",
    "gn:country_code":"JP",
    "gn:dem":89,
    "gn:feature_class":"P",
    "gn:feature_code":"PPLL",
    "gn:name":"Kot\u014dge",
    "gn:population":0,
    "gn:timezone":"Asia/Tokyo",
    "iso:country":"JP",
    "name:jpn_x_preferred":[
        "\u5c0f\u5ce0"
    ],
    "name:und_x_variant":[
        "Kot\u014dge"
    ],
    "wof:name":"Kotoge",
    "wof:placetype":"locality"
},
  "geometry": {"coordinates":[130.74753999999999,33.68535],"type":"Point"}
}