{
  "type": "Feature",
  "properties": {
    "iso:country":"JP",
    "label:eng_x_preferred_longname":[
        "Tonosho Town"
    ],
    "label:eng_x_preferred_placetype":[
        "town"
    ],
    "name:eng_x_preferred":[
        "Tonosho"
    ],
    "name:eng_x_variant":[
        "Tonosho Town"
    ],
    "name:jpn_x_preferred":[
        "\u571f\u5e84\u753a"
    ],
    "qs:name":"\u571f\u5e84\u753a",
    "qs:name_adm0":"\u65e5\u672c",
    "qs:name_adm1":"\u9999\u5ddd\u770c",
    "qs:photos":998,
    "qs:photos_1k":202,
    "qs:photos_9k":4,
    "qs:photos_9r":6,
    "qs:photos_all":998,
    "qs:photos_sr":10,
    "qs:placetype":"Town",
    "qs:pop_sr":"0",
    "wof:name":"Tonosho",
    "wof:placetype":"locality"
},
  "geometry": {"coordinates":[134.09143800000001,34.485386],"type":"Point"}
}