{
  "type": "Feature",
  "properties": {
    "gn:admin1_code":"12.0",
    "gn:admin2_code":"7428111.0",
    "gn:admin3_code":"1462.0",
    "gn:asciiname":"Ochiai",
    "gn:country_code":"JP",
    "gn:dem":490,
    "gn:feature_class":"P",
    "gn:feature_code":"PPL",
    "gn:name":"Ochiai",
    "gn:population":0,
    "gn:timezone":"Asia/Tokyo",
    "iso:country":"JP",
    "wof:name":"Ochiai",
    "wof:placetype":"locality"
},
  "geometry": {"coordinates":[142.67250000000001,43.11944],"type":"Point"}
}