{
  "type": "Feature",
  "properties": {
    "gn:admin1_code":"3.0",
    "gn:admin2_code":"7439937.0",
    "gn:asciiname":"Koshishita",
    "gn:country_code":"JP",
    "gn:dem":23,
    "gn:feature_class":"P",
    "gn:feature_code":"PPL",
    "gn:name":"Koshishita",
    "gn:population":0,
    "gn:timezone":"Asia/Tokyo",
    "iso:country":"JP",
    "name:jpn_x_preferred":[
        "\u8d8a\u4e0b"
    ],
    "name:jpn_x_variant":[
        "\u3053\u3057\u3057\u305f",
        "\u30b3\u30b7\u30b7\u30bf"
    ],
    "wof:name":"Koshishita",
    "wof:placetype":"locality"
},
  "geometry": {"coordinates":[141.35602,40.79938],"type":"Point"}
}