{
  "type": "Feature",
  "properties": {
    "iso:country":"JP",
    "name:eng_x_preferred":[
        "Nagatsutaminamidai 7 Chome"
    ],
    "name:eng_x_variant":[
        "Nagatsutaminamidai 7 Choume",
        "Nagatsutaminamidai 7 Chome"
    ],
    "name:jpn_x_preferred":[
        "\uff17\u4e01\u76ee"
    ],
    "name:jpn_x_variant":[
        "\u306a\u304c\u3064\u305f\u307f\u306a\u307f\u3060\u3044 \uff17\u3061\u3087\u3046\u3081",
        "\u9577\u6d25\u7530\u307f\u306a\u307f\u53f0 \uff17\u4e01\u76ee",
        "\uff17\u3061\u3087\u3046\u3081"
    ],
    "qs:gn_local":0,
    "qs:local_max":6208,
    "qs:local_sum":82309,
    "qs:localhoods":190,
    "qs:name":"\uff17\u4e01\u76ee",
    "qs:name_adm0":"\u65e5\u672c",
    "qs:name_adm1":"\u795e\u5948\u5ddd\u770c",
    "qs:name_adm2":"\u7dd1\u533a",
    "qs:name_en":"Nagatsutaminamidai 7 Chome",
    "qs:name_lau":"\u9577\u6d25\u7530\u307f\u306a\u307f\u53f0",
    "qs:name_local":"\u6a2a\u6d5c\u5e02",
    "qs:photo_max":1,
    "qs:photo_sum":1,
    "qs:placetype":"Suburb",
    "qs:quad_count":1,
    "qs:woe_adm0":23424856,
    "qs:woe_adm1":2345868,
    "qs:woe_adm2":15015407,
    "qs:woe_lau":28416110,
    "qs:woe_local":1118550,
    "qs:woe_ver":"7.10.0",
    "wof:lang":[
        "jpn"
    ],
    "wof:name":"\uff17\u4e01\u76ee",
    "wof:placetype":"neighbourhood"
},
  "geometry": {"coordinates":[139.50714099999999,35.52552],"type":"Point"}
}