{
  "type": "Feature",
  "properties": {
    "gn:admin1_code":"05",
    "gn:admin2_code":"1849041.0",
    "gn:asciiname":"Orabana",
    "gn:cc2":"JP",
    "gn:country_code":"JP",
    "gn:dem":25,
    "gn:feature_class":"P",
    "gn:feature_code":"PPL",
    "gn:name":"\u014crabana",
    "gn:population":0,
    "gn:timezone":"Asia/Tokyo",
    "iso:country":"JP",
    "name:und_x_variant":[
        "\u014crahana"
    ],
    "wof:name":"Orabana",
    "wof:placetype":"locality"
},
  "geometry": {"coordinates":[132.47382999999999,33.25649],"type":"Point"}
}