{
  "type": "Feature",
  "properties": {
    "gn:admin1_code":"21.0",
    "gn:admin2_code":"1864975.0",
    "gn:admin3_code":"43432.0",
    "gn:asciiname":"Miyayama",
    "gn:country_code":"JP",
    "gn:dem":294,
    "gn:feature_class":"P",
    "gn:feature_code":"PPLL",
    "gn:name":"Miyayama",
    "gn:population":0,
    "gn:timezone":"Asia/Tokyo",
    "iso:country":"JP",
    "name:jpn_x_preferred":[
        "\u5bae\u5c71"
    ],
    "name:jpn_x_variant":[
        "\u307f\u3084\u3084\u307e",
        "\u30df\u30e4\u30e4\u30de"
    ],
    "wof:name":"Miyayama",
    "wof:placetype":"locality"
},
  "geometry": {"coordinates":[130.91947999999999,32.82311],"type":"Point"}
}