{
  "type": "Feature",
  "properties": {
    "gn:admin1_code":"15.0",
    "gn:admin2_code":"1851337.0",
    "gn:asciiname":"Sasanamimachi",
    "gn:country_code":"JP",
    "gn:dem":87,
    "gn:feature_class":"P",
    "gn:feature_code":"PPL",
    "gn:name":"Sasanamimachi",
    "gn:population":0,
    "gn:timezone":"Asia/Tokyo",
    "iso:country":"JP",
    "name:jpn_x_preferred":[
        "\u7b39\u6ce2\u753a"
    ],
    "wof:name":"Sasanamimachi",
    "wof:placetype":"locality"
},
  "geometry": {"coordinates":[137.23051999999998,37.50405],"type":"Point"}
}