{
  "type": "Feature",
  "properties": {
    "gn:admin1_code":"40",
    "gn:admin2_code":"1864487.0",
    "gn:asciiname":"Hatchobori",
    "gn:country_code":"JP",
    "gn:dem":21,
    "gn:feature_class":"P",
    "gn:feature_code":"PPL",
    "gn:name":"Hatch\u014dbori",
    "gn:population":0,
    "gn:timezone":"Asia/Tokyo",
    "iso:country":"JP",
    "name:jpn_x_preferred":[
        "\u516b\u4e01\u5800"
    ],
    "name:und_x_variant":[
        "Hatch\u014dbori"
    ],
    "wof:name":"Hatchobori",
    "wof:placetype":"locality"
},
  "geometry": {"coordinates":[139.77528999999998,35.67532999999999],"type":"Point"}
}