{
  "type": "Feature",
  "properties": {
    "gn:admin1_code":"2.0",
    "gn:admin2_code":"2111935.0",
    "gn:admin3_code":"5361.0",
    "gn:asciiname":"Gojonome",
    "gn:cc2":"JP",
    "gn:country_code":"JP",
    "gn:dem":14,
    "gn:feature_class":"P",
    "gn:feature_code":"PPL",
    "gn:name":"Goj\u014dnome",
    "gn:population":0,
    "gn:timezone":"Asia/Tokyo",
    "iso:country":"JP",
    "name:und_x_variant":[
        "Goj\u014dme",
        "Goj\u014dnome"
    ],
    "wof:name":"Gojonome",
    "wof:placetype":"locality"
},
  "geometry": {"coordinates":[140.11667,39.93333],"type":"Point"}
}