{
  "type": "Feature",
  "properties": {
    "gn:admin1_code":"2.0",
    "gn:admin2_code":"2111935.0",
    "gn:admin3_code":"5361.0",
    "gn:asciiname":"Gojonome",
    "gn:cc2":"JP",
    "gn:country_code":"JP",
    "gn:dem":14,
    "gn:feature_class":"P",
    "gn:feature_code":"PPL",
    "gn:name":"Goj\u014dnome",
    "gn:population":0,
    "gn:timezone":"Asia/Tokyo",
    "iso:country":"JP",
    "name:ceb_x_preferred":[
        "Goj\u014dme-machi"
    ],
    "name:fas_x_preferred":[
        "\u06af\u0648\u062c\u0648\u0645\u0647"
    ],
    "name:fra_x_preferred":[
        "Goj\u014dme"
    ],
    "name:ita_x_preferred":[
        "Goj\u014dme"
    ],
    "name:jpn_x_preferred":[
        "\u4e94\u57ce\u76ee\u753a"
    ],
    "name:kor_x_preferred":[
        "\uace0\uc870\uba54\uc815"
    ],
    "name:msa_x_preferred":[
        "Goj\u014dme"
    ],
    "name:mya_x_preferred":[
        "\u1002\u1031\u102b\u1037\u1002\u103b\u1031\u102c\u1038\u1019\u1032\u1019\u103c\u102d\u102f\u1037\u104a \u1021\u1001\u102d\u1010"
    ],
    "name:rus_x_preferred":[
        "\u0413\u043e\u0434\u0437\u0451\u043c\u0435"
    ],
    "name:spa_x_preferred":[
        "Goj\u014dme"
    ],
    "name:tgl_x_preferred":[
        "Goj\u014dme"
    ],
    "name:ukr_x_preferred":[
        "\u0490\u043e\u0434\u0437\u044c\u043e\u043c\u0435"
    ],
    "name:und_x_variant":[
        "Goj\u014dme",
        "Goj\u014dnome"
    ],
    "name:urd_x_preferred":[
        "\u06af\u0648\u062c\u0624\u0645\u06d2"
    ],
    "name:vie_x_preferred":[
        "Goj\u014dme"
    ],
    "name:zho_x_preferred":[
        "\u4e94\u57ce\u76ee\u753a"
    ],
    "wof:name":"Gojonome",
    "wof:placetype":"locality"
},
  "geometry": {"coordinates":[140.11667,39.93333],"type":"Point"}
}