{
  "type": "Feature",
  "properties": {
    "gn:admin1_code":"46.0",
    "gn:admin2_code":"7415908.0",
    "gn:admin3_code":"19425.0",
    "gn:asciiname":"Yanagihara",
    "gn:country_code":"JP",
    "gn:dem":1012,
    "gn:feature_class":"P",
    "gn:feature_code":"PPLL",
    "gn:name":"Yanagihara",
    "gn:population":0,
    "gn:timezone":"Asia/Tokyo",
    "iso:country":"JP",
    "name:jpn_x_preferred":[
        "\u67f3\u539f"
    ],
    "wof:name":"Yanagihara",
    "wof:placetype":"locality"
},
  "geometry": {"coordinates":[138.91363999999999,35.42018],"type":"Point"}
}