{
  "type": "Feature",
  "properties": {
    "gn:admin1_code":"29.0",
    "gn:admin2_code":"1863539.0",
    "gn:asciiname":"Shimojo",
    "gn:country_code":"JP",
    "gn:dem":11,
    "gn:feature_class":"P",
    "gn:feature_code":"PPL",
    "gn:name":"Shimoj\u014d",
    "gn:population":0,
    "gn:timezone":"Asia/Tokyo",
    "iso:country":"JP",
    "name:jpn_x_preferred":[
        "\u4e0b\u6761"
    ],
    "name:und_x_variant":[
        "Shimoj\u014d"
    ],
    "wof:name":"Shimojo",
    "wof:placetype":"locality"
},
  "geometry": {"coordinates":[139.16987,37.7636],"type":"Point"}
}