{
  "type": "Feature",
  "properties": {
    "gn:admin1_code":"13",
    "gn:admin2_code":"1862625.0",
    "gn:asciiname":"Yumesakicho-maenosho",
    "gn:country_code":"JP",
    "gn:dem":86,
    "gn:feature_class":"P",
    "gn:feature_code":"PPL",
    "gn:name":"Yumesakich\u014d-maenosh\u014d",
    "gn:population":0,
    "gn:timezone":"Asia/Tokyo",
    "iso:country":"JP",
    "name:jpn_x_preferred":[
        "\u5922\u524d\u753a\u524d\u4e4b\u5e84"
    ],
    "name:und_x_variant":[
        "Yumesakich\u014d-maenosh\u014d",
        "Maenosh\u014d"
    ],
    "wof:name":"Yumesakicho-maenosho",
    "wof:placetype":"locality"
},
  "geometry": {"coordinates":[134.68333000000001,34.96667],"type":"Point"}
}