{
  "type": "Feature",
  "properties": {
    "iso:country":"JP",
    "name:eng_x_preferred":[
        "Higashiko 5 Chome"
    ],
    "name:eng_x_variant":[
        "Higashikou 5 Choume",
        "Higashiko 5 Chome"
    ],
    "name:jpn_x_preferred":[
        "\uff15\u4e01\u76ee"
    ],
    "name:jpn_x_variant":[
        "\u3072\u304c\u3057\u3053\u3046 \uff15\u3061\u3087\u3046\u3081",
        "\u6771\u6e2f \uff15\u4e01\u76ee",
        "\uff15\u3061\u3087\u3046\u3081"
    ],
    "name:unk_x_variant":[
        "\uff15\u4e01\u76ee"
    ],
    "qs:gn_local":0,
    "qs:local_max":11,
    "qs:local_sum":11,
    "qs:localhoods":1,
    "qs:name":"\uff15\u4e01\u76ee",
    "qs:name_adm0":"\u65e5\u672c",
    "qs:name_adm1":"\u65b0\u6f5f\u770c",
    "qs:name_adm2":"\u5317\u84b2\u539f\u90e1",
    "qs:name_en":"Higashiko 5 Chome",
    "qs:name_lau":"\u6771\u6e2f",
    "qs:name_local":"\u8056\u7c60\u753a",
    "qs:photo_max":5,
    "qs:photo_sum":11,
    "qs:placetype":"Suburb",
    "qs:quad_count":5,
    "qs:woe_adm0":23424856,
    "qs:woe_adm1":2345878,
    "qs:woe_adm2":24857464,
    "qs:woe_lau":28422550,
    "qs:woe_local":1114228,
    "qs:woe_ver":"7.10.0",
    "wof:lang":[
        "jpn"
    ],
    "wof:name":"\uff15\u4e01\u76ee",
    "wof:placetype":"neighbourhood"
},
  "geometry": {"coordinates":[139.25295700000001,37.994786],"type":"Point"}
}