{
  "type": "Feature",
  "properties": {
    "gn:admin1_code":"42.0",
    "gn:admin2_code":"1855873.0",
    "gn:admin3_code":"16322.0",
    "gn:asciiname":"Nakamura",
    "gn:country_code":"JP",
    "gn:dem":294,
    "gn:feature_class":"P",
    "gn:feature_code":"PPL",
    "gn:name":"Nakamura",
    "gn:population":0,
    "gn:timezone":"Asia/Tokyo",
    "iso:country":"JP",
    "name:jpn_x_preferred":[
        "\u4e2d\u6751"
    ],
    "wof:name":"Nakamura",
    "wof:placetype":"locality"
},
  "geometry": {"coordinates":[137.44618,36.69388],"type":"Point"}
}