{
  "type": "Feature",
  "properties": {
    "gn:country":"JP",
    "gn:fcode":"PPLH",
    "gn:population":34354,
    "iso:country":"JP",
    "name:ceb_x_preferred":[
        "Hirara"
    ],
    "name:ces_x_preferred":[
        "Hirara"
    ],
    "name:eng_x_preferred":[
        "Hirara"
    ],
    "name:fra_x_preferred":[
        "Hirara"
    ],
    "name:gle_x_preferred":[
        "Hirara"
    ],
    "name:ita_x_preferred":[
        "Hirara"
    ],
    "name:jpn_x_preferred":[
        "\u5e73\u826f"
    ],
    "name:jpn_x_variant":[
        "\u3072\u3089\u3089",
        "\u5e73\u826f\u5e02"
    ],
    "name:kor_x_preferred":[
        "\ud788\ub77c\ub77c \uc2dc"
    ],
    "name:kor_x_variant":[
        "\ud788\ub77c\ub77c\uc2dc"
    ],
    "name:mlg_x_preferred":[
        "Hirara"
    ],
    "name:nld_x_preferred":[
        "Hirara"
    ],
    "name:por_x_preferred":[
        "Hirara"
    ],
    "name:slk_x_preferred":[
        "Hirara"
    ],
    "name:srp_x_preferred":[
        "\u0425\u0438\u0440\u0430\u0440\u0430"
    ],
    "name:tgk_x_preferred":[
        "\u04b2\u0438\u0440\u0430\u0440\u0430"
    ],
    "name:und_x_variant":[
        "Taira"
    ],
    "name:zho_x_preferred":[
        "\u5e73\u826f\u5e02"
    ],
    "qs:name":"Hirara",
    "qs:photos_9r":0,
    "qs:photos_sr":0,
    "qs:pop_sr":"7",
    "wof:name":"Hirara",
    "wof:placetype":"locality",
    "wof:population":34354
},
  "geometry": {"coordinates":[125.30222000000001,24.80379],"type":"Point"}
}