{
  "type": "Feature",
  "properties": {
    "iso:country":"JP",
    "name:eng_x_preferred":[
        "Osaka 2 Chome"
    ],
    "name:eng_x_variant":[
        "Ousaka 2 Choume",
        "Osaka 2 Chome"
    ],
    "name:jpn_x_preferred":[
        "\uff12\u4e01\u76ee"
    ],
    "name:jpn_x_variant":[
        "\u304a\u3046\u3055\u304b \uff12\u3061\u3087\u3046\u3081",
        "\u9022\u5742 \uff12\u4e01\u76ee",
        "\uff12\u3061\u3087\u3046\u3081"
    ],
    "qs:gn_local":0,
    "qs:local_max":966,
    "qs:local_sum":4101,
    "qs:localhoods":25,
    "qs:name":"\uff12\u4e01\u76ee",
    "qs:name_adm0":"\u65e5\u672c",
    "qs:name_adm1":"\u6ecb\u8cc0\u770c",
    "qs:name_en":"Osaka 2 Chome",
    "qs:name_lau":"\u9022\u5742",
    "qs:name_local":"\u5927\u6d25\u5e02",
    "qs:photo_max":8,
    "qs:photo_sum":13,
    "qs:placetype":"Suburb",
    "qs:quad_count":5,
    "qs:woe_adm0":23424856,
    "qs:woe_adm1":2345884,
    "qs:woe_adm2":0,
    "qs:woe_lau":28447964,
    "qs:woe_local":1118029,
    "qs:woe_ver":"7.10.0",
    "wof:lang":[
        "jpn"
    ],
    "wof:name":"\uff12\u4e01\u76ee",
    "wof:placetype":"neighbourhood"
},
  "geometry": {"coordinates":[135.84859,35.006552],"type":"Point"}
}