{
  "type": "Feature",
  "properties": {
    "iso:country":"JP",
    "name:eng_x_preferred":[
        "Kamikoshien 5 Chome"
    ],
    "name:eng_x_variant":[
        "Kamikoushien 5 Choume",
        "Kamikoshien 5 Chome"
    ],
    "name:jpn_x_preferred":[
        "\uff15\u4e01\u76ee"
    ],
    "name:jpn_x_variant":[
        "\u304b\u307f\u3053\u3046\u3057\u3048\u3093 \uff15\u3061\u3087\u3046\u3081",
        "\u4e0a\u7532\u5b50\u5712 \uff15\u4e01\u76ee",
        "\uff15\u3061\u3087\u3046\u3081"
    ],
    "qs:gn_adm0_cc":"JP",
    "qs:gn_local":1855207,
    "qs:gn_nam_loc":"\u897f\u5bae\u5e02, \u5175\u5eab\u770c, JP",
    "qs:gn_namadm1":"13",
    "qs:local_max":870,
    "qs:local_sum":3110,
    "qs:localhoods":22,
    "qs:name":"\uff15\u4e01\u76ee",
    "qs:name_adm0":"\u65e5\u672c",
    "qs:name_adm1":"\u5175\u5eab\u770c",
    "qs:name_en":"Kamikoshien 5 Chome",
    "qs:name_lau":"\u4e0a\u7532\u5b50\u5712",
    "qs:name_local":"\u897f\u5bae\u5e02",
    "qs:photo_max":14,
    "qs:photo_sum":15,
    "qs:placetype":"Suburb",
    "qs:quad_count":2,
    "qs:woe_adm0":23424856,
    "qs:woe_adm1":2345862,
    "qs:woe_adm2":0,
    "qs:woe_lau":28462199,
    "qs:woe_local":1112962,
    "qs:woe_ver":"7.10.0",
    "wof:lang":[
        "jpn"
    ],
    "wof:name":"\uff15\u4e01\u76ee",
    "wof:placetype":"neighbourhood"
},
  "geometry": {"coordinates":[135.35549900000001,34.73386],"type":"Point"}
}