{
  "type": "Feature",
  "properties": {
    "gn:admin1_code":"32.0",
    "gn:admin2_code":"1850907.0",
    "gn:asciiname":"Tano",
    "gn:country_code":"JP",
    "gn:dem":327,
    "gn:feature_class":"P",
    "gn:feature_code":"PPL",
    "gn:name":"Tan\u014d",
    "gn:population":0,
    "gn:timezone":"Asia/Tokyo",
    "iso:country":"JP",
    "name:jpn_x_preferred":[
        "\u7530\u80fd"
    ],
    "name:und_x_variant":[
        "Tan\u014d"
    ],
    "wof:name":"Tano",
    "wof:placetype":"locality"
},
  "geometry": {"coordinates":[135.58968000000002,34.95531],"type":"Point"}
}