{
  "type": "Feature",
  "properties": {
    "gn:admin1_code":"28.0",
    "gn:admin2_code":"7411375.0",
    "gn:admin3_code":"29427.0",
    "gn:asciiname":"Takatsukadai",
    "gn:country_code":"JP",
    "gn:dem":60,
    "gn:feature_class":"P",
    "gn:feature_code":"PPL",
    "gn:name":"Takatsukadai",
    "gn:population":0,
    "gn:timezone":"Asia/Tokyo",
    "iso:country":"JP",
    "name:jpn_x_preferred":[
        "\u9ad8\u585a\u53f0"
    ],
    "wof:name":"Takatsukadai",
    "wof:placetype":"locality"
},
  "geometry": {"coordinates":[135.72604999999999,34.58271],"type":"Point"}
}