{
  "type": "Feature",
  "properties": {
    "gn:admin1_code":"43",
    "gn:admin2_code":"1865121.0",
    "gn:asciiname":"Minoshima",
    "gn:country_code":"JP",
    "gn:dem":3,
    "gn:feature_class":"P",
    "gn:feature_code":"PPL",
    "gn:name":"Minoshima",
    "gn:population":0,
    "gn:timezone":"Asia/Tokyo",
    "iso:country":"JP",
    "name:jpn_x_preferred":[
        "\u7b95\u5cf6"
    ],
    "wof:name":"Minoshima",
    "wof:placetype":"locality"
},
  "geometry": {"coordinates":[135.11923999999999,34.08566],"type":"Point"}
}