{
  "type": "Feature",
  "properties": {
    "gn:admin1_code":"19.0",
    "gn:admin2_code":"1848350.0",
    "gn:admin3_code":"14109.0",
    "gn:asciiname":"Osone",
    "gn:country_code":"JP",
    "gn:dem":5,
    "gn:feature_class":"P",
    "gn:feature_code":"PPL",
    "gn:name":"\u014csone",
    "gn:population":0,
    "gn:timezone":"Asia/Tokyo",
    "iso:country":"JP",
    "name:jpn_x_preferred":[
        "\u5927\u66fd\u6839"
    ],
    "name:und_x_variant":[
        "\u014csone"
    ],
    "wof:name":"Osone",
    "wof:placetype":"locality"
},
  "geometry": {"coordinates":[139.62842000000001,35.53135],"type":"Point"}
}