{
  "type": "Feature",
  "properties": {
    "gn:admin1_code":"3.0",
    "gn:admin2_code":"2127674.0",
    "gn:asciiname":"Saihaba",
    "gn:country_code":"JP",
    "gn:dem":85,
    "gn:feature_class":"P",
    "gn:feature_code":"PPL",
    "gn:name":"Saihaba",
    "gn:population":0,
    "gn:timezone":"Asia/Tokyo",
    "iso:country":"JP",
    "name:jpn_x_preferred":[
        "\u4f50\u4e95\u5e45"
    ],
    "name:jpn_x_variant":[
        "\u3055\u3044\u306f\u3070",
        "\u30b5\u30a4\u30cf\u30d0"
    ],
    "wof:name":"Saihaba",
    "wof:placetype":"locality"
},
  "geometry": {"coordinates":[141.16721999999999,40.6092],"type":"Point"}
}