{
  "type": "Feature",
  "properties": {
    "gn:admin1_code":"21.0",
    "gn:admin2_code":"1850744.0",
    "gn:admin3_code":"43369.0",
    "gn:asciiname":"Suigen-kaitaku",
    "gn:country_code":"JP",
    "gn:dem":355,
    "gn:feature_class":"P",
    "gn:feature_code":"PPLL",
    "gn:name":"Suigen-kaitaku",
    "gn:population":0,
    "gn:timezone":"Asia/Tokyo",
    "iso:country":"JP",
    "name:jpn_x_preferred":[
        "\u6c34\u6e90\u958b\u62d3"
    ],
    "name:jpn_x_variant":[
        "\u3059\u3044\u3052\u3093\u304b\u3044\u305f\u304f",
        "\u30b9\u30a4\u30b2\u30f3\u30ab\u30a4\u30bf\u30af"
    ],
    "wof:name":"Suigen-kaitaku",
    "wof:placetype":"locality"
},
  "geometry": {"coordinates":[130.58787000000001,33.11148],"type":"Point"}
}