{
  "type": "Feature",
  "properties": {
    "iso:country":"JP",
    "name:eng_x_preferred":[
        "Moriyacho 3 Chome"
    ],
    "name:eng_x_variant":[
        "Moriyachou 3 Choume",
        "Moriyacho 3 Chome"
    ],
    "name:jpn_x_preferred":[
        "\uff13\u4e01\u76ee"
    ],
    "name:jpn_x_variant":[
        "\u3082\u308a\u3084\u3061\u3087\u3046 \uff13\u3061\u3087\u3046\u3081",
        "\u5b88\u5c4b\u753a \uff13\u4e01\u76ee",
        "\uff13\u3061\u3087\u3046\u3081"
    ],
    "qs:gn_local":0,
    "qs:local_max":6208,
    "qs:local_sum":82309,
    "qs:localhoods":190,
    "qs:name":"\uff13\u4e01\u76ee",
    "qs:name_adm0":"\u65e5\u672c",
    "qs:name_adm1":"\u795e\u5948\u5ddd\u770c",
    "qs:name_adm2":"\u795e\u5948\u5ddd\u533a",
    "qs:name_en":"Moriyacho 3 Chome",
    "qs:name_lau":"\u5b88\u5c4b\u753a",
    "qs:name_local":"\u6a2a\u6d5c\u5e02",
    "qs:photo_max":8,
    "qs:photo_sum":26,
    "qs:placetype":"Suburb",
    "qs:quad_count":9,
    "qs:woe_adm0":23424856,
    "qs:woe_adm1":2345868,
    "qs:woe_adm2":15015382,
    "qs:woe_lau":28415653,
    "qs:woe_local":1118550,
    "qs:woe_ver":"7.10.0",
    "wof:lang":[
        "jpn"
    ],
    "wof:name":"\uff13\u4e01\u76ee",
    "wof:placetype":"neighbourhood"
},
  "geometry": {"coordinates":[139.66050799999999,35.480441],"type":"Point"}
}