{
  "type": "Feature",
  "properties": {
    "gn:admin1_code":"4.0",
    "gn:admin2_code":"2111854.0",
    "gn:asciiname":"Kogutsuwa",
    "gn:country_code":"JP",
    "gn:dem":5,
    "gn:feature_class":"P",
    "gn:feature_code":"PPLL",
    "gn:name":"Kogutsuwa",
    "gn:population":0,
    "gn:timezone":"Asia/Tokyo",
    "iso:country":"JP",
    "name:jpn_x_preferred":[
        "\u5c0f\u8f61"
    ],
    "name:jpn_x_variant":[
        "\u3053\u3050\u3064\u308f",
        "\u30b3\u30b0\u30c4\u30ef"
    ],
    "wof:name":"Kogutsuwa",
    "wof:placetype":"locality"
},
  "geometry": {"coordinates":[140.32843,35.45041],"type":"Point"}
}