{
  "type": "Feature",
  "properties": {
    "gn:admin1_code":"4.0",
    "gn:admin2_code":"8304237.0",
    "gn:asciiname":"Sokura",
    "gn:country_code":"JP",
    "gn:dem":77,
    "gn:feature_class":"P",
    "gn:feature_code":"PPLL",
    "gn:name":"Sokura",
    "gn:population":0,
    "gn:timezone":"Asia/Tokyo",
    "iso:country":"JP",
    "name:jpn_x_preferred":[
        "\u66fd\u5009"
    ],
    "name:jpn_x_variant":[
        "\u305d\u304f\u3089",
        "\u30bd\u30af\u30e9"
    ],
    "wof:name":"Sokura",
    "wof:placetype":"locality"
},
  "geometry": {"coordinates":[140.10114999999999,35.33799000000001],"type":"Point"}
}