{
  "type": "Feature",
  "properties": {
    "gn:admin1_code":"12.0",
    "gn:admin2_code":"2128971.0",
    "gn:asciiname":"Habomai",
    "gn:country_code":"JP",
    "gn:dem":13,
    "gn:feature_class":"P",
    "gn:feature_code":"PPL",
    "gn:name":"Habomai",
    "gn:population":0,
    "gn:timezone":"Asia/Tokyo",
    "iso:country":"JP",
    "name:jpn_x_preferred":[
        "\u6b6f\u821e"
    ],
    "name:jpn_x_variant":[
        "\u306f\u307c\u307e\u3044",
        "\u30cf\u30dc\u30de\u30a4"
    ],
    "wof:name":"Habomai",
    "wof:placetype":"locality"
},
  "geometry": {"coordinates":[145.74635000000001,43.34247],"type":"Point"}
}