{
  "type": "Feature",
  "properties": {
    "gn:admin1_code":"33.0",
    "gn:admin2_code":"8300623.0",
    "gn:asciiname":"Hatashima",
    "gn:country_code":"JP",
    "gn:dem":35,
    "gn:feature_class":"P",
    "gn:feature_code":"PPL",
    "gn:name":"Hatashima",
    "gn:population":0,
    "gn:timezone":"Asia/Tokyo",
    "iso:country":"JP",
    "name:jpn_x_preferred":[
        "\u7551\u5cf6"
    ],
    "wof:name":"Hatashima",
    "wof:placetype":"locality"
},
  "geometry": {"coordinates":[129.95240000000001,33.39376],"type":"Point"}
}