{
  "type": "Feature",
  "properties": {
    "gn:admin1_code":"44",
    "gn:admin2_code":"1849562.0",
    "gn:asciiname":"Kurasawa",
    "gn:country_code":"JP",
    "gn:dem":204,
    "gn:feature_class":"P",
    "gn:feature_code":"PPL",
    "gn:name":"Kurasawa",
    "gn:population":0,
    "gn:timezone":"Asia/Tokyo",
    "iso:country":"JP",
    "name:jpn_x_preferred":[
        "\u5009\u6ca2"
    ],
    "name:und_x_variant":[
        "Kurazawa"
    ],
    "wof:name":"Kurasawa",
    "wof:placetype":"locality"
},
  "geometry": {"coordinates":[139.78023000000002,38.52576],"type":"Point"}
}