{
  "type": "Feature",
  "properties": {
    "gn:admin1_code":"21.0",
    "gn:admin2_code":"1859488.0",
    "gn:asciiname":"Motomura",
    "gn:country_code":"JP",
    "gn:dem":31,
    "gn:feature_class":"P",
    "gn:feature_code":"PPLL",
    "gn:name":"Motomura",
    "gn:population":0,
    "gn:timezone":"Asia/Tokyo",
    "iso:country":"JP",
    "name:jpn_x_preferred":[
        "\u5143\u6751"
    ],
    "name:jpn_x_variant":[
        "\u3082\u3068\u3080\u3089",
        "\u30e2\u30c8\u30e0\u30e9"
    ],
    "wof:name":"Motomura",
    "wof:placetype":"locality"
},
  "geometry": {"coordinates":[130.74594999999999,32.96241],"type":"Point"}
}