{
  "type": "Feature",
  "properties": {
    "gn:admin1_code":"21.0",
    "gn:admin2_code":"1850744.0",
    "gn:admin3_code":"43368.0",
    "gn:asciiname":"Kojinmachi",
    "gn:country_code":"JP",
    "gn:dem":4,
    "gn:feature_class":"P",
    "gn:feature_code":"PPLL",
    "gn:name":"K\u014djinmachi",
    "gn:population":0,
    "gn:timezone":"Asia/Tokyo",
    "iso:country":"JP",
    "name:jpn_x_preferred":[
        "\u8352\u795e\u753a"
    ],
    "name:jpn_x_variant":[
        "\u3053\u3046\u3058\u3093\u307e\u3061",
        "\u30b3\u30a6\u30b8\u30f3\u30de\u30c1"
    ],
    "name:und_x_variant":[
        "K\u014djinmachi"
    ],
    "wof:name":"Kojinmachi",
    "wof:placetype":"locality"
},
  "geometry": {"coordinates":[130.44606000000002,32.92846],"type":"Point"}
}