{
  "type": "Feature",
  "properties": {
    "gn:admin1_code":"12.0",
    "gn:admin2_code":"7429515.0",
    "gn:asciiname":"Tatsuushi",
    "gn:country_code":"JP",
    "gn:dem":207,
    "gn:feature_class":"P",
    "gn:feature_code":"PPL",
    "gn:name":"Tatsuushi",
    "gn:population":0,
    "gn:timezone":"Asia/Tokyo",
    "iso:country":"JP",
    "name:jpn_x_preferred":[
        "\u7acb\u725b"
    ],
    "name:jpn_x_variant":[
        "\u305f\u3064\u3046\u3057",
        "\u30bf\u30c4\u30a6\u30b7"
    ],
    "name:und_x_variant":[
        "Tachiushi"
    ],
    "wof:name":"Tatsuushi",
    "wof:placetype":"locality"
},
  "geometry": {"coordinates":[143.21666999999999,44.13333],"type":"Point"}
}