{
  "type": "Feature",
  "properties": {
    "gn:admin1_code":"21.0",
    "gn:admin2_code":"1862350.0",
    "gn:asciiname":"Nakabayashimachi",
    "gn:country_code":"JP",
    "gn:dem":102,
    "gn:feature_class":"P",
    "gn:feature_code":"PPL",
    "gn:name":"Nakabayashimachi",
    "gn:population":0,
    "gn:timezone":"Asia/Tokyo",
    "iso:country":"JP",
    "name:jpn_x_preferred":[
        "\u4e2d\u6797\u753a"
    ],
    "name:jpn_x_variant":[
        "\u306a\u304b\u3070\u3084\u3057\u307e\u3061",
        "\u30ca\u30ab\u30d0\u30e4\u30b7\u30de\u30c1"
    ],
    "wof:name":"Nakabayashimachi",
    "wof:placetype":"locality"
},
  "geometry": {"coordinates":[130.73612,32.22364],"type":"Point"}
}