{
  "type": "Feature",
  "properties": {
    "gn:admin1_code":"4.0",
    "gn:admin2_code":"2111854.0",
    "gn:asciiname":"Washinosu",
    "gn:country_code":"JP",
    "gn:dem":10,
    "gn:feature_class":"P",
    "gn:feature_code":"PPL",
    "gn:name":"Washinosu",
    "gn:population":0,
    "gn:timezone":"Asia/Tokyo",
    "iso:country":"JP",
    "name:jpn_x_preferred":[
        "\u9df2\u5de3"
    ],
    "name:jpn_x_variant":[
        "\u308f\u3057\u306e\u3059",
        "\u30ef\u30b7\u30ce\u30b9"
    ],
    "wof:name":"Washinosu",
    "wof:placetype":"locality"
},
  "geometry": {"coordinates":[140.27945,35.42655999999999],"type":"Point"}
}