{
  "type": "Feature",
  "properties": {
    "gn:admin1_code":"36.0",
    "gn:admin2_code":"1854361.0",
    "gn:admin3_code":"32528.0",
    "gn:asciiname":"Igo",
    "gn:country_code":"JP",
    "gn:dem":116,
    "gn:feature_class":"P",
    "gn:feature_code":"PPL",
    "gn:name":"Igo",
    "gn:population":0,
    "gn:timezone":"Asia/Tokyo",
    "iso:country":"JP",
    "name:ind_x_preferred":[
        "Igo"
    ],
    "name:jpn_x_preferred":[
        "\u4f0a\u5f8c"
    ],
    "name:lav_x_preferred":[
        "Igo"
    ],
    "name:srp_x_preferred":[
        "\u0418\u0433\u043e"
    ],
    "name:swe_x_preferred":[
        "Igo"
    ],
    "wof:name":"Igo",
    "wof:placetype":"locality"
},
  "geometry": {"coordinates":[133.27386999999999,36.32781],"type":"Point"}
}