{
  "type": "Feature",
  "properties": {
    "gn:admin1_code":"27.0",
    "gn:admin2_code":"7418810.0",
    "gn:asciiname":"Kamitsushimacho-furusato",
    "gn:country_code":"JP",
    "gn:dem":19,
    "gn:feature_class":"P",
    "gn:feature_code":"PPL",
    "gn:name":"Kamitsushimach\u014d-furusato",
    "gn:population":0,
    "gn:timezone":"Asia/Tokyo",
    "iso:country":"JP",
    "name:jpn_x_preferred":[
        "\u4e0a\u5bfe\u99ac\u753a\u53e4\u91cc"
    ],
    "name:und_x_variant":[
        "Kamitsushimach\u014d-furusato"
    ],
    "wof:name":"Kamitsushimacho-furusato",
    "wof:placetype":"locality"
},
  "geometry": {"coordinates":[129.46608999999998,34.65947],"type":"Point"}
}