{
  "type": "Feature",
  "properties": {
    "gn:admin1_code":"40",
    "gn:admin2_code":"1864529.0",
    "gn:asciiname":"Marunouchi",
    "gn:country_code":"JP",
    "gn:dem":23,
    "gn:feature_class":"P",
    "gn:feature_code":"PPL",
    "gn:name":"Marunouchi",
    "gn:population":0,
    "gn:timezone":"Asia/Tokyo",
    "iso:country":"JP",
    "name:deu_x_preferred":[
        "Marunouchi"
    ],
    "name:fas_x_preferred":[
        "\u0645\u0627\u0631\u0648\u0646\u0648\u0627\u0648\u0686\u06cc"
    ],
    "name:fra_x_preferred":[
        "Marunouchi"
    ],
    "name:jpn_x_preferred":[
        "\u6771\u4eac\u90fd\u5343\u4ee3\u7530\u533a\u4e38\u306e\u5185"
    ],
    "name:jpn_x_variant":[
        "\u4e38\u306e\u5185"
    ],
    "name:kor_x_preferred":[
        "\ub9c8\ub8e8\ub178\uc6b0\uce58"
    ],
    "name:rus_x_preferred":[
        "\u041c\u0430\u0440\u0443\u043d\u043e\u0443\u0442\u0438"
    ],
    "name:spa_x_preferred":[
        "Marunouchi"
    ],
    "name:tha_x_preferred":[
        "\u0e21\u0e32\u0e23\u0e39\u0e42\u0e19\u0e2d\u0e39\u0e08\u0e34"
    ],
    "name:tur_x_preferred":[
        "Marunouchi"
    ],
    "name:ukr_x_preferred":[
        "\u041c\u0430\u0440\u0443\u043d\u043e\u0443\u0447\u0456"
    ],
    "name:war_x_preferred":[
        "Marunouchi"
    ],
    "name:zho_x_preferred":[
        "\u4e38\u4e4b\u5167"
    ],
    "wof:name":"Marunouchi",
    "wof:placetype":"locality"
},
  "geometry": {"coordinates":[139.76328000000001,35.68145999999999],"type":"Point"}
}