{
  "type": "Feature",
  "properties": {
    "gn:admin1_code":"40",
    "gn:admin2_code":"1864529.0",
    "gn:asciiname":"Marunouchi",
    "gn:country_code":"JP",
    "gn:dem":23,
    "gn:feature_class":"P",
    "gn:feature_code":"PPL",
    "gn:name":"Marunouchi",
    "gn:population":0,
    "gn:timezone":"Asia/Tokyo",
    "iso:country":"JP",
    "name:jpn_x_preferred":[
        "\u6771\u4eac\u90fd\u5343\u4ee3\u7530\u533a\u4e38\u306e\u5185"
    ],
    "name:jpn_x_variant":[
        "\u4e38\u306e\u5185"
    ],
    "wof:name":"Marunouchi",
    "wof:placetype":"locality"
},
  "geometry": {"coordinates":[139.76328000000001,35.68145999999999],"type":"Point"}
}