{
  "type": "Feature",
  "properties": {
    "gn:admin1_code":"34.0",
    "gn:admin2_code":"7464128.0",
    "gn:asciiname":"Nishihara",
    "gn:country_code":"JP",
    "gn:dem":25,
    "gn:feature_class":"P",
    "gn:feature_code":"PPL",
    "gn:name":"Nishihara",
    "gn:population":0,
    "gn:timezone":"Asia/Tokyo",
    "iso:country":"JP",
    "name:jpn_x_preferred":[
        "\u897f\u539f"
    ],
    "wof:name":"Nishihara",
    "wof:placetype":"locality"
},
  "geometry": {"coordinates":[139.51476,35.84974000000001],"type":"Point"}
}