{
  "type": "Feature",
  "properties": {
    "gn:admin1_code":"7.0",
    "gn:admin2_code":"1859090.0",
    "gn:asciiname":"Yakuoji-onsen",
    "gn:country_code":"JP",
    "gn:dem":132,
    "gn:feature_class":"P",
    "gn:feature_code":"PPLL",
    "gn:name":"Yaku\u014dji-onsen",
    "gn:population":0,
    "gn:timezone":"Asia/Tokyo",
    "iso:country":"JP",
    "name:jpn_x_preferred":[
        "\u85ac\u738b\u5bfa\u6e29\u6cc9"
    ],
    "name:und_x_variant":[
        "Yaku\u014dji-onsen"
    ],
    "wof:name":"Yakuoji-onsen",
    "wof:placetype":"locality"
},
  "geometry": {"coordinates":[130.52319,33.71250999999999],"type":"Point"}
}