{
  "type": "Feature",
  "properties": {
    "gn:admin1_code":"37.0",
    "gn:admin2_code":"1851376.0",
    "gn:asciiname":"Waichi",
    "gn:country_code":"JP",
    "gn:dem":196,
    "gn:feature_class":"P",
    "gn:feature_code":"PPLL",
    "gn:name":"Waichi",
    "gn:population":0,
    "gn:timezone":"Asia/Tokyo",
    "iso:country":"JP",
    "name:jpn_x_preferred":[
        "\u548c\u5e02"
    ],
    "wof:name":"Waichi",
    "wof:placetype":"locality"
},
  "geometry": {"coordinates":[138.91938999999999,35.19734000000001],"type":"Point"}
}