{
  "type": "Feature",
  "properties": {
    "iso:country":"JP",
    "name:eng_x_preferred":[
        "Fujimi 2 Chome"
    ],
    "name:eng_x_variant":[
        "Fujimi 2 Choume",
        "Fujimi 2 Chome"
    ],
    "name:jpn_x_preferred":[
        "\uff12\u4e01\u76ee"
    ],
    "name:jpn_x_variant":[
        "\u3075\u3058\u307f \uff12\u3061\u3087\u3046\u3081",
        "\u5bcc\u58eb\u898b \uff12\u4e01\u76ee",
        "\uff12\u3061\u3087\u3046\u3081"
    ],
    "name:unk_x_variant":[
        "\uff12\u4e01\u76ee"
    ],
    "qs:gn_local":0,
    "qs:local_max":59,
    "qs:local_sum":164,
    "qs:localhoods":5,
    "qs:name":"\uff12\u4e01\u76ee",
    "qs:name_adm0":"\u65e5\u672c",
    "qs:name_adm1":"\u5343\u8449\u770c",
    "qs:name_en":"Fujimi 2 Chome",
    "qs:name_lau":"\u5bcc\u58eb\u898b",
    "qs:name_local":"\u6728\u66f4\u6d25\u5e02",
    "qs:photo_max":23,
    "qs:photo_sum":59,
    "qs:placetype":"Suburb",
    "qs:quad_count":6,
    "qs:woe_adm0":23424856,
    "qs:woe_adm1":2345854,
    "qs:woe_adm2":0,
    "qs:woe_lau":28411141,
    "qs:woe_local":1117525,
    "qs:woe_ver":"7.10.0",
    "wof:lang":[
        "jpn"
    ],
    "wof:name":"\uff12\u4e01\u76ee",
    "wof:placetype":"neighbourhood"
},
  "geometry": {"coordinates":[139.91578100000001,35.382369],"type":"Point"}
}