{
  "type": "Feature",
  "properties": {
    "iso:country":"JP",
    "label:eng_x_preferred_longname":[
        "Ikoma City"
    ],
    "label:eng_x_preferred_placetype":[
        "city"
    ],
    "name:eng_x_preferred":[
        "Ikoma"
    ],
    "name:eng_x_variant":[
        "Ikoma City"
    ],
    "name:jpn_x_preferred":[
        "\u751f\u99d2\u5e02"
    ],
    "qs:name":"\u751f\u99d2\u5e02",
    "qs:name_adm0":"\u65e5\u672c",
    "qs:name_adm1":"\u5948\u826f\u770c",
    "qs:photos":173,
    "qs:photos_1k":35,
    "qs:photos_9k":5,
    "qs:photos_9r":7,
    "qs:photos_all":1184,
    "qs:photos_sr":4,
    "qs:placetype":"Town",
    "qs:pop_sr":"0",
    "wof:name":"Ikoma",
    "wof:placetype":"locality"
},
  "geometry": {"coordinates":[135.711364,34.699989],"type":"Point"}
}