{
  "type": "Feature",
  "properties": {
    "gn:admin1_code":"12.0",
    "gn:admin2_code":"7428084.0",
    "gn:admin3_code":"1609.0",
    "gn:asciiname":"Endomo",
    "gn:country_code":"JP",
    "gn:dem":30,
    "gn:feature_class":"P",
    "gn:feature_code":"PPLL",
    "gn:name":"Endomo",
    "gn:population":0,
    "gn:timezone":"Asia/Tokyo",
    "iso:country":"JP",
    "name:jpn_x_preferred":[
        "\u30a8\u30f3\u30c9\u30e2"
    ],
    "name:jpn_x_variant":[
        "\u3048\u3093\u3069\u3082"
    ],
    "wof:name":"Endomo",
    "wof:placetype":"locality"
},
  "geometry": {"coordinates":[143.19923,41.95903],"type":"Point"}
}