{
  "type": "Feature",
  "properties": {
    "gn:admin1_code":"21.0",
    "gn:admin2_code":"1848441.0",
    "gn:asciiname":"Itaneri",
    "gn:country_code":"JP",
    "gn:dem":134,
    "gn:feature_class":"P",
    "gn:feature_code":"PPLL",
    "gn:name":"Itaneri",
    "gn:population":0,
    "gn:timezone":"Asia/Tokyo",
    "iso:country":"JP",
    "name:jpn_x_preferred":[
        "\u677f\u7df4"
    ],
    "wof:name":"Itaneri",
    "wof:placetype":"locality"
},
  "geometry": {"coordinates":[130.58255,32.39082],"type":"Point"}
}