{
  "type": "Feature",
  "properties": {
    "gn:admin1_code":"24.0",
    "gn:admin2_code":"2111147.0",
    "gn:admin3_code":"4104.0",
    "gn:asciiname":"Akiumachi-baba",
    "gn:country_code":"JP",
    "gn:dem":198,
    "gn:feature_class":"P",
    "gn:feature_code":"PPL",
    "gn:name":"Akiumachi-baba",
    "gn:population":0,
    "gn:timezone":"Asia/Tokyo",
    "iso:country":"JP",
    "name:jpn_x_preferred":[
        "\u79cb\u4fdd\u753a\u99ac\u5834"
    ],
    "name:und_x_variant":[
        "Baba"
    ],
    "wof:name":"Akiumachi-baba",
    "wof:placetype":"locality"
},
  "geometry": {"coordinates":[140.64193999999998,38.26778],"type":"Point"}
}