{
  "type": "Feature",
  "properties": {
    "gn:admin1_code":"47",
    "gn:admin2_code":"1858371.0",
    "gn:admin3_code":"47308.0",
    "gn:asciiname":"Uzanbaru",
    "gn:country_code":"JP",
    "gn:dem":17,
    "gn:feature_class":"P",
    "gn:feature_code":"PPL",
    "gn:name":"Uzanbaru",
    "gn:population":0,
    "gn:timezone":"Asia/Tokyo",
    "iso:country":"JP",
    "name:jpn_x_preferred":[
        "\u5b87\u5c71\u539f"
    ],
    "name:jpn_x_variant":[
        "\u3046\u3056\u3093\u3070\u308b"
    ],
    "name:und_x_variant":[
        "Usambara",
        "Usambaru",
        "Uzanbaru"
    ],
    "wof:name":"Uzanbaru",
    "wof:placetype":"locality"
},
  "geometry": {"coordinates":[127.88204,26.70011],"type":"Point"}
}