{
  "type": "Feature",
  "properties": {
    "gn:admin1_code":"46.0",
    "gn:admin2_code":"1857168.0",
    "gn:admin3_code":"19365.0",
    "gn:asciiname":"Nakanokura",
    "gn:country_code":"JP",
    "gn:dem":482,
    "gn:feature_class":"P",
    "gn:feature_code":"PPL",
    "gn:name":"Nakanokura",
    "gn:population":0,
    "gn:timezone":"Asia/Tokyo",
    "iso:country":"JP",
    "name:jpn_x_preferred":[
        "\u4e2d\u30ce\u5009"
    ],
    "wof:name":"Nakanokura",
    "wof:placetype":"locality"
},
  "geometry": {"coordinates":[138.53703000000002,35.47594],"type":"Point"}
}