{
  "type": "Feature",
  "properties": {
    "gn:admin1_code":"12.0",
    "gn:admin2_code":"2128405.0",
    "gn:admin3_code":"1519.0",
    "gn:asciiname":"Asahihama",
    "gn:country_code":"JP",
    "gn:dem":1,
    "gn:feature_class":"P",
    "gn:feature_code":"PPL",
    "gn:name":"Asahihama",
    "gn:population":0,
    "gn:timezone":"Asia/Tokyo",
    "iso:country":"JP",
    "name:jpn_x_preferred":[
        "\u65ed\u6d5c"
    ],
    "name:jpn_x_variant":[
        "\u3042\u3055\u3072\u306f\u307e",
        "\u30a2\u30b5\u30d2\u30cf\u30de"
    ],
    "name:und_x_variant":[
        "Otoromanai",
        "Afutoromanai",
        "Asahihama"
    ],
    "wof:name":"Asahihama",
    "wof:placetype":"locality"
},
  "geometry": {"coordinates":[141.3169,45.19276],"type":"Point"}
}