{
  "type": "Feature",
  "properties": {
    "gn:admin1_code":"4.0",
    "gn:admin2_code":"7465521.0",
    "gn:asciiname":"Daihanzu",
    "gn:country_code":"JP",
    "gn:dem":8,
    "gn:feature_class":"P",
    "gn:feature_code":"PPLL",
    "gn:name":"Daihanzu",
    "gn:population":0,
    "gn:timezone":"Asia/Tokyo",
    "iso:country":"JP",
    "name:jpn_x_preferred":[
        "\u5927\u534a\u6d25"
    ],
    "name:jpn_x_variant":[
        "\u3060\u3044\u306f\u3093\u3065",
        "\u30c0\u30a4\u30cf\u30f3\u30c5"
    ],
    "wof:name":"Daihanzu",
    "wof:placetype":"locality"
},
  "geometry": {"coordinates":[139.84285,35.03467],"type":"Point"}
}