{
  "type": "Feature",
  "properties": {
    "gn:admin1_code":"21.0",
    "gn:admin2_code":"7413151.0",
    "gn:asciiname":"Yatsutsuji",
    "gn:country_code":"JP",
    "gn:dem":303,
    "gn:feature_class":"P",
    "gn:feature_code":"PPLL",
    "gn:name":"Yatsutsuji",
    "gn:population":0,
    "gn:timezone":"Asia/Tokyo",
    "iso:country":"JP",
    "name:jpn_x_preferred":[
        "\u516b\u8fbb"
    ],
    "name:jpn_x_variant":[
        "\u3084\u3064\u3064\u3058",
        "\u30e4\u30c4\u30c4\u30b8"
    ],
    "wof:name":"Yatsutsuji",
    "wof:placetype":"locality"
},
  "geometry": {"coordinates":[130.34491,32.46755],"type":"Point"}
}