{
  "type": "Feature",
  "properties": {
    "gn:admin1_code":"7.0",
    "gn:admin2_code":"1851269.0",
    "gn:admin3_code":"40602.0",
    "gn:asciiname":"Honmura",
    "gn:country_code":"JP",
    "gn:dem":91,
    "gn:feature_class":"P",
    "gn:feature_code":"PPLL",
    "gn:name":"Honmura",
    "gn:population":0,
    "gn:timezone":"Asia/Tokyo",
    "iso:country":"JP",
    "name:jpn_x_preferred":[
        "\u672c\u6751"
    ],
    "wof:name":"Honmura",
    "wof:placetype":"locality"
},
  "geometry": {"coordinates":[130.86328,33.5547],"type":"Point"}
}