{
  "type": "Feature",
  "properties": {
    "gn:admin1_code":"4.0",
    "gn:admin2_code":"8304237.0",
    "gn:asciiname":"Miyashimone",
    "gn:country_code":"JP",
    "gn:dem":27,
    "gn:feature_class":"P",
    "gn:feature_code":"PPLL",
    "gn:name":"Miyashimone",
    "gn:population":0,
    "gn:timezone":"Asia/Tokyo",
    "iso:country":"JP",
    "name:jpn_x_preferred":[
        "\u5bae\u4e0b\u6839"
    ],
    "name:jpn_x_variant":[
        "\u307f\u3084\u3057\u3082\u306d",
        "\u30df\u30e4\u30b7\u30e2\u30cd"
    ],
    "wof:name":"Miyashimone",
    "wof:placetype":"locality"
},
  "geometry": {"coordinates":[139.9263,35.35516],"type":"Point"}
}