{
  "type": "Feature",
  "properties": {
    "gn:admin1_code":"4.0",
    "gn:admin2_code":"1859468.0",
    "gn:asciiname":"Hongo",
    "gn:country_code":"JP",
    "gn:dem":19,
    "gn:feature_class":"P",
    "gn:feature_code":"PPLL",
    "gn:name":"Hong\u014d",
    "gn:population":0,
    "gn:timezone":"Asia/Tokyo",
    "iso:country":"JP",
    "name:jpn_x_preferred":[
        "\u672c\u90f7"
    ],
    "name:jpn_x_variant":[
        "\u307b\u3093\u3054\u3046",
        "\u30db\u30f3\u30b4\u30a6"
    ],
    "name:und_x_variant":[
        "Hong\u014d"
    ],
    "wof:name":"Hongo",
    "wof:placetype":"locality"
},
  "geometry": {"coordinates":[139.93708999999998,35.31463],"type":"Point"}
}