{
  "type": "Feature",
  "properties": {
    "gn:admin1_code":"42",
    "gn:admin2_code":"1862610.0",
    "gn:asciiname":"Iwagase",
    "gn:country_code":"JP",
    "gn:dem":36,
    "gn:feature_class":"P",
    "gn:feature_code":"PPL",
    "gn:name":"Iwagase",
    "gn:population":0,
    "gn:timezone":"Asia/Tokyo",
    "iso:country":"JP",
    "name:jpn_x_preferred":[
        "\u5ca9\u702c"
    ],
    "name:und_x_variant":[
        "Iwase",
        "Iwagase"
    ],
    "wof:name":"Iwagase",
    "wof:placetype":"locality"
},
  "geometry": {"coordinates":[136.87766999999999,36.8292],"type":"Point"}
}