{
  "type": "Feature",
  "properties": {
    "gn:admin1_code":"34.0",
    "gn:admin2_code":"7464124.0",
    "gn:asciiname":"Shobucho-sanga",
    "gn:country_code":"JP",
    "gn:dem":13,
    "gn:feature_class":"P",
    "gn:feature_code":"PPL",
    "gn:name":"Sh\u014dbuch\u014d-sanga",
    "gn:population":0,
    "gn:timezone":"Asia/Tokyo",
    "iso:country":"JP",
    "name:jpn_x_preferred":[
        "\u83d6\u84b2\u753a\u4e09\u7b87"
    ],
    "name:jpn_x_variant":[
        "\u3057\u3087\u3046\u3076\u3061\u3087\u3046\u3055\u3093\u304c",
        "\u30b7\u30e7\u30a6\u30d6\u30c1\u30e7\u30a6\u30b5\u30f3\u30ac"
    ],
    "name:und_x_variant":[
        "Sh\u014dbuch\u014d-sanga"
    ],
    "wof:name":"Shobucho-sanga",
    "wof:placetype":"locality"
},
  "geometry": {"coordinates":[139.61876999999998,36.06354],"type":"Point"}
}