{
  "type": "Feature",
  "properties": {
    "gn:admin1_code":"11",
    "gn:admin2_code":"1856691.0",
    "gn:asciiname":"Hige",
    "gn:country_code":"JP",
    "gn:dem":174,
    "gn:feature_class":"P",
    "gn:feature_code":"PPL",
    "gn:name":"Hige",
    "gn:population":0,
    "gn:timezone":"Asia/Tokyo",
    "iso:country":"JP",
    "wof:name":"Hige",
    "wof:placetype":"locality"
},
  "geometry": {"coordinates":[132.81666999999999,34.81667],"type":"Point"}
}