{
  "type": "Feature",
  "properties": {
    "gn:admin1_code":"05",
    "gn:admin2_code":"1859256.0",
    "gn:admin3_code":"38484.0",
    "gn:asciiname":"Matsumaru",
    "gn:cc2":"JP",
    "gn:country_code":"JP",
    "gn:dem":91,
    "gn:feature_class":"P",
    "gn:feature_code":"PPL",
    "gn:name":"Matsumaru",
    "gn:population":0,
    "gn:timezone":"Asia/Tokyo",
    "iso:country":"JP",
    "name:und_x_variant":[
        "Akeharu"
    ],
    "wof:name":"Matsumaru",
    "wof:placetype":"locality"
},
  "geometry": {"coordinates":[132.70762999999999,33.22749],"type":"Point"}
}