{
  "type": "Feature",
  "properties": {
    "gn:country":"JP",
    "gn:fcode":"ADM3",
    "gn:pop":0,
    "iso:country":"JP",
    "name:jpn_x_preferred":[
        "\u5de6\u4eac\u533a"
    ],
    "name:jpn_x_variant":[
        "\u3055\u304d\u3087\u3046\u304f",
        "\u4eac\u90fd\u5e02\u5de6\u4eac\u533a"
    ],
    "name:unk_x_variant":[
        "Sa-ky\u014d-ku"
    ],
    "qs:name":"Saky\u014d-ku",
    "qs:photos_9r":0,
    "qs:photos_sr":0,
    "qs:pop_sr":"0",
    "wof:name":"Saky\u014d-ku",
    "wof:placetype":"localadmin",
    "wof:population":0
},
  "geometry": {"coordinates":[135.79624999999999,35.16563],"type":"Point"}
}