{
  "type": "Feature",
  "properties": {
    "gn:admin1_code":"4.0",
    "gn:admin2_code":"2112997.0",
    "gn:admin3_code":"12427.0",
    "gn:asciiname":"Horinouchi",
    "gn:country_code":"JP",
    "gn:dem":46,
    "gn:feature_class":"P",
    "gn:feature_code":"PPLL",
    "gn:name":"Horinouchi",
    "gn:population":0,
    "gn:timezone":"Asia/Tokyo",
    "iso:country":"JP",
    "name:jpn_x_preferred":[
        "\u5800\u4e4b\u5185"
    ],
    "name:jpn_x_variant":[
        "\u307b\u308a\u306e\u3046\u3061",
        "\u30db\u30ea\u30ce\u30a6\u30c1"
    ],
    "wof:name":"Horinouchi",
    "wof:placetype":"locality"
},
  "geometry": {"coordinates":[140.22537,35.36247],"type":"Point"}
}