{
  "type": "Feature",
  "properties": {
    "gn:admin1_code":"26",
    "gn:admin2_code":"1851367.0",
    "gn:admin3_code":"20363.0",
    "gn:asciiname":"Nakazawa",
    "gn:cc2":"JP",
    "gn:country_code":"JP",
    "gn:dem":1008,
    "gn:feature_class":"P",
    "gn:feature_code":"PPL",
    "gn:name":"Nakazawa",
    "gn:population":0,
    "gn:timezone":"Asia/Tokyo",
    "iso:country":"JP",
    "name:fin_x_preferred":[
        "Nakazawa"
    ],
    "name:und_x_variant":[
        "Nakasawa",
        "Nakassawa"
    ],
    "wof:name":"Nakazawa",
    "wof:placetype":"locality"
},
  "geometry": {"coordinates":[138.21666999999999,35.98333],"type":"Point"}
}