{
  "type": "Feature",
  "properties": {
    "gn:admin1_code":"26.0",
    "gn:admin2_code":"1854378.0",
    "gn:asciiname":"Komazawa",
    "gn:country_code":"JP",
    "gn:dem":774,
    "gn:feature_class":"P",
    "gn:feature_code":"PPLL",
    "gn:name":"Komazawa",
    "gn:population":0,
    "gn:timezone":"Asia/Tokyo",
    "iso:country":"JP",
    "name:jpn_x_preferred":[
        "\u99d2\u6ca2"
    ],
    "wof:name":"Komazawa",
    "wof:placetype":"locality"
},
  "geometry": {"coordinates":[138.01886999999999,36.02602],"type":"Point"}
}