{
  "type": "Feature",
  "properties": {
    "gn:admin1_code":"19.0",
    "gn:admin2_code":"1862461.0",
    "gn:asciiname":"Nakado",
    "gn:country_code":"JP",
    "gn:dem":4,
    "gn:feature_class":"P",
    "gn:feature_code":"PPL",
    "gn:name":"Nakad\u014d",
    "gn:population":0,
    "gn:timezone":"Asia/Tokyo",
    "iso:country":"JP",
    "name:jpn_x_preferred":[
        "\u4e2d\u5802"
    ],
    "name:und_x_variant":[
        "Nakad\u014d"
    ],
    "wof:name":"Nakado",
    "wof:placetype":"locality"
},
  "geometry": {"coordinates":[139.36143999999999,35.33564000000001],"type":"Point"}
}