{
  "type": "Feature",
  "properties": {
    "gn:admin1_code":"16.0",
    "gn:admin2_code":"2128940.0",
    "gn:asciiname":"Serisawa",
    "gn:country_code":"JP",
    "gn:dem":148,
    "gn:feature_class":"P",
    "gn:feature_code":"PPL",
    "gn:name":"Serisawa",
    "gn:population":0,
    "gn:timezone":"Asia/Tokyo",
    "iso:country":"JP",
    "name:jpn_x_preferred":[
        "\u82b9\u6ca2"
    ],
    "name:jpn_x_variant":[
        "\u305b\u308a\u3055\u308f",
        "\u30bb\u30ea\u30b5\u30ef"
    ],
    "wof:name":"Serisawa",
    "wof:placetype":"locality"
},
  "geometry": {"coordinates":[141.22728999999995,40.30722],"type":"Point"}
}