{
  "type": "Feature",
  "properties": {
    "gn:admin1_code":"3.0",
    "gn:admin2_code":"2127674.0",
    "gn:asciiname":"Ushirono",
    "gn:country_code":"JP",
    "gn:dem":64,
    "gn:feature_class":"P",
    "gn:feature_code":"PPL",
    "gn:name":"Ushirono",
    "gn:population":0,
    "gn:timezone":"Asia/Tokyo",
    "iso:country":"JP",
    "name:jpn_x_preferred":[
        "\u5f8c\u91ce"
    ],
    "name:jpn_x_variant":[
        "\u3046\u3057\u308d\u306e",
        "\u30a6\u30b7\u30ed\u30ce"
    ],
    "wof:name":"Ushirono",
    "wof:placetype":"locality"
},
  "geometry": {"coordinates":[141.19711999999996,40.64106],"type":"Point"}
}