{
  "type": "Feature",
  "properties": {
    "gn:admin1_code":"34",
    "gn:asciiname":"Takatsuto",
    "gn:country_code":"JP",
    "gn:dem":441,
    "gn:feature_class":"P",
    "gn:feature_code":"PPL",
    "gn:name":"Takatsuto",
    "gn:population":0,
    "gn:timezone":"Asia/Tokyo",
    "iso:country":"JP",
    "wof:name":"Takatsuto",
    "wof:placetype":"locality"
},
  "geometry": {"coordinates":[139.22556,35.83972],"type":"Point"}
}