{
  "type": "Feature",
  "properties": {
    "gn:admin1_code":"32.0",
    "gn:admin2_code":"1863185.0",
    "gn:asciiname":"Mai",
    "gn:country_code":"JP",
    "gn:dem":45,
    "gn:feature_class":"P",
    "gn:feature_code":"PPL",
    "gn:name":"Mai",
    "gn:population":0,
    "gn:timezone":"Asia/Tokyo",
    "iso:country":"JP",
    "name:jpn_x_preferred":[
        "\u821e"
    ],
    "wof:name":"Mai",
    "wof:placetype":"locality"
},
  "geometry": {"coordinates":[135.23088000000001,34.34203],"type":"Point"}
}