{
  "type": "Feature",
  "properties": {
    "gn:admin1_code":"32.0",
    "gn:admin2_code":"1863185.0",
    "gn:asciiname":"Mai",
    "gn:country_code":"JP",
    "gn:dem":45,
    "gn:feature_class":"P",
    "gn:feature_code":"PPL",
    "gn:name":"Mai",
    "gn:population":0,
    "gn:timezone":"Asia/Tokyo",
    "iso:country":"JP",
    "name:als_x_preferred":[
        "Mai"
    ],
    "name:arg_x_preferred":[
        "Mai"
    ],
    "name:bar_x_preferred":[
        "Mai"
    ],
    "name:ceb_x_preferred":[
        "Mai"
    ],
    "name:deu_x_preferred":[
        "Mai"
    ],
    "name:fin_x_preferred":[
        "Mai"
    ],
    "name:fra_x_preferred":[
        "Mai"
    ],
    "name:jpn_x_preferred":[
        "\u821e"
    ],
    "name:lin_x_preferred":[
        "Mai"
    ],
    "name:nds_x_preferred":[
        "Mai"
    ],
    "name:nld_x_preferred":[
        "Mai"
    ],
    "name:nor_x_preferred":[
        "Mai"
    ],
    "name:pol_x_preferred":[
        "Mai"
    ],
    "name:spa_x_preferred":[
        "Mai"
    ],
    "name:vie_x_preferred":[
        "Mai"
    ],
    "wof:name":"Mai",
    "wof:placetype":"locality"
},
  "geometry": {"coordinates":[135.23088000000001,34.34203],"type":"Point"}
}