{
  "type": "Feature",
  "properties": {
    "gn:admin1_code":"33.0",
    "gn:admin2_code":"1854650.0",
    "gn:asciiname":"Ogimachi-hatakeda",
    "gn:country_code":"JP",
    "gn:dem":29,
    "gn:feature_class":"P",
    "gn:feature_code":"PPL",
    "gn:name":"Ogimachi-hatakeda",
    "gn:population":0,
    "gn:timezone":"Asia/Tokyo",
    "iso:country":"JP",
    "name:jpn_x_preferred":[
        "\u5c0f\u57ce\u753a\u7551\u7530"
    ],
    "wof:name":"Ogimachi-hatakeda",
    "wof:placetype":"locality"
},
  "geometry": {"coordinates":[130.18702999999999,33.29476],"type":"Point"}
}