{
  "type": "Feature",
  "properties": {
    "gn:admin1_code":"23.0",
    "gn:admin2_code":"1856290.0",
    "gn:asciiname":"Matsusakimachi",
    "gn:country_code":"JP",
    "gn:dem":193,
    "gn:feature_class":"P",
    "gn:feature_code":"PPL",
    "gn:name":"Matsusakimachi",
    "gn:population":0,
    "gn:timezone":"Asia/Tokyo",
    "iso:country":"JP",
    "name:jpn_x_preferred":[
        "\u677e\u5d0e\u753a"
    ],
    "wof:name":"Matsusakimachi",
    "wof:placetype":"locality"
},
  "geometry": {"coordinates":[136.08851000000001,34.62416],"type":"Point"}
}