{
  "type": "Feature",
  "properties": {
    "gn:admin1_code":"28.0",
    "gn:admin2_code":"1853062.0",
    "gn:asciiname":"Abe",
    "gn:country_code":"JP",
    "gn:dem":88,
    "gn:feature_class":"P",
    "gn:feature_code":"PPL",
    "gn:name":"Abe",
    "gn:population":0,
    "gn:timezone":"Asia/Tokyo",
    "iso:country":"JP",
    "name:cat_x_preferred":[
        "Abe"
    ],
    "name:ceb_x_preferred":[
        "Abe"
    ],
    "name:ces_x_preferred":[
        "Abe"
    ],
    "name:dan_x_preferred":[
        "Abe"
    ],
    "name:deu_x_preferred":[
        "Abe"
    ],
    "name:est_x_preferred":[
        "Abe"
    ],
    "name:fin_x_preferred":[
        "Abe"
    ],
    "name:fra_x_preferred":[
        "Abe"
    ],
    "name:jpn_x_preferred":[
        "\u963f\u90e8"
    ],
    "name:kat_x_preferred":[
        "\u10d0\u10d1\u10d4"
    ],
    "name:nld_x_preferred":[
        "Abe"
    ],
    "name:pol_x_preferred":[
        "Abe"
    ],
    "name:por_x_preferred":[
        "Abe"
    ],
    "name:spa_x_preferred":[
        "Abe"
    ],
    "name:swe_x_preferred":[
        "Abe"
    ],
    "wof:name":"Abe",
    "wof:placetype":"locality"
},
  "geometry": {"coordinates":[135.84094999999999,34.50238],"type":"Point"}
}