{
  "type": "Feature",
  "properties": {
    "gn:admin1_code":"40",
    "gn:admin2_code":"1863453.0",
    "gn:admin3_code":"13401.0",
    "gn:asciiname":"Mikonoo",
    "gn:country_code":"JP",
    "gn:dem":169,
    "gn:feature_class":"P",
    "gn:feature_code":"PPLL",
    "gn:name":"Mikonoo",
    "gn:population":0,
    "gn:timezone":"Asia/Tokyo",
    "iso:country":"JP",
    "name:jpn_x_preferred":[
        "\u795e\u5b50\u5c3e"
    ],
    "name:und_x_variant":[
        "Kamikonoo",
        "Kamijinoo"
    ],
    "wof:name":"Mikonoo",
    "wof:placetype":"locality"
},
  "geometry": {"coordinates":[139.84666000000001,33.07976],"type":"Point"}
}