{
  "type": "Feature",
  "properties": {
    "gn:admin1_code":"16.0",
    "gn:admin2_code":"2112441.0",
    "gn:asciiname":"Heida",
    "gn:cc2":"JP",
    "gn:country_code":"JP",
    "gn:dem":106,
    "gn:feature_class":"P",
    "gn:feature_code":"PPL",
    "gn:name":"Heida",
    "gn:population":0,
    "gn:timezone":"Asia/Tokyo",
    "iso:country":"JP",
    "name:und_x_variant":[
        "Heita",
        "H\u0113da",
        "Heeta",
        "Hirata",
        "Heida"
    ],
    "wof:name":"Heida",
    "wof:placetype":"locality"
},
  "geometry": {"coordinates":[141.88333,39.23333],"type":"Point"}
}