{
  "type": "Feature",
  "properties": {
    "gn:admin1_code":"45",
    "gn:admin2_code":"7393001.0",
    "gn:asciiname":"O-kawachi",
    "gn:country_code":"JP",
    "gn:dem":90,
    "gn:feature_class":"P",
    "gn:feature_code":"PPL",
    "gn:name":"\u014c-kawachi",
    "gn:population":0,
    "gn:timezone":"Asia/Tokyo",
    "iso:country":"JP",
    "wof:name":"O-kawachi",
    "wof:placetype":"locality"
},
  "geometry": {"coordinates":[131.93333000000001,34.03333],"type":"Point"}
}