{
  "type": "Feature",
  "properties": {
    "gn:admin1_code":"34.0",
    "gn:admin2_code":"7464123.0",
    "gn:asciiname":"Yatsukacho",
    "gn:country_code":"JP",
    "gn:dem":8,
    "gn:feature_class":"P",
    "gn:feature_code":"PPL",
    "gn:name":"Yatsukach\u014d",
    "gn:population":0,
    "gn:timezone":"Asia/Tokyo",
    "iso:country":"JP",
    "name:jpn_x_preferred":[
        "\u8c37\u585a\u753a"
    ],
    "name:und_x_variant":[
        "Yatsukach\u014d"
    ],
    "wof:name":"Yatsukacho",
    "wof:placetype":"locality"
},
  "geometry": {"coordinates":[139.79848999999999,35.8152],"type":"Point"}
}