{
  "type": "Feature",
  "properties": {
    "gn:admin1_code":"3.0",
    "gn:admin2_code":"2130225.0",
    "gn:asciiname":"Katsuragawa",
    "gn:country_code":"JP",
    "gn:dem":34,
    "gn:feature_class":"P",
    "gn:feature_code":"PPL",
    "gn:name":"Katsuragawa",
    "gn:population":0,
    "gn:timezone":"Asia/Tokyo",
    "iso:country":"JP",
    "name:jpn_x_preferred":[
        "\u6842\u5ddd"
    ],
    "name:jpn_x_variant":[
        "\u304b\u3064\u3089\u304c\u308f",
        "\u30ab\u30c4\u30e9\u30ac\u30ef"
    ],
    "wof:name":"Katsuragawa",
    "wof:placetype":"locality"
},
  "geometry": {"coordinates":[140.37839,41.06372],"type":"Point"}
}