{
  "type": "Feature",
  "properties": {
    "gn:admin1_code":"12.0",
    "gn:admin2_code":"2129532.0",
    "gn:asciiname":"Tannocho-hiushinai",
    "gn:country_code":"JP",
    "gn:dem":60,
    "gn:feature_class":"P",
    "gn:feature_code":"PPL",
    "gn:name":"Tannoch\u014d-hiushinai",
    "gn:population":0,
    "gn:timezone":"Asia/Tokyo",
    "iso:country":"JP",
    "name:jpn_x_preferred":[
        "\u7aef\u91ce\u753a\u7dcb\u725b\u5185"
    ],
    "name:jpn_x_variant":[
        "\u305f\u3093\u306e\u3061\u3087\u3046\u3072\u3046\u3057\u306a\u3044",
        "\u30bf\u30f3\u30ce\u30c1\u30e7\u30a6\u30d2\u30a6\u30b7\u30ca\u30a4"
    ],
    "name:und_x_variant":[
        "Tannoch\u014d-hiushinai",
        "Hiushinai"
    ],
    "wof:name":"Tannocho-hiushinai",
    "wof:placetype":"locality"
},
  "geometry": {"coordinates":[143.99836000000005,43.88224],"type":"Point"}
}