{
  "type": "Feature",
  "properties": {
    "gn:admin1_code":"10",
    "gn:admin2_code":"7453748.0",
    "gn:admin3_code":"10443.0",
    "gn:asciiname":"Hataya",
    "gn:country_code":"JP",
    "gn:dem":696,
    "gn:feature_class":"P",
    "gn:feature_code":"PPL",
    "gn:name":"Hataya",
    "gn:population":0,
    "gn:timezone":"Asia/Tokyo",
    "iso:country":"JP",
    "name:jpn_x_preferred":[
        "\u5e61\u8c37"
    ],
    "wof:name":"Hataya",
    "wof:placetype":"locality"
},
  "geometry": {"coordinates":[139.21666999999999,36.73333],"type":"Point"}
}