{
  "type": "Feature",
  "properties": {
    "gn:admin1_code":"9.0",
    "gn:admin2_code":"1850890.0",
    "gn:asciiname":"Shokawamachi-mumaya",
    "gn:country_code":"JP",
    "gn:dem":1021,
    "gn:feature_class":"P",
    "gn:feature_code":"PPL",
    "gn:name":"Sh\u014dkawamachi-mumaya",
    "gn:population":0,
    "gn:timezone":"Asia/Tokyo",
    "iso:country":"JP",
    "name:jpn_x_preferred":[
        "\u8358\u5ddd\u753a\u516d\u53a9"
    ],
    "name:und_x_variant":[
        "Sh\u014dkawamachi-mumaya"
    ],
    "wof:name":"Shokawamachi-mumaya",
    "wof:placetype":"locality"
},
  "geometry": {"coordinates":[137.03412,36.0626],"type":"Point"}
}