{
  "type": "Feature",
  "properties": {
    "gn:admin1_code":"34.0",
    "gn:admin2_code":"7464126.0",
    "gn:asciiname":"Chizuka",
    "gn:country_code":"JP",
    "gn:dem":9,
    "gn:feature_class":"P",
    "gn:feature_code":"PPL",
    "gn:name":"Chizuka",
    "gn:population":0,
    "gn:timezone":"Asia/Tokyo",
    "iso:country":"JP",
    "name:jpn_x_preferred":[
        "\u5343\u585a"
    ],
    "name:jpn_x_variant":[
        "\u3061\u3065\u304b",
        "\u30c1\u30c5\u30ab"
    ],
    "wof:name":"Chizuka",
    "wof:placetype":"locality"
},
  "geometry": {"coordinates":[139.70098999999999,36.08999],"type":"Point"}
}