{
  "type": "Feature",
  "properties": {
    "gn:admin1_code":"21.0",
    "gn:admin2_code":"1859490.0",
    "gn:admin3_code":"43403.0",
    "gn:asciiname":"Nakajinnai",
    "gn:country_code":"JP",
    "gn:dem":100,
    "gn:feature_class":"P",
    "gn:feature_code":"PPLL",
    "gn:name":"Nakajinnai",
    "gn:population":0,
    "gn:timezone":"Asia/Tokyo",
    "iso:country":"JP",
    "name:jpn_x_preferred":[
        "\u4e2d\u9663\u5185"
    ],
    "name:jpn_x_variant":[
        "\u306a\u304b\u3058\u3093\u306a\u3044",
        "\u30ca\u30ab\u30b8\u30f3\u30ca\u30a4"
    ],
    "wof:name":"Nakajinnai",
    "wof:placetype":"locality"
},
  "geometry": {"coordinates":[130.87336999999999,32.86393],"type":"Point"}
}