{
  "type": "Feature",
  "properties": {
    "gn:admin1_code":"19.0",
    "gn:admin2_code":"1862461.0",
    "gn:asciiname":"Nakahara",
    "gn:country_code":"JP",
    "gn:dem":12,
    "gn:feature_class":"P",
    "gn:feature_code":"PPL",
    "gn:name":"Nakahara",
    "gn:population":0,
    "gn:timezone":"Asia/Tokyo",
    "iso:country":"JP",
    "name:jpn_x_preferred":[
        "\u4e2d\u539f"
    ],
    "name:kor_x_preferred":[
        "\ub098\uce74\ud558\ub77c"
    ],
    "wof:name":"Nakahara",
    "wof:placetype":"locality"
},
  "geometry": {"coordinates":[139.33518000000001,35.3476],"type":"Point"}
}