{
  "type": "Feature",
  "properties": {
    "gn:admin1_code":"7.0",
    "gn:admin2_code":"1859306.0",
    "gn:admin3_code":"40109.0",
    "gn:asciiname":"Nobu",
    "gn:country_code":"JP",
    "gn:dem":10,
    "gn:feature_class":"P",
    "gn:feature_code":"PPL",
    "gn:name":"Nobu",
    "gn:population":0,
    "gn:timezone":"Asia/Tokyo",
    "iso:country":"JP",
    "name:jpn_x_preferred":[
        "\u91ce\u9762"
    ],
    "wof:name":"Nobu",
    "wof:placetype":"locality"
},
  "geometry": {"coordinates":[130.73746,33.78068],"type":"Point"}
}