{
  "type": "Feature",
  "properties": {
    "gn:admin1_code":"34.0",
    "gn:admin2_code":"1849187.0",
    "gn:admin3_code":"11108.0",
    "gn:asciiname":"Zenmae",
    "gn:country_code":"JP",
    "gn:dem":10,
    "gn:feature_class":"P",
    "gn:feature_code":"PPLL",
    "gn:name":"Zenmae",
    "gn:population":0,
    "gn:timezone":"Asia/Tokyo",
    "iso:country":"JP",
    "name:jpn_x_preferred":[
        "\u5584\u524d"
    ],
    "name:jpn_x_variant":[
        "\u305c\u3093\u307e\u3048",
        "\u30bc\u30f3\u30de\u30a8"
    ],
    "wof:name":"Zenmae",
    "wof:placetype":"locality"
},
  "geometry": {"coordinates":[139.68573000000001,35.85488],"type":"Point"}
}