{
  "type": "Feature",
  "properties": {
    "gn:admin1_code":"21.0",
    "gn:admin2_code":"1848443.0",
    "gn:admin3_code":"43468.0",
    "gn:asciiname":"Shinmura",
    "gn:country_code":"JP",
    "gn:dem":8,
    "gn:feature_class":"P",
    "gn:feature_code":"PPLL",
    "gn:name":"Shinmura",
    "gn:population":0,
    "gn:timezone":"Asia/Tokyo",
    "iso:country":"JP",
    "name:jpn_x_preferred":[
        "\u65b0\u6751"
    ],
    "name:jpn_x_variant":[
        "\u3057\u3093\u3080\u3089",
        "\u30b7\u30f3\u30e0\u30e9"
    ],
    "wof:name":"Shinmura",
    "wof:placetype":"locality"
},
  "geometry": {"coordinates":[130.6722,32.56009],"type":"Point"}
}