{
  "type": "Feature",
  "properties": {
    "gn:admin1_code":"23.0",
    "gn:admin2_code":"1849544.0",
    "gn:asciiname":"Misugicho-kamitage",
    "gn:country_code":"JP",
    "gn:dem":437,
    "gn:feature_class":"P",
    "gn:feature_code":"PPL",
    "gn:name":"Misugich\u014d-kamitage",
    "gn:population":0,
    "gn:timezone":"Asia/Tokyo",
    "iso:country":"JP",
    "name:jpn_x_preferred":[
        "\u7f8e\u6749\u753a\u4e0a\u591a\u6c17"
    ],
    "name:und_x_variant":[
        "Misugich\u014d-kamitage"
    ],
    "wof:name":"Misugicho-kamitage",
    "wof:placetype":"locality"
},
  "geometry": {"coordinates":[136.30862999999999,34.5149],"type":"Point"}
}