{
  "type": "Feature",
  "properties": {
    "gn:admin1_code":"21.0",
    "gn:admin2_code":"1864975.0",
    "gn:admin3_code":"43433.0",
    "gn:asciiname":"Gion",
    "gn:country_code":"JP",
    "gn:dem":412,
    "gn:feature_class":"P",
    "gn:feature_code":"PPLL",
    "gn:name":"Gion",
    "gn:population":0,
    "gn:timezone":"Asia/Tokyo",
    "iso:country":"JP",
    "name:cat_x_preferred":[
        "Gion"
    ],
    "name:ces_x_preferred":[
        "Gion"
    ],
    "name:cym_x_preferred":[
        "Gion"
    ],
    "name:eus_x_preferred":[
        "Gion barrutia"
    ],
    "name:fin_x_preferred":[
        "Gion"
    ],
    "name:fra_x_preferred":[
        "Gion"
    ],
    "name:hun_x_preferred":[
        "Gion g\u00e9sanegyed"
    ],
    "name:ita_x_preferred":[
        "Gion"
    ],
    "name:jpn_x_preferred":[
        "\u7947\u5712"
    ],
    "name:jpn_x_variant":[
        "\u304e\u304a\u3093",
        "\u30ae\u30aa\u30f3"
    ],
    "name:kat_x_preferred":[
        "\u10d2\u10d8\u10dd\u10dc\u10d8"
    ],
    "name:kor_x_preferred":[
        "\uae30\uc628"
    ],
    "name:rus_x_preferred":[
        "\u0413\u0438\u043e\u043d"
    ],
    "name:slk_x_preferred":[
        "Gion"
    ],
    "name:spa_x_preferred":[
        "Gion"
    ],
    "name:tur_x_preferred":[
        "Gion"
    ],
    "name:ukr_x_preferred":[
        "\u0490\u0456\u043e\u043d"
    ],
    "wof:name":"Gion",
    "wof:placetype":"locality"
},
  "geometry": {"coordinates":[131.05243000000002,32.82261],"type":"Point"}
}