{
  "type": "Feature",
  "properties": {
    "gn:admin1_code":"32.0",
    "gn:admin2_code":"1853167.0",
    "gn:admin3_code":"27145.0",
    "gn:asciiname":"Hinoo",
    "gn:country_code":"JP",
    "gn:dem":70,
    "gn:feature_class":"P",
    "gn:feature_code":"PPL",
    "gn:name":"Hinoo",
    "gn:population":0,
    "gn:timezone":"Asia/Tokyo",
    "iso:country":"JP",
    "name:jpn_x_preferred":[
        "\u6a9c\u5c3e"
    ],
    "wof:name":"Hinoo",
    "wof:placetype":"locality"
},
  "geometry": {"coordinates":[135.46791999999999,34.48537],"type":"Point"}
}