{
  "type": "Feature",
  "properties": {
    "gn:admin1_code":"3.0",
    "gn:admin2_code":"2127674.0",
    "gn:asciiname":"Mukaimura",
    "gn:country_code":"JP",
    "gn:dem":104,
    "gn:feature_class":"P",
    "gn:feature_code":"PPL",
    "gn:name":"Mukaimura",
    "gn:population":0,
    "gn:timezone":"Asia/Tokyo",
    "iso:country":"JP",
    "name:jpn_x_preferred":[
        "\u5411\u6751"
    ],
    "name:jpn_x_variant":[
        "\u3080\u304b\u3044\u3080\u3089",
        "\u30e0\u30ab\u30a4\u30e0\u30e9"
    ],
    "wof:name":"Mukaimura",
    "wof:placetype":"locality"
},
  "geometry": {"coordinates":[141.14158,40.579],"type":"Point"}
}