{
  "type": "Feature",
  "properties": {
    "gn:admin1_code":"21.0",
    "gn:admin2_code":"7412708.0",
    "gn:admin3_code":"43505.0",
    "gn:asciiname":"Doyama",
    "gn:country_code":"JP",
    "gn:dem":193,
    "gn:feature_class":"P",
    "gn:feature_code":"PPLL",
    "gn:name":"D\u014dyama",
    "gn:population":0,
    "gn:timezone":"Asia/Tokyo",
    "iso:country":"JP",
    "name:jpn_x_preferred":[
        "\u5802\u5c71"
    ],
    "name:jpn_x_variant":[
        "\u3069\u3046\u3084\u307e",
        "\u30c9\u30a6\u30e4\u30de"
    ],
    "name:und_x_variant":[
        "D\u014dyama"
    ],
    "wof:name":"Doyama",
    "wof:placetype":"locality"
},
  "geometry": {"coordinates":[130.95778000000001,32.25172],"type":"Point"}
}