{
  "type": "Feature",
  "properties": {
    "gn:admin1_code":"39",
    "gn:admin2_code":"1850156.0",
    "gn:asciiname":"Sumiyoshi",
    "gn:country_code":"JP",
    "gn:dem":4,
    "gn:feature_class":"P",
    "gn:feature_code":"PPL",
    "gn:name":"Sumiyoshi",
    "gn:population":0,
    "gn:timezone":"Asia/Tokyo",
    "iso:country":"JP",
    "name:deu_x_preferred":[
        "Sumiyoshi"
    ],
    "name:epo_x_preferred":[
        "Sumijo\u015di"
    ],
    "name:fra_x_preferred":[
        "Sumiyoshi"
    ],
    "name:jpn_x_preferred":[
        "\u4f4f\u5409"
    ],
    "name:kor_x_preferred":[
        "\uc2a4\ubbf8\uc694\uc2dc"
    ],
    "name:pol_x_preferred":[
        "Sumiyoshi"
    ],
    "name:und_x_variant":[
        "Hon-ch\u014d",
        "Sumiyoshihon-ch\u014d",
        "Sumiyoshi-hommachi",
        "Sumiyoshi"
    ],
    "wof:name":"Sumiyoshi",
    "wof:placetype":"locality"
},
  "geometry": {"coordinates":[134.57078999999999,34.07777],"type":"Point"}
}