{
  "type": "Feature",
  "properties": {
    "iso:country":"JP",
    "name:eng_x_preferred":[
        "Tsuboi 1 Chome"
    ],
    "name:eng_x_variant":[
        "Tsuboi 1 Choume",
        "Tsuboi 1 Chome"
    ],
    "name:jpn_x_preferred":[
        "\uff11\u4e01\u76ee"
    ],
    "name:jpn_x_variant":[
        "\u3064\u307c\u3044 \uff11\u3061\u3087\u3046\u3081",
        "\u576a\u4e95 \uff11\u4e01\u76ee",
        "\uff11\u3061\u3087\u3046\u3081"
    ],
    "qs:gn_local":0,
    "qs:local_max":2020,
    "qs:local_sum":4255,
    "qs:localhoods":12,
    "qs:name":"\uff11\u4e01\u76ee",
    "qs:name_adm0":"\u65e5\u672c",
    "qs:name_adm1":"\u718a\u672c\u770c",
    "qs:name_en":"Tsuboi 1 Chome",
    "qs:name_lau":"\u576a\u4e95",
    "qs:name_local":"\u718a\u672c\u5e02",
    "qs:photo_max":16,
    "qs:photo_sum":38,
    "qs:placetype":"Suburb",
    "qs:quad_count":6,
    "qs:woe_adm0":23424856,
    "qs:woe_adm1":2345870,
    "qs:woe_adm2":0,
    "qs:woe_lau":28488246,
    "qs:woe_local":1117605,
    "qs:woe_ver":"7.10.0",
    "wof:lang":[
        "jpn"
    ],
    "wof:name":"\uff11\u4e01\u76ee",
    "wof:placetype":"neighbourhood"
},
  "geometry": {"coordinates":[130.707346,32.812616],"type":"Point"}
}