{
  "type": "Feature",
  "properties": {
    "gn:admin1_code":"21.0",
    "gn:admin2_code":"1848441.0",
    "gn:asciiname":"Gezunomata",
    "gn:country_code":"JP",
    "gn:dem":224,
    "gn:feature_class":"P",
    "gn:feature_code":"PPLL",
    "gn:name":"Gezunomata",
    "gn:population":0,
    "gn:timezone":"Asia/Tokyo",
    "iso:country":"JP",
    "name:jpn_x_preferred":[
        "\u67b3\u30ce \u4fe3"
    ],
    "name:und_x_variant":[
        "Kezunomata"
    ],
    "wof:name":"Gezunomata",
    "wof:placetype":"locality"
},
  "geometry": {"coordinates":[130.68133999999998,32.38368],"type":"Point"}
}