{
  "type": "Feature",
  "properties": {
    "gn:admin1_code":"13",
    "gn:admin2_code":"1862625.0",
    "gn:asciiname":"Yumesakicho-miyaoki",
    "gn:country_code":"JP",
    "gn:dem":50,
    "gn:feature_class":"P",
    "gn:feature_code":"PPL",
    "gn:name":"Yumesakich\u014d-miyaoki",
    "gn:population":0,
    "gn:timezone":"Asia/Tokyo",
    "iso:country":"JP",
    "name:jpn_x_preferred":[
        "\u5922\u524d\u753a\u5bae\u7f6e"
    ],
    "name:und_x_variant":[
        "Yumesakich\u014d-miyaoki",
        "Miyaoki"
    ],
    "wof:name":"Yumesakicho-miyaoki",
    "wof:placetype":"locality"
},
  "geometry": {"coordinates":[134.67502999999999,34.91322],"type":"Point"}
}