{
  "type": "Feature",
  "properties": {
    "gn:admin1_code":"28.0",
    "gn:admin2_code":"1853062.0",
    "gn:asciiname":"Yokogaki",
    "gn:country_code":"JP",
    "gn:dem":257,
    "gn:feature_class":"P",
    "gn:feature_code":"PPL",
    "gn:name":"Yokogaki",
    "gn:population":0,
    "gn:timezone":"Asia/Tokyo",
    "iso:country":"JP",
    "name:jpn_x_preferred":[
        "\u6a2a\u67ff"
    ],
    "wof:name":"Yokogaki",
    "wof:placetype":"locality"
},
  "geometry": {"coordinates":[135.8588,34.48452],"type":"Point"}
}