{
  "type": "Feature",
  "properties": {
    "gn:admin1_code":"12.0",
    "gn:admin2_code":"7428109.0",
    "gn:admin3_code":"1668.0",
    "gn:asciiname":"Pashikuru",
    "gn:country_code":"JP",
    "gn:dem":69,
    "gn:feature_class":"P",
    "gn:feature_code":"PPL",
    "gn:name":"Pashikuru",
    "gn:population":0,
    "gn:timezone":"Asia/Tokyo",
    "iso:country":"JP",
    "name:jpn_x_preferred":[
        "\u99ac\u4e3b\u6765"
    ],
    "name:jpn_x_variant":[
        "\u3071\u3057\u304f\u308b",
        "\u30d1\u30b7\u30af\u30eb"
    ],
    "name:und_x_variant":[
        "Bashukuru"
    ],
    "wof:name":"Pashikuru",
    "wof:placetype":"locality"
},
  "geometry": {"coordinates":[144.017,42.94048],"type":"Point"}
}