{
  "type": "Feature",
  "properties": {
    "gn:admin1_code":"34.0",
    "gn:admin2_code":"1864112.0",
    "gn:asciiname":"Jonoshita",
    "gn:country_code":"JP",
    "gn:dem":17,
    "gn:feature_class":"P",
    "gn:feature_code":"PPLL",
    "gn:name":"J\u014dnoshita",
    "gn:population":0,
    "gn:timezone":"Asia/Tokyo",
    "iso:country":"JP",
    "name:jpn_x_preferred":[
        "\u57ce\u30ce\u4e0b"
    ],
    "name:und_x_variant":[
        "J\u014dnoshita"
    ],
    "wof:name":"Jonoshita",
    "wof:placetype":"locality"
},
  "geometry": {"coordinates":[139.56996999999998,35.84434],"type":"Point"}
}