{
  "type": "Feature",
  "properties": {
    "gn:admin1_code":"23.0",
    "gn:admin2_code":"1857496.0",
    "gn:asciiname":"Iinancho-kaminigaki",
    "gn:country_code":"JP",
    "gn:dem":250,
    "gn:feature_class":"P",
    "gn:feature_code":"PPL",
    "gn:name":"Iinanch\u014d-kaminigaki",
    "gn:population":0,
    "gn:timezone":"Asia/Tokyo",
    "iso:country":"JP",
    "name:jpn_x_preferred":[
        "\u98ef\u5357\u753a\u4e0a\u4ec1\u67ff"
    ],
    "name:und_x_variant":[
        "Iinanch\u014d-kaminigaki"
    ],
    "wof:name":"Iinancho-kaminigaki",
    "wof:placetype":"locality"
},
  "geometry": {"coordinates":[136.35952,34.48813],"type":"Point"}
}