{
  "type": "Feature",
  "properties": {
    "gn:admin1_code":"21.0",
    "gn:admin2_code":"1865358.0",
    "gn:asciiname":"Nishi",
    "gn:country_code":"JP",
    "gn:dem":49,
    "gn:feature_class":"P",
    "gn:feature_code":"PPLL",
    "gn:name":"Nishi",
    "gn:population":0,
    "gn:timezone":"Asia/Tokyo",
    "iso:country":"JP",
    "name:bul_x_preferred":[
        "\u041d\u0438\u0441\u0438"
    ],
    "name:ceb_x_preferred":[
        "Nishi"
    ],
    "name:deu_x_preferred":[
        "Nishi"
    ],
    "name:fra_x_preferred":[
        "Nishi"
    ],
    "name:jpn_x_preferred":[
        "\u897f"
    ],
    "name:jpn_x_variant":[
        "\u306b\u3057",
        "\u30cb\u30b7"
    ],
    "name:mkd_x_preferred":[
        "\u041d\u0438\u0441\u0438"
    ],
    "name:nld_x_preferred":[
        "Nishi"
    ],
    "name:pol_x_preferred":[
        "Nishi"
    ],
    "name:rus_x_preferred":[
        "\u041d\u0438\u0441\u0438"
    ],
    "name:ukr_x_preferred":[
        "\u041d\u0456\u0441\u0456"
    ],
    "wof:name":"Nishi",
    "wof:placetype":"locality"
},
  "geometry": {"coordinates":[130.15683000000001,32.33456],"type":"Point"}
}