{
  "type": "Feature",
  "properties": {
    "gn:admin1_code":"28.0",
    "gn:admin2_code":"1848164.0",
    "gn:admin3_code":"29443.0",
    "gn:asciiname":"Hirosedani",
    "gn:country_code":"JP",
    "gn:dem":422,
    "gn:feature_class":"P",
    "gn:feature_code":"PPLL",
    "gn:name":"Hirosedani",
    "gn:population":0,
    "gn:timezone":"Asia/Tokyo",
    "iso:country":"JP",
    "name:jpn_x_preferred":[
        "\u5e83\u702c\u8c37"
    ],
    "wof:name":"Hirosedani",
    "wof:placetype":"locality"
},
  "geometry": {"coordinates":[135.81646999999998,34.3294],"type":"Point"}
}