{
  "type": "Feature",
  "properties": {
    "gn:admin1_code":"7.0",
    "gn:admin2_code":"1861834.0",
    "gn:asciiname":"Happonmatsu",
    "gn:country_code":"JP",
    "gn:dem":96,
    "gn:feature_class":"P",
    "gn:feature_code":"PPLL",
    "gn:name":"Happonmatsu",
    "gn:population":0,
    "gn:timezone":"Asia/Tokyo",
    "iso:country":"JP",
    "name:jpn_x_preferred":[
        "\u516b\u672c\u677e"
    ],
    "wof:name":"Happonmatsu",
    "wof:placetype":"locality"
},
  "geometry": {"coordinates":[130.62763000000001,33.56554000000001],"type":"Point"}
}