{
  "type": "Feature",
  "properties": {
    "gn:admin1_code":"3.0",
    "gn:admin2_code":"2130200.0",
    "gn:asciiname":"Numadate",
    "gn:country_code":"JP",
    "gn:dem":4,
    "gn:feature_class":"P",
    "gn:feature_code":"PPL",
    "gn:name":"Numadate",
    "gn:population":0,
    "gn:timezone":"Asia/Tokyo",
    "iso:country":"JP",
    "name:jpn_x_preferred":[
        "\u6cbc\u9928"
    ],
    "name:jpn_x_variant":[
        "\u306c\u307e\u3060\u3066",
        "\u30cc\u30de\u30c0\u30c6"
    ],
    "wof:name":"Numadate",
    "wof:placetype":"locality"
},
  "geometry": {"coordinates":[141.49288999999999,40.52935],"type":"Point"}
}