{
  "type": "Feature",
  "properties": {
    "gn:admin1_code":"29.0",
    "gn:admin2_code":"7468182.0",
    "gn:asciiname":"Momozakihama",
    "gn:country_code":"JP",
    "gn:dem":7,
    "gn:feature_class":"P",
    "gn:feature_code":"PPL",
    "gn:name":"Momozakihama",
    "gn:population":0,
    "gn:timezone":"Asia/Tokyo",
    "iso:country":"JP",
    "name:jpn_x_preferred":[
        "\u6843\u5d0e\u6d5c"
    ],
    "wof:name":"Momozakihama",
    "wof:placetype":"locality"
},
  "geometry": {"coordinates":[139.40511000000001,38.14195],"type":"Point"}
}