{
  "type": "Feature",
  "properties": {
    "gn:admin1_code":"21.0",
    "gn:admin2_code":"1864975.0",
    "gn:admin3_code":"43423.0",
    "gn:asciiname":"Sugita",
    "gn:country_code":"JP",
    "gn:dem":458,
    "gn:feature_class":"P",
    "gn:feature_code":"PPLL",
    "gn:name":"Sugita",
    "gn:population":0,
    "gn:timezone":"Asia/Tokyo",
    "iso:country":"JP",
    "name:jpn_x_preferred":[
        "\u6749\u7530"
    ],
    "name:jpn_x_variant":[
        "\u3059\u304e\u305f",
        "\u30b9\u30ae\u30bf"
    ],
    "wof:name":"Sugita",
    "wof:placetype":"locality"
},
  "geometry": {"coordinates":[131.06634,33.10155],"type":"Point"}
}