{
  "type": "Feature",
  "properties": {
    "gn:admin1_code":"29",
    "gn:admin2_code":"1860992.0",
    "gn:asciiname":"Kuroi",
    "gn:country_code":"JP",
    "gn:dem":4,
    "gn:feature_class":"P",
    "gn:feature_code":"PPL",
    "gn:name":"Kuroi",
    "gn:population":0,
    "gn:timezone":"Asia/Tokyo",
    "iso:country":"JP",
    "wof:name":"Kuroi",
    "wof:placetype":"locality"
},
  "geometry": {"coordinates":[138.26667,37.18333],"type":"Point"}
}