{
  "type": "Feature",
  "properties": {
    "gn:admin1_code":"28.0",
    "gn:admin2_code":"1848164.0",
    "gn:admin3_code":"29441.0",
    "gn:asciiname":"Takihata",
    "gn:country_code":"JP",
    "gn:dem":436,
    "gn:feature_class":"P",
    "gn:feature_code":"PPL",
    "gn:name":"Takihata",
    "gn:population":0,
    "gn:timezone":"Asia/Tokyo",
    "iso:country":"JP",
    "name:jpn_x_preferred":[
        "\u6edd\u7551"
    ],
    "wof:name":"Takihata",
    "wof:placetype":"locality"
},
  "geometry": {"coordinates":[135.86394999999999,34.43151],"type":"Point"}
}