{
  "type": "Feature",
  "properties": {
    "gn:admin1_code":"26.0",
    "gn:admin2_code":"1861837.0",
    "gn:asciiname":"Godo",
    "gn:country_code":"JP",
    "gn:dem":338,
    "gn:feature_class":"P",
    "gn:feature_code":"PPLL",
    "gn:name":"G\u014ddo",
    "gn:population":0,
    "gn:timezone":"Asia/Tokyo",
    "iso:country":"JP",
    "name:ceb_x_preferred":[
        "Godo"
    ],
    "name:deu_x_preferred":[
        "Godo"
    ],
    "name:fra_x_preferred":[
        "Godo"
    ],
    "name:jpn_x_preferred":[
        "\u9854\u6238"
    ],
    "name:spa_x_preferred":[
        "Godo"
    ],
    "name:swe_x_preferred":[
        "Godo"
    ],
    "name:ukr_x_preferred":[
        "\u0490\u043e\u0434\u043e"
    ],
    "name:und_x_variant":[
        "G\u014ddo"
    ],
    "wof:name":"Godo",
    "wof:placetype":"locality"
},
  "geometry": {"coordinates":[138.36080999999999,36.90353],"type":"Point"}
}