{
  "type": "Feature",
  "properties": {
    "gn:admin1_code":"7.0",
    "gn:admin2_code":"1859306.0",
    "gn:admin3_code":"40107.0",
    "gn:asciiname":"Sone-shinden-minami",
    "gn:country_code":"JP",
    "gn:dem":-3,
    "gn:feature_class":"P",
    "gn:feature_code":"PPL",
    "gn:name":"Sone-shinden-minami",
    "gn:population":0,
    "gn:timezone":"Asia/Tokyo",
    "iso:country":"JP",
    "name:jpn_x_preferred":[
        "\u66fd\u6839\u65b0\u7530\u5357"
    ],
    "wof:name":"Sone-shinden-minami",
    "wof:placetype":"locality"
},
  "geometry": {"coordinates":[130.95504,33.81656],"type":"Point"}
}