{
  "type": "Feature",
  "properties": {
    "gn:admin1_code":"18",
    "gn:admin2_code":"7383999.0",
    "gn:admin3_code":"46492.0",
    "gn:asciiname":"Shiraki",
    "gn:country_code":"JP",
    "gn:dem":107,
    "gn:feature_class":"P",
    "gn:feature_code":"PPL",
    "gn:name":"Shiraki",
    "gn:population":0,
    "gn:timezone":"Asia/Tokyo",
    "iso:country":"JP",
    "name:jpn_x_preferred":[
        "\u767d\u6728"
    ],
    "wof:name":"Shiraki",
    "wof:placetype":"locality"
},
  "geometry": {"coordinates":[131.09771999999998,31.2753],"type":"Point"}
}