{
  "type": "Feature",
  "properties": {
    "gn:admin1_code":"21.0",
    "gn:admin2_code":"1848441.0",
    "gn:asciiname":"Fukune",
    "gn:country_code":"JP",
    "gn:dem":940,
    "gn:feature_class":"P",
    "gn:feature_code":"PPLL",
    "gn:name":"Fukune",
    "gn:population":0,
    "gn:timezone":"Asia/Tokyo",
    "iso:country":"JP",
    "name:jpn_x_preferred":[
        "\u798f\u6839"
    ],
    "name:jpn_x_variant":[
        "\u3075\u304f\u306d",
        "\u30d5\u30af\u30cd"
    ],
    "wof:name":"Fukune",
    "wof:placetype":"locality"
},
  "geometry": {"coordinates":[130.93115,32.54202],"type":"Point"}
}