{
  "type": "Feature",
  "properties": {
    "iso:country":"JP",
    "name:eng_x_preferred":[
        "Numame 6 Chome"
    ],
    "name:eng_x_variant":[
        "Numame 6 Choume",
        "Numame 6 Chome"
    ],
    "name:jpn_x_preferred":[
        "\uff16\u4e01\u76ee"
    ],
    "name:jpn_x_variant":[
        "\u306c\u307e\u3081 \uff16\u3061\u3087\u3046\u3081",
        "\u6cbc\u76ee \uff16\u4e01\u76ee",
        "\uff16\u3061\u3087\u3046\u3081"
    ],
    "qs:gn_local":0,
    "qs:local_max":512,
    "qs:local_sum":845,
    "qs:localhoods":6,
    "qs:name":"\uff16\u4e01\u76ee",
    "qs:name_adm0":"\u65e5\u672c",
    "qs:name_adm1":"\u795e\u5948\u5ddd\u770c",
    "qs:name_en":"Numame 6 Chome",
    "qs:name_lau":"\u6cbc\u76ee",
    "qs:name_local":"\u4f0a\u52e2\u539f\u5e02",
    "qs:photo_max":111,
    "qs:photo_sum":512,
    "qs:placetype":"Suburb",
    "qs:quad_count":27,
    "qs:woe_adm0":23424856,
    "qs:woe_adm1":2345868,
    "qs:woe_adm2":0,
    "qs:woe_lau":28417293,
    "qs:woe_local":1109566,
    "qs:woe_ver":"7.10.0",
    "wof:lang":[
        "jpn"
    ],
    "wof:name":"\uff16\u4e01\u76ee",
    "wof:placetype":"neighbourhood"
},
  "geometry": {"coordinates":[139.33462299999999,35.378166],"type":"Point"}
}