{
  "type": "Feature",
  "properties": {
    "gn:admin1_code":"29",
    "gn:admin2_code":"7468178.0",
    "gn:asciiname":"Uta",
    "gn:country_code":"JP",
    "gn:dem":9,
    "gn:feature_class":"P",
    "gn:feature_code":"PPL",
    "gn:name":"Uta",
    "gn:population":0,
    "gn:timezone":"Asia/Tokyo",
    "iso:country":"JP",
    "name:lat_x_preferred":[
        "Uta"
    ],
    "name:nld_x_preferred":[
        "Uta"
    ],
    "name:por_x_preferred":[
        "Uta"
    ],
    "name:swe_x_preferred":[
        "Uta"
    ],
    "wof:name":"Uta",
    "wof:placetype":"locality"
},
  "geometry": {"coordinates":[137.74045000000001,37.00627],"type":"Point"}
}