{
  "type": "Feature",
  "properties": {
    "gn:admin1_code":"19.0",
    "gn:admin2_code":"1856851.0",
    "gn:admin3_code":"14301.0",
    "gn:asciiname":"Shinzawa",
    "gn:country_code":"JP",
    "gn:dem":47,
    "gn:feature_class":"P",
    "gn:feature_code":"PPLL",
    "gn:name":"Shinzawa",
    "gn:population":0,
    "gn:timezone":"Asia/Tokyo",
    "iso:country":"JP",
    "name:jpn_x_preferred":[
        "\u65b0\u6ca2"
    ],
    "name:jpn_x_variant":[
        "\u3057\u3093\u3056\u308f",
        "\u30b7\u30f3\u30b6\u30ef"
    ],
    "wof:name":"Shinzawa",
    "wof:placetype":"locality"
},
  "geometry": {"coordinates":[139.60763,35.26885],"type":"Point"}
}