{
  "type": "Feature",
  "properties": {
    "gn:admin1_code":"12.0",
    "gn:admin2_code":"2128812.0",
    "gn:asciiname":"Fujicho",
    "gn:country_code":"JP",
    "gn:dem":129,
    "gn:feature_class":"P",
    "gn:feature_code":"PPL",
    "gn:name":"Fujich\u014d",
    "gn:population":0,
    "gn:timezone":"Asia/Tokyo",
    "iso:country":"JP",
    "name:jpn_x_preferred":[
        "\u5bcc\u58eb\u753a"
    ],
    "name:und_x_variant":[
        "Fujich\u014d",
        "Fuji"
    ],
    "wof:name":"Fujicho",
    "wof:placetype":"locality"
},
  "geometry": {"coordinates":[143.12393,42.78265],"type":"Point"}
}