{
  "type": "Feature",
  "properties": {
    "gn:admin1_code":"39",
    "gn:admin2_code":"1859771.0",
    "gn:admin3_code":"36301.0",
    "gn:asciiname":"Yokose",
    "gn:cc2":"JP",
    "gn:country_code":"JP",
    "gn:dem":61,
    "gn:feature_class":"P",
    "gn:feature_code":"PPL",
    "gn:name":"Yokose",
    "gn:population":0,
    "gn:timezone":"Asia/Tokyo",
    "iso:country":"JP",
    "name:und_x_variant":[
        "Mitani",
        "Yokose"
    ],
    "wof:name":"Yokose",
    "wof:placetype":"locality"
},
  "geometry": {"coordinates":[134.48333,33.93333],"type":"Point"}
}