{
  "type": "Feature",
  "properties": {
    "gn:admin1_code":"37.0",
    "gn:admin2_code":"1856971.0",
    "gn:asciiname":"Ichibancho",
    "gn:country_code":"JP",
    "gn:dem":38,
    "gn:feature_class":"P",
    "gn:feature_code":"PPL",
    "gn:name":"Ichibanch\u014d",
    "gn:population":0,
    "gn:timezone":"Asia/Tokyo",
    "iso:country":"JP",
    "name:jpn_x_preferred":[
        "\u4e00\u756a\u753a"
    ],
    "name:und_x_variant":[
        "Ichibanch\u014d"
    ],
    "wof:name":"Ichibancho",
    "wof:placetype":"locality"
},
  "geometry": {"coordinates":[138.91376,35.12586],"type":"Point"}
}