{
  "type": "Feature",
  "properties": {
    "iso:country":"JP",
    "label:eng_x_preferred_longname":[
        "Amakusa City"
    ],
    "label:eng_x_preferred_placetype":[
        "city"
    ],
    "name:eng_x_preferred":[
        "Amakusa"
    ],
    "name:eng_x_variant":[
        "Amakusa City"
    ],
    "name:jpn_x_preferred":[
        "\u5929\u8349\u5e02"
    ],
    "qs:name":"\u5929\u8349\u5e02",
    "qs:name_adm0":"\u65e5\u672c",
    "qs:name_adm1":"\u718a\u672c\u770c",
    "qs:photos":569,
    "qs:photos_1k":115,
    "qs:photos_9k":3,
    "qs:photos_9r":5,
    "qs:photos_all":571,
    "qs:photos_sr":8,
    "qs:placetype":"Town",
    "qs:pop_sr":"0",
    "wof:name":"Amakusa",
    "wof:placetype":"locality"
},
  "geometry": {"coordinates":[130.11946599999999,32.416196],"type":"Point"}
}