{
  "type": "Feature",
  "properties": {
    "gn:admin1_code":"21.0",
    "gn:admin2_code":"7413150.0",
    "gn:asciiname":"Kamiiwabaru",
    "gn:country_code":"JP",
    "gn:dem":69,
    "gn:feature_class":"P",
    "gn:feature_code":"PPLL",
    "gn:name":"Kamiiwabaru",
    "gn:population":0,
    "gn:timezone":"Asia/Tokyo",
    "iso:country":"JP",
    "name:jpn_x_preferred":[
        "\u4e0a\u5ca9\u539f"
    ],
    "name:jpn_x_variant":[
        "\u304b\u307f\u3044\u308f\u3070\u308b",
        "\u30ab\u30df\u30a4\u30ef\u30d0\u30eb"
    ],
    "wof:name":"Kamiiwabaru",
    "wof:placetype":"locality"
},
  "geometry": {"coordinates":[130.67757,32.98583],"type":"Point"}
}