{
  "type": "Feature",
  "properties": {
    "gn:admin1_code":"4.0",
    "gn:admin2_code":"1859468.0",
    "gn:asciiname":"Gogyodai",
    "gn:country_code":"JP",
    "gn:dem":141,
    "gn:feature_class":"P",
    "gn:feature_code":"PPLL",
    "gn:name":"Gogy\u014ddai",
    "gn:population":0,
    "gn:timezone":"Asia/Tokyo",
    "iso:country":"JP",
    "name:jpn_x_preferred":[
        "\u4e94\u884c\u53f0"
    ],
    "name:jpn_x_variant":[
        "\u3054\u304e\u3087\u3046\u3060\u3044",
        "\u30b4\u30ae\u30e7\u30a6\u30c0\u30a4"
    ],
    "name:und_x_variant":[
        "Gogy\u014ddai"
    ],
    "wof:name":"Gogyodai",
    "wof:placetype":"locality"
},
  "geometry": {"coordinates":[140.00779,35.27227],"type":"Point"}
}