{
  "type": "Feature",
  "properties": {
    "gn:admin1_code":"2.0",
    "gn:admin2_code":"2111153.0",
    "gn:admin3_code":"5434.0",
    "gn:asciiname":"Hataya",
    "gn:country_code":"JP",
    "gn:dem":37,
    "gn:feature_class":"P",
    "gn:feature_code":"PPL",
    "gn:name":"Hataya",
    "gn:population":0,
    "gn:timezone":"Asia/Tokyo",
    "iso:country":"JP",
    "name:jpn_x_preferred":[
        "\u7551\u5c4b"
    ],
    "wof:name":"Hataya",
    "wof:placetype":"locality"
},
  "geometry": {"coordinates":[140.54028,39.44008],"type":"Point"}
}