{
  "type": "Feature",
  "properties": {
    "gn:admin1_code":"3.0",
    "gn:admin2_code":"2129224.0",
    "gn:admin3_code":"2361.0",
    "gn:asciiname":"Honcho",
    "gn:country_code":"JP",
    "gn:dem":23,
    "gn:feature_class":"P",
    "gn:feature_code":"PPL",
    "gn:name":"Honch\u014d",
    "gn:population":0,
    "gn:timezone":"Asia/Tokyo",
    "iso:country":"JP",
    "name:deu_x_preferred":[
        "Honcho"
    ],
    "name:jpn_x_preferred":[
        "\u672c\u753a"
    ],
    "name:jpn_x_variant":[
        "\u307b\u3093\u3061\u3087\u3046",
        "\u30db\u30f3\u30c1\u30e7\u30a6"
    ],
    "name:und_x_variant":[
        "Honch\u014d"
    ],
    "wof:name":"Honcho",
    "wof:placetype":"locality"
},
  "geometry": {"coordinates":[140.49382,40.65286],"type":"Point"}
}