{
  "type": "Feature",
  "properties": {
    "gn:admin1_code":"19",
    "gn:admin2_code":"7468160.0",
    "gn:admin3_code":"14402.0",
    "gn:asciiname":"Fudakake",
    "gn:country_code":"JP",
    "gn:dem":498,
    "gn:feature_class":"P",
    "gn:feature_code":"PPL",
    "gn:name":"Fudakake",
    "gn:population":0,
    "gn:timezone":"Asia/Tokyo",
    "iso:country":"JP",
    "name:jpn_x_preferred":[
        "\u672d\u639b\u3000"
    ],
    "wof:name":"Fudakake",
    "wof:placetype":"locality"
},
  "geometry": {"coordinates":[139.21076000000002,35.4602],"type":"Point"}
}