{
  "type": "Feature",
  "properties": {
    "iso:country":"JP",
    "name:eng_x_preferred":[
        "Imakatata 3 Chome"
    ],
    "name:eng_x_variant":[
        "Imakatata 3 Choume",
        "Imakatata 3 Chome"
    ],
    "name:jpn_x_preferred":[
        "\uff13\u4e01\u76ee"
    ],
    "name:jpn_x_variant":[
        "\u3044\u307e\u304b\u305f\u305f \uff13\u3061\u3087\u3046\u3081",
        "\u4eca\u5805\u7530 \uff13\u4e01\u76ee",
        "\uff13\u3061\u3087\u3046\u3081"
    ],
    "qs:gn_local":0,
    "qs:local_max":966,
    "qs:local_sum":4101,
    "qs:localhoods":25,
    "qs:name":"\uff13\u4e01\u76ee",
    "qs:name_adm0":"\u65e5\u672c",
    "qs:name_adm1":"\u6ecb\u8cc0\u770c",
    "qs:name_en":"Imakatata 3 Chome",
    "qs:name_lau":"\u4eca\u5805\u7530",
    "qs:name_local":"\u5927\u6d25\u5e02",
    "qs:photo_max":26,
    "qs:photo_sum":70,
    "qs:placetype":"Suburb",
    "qs:quad_count":11,
    "qs:woe_adm0":23424856,
    "qs:woe_adm1":2345884,
    "qs:woe_adm2":0,
    "qs:woe_lau":28447958,
    "qs:woe_local":1118029,
    "qs:woe_ver":"7.10.0",
    "wof:lang":[
        "jpn"
    ],
    "wof:name":"\uff13\u4e01\u76ee",
    "wof:placetype":"neighbourhood"
},
  "geometry": {"coordinates":[135.929148,35.125092],"type":"Point"}
}