{
  "type": "Feature",
  "properties": {
    "gn:admin1_code":"3.0",
    "gn:admin2_code":"2128302.0",
    "gn:admin3_code":"2445.0",
    "gn:asciiname":"Okitaomote",
    "gn:country_code":"JP",
    "gn:dem":28,
    "gn:feature_class":"P",
    "gn:feature_code":"PPL",
    "gn:name":"Okitaomote",
    "gn:population":0,
    "gn:timezone":"Asia/Tokyo",
    "iso:country":"JP",
    "name:jpn_x_preferred":[
        "\u6c96\u7530\u9762"
    ],
    "name:jpn_x_variant":[
        "\u304a\u304d\u305f\u304a\u3082\u3066",
        "\u30aa\u30ad\u30bf\u30aa\u30e2\u30c6"
    ],
    "wof:name":"Okitaomote",
    "wof:placetype":"locality"
},
  "geometry": {"coordinates":[141.28753999999995,40.41769],"type":"Point"}
}