{
  "type": "Feature",
  "properties": {
    "iso:country":"JP",
    "name:eng_x_preferred":[
        "Inukura 1 Chome"
    ],
    "name:eng_x_variant":[
        "Inukura 1 Choume",
        "Inukura 1 Chome"
    ],
    "name:jpn_x_preferred":[
        "\uff11\u4e01\u76ee"
    ],
    "name:jpn_x_variant":[
        "\u3044\u306c\u304f\u3089 \uff11\u3061\u3087\u3046\u3081",
        "\u72ac\u8535 \uff11\u4e01\u76ee",
        "\uff11\u3061\u3087\u3046\u3081"
    ],
    "qs:gn_adm0_cc":"JP",
    "qs:gn_local":1859642,
    "qs:local_max":4758,
    "qs:local_sum":25395,
    "qs:localhoods":83,
    "qs:name":"\uff11\u4e01\u76ee",
    "qs:name_adm0":"\u65e5\u672c",
    "qs:name_adm1":"\u795e\u5948\u5ddd\u770c",
    "qs:name_adm2":"\u5bae\u524d\u533a",
    "qs:name_en":"Inukura 1 Chome",
    "qs:name_lau":"\u72ac\u8535",
    "qs:name_local":"\u5ddd\u5d0e\u5e02",
    "qs:photo_max":1,
    "qs:photo_sum":2,
    "qs:placetype":"Suburb",
    "qs:quad_count":2,
    "qs:woe_adm0":23424856,
    "qs:woe_adm1":2345868,
    "qs:woe_adm2":15015511,
    "qs:woe_lau":28416475,
    "qs:woe_local":1117502,
    "qs:woe_ver":"7.10.0",
    "wof:lang":[
        "jpn"
    ],
    "wof:name":"\uff11\u4e01\u76ee",
    "wof:placetype":"neighbourhood"
},
  "geometry": {"coordinates":[139.559326,35.592552],"type":"Point"}
}