{
  "type": "Feature",
  "properties": {
    "gn:admin1_code":"4.0",
    "gn:admin2_code":"1859468.0",
    "gn:asciiname":"Okuradai",
    "gn:country_code":"JP",
    "gn:dem":143,
    "gn:feature_class":"P",
    "gn:feature_code":"PPLL",
    "gn:name":"\u014ckuradai",
    "gn:population":0,
    "gn:timezone":"Asia/Tokyo",
    "iso:country":"JP",
    "name:jpn_x_preferred":[
        "\u5927\u5009\u53f0"
    ],
    "name:jpn_x_variant":[
        "\u304a\u304a\u304f\u3089\u3060\u3044",
        "\u30aa\u30aa\u30af\u30e9\u30c0\u30a4"
    ],
    "name:und_x_variant":[
        "\u014ckuradai"
    ],
    "wof:name":"Okuradai",
    "wof:placetype":"locality"
},
  "geometry": {"coordinates":[140.00852,35.27644],"type":"Point"}
}