{
  "type": "Feature",
  "properties": {
    "iso:country":"JP",
    "name:eng_x_preferred":[
        "Hamamachi 2 Chome"
    ],
    "name:eng_x_variant":[
        "Hamamachi 2 Choume",
        "Hamamachi 2 Chome"
    ],
    "name:jpn_x_preferred":[
        "\uff12\u4e01\u76ee"
    ],
    "name:jpn_x_variant":[
        "\u306f\u307e\u307e\u3061 \uff12\u3061\u3087\u3046\u3081",
        "\u6d5c\u753a \uff12\u4e01\u76ee",
        "\uff12\u3061\u3087\u3046\u3081"
    ],
    "qs:gn_adm0_cc":"JP",
    "qs:gn_local":1858311,
    "qs:gn_nam_loc":"\u5009\u6577\u5e02, \u5ca1\u5c71\u770c, JP",
    "qs:gn_namadm1":"31",
    "qs:local_max":585,
    "qs:local_sum":2198,
    "qs:localhoods":12,
    "qs:name":"\uff12\u4e01\u76ee",
    "qs:name_adm0":"\u65e5\u672c",
    "qs:name_adm1":"\u5ca1\u5c71\u770c",
    "qs:name_en":"Hamamachi 2 Chome",
    "qs:name_lau":"\u6d5c\u753a",
    "qs:name_local":"\u5009\u6577\u5e02",
    "qs:photo_max":74,
    "qs:photo_sum":278,
    "qs:placetype":"Suburb",
    "qs:quad_count":8,
    "qs:woe_adm0":23424856,
    "qs:woe_adm1":2345880,
    "qs:woe_adm2":0,
    "qs:woe_lau":28472206,
    "qs:woe_local":1117618,
    "qs:woe_ver":"7.10.0",
    "qs_pg:name":"\uff12\u4e01\u76ee",
    "qs_pg:name_adm0":"\u65e5\u672c",
    "qs_pg:name_adm1":"\u5ca1\u5c71\u770c",
    "qs_pg:photos":173,
    "qs_pg:photos_1k":35,
    "qs_pg:photos_9k":1,
    "qs_pg:photos_9r":4,
    "qs_pg:photos_all":173,
    "qs_pg:photos_sr":4,
    "qs_pg:pop_sr":0,
    "qs_pg:qs_pg_placetype":"neighbourhood",
    "qs_pg:qs_pg_placetype_gp":"Suburb",
    "qs_pg:woe_adm0":23424856,
    "woe:adm0_id":23424856,
    "woe:name_adm0":"\u65e5\u672c",
    "woe:name_adm1":"\u5ca1\u5c71\u770c",
    "woe:placetype":"Suburb",
    "wof:lang":[
        "jpn"
    ],
    "wof:name":"\uff12\u4e01\u76ee",
    "wof:placetype":"neighbourhood"
},
  "geometry": {"coordinates":[133.77229399999999,34.609142],"type":"Point"}
}