{
  "type": "Feature",
  "properties": {
    "gn:admin1_code":"16.0",
    "gn:admin2_code":"2112822.0",
    "gn:asciiname":"Kitanarushima-kami",
    "gn:country_code":"JP",
    "gn:dem":171,
    "gn:feature_class":"P",
    "gn:feature_code":"PPL",
    "gn:name":"Kitanarushima-kami",
    "gn:population":0,
    "gn:timezone":"Asia/Tokyo",
    "iso:country":"JP",
    "name:jpn_x_preferred":[
        "\u5317\u6210\u5cf6\u4e0a"
    ],
    "name:jpn_x_variant":[
        "\u304d\u305f\u306a\u308b\u3057\u307e\u304b\u307f",
        "\u30ad\u30bf\u30ca\u30eb\u30b7\u30de\u30ab\u30df"
    ],
    "wof:name":"Kitanarushima-kami",
    "wof:placetype":"locality"
},
  "geometry": {"coordinates":[141.20578999999995,39.36662000000001],"type":"Point"}
}