{
  "type": "Feature",
  "properties": {
    "gn:admin1_code":"12.0",
    "gn:admin2_code":"7428090.0",
    "gn:admin3_code":"1664.0",
    "gn:asciiname":"Nakaosotsubetsu-gen'ya",
    "gn:country_code":"JP",
    "gn:dem":136,
    "gn:feature_class":"P",
    "gn:feature_code":"PPL",
    "gn:name":"Nakaosotsubetsu-gen\u2019ya",
    "gn:population":0,
    "gn:timezone":"Asia/Tokyo",
    "iso:country":"JP",
    "name:jpn_x_preferred":[
        "\u4e2d\u30aa\u30bd\u30c4\u30d9\u30c4\u539f\u91ce"
    ],
    "name:jpn_x_variant":[
        "\u306a\u304b\u304a\u305d\u3064\u3079\u3064\u3052\u3093\u3084",
        "\u30ca\u30ab\u30aa\u30bd\u30c4\u30d9\u30c4\u30b2\u30f3\u30e4"
    ],
    "name:und_x_variant":[
        "Nakaosotsubetsu-gen\u2019ya"
    ],
    "wof:name":"Nakaosotsubetsu-gen'ya",
    "wof:placetype":"locality"
},
  "geometry": {"coordinates":[144.46197000000001,43.31698],"type":"Point"}
}