{
  "type": "Feature",
  "properties": {
    "gn:admin1_code":"15",
    "gn:admin2_code":"7467839.0",
    "gn:admin3_code":"17461.0",
    "gn:asciiname":"Kanami",
    "gn:country_code":"JP",
    "gn:dem":16,
    "gn:feature_class":"P",
    "gn:feature_code":"PPL",
    "gn:name":"Kanami",
    "gn:population":0,
    "gn:timezone":"Asia/Tokyo",
    "iso:country":"JP",
    "name:jpn_x_preferred":[
        "\u9e7f\u6ce2"
    ],
    "wof:name":"Kanami",
    "wof:placetype":"locality"
},
  "geometry": {"coordinates":[136.98493999999999,37.20396],"type":"Point"}
}