{
  "type": "Feature",
  "properties": {
    "gn:admin1_code":"33.0",
    "gn:admin2_code":"1854650.0",
    "gn:asciiname":"Mikatsukicho-michibe",
    "gn:country_code":"JP",
    "gn:dem":6,
    "gn:feature_class":"P",
    "gn:feature_code":"PPL",
    "gn:name":"Mikatsukich\u014d-michibe",
    "gn:population":0,
    "gn:timezone":"Asia/Tokyo",
    "iso:country":"JP",
    "name:jpn_x_preferred":[
        "\u4e09\u65e5\u6708\u753a\u9053\u8fba"
    ],
    "name:und_x_variant":[
        "Mikatsukich\u014d-michibe"
    ],
    "wof:name":"Mikatsukicho-michibe",
    "wof:placetype":"locality"
},
  "geometry": {"coordinates":[130.23580000000001,33.28727],"type":"Point"}
}