{
  "type": "Feature",
  "properties": {
    "gn:admin1_code":"28.0",
    "gn:admin2_code":"1848164.0",
    "gn:admin3_code":"29446.0",
    "gn:asciiname":"Yamanishi",
    "gn:country_code":"JP",
    "gn:dem":558,
    "gn:feature_class":"P",
    "gn:feature_code":"PPL",
    "gn:name":"Yamanishi",
    "gn:population":0,
    "gn:timezone":"Asia/Tokyo",
    "iso:country":"JP",
    "name:deu_x_preferred":[
        "Yamanishi"
    ],
    "name:jpn_x_preferred":[
        "\u5c71\u897f"
    ],
    "wof:name":"Yamanishi",
    "wof:placetype":"locality"
},
  "geometry": {"coordinates":[135.77618000000001,34.19211],"type":"Point"}
}