{
  "type": "Feature",
  "properties": {
    "gn:admin1_code":"7.0",
    "gn:admin2_code":"1859306.0",
    "gn:admin3_code":"40107.0",
    "gn:asciiname":"Minami-wakazonomachi",
    "gn:country_code":"JP",
    "gn:dem":23,
    "gn:feature_class":"P",
    "gn:feature_code":"PPL",
    "gn:name":"Minami-wakazonomachi",
    "gn:population":0,
    "gn:timezone":"Asia/Tokyo",
    "iso:country":"JP",
    "name:jpn_x_preferred":[
        "\u5357\u82e5\u5712\u753a"
    ],
    "wof:name":"Minami-wakazonomachi",
    "wof:placetype":"locality"
},
  "geometry": {"coordinates":[130.88742999999999,33.8421],"type":"Point"}
}