{
  "type": "Feature",
  "properties": {
    "gn:admin1_code":"15",
    "gn:admin2_code":"7467838.0",
    "gn:admin3_code":"17386.0",
    "gn:asciiname":"Kitakawashiri",
    "gn:country_code":"JP",
    "gn:dem":16,
    "gn:feature_class":"P",
    "gn:feature_code":"PPL",
    "gn:name":"Kitakawashiri",
    "gn:population":0,
    "gn:timezone":"Asia/Tokyo",
    "iso:country":"JP",
    "name:jpn_x_preferred":[
        "\u5317\u5ddd\u5c3b"
    ],
    "name:und_x_variant":[
        "Kita-kawajiri",
        "Kita-kawashiri",
        "Kitakawashiri"
    ],
    "wof:name":"Kitakawashiri",
    "wof:placetype":"locality"
},
  "geometry": {"coordinates":[136.74420000000001,36.80199],"type":"Point"}
}