{
  "type": "Feature",
  "properties": {
    "gn:admin1_code":"25.0",
    "gn:admin2_code":"7413970.0",
    "gn:asciiname":"Ohira",
    "gn:country_code":"JP",
    "gn:dem":304,
    "gn:feature_class":"P",
    "gn:feature_code":"PPLL",
    "gn:name":"\u014chira",
    "gn:population":0,
    "gn:timezone":"Asia/Tokyo",
    "iso:country":"JP",
    "name:jpn_x_preferred":[
        "\u5927\u5e73"
    ],
    "name:jpn_x_variant":[
        "\u304a\u304a\u3072\u3089",
        "\u30aa\u30aa\u30d2\u30e9"
    ],
    "name:kor_x_preferred":[
        "\uc624\ud788\ub77c"
    ],
    "name:rus_x_preferred":[
        "\u041e\u0445\u0438\u0440\u0430"
    ],
    "name:ukr_x_preferred":[
        "\u041e\u0445\u0456\u0440\u0430"
    ],
    "name:und_x_variant":[
        "\u014chira"
    ],
    "wof:name":"Ohira",
    "wof:placetype":"locality"
},
  "geometry": {"coordinates":[130.96021000000002,32.03946],"type":"Point"}
}