{
  "type": "Feature",
  "properties": {
    "gn:admin1_code":"4.0",
    "gn:admin2_code":"2112663.0",
    "gn:asciiname":"Kayahashi",
    "gn:country_code":"JP",
    "gn:dem":49,
    "gn:feature_class":"P",
    "gn:feature_code":"PPL",
    "gn:name":"Kayahashi",
    "gn:population":0,
    "gn:timezone":"Asia/Tokyo",
    "iso:country":"JP",
    "name:jpn_x_preferred":[
        "\u6822\u6a4b"
    ],
    "name:jpn_x_variant":[
        "\u304b\u3084\u306f\u3057",
        "\u30ab\u30e4\u30cf\u30b7"
    ],
    "wof:name":"Kayahashi",
    "wof:placetype":"locality"
},
  "geometry": {"coordinates":[140.09818999999999,35.39417],"type":"Point"}
}