{
  "type": "Feature",
  "properties": {
    "gn:admin1_code":"3.0",
    "gn:admin2_code":"2130654.0",
    "gn:asciiname":"Hotarudani",
    "gn:country_code":"JP",
    "gn:dem":28,
    "gn:feature_class":"P",
    "gn:feature_code":"PPL",
    "gn:name":"Hotarudani",
    "gn:population":0,
    "gn:timezone":"Asia/Tokyo",
    "iso:country":"JP",
    "name:jpn_x_preferred":[
        "\u86cd\u8c37"
    ],
    "name:jpn_x_variant":[
        "\u307b\u305f\u308b\u3060\u306b",
        "\u30db\u30bf\u30eb\u30c0\u30cb"
    ],
    "wof:name":"Hotarudani",
    "wof:placetype":"locality"
},
  "geometry": {"coordinates":[140.86443,40.89309],"type":"Point"}
}