{
  "type": "Feature",
  "properties": {
    "gn:admin1_code":"4.0",
    "gn:admin2_code":"1857552.0",
    "gn:asciiname":"Tokiwadaira-nishikubocho",
    "gn:country_code":"JP",
    "gn:dem":24,
    "gn:feature_class":"P",
    "gn:feature_code":"PPL",
    "gn:name":"Tokiwadaira-nishikuboch\u014d",
    "gn:population":0,
    "gn:timezone":"Asia/Tokyo",
    "iso:country":"JP",
    "name:jpn_x_preferred":[
        "\u5e38\u76e4\u5e73\u897f\u7aaa\u753a"
    ],
    "name:und_x_variant":[
        "Tokiwadaira-nishikuboch\u014d"
    ],
    "wof:name":"Tokiwadaira-nishikubocho",
    "wof:placetype":"locality"
},
  "geometry": {"coordinates":[139.94391000000002,35.79643],"type":"Point"}
}