{
  "type": "Feature",
  "properties": {
    "gn:admin1_code":"4.0",
    "gn:admin2_code":"8304237.0",
    "gn:asciiname":"Ichinono",
    "gn:country_code":"JP",
    "gn:dem":58,
    "gn:feature_class":"P",
    "gn:feature_code":"PPLL",
    "gn:name":"Ichinono",
    "gn:population":0,
    "gn:timezone":"Asia/Tokyo",
    "iso:country":"JP",
    "name:jpn_x_preferred":[
        "\u5e02\u91ce\u3005"
    ],
    "name:jpn_x_variant":[
        "\u3044\u3061\u306e\u306e",
        "\u30a4\u30c1\u30ce\u30ce"
    ],
    "wof:name":"Ichinono",
    "wof:placetype":"locality"
},
  "geometry": {"coordinates":[140.11193,35.35784],"type":"Point"}
}