{
  "type": "Feature",
  "properties": {
    "gn:admin1_code":"34.0",
    "gn:admin2_code":"1850300.0",
    "gn:asciiname":"Sasame",
    "gn:country_code":"JP",
    "gn:dem":8,
    "gn:feature_class":"P",
    "gn:feature_code":"PPL",
    "gn:name":"Sasame",
    "gn:population":0,
    "gn:timezone":"Asia/Tokyo",
    "iso:country":"JP",
    "name:jpn_x_preferred":[
        "\u7b39\u76ee"
    ],
    "name:jpn_x_variant":[
        "\u3055\u3055\u3081",
        "\u30b5\u30b5\u30e1"
    ],
    "wof:name":"Sasame",
    "wof:placetype":"locality"
},
  "geometry": {"coordinates":[139.64666,35.81498],"type":"Point"}
}