{
  "type": "Feature",
  "properties": {
    "gn:admin1_code":"4.0",
    "gn:admin2_code":"8304237.0",
    "gn:asciiname":"Sakuraiyatsu",
    "gn:country_code":"JP",
    "gn:dem":44,
    "gn:feature_class":"P",
    "gn:feature_code":"PPLL",
    "gn:name":"Sakuraiyatsu",
    "gn:population":0,
    "gn:timezone":"Asia/Tokyo",
    "iso:country":"JP",
    "name:jpn_x_preferred":[
        "\u685c\u4e95\u8c37"
    ],
    "name:jpn_x_variant":[
        "\u3055\u304f\u3089\u3044\u3084\u3064",
        "\u30b5\u30af\u30e9\u30a4\u30e4\u30c4"
    ],
    "wof:name":"Sakuraiyatsu",
    "wof:placetype":"locality"
},
  "geometry": {"coordinates":[139.9272,35.36139],"type":"Point"}
}