{
  "type": "Feature",
  "properties": {
    "gn:admin1_code":"19",
    "gn:admin2_code":"1864928.0",
    "gn:asciiname":"Tomuro",
    "gn:country_code":"JP",
    "gn:dem":53,
    "gn:feature_class":"P",
    "gn:feature_code":"PPL",
    "gn:name":"Tomuro",
    "gn:population":0,
    "gn:timezone":"Asia/Tokyo",
    "iso:country":"JP",
    "name:jpn_x_preferred":[
        "\u6238\u5ba4"
    ],
    "wof:name":"Tomuro",
    "wof:placetype":"locality"
},
  "geometry": {"coordinates":[139.35026000000002,35.44864000000001],"type":"Point"}
}