{
  "type": "Feature",
  "properties": {
    "gn:admin1_code":"32.0",
    "gn:admin2_code":"1864413.0",
    "gn:asciiname":"Sanga",
    "gn:country_code":"JP",
    "gn:dem":5,
    "gn:feature_class":"P",
    "gn:feature_code":"PPL",
    "gn:name":"Sanga",
    "gn:population":0,
    "gn:timezone":"Asia/Tokyo",
    "iso:country":"JP",
    "name:ceb_x_preferred":[
        "Sanga"
    ],
    "name:deu_x_preferred":[
        "Sanga"
    ],
    "name:fra_x_preferred":[
        "Sanga"
    ],
    "name:ita_x_preferred":[
        "Sanga"
    ],
    "name:jpn_x_preferred":[
        "\u4e09\u7b87"
    ],
    "name:por_x_preferred":[
        "Sanga"
    ],
    "name:swe_x_preferred":[
        "Sanga"
    ],
    "wof:name":"Sanga",
    "wof:placetype":"locality"
},
  "geometry": {"coordinates":[135.62594000000001,34.72257],"type":"Point"}
}