{
  "type": "Feature",
  "properties": {
    "gn:admin1_code":"4.0",
    "gn:admin2_code":"7465524.0",
    "gn:asciiname":"Wakayama",
    "gn:country_code":"JP",
    "gn:dem":5,
    "gn:feature_class":"P",
    "gn:feature_code":"PPL",
    "gn:name":"Wakayama",
    "gn:population":0,
    "gn:timezone":"Asia/Tokyo",
    "iso:country":"JP",
    "name:aze_x_preferred":[
        "Vakayama"
    ],
    "name:ceb_x_preferred":[
        "Wakayama"
    ],
    "name:deu_x_preferred":[
        "Wakayama"
    ],
    "name:epo_x_preferred":[
        "\u016cakajama"
    ],
    "name:jpn_x_preferred":[
        "\u82e5\u5c71"
    ],
    "name:jpn_x_variant":[
        "\u308f\u304b\u3084\u307e",
        "\u30ef\u30ab\u30e4\u30de",
        "\u548c\u6b4c\u5c71"
    ],
    "name:kaz_x_preferred":[
        "\u0412\u0430\u043a\u0430\u044f\u043c\u0430"
    ],
    "name:kor_x_preferred":[
        "\uc640\uce74\uc57c\ub9c8"
    ],
    "name:mlg_x_preferred":[
        "Wakayama"
    ],
    "name:nld_x_preferred":[
        "Wakayama"
    ],
    "name:nor_x_preferred":[
        "Wakayama"
    ],
    "name:ron_x_preferred":[
        "Wakayama"
    ],
    "name:rus_x_preferred":[
        "\u0412\u0430\u043a\u0430\u044f\u043c\u0430"
    ],
    "name:slk_x_preferred":[
        "Wakajama"
    ],
    "name:swa_x_preferred":[
        "Wakayama"
    ],
    "name:ukr_x_preferred":[
        "\u0412\u0430\u043a\u0430\u044f\u043c\u0430"
    ],
    "name:zho_x_preferred":[
        "\u548c\u6b4c\u5c71"
    ],
    "wof:name":"Wakayama",
    "wof:placetype":"locality"
},
  "geometry": {"coordinates":[140.38326000000001,35.26897],"type":"Point"}
}