{
  "type": "Feature",
  "properties": {
    "gn:admin1_code":"4.0",
    "gn:admin2_code":"7465524.0",
    "gn:asciiname":"Wakayama",
    "gn:country_code":"JP",
    "gn:dem":5,
    "gn:feature_class":"P",
    "gn:feature_code":"PPL",
    "gn:name":"Wakayama",
    "gn:population":0,
    "gn:timezone":"Asia/Tokyo",
    "iso:country":"JP",
    "name:jpn_x_preferred":[
        "\u82e5\u5c71"
    ],
    "name:jpn_x_variant":[
        "\u308f\u304b\u3084\u307e",
        "\u30ef\u30ab\u30e4\u30de"
    ],
    "wof:name":"Wakayama",
    "wof:placetype":"locality"
},
  "geometry": {"coordinates":[140.38326000000001,35.26897],"type":"Point"}
}