{
  "type": "Feature",
  "properties": {
    "gn:admin1_code":"21.0",
    "gn:admin2_code":"7412706.0",
    "gn:admin3_code":"43444.0",
    "gn:asciiname":"Sanga",
    "gn:country_code":"JP",
    "gn:dem":35,
    "gn:feature_class":"P",
    "gn:feature_code":"PPLL",
    "gn:name":"Sanga",
    "gn:population":0,
    "gn:timezone":"Asia/Tokyo",
    "iso:country":"JP",
    "name:jpn_x_preferred":[
        "\u4e09\u7b87"
    ],
    "name:jpn_x_variant":[
        "\u3055\u3093\u304c",
        "\u30b5\u30f3\u30ac"
    ],
    "wof:name":"Sanga",
    "wof:placetype":"locality"
},
  "geometry": {"coordinates":[130.78068999999999,32.68264],"type":"Point"}
}