{
  "type": "Feature",
  "properties": {
    "gn:admin1_code":"15.0",
    "gn:admin2_code":"7467838.0",
    "gn:admin3_code":"17384.0",
    "gn:asciiname":"Togi-ushioroshi",
    "gn:country_code":"JP",
    "gn:dem":48,
    "gn:feature_class":"P",
    "gn:feature_code":"PPL",
    "gn:name":"Togi-ushioroshi",
    "gn:population":0,
    "gn:timezone":"Asia/Tokyo",
    "iso:country":"JP",
    "name:jpn_x_preferred":[
        "\u5bcc\u6765\u725b\u4e0b"
    ],
    "wof:name":"Togi-ushioroshi",
    "wof:placetype":"locality"
},
  "geometry": {"coordinates":[136.73092,37.10473],"type":"Point"}
}