{
  "type": "Feature",
  "properties": {
    "gn:admin1_code":"23.0",
    "gn:admin2_code":"1857496.0",
    "gn:asciiname":"Ureshino-sukaryocho",
    "gn:country_code":"JP",
    "gn:dem":-1,
    "gn:feature_class":"P",
    "gn:feature_code":"PPL",
    "gn:name":"Ureshino-sukary\u014dch\u014d",
    "gn:population":0,
    "gn:timezone":"Asia/Tokyo",
    "iso:country":"JP",
    "name:jpn_x_preferred":[
        "\u5b09\u91ce\u9808\u8cc0\u9818\u753a"
    ],
    "name:und_x_variant":[
        "Ureshino-sukary\u014dch\u014d"
    ],
    "wof:name":"Ureshino-sukaryocho",
    "wof:placetype":"locality"
},
  "geometry": {"coordinates":[136.49026000000001,34.61265],"type":"Point"}
}