{
  "type": "Feature",
  "properties": {
    "gn:admin1_code":"19.0",
    "gn:admin2_code":"1854744.0",
    "gn:asciiname":"Uchikoshi",
    "gn:country_code":"JP",
    "gn:dem":51,
    "gn:feature_class":"P",
    "gn:feature_code":"PPLL",
    "gn:name":"Uchikoshi",
    "gn:population":0,
    "gn:timezone":"Asia/Tokyo",
    "iso:country":"JP",
    "name:jpn_x_preferred":[
        "\u6253\u8d8a"
    ],
    "wof:name":"Uchikoshi",
    "wof:placetype":"locality"
},
  "geometry": {"coordinates":[139.22792999999999,35.31509000000001],"type":"Point"}
}