{
  "type": "Feature",
  "properties": {
    "gn:admin1_code":"4.0",
    "gn:admin2_code":"8304237.0",
    "gn:asciiname":"Nagasuka",
    "gn:country_code":"JP",
    "gn:dem":2,
    "gn:feature_class":"P",
    "gn:feature_code":"PPL",
    "gn:name":"Nagasuka",
    "gn:population":0,
    "gn:timezone":"Asia/Tokyo",
    "iso:country":"JP",
    "name:jpn_x_preferred":[
        "\u9577\u9808\u8cc0"
    ],
    "name:jpn_x_variant":[
        "\u306a\u304c\u3059\u304b",
        "\u30ca\u30ac\u30b9\u30ab"
    ],
    "wof:name":"Nagasuka",
    "wof:placetype":"locality"
},
  "geometry": {"coordinates":[139.93456,35.3925],"type":"Point"}
}