{
  "type": "Feature",
  "properties": {
    "gn:admin1_code":"45.0",
    "gn:admin2_code":"1852222.0",
    "gn:asciiname":"Hikoshima-deshimatsu-higashimachi",
    "gn:country_code":"JP",
    "gn:dem":52,
    "gn:feature_class":"P",
    "gn:feature_code":"PPL",
    "gn:name":"Hikoshima-deshimatsu-higashimachi",
    "gn:population":0,
    "gn:timezone":"Asia/Tokyo",
    "iso:country":"JP",
    "name:jpn_x_preferred":[
        "\u5f66\u5cf6\u5f1f\u5b50\u5f85\u6771\u753a"
    ],
    "wof:name":"Hikoshima-deshimatsu-higashimachi",
    "wof:placetype":"locality"
},
  "geometry": {"coordinates":[130.92461,33.92896],"type":"Point"}
}