{
  "type": "Feature",
  "properties": {
    "gn:admin1_code":"10.0",
    "gn:admin2_code":"1860108.0",
    "gn:admin3_code":"10382.0",
    "gn:asciiname":"Negoya",
    "gn:country_code":"JP",
    "gn:dem":382,
    "gn:feature_class":"P",
    "gn:feature_code":"PPLL",
    "gn:name":"Negoya",
    "gn:population":0,
    "gn:timezone":"Asia/Tokyo",
    "iso:country":"JP",
    "name:jpn_x_preferred":[
        "\u6839\u5c0f\u5c4b"
    ],
    "wof:name":"Negoya",
    "wof:placetype":"locality"
},
  "geometry": {"coordinates":[138.70581999999999,36.24986],"type":"Point"}
}