{
  "type": "Feature",
  "properties": {
    "gn:admin1_code":"35.0",
    "gn:admin2_code":"1858984.0",
    "gn:asciiname":"Tsuchiyamacho-kurokawa",
    "gn:country_code":"JP",
    "gn:dem":306,
    "gn:feature_class":"P",
    "gn:feature_code":"PPL",
    "gn:name":"Tsuchiyamach\u014d-kurokawa",
    "gn:population":0,
    "gn:timezone":"Asia/Tokyo",
    "iso:country":"JP",
    "name:jpn_x_preferred":[
        "\u571f\u5c71\u753a\u9ed2\u5ddd"
    ],
    "name:und_x_variant":[
        "Tsuchiyamach\u014d-kurokawa"
    ],
    "wof:name":"Tsuchiyamacho-kurokawa",
    "wof:placetype":"locality"
},
  "geometry": {"coordinates":[136.33189999999999,34.92825],"type":"Point"}
}