{
  "type": "Feature",
  "properties": {
    "iso:country":"JP",
    "name:eng_x_preferred":[
        "Ushikubonishi 4 Chome"
    ],
    "name:eng_x_variant":[
        "Ushikubonishi 4 Choume",
        "Ushikubonishi 4 Chome"
    ],
    "name:jpn_x_preferred":[
        "\uff14\u4e01\u76ee"
    ],
    "name:jpn_x_variant":[
        "\u3046\u3057\u304f\u307c\u306b\u3057 \uff14\u3061\u3087\u3046\u3081",
        "\u725b\u4e45\u4fdd\u897f \uff14\u4e01\u76ee",
        "\uff14\u3061\u3087\u3046\u3081"
    ],
    "qs:gn_local":0,
    "qs:local_max":6208,
    "qs:local_sum":82309,
    "qs:localhoods":190,
    "qs:name":"\uff14\u4e01\u76ee",
    "qs:name_adm0":"\u65e5\u672c",
    "qs:name_adm1":"\u795e\u5948\u5ddd\u770c",
    "qs:name_adm2":"\u90fd\u7b51\u533a",
    "qs:name_en":"Ushikubonishi 4 Chome",
    "qs:name_lau":"\u725b\u4e45\u4fdd\u897f",
    "qs:name_local":"\u6a2a\u6d5c\u5e02",
    "qs:photo_max":99,
    "qs:photo_sum":547,
    "qs:placetype":"Suburb",
    "qs:quad_count":27,
    "qs:woe_adm0":23424856,
    "qs:woe_adm1":2345868,
    "qs:woe_adm2":15015541,
    "qs:woe_lau":28416234,
    "qs:woe_local":1118550,
    "qs:woe_ver":"7.10.0",
    "wof:lang":[
        "jpn"
    ],
    "wof:name":"\uff14\u4e01\u76ee",
    "wof:placetype":"neighbourhood"
},
  "geometry": {"coordinates":[139.577519,35.55545],"type":"Point"}
}