{
  "type": "Feature",
  "properties": {
    "gn:admin1_code":"28.0",
    "gn:admin2_code":"7411377.0",
    "gn:admin3_code":"29322.0",
    "gn:asciiname":"Matsuo",
    "gn:country_code":"JP",
    "gn:dem":360,
    "gn:feature_class":"P",
    "gn:feature_code":"PPL",
    "gn:name":"Matsuo",
    "gn:population":0,
    "gn:timezone":"Asia/Tokyo",
    "iso:country":"JP",
    "name:deu_x_preferred":[
        "Matsuo"
    ],
    "name:jpn_x_preferred":[
        "\u677e\u5c3e"
    ],
    "name:kor_x_preferred":[
        "\ub9c8\uc4f0\uc624"
    ],
    "wof:name":"Matsuo",
    "wof:placetype":"locality"
},
  "geometry": {"coordinates":[135.96173000000002,34.68035],"type":"Point"}
}