{
  "type": "Feature",
  "properties": {
    "gn:admin1_code":"19.0",
    "gn:admin2_code":"1848350.0",
    "gn:admin3_code":"14104.0",
    "gn:asciiname":"Nakaodai",
    "gn:country_code":"JP",
    "gn:dem":33,
    "gn:feature_class":"P",
    "gn:feature_code":"PPL",
    "gn:name":"Nakaodai",
    "gn:population":0,
    "gn:timezone":"Asia/Tokyo",
    "iso:country":"JP",
    "name:jpn_x_preferred":[
        "\u4ef2\u5c3e\u53f0"
    ],
    "name:jpn_x_variant":[
        "\u306a\u304b\u304a\u3060\u3044",
        "\u30ca\u30ab\u30aa\u30c0\u30a4"
    ],
    "wof:name":"Nakaodai",
    "wof:placetype":"locality"
},
  "geometry": {"coordinates":[139.64338000000001,35.42644],"type":"Point"}
}