{
  "type": "Feature",
  "properties": {
    "gn:admin1_code":"2.0",
    "gn:admin2_code":"2128783.0",
    "gn:asciiname":"Akihitodome",
    "gn:country_code":"JP",
    "gn:dem":81,
    "gn:feature_class":"P",
    "gn:feature_code":"PPL",
    "gn:name":"Akihitodome",
    "gn:population":0,
    "gn:timezone":"Asia/Tokyo",
    "iso:country":"JP",
    "name:jpn_x_preferred":[
        "\u5546\u4eba\u7559"
    ],
    "name:jpn_x_variant":[
        "\u3042\u304d\u3072\u3068\u3069\u3081",
        "\u30a2\u30ad\u30d2\u30c8\u30c9\u30e1"
    ],
    "wof:name":"Akihitodome",
    "wof:placetype":"locality"
},
  "geometry": {"coordinates":[140.58545000000001,40.31443],"type":"Point"}
}