{
  "type": "Feature",
  "properties": {
    "gn:admin1_code":"19.0",
    "gn:admin2_code":"1862461.0",
    "gn:asciiname":"Tsubonouchi",
    "gn:country_code":"JP",
    "gn:dem":35,
    "gn:feature_class":"P",
    "gn:feature_code":"PPLL",
    "gn:name":"Tsubonouchi",
    "gn:population":0,
    "gn:timezone":"Asia/Tokyo",
    "iso:country":"JP",
    "name:jpn_x_preferred":[
        "\u576a\u30ce\u5185"
    ],
    "wof:name":"Tsubonouchi",
    "wof:placetype":"locality"
},
  "geometry": {"coordinates":[139.28656000000001,35.35738],"type":"Point"}
}