{
  "type": "Feature",
  "properties": {
    "gn:admin1_code":"27",
    "gn:admin2_code":"1857159.0",
    "gn:admin3_code":"42411.0",
    "gn:asciiname":"Yakezaki",
    "gn:country_code":"JP",
    "gn:dem":14,
    "gn:feature_class":"P",
    "gn:feature_code":"PPL",
    "gn:name":"Yakezaki",
    "gn:population":0,
    "gn:timezone":"Asia/Tokyo",
    "iso:country":"JP",
    "name:jpn_x_preferred":[
        "\u713c\u5d0e"
    ],
    "name:und_x_variant":[
        "Yakisaki",
        "Yakezaki"
    ],
    "wof:name":"Yakezaki",
    "wof:placetype":"locality"
},
  "geometry": {"coordinates":[129.00323,32.94618],"type":"Point"}
}