{
  "type": "Feature",
  "properties": {
    "gn:admin1_code":"12.0",
    "gn:admin2_code":"7428116.0",
    "gn:admin3_code":"1607.0",
    "gn:asciiname":"Sakaimachi-nishi",
    "gn:country_code":"JP",
    "gn:dem":8,
    "gn:feature_class":"P",
    "gn:feature_code":"PPL",
    "gn:name":"Sakaimachi-nishi",
    "gn:population":0,
    "gn:timezone":"Asia/Tokyo",
    "iso:country":"JP",
    "name:jpn_x_preferred":[
        "\u583a\u753a\u897f"
    ],
    "name:jpn_x_variant":[
        "\u3055\u304b\u3044\u307e\u3061\u306b\u3057",
        "\u30b5\u30ab\u30a4\u30de\u30c1\u30cb\u30b7"
    ],
    "wof:name":"Sakaimachi-nishi",
    "wof:placetype":"locality"
},
  "geometry": {"coordinates":[142.76156,42.18314],"type":"Point"}
}