{
  "type": "Feature",
  "properties": {
    "gn:admin1_code":"34.0",
    "gn:admin2_code":"1854369.0",
    "gn:asciiname":"Okamura",
    "gn:country_code":"JP",
    "gn:dem":18,
    "gn:feature_class":"P",
    "gn:feature_code":"PPLL",
    "gn:name":"Okamura",
    "gn:population":0,
    "gn:timezone":"Asia/Tokyo",
    "iso:country":"JP",
    "name:jpn_x_preferred":[
        "\u5ca1\u6751"
    ],
    "name:jpn_x_variant":[
        "\u304a\u304b\u3080\u3089",
        "\u30aa\u30ab\u30e0\u30e9"
    ],
    "wof:name":"Okamura",
    "wof:placetype":"locality"
},
  "geometry": {"coordinates":[139.53344999999999,35.99795],"type":"Point"}
}