{
  "type": "Feature",
  "properties": {
    "gn:admin1_code":"15.0",
    "gn:admin2_code":"7467838.0",
    "gn:admin3_code":"17386.0",
    "gn:asciiname":"Azuma",
    "gn:country_code":"JP",
    "gn:dem":87,
    "gn:feature_class":"P",
    "gn:feature_code":"PPL",
    "gn:name":"Azuma",
    "gn:population":0,
    "gn:timezone":"Asia/Tokyo",
    "iso:country":"JP",
    "name:ces_x_preferred":[
        "Azuma"
    ],
    "name:deu_x_preferred":[
        "Azuma"
    ],
    "name:fra_x_preferred":[
        "Azuma"
    ],
    "name:ita_x_preferred":[
        "Azuma"
    ],
    "name:jpn_x_preferred":[
        "\u6771\u9593"
    ],
    "name:kaz_x_preferred":[
        "\u0410\u0434\u0437\u0443\u043c\u0430"
    ],
    "name:kor_x_preferred":[
        "\uc544\uc988\ub9c8"
    ],
    "name:rus_x_preferred":[
        "\u0410\u0434\u0437\u0443\u043c\u0430"
    ],
    "name:slk_x_preferred":[
        "Azuma"
    ],
    "name:spa_x_preferred":[
        "Azuma"
    ],
    "wof:name":"Azuma",
    "wof:placetype":"locality"
},
  "geometry": {"coordinates":[136.77592000000001,36.79237],"type":"Point"}
}