{
  "type": "Feature",
  "properties": {
    "gn:admin1_code":"24.0",
    "gn:admin2_code":"7446985.0",
    "gn:admin3_code":"4445.0",
    "gn:asciiname":"Kanohara",
    "gn:country_code":"JP",
    "gn:dem":127,
    "gn:feature_class":"P",
    "gn:feature_code":"PPL",
    "gn:name":"Kanohara",
    "gn:population":0,
    "gn:timezone":"Asia/Tokyo",
    "iso:country":"JP",
    "name:jpn_x_preferred":[
        "\u9e7f\u539f"
    ],
    "wof:name":"Kanohara",
    "wof:placetype":"locality"
},
  "geometry": {"coordinates":[140.73407,38.55219],"type":"Point"}
}