{
  "type": "Feature",
  "properties": {
    "gn:admin1_code":"15",
    "gn:admin2_code":"1858904.0",
    "gn:asciiname":"Atakamachi",
    "gn:cc2":"JP",
    "gn:country_code":"JP",
    "gn:dem":6,
    "gn:feature_class":"P",
    "gn:feature_code":"PPL",
    "gn:name":"Atakamachi",
    "gn:population":0,
    "gn:timezone":"Asia/Tokyo",
    "iso:country":"JP",
    "name:und_x_variant":[
        "Ataku",
        "Ataka"
    ],
    "wof:name":"Atakamachi",
    "wof:placetype":"locality"
},
  "geometry": {"coordinates":[136.4211,36.42232],"type":"Point"}
}