{
  "type": "Feature",
  "properties": {
    "gn:admin1_code":"40.0",
    "gn:admin2_code":"1861322.0",
    "gn:asciiname":"Narimasu",
    "gn:country_code":"JP",
    "gn:dem":29,
    "gn:feature_class":"P",
    "gn:feature_code":"PPL",
    "gn:name":"Narimasu",
    "gn:population":0,
    "gn:timezone":"Asia/Tokyo",
    "iso:country":"JP",
    "name:jpn_x_preferred":[
        "\u6210\u5897"
    ],
    "name:jpn_x_variant":[
        "\u306a\u308a\u307e\u3059",
        "\u30ca\u30ea\u30de\u30b9"
    ],
    "wof:name":"Narimasu",
    "wof:placetype":"locality"
},
  "geometry": {"coordinates":[139.63229999999999,35.78355],"type":"Point"}
}