{
  "type": "Feature",
  "properties": {
    "iso:country":"JP",
    "name:eng_x_preferred":[
        "Sakuragawa 1 Chome"
    ],
    "name:eng_x_variant":[
        "Sakuragawa 1 Choume",
        "Sakuragawa 1 Chome"
    ],
    "name:jpn_x_preferred":[
        "\uff11\u4e01\u76ee"
    ],
    "name:jpn_x_variant":[
        "\u3055\u304f\u3089\u304c\u308f \uff11\u3061\u3087\u3046\u3081",
        "\u685c\u5ddd \uff11\u4e01\u76ee",
        "\uff11\u3061\u3087\u3046\u3081"
    ],
    "qs:gn_adm0_cc":"JP",
    "qs:gn_local":1850147,
    "qs:local_max":18112,
    "qs:local_sum":895907,
    "qs:localhoods":857,
    "qs:name":"\uff11\u4e01\u76ee",
    "qs:name_adm0":"\u65e5\u672c",
    "qs:name_adm1":"\u6771\u4eac\u90fd",
    "qs:name_adm2":"\u677f\u6a4b\u533a",
    "qs:name_en":"Sakuragawa 1 Chome",
    "qs:name_lau":"\u685c\u5ddd",
    "qs:name_local":"\u6771\u4eac",
    "qs:photo_max":10,
    "qs:photo_sum":52,
    "qs:placetype":"Suburb",
    "qs:quad_count":7,
    "qs:woe_adm0":23424856,
    "qs:woe_adm1":2345889,
    "qs:woe_adm2":15015502,
    "qs:woe_lau":28414546,
    "qs:woe_local":1118370,
    "qs:woe_ver":"7.10.0",
    "wof:lang":[
        "jpn"
    ],
    "wof:name":"\uff11\u4e01\u76ee",
    "wof:placetype":"neighbourhood"
},
  "geometry": {"coordinates":[139.671683,35.753817],"type":"Point"}
}