{
  "type": "Feature",
  "properties": {
    "gn:admin1_code":"29",
    "gn:admin2_code":"1852604.0",
    "gn:asciiname":"Matsuoka",
    "gn:country_code":"JP",
    "gn:dem":29,
    "gn:feature_class":"P",
    "gn:feature_code":"PPL",
    "gn:name":"Matsuoka",
    "gn:population":0,
    "gn:timezone":"Asia/Tokyo",
    "iso:country":"JP",
    "name:jpn_x_preferred":[
        "\u677e\u5ca1"
    ],
    "wof:name":"Matsuoka",
    "wof:placetype":"locality"
},
  "geometry": {"coordinates":[139.34163999999998,37.8958],"type":"Point"}
}