{
  "type": "Feature",
  "properties": {
    "gn:admin1_code":"27.0",
    "gn:admin2_code":"7418808.0",
    "gn:asciiname":"Oshimacho",
    "gn:country_code":"JP",
    "gn:dem":105,
    "gn:feature_class":"P",
    "gn:feature_code":"PPL",
    "gn:name":"\u014cshimach\u014d",
    "gn:population":0,
    "gn:timezone":"Asia/Tokyo",
    "iso:country":"JP",
    "name:jpn_x_preferred":[
        "\u5927\u5cf6\u753a"
    ],
    "name:und_x_variant":[
        "\u014cshimach\u014d"
    ],
    "wof:name":"Oshimacho",
    "wof:placetype":"locality"
},
  "geometry": {"coordinates":[129.60968,33.04551],"type":"Point"}
}