{
  "type": "Feature",
  "properties": {
    "gn:admin1_code":"4.0",
    "gn:admin2_code":"7465524.0",
    "gn:asciiname":"Satsuso",
    "gn:country_code":"JP",
    "gn:dem":22,
    "gn:feature_class":"P",
    "gn:feature_code":"PPLL",
    "gn:name":"Satsus\u014d",
    "gn:population":0,
    "gn:timezone":"Asia/Tokyo",
    "iso:country":"JP",
    "name:jpn_x_preferred":[
        "\u672d\u66fd"
    ],
    "name:jpn_x_variant":[
        "\u3055\u3064\u305d\u3046",
        "\u30b5\u30c4\u30bd\u30a6"
    ],
    "name:und_x_variant":[
        "Satsus\u014d"
    ],
    "wof:name":"Satsuso",
    "wof:placetype":"locality"
},
  "geometry": {"coordinates":[140.28724,35.27081],"type":"Point"}
}