{
  "type": "Feature",
  "properties": {
    "gn:admin1_code":"12.0",
    "gn:admin2_code":"2128812.0",
    "gn:asciiname":"Kawanishicho",
    "gn:country_code":"JP",
    "gn:dem":85,
    "gn:feature_class":"P",
    "gn:feature_code":"PPL",
    "gn:name":"Kawanishich\u014d",
    "gn:population":0,
    "gn:timezone":"Asia/Tokyo",
    "iso:country":"JP",
    "name:jpn_x_preferred":[
        "\u5ddd\u897f\u753a"
    ],
    "name:und_x_variant":[
        "Kawanishich\u014d",
        "Kawanishi"
    ],
    "wof:name":"Kawanishicho",
    "wof:placetype":"locality"
},
  "geometry": {"coordinates":[143.17271000000005,42.85715],"type":"Point"}
}