{
  "type": "Feature",
  "properties": {
    "gn:admin1_code":"24.0",
    "gn:admin2_code":"2112574.0",
    "gn:asciiname":"Nagatsura",
    "gn:country_code":"JP",
    "gn:dem":-1,
    "gn:feature_class":"P",
    "gn:feature_code":"PPL",
    "gn:name":"Nagatsura",
    "gn:population":0,
    "gn:timezone":"Asia/Tokyo",
    "iso:country":"JP",
    "name:jpn_x_preferred":[
        "\u9577\u9762"
    ],
    "name:und_x_variant":[
        "Nagatsurahama",
        "Nagatsura"
    ],
    "wof:name":"Nagatsura",
    "wof:placetype":"locality"
},
  "geometry": {"coordinates":[141.45570000000001,38.5619],"type":"Point"}
}