{
  "type": "Feature",
  "properties": {
    "gn:admin1_code":"19",
    "gn:admin2_code":"7470890.0",
    "gn:asciiname":"Yagurasawa",
    "gn:country_code":"JP",
    "gn:dem":262,
    "gn:feature_class":"P",
    "gn:feature_code":"PPL",
    "gn:name":"Yagurasawa",
    "gn:population":0,
    "gn:timezone":"Asia/Tokyo",
    "iso:country":"JP",
    "name:jpn_x_preferred":[
        "\u77e2\u5009\u6ca2"
    ],
    "wof:name":"Yagurasawa",
    "wof:placetype":"locality"
},
  "geometry": {"coordinates":[139.05296999999999,35.32955],"type":"Point"}
}