{
  "type": "Feature",
  "properties": {
    "iso:country":"JP",
    "name:eng_x_preferred":[
        "Komoashiotsu 4 Chome"
    ],
    "name:eng_x_variant":[
        "Komoashiotsu 4 Choume",
        "Komoashiotsu 4 Chome"
    ],
    "name:jpn_x_preferred":[
        "\uff14\u4e01\u76ee"
    ],
    "name:jpn_x_variant":[
        "\u3053\u3082\u3042\u3057\u304a\u3064 \uff14\u3061\u3087\u3046\u3081",
        "\u30b3\u30e2\u30a2\u3057\u304a\u3064 \uff14\u4e01\u76ee",
        "\uff14\u3061\u3087\u3046\u3081"
    ],
    "name:unk_x_variant":[
        "\uff14\u4e01\u76ee"
    ],
    "qs:gn_local":0,
    "qs:local_max":121,
    "qs:local_sum":121,
    "qs:localhoods":1,
    "qs:name":"\uff14\u4e01\u76ee",
    "qs:name_adm0":"\u65e5\u672c",
    "qs:name_adm1":"\u5c71\u68a8\u770c",
    "qs:name_en":"Komoashiotsu 4 Chome",
    "qs:name_lau":"\u30b3\u30e2\u30a2\u3057\u304a\u3064",
    "qs:name_local":"\u4e0a\u91ce\u539f\u5e02",
    "qs:photo_max":79,
    "qs:photo_sum":121,
    "qs:placetype":"Suburb",
    "qs:quad_count":12,
    "qs:woe_adm0":23424856,
    "qs:woe_adm1":2345895,
    "qs:woe_adm2":0,
    "qs:woe_lau":28430992,
    "qs:woe_local":28379353,
    "qs:woe_ver":"7.10.0",
    "wof:lang":[
        "jpn"
    ],
    "wof:name":"\uff14\u4e01\u76ee",
    "wof:placetype":"neighbourhood"
},
  "geometry": {"coordinates":[139.064672,35.628059],"type":"Point"}
}