{
  "type": "Feature",
  "properties": {
    "gn:admin1_code":"44.0",
    "gn:admin2_code":"2111805.0",
    "gn:asciiname":"Kawashima",
    "gn:country_code":"JP",
    "gn:dem":74,
    "gn:feature_class":"P",
    "gn:feature_code":"PPL",
    "gn:name":"Kawashima",
    "gn:population":0,
    "gn:timezone":"Asia/Tokyo",
    "iso:country":"JP",
    "name:jpn_x_preferred":[
        "\u6cb3\u5cf6"
    ],
    "wof:name":"Kawashima",
    "wof:placetype":"locality"
},
  "geometry": {"coordinates":[140.36667,38.48333],"type":"Point"}
}