{
  "type": "Feature",
  "properties": {
    "gn:admin1_code":"24.0",
    "gn:admin2_code":"2112074.0",
    "gn:admin3_code":"4422.0",
    "gn:asciiname":"Nakamura",
    "gn:country_code":"JP",
    "gn:dem":53,
    "gn:feature_class":"P",
    "gn:feature_code":"PPL",
    "gn:name":"Nakamura",
    "gn:population":0,
    "gn:timezone":"Asia/Tokyo",
    "iso:country":"JP",
    "name:bar_x_preferred":[
        "Nakamura"
    ],
    "name:cat_x_preferred":[
        "Nakamura"
    ],
    "name:deu_x_preferred":[
        "Nakamura"
    ],
    "name:epo_x_preferred":[
        "Nakamura"
    ],
    "name:fin_x_preferred":[
        "Nakamura"
    ],
    "name:fra_x_preferred":[
        "Nakamura"
    ],
    "name:heb_x_preferred":[
        "\u05e0\u05e7\u05de\u05d5\u05e8\u05d4"
    ],
    "name:ita_x_preferred":[
        "Nakamura"
    ],
    "name:jpn_x_preferred":[
        "\u4e2d\u6751"
    ],
    "name:jpn_x_variant":[
        "\u306a\u304b\u3080\u3089",
        "\u30ca\u30ab\u30e0\u30e9"
    ],
    "name:kor_x_preferred":[
        "\ub098\uce74\ubb34\ub77c"
    ],
    "name:mlg_x_preferred":[
        "Nakamura"
    ],
    "name:nld_x_preferred":[
        "Nakamura"
    ],
    "name:pol_x_preferred":[
        "Nakamura"
    ],
    "name:por_x_preferred":[
        "Nakamura"
    ],
    "name:rus_x_preferred":[
        "\u041d\u0430\u043a\u0430\u043c\u0443\u0440\u0430"
    ],
    "name:ukr_x_preferred":[
        "\u041d\u0430\u043a\u0430\u043c\u0443\u0440\u0430"
    ],
    "wof:name":"Nakamura",
    "wof:placetype":"locality"
},
  "geometry": {"coordinates":[140.99929,38.41783],"type":"Point"}
}