{
  "type": "Feature",
  "properties": {
    "iso:country":"JP",
    "label:eng_x_preferred_longname":[
        "Pippu Town"
    ],
    "label:eng_x_preferred_placetype":[
        "town"
    ],
    "name:eng_x_preferred":[
        "Pippu"
    ],
    "name:eng_x_variant":[
        "Pippu Town"
    ],
    "name:jpn_x_preferred":[
        "\u6bd4\u5e03\u753a"
    ],
    "qs:name":"\u6bd4\u5e03\u753a",
    "qs:name_adm0":"\u65e5\u672c",
    "qs:name_adm1":"\u5317\u6d77\u9053",
    "qs:photos":81,
    "qs:photos_1k":16,
    "qs:photos_9k":1,
    "qs:photos_9r":3,
    "qs:photos_all":115,
    "qs:photos_sr":3,
    "qs:placetype":"Town",
    "qs:pop_sr":"0",
    "wof:name":"Pippu",
    "wof:placetype":"locality"
},
  "geometry": {"coordinates":[142.495833,43.924444],"type":"Point"}
}