{
  "type": "Feature",
  "properties": {
    "gn:admin1_code":"26.0",
    "gn:admin2_code":"1852001.0",
    "gn:asciiname":"Kuwazaki",
    "gn:country_code":"JP",
    "gn:dem":1071,
    "gn:feature_class":"P",
    "gn:feature_code":"PPL",
    "gn:name":"Kuwazaki",
    "gn:population":0,
    "gn:timezone":"Asia/Tokyo",
    "iso:country":"JP",
    "name:jpn_x_preferred":[
        "\u6851\u5d0e"
    ],
    "wof:name":"Kuwazaki",
    "wof:placetype":"locality"
},
  "geometry": {"coordinates":[137.88534999999999,36.01429],"type":"Point"}
}