{
  "type": "Feature",
  "properties": {
    "gn:admin1_code":"32.0",
    "gn:admin2_code":"7391701.0",
    "gn:asciiname":"Shinsenri-nishimachi",
    "gn:country_code":"JP",
    "gn:dem":92,
    "gn:feature_class":"P",
    "gn:feature_code":"PPL",
    "gn:name":"Shinsenri-nishimachi",
    "gn:population":0,
    "gn:timezone":"Asia/Tokyo",
    "iso:country":"JP",
    "name:jpn_x_preferred":[
        "\u65b0\u5343\u91cc\u897f\u753a"
    ],
    "wof:name":"Shinsenri-nishimachi",
    "wof:placetype":"locality"
},
  "geometry": {"coordinates":[135.49229,34.81193],"type":"Point"}
}