{
  "type": "Feature",
  "properties": {
    "gn:admin1_code":"28.0",
    "gn:admin2_code":"1848164.0",
    "gn:admin3_code":"29453.0",
    "gn:asciiname":"Hagiwara",
    "gn:country_code":"JP",
    "gn:dem":570,
    "gn:feature_class":"P",
    "gn:feature_code":"PPL",
    "gn:name":"Hagiwara",
    "gn:population":0,
    "gn:timezone":"Asia/Tokyo",
    "iso:country":"JP",
    "name:jpn_x_preferred":[
        "\u8429\u539f"
    ],
    "wof:name":"Hagiwara",
    "wof:placetype":"locality"
},
  "geometry": {"coordinates":[135.99988999999999,34.41523],"type":"Point"}
}