{
  "type": "Feature",
  "properties": {
    "gn:admin1_code":"15",
    "gn:admin2_code":"7467881.0",
    "gn:asciiname":"Kawarayamamachi",
    "gn:country_code":"JP",
    "gn:dem":256,
    "gn:feature_class":"P",
    "gn:feature_code":"PPL",
    "gn:name":"Kawarayamamachi",
    "gn:population":0,
    "gn:timezone":"Asia/Tokyo",
    "iso:country":"JP",
    "name:jpn_x_preferred":[
        "\u6cb3\u539f\u5c71\u753a"
    ],
    "name:und_x_variant":[
        "Kawarayama"
    ],
    "wof:name":"Kawarayamamachi",
    "wof:placetype":"locality"
},
  "geometry": {"coordinates":[136.63945000000001,36.30587],"type":"Point"}
}