{
  "type": "Feature",
  "properties": {
    "gn:admin1_code":"34.0",
    "gn:admin2_code":"7464126.0",
    "gn:asciiname":"Kamiogi",
    "gn:country_code":"JP",
    "gn:dem":6,
    "gn:feature_class":"P",
    "gn:feature_code":"PPL",
    "gn:name":"Kami\u014dgi",
    "gn:population":0,
    "gn:timezone":"Asia/Tokyo",
    "iso:country":"JP",
    "name:jpn_x_preferred":[
        "\u795e\u6247"
    ],
    "name:jpn_x_variant":[
        "\u304b\u307f\u304a\u3046\u304e",
        "\u30ab\u30df\u30aa\u30a6\u30ae"
    ],
    "name:und_x_variant":[
        "Kami\u014dgi"
    ],
    "wof:name":"Kamiogi",
    "wof:placetype":"locality"
},
  "geometry": {"coordinates":[139.74487999999999,36.06025],"type":"Point"}
}