{
  "type": "Feature",
  "properties": {
    "gn:admin1_code":"21.0",
    "gn:admin2_code":"1865358.0",
    "gn:asciiname":"Maruomachi",
    "gn:country_code":"JP",
    "gn:dem":7,
    "gn:feature_class":"P",
    "gn:feature_code":"PPL",
    "gn:name":"Maruomachi",
    "gn:population":0,
    "gn:timezone":"Asia/Tokyo",
    "iso:country":"JP",
    "name:jpn_x_preferred":[
        "\u4e38\u5c3e\u753a"
    ],
    "name:jpn_x_variant":[
        "\u307e\u308b\u304a\u307e\u3061",
        "\u30de\u30eb\u30aa\u30de\u30c1"
    ],
    "wof:name":"Maruomachi",
    "wof:placetype":"locality"
},
  "geometry": {"coordinates":[130.18426000000002,32.47011],"type":"Point"}
}