{
  "type": "Feature",
  "properties": {
    "gn:admin1_code":"7.0",
    "gn:admin2_code":"1851269.0",
    "gn:admin3_code":"40608.0",
    "gn:asciiname":"Kamimotomatsu",
    "gn:country_code":"JP",
    "gn:dem":54,
    "gn:feature_class":"P",
    "gn:feature_code":"PPLL",
    "gn:name":"Kamimotomatsu",
    "gn:population":0,
    "gn:timezone":"Asia/Tokyo",
    "iso:country":"JP",
    "name:jpn_x_preferred":[
        "\u4e0a\u5143\u677e"
    ],
    "wof:name":"Kamimotomatsu",
    "wof:placetype":"locality"
},
  "geometry": {"coordinates":[130.84723,33.58967],"type":"Point"}
}