{
  "type": "Feature",
  "properties": {
    "gn:admin1_code":"21.0",
    "gn:admin2_code":"7412708.0",
    "gn:admin3_code":"43501.0",
    "gn:asciiname":"Nakabaru",
    "gn:country_code":"JP",
    "gn:dem":176,
    "gn:feature_class":"P",
    "gn:feature_code":"PPLL",
    "gn:name":"Nakabaru",
    "gn:population":0,
    "gn:timezone":"Asia/Tokyo",
    "iso:country":"JP",
    "name:jpn_x_preferred":[
        "\u4e2d\u539f"
    ],
    "name:jpn_x_variant":[
        "\u306a\u304b\u3070\u308b",
        "\u30ca\u30ab\u30d0\u30eb"
    ],
    "wof:name":"Nakabaru",
    "wof:placetype":"locality"
},
  "geometry": {"coordinates":[130.8691,32.20318],"type":"Point"}
}