{
  "type": "Feature",
  "properties": {
    "gn:admin1_code":"23.0",
    "gn:admin2_code":"1849544.0",
    "gn:asciiname":"Hakusancho-futamata",
    "gn:country_code":"JP",
    "gn:dem":156,
    "gn:feature_class":"P",
    "gn:feature_code":"PPL",
    "gn:name":"Hakusanch\u014d-futamata",
    "gn:population":0,
    "gn:timezone":"Asia/Tokyo",
    "iso:country":"JP",
    "name:jpn_x_preferred":[
        "\u767d\u5c71\u753a\u4e8c\u4fe3"
    ],
    "name:und_x_variant":[
        "Hakusanch\u014d-futamata"
    ],
    "wof:name":"Hakusancho-futamata",
    "wof:placetype":"locality"
},
  "geometry": {"coordinates":[136.30101999999999,34.61799],"type":"Point"}
}