{
  "type": "Feature",
  "properties": {
    "gn:admin1_code":"19",
    "gn:admin2_code":"1854744.0",
    "gn:asciiname":"Kamonomiya",
    "gn:country_code":"JP",
    "gn:dem":15,
    "gn:feature_class":"P",
    "gn:feature_code":"PPL",
    "gn:name":"Kamonomiya",
    "gn:population":0,
    "gn:timezone":"Asia/Tokyo",
    "iso:country":"JP",
    "name:jpn_x_preferred":[
        "\u9d28\u5bae"
    ],
    "name:und_x_variant":[
        "Kamomiya",
        "Kamonomiya"
    ],
    "wof:name":"Kamonomiya",
    "wof:placetype":"locality"
},
  "geometry": {"coordinates":[139.17581999999999,35.27818],"type":"Point"}
}