{
  "type": "Feature",
  "properties": {
    "gn:admin1_code":"37.0",
    "gn:admin2_code":"1856971.0",
    "gn:asciiname":"Hagi",
    "gn:country_code":"JP",
    "gn:dem":86,
    "gn:feature_class":"P",
    "gn:feature_code":"PPL",
    "gn:name":"Hagi",
    "gn:population":0,
    "gn:timezone":"Asia/Tokyo",
    "iso:country":"JP",
    "name:jpn_x_preferred":[
        "\u8429"
    ],
    "wof:name":"Hagi",
    "wof:placetype":"locality"
},
  "geometry": {"coordinates":[138.90926999999999,35.15048],"type":"Point"}
}