{
  "type": "Feature",
  "properties": {
    "gn:admin1_code":"21.0",
    "gn:admin2_code":"7412708.0",
    "gn:admin3_code":"43513.0",
    "gn:asciiname":"Maitoko",
    "gn:country_code":"JP",
    "gn:dem":248,
    "gn:feature_class":"P",
    "gn:feature_code":"PPLL",
    "gn:name":"Maitoko",
    "gn:population":0,
    "gn:timezone":"Asia/Tokyo",
    "iso:country":"JP",
    "name:jpn_x_preferred":[
        "\u6bce\u5e8a"
    ],
    "name:jpn_x_variant":[
        "\u307e\u3044\u3068\u3053",
        "\u30de\u30a4\u30c8\u30b3"
    ],
    "wof:name":"Maitoko",
    "wof:placetype":"locality"
},
  "geometry": {"coordinates":[130.65759,32.22732],"type":"Point"}
}