{
  "type": "Feature",
  "properties": {
    "gn:admin1_code":"37.0",
    "gn:admin2_code":"1864089.0",
    "gn:asciiname":"Nakanocho",
    "gn:country_code":"JP",
    "gn:dem":251,
    "gn:feature_class":"P",
    "gn:feature_code":"PPLL",
    "gn:name":"Nakanoch\u014d",
    "gn:population":0,
    "gn:timezone":"Asia/Tokyo",
    "iso:country":"JP",
    "name:jpn_x_preferred":[
        "\u4e2d\u91ce\u753a"
    ],
    "name:und_x_variant":[
        "Nakanoch\u014d"
    ],
    "wof:name":"Nakanocho",
    "wof:placetype":"locality"
},
  "geometry": {"coordinates":[138.68791000000002,35.21156],"type":"Point"}
}