{
  "type": "Feature",
  "properties": {
    "gn:admin1_code":"12.0",
    "gn:admin2_code":"2130058.0",
    "gn:admin3_code":"1641.0",
    "gn:asciiname":"Akatsukicho",
    "gn:country_code":"JP",
    "gn:dem":67,
    "gn:feature_class":"P",
    "gn:feature_code":"PPL",
    "gn:name":"Akatsukich\u014d",
    "gn:population":0,
    "gn:timezone":"Asia/Tokyo",
    "iso:country":"JP",
    "name:jpn_x_preferred":[
        "\u6681\u753a"
    ],
    "name:jpn_x_variant":[
        "\u3042\u304b\u3064\u304d\u3061\u3087\u3046",
        "\u30a2\u30ab\u30c4\u30ad\u30c1\u30e7\u30a6"
    ],
    "name:und_x_variant":[
        "Akatsukich\u014d"
    ],
    "wof:name":"Akatsukicho",
    "wof:placetype":"locality"
},
  "geometry": {"coordinates":[143.28099,42.48882],"type":"Point"}
}