{
  "type": "Feature",
  "properties": {
    "gn:admin1_code":"23",
    "gn:admin2_code":"1861901.0",
    "gn:asciiname":"Hirata",
    "gn:country_code":"JP",
    "gn:dem":192,
    "gn:feature_class":"P",
    "gn:feature_code":"PPL",
    "gn:name":"Hirata",
    "gn:population":0,
    "gn:timezone":"Asia/Tokyo",
    "iso:country":"JP",
    "name:deu_x_preferred":[
        "Hirata"
    ],
    "name:fra_x_preferred":[
        "Hirata"
    ],
    "name:jpn_x_preferred":[
        "\u5e73\u7530"
    ],
    "name:kor_x_preferred":[
        "\ud788\ub77c\ud0c0"
    ],
    "wof:name":"Hirata",
    "wof:placetype":"locality"
},
  "geometry": {"coordinates":[136.21355,34.76559],"type":"Point"}
}