{
  "type": "Feature",
  "properties": {
    "gn:admin1_code":"40.0",
    "gn:admin2_code":"1861634.0",
    "gn:asciiname":"Tsukado",
    "gn:country_code":"JP",
    "gn:dem":33,
    "gn:feature_class":"P",
    "gn:feature_code":"PPLL",
    "gn:name":"Tsukado",
    "gn:population":0,
    "gn:timezone":"Asia/Tokyo",
    "iso:country":"JP",
    "name:jpn_x_preferred":[
        "\u585a\u6238"
    ],
    "wof:name":"Tsukado",
    "wof:placetype":"locality"
},
  "geometry": {"coordinates":[139.52148,35.6384],"type":"Point"}
}