{
  "type": "Feature",
  "properties": {
    "gn:admin1_code":"24.0",
    "gn:admin2_code":"2112574.0",
    "gn:asciiname":"Marumori",
    "gn:country_code":"JP",
    "gn:dem":4,
    "gn:feature_class":"P",
    "gn:feature_code":"PPL",
    "gn:name":"Marumori",
    "gn:population":0,
    "gn:timezone":"Asia/Tokyo",
    "iso:country":"JP",
    "name:jpn_x_preferred":[
        "\u4e38\u68ee"
    ],
    "name:jpn_x_variant":[
        "\u307e\u308b\u3082\u308a",
        "\u30de\u30eb\u30e2\u30ea"
    ],
    "wof:name":"Marumori",
    "wof:placetype":"locality"
},
  "geometry": {"coordinates":[141.35667000000001,38.44874],"type":"Point"}
}