{
  "type": "Feature",
  "properties": {
    "gn:admin1_code":"24.0",
    "gn:admin2_code":"2112525.0",
    "gn:asciiname":"Kabasaki",
    "gn:country_code":"JP",
    "gn:dem":5,
    "gn:feature_class":"P",
    "gn:feature_code":"PPLL",
    "gn:name":"Kabasaki",
    "gn:population":0,
    "gn:timezone":"Asia/Tokyo",
    "iso:country":"JP",
    "name:jpn_x_preferred":[
        "\u84b2\u5d0e"
    ],
    "name:und_x_variant":[
        "Kabasagi",
        "Kamasaki",
        "Kabasaki"
    ],
    "wof:name":"Kabasaki",
    "wof:placetype":"locality"
},
  "geometry": {"coordinates":[140.91693999999995,38.07],"type":"Point"}
}