{
  "type": "Feature",
  "properties": {
    "gn:admin1_code":"28",
    "gn:admin2_code":"1848164.0",
    "gn:admin3_code":"29443.0",
    "gn:asciiname":"Tsuchida",
    "gn:cc2":"JP",
    "gn:country_code":"JP",
    "gn:dem":260,
    "gn:feature_class":"P",
    "gn:feature_code":"PPL",
    "gn:name":"Tsuchida",
    "gn:population":0,
    "gn:timezone":"Asia/Tokyo",
    "iso:country":"JP",
    "name:und_x_variant":[
        "Tsutta",
        "Tsuchita",
        "Tsuchida"
    ],
    "wof:name":"Tsuchida",
    "wof:placetype":"locality"
},
  "geometry": {"coordinates":[135.81666999999999,34.38333],"type":"Point"}
}