{
  "type": "Feature",
  "properties": {
    "gn:admin1_code":"24.0",
    "gn:admin2_code":"2112574.0",
    "gn:asciiname":"Mizuoshi",
    "gn:country_code":"JP",
    "gn:dem":4,
    "gn:feature_class":"P",
    "gn:feature_code":"PPL",
    "gn:name":"Mizuoshi",
    "gn:population":0,
    "gn:timezone":"Asia/Tokyo",
    "iso:country":"JP",
    "name:jpn_x_preferred":[
        "\u6c34\u62bc"
    ],
    "name:jpn_x_variant":[
        "\u307f\u305a\u304a\u3057",
        "\u30df\u30ba\u30aa\u30b7"
    ],
    "wof:name":"Mizuoshi",
    "wof:placetype":"locality"
},
  "geometry": {"coordinates":[141.30345,38.44692],"type":"Point"}
}