{
  "type": "Feature",
  "properties": {
    "gn:admin1_code":"4.0",
    "gn:admin2_code":"2112997.0",
    "gn:admin3_code":"12427.0",
    "gn:asciiname":"Uriboyatsu",
    "gn:country_code":"JP",
    "gn:dem":21,
    "gn:feature_class":"P",
    "gn:feature_code":"PPLL",
    "gn:name":"Urib\u014dyatsu",
    "gn:population":0,
    "gn:timezone":"Asia/Tokyo",
    "iso:country":"JP",
    "name:jpn_x_preferred":[
        "\u74dc\u623f\u8c37"
    ],
    "name:jpn_x_variant":[
        "\u3046\u308a\u307c\u3046\u3084\u3064",
        "\u30a6\u30ea\u30dc\u30a6\u30e4\u30c4"
    ],
    "name:und_x_variant":[
        "Urib\u014dyatsu"
    ],
    "wof:name":"Uriboyatsu",
    "wof:placetype":"locality"
},
  "geometry": {"coordinates":[140.28776999999999,35.36562],"type":"Point"}
}