{
  "type": "Feature",
  "properties": {
    "gn:admin1_code":"21.0",
    "gn:admin2_code":"1859490.0",
    "gn:admin3_code":"43403.0",
    "gn:asciiname":"Shimojinnai",
    "gn:country_code":"JP",
    "gn:dem":99,
    "gn:feature_class":"P",
    "gn:feature_code":"PPLL",
    "gn:name":"Shimojinnai",
    "gn:population":0,
    "gn:timezone":"Asia/Tokyo",
    "iso:country":"JP",
    "name:jpn_x_preferred":[
        "\u4e0b\u9663\u5185"
    ],
    "name:jpn_x_variant":[
        "\u3057\u3082\u3058\u3093\u306a\u3044",
        "\u30b7\u30e2\u30b8\u30f3\u30ca\u30a4"
    ],
    "wof:name":"Shimojinnai",
    "wof:placetype":"locality"
},
  "geometry": {"coordinates":[130.87045000000001,32.86155],"type":"Point"}
}