{
  "type": "Feature",
  "properties": {
    "gn:admin1_code":"37.0",
    "gn:admin2_code":"1863526.0",
    "gn:asciiname":"Takigahara",
    "gn:country_code":"JP",
    "gn:dem":633,
    "gn:feature_class":"P",
    "gn:feature_code":"PPLL",
    "gn:name":"Takigahara",
    "gn:population":0,
    "gn:timezone":"Asia/Tokyo",
    "iso:country":"JP",
    "name:jpn_x_preferred":[
        "\u6edd\u30f6\u539f"
    ],
    "wof:name":"Takigahara",
    "wof:placetype":"locality"
},
  "geometry": {"coordinates":[138.88463000000002,35.32097],"type":"Point"}
}