{
  "type": "Feature",
  "properties": {
    "gn:admin1_code":"7.0",
    "gn:admin2_code":"1851269.0",
    "gn:admin3_code":"40609.0",
    "gn:asciiname":"Fushiwara",
    "gn:country_code":"JP",
    "gn:dem":98,
    "gn:feature_class":"P",
    "gn:feature_code":"PPLL",
    "gn:name":"Fushiwara",
    "gn:population":0,
    "gn:timezone":"Asia/Tokyo",
    "iso:country":"JP",
    "name:jpn_x_preferred":[
        "\u4f0f\u539f"
    ],
    "wof:name":"Fushiwara",
    "wof:placetype":"locality"
},
  "geometry": {"coordinates":[130.86951000000002,33.61287],"type":"Point"}
}