{
  "type": "Feature",
  "properties": {
    "gn:admin1_code":"28",
    "gn:admin2_code":"1848164.0",
    "gn:admin3_code":"29442.0",
    "gn:asciiname":"Shimobuchi",
    "gn:country_code":"JP",
    "gn:dem":171,
    "gn:feature_class":"P",
    "gn:feature_code":"PPL",
    "gn:name":"Shimobuchi",
    "gn:population":0,
    "gn:timezone":"Asia/Tokyo",
    "iso:country":"JP",
    "name:jpn_x_preferred":[
        "\u4e0b\u6e15"
    ],
    "wof:name":"Shimobuchi",
    "wof:placetype":"locality"
},
  "geometry": {"coordinates":[135.78710000000001,34.38617],"type":"Point"}
}