{
  "type": "Feature",
  "properties": {
    "gn:admin1_code":"29.0",
    "gn:admin2_code":"1853313.0",
    "gn:asciiname":"Shukunegi-shinden",
    "gn:country_code":"JP",
    "gn:dem":27,
    "gn:feature_class":"P",
    "gn:feature_code":"PPLL",
    "gn:name":"Shukunegi-shinden",
    "gn:population":0,
    "gn:timezone":"Asia/Tokyo",
    "iso:country":"JP",
    "name:jpn_x_preferred":[
        "\u5bbf\u6839\u6728\u65b0\u7530"
    ],
    "wof:name":"Shukunegi-shinden",
    "wof:placetype":"locality"
},
  "geometry": {"coordinates":[138.24741,37.80713],"type":"Point"}
}