{
  "type": "Feature",
  "properties": {
    "gn:admin1_code":"7.0",
    "gn:admin2_code":"1851269.0",
    "gn:admin3_code":"40605.0",
    "gn:asciiname":"Miyaura",
    "gn:country_code":"JP",
    "gn:dem":51,
    "gn:feature_class":"P",
    "gn:feature_code":"PPLL",
    "gn:name":"Miyaura",
    "gn:population":0,
    "gn:timezone":"Asia/Tokyo",
    "iso:country":"JP",
    "name:jpn_x_preferred":[
        "\u5bae\u6d66"
    ],
    "wof:name":"Miyaura",
    "wof:placetype":"locality"
},
  "geometry": {"coordinates":[130.80895000000001,33.61483],"type":"Point"}
}