{
  "type": "Feature",
  "properties": {
    "gn:admin1_code":"21.0",
    "gn:admin2_code":"7413152.0",
    "gn:asciiname":"Furukori",
    "gn:country_code":"JP",
    "gn:dem":18,
    "gn:feature_class":"P",
    "gn:feature_code":"PPLL",
    "gn:name":"Furuk\u014dri",
    "gn:population":0,
    "gn:timezone":"Asia/Tokyo",
    "iso:country":"JP",
    "name:jpn_x_preferred":[
        "\u53e4\u6c37"
    ],
    "name:jpn_x_variant":[
        "\u3075\u308b\u3053\u304a\u308a",
        "\u30d5\u30eb\u30b3\u30aa\u30ea"
    ],
    "name:und_x_variant":[
        "Furuk\u014dri"
    ],
    "wof:name":"Furukori",
    "wof:placetype":"locality"
},
  "geometry": {"coordinates":[130.47689,32.61669000000001],"type":"Point"}
}