{
  "type": "Feature",
  "properties": {
    "gn:admin1_code":"7.0",
    "gn:admin2_code":"7407416.0",
    "gn:asciiname":"Iwano",
    "gn:country_code":"JP",
    "gn:dem":30,
    "gn:feature_class":"P",
    "gn:feature_code":"PPLL",
    "gn:name":"Iwano",
    "gn:population":0,
    "gn:timezone":"Asia/Tokyo",
    "iso:country":"JP",
    "name:deu_x_preferred":[
        "Iwano"
    ],
    "name:jpn_x_preferred":[
        "\u5ca9\u91ce"
    ],
    "wof:name":"Iwano",
    "wof:placetype":"locality"
},
  "geometry": {"coordinates":[130.65038000000001,33.73240999999999],"type":"Point"}
}