{
  "type": "Feature",
  "properties": {
    "gn:admin1_code":"21.0",
    "gn:admin2_code":"7412708.0",
    "gn:admin3_code":"43511.0",
    "gn:asciiname":"Mizonoguchi",
    "gn:country_code":"JP",
    "gn:dem":277,
    "gn:feature_class":"P",
    "gn:feature_code":"PPL",
    "gn:name":"Mizonoguchi",
    "gn:population":0,
    "gn:timezone":"Asia/Tokyo",
    "iso:country":"JP",
    "name:jpn_x_preferred":[
        "\u6e9d\u306e\u53e3"
    ],
    "name:jpn_x_variant":[
        "\u307f\u305e\u306e\u3050\u3061",
        "\u30df\u30be\u30ce\u30b0\u30c1"
    ],
    "wof:name":"Mizonoguchi",
    "wof:placetype":"locality"
},
  "geometry": {"coordinates":[130.82536999999999,32.40161],"type":"Point"}
}