{
  "type": "Feature",
  "properties": {
    "gn:admin1_code":"19.0",
    "gn:admin2_code":"1864091.0",
    "gn:asciiname":"Nishimatano",
    "gn:country_code":"JP",
    "gn:dem":10,
    "gn:feature_class":"P",
    "gn:feature_code":"PPL",
    "gn:name":"Nishimatano",
    "gn:population":0,
    "gn:timezone":"Asia/Tokyo",
    "iso:country":"JP",
    "name:jpn_x_preferred":[
        "\u897f\u4fe3\u91ce"
    ],
    "wof:name":"Nishimatano",
    "wof:placetype":"locality"
},
  "geometry": {"coordinates":[139.48837,35.37344],"type":"Point"}
}