{
  "type": "Feature",
  "properties": {
    "gn:admin1_code":"4.0",
    "gn:admin2_code":"1859468.0",
    "gn:asciiname":"Shoko",
    "gn:country_code":"JP",
    "gn:dem":38,
    "gn:feature_class":"P",
    "gn:feature_code":"PPL",
    "gn:name":"Sh\u014dk\u014d",
    "gn:population":0,
    "gn:timezone":"Asia/Tokyo",
    "iso:country":"JP",
    "name:ceb_x_preferred":[
        "Shoko"
    ],
    "name:deu_x_preferred":[
        "Shoko"
    ],
    "name:fra_x_preferred":[
        "Shoko"
    ],
    "name:ido_x_preferred":[
        "Shoko"
    ],
    "name:jpn_x_preferred":[
        "\u5c0f\u9999"
    ],
    "name:jpn_x_variant":[
        "\u3057\u3087\u3046\u3053\u3046",
        "\u30b7\u30e7\u30a6\u30b3\u30a6",
        "Shoko"
    ],
    "name:spa_x_preferred":[
        "Shoko"
    ],
    "name:und_x_variant":[
        "Sh\u014dk\u014d"
    ],
    "wof:name":"Shoko",
    "wof:placetype":"locality"
},
  "geometry": {"coordinates":[139.90039999999999,35.3055],"type":"Point"}
}