{
  "type": "Feature",
  "properties": {
    "gn:admin1_code":"19.0",
    "gn:admin2_code":"1864928.0",
    "gn:asciiname":"Katahira",
    "gn:country_code":"JP",
    "gn:dem":19,
    "gn:feature_class":"P",
    "gn:feature_code":"PPLL",
    "gn:name":"Katahira",
    "gn:population":0,
    "gn:timezone":"Asia/Tokyo",
    "iso:country":"JP",
    "name:jpn_x_preferred":[
        "\u7247\u5e73"
    ],
    "wof:name":"Katahira",
    "wof:placetype":"locality"
},
  "geometry": {"coordinates":[139.35121000000001,35.42268],"type":"Point"}
}