{
  "type": "Feature",
  "properties": {
    "gn:admin1_code":"4.0",
    "gn:admin2_code":"9062338.0",
    "gn:asciiname":"Kamiueno",
    "gn:country_code":"JP",
    "gn:dem":149,
    "gn:feature_class":"P",
    "gn:feature_code":"PPL",
    "gn:name":"Kamiueno",
    "gn:population":0,
    "gn:timezone":"Asia/Tokyo",
    "iso:country":"JP",
    "name:jpn_x_preferred":[
        "\u4e0a\u690d\u91ce"
    ],
    "name:jpn_x_variant":[
        "\u304b\u307f\u3046\u3048\u306e",
        "\u30ab\u30df\u30a6\u30a8\u30ce"
    ],
    "wof:name":"Kamiueno",
    "wof:placetype":"locality"
},
  "geometry": {"coordinates":[140.22481000000002,35.15204],"type":"Point"}
}