{
  "type": "Feature",
  "properties": {
    "gn:admin1_code":"41",
    "gn:admin2_code":"7392260.0",
    "gn:admin3_code":"31302.0",
    "gn:asciiname":"Uradome",
    "gn:country_code":"JP",
    "gn:dem":6,
    "gn:feature_class":"P",
    "gn:feature_code":"PPL",
    "gn:name":"Uradome",
    "gn:population":0,
    "gn:timezone":"Asia/Tokyo",
    "iso:country":"JP",
    "name:und_x_variant":[
        "Uratomi",
        "Uradome"
    ],
    "wof:name":"Uradome",
    "wof:placetype":"locality"
},
  "geometry": {"coordinates":[134.33053000000001,35.58523],"type":"Point"}
}