{
  "type": "Feature",
  "properties": {
    "gn:admin1_code":"43.0",
    "gn:admin2_code":"7411113.0",
    "gn:asciiname":"Nakabusa",
    "gn:country_code":"JP",
    "gn:dem":24,
    "gn:feature_class":"P",
    "gn:feature_code":"PPL",
    "gn:name":"Nakabusa",
    "gn:population":0,
    "gn:timezone":"Asia/Tokyo",
    "iso:country":"JP",
    "name:jpn_x_preferred":[
        "\u4e2d\u8feb"
    ],
    "wof:name":"Nakabusa",
    "wof:placetype":"locality"
},
  "geometry": {"coordinates":[135.31704999999999,34.26237],"type":"Point"}
}