{
  "type": "Feature",
  "properties": {
    "gn:admin1_code":"18.0",
    "gn:admin2_code":"1865649.0",
    "gn:admin3_code":"46452.0",
    "gn:asciiname":"Kakinoki",
    "gn:country_code":"JP",
    "gn:dem":212,
    "gn:feature_class":"P",
    "gn:feature_code":"PPLL",
    "gn:name":"Kakinoki",
    "gn:population":0,
    "gn:timezone":"Asia/Tokyo",
    "iso:country":"JP",
    "name:jpn_x_preferred":[
        "\u67ff\u6728"
    ],
    "name:jpn_x_variant":[
        "\u304b\u304d\u306e\u304d",
        "\u30ab\u30ad\u30ce\u30ad"
    ],
    "wof:name":"Kakinoki",
    "wof:placetype":"locality"
},
  "geometry": {"coordinates":[130.74642,32.00715],"type":"Point"}
}