{
  "type": "Feature",
  "properties": {
    "gn:admin1_code":"11",
    "gn:admin2_code":"1857327.0",
    "gn:asciiname":"Kainocho",
    "gn:cc2":"JP",
    "gn:country_code":"JP",
    "gn:dem":2,
    "gn:feature_class":"P",
    "gn:feature_code":"PPL",
    "gn:name":"Kainoch\u014d",
    "gn:population":0,
    "gn:timezone":"Asia/Tokyo",
    "iso:country":"JP",
    "name:und_x_variant":[
        "Kaino",
        "Kainoch\u014d"
    ],
    "wof:name":"Kainocho",
    "wof:placetype":"locality"
},
  "geometry": {"coordinates":[133.08333000000002,34.38333],"type":"Point"}
}