{
  "type": "Feature",
  "properties": {
    "gn:admin1_code":"36",
    "gn:admin2_code":"7392549.0",
    "gn:admin3_code":"32505.0",
    "gn:asciiname":"Muikaichi",
    "gn:country_code":"JP",
    "gn:dem":338,
    "gn:feature_class":"P",
    "gn:feature_code":"PPL",
    "gn:name":"Muikaichi",
    "gn:population":0,
    "gn:timezone":"Asia/Tokyo",
    "iso:country":"JP",
    "name:jpn_x_preferred":[
        "\u516d\u65e5\u753a"
    ],
    "wof:name":"Muikaichi",
    "wof:placetype":"locality"
},
  "geometry": {"coordinates":[131.93288000000001,34.35590999999999],"type":"Point"}
}