{
  "type": "Feature",
  "properties": {
    "gn:admin1_code":"26.0",
    "gn:admin2_code":"1857516.0",
    "gn:asciiname":"Furuyado",
    "gn:country_code":"JP",
    "gn:dem":1041,
    "gn:feature_class":"P",
    "gn:feature_code":"PPL",
    "gn:name":"Furuyado",
    "gn:population":0,
    "gn:timezone":"Asia/Tokyo",
    "iso:country":"JP",
    "name:jpn_x_preferred":[
        "\u53e4\u5bbf"
    ],
    "wof:name":"Furuyado",
    "wof:placetype":"locality"
},
  "geometry": {"coordinates":[137.6859,36.09386],"type":"Point"}
}