{
  "type": "Feature",
  "properties": {
    "gn:country":"JP",
    "gn:fcode":"PPLX",
    "gn:pop":375339,
    "iso:country":"JP",
    "name:jpn_x_preferred":[
        "\u6e4a"
    ],
    "name:unk_x_variant":[
        "Shink\u014dmachi"
    ],
    "qs:name":"Shimminatoch\u014d",
    "qs:photos_9r":0,
    "qs:photos_sr":0,
    "qs:pop_sr":"10",
    "wof:name":"Shimminatoch\u014d",
    "wof:placetype":"neighbourhood",
    "wof:population":375339
},
  "geometry": {"coordinates":[135.19999999999999,34.18333],"type":"Point"}
}