{
  "type": "Feature",
  "properties": {
    "gn:admin1_code":"45.0",
    "gn:admin2_code":"1852222.0",
    "gn:asciiname":"Hikoshima-oimachi",
    "gn:country_code":"JP",
    "gn:dem":53,
    "gn:feature_class":"P",
    "gn:feature_code":"PPL",
    "gn:name":"Hikoshima-oimachi",
    "gn:population":0,
    "gn:timezone":"Asia/Tokyo",
    "iso:country":"JP",
    "name:jpn_x_preferred":[
        "\u5f66\u5cf6\u8001\u753a"
    ],
    "wof:name":"Hikoshima-oimachi",
    "wof:placetype":"locality"
},
  "geometry": {"coordinates":[130.91267999999999,33.94836],"type":"Point"}
}