{
  "type": "Feature",
  "properties": {
    "gn:admin1_code":"15",
    "gn:admin2_code":"7467880.0",
    "gn:asciiname":"Takamatsu",
    "gn:country_code":"JP",
    "gn:dem":18,
    "gn:feature_class":"P",
    "gn:feature_code":"PPL",
    "gn:name":"Takamatsu",
    "gn:population":0,
    "gn:timezone":"Asia/Tokyo",
    "iso:country":"JP",
    "name:ceb_x_preferred":[
        "Takamatsu"
    ],
    "name:deu_x_preferred":[
        "Takamatsu"
    ],
    "name:fra_x_preferred":[
        "Takamatsu"
    ],
    "name:jpn_x_preferred":[
        "\u9ad8\u677e"
    ],
    "name:mlg_x_preferred":[
        "Takamatsu"
    ],
    "name:rus_x_preferred":[
        "\u0422\u0430\u043a\u0430\u043c\u0430\u0446\u0443"
    ],
    "name:swe_x_preferred":[
        "Takamatsu"
    ],
    "name:ukr_x_preferred":[
        "\u0422\u0430\u043a\u0430\u043c\u0430\u0446\u0443"
    ],
    "wof:name":"Takamatsu",
    "wof:placetype":"locality"
},
  "geometry": {"coordinates":[136.71666999999999,36.76667],"type":"Point"}
}