{
  "type": "Feature",
  "properties": {
    "gn:admin1_code":"24.0",
    "gn:admin2_code":"2112261.0",
    "gn:asciiname":"Asane",
    "gn:country_code":"JP",
    "gn:dem":10,
    "gn:feature_class":"P",
    "gn:feature_code":"PPL",
    "gn:name":"Asane",
    "gn:population":0,
    "gn:timezone":"Asia/Tokyo",
    "iso:country":"JP",
    "name:jpn_x_preferred":[
        "\u6d45\u6839"
    ],
    "name:jpn_x_variant":[
        "\u3042\u3055\u306d",
        "\u30a2\u30b5\u30cd"
    ],
    "wof:name":"Asane",
    "wof:placetype":"locality"
},
  "geometry": {"coordinates":[141.61324999999999,38.85135],"type":"Point"}
}