{
  "type": "Feature",
  "properties": {
    "gn:admin1_code":"16.0",
    "gn:admin2_code":"2129400.0",
    "gn:admin3_code":"3501.0",
    "gn:asciiname":"Komagi",
    "gn:country_code":"JP",
    "gn:dem":204,
    "gn:feature_class":"P",
    "gn:feature_code":"PPL",
    "gn:name":"Komagi",
    "gn:population":0,
    "gn:timezone":"Asia/Tokyo",
    "iso:country":"JP",
    "name:jpn_x_preferred":[
        "\u99d2\u6728"
    ],
    "name:jpn_x_variant":[
        "\u3053\u307e\u304e",
        "\u30b3\u30de\u30ae"
    ],
    "wof:name":"Komagi",
    "wof:placetype":"locality"
},
  "geometry": {"coordinates":[141.39773,40.31062],"type":"Point"}
}