{
  "type": "Feature",
  "properties": {
    "gn:admin1_code":"34.0",
    "gn:admin2_code":"7458572.0",
    "gn:admin3_code":"11385.0",
    "gn:asciiname":"Omido",
    "gn:country_code":"JP",
    "gn:dem":78,
    "gn:feature_class":"P",
    "gn:feature_code":"PPL",
    "gn:name":"\u014cmid\u014d",
    "gn:population":0,
    "gn:timezone":"Asia/Tokyo",
    "iso:country":"JP",
    "name:jpn_x_preferred":[
        "\u5927\u5fa1\u5802"
    ],
    "name:und_x_variant":[
        "\u014cmid\u014d"
    ],
    "wof:name":"Omido",
    "wof:placetype":"locality"
},
  "geometry": {"coordinates":[139.12537,36.2289],"type":"Point"}
}