{
  "type": "Feature",
  "properties": {
    "gn:admin1_code":"23.0",
    "gn:admin2_code":"1859297.0",
    "gn:admin3_code":"24543.0",
    "gn:asciiname":"Iguma",
    "gn:country_code":"JP",
    "gn:dem":18,
    "gn:feature_class":"P",
    "gn:feature_code":"PPL",
    "gn:name":"Iguma",
    "gn:population":0,
    "gn:timezone":"Asia/Tokyo",
    "iso:country":"JP",
    "name:jpn_x_preferred":[
        "\u751f\u718a"
    ],
    "wof:name":"Iguma",
    "wof:placetype":"locality"
},
  "geometry": {"coordinates":[136.26158000000001,34.12333],"type":"Point"}
}