{
  "type": "Feature",
  "properties": {
    "gn:admin1_code":"21.0",
    "gn:admin2_code":"1864975.0",
    "gn:admin3_code":"43424.0",
    "gn:asciiname":"Kurabaru",
    "gn:country_code":"JP",
    "gn:dem":448,
    "gn:feature_class":"P",
    "gn:feature_code":"PPLL",
    "gn:name":"Kurabaru",
    "gn:population":0,
    "gn:timezone":"Asia/Tokyo",
    "iso:country":"JP",
    "name:jpn_x_preferred":[
        "\u8535\u539f"
    ],
    "name:jpn_x_variant":[
        "\u304f\u3089\u3070\u308b",
        "\u30af\u30e9\u30d0\u30eb"
    ],
    "wof:name":"Kurabaru",
    "wof:placetype":"locality"
},
  "geometry": {"coordinates":[131.06217000000001,33.11906],"type":"Point"}
}