{
  "type": "Feature",
  "properties": {
    "gn:admin1_code":"21.0",
    "gn:admin2_code":"7413150.0",
    "gn:asciiname":"Taira",
    "gn:country_code":"JP",
    "gn:dem":330,
    "gn:feature_class":"P",
    "gn:feature_code":"PPLL",
    "gn:name":"Taira",
    "gn:population":0,
    "gn:timezone":"Asia/Tokyo",
    "iso:country":"JP",
    "name:jpn_x_preferred":[
        "\u5e73"
    ],
    "name:jpn_x_variant":[
        "\u305f\u3044\u3089",
        "\u30bf\u30a4\u30e9"
    ],
    "wof:name":"Taira",
    "wof:placetype":"locality"
},
  "geometry": {"coordinates":[130.79681000000002,33.07358],"type":"Point"}
}