{
  "type": "Feature",
  "properties": {
    "gn:admin1_code":"6.0",
    "gn:admin2_code":"7467387.0",
    "gn:asciiname":"Maruokacho-yoko",
    "gn:country_code":"JP",
    "gn:dem":27,
    "gn:feature_class":"P",
    "gn:feature_code":"PPL",
    "gn:name":"Maruokach\u014d-y\u014dk\u014d",
    "gn:population":0,
    "gn:timezone":"Asia/Tokyo",
    "iso:country":"JP",
    "name:jpn_x_preferred":[
        "\u4e38\u5ca1\u753a\u4e0e\u6cb3"
    ],
    "name:und_x_variant":[
        "Maruokach\u014d-y\u014dk\u014d"
    ],
    "wof:name":"Maruokacho-yoko",
    "wof:placetype":"locality"
},
  "geometry": {"coordinates":[136.28887,36.15365],"type":"Point"}
}