{
  "type": "Feature",
  "properties": {
    "gn:country":"JP",
    "gn:fcode":"ADM3",
    "gn:population":0,
    "iso:country":"JP",
    "name:eng_x_preferred":[
        "Sh\u014dnai"
    ],
    "name:eng_x_variant":[
        "Sh\u014dnai-machi"
    ],
    "name:jpn_x_preferred":[
        "\u5e84\u5185\u753a"
    ],
    "name:jpn_x_variant":[
        "\u3057\u3087\u3046\u306a\u3044\u307e\u3061"
    ],
    "name:und_x_variant":[
        "Sh\u014dnai Machi"
    ],
    "qs:name":"Sh\u014dnai-machi",
    "qs:photos_9r":0,
    "qs:photos_sr":0,
    "qs:pop_sr":"0",
    "wof:name":"Sh\u014dnai",
    "wof:placetype":"localadmin",
    "wof:population":0
},
  "geometry": {"coordinates":[140.001,38.70554],"type":"Point"}
}