{
  "type": "Feature",
  "properties": {
    "gn:admin1_code":"12.0",
    "gn:admin2_code":"7428090.0",
    "gn:admin3_code":"1664.0",
    "gn:asciiname":"Awa",
    "gn:cc2":"JP",
    "gn:country_code":"JP",
    "gn:dem":31,
    "gn:feature_class":"P",
    "gn:feature_code":"PPL",
    "gn:name":"Awa",
    "gn:population":0,
    "gn:timezone":"Asia/Tokyo",
    "iso:country":"JP",
    "name:und_x_variant":[
        "Awa-dantai",
        "Awa"
    ],
    "wof:name":"Awa",
    "wof:placetype":"locality"
},
  "geometry": {"coordinates":[144.41666999999995,43.25],"type":"Point"}
}