{
  "type": "Feature",
  "properties": {
    "gn:admin1_code":"26.0",
    "gn:admin2_code":"1862841.0",
    "gn:admin3_code":"20450.0",
    "gn:asciiname":"Kamitakeda",
    "gn:country_code":"JP",
    "gn:dem":692,
    "gn:feature_class":"P",
    "gn:feature_code":"PPL",
    "gn:name":"Kamitakeda",
    "gn:population":0,
    "gn:timezone":"Asia/Tokyo",
    "iso:country":"JP",
    "name:jpn_x_preferred":[
        "\u4e0a\u7af9\u7530"
    ],
    "wof:name":"Kamitakeda",
    "wof:placetype":"locality"
},
  "geometry": {"coordinates":[137.87481,36.17605],"type":"Point"}
}