{
  "type": "Feature",
  "properties": {
    "gn:admin1_code":"21.0",
    "gn:admin2_code":"7412706.0",
    "gn:admin3_code":"43447.0",
    "gn:asciiname":"Motokashiwa",
    "gn:country_code":"JP",
    "gn:dem":548,
    "gn:feature_class":"P",
    "gn:feature_code":"PPLL",
    "gn:name":"Motokashiwa",
    "gn:population":0,
    "gn:timezone":"Asia/Tokyo",
    "iso:country":"JP",
    "name:jpn_x_preferred":[
        "\u5143\u67cf"
    ],
    "name:jpn_x_variant":[
        "\u3082\u3068\u304b\u3057\u308f",
        "\u30e2\u30c8\u30ab\u30b7\u30ef"
    ],
    "wof:name":"Motokashiwa",
    "wof:placetype":"locality"
},
  "geometry": {"coordinates":[131.18611000000001,32.74363],"type":"Point"}
}