{
  "type": "Feature",
  "properties": {
    "gn:admin1_code":"21.0",
    "gn:admin2_code":"1858418.0",
    "gn:admin3_code":"43101.0",
    "gn:asciiname":"Honjomachi",
    "gn:country_code":"JP",
    "gn:dem":8,
    "gn:feature_class":"P",
    "gn:feature_code":"PPL",
    "gn:name":"Honj\u014dmachi",
    "gn:population":0,
    "gn:timezone":"Asia/Tokyo",
    "iso:country":"JP",
    "name:jpn_x_preferred":[
        "\u672c\u8358\u753a"
    ],
    "name:jpn_x_variant":[
        "\u307b\u3093\u3058\u3087\u3046\u307e\u3061",
        "\u30db\u30f3\u30b8\u30e7\u30a6\u30de\u30c1"
    ],
    "name:und_x_variant":[
        "Honj\u014dmachi"
    ],
    "wof:name":"Honjomachi",
    "wof:placetype":"locality"
},
  "geometry": {"coordinates":[130.7022,32.78651],"type":"Point"}
}