{
  "type": "Feature",
  "properties": {
    "gn:admin1_code":"21.0",
    "gn:admin2_code":"1864975.0",
    "gn:admin3_code":"43423.0",
    "gn:asciiname":"Koga",
    "gn:country_code":"JP",
    "gn:dem":563,
    "gn:feature_class":"P",
    "gn:feature_code":"PPLL",
    "gn:name":"Koga",
    "gn:population":0,
    "gn:timezone":"Asia/Tokyo",
    "iso:country":"JP",
    "name:jpn_x_preferred":[
        "\u53e4\u8cc0"
    ],
    "name:jpn_x_variant":[
        "\u3053\u304c",
        "\u30b3\u30ac"
    ],
    "wof:name":"Koga",
    "wof:placetype":"locality"
},
  "geometry": {"coordinates":[131.03818000000001,33.07451],"type":"Point"}
}