{
  "type": "Feature",
  "properties": {
    "gn:admin1_code":"21.0",
    "gn:admin2_code":"1864975.0",
    "gn:admin3_code":"43423.0",
    "gn:asciiname":"Koga",
    "gn:country_code":"JP",
    "gn:dem":563,
    "gn:feature_class":"P",
    "gn:feature_code":"PPLL",
    "gn:name":"Koga",
    "gn:population":0,
    "gn:timezone":"Asia/Tokyo",
    "iso:country":"JP",
    "name:cat_x_preferred":[
        "Koga"
    ],
    "name:ceb_x_preferred":[
        "Koga"
    ],
    "name:deu_x_preferred":[
        "Koga"
    ],
    "name:fin_x_preferred":[
        "Koga"
    ],
    "name:fra_x_preferred":[
        "Koga"
    ],
    "name:ita_x_preferred":[
        "Koga"
    ],
    "name:jpn_x_preferred":[
        "\u53e4\u8cc0"
    ],
    "name:jpn_x_variant":[
        "\u3053\u304c",
        "\u30b3\u30ac"
    ],
    "name:kor_x_preferred":[
        "\uace0\uac00\uc2dc"
    ],
    "name:nld_x_preferred":[
        "Koga"
    ],
    "name:pol_x_preferred":[
        "Koga"
    ],
    "name:por_x_preferred":[
        "Koga"
    ],
    "name:ron_x_preferred":[
        "Koga"
    ],
    "name:rus_x_preferred":[
        "\u041a\u043e\u0433\u0430"
    ],
    "name:sco_x_preferred":[
        "Koga"
    ],
    "name:slk_x_preferred":[
        "Koga"
    ],
    "name:spa_x_preferred":[
        "Koga"
    ],
    "name:swe_x_preferred":[
        "Koga"
    ],
    "name:ukr_x_preferred":[
        "\u041a\u043e\u0491\u0430"
    ],
    "wof:name":"Koga",
    "wof:placetype":"locality"
},
  "geometry": {"coordinates":[131.03818000000001,33.07451],"type":"Point"}
}