{
  "type": "Feature",
  "properties": {
    "gn:admin1_code":"3.0",
    "gn:admin2_code":"2130225.0",
    "gn:asciiname":"Yanagimachi",
    "gn:country_code":"JP",
    "gn:dem":11,
    "gn:feature_class":"P",
    "gn:feature_code":"PPL",
    "gn:name":"Yanagimachi",
    "gn:population":0,
    "gn:timezone":"Asia/Tokyo",
    "iso:country":"JP",
    "name:jpn_x_preferred":[
        "\u67f3\u753a"
    ],
    "name:jpn_x_variant":[
        "\u3084\u306a\u304e\u307e\u3061",
        "\u30e4\u30ca\u30ae\u30de\u30c1"
    ],
    "wof:name":"Yanagimachi",
    "wof:placetype":"locality"
},
  "geometry": {"coordinates":[140.44183000000001,40.80647],"type":"Point"}
}