{
  "type": "Feature",
  "properties": {
    "gn:admin1_code":"21.0",
    "gn:admin2_code":"1865358.0",
    "gn:asciiname":"Yokogashira",
    "gn:country_code":"JP",
    "gn:dem":36,
    "gn:feature_class":"P",
    "gn:feature_code":"PPLL",
    "gn:name":"Yokogashira",
    "gn:population":0,
    "gn:timezone":"Asia/Tokyo",
    "iso:country":"JP",
    "name:jpn_x_preferred":[
        "\u6a2a\u982d"
    ],
    "name:jpn_x_variant":[
        "\u3088\u3053\u304c\u3057\u3089",
        "\u30e8\u30b3\u30ac\u30b7\u30e9"
    ],
    "wof:name":"Yokogashira",
    "wof:placetype":"locality"
},
  "geometry": {"coordinates":[130.1876,32.41125],"type":"Point"}
}