{
  "type": "Feature",
  "properties": {
    "gn:admin1_code":"7.0",
    "gn:admin2_code":"7406950.0",
    "gn:admin3_code":"40625.0",
    "gn:asciiname":"Tanaka",
    "gn:country_code":"JP",
    "gn:dem":19,
    "gn:feature_class":"P",
    "gn:feature_code":"PPL",
    "gn:name":"Tanaka",
    "gn:population":0,
    "gn:timezone":"Asia/Tokyo",
    "iso:country":"JP",
    "name:epo_x_preferred":[
        "Tanaka"
    ],
    "name:jpn_x_preferred":[
        "\u7530\u4e2d"
    ],
    "name:spa_x_preferred":[
        "Tanaka"
    ],
    "name:ukr_x_preferred":[
        "\u0422\u0430\u043d\u0430\u043a\u0430"
    ],
    "wof:name":"Tanaka",
    "wof:placetype":"locality"
},
  "geometry": {"coordinates":[130.99404999999999,33.69032],"type":"Point"}
}