{
  "type": "Feature",
  "properties": {
    "gn:admin1_code":"3.0",
    "gn:admin2_code":"2130088.0",
    "gn:admin3_code":"2307.0",
    "gn:asciiname":"Kamiutetsu",
    "gn:country_code":"JP",
    "gn:dem":30,
    "gn:feature_class":"P",
    "gn:feature_code":"PPL",
    "gn:name":"Kamiutetsu",
    "gn:population":0,
    "gn:timezone":"Asia/Tokyo",
    "iso:country":"JP",
    "name:jpn_x_preferred":[
        "\u4e0a\u5b87\u9244"
    ],
    "name:jpn_x_variant":[
        "\u304b\u307f\u3046\u3066\u3064",
        "\u30ab\u30df\u30a6\u30c6\u30c4"
    ],
    "wof:name":"Kamiutetsu",
    "wof:placetype":"locality"
},
  "geometry": {"coordinates":[140.39291,41.23525],"type":"Point"}
}