{
  "type": "Feature",
  "properties": {
    "iso:country":"JP",
    "qs:name":"\u793c\u6587\u753a",
    "qs:name_adm0":"\u65e5\u672c",
    "qs:name_adm1":"\u5317\u6d77\u9053",
    "qs:photos":564,
    "qs:photos_1k":114,
    "qs:photos_9k":2,
    "qs:photos_9r":5,
    "qs:photos_all":564,
    "qs:photos_sr":8,
    "qs:placetype":"Town",
    "qs:pop_sr":"0",
    "wof:name":"\u793c\u6587\u753a",
    "wof:placetype":"locality"
},
  "geometry": {"coordinates":[141.025487,45.3120755],"type":"Point"}
}