{
  "type": "Feature",
  "properties": {
    "gn:admin1_code":"17",
    "gn:admin2_code":"1851095.0",
    "gn:asciiname":"Kozai-honmachi",
    "gn:country_code":"JP",
    "gn:dem":8,
    "gn:feature_class":"P",
    "gn:feature_code":"PPL",
    "gn:name":"K\u014dzai-honmachi",
    "gn:population":0,
    "gn:timezone":"Asia/Tokyo",
    "iso:country":"JP",
    "name:jpn_x_preferred":[
        "\u9999\u897f\u672c\u753a"
    ],
    "name:und_x_variant":[
        "Kosai",
        "K\u014dzai",
        "K\u014dzai-honmachi"
    ],
    "wof:name":"Kozai-honmachi",
    "wof:placetype":"locality"
},
  "geometry": {"coordinates":[134.00128000000001,34.34949],"type":"Point"}
}