{
  "type": "Feature",
  "properties": {
    "gn:admin1_code":"23",
    "gn:admin2_code":"1848370.0",
    "gn:asciiname":"Oiwake",
    "gn:country_code":"JP",
    "gn:dem":3,
    "gn:feature_class":"P",
    "gn:feature_code":"PPL",
    "gn:name":"Oiwake",
    "gn:population":0,
    "gn:timezone":"Asia/Tokyo",
    "iso:country":"JP",
    "wof:name":"Oiwake",
    "wof:placetype":"locality"
},
  "geometry": {"coordinates":[136.59999999999999,34.93333],"type":"Point"}
}