{
  "type": "Feature",
  "properties": {
    "gn:admin1_code":"3.0",
    "gn:admin2_code":"2129754.0",
    "gn:admin3_code":"2412.0",
    "gn:asciiname":"Fujigamori",
    "gn:country_code":"JP",
    "gn:dem":4,
    "gn:feature_class":"P",
    "gn:feature_code":"PPL",
    "gn:name":"Fujigamori",
    "gn:population":0,
    "gn:timezone":"Asia/Tokyo",
    "iso:country":"JP",
    "name:jpn_x_preferred":[
        "\u85e4\u30f6\u68ee"
    ],
    "name:jpn_x_variant":[
        "\u3075\u3058\u304c\u3082\u308a",
        "\u30d5\u30b8\u30ac\u30e2\u30ea"
    ],
    "wof:name":"Fujigamori",
    "wof:placetype":"locality"
},
  "geometry": {"coordinates":[141.44415000000001,40.59983],"type":"Point"}
}