{
  "type": "Feature",
  "properties": {
    "gn:admin1_code":"22.0",
    "gn:admin2_code":"1859202.0",
    "gn:asciiname":"Yamashirocho-kabata",
    "gn:country_code":"JP",
    "gn:dem":26,
    "gn:feature_class":"P",
    "gn:feature_code":"PPL",
    "gn:name":"Yamashiroch\u014d-kabata",
    "gn:population":0,
    "gn:timezone":"Asia/Tokyo",
    "iso:country":"JP",
    "name:jpn_x_preferred":[
        "\u5c71\u57ce\u753a\u7dba\u7530"
    ],
    "name:und_x_variant":[
        "Yamashiroch\u014d-kabata"
    ],
    "wof:name":"Yamashirocho-kabata",
    "wof:placetype":"locality"
},
  "geometry": {"coordinates":[135.81066999999999,34.78791],"type":"Point"}
}