{
  "type": "Feature",
  "properties": {
    "gn:admin1_code":"30",
    "gn:admin2_code":"7279571.0",
    "gn:asciiname":"Kunimimachi-taketazu",
    "gn:country_code":"JP",
    "gn:dem":11,
    "gn:feature_class":"P",
    "gn:feature_code":"PPL",
    "gn:name":"Kunimimachi-taketazu",
    "gn:population":0,
    "gn:timezone":"Asia/Tokyo",
    "iso:country":"JP",
    "name:jpn_x_preferred":[
        "\u56fd\u898b\u753a\u7af9\u7530\u6d25"
    ],
    "name:und_x_variant":[
        "Takedatsu",
        "Taketazu",
        "Taketatsu",
        "Takedazu",
        "Kunimimachi-taketazu"
    ],
    "wof:name":"Kunimimachi-taketazu",
    "wof:placetype":"locality"
},
  "geometry": {"coordinates":[131.55784,33.66856],"type":"Point"}
}