{
  "type": "Feature",
  "properties": {
    "gn:country":"JP",
    "gn:fcode":"ADM3",
    "gn:population":0,
    "iso:country":"JP",
    "name:eng_x_preferred":[
        "Misato"
    ],
    "name:eng_x_variant":[
        "Misato-machi"
    ],
    "name:jpn_x_preferred":[
        "\u7f8e\u91cc\u753a"
    ],
    "name:jpn_x_variant":[
        "\u307f\u3055\u3068\u307e\u3061"
    ],
    "name:und_x_variant":[
        "Misato Machi"
    ],
    "qs:name":"Misato-machi",
    "qs:photos_9r":0,
    "qs:photos_sr":0,
    "qs:pop_sr":"0",
    "wof:name":"Misato",
    "wof:placetype":"localadmin",
    "wof:population":0
},
  "geometry": {"coordinates":[141.09297000000001,38.52016],"type":"Point"}
}