{
  "type": "Feature",
  "properties": {
    "gn:admin1_code":"21.0",
    "gn:admin2_code":"7413151.0",
    "gn:asciiname":"Taibaru",
    "gn:country_code":"JP",
    "gn:dem":31,
    "gn:feature_class":"P",
    "gn:feature_code":"PPLL",
    "gn:name":"Taibaru",
    "gn:population":0,
    "gn:timezone":"Asia/Tokyo",
    "iso:country":"JP",
    "name:jpn_x_preferred":[
        "\u592a\u539f"
    ],
    "name:jpn_x_variant":[
        "\u305f\u3044\u3070\u308b",
        "\u30bf\u30a4\u30d0\u30eb"
    ],
    "wof:name":"Taibaru",
    "wof:placetype":"locality"
},
  "geometry": {"coordinates":[130.40236999999999,32.45984],"type":"Point"}
}