{
  "type": "Feature",
  "properties": {
    "gn:admin1_code":"10.0",
    "gn:admin2_code":"1860108.0",
    "gn:admin3_code":"10382.0",
    "gn:asciiname":"Takakura",
    "gn:country_code":"JP",
    "gn:dem":502,
    "gn:feature_class":"P",
    "gn:feature_code":"PPLL",
    "gn:name":"Takakura",
    "gn:population":0,
    "gn:timezone":"Asia/Tokyo",
    "iso:country":"JP",
    "name:deu_x_preferred":[
        "Takakura"
    ],
    "name:jpn_x_preferred":[
        "\u9ad8\u5009"
    ],
    "name:kor_x_preferred":[
        "\ub2e4\uce74\ucfe0\ub77c"
    ],
    "name:rus_x_preferred":[
        "\u0422\u0430\u043a\u0430\u043a\u0443\u0440\u0430"
    ],
    "wof:name":"Takakura",
    "wof:placetype":"locality"
},
  "geometry": {"coordinates":[138.80251000000001,36.18523],"type":"Point"}
}