{
  "type": "Feature",
  "properties": {
    "gn:admin1_code":"13",
    "gn:admin2_code":"1862022.0",
    "gn:admin3_code":"28464.0",
    "gn:asciiname":"Ikaruga",
    "gn:country_code":"JP",
    "gn:dem":17,
    "gn:feature_class":"P",
    "gn:feature_code":"PPL",
    "gn:name":"Ikaruga",
    "gn:population":0,
    "gn:timezone":"Asia/Tokyo",
    "iso:country":"JP",
    "name:deu_x_preferred":[
        "Ikaruga"
    ],
    "name:fra_x_preferred":[
        "Ikaruga"
    ],
    "name:ita_x_preferred":[
        "Ikaruga"
    ],
    "name:jpn_x_preferred":[
        "\u9d64"
    ],
    "name:jpn_x_variant":[
        "\u6591\u9ce9"
    ],
    "name:nld_x_preferred":[
        "Ikaruga"
    ],
    "name:por_x_preferred":[
        "Ikaruga"
    ],
    "name:rus_x_preferred":[
        "Ikaruga"
    ],
    "name:spa_x_preferred":[
        "Ikaruga"
    ],
    "name:swe_x_preferred":[
        "Ikaruga"
    ],
    "name:ukr_x_preferred":[
        "Ikaruga"
    ],
    "name:wuu_x_preferred":[
        "\u6591\u9e20"
    ],
    "name:zho_x_preferred":[
        "\u6591\u9ce9"
    ],
    "wof:name":"Ikaruga",
    "wof:placetype":"locality"
},
  "geometry": {"coordinates":[134.57803000000001,34.83475],"type":"Point"}
}