{
  "type": "Feature",
  "properties": {
    "gn:admin1_code":"4.0",
    "gn:admin2_code":"2112386.0",
    "gn:asciiname":"Odagaku",
    "gn:country_code":"JP",
    "gn:dem":39,
    "gn:feature_class":"P",
    "gn:feature_code":"PPL",
    "gn:name":"Odagaku",
    "gn:population":0,
    "gn:timezone":"Asia/Tokyo",
    "iso:country":"JP",
    "name:jpn_x_preferred":[
        "\u592a\u7530\u5b66"
    ],
    "name:jpn_x_variant":[
        "\u304a\u3060\u304c\u304f",
        "\u30aa\u30c0\u30ac\u30af"
    ],
    "wof:name":"Odagaku",
    "wof:placetype":"locality"
},
  "geometry": {"coordinates":[140.05721,35.1327],"type":"Point"}
}