{
  "type": "Feature",
  "properties": {
    "gn:admin1_code":"28.0",
    "gn:admin2_code":"1863590.0",
    "gn:asciiname":"Nishiyoshinocho-taki",
    "gn:country_code":"JP",
    "gn:dem":154,
    "gn:feature_class":"P",
    "gn:feature_code":"PPL",
    "gn:name":"Nishiyoshinoch\u014d-taki",
    "gn:population":0,
    "gn:timezone":"Asia/Tokyo",
    "iso:country":"JP",
    "name:jpn_x_preferred":[
        "\u897f\u5409\u91ce\u753a\u6edd"
    ],
    "name:und_x_variant":[
        "Nishiyoshinoch\u014d-taki"
    ],
    "wof:name":"Nishiyoshinocho-taki",
    "wof:placetype":"locality"
},
  "geometry": {"coordinates":[135.71457000000001,34.31268],"type":"Point"}
}