{
  "type": "Feature",
  "properties": {
    "gn:admin1_code":"12.0",
    "gn:admin2_code":"7428119.0",
    "gn:admin3_code":"1347.0",
    "gn:asciiname":"Kunnui",
    "gn:country_code":"JP",
    "gn:dem":2,
    "gn:feature_class":"P",
    "gn:feature_code":"PPL",
    "gn:name":"Kunnui",
    "gn:population":0,
    "gn:timezone":"Asia/Tokyo",
    "iso:country":"JP",
    "wof:name":"Kunnui",
    "wof:placetype":"locality"
},
  "geometry": {"coordinates":[140.31917000000001,42.43444],"type":"Point"}
}