{
  "type": "Feature",
  "properties": {
    "gn:admin1_code":"33.0",
    "gn:admin2_code":"7391358.0",
    "gn:admin3_code":"41425.0",
    "gn:asciiname":"Imaizumi",
    "gn:country_code":"JP",
    "gn:dem":-2,
    "gn:feature_class":"P",
    "gn:feature_code":"PPL",
    "gn:name":"Imaizumi",
    "gn:population":0,
    "gn:timezone":"Asia/Tokyo",
    "iso:country":"JP",
    "name:jpn_x_preferred":[
        "\u4eca\u6cc9"
    ],
    "wof:name":"Imaizumi",
    "wof:placetype":"locality"
},
  "geometry": {"coordinates":[130.12293,33.19406],"type":"Point"}
}