{
  "type": "Feature",
  "properties": {
    "gn:country":"JP",
    "gn:fcode":"ADM3",
    "gn:pop":0,
    "iso:country":"JP",
    "name:jpn_x_preferred":[
        "\u4e09\u80a1\u753a"
    ],
    "name:jpn_x_variant":[
        "\u307f\u307e\u305f\u3061\u3087\u3046"
    ],
    "name:unk_x_variant":[
        "Mimata Ch\u014d"
    ],
    "qs:name":"Mimata-ch\u014d",
    "qs:photos_9r":0,
    "qs:photos_sr":0,
    "qs:pop_sr":"0",
    "wof:name":"Mimata-ch\u014d",
    "wof:placetype":"localadmin",
    "wof:population":0
},
  "geometry": {"coordinates":[131.17703,31.73105],"type":"Point"}
}