{
  "type": "Feature",
  "properties": {
    "gn:admin1_code":"4.0",
    "gn:admin2_code":"2110982.0",
    "gn:asciiname":"Hananokiyatsu",
    "gn:country_code":"JP",
    "gn:dem":39,
    "gn:feature_class":"P",
    "gn:feature_code":"PPLL",
    "gn:name":"Hananokiyatsu",
    "gn:population":0,
    "gn:timezone":"Asia/Tokyo",
    "iso:country":"JP",
    "name:jpn_x_preferred":[
        "\u82b1\u30ce\u6728\u8c37"
    ],
    "name:jpn_x_variant":[
        "\u306f\u306a\u306e\u304d\u3084\u3064",
        "\u30cf\u30ca\u30ce\u30ad\u30e4\u30c4"
    ],
    "wof:name":"Hananokiyatsu",
    "wof:placetype":"locality"
},
  "geometry": {"coordinates":[140.00620000000001,35.37805],"type":"Point"}
}