{
  "type": "Feature",
  "properties": {
    "gn:admin1_code":"28",
    "gn:admin2_code":"1863538.0",
    "gn:asciiname":"Kashiwara",
    "gn:cc2":"JP",
    "gn:country_code":"JP",
    "gn:dem":83,
    "gn:feature_class":"P",
    "gn:feature_code":"PPL",
    "gn:name":"Kashiwara",
    "gn:population":0,
    "gn:timezone":"Asia/Tokyo",
    "iso:country":"JP",
    "name:und_x_variant":[
        "Kashiwabara",
        "Kashihara",
        "Kashiwara"
    ],
    "wof:name":"Kashiwara",
    "wof:placetype":"locality"
},
  "geometry": {"coordinates":[135.76667,34.45],"type":"Point"}
}