{
  "type": "Feature",
  "properties": {
    "gn:admin1_code":"40.0",
    "gn:admin2_code":"1852083.0",
    "gn:asciiname":"Yaraicho",
    "gn:country_code":"JP",
    "gn:dem":25,
    "gn:feature_class":"P",
    "gn:feature_code":"PPL",
    "gn:name":"Yaraich\u014d",
    "gn:population":0,
    "gn:timezone":"Asia/Tokyo",
    "iso:country":"JP",
    "name:jpn_x_preferred":[
        "\u77e2\u6765\u753a"
    ],
    "name:und_x_variant":[
        "Yaraich\u014d"
    ],
    "wof:name":"Yaraicho",
    "wof:placetype":"locality"
},
  "geometry": {"coordinates":[139.73175000000001,35.70330999999999],"type":"Point"}
}