{
  "type": "Feature",
  "properties": {
    "gn:admin1_code":"24.0",
    "gn:admin2_code":"7446988.0",
    "gn:admin3_code":"4362.0",
    "gn:asciiname":"Yokoyama",
    "gn:country_code":"JP",
    "gn:dem":7,
    "gn:feature_class":"P",
    "gn:feature_code":"PPLL",
    "gn:name":"Yokoyama",
    "gn:population":0,
    "gn:timezone":"Asia/Tokyo",
    "iso:country":"JP",
    "name:jpn_x_preferred":[
        "\u6a2a\u5c71"
    ],
    "wof:name":"Yokoyama",
    "wof:placetype":"locality"
},
  "geometry": {"coordinates":[140.86911000000001,37.99269],"type":"Point"}
}