{
  "type": "Feature",
  "properties": {
    "gn:admin1_code":"13",
    "gn:admin2_code":"1862625.0",
    "gn:asciiname":"Otsuku-kibi",
    "gn:country_code":"JP",
    "gn:dem":4,
    "gn:feature_class":"P",
    "gn:feature_code":"PPL",
    "gn:name":"\u014ctsuku-kibi",
    "gn:population":0,
    "gn:timezone":"Asia/Tokyo",
    "iso:country":"JP",
    "name:jpn_x_preferred":[
        "\u5927\u6d25\u533a\u5409\u7f8e"
    ],
    "name:und_x_variant":[
        "Yoshimi",
        "Kibi",
        "\u014ctsuku-kibi"
    ],
    "wof:name":"Otsuku-kibi",
    "wof:placetype":"locality"
},
  "geometry": {"coordinates":[134.60299999999998,34.78570999999999],"type":"Point"}
}