{
  "type": "Feature",
  "properties": {
    "iso:country":"JP",
    "name:eng_x_preferred":[
        "Kumiyama Town"
    ],
    "name:jpn_x_preferred":[
        "\u4e45\u5fa1\u5c71\u753a"
    ],
    "qs:name":"\u4e45\u5fa1\u5c71\u753a",
    "qs:name_adm0":"\u65e5\u672c",
    "qs:name_adm1":"\u4eac\u90fd\u5e9c",
    "qs:photos":108,
    "qs:photos_1k":22,
    "qs:photos_9k":1,
    "qs:photos_9r":4,
    "qs:photos_all":194,
    "qs:photos_sr":3,
    "qs:placetype":"Town",
    "qs:pop_sr":"0",
    "wof:name":"Kumiyama Town",
    "wof:placetype":"locality"
},
  "geometry": {"coordinates":[135.74191999999999,34.895293],"type":"Point"}
}