{
  "type": "Feature",
  "properties": {
    "gn:admin1_code":"16.0",
    "gn:admin2_code":"2111005.0",
    "gn:admin3_code":"3321.0",
    "gn:asciiname":"Yokodera",
    "gn:country_code":"JP",
    "gn:dem":156,
    "gn:feature_class":"P",
    "gn:feature_code":"PPL",
    "gn:name":"Yokodera",
    "gn:population":0,
    "gn:timezone":"Asia/Tokyo",
    "iso:country":"JP",
    "name:jpn_x_preferred":[
        "\u6a2a\u5bfa"
    ],
    "name:jpn_x_variant":[
        "\u3088\u3053\u3067\u3089",
        "\u30e8\u30b3\u30c7\u30e9"
    ],
    "wof:name":"Yokodera",
    "wof:placetype":"locality"
},
  "geometry": {"coordinates":[141.22633000000005,39.49731],"type":"Point"}
}