{
  "type": "Feature",
  "properties": {
    "gn:admin1_code":"4.0",
    "gn:admin2_code":"1859468.0",
    "gn:asciiname":"Mino'o",
    "gn:country_code":"JP",
    "gn:dem":24,
    "gn:feature_class":"P",
    "gn:feature_code":"PPL",
    "gn:name":"Mino\u2019o",
    "gn:population":0,
    "gn:timezone":"Asia/Tokyo",
    "iso:country":"JP",
    "name:jpn_x_preferred":[
        "\u4e09\u76f4"
    ],
    "name:jpn_x_variant":[
        "\u307f\u306e\u304a",
        "\u30df\u30ce\u30aa"
    ],
    "name:und_x_variant":[
        "Mino\u2019o"
    ],
    "wof:name":"Mino'o",
    "wof:placetype":"locality"
},
  "geometry": {"coordinates":[139.93582000000001,35.31924],"type":"Point"}
}