{
  "type": "Feature",
  "properties": {
    "iso:country":"JP",
    "label:eng_x_preferred_longname":[
        "Koumi Town"
    ],
    "label:eng_x_preferred_placetype":[
        "town"
    ],
    "name:eng_x_preferred":[
        "Koumi"
    ],
    "name:eng_x_variant":[
        "Koumi Town"
    ],
    "name:jpn_x_preferred":[
        "\u5c0f\u6d77\u753a"
    ],
    "qs:name":"\u5c0f\u6d77\u753a",
    "qs:name_adm0":"\u65e5\u672c",
    "qs:name_adm1":"\u9577\u91ce\u770c",
    "qs:photos":536,
    "qs:photos_1k":109,
    "qs:photos_9k":2,
    "qs:photos_9r":5,
    "qs:photos_all":536,
    "qs:photos_sr":7,
    "qs:placetype":"Town",
    "qs:pop_sr":"0",
    "wof:name":"Koumi",
    "wof:placetype":"locality"
},
  "geometry": {"coordinates":[138.36174700000001,36.034131],"type":"Point"}
}