{
  "type": "Feature",
  "properties": {
    "gn:admin1_code":"16.0",
    "gn:admin2_code":"2112223.0",
    "gn:asciiname":"Tozakura",
    "gn:country_code":"JP",
    "gn:dem":66,
    "gn:feature_class":"P",
    "gn:feature_code":"PPL",
    "gn:name":"Tozakura",
    "gn:population":0,
    "gn:timezone":"Asia/Tokyo",
    "iso:country":"JP",
    "name:jpn_x_preferred":[
        "\u6238\u685c"
    ],
    "name:jpn_x_variant":[
        "\u3068\u3056\u304f\u3089",
        "\u30c8\u30b6\u30af\u30e9"
    ],
    "wof:name":"Tozakura",
    "wof:placetype":"locality"
},
  "geometry": {"coordinates":[141.14802,39.33972],"type":"Point"}
}