{
  "type": "Feature",
  "properties": {
    "gn:admin1_code":"4.0",
    "gn:admin2_code":"2112997.0",
    "gn:admin3_code":"12422.0",
    "gn:asciiname":"Kikugaya",
    "gn:country_code":"JP",
    "gn:dem":28,
    "gn:feature_class":"P",
    "gn:feature_code":"PPLL",
    "gn:name":"Kikugaya",
    "gn:population":0,
    "gn:timezone":"Asia/Tokyo",
    "iso:country":"JP",
    "name:jpn_x_preferred":[
        "\u97a0\u30f6\u8c37"
    ],
    "name:jpn_x_variant":[
        "\u304d\u304f\u304c\u3084",
        "\u30ad\u30af\u30ac\u30e4"
    ],
    "wof:name":"Kikugaya",
    "wof:placetype":"locality"
},
  "geometry": {"coordinates":[140.29077000000001,35.35915],"type":"Point"}
}