{
  "type": "Feature",
  "properties": {
    "gn:admin1_code":"4.0",
    "gn:admin2_code":"7465521.0",
    "gn:asciiname":"Hiratsuka",
    "gn:country_code":"JP",
    "gn:dem":192,
    "gn:feature_class":"P",
    "gn:feature_code":"PPL",
    "gn:name":"Hiratsuka",
    "gn:population":0,
    "gn:timezone":"Asia/Tokyo",
    "iso:country":"JP",
    "name:ara_x_preferred":[
        "\u0647\u064a\u0631\u0627\u062a\u0633\u0648\u0643\u0627"
    ],
    "name:azb_x_preferred":[
        "\u0647\u06cc\u0631\u0627\u062a\u0633\u0648\u06a9\u0627"
    ],
    "name:bul_x_preferred":[
        "\u0425\u0438\u0440\u0430\u0446\u0443\u043a\u0430"
    ],
    "name:cat_x_preferred":[
        "Hiratsuka"
    ],
    "name:ceb_x_preferred":[
        "Hiratsuka"
    ],
    "name:ces_x_preferred":[
        "Hiracuka"
    ],
    "name:deu_x_preferred":[
        "Hiratsuka"
    ],
    "name:fas_x_preferred":[
        "\u0647\u06cc\u0631\u0627\u062a\u0633\u0648\u06a9\u0627"
    ],
    "name:fin_x_preferred":[
        "Hiratsuka"
    ],
    "name:fra_x_preferred":[
        "Hiratsuka"
    ],
    "name:gle_x_preferred":[
        "Hiratsuka"
    ],
    "name:glg_x_preferred":[
        "Hiratsuka"
    ],
    "name:ita_x_preferred":[
        "Hiratsuka"
    ],
    "name:jpn_x_preferred":[
        "\u5e73\u585a"
    ],
    "name:jpn_x_variant":[
        "\u3072\u3089\u3064\u304b",
        "\u30d2\u30e9\u30c4\u30ab",
        "\u5e73\u585a\u5e02"
    ],
    "name:kat_x_preferred":[
        "\u10f0\u10d8\u10e0\u10d0\u10ea\u10e3\u10d9\u10d0"
    ],
    "name:kor_x_preferred":[
        "\ud788\ub77c\uc4f0\uce74\uc2dc"
    ],
    "name:lit_x_preferred":[
        "Hiracuka"
    ],
    "name:mlg_x_preferred":[
        "Hiratsuka"
    ],
    "name:mzn_x_preferred":[
        "\u0647\u06cc\u0631\u0627\u062a\u0633\u0648\u06a9\u0627"
    ],
    "name:nld_x_preferred":[
        "Hiratsuka"
    ],
    "name:pol_x_preferred":[
        "Hiratsuka"
    ],
    "name:por_x_preferred":[
        "Hiratsuka"
    ],
    "name:ron_x_preferred":[
        "Hiratsuka"
    ],
    "name:rus_x_preferred":[
        "\u0425\u0438\u0440\u0430\u0446\u0443\u043a\u0430"
    ],
    "name:spa_x_preferred":[
        "Hiratsuka"
    ],
    "name:srp_x_preferred":[
        "\u0425\u0438\u0440\u0430\u0446\u0443\u043a\u0430"
    ],
    "name:swe_x_preferred":[
        "Hiratsuka"
    ],
    "name:tgk_x_preferred":[
        "\u04b2\u0438\u0440\u0430\u0442\u0441\u0443\u043a\u0430"
    ],
    "name:tgl_x_preferred":[
        "Hiratsuka"
    ],
    "name:tha_x_preferred":[
        "\u0e2e\u0e34\u0e23\u0e31\u0e15\u0e2a\u0e36\u0e01\u0e30"
    ],
    "name:tum_x_preferred":[
        "Hiratsuka"
    ],
    "name:tur_x_preferred":[
        "Hiratsuka"
    ],
    "name:ukr_x_preferred":[
        "\u0425\u0456\u0440\u0430\u0446\u0443\u043a\u0430"
    ],
    "name:urd_x_preferred":[
        "\u06c1\u06cc\u0631\u0627\u062a\u0633\u0648\u06a9\u0627"
    ],
    "name:vie_x_preferred":[
        "Hiratsuka"
    ],
    "name:war_x_preferred":[
        "Hiratsuka"
    ],
    "name:zho_x_preferred":[
        "\u5e73\u585a\u5e02"
    ],
    "wof:name":"Hiratsuka",
    "wof:placetype":"locality"
},
  "geometry": {"coordinates":[139.98580000000001,35.05875],"type":"Point"}
}