{
  "type": "Feature",
  "properties": {
    "gn:admin1_code":"4.0",
    "gn:admin2_code":"7465521.0",
    "gn:asciiname":"Hiratsuka",
    "gn:country_code":"JP",
    "gn:dem":192,
    "gn:feature_class":"P",
    "gn:feature_code":"PPL",
    "gn:name":"Hiratsuka",
    "gn:population":0,
    "gn:timezone":"Asia/Tokyo",
    "iso:country":"JP",
    "name:jpn_x_preferred":[
        "\u5e73\u585a"
    ],
    "name:jpn_x_variant":[
        "\u3072\u3089\u3064\u304b",
        "\u30d2\u30e9\u30c4\u30ab"
    ],
    "wof:name":"Hiratsuka",
    "wof:placetype":"locality"
},
  "geometry": {"coordinates":[139.98580000000001,35.05875],"type":"Point"}
}