{
  "type": "Feature",
  "properties": {
    "gn:admin1_code":"45",
    "gn:admin2_code":"1852222.0",
    "gn:asciiname":"Hohokucho-yatama",
    "gn:country_code":"JP",
    "gn:dem":1,
    "gn:feature_class":"P",
    "gn:feature_code":"PPL",
    "gn:name":"H\u014dhokuch\u014d-yatama",
    "gn:population":0,
    "gn:timezone":"Asia/Tokyo",
    "iso:country":"JP",
    "name:jpn_x_preferred":[
        "\u8c4a\u5317\u753a\u77e2\u7389"
    ],
    "name:und_x_variant":[
        "H\u014dhokuch\u014d-yatama",
        "Yatama"
    ],
    "wof:name":"Hohokucho-yatama",
    "wof:placetype":"locality"
},
  "geometry": {"coordinates":[130.88934,34.27353],"type":"Point"}
}