{
  "type": "Feature",
  "properties": {
    "gn:admin1_code":"21.0",
    "gn:admin2_code":"1850744.0",
    "gn:admin3_code":"43364.0",
    "gn:asciiname":"Uriuda",
    "gn:country_code":"JP",
    "gn:dem":87,
    "gn:feature_class":"P",
    "gn:feature_code":"PPLL",
    "gn:name":"Uriuda",
    "gn:population":0,
    "gn:timezone":"Asia/Tokyo",
    "iso:country":"JP",
    "name:jpn_x_preferred":[
        "\u74dc\u751f\u7530"
    ],
    "name:jpn_x_variant":[
        "\u3046\u308a\u3046\u3060",
        "\u30a6\u30ea\u30a6\u30c0"
    ],
    "wof:name":"Uriuda",
    "wof:placetype":"locality"
},
  "geometry": {"coordinates":[130.64376999999999,32.9062],"type":"Point"}
}