{
  "type": "Feature",
  "properties": {
    "gn:admin1_code":"06",
    "gn:admin2_code":"1849587.0",
    "gn:asciiname":"Futamura",
    "gn:country_code":"JP",
    "gn:dem":23,
    "gn:feature_class":"P",
    "gn:feature_code":"PPL",
    "gn:name":"Futamura",
    "gn:population":0,
    "gn:timezone":"Asia/Tokyo",
    "iso:country":"JP",
    "wof:name":"Futamura",
    "wof:placetype":"locality"
},
  "geometry": {"coordinates":[136.03861000000001,35.67028],"type":"Point"}
}