{
  "type": "Feature",
  "properties": {
    "gn:admin1_code":"2.0",
    "gn:admin2_code":"2113122.0",
    "gn:asciiname":"Iijima-nishibukuro",
    "gn:country_code":"JP",
    "gn:dem":10,
    "gn:feature_class":"P",
    "gn:feature_code":"PPL",
    "gn:name":"Iijima-nishibukuro",
    "gn:population":0,
    "gn:timezone":"Asia/Tokyo",
    "iso:country":"JP",
    "name:jpn_x_preferred":[
        "\u98ef\u5cf6\u897f\u888b"
    ],
    "name:jpn_x_variant":[
        "\u3044\u3044\u3058\u307e\u306b\u3057\u3076\u304f\u308d",
        "\u30a4\u30a4\u30b8\u30de\u30cb\u30b7\u30d6\u30af\u30ed"
    ],
    "wof:name":"Iijima-nishibukuro",
    "wof:placetype":"locality"
},
  "geometry": {"coordinates":[140.08955,39.77],"type":"Point"}
}