{
  "type": "Feature",
  "properties": {
    "gn:admin1_code":"21.0",
    "gn:admin2_code":"1858418.0",
    "gn:admin3_code":"43103.0",
    "gn:asciiname":"Nangoshi",
    "gn:country_code":"JP",
    "gn:dem":235,
    "gn:feature_class":"P",
    "gn:feature_code":"PPLL",
    "gn:name":"Nangoshi",
    "gn:population":0,
    "gn:timezone":"Asia/Tokyo",
    "iso:country":"JP",
    "name:jpn_x_preferred":[
        "\u5357\u8d8a"
    ],
    "name:jpn_x_variant":[
        "\u306a\u3093\u3054\u3057",
        "\u30ca\u30f3\u30b4\u30b7"
    ],
    "wof:name":"Nangoshi",
    "wof:placetype":"locality"
},
  "geometry": {"coordinates":[130.60168999999999,32.84419],"type":"Point"}
}