{
  "type": "Feature",
  "properties": {
    "gn:admin1_code":"26.0",
    "gn:admin2_code":"1860552.0",
    "gn:admin3_code":"20382.0",
    "gn:asciiname":"Kawakami",
    "gn:country_code":"JP",
    "gn:dem":854,
    "gn:feature_class":"P",
    "gn:feature_code":"PPL",
    "gn:name":"Kawakami",
    "gn:population":0,
    "gn:timezone":"Asia/Tokyo",
    "iso:country":"JP",
    "name:jpn_x_preferred":[
        "\u5ddd\u4e0a"
    ],
    "wof:name":"Kawakami",
    "wof:placetype":"locality"
},
  "geometry": {"coordinates":[137.91533000000001,36.00037000000001],"type":"Point"}
}