{
  "type": "Feature",
  "properties": {
    "gn:admin1_code":"13.0",
    "gn:admin2_code":"1861308.0",
    "gn:asciiname":"Ogino",
    "gn:country_code":"JP",
    "gn:dem":32,
    "gn:feature_class":"P",
    "gn:feature_code":"PPL",
    "gn:name":"Ogino",
    "gn:population":0,
    "gn:timezone":"Asia/Tokyo",
    "iso:country":"JP",
    "name:jpn_x_preferred":[
        "\u837b\u91ce"
    ],
    "wof:name":"Ogino",
    "wof:placetype":"locality"
},
  "geometry": {"coordinates":[135.39094,34.80744],"type":"Point"}
}