{
  "type": "Feature",
  "properties": {
    "gn:admin1_code":"31",
    "gn:admin2_code":"7405228.0",
    "gn:asciiname":"Ochiai",
    "gn:country_code":"JP",
    "gn:dem":125,
    "gn:feature_class":"P",
    "gn:feature_code":"PPL",
    "gn:name":"Ochiai",
    "gn:population":0,
    "gn:timezone":"Asia/Tokyo",
    "iso:country":"JP",
    "name:fas_x_preferred":[
        "\u0627\u0648\u0686\u06cc\u200c\u0622\u06cc"
    ],
    "name:jpn_x_preferred":[
        "\u843d\u5408\u753a"
    ],
    "wof:name":"Ochiai",
    "wof:placetype":"locality"
},
  "geometry": {"coordinates":[133.75,35.01667],"type":"Point"}
}