{
  "type": "Feature",
  "properties": {
    "gn:admin1_code":"21.0",
    "gn:admin2_code":"1864975.0",
    "gn:admin3_code":"43428.0",
    "gn:asciiname":"Mori",
    "gn:country_code":"JP",
    "gn:dem":525,
    "gn:feature_class":"P",
    "gn:feature_code":"PPLL",
    "gn:name":"Mori",
    "gn:population":0,
    "gn:timezone":"Asia/Tokyo",
    "iso:country":"JP",
    "name:ces_x_preferred":[
        "Mori"
    ],
    "name:jpn_x_preferred":[
        "\u68ee"
    ],
    "name:jpn_x_variant":[
        "\u3082\u308a",
        "\u30e2\u30ea"
    ],
    "name:lit_x_preferred":[
        "Mori"
    ],
    "name:slk_x_preferred":[
        "Mori"
    ],
    "name:slv_x_preferred":[
        "Mori"
    ],
    "name:spa_x_preferred":[
        "Mori"
    ],
    "wof:name":"Mori",
    "wof:placetype":"locality"
},
  "geometry": {"coordinates":[131.11816000000002,32.81166],"type":"Point"}
}