{
  "type": "Feature",
  "properties": {
    "gn:admin1_code":"28",
    "gn:admin2_code":"1855604.0",
    "gn:asciiname":"Mitsugarasu",
    "gn:country_code":"JP",
    "gn:dem":103,
    "gn:feature_class":"P",
    "gn:feature_code":"PPL",
    "gn:name":"Mitsugarasu",
    "gn:population":0,
    "gn:timezone":"Asia/Tokyo",
    "iso:country":"JP",
    "name:jpn_x_preferred":[
        "\u4e09\u7893"
    ],
    "name:und_x_variant":[
        "Mikarasuch\u014d",
        "Mitsukarasuch\u014d",
        "Mitsugarasuch\u014d",
        "Mitsugarasu"
    ],
    "wof:name":"Mitsugarasu",
    "wof:placetype":"locality"
},
  "geometry": {"coordinates":[135.73828,34.68862],"type":"Point"}
}