{
  "type": "Feature",
  "properties": {
    "gn:admin1_code":"16.0",
    "gn:admin2_code":"2129400.0",
    "gn:admin3_code":"3501.0",
    "gn:asciiname":"Sannai",
    "gn:country_code":"JP",
    "gn:dem":282,
    "gn:feature_class":"P",
    "gn:feature_code":"PPL",
    "gn:name":"Sannai",
    "gn:population":0,
    "gn:timezone":"Asia/Tokyo",
    "iso:country":"JP",
    "name:jpn_x_preferred":[
        "\u5c71\u5185"
    ],
    "name:jpn_x_variant":[
        "\u3055\u3093\u306a\u3044",
        "\u30b5\u30f3\u30ca\u30a4"
    ],
    "wof:name":"Sannai",
    "wof:placetype":"locality"
},
  "geometry": {"coordinates":[141.4076,40.29712],"type":"Point"}
}