{
  "type": "Feature",
  "properties": {
    "gn:admin1_code":"21.0",
    "gn:admin2_code":"7412706.0",
    "gn:admin3_code":"43442.0",
    "gn:asciiname":"Kitaamagi",
    "gn:country_code":"JP",
    "gn:dem":16,
    "gn:feature_class":"P",
    "gn:feature_code":"PPL",
    "gn:name":"Kitaamagi",
    "gn:population":0,
    "gn:timezone":"Asia/Tokyo",
    "iso:country":"JP",
    "name:jpn_x_preferred":[
        "\u5317\u7518\u6728"
    ],
    "name:jpn_x_variant":[
        "\u304d\u305f\u3042\u307e\u304e",
        "\u30ad\u30bf\u30a2\u30de\u30ae"
    ],
    "wof:name":"Kitaamagi",
    "wof:placetype":"locality"
},
  "geometry": {"coordinates":[130.77455,32.74675],"type":"Point"}
}