{
  "type": "Feature",
  "properties": {
    "gn:admin1_code":"32.0",
    "gn:admin2_code":"1853167.0",
    "gn:admin3_code":"27145.0",
    "gn:asciiname":"Takakuradai",
    "gn:country_code":"JP",
    "gn:dem":90,
    "gn:feature_class":"P",
    "gn:feature_code":"PPL",
    "gn:name":"Takakuradai",
    "gn:population":0,
    "gn:timezone":"Asia/Tokyo",
    "iso:country":"JP",
    "name:jpn_x_preferred":[
        "\u9ad8\u5009\u53f0"
    ],
    "wof:name":"Takakuradai",
    "wof:placetype":"locality"
},
  "geometry": {"coordinates":[135.52562,34.4954],"type":"Point"}
}