{
  "type": "Feature",
  "properties": {
    "gn:admin1_code":"09",
    "gn:admin2_code":"1850890.0",
    "gn:asciiname":"Nyukawacho-hatahoko",
    "gn:country_code":"JP",
    "gn:dem":953,
    "gn:feature_class":"P",
    "gn:feature_code":"PPL",
    "gn:name":"Ny\u016bkawach\u014d-hatahoko",
    "gn:population":0,
    "gn:timezone":"Asia/Tokyo",
    "iso:country":"JP",
    "name:jpn_x_preferred":[
        "\u4e39\u751f\u5ddd\u753a\u65d7\u927e"
    ],
    "name:und_x_variant":[
        "Ny\u016bkawach\u014d-hatahoko",
        "Hatahoko"
    ],
    "wof:name":"Nyukawacho-hatahoko",
    "wof:placetype":"locality"
},
  "geometry": {"coordinates":[137.45608999999999,36.17559],"type":"Point"}
}