{
  "type": "Feature",
  "properties": {
    "gn:admin1_code":"4.0",
    "gn:admin2_code":"2112330.0",
    "gn:asciiname":"Minamimasuo",
    "gn:country_code":"JP",
    "gn:dem":31,
    "gn:feature_class":"P",
    "gn:feature_code":"PPL",
    "gn:name":"Minamimasuo",
    "gn:population":0,
    "gn:timezone":"Asia/Tokyo",
    "iso:country":"JP",
    "name:jpn_x_preferred":[
        "\u5357\u5897\u5c3e"
    ],
    "wof:name":"Minamimasuo",
    "wof:placetype":"locality"
},
  "geometry": {"coordinates":[139.96611999999999,35.81371],"type":"Point"}
}