{
  "type": "Feature",
  "properties": {
    "gn:admin1_code":"37.0",
    "gn:admin2_code":"1856971.0",
    "gn:asciiname":"Tanaka",
    "gn:country_code":"JP",
    "gn:dem":118,
    "gn:feature_class":"P",
    "gn:feature_code":"PPLL",
    "gn:name":"Tanaka",
    "gn:population":0,
    "gn:timezone":"Asia/Tokyo",
    "iso:country":"JP",
    "name:jpn_x_preferred":[
        "\u7530\u4e2d"
    ],
    "wof:name":"Tanaka",
    "wof:placetype":"locality"
},
  "geometry": {"coordinates":[138.92686,35.16928],"type":"Point"}
}