{
  "type": "Feature",
  "properties": {
    "iso:country":"JP",
    "name:eng_x_preferred":[
        "Ichigayatamachi 1 Chome"
    ],
    "name:eng_x_variant":[
        "Ichigayatamachi 1 Choume",
        "Ichigayatamachi 1 Chome"
    ],
    "name:jpn_x_preferred":[
        "\uff11\u4e01\u76ee"
    ],
    "name:jpn_x_variant":[
        "\u3044\u3061\u304c\u3084\u305f\u307e\u3061 \uff11\u3061\u3087\u3046\u3081",
        "\u5e02\u8c37\u7530\u753a \uff11\u4e01\u76ee",
        "\uff11\u3061\u3087\u3046\u3081"
    ],
    "qs:gn_adm0_cc":"JP",
    "qs:gn_local":1850147,
    "qs:local_max":18112,
    "qs:local_sum":895907,
    "qs:localhoods":857,
    "qs:name":"\uff11\u4e01\u76ee",
    "qs:name_adm0":"\u65e5\u672c",
    "qs:name_adm1":"\u6771\u4eac\u90fd",
    "qs:name_adm2":"\u65b0\u5bbf\u533a",
    "qs:name_en":"Ichigayatamachi 1 Chome",
    "qs:name_lau":"\u5e02\u8c37\u7530\u753a",
    "qs:name_local":"\u6771\u4eac",
    "qs:photo_max":326,
    "qs:photo_sum":778,
    "qs:placetype":"Suburb",
    "qs:quad_count":5,
    "qs:woe_adm0":23424856,
    "qs:woe_adm1":2345889,
    "qs:woe_adm2":15015378,
    "qs:woe_lau":28414028,
    "qs:woe_local":1118370,
    "qs:woe_ver":"7.10.0",
    "wof:lang":[
        "jpn"
    ],
    "wof:name":"\uff11\u4e01\u76ee",
    "wof:placetype":"neighbourhood"
},
  "geometry": {"coordinates":[139.73516699999999,35.6923],"type":"Point"}
}