{
  "type": "Feature",
  "properties": {
    "gn:admin1_code":"33.0",
    "gn:admin2_code":"1854650.0",
    "gn:asciiname":"Mikatsukicho-higuchi",
    "gn:country_code":"JP",
    "gn:dem":3,
    "gn:feature_class":"P",
    "gn:feature_code":"PPL",
    "gn:name":"Mikatsukich\u014d-higuchi",
    "gn:population":0,
    "gn:timezone":"Asia/Tokyo",
    "iso:country":"JP",
    "name:jpn_x_preferred":[
        "\u4e09\u65e5\u6708\u753a\u6a0b\u53e3"
    ],
    "name:und_x_variant":[
        "Mikatsukich\u014d-higuchi"
    ],
    "wof:name":"Mikatsukicho-higuchi",
    "wof:placetype":"locality"
},
  "geometry": {"coordinates":[130.22280000000001,33.26658],"type":"Point"}
}