{
  "type": "Feature",
  "properties": {
    "gn:admin1_code":"2.0",
    "gn:admin2_code":"7443160.0",
    "gn:asciiname":"Ishiwaki",
    "gn:cc2":"JP",
    "gn:country_code":"JP",
    "gn:dem":7,
    "gn:feature_class":"P",
    "gn:feature_code":"PPL",
    "gn:name":"Ishiwaki",
    "gn:population":0,
    "gn:timezone":"Asia/Tokyo",
    "iso:country":"JP",
    "name:und_x_variant":[
        "Ishikawa",
        "Ishiwaki"
    ],
    "wof:name":"Ishiwaki",
    "wof:placetype":"locality"
},
  "geometry": {"coordinates":[140.05000000000001,39.38333],"type":"Point"}
}