{
  "type": "Feature",
  "properties": {
    "iso:country":"JP",
    "name:eng_x_preferred":[
        "Fuseshinmachi 2 Chome"
    ],
    "name:eng_x_variant":[
        "Fuseshinmachi 2 Choume",
        "Fuseshinmachi 2 Chome"
    ],
    "name:jpn_x_preferred":[
        "\uff12\u4e01\u76ee"
    ],
    "name:jpn_x_variant":[
        "\u3075\u305b\u3057\u3093\u307e\u3061 \uff12\u3061\u3087\u3046\u3081",
        "\u5e03\u65bd\u65b0\u753a \uff12\u4e01\u76ee",
        "\uff12\u3061\u3087\u3046\u3081"
    ],
    "qs:gn_adm0_cc":"JP",
    "qs:gn_local":1859924,
    "qs:gn_nam_loc":"\u67cf\u5e02, \u5343\u8449\u770c, JP",
    "qs:gn_namadm1":"04",
    "qs:local_max":531,
    "qs:local_sum":2701,
    "qs:localhoods":19,
    "qs:name":"\uff12\u4e01\u76ee",
    "qs:name_adm0":"\u65e5\u672c",
    "qs:name_adm1":"\u5343\u8449\u770c",
    "qs:name_en":"Fuseshinmachi 2 Chome",
    "qs:name_lau":"\u5e03\u65bd\u65b0\u753a",
    "qs:name_local":"\u67cf\u5e02",
    "qs:photo_max":77,
    "qs:photo_sum":201,
    "qs:placetype":"Suburb",
    "qs:quad_count":10,
    "qs:woe_adm0":23424856,
    "qs:woe_adm1":2345854,
    "qs:woe_adm2":0,
    "qs:woe_lau":28411925,
    "qs:woe_local":1117469,
    "qs:woe_ver":"7.10.0",
    "wof:lang":[
        "jpn"
    ],
    "wof:name":"\uff12\u4e01\u76ee",
    "wof:placetype":"neighbourhood"
},
  "geometry": {"coordinates":[140.006259,35.896218],"type":"Point"}
}