{
  "type": "Feature",
  "properties": {
    "gn:admin1_code":"15",
    "gn:admin2_code":"1851337.0",
    "gn:asciiname":"Shoinmachi-koji",
    "gn:country_code":"JP",
    "gn:dem":0,
    "gn:feature_class":"P",
    "gn:feature_code":"PPL",
    "gn:name":"Sh\u014dinmachi-k\u014dji",
    "gn:population":0,
    "gn:timezone":"Asia/Tokyo",
    "iso:country":"JP",
    "name:jpn_x_preferred":[
        "\u6b63\u9662\u753a\u5c0f\u8def"
    ],
    "name:und_x_variant":[
        "Sh\u014dinmachi-k\u014dji",
        "Sh\u014din"
    ],
    "wof:name":"Shoinmachi-koji",
    "wof:placetype":"locality"
},
  "geometry": {"coordinates":[137.29113000000001,37.45049],"type":"Point"}
}