{
  "type": "Feature",
  "properties": {
    "gn:admin1_code":"22.0",
    "gn:admin2_code":"7412210.0",
    "gn:asciiname":"Fugenji",
    "gn:country_code":"JP",
    "gn:dem":60,
    "gn:feature_class":"P",
    "gn:feature_code":"PPL",
    "gn:name":"Fugenji",
    "gn:population":0,
    "gn:timezone":"Asia/Tokyo",
    "iso:country":"JP",
    "name:jpn_x_preferred":[
        "\u666e\u8ce2\u5bfa"
    ],
    "wof:name":"Fugenji",
    "wof:placetype":"locality"
},
  "geometry": {"coordinates":[135.76087999999999,34.7945],"type":"Point"}
}