{
  "type": "Feature",
  "properties": {
    "gn:admin1_code":"15.0",
    "gn:admin2_code":"7467838.0",
    "gn:admin3_code":"17384.0",
    "gn:asciiname":"Higeta",
    "gn:country_code":"JP",
    "gn:dem":55,
    "gn:feature_class":"P",
    "gn:feature_code":"PPL",
    "gn:name":"Higeta",
    "gn:population":0,
    "gn:timezone":"Asia/Tokyo",
    "iso:country":"JP",
    "name:jpn_x_preferred":[
        "\u65e5\u4e0b\u7530"
    ],
    "wof:name":"Higeta",
    "wof:placetype":"locality"
},
  "geometry": {"coordinates":[136.7843,37.0956],"type":"Point"}
}