{
  "type": "Feature",
  "properties": {
    "gn:admin1_code":"19.0",
    "gn:admin2_code":"1864091.0",
    "gn:asciiname":"Kugenuma-matsugaoka",
    "gn:country_code":"JP",
    "gn:dem":6,
    "gn:feature_class":"P",
    "gn:feature_code":"PPL",
    "gn:name":"Kugenuma-matsugaoka",
    "gn:population":0,
    "gn:timezone":"Asia/Tokyo",
    "iso:country":"JP",
    "name:jpn_x_preferred":[
        "\u9d60\u6cbc\u677e\u304c\u5ca1"
    ],
    "wof:name":"Kugenuma-matsugaoka",
    "wof:placetype":"locality"
},
  "geometry": {"coordinates":[139.47531999999998,35.3209],"type":"Point"}
}