{
  "type": "Feature",
  "properties": {
    "gn:admin1_code":"3.0",
    "gn:admin2_code":"7439934.0",
    "gn:asciiname":"Idozawa",
    "gn:country_code":"JP",
    "gn:dem":309,
    "gn:feature_class":"P",
    "gn:feature_code":"PPL",
    "gn:name":"Idozawa",
    "gn:population":0,
    "gn:timezone":"Asia/Tokyo",
    "iso:country":"JP",
    "name:jpn_x_preferred":[
        "\u4e95\u6238\u6ca2"
    ],
    "name:jpn_x_variant":[
        "\u3044\u3069\u3056\u308f",
        "\u30a4\u30c9\u30b6\u30ef"
    ],
    "wof:name":"Idozawa",
    "wof:placetype":"locality"
},
  "geometry": {"coordinates":[140.74684999999999,40.52715],"type":"Point"}
}