{
  "type": "Feature",
  "properties": {
    "gn:admin1_code":"29.0",
    "gn:admin2_code":"1853313.0",
    "gn:asciiname":"Hamochi-osaki",
    "gn:country_code":"JP",
    "gn:dem":92,
    "gn:feature_class":"P",
    "gn:feature_code":"PPL",
    "gn:name":"Hamochi-\u014dsaki",
    "gn:population":0,
    "gn:timezone":"Asia/Tokyo",
    "iso:country":"JP",
    "name:jpn_x_preferred":[
        "\u7fbd\u8302\u5927\u5d0e"
    ],
    "name:und_x_variant":[
        "Hamochi-\u014dsaki"
    ],
    "wof:name":"Hamochi-osaki",
    "wof:placetype":"locality"
},
  "geometry": {"coordinates":[138.33466000000001,37.87695],"type":"Point"}
}