{
  "type": "Feature",
  "properties": {
    "gn:admin1_code":"18.0",
    "gn:admin2_code":"7383999.0",
    "gn:admin3_code":"46492.0",
    "gn:asciiname":"Miyagekita",
    "gn:country_code":"JP",
    "gn:dem":11,
    "gn:feature_class":"P",
    "gn:feature_code":"PPLL",
    "gn:name":"Miyagekita",
    "gn:population":0,
    "gn:timezone":"Asia/Tokyo",
    "iso:country":"JP",
    "name:jpn_x_preferred":[
        "\u5bae\u4e0b\u5317"
    ],
    "wof:name":"Miyagekita",
    "wof:placetype":"locality"
},
  "geometry": {"coordinates":[130.91512,31.36384],"type":"Point"}
}