{
  "type": "Feature",
  "properties": {
    "gn:admin1_code":"21.0",
    "gn:admin2_code":"1848441.0",
    "gn:asciiname":"Demachi",
    "gn:country_code":"JP",
    "gn:dem":5,
    "gn:feature_class":"P",
    "gn:feature_code":"PPL",
    "gn:name":"Demachi",
    "gn:population":0,
    "gn:timezone":"Asia/Tokyo",
    "iso:country":"JP",
    "name:jpn_x_preferred":[
        "\u51fa\u753a"
    ],
    "name:jpn_x_variant":[
        "\u3067\u307e\u3061",
        "\u30c7\u30de\u30c1"
    ],
    "wof:name":"Demachi",
    "wof:placetype":"locality"
},
  "geometry": {"coordinates":[130.60848999999999,32.50956],"type":"Point"}
}