{
  "type": "Feature",
  "properties": {
    "gn:admin1_code":"3.0",
    "gn:admin2_code":"2128302.0",
    "gn:admin3_code":"2442.0",
    "gn:asciiname":"Kitaichikawa",
    "gn:country_code":"JP",
    "gn:dem":20,
    "gn:feature_class":"P",
    "gn:feature_code":"PPL",
    "gn:name":"Kitaichikawa",
    "gn:population":0,
    "gn:timezone":"Asia/Tokyo",
    "iso:country":"JP",
    "name:jpn_x_preferred":[
        "\u5317\u5e02\u5ddd"
    ],
    "name:jpn_x_variant":[
        "\u304d\u305f\u3044\u3061\u304b\u308f",
        "\u30ad\u30bf\u30a4\u30c1\u30ab\u30ef"
    ],
    "wof:name":"Kitaichikawa",
    "wof:placetype":"locality"
},
  "geometry": {"coordinates":[141.38381999999999,40.55805],"type":"Point"}
}