{
  "type": "Feature",
  "properties": {
    "gn:admin1_code":"7.0",
    "gn:admin2_code":"1851269.0",
    "gn:admin3_code":"40610.0",
    "gn:asciiname":"Fushihara",
    "gn:country_code":"JP",
    "gn:dem":44,
    "gn:feature_class":"P",
    "gn:feature_code":"PPLL",
    "gn:name":"Fushihara",
    "gn:population":0,
    "gn:timezone":"Asia/Tokyo",
    "iso:country":"JP",
    "name:jpn_x_preferred":[
        "\u4f0f\u539f"
    ],
    "wof:name":"Fushihara",
    "wof:placetype":"locality"
},
  "geometry": {"coordinates":[130.75970000000001,33.6888],"type":"Point"}
}