{
  "type": "Feature",
  "properties": {
    "gn:admin1_code":"07",
    "gn:admin2_code":"9035649.0",
    "gn:asciiname":"Dainyu",
    "gn:country_code":"JP",
    "gn:dem":2,
    "gn:feature_class":"P",
    "gn:feature_code":"PPLL",
    "gn:name":"Dainy\u016b",
    "gn:population":0,
    "gn:timezone":"Asia/Tokyo",
    "iso:country":"JP",
    "name:jpn_x_preferred":[
        "\u5927\u5165"
    ],
    "name:und_x_variant":[
        "Dainy\u016b"
    ],
    "wof:name":"Dainyu",
    "wof:placetype":"locality"
},
  "geometry": {"coordinates":[130.10069999999999,33.51257],"type":"Point"}
}