{
  "type": "Feature",
  "properties": {
    "gn:admin1_code":"3.0",
    "gn:admin2_code":"2130088.0",
    "gn:admin3_code":"2307.0",
    "gn:asciiname":"Yazokama",
    "gn:country_code":"JP",
    "gn:dem":13,
    "gn:feature_class":"P",
    "gn:feature_code":"PPL",
    "gn:name":"Yaz\u014dkama",
    "gn:population":0,
    "gn:timezone":"Asia/Tokyo",
    "iso:country":"JP",
    "name:jpn_x_preferred":[
        "\u5f25\u8535\u91dc"
    ],
    "name:jpn_x_variant":[
        "\u3084\u305e\u3046\u304b\u307e",
        "\u30e4\u30be\u30a6\u30ab\u30de"
    ],
    "name:und_x_variant":[
        "Yaz\u014dkama"
    ],
    "wof:name":"Yazokama",
    "wof:placetype":"locality"
},
  "geometry": {"coordinates":[140.62538999999998,41.19306],"type":"Point"}
}