{
  "type": "Feature",
  "properties": {
    "gn:admin1_code":"3.0",
    "gn:admin2_code":"2129754.0",
    "gn:admin3_code":"2405.0",
    "gn:asciiname":"Omagari",
    "gn:country_code":"JP",
    "gn:dem":57,
    "gn:feature_class":"P",
    "gn:feature_code":"PPL",
    "gn:name":"\u014cmagari",
    "gn:population":0,
    "gn:timezone":"Asia/Tokyo",
    "iso:country":"JP",
    "name:jpn_x_preferred":[
        "\u5927\u66f2"
    ],
    "name:jpn_x_variant":[
        "\u304a\u304a\u307e\u304c\u308a",
        "\u30aa\u30aa\u30de\u30ac\u30ea"
    ],
    "name:und_x_variant":[
        "\u014cmagari"
    ],
    "wof:name":"Omagari",
    "wof:placetype":"locality"
},
  "geometry": {"coordinates":[141.33983000000001,40.65089],"type":"Point"}
}