{
  "type": "Feature",
  "properties": {
    "gn:admin1_code":"34.0",
    "gn:admin2_code":"1857143.0",
    "gn:admin3_code":"11442.0",
    "gn:asciiname":"Suka",
    "gn:country_code":"JP",
    "gn:dem":8,
    "gn:feature_class":"P",
    "gn:feature_code":"PPL",
    "gn:name":"Suka",
    "gn:population":0,
    "gn:timezone":"Asia/Tokyo",
    "iso:country":"JP",
    "name:ceb_x_preferred":[
        "Suka"
    ],
    "name:deu_x_preferred":[
        "Suka"
    ],
    "name:jpn_x_preferred":[
        "\u9808\u8cc0"
    ],
    "name:jpn_x_variant":[
        "\u3059\u304b",
        "\u30b9\u30ab"
    ],
    "name:nld_x_preferred":[
        "Suka"
    ],
    "name:pol_x_preferred":[
        "Suka"
    ],
    "name:rus_x_preferred":[
        "\u0421\u0443\u043a\u0430"
    ],
    "name:slk_x_preferred":[
        "Suka"
    ],
    "name:swe_x_preferred":[
        "Suka"
    ],
    "name:tgl_x_preferred":[
        "Suka"
    ],
    "name:ukr_x_preferred":[
        "\u0421\u0443\u043a\u0430"
    ],
    "wof:name":"Suka",
    "wof:placetype":"locality"
},
  "geometry": {"coordinates":[139.71278999999998,36.03241],"type":"Point"}
}