{
  "type": "Feature",
  "properties": {
    "gn:admin1_code":"16.0",
    "gn:admin2_code":"2112822.0",
    "gn:asciiname":"Shimotate",
    "gn:country_code":"JP",
    "gn:dem":118,
    "gn:feature_class":"P",
    "gn:feature_code":"PPL",
    "gn:name":"Shimotate",
    "gn:population":0,
    "gn:timezone":"Asia/Tokyo",
    "iso:country":"JP",
    "name:jpn_x_preferred":[
        "\u4e0b\u8218"
    ],
    "name:jpn_x_variant":[
        "\u3057\u3082\u305f\u3066",
        "\u30b7\u30e2\u30bf\u30c6"
    ],
    "wof:name":"Shimotate",
    "wof:placetype":"locality"
},
  "geometry": {"coordinates":[141.06645,39.39767],"type":"Point"}
}