{
  "type": "Feature",
  "properties": {
    "gn:admin1_code":"14.0",
    "gn:admin2_code":"8304033.0",
    "gn:asciiname":"Koya",
    "gn:country_code":"JP",
    "gn:dem":32,
    "gn:feature_class":"P",
    "gn:feature_code":"PPL",
    "gn:name":"K\u014dya",
    "gn:population":0,
    "gn:timezone":"Asia/Tokyo",
    "iso:country":"JP",
    "name:ceb_x_preferred":[
        "Koya"
    ],
    "name:deu_x_preferred":[
        "Koya"
    ],
    "name:swe_x_preferred":[
        "Koya"
    ],
    "name:und_x_variant":[
        "K\u014dya"
    ],
    "wof:name":"Koya",
    "wof:placetype":"locality"
},
  "geometry": {"coordinates":[140.55000000000001,36.41667],"type":"Point"}
}