{
  "type": "Feature",
  "properties": {
    "gn:admin1_code":"21.0",
    "gn:admin2_code":"7412706.0",
    "gn:admin3_code":"43447.0",
    "gn:asciiname":"Kurakiyama",
    "gn:country_code":"JP",
    "gn:dem":605,
    "gn:feature_class":"P",
    "gn:feature_code":"PPLL",
    "gn:name":"Kurakiyama",
    "gn:population":0,
    "gn:timezone":"Asia/Tokyo",
    "iso:country":"JP",
    "name:jpn_x_preferred":[
        "\u5009\u6728\u5c71"
    ],
    "name:jpn_x_variant":[
        "\u304f\u3089\u304d\u3084\u307e",
        "\u30af\u30e9\u30ad\u30e4\u30de"
    ],
    "wof:name":"Kurakiyama",
    "wof:placetype":"locality"
},
  "geometry": {"coordinates":[131.18444,32.75817],"type":"Point"}
}