{
  "type": "Feature",
  "properties": {
    "gn:admin1_code":"16.0",
    "gn:admin2_code":"2112223.0",
    "gn:asciiname":"Tateno",
    "gn:country_code":"JP",
    "gn:dem":104,
    "gn:feature_class":"P",
    "gn:feature_code":"PPL",
    "gn:name":"Tateno",
    "gn:population":0,
    "gn:timezone":"Asia/Tokyo",
    "iso:country":"JP",
    "name:jpn_x_preferred":[
        "\u7acb\u91ce"
    ],
    "name:jpn_x_variant":[
        "\u305f\u3066\u306e",
        "\u30bf\u30c6\u30ce"
    ],
    "wof:name":"Tateno",
    "wof:placetype":"locality"
},
  "geometry": {"coordinates":[141.03989999999999,39.3268],"type":"Point"}
}