{
  "type": "Feature",
  "properties": {
    "gn:admin1_code":"4.0",
    "gn:admin2_code":"7465521.0",
    "gn:asciiname":"Daigahara",
    "gn:country_code":"JP",
    "gn:dem":78,
    "gn:feature_class":"P",
    "gn:feature_code":"PPLL",
    "gn:name":"Daigahara",
    "gn:population":0,
    "gn:timezone":"Asia/Tokyo",
    "iso:country":"JP",
    "name:jpn_x_preferred":[
        "\u53f0\u30f6\u539f"
    ],
    "name:jpn_x_variant":[
        "\u3060\u3044\u304c\u306f\u3089",
        "\u30c0\u30a4\u30ac\u30cf\u30e9"
    ],
    "wof:name":"Daigahara",
    "wof:placetype":"locality"
},
  "geometry": {"coordinates":[139.89623,35.0769],"type":"Point"}
}