{
  "type": "Feature",
  "properties": {
    "gn:admin1_code":"18.0",
    "gn:admin2_code":"7383991.0",
    "gn:asciiname":"Kizaki",
    "gn:country_code":"JP",
    "gn:dem":205,
    "gn:feature_class":"P",
    "gn:feature_code":"PPLL",
    "gn:name":"Kizaki",
    "gn:population":0,
    "gn:timezone":"Asia/Tokyo",
    "iso:country":"JP",
    "name:jpn_x_preferred":[
        "\u6728\u5d0e"
    ],
    "name:jpn_x_variant":[
        "\u304d\u3056\u304d",
        "\u30ad\u30b6\u30ad"
    ],
    "wof:name":"Kizaki",
    "wof:placetype":"locality"
},
  "geometry": {"coordinates":[130.60916,32.07917],"type":"Point"}
}