{
  "type": "Feature",
  "properties": {
    "gn:admin1_code":"23",
    "gn:admin2_code":"1853513.0",
    "gn:asciiname":"Kukicho",
    "gn:country_code":"JP",
    "gn:dem":30,
    "gn:feature_class":"P",
    "gn:feature_code":"PPL",
    "gn:name":"Kukich\u014d",
    "gn:population":0,
    "gn:timezone":"Asia/Tokyo",
    "iso:country":"JP",
    "name:jbn_x_preferred":[
        "Kuki"
    ],
    "name:jpn_x_preferred":[
        "\u4e5d\u9b3c\u753a"
    ],
    "name:und_x_variant":[
        "Kukich\u014d"
    ],
    "wof:name":"Kukicho",
    "wof:placetype":"locality"
},
  "geometry": {"coordinates":[136.25173999999998,34.01849],"type":"Point"}
}