{
  "type": "Feature",
  "properties": {
    "gn:admin1_code":"29.0",
    "gn:admin2_code":"1863539.0",
    "gn:asciiname":"Yasuide",
    "gn:country_code":"JP",
    "gn:dem":56,
    "gn:feature_class":"P",
    "gn:feature_code":"PPL",
    "gn:name":"Yasuide",
    "gn:population":0,
    "gn:timezone":"Asia/Tokyo",
    "iso:country":"JP",
    "name:jpn_x_preferred":[
        "\u5b89\u51fa"
    ],
    "wof:name":"Yasuide",
    "wof:placetype":"locality"
},
  "geometry": {"coordinates":[139.18593999999999,37.67126],"type":"Point"}
}