{
  "type": "Feature",
  "properties": {
    "gn:admin1_code":"24.0",
    "gn:admin2_code":"2112574.0",
    "gn:asciiname":"Nishisanken'ya",
    "gn:country_code":"JP",
    "gn:dem":3,
    "gn:feature_class":"P",
    "gn:feature_code":"PPL",
    "gn:name":"Nishisanken\u2019ya",
    "gn:population":0,
    "gn:timezone":"Asia/Tokyo",
    "iso:country":"JP",
    "name:jpn_x_preferred":[
        "\u897f\u4e09\u8ed2\u5c4b"
    ],
    "name:jpn_x_variant":[
        "\u306b\u3057\u3055\u3093\u3051\u3093\u3084",
        "\u30cb\u30b7\u30b5\u30f3\u30b1\u30f3\u30e4"
    ],
    "name:und_x_variant":[
        "Nishisanken\u2019ya"
    ],
    "wof:name":"Nishisanken'ya",
    "wof:placetype":"locality"
},
  "geometry": {"coordinates":[141.28173000000001,38.42415],"type":"Point"}
}