{
  "type": "Feature",
  "properties": {
    "gn:admin1_code":"19.0",
    "gn:admin2_code":"1848308.0",
    "gn:asciiname":"Higashihemicho",
    "gn:country_code":"JP",
    "gn:dem":27,
    "gn:feature_class":"P",
    "gn:feature_code":"PPL",
    "gn:name":"Higashihemich\u014d",
    "gn:population":0,
    "gn:timezone":"Asia/Tokyo",
    "iso:country":"JP",
    "name:jpn_x_preferred":[
        "\u6771\u9038\u898b\u753a"
    ],
    "name:jpn_x_variant":[
        "\u3072\u304c\u3057\u3078\u307f\u3061\u3087\u3046",
        "\u30d2\u30ac\u30b7\u30d8\u30df\u30c1\u30e7\u30a6"
    ],
    "name:und_x_variant":[
        "Higashihemich\u014d"
    ],
    "wof:name":"Higashihemicho",
    "wof:placetype":"locality"
},
  "geometry": {"coordinates":[139.64971,35.27672000000001],"type":"Point"}
}