{
  "type": "Feature",
  "properties": {
    "gn:admin1_code":"29.0",
    "gn:admin2_code":"1855427.0",
    "gn:admin3_code":"15107.0",
    "gn:asciiname":"Onomachi",
    "gn:country_code":"JP",
    "gn:dem":-1,
    "gn:feature_class":"P",
    "gn:feature_code":"PPL",
    "gn:name":"\u014cnomachi",
    "gn:population":0,
    "gn:timezone":"Asia/Tokyo",
    "iso:country":"JP",
    "name:jpn_x_preferred":[
        "\u5927\u91ce\u753a"
    ],
    "name:und_x_variant":[
        "\u014cnomachi"
    ],
    "wof:name":"Onomachi",
    "wof:placetype":"locality"
},
  "geometry": {"coordinates":[139.01591999999999,37.8478],"type":"Point"}
}