{
  "type": "Feature",
  "properties": {
    "gn:admin1_code":"19",
    "gn:admin2_code":"7470890.0",
    "gn:asciiname":"Koichi",
    "gn:country_code":"JP",
    "gn:dem":76,
    "gn:feature_class":"P",
    "gn:feature_code":"PPLL",
    "gn:name":"Koichi",
    "gn:population":0,
    "gn:timezone":"Asia/Tokyo",
    "iso:country":"JP",
    "name:jpn_x_preferred":[
        "\u5c0f\u5e02"
    ],
    "wof:name":"Koichi",
    "wof:placetype":"locality"
},
  "geometry": {"coordinates":[139.10039,35.34681],"type":"Point"}
}