{
  "type": "Feature",
  "properties": {
    "gn:admin1_code":"4.0",
    "gn:admin2_code":"2111211.0",
    "gn:asciiname":"Shitengi",
    "gn:country_code":"JP",
    "gn:dem":0,
    "gn:feature_class":"P",
    "gn:feature_code":"PPL",
    "gn:name":"Shitengi",
    "gn:population":0,
    "gn:timezone":"Asia/Tokyo",
    "iso:country":"JP",
    "name:jpn_x_preferred":[
        "\u56db\u5929\u6728"
    ],
    "name:jpn_x_variant":[
        "\u3057\u3066\u3093\u304e",
        "\u30b7\u30c6\u30f3\u30ae"
    ],
    "wof:name":"Shitengi",
    "wof:placetype":"locality"
},
  "geometry": {"coordinates":[140.40291000000002,35.48031],"type":"Point"}
}