{
  "type": "Feature",
  "properties": {
    "gn:admin1_code":"21.0",
    "gn:admin2_code":"7413150.0",
    "gn:asciiname":"Hodata",
    "gn:country_code":"JP",
    "gn:dem":87,
    "gn:feature_class":"P",
    "gn:feature_code":"PPL",
    "gn:name":"Hodata",
    "gn:population":0,
    "gn:timezone":"Asia/Tokyo",
    "iso:country":"JP",
    "name:jpn_x_preferred":[
        "\u4fdd\u591a\u7530"
    ],
    "name:jpn_x_variant":[
        "\u307b\u3060\u305f",
        "\u30db\u30c0\u30bf"
    ],
    "wof:name":"Hodata",
    "wof:placetype":"locality"
},
  "geometry": {"coordinates":[130.65261000000001,33.00897],"type":"Point"}
}