{
  "type": "Feature",
  "properties": {
    "gn:admin1_code":"18",
    "gn:admin2_code":"1853737.0",
    "gn:admin3_code":"46535.0",
    "gn:asciiname":"Nama",
    "gn:country_code":"JP",
    "gn:dem":34,
    "gn:feature_class":"P",
    "gn:feature_code":"PPL",
    "gn:name":"Nama",
    "gn:population":0,
    "gn:timezone":"Asia/Tokyo",
    "iso:country":"JP",
    "name:ceb_x_preferred":[
        "Nama"
    ],
    "name:deu_x_preferred":[
        "Nama"
    ],
    "name:ell_x_preferred":[
        "\u039d\u03ac\u03bc\u03b1"
    ],
    "name:fin_x_preferred":[
        "Nama"
    ],
    "name:fra_x_preferred":[
        "Nama"
    ],
    "name:jpn_x_preferred":[
        "\u90a3\u9593"
    ],
    "name:nld_x_preferred":[
        "Nama"
    ],
    "name:pol_x_preferred":[
        "Nama"
    ],
    "name:por_x_preferred":[
        "Nama"
    ],
    "name:swe_x_preferred":[
        "Nama"
    ],
    "wof:name":"Nama",
    "wof:placetype":"locality"
},
  "geometry": {"coordinates":[128.43738000000002,27.05265],"type":"Point"}
}