{
  "type": "Feature",
  "properties": {
    "iso:country":"JP",
    "qs:name":"\uff12\u4e01\u76ee",
    "qs:name_adm0":"\u65e5\u672c",
    "qs:name_adm1":"\u5927\u962a\u5e9c",
    "qs:photos":69,
    "qs:photos_1k":14,
    "qs:photos_9k":1,
    "qs:photos_9r":2,
    "qs:photos_all":69,
    "qs:photos_sr":2,
    "qs:placetype":"Suburb",
    "qs:pop_sr":"0",
    "wof:name":"\uff12\u4e01\u76ee",
    "wof:placetype":"neighbourhood"
},
  "geometry": {"coordinates":[135.53156000000001,34.693238],"type":"Point"}
}