{
  "type": "Feature",
  "properties": {
    "iso:country":"JP",
    "name:eng_x_preferred":[
        "Motomachidori 2 Chome"
    ],
    "name:eng_x_variant":[
        "Motomachidoori 2 Choume",
        "Motomachidori 2 Chome"
    ],
    "name:jpn_x_preferred":[
        "\uff12\u4e01\u76ee"
    ],
    "name:jpn_x_variant":[
        "\u3082\u3068\u307e\u3061\u3069\u304a\u308a \uff12\u3061\u3087\u3046\u3081",
        "\u5143\u753a\u901a \uff12\u4e01\u76ee",
        "\uff12\u3061\u3087\u3046\u3081"
    ],
    "qs:gn_local":0,
    "qs:local_max":2400,
    "qs:local_sum":22318,
    "qs:localhoods":72,
    "qs:name":"\uff12\u4e01\u76ee",
    "qs:name_adm0":"\u65e5\u672c",
    "qs:name_adm1":"\u5175\u5eab\u770c",
    "qs:name_adm2":"\u4e2d\u592e\u533a",
    "qs:name_en":"Motomachidori 2 Chome",
    "qs:name_lau":"\u5143\u753a\u901a",
    "qs:name_local":"\u795e\u6238\u5e02",
    "qs:photo_max":140,
    "qs:photo_sum":348,
    "qs:placetype":"Suburb",
    "qs:quad_count":9,
    "qs:woe_adm0":23424856,
    "qs:woe_adm1":2345862,
    "qs:woe_adm2":15015438,
    "qs:woe_lau":28461228,
    "qs:woe_local":1117545,
    "qs:woe_ver":"7.10.0",
    "wof:lang":[
        "jpn"
    ],
    "wof:name":"\uff12\u4e01\u76ee",
    "wof:placetype":"neighbourhood"
},
  "geometry": {"coordinates":[135.18796,34.688151],"type":"Point"}
}