{
  "type": "Feature",
  "properties": {
    "gn:admin1_code":"12.0",
    "gn:admin2_code":"7428109.0",
    "gn:admin3_code":"1668.0",
    "gn:asciiname":"Hidarimata",
    "gn:country_code":"JP",
    "gn:dem":217,
    "gn:feature_class":"P",
    "gn:feature_code":"PPL",
    "gn:name":"Hidarimata",
    "gn:population":0,
    "gn:timezone":"Asia/Tokyo",
    "iso:country":"JP",
    "name:jpn_x_preferred":[
        "\u5de6\u80a1"
    ],
    "name:jpn_x_variant":[
        "\u3072\u3060\u308a\u307e\u305f",
        "\u30d2\u30c0\u30ea\u30de\u30bf"
    ],
    "wof:name":"Hidarimata",
    "wof:placetype":"locality"
},
  "geometry": {"coordinates":[143.86671999999999,43.17803],"type":"Point"}
}