{
  "type": "Feature",
  "properties": {
    "gn:admin1_code":"5.0",
    "gn:admin2_code":"1926135.0",
    "gn:asciiname":"Mihocho",
    "gn:country_code":"JP",
    "gn:dem":5,
    "gn:feature_class":"P",
    "gn:feature_code":"PPL",
    "gn:name":"Mihoch\u014d",
    "gn:population":0,
    "gn:timezone":"Asia/Tokyo",
    "iso:country":"JP",
    "name:und_x_variant":[
        "Mihoch\u014d"
    ],
    "wof:name":"Mihocho",
    "wof:placetype":"locality"
},
  "geometry": {"coordinates":[132.99916999999999,34.07389000000001],"type":"Point"}
}