{
  "type": "Feature",
  "properties": {
    "gn:admin1_code":"18.0",
    "gn:admin2_code":"7383999.0",
    "gn:admin3_code":"46492.0",
    "gn:asciiname":"Kisanuki",
    "gn:country_code":"JP",
    "gn:dem":50,
    "gn:feature_class":"P",
    "gn:feature_code":"PPLL",
    "gn:name":"Kisanuki",
    "gn:population":0,
    "gn:timezone":"Asia/Tokyo",
    "iso:country":"JP",
    "name:jpn_x_preferred":[
        "\u6728\u4f50\u8cab"
    ],
    "wof:name":"Kisanuki",
    "wof:placetype":"locality"
},
  "geometry": {"coordinates":[130.96352999999999,31.3185],"type":"Point"}
}