{
  "type": "Feature",
  "properties": {
    "gn:admin1_code":"01",
    "gn:admin2_code":"1851258.0",
    "gn:asciiname":"Noda",
    "gn:country_code":"JP",
    "gn:dem":48,
    "gn:feature_class":"P",
    "gn:feature_code":"PPL",
    "gn:name":"Noda",
    "gn:population":0,
    "gn:timezone":"Asia/Tokyo",
    "iso:country":"JP",
    "name:ceb_x_preferred":[
        "Noda"
    ],
    "name:deu_x_preferred":[
        "Noda"
    ],
    "name:fra_x_preferred":[
        "Noda"
    ],
    "name:lav_x_preferred":[
        "Noda"
    ],
    "name:mlg_x_preferred":[
        "Noda"
    ],
    "name:nld_x_preferred":[
        "Noda"
    ],
    "name:pol_x_preferred":[
        "Noda"
    ],
    "name:por_x_preferred":[
        "Noda"
    ],
    "name:spa_x_preferred":[
        "Noda"
    ],
    "name:swe_x_preferred":[
        "Noda"
    ],
    "wof:name":"Noda",
    "wof:placetype":"locality"
},
  "geometry": {"coordinates":[137.19999999999999,34.65],"type":"Point"}
}