{
  "type": "Feature",
  "properties": {
    "gn:admin1_code":"43.0",
    "gn:admin2_code":"1863079.0",
    "gn:asciiname":"Sakaibara",
    "gn:country_code":"JP",
    "gn:dem":176,
    "gn:feature_class":"P",
    "gn:feature_code":"PPL",
    "gn:name":"Sakaibara",
    "gn:population":0,
    "gn:timezone":"Asia/Tokyo",
    "iso:country":"JP",
    "name:jpn_x_preferred":[
        "\u5883\u539f"
    ],
    "wof:name":"Sakaibara",
    "wof:placetype":"locality"
},
  "geometry": {"coordinates":[135.62728000000001,34.35388],"type":"Point"}
}