{
  "type": "Feature",
  "properties": {
    "gn:admin1_code":"4.0",
    "gn:admin2_code":"1857552.0",
    "gn:asciiname":"Takatsuka-shinden",
    "gn:country_code":"JP",
    "gn:dem":25,
    "gn:feature_class":"P",
    "gn:feature_code":"PPL",
    "gn:name":"Takatsuka-shinden",
    "gn:population":0,
    "gn:timezone":"Asia/Tokyo",
    "iso:country":"JP",
    "name:jpn_x_preferred":[
        "\u9ad8\u585a\u65b0\u7530"
    ],
    "wof:name":"Takatsuka-shinden",
    "wof:placetype":"locality"
},
  "geometry": {"coordinates":[139.93433999999999,35.75485],"type":"Point"}
}