{
  "type": "Feature",
  "properties": {
    "gn:admin1_code":"4.0",
    "gn:admin2_code":"1859468.0",
    "gn:asciiname":"Yaehara",
    "gn:country_code":"JP",
    "gn:dem":37,
    "gn:feature_class":"P",
    "gn:feature_code":"PPL",
    "gn:name":"Yaehara",
    "gn:population":0,
    "gn:timezone":"Asia/Tokyo",
    "iso:country":"JP",
    "name:jpn_x_preferred":[
        "\u516b\u91cd\u539f"
    ],
    "name:jpn_x_variant":[
        "\u3084\u3048\u306f\u3089",
        "\u30e4\u30a8\u30cf\u30e9"
    ],
    "wof:name":"Yaehara",
    "wof:placetype":"locality"
},
  "geometry": {"coordinates":[139.93617,35.32754],"type":"Point"}
}