{
  "type": "Feature",
  "properties": {
    "gn:admin1_code":"2.0",
    "gn:admin2_code":"2113122.0",
    "gn:asciiname":"Kamishinjo-yunosato",
    "gn:country_code":"JP",
    "gn:dem":84,
    "gn:feature_class":"P",
    "gn:feature_code":"PPL",
    "gn:name":"Kamishinj\u014d-yunosato",
    "gn:population":0,
    "gn:timezone":"Asia/Tokyo",
    "iso:country":"JP",
    "name:jpn_x_preferred":[
        "\u4e0a\u65b0\u57ce\u6e6f\u30ce\u91cc"
    ],
    "name:jpn_x_variant":[
        "\u304b\u307f\u3057\u3093\u3058\u3087\u3046\u3086\u306e\u3055\u3068",
        "\u30ab\u30df\u30b7\u30f3\u30b8\u30e7\u30a6\u30e6\u30ce\u30b5\u30c8",
        "\u6e6f\u30ce\u91cc"
    ],
    "name:und_x_variant":[
        "Kamishinj\u014d-yunosato",
        "Yunosato"
    ],
    "wof:name":"Kamishinjo-yunosato",
    "wof:placetype":"locality"
},
  "geometry": {"coordinates":[140.13878,39.80529],"type":"Point"}
}