{
  "type": "Feature",
  "properties": {
    "gn:admin1_code":"21.0",
    "gn:admin2_code":"1865358.0",
    "gn:asciiname":"Kakizuka",
    "gn:country_code":"JP",
    "gn:dem":52,
    "gn:feature_class":"P",
    "gn:feature_code":"PPLL",
    "gn:name":"Kakizuka",
    "gn:population":0,
    "gn:timezone":"Asia/Tokyo",
    "iso:country":"JP",
    "name:jpn_x_preferred":[
        "\u67ff\u585a"
    ],
    "name:jpn_x_variant":[
        "\u304b\u304d\u3065\u304b",
        "\u30ab\u30ad\u30c5\u30ab"
    ],
    "wof:name":"Kakizuka",
    "wof:placetype":"locality"
},
  "geometry": {"coordinates":[130.25203999999999,32.41763],"type":"Point"}
}