{
  "type": "Feature",
  "properties": {
    "gn:admin1_code":"33.0",
    "gn:admin2_code":"7391358.0",
    "gn:admin3_code":"41423.0",
    "gn:asciiname":"Hatakeda",
    "gn:country_code":"JP",
    "gn:dem":9,
    "gn:feature_class":"P",
    "gn:feature_code":"PPLL",
    "gn:name":"Hatakeda",
    "gn:population":0,
    "gn:timezone":"Asia/Tokyo",
    "iso:country":"JP",
    "name:jpn_x_preferred":[
        "\u7551\u30f6\u7530"
    ],
    "wof:name":"Hatakeda",
    "wof:placetype":"locality"
},
  "geometry": {"coordinates":[130.12718000000001,33.21532],"type":"Point"}
}