{
  "type": "Feature",
  "properties": {
    "gn:admin1_code":"34.0",
    "gn:admin2_code":"1849187.0",
    "gn:admin3_code":"11103.0",
    "gn:asciiname":"Junocho",
    "gn:country_code":"JP",
    "gn:dem":16,
    "gn:feature_class":"P",
    "gn:feature_code":"PPL",
    "gn:name":"Jun\u014dch\u014d",
    "gn:population":0,
    "gn:timezone":"Asia/Tokyo",
    "iso:country":"JP",
    "name:jpn_x_preferred":[
        "\u5bff\u80fd\u753a"
    ],
    "name:und_x_variant":[
        "Jun\u014dch\u014d"
    ],
    "wof:name":"Junocho",
    "wof:placetype":"locality"
},
  "geometry": {"coordinates":[139.63489999999999,35.92185],"type":"Point"}
}