{
  "type": "Feature",
  "properties": {
    "gn:admin1_code":"4.0",
    "gn:admin2_code":"2112997.0",
    "gn:admin3_code":"12422.0",
    "gn:asciiname":"Chorakuji",
    "gn:country_code":"JP",
    "gn:dem":17,
    "gn:feature_class":"P",
    "gn:feature_code":"PPL",
    "gn:name":"Ch\u014drakuji",
    "gn:population":0,
    "gn:timezone":"Asia/Tokyo",
    "iso:country":"JP",
    "name:jpn_x_preferred":[
        "\u9577\u697d\u5bfa"
    ],
    "name:jpn_x_variant":[
        "\u3061\u3087\u3046\u3089\u304f\u3058",
        "\u30c1\u30e7\u30a6\u30e9\u30af\u30b8"
    ],
    "name:und_x_variant":[
        "Ch\u014drakuji"
    ],
    "wof:name":"Chorakuji",
    "wof:placetype":"locality"
},
  "geometry": {"coordinates":[140.29901000000001,35.36009],"type":"Point"}
}