{
  "type": "Feature",
  "properties": {
    "gn:admin1_code":"7.0",
    "gn:admin2_code":"7407413.0",
    "gn:asciiname":"Mizoguchi",
    "gn:country_code":"JP",
    "gn:dem":64,
    "gn:feature_class":"P",
    "gn:feature_code":"PPLL",
    "gn:name":"Mizoguchi",
    "gn:population":0,
    "gn:timezone":"Asia/Tokyo",
    "iso:country":"JP",
    "name:jpn_x_preferred":[
        "\u6e9d\u53e3"
    ],
    "name:rus_x_preferred":[
        "\u041c\u0438\u0434\u0437\u043e\u0433\u0443\u0442\u0438"
    ],
    "wof:name":"Mizoguchi",
    "wof:placetype":"locality"
},
  "geometry": {"coordinates":[130.70954,33.53324],"type":"Point"}
}