{
  "type": "Feature",
  "properties": {
    "gn:admin1_code":"21.0",
    "gn:admin2_code":"1865358.0",
    "gn:asciiname":"Nigaki",
    "gn:country_code":"JP",
    "gn:dem":155,
    "gn:feature_class":"P",
    "gn:feature_code":"PPLL",
    "gn:name":"Nigaki",
    "gn:population":0,
    "gn:timezone":"Asia/Tokyo",
    "iso:country":"JP",
    "name:jpn_x_preferred":[
        "\u4e8c\u57a3"
    ],
    "name:jpn_x_variant":[
        "\u306b\u304c\u304d",
        "\u30cb\u30ac\u30ad"
    ],
    "wof:name":"Nigaki",
    "wof:placetype":"locality"
},
  "geometry": {"coordinates":[130.18188000000001,32.31756],"type":"Point"}
}