{
  "type": "Feature",
  "properties": {
    "gn:admin1_code":"29",
    "gn:admin2_code":"1860992.0",
    "gn:asciiname":"Nadachi",
    "gn:cc2":"JP",
    "gn:country_code":"JP",
    "gn:dem":41,
    "gn:feature_class":"P",
    "gn:feature_code":"PPL",
    "gn:name":"Nadachi",
    "gn:population":0,
    "gn:timezone":"Asia/Tokyo",
    "iso:country":"JP",
    "name:und_x_variant":[
        "Natachi",
        "Nadachimachi",
        "Natachi\u014dmachi",
        "Nadachi\u014dmachi",
        "Nadati Mati",
        "Nadachi"
    ],
    "wof:name":"Nadachi",
    "wof:placetype":"locality"
},
  "geometry": {"coordinates":[138.09999999999999,37.15],"type":"Point"}
}