{
  "type": "Feature",
  "properties": {
    "gn:admin1_code":"45.0",
    "gn:admin2_code":"1852222.0",
    "gn:asciiname":"Fujigatanicho",
    "gn:country_code":"JP",
    "gn:dem":42,
    "gn:feature_class":"P",
    "gn:feature_code":"PPL",
    "gn:name":"Fujigatanich\u014d",
    "gn:population":0,
    "gn:timezone":"Asia/Tokyo",
    "iso:country":"JP",
    "name:jpn_x_preferred":[
        "\u85e4\u30f6\u8c37\u753a"
    ],
    "name:und_x_variant":[
        "Fujigatanich\u014d"
    ],
    "wof:name":"Fujigatanicho",
    "wof:placetype":"locality"
},
  "geometry": {"coordinates":[130.95384999999999,33.98098],"type":"Point"}
}