{
  "type": "Feature",
  "properties": {
    "iso:country":"JP",
    "name:jpn_x_preferred":[
        "\uff08\u4e01\u76ee\u306a\u3057\uff09"
    ],
    "qs:gn_adm0_cc":"JP",
    "qs:gn_local":1926099,
    "qs:gn_nam_loc":"\u677e\u5c71\u5e02, \u611b\u5a9b\u770c, JP",
    "qs:gn_namadm1":"05",
    "qs:local_max":845,
    "qs:local_sum":2298,
    "qs:localhoods":15,
    "qs:name":"\uff08\u4e01\u76ee\u306a\u3057\uff09",
    "qs:name_adm0":"\u65e5\u672c",
    "qs:name_adm1":"\u611b\u5a9b\u770c",
    "qs:name_lau":"\u7af9\u539f\u753a",
    "qs:name_local":"\u677e\u5c71\u5e02",
    "qs:photo_max":18,
    "qs:photo_sum":22,
    "qs:placetype":"Suburb",
    "qs:quad_count":4,
    "qs:woe_adm0":23424856,
    "qs:woe_adm1":2345855,
    "qs:woe_adm2":0,
    "qs:woe_lau":28479140,
    "qs:woe_local":1117690,
    "qs:woe_ver":"7.10.0",
    "qs_pg:name":"\uff08\u4e01\u76ee\u306a\u3057\uff09",
    "qs_pg:name_adm0":"\u65e5\u672c",
    "qs_pg:name_adm1":"\u611b\u5a9b\u770c",
    "qs_pg:photos":6,
    "qs_pg:photos_1k":1,
    "qs_pg:photos_9k":1,
    "qs_pg:photos_9r":1,
    "qs_pg:photos_all":6,
    "qs_pg:photos_sr":1,
    "qs_pg:pop_sr":0,
    "qs_pg:qs_pg_placetype":"neighbourhood",
    "qs_pg:qs_pg_placetype_gp":"Suburb",
    "qs_pg:woe_adm0":23424856,
    "woe:adm0_id":23424856,
    "woe:name_adm0":"\u65e5\u672c",
    "woe:name_adm1":"\u611b\u5a9b\u770c",
    "woe:placetype":"Suburb",
    "wof:lang":[
        "jpn"
    ],
    "wof:name":"\uff08\u4e01\u76ee\u306a\u3057\uff09",
    "wof:placetype":"neighbourhood"
},
  "geometry": {"coordinates":[132.75535600000001,33.840383],"type":"Point"}
}