{
  "type": "Feature",
  "properties": {
    "gn:admin1_code":"29.0",
    "gn:admin2_code":"1852604.0",
    "gn:asciiname":"Nakanakayama",
    "gn:country_code":"JP",
    "gn:dem":123,
    "gn:feature_class":"P",
    "gn:feature_code":"PPL",
    "gn:name":"Nakanakayama",
    "gn:population":0,
    "gn:timezone":"Asia/Tokyo",
    "iso:country":"JP",
    "name:jpn_x_preferred":[
        "\u4e2d\u3005\u5c71"
    ],
    "wof:name":"Nakanakayama",
    "wof:placetype":"locality"
},
  "geometry": {"coordinates":[139.41123999999999,37.85521],"type":"Point"}
}