{
  "type": "Feature",
  "properties": {
    "iso:country":"JP",
    "name:eng_x_preferred":[
        "Fukiagehoncho 4 Chome"
    ],
    "name:eng_x_variant":[
        "Fukiagehonchou 4 Choume",
        "Fukiagehoncho 4 Chome"
    ],
    "name:jpn_x_preferred":[
        "\uff14\u4e01\u76ee"
    ],
    "name:jpn_x_variant":[
        "\u3075\u304d\u3042\u3052\u307b\u3093\u3061\u3087\u3046 \uff14\u3061\u3087\u3046\u3081",
        "\u5439\u4e0a\u672c\u753a \uff14\u4e01\u76ee",
        "\uff14\u3061\u3087\u3046\u3081"
    ],
    "qs:gn_local":0,
    "qs:local_max":159,
    "qs:local_sum":244,
    "qs:localhoods":4,
    "qs:name":"\uff14\u4e01\u76ee",
    "qs:name_adm0":"\u65e5\u672c",
    "qs:name_adm1":"\u57fc\u7389\u770c",
    "qs:name_en":"Fukiagehoncho 4 Chome",
    "qs:name_lau":"\u5439\u4e0a\u672c\u753a",
    "qs:name_local":"\u9d3b\u5de3\u5e02",
    "qs:photo_max":10,
    "qs:photo_sum":10,
    "qs:placetype":"Suburb",
    "qs:quad_count":1,
    "qs:woe_adm0":23424856,
    "qs:woe_adm1":2345883,
    "qs:woe_adm2":0,
    "qs:woe_lau":28408984,
    "qs:woe_local":1117572,
    "qs:woe_ver":"7.10.0",
    "wof:lang":[
        "jpn"
    ],
    "wof:name":"\uff14\u4e01\u76ee",
    "wof:placetype":"neighbourhood"
},
  "geometry": {"coordinates":[139.45220900000001,36.104595],"type":"Point"}
}