{
  "type": "Feature",
  "properties": {
    "gn:admin1_code":"19.0",
    "gn:admin2_code":"1865009.0",
    "gn:admin3_code":"14382.0",
    "gn:asciiname":"Miyagino",
    "gn:country_code":"JP",
    "gn:dem":502,
    "gn:feature_class":"P",
    "gn:feature_code":"PPL",
    "gn:name":"Miyagino",
    "gn:population":0,
    "gn:timezone":"Asia/Tokyo",
    "iso:country":"JP",
    "name:jpn_x_preferred":[
        "\u5bae\u57ce\u91ce"
    ],
    "wof:name":"Miyagino",
    "wof:placetype":"locality"
},
  "geometry": {"coordinates":[139.0558,35.25172],"type":"Point"}
}