{
  "type": "Feature",
  "properties": {
    "gn:admin1_code":"21.0",
    "gn:admin2_code":"7412708.0",
    "gn:admin3_code":"43512.0",
    "gn:asciiname":"Shinso",
    "gn:country_code":"JP",
    "gn:dem":187,
    "gn:feature_class":"P",
    "gn:feature_code":"PPLL",
    "gn:name":"Shins\u014d",
    "gn:population":0,
    "gn:timezone":"Asia/Tokyo",
    "iso:country":"JP",
    "name:jpn_x_preferred":[
        "\u65b0\u5c64"
    ],
    "name:und_x_variant":[
        "Shins\u014d"
    ],
    "wof:name":"Shinso",
    "wof:placetype":"locality"
},
  "geometry": {"coordinates":[130.79268000000002,32.24965],"type":"Point"}
}