{
  "type": "Feature",
  "properties": {
    "gn:admin1_code":"21.0",
    "gn:admin2_code":"1864975.0",
    "gn:admin3_code":"43424.0",
    "gn:asciiname":"Kashiwada",
    "gn:country_code":"JP",
    "gn:dem":427,
    "gn:feature_class":"P",
    "gn:feature_code":"PPLL",
    "gn:name":"Kashiwada",
    "gn:population":0,
    "gn:timezone":"Asia/Tokyo",
    "iso:country":"JP",
    "name:jpn_x_preferred":[
        "\u67cf\u7530"
    ],
    "name:jpn_x_variant":[
        "\u304b\u3057\u308f\u3060",
        "\u30ab\u30b7\u30ef\u30c0"
    ],
    "wof:name":"Kashiwada",
    "wof:placetype":"locality"
},
  "geometry": {"coordinates":[131.06523999999999,33.12566],"type":"Point"}
}