{
  "type": "Feature",
  "properties": {
    "iso:country":"JP",
    "name:jpn_x_preferred":[
        "\uff08\u4e01\u76ee\u306a\u3057\uff09"
    ],
    "name:unk_x_variant":[
        "\uff08\u4e01\u76ee\u306a\u3057\uff09"
    ],
    "qs:gn_local":0,
    "qs:local_max":603,
    "qs:local_sum":1870,
    "qs:localhoods":15,
    "qs:name":"\uff08\u4e01\u76ee\u306a\u3057\uff09",
    "qs:name_adm0":"\u65e5\u672c",
    "qs:name_adm1":"\u5343\u8449\u770c",
    "qs:name_lau":"\u516b\u30b1\u5d0e",
    "qs:name_local":"\u677e\u6238\u5e02",
    "qs:photo_max":63,
    "qs:photo_sum":91,
    "qs:placetype":"Suburb",
    "qs:quad_count":8,
    "qs:woe_adm0":23424856,
    "qs:woe_adm1":2345854,
    "qs:woe_adm2":0,
    "qs:woe_lau":28411232,
    "qs:woe_local":1111642,
    "qs:woe_ver":"7.10.0",
    "wof:lang":[
        "jpn"
    ],
    "wof:name":"\uff08\u4e01\u76ee\u306a\u3057\uff09",
    "wof:placetype":"neighbourhood"
},
  "geometry": {"coordinates":[139.93357900000001,35.819929],"type":"Point"}
}