{
  "type": "Feature",
  "properties": {
    "gn:admin1_code":"18.0",
    "gn:admin2_code":"1853737.0",
    "gn:admin3_code":"46532.0",
    "gn:asciiname":"Metegu",
    "gn:country_code":"JP",
    "gn:dem":39,
    "gn:feature_class":"P",
    "gn:feature_code":"PPL",
    "gn:name":"Metegu",
    "gn:population":0,
    "gn:timezone":"Asia/Tokyo",
    "iso:country":"JP",
    "name:jpn_x_preferred":[
        "\u76ee\u624b\u4e45"
    ],
    "wof:name":"Metegu",
    "wof:placetype":"locality"
},
  "geometry": {"coordinates":[128.98139,27.68089],"type":"Point"}
}