{
  "type": "Feature",
  "properties": {
    "gn:admin1_code":"6.0",
    "gn:admin2_code":"1854517.0",
    "gn:admin3_code":"18481.0",
    "gn:asciiname":"Konoura",
    "gn:country_code":"JP",
    "gn:dem":22,
    "gn:feature_class":"P",
    "gn:feature_code":"PPL",
    "gn:name":"K\u014dnoura",
    "gn:population":0,
    "gn:timezone":"Asia/Tokyo",
    "iso:country":"JP",
    "name:und_x_variant":[
        "K\u014dnoura"
    ],
    "wof:name":"Konoura",
    "wof:placetype":"locality"
},
  "geometry": {"coordinates":[135.48556000000002,35.52194],"type":"Point"}
}