{
  "type": "Feature",
  "properties": {
    "gn:admin1_code":"26",
    "gn:admin2_code":"1861858.0",
    "gn:asciiname":"Wada",
    "gn:country_code":"JP",
    "gn:dem":562,
    "gn:feature_class":"P",
    "gn:feature_code":"PPL",
    "gn:name":"Wada",
    "gn:population":0,
    "gn:timezone":"Asia/Tokyo",
    "iso:country":"JP",
    "name:ceb_x_preferred":[
        "Wada"
    ],
    "name:deu_x_preferred":[
        "Wada"
    ],
    "name:fra_x_preferred":[
        "Wada"
    ],
    "name:mar_x_preferred":[
        "\u0935\u093e\u0921\u093e"
    ],
    "name:pol_x_preferred":[
        "Wada"
    ],
    "name:rus_x_preferred":[
        "\u0412\u0430\u0434\u0430"
    ],
    "name:swe_x_preferred":[
        "Wada"
    ],
    "wof:name":"Wada",
    "wof:placetype":"locality"
},
  "geometry": {"coordinates":[137.93333000000001,35.31667],"type":"Point"}
}