{
  "type": "Feature",
  "properties": {
    "gn:admin1_code":"6.0",
    "gn:admin2_code":"1854875.0",
    "gn:admin3_code":"18423.0",
    "gn:asciiname":"Amadani",
    "gn:country_code":"JP",
    "gn:dem":148,
    "gn:feature_class":"P",
    "gn:feature_code":"PPL",
    "gn:name":"Amadani",
    "gn:population":0,
    "gn:timezone":"Asia/Tokyo",
    "iso:country":"JP",
    "name:jpn_x_preferred":[
        "\u5929\u8c37"
    ],
    "wof:name":"Amadani",
    "wof:placetype":"locality"
},
  "geometry": {"coordinates":[136.06122999999999,36.02197],"type":"Point"}
}