{
  "type": "Feature",
  "properties": {
    "gn:admin1_code":"28.0",
    "gn:admin2_code":"7412212.0",
    "gn:asciiname":"Haibara-akabane",
    "gn:country_code":"JP",
    "gn:dem":441,
    "gn:feature_class":"P",
    "gn:feature_code":"PPL",
    "gn:name":"Haibara-akabane",
    "gn:population":0,
    "gn:timezone":"Asia/Tokyo",
    "iso:country":"JP",
    "name:jpn_x_preferred":[
        "\u699b\u539f\u8d64\u57f4"
    ],
    "wof:name":"Haibara-akabane",
    "wof:placetype":"locality"
},
  "geometry": {"coordinates":[136.00308999999999,34.51075],"type":"Point"}
}