{
  "type": "Feature",
  "properties": {
    "gn:admin1_code":"19.0",
    "gn:admin2_code":"1848595.0",
    "gn:asciiname":"Umenokishita",
    "gn:country_code":"JP",
    "gn:dem":36,
    "gn:feature_class":"P",
    "gn:feature_code":"PPLL",
    "gn:name":"Umenokishita",
    "gn:population":0,
    "gn:timezone":"Asia/Tokyo",
    "iso:country":"JP",
    "name:jpn_x_preferred":[
        "\u6885\u30ce\u6728\u4e0b"
    ],
    "wof:name":"Umenokishita",
    "wof:placetype":"locality"
},
  "geometry": {"coordinates":[139.47128000000001,35.4245],"type":"Point"}
}