{
  "type": "Feature",
  "properties": {
    "gn:admin1_code":"19.0",
    "gn:admin2_code":"1858593.0",
    "gn:admin3_code":"14321.0",
    "gn:asciiname":"Omagari",
    "gn:country_code":"JP",
    "gn:dem":6,
    "gn:feature_class":"P",
    "gn:feature_code":"PPL",
    "gn:name":"\u014cmagari",
    "gn:population":0,
    "gn:timezone":"Asia/Tokyo",
    "iso:country":"JP",
    "name:jpn_x_preferred":[
        "\u5927\u66f2"
    ],
    "name:und_x_variant":[
        "\u014cmagari"
    ],
    "wof:name":"Omagari",
    "wof:placetype":"locality"
},
  "geometry": {"coordinates":[139.3929,35.35720999999999],"type":"Point"}
}