{
  "type": "Feature",
  "properties": {
    "gn:admin1_code":"26.0",
    "gn:admin2_code":"1855829.0",
    "gn:asciiname":"Kasahara",
    "gn:country_code":"JP",
    "gn:dem":351,
    "gn:feature_class":"P",
    "gn:feature_code":"PPL",
    "gn:name":"Kasahara",
    "gn:population":0,
    "gn:timezone":"Asia/Tokyo",
    "iso:country":"JP",
    "name:deu_x_preferred":[
        "Kasahara"
    ],
    "name:fra_x_preferred":[
        "Kasahara"
    ],
    "name:ita_x_preferred":[
        "Kasahara"
    ],
    "name:jpn_x_preferred":[
        "\u7b20\u539f"
    ],
    "name:rus_x_preferred":[
        "\u041a\u0430\u0441\u0430\u0445\u0430\u0440\u0430"
    ],
    "wof:name":"Kasahara",
    "wof:placetype":"locality"
},
  "geometry": {"coordinates":[138.35651999999999,36.7796],"type":"Point"}
}