{
  "type": "Feature",
  "properties": {
    "gn:admin1_code":"21.0",
    "gn:admin2_code":"7413152.0",
    "gn:asciiname":"Kurosaki",
    "gn:country_code":"JP",
    "gn:dem":24,
    "gn:feature_class":"P",
    "gn:feature_code":"PPLL",
    "gn:name":"Kurosaki",
    "gn:population":0,
    "gn:timezone":"Asia/Tokyo",
    "iso:country":"JP",
    "name:deu_x_preferred":[
        "Kurosaki"
    ],
    "name:jpn_x_preferred":[
        "\u9ed2\u5d0e"
    ],
    "name:jpn_x_variant":[
        "\u304f\u308d\u3055\u304d",
        "\u30af\u30ed\u30b5\u30ad"
    ],
    "name:kor_x_preferred":[
        "\uad6c\ub85c\uc0ac\ud0a4"
    ],
    "name:rus_x_preferred":[
        "\u041a\u0443\u0440\u043e\u0441\u0430\u043a\u0438"
    ],
    "wof:name":"Kurosaki",
    "wof:placetype":"locality"
},
  "geometry": {"coordinates":[130.50027,32.61347],"type":"Point"}
}