{
  "type": "Feature",
  "properties": {
    "gn:admin1_code":"4.0",
    "gn:admin2_code":"8304237.0",
    "gn:asciiname":"Tsukiji",
    "gn:country_code":"JP",
    "gn:dem":3,
    "gn:feature_class":"P",
    "gn:feature_code":"PPL",
    "gn:name":"Tsukiji",
    "gn:population":0,
    "gn:timezone":"Asia/Tokyo",
    "iso:country":"JP",
    "name:jpn_x_preferred":[
        "\u7bc9\u5730"
    ],
    "name:jpn_x_variant":[
        "\u3064\u304d\u3058",
        "\u30c4\u30ad\u30b8"
    ],
    "wof:name":"Tsukiji",
    "wof:placetype":"locality"
},
  "geometry": {"coordinates":[139.90000000000001,35.35889],"type":"Point"}
}