{
  "type": "Feature",
  "properties": {
    "gn:admin1_code":"21.0",
    "gn:admin2_code":"1865168.0",
    "gn:asciiname":"Taishomachi",
    "gn:country_code":"JP",
    "gn:dem":2,
    "gn:feature_class":"P",
    "gn:feature_code":"PPL",
    "gn:name":"Taish\u014dmachi",
    "gn:population":0,
    "gn:timezone":"Asia/Tokyo",
    "iso:country":"JP",
    "name:jpn_x_preferred":[
        "\u5927\u6b63\u753a"
    ],
    "name:jpn_x_variant":[
        "\u305f\u3044\u3057\u3087\u3046\u307e\u3061",
        "\u30bf\u30a4\u30b7\u30e7\u30a6\u30de\u30c1"
    ],
    "name:und_x_variant":[
        "Taish\u014dmachi"
    ],
    "wof:name":"Taishomachi",
    "wof:placetype":"locality"
},
  "geometry": {"coordinates":[130.43361000000002,32.9963],"type":"Point"}
}