{
  "type": "Feature",
  "properties": {
    "gn:admin1_code":"21.0",
    "gn:admin2_code":"1858418.0",
    "gn:admin3_code":"43104.0",
    "gn:asciiname":"Tomiaimachi-komonoe",
    "gn:country_code":"JP",
    "gn:dem":1,
    "gn:feature_class":"P",
    "gn:feature_code":"PPL",
    "gn:name":"Tomiaimachi-komonoe",
    "gn:population":0,
    "gn:timezone":"Asia/Tokyo",
    "iso:country":"JP",
    "name:jpn_x_preferred":[
        "\u5bcc\u5408\u753a\u83f0\u6c5f"
    ],
    "name:jpn_x_variant":[
        "\u3068\u307f\u3042\u3044\u307e\u3061\u3053\u3082\u306e\u3048",
        "\u30c8\u30df\u30a2\u30a4\u30de\u30c1\u30b3\u30e2\u30ce\u30a8"
    ],
    "wof:name":"Tomiaimachi-komonoe",
    "wof:placetype":"locality"
},
  "geometry": {"coordinates":[130.66036,32.7229],"type":"Point"}
}