{
  "type": "Feature",
  "properties": {
    "gn:admin1_code":"21.0",
    "gn:admin2_code":"7412705.0",
    "gn:admin3_code":"43482.0",
    "gn:asciiname":"Takaoka",
    "gn:country_code":"JP",
    "gn:dem":236,
    "gn:feature_class":"P",
    "gn:feature_code":"PPL",
    "gn:name":"Takaoka",
    "gn:population":0,
    "gn:timezone":"Asia/Tokyo",
    "iso:country":"JP",
    "name:ceb_x_preferred":[
        "Takaoka"
    ],
    "name:deu_x_preferred":[
        "Takaoka"
    ],
    "name:epo_x_preferred":[
        "Takaoka"
    ],
    "name:jpn_x_preferred":[
        "\u9ad8\u5ca1"
    ],
    "name:jpn_x_variant":[
        "\u305f\u304b\u304a\u304b",
        "\u30bf\u30ab\u30aa\u30ab"
    ],
    "name:kor_x_preferred":[
        "\ub2e4\uce74\uc624\uce74"
    ],
    "wof:name":"Takaoka",
    "wof:placetype":"locality"
},
  "geometry": {"coordinates":[130.50118000000001,32.21772],"type":"Point"}
}