{
  "type": "Feature",
  "properties": {
    "gn:admin1_code":"10.0",
    "gn:admin2_code":"7453747.0",
    "gn:admin3_code":"10424.0",
    "gn:asciiname":"Yokokabe",
    "gn:country_code":"JP",
    "gn:dem":667,
    "gn:feature_class":"P",
    "gn:feature_code":"PPL",
    "gn:name":"Yokokabe",
    "gn:population":0,
    "gn:timezone":"Asia/Tokyo",
    "iso:country":"JP",
    "name:jpn_x_preferred":[
        "\u6a2a\u58c1"
    ],
    "wof:name":"Yokokabe",
    "wof:placetype":"locality"
},
  "geometry": {"coordinates":[138.66248000000002,36.53732],"type":"Point"}
}