{
  "type": "Feature",
  "properties": {
    "gn:admin1_code":"4.0",
    "gn:admin2_code":"7465524.0",
    "gn:asciiname":"Bando",
    "gn:country_code":"JP",
    "gn:dem":6,
    "gn:feature_class":"P",
    "gn:feature_code":"PPLL",
    "gn:name":"Band\u014d",
    "gn:population":0,
    "gn:timezone":"Asia/Tokyo",
    "iso:country":"JP",
    "name:jpn_x_preferred":[
        "\u5742\u6771"
    ],
    "name:jpn_x_variant":[
        "\u3070\u3093\u3069\u3046",
        "\u30d0\u30f3\u30c9\u30a6"
    ],
    "name:und_x_variant":[
        "Band\u014d"
    ],
    "wof:name":"Bando",
    "wof:placetype":"locality"
},
  "geometry": {"coordinates":[140.40021000000002,35.24998],"type":"Point"}
}