{
  "type": "Feature",
  "properties": {
    "gn:admin1_code":"44.0",
    "gn:admin2_code":"1849562.0",
    "gn:asciiname":"Tsujikoya",
    "gn:country_code":"JP",
    "gn:dem":5,
    "gn:feature_class":"P",
    "gn:feature_code":"PPL",
    "gn:name":"Tsujik\u014dya",
    "gn:population":0,
    "gn:timezone":"Asia/Tokyo",
    "iso:country":"JP",
    "name:jpn_x_preferred":[
        "\u8fbb\u8208\u5c4b"
    ],
    "name:und_x_variant":[
        "Tsujik\u014dya"
    ],
    "wof:name":"Tsujikoya",
    "wof:placetype":"locality"
},
  "geometry": {"coordinates":[139.80794,38.78735],"type":"Point"}
}