{
  "type": "Feature",
  "properties": {
    "gn:admin1_code":"16.0",
    "gn:admin2_code":"2128940.0",
    "gn:asciiname":"Shimokaijo",
    "gn:country_code":"JP",
    "gn:dem":121,
    "gn:feature_class":"P",
    "gn:feature_code":"PPL",
    "gn:name":"Shimokaij\u014d",
    "gn:population":0,
    "gn:timezone":"Asia/Tokyo",
    "iso:country":"JP",
    "name:jpn_x_preferred":[
        "\u4e0b\u6d77\u4e0a"
    ],
    "name:jpn_x_variant":[
        "\u3057\u3082\u304b\u3044\u3058\u3087\u3046",
        "\u30b7\u30e2\u30ab\u30a4\u30b8\u30e7\u30a6"
    ],
    "name:und_x_variant":[
        "Shimokaij\u014d"
    ],
    "wof:name":"Shimokaijo",
    "wof:placetype":"locality"
},
  "geometry": {"coordinates":[141.25788,40.33042],"type":"Point"}
}