{
  "type": "Feature",
  "properties": {
    "gn:admin1_code":"27",
    "gn:admin2_code":"1856152.0",
    "gn:asciiname":"Sembonyama",
    "gn:cc2":"JP",
    "gn:country_code":"JP",
    "gn:dem":8,
    "gn:feature_class":"P",
    "gn:feature_code":"PPL",
    "gn:name":"Sembonyama",
    "gn:population":0,
    "gn:timezone":"Asia/Tokyo",
    "iso:country":"JP",
    "name:und_x_variant":[
        "Sembon",
        "Sembonyama"
    ],
    "wof:name":"Sembonyama",
    "wof:placetype":"locality"
},
  "geometry": {"coordinates":[129.84712999999999,32.70297],"type":"Point"}
}