{
  "type": "Feature",
  "properties": {
    "gn:admin1_code":"35.0",
    "gn:admin2_code":"1858984.0",
    "gn:asciiname":"Minakuchicho-nishihayashiguchi",
    "gn:country_code":"JP",
    "gn:dem":168,
    "gn:feature_class":"P",
    "gn:feature_code":"PPL",
    "gn:name":"Minakuchich\u014d-nishihayashiguchi",
    "gn:population":0,
    "gn:timezone":"Asia/Tokyo",
    "iso:country":"JP",
    "name:jpn_x_preferred":[
        "\u6c34\u53e3\u753a\u897f\u6797\u53e3"
    ],
    "name:und_x_variant":[
        "Minakuchich\u014d-nishihayashiguchi"
    ],
    "wof:name":"Minakuchicho-nishihayashiguchi",
    "wof:placetype":"locality"
},
  "geometry": {"coordinates":[136.16048999999998,34.97362],"type":"Point"}
}