{
  "type": "Feature",
  "properties": {
    "gn:admin1_code":"4.0",
    "gn:admin2_code":"1863903.0",
    "gn:asciiname":"Minamikaijin",
    "gn:country_code":"JP",
    "gn:dem":6,
    "gn:feature_class":"P",
    "gn:feature_code":"PPL",
    "gn:name":"Minamikaijin",
    "gn:population":0,
    "gn:timezone":"Asia/Tokyo",
    "iso:country":"JP",
    "name:jpn_x_preferred":[
        "\u5357\u6d77\u795e"
    ],
    "wof:name":"Minamikaijin",
    "wof:placetype":"locality"
},
  "geometry": {"coordinates":[139.96588,35.69702],"type":"Point"}
}