{
  "type": "Feature",
  "properties": {
    "gn:admin1_code":"4.0",
    "gn:admin2_code":"1857552.0",
    "gn:asciiname":"Monto-shinden",
    "gn:country_code":"JP",
    "gn:dem":3,
    "gn:feature_class":"P",
    "gn:feature_code":"PPL",
    "gn:name":"Monto-shinden",
    "gn:population":0,
    "gn:timezone":"Asia/Tokyo",
    "iso:country":"JP",
    "name:jpn_x_preferred":[
        "\u4e3b\u6c34\u65b0\u7530"
    ],
    "wof:name":"Monto-shinden",
    "wof:placetype":"locality"
},
  "geometry": {"coordinates":[139.89652000000001,35.82106],"type":"Point"}
}