{
  "type": "Feature",
  "properties": {
    "gn:admin1_code":"16.0",
    "gn:admin2_code":"2112822.0",
    "gn:asciiname":"Sakuramachi",
    "gn:country_code":"JP",
    "gn:dem":80,
    "gn:feature_class":"P",
    "gn:feature_code":"PPL",
    "gn:name":"Sakuramachi",
    "gn:population":0,
    "gn:timezone":"Asia/Tokyo",
    "iso:country":"JP",
    "name:jpn_x_preferred":[
        "\u685c\u753a"
    ],
    "name:jpn_x_variant":[
        "\u3055\u304f\u3089\u307e\u3061",
        "\u30b5\u30af\u30e9\u30de\u30c1"
    ],
    "wof:name":"Sakuramachi",
    "wof:placetype":"locality"
},
  "geometry": {"coordinates":[141.12039999999999,39.37679],"type":"Point"}
}