{
  "type": "Feature",
  "properties": {
    "gn:country":"JP",
    "gn:fcode":"ADM3",
    "gn:pop":0,
    "iso:country":"JP",
    "name:jpn_x_preferred":[
        "\u6771\u533a"
    ],
    "name:jpn_x_variant":[
        "\u3072\u304c\u3057\u304f",
        "\u798f\u5ca1\u5e02\u6771\u533a"
    ],
    "name:unk_x_variant":[
        "Higashi Ku"
    ],
    "qs:name":"Higashi-ku",
    "qs:photos_9r":0,
    "qs:photos_sr":0,
    "qs:pop_sr":"0",
    "wd:wordcount":92,
    "wof:name":"Higashi-ku",
    "wof:placetype":"localadmin",
    "wof:population":0
},
  "geometry": {"coordinates":[130.41879,33.65663],"type":"Point"}
}