{
  "type": "Feature",
  "properties": {
    "gn:admin1_code":"13",
    "gn:admin2_code":"1848845.0",
    "gn:asciiname":"Sekinomiya",
    "gn:country_code":"JP",
    "gn:dem":224,
    "gn:feature_class":"P",
    "gn:feature_code":"PPL",
    "gn:name":"Sekinomiya",
    "gn:population":0,
    "gn:timezone":"Asia/Tokyo",
    "iso:country":"JP",
    "wof:name":"Sekinomiya",
    "wof:placetype":"locality"
},
  "geometry": {"coordinates":[134.63333,35.36667],"type":"Point"}
}