{
  "type": "Feature",
  "properties": {
    "gn:admin1_code":"4.0",
    "gn:admin2_code":"2112997.0",
    "gn:admin3_code":"12422.0",
    "gn:asciiname":"Iizawa",
    "gn:country_code":"JP",
    "gn:dem":24,
    "gn:feature_class":"P",
    "gn:feature_code":"PPLL",
    "gn:name":"Iizawa",
    "gn:population":0,
    "gn:timezone":"Asia/Tokyo",
    "iso:country":"JP",
    "name:jpn_x_preferred":[
        "\u98ef\u6ca2"
    ],
    "name:jpn_x_variant":[
        "\u3044\u3044\u3056\u308f",
        "\u30a4\u30a4\u30b6\u30ef"
    ],
    "wof:name":"Iizawa",
    "wof:placetype":"locality"
},
  "geometry": {"coordinates":[140.29979,35.34546],"type":"Point"}
}