{
  "type": "Feature",
  "properties": {
    "gn:admin1_code":"21.0",
    "gn:admin2_code":"7413152.0",
    "gn:asciiname":"Senbo",
    "gn:country_code":"JP",
    "gn:dem":181,
    "gn:feature_class":"P",
    "gn:feature_code":"PPLL",
    "gn:name":"Senb\u014d",
    "gn:population":0,
    "gn:timezone":"Asia/Tokyo",
    "iso:country":"JP",
    "name:jpn_x_preferred":[
        "\u5343\u623f"
    ],
    "name:jpn_x_variant":[
        "\u305b\u3093\u307c\u3046",
        "\u30bb\u30f3\u30dc\u30a6"
    ],
    "name:und_x_variant":[
        "Senb\u014d"
    ],
    "wof:name":"Senbo",
    "wof:placetype":"locality"
},
  "geometry": {"coordinates":[130.54234,32.64796],"type":"Point"}
}