{
  "type": "Feature",
  "properties": {
    "gn:admin1_code":"18.0",
    "gn:admin2_code":"8300556.0",
    "gn:asciiname":"Funamacho",
    "gn:country_code":"JP",
    "gn:dem":27,
    "gn:feature_class":"P",
    "gn:feature_code":"PPL",
    "gn:name":"Funamach\u014d",
    "gn:population":0,
    "gn:timezone":"Asia/Tokyo",
    "iso:country":"JP",
    "name:jpn_x_preferred":[
        "\u8239\u9593\u753a"
    ],
    "name:und_x_variant":[
        "Funamach\u014d"
    ],
    "wof:name":"Funamacho",
    "wof:placetype":"locality"
},
  "geometry": {"coordinates":[130.77253999999999,31.38914],"type":"Point"}
}