{
  "type": "Feature",
  "properties": {
    "gn:admin1_code":"34.0",
    "gn:admin2_code":"8304215.0",
    "gn:asciiname":"Kashiwacho",
    "gn:country_code":"JP",
    "gn:dem":18,
    "gn:feature_class":"P",
    "gn:feature_code":"PPL",
    "gn:name":"Kashiwach\u014d",
    "gn:population":0,
    "gn:timezone":"Asia/Tokyo",
    "iso:country":"JP",
    "name:jpn_x_preferred":[
        "\u67cf\u753a"
    ],
    "name:jpn_x_variant":[
        "\u304b\u3057\u308f\u3061\u3087\u3046",
        "\u30ab\u30b7\u30ef\u30c1\u30e7\u30a6"
    ],
    "name:und_x_variant":[
        "Kashiwach\u014d"
    ],
    "wof:name":"Kashiwacho",
    "wof:placetype":"locality"
},
  "geometry": {"coordinates":[139.57005000000001,35.83157],"type":"Point"}
}