{
  "type": "Feature",
  "properties": {
    "gn:admin1_code":"2.0",
    "gn:admin2_code":"2128864.0",
    "gn:asciiname":"Madoyama",
    "gn:country_code":"JP",
    "gn:dem":169,
    "gn:feature_class":"P",
    "gn:feature_code":"PPLL",
    "gn:name":"Madoyama",
    "gn:population":0,
    "gn:timezone":"Asia/Tokyo",
    "iso:country":"JP",
    "name:jpn_x_preferred":[
        "\u7a93\u5c71"
    ],
    "wof:name":"Madoyama",
    "wof:placetype":"locality"
},
  "geometry": {"coordinates":[140.19398000000001,40.31205],"type":"Point"}
}