{
  "type": "Feature",
  "properties": {
    "gn:admin1_code":"45.0",
    "gn:admin2_code":"1852222.0",
    "gn:asciiname":"Shin'akada-minamimachi",
    "gn:country_code":"JP",
    "gn:dem":24,
    "gn:feature_class":"P",
    "gn:feature_code":"PPL",
    "gn:name":"Shin\u2019akada-minamimachi",
    "gn:population":0,
    "gn:timezone":"Asia/Tokyo",
    "iso:country":"JP",
    "name:jpn_x_preferred":[
        "\u65b0\u57a2\u7530\u5357\u753a"
    ],
    "name:und_x_variant":[
        "Shin\u2019akada-minamimachi"
    ],
    "wof:name":"Shin'akada-minamimachi",
    "wof:placetype":"locality"
},
  "geometry": {"coordinates":[130.91582,33.98716],"type":"Point"}
}