{
  "type": "Feature",
  "properties": {
    "iso:country":"JP",
    "name:eng_x_preferred":[
        "Shingu"
    ],
    "name:eng_x_variant":[
        "Shingu City"
    ],
    "name:jpn_x_preferred":[
        "\u65b0\u5bae\u5e02"
    ],
    "qs:name":"\u65b0\u5bae\u5e02",
    "qs:name_adm0":"\u65e5\u672c",
    "qs:name_adm1":"\u548c\u6b4c\u5c71\u770c",
    "qs:photos":320,
    "qs:photos_1k":65,
    "qs:photos_9k":2,
    "qs:photos_9r":5,
    "qs:photos_all":564,
    "qs:photos_sr":5,
    "qs:placetype":"Town",
    "qs:pop_sr":"0",
    "wof:name":"Shingu",
    "wof:placetype":"locality"
},
  "geometry": {"coordinates":[135.99411599999999,33.727195],"type":"Point"}
}