{
  "type": "Feature",
  "properties": {
    "gn:admin1_code":"24.0",
    "gn:admin2_code":"7447001.0",
    "gn:asciiname":"Odai",
    "gn:country_code":"JP",
    "gn:dem":15,
    "gn:feature_class":"P",
    "gn:feature_code":"PPL",
    "gn:name":"Odai",
    "gn:population":0,
    "gn:timezone":"Asia/Tokyo",
    "iso:country":"JP",
    "name:jpn_x_preferred":[
        "\u5c0f\u53f0"
    ],
    "name:jpn_x_variant":[
        "\u304a\u3060\u3044",
        "\u30aa\u30c0\u30a4"
    ],
    "wof:name":"Odai",
    "wof:placetype":"locality"
},
  "geometry": {"coordinates":[141.12233999999995,38.49076],"type":"Point"}
}