{
  "type": "Feature",
  "properties": {
    "gn:admin1_code":"47",
    "gn:admin2_code":"1849184.0",
    "gn:asciiname":"Nakanishi",
    "gn:country_code":"JP",
    "gn:dem":24,
    "gn:feature_class":"P",
    "gn:feature_code":"PPL",
    "gn:name":"Nakanishi",
    "gn:population":0,
    "gn:timezone":"Asia/Tokyo",
    "iso:country":"JP",
    "name:jpn_x_preferred":[
        "\u4ef2\u897f"
    ],
    "wof:name":"Nakanishi",
    "wof:placetype":"locality"
},
  "geometry": {"coordinates":[127.69551,26.25314],"type":"Point"}
}