{
  "type": "Feature",
  "properties": {
    "gn:admin1_code":"37.0",
    "gn:admin2_code":"1864089.0",
    "gn:asciiname":"Kuchiwa",
    "gn:country_code":"JP",
    "gn:dem":66,
    "gn:feature_class":"P",
    "gn:feature_code":"PPLL",
    "gn:name":"Kuchiwa",
    "gn:population":0,
    "gn:timezone":"Asia/Tokyo",
    "iso:country":"JP",
    "name:jpn_x_preferred":[
        "\u53e3\u548c"
    ],
    "wof:name":"Kuchiwa",
    "wof:placetype":"locality"
},
  "geometry": {"coordinates":[138.57248999999999,35.19156],"type":"Point"}
}