{
  "type": "Feature",
  "properties": {
    "gn:admin1_code":"36",
    "gn:admin2_code":"1854781.0",
    "gn:admin3_code":"32449.0",
    "gn:asciiname":"Asuna",
    "gn:country_code":"JP",
    "gn:dem":286,
    "gn:feature_class":"P",
    "gn:feature_code":"PPL",
    "gn:name":"Asuna",
    "gn:population":0,
    "gn:timezone":"Asia/Tokyo",
    "iso:country":"JP",
    "name:aze_x_preferred":[
        "Asuna"
    ],
    "name:fra_x_preferred":[
        "Asuna"
    ],
    "wof:name":"Asuna",
    "wof:placetype":"locality"
},
  "geometry": {"coordinates":[132.61667,34.86667],"type":"Point"}
}