{
  "type": "Feature",
  "properties": {
    "gn:admin1_code":"19.0",
    "gn:admin2_code":"1856849.0",
    "gn:asciiname":"Morinoushiro",
    "gn:country_code":"JP",
    "gn:dem":25,
    "gn:feature_class":"P",
    "gn:feature_code":"PPLL",
    "gn:name":"Morinoushiro",
    "gn:population":0,
    "gn:timezone":"Asia/Tokyo",
    "iso:country":"JP",
    "name:jpn_x_preferred":[
        "\u68ee\u30ce\u5f8c"
    ],
    "name:jpn_x_variant":[
        "\u3082\u308a\u306e\u3046\u3057\u308d",
        "\u30e2\u30ea\u30ce\u30a6\u30b7\u30ed"
    ],
    "wof:name":"Morinoushiro",
    "wof:placetype":"locality"
},
  "geometry": {"coordinates":[139.62305000000001,35.1971],"type":"Point"}
}