{
  "type": "Feature",
  "properties": {
    "gn:admin1_code":"4.0",
    "gn:admin2_code":"7465524.0",
    "gn:asciiname":"Nishiogura",
    "gn:country_code":"JP",
    "gn:dem":25,
    "gn:feature_class":"P",
    "gn:feature_code":"PPLL",
    "gn:name":"Nishiogura",
    "gn:population":0,
    "gn:timezone":"Asia/Tokyo",
    "iso:country":"JP",
    "name:jpn_x_preferred":[
        "\u897f\u5c0f\u5009"
    ],
    "name:jpn_x_variant":[
        "\u306b\u3057\u304a\u3050\u3089",
        "\u30cb\u30b7\u30aa\u30b0\u30e9"
    ],
    "wof:name":"Nishiogura",
    "wof:placetype":"locality"
},
  "geometry": {"coordinates":[140.31457,35.32706],"type":"Point"}
}