{
  "type": "Feature",
  "properties": {
    "iso:country":"JP",
    "name:eng_x_preferred":[
        "Gakuen 1 Chome"
    ],
    "name:eng_x_variant":[
        "Gakuen 1 Choume",
        "Gakuen 1 Chome"
    ],
    "name:jpn_x_preferred":[
        "\uff11\u4e01\u76ee"
    ],
    "name:jpn_x_variant":[
        "\u304c\u304f\u3048\u3093 \uff11\u3061\u3087\u3046\u3081",
        "\u5b66\u5712 \uff11\u4e01\u76ee",
        "\uff11\u3061\u3087\u3046\u3081"
    ],
    "name:unk_x_variant":[
        "\uff11\u4e01\u76ee"
    ],
    "qs:gn_adm0_cc":"JP",
    "qs:gn_local":1857550,
    "qs:gn_nam_loc":"\u677e\u6c5f\u5e02, \u5cf6\u6839\u770c, JP",
    "qs:gn_namadm1":"36",
    "qs:local_max":2199,
    "qs:local_sum":3460,
    "qs:localhoods":6,
    "qs:name":"\uff11\u4e01\u76ee",
    "qs:name_adm0":"\u65e5\u672c",
    "qs:name_adm1":"\u5cf6\u6839\u770c",
    "qs:name_en":"Gakuen 1 Chome",
    "qs:name_lau":"\u5b66\u5712",
    "qs:name_local":"\u677e\u6c5f\u5e02",
    "qs:photo_max":753,
    "qs:photo_sum":797,
    "qs:placetype":"Suburb",
    "qs:quad_count":7,
    "qs:woe_adm0":23424856,
    "qs:woe_adm1":2345885,
    "qs:woe_adm2":0,
    "qs:woe_lau":28470559,
    "qs:woe_local":1117681,
    "qs:woe_ver":"7.10.0",
    "wof:lang":[
        "jpn"
    ],
    "wof:name":"\uff11\u4e01\u76ee",
    "wof:placetype":"neighbourhood"
},
  "geometry": {"coordinates":[133.05698100000001,35.479657],"type":"Point"}
}