{
  "type": "Feature",
  "properties": {
    "gn:admin1_code":"36.0",
    "gn:admin2_code":"1857549.0",
    "gn:asciiname":"Agenogi",
    "gn:country_code":"JP",
    "gn:dem":18,
    "gn:feature_class":"P",
    "gn:feature_code":"PPL",
    "gn:name":"Agenogi",
    "gn:population":0,
    "gn:timezone":"Asia/Tokyo",
    "iso:country":"JP",
    "name:jpn_x_preferred":[
        "\u4e0a\u4e43\u6728"
    ],
    "wof:name":"Agenogi",
    "wof:placetype":"locality"
},
  "geometry": {"coordinates":[133.06290000000001,35.43922],"type":"Point"}
}