{
  "type": "Feature",
  "properties": {
    "gn:admin1_code":"12.0",
    "gn:admin2_code":"2128971.0",
    "gn:asciiname":"Yayoicho",
    "gn:country_code":"JP",
    "gn:dem":5,
    "gn:feature_class":"P",
    "gn:feature_code":"PPL",
    "gn:name":"Yayoich\u014d",
    "gn:population":0,
    "gn:timezone":"Asia/Tokyo",
    "iso:country":"JP",
    "name:jpn_x_preferred":[
        "\u5f25\u751f\u753a"
    ],
    "name:jpn_x_variant":[
        "\u3084\u3088\u3044\u3061\u3087\u3046",
        "\u30e4\u30e8\u30a4\u30c1\u30e7\u30a6"
    ],
    "name:und_x_variant":[
        "Yayoich\u014d"
    ],
    "wof:name":"Yayoicho",
    "wof:placetype":"locality"
},
  "geometry": {"coordinates":[145.57714999999999,43.33247],"type":"Point"}
}