{
  "type": "Feature",
  "properties": {
    "gn:admin1_code":"24.0",
    "gn:admin2_code":"2112261.0",
    "gn:asciiname":"Dokaku",
    "gn:country_code":"JP",
    "gn:dem":89,
    "gn:feature_class":"P",
    "gn:feature_code":"PPL",
    "gn:name":"D\u014dkaku",
    "gn:population":0,
    "gn:timezone":"Asia/Tokyo",
    "iso:country":"JP",
    "name:jpn_x_preferred":[
        "\u5802\u89d2"
    ],
    "name:jpn_x_variant":[
        "\u3069\u3046\u304b\u304f",
        "\u30c9\u30a6\u30ab\u30af"
    ],
    "name:und_x_variant":[
        "D\u014dkaku"
    ],
    "wof:name":"Dokaku",
    "wof:placetype":"locality"
},
  "geometry": {"coordinates":[141.63706000000005,38.9357],"type":"Point"}
}