{
  "type": "Feature",
  "properties": {
    "gn:admin1_code":"12.0",
    "gn:admin2_code":"2130287.0",
    "gn:admin3_code":"1406.0",
    "gn:asciiname":"Sawae",
    "gn:cc2":"JP",
    "gn:country_code":"JP",
    "gn:dem":10,
    "gn:feature_class":"P",
    "gn:feature_code":"PPL",
    "gn:name":"Sawae",
    "gn:population":0,
    "gn:timezone":"Asia/Tokyo",
    "iso:country":"JP",
    "name:und_x_variant":[
        "Sawaemura",
        "Sawae"
    ],
    "wof:name":"Sawae",
    "wof:placetype":"locality"
},
  "geometry": {"coordinates":[140.63333,43.25],"type":"Point"}
}