{
  "type": "Feature",
  "properties": {
    "gn:admin1_code":"37.0",
    "gn:admin2_code":"1863526.0",
    "gn:asciiname":"Mashida",
    "gn:country_code":"JP",
    "gn:dem":428,
    "gn:feature_class":"P",
    "gn:feature_code":"PPL",
    "gn:name":"Mashida",
    "gn:population":0,
    "gn:timezone":"Asia/Tokyo",
    "iso:country":"JP",
    "name:jpn_x_preferred":[
        "\u5897\u7530"
    ],
    "name:jpn_x_variant":[
        "\u307e\u3057\u3060"
    ],
    "wof:name":"Mashida",
    "wof:placetype":"locality"
},
  "geometry": {"coordinates":[138.9495,35.332],"type":"Point"}
}