{
  "type": "Feature",
  "properties": {
    "iso:country":"JP",
    "name:eng_x_preferred":[
        "Harukidai 3 Chome"
    ],
    "name:eng_x_variant":[
        "Harukidai 3 Choume",
        "Harukidai 3 Chome"
    ],
    "name:jpn_x_preferred":[
        "\uff13\u4e01\u76ee"
    ],
    "name:jpn_x_variant":[
        "\u306f\u308b\u304d\u3060\u3044 \uff13\u3061\u3087\u3046\u3081",
        "\u6625\u6728\u53f0 \uff13\u4e01\u76ee",
        "\uff13\u3061\u3087\u3046\u3081"
    ],
    "qs:gn_local":0,
    "qs:local_max":15,
    "qs:local_sum":15,
    "qs:localhoods":1,
    "qs:name":"\uff13\u4e01\u76ee",
    "qs:name_adm0":"\u65e5\u672c",
    "qs:name_adm1":"\u611b\u77e5\u770c",
    "qs:name_adm2":"\u611b\u77e5\u90e1",
    "qs:name_en":"Harukidai 3 Chome",
    "qs:name_lau":"\u6625\u6728\u53f0",
    "qs:name_local":"\u6771\u90f7\u753a",
    "qs:photo_max":14,
    "qs:photo_sum":15,
    "qs:placetype":"Suburb",
    "qs:quad_count":2,
    "qs:woe_adm0":23424856,
    "qs:woe_adm1":2345851,
    "qs:woe_adm2":24857013,
    "qs:woe_lau":28445078,
    "qs:woe_local":24726035,
    "qs:woe_ver":"7.10.0",
    "wof:lang":[
        "jpn"
    ],
    "wof:name":"\uff13\u4e01\u76ee",
    "wof:placetype":"neighbourhood"
},
  "geometry": {"coordinates":[137.041077,35.095192],"type":"Point"}
}