{
  "type": "Feature",
  "properties": {
    "gn:admin1_code":"21.0",
    "gn:admin2_code":"7412706.0",
    "gn:admin3_code":"43441.0",
    "gn:asciiname":"Matate",
    "gn:country_code":"JP",
    "gn:dem":316,
    "gn:feature_class":"P",
    "gn:feature_code":"PPLL",
    "gn:name":"Matate",
    "gn:population":0,
    "gn:timezone":"Asia/Tokyo",
    "iso:country":"JP",
    "name:jpn_x_preferred":[
        "\u99ac\u7acb"
    ],
    "name:jpn_x_variant":[
        "\u307e\u305f\u3066",
        "\u30de\u30bf\u30c6"
    ],
    "wof:name":"Matate",
    "wof:placetype":"locality"
},
  "geometry": {"coordinates":[130.88199,32.68076],"type":"Point"}
}