{
  "type": "Feature",
  "properties": {
    "gn:admin1_code":"29",
    "gn:admin2_code":"1865200.0",
    "gn:asciiname":"Kamihorinouchi",
    "gn:country_code":"JP",
    "gn:dem":199,
    "gn:feature_class":"P",
    "gn:feature_code":"PPL",
    "gn:name":"Kamihorinouchi",
    "gn:population":0,
    "gn:timezone":"Asia/Tokyo",
    "iso:country":"JP",
    "name:jpn_x_preferred":[
        "\u4e0a\u5800\u4e4b\u5185"
    ],
    "wof:name":"Kamihorinouchi",
    "wof:placetype":"locality"
},
  "geometry": {"coordinates":[138.26667,36.98333],"type":"Point"}
}