{
  "type": "Feature",
  "properties": {
    "gn:admin1_code":"26",
    "gn:admin2_code":"1857516.0",
    "gn:asciiname":"Kitaozuma",
    "gn:country_code":"JP",
    "gn:dem":632,
    "gn:feature_class":"P",
    "gn:feature_code":"PPL",
    "gn:name":"Kita\u014dzuma",
    "gn:population":0,
    "gn:timezone":"Asia/Tokyo",
    "iso:country":"JP",
    "name:jpn_x_preferred":[
        "\u5317\u5927\u59bb"
    ],
    "name:und_x_variant":[
        "Otsuma",
        "Kita-\u014dtsuma",
        "Kita-\u014dzuma",
        "Kita\u014dzuma"
    ],
    "wof:name":"Kitaozuma",
    "wof:placetype":"locality"
},
  "geometry": {"coordinates":[137.88333,36.23333],"type":"Point"}
}