{
  "type": "Feature",
  "properties": {
    "gn:admin1_code":"43.0",
    "gn:admin2_code":"7411114.0",
    "gn:asciiname":"Kishigawacho-kishiono",
    "gn:country_code":"JP",
    "gn:dem":39,
    "gn:feature_class":"P",
    "gn:feature_code":"PPL",
    "gn:name":"Kishigawach\u014d-kishiono",
    "gn:population":0,
    "gn:timezone":"Asia/Tokyo",
    "iso:country":"JP",
    "name:jpn_x_preferred":[
        "\u8cb4\u5fd7\u5ddd\u753a\u5cb8\u5c0f\u91ce"
    ],
    "name:und_x_variant":[
        "Kishigawach\u014d-kishiono"
    ],
    "wof:name":"Kishigawacho-kishiono",
    "wof:placetype":"locality"
},
  "geometry": {"coordinates":[135.32945000000001,34.20636],"type":"Point"}
}