{
  "type": "Feature",
  "properties": {
    "gn:admin1_code":"43",
    "gn:admin2_code":"1862875.0",
    "gn:admin3_code":"30392.0",
    "gn:asciiname":"Funatsu",
    "gn:country_code":"JP",
    "gn:dem":71,
    "gn:feature_class":"P",
    "gn:feature_code":"PPL",
    "gn:name":"Funatsu",
    "gn:population":0,
    "gn:timezone":"Asia/Tokyo",
    "iso:country":"JP",
    "wof:name":"Funatsu",
    "wof:placetype":"locality"
},
  "geometry": {"coordinates":[135.26667,33.95],"type":"Point"}
}