{
  "type": "Feature",
  "properties": {
    "gn:admin1_code":"40.0",
    "gn:admin2_code":"1865750.0",
    "gn:asciiname":"Motoki-minamimachi",
    "gn:country_code":"JP",
    "gn:dem":6,
    "gn:feature_class":"P",
    "gn:feature_code":"PPL",
    "gn:name":"Motoki-minamimachi",
    "gn:population":0,
    "gn:timezone":"Asia/Tokyo",
    "iso:country":"JP",
    "name:jpn_x_preferred":[
        "\u672c\u6728\u5357\u753a"
    ],
    "wof:name":"Motoki-minamimachi",
    "wof:placetype":"locality"
},
  "geometry": {"coordinates":[139.78266000000002,35.7621],"type":"Point"}
}