{
  "type": "Feature",
  "properties": {
    "gn:admin1_code":"16.0",
    "gn:admin2_code":"2129400.0",
    "gn:admin3_code":"3501.0",
    "gn:asciiname":"Kannonbayashi",
    "gn:country_code":"JP",
    "gn:dem":265,
    "gn:feature_class":"P",
    "gn:feature_code":"PPL",
    "gn:name":"Kannonbayashi",
    "gn:population":0,
    "gn:timezone":"Asia/Tokyo",
    "iso:country":"JP",
    "name:jpn_x_preferred":[
        "\u89b3\u97f3\u6797"
    ],
    "name:jpn_x_variant":[
        "\u304b\u3093\u306e\u3093\u3070\u3084\u3057",
        "\u30ab\u30f3\u30ce\u30f3\u30d0\u30e4\u30b7"
    ],
    "name:und_x_variant":[
        "Kannombayashi"
    ],
    "wof:name":"Kannonbayashi",
    "wof:placetype":"locality"
},
  "geometry": {"coordinates":[141.37624,40.3264],"type":"Point"}
}