{
  "type": "Feature",
  "properties": {
    "gn:admin1_code":"7.0",
    "gn:admin2_code":"1851269.0",
    "gn:admin3_code":"40602.0",
    "gn:asciiname":"Muta",
    "gn:country_code":"JP",
    "gn:dem":407,
    "gn:feature_class":"P",
    "gn:feature_code":"PPLL",
    "gn:name":"Muta",
    "gn:population":0,
    "gn:timezone":"Asia/Tokyo",
    "iso:country":"JP",
    "name:ceb_x_preferred":[
        "Muta"
    ],
    "name:deu_x_preferred":[
        "Muta"
    ],
    "name:fra_x_preferred":[
        "Muta"
    ],
    "name:hye_x_preferred":[
        "\u0544\u0578\u0582\u057f\u0561"
    ],
    "name:ita_x_preferred":[
        "Muta"
    ],
    "name:jpn_x_preferred":[
        "\u725f\u7530"
    ],
    "name:rus_x_preferred":[
        "\u041c\u0443\u0442\u0430"
    ],
    "name:swe_x_preferred":[
        "Muta"
    ],
    "wof:name":"Muta",
    "wof:placetype":"locality"
},
  "geometry": {"coordinates":[130.88829999999999,33.51979],"type":"Point"}
}