{
  "type": "Feature",
  "properties": {
    "gn:admin1_code":"43",
    "gn:admin2_code":"1862767.0",
    "gn:admin3_code":"30428.0",
    "gn:asciiname":"Nishimukai",
    "gn:country_code":"JP",
    "gn:dem":18,
    "gn:feature_class":"P",
    "gn:feature_code":"PPL",
    "gn:name":"Nishimukai",
    "gn:population":0,
    "gn:timezone":"Asia/Tokyo",
    "iso:country":"JP",
    "wof:name":"Nishimukai",
    "wof:placetype":"locality"
},
  "geometry": {"coordinates":[135.81666999999999,33.51667],"type":"Point"}
}