{
  "type": "Feature",
  "properties": {
    "gn:admin1_code":"12.0",
    "gn:admin2_code":"2130058.0",
    "gn:admin3_code":"1641.0",
    "gn:asciiname":"Matsuyamacho",
    "gn:country_code":"JP",
    "gn:dem":74,
    "gn:feature_class":"P",
    "gn:feature_code":"PPL",
    "gn:name":"Matsuyamach\u014d",
    "gn:population":0,
    "gn:timezone":"Asia/Tokyo",
    "iso:country":"JP",
    "name:jpn_x_preferred":[
        "\u677e\u5c71\u753a"
    ],
    "name:jpn_x_variant":[
        "\u307e\u3064\u3084\u307e\u3061\u3087\u3046",
        "\u30de\u30c4\u30e4\u30de\u30c1\u30e7\u30a6"
    ],
    "name:und_x_variant":[
        "Matsuyamach\u014d"
    ],
    "wof:name":"Matsuyamacho",
    "wof:placetype":"locality"
},
  "geometry": {"coordinates":[143.28519,42.49474],"type":"Point"}
}