{
  "type": "Feature",
  "properties": {
    "gn:admin1_code":"10",
    "gn:admin2_code":"7453748.0",
    "gn:admin3_code":"10449.0",
    "gn:asciiname":"Sudagai",
    "gn:country_code":"JP",
    "gn:dem":696,
    "gn:feature_class":"P",
    "gn:feature_code":"PPLL",
    "gn:name":"Sudagai",
    "gn:population":0,
    "gn:timezone":"Asia/Tokyo",
    "iso:country":"JP",
    "name:jpn_x_preferred":[
        "\u9808\u7530\u8c9d"
    ],
    "name:und_x_variant":[
        "Sudakai",
        "Sudagai"
    ],
    "wof:name":"Sudagai",
    "wof:placetype":"locality"
},
  "geometry": {"coordinates":[139.05829,36.85183],"type":"Point"}
}