{
  "type": "Feature",
  "properties": {
    "gn:admin1_code":"42.0",
    "gn:admin2_code":"1849870.0",
    "gn:asciiname":"Fuchucho-osedani",
    "gn:country_code":"JP",
    "gn:dem":125,
    "gn:feature_class":"P",
    "gn:feature_code":"PPL",
    "gn:name":"Fuch\u016bch\u014d-\u014dsedani",
    "gn:population":0,
    "gn:timezone":"Asia/Tokyo",
    "iso:country":"JP",
    "name:jpn_x_preferred":[
        "\u5a66\u4e2d\u753a\u5927\u702c\u8c37"
    ],
    "name:und_x_variant":[
        "Fuch\u016bch\u014d-\u014dsedani"
    ],
    "wof:name":"Fuchucho-osedani",
    "wof:placetype":"locality"
},
  "geometry": {"coordinates":[137.06976,36.60965],"type":"Point"}
}