{
  "type": "Feature",
  "properties": {
    "gn:admin1_code":"33",
    "gn:admin2_code":"1850832.0",
    "gn:asciiname":"Shakushi",
    "gn:country_code":"JP",
    "gn:dem":66,
    "gn:feature_class":"P",
    "gn:feature_code":"PPL",
    "gn:name":"Shakushi",
    "gn:population":0,
    "gn:timezone":"Asia/Tokyo",
    "iso:country":"JP",
    "wof:name":"Shakushi",
    "wof:placetype":"locality"
},
  "geometry": {"coordinates":[129.93333000000001,33.205],"type":"Point"}
}