{
  "type": "Feature",
  "properties": {
    "gn:admin1_code":"19.0",
    "gn:admin2_code":"1848350.0",
    "gn:admin3_code":"14117.0",
    "gn:asciiname":"Moegino",
    "gn:country_code":"JP",
    "gn:dem":44,
    "gn:feature_class":"P",
    "gn:feature_code":"PPL",
    "gn:name":"Moegino",
    "gn:population":0,
    "gn:timezone":"Asia/Tokyo",
    "iso:country":"JP",
    "name:jpn_x_preferred":[
        "\u3082\u3048\u304e\u91ce"
    ],
    "wof:name":"Moegino",
    "wof:placetype":"locality"
},
  "geometry": {"coordinates":[139.52319,35.54665],"type":"Point"}
}