{
  "type": "Feature",
  "properties": {
    "gn:admin1_code":"45",
    "gn:admin2_code":"1856090.0",
    "gn:asciiname":"Furuichi",
    "gn:country_code":"JP",
    "gn:dem":26,
    "gn:feature_class":"P",
    "gn:feature_code":"PPL",
    "gn:name":"Furuichi",
    "gn:population":0,
    "gn:timezone":"Asia/Tokyo",
    "iso:country":"JP",
    "wof:name":"Furuichi",
    "wof:placetype":"locality"
},
  "geometry": {"coordinates":[131.09999999999999,34.38333],"type":"Point"}
}