{
  "type": "Feature",
  "properties": {
    "iso:country":"JP",
    "name:eng_x_preferred":[
        "Iwabatake 3 Chome"
    ],
    "name:eng_x_variant":[
        "Iwabatake 3 Choume",
        "Iwabatake 3 Chome"
    ],
    "name:jpn_x_preferred":[
        "\uff13\u4e01\u76ee"
    ],
    "name:jpn_x_variant":[
        "\u3044\u308f\u3070\u305f\u3051 \uff13\u3061\u3087\u3046\u3081",
        "\u5ca9\u7560 \uff13\u4e01\u76ee",
        "\uff13\u3061\u3087\u3046\u3081"
    ],
    "qs:gn_local":0,
    "qs:local_max":49,
    "qs:local_sum":104,
    "qs:localhoods":3,
    "qs:name":"\uff13\u4e01\u76ee",
    "qs:name_adm0":"\u65e5\u672c",
    "qs:name_adm1":"\u5c71\u53e3\u770c",
    "qs:name_en":"Iwabatake 3 Chome",
    "qs:name_lau":"\u5ca9\u7560",
    "qs:name_local":"\u9632\u5e9c\u5e02",
    "qs:photo_max":29,
    "qs:photo_sum":40,
    "qs:placetype":"Suburb",
    "qs:quad_count":2,
    "qs:woe_adm0":23424856,
    "qs:woe_adm1":2345894,
    "qs:woe_adm2":0,
    "qs:woe_lau":28476573,
    "qs:woe_local":1117239,
    "qs:woe_ver":"7.10.0",
    "qs_pg:name":"\uff13\u4e01\u76ee",
    "qs_pg:name_adm0":"\u65e5\u672c",
    "qs_pg:name_adm1":"\u5c71\u53e3\u770c",
    "qs_pg:photos":40,
    "qs_pg:photos_1k":8,
    "qs_pg:photos_9k":1,
    "qs_pg:photos_9r":2,
    "qs_pg:photos_all":40,
    "qs_pg:photos_sr":2,
    "qs_pg:pop_sr":0,
    "qs_pg:qs_pg_placetype":"neighbourhood",
    "qs_pg:qs_pg_placetype_gp":"Suburb",
    "qs_pg:woe_adm0":23424856,
    "woe:adm0_id":23424856,
    "woe:name_adm0":"\u65e5\u672c",
    "woe:name_adm1":"\u5c71\u53e3\u770c",
    "woe:placetype":"Suburb",
    "wof:lang":[
        "jpn"
    ],
    "wof:name":"\uff13\u4e01\u76ee",
    "wof:placetype":"neighbourhood"
},
  "geometry": {"coordinates":[131.61346399999999,34.076435],"type":"Point"}
}