{
  "type": "Feature",
  "properties": {
    "gn:admin1_code":"37.0",
    "gn:admin2_code":"1864943.0",
    "gn:asciiname":"Midorigaokacho",
    "gn:country_code":"JP",
    "gn:dem":197,
    "gn:feature_class":"P",
    "gn:feature_code":"PPL",
    "gn:name":"Midorigaokach\u014d",
    "gn:population":0,
    "gn:timezone":"Asia/Tokyo",
    "iso:country":"JP",
    "name:jpn_x_preferred":[
        "\u7dd1\u30f6\u4e18\u753a"
    ],
    "name:und_x_variant":[
        "Midorigaokach\u014d"
    ],
    "wof:name":"Midorigaokacho",
    "wof:placetype":"locality"
},
  "geometry": {"coordinates":[139.06651000000002,35.10692],"type":"Point"}
}