{
  "type": "Feature",
  "properties": {
    "gn:admin1_code":"21.0",
    "gn:admin2_code":"1859490.0",
    "gn:admin3_code":"43403.0",
    "gn:asciiname":"Horigatani",
    "gn:country_code":"JP",
    "gn:dem":342,
    "gn:feature_class":"P",
    "gn:feature_code":"PPLL",
    "gn:name":"Horigatani",
    "gn:population":0,
    "gn:timezone":"Asia/Tokyo",
    "iso:country":"JP",
    "name:jpn_x_preferred":[
        "\u5800\u30f6\u8c37"
    ],
    "name:jpn_x_variant":[
        "\u307b\u308a\u304c\u305f\u306b",
        "\u30db\u30ea\u30ac\u30bf\u30cb"
    ],
    "wof:name":"Horigatani",
    "wof:placetype":"locality"
},
  "geometry": {"coordinates":[130.93246000000002,32.89824],"type":"Point"}
}