{
  "type": "Feature",
  "properties": {
    "gn:admin1_code":"19.0",
    "gn:admin2_code":"1848350.0",
    "gn:admin3_code":"14104.0",
    "gn:asciiname":"Kaigandori",
    "gn:country_code":"JP",
    "gn:dem":12,
    "gn:feature_class":"P",
    "gn:feature_code":"PPL",
    "gn:name":"Kaigand\u014dri",
    "gn:population":0,
    "gn:timezone":"Asia/Tokyo",
    "iso:country":"JP",
    "name:jpn_x_preferred":[
        "\u6d77\u5cb8\u901a"
    ],
    "name:jpn_x_variant":[
        "\u304b\u3044\u304c\u3093\u3069\u304a\u308a",
        "\u30ab\u30a4\u30ac\u30f3\u30c9\u30aa\u30ea"
    ],
    "name:und_x_variant":[
        "Kaigand\u014dri"
    ],
    "wof:name":"Kaigandori",
    "wof:placetype":"locality"
},
  "geometry": {"coordinates":[139.63863000000001,35.45085],"type":"Point"}
}