{
  "type": "Feature",
  "properties": {
    "gn:admin1_code":"21.0",
    "gn:admin2_code":"7413152.0",
    "gn:asciiname":"Matsubasemachi-kugu",
    "gn:country_code":"JP",
    "gn:dem":7,
    "gn:feature_class":"P",
    "gn:feature_code":"PPL",
    "gn:name":"Matsubasemachi-kugu",
    "gn:population":0,
    "gn:timezone":"Asia/Tokyo",
    "iso:country":"JP",
    "name:jpn_x_preferred":[
        "\u677e\u6a4b\u753a\u4e45\u5177"
    ],
    "name:jpn_x_variant":[
        "\u307e\u3064\u3070\u305b\u307e\u3061\u304f\u3050",
        "\u30de\u30c4\u30d0\u30bb\u30de\u30c1\u30af\u30b0"
    ],
    "wof:name":"Matsubasemachi-kugu",
    "wof:placetype":"locality"
},
  "geometry": {"coordinates":[130.69001,32.64492],"type":"Point"}
}