{
  "type": "Feature",
  "properties": {
    "gn:admin1_code":"40.0",
    "gn:admin2_code":"1851510.0",
    "gn:asciiname":"Imagawa",
    "gn:country_code":"JP",
    "gn:dem":52,
    "gn:feature_class":"P",
    "gn:feature_code":"PPL",
    "gn:name":"Imagawa",
    "gn:population":0,
    "gn:timezone":"Asia/Tokyo",
    "iso:country":"JP",
    "name:jpn_x_preferred":[
        "\u4eca\u5ddd"
    ],
    "wof:name":"Imagawa",
    "wof:placetype":"locality"
},
  "geometry": {"coordinates":[139.6062,35.71692],"type":"Point"}
}