{
  "type": "Feature",
  "properties": {
    "gn:admin1_code":"7.0",
    "gn:admin2_code":"1851269.0",
    "gn:admin3_code":"40601.0",
    "gn:asciiname":"Takasu",
    "gn:country_code":"JP",
    "gn:dem":93,
    "gn:feature_class":"P",
    "gn:feature_code":"PPLL",
    "gn:name":"Takasu",
    "gn:population":0,
    "gn:timezone":"Asia/Tokyo",
    "iso:country":"JP",
    "name:jpn_x_preferred":[
        "\u9ad8\u5de3"
    ],
    "wof:name":"Takasu",
    "wof:placetype":"locality"
},
  "geometry": {"coordinates":[130.85266999999999,33.70358],"type":"Point"}
}