{
  "type": "Feature",
  "properties": {
    "gn:admin1_code":"40.0",
    "gn:admin2_code":"1851451.0",
    "gn:asciiname":"Tachibana",
    "gn:country_code":"JP",
    "gn:dem":1,
    "gn:feature_class":"P",
    "gn:feature_code":"PPL",
    "gn:name":"Tachibana",
    "gn:population":0,
    "gn:timezone":"Asia/Tokyo",
    "iso:country":"JP",
    "name:deu_x_preferred":[
        "Tachibana"
    ],
    "name:fin_x_preferred":[
        "Tachibana"
    ],
    "name:jpn_x_preferred":[
        "\u7acb\u82b1"
    ],
    "name:jpn_x_variant":[
        "\u6a58"
    ],
    "name:kor_x_preferred":[
        "\ub2e4\uce58\ubc14\ub098"
    ],
    "name:rus_x_preferred":[
        "\u0422\u0430\u0442\u0438\u0431\u0430\u043d\u0430"
    ],
    "wof:name":"Tachibana",
    "wof:placetype":"locality"
},
  "geometry": {"coordinates":[139.83168999999998,35.70868],"type":"Point"}
}