{
  "type": "Feature",
  "properties": {
    "gn:admin1_code":"19.0",
    "gn:admin2_code":"1848308.0",
    "gn:asciiname":"Koyabe",
    "gn:country_code":"JP",
    "gn:dem":56,
    "gn:feature_class":"P",
    "gn:feature_code":"PPL",
    "gn:name":"Koyabe",
    "gn:population":0,
    "gn:timezone":"Asia/Tokyo",
    "iso:country":"JP",
    "name:jpn_x_preferred":[
        "\u5c0f\u77e2\u90e8"
    ],
    "name:jpn_x_variant":[
        "\u3053\u3084\u3079",
        "\u30b3\u30e4\u30d9"
    ],
    "wof:name":"Koyabe",
    "wof:placetype":"locality"
},
  "geometry": {"coordinates":[139.66698,35.2497],"type":"Point"}
}