{
  "type": "Feature",
  "properties": {
    "iso:country":"JP",
    "name:eng_x_preferred":[
        "Oshima"
    ],
    "name:eng_x_variant":[
        "Oshima Town"
    ],
    "name:jpn_x_preferred":[
        "\u5927\u5cf6\u753a"
    ],
    "qs:name":"\u5927\u5cf6\u753a",
    "qs:name_adm0":"\u65e5\u672c",
    "qs:name_adm1":"\u6771\u4eac\u90fd",
    "qs:photos":1404,
    "qs:photos_1k":284,
    "qs:photos_9k":9,
    "qs:photos_9r":9,
    "qs:photos_all":2129,
    "qs:photos_sr":12,
    "qs:placetype":"Town",
    "qs:pop_sr":"0",
    "wof:name":"Oshima",
    "wof:placetype":"locality"
},
  "geometry": {"coordinates":[139.392471,34.741048],"type":"Point"}
}