{
  "type": "Feature",
  "properties": {
    "gn:admin1_code":"12.0",
    "gn:admin2_code":"7428089.0",
    "gn:admin3_code":"1632.0",
    "gn:asciiname":"Sakuraminami",
    "gn:country_code":"JP",
    "gn:dem":173,
    "gn:feature_class":"P",
    "gn:feature_code":"PPL",
    "gn:name":"Sakuraminami",
    "gn:population":0,
    "gn:timezone":"Asia/Tokyo",
    "iso:country":"JP",
    "name:jpn_x_preferred":[
        "\u4f50\u5009\u5357"
    ],
    "name:jpn_x_variant":[
        "\u3055\u304f\u3089\u307f\u306a\u307f",
        "\u30b5\u30af\u30e9\u30df\u30ca\u30df"
    ],
    "name:und_x_variant":[
        "Sakura-n\u014dj\u014d",
        "Saguran\u014dj\u014d",
        "Sakura",
        "Sakuraminami"
    ],
    "wof:name":"Sakuraminami",
    "wof:placetype":"locality"
},
  "geometry": {"coordinates":[143.30396999999999,43.12907],"type":"Point"}
}