{
  "type": "Feature",
  "properties": {
    "gn:admin1_code":"4.0",
    "gn:admin2_code":"2112663.0",
    "gn:asciiname":"Katamatagi",
    "gn:country_code":"JP",
    "gn:dem":33,
    "gn:feature_class":"P",
    "gn:feature_code":"PPL",
    "gn:name":"Katamatagi",
    "gn:population":0,
    "gn:timezone":"Asia/Tokyo",
    "iso:country":"JP",
    "name:jpn_x_preferred":[
        "\u7247\u53c8\u6728"
    ],
    "name:jpn_x_variant":[
        "\u304b\u305f\u307e\u305f\u304e",
        "\u30ab\u30bf\u30de\u30bf\u30ae"
    ],
    "wof:name":"Katamatagi",
    "wof:placetype":"locality"
},
  "geometry": {"coordinates":[140.06153999999998,35.46451],"type":"Point"}
}