{
  "type": "Feature",
  "properties": {
    "gn:admin1_code":"21.0",
    "gn:admin2_code":"1848441.0",
    "gn:asciiname":"Minamigawachi",
    "gn:country_code":"JP",
    "gn:dem":441,
    "gn:feature_class":"P",
    "gn:feature_code":"PPLL",
    "gn:name":"Minamigawachi",
    "gn:population":0,
    "gn:timezone":"Asia/Tokyo",
    "iso:country":"JP",
    "name:jpn_x_preferred":[
        "\u5357\u5ddd\u5185"
    ],
    "name:jpn_x_variant":[
        "\u307f\u306a\u307f\u304c\u308f\u3061",
        "\u30df\u30ca\u30df\u30ac\u30ef\u30c1"
    ],
    "wof:name":"Minamigawachi",
    "wof:placetype":"locality"
},
  "geometry": {"coordinates":[130.83363,32.53052],"type":"Point"}
}