{
  "type": "Feature",
  "properties": {
    "gn:admin1_code":"21.0",
    "gn:admin2_code":"7412708.0",
    "gn:admin3_code":"43507.0",
    "gn:asciiname":"Hibira",
    "gn:country_code":"JP",
    "gn:dem":753,
    "gn:feature_class":"P",
    "gn:feature_code":"PPLL",
    "gn:name":"Hibira",
    "gn:population":0,
    "gn:timezone":"Asia/Tokyo",
    "iso:country":"JP",
    "name:jpn_x_preferred":[
        "\u65e5\u5e73"
    ],
    "name:jpn_x_variant":[
        "\u3072\u3073\u3089",
        "\u30d2\u30d3\u30e9"
    ],
    "wof:name":"Hibira",
    "wof:placetype":"locality"
},
  "geometry": {"coordinates":[131.01828999999998,32.41056],"type":"Point"}
}