{
  "type": "Feature",
  "properties": {
    "gn:admin1_code":"19.0",
    "gn:admin2_code":"7470890.0",
    "gn:asciiname":"Wadagahara",
    "gn:country_code":"JP",
    "gn:dem":39,
    "gn:feature_class":"P",
    "gn:feature_code":"PPL",
    "gn:name":"Wadagahara",
    "gn:population":0,
    "gn:timezone":"Asia/Tokyo",
    "iso:country":"JP",
    "name:jpn_x_preferred":[
        "\u548c\u7530\u6cb3\u539f"
    ],
    "wof:name":"Wadagahara",
    "wof:placetype":"locality"
},
  "geometry": {"coordinates":[139.11940000000001,35.3174],"type":"Point"}
}