{
  "type": "Feature",
  "properties": {
    "gn:admin1_code":"34.0",
    "gn:admin2_code":"1859726.0",
    "gn:asciiname":"Yananecho",
    "gn:country_code":"JP",
    "gn:dem":7,
    "gn:feature_class":"P",
    "gn:feature_code":"PPL",
    "gn:name":"Yananech\u014d",
    "gn:population":0,
    "gn:timezone":"Asia/Tokyo",
    "iso:country":"JP",
    "name:jpn_x_preferred":[
        "\u67f3\u6839\u753a"
    ],
    "name:jpn_x_variant":[
        "\u3084\u306a\u306d\u3061\u3087\u3046",
        "\u30e4\u30ca\u30cd\u30c1\u30e7\u30a6"
    ],
    "name:und_x_variant":[
        "Yananech\u014d"
    ],
    "wof:name":"Yananecho",
    "wof:placetype":"locality"
},
  "geometry": {"coordinates":[139.70612,35.85133],"type":"Point"}
}