{
  "type": "Feature",
  "properties": {
    "gn:admin1_code":"25.0",
    "gn:admin2_code":"7413970.0",
    "gn:asciiname":"Hashidani",
    "gn:country_code":"JP",
    "gn:dem":314,
    "gn:feature_class":"P",
    "gn:feature_code":"PPLL",
    "gn:name":"Hashidani",
    "gn:population":0,
    "gn:timezone":"Asia/Tokyo",
    "iso:country":"JP",
    "name:jpn_x_preferred":[
        "\u6a4b\u8c37"
    ],
    "name:jpn_x_variant":[
        "\u306f\u3057\u3060\u306b",
        "\u30cf\u30b7\u30c0\u30cb"
    ],
    "wof:name":"Hashidani",
    "wof:placetype":"locality"
},
  "geometry": {"coordinates":[130.90304,32.02865],"type":"Point"}
}