{
  "type": "Feature",
  "properties": {
    "gn:admin1_code":"21.0",
    "gn:admin2_code":"1858418.0",
    "gn:admin3_code":"43103.0",
    "gn:asciiname":"Oshima-shimomachi",
    "gn:country_code":"JP",
    "gn:dem":-3,
    "gn:feature_class":"P",
    "gn:feature_code":"PPL",
    "gn:name":"Oshima-shimomachi",
    "gn:population":0,
    "gn:timezone":"Asia/Tokyo",
    "iso:country":"JP",
    "name:jpn_x_preferred":[
        "\u5c0f\u5cf6\u4e0b\u753a"
    ],
    "name:jpn_x_variant":[
        "\u304a\u3057\u307e\u3057\u3082\u307e\u3061",
        "\u30aa\u30b7\u30de\u30b7\u30e2\u30de\u30c1"
    ],
    "wof:name":"Oshima-shimomachi",
    "wof:placetype":"locality"
},
  "geometry": {"coordinates":[130.61328,32.78455],"type":"Point"}
}