{
  "type": "Feature",
  "properties": {
    "gn:admin1_code":"12.0",
    "gn:admin2_code":"7428109.0",
    "gn:admin3_code":"1668.0",
    "gn:asciiname":"Karisho",
    "gn:country_code":"JP",
    "gn:dem":89,
    "gn:feature_class":"P",
    "gn:feature_code":"PPL",
    "gn:name":"Karisho",
    "gn:population":0,
    "gn:timezone":"Asia/Tokyo",
    "iso:country":"JP",
    "wof:name":"Karisho",
    "wof:placetype":"locality"
},
  "geometry": {"coordinates":[144.08333000000005,42.98333],"type":"Point"}
}