{
  "type": "Feature",
  "properties": {
    "gn:admin1_code":"13.0",
    "gn:admin2_code":"1859755.0",
    "gn:admin3_code":"28301.0",
    "gn:asciiname":"Kizu",
    "gn:country_code":"JP",
    "gn:dem":152,
    "gn:feature_class":"P",
    "gn:feature_code":"PPL",
    "gn:name":"Kizu",
    "gn:population":0,
    "gn:timezone":"Asia/Tokyo",
    "iso:country":"JP",
    "name:fra_x_preferred":[
        "Kizu"
    ],
    "name:ita_x_preferred":[
        "Kizu"
    ],
    "name:jpn_x_preferred":[
        "\u6728\u6d25"
    ],
    "name:nld_x_preferred":[
        "Kizu"
    ],
    "wof:name":"Kizu",
    "wof:placetype":"locality"
},
  "geometry": {"coordinates":[135.34582,34.93507],"type":"Point"}
}