{
  "type": "Feature",
  "properties": {
    "gn:admin1_code":"40.0",
    "gn:admin2_code":"1853655.0",
    "gn:asciiname":"Den'enchofu-minami",
    "gn:country_code":"JP",
    "gn:dem":10,
    "gn:feature_class":"P",
    "gn:feature_code":"PPL",
    "gn:name":"Den\u2019ench\u014dfu-minami",
    "gn:population":0,
    "gn:timezone":"Asia/Tokyo",
    "iso:country":"JP",
    "name:jpn_x_preferred":[
        "\u7530\u5712\u8abf\u5e03\u5357"
    ],
    "name:und_x_variant":[
        "Den\u2019ench\u014dfu-minami"
    ],
    "wof:name":"Den'enchofu-minami",
    "wof:placetype":"locality"
},
  "geometry": {"coordinates":[139.67427000000001,35.57978],"type":"Point"}
}