{
  "type": "Feature",
  "properties": {
    "gn:admin1_code":"3.0",
    "gn:admin2_code":"2128302.0",
    "gn:admin3_code":"2442.0",
    "gn:asciiname":"Kamitoyokawa",
    "gn:country_code":"JP",
    "gn:dem":141,
    "gn:feature_class":"P",
    "gn:feature_code":"PPL",
    "gn:name":"Kamitoyokawa",
    "gn:population":0,
    "gn:timezone":"Asia/Tokyo",
    "iso:country":"JP",
    "name:jpn_x_preferred":[
        "\u4e0a\u8c4a\u5ddd"
    ],
    "name:jpn_x_variant":[
        "\u304b\u307f\u3068\u3088\u304b\u308f",
        "\u30ab\u30df\u30c8\u30e8\u30ab\u30ef"
    ],
    "wof:name":"Kamitoyokawa",
    "wof:placetype":"locality"
},
  "geometry": {"coordinates":[141.26068000000001,40.47362],"type":"Point"}
}