{
  "type": "Feature",
  "properties": {
    "gn:admin1_code":"4.0",
    "gn:admin2_code":"2112386.0",
    "gn:asciiname":"Shibao",
    "gn:country_code":"JP",
    "gn:dem":58,
    "gn:feature_class":"P",
    "gn:feature_code":"PPLL",
    "gn:name":"Shibao",
    "gn:population":0,
    "gn:timezone":"Asia/Tokyo",
    "iso:country":"JP",
    "name:jpn_x_preferred":[
        "\u829d\u5c3e"
    ],
    "name:jpn_x_variant":[
        "\u3057\u3070\u304a",
        "\u30b7\u30d0\u30aa"
    ],
    "wof:name":"Shibao",
    "wof:placetype":"locality"
},
  "geometry": {"coordinates":[140.06332,35.0931],"type":"Point"}
}