{
  "type": "Feature",
  "properties": {
    "gn:admin1_code":"6.0",
    "gn:admin2_code":"7467385.0",
    "gn:asciiname":"Ushiroyama",
    "gn:country_code":"JP",
    "gn:dem":36,
    "gn:feature_class":"P",
    "gn:feature_code":"PPL",
    "gn:name":"Ushiroyama",
    "gn:population":0,
    "gn:timezone":"Asia/Tokyo",
    "iso:country":"JP",
    "name:jpn_x_preferred":[
        "\u5f8c\u5c71"
    ],
    "wof:name":"Ushiroyama",
    "wof:placetype":"locality"
},
  "geometry": {"coordinates":[136.28783000000001,36.19078],"type":"Point"}
}