{
  "type": "Feature",
  "properties": {
    "gn:admin1_code":"16.0",
    "gn:admin2_code":"2112223.0",
    "gn:asciiname":"Toda",
    "gn:country_code":"JP",
    "gn:dem":100,
    "gn:feature_class":"P",
    "gn:feature_code":"PPL",
    "gn:name":"Toda",
    "gn:population":0,
    "gn:timezone":"Asia/Tokyo",
    "iso:country":"JP",
    "name:cat_x_preferred":[
        "Toda"
    ],
    "name:ceb_x_preferred":[
        "Toda"
    ],
    "name:deu_x_preferred":[
        "Toda"
    ],
    "name:fra_x_preferred":[
        "Toda"
    ],
    "name:ita_x_preferred":[
        "Toda"
    ],
    "name:jpn_x_preferred":[
        "\u6238\u7530"
    ],
    "name:jpn_x_variant":[
        "\u3068\u3060",
        "\u30c8\u30c0"
    ],
    "name:lav_x_preferred":[
        "Toda"
    ],
    "name:nld_x_preferred":[
        "Toda"
    ],
    "name:pol_x_preferred":[
        "Toda"
    ],
    "name:por_x_preferred":[
        "Toda"
    ],
    "name:rus_x_preferred":[
        "\u0422\u043e\u0434\u0430"
    ],
    "name:spa_x_preferred":[
        "Analfabetismo digital"
    ],
    "name:swe_x_preferred":[
        "Toda"
    ],
    "name:ukr_x_preferred":[
        "\u0422\u043e\u0434\u0430"
    ],
    "wof:name":"Toda",
    "wof:placetype":"locality"
},
  "geometry": {"coordinates":[141.06179,39.34142],"type":"Point"}
}