{
  "type": "Feature",
  "properties": {
    "gn:admin1_code":"3.0",
    "gn:admin2_code":"2127674.0",
    "gn:asciiname":"Tomioka",
    "gn:country_code":"JP",
    "gn:dem":50,
    "gn:feature_class":"P",
    "gn:feature_code":"PPL",
    "gn:name":"Tomioka",
    "gn:population":0,
    "gn:timezone":"Asia/Tokyo",
    "iso:country":"JP",
    "name:jpn_x_preferred":[
        "\u5341\u7f8e\u5ca1"
    ],
    "name:jpn_x_variant":[
        "\u3068\u307f\u304a\u304b",
        "\u30c8\u30df\u30aa\u30ab"
    ],
    "wof:name":"Tomioka",
    "wof:placetype":"locality"
},
  "geometry": {"coordinates":[141.24292,40.64815],"type":"Point"}
}