{
  "type": "Feature",
  "properties": {
    "gn:admin1_code":"31",
    "gn:admin2_code":"1854380.0",
    "gn:admin3_code":"33101.0",
    "gn:asciiname":"Oi",
    "gn:country_code":"JP",
    "gn:dem":64,
    "gn:feature_class":"P",
    "gn:feature_code":"PPL",
    "gn:name":"\u014ci",
    "gn:population":0,
    "gn:timezone":"Asia/Tokyo",
    "iso:country":"JP",
    "name:eus_x_preferred":[
        "Oi"
    ],
    "name:jpn_x_preferred":[
        "\u5927\u4e95"
    ],
    "name:rus_x_preferred":[
        "\u041e\u0438"
    ],
    "name:swe_x_preferred":[
        "Oi"
    ],
    "name:und_x_variant":[
        "\u014ci"
    ],
    "wof:name":"Oi",
    "wof:placetype":"locality"
},
  "geometry": {"coordinates":[133.80000000000001,34.73333],"type":"Point"}
}