{
  "type": "Feature",
  "properties": {
    "gn:admin1_code":"13.0",
    "gn:admin2_code":"1859161.0",
    "gn:admin3_code":"28111.0",
    "gn:asciiname":"Hasetanicho-teratani",
    "gn:country_code":"JP",
    "gn:dem":95,
    "gn:feature_class":"P",
    "gn:feature_code":"PPL",
    "gn:name":"Hasetanich\u014d-teratani",
    "gn:population":0,
    "gn:timezone":"Asia/Tokyo",
    "iso:country":"JP",
    "name:jpn_x_preferred":[
        "\u6ae8\u8c37\u753a\u5bfa\u8c37"
    ],
    "name:und_x_variant":[
        "Hasetanich\u014d-teratani"
    ],
    "wof:name":"Hasetanicho-teratani",
    "wof:placetype":"locality"
},
  "geometry": {"coordinates":[135.05168,34.72646],"type":"Point"}
}