{
  "type": "Feature",
  "properties": {
    "gn:admin1_code":"2.0",
    "gn:admin2_code":"2113122.0",
    "gn:asciiname":"Sannoshinmachi",
    "gn:country_code":"JP",
    "gn:dem":4,
    "gn:feature_class":"P",
    "gn:feature_code":"PPL",
    "gn:name":"Sann\u014dshinmachi",
    "gn:population":0,
    "gn:timezone":"Asia/Tokyo",
    "iso:country":"JP",
    "name:jpn_x_preferred":[
        "\u5c71\u738b\u65b0\u753a"
    ],
    "name:jpn_x_variant":[
        "\u3055\u3093\u306e\u3046\u3057\u3093\u307e\u3061",
        "\u30b5\u30f3\u30ce\u30a6\u30b7\u30f3\u30de\u30c1"
    ],
    "name:und_x_variant":[
        "Sann\u014dshinmachi"
    ],
    "wof:name":"Sannoshinmachi",
    "wof:placetype":"locality"
},
  "geometry": {"coordinates":[140.09413999999998,39.71695],"type":"Point"}
}