{
  "type": "Feature",
  "properties": {
    "gn:admin1_code":"24.0",
    "gn:admin2_code":"7447001.0",
    "gn:asciiname":"Iwabuchi",
    "gn:country_code":"JP",
    "gn:dem":175,
    "gn:feature_class":"P",
    "gn:feature_code":"PPL",
    "gn:name":"Iwabuchi",
    "gn:population":0,
    "gn:timezone":"Asia/Tokyo",
    "iso:country":"JP",
    "name:jpn_x_preferred":[
        "\u5ca9\u6e15"
    ],
    "name:jpn_x_variant":[
        "\u3044\u308f\u3076\u3061",
        "\u30a4\u30ef\u30d6\u30c1"
    ],
    "wof:name":"Iwabuchi",
    "wof:placetype":"locality"
},
  "geometry": {"coordinates":[140.70183,38.74417],"type":"Point"}
}