{
  "type": "Feature",
  "properties": {
    "gn:admin1_code":"23",
    "gn:admin2_code":"1851345.0",
    "gn:asciiname":"Kita-nago",
    "gn:cc2":"JP",
    "gn:country_code":"JP",
    "gn:dem":2,
    "gn:feature_class":"P",
    "gn:feature_code":"PPL",
    "gn:name":"Kita-nago",
    "gn:population":0,
    "gn:timezone":"Asia/Tokyo",
    "iso:country":"JP",
    "name:und_x_variant":[
        "Kita-nagoch\u014d",
        "Kita-nagomachi",
        "Kita-nago"
    ],
    "wof:name":"Kita-nago",
    "wof:placetype":"locality"
},
  "geometry": {"coordinates":[136.61667,34.88333],"type":"Point"}
}