{
  "type": "Feature",
  "properties": {
    "gn:admin1_code":"21.0",
    "gn:admin2_code":"1864973.0",
    "gn:asciiname":"Onizuka",
    "gn:country_code":"JP",
    "gn:dem":535,
    "gn:feature_class":"P",
    "gn:feature_code":"PPLL",
    "gn:name":"Onizuka",
    "gn:population":0,
    "gn:timezone":"Asia/Tokyo",
    "iso:country":"JP",
    "name:deu_x_preferred":[
        "Onizuka"
    ],
    "name:ita_x_preferred":[
        "Onizuka"
    ],
    "name:jpn_x_preferred":[
        "\u9b3c\u585a"
    ],
    "name:jpn_x_variant":[
        "\u304a\u306b\u3065\u304b",
        "\u30aa\u30cb\u30c5\u30ab"
    ],
    "name:rus_x_preferred":[
        "\u041e\u043d\u0438\u0434\u0437\u0443\u043a\u0430"
    ],
    "wof:name":"Onizuka",
    "wof:placetype":"locality"
},
  "geometry": {"coordinates":[131.14230000000001,32.95059000000001],"type":"Point"}
}