{
  "type": "Feature",
  "properties": {
    "gn:admin1_code":"33.0",
    "gn:admin2_code":"7391357.0",
    "gn:asciiname":"Kanzakimachi-nagauta",
    "gn:country_code":"JP",
    "gn:dem":3,
    "gn:feature_class":"P",
    "gn:feature_code":"PPL",
    "gn:name":"Kanzakimachi-nagauta",
    "gn:population":0,
    "gn:timezone":"Asia/Tokyo",
    "iso:country":"JP",
    "name:jpn_x_preferred":[
        "\u795e\u57fc\u753a\u6c38\u6b4c"
    ],
    "wof:name":"Kanzakimachi-nagauta",
    "wof:placetype":"locality"
},
  "geometry": {"coordinates":[130.37618000000001,33.2957],"type":"Point"}
}