{
  "type": "Feature",
  "properties": {
    "gn:admin1_code":"21.0",
    "gn:admin2_code":"1858418.0",
    "gn:admin3_code":"43104.0",
    "gn:asciiname":"Otsuhataguchi",
    "gn:country_code":"JP",
    "gn:dem":-2,
    "gn:feature_class":"P",
    "gn:feature_code":"PPLL",
    "gn:name":"Otsuhataguchi",
    "gn:population":0,
    "gn:timezone":"Asia/Tokyo",
    "iso:country":"JP",
    "name:jpn_x_preferred":[
        "\u4e59\u7560\u53e3"
    ],
    "name:jpn_x_variant":[
        "\u304a\u3064\u306f\u305f\u3050\u3061",
        "\u30aa\u30c4\u30cf\u30bf\u30b0\u30c1"
    ],
    "wof:name":"Otsuhataguchi",
    "wof:placetype":"locality"
},
  "geometry": {"coordinates":[130.61333999999999,32.75095],"type":"Point"}
}