{
  "type": "Feature",
  "properties": {
    "gn:admin1_code":"22",
    "gn:admin2_code":"1857764.0",
    "gn:asciiname":"Taira",
    "gn:country_code":"JP",
    "gn:dem":30,
    "gn:feature_class":"P",
    "gn:feature_code":"PPL",
    "gn:name":"Taira",
    "gn:population":0,
    "gn:timezone":"Asia/Tokyo",
    "iso:country":"JP",
    "wof:name":"Taira",
    "wof:placetype":"locality"
},
  "geometry": {"coordinates":[135.38333,35.51667],"type":"Point"}
}