{
  "type": "Feature",
  "properties": {
    "gn:admin1_code":"7.0",
    "gn:admin2_code":"1856443.0",
    "gn:asciiname":"Nakano'o",
    "gn:country_code":"JP",
    "gn:dem":29,
    "gn:feature_class":"P",
    "gn:feature_code":"PPLL",
    "gn:name":"Nakano\u2019o",
    "gn:population":0,
    "gn:timezone":"Asia/Tokyo",
    "iso:country":"JP",
    "name:jpn_x_preferred":[
        "\u4e2d\u30ce\u5c3e"
    ],
    "name:und_x_variant":[
        "Nakano\u2019o"
    ],
    "wof:name":"Nakano'o",
    "wof:placetype":"locality"
},
  "geometry": {"coordinates":[130.61566000000002,33.80272],"type":"Point"}
}