{
  "type": "Feature",
  "properties": {
    "gn:admin1_code":"21.0",
    "gn:admin2_code":"1850744.0",
    "gn:admin3_code":"43364.0",
    "gn:asciiname":"Yamaguchi",
    "gn:country_code":"JP",
    "gn:dem":18,
    "gn:feature_class":"P",
    "gn:feature_code":"PPL",
    "gn:name":"Yamaguchi",
    "gn:population":0,
    "gn:timezone":"Asia/Tokyo",
    "iso:country":"JP",
    "name:jpn_x_preferred":[
        "\u5c71\u53e3"
    ],
    "name:jpn_x_variant":[
        "\u3084\u307e\u3050\u3061",
        "\u30e4\u30de\u30b0\u30c1"
    ],
    "wof:name":"Yamaguchi",
    "wof:placetype":"locality"
},
  "geometry": {"coordinates":[130.61622,32.92148],"type":"Point"}
}