{
  "type": "Feature",
  "properties": {
    "gn:admin1_code":"3.0",
    "gn:admin2_code":"7439934.0",
    "gn:asciiname":"Kanaya",
    "gn:country_code":"JP",
    "gn:dem":59,
    "gn:feature_class":"P",
    "gn:feature_code":"PPL",
    "gn:name":"Kanaya",
    "gn:population":0,
    "gn:timezone":"Asia/Tokyo",
    "iso:country":"JP",
    "name:deu_x_preferred":[
        "Kanaya"
    ],
    "name:ita_x_preferred":[
        "Kanaya"
    ],
    "name:jpn_x_preferred":[
        "\u91d1\u5c4b"
    ],
    "name:jpn_x_variant":[
        "\u304b\u306a\u3084",
        "\u30ab\u30ca\u30e4"
    ],
    "wof:name":"Kanaya",
    "wof:placetype":"locality"
},
  "geometry": {"coordinates":[140.60536000000002,40.60753],"type":"Point"}
}