{
  "type": "Feature",
  "properties": {
    "gn:admin1_code":"7.0",
    "gn:admin2_code":"7407413.0",
    "gn:asciiname":"Kamo'o",
    "gn:country_code":"JP",
    "gn:dem":40,
    "gn:feature_class":"P",
    "gn:feature_code":"PPL",
    "gn:name":"Kamo\u2019o",
    "gn:population":0,
    "gn:timezone":"Asia/Tokyo",
    "iso:country":"JP",
    "name:jpn_x_preferred":[
        "\u9d28\u751f"
    ],
    "name:und_x_variant":[
        "Kamo\u2019o"
    ],
    "wof:name":"Kamo'o",
    "wof:placetype":"locality"
},
  "geometry": {"coordinates":[130.73391000000001,33.6079],"type":"Point"}
}