{
  "type": "Feature",
  "properties": {
    "gn:admin1_code":"7.0",
    "gn:admin2_code":"1860814.0",
    "gn:admin3_code":"40421.0",
    "gn:asciiname":"Tendo",
    "gn:country_code":"JP",
    "gn:dem":39,
    "gn:feature_class":"P",
    "gn:feature_code":"PPLL",
    "gn:name":"Tend\u014d",
    "gn:population":0,
    "gn:timezone":"Asia/Tokyo",
    "iso:country":"JP",
    "name:jpn_x_preferred":[
        "\u5929\u9053"
    ],
    "name:und_x_variant":[
        "Tend\u014d"
    ],
    "wof:name":"Tendo",
    "wof:placetype":"locality"
},
  "geometry": {"coordinates":[130.68364,33.59124],"type":"Point"}
}