{
  "type": "Feature",
  "properties": {
    "gn:admin1_code":"4.0",
    "gn:admin2_code":"1863711.0",
    "gn:asciiname":"Omori",
    "gn:country_code":"JP",
    "gn:dem":28,
    "gn:feature_class":"P",
    "gn:feature_code":"PPL",
    "gn:name":"\u014cmori",
    "gn:population":0,
    "gn:timezone":"Asia/Tokyo",
    "iso:country":"JP",
    "name:jpn_x_preferred":[
        "\u5927\u68ee"
    ],
    "name:jpn_x_variant":[
        "\u304a\u304a\u3082\u308a",
        "\u30aa\u30aa\u30e2\u30ea"
    ],
    "name:und_x_variant":[
        "\u014cmori"
    ],
    "wof:name":"Omori",
    "wof:placetype":"locality"
},
  "geometry": {"coordinates":[139.91596999999999,35.21707],"type":"Point"}
}