{
  "type": "Feature",
  "properties": {
    "gn:admin1_code":"16.0",
    "gn:admin2_code":"2112655.0",
    "gn:asciiname":"Gotanda",
    "gn:country_code":"JP",
    "gn:dem":177,
    "gn:feature_class":"P",
    "gn:feature_code":"PPLL",
    "gn:name":"Gotanda",
    "gn:population":0,
    "gn:timezone":"Asia/Tokyo",
    "iso:country":"JP",
    "name:jpn_x_preferred":[
        "\u4e94\u53cd\u7530"
    ],
    "wof:name":"Gotanda",
    "wof:placetype":"locality"
},
  "geometry": {"coordinates":[141.42401999999996,38.9368],"type":"Point"}
}