{
  "type": "Feature",
  "properties": {
    "gn:admin1_code":"7.0",
    "gn:admin2_code":"1859306.0",
    "gn:admin3_code":"40107.0",
    "gn:asciiname":"Nishinuki",
    "gn:country_code":"JP",
    "gn:dem":21,
    "gn:feature_class":"P",
    "gn:feature_code":"PPL",
    "gn:name":"Nishinuki",
    "gn:population":0,
    "gn:timezone":"Asia/Tokyo",
    "iso:country":"JP",
    "name:jpn_x_preferred":[
        "\u897f\u8cab"
    ],
    "wof:name":"Nishinuki",
    "wof:placetype":"locality"
},
  "geometry": {"coordinates":[130.91959,33.81809000000001],"type":"Point"}
}