{
  "type": "Feature",
  "properties": {
    "gn:admin1_code":"4.0",
    "gn:admin2_code":"2110982.0",
    "gn:asciiname":"Hayashi",
    "gn:country_code":"JP",
    "gn:dem":94,
    "gn:feature_class":"P",
    "gn:feature_code":"PPLL",
    "gn:name":"Hayashi",
    "gn:population":0,
    "gn:timezone":"Asia/Tokyo",
    "iso:country":"JP",
    "name:jpn_x_preferred":[
        "\u6797"
    ],
    "name:jpn_x_variant":[
        "\u306f\u3084\u3057",
        "\u30cf\u30e4\u30b7"
    ],
    "wof:name":"Hayashi",
    "wof:placetype":"locality"
},
  "geometry": {"coordinates":[140.07186000000002,35.39487000000001],"type":"Point"}
}