{
  "type": "Feature",
  "properties": {
    "gn:admin1_code":"21.0",
    "gn:admin2_code":"1858418.0",
    "gn:admin3_code":"43104.0",
    "gn:asciiname":"Jutcho",
    "gn:country_code":"JP",
    "gn:dem":-1,
    "gn:feature_class":"P",
    "gn:feature_code":"PPLL",
    "gn:name":"Jutch\u014d",
    "gn:population":0,
    "gn:timezone":"Asia/Tokyo",
    "iso:country":"JP",
    "name:jpn_x_preferred":[
        "\u62fe\u753a"
    ],
    "name:jpn_x_variant":[
        "\u3058\u3085\u3063\u3061\u3087\u3046",
        "\u30b8\u30e5\u30c3\u30c1\u30e7\u30a6"
    ],
    "name:und_x_variant":[
        "Jutch\u014d"
    ],
    "wof:name":"Jutcho",
    "wof:placetype":"locality"
},
  "geometry": {"coordinates":[130.64626000000001,32.73965],"type":"Point"}
}