{
  "type": "Feature",
  "properties": {
    "gn:admin1_code":"14",
    "gn:admin2_code":"7452678.0",
    "gn:asciiname":"Shimo-oguri",
    "gn:country_code":"JP",
    "gn:dem":40,
    "gn:feature_class":"P",
    "gn:feature_code":"PPL",
    "gn:name":"Shimo-oguri",
    "gn:population":0,
    "gn:timezone":"Asia/Tokyo",
    "iso:country":"JP",
    "wof:name":"Shimo-oguri",
    "wof:placetype":"locality"
},
  "geometry": {"coordinates":[140.01667,36.35],"type":"Point"}
}