{
  "type": "Feature",
  "properties": {
    "iso:country":"JP",
    "name:eng_x_preferred":[
        "Nishikatsura"
    ],
    "name:eng_x_variant":[
        "Nishikatsura Town"
    ],
    "name:jpn_x_preferred":[
        "\u897f\u6842\u753a"
    ],
    "qs:name":"\u897f\u6842\u753a",
    "qs:name_adm0":"\u65e5\u672c",
    "qs:name_adm1":"\u5c71\u68a8\u770c",
    "qs:photos":69,
    "qs:photos_1k":14,
    "qs:photos_9k":1,
    "qs:photos_9r":2,
    "qs:photos_all":69,
    "qs:photos_sr":2,
    "qs:placetype":"Town",
    "qs:pop_sr":"0",
    "wof:name":"Nishikatsura",
    "wof:placetype":"locality"
},
  "geometry": {"coordinates":[138.812907,35.545282],"type":"Point"}
}