{
  "type": "Feature",
  "properties": {
    "gn:admin1_code":"3.0",
    "gn:admin2_code":"7439944.0",
    "gn:asciiname":"Fukushima",
    "gn:country_code":"JP",
    "gn:dem":8,
    "gn:feature_class":"P",
    "gn:feature_code":"PPL",
    "gn:name":"Fukushima",
    "gn:population":0,
    "gn:timezone":"Asia/Tokyo",
    "iso:country":"JP",
    "name:bre_x_preferred":[
        "Fukushima"
    ],
    "name:cat_x_preferred":[
        "Fukushima"
    ],
    "name:ceb_x_preferred":[
        "Fukushima"
    ],
    "name:ces_x_preferred":[
        "Fuku\u0161ima"
    ],
    "name:deu_x_preferred":[
        "Fukushima"
    ],
    "name:epo_x_preferred":[
        "Fuku\u015dima"
    ],
    "name:fas_x_preferred":[
        "\u0641\u0648\u06a9\u0648\u0634\u06cc\u0645\u0627"
    ],
    "name:fin_x_preferred":[
        "Fukushima"
    ],
    "name:fra_x_preferred":[
        "Fukushima"
    ],
    "name:heb_x_preferred":[
        "\u05e4\u05d5\u05e7\u05d5\u05e9\u05d9\u05de\u05d4"
    ],
    "name:hye_x_preferred":[
        "\u0556\u0578\u0582\u056f\u0578\u0582\u057d\u056b\u0574\u0561"
    ],
    "name:jpn_x_preferred":[
        "\u798f\u5cf6"
    ],
    "name:jpn_x_variant":[
        "\u3075\u304f\u3057\u307e",
        "\u30d5\u30af\u30b7\u30de"
    ],
    "name:kor_x_preferred":[
        "\ud6c4\ucfe0\uc2dc\ub9c8"
    ],
    "name:mlg_x_preferred":[
        "Fukushima"
    ],
    "name:nld_x_preferred":[
        "Fukushima"
    ],
    "name:nor_x_preferred":[
        "Fukushima"
    ],
    "name:pol_x_preferred":[
        "Fukushima"
    ],
    "name:por_x_preferred":[
        "Fukushima"
    ],
    "name:ron_x_preferred":[
        "Fukushima"
    ],
    "name:rus_x_preferred":[
        "\u0424\u0443\u043a\u0443\u0441\u0438\u043c\u0430"
    ],
    "name:spa_x_preferred":[
        "Fukushima"
    ],
    "name:swa_x_preferred":[
        "Fukushima"
    ],
    "name:swe_x_preferred":[
        "Fukushima"
    ],
    "name:tha_x_preferred":[
        "\u0e1f\u0e39\u0e01\u0e39\u0e0a\u0e34\u0e21\u0e30"
    ],
    "name:ukr_x_preferred":[
        "\u0424\u0443\u043a\u0443\u0441\u0456\u043c\u0430"
    ],
    "wof:name":"Fukushima",
    "wof:placetype":"locality"
},
  "geometry": {"coordinates":[140.40648000000002,40.78889],"type":"Point"}
}