{
  "type": "Feature",
  "properties": {
    "gn:admin1_code":"24.0",
    "gn:admin2_code":"7447001.0",
    "gn:asciiname":"Takehara",
    "gn:country_code":"JP",
    "gn:dem":101,
    "gn:feature_class":"P",
    "gn:feature_code":"PPLL",
    "gn:name":"Takehara",
    "gn:population":0,
    "gn:timezone":"Asia/Tokyo",
    "iso:country":"JP",
    "name:jpn_x_preferred":[
        "\u7af9\u539f"
    ],
    "wof:name":"Takehara",
    "wof:placetype":"locality"
},
  "geometry": {"coordinates":[140.80139,38.71972],"type":"Point"}
}