{
  "type": "Feature",
  "properties": {
    "gn:admin1_code":"21.0",
    "gn:admin2_code":"7413150.0",
    "gn:asciiname":"Kamiishibuchi",
    "gn:country_code":"JP",
    "gn:dem":38,
    "gn:feature_class":"P",
    "gn:feature_code":"PPLL",
    "gn:name":"Kamiishibuchi",
    "gn:population":0,
    "gn:timezone":"Asia/Tokyo",
    "iso:country":"JP",
    "name:jpn_x_preferred":[
        "\u4e0a\u77f3\u6e15"
    ],
    "name:jpn_x_variant":[
        "\u304b\u307f\u3044\u3057\u3076\u3061",
        "\u30ab\u30df\u30a4\u30b7\u30d6\u30c1"
    ],
    "wof:name":"Kamiishibuchi",
    "wof:placetype":"locality"
},
  "geometry": {"coordinates":[130.76242999999999,32.99857],"type":"Point"}
}