{
  "type": "Feature",
  "properties": {
    "gn:admin1_code":"33.0",
    "gn:admin2_code":"8300623.0",
    "gn:asciiname":"Nanayama-fujikawa",
    "gn:country_code":"JP",
    "gn:dem":203,
    "gn:feature_class":"P",
    "gn:feature_code":"PPL",
    "gn:name":"Nanayama-fujikawa",
    "gn:population":0,
    "gn:timezone":"Asia/Tokyo",
    "iso:country":"JP",
    "name:jpn_x_preferred":[
        "\u4e03\u5c71\u85e4\u5ddd"
    ],
    "wof:name":"Nanayama-fujikawa",
    "wof:placetype":"locality"
},
  "geometry": {"coordinates":[130.11563999999998,33.44773],"type":"Point"}
}