{
  "type": "Feature",
  "properties": {
    "gn:admin1_code":"45",
    "gn:admin2_code":"1848678.0",
    "gn:asciiname":"Kewari",
    "gn:country_code":"JP",
    "gn:dem":47,
    "gn:feature_class":"P",
    "gn:feature_code":"PPL",
    "gn:name":"Kewari",
    "gn:population":0,
    "gn:timezone":"Asia/Tokyo",
    "iso:country":"JP",
    "wof:name":"Kewari",
    "wof:placetype":"locality"
},
  "geometry": {"coordinates":[131.51667,34.13333],"type":"Point"}
}