{
  "type": "Feature",
  "properties": {
    "gn:admin1_code":"20",
    "gn:admin2_code":"1863048.0",
    "gn:admin3_code":"39428.0",
    "gn:asciiname":"Kamikawaguchi",
    "gn:country_code":"JP",
    "gn:dem":10,
    "gn:feature_class":"P",
    "gn:feature_code":"PPL",
    "gn:name":"Kamikawaguchi",
    "gn:population":0,
    "gn:timezone":"Asia/Tokyo",
    "iso:country":"JP",
    "wof:name":"Kamikawaguchi",
    "wof:placetype":"locality"
},
  "geometry": {"coordinates":[133.05606,33.03987],"type":"Point"}
}