{
  "type": "Feature",
  "properties": {
    "gn:admin1_code":"3.0",
    "gn:admin2_code":"2127674.0",
    "gn:asciiname":"Sakaimatsu",
    "gn:country_code":"JP",
    "gn:dem":72,
    "gn:feature_class":"P",
    "gn:feature_code":"PPL",
    "gn:name":"Sakaimatsu",
    "gn:population":0,
    "gn:timezone":"Asia/Tokyo",
    "iso:country":"JP",
    "name:jpn_x_preferred":[
        "\u6804\u677e"
    ],
    "name:jpn_x_variant":[
        "\u3055\u304b\u3044\u307e\u3064",
        "\u30b5\u30ab\u30a4\u30de\u30c4"
    ],
    "wof:name":"Sakaimatsu",
    "wof:placetype":"locality"
},
  "geometry": {"coordinates":[141.22685000000001,40.65556],"type":"Point"}
}