{
  "type": "Feature",
  "properties": {
    "gn:country":"JP",
    "gn:fcode":"PPL",
    "gn:population":42312,
    "iso:country":"JP",
    "name:ces_x_preferred":[
        "Amagi"
    ],
    "name:deu_x_preferred":[
        "Amagi"
    ],
    "name:fra_x_preferred":[
        "Amagi"
    ],
    "name:ita_x_preferred":[
        "Amagi"
    ],
    "name:jpn_x_preferred":[
        "\u7518\u6728"
    ],
    "name:kor_x_preferred":[
        "\uc544\ub9c8\uae30"
    ],
    "name:mlg_x_preferred":[
        "Amagi"
    ],
    "name:pol_x_preferred":[
        "Amagi"
    ],
    "name:rus_x_preferred":[
        "\u0410\u043c\u0430\u0433\u0438"
    ],
    "name:spa_x_preferred":[
        "Amagi"
    ],
    "name:ukr_x_preferred":[
        "\u0410\u043c\u0430\u0491\u0456"
    ],
    "name:und_x_variant":[
        "Amaki"
    ],
    "qs:name":"Amagi",
    "qs:photos_9r":0,
    "qs:photos_sr":0,
    "qs:pop_sr":"7",
    "wd:wordcount":105,
    "wof:name":"Amagi",
    "wof:placetype":"locality",
    "wof:population":42312
},
  "geometry": {"coordinates":[130.65000000000001,33.41667],"type":"Point"}
}