{
  "type": "Feature",
  "properties": {
    "gn:country":"JP",
    "gn:fcode":"PPL",
    "gn:pop":42312,
    "iso:country":"JP",
    "name:jpn_x_preferred":[
        "\u7518\u6728"
    ],
    "name:unk_x_variant":[
        "Amaki"
    ],
    "qs:name":"Amagi",
    "qs:photos_9r":0,
    "qs:photos_sr":0,
    "qs:pop_sr":"7",
    "wd:wordcount":105,
    "wof:name":"Amagi",
    "wof:placetype":"locality",
    "wof:population":42312
},
  "geometry": {"coordinates":[130.65000000000001,33.41667],"type":"Point"}
}