{
  "type": "Feature",
  "properties": {
    "iso:country":"JP",
    "qs:name":"\u539f\u6751",
    "qs:name_adm0":"\u65e5\u672c",
    "qs:name_adm1":"\u9577\u91ce\u770c",
    "qs:photos":300,
    "qs:photos_1k":61,
    "qs:photos_9k":1,
    "qs:photos_9r":4,
    "qs:photos_all":300,
    "qs:photos_sr":5,
    "qs:placetype":"Town",
    "qs:pop_sr":"0",
    "wof:name":"\u539f\u6751",
    "wof:placetype":"locality"
},
  "geometry": {"coordinates":[138.30614,35.979825],"type":"Point"}
}