{
  "type": "Feature",
  "properties": {
    "gn:admin1_code":"47",
    "gn:admin2_code":"1852456.0",
    "gn:admin3_code":"47362.0",
    "gn:asciiname":"Gushichan",
    "gn:country_code":"JP",
    "gn:dem":43,
    "gn:feature_class":"P",
    "gn:feature_code":"PPL",
    "gn:name":"Gushichan",
    "gn:population":0,
    "gn:timezone":"Asia/Tokyo",
    "iso:country":"JP",
    "name:jpn_x_preferred":[
        "\u5177\u5fd7\u982d"
    ],
    "name:und_x_variant":[
        "Kushikami",
        "Gusityan",
        "Gushicha",
        "Gushikami",
        "Gushichan"
    ],
    "wof:name":"Gushichan",
    "wof:placetype":"locality"
},
  "geometry": {"coordinates":[127.75009,26.12252],"type":"Point"}
}