{
  "type": "Feature",
  "properties": {
    "gn:admin1_code":"16.0",
    "gn:admin2_code":"2128940.0",
    "gn:asciiname":"Kamisawa",
    "gn:country_code":"JP",
    "gn:dem":330,
    "gn:feature_class":"P",
    "gn:feature_code":"PPL",
    "gn:name":"Kamisawa",
    "gn:population":0,
    "gn:timezone":"Asia/Tokyo",
    "iso:country":"JP",
    "name:jpn_x_preferred":[
        "\u4e0a\u6ca2"
    ],
    "name:jpn_x_variant":[
        "\u304b\u307f\u3055\u308f",
        "\u30ab\u30df\u30b5\u30ef"
    ],
    "wof:name":"Kamisawa",
    "wof:placetype":"locality"
},
  "geometry": {"coordinates":[141.11626999999999,40.23872],"type":"Point"}
}