{
  "type": "Feature",
  "properties": {
    "gn:admin1_code":"31",
    "gn:admin2_code":"7405226.0",
    "gn:asciiname":"Ushimadocho-kashino",
    "gn:country_code":"JP",
    "gn:dem":3,
    "gn:feature_class":"P",
    "gn:feature_code":"PPL",
    "gn:name":"Ushimadoch\u014d-kashino",
    "gn:population":0,
    "gn:timezone":"Asia/Tokyo",
    "iso:country":"JP",
    "name:jpn_x_preferred":[
        "\u725b\u7a93\u753a\u9e7f\u5fcd"
    ],
    "name:und_x_variant":[
        "Kasino",
        "Kashinobu",
        "Kashino",
        "Ushimadoch\u014d-kashino"
    ],
    "wof:name":"Ushimadocho-kashino",
    "wof:placetype":"locality"
},
  "geometry": {"coordinates":[134.13333,34.61667],"type":"Point"}
}