{
  "type": "Feature",
  "properties": {
    "gn:admin1_code":"33.0",
    "gn:admin2_code":"8300623.0",
    "gn:asciiname":"Hizenmachi-magarikawa",
    "gn:country_code":"JP",
    "gn:dem":159,
    "gn:feature_class":"P",
    "gn:feature_code":"PPL",
    "gn:name":"Hizenmachi-magarikawa",
    "gn:population":0,
    "gn:timezone":"Asia/Tokyo",
    "iso:country":"JP",
    "name:jpn_x_preferred":[
        "\u80a5\u524d\u753a\u4e07\u8cc0\u91cc\u5ddd"
    ],
    "wof:name":"Hizenmachi-magarikawa",
    "wof:placetype":"locality"
},
  "geometry": {"coordinates":[129.87134,33.41946],"type":"Point"}
}