{
  "type": "Feature",
  "properties": {
    "gn:admin1_code":"21.0",
    "gn:admin2_code":"1850743.0",
    "gn:asciiname":"Eitokuji",
    "gn:country_code":"JP",
    "gn:dem":4,
    "gn:feature_class":"P",
    "gn:feature_code":"PPL",
    "gn:name":"Eitokuji",
    "gn:population":0,
    "gn:timezone":"Asia/Tokyo",
    "iso:country":"JP",
    "name:jpn_x_preferred":[
        "\u6c38\u5fb3\u5bfa"
    ],
    "name:jpn_x_variant":[
        "\u3048\u3044\u3068\u304f\u3058",
        "\u30a8\u30a4\u30c8\u30af\u30b8"
    ],
    "wof:name":"Eitokuji",
    "wof:placetype":"locality"
},
  "geometry": {"coordinates":[130.55878000000001,32.92234000000001],"type":"Point"}
}