{
  "type": "Feature",
  "properties": {
    "gn:admin1_code":"23.0",
    "gn:admin2_code":"1861901.0",
    "gn:asciiname":"Shimoyama",
    "gn:country_code":"JP",
    "gn:dem":204,
    "gn:feature_class":"P",
    "gn:feature_code":"PPL",
    "gn:name":"Shimoyama",
    "gn:population":0,
    "gn:timezone":"Asia/Tokyo",
    "iso:country":"JP",
    "name:jpn_x_preferred":[
        "\u4e0b\u5c71"
    ],
    "wof:name":"Shimoyama",
    "wof:placetype":"locality"
},
  "geometry": {"coordinates":[136.15101000000001,34.86275],"type":"Point"}
}