{
  "type": "Feature",
  "properties": {
    "gn:admin1_code":"11",
    "gn:admin2_code":"1853990.0",
    "gn:asciiname":"Shimogumi",
    "gn:cc2":"JP",
    "gn:country_code":"JP",
    "gn:dem":114,
    "gn:feature_class":"P",
    "gn:feature_code":"PPL",
    "gn:name":"Shimogumi",
    "gn:population":0,
    "gn:timezone":"Asia/Tokyo",
    "iso:country":"JP",
    "name:und_x_variant":[
        "Shimokumi",
        "Shimogumi"
    ],
    "wof:name":"Shimogumi",
    "wof:placetype":"locality"
},
  "geometry": {"coordinates":[133.18333000000001,34.45],"type":"Point"}
}