{
  "type": "Feature",
  "properties": {
    "gn:admin1_code":"4.0",
    "gn:admin2_code":"2112330.0",
    "gn:asciiname":"Hachiman",
    "gn:country_code":"JP",
    "gn:dem":18,
    "gn:feature_class":"P",
    "gn:feature_code":"PPL",
    "gn:name":"Hachiman",
    "gn:population":0,
    "gn:timezone":"Asia/Tokyo",
    "iso:country":"JP",
    "name:cat_x_preferred":[
        "Hachiman"
    ],
    "name:deu_x_preferred":[
        "Hachiman"
    ],
    "name:fas_x_preferred":[
        "\u0647\u0627\u0686\u06cc\u0645\u0627\u0646"
    ],
    "name:fin_x_preferred":[
        "Hachiman"
    ],
    "name:fra_x_preferred":[
        "Hachiman"
    ],
    "name:hun_x_preferred":[
        "Hacsiman"
    ],
    "name:ind_x_preferred":[
        "Hachiman"
    ],
    "name:ita_x_preferred":[
        "Hachiman"
    ],
    "name:jpn_x_preferred":[
        "\u516b\u5e61"
    ],
    "name:jpn_x_variant":[
        "\u516b\u5e61\u795e"
    ],
    "name:kor_x_preferred":[
        "\ud558\uce58\ub9cc \uc2e0"
    ],
    "name:mya_x_preferred":[
        "\u101f\u1001\u103b\u102d\u1019\u1014\u103a\u1038"
    ],
    "name:pol_x_preferred":[
        "Hachiman"
    ],
    "name:por_x_preferred":[
        "Hachiman"
    ],
    "name:rus_x_preferred":[
        "\u0425\u0430\u0442\u0438\u043c\u0430\u043d"
    ],
    "name:slv_x_preferred":[
        "Hachiman"
    ],
    "name:spa_x_preferred":[
        "Hachiman"
    ],
    "name:swe_x_preferred":[
        "Hachiman"
    ],
    "name:ukr_x_preferred":[
        "\u0425\u0430\u0447\u0456\u043c\u0430\u043d"
    ],
    "name:vie_x_preferred":[
        "Hachiman"
    ],
    "name:wuu_x_preferred":[
        "\u516b\u5e61\u795e"
    ],
    "name:zho_x_preferred":[
        "\u516b\u5e61\u795e"
    ],
    "wof:name":"Hachiman",
    "wof:placetype":"locality"
},
  "geometry": {"coordinates":[139.94539,35.8701],"type":"Point"}
}