{
  "type": "Feature",
  "properties": {
    "gn:admin1_code":"28.0",
    "gn:admin2_code":"1855604.0",
    "gn:asciiname":"Tsukigase-momogano",
    "gn:country_code":"JP",
    "gn:dem":265,
    "gn:feature_class":"P",
    "gn:feature_code":"PPL",
    "gn:name":"Tsukigase-momogano",
    "gn:population":0,
    "gn:timezone":"Asia/Tokyo",
    "iso:country":"JP",
    "name:jpn_x_preferred":[
        "\u6708\u30f6\u702c\u6843\u9999\u91ce"
    ],
    "wof:name":"Tsukigase-momogano",
    "wof:placetype":"locality"
},
  "geometry": {"coordinates":[136.00228999999999,34.70522],"type":"Point"}
}