{
  "type": "Feature",
  "properties": {
    "gn:admin1_code":"21.0",
    "gn:admin2_code":"7413150.0",
    "gn:asciiname":"Mitsugusu",
    "gn:country_code":"JP",
    "gn:dem":108,
    "gn:feature_class":"P",
    "gn:feature_code":"PPLL",
    "gn:name":"Mitsugusu",
    "gn:population":0,
    "gn:timezone":"Asia/Tokyo",
    "iso:country":"JP",
    "name:jpn_x_preferred":[
        "\u4e09\u6960"
    ],
    "name:jpn_x_variant":[
        "\u307f\u3064\u3050\u3059",
        "\u30df\u30c4\u30b0\u30b9"
    ],
    "wof:name":"Mitsugusu",
    "wof:placetype":"locality"
},
  "geometry": {"coordinates":[130.67403000000002,33.1173],"type":"Point"}
}