{
  "type": "Feature",
  "properties": {
    "gn:admin1_code":"40.0",
    "gn:admin2_code":"1862785.0",
    "gn:asciiname":"Higashikurume",
    "gn:country_code":"JP",
    "gn:dem":61,
    "gn:feature_class":"P",
    "gn:feature_code":"PPLA2",
    "gn:name":"Higashikurume",
    "gn:population":0,
    "gn:timezone":"Asia/Tokyo",
    "iso:country":"JP",
    "name:jpn_x_preferred":[
        "\u6771\u4e45\u7559\u7c73"
    ],
    "wof:name":"Higashikurume",
    "wof:placetype":"locality"
},
  "geometry": {"coordinates":[139.51168999999999,35.75202],"type":"Point"}
}