{
  "type": "Feature",
  "properties": {
    "gn:admin1_code":"44.0",
    "gn:admin2_code":"2111620.0",
    "gn:admin3_code":"6322.0",
    "gn:asciiname":"Mizusawa",
    "gn:country_code":"JP",
    "gn:dem":236,
    "gn:feature_class":"P",
    "gn:feature_code":"PPL",
    "gn:name":"Mizusawa",
    "gn:population":0,
    "gn:timezone":"Asia/Tokyo",
    "iso:country":"JP",
    "name:deu_x_preferred":[
        "Mizusawa"
    ],
    "name:jpn_x_preferred":[
        "\u6c34\u6ca2"
    ],
    "name:mlg_x_preferred":[
        "Mizusawa"
    ],
    "wof:name":"Mizusawa",
    "wof:placetype":"locality"
},
  "geometry": {"coordinates":[140.10138999999998,38.43417],"type":"Point"}
}