{
  "type": "Feature",
  "properties": {
    "iso:country":"JP",
    "qs:name":"\u559c\u591a\u65b9\u5e02",
    "qs:name_adm0":"\u65e5\u672c",
    "qs:name_adm1":"\u798f\u5cf6\u770c",
    "qs:photos":312,
    "qs:photos_1k":63,
    "qs:photos_9k":3,
    "qs:photos_9r":5,
    "qs:photos_all":745,
    "qs:photos_sr":5,
    "qs:placetype":"Town",
    "qs:pop_sr":"0",
    "wof:name":"\u559c\u591a\u65b9\u5e02",
    "wof:placetype":"locality"
},
  "geometry": {"coordinates":[139.87835899999999,37.6532985],"type":"Point"}
}