{
  "type": "Feature",
  "properties": {
    "gn:admin1_code":"21.0",
    "gn:admin2_code":"1849062.0",
    "gn:asciiname":"Nakano",
    "gn:country_code":"JP",
    "gn:dem":-2,
    "gn:feature_class":"P",
    "gn:feature_code":"PPLL",
    "gn:name":"Nakano",
    "gn:population":0,
    "gn:timezone":"Asia/Tokyo",
    "iso:country":"JP",
    "name:jpn_x_preferred":[
        "\u4e2d\u91ce"
    ],
    "name:jpn_x_variant":[
        "\u306a\u304b\u306e",
        "\u30ca\u30ab\u30ce"
    ],
    "wof:name":"Nakano",
    "wof:placetype":"locality"
},
  "geometry": {"coordinates":[130.66791000000001,32.69633],"type":"Point"}
}