{
  "type": "Feature",
  "properties": {
    "gn:admin1_code":"01",
    "gn:admin2_code":"1859890.0",
    "gn:asciiname":"Sakashita",
    "gn:cc2":"JP",
    "gn:country_code":"JP",
    "gn:dem":95,
    "gn:feature_class":"P",
    "gn:feature_code":"PPL",
    "gn:name":"Sakashita",
    "gn:population":0,
    "gn:timezone":"Asia/Tokyo",
    "iso:country":"JP",
    "name:und_x_variant":[
        "Sakashita-ch\u014d",
        "Sakashita"
    ],
    "wof:name":"Sakashita",
    "wof:placetype":"locality"
},
  "geometry": {"coordinates":[137.01667,35.28333],"type":"Point"}
}