{
  "type": "Feature",
  "properties": {
    "iso:country":"JP",
    "name:jpn_x_preferred":[
        "\uff08\u4e01\u76ee\u306a\u3057\uff09"
    ],
    "qs:gn_adm0_cc":"JP",
    "qs:gn_local":1907165,
    "qs:gn_nam_loc":"\u56fd\u7acb\u5e02, \u6771\u4eac\u90fd, JP",
    "qs:gn_namadm1":"40",
    "qs:local_max":524,
    "qs:local_sum":1030,
    "qs:localhoods":7,
    "qs:name":"\uff08\u4e01\u76ee\u306a\u3057\uff09",
    "qs:name_adm0":"\u65e5\u672c",
    "qs:name_adm1":"\u6771\u4eac\u90fd",
    "qs:name_lau":"\u9752\u67f3",
    "qs:name_local":"\u56fd\u7acb\u5e02",
    "qs:photo_max":9,
    "qs:photo_sum":17,
    "qs:placetype":"Suburb",
    "qs:quad_count":5,
    "qs:woe_adm0":23424856,
    "qs:woe_adm1":2345889,
    "qs:woe_adm2":0,
    "qs:woe_lau":28415215,
    "qs:woe_local":15015480,
    "qs:woe_ver":"7.10.0",
    "wof:lang":[
        "jpn"
    ],
    "wof:name":"\uff08\u4e01\u76ee\u306a\u3057\uff09",
    "wof:placetype":"neighbourhood"
},
  "geometry": {"coordinates":[139.42749000000001,35.676264],"type":"Point"}
}