{
  "type": "Feature",
  "properties": {
    "gn:admin1_code":"40.0",
    "gn:admin2_code":"1861322.0",
    "gn:asciiname":"Oyaguchi",
    "gn:country_code":"JP",
    "gn:dem":40,
    "gn:feature_class":"P",
    "gn:feature_code":"PPL",
    "gn:name":"\u014cyaguchi",
    "gn:population":0,
    "gn:timezone":"Asia/Tokyo",
    "iso:country":"JP",
    "name:jpn_x_preferred":[
        "\u5927\u8c37\u53e3"
    ],
    "name:jpn_x_variant":[
        "\u304a\u304a\u3084\u3050\u3061",
        "\u30aa\u30aa\u30e4\u30b0\u30c1"
    ],
    "name:und_x_variant":[
        "\u014cyaguchi"
    ],
    "wof:name":"Oyaguchi",
    "wof:placetype":"locality"
},
  "geometry": {"coordinates":[139.68888000000001,35.74508],"type":"Point"}
}