{
  "type": "Feature",
  "properties": {
    "gn:admin1_code":"44.0",
    "gn:admin2_code":"2111620.0",
    "gn:admin3_code":"6322.0",
    "gn:asciiname":"Kaishu",
    "gn:country_code":"JP",
    "gn:dem":179,
    "gn:feature_class":"P",
    "gn:feature_code":"PPL",
    "gn:name":"Kaish\u016b",
    "gn:population":0,
    "gn:timezone":"Asia/Tokyo",
    "iso:country":"JP",
    "name:jpn_x_preferred":[
        "\u6d77\u5473"
    ],
    "name:und_x_variant":[
        "Kaish\u016b"
    ],
    "wof:name":"Kaishu",
    "wof:placetype":"locality"
},
  "geometry": {"coordinates":[140.14675,38.42257],"type":"Point"}
}