{
  "type": "Feature",
  "properties": {
    "gn:country":"JP",
    "iso:country":"JP",
    "qs:name":"\u5317\u8c37\u753a",
    "qs:name_adm0":"\u65e5\u672c",
    "qs:name_adm1":"\u6c96\u7e04\u770c",
    "qs:photos":1167,
    "qs:photos_1k":236,
    "qs:photos_9k":247,
    "qs:photos_9r":25,
    "qs:photos_all":55619,
    "qs:photos_sr":11,
    "qs:placetype":"Town",
    "qs:pop_sr":"0",
    "wof:name":"\u5317\u8c37\u753a",
    "wof:placetype":"locality"
},
  "geometry": {"coordinates":[127.75836,26.31168],"type":"Point"}
}