{
  "type": "Feature",
  "properties": {
    "gn:admin1_code":"3.0",
    "gn:admin2_code":"2127674.0",
    "gn:asciiname":"Yagami",
    "gn:country_code":"JP",
    "gn:dem":111,
    "gn:feature_class":"P",
    "gn:feature_code":"PPL",
    "gn:name":"Yagami",
    "gn:population":0,
    "gn:timezone":"Asia/Tokyo",
    "iso:country":"JP",
    "name:deu_x_preferred":[
        "Yagami"
    ],
    "name:jpn_x_preferred":[
        "\u77e2\u795e"
    ],
    "name:jpn_x_variant":[
        "\u3084\u304c\u307f",
        "\u30e4\u30ac\u30df"
    ],
    "wof:name":"Yagami",
    "wof:placetype":"locality"
},
  "geometry": {"coordinates":[141.14011000000005,40.5958],"type":"Point"}
}