{
  "type": "Feature",
  "properties": {
    "gn:admin1_code":"21.0",
    "gn:admin2_code":"1865358.0",
    "gn:asciiname":"Kokushigo",
    "gn:country_code":"JP",
    "gn:dem":20,
    "gn:feature_class":"P",
    "gn:feature_code":"PPLL",
    "gn:name":"Kokushigo",
    "gn:population":0,
    "gn:timezone":"Asia/Tokyo",
    "iso:country":"JP",
    "name:jpn_x_preferred":[
        "\u5c0f\u4e32\u5ddd"
    ],
    "name:jpn_x_variant":[
        "\u3053\u304f\u3057\u3054",
        "\u30b3\u30af\u30b7\u30b4"
    ],
    "wof:name":"Kokushigo",
    "wof:placetype":"locality"
},
  "geometry": {"coordinates":[130.36239,32.42907],"type":"Point"}
}