{
  "type": "Feature",
  "properties": {
    "gn:admin1_code":"37.0",
    "gn:admin2_code":"1864089.0",
    "gn:asciiname":"Katakuracho",
    "gn:country_code":"JP",
    "gn:dem":209,
    "gn:feature_class":"P",
    "gn:feature_code":"PPLL",
    "gn:name":"Katakurach\u014d",
    "gn:population":0,
    "gn:timezone":"Asia/Tokyo",
    "iso:country":"JP",
    "name:jpn_x_preferred":[
        "\u7247\u5009\u753a\u3000"
    ],
    "name:und_x_variant":[
        "Katakurach\u014d"
    ],
    "wof:name":"Katakuracho",
    "wof:placetype":"locality"
},
  "geometry": {"coordinates":[138.68817000000001,35.20504000000001],"type":"Point"}
}