{
  "type": "Feature",
  "properties": {
    "iso:country":"JP",
    "name:eng_x_preferred":[
        "Nojihigashi 1 Chome"
    ],
    "name:eng_x_variant":[
        "Nojihigashi 1 Choume",
        "Nojihigashi 1 Chome"
    ],
    "name:jpn_x_preferred":[
        "\uff11\u4e01\u76ee"
    ],
    "name:jpn_x_variant":[
        "\u306e\u3058\u3072\u304c\u3057 \uff11\u3061\u3087\u3046\u3081",
        "\u91ce\u8def\u6771 \uff11\u4e01\u76ee",
        "\uff11\u3061\u3087\u3046\u3081"
    ],
    "qs:gn_local":0,
    "qs:local_max":195,
    "qs:local_sum":293,
    "qs:localhoods":3,
    "qs:name":"\uff11\u4e01\u76ee",
    "qs:name_adm0":"\u65e5\u672c",
    "qs:name_adm1":"\u6ecb\u8cc0\u770c",
    "qs:name_en":"Nojihigashi 1 Chome",
    "qs:name_lau":"\u91ce\u8def\u6771",
    "qs:name_local":"\u8349\u6d25\u5e02",
    "qs:photo_max":16,
    "qs:photo_sum":34,
    "qs:placetype":"Suburb",
    "qs:quad_count":4,
    "qs:woe_adm0":23424856,
    "qs:woe_adm1":2345884,
    "qs:woe_adm2":0,
    "qs:woe_lau":28448655,
    "qs:woe_local":1117636,
    "qs:woe_ver":"7.10.0",
    "wof:lang":[
        "jpn"
    ],
    "wof:name":"\uff11\u4e01\u76ee",
    "wof:placetype":"neighbourhood"
},
  "geometry": {"coordinates":[135.96340599999999,34.981033],"type":"Point"}
}