{
  "type": "Feature",
  "properties": {
    "gn:admin1_code":"3.0",
    "gn:admin2_code":"7439944.0",
    "gn:asciiname":"Yoda",
    "gn:country_code":"JP",
    "gn:dem":7,
    "gn:feature_class":"P",
    "gn:feature_code":"PPL",
    "gn:name":"Y\u014dda",
    "gn:population":0,
    "gn:timezone":"Asia/Tokyo",
    "iso:country":"JP",
    "name:ara_x_preferred":[
        "\u064a\u0648\u062f\u0627"
    ],
    "name:ast_x_preferred":[
        "Yoda"
    ],
    "name:bel_x_preferred":[
        "\u0401\u0434\u0430"
    ],
    "name:bul_x_preferred":[
        "\u0419\u043e\u0434\u0430"
    ],
    "name:cat_x_preferred":[
        "Yoda"
    ],
    "name:ces_x_preferred":[
        "Yoda"
    ],
    "name:dan_x_preferred":[
        "Yoda"
    ],
    "name:ell_x_preferred":[
        "\u0393\u03b9\u03cc\u03bd\u03c4\u03b1"
    ],
    "name:epo_x_preferred":[
        "Joda"
    ],
    "name:eus_x_preferred":[
        "Yoda"
    ],
    "name:fas_x_preferred":[
        "\u06cc\u0648\u062f\u0627"
    ],
    "name:fin_x_preferred":[
        "Yoda"
    ],
    "name:fra_x_preferred":[
        "Yoda"
    ],
    "name:glg_x_preferred":[
        "Yoda"
    ],
    "name:heb_x_preferred":[
        "\u05d9\u05d5\u05d3\u05d4"
    ],
    "name:hrv_x_preferred":[
        "Yoda"
    ],
    "name:hun_x_preferred":[
        "Yoda"
    ],
    "name:ind_x_preferred":[
        "Yoda"
    ],
    "name:ita_x_preferred":[
        "Yoda"
    ],
    "name:jpn_x_preferred":[
        "\u6804\u7530"
    ],
    "name:jpn_x_variant":[
        "\u3088\u3046\u3060",
        "\u30e8\u30a6\u30c0",
        "\u30e8\u30fc\u30c0"
    ],
    "name:kat_x_preferred":[
        "\u10d8\u10dd\u10d3\u10d0"
    ],
    "name:kaz_x_preferred":[
        "\u0419\u043e\u0434\u0430"
    ],
    "name:lat_x_preferred":[
        "Yoda"
    ],
    "name:lav_x_preferred":[
        "Joda"
    ],
    "name:nld_x_preferred":[
        "Yoda"
    ],
    "name:nor_x_preferred":[
        "Yoda"
    ],
    "name:pol_x_preferred":[
        "Yoda"
    ],
    "name:por_x_preferred":[
        "Yoda"
    ],
    "name:ron_x_preferred":[
        "Yoda"
    ],
    "name:rus_x_preferred":[
        "\u0419\u043e\u0434\u0430"
    ],
    "name:sco_x_preferred":[
        "Yoda"
    ],
    "name:slk_x_preferred":[
        "Yoda"
    ],
    "name:slv_x_preferred":[
        "Yoda"
    ],
    "name:spa_x_preferred":[
        "Yoda"
    ],
    "name:srp_x_preferred":[
        "\u0408\u043e\u0434\u0430"
    ],
    "name:swe_x_preferred":[
        "Yoda"
    ],
    "name:tha_x_preferred":[
        "\u0e42\u0e22\u0e14\u0e32"
    ],
    "name:tur_x_preferred":[
        "Yoda"
    ],
    "name:ukr_x_preferred":[
        "\u0419\u043e\u0434\u0430"
    ],
    "name:und_x_variant":[
        "Y\u014dda"
    ],
    "name:vie_x_preferred":[
        "Yoda"
    ],
    "name:yid_x_preferred":[
        "\u05d9\u05d0\u05d3\u05d0"
    ],
    "wof:name":"Yoda",
    "wof:placetype":"locality"
},
  "geometry": {"coordinates":[140.39009999999999,40.79186],"type":"Point"}
}