{
  "type": "Feature",
  "properties": {
    "gn:admin1_code":"3.0",
    "gn:admin2_code":"7439944.0",
    "gn:asciiname":"Yoda",
    "gn:country_code":"JP",
    "gn:dem":7,
    "gn:feature_class":"P",
    "gn:feature_code":"PPL",
    "gn:name":"Y\u014dda",
    "gn:population":0,
    "gn:timezone":"Asia/Tokyo",
    "iso:country":"JP",
    "name:jpn_x_preferred":[
        "\u6804\u7530"
    ],
    "name:jpn_x_variant":[
        "\u3088\u3046\u3060",
        "\u30e8\u30a6\u30c0"
    ],
    "name:und_x_variant":[
        "Y\u014dda"
    ],
    "wof:name":"Yoda",
    "wof:placetype":"locality"
},
  "geometry": {"coordinates":[140.39009999999999,40.79186],"type":"Point"}
}