{
  "type": "Feature",
  "properties": {
    "gn:admin1_code":"3.0",
    "gn:admin2_code":"7439934.0",
    "gn:asciiname":"Ikarigaseki",
    "gn:country_code":"JP",
    "gn:dem":141,
    "gn:feature_class":"P",
    "gn:feature_code":"PPL",
    "gn:name":"Ikarigaseki",
    "gn:population":0,
    "gn:timezone":"Asia/Tokyo",
    "iso:country":"JP",
    "name:fas_x_preferred":[
        "\u0627\u06cc\u06a9\u0627\u0631\u06cc\u06af\u0627\u0633\u06a9\u06cc"
    ],
    "name:jpn_x_preferred":[
        "\u7887\u30f6\u95a2"
    ],
    "name:jpn_x_variant":[
        "\u3044\u304b\u308a\u304c\u305b\u304d",
        "\u30a4\u30ab\u30ea\u30ac\u30bb\u30ad",
        "\u7887\u30f6\u95a2\u6751"
    ],
    "wof:name":"Ikarigaseki",
    "wof:placetype":"locality"
},
  "geometry": {"coordinates":[140.62922,40.47807],"type":"Point"}
}