{
  "type": "Feature",
  "properties": {
    "gn:admin1_code":"12.0",
    "gn:admin2_code":"7428097.0",
    "gn:admin3_code":"1643.0",
    "gn:asciiname":"Churui-nishikimachi",
    "gn:country_code":"JP",
    "gn:dem":87,
    "gn:feature_class":"P",
    "gn:feature_code":"PPL",
    "gn:name":"Ch\u016brui-nishikimachi",
    "gn:population":0,
    "gn:timezone":"Asia/Tokyo",
    "iso:country":"JP",
    "name:jpn_x_preferred":[
        "\u5fe0\u985e\u9326\u753a"
    ],
    "name:jpn_x_variant":[
        "\u3061\u3085\u3046\u308b\u3044\u306b\u3057\u304d\u307e\u3061",
        "\u30c1\u30e5\u30a6\u30eb\u30a4\u30cb\u30b7\u30ad\u30de\u30c1"
    ],
    "name:und_x_variant":[
        "Ch\u016brui-nishikimachi"
    ],
    "wof:name":"Churui-nishikimachi",
    "wof:placetype":"locality"
},
  "geometry": {"coordinates":[143.30991,42.56809000000001],"type":"Point"}
}