{
  "type": "Feature",
  "properties": {
    "gn:admin1_code":"2.0",
    "gn:admin2_code":"2113122.0",
    "gn:asciiname":"Tsuchizakimminato-sozenmachi",
    "gn:country_code":"JP",
    "gn:dem":8,
    "gn:feature_class":"P",
    "gn:feature_code":"PPL",
    "gn:name":"Tsuchizakimminato-s\u014dzenmachi",
    "gn:population":0,
    "gn:timezone":"Asia/Tokyo",
    "iso:country":"JP",
    "name:jpn_x_preferred":[
        "\u571f\u5d0e\u6e2f\u76f8\u67d3\u753a"
    ],
    "name:jpn_x_variant":[
        "\u3064\u3061\u3056\u304d\u307f\u306a\u3068\u305d\u3046\u305c\u3093\u307e\u3061",
        "\u30c4\u30c1\u30b6\u30ad\u30df\u30ca\u30c8\u30bd\u30a6\u30bc\u30f3\u30de\u30c1"
    ],
    "name:und_x_variant":[
        "Tsuchizakimminato-s\u014dzenmachi"
    ],
    "wof:name":"Tsuchizakimminato-sozenmachi",
    "wof:placetype":"locality"
},
  "geometry": {"coordinates":[140.06044,39.76931],"type":"Point"}
}