{
  "type": "Feature",
  "properties": {
    "gn:admin1_code":"3.0",
    "gn:admin2_code":"2130200.0",
    "gn:asciiname":"Aotsukuri",
    "gn:country_code":"JP",
    "gn:dem":180,
    "gn:feature_class":"P",
    "gn:feature_code":"PPL",
    "gn:name":"Aotsukuri",
    "gn:population":0,
    "gn:timezone":"Asia/Tokyo",
    "iso:country":"JP",
    "name:jpn_x_preferred":[
        "\u6ce5\u969c\u4f5c"
    ],
    "name:jpn_x_variant":[
        "\u3042\u304a\u3064\u304f\u308a",
        "\u30a2\u30aa\u30c4\u30af\u30ea"
    ],
    "wof:name":"Aotsukuri",
    "wof:placetype":"locality"
},
  "geometry": {"coordinates":[141.45264,40.43053],"type":"Point"}
}