{
  "type": "Feature",
  "properties": {
    "iso:country":"JP",
    "name:eng_x_preferred":[
        "Okitamachi 3 Chome"
    ],
    "name:eng_x_variant":[
        "Okitamachi 3 Choume",
        "Okitamachi 3 Chome"
    ],
    "name:jpn_x_preferred":[
        "\uff13\u4e01\u76ee"
    ],
    "name:jpn_x_variant":[
        "\u304a\u304d\u305f\u307e\u3061 \uff13\u3061\u3087\u3046\u3081",
        "\u6c96\u7530\u753a \uff13\u4e01\u76ee",
        "\uff13\u3061\u3087\u3046\u3081"
    ],
    "qs:gn_local":0,
    "qs:local_max":497,
    "qs:local_sum":807,
    "qs:localhoods":6,
    "qs:name":"\uff13\u4e01\u76ee",
    "qs:name_adm0":"\u65e5\u672c",
    "qs:name_adm1":"\u9577\u91ce\u770c",
    "qs:name_en":"Okitamachi 3 Chome",
    "qs:name_lau":"\u6c96\u7530\u753a",
    "qs:name_local":"\u8acf\u8a2a\u5e02",
    "qs:photo_max":13,
    "qs:photo_sum":58,
    "qs:placetype":"Suburb",
    "qs:quad_count":14,
    "qs:woe_adm0":23424856,
    "qs:woe_adm1":2345875,
    "qs:woe_adm2":0,
    "qs:woe_lau":28431886,
    "qs:woe_local":1118248,
    "qs:woe_ver":"7.10.0",
    "wof:lang":[
        "jpn"
    ],
    "wof:name":"\uff13\u4e01\u76ee",
    "wof:placetype":"neighbourhood"
},
  "geometry": {"coordinates":[138.13373200000001,35.995346],"type":"Point"}
}