{
  "type": "Feature",
  "properties": {
    "gn:admin1_code":"28.0",
    "gn:admin2_code":"1853062.0",
    "gn:asciiname":"Wada",
    "gn:country_code":"JP",
    "gn:dem":283,
    "gn:feature_class":"P",
    "gn:feature_code":"PPL",
    "gn:name":"Wada",
    "gn:population":0,
    "gn:timezone":"Asia/Tokyo",
    "iso:country":"JP",
    "name:jpn_x_preferred":[
        "\u548c\u7530"
    ],
    "wof:name":"Wada",
    "wof:placetype":"locality"
},
  "geometry": {"coordinates":[135.91141999999999,34.55163],"type":"Point"}
}