{
  "type": "Feature",
  "properties": {
    "gn:admin1_code":"2.0",
    "gn:admin2_code":"2129594.0",
    "gn:admin3_code":"5303.0",
    "gn:asciiname":"Araya",
    "gn:country_code":"JP",
    "gn:dem":166,
    "gn:feature_class":"P",
    "gn:feature_code":"PPL",
    "gn:name":"Araya",
    "gn:population":0,
    "gn:timezone":"Asia/Tokyo",
    "iso:country":"JP",
    "name:ceb_x_preferred":[
        "Araya"
    ],
    "name:deu_x_preferred":[
        "Araya"
    ],
    "name:fra_x_preferred":[
        "Araya"
    ],
    "name:ita_x_preferred":[
        "Araya"
    ],
    "name:jpn_x_preferred":[
        "\u8352\u8c37"
    ],
    "name:rus_x_preferred":[
        "\u0410\u0440\u0430\u044f"
    ],
    "name:spa_x_preferred":[
        "Araya"
    ],
    "name:swe_x_preferred":[
        "Araya"
    ],
    "wof:name":"Araya",
    "wof:placetype":"locality"
},
  "geometry": {"coordinates":[140.76154,40.29727000000001],"type":"Point"}
}