{
  "type": "Feature",
  "properties": {
    "gn:admin1_code":"24.0",
    "gn:admin2_code":"2112574.0",
    "gn:asciiname":"Futawatashihama",
    "gn:country_code":"JP",
    "gn:dem":18,
    "gn:feature_class":"P",
    "gn:feature_code":"PPL",
    "gn:name":"Futawatashihama",
    "gn:population":0,
    "gn:timezone":"Asia/Tokyo",
    "iso:country":"JP",
    "name:jpn_x_preferred":[
        "\u821f\u6e21\u6d5c"
    ],
    "name:jpn_x_variant":[
        "\u3075\u305f\u308f\u305f\u3057\u306f\u307e",
        "\u30d5\u30bf\u30ef\u30bf\u30b7\u30cf\u30de"
    ],
    "name:und_x_variant":[
        "Futawadashi",
        "Futawatashi",
        "Hutawatasi",
        "Ch\u014dt\u014d",
        "Futawatari",
        "Futawatashihama"
    ],
    "wof:name":"Futawatashihama",
    "wof:placetype":"locality"
},
  "geometry": {"coordinates":[141.4939,38.25394],"type":"Point"}
}