{
  "type": "Feature",
  "properties": {
    "gn:admin1_code":"11",
    "gn:admin2_code":"1858288.0",
    "gn:asciiname":"Hiro-honmachi",
    "gn:country_code":"JP",
    "gn:dem":7,
    "gn:feature_class":"P",
    "gn:feature_code":"PPL",
    "gn:name":"Hiro-honmachi",
    "gn:population":0,
    "gn:timezone":"Asia/Tokyo",
    "iso:country":"JP",
    "name:jpn_x_preferred":[
        "\u5e83\u672c\u753a"
    ],
    "name:und_x_variant":[
        "Hiro",
        "Hiromachi",
        "Hiro-honmachi"
    ],
    "wof:name":"Hiro-honmachi",
    "wof:placetype":"locality"
},
  "geometry": {"coordinates":[132.61994999999999,34.2323],"type":"Point"}
}