{
  "type": "Feature",
  "properties": {
    "gn:admin1_code":"3.0",
    "gn:admin2_code":"8534376.0",
    "gn:admin3_code":"2321.0",
    "gn:asciiname":"Akaishimachi",
    "gn:country_code":"JP",
    "gn:dem":41,
    "gn:feature_class":"P",
    "gn:feature_code":"PPL",
    "gn:name":"Akaishimachi",
    "gn:population":0,
    "gn:timezone":"Asia/Tokyo",
    "iso:country":"JP",
    "name:jpn_x_preferred":[
        "\u8d64\u77f3\u753a"
    ],
    "name:jpn_x_variant":[
        "\u3042\u304b\u3044\u3057\u307e\u3061",
        "\u30a2\u30ab\u30a4\u30b7\u30de\u30c1"
    ],
    "wof:name":"Akaishimachi",
    "wof:placetype":"locality"
},
  "geometry": {"coordinates":[140.17807999999999,40.76878],"type":"Point"}
}