{
  "type": "Feature",
  "properties": {
    "gn:admin1_code":"19.0",
    "gn:admin2_code":"1856851.0",
    "gn:admin3_code":"14301.0",
    "gn:asciiname":"Shimoyamaguchi",
    "gn:country_code":"JP",
    "gn:dem":90,
    "gn:feature_class":"P",
    "gn:feature_code":"PPL",
    "gn:name":"Shimoyamaguchi",
    "gn:population":0,
    "gn:timezone":"Asia/Tokyo",
    "iso:country":"JP",
    "name:jpn_x_preferred":[
        "\u4e0b\u5c71\u53e3"
    ],
    "name:jpn_x_variant":[
        "\u3057\u3082\u3084\u307e\u3050\u3061",
        "\u30b7\u30e2\u30e4\u30de\u30b0\u30c1"
    ],
    "wof:name":"Shimoyamaguchi",
    "wof:placetype":"locality"
},
  "geometry": {"coordinates":[139.58931999999999,35.25775],"type":"Point"}
}