{
  "type": "Feature",
  "properties": {
    "gn:admin1_code":"13",
    "gn:admin2_code":"7370809.0",
    "gn:admin3_code":"28585.0",
    "gn:asciiname":"Okinoura",
    "gn:country_code":"JP",
    "gn:dem":3,
    "gn:feature_class":"P",
    "gn:feature_code":"PPL",
    "gn:name":"Okinoura",
    "gn:population":0,
    "gn:timezone":"Asia/Tokyo",
    "iso:country":"JP",
    "wof:name":"Okinoura",
    "wof:placetype":"locality"
},
  "geometry": {"coordinates":[134.65853999999999,35.65851],"type":"Point"}
}