{
  "type": "Feature",
  "properties": {
    "iso:country":"JP",
    "name:eng_x_preferred":[
        "Kannonjishinmachi 2 Chome"
    ],
    "name:eng_x_variant":[
        "Kannonjishinmachi 2 Choume",
        "Kannonjishinmachi 2 Chome"
    ],
    "name:jpn_x_preferred":[
        "\uff12\u4e01\u76ee"
    ],
    "name:jpn_x_variant":[
        "\u304b\u3093\u306e\u3093\u3058\u3057\u3093\u307e\u3061 \uff12\u3061\u3087\u3046\u3081",
        "\u89b3\u97f3\u5bfa\u65b0\u753a \uff12\u4e01\u76ee",
        "\uff12\u3061\u3087\u3046\u3081"
    ],
    "qs:gn_local":0,
    "qs:local_max":94,
    "qs:local_sum":136,
    "qs:localhoods":7,
    "qs:name":"\uff12\u4e01\u76ee",
    "qs:name_adm0":"\u65e5\u672c",
    "qs:name_adm1":"\u9ce5\u53d6\u770c",
    "qs:name_en":"Kannonjishinmachi 2 Chome",
    "qs:name_lau":"\u89b3\u97f3\u5bfa\u65b0\u753a",
    "qs:name_local":"\u7c73\u5b50\u5e02",
    "qs:photo_max":1,
    "qs:photo_sum":1,
    "qs:placetype":"Suburb",
    "qs:quad_count":1,
    "qs:woe_adm0":23424856,
    "qs:woe_adm1":2345890,
    "qs:woe_adm2":0,
    "qs:woe_lau":28469591,
    "qs:woe_local":1118555,
    "qs:woe_ver":"7.10.0",
    "wof:lang":[
        "jpn"
    ],
    "wof:name":"\uff12\u4e01\u76ee",
    "wof:placetype":"neighbourhood"
},
  "geometry": {"coordinates":[133.35479699999999,35.413677],"type":"Point"}
}