{
  "type": "Feature",
  "properties": {
    "gn:admin1_code":"7.0",
    "gn:admin2_code":"7406950.0",
    "gn:admin3_code":"40625.0",
    "gn:asciiname":"Saigawa-honjo",
    "gn:country_code":"JP",
    "gn:dem":26,
    "gn:feature_class":"P",
    "gn:feature_code":"PPL",
    "gn:name":"Saigawa-honj\u014d",
    "gn:population":0,
    "gn:timezone":"Asia/Tokyo",
    "iso:country":"JP",
    "name:jpn_x_preferred":[
        "\u7280\u5ddd\u672c\u5e84"
    ],
    "name:und_x_variant":[
        "Saigawa-honj\u014d"
    ],
    "wof:name":"Saigawa-honjo",
    "wof:placetype":"locality"
},
  "geometry": {"coordinates":[130.93827999999999,33.64783],"type":"Point"}
}