{
  "type": "Feature",
  "properties": {
    "gn:admin1_code":"17",
    "gn:admin2_code":"1853186.0",
    "gn:asciiname":"Takayacho",
    "gn:country_code":"JP",
    "gn:dem":8,
    "gn:feature_class":"P",
    "gn:feature_code":"PPL",
    "gn:name":"Takayach\u014d",
    "gn:population":0,
    "gn:timezone":"Asia/Tokyo",
    "iso:country":"JP",
    "name:jpn_x_preferred":[
        "\u9ad8\u5c4b\u753a"
    ],
    "name:und_x_variant":[
        "Takayach\u014d",
        "Takaya"
    ],
    "wof:name":"Takayacho",
    "wof:placetype":"locality"
},
  "geometry": {"coordinates":[133.90928,34.33371],"type":"Point"}
}