{
  "type": "Feature",
  "properties": {
    "gn:admin1_code":"19.0",
    "gn:admin2_code":"1848595.0",
    "gn:asciiname":"Uenohara",
    "gn:country_code":"JP",
    "gn:dem":37,
    "gn:feature_class":"P",
    "gn:feature_code":"PPLL",
    "gn:name":"Uenohara",
    "gn:population":0,
    "gn:timezone":"Asia/Tokyo",
    "iso:country":"JP",
    "name:jpn_x_preferred":[
        "\u4e0a\u30ce\u539f"
    ],
    "wof:name":"Uenohara",
    "wof:placetype":"locality"
},
  "geometry": {"coordinates":[139.47135,35.43342],"type":"Point"}
}