{
  "type": "Feature",
  "properties": {
    "gn:admin1_code":"46.0",
    "gn:asciiname":"Mizunoki",
    "gn:country_code":"JP",
    "gn:dem":618,
    "gn:feature_class":"P",
    "gn:feature_code":"PPLL",
    "gn:name":"Mizunoki",
    "gn:population":0,
    "gn:timezone":"Asia/Tokyo",
    "iso:country":"JP",
    "name:jpn_x_preferred":[
        "\u6c34\u30ce\u6728\u3000"
    ],
    "wof:name":"Mizunoki",
    "wof:placetype":"locality"
},
  "geometry": {"coordinates":[138.96875,35.42856],"type":"Point"}
}