{
  "type": "Feature",
  "properties": {
    "gn:admin1_code":"4.0",
    "gn:admin2_code":"1850520.0",
    "gn:asciiname":"Takigawa",
    "gn:country_code":"JP",
    "gn:dem":15,
    "gn:feature_class":"P",
    "gn:feature_code":"PPLL",
    "gn:name":"Takigawa",
    "gn:population":0,
    "gn:timezone":"Asia/Tokyo",
    "iso:country":"JP",
    "name:jpn_x_preferred":[
        "\u6edd\u5ddd"
    ],
    "name:jpn_x_variant":[
        "\u305f\u304d\u304c\u308f",
        "\u30bf\u30ad\u30ac\u30ef"
    ],
    "wof:name":"Takigawa",
    "wof:placetype":"locality"
},
  "geometry": {"coordinates":[139.89453999999998,35.00147],"type":"Point"}
}