{
  "type": "Feature",
  "properties": {
    "gn:admin1_code":"29",
    "gn:admin2_code":"7468181.0",
    "gn:asciiname":"Toya",
    "gn:country_code":"JP",
    "gn:dem":510,
    "gn:feature_class":"P",
    "gn:feature_code":"PPL",
    "gn:name":"Toya",
    "gn:population":0,
    "gn:timezone":"Asia/Tokyo",
    "iso:country":"JP",
    "name:ceb_x_preferred":[
        "Toya"
    ],
    "name:deu_x_preferred":[
        "Toya"
    ],
    "name:fra_x_preferred":[
        "Toya"
    ],
    "name:ita_x_preferred":[
        "Toya"
    ],
    "name:spa_x_preferred":[
        "Toya"
    ],
    "wof:name":"Toya",
    "wof:placetype":"locality"
},
  "geometry": {"coordinates":[138.83333000000002,37.06667],"type":"Point"}
}