{
  "type": "Feature",
  "properties": {
    "gn:admin1_code":"18.0",
    "gn:admin2_code":"7383999.0",
    "gn:admin3_code":"46490.0",
    "gn:asciiname":"Ohashi",
    "gn:country_code":"JP",
    "gn:dem":5,
    "gn:feature_class":"P",
    "gn:feature_code":"PPLL",
    "gn:name":"\u014chashi",
    "gn:population":0,
    "gn:timezone":"Asia/Tokyo",
    "iso:country":"JP",
    "name:jpn_x_preferred":[
        "\u5927\u6a4b"
    ],
    "name:und_x_variant":[
        "\u014chashi"
    ],
    "wof:name":"Ohashi",
    "wof:placetype":"locality"
},
  "geometry": {"coordinates":[130.77553999999998,31.23972],"type":"Point"}
}