{
  "type": "Feature",
  "properties": {
    "gn:admin1_code":"23.0",
    "gn:admin2_code":"1848873.0",
    "gn:admin3_code":"24472.0",
    "gn:asciiname":"Sarakuwagama",
    "gn:country_code":"JP",
    "gn:dem":9,
    "gn:feature_class":"P",
    "gn:feature_code":"PPL",
    "gn:name":"Sarakuwagama",
    "gn:population":0,
    "gn:timezone":"Asia/Tokyo",
    "iso:country":"JP",
    "name:jpn_x_preferred":[
        "\u65b0\u6851\u7ac8"
    ],
    "wof:name":"Sarakuwagama",
    "wof:placetype":"locality"
},
  "geometry": {"coordinates":[136.43803,34.24516],"type":"Point"}
}