{
  "type": "Feature",
  "properties": {
    "gn:admin1_code":"21",
    "gn:admin2_code":"7412706.0",
    "gn:admin3_code":"43447.0",
    "gn:asciiname":"Mamihara",
    "gn:country_code":"JP",
    "gn:dem":527,
    "gn:feature_class":"P",
    "gn:feature_code":"PPL",
    "gn:name":"Mamihara",
    "gn:population":0,
    "gn:timezone":"Asia/Tokyo",
    "iso:country":"JP",
    "name:jpn_x_preferred":[
        "\u99ac\u898b\u539f"
    ],
    "name:jpn_x_variant":[
        "\u307e\u307f\u306f\u3089",
        "\u30de\u30df\u30cf\u30e9"
    ],
    "wof:name":"Mamihara",
    "wof:placetype":"locality"
},
  "geometry": {"coordinates":[131.15441999999999,32.68141],"type":"Point"}
}