{
  "type": "Feature",
  "properties": {
    "gn:admin1_code":"12.0",
    "gn:admin2_code":"2127513.0",
    "gn:asciiname":"Tomarikese",
    "gn:country_code":"JP",
    "gn:dem":56,
    "gn:feature_class":"P",
    "gn:feature_code":"PPLL",
    "gn:name":"Tomarikese",
    "gn:population":0,
    "gn:timezone":"Asia/Tokyo",
    "iso:country":"JP",
    "name:und_x_variant":[
        "Tomarikishi",
        "Tomarikese"
    ],
    "wof:name":"Tomarikese",
    "wof:placetype":"locality"
},
  "geometry": {"coordinates":[141.89490000000001,45.50106],"type":"Point"}
}