{
  "type": "Feature",
  "properties": {
    "gn:admin1_code":"47",
    "gn:admin2_code":"1849184.0",
    "gn:asciiname":"Minatogawa",
    "gn:country_code":"JP",
    "gn:dem":36,
    "gn:feature_class":"P",
    "gn:feature_code":"PPL",
    "gn:name":"Minatogawa",
    "gn:population":0,
    "gn:timezone":"Asia/Tokyo",
    "iso:country":"JP",
    "name:jpn_x_preferred":[
        "\u6e2f\u5ddd"
    ],
    "name:jpn_x_variant":[
        "\u307f\u306a\u3068\u304c\u308f"
    ],
    "wof:name":"Minatogawa",
    "wof:placetype":"locality"
},
  "geometry": {"coordinates":[127.71868000000001,26.26026],"type":"Point"}
}