{
  "type": "Feature",
  "properties": {
    "gn:admin1_code":"12.0",
    "gn:admin2_code":"7428090.0",
    "gn:admin3_code":"1664.0",
    "gn:asciiname":"Kosei",
    "gn:country_code":"JP",
    "gn:dem":55,
    "gn:feature_class":"P",
    "gn:feature_code":"PPL",
    "gn:name":"K\u014dsei",
    "gn:population":0,
    "gn:timezone":"Asia/Tokyo",
    "iso:country":"JP",
    "name:jpn_x_preferred":[
        "\u539a\u751f"
    ],
    "name:jpn_x_variant":[
        "\u3053\u3046\u305b\u3044",
        "\u30b3\u30a6\u30bb\u30a4"
    ],
    "name:und_x_variant":[
        "K\u014dsei"
    ],
    "wof:name":"Kosei",
    "wof:placetype":"locality"
},
  "geometry": {"coordinates":[144.55136999999999,43.29962],"type":"Point"}
}