{
  "type": "Feature",
  "properties": {
    "gn:admin1_code":"19.0",
    "gn:admin2_code":"1860670.0",
    "gn:asciiname":"Kobukuroya",
    "gn:country_code":"JP",
    "gn:dem":15,
    "gn:feature_class":"P",
    "gn:feature_code":"PPL",
    "gn:name":"Kobukuroya",
    "gn:population":0,
    "gn:timezone":"Asia/Tokyo",
    "iso:country":"JP",
    "name:jpn_x_preferred":[
        "\u5c0f\u888b\u8c37"
    ],
    "name:jpn_x_variant":[
        "\u3053\u3076\u304f\u308d\u3084",
        "\u30b3\u30d6\u30af\u30ed\u30e4"
    ],
    "wof:name":"Kobukuroya",
    "wof:placetype":"locality"
},
  "geometry": {"coordinates":[139.53465,35.34543],"type":"Point"}
}