{
  "type": "Feature",
  "properties": {
    "gn:admin1_code":"4.0",
    "gn:admin2_code":"1863711.0",
    "gn:asciiname":"Tabara",
    "gn:country_code":"JP",
    "gn:dem":30,
    "gn:feature_class":"P",
    "gn:feature_code":"PPL",
    "gn:name":"Tabara",
    "gn:population":0,
    "gn:timezone":"Asia/Tokyo",
    "iso:country":"JP",
    "name:jpn_x_preferred":[
        "\u7530\u539f"
    ],
    "name:jpn_x_variant":[
        "\u305f\u3070\u3089",
        "\u30bf\u30d0\u30e9"
    ],
    "wof:name":"Tabara",
    "wof:placetype":"locality"
},
  "geometry": {"coordinates":[139.91561000000002,35.2089],"type":"Point"}
}