{
  "type": "Feature",
  "properties": {
    "gn:admin1_code":"37.0",
    "gn:admin2_code":"1859485.0",
    "gn:asciiname":"Takahashi",
    "gn:country_code":"JP",
    "gn:dem":88,
    "gn:feature_class":"P",
    "gn:feature_code":"PPL",
    "gn:name":"Takahashi",
    "gn:population":0,
    "gn:timezone":"Asia/Tokyo",
    "iso:country":"JP",
    "name:jpn_x_preferred":[
        "\u9ad8\u6a4b"
    ],
    "name:lav_x_preferred":[
        "Takaha\u0161i"
    ],
    "name:mlg_x_preferred":[
        "Takahashi"
    ],
    "name:rus_x_preferred":[
        "\u0422\u0430\u043a\u0430\u0445\u0430\u0441\u0438"
    ],
    "name:vie_x_preferred":[
        "Takahashi"
    ],
    "wof:name":"Takahashi",
    "wof:placetype":"locality"
},
  "geometry": {"coordinates":[138.13279,34.70152],"type":"Point"}
}