{
  "type": "Feature",
  "properties": {
    "gn:admin1_code":"4.0",
    "gn:admin2_code":"2112997.0",
    "gn:admin3_code":"12427.0",
    "gn:asciiname":"Motojuku",
    "gn:country_code":"JP",
    "gn:dem":39,
    "gn:feature_class":"P",
    "gn:feature_code":"PPLL",
    "gn:name":"Motojuku",
    "gn:population":0,
    "gn:timezone":"Asia/Tokyo",
    "iso:country":"JP",
    "name:jpn_x_preferred":[
        "\u5143\u5bbf"
    ],
    "name:jpn_x_variant":[
        "\u3082\u3068\u3058\u3085\u304f",
        "\u30e2\u30c8\u30b8\u30e5\u30af"
    ],
    "wof:name":"Motojuku",
    "wof:placetype":"locality"
},
  "geometry": {"coordinates":[140.23653000000002,35.40233],"type":"Point"}
}