{
  "type": "Feature",
  "properties": {
    "gn:admin1_code":"19.0",
    "gn:admin2_code":"1864928.0",
    "gn:asciiname":"Hataya",
    "gn:country_code":"JP",
    "gn:dem":67,
    "gn:feature_class":"P",
    "gn:feature_code":"PPLL",
    "gn:name":"Hataya",
    "gn:population":0,
    "gn:timezone":"Asia/Tokyo",
    "iso:country":"JP",
    "name:jpn_x_preferred":[
        "\u65d7\u8c37"
    ],
    "wof:name":"Hataya",
    "wof:placetype":"locality"
},
  "geometry": {"coordinates":[139.32453999999998,35.45745],"type":"Point"}
}