{
  "type": "Feature",
  "properties": {
    "gn:admin1_code":"33.0",
    "gn:admin2_code":"7391355.0",
    "gn:asciiname":"Sodeotoshi",
    "gn:country_code":"JP",
    "gn:dem":26,
    "gn:feature_class":"P",
    "gn:feature_code":"PPLL",
    "gn:name":"Sodeotoshi",
    "gn:population":0,
    "gn:timezone":"Asia/Tokyo",
    "iso:country":"JP",
    "name:jpn_x_preferred":[
        "\u8896\u843d"
    ],
    "wof:name":"Sodeotoshi",
    "wof:placetype":"locality"
},
  "geometry": {"coordinates":[129.87575000000001,33.33465],"type":"Point"}
}