{
  "type": "Feature",
  "properties": {
    "gn:admin1_code":"12.0",
    "gn:admin2_code":"7428084.0",
    "gn:admin3_code":"1609.0",
    "gn:asciiname":"Utaroppu",
    "gn:country_code":"JP",
    "gn:dem":37,
    "gn:feature_class":"P",
    "gn:feature_code":"PPL",
    "gn:name":"Utaroppu",
    "gn:population":0,
    "gn:timezone":"Asia/Tokyo",
    "iso:country":"JP",
    "name:jpn_x_preferred":[
        "\u6b4c\u9732"
    ],
    "name:jpn_x_variant":[
        "\u3046\u305f\u308d\u3063\u3077",
        "\u30a6\u30bf\u30ed\u30c3\u30d7"
    ],
    "name:und_x_variant":[
        "Utaro",
        "Utaroppu"
    ],
    "wof:name":"Utaroppu",
    "wof:placetype":"locality"
},
  "geometry": {"coordinates":[143.19343000000001,41.96556],"type":"Point"}
}