{
  "type": "Feature",
  "properties": {
    "gn:admin1_code":"19.0",
    "gn:admin2_code":"1848350.0",
    "gn:admin3_code":"14106.0",
    "gn:asciiname":"Sakaigi-honcho",
    "gn:country_code":"JP",
    "gn:dem":67,
    "gn:feature_class":"P",
    "gn:feature_code":"PPL",
    "gn:name":"Sakaigi-honch\u014d",
    "gn:population":0,
    "gn:timezone":"Asia/Tokyo",
    "iso:country":"JP",
    "name:jpn_x_preferred":[
        "\u5883\u6728\u672c\u753a"
    ],
    "name:jpn_x_variant":[
        "\u3055\u304b\u3044\u304e\u307b\u3093\u3061\u3087\u3046",
        "\u30b5\u30ab\u30a4\u30ae\u30db\u30f3\u30c1\u30e7\u30a6"
    ],
    "name:und_x_variant":[
        "Sakaigi-honch\u014d"
    ],
    "wof:name":"Sakaigi-honcho",
    "wof:placetype":"locality"
},
  "geometry": {"coordinates":[139.56484,35.43849],"type":"Point"}
}