{
  "type": "Feature",
  "properties": {
    "gn:admin1_code":"7.0",
    "gn:admin2_code":"1861834.0",
    "gn:asciiname":"Komodanishi",
    "gn:country_code":"JP",
    "gn:dem":17,
    "gn:feature_class":"P",
    "gn:feature_code":"PPL",
    "gn:name":"Komodanishi",
    "gn:population":0,
    "gn:timezone":"Asia/Tokyo",
    "iso:country":"JP",
    "name:jpn_x_preferred":[
        "\u83f0\u7530\u897f"
    ],
    "wof:name":"Komodanishi",
    "wof:placetype":"locality"
},
  "geometry": {"coordinates":[130.68716000000001,33.62927],"type":"Point"}
}