{
  "type": "Feature",
  "properties": {
    "gn:admin1_code":"21.0",
    "gn:admin2_code":"7412709.0",
    "gn:admin3_code":"43348.0",
    "gn:asciiname":"Horaoka",
    "gn:country_code":"JP",
    "gn:dem":330,
    "gn:feature_class":"P",
    "gn:feature_code":"PPL",
    "gn:name":"Horaoka",
    "gn:population":0,
    "gn:timezone":"Asia/Tokyo",
    "iso:country":"JP",
    "name:jpn_x_preferred":[
        "\u6d1e\u5cb3"
    ],
    "name:jpn_x_variant":[
        "\u307b\u3089\u304a\u304b",
        "\u30db\u30e9\u30aa\u30ab"
    ],
    "wof:name":"Horaoka",
    "wof:placetype":"locality"
},
  "geometry": {"coordinates":[130.94072,32.62852],"type":"Point"}
}