{
  "type": "Feature",
  "properties": {
    "gn:admin1_code":"32.0",
    "gn:admin2_code":"1862032.0",
    "gn:asciiname":"Nakamuracho",
    "gn:country_code":"JP",
    "gn:dem":9,
    "gn:feature_class":"P",
    "gn:feature_code":"PPL",
    "gn:name":"Nakamurach\u014d",
    "gn:population":0,
    "gn:timezone":"Asia/Tokyo",
    "iso:country":"JP",
    "name:jpn_x_preferred":[
        "\u4e2d\u6751\u753a"
    ],
    "name:und_x_variant":[
        "Nakamurach\u014d"
    ],
    "wof:name":"Nakamuracho",
    "wof:placetype":"locality"
},
  "geometry": {"coordinates":[135.58399,34.81905],"type":"Point"}
}