{
  "type": "Feature",
  "properties": {
    "iso:country":"JP",
    "name:eng_x_preferred":[
        "Higashimachi 4 Chome"
    ],
    "name:eng_x_variant":[
        "Higashimachi 4 Choume",
        "Higashimachi 4 Chome"
    ],
    "name:jpn_x_preferred":[
        "\uff14\u4e01\u76ee"
    ],
    "name:jpn_x_variant":[
        "\u3072\u304c\u3057\u307e\u3061 \uff14\u3061\u3087\u3046\u3081",
        "\u6771\u753a \uff14\u4e01\u76ee",
        "\uff14\u3061\u3087\u3046\u3081"
    ],
    "name:unk_x_variant":[
        "\uff14\u4e01\u76ee"
    ],
    "qs:gn_local":0,
    "qs:local_max":311,
    "qs:local_sum":1154,
    "qs:localhoods":8,
    "qs:name":"\uff14\u4e01\u76ee",
    "qs:name_adm0":"\u65e5\u672c",
    "qs:name_adm1":"\u5317\u6d77\u9053",
    "qs:name_adm2":"\u4e0a\u5ddd\u90e1",
    "qs:name_en":"Higashimachi 4 Chome",
    "qs:name_lau":"\u6771\u753a",
    "qs:name_local":"\u7f8e\u745b\u753a",
    "qs:photo_max":1,
    "qs:photo_sum":1,
    "qs:placetype":"Suburb",
    "qs:quad_count":1,
    "qs:woe_adm0":23424856,
    "qs:woe_adm1":7153351,
    "qs:woe_adm2":24853906,
    "qs:woe_lau":28384332,
    "qs:woe_local":1117024,
    "qs:woe_ver":"7.10.0",
    "wof:lang":[
        "jpn"
    ],
    "wof:name":"\uff14\u4e01\u76ee",
    "wof:placetype":"neighbourhood"
},
  "geometry": {"coordinates":[142.48992899999999,43.594318],"type":"Point"}
}