{
  "type": "Feature",
  "properties": {
    "gn:admin1_code":"8.0",
    "gn:admin2_code":"1857203.0",
    "gn:admin3_code":"7362.0",
    "gn:asciiname":"Nakayama",
    "gn:country_code":"JP",
    "gn:dem":672,
    "gn:feature_class":"P",
    "gn:feature_code":"PPL",
    "gn:name":"Nakayama",
    "gn:population":0,
    "gn:timezone":"Asia/Tokyo",
    "iso:country":"JP",
    "name:deu_x_preferred":[
        "Nakayama"
    ],
    "name:fra_x_preferred":[
        "Nakayama"
    ],
    "name:jpn_x_preferred":[
        "\u4e2d\u5c71"
    ],
    "name:kor_x_preferred":[
        "\ub098\uce74\uc57c\ub9c8"
    ],
    "name:rus_x_preferred":[
        "\u041d\u0430\u043a\u0430\u044f\u043c\u0430"
    ],
    "name:ukr_x_preferred":[
        "\u041d\u0430\u043a\u0430\u044f\u043c\u0430"
    ],
    "wof:name":"Nakayama",
    "wof:placetype":"locality"
},
  "geometry": {"coordinates":[139.84391000000002,37.29409],"type":"Point"}
}