{
  "type": "Feature",
  "properties": {
    "gn:admin1_code":"27.0",
    "gn:admin2_code":"7418808.0",
    "gn:asciiname":"Sakitocho-kakinourago",
    "gn:country_code":"JP",
    "gn:dem":4,
    "gn:feature_class":"P",
    "gn:feature_code":"PPL",
    "gn:name":"Sakitoch\u014d-kakinourag\u014d",
    "gn:population":0,
    "gn:timezone":"Asia/Tokyo",
    "iso:country":"JP",
    "name:jpn_x_preferred":[
        "\u5d0e\u6238\u753a\u8823\u6d66\u90f7"
    ],
    "name:und_x_variant":[
        "Sakitoch\u014d-kakinourag\u014d"
    ],
    "wof:name":"Sakitocho-kakinourago",
    "wof:placetype":"locality"
},
  "geometry": {"coordinates":[129.56949,33.02437],"type":"Point"}
}