{
  "type": "Feature",
  "properties": {
    "iso:country":"JP",
    "name:eng_x_preferred":[
        "Aoyama 5 Chome"
    ],
    "name:eng_x_variant":[
        "Aoyama 5 Choume",
        "Aoyama 5 Chome"
    ],
    "name:jpn_x_preferred":[
        "\uff15\u4e01\u76ee"
    ],
    "name:jpn_x_variant":[
        "\u3042\u304a\u3084\u307e \uff15\u3061\u3087\u3046\u3081",
        "\u9752\u5c71 \uff15\u4e01\u76ee",
        "\uff15\u3061\u3087\u3046\u3081"
    ],
    "name:unk_x_variant":[
        "\uff15\u4e01\u76ee"
    ],
    "qs:gn_local":0,
    "qs:local_max":12821,
    "qs:local_sum":32218,
    "qs:localhoods":19,
    "qs:name":"\uff15\u4e01\u76ee",
    "qs:name_adm0":"\u65e5\u672c",
    "qs:name_adm1":"\u5948\u826f\u770c",
    "qs:name_en":"Aoyama 5 Chome",
    "qs:name_lau":"\u9752\u5c71",
    "qs:name_local":"\u5948\u826f\u5e02",
    "qs:photo_max":172,
    "qs:photo_sum":332,
    "qs:placetype":"Suburb",
    "qs:quad_count":8,
    "qs:woe_adm0":23424856,
    "qs:woe_adm1":2345877,
    "qs:woe_adm2":0,
    "qs:woe_lau":28466003,
    "qs:woe_local":1117858,
    "qs:woe_ver":"7.10.0",
    "wof:lang":[
        "jpn"
    ],
    "wof:name":"\uff15\u4e01\u76ee",
    "wof:placetype":"neighbourhood"
},
  "geometry": {"coordinates":[135.83597599999999,34.699259],"type":"Point"}
}