{
  "type": "Feature",
  "properties": {
    "iso:country":"JP",
    "label:eng_x_preferred_longname":[
        "Kozagawa Town"
    ],
    "label:eng_x_preferred_placetype":[
        "town"
    ],
    "name:eng_x_preferred":[
        "Kozagawa"
    ],
    "name:eng_x_variant":[
        "Kozagawa Town"
    ],
    "name:jpn_x_preferred":[
        "\u53e4\u5ea7\u5ddd\u753a"
    ],
    "qs:name":"\u53e4\u5ea7\u5ddd\u753a",
    "qs:name_adm0":"\u65e5\u672c",
    "qs:name_adm1":"\u548c\u6b4c\u5c71\u770c",
    "qs:photos":21,
    "qs:photos_1k":4,
    "qs:photos_9k":1,
    "qs:photos_9r":1,
    "qs:photos_all":21,
    "qs:photos_sr":1,
    "qs:placetype":"Town",
    "qs:pop_sr":"0",
    "wof:name":"Kozagawa",
    "wof:placetype":"locality"
},
  "geometry": {"coordinates":[135.77484000000001,33.537851],"type":"Point"}
}