{
  "type": "Feature",
  "properties": {
    "gn:admin1_code":"19.0",
    "gn:admin2_code":"1848350.0",
    "gn:admin3_code":"14104.0",
    "gn:asciiname":"Chojamachi",
    "gn:country_code":"JP",
    "gn:dem":11,
    "gn:feature_class":"P",
    "gn:feature_code":"PPL",
    "gn:name":"Ch\u014djamachi",
    "gn:population":0,
    "gn:timezone":"Asia/Tokyo",
    "iso:country":"JP",
    "name:jpn_x_preferred":[
        "\u9577\u8005\u753a"
    ],
    "name:jpn_x_variant":[
        "\u3061\u3087\u3046\u3058\u3083\u307e\u3061",
        "\u30c1\u30e7\u30a6\u30b8\u30e3\u30de\u30c1"
    ],
    "name:und_x_variant":[
        "Ch\u014djamachi"
    ],
    "wof:name":"Chojamachi",
    "wof:placetype":"locality"
},
  "geometry": {"coordinates":[139.63103999999998,35.44219000000001],"type":"Point"}
}