{
  "type": "Feature",
  "properties": {
    "gn:admin1_code":"21.0",
    "gn:admin2_code":"1865358.0",
    "gn:asciiname":"Ikenokubo",
    "gn:country_code":"JP",
    "gn:dem":102,
    "gn:feature_class":"P",
    "gn:feature_code":"PPLL",
    "gn:name":"Ikenokubo",
    "gn:population":0,
    "gn:timezone":"Asia/Tokyo",
    "iso:country":"JP",
    "name:jpn_x_preferred":[
        "\u6c60\u306e\u4e45\u4fdd"
    ],
    "name:jpn_x_variant":[
        "\u3044\u3051\u306e\u304f\u307c",
        "\u30a4\u30b1\u30ce\u30af\u30dc"
    ],
    "wof:name":"Ikenokubo",
    "wof:placetype":"locality"
},
  "geometry": {"coordinates":[130.22208000000001,32.44443],"type":"Point"}
}