{
  "type": "Feature",
  "properties": {
    "gn:admin1_code":"47",
    "gn:admin2_code":"1858371.0",
    "gn:admin3_code":"47308.0",
    "gn:asciiname":"Zakaja",
    "gn:country_code":"JP",
    "gn:dem":139,
    "gn:feature_class":"P",
    "gn:feature_code":"PPL",
    "gn:name":"Zakaja",
    "gn:population":0,
    "gn:timezone":"Asia/Tokyo",
    "iso:country":"JP",
    "name:jpn_x_preferred":[
        "\u5c4b\u540d\u5ea7"
    ],
    "name:jpn_x_variant":[
        "\u3056\u304b\u3058\u3083"
    ],
    "name:und_x_variant":[
        "Yanata",
        "Yanaza",
        "Zakaja"
    ],
    "wof:name":"Zakaja",
    "wof:placetype":"locality"
},
  "geometry": {"coordinates":[127.92917,26.65056],"type":"Point"}
}