{
  "type": "Feature",
  "properties": {
    "gn:admin1_code":"22.0",
    "gn:admin2_code":"1851574.0",
    "gn:admin3_code":"26365.0",
    "gn:asciiname":"Somada",
    "gn:country_code":"JP",
    "gn:dem":145,
    "gn:feature_class":"P",
    "gn:feature_code":"PPL",
    "gn:name":"Somada",
    "gn:population":0,
    "gn:timezone":"Asia/Tokyo",
    "iso:country":"JP",
    "name:jpn_x_preferred":[
        "\u6763\u7530"
    ],
    "wof:name":"Somada",
    "wof:placetype":"locality"
},
  "geometry": {"coordinates":[135.90461000000002,34.78973],"type":"Point"}
}