{
  "type": "Feature",
  "properties": {
    "gn:admin1_code":"36",
    "gn:admin2_code":"1854750.0",
    "gn:asciiname":"Yamaguchicho-satsume",
    "gn:country_code":"JP",
    "gn:dem":305,
    "gn:feature_class":"P",
    "gn:feature_code":"PPL",
    "gn:name":"Yamaguchich\u014d-satsume",
    "gn:population":0,
    "gn:timezone":"Asia/Tokyo",
    "iso:country":"JP",
    "name:jpn_x_preferred":[
        "\u5c71\u53e3\u753a\u4f50\u6d25\u76ee"
    ],
    "name:und_x_variant":[
        "Yamaguchich\u014d-satsume",
        "Kami-satsume"
    ],
    "wof:name":"Yamaguchicho-satsume",
    "wof:placetype":"locality"
},
  "geometry": {"coordinates":[132.65013000000002,35.2026],"type":"Point"}
}