{
  "type": "Feature",
  "properties": {
    "gn:admin1_code":"4.0",
    "gn:admin2_code":"8304237.0",
    "gn:asciiname":"Gota",
    "gn:country_code":"JP",
    "gn:dem":72,
    "gn:feature_class":"P",
    "gn:feature_code":"PPLL",
    "gn:name":"Gota",
    "gn:population":0,
    "gn:timezone":"Asia/Tokyo",
    "iso:country":"JP",
    "name:cat_x_preferred":[
        "Gota"
    ],
    "name:ceb_x_preferred":[
        "Gota"
    ],
    "name:deu_x_preferred":[
        "Gota"
    ],
    "name:fin_x_preferred":[
        "G\u00f6ta"
    ],
    "name:fra_x_preferred":[
        "G\u00f6ta"
    ],
    "name:glg_x_preferred":[
        "Gota"
    ],
    "name:ita_x_preferred":[
        "Gota"
    ],
    "name:jpn_x_preferred":[
        "\u4e94\u7530"
    ],
    "name:jpn_x_variant":[
        "\u3054\u305f",
        "\u30b4\u30bf"
    ],
    "name:por_x_preferred":[
        "Gota"
    ],
    "name:spa_x_preferred":[
        "Gota"
    ],
    "name:swe_x_preferred":[
        "Gota"
    ],
    "wof:name":"Gota",
    "wof:placetype":"locality"
},
  "geometry": {"coordinates":[140.02798000000001,35.3376],"type":"Point"}
}