{
  "type": "Feature",
  "properties": {
    "gn:admin1_code":"8.0",
    "gn:admin2_code":"1857203.0",
    "gn:admin3_code":"7362.0",
    "gn:asciiname":"Toyonari",
    "gn:country_code":"JP",
    "gn:dem":495,
    "gn:feature_class":"P",
    "gn:feature_code":"PPL",
    "gn:name":"Toyonari",
    "gn:population":0,
    "gn:timezone":"Asia/Tokyo",
    "iso:country":"JP",
    "name:jpn_x_preferred":[
        "\u8c4a\u6210"
    ],
    "wof:name":"Toyonari",
    "wof:placetype":"locality"
},
  "geometry": {"coordinates":[139.84483,37.24104000000001],"type":"Point"}
}