{
  "type": "Feature",
  "properties": {
    "gn:admin1_code":"40.0",
    "gn:admin2_code":"1852675.0",
    "gn:asciiname":"Higashitamagawa",
    "gn:country_code":"JP",
    "gn:dem":30,
    "gn:feature_class":"P",
    "gn:feature_code":"PPL",
    "gn:name":"Higashitamagawa",
    "gn:population":0,
    "gn:timezone":"Asia/Tokyo",
    "iso:country":"JP",
    "name:jpn_x_preferred":[
        "\u6771\u7389\u5ddd"
    ],
    "wof:name":"Higashitamagawa",
    "wof:placetype":"locality"
},
  "geometry": {"coordinates":[139.67626999999999,35.59672],"type":"Point"}
}