{
  "type": "Feature",
  "properties": {
    "gn:admin1_code":"27.0",
    "gn:admin2_code":"7418810.0",
    "gn:asciiname":"Kamiagatacho-kubara",
    "gn:country_code":"JP",
    "gn:dem":10,
    "gn:feature_class":"P",
    "gn:feature_code":"PPL",
    "gn:name":"Kamiagatach\u014d-kubara",
    "gn:population":0,
    "gn:timezone":"Asia/Tokyo",
    "iso:country":"JP",
    "name:jpn_x_preferred":[
        "\u4e0a\u770c\u753a\u4e45\u539f"
    ],
    "name:und_x_variant":[
        "Kamiagatach\u014d-kubara"
    ],
    "wof:name":"Kamiagatacho-kubara",
    "wof:placetype":"locality"
},
  "geometry": {"coordinates":[129.31065000000001,34.51305],"type":"Point"}
}