{
  "type": "Feature",
  "properties": {
    "gn:admin1_code":"3.0",
    "gn:admin2_code":"2130225.0",
    "gn:asciiname":"Itabashi",
    "gn:country_code":"JP",
    "gn:dem":13,
    "gn:feature_class":"P",
    "gn:feature_code":"PPL",
    "gn:name":"Itabashi",
    "gn:population":0,
    "gn:timezone":"Asia/Tokyo",
    "iso:country":"JP",
    "name:jpn_x_preferred":[
        "\u677f\u6a4b"
    ],
    "name:jpn_x_variant":[
        "\u3044\u305f\u3070\u3057",
        "\u30a4\u30bf\u30d0\u30b7"
    ],
    "wof:name":"Itabashi",
    "wof:placetype":"locality"
},
  "geometry": {"coordinates":[140.42971,40.81629],"type":"Point"}
}