{
  "type": "Feature",
  "properties": {
    "gn:admin1_code":"11.0",
    "gn:admin2_code":"1849812.0",
    "gn:admin3_code":"34431.0",
    "gn:asciiname":"Akashi",
    "gn:country_code":"JP",
    "gn:dem":9,
    "gn:feature_class":"P",
    "gn:feature_code":"PPL",
    "gn:name":"Akashi",
    "gn:population":0,
    "gn:timezone":"Asia/Tokyo",
    "iso:country":"JP",
    "name:ceb_x_preferred":[
        "Akashi"
    ],
    "name:deu_x_preferred":[
        "Akashi"
    ],
    "name:fra_x_preferred":[
        "Akashi"
    ],
    "name:jpn_x_preferred":[
        "\u660e\u77f3"
    ],
    "name:mlg_x_preferred":[
        "Akashi"
    ],
    "name:ron_x_preferred":[
        "Akashi"
    ],
    "name:rus_x_preferred":[
        "\u0410\u043a\u0430\u0441\u0438"
    ],
    "name:sah_x_preferred":[
        "\u0410\u043a\u0430\u0441\u0438"
    ],
    "name:spa_x_preferred":[
        "Akashi"
    ],
    "name:ukr_x_preferred":[
        "\u0410\u043a\u0430\u0441\u0456"
    ],
    "wof:name":"Akashi",
    "wof:placetype":"locality"
},
  "geometry": {"coordinates":[132.87833000000001,34.20833],"type":"Point"}
}