{
  "type": "Feature",
  "properties": {
    "gn:admin1_code":"2.0",
    "gn:admin2_code":"2113122.0",
    "gn:asciiname":"Terauchi-kamiyashiki",
    "gn:country_code":"JP",
    "gn:dem":34,
    "gn:feature_class":"P",
    "gn:feature_code":"PPL",
    "gn:name":"Terauchi-kamiyashiki",
    "gn:population":0,
    "gn:timezone":"Asia/Tokyo",
    "iso:country":"JP",
    "name:jpn_x_preferred":[
        "\u5bfa\u5185\u795e\u5c4b\u6577"
    ],
    "name:jpn_x_variant":[
        "\u3066\u3089\u3046\u3061\u304b\u307f\u3084\u3057\u304d",
        "\u30c6\u30e9\u30a6\u30c1\u30ab\u30df\u30e4\u30b7\u30ad",
        "\u795e\u5c4b\u6577"
    ],
    "name:und_x_variant":[
        "Kamiyashiki"
    ],
    "wof:name":"Terauchi-kamiyashiki",
    "wof:placetype":"locality"
},
  "geometry": {"coordinates":[140.08095,39.73364],"type":"Point"}
}