{
  "type": "Feature",
  "properties": {
    "gn:admin1_code":"12.0",
    "gn:admin2_code":"2128405.0",
    "gn:admin3_code":"1518.0",
    "gn:asciiname":"Shimminato",
    "gn:country_code":"JP",
    "gn:dem":9,
    "gn:feature_class":"P",
    "gn:feature_code":"PPLL",
    "gn:name":"Shimminato",
    "gn:population":0,
    "gn:timezone":"Asia/Tokyo",
    "iso:country":"JP",
    "name:jpn_x_preferred":[
        "\u65b0\u6e4a"
    ],
    "name:jpn_x_variant":[
        "\u3057\u3093\u307f\u306a\u3068",
        "\u30b7\u30f3\u30df\u30ca\u30c8"
    ],
    "wof:name":"Shimminato",
    "wof:placetype":"locality"
},
  "geometry": {"coordinates":[141.13786000000005,45.21016],"type":"Point"}
}