{
  "type": "Feature",
  "properties": {
    "gn:admin1_code":"13.0",
    "gn:admin2_code":"7370811.0",
    "gn:asciiname":"Yokawacho-okudani",
    "gn:country_code":"JP",
    "gn:dem":179,
    "gn:feature_class":"P",
    "gn:feature_code":"PPL",
    "gn:name":"Yokawach\u014d-okudani",
    "gn:population":0,
    "gn:timezone":"Asia/Tokyo",
    "iso:country":"JP",
    "name:jbn_x_preferred":[
        "Yokawach\u014d-okudani"
    ],
    "name:jpn_x_preferred":[
        "\u5409\u5ddd\u753a\u5965\u8c37"
    ],
    "wof:name":"Yokawacho-okudani",
    "wof:placetype":"locality"
},
  "geometry": {"coordinates":[135.12056999999999,34.85332],"type":"Point"}
}