{
  "type": "Feature",
  "properties": {
    "gn:admin1_code":"2.0",
    "gn:admin2_code":"2113122.0",
    "gn:asciiname":"Asahikawa-shintoda-higashimachi",
    "gn:country_code":"JP",
    "gn:dem":13,
    "gn:feature_class":"P",
    "gn:feature_code":"PPL",
    "gn:name":"Asahikawa-shint\u014dda-higashimachi",
    "gn:population":0,
    "gn:timezone":"Asia/Tokyo",
    "iso:country":"JP",
    "name:jpn_x_preferred":[
        "\u65ed\u5ddd\u65b0\u85e4\u7530\u6771\u753a"
    ],
    "name:jpn_x_variant":[
        "\u3042\u3055\u3072\u304b\u308f\u3057\u3093\u3068\u3046\u3060\u3072\u304c\u3057\u307e\u3061",
        "\u30a2\u30b5\u30d2\u30ab\u30ef\u30b7\u30f3\u30c8\u30a6\u30c0\u30d2\u30ac\u30b7\u30de\u30c1"
    ],
    "name:und_x_variant":[
        "Asahikawa-shint\u014dda-higashimachi"
    ],
    "wof:name":"Asahikawa-shintoda-higashimachi",
    "wof:placetype":"locality"
},
  "geometry": {"coordinates":[140.12861999999998,39.74093],"type":"Point"}
}