{
  "type": "Feature",
  "properties": {
    "gn:admin1_code":"23.0",
    "gn:admin2_code":"1849544.0",
    "gn:asciiname":"Motokonishi",
    "gn:country_code":"JP",
    "gn:dem":161,
    "gn:feature_class":"P",
    "gn:feature_code":"PPLL",
    "gn:name":"Motokonishi",
    "gn:population":0,
    "gn:timezone":"Asia/Tokyo",
    "iso:country":"JP",
    "name:jpn_x_preferred":[
        "\u5143\u5c0f\u897f"
    ],
    "wof:name":"Motokonishi",
    "wof:placetype":"locality"
},
  "geometry": {"coordinates":[136.27438999999998,34.56643],"type":"Point"}
}