{
  "type": "Feature",
  "properties": {
    "iso:country":"JP",
    "qs:name":"\u9ce9\u30f6\u8c37\u5e02",
    "qs:name_adm0":"\u65e5\u672c",
    "qs:name_adm1":"\u57fc\u7389\u770c",
    "qs:photos":438,
    "qs:photos_1k":89,
    "qs:photos_9k":4,
    "qs:photos_9r":6,
    "qs:photos_all":844,
    "qs:photos_sr":6,
    "qs:placetype":"Town",
    "qs:pop_sr":"0",
    "wof:name":"\u9ce9\u30f6\u8c37\u5e02",
    "wof:placetype":"locality"
},
  "geometry": {"coordinates":[139.72878149999997,35.8243345],"type":"Point"}
}