{
  "type": "Feature",
  "properties": {
    "gn:admin1_code":"4.0",
    "gn:admin2_code":"2112386.0",
    "gn:asciiname":"Sakaori",
    "gn:country_code":"JP",
    "gn:dem":17,
    "gn:feature_class":"P",
    "gn:feature_code":"PPLL",
    "gn:name":"Sakaori",
    "gn:population":0,
    "gn:timezone":"Asia/Tokyo",
    "iso:country":"JP",
    "name:jpn_x_preferred":[
        "\u5742\u4e0b"
    ],
    "name:jpn_x_variant":[
        "\u3055\u304b\u304a\u308a",
        "\u30b5\u30ab\u30aa\u30ea"
    ],
    "wof:name":"Sakaori",
    "wof:placetype":"locality"
},
  "geometry": {"coordinates":[140.13521,35.12214],"type":"Point"}
}