{
  "type": "Feature",
  "properties": {
    "gn:admin1_code":"3.0",
    "gn:admin2_code":"2130200.0",
    "gn:asciiname":"Choja-kubo",
    "gn:country_code":"JP",
    "gn:dem":53,
    "gn:feature_class":"P",
    "gn:feature_code":"PPL",
    "gn:name":"Ch\u014dja-kubo",
    "gn:population":0,
    "gn:timezone":"Asia/Tokyo",
    "iso:country":"JP",
    "name:jpn_x_preferred":[
        "\u9577\u8005\u4e45\u4fdd"
    ],
    "name:jpn_x_variant":[
        "\u3061\u3087\u3046\u3058\u3083\u304f\u307c",
        "\u30c1\u30e7\u30a6\u30b8\u30e3\u30af\u30dc"
    ],
    "name:und_x_variant":[
        "Ch\u014dja-kubo"
    ],
    "wof:name":"Choja-kubo",
    "wof:placetype":"locality"
},
  "geometry": {"coordinates":[141.44388000000001,40.5515],"type":"Point"}
}