{
  "type": "Feature",
  "properties": {
    "gn:admin1_code":"12.0",
    "gn:asciiname":"Morikoshi",
    "gn:country_code":"JP",
    "gn:dem":10,
    "gn:feature_class":"P",
    "gn:feature_code":"PPL",
    "gn:name":"Morikoshi",
    "gn:population":0,
    "gn:timezone":"Asia/Tokyo",
    "iso:country":"JP",
    "name:jpn_x_preferred":[
        "\u68ee\u8d8a"
    ],
    "name:jpn_x_variant":[
        "\u3082\u308a\u3053\u3057",
        "\u30e2\u30ea\u30b3\u30b7"
    ],
    "wof:name":"Morikoshi",
    "wof:placetype":"locality"
},
  "geometry": {"coordinates":[140.41871,41.62948],"type":"Point"}
}