{
  "type": "Feature",
  "properties": {
    "iso:country":"JP",
    "name:eng_x_preferred":[
        "Nagaminedai 2 Chome"
    ],
    "name:eng_x_variant":[
        "Nagaminedai 2 Choume",
        "Nagaminedai 2 Chome"
    ],
    "name:jpn_x_preferred":[
        "\uff12\u4e01\u76ee"
    ],
    "name:jpn_x_variant":[
        "\u306a\u304c\u307f\u306d\u3060\u3044 \uff12\u3061\u3087\u3046\u3081",
        "\u9577\u5cf0\u53f0 \uff12\u4e01\u76ee",
        "\uff12\u3061\u3087\u3046\u3081"
    ],
    "qs:gn_local":0,
    "qs:local_max":2400,
    "qs:local_sum":22318,
    "qs:localhoods":72,
    "qs:name":"\uff12\u4e01\u76ee",
    "qs:name_adm0":"\u65e5\u672c",
    "qs:name_adm1":"\u5175\u5eab\u770c",
    "qs:name_adm2":"\u7058\u533a",
    "qs:name_en":"Nagaminedai 2 Chome",
    "qs:name_lau":"\u9577\u5cf0\u53f0",
    "qs:name_local":"\u795e\u6238\u5e02",
    "qs:photo_max":436,
    "qs:photo_sum":563,
    "qs:placetype":"Suburb",
    "qs:quad_count":11,
    "qs:woe_adm0":23424856,
    "qs:woe_adm1":2345862,
    "qs:woe_adm2":15015437,
    "qs:woe_lau":28460665,
    "qs:woe_local":1117545,
    "qs:woe_ver":"7.10.0",
    "wof:lang":[
        "jpn"
    ],
    "wof:name":"\uff12\u4e01\u76ee",
    "wof:placetype":"neighbourhood"
},
  "geometry": {"coordinates":[135.20942600000001,34.732057],"type":"Point"}
}