{
  "type": "Feature",
  "properties": {
    "gn:admin1_code":"19.0",
    "gn:admin2_code":"1848350.0",
    "gn:admin3_code":"14105.0",
    "gn:asciiname":"Nagataminami",
    "gn:country_code":"JP",
    "gn:dem":20,
    "gn:feature_class":"P",
    "gn:feature_code":"PPL",
    "gn:name":"Nagataminami",
    "gn:population":0,
    "gn:timezone":"Asia/Tokyo",
    "iso:country":"JP",
    "name:jpn_x_preferred":[
        "\u6c38\u7530\u5357"
    ],
    "name:jpn_x_variant":[
        "\u306a\u304c\u305f\u307f\u306a\u307f",
        "\u30ca\u30ac\u30bf\u30df\u30ca\u30df"
    ],
    "wof:name":"Nagataminami",
    "wof:placetype":"locality"
},
  "geometry": {"coordinates":[139.59444999999999,35.42838],"type":"Point"}
}