{
  "type": "Feature",
  "properties": {
    "gn:admin1_code":"21.0",
    "gn:admin2_code":"1865358.0",
    "gn:asciiname":"Nakanokubo",
    "gn:country_code":"JP",
    "gn:dem":123,
    "gn:feature_class":"P",
    "gn:feature_code":"PPLL",
    "gn:name":"Nakanokubo",
    "gn:population":0,
    "gn:timezone":"Asia/Tokyo",
    "iso:country":"JP",
    "name:jpn_x_preferred":[
        "\u4e2d\u30ce\u4e45\u4fdd"
    ],
    "name:jpn_x_variant":[
        "\u306a\u304b\u306e\u304f\u307c",
        "\u30ca\u30ab\u30ce\u30af\u30dc"
    ],
    "wof:name":"Nakanokubo",
    "wof:placetype":"locality"
},
  "geometry": {"coordinates":[130.04356000000001,32.33793],"type":"Point"}
}