{
  "type": "Feature",
  "properties": {
    "gn:admin1_code":"21.0",
    "gn:admin2_code":"7413150.0",
    "gn:asciiname":"Fujii",
    "gn:country_code":"JP",
    "gn:dem":24,
    "gn:feature_class":"P",
    "gn:feature_code":"PPL",
    "gn:name":"Fujii",
    "gn:population":0,
    "gn:timezone":"Asia/Tokyo",
    "iso:country":"JP",
    "name:deu_x_preferred":[
        "Fujii"
    ],
    "name:fra_x_preferred":[
        "Fujii"
    ],
    "name:jpn_x_preferred":[
        "\u85e4\u4e95"
    ],
    "name:jpn_x_variant":[
        "\u3075\u3058\u3044",
        "\u30d5\u30b8\u30a4"
    ],
    "name:rus_x_preferred":[
        "\u0424\u0443\u0434\u0437\u0438\u0438"
    ],
    "name:zho_x_preferred":[
        "\u85e4\u4e95\u6c0f"
    ],
    "wof:name":"Fujii",
    "wof:placetype":"locality"
},
  "geometry": {"coordinates":[130.73235,32.99133],"type":"Point"}
}