{
  "type": "Feature",
  "properties": {
    "gn:admin1_code":"15.0",
    "gn:admin2_code":"1860845.0",
    "gn:asciiname":"Matsuyamamachi",
    "gn:country_code":"JP",
    "gn:dem":12,
    "gn:feature_class":"P",
    "gn:feature_code":"PPL",
    "gn:name":"Matsuyamamachi",
    "gn:population":0,
    "gn:timezone":"Asia/Tokyo",
    "iso:country":"JP",
    "name:jpn_x_preferred":[
        "\u677e\u5c71\u753a"
    ],
    "wof:name":"Matsuyamamachi",
    "wof:placetype":"locality"
},
  "geometry": {"coordinates":[136.39088000000001,36.31406],"type":"Point"}
}