{
  "type": "Feature",
  "properties": {
    "gn:admin1_code":"31",
    "gn:admin2_code":"1854380.0",
    "gn:admin3_code":"33102.0",
    "gn:asciiname":"Amihama",
    "gn:country_code":"JP",
    "gn:dem":5,
    "gn:feature_class":"P",
    "gn:feature_code":"PPL",
    "gn:name":"Amihama",
    "gn:population":0,
    "gn:timezone":"Asia/Tokyo",
    "iso:country":"JP",
    "name:jpn_x_preferred":[
        "\u7db2\u6d5c"
    ],
    "name:und_x_variant":[
        "Aminohama"
    ],
    "wof:name":"Amihama",
    "wof:placetype":"locality"
},
  "geometry": {"coordinates":[133.93716000000001,34.64754],"type":"Point"}
}