{
  "type": "Feature",
  "properties": {
    "gn:admin1_code":"23.0",
    "gn:admin2_code":"1857496.0",
    "gn:asciiname":"Iitakacho-sogano",
    "gn:country_code":"JP",
    "gn:dem":561,
    "gn:feature_class":"P",
    "gn:feature_code":"PPL",
    "gn:name":"Iitakach\u014d-s\u014dgano",
    "gn:population":0,
    "gn:timezone":"Asia/Tokyo",
    "iso:country":"JP",
    "name:jpn_x_preferred":[
        "\u98ef\u9ad8\u753a\u8349\u9e7f\u91ce"
    ],
    "name:und_x_variant":[
        "Iitakach\u014d-s\u014dgano"
    ],
    "wof:name":"Iitakacho-sogano",
    "wof:placetype":"locality"
},
  "geometry": {"coordinates":[136.12413000000001,34.43003],"type":"Point"}
}