{
  "type": "Feature",
  "properties": {
    "gn:admin1_code":"4.0",
    "gn:admin2_code":"1861964.0",
    "gn:asciiname":"Kitakokubun",
    "gn:country_code":"JP",
    "gn:dem":20,
    "gn:feature_class":"P",
    "gn:feature_code":"PPL",
    "gn:name":"Kitakokubun",
    "gn:population":0,
    "gn:timezone":"Asia/Tokyo",
    "iso:country":"JP",
    "name:jpn_x_preferred":[
        "\u5317\u56fd\u5206"
    ],
    "wof:name":"Kitakokubun",
    "wof:placetype":"locality"
},
  "geometry": {"coordinates":[139.90598,35.76245],"type":"Point"}
}