{
  "type": "Feature",
  "properties": {
    "gn:admin1_code":"24.0",
    "gn:admin2_code":"7447001.0",
    "gn:asciiname":"Kogawa",
    "gn:country_code":"JP",
    "gn:dem":5,
    "gn:feature_class":"P",
    "gn:feature_code":"PPL",
    "gn:name":"Kogawa",
    "gn:population":0,
    "gn:timezone":"Asia/Tokyo",
    "iso:country":"JP",
    "name:jpn_x_preferred":[
        "\u5c0f\u5ddd"
    ],
    "name:jpn_x_variant":[
        "\u3053\u304c\u308f",
        "\u30b3\u30ac\u30ef"
    ],
    "wof:name":"Kogawa",
    "wof:placetype":"locality"
},
  "geometry": {"coordinates":[141.09211000000005,38.4489],"type":"Point"}
}