{
  "type": "Feature",
  "properties": {
    "iso:country":"JP",
    "name:eng_x_preferred":[
        "Otsubomachi 1 Chome"
    ],
    "name:eng_x_variant":[
        "Ootsubomachi 1 Choume",
        "Otsubomachi 1 Chome"
    ],
    "name:jpn_x_preferred":[
        "\uff11\u4e01\u76ee"
    ],
    "name:jpn_x_variant":[
        "\u304a\u304a\u3064\u307c\u307e\u3061 \uff11\u3061\u3087\u3046\u3081",
        "\u5927\u576a\u753a \uff11\u4e01\u76ee",
        "\uff11\u3061\u3087\u3046\u3081"
    ],
    "qs:gn_local":0,
    "qs:local_max":167,
    "qs:local_sum":381,
    "qs:localhoods":5,
    "qs:name":"\uff11\u4e01\u76ee",
    "qs:name_adm0":"\u65e5\u672c",
    "qs:name_adm1":"\u5bcc\u5c71\u770c",
    "qs:name_en":"Otsubomachi 1 Chome",
    "qs:name_lau":"\u5927\u576a\u753a",
    "qs:name_local":"\u9ad8\u5ca1\u5e02",
    "qs:photo_max":36,
    "qs:photo_sum":167,
    "qs:placetype":"Suburb",
    "qs:quad_count":13,
    "qs:woe_adm0":23424856,
    "qs:woe_adm1":2345891,
    "qs:woe_adm2":0,
    "qs:woe_lau":28423968,
    "qs:woe_local":1118292,
    "qs:woe_ver":"7.10.0",
    "wof:lang":[
        "jpn"
    ],
    "wof:name":"\uff11\u4e01\u76ee",
    "wof:placetype":"neighbourhood"
},
  "geometry": {"coordinates":[137.020037,36.748199],"type":"Point"}
}