{
  "type": "Feature",
  "properties": {
    "gn:country":"JP",
    "gn:fcode":"ADM3",
    "gn:population":0,
    "iso:country":"JP",
    "name:jpn_x_preferred":[
        "\u65e5\u5409\u6d25\u6751"
    ],
    "name:jpn_x_variant":[
        "\u3072\u3048\u3065\u305d\u3093"
    ],
    "name:und_x_variant":[
        "Hiezu Son"
    ],
    "qs:name":"Hiezu-son",
    "qs:photos_9r":0,
    "qs:photos_sr":0,
    "qs:pop_sr":"0",
    "wof:name":"Hiezu-son",
    "wof:placetype":"localadmin",
    "wof:population":0
},
  "geometry": {"coordinates":[133.37921,35.44464],"type":"Point"}
}