{
  "type": "Feature",
  "properties": {
    "gn:admin1_code":"25.0",
    "gn:admin2_code":"7413970.0",
    "gn:asciiname":"Yumibanari",
    "gn:country_code":"JP",
    "gn:dem":285,
    "gn:feature_class":"P",
    "gn:feature_code":"PPLL",
    "gn:name":"Yumibanari",
    "gn:population":0,
    "gn:timezone":"Asia/Tokyo",
    "iso:country":"JP",
    "name:jpn_x_preferred":[
        "\u5f13\u5834\u6210"
    ],
    "name:jpn_x_variant":[
        "\u3086\u307f\u3070\u306a\u308a",
        "\u30e6\u30df\u30d0\u30ca\u30ea"
    ],
    "wof:name":"Yumibanari",
    "wof:placetype":"locality"
},
  "geometry": {"coordinates":[130.94145,32.02203],"type":"Point"}
}