{
  "type": "Feature",
  "properties": {
    "gn:admin1_code":"47",
    "gn:admin2_code":"1858371.0",
    "gn:admin3_code":"47311.0",
    "gn:asciiname":"Afuso",
    "gn:country_code":"JP",
    "gn:dem":52,
    "gn:feature_class":"P",
    "gn:feature_code":"PPL",
    "gn:name":"Afuso",
    "gn:population":0,
    "gn:timezone":"Asia/Tokyo",
    "iso:country":"JP",
    "name:jpn_x_preferred":[
        "\u5b89\u5bcc\u7956"
    ],
    "name:und_x_variant":[
        "Ahuso",
        "Anfuso",
        "Anfusu",
        "Afusu",
        "Afuso"
    ],
    "wof:name":"Afuso",
    "wof:placetype":"locality"
},
  "geometry": {"coordinates":[127.89277,26.4969],"type":"Point"}
}