{
  "type": "Feature",
  "properties": {
    "iso:country":"JP",
    "name:eng_x_preferred":[
        "Chayamadai 1cho"
    ],
    "name:eng_x_variant":[
        "Chayamadai 1chou",
        "Chayamadai 1cho"
    ],
    "name:jpn_x_preferred":[
        "\uff11\u4e01"
    ],
    "name:jpn_x_variant":[
        "\u3061\u3083\u3084\u307e\u3060\u3044 \uff11\u3061\u3087\u3046",
        "\u8336\u5c71\u53f0 \uff11\u4e01",
        "\uff11\u3061\u3087\u3046"
    ],
    "qs:gn_local":0,
    "qs:local_max":237,
    "qs:local_sum":517,
    "qs:localhoods":11,
    "qs:name":"\uff11\u4e01",
    "qs:name_adm0":"\u65e5\u672c",
    "qs:name_adm1":"\u5927\u962a\u5e9c",
    "qs:name_adm2":"\u5357\u533a",
    "qs:name_en":"Chayamadai 1cho",
    "qs:name_lau":"\u8336\u5c71\u53f0",
    "qs:name_local":"\u583a\u5e02",
    "qs:photo_max":9,
    "qs:photo_sum":10,
    "qs:placetype":"Suburb",
    "qs:quad_count":2,
    "qs:woe_adm0":23424856,
    "qs:woe_adm1":2345881,
    "qs:woe_adm2":28379247,
    "qs:woe_lau":28457954,
    "qs:woe_local":1118083,
    "qs:woe_ver":"7.10.0",
    "wof:lang":[
        "jpn"
    ],
    "wof:name":"\uff11\u4e01",
    "wof:placetype":"neighbourhood"
},
  "geometry": {"coordinates":[135.513611,34.495692],"type":"Point"}
}