{
  "type": "Feature",
  "properties": {
    "iso:country":"JP",
    "qs:name":"\u6591\u9ce9\u753a",
    "qs:name_adm0":"\u65e5\u672c",
    "qs:name_adm1":"\u5948\u826f\u770c",
    "qs:photos":253,
    "qs:photos_1k":51,
    "qs:photos_9k":8,
    "qs:photos_9r":8,
    "qs:photos_all":1743,
    "qs:photos_sr":5,
    "qs:placetype":"Town",
    "qs:pop_sr":"0",
    "wof:name":"\u6591\u9ce9\u753a",
    "wof:placetype":"locality"
},
  "geometry": {"coordinates":[135.73299399999999,34.620268],"type":"Point"}
}