{
  "type": "Feature",
  "properties": {
    "gn:admin1_code":"45",
    "gn:admin2_code":"1863413.0",
    "gn:asciiname":"Ichi",
    "gn:cc2":"JP",
    "gn:country_code":"JP",
    "gn:dem":267,
    "gn:feature_class":"P",
    "gn:feature_code":"PPL",
    "gn:name":"Ichi",
    "gn:population":0,
    "gn:timezone":"Asia/Tokyo",
    "iso:country":"JP",
    "name:dan_x_preferred":[
        "Ichi"
    ],
    "name:fra_x_preferred":[
        "Ichi"
    ],
    "name:ita_x_preferred":[
        "Ichi"
    ],
    "name:und_x_variant":[
        "Iichi",
        "Ichi"
    ],
    "wof:name":"Ichi",
    "wof:placetype":"locality"
},
  "geometry": {"coordinates":[131.41666999999998,34.33333],"type":"Point"}
}