{
  "type": "Feature",
  "properties": {
    "gn:admin1_code":"21.0",
    "gn:admin2_code":"7412708.0",
    "gn:admin3_code":"43513.0",
    "gn:asciiname":"Higakure",
    "gn:country_code":"JP",
    "gn:dem":137,
    "gn:feature_class":"P",
    "gn:feature_code":"PPLL",
    "gn:name":"Higakure",
    "gn:population":0,
    "gn:timezone":"Asia/Tokyo",
    "iso:country":"JP",
    "name:jpn_x_preferred":[
        "\u65e5\u96a0"
    ],
    "name:jpn_x_variant":[
        "\u3072\u304c\u304f\u308c",
        "\u30d2\u30ac\u30af\u30ec"
    ],
    "wof:name":"Higakure",
    "wof:placetype":"locality"
},
  "geometry": {"coordinates":[130.63751000000002,32.23549000000001],"type":"Point"}
}