{
  "type": "Feature",
  "properties": {
    "gn:admin1_code":"4.0",
    "gn:admin2_code":"1857552.0",
    "gn:asciiname":"Matsudo-shinden",
    "gn:country_code":"JP",
    "gn:dem":31,
    "gn:feature_class":"P",
    "gn:feature_code":"PPL",
    "gn:name":"Matsudo-shinden",
    "gn:population":0,
    "gn:timezone":"Asia/Tokyo",
    "iso:country":"JP",
    "name:jpn_x_preferred":[
        "\u677e\u6238\u65b0\u7530"
    ],
    "wof:name":"Matsudo-shinden",
    "wof:placetype":"locality"
},
  "geometry": {"coordinates":[139.92708999999999,35.79162],"type":"Point"}
}