{
  "type": "Feature",
  "properties": {
    "gn:admin1_code":"12.0",
    "gn:admin2_code":"7428117.0",
    "gn:admin3_code":"1434.0",
    "gn:asciiname":"Shin-shigai",
    "gn:cc2":"JP",
    "gn:country_code":"JP",
    "gn:dem":46,
    "gn:feature_class":"P",
    "gn:feature_code":"PPL",
    "gn:name":"Shin-shigai",
    "gn:population":0,
    "gn:timezone":"Asia/Tokyo",
    "iso:country":"JP",
    "name:und_x_variant":[
        "Chikushi",
        "Shin-shigai"
    ],
    "wof:name":"Shin-shigai",
    "wof:placetype":"locality"
},
  "geometry": {"coordinates":[141.96666999999999,43.76667],"type":"Point"}
}