{
  "type": "Feature",
  "properties": {
    "gn:admin1_code":"24.0",
    "gn:admin2_code":"2111889.0",
    "gn:admin3_code":"4401.0",
    "gn:asciiname":"Ichinowatari",
    "gn:country_code":"JP",
    "gn:dem":27,
    "gn:feature_class":"P",
    "gn:feature_code":"PPL",
    "gn:name":"Ichinowatari",
    "gn:population":0,
    "gn:timezone":"Asia/Tokyo",
    "iso:country":"JP",
    "name:jpn_x_preferred":[
        "\u4e00\u30ce\u6e21"
    ],
    "name:jpn_x_variant":[
        "\u3044\u3061\u306e\u308f\u305f\u308a",
        "\u30a4\u30c1\u30ce\u30ef\u30bf\u30ea"
    ],
    "wof:name":"Ichinowatari",
    "wof:placetype":"locality"
},
  "geometry": {"coordinates":[141.07996,38.40146],"type":"Point"}
}