{
  "type": "Feature",
  "properties": {
    "gn:admin1_code":"21.0",
    "gn:admin2_code":"1864975.0",
    "gn:admin3_code":"43433.0",
    "gn:asciiname":"Kain",
    "gn:country_code":"JP",
    "gn:dem":378,
    "gn:feature_class":"P",
    "gn:feature_code":"PPL",
    "gn:name":"Kain",
    "gn:population":0,
    "gn:timezone":"Asia/Tokyo",
    "iso:country":"JP",
    "name:jpn_x_preferred":[
        "\u6cb3\u9670"
    ],
    "name:jpn_x_variant":[
        "\u304b\u3044\u3093",
        "\u30ab\u30a4\u30f3"
    ],
    "wof:name":"Kain",
    "wof:placetype":"locality"
},
  "geometry": {"coordinates":[131.01050000000001,32.83685],"type":"Point"}
}