{
  "type": "Feature",
  "properties": {
    "gn:admin1_code":"36.0",
    "gn:admin2_code":"1854781.0",
    "gn:admin3_code":"32448.0",
    "gn:asciiname":"Onbara",
    "gn:country_code":"JP",
    "gn:dem":335,
    "gn:feature_class":"P",
    "gn:feature_code":"PPL",
    "gn:name":"Onbara",
    "gn:population":0,
    "gn:timezone":"Asia/Tokyo",
    "iso:country":"JP",
    "name:jpn_x_preferred":[
        "\u4e59\u539f"
    ],
    "wof:name":"Onbara",
    "wof:placetype":"locality"
},
  "geometry": {"coordinates":[132.53014999999999,34.99335],"type":"Point"}
}