{
  "type": "Feature",
  "properties": {
    "gn:admin1_code":"38.0",
    "gn:admin2_code":"2112845.0",
    "gn:admin3_code":"9342.0",
    "gn:asciiname":"Nagatsutsumi",
    "gn:country_code":"JP",
    "gn:dem":74,
    "gn:feature_class":"P",
    "gn:feature_code":"PPL",
    "gn:name":"Nagatsutsumi",
    "gn:population":0,
    "gn:timezone":"Asia/Tokyo",
    "iso:country":"JP",
    "wof:name":"Nagatsutsumi",
    "wof:placetype":"locality"
},
  "geometry": {"coordinates":[140.08333000000002,36.43333],"type":"Point"}
}