{
  "type": "Feature",
  "properties": {
    "gn:admin1_code":"16.0",
    "gn:admin2_code":"2128941.0",
    "gn:admin3_code":"3524.0",
    "gn:asciiname":"Otomo",
    "gn:country_code":"JP",
    "gn:dem":309,
    "gn:feature_class":"P",
    "gn:feature_code":"PPL",
    "gn:name":"Otomo",
    "gn:population":0,
    "gn:timezone":"Asia/Tokyo",
    "iso:country":"JP",
    "name:deu_x_preferred":[
        "Otomo"
    ],
    "name:fra_x_preferred":[
        "\u014ctomo"
    ],
    "name:ita_x_preferred":[
        "Otomo"
    ],
    "name:jpn_x_preferred":[
        "\u5c0f\u53cb"
    ],
    "name:jpn_x_variant":[
        "\u304a\u3068\u3082",
        "\u30aa\u30c8\u30e2"
    ],
    "name:por_x_preferred":[
        "Otomo"
    ],
    "name:slv_x_preferred":[
        "Otomo"
    ],
    "wof:name":"Otomo",
    "wof:placetype":"locality"
},
  "geometry": {"coordinates":[141.25946999999999,40.17836],"type":"Point"}
}