{
  "type": "Feature",
  "properties": {
    "gn:admin1_code":"18",
    "gn:admin2_code":"8714932.0",
    "gn:admin3_code":"46502.0",
    "gn:asciiname":"Okawa",
    "gn:country_code":"JP",
    "gn:dem":5,
    "gn:feature_class":"P",
    "gn:feature_code":"PPL",
    "gn:name":"\u014ckawa",
    "gn:population":0,
    "gn:timezone":"Asia/Tokyo",
    "iso:country":"JP",
    "name:jpn_x_preferred":[
        "\u5927\u5ddd"
    ],
    "name:und_x_variant":[
        "\u014ckawa"
    ],
    "wof:name":"Okawa",
    "wof:placetype":"locality"
},
  "geometry": {"coordinates":[130.86607000000001,30.41735],"type":"Point"}
}