{
  "type": "Feature",
  "properties": {
    "gn:admin1_code":"2.0",
    "gn:admin2_code":"7443156.0",
    "gn:asciiname":"Kamifunagi",
    "gn:country_code":"JP",
    "gn:dem":130,
    "gn:feature_class":"P",
    "gn:feature_code":"PPLL",
    "gn:name":"Kamifunagi",
    "gn:population":0,
    "gn:timezone":"Asia/Tokyo",
    "iso:country":"JP",
    "name:jpn_x_preferred":[
        "\u4e0a\u821f\u6728"
    ],
    "wof:name":"Kamifunagi",
    "wof:placetype":"locality"
},
  "geometry": {"coordinates":[140.45043999999999,40.1033],"type":"Point"}
}