{
  "type": "Feature",
  "properties": {
    "iso:country":"JP",
    "name:eng_x_preferred":[
        "Shimoda City"
    ],
    "name:jpn_x_preferred":[
        "\u4e0b\u7530\u5e02"
    ],
    "qs:name":"\u4e0b\u7530\u5e02",
    "qs:name_adm0":"\u65e5\u672c",
    "qs:name_adm1":"\u9759\u5ca1\u770c",
    "qs:photos":1976,
    "qs:photos_1k":400,
    "qs:photos_9k":16,
    "qs:photos_9r":12,
    "qs:photos_all":3524,
    "qs:photos_sr":15,
    "qs:placetype":"Town",
    "qs:pop_sr":"0",
    "wof:name":"Shimoda City",
    "wof:placetype":"locality"
},
  "geometry": {"coordinates":[138.966522,34.67557],"type":"Point"}
}