{
  "type": "Feature",
  "properties": {
    "iso:country":"JP",
    "name:eng_x_preferred":[
        "Kodo 2 Chome"
    ],
    "name:eng_x_variant":[
        "Koudou 2 Choume",
        "Kodo 2 Chome"
    ],
    "name:jpn_x_preferred":[
        "\uff12\u4e01\u76ee"
    ],
    "name:jpn_x_variant":[
        "\u3053\u3046\u3069\u3046 \uff12\u3061\u3087\u3046\u3081",
        "\u5f18\u9053 \uff12\u4e01\u76ee",
        "\uff12\u3061\u3087\u3046\u3081"
    ],
    "qs:gn_adm0_cc":"JP",
    "qs:gn_local":1850147,
    "qs:local_max":18112,
    "qs:local_sum":895907,
    "qs:localhoods":857,
    "qs:name":"\uff12\u4e01\u76ee",
    "qs:name_adm0":"\u65e5\u672c",
    "qs:name_adm1":"\u6771\u4eac\u90fd",
    "qs:name_adm2":"\u8db3\u7acb\u533a",
    "qs:name_en":"Kodo 2 Chome",
    "qs:name_lau":"\u5f18\u9053",
    "qs:name_local":"\u6771\u4eac",
    "qs:photo_max":20,
    "qs:photo_sum":37,
    "qs:placetype":"Suburb",
    "qs:quad_count":5,
    "qs:woe_adm0":23424856,
    "qs:woe_adm1":2345889,
    "qs:woe_adm2":1118608,
    "qs:woe_lau":28414641,
    "qs:woe_local":1118370,
    "qs:woe_ver":"7.10.0",
    "wof:lang":[
        "jpn"
    ],
    "wof:name":"\uff12\u4e01\u76ee",
    "wof:placetype":"neighbourhood"
},
  "geometry": {"coordinates":[139.82021700000001,35.771504],"type":"Point"}
}