{
  "type": "Feature",
  "properties": {
    "gn:admin1_code":"20",
    "gn:admin2_code":"1865443.0",
    "gn:admin3_code":"39305.0",
    "gn:asciiname":"Agura",
    "gn:cc2":"JP",
    "gn:country_code":"JP",
    "gn:dem":330,
    "gn:feature_class":"P",
    "gn:feature_code":"PPL",
    "gn:name":"Agura",
    "gn:population":0,
    "gn:timezone":"Asia/Tokyo",
    "iso:country":"JP",
    "name:ces_x_preferred":[
        "Agura"
    ],
    "name:heb_x_preferred":[
        "\u05d0\u05d2\u05d5\u05e8\u05d4"
    ],
    "name:ita_x_preferred":[
        "Agura"
    ],
    "name:jpn_x_preferred":[
        "\u5b89\u5009"
    ],
    "name:pol_x_preferred":[
        "Agura"
    ],
    "name:ron_x_preferred":[
        "Agura"
    ],
    "name:slk_x_preferred":[
        "Agura"
    ],
    "name:und_x_variant":[
        "Akura",
        "Agura"
    ],
    "wof:name":"Agura",
    "wof:placetype":"locality"
},
  "geometry": {"coordinates":[134.16666999999998,33.51667],"type":"Point"}
}