{
  "type": "Feature",
  "properties": {
    "gn:admin1_code":"7.0",
    "gn:admin2_code":"1859306.0",
    "gn:admin3_code":"40109.0",
    "gn:asciiname":"Kumade",
    "gn:country_code":"JP",
    "gn:dem":12,
    "gn:feature_class":"P",
    "gn:feature_code":"PPL",
    "gn:name":"Kumade",
    "gn:population":0,
    "gn:timezone":"Asia/Tokyo",
    "iso:country":"JP",
    "name:jpn_x_preferred":[
        "\u718a\u624b"
    ],
    "wof:name":"Kumade",
    "wof:placetype":"locality"
},
  "geometry": {"coordinates":[130.76724999999999,33.86305],"type":"Point"}
}