{
  "type": "Feature",
  "properties": {
    "gn:admin1_code":"22.0",
    "gn:admin2_code":"7412123.0",
    "gn:admin3_code":"26322.0",
    "gn:asciiname":"Kitakawazura",
    "gn:country_code":"JP",
    "gn:dem":13,
    "gn:feature_class":"P",
    "gn:feature_code":"PPL",
    "gn:name":"Kitakawazura",
    "gn:population":0,
    "gn:timezone":"Asia/Tokyo",
    "iso:country":"JP",
    "name:jpn_x_preferred":[
        "\u5317\u5ddd\u9854"
    ],
    "wof:name":"Kitakawazura",
    "wof:placetype":"locality"
},
  "geometry": {"coordinates":[135.72186000000002,34.8945],"type":"Point"}
}