{
  "type": "Feature",
  "properties": {
    "gn:admin1_code":"4.0",
    "gn:admin2_code":"8304237.0",
    "gn:asciiname":"Tanka",
    "gn:country_code":"JP",
    "gn:dem":25,
    "gn:feature_class":"P",
    "gn:feature_code":"PPLL",
    "gn:name":"Tanka",
    "gn:population":0,
    "gn:timezone":"Asia/Tokyo",
    "iso:country":"JP",
    "name:jpn_x_preferred":[
        "\u4e39\u904e"
    ],
    "name:jpn_x_variant":[
        "\u305f\u3093\u304b",
        "\u30bf\u30f3\u30ab"
    ],
    "wof:name":"Tanka",
    "wof:placetype":"locality"
},
  "geometry": {"coordinates":[140.05475000000001,35.36223],"type":"Point"}
}