{
  "type": "Feature",
  "properties": {
    "gn:admin1_code":"4.0",
    "gn:admin2_code":"8304237.0",
    "gn:asciiname":"Tanka",
    "gn:country_code":"JP",
    "gn:dem":25,
    "gn:feature_class":"P",
    "gn:feature_code":"PPLL",
    "gn:name":"Tanka",
    "gn:population":0,
    "gn:timezone":"Asia/Tokyo",
    "iso:country":"JP",
    "name:aze_x_preferred":[
        "Tanka"
    ],
    "name:bar_x_preferred":[
        "Tanka"
    ],
    "name:bel_x_preferred":[
        "\u0422\u0430\u043d\u043a\u0430"
    ],
    "name:cat_x_preferred":[
        "Tanka"
    ],
    "name:ces_x_preferred":[
        "Tanka"
    ],
    "name:chu_x_preferred":[
        "\u0422\u0430\u043d\u043a\u0430"
    ],
    "name:deu_x_preferred":[
        "Tanka"
    ],
    "name:epo_x_preferred":[
        "Tankao"
    ],
    "name:est_x_preferred":[
        "Tanka"
    ],
    "name:fin_x_preferred":[
        "Tanka"
    ],
    "name:fra_x_preferred":[
        "Tanka"
    ],
    "name:guj_x_preferred":[
        "\u0aa4\u0abe\u0aa8\u0a95\u0abe"
    ],
    "name:heb_x_preferred":[
        "\u05d8\u05e0\u05e7\u05d4"
    ],
    "name:hun_x_preferred":[
        "Tanka"
    ],
    "name:hye_x_preferred":[
        "\u0539\u0561\u0576\u056f\u0561"
    ],
    "name:ind_x_preferred":[
        "Tanka"
    ],
    "name:isl_x_preferred":[
        "Tanka"
    ],
    "name:ita_x_preferred":[
        "Tanka"
    ],
    "name:jpn_x_preferred":[
        "\u4e39\u904e"
    ],
    "name:jpn_x_variant":[
        "\u305f\u3093\u304b",
        "\u30bf\u30f3\u30ab"
    ],
    "name:kir_x_preferred":[
        "\u0422\u0430\u043d\u043a\u0430"
    ],
    "name:lav_x_preferred":[
        "Tanka"
    ],
    "name:ltz_x_preferred":[
        "Tanka"
    ],
    "name:nld_x_preferred":[
        "Tanka"
    ],
    "name:nor_x_preferred":[
        "Tanka"
    ],
    "name:pol_x_preferred":[
        "Tanka"
    ],
    "name:por_x_preferred":[
        "Tanka"
    ],
    "name:ron_x_preferred":[
        "Tanka"
    ],
    "name:rus_x_preferred":[
        "\u0422\u0430\u043d\u043a\u0430"
    ],
    "name:slk_x_preferred":[
        "Tanka"
    ],
    "name:slv_x_preferred":[
        "Tanka"
    ],
    "name:snd_x_preferred":[
        "\u067d\u0646\u06aa\u0627"
    ],
    "name:spa_x_preferred":[
        "Tanka"
    ],
    "name:tur_x_preferred":[
        "Tanka"
    ],
    "name:ukr_x_preferred":[
        "\u0422\u0430\u043d\u043a\u0430"
    ],
    "name:vie_x_preferred":[
        "Tanka"
    ],
    "name:xmf_x_preferred":[
        "\u10e2\u10d0\u10dc\u10d9\u10d0"
    ],
    "wof:name":"Tanka",
    "wof:placetype":"locality"
},
  "geometry": {"coordinates":[140.05475000000001,35.36223],"type":"Point"}
}