{
  "type": "Feature",
  "properties": {
    "gn:admin1_code":"37.0",
    "gn:admin2_code":"1864104.0",
    "gn:asciiname":"Yokonzawa",
    "gn:country_code":"JP",
    "gn:dem":538,
    "gn:feature_class":"P",
    "gn:feature_code":"PPLL",
    "gn:name":"Yokonzawa",
    "gn:population":0,
    "gn:timezone":"Asia/Tokyo",
    "iso:country":"JP",
    "name:jpn_x_preferred":[
        "\u6a2a\u624b\u6ca2"
    ],
    "name:jpn_x_variant":[
        "\u3088\u3053\u3093\u3056\u308f"
    ],
    "wof:name":"Yokonzawa",
    "wof:placetype":"locality"
},
  "geometry": {"coordinates":[138.58223000000001,35.31989],"type":"Point"}
}