{
  "type": "Feature",
  "properties": {
    "iso:country":"JP",
    "qs:name":"\u666e\u4ee3\u6751",
    "qs:name_adm0":"\u65e5\u672c",
    "qs:name_adm1":"\u5ca9\u624b\u770c",
    "qs:photos":37,
    "qs:photos_1k":7,
    "qs:photos_9k":1,
    "qs:photos_9r":2,
    "qs:photos_all":37,
    "qs:photos_sr":2,
    "qs:placetype":"Town",
    "qs:pop_sr":"0",
    "wof:name":"\u666e\u4ee3\u6751",
    "wof:placetype":"locality"
},
  "geometry": {"coordinates":[141.85581199999999,40.055475],"type":"Point"}
}