{
  "type": "Feature",
  "properties": {
    "gn:admin1_code":"32.0",
    "gn:admin2_code":"1853167.0",
    "gn:admin3_code":"27145.0",
    "gn:asciiname":"Hata",
    "gn:country_code":"JP",
    "gn:dem":97,
    "gn:feature_class":"P",
    "gn:feature_code":"PPL",
    "gn:name":"Hata",
    "gn:population":0,
    "gn:timezone":"Asia/Tokyo",
    "iso:country":"JP",
    "name:ceb_x_preferred":[
        "Hata"
    ],
    "name:deu_x_preferred":[
        "Hata"
    ],
    "name:fra_x_preferred":[
        "Hata"
    ],
    "name:jpn_x_preferred":[
        "\u7551"
    ],
    "name:rus_x_preferred":[
        "\u0425\u0430\u0442\u0430"
    ],
    "name:tur_x_preferred":[
        "Hata"
    ],
    "name:ukr_x_preferred":[
        "\u0425\u0430\u0442\u0430"
    ],
    "name:vie_x_preferred":[
        "Hata"
    ],
    "wof:name":"Hata",
    "wof:placetype":"locality"
},
  "geometry": {"coordinates":[135.52736000000002,34.46921],"type":"Point"}
}