{
  "type": "Feature",
  "properties": {
    "gn:admin1_code":"6.0",
    "gn:admin2_code":"1863982.0",
    "gn:asciiname":"Shijutanicho",
    "gn:country_code":"JP",
    "gn:dem":9,
    "gn:feature_class":"P",
    "gn:feature_code":"PPL",
    "gn:name":"Shij\u016btanich\u014d",
    "gn:population":0,
    "gn:timezone":"Asia/Tokyo",
    "iso:country":"JP",
    "name:jpn_x_preferred":[
        "\u56db\u5341\u8c37\u753a"
    ],
    "name:und_x_variant":[
        "Shij\u016btanich\u014d"
    ],
    "wof:name":"Shijutanicho",
    "wof:placetype":"locality"
},
  "geometry": {"coordinates":[136.17594,36.10818],"type":"Point"}
}