{
  "type": "Feature",
  "properties": {
    "gn:admin1_code":"6.0",
    "gn:admin2_code":"1854875.0",
    "gn:admin3_code":"18423.0",
    "gn:asciiname":"Chigadaira",
    "gn:country_code":"JP",
    "gn:dem":174,
    "gn:feature_class":"P",
    "gn:feature_code":"PPL",
    "gn:name":"Chigadaira",
    "gn:population":0,
    "gn:timezone":"Asia/Tokyo",
    "iso:country":"JP",
    "wof:name":"Chigadaira",
    "wof:placetype":"locality"
},
  "geometry": {"coordinates":[135.97426000000002,35.97623],"type":"Point"}
}