{
  "type": "Feature",
  "properties": {
    "iso:country":"JP",
    "label:eng_x_preferred_longname":[
        "Iwakuni City"
    ],
    "label:eng_x_preferred_placetype":[
        "city"
    ],
    "name:eng_x_preferred":[
        "Iwakuni"
    ],
    "name:eng_x_variant":[
        "Iwakuni City"
    ],
    "name:jpn_x_preferred":[
        "\u5ca9\u56fd\u5e02"
    ],
    "qs:name":"\u5ca9\u56fd\u5e02",
    "qs:name_adm0":"\u65e5\u672c",
    "qs:name_adm1":"\u5c71\u53e3\u770c",
    "qs:photos":1136,
    "qs:photos_1k":230,
    "qs:photos_9k":13,
    "qs:photos_9r":11,
    "qs:photos_all":2851,
    "qs:photos_sr":11,
    "qs:placetype":"Town",
    "qs:pop_sr":"0",
    "wof:name":"Iwakuni",
    "wof:placetype":"locality"
},
  "geometry": {"coordinates":[132.1769425,34.171414],"type":"Point"}
}