{
  "type": "Feature",
  "properties": {
    "gn:admin1_code":"19.0",
    "gn:admin2_code":"1848595.0",
    "gn:asciiname":"Teranoue",
    "gn:country_code":"JP",
    "gn:dem":53,
    "gn:feature_class":"P",
    "gn:feature_code":"PPLL",
    "gn:name":"Teranoue",
    "gn:population":0,
    "gn:timezone":"Asia/Tokyo",
    "iso:country":"JP",
    "name:jpn_x_preferred":[
        "\u5bfa\u30ce\u4e0a"
    ],
    "wof:name":"Teranoue",
    "wof:placetype":"locality"
},
  "geometry": {"coordinates":[139.46993000000001,35.44221],"type":"Point"}
}