{
  "type": "Feature",
  "properties": {
    "gn:admin1_code":"42.0",
    "gn:admin2_code":"7391183.0",
    "gn:asciiname":"Itodanishin",
    "gn:country_code":"JP",
    "gn:dem":246,
    "gn:feature_class":"P",
    "gn:feature_code":"PPL",
    "gn:name":"Itodanishin",
    "gn:population":0,
    "gn:timezone":"Asia/Tokyo",
    "iso:country":"JP",
    "name:jpn_x_preferred":[
        "\u7cf8\u8c37\u65b0"
    ],
    "wof:name":"Itodanishin",
    "wof:placetype":"locality"
},
  "geometry": {"coordinates":[136.83116999999999,36.52498],"type":"Point"}
}