{
  "type": "Feature",
  "properties": {
    "gn:admin1_code":"2.0",
    "gn:admin2_code":"2112235.0",
    "gn:admin3_code":"5327.0",
    "gn:asciiname":"Bussha",
    "gn:country_code":"JP",
    "gn:dem":50,
    "gn:feature_class":"P",
    "gn:feature_code":"PPL",
    "gn:name":"Bussha",
    "gn:population":0,
    "gn:timezone":"Asia/Tokyo",
    "iso:country":"JP",
    "name:jpn_x_preferred":[
        "\u4ecf\u793e"
    ],
    "wof:name":"Bussha",
    "wof:placetype":"locality"
},
  "geometry": {"coordinates":[140.31936999999999,40.08091],"type":"Point"}
}