{
  "type": "Feature",
  "properties": {
    "gn:admin1_code":"28.0",
    "gn:admin2_code":"1852501.0",
    "gn:admin3_code":"29363.0",
    "gn:asciiname":"O",
    "gn:country_code":"JP",
    "gn:dem":51,
    "gn:feature_class":"P",
    "gn:feature_code":"PPL",
    "gn:name":"\u014c",
    "gn:population":0,
    "gn:timezone":"Asia/Tokyo",
    "iso:country":"JP",
    "name:jpn_x_preferred":[
        "\u014c"
    ],
    "name:jpn_x_variant":[
        "\u591a"
    ],
    "wof:name":"O",
    "wof:placetype":"locality"
},
  "geometry": {"coordinates":[135.79040000000001,34.53509],"type":"Point"}
}