{
  "type": "Feature",
  "properties": {
    "gn:admin1_code":"28.0",
    "gn:admin2_code":"1852501.0",
    "gn:admin3_code":"29363.0",
    "gn:asciiname":"O",
    "gn:country_code":"JP",
    "gn:dem":51,
    "gn:feature_class":"P",
    "gn:feature_code":"PPL",
    "gn:name":"\u014c",
    "gn:population":0,
    "gn:timezone":"Asia/Tokyo",
    "iso:country":"JP",
    "name:bel_x_preferred":[
        "O"
    ],
    "name:bre_x_preferred":[
        "O"
    ],
    "name:fra_x_preferred":[
        "O"
    ],
    "name:frr_x_preferred":[
        "O"
    ],
    "name:glv_x_preferred":[
        "Onnane"
    ],
    "name:hye_x_preferred":[
        "O"
    ],
    "name:jpn_x_preferred":[
        "\u014c"
    ],
    "name:jpn_x_variant":[
        "\u591a"
    ],
    "name:kur_x_preferred":[
        "O"
    ],
    "name:mhr_x_preferred":[
        "O"
    ],
    "name:mkd_x_preferred":[
        "O"
    ],
    "name:mya_x_preferred":[
        "\u1021\u102d\u102f"
    ],
    "name:nld_x_preferred":[
        "O"
    ],
    "name:pan_x_preferred":[
        "\u0a13"
    ],
    "name:rus_x_preferred":[
        "O"
    ],
    "name:srp_x_preferred":[
        "O"
    ],
    "name:ukr_x_preferred":[
        "O"
    ],
    "name:uzb_x_preferred":[
        "O"
    ],
    "name:wln_x_preferred":[
        "Lete"
    ],
    "name:xal_x_preferred":[
        "O \u04af\u0437\u0433"
    ],
    "wof:name":"O",
    "wof:placetype":"locality"
},
  "geometry": {"coordinates":[135.79040000000001,34.53509],"type":"Point"}
}