{
  "type": "Feature",
  "properties": {
    "gn:admin1_code":"26",
    "gn:admin2_code":"1856209.0",
    "gn:asciiname":"Kawanakajimamachi-hara",
    "gn:country_code":"JP",
    "gn:dem":355,
    "gn:feature_class":"P",
    "gn:feature_code":"PPL",
    "gn:name":"Kawanakajimamachi-hara",
    "gn:population":0,
    "gn:timezone":"Asia/Tokyo",
    "iso:country":"JP",
    "name:jpn_x_preferred":[
        "\u5ddd\u4e2d\u5cf6\u753a\u539f"
    ],
    "name:und_x_variant":[
        "Kawanakajimamachi"
    ],
    "wof:name":"Kawanakajimamachi-hara",
    "wof:placetype":"locality"
},
  "geometry": {"coordinates":[138.15000000000001,36.58333],"type":"Point"}
}