{
  "type": "Feature",
  "properties": {
    "gn:admin1_code":"18.0",
    "gn:admin2_code":"7383991.0",
    "gn:asciiname":"Nishihonmachi",
    "gn:country_code":"JP",
    "gn:dem":177,
    "gn:feature_class":"P",
    "gn:feature_code":"PPLL",
    "gn:name":"Nishihonmachi",
    "gn:population":0,
    "gn:timezone":"Asia/Tokyo",
    "iso:country":"JP",
    "name:jpn_x_preferred":[
        "\u897f\u672c\u753a"
    ],
    "name:jpn_x_variant":[
        "\u306b\u3057\u307b\u3093\u307e\u3061",
        "\u30cb\u30b7\u30db\u30f3\u30de\u30c1"
    ],
    "wof:name":"Nishihonmachi",
    "wof:placetype":"locality"
},
  "geometry": {"coordinates":[130.60183999999998,32.05997],"type":"Point"}
}