{
  "type": "Feature",
  "properties": {
    "gn:admin1_code":"24",
    "gn:admin2_code":"7446986.0",
    "gn:admin3_code":"4581.0",
    "gn:asciiname":"Takashirohama",
    "gn:country_code":"JP",
    "gn:dem":8,
    "gn:feature_class":"P",
    "gn:feature_code":"PPL",
    "gn:name":"Takashirohama",
    "gn:population":0,
    "gn:timezone":"Asia/Tokyo",
    "iso:country":"JP",
    "name:jpn_x_preferred":[
        "\u9ad8\u767d\u6d5c"
    ],
    "name:jpn_x_variant":[
        "\u305f\u304b\u3057\u308d\u306f\u307e",
        "\u30bf\u30ab\u30b7\u30ed\u30cf\u30de"
    ],
    "name:und_x_variant":[
        "Takashiro"
    ],
    "wof:name":"Takashirohama",
    "wof:placetype":"locality"
},
  "geometry": {"coordinates":[141.46222,38.42398],"type":"Point"}
}