{
  "type": "Feature",
  "properties": {
    "gn:admin1_code":"12.0",
    "gn:asciiname":"Wakimoto",
    "gn:country_code":"JP",
    "gn:dem":12,
    "gn:feature_class":"P",
    "gn:feature_code":"PPL",
    "gn:name":"Wakimoto",
    "gn:population":0,
    "gn:timezone":"Asia/Tokyo",
    "iso:country":"JP",
    "name:jpn_x_preferred":[
        "\u6d8c\u5143"
    ],
    "name:jpn_x_variant":[
        "\u308f\u304d\u3082\u3068",
        "\u30ef\u30ad\u30e2\u30c8"
    ],
    "wof:name":"Wakimoto",
    "wof:placetype":"locality"
},
  "geometry": {"coordinates":[140.42952,41.56407],"type":"Point"}
}