{
  "type": "Feature",
  "properties": {
    "iso:country":"JP",
    "name:eng_x_preferred":[
        "Suwa 2 Chome"
    ],
    "name:eng_x_variant":[
        "Suwa 2 Choume",
        "Suwa 2 Chome"
    ],
    "name:jpn_x_preferred":[
        "\uff12\u4e01\u76ee"
    ],
    "name:jpn_x_variant":[
        "\u3059\u308f \uff12\u3061\u3087\u3046\u3081",
        "\u8acf\u8a2a \uff12\u4e01\u76ee",
        "\uff12\u3061\u3087\u3046\u3081"
    ],
    "qs:gn_adm0_cc":"JP",
    "qs:gn_local":1859642,
    "qs:local_max":4758,
    "qs:local_sum":25395,
    "qs:localhoods":83,
    "qs:name":"\uff12\u4e01\u76ee",
    "qs:name_adm0":"\u65e5\u672c",
    "qs:name_adm1":"\u795e\u5948\u5ddd\u770c",
    "qs:name_adm2":"\u9ad8\u6d25\u533a",
    "qs:name_en":"Suwa 2 Chome",
    "qs:name_lau":"\u8acf\u8a2a",
    "qs:name_local":"\u5ddd\u5d0e\u5e02",
    "qs:photo_max":234,
    "qs:photo_sum":503,
    "qs:placetype":"Suburb",
    "qs:quad_count":4,
    "qs:woe_adm0":23424856,
    "qs:woe_adm1":2345868,
    "qs:woe_adm2":1115335,
    "qs:woe_lau":28416423,
    "qs:woe_local":1117502,
    "qs:woe_ver":"7.10.0",
    "wof:lang":[
        "jpn"
    ],
    "wof:name":"\uff12\u4e01\u76ee",
    "wof:placetype":"neighbourhood"
},
  "geometry": {"coordinates":[139.63078300000001,35.604241],"type":"Point"}
}