{
  "type": "Feature",
  "properties": {
    "gn:admin1_code":"28",
    "gn:admin2_code":"1850395.0",
    "gn:asciiname":"Nagaracho",
    "gn:country_code":"JP",
    "gn:dem":54,
    "gn:feature_class":"P",
    "gn:feature_code":"PPL",
    "gn:name":"Nagarach\u014d",
    "gn:population":0,
    "gn:timezone":"Asia/Tokyo",
    "iso:country":"JP",
    "name:jpn_x_preferred":[
        "\u9577\u67c4\u753a"
    ],
    "name:und_x_variant":[
        "Nagarach\u014d",
        "Nagara"
    ],
    "wof:name":"Nagaracho",
    "wof:placetype":"locality"
},
  "geometry": {"coordinates":[135.82877999999999,34.57357],"type":"Point"}
}