{
  "type": "Feature",
  "properties": {
    "gn:admin1_code":"19.0",
    "gn:admin2_code":"1859635.0",
    "gn:admin3_code":"14134.0",
    "gn:asciiname":"Kanigaya",
    "gn:country_code":"JP",
    "gn:dem":34,
    "gn:feature_class":"P",
    "gn:feature_code":"PPL",
    "gn:name":"Kanigaya",
    "gn:population":0,
    "gn:timezone":"Asia/Tokyo",
    "iso:country":"JP",
    "name:jpn_x_preferred":[
        "\u87f9\u30f6\u8c37"
    ],
    "wof:name":"Kanigaya",
    "wof:placetype":"locality"
},
  "geometry": {"coordinates":[139.63079999999999,35.5654],"type":"Point"}
}