{
  "type": "Feature",
  "properties": {
    "gn:admin1_code":"4.0",
    "gn:admin2_code":"2112997.0",
    "gn:admin3_code":"12421.0",
    "gn:asciiname":"Kaigan",
    "gn:country_code":"JP",
    "gn:dem":2,
    "gn:feature_class":"P",
    "gn:feature_code":"PPLL",
    "gn:name":"Kaigan",
    "gn:population":0,
    "gn:timezone":"Asia/Tokyo",
    "iso:country":"JP",
    "name:jpn_x_preferred":[
        "\u6d77\u5cb8"
    ],
    "name:jpn_x_variant":[
        "\u304b\u3044\u304c\u3093",
        "\u30ab\u30a4\u30ac\u30f3"
    ],
    "wof:name":"Kaigan",
    "wof:placetype":"locality"
},
  "geometry": {"coordinates":[140.38956999999999,35.38302],"type":"Point"}
}