{
  "type": "Feature",
  "properties": {
    "gn:admin1_code":"3.0",
    "gn:admin2_code":"2130088.0",
    "gn:admin3_code":"2303.0",
    "gn:asciiname":"Yomonai",
    "gn:country_code":"JP",
    "gn:dem":11,
    "gn:feature_class":"P",
    "gn:feature_code":"PPL",
    "gn:name":"Yomonai",
    "gn:population":0,
    "gn:timezone":"Asia/Tokyo",
    "iso:country":"JP",
    "name:jpn_x_preferred":[
        "\u4e0e\u8302\u5185"
    ],
    "name:jpn_x_variant":[
        "\u3088\u3082\u306a\u3044",
        "\u30e8\u30e2\u30ca\u30a4"
    ],
    "wof:name":"Yomonai",
    "wof:placetype":"locality"
},
  "geometry": {"coordinates":[140.52328,41.20774],"type":"Point"}
}