{
  "type": "Feature",
  "properties": {
    "iso:country":"JP",
    "name:eng_x_preferred":[
        "Chiwakacho 2 Chome"
    ],
    "name:eng_x_variant":[
        "Chiwakachou 2 Choume",
        "Chiwakacho 2 Chome"
    ],
    "name:jpn_x_preferred":[
        "\uff12\u4e01\u76ee"
    ],
    "name:jpn_x_variant":[
        "\u3061\u308f\u304b\u3061\u3087\u3046 \uff12\u3061\u3087\u3046\u3081",
        "\u5343\u82e5\u753a \uff12\u4e01\u76ee",
        "\uff12\u3061\u3087\u3046\u3081"
    ],
    "qs:gn_local":0,
    "qs:local_max":6208,
    "qs:local_sum":82309,
    "qs:localhoods":190,
    "qs:name":"\uff12\u4e01\u76ee",
    "qs:name_adm0":"\u65e5\u672c",
    "qs:name_adm1":"\u795e\u5948\u5ddd\u770c",
    "qs:name_adm2":"\u795e\u5948\u5ddd\u533a",
    "qs:name_en":"Chiwakacho 2 Chome",
    "qs:name_lau":"\u5343\u82e5\u753a",
    "qs:name_local":"\u6a2a\u6d5c\u5e02",
    "qs:photo_max":40,
    "qs:photo_sum":210,
    "qs:photos":30,
    "qs:photos_1k":6,
    "qs:photos_9k":1,
    "qs:photos_9r":2,
    "qs:photos_all":30,
    "qs:photos_sr":2,
    "qs:placetype":"Suburb",
    "qs:pop_sr":"0",
    "qs:quad_count":13,
    "qs:woe_adm0":23424856,
    "qs:woe_adm1":2345868,
    "qs:woe_adm2":15015382,
    "qs:woe_lau":1107808,
    "qs:woe_local":1118550,
    "qs:woe_ver":"7.10.0",
    "wof:lang":[
        "jpn"
    ],
    "wof:name":"\uff12\u4e01\u76ee",
    "wof:placetype":"neighbourhood"
},
  "geometry": {"coordinates":[139.63932700000001,35.472021],"type":"Point"}
}