{
  "type": "Feature",
  "properties": {
    "gn:admin1_code":"18.0",
    "gn:admin2_code":"8714932.0",
    "gn:admin3_code":"46502.0",
    "gn:asciiname":"Hamada",
    "gn:country_code":"JP",
    "gn:dem":8,
    "gn:feature_class":"P",
    "gn:feature_code":"PPLL",
    "gn:name":"Hamada",
    "gn:population":0,
    "gn:timezone":"Asia/Tokyo",
    "iso:country":"JP",
    "name:jpn_x_preferred":[
        "\u6d5c\u7530"
    ],
    "wof:name":"Hamada",
    "wof:placetype":"locality"
},
  "geometry": {"coordinates":[130.96799999999999,30.44489],"type":"Point"}
}