{
  "type": "Feature",
  "properties": {
    "gn:admin1_code":"7.0",
    "gn:admin2_code":"1859874.0",
    "gn:admin3_code":"40342.0",
    "gn:asciiname":"Futasegawa",
    "gn:country_code":"JP",
    "gn:dem":147,
    "gn:feature_class":"P",
    "gn:feature_code":"PPLL",
    "gn:name":"Futasegawa",
    "gn:population":0,
    "gn:timezone":"Asia/Tokyo",
    "iso:country":"JP",
    "name:jpn_x_preferred":[
        "\u4e8c\u702c\u5ddd"
    ],
    "wof:name":"Futasegawa",
    "wof:placetype":"locality"
},
  "geometry": {"coordinates":[130.58056999999999,33.619],"type":"Point"}
}