{
  "type": "Feature",
  "properties": {
    "iso:country":"JP",
    "name:eng_x_preferred":[
        "Honkawacho 3 Chome"
    ],
    "name:eng_x_variant":[
        "Honkawachou 3 Choume",
        "Honkawacho 3 Chome"
    ],
    "name:jpn_x_preferred":[
        "\uff13\u4e01\u76ee"
    ],
    "name:jpn_x_variant":[
        "\u307b\u3093\u304b\u308f\u3061\u3087\u3046 \uff13\u3061\u3087\u3046\u3081",
        "\u672c\u5ddd\u753a \uff13\u4e01\u76ee",
        "\uff13\u3061\u3087\u3046\u3081"
    ],
    "name:unk_x_variant":[
        "\uff13\u4e01\u76ee"
    ],
    "qs:gn_adm0_cc":"JP",
    "qs:gn_local":1862415,
    "qs:gn_nam_loc":"\u5e83\u5cf6\u5e02, \u5e83\u5cf6\u770c, JP",
    "qs:gn_namadm1":"11",
    "qs:local_max":2245,
    "qs:local_sum":19695,
    "qs:localhoods":32,
    "qs:name":"\uff13\u4e01\u76ee",
    "qs:name_adm0":"\u65e5\u672c",
    "qs:name_adm1":"\u5e83\u5cf6\u770c",
    "qs:name_adm2":"\u4e2d\u533a",
    "qs:name_en":"Honkawacho 3 Chome",
    "qs:name_lau":"\u672c\u5ddd\u753a",
    "qs:name_local":"\u5e83\u5cf6\u5e02",
    "qs:photo_max":200,
    "qs:photo_sum":1676,
    "qs:placetype":"Suburb",
    "qs:quad_count":39,
    "qs:woe_adm0":23424856,
    "qs:woe_adm1":2345861,
    "qs:woe_adm2":15015430,
    "qs:woe_lau":28473769,
    "qs:woe_local":1117227,
    "qs:woe_ver":"7.10.0",
    "wof:lang":[
        "jpn"
    ],
    "wof:name":"\uff13\u4e01\u76ee",
    "wof:placetype":"neighbourhood"
},
  "geometry": {"coordinates":[132.45437699999999,34.398652],"type":"Point"}
}