{
  "type": "Feature",
  "properties": {
    "gn:admin1_code":"3.0",
    "gn:admin2_code":"2130056.0",
    "gn:asciiname":"Zao",
    "gn:country_code":"JP",
    "gn:dem":66,
    "gn:feature_class":"P",
    "gn:feature_code":"PPL",
    "gn:name":"Za\u014d",
    "gn:population":0,
    "gn:timezone":"Asia/Tokyo",
    "iso:country":"JP",
    "name:jpn_x_preferred":[
        "\u8535\u738b"
    ],
    "name:jpn_x_variant":[
        "\u3056\u304a\u3046",
        "\u30b6\u30aa\u30a6"
    ],
    "name:und_x_variant":[
        "Za\u014d"
    ],
    "wof:name":"Zao",
    "wof:placetype":"locality"
},
  "geometry": {"coordinates":[140.39636000000002,40.61035],"type":"Point"}
}