{
  "type": "Feature",
  "properties": {
    "gn:admin1_code":"28",
    "gn:admin2_code":"1863590.0",
    "gn:asciiname":"Noharanaka",
    "gn:country_code":"JP",
    "gn:dem":113,
    "gn:feature_class":"P",
    "gn:feature_code":"PPL",
    "gn:name":"Noharanaka",
    "gn:population":0,
    "gn:timezone":"Asia/Tokyo",
    "iso:country":"JP",
    "name:jpn_x_preferred":[
        "\u91ce\u539f\u4e2d"
    ],
    "name:und_x_variant":[
        "Nowara",
        "Nohara",
        "Noharanaka"
    ],
    "wof:name":"Noharanaka",
    "wof:placetype":"locality"
},
  "geometry": {"coordinates":[135.7073,34.34382],"type":"Point"}
}