{
  "type": "Feature",
  "properties": {
    "gn:admin1_code":"33.0",
    "gn:admin2_code":"7391357.0",
    "gn:asciiname":"Chiyodacho-amarie",
    "gn:country_code":"JP",
    "gn:dem":2,
    "gn:feature_class":"P",
    "gn:feature_code":"PPL",
    "gn:name":"Chiyodach\u014d-amarie",
    "gn:population":0,
    "gn:timezone":"Asia/Tokyo",
    "iso:country":"JP",
    "name:jpn_x_preferred":[
        "\u5343\u4ee3\u7530\u753a\u9918\u6c5f"
    ],
    "name:und_x_variant":[
        "Chiyodach\u014d-amarie"
    ],
    "wof:name":"Chiyodacho-amarie",
    "wof:placetype":"locality"
},
  "geometry": {"coordinates":[130.36321999999998,33.25947],"type":"Point"}
}