{
  "type": "Feature",
  "properties": {
    "iso:country":"JP",
    "name:eng_x_preferred":[
        "Minamijuyojonishi 5 Chome"
    ],
    "name:eng_x_variant":[
        "Minamijuuyojounishi 5 Choume",
        "Minamijuyojonishi 5 Chome"
    ],
    "name:jpn_x_preferred":[
        "\uff15\u4e01\u76ee"
    ],
    "name:jpn_x_variant":[
        "\u307f\u306a\u307f\u3058\u3085\u3046\u3088\u3058\u3087\u3046\u306b\u3057 \uff15\u3061\u3087\u3046\u3081",
        "\u5357\u5341\u56db\u6761\u897f \uff15\u4e01\u76ee",
        "\uff15\u3061\u3087\u3046\u3081"
    ],
    "qs:gn_local":0,
    "qs:local_max":2554,
    "qs:local_sum":22076,
    "qs:localhoods":97,
    "qs:name":"\uff15\u4e01\u76ee",
    "qs:name_adm0":"\u65e5\u672c",
    "qs:name_adm1":"\u5317\u6d77\u9053",
    "qs:name_adm2":"\u4e2d\u592e\u533a",
    "qs:name_en":"Minamijuyojonishi 5 Chome",
    "qs:name_lau":"\u5357\u5341\u56db\u6761\u897f",
    "qs:name_local":"\u672d\u5e4c\u5e02",
    "qs:photo_max":8,
    "qs:photo_sum":15,
    "qs:placetype":"Suburb",
    "qs:quad_count":3,
    "qs:woe_adm0":23424856,
    "qs:woe_adm1":7153351,
    "qs:woe_adm2":15015394,
    "qs:woe_lau":28379467,
    "qs:woe_local":1118108,
    "qs:woe_ver":"7.10.0",
    "wof:lang":[
        "jpn"
    ],
    "wof:name":"\uff15\u4e01\u76ee",
    "wof:placetype":"neighbourhood"
},
  "geometry": {"coordinates":[141.35538500000001,43.041943],"type":"Point"}
}