{
  "type": "Feature",
  "properties": {
    "gn:admin1_code":"12.0",
    "gn:admin2_code":"2129373.0",
    "gn:admin3_code":"1661.0",
    "gn:asciiname":"Mutsumi",
    "gn:country_code":"JP",
    "gn:dem":4,
    "gn:feature_class":"P",
    "gn:feature_code":"PPL",
    "gn:name":"Mutsumi",
    "gn:population":0,
    "gn:timezone":"Asia/Tokyo",
    "iso:country":"JP",
    "name:jpn_x_preferred":[
        "\u7766"
    ],
    "name:jpn_x_variant":[
        "\u3080\u3064\u307f",
        "\u30e0\u30c4\u30df"
    ],
    "name:pol_x_preferred":[
        "Mutsumi"
    ],
    "name:slk_x_preferred":[
        "Mutsumi"
    ],
    "wof:name":"Mutsumi",
    "wof:placetype":"locality"
},
  "geometry": {"coordinates":[144.41369,43.01194],"type":"Point"}
}