{
  "type": "Feature",
  "properties": {
    "gn:admin1_code":"22.0",
    "gn:admin2_code":"1860951.0",
    "gn:asciiname":"Joyo",
    "gn:country_code":"JP",
    "gn:dem":88,
    "gn:feature_class":"P",
    "gn:feature_code":"PPLA2",
    "gn:name":"J\u014dy\u014d",
    "gn:population":0,
    "gn:timezone":"Asia/Tokyo",
    "iso:country":"JP",
    "name:jpn_x_preferred":[
        "\u57ce\u967d"
    ],
    "name:spa_x_preferred":[
        "Joyo"
    ],
    "wof:name":"Joyo",
    "wof:placetype":"locality"
},
  "geometry": {"coordinates":[135.80561,34.84396],"type":"Point"}
}