{
  "type": "Feature",
  "properties": {
    "iso:country":"JP",
    "name:eng_x_preferred":[
        "Engyo 1 Chome"
    ],
    "name:eng_x_variant":[
        "Engyou 1 Choume",
        "Engyo 1 Chome"
    ],
    "name:jpn_x_preferred":[
        "\uff11\u4e01\u76ee"
    ],
    "name:jpn_x_variant":[
        "\u3048\u3093\u304e\u3087\u3046 \uff11\u3061\u3087\u3046\u3081",
        "\u5186\u884c \uff11\u4e01\u76ee",
        "\uff11\u3061\u3087\u3046\u3081"
    ],
    "qs:gn_local":0,
    "qs:local_max":3043,
    "qs:local_sum":11012,
    "qs:localhoods":21,
    "qs:name":"\uff11\u4e01\u76ee",
    "qs:name_adm0":"\u65e5\u672c",
    "qs:name_adm1":"\u795e\u5948\u5ddd\u770c",
    "qs:name_en":"Engyo 1 Chome",
    "qs:name_lau":"\u5186\u884c",
    "qs:name_local":"\u85e4\u6ca2\u5e02",
    "qs:photo_max":6,
    "qs:photo_sum":10,
    "qs:placetype":"Suburb",
    "qs:quad_count":3,
    "qs:woe_adm0":23424856,
    "qs:woe_adm1":2345868,
    "qs:woe_adm2":0,
    "qs:woe_lau":28416769,
    "qs:woe_local":1117087,
    "qs:woe_ver":"7.10.0",
    "wof:lang":[
        "jpn"
    ],
    "wof:name":"\uff11\u4e01\u76ee",
    "wof:placetype":"neighbourhood"
},
  "geometry": {"coordinates":[139.45670799999999,35.386404],"type":"Point"}
}