{
  "type": "Feature",
  "properties": {
    "gn:admin1_code":"21",
    "gn:admin2_code":"1865358.0",
    "gn:asciiname":"Nishikone",
    "gn:country_code":"JP",
    "gn:dem":26,
    "gn:feature_class":"P",
    "gn:feature_code":"PPL",
    "gn:name":"Nishik\u014dne",
    "gn:population":0,
    "gn:timezone":"Asia/Tokyo",
    "iso:country":"JP",
    "name:jpn_x_preferred":[
        "\u897f\u9ad8\u6839"
    ],
    "name:jpn_x_variant":[
        "\u306b\u3057\u3053\u3046\u306d",
        "\u30cb\u30b7\u30b3\u30a6\u30cd"
    ],
    "name:und_x_variant":[
        "Nishi-g\u014dne",
        "Nishik\u014dne"
    ],
    "wof:name":"Nishikone",
    "wof:placetype":"locality"
},
  "geometry": {"coordinates":[130.14014,32.31117],"type":"Point"}
}