{
  "type": "Feature",
  "properties": {
    "gn:admin1_code":"12.0",
    "gn:admin2_code":"7428100.0",
    "gn:admin3_code":"1691.0",
    "gn:asciiname":"Odaito",
    "gn:cc2":"JP",
    "gn:country_code":"JP",
    "gn:dem":4,
    "gn:feature_class":"P",
    "gn:feature_code":"PPL",
    "gn:name":"Odait\u014d",
    "gn:population":0,
    "gn:timezone":"Asia/Tokyo",
    "iso:country":"JP",
    "name:und_x_variant":[
        "Odaitou",
        "Radaitou"
    ],
    "wof:name":"Odaito",
    "wof:placetype":"locality"
},
  "geometry": {"coordinates":[145.21883,43.57144],"type":"Point"}
}