{
  "type": "Feature",
  "properties": {
    "gn:admin1_code":"21.0",
    "gn:admin2_code":"7413150.0",
    "gn:asciiname":"Teramura",
    "gn:country_code":"JP",
    "gn:dem":27,
    "gn:feature_class":"P",
    "gn:feature_code":"PPLL",
    "gn:name":"Teramura",
    "gn:population":0,
    "gn:timezone":"Asia/Tokyo",
    "iso:country":"JP",
    "name:jpn_x_preferred":[
        "\u5bfa\u6751"
    ],
    "name:jpn_x_variant":[
        "\u3066\u3089\u3080\u3089",
        "\u30c6\u30e9\u30e0\u30e9"
    ],
    "wof:name":"Teramura",
    "wof:placetype":"locality"
},
  "geometry": {"coordinates":[130.7414,32.97873],"type":"Point"}
}