{
  "type": "Feature",
  "properties": {
    "gn:admin1_code":"19.0",
    "gn:admin2_code":"1848308.0",
    "gn:asciiname":"Tsukui-sanchome",
    "gn:country_code":"JP",
    "gn:dem":16,
    "gn:feature_class":"P",
    "gn:feature_code":"PPLL",
    "gn:name":"Tsukui-sanch\u014dme",
    "gn:population":0,
    "gn:timezone":"Asia/Tokyo",
    "iso:country":"JP",
    "name:jpn_x_preferred":[
        "\u6d25\u4e45\u4e95\u4e09\u4e01\u76ee"
    ],
    "name:jpn_x_variant":[
        "\u3064\u304f\u3044\u3055\u3093\u3061\u3087\u3046\u3081",
        "\u30c4\u30af\u30a4\u30b5\u30f3\u30c1\u30e7\u30a6\u30e1"
    ],
    "name:und_x_variant":[
        "Tsukui-sanch\u014dme"
    ],
    "wof:name":"Tsukui-sanchome",
    "wof:placetype":"locality"
},
  "geometry": {"coordinates":[139.66476,35.20307000000001],"type":"Point"}
}