{
  "type": "Feature",
  "properties": {
    "gn:admin1_code":"47",
    "gn:admin2_code":"7415820.0",
    "gn:asciiname":"Miibaru",
    "gn:country_code":"JP",
    "gn:dem":27,
    "gn:feature_class":"P",
    "gn:feature_code":"PPLL",
    "gn:name":"Miibaru",
    "gn:population":0,
    "gn:timezone":"Asia/Tokyo",
    "iso:country":"JP",
    "name:jpn_x_preferred":[
        "\u65b0\u539f"
    ],
    "name:jpn_x_variant":[
        "\u307f\u3044\u3070\u308b"
    ],
    "name:und_x_variant":[
        "Shimbaru"
    ],
    "wof:name":"Miibaru",
    "wof:placetype":"locality"
},
  "geometry": {"coordinates":[127.78897000000001,26.13504],"type":"Point"}
}