{
  "type": "Feature",
  "properties": {
    "gn:admin1_code":"24.0",
    "gn:admin2_code":"2111147.0",
    "gn:admin3_code":"4104.0",
    "gn:asciiname":"Kita-akaishi",
    "gn:cc2":"JP",
    "gn:country_code":"JP",
    "gn:dem":112,
    "gn:feature_class":"P",
    "gn:feature_code":"PPL",
    "gn:name":"Kita-akaishi",
    "gn:population":0,
    "gn:timezone":"Asia/Tokyo",
    "iso:country":"JP",
    "name:und_x_variant":[
        "Akaishi",
        "Kita-akaishi"
    ],
    "wof:name":"Kita-akaishi",
    "wof:placetype":"locality"
},
  "geometry": {"coordinates":[140.75306,38.20972],"type":"Point"}
}