{
  "type": "Feature",
  "properties": {
    "gn:admin1_code":"3.0",
    "gn:admin2_code":"2130225.0",
    "gn:asciiname":"Wakimoto",
    "gn:country_code":"JP",
    "gn:dem":19,
    "gn:feature_class":"P",
    "gn:feature_code":"PPL",
    "gn:name":"Wakimoto",
    "gn:population":0,
    "gn:timezone":"Asia/Tokyo",
    "iso:country":"JP",
    "name:jpn_x_preferred":[
        "\u8107\u5143"
    ],
    "name:jpn_x_variant":[
        "\u308f\u304d\u3082\u3068",
        "\u30ef\u30ad\u30e2\u30c8"
    ],
    "wof:name":"Wakimoto",
    "wof:placetype":"locality"
},
  "geometry": {"coordinates":[140.32538,41.09103],"type":"Point"}
}