{
  "type": "Feature",
  "properties": {
    "gn:admin1_code":"18.0",
    "gn:admin2_code":"7383991.0",
    "gn:asciiname":"Okuchi-shimotono",
    "gn:country_code":"JP",
    "gn:dem":168,
    "gn:feature_class":"P",
    "gn:feature_code":"PPL",
    "gn:name":"\u014ckuchi-shimotono",
    "gn:population":0,
    "gn:timezone":"Asia/Tokyo",
    "iso:country":"JP",
    "name:jpn_x_preferred":[
        "\u5927\u53e3\u4e0b\u6bbf"
    ],
    "name:jpn_x_variant":[
        "\u304a\u304a\u304f\u3061\u3057\u3082\u3068\u306e",
        "\u30aa\u30aa\u30af\u30c1\u30b7\u30e2\u30c8\u30ce"
    ],
    "name:und_x_variant":[
        "\u014ckuchi-shimotono"
    ],
    "wof:name":"Okuchi-shimotono",
    "wof:placetype":"locality"
},
  "geometry": {"coordinates":[130.59153999999998,32.03422],"type":"Point"}
}