{
  "type": "Feature",
  "properties": {
    "gn:admin1_code":"2.0",
    "gn:admin2_code":"2113122.0",
    "gn:asciiname":"Hamanashiyama",
    "gn:country_code":"JP",
    "gn:dem":7,
    "gn:feature_class":"P",
    "gn:feature_code":"PPL",
    "gn:name":"Hamanashiyama",
    "gn:population":0,
    "gn:timezone":"Asia/Tokyo",
    "iso:country":"JP",
    "name:jpn_x_preferred":[
        "\u6d5c\u30ca\u30b7\u5c71"
    ],
    "name:jpn_x_variant":[
        "\u306f\u307e\u306a\u3057\u3084\u307e",
        "\u30cf\u30de\u30ca\u30b7\u30e4\u30de"
    ],
    "wof:name":"Hamanashiyama",
    "wof:placetype":"locality"
},
  "geometry": {"coordinates":[140.06124,39.76429],"type":"Point"}
}