{
  "type": "Feature",
  "properties": {
    "gn:admin1_code":"22.0",
    "gn:admin2_code":"7412210.0",
    "gn:asciiname":"Matsui",
    "gn:country_code":"JP",
    "gn:dem":19,
    "gn:feature_class":"P",
    "gn:feature_code":"PPL",
    "gn:name":"Matsui",
    "gn:population":0,
    "gn:timezone":"Asia/Tokyo",
    "iso:country":"JP",
    "name:jpn_x_preferred":[
        "\u677e\u4e95"
    ],
    "name:lav_x_preferred":[
        "Macui"
    ],
    "name:por_x_preferred":[
        "Matsui"
    ],
    "wof:name":"Matsui",
    "wof:placetype":"locality"
},
  "geometry": {"coordinates":[135.73432,34.84587],"type":"Point"}
}