{
  "type": "Feature",
  "properties": {
    "iso:country":"JP",
    "name:eng_x_preferred":[
        "Kanocho 1 Chome"
    ],
    "name:eng_x_variant":[
        "Kanouchou 1 Choume",
        "Kanocho 1 Chome"
    ],
    "name:jpn_x_preferred":[
        "\uff11\u4e01\u76ee"
    ],
    "name:jpn_x_variant":[
        "\u304b\u306e\u3046\u3061\u3087\u3046 \uff11\u3061\u3087\u3046\u3081",
        "\u52a0\u7d0d\u753a \uff11\u4e01\u76ee",
        "\uff11\u3061\u3087\u3046\u3081"
    ],
    "name:unk_x_variant":[
        "\uff11\u4e01\u76ee"
    ],
    "qs:gn_local":0,
    "qs:local_max":2400,
    "qs:local_sum":22318,
    "qs:localhoods":72,
    "qs:name":"\uff11\u4e01\u76ee",
    "qs:name_adm0":"\u65e5\u672c",
    "qs:name_adm1":"\u5175\u5eab\u770c",
    "qs:name_adm2":"\u4e2d\u592e\u533a",
    "qs:name_en":"Kanocho 1 Chome",
    "qs:name_lau":"\u52a0\u7d0d\u753a",
    "qs:name_local":"\u795e\u6238\u5e02",
    "qs:photo_max":101,
    "qs:photo_sum":307,
    "qs:placetype":"Suburb",
    "qs:quad_count":10,
    "qs:woe_adm0":23424856,
    "qs:woe_adm1":2345862,
    "qs:woe_adm2":15015438,
    "qs:woe_lau":28461172,
    "qs:woe_local":1117545,
    "qs:woe_ver":"7.10.0",
    "wof:lang":[
        "jpn"
    ],
    "wof:name":"\uff11\u4e01\u76ee",
    "wof:placetype":"neighbourhood"
},
  "geometry": {"coordinates":[135.19527099999999,34.705129],"type":"Point"}
}