{
  "type": "Feature",
  "properties": {
    "gn:admin1_code":"16.0",
    "gn:admin2_code":"2128940.0",
    "gn:asciiname":"Ninohe",
    "gn:country_code":"JP",
    "gn:dem":261,
    "gn:feature_class":"P",
    "gn:feature_code":"PPLA2",
    "gn:name":"Ninohe",
    "gn:population":0,
    "gn:timezone":"Asia/Tokyo",
    "iso:country":"JP",
    "name:ara_x_preferred":[
        "\u0646\u064a\u0646\u0648\u0647\u064a"
    ],
    "name:azb_x_preferred":[
        "\u0646\u06cc\u0646\u0648\u0647\u0647"
    ],
    "name:ceb_x_preferred":[
        "Ninohe"
    ],
    "name:deu_x_preferred":[
        "Ninohe"
    ],
    "name:epo_x_preferred":[
        "Ninohe"
    ],
    "name:fas_x_preferred":[
        "\u0646\u06cc\u0646\u0648\u0647\u0647"
    ],
    "name:fin_x_preferred":[
        "Ninohe"
    ],
    "name:fra_x_preferred":[
        "Ninohe"
    ],
    "name:glg_x_preferred":[
        "Ninohe"
    ],
    "name:ita_x_preferred":[
        "Ninohe"
    ],
    "name:jpn_x_preferred":[
        "\u4e8c\u6238"
    ],
    "name:jpn_x_variant":[
        "\u4e8c\u6238\u5e02"
    ],
    "name:kor_x_preferred":[
        "\ub2c8\ub178\ud5e4\uc2dc"
    ],
    "name:lit_x_preferred":[
        "Ninoh\u0117"
    ],
    "name:mzn_x_preferred":[
        "\u0646\u06cc\u0646\u0648\u0647\u0647"
    ],
    "name:nld_x_preferred":[
        "Ninohe"
    ],
    "name:pol_x_preferred":[
        "Ninohe"
    ],
    "name:por_x_preferred":[
        "Ninohe"
    ],
    "name:ron_x_preferred":[
        "Ninohe"
    ],
    "name:rus_x_preferred":[
        "\u041d\u0438\u043d\u043e\u0445\u0435"
    ],
    "name:swe_x_preferred":[
        "Ninohe"
    ],
    "name:tgk_x_preferred":[
        "\u041d\u0438\u043d\u043e\u04b3\u0435"
    ],
    "name:tgl_x_preferred":[
        "Ninohe"
    ],
    "name:tum_x_preferred":[
        "Ninohe"
    ],
    "name:tur_x_preferred":[
        "Ninohe"
    ],
    "name:ukr_x_preferred":[
        "\u041d\u0456\u043d\u043e\u0445\u0435"
    ],
    "name:vie_x_preferred":[
        "Ninohe"
    ],
    "name:war_x_preferred":[
        "Ninohe"
    ],
    "name:zho_x_preferred":[
        "\u4e8c\u6236\u5e02"
    ],
    "wof:name":"Ninohe",
    "wof:placetype":"locality"
},
  "geometry": {"coordinates":[141.31333999999995,40.29081],"type":"Point"}
}