{
  "type": "Feature",
  "properties": {
    "gn:admin1_code":"16.0",
    "gn:admin2_code":"2128940.0",
    "gn:asciiname":"Ninohe",
    "gn:country_code":"JP",
    "gn:dem":261,
    "gn:feature_class":"P",
    "gn:feature_code":"PPLA2",
    "gn:name":"Ninohe",
    "gn:population":0,
    "gn:timezone":"Asia/Tokyo",
    "iso:country":"JP",
    "name:jpn_x_preferred":[
        "\u4e8c\u6238"
    ],
    "wof:name":"Ninohe",
    "wof:placetype":"locality"
},
  "geometry": {"coordinates":[141.31333999999995,40.29081],"type":"Point"}
}