{
  "type": "Feature",
  "properties": {
    "gn:admin1_code":"3.0",
    "gn:admin2_code":"2127674.0",
    "gn:asciiname":"Shinden",
    "gn:country_code":"JP",
    "gn:dem":86,
    "gn:feature_class":"P",
    "gn:feature_code":"PPL",
    "gn:name":"Shinden",
    "gn:population":0,
    "gn:timezone":"Asia/Tokyo",
    "iso:country":"JP",
    "name:deu_x_preferred":[
        "Shinden"
    ],
    "name:jpn_x_preferred":[
        "\u65b0\u7530"
    ],
    "name:jpn_x_variant":[
        "\u3057\u3093\u3067\u3093",
        "\u30b7\u30f3\u30c7\u30f3"
    ],
    "wof:name":"Shinden",
    "wof:placetype":"locality"
},
  "geometry": {"coordinates":[141.11726999999999,40.59277],"type":"Point"}
}