{
  "type": "Feature",
  "properties": {
    "gn:admin1_code":"32.0",
    "gn:admin2_code":"1850033.0",
    "gn:asciiname":"Teraikedai",
    "gn:country_code":"JP",
    "gn:dem":123,
    "gn:feature_class":"P",
    "gn:feature_code":"PPL",
    "gn:name":"Teraikedai",
    "gn:population":0,
    "gn:timezone":"Asia/Tokyo",
    "iso:country":"JP",
    "name:jpn_x_preferred":[
        "\u5bfa\u6c60\u53f0"
    ],
    "wof:name":"Teraikedai",
    "wof:placetype":"locality"
},
  "geometry": {"coordinates":[135.56707,34.49168],"type":"Point"}
}