{
  "type": "Feature",
  "properties": {
    "gn:admin1_code":"21.0",
    "gn:admin2_code":"1848441.0",
    "gn:asciiname":"Tsuji",
    "gn:country_code":"JP",
    "gn:dem":378,
    "gn:feature_class":"P",
    "gn:feature_code":"PPLL",
    "gn:name":"Tsuji",
    "gn:population":0,
    "gn:timezone":"Asia/Tokyo",
    "iso:country":"JP",
    "name:jpn_x_preferred":[
        "\u8fbb"
    ],
    "name:jpn_x_variant":[
        "\u3064\u3058",
        "\u30c4\u30b8"
    ],
    "wof:name":"Tsuji",
    "wof:placetype":"locality"
},
  "geometry": {"coordinates":[130.70386999999999,32.43339],"type":"Point"}
}