{
  "type": "Feature",
  "properties": {
    "gn:admin1_code":"2.0",
    "gn:admin2_code":"2113122.0",
    "gn:asciiname":"Kurinokidai",
    "gn:country_code":"JP",
    "gn:dem":82,
    "gn:feature_class":"P",
    "gn:feature_code":"PPL",
    "gn:name":"Kurinokidai",
    "gn:population":0,
    "gn:timezone":"Asia/Tokyo",
    "iso:country":"JP",
    "name:jpn_x_preferred":[
        "\u6817\u30ce\u6728\u53f0"
    ],
    "name:jpn_x_variant":[
        "\u304f\u308a\u306e\u304d\u3060\u3044",
        "\u30af\u30ea\u30ce\u30ad\u30c0\u30a4"
    ],
    "wof:name":"Kurinokidai",
    "wof:placetype":"locality"
},
  "geometry": {"coordinates":[140.21249,39.75353],"type":"Point"}
}