{
  "type": "Feature",
  "properties": {
    "gn:admin1_code":"2.0",
    "gn:admin2_code":"2128783.0",
    "gn:asciiname":"Akadatecho",
    "gn:country_code":"JP",
    "gn:dem":75,
    "gn:feature_class":"P",
    "gn:feature_code":"PPL",
    "gn:name":"Akadatech\u014d",
    "gn:population":0,
    "gn:timezone":"Asia/Tokyo",
    "iso:country":"JP",
    "name:jpn_x_preferred":[
        "\u8d64\u9928\u753a"
    ],
    "name:jpn_x_variant":[
        "\u3042\u304b\u3060\u3066\u3061\u3087\u3046",
        "\u30a2\u30ab\u30c0\u30c6\u30c1\u30e7\u30a6"
    ],
    "name:und_x_variant":[
        "Akadatech\u014d"
    ],
    "wof:name":"Akadatecho",
    "wof:placetype":"locality"
},
  "geometry": {"coordinates":[140.57037,40.27056],"type":"Point"}
}