{
  "type": "Feature",
  "properties": {
    "gn:admin1_code":"45",
    "gn:admin2_code":"1861209.0",
    "gn:asciiname":"Hirose",
    "gn:country_code":"JP",
    "gn:dem":225,
    "gn:feature_class":"P",
    "gn:feature_code":"PPL",
    "gn:name":"Hirose",
    "gn:population":0,
    "gn:timezone":"Asia/Tokyo",
    "iso:country":"JP",
    "wof:name":"Hirose",
    "wof:placetype":"locality"
},
  "geometry": {"coordinates":[131.94999999999999,34.26667],"type":"Point"}
}