{
  "type": "Feature",
  "properties": {
    "gn:admin1_code":"9.0",
    "gn:admin2_code":"7419032.0",
    "gn:asciiname":"Kamiokacho-wariishi",
    "gn:country_code":"JP",
    "gn:dem":390,
    "gn:feature_class":"P",
    "gn:feature_code":"PPL",
    "gn:name":"Kamiokach\u014d-wariishi",
    "gn:population":0,
    "gn:timezone":"Asia/Tokyo",
    "iso:country":"JP",
    "name:jpn_x_preferred":[
        "\u795e\u5ca1\u753a\u5272\u77f3"
    ],
    "name:und_x_variant":[
        "Kamiokach\u014d-wariishi"
    ],
    "wof:name":"Kamiokacho-wariishi",
    "wof:placetype":"locality"
},
  "geometry": {"coordinates":[137.28342000000001,36.36678],"type":"Point"}
}