{
  "type": "Feature",
  "properties": {
    "gn:admin1_code":"45",
    "gn:admin2_code":"1861209.0",
    "gn:asciiname":"Yumachi",
    "gn:country_code":"JP",
    "gn:dem":50,
    "gn:feature_class":"P",
    "gn:feature_code":"PPL",
    "gn:name":"Y\u016bmachi",
    "gn:population":0,
    "gn:timezone":"Asia/Tokyo",
    "iso:country":"JP",
    "name:jpn_x_preferred":[
        "\u7531\u5b87\u753a"
    ],
    "name:und_x_variant":[
        "Yuu",
        "Y\u016b",
        "Y\u016bmachi"
    ],
    "wof:name":"Yumachi",
    "wof:placetype":"locality"
},
  "geometry": {"coordinates":[132.1748,34.03219],"type":"Point"}
}