{
  "type": "Feature",
  "properties": {
    "iso:country":"JP",
    "name:eng_x_preferred":[
        "Yamashitatori 5 Chome"
    ],
    "name:eng_x_variant":[
        "Yamashitatoori 5 Choume",
        "Yamashitatori 5 Chome"
    ],
    "name:jpn_x_preferred":[
        "\uff15\u4e01\u76ee"
    ],
    "name:jpn_x_variant":[
        "\u3084\u307e\u3057\u305f\u3068\u304a\u308a \uff15\u3061\u3087\u3046\u3081",
        "\u5c71\u4e0b\u901a \uff15\u4e01\u76ee",
        "\uff15\u3061\u3087\u3046\u3081"
    ],
    "name:unk_x_variant":[
        "\uff15\u4e01\u76ee"
    ],
    "qs:gn_local":0,
    "qs:local_max":3194,
    "qs:local_sum":30209,
    "qs:localhoods":92,
    "qs:name":"\uff15\u4e01\u76ee",
    "qs:name_adm0":"\u65e5\u672c",
    "qs:name_adm1":"\u611b\u77e5\u770c",
    "qs:name_adm2":"\u745e\u7a42\u533a",
    "qs:name_en":"Yamashitatori 5 Chome",
    "qs:name_lau":"\u5c71\u4e0b\u901a",
    "qs:name_local":"\u540d\u53e4\u5c4b\u5e02",
    "qs:photo_max":75,
    "qs:photo_sum":131,
    "qs:placetype":"Suburb",
    "qs:quad_count":8,
    "qs:woe_adm0":23424856,
    "qs:woe_adm1":2345851,
    "qs:woe_adm2":15015444,
    "qs:woe_lau":28439598,
    "qs:woe_local":1117817,
    "qs:woe_ver":"7.10.0",
    "wof:lang":[
        "jpn"
    ],
    "wof:name":"\uff15\u4e01\u76ee",
    "wof:placetype":"neighbourhood"
},
  "geometry": {"coordinates":[136.94375500000001,35.123796],"type":"Point"}
}