{
  "type": "Feature",
  "properties": {
    "gn:admin1_code":"12.0",
    "gn:admin2_code":"2130058.0",
    "gn:admin3_code":"1641.0",
    "gn:asciiname":"Oda",
    "gn:cc2":"JP",
    "gn:country_code":"JP",
    "gn:dem":144,
    "gn:feature_class":"P",
    "gn:feature_code":"PPL",
    "gn:name":"Oda",
    "gn:population":0,
    "gn:timezone":"Asia/Tokyo",
    "iso:country":"JP",
    "name:jpn_x_preferred":[
        "\u5c3e\u7530"
    ],
    "name:und_x_variant":[
        "Odamura",
        "Oda"
    ],
    "wof:name":"Oda",
    "wof:placetype":"locality"
},
  "geometry": {"coordinates":[143.18722,42.53528],"type":"Point"}
}