{
  "type": "Feature",
  "properties": {
    "gn:admin1_code":"37.0",
    "gn:admin2_code":"1856971.0",
    "gn:asciiname":"Daiba",
    "gn:country_code":"JP",
    "gn:dem":14,
    "gn:feature_class":"P",
    "gn:feature_code":"PPL",
    "gn:name":"Daiba",
    "gn:population":0,
    "gn:timezone":"Asia/Tokyo",
    "iso:country":"JP",
    "name:jpn_x_preferred":[
        "\u5927\u5834"
    ],
    "wof:name":"Daiba",
    "wof:placetype":"locality"
},
  "geometry": {"coordinates":[138.94141000000002,35.0933],"type":"Point"}
}