{
  "type": "Feature",
  "properties": {
    "gn:admin1_code":"8.0",
    "gn:admin2_code":"2112921.0",
    "gn:asciiname":"Takayu",
    "gn:country_code":"JP",
    "gn:dem":760,
    "gn:feature_class":"P",
    "gn:feature_code":"PPLL",
    "gn:name":"Takayu",
    "gn:population":0,
    "gn:timezone":"Asia/Tokyo",
    "iso:country":"JP",
    "name:jpn_x_preferred":[
        "\u9ad8\u6e6f"
    ],
    "wof:name":"Takayu",
    "wof:placetype":"locality"
},
  "geometry": {"coordinates":[140.30674999999999,37.75013],"type":"Point"}
}