{
  "type": "Feature",
  "properties": {
    "gn:admin1_code":"35.0",
    "gn:admin2_code":"1858984.0",
    "gn:asciiname":"Higashide",
    "gn:country_code":"JP",
    "gn:dem":290,
    "gn:feature_class":"P",
    "gn:feature_code":"PPLL",
    "gn:name":"Higashide",
    "gn:population":0,
    "gn:timezone":"Asia/Tokyo",
    "iso:country":"JP",
    "name:jpn_x_preferred":[
        "\u6771\u51fa"
    ],
    "wof:name":"Higashide",
    "wof:placetype":"locality"
},
  "geometry": {"coordinates":[136.06164999999999,34.87522],"type":"Point"}
}