{
  "type": "Feature",
  "properties": {
    "gn:admin1_code":"4.0",
    "gn:admin2_code":"2112557.0",
    "gn:admin3_code":"12441.0",
    "gn:asciiname":"Kozawamata",
    "gn:country_code":"JP",
    "gn:dem":151,
    "gn:feature_class":"P",
    "gn:feature_code":"PPL",
    "gn:name":"Kozawamata",
    "gn:population":0,
    "gn:timezone":"Asia/Tokyo",
    "iso:country":"JP",
    "name:jpn_x_preferred":[
        "\u5c0f\u6ca2\u53c8"
    ],
    "name:jpn_x_variant":[
        "\u3053\u3056\u308f\u307e\u305f",
        "\u30b3\u30b6\u30ef\u30de\u30bf"
    ],
    "wof:name":"Kozawamata",
    "wof:placetype":"locality"
},
  "geometry": {"coordinates":[140.17821000000001,35.22678],"type":"Point"}
}