{
  "type": "Feature",
  "properties": {
    "gn:admin1_code":"23.0",
    "gn:admin2_code":"7417704.0",
    "gn:admin3_code":"24443.0",
    "gn:asciiname":"Yakii",
    "gn:country_code":"JP",
    "gn:dem":98,
    "gn:feature_class":"P",
    "gn:feature_code":"PPL",
    "gn:name":"Yakii",
    "gn:population":0,
    "gn:timezone":"Asia/Tokyo",
    "iso:country":"JP",
    "name:jpn_x_preferred":[
        "\u5f25\u8d77\u4e95"
    ],
    "wof:name":"Yakii",
    "wof:placetype":"locality"
},
  "geometry": {"coordinates":[136.39696999999998,34.3914],"type":"Point"}
}