{
  "type": "Feature",
  "properties": {
    "gn:admin1_code":"21.0",
    "gn:admin2_code":"1850744.0",
    "gn:admin3_code":"43369.0",
    "gn:asciiname":"Motegi",
    "gn:country_code":"JP",
    "gn:dem":21,
    "gn:feature_class":"P",
    "gn:feature_code":"PPL",
    "gn:name":"Motegi",
    "gn:population":0,
    "gn:timezone":"Asia/Tokyo",
    "iso:country":"JP",
    "name:jpn_x_preferred":[
        "\u7528\u6728"
    ],
    "name:jpn_x_variant":[
        "\u3082\u3066\u304e",
        "\u30e2\u30c6\u30ae"
    ],
    "wof:name":"Motegi",
    "wof:placetype":"locality"
},
  "geometry": {"coordinates":[130.63137,32.96941],"type":"Point"}
}