{
  "type": "Feature",
  "properties": {
    "gn:admin1_code":"21.0",
    "gn:admin2_code":"1850743.0",
    "gn:asciiname":"Hinode",
    "gn:country_code":"JP",
    "gn:dem":45,
    "gn:feature_class":"P",
    "gn:feature_code":"PPLL",
    "gn:name":"Hinode",
    "gn:population":0,
    "gn:timezone":"Asia/Tokyo",
    "iso:country":"JP",
    "name:jpn_x_preferred":[
        "\u65e5\u30ce\u51fa"
    ],
    "name:jpn_x_variant":[
        "\u3072\u306e\u3067",
        "\u30d2\u30ce\u30c7"
    ],
    "wof:name":"Hinode",
    "wof:placetype":"locality"
},
  "geometry": {"coordinates":[130.58467999999999,32.91186],"type":"Point"}
}