{
  "type": "Feature",
  "properties": {
    "gn:admin1_code":"21.0",
    "gn:admin2_code":"7412708.0",
    "gn:admin3_code":"43511.0",
    "gn:asciiname":"Kuzunohae",
    "gn:country_code":"JP",
    "gn:dem":497,
    "gn:feature_class":"P",
    "gn:feature_code":"PPL",
    "gn:name":"Kuzunohae",
    "gn:population":0,
    "gn:timezone":"Asia/Tokyo",
    "iso:country":"JP",
    "name:jpn_x_preferred":[
        "\u845b\u306e\u516b\u91cd"
    ],
    "name:jpn_x_variant":[
        "\u304f\u305a\u306e\u306f\u3048",
        "\u30af\u30ba\u30ce\u30cf\u30a8"
    ],
    "wof:name":"Kuzunohae",
    "wof:placetype":"locality"
},
  "geometry": {"coordinates":[130.85747000000001,32.3645],"type":"Point"}
}