{
  "type": "Feature",
  "properties": {
    "gn:admin1_code":"37.0",
    "gn:admin2_code":"1851401.0",
    "gn:admin3_code":"22344.0",
    "gn:asciiname":"Shimo'ogoda",
    "gn:country_code":"JP",
    "gn:dem":394,
    "gn:feature_class":"P",
    "gn:feature_code":"PPLL",
    "gn:name":"Shimo\u2019\u014dgoda",
    "gn:population":0,
    "gn:timezone":"Asia/Tokyo",
    "iso:country":"JP",
    "name:jpn_x_preferred":[
        "\u4e0b\u5927\u80e1\u7530"
    ],
    "name:und_x_variant":[
        "Shimo\u2019\u014dgoda"
    ],
    "wof:name":"Shimo'ogoda",
    "wof:placetype":"locality"
},
  "geometry": {"coordinates":[138.96051,35.33526],"type":"Point"}
}