{
  "type": "Feature",
  "properties": {
    "gn:admin1_code":"43.0",
    "gn:admin2_code":"1861287.0",
    "gn:admin3_code":"30341.0",
    "gn:asciiname":"Shinden",
    "gn:country_code":"JP",
    "gn:dem":56,
    "gn:feature_class":"P",
    "gn:feature_code":"PPL",
    "gn:name":"Shinden",
    "gn:population":0,
    "gn:timezone":"Asia/Tokyo",
    "iso:country":"JP",
    "name:deu_x_preferred":[
        "Shinden"
    ],
    "name:jpn_x_preferred":[
        "\u65b0\u7530"
    ],
    "wof:name":"Shinden",
    "wof:placetype":"locality"
},
  "geometry": {"coordinates":[135.51282,34.29634],"type":"Point"}
}