{
  "type": "Feature",
  "properties": {
    "gn:admin1_code":"33.0",
    "gn:admin2_code":"1853274.0",
    "gn:asciiname":"Daiju",
    "gn:country_code":"JP",
    "gn:dem":-3,
    "gn:feature_class":"P",
    "gn:feature_code":"PPLL",
    "gn:name":"Daiju",
    "gn:population":0,
    "gn:timezone":"Asia/Tokyo",
    "iso:country":"JP",
    "name:jpn_x_preferred":[
        "\u5927\u6388"
    ],
    "wof:name":"Daiju",
    "wof:placetype":"locality"
},
  "geometry": {"coordinates":[130.26933,33.18658],"type":"Point"}
}