{
  "type": "Feature",
  "properties": {
    "iso:country":"JP",
    "name:eng_x_preferred":[
        "Nodamachi 3 Chome"
    ],
    "name:eng_x_variant":[
        "Nodamachi 3 Choume",
        "Nodamachi 3 Chome"
    ],
    "name:jpn_x_preferred":[
        "\uff13\u4e01\u76ee"
    ],
    "name:jpn_x_variant":[
        "\u306e\u3060\u307e\u3061 \uff13\u3061\u3087\u3046\u3081",
        "\u91ce\u7530\u753a \uff13\u4e01\u76ee",
        "\uff13\u3061\u3087\u3046\u3081"
    ],
    "name:unk_x_variant":[
        "\uff13\u4e01\u76ee"
    ],
    "qs:gn_local":0,
    "qs:local_max":253,
    "qs:local_sum":612,
    "qs:localhoods":5,
    "qs:name":"\uff13\u4e01\u76ee",
    "qs:name_adm0":"\u65e5\u672c",
    "qs:name_adm1":"\u798f\u5cf6\u770c",
    "qs:name_en":"Nodamachi 3 Chome",
    "qs:name_lau":"\u91ce\u7530\u753a",
    "qs:name_local":"\u798f\u5cf6\u5e02",
    "qs:photo_max":5,
    "qs:photo_sum":18,
    "qs:placetype":"Suburb",
    "qs:quad_count":6,
    "qs:woe_adm0":23424856,
    "qs:woe_adm1":2345858,
    "qs:woe_adm2":0,
    "qs:woe_lau":28398144,
    "qs:woe_local":1117103,
    "qs:woe_ver":"7.10.0",
    "wof:lang":[
        "jpn"
    ],
    "wof:name":"\uff13\u4e01\u76ee",
    "wof:placetype":"neighbourhood"
},
  "geometry": {"coordinates":[140.466309,37.763719],"type":"Point"}
}