{
  "type": "Feature",
  "properties": {
    "gn:admin1_code":"5.0",
    "gn:admin2_code":"10861187.0",
    "gn:asciiname":"Seiyo",
    "gn:country_code":"JP",
    "gn:dem":197,
    "gn:feature_class":"P",
    "gn:feature_code":"PPLA2",
    "gn:name":"Seiyo",
    "gn:population":0,
    "gn:timezone":"Asia/Tokyo",
    "iso:country":"JP",
    "name:jpn_x_preferred":[
        "\u897f\u4e88"
    ],
    "wof:name":"Seiyo",
    "wof:placetype":"locality"
},
  "geometry": {"coordinates":[132.63176000000001,33.38817],"type":"Point"}
}