{
  "type": "Feature",
  "properties": {
    "gn:admin1_code":"40",
    "gn:admin2_code":"1856786.0",
    "gn:admin3_code":"13381.0",
    "gn:asciiname":"Ako",
    "gn:country_code":"JP",
    "gn:dem":34,
    "gn:feature_class":"P",
    "gn:feature_code":"PPL",
    "gn:name":"Ako",
    "gn:population":0,
    "gn:timezone":"Asia/Tokyo",
    "iso:country":"JP",
    "name:ceb_x_preferred":[
        "Ako"
    ],
    "name:jpn_x_preferred":[
        "\u963f\u53e4"
    ],
    "name:swe_x_preferred":[
        "Ako"
    ],
    "wof:name":"Ako",
    "wof:placetype":"locality"
},
  "geometry": {"coordinates":[139.48341000000002,34.0718],"type":"Point"}
}