{
  "type": "Feature",
  "properties": {
    "gn:admin1_code":"7.0",
    "gn:admin2_code":"1859874.0",
    "gn:admin3_code":"40341.0",
    "gn:asciiname":"Shioji",
    "gn:country_code":"JP",
    "gn:dem":281,
    "gn:feature_class":"P",
    "gn:feature_code":"PPL",
    "gn:name":"Shi\u014dji",
    "gn:population":0,
    "gn:timezone":"Asia/Tokyo",
    "iso:country":"JP",
    "name:jpn_x_preferred":[
        "\u56db\u738b\u5bfa"
    ],
    "name:und_x_variant":[
        "Shi\u014dji"
    ],
    "wof:name":"Shioji",
    "wof:placetype":"locality"
},
  "geometry": {"coordinates":[130.52098999999998,33.53538],"type":"Point"}
}