{
  "type": "Feature",
  "properties": {
    "iso:country":"JP",
    "name:eng_x_preferred":[
        "Kishibeminami 1 Chome"
    ],
    "name:eng_x_variant":[
        "Kishibeminami 1 Choume",
        "Kishibeminami 1 Chome"
    ],
    "name:jpn_x_preferred":[
        "\uff11\u4e01\u76ee"
    ],
    "name:jpn_x_variant":[
        "\u304d\u3057\u3079\u307f\u306a\u307f \uff11\u3061\u3087\u3046\u3081",
        "\u5cb8\u90e8\u5357 \uff11\u4e01\u76ee",
        "\uff11\u3061\u3087\u3046\u3081"
    ],
    "qs:gn_adm0_cc":"JP",
    "qs:gn_local":1851483,
    "qs:gn_nam_loc":"\u5439\u7530\u5e02, \u5927\u962a\u5e9c, JP",
    "qs:gn_namadm1":"32",
    "qs:local_max":513,
    "qs:local_sum":1302,
    "qs:localhoods":11,
    "qs:name":"\uff11\u4e01\u76ee",
    "qs:name_adm0":"\u65e5\u672c",
    "qs:name_adm1":"\u5927\u962a\u5e9c",
    "qs:name_en":"Kishibeminami 1 Chome",
    "qs:name_lau":"\u5cb8\u90e8\u5357",
    "qs:name_local":"\u5439\u7530\u5e02",
    "qs:photo_max":10,
    "qs:photo_sum":11,
    "qs:placetype":"Suburb",
    "qs:quad_count":2,
    "qs:woe_adm0":23424856,
    "qs:woe_adm1":2345881,
    "qs:woe_adm2":0,
    "qs:woe_lau":28458294,
    "qs:woe_local":1118234,
    "qs:woe_ver":"7.10.0",
    "wof:lang":[
        "jpn"
    ],
    "wof:name":"\uff11\u4e01\u76ee",
    "wof:placetype":"neighbourhood"
},
  "geometry": {"coordinates":[135.54157699999999,34.775459],"type":"Point"}
}