{
  "type": "Feature",
  "properties": {
    "gn:admin1_code":"35.0",
    "gn:admin2_code":"1858984.0",
    "gn:asciiname":"Kamide",
    "gn:country_code":"JP",
    "gn:dem":491,
    "gn:feature_class":"P",
    "gn:feature_code":"PPL",
    "gn:name":"Kamide",
    "gn:population":0,
    "gn:timezone":"Asia/Tokyo",
    "iso:country":"JP",
    "name:jpn_x_preferred":[
        "\u4e0a\u51fa"
    ],
    "wof:name":"Kamide",
    "wof:placetype":"locality"
},
  "geometry": {"coordinates":[136.03421,34.80659],"type":"Point"}
}