{
  "type": "Feature",
  "properties": {
    "gn:admin1_code":"3.0",
    "gn:admin2_code":"2130654.0",
    "gn:asciiname":"Yatsuhashi",
    "gn:country_code":"JP",
    "gn:dem":7,
    "gn:feature_class":"P",
    "gn:feature_code":"PPL",
    "gn:name":"Yatsuhashi",
    "gn:population":0,
    "gn:timezone":"Asia/Tokyo",
    "iso:country":"JP",
    "name:dan_x_preferred":[
        "Yatsuhashi"
    ],
    "name:deu_x_preferred":[
        "Yatsuhashi"
    ],
    "name:fas_x_preferred":[
        "\u06cc\u0627\u062a\u0633\u0648\u0647\u0627\u0634\u06cc"
    ],
    "name:fra_x_preferred":[
        "Yatsuhashi"
    ],
    "name:jpn_x_preferred":[
        "\u516b\u30c3\u6a4b"
    ],
    "name:jpn_x_variant":[
        "\u3084\u3064\u306f\u3057",
        "\u30e4\u30c4\u30cf\u30b7",
        "\u516b\u30c4\u6a4b"
    ],
    "name:kor_x_preferred":[
        "\uc57c\uc4f0\ud558\uc2dc"
    ],
    "name:rus_x_preferred":[
        "\u042f\u0446\u0443\u0445\u0430\u0441\u0438"
    ],
    "name:spa_x_preferred":[
        "Yatsuhashi"
    ],
    "wof:name":"Yatsuhashi",
    "wof:placetype":"locality"
},
  "geometry": {"coordinates":[140.76871,40.80104],"type":"Point"}
}