{
  "type": "Feature",
  "properties": {
    "gn:admin1_code":"3.0",
    "gn:admin2_code":"2130654.0",
    "gn:asciiname":"Yatsuhashi",
    "gn:country_code":"JP",
    "gn:dem":7,
    "gn:feature_class":"P",
    "gn:feature_code":"PPL",
    "gn:name":"Yatsuhashi",
    "gn:population":0,
    "gn:timezone":"Asia/Tokyo",
    "iso:country":"JP",
    "name:jpn_x_preferred":[
        "\u516b\u30c3\u6a4b"
    ],
    "name:jpn_x_variant":[
        "\u3084\u3064\u306f\u3057",
        "\u30e4\u30c4\u30cf\u30b7"
    ],
    "wof:name":"Yatsuhashi",
    "wof:placetype":"locality"
},
  "geometry": {"coordinates":[140.76871,40.80104],"type":"Point"}
}