{
  "type": "Feature",
  "properties": {
    "gn:admin1_code":"21.0",
    "gn:admin2_code":"7412708.0",
    "gn:admin3_code":"43511.0",
    "gn:asciiname":"Chiikiri",
    "gn:country_code":"JP",
    "gn:dem":446,
    "gn:feature_class":"P",
    "gn:feature_code":"PPLL",
    "gn:name":"Chiikiri",
    "gn:population":0,
    "gn:timezone":"Asia/Tokyo",
    "iso:country":"JP",
    "name:jpn_x_preferred":[
        "\u7bc9\u5207"
    ],
    "name:jpn_x_variant":[
        "\u3061\u3044\u304d\u308a",
        "\u30c1\u30a4\u30ad\u30ea"
    ],
    "wof:name":"Chiikiri",
    "wof:placetype":"locality"
},
  "geometry": {"coordinates":[130.85835,32.42436],"type":"Point"}
}