{
  "type": "Feature",
  "properties": {
    "gn:admin1_code":"3.0",
    "gn:admin2_code":"2130088.0",
    "gn:admin3_code":"2303.0",
    "gn:asciiname":"Nakasawa",
    "gn:country_code":"JP",
    "gn:dem":17,
    "gn:feature_class":"P",
    "gn:feature_code":"PPL",
    "gn:name":"Nakasawa",
    "gn:population":0,
    "gn:timezone":"Asia/Tokyo",
    "iso:country":"JP",
    "name:jpn_x_preferred":[
        "\u4e2d\u6ca2"
    ],
    "name:jpn_x_variant":[
        "\u306a\u304b\u3055\u308f",
        "\u30ca\u30ab\u30b5\u30ef"
    ],
    "wof:name":"Nakasawa",
    "wof:placetype":"locality"
},
  "geometry": {"coordinates":[140.48766000000001,41.18044],"type":"Point"}
}