{
  "type": "Feature",
  "properties": {
    "gn:admin1_code":"31",
    "gn:admin2_code":"1854380.0",
    "gn:admin3_code":"33103.0",
    "gn:asciiname":"Hoden",
    "gn:country_code":"JP",
    "gn:dem":10,
    "gn:feature_class":"P",
    "gn:feature_code":"PPL",
    "gn:name":"H\u014dden",
    "gn:population":0,
    "gn:timezone":"Asia/Tokyo",
    "iso:country":"JP",
    "name:jpn_x_preferred":[
        "\u5b9d\u4f1d"
    ],
    "name:und_x_variant":[
        "H\u014dden"
    ],
    "wof:name":"Hoden",
    "wof:placetype":"locality"
},
  "geometry": {"coordinates":[134.10093000000001,34.5912],"type":"Point"}
}