{
  "type": "Feature",
  "properties": {
    "gn:admin1_code":"12.0",
    "gn:admin2_code":"2128405.0",
    "gn:admin3_code":"1519.0",
    "gn:asciiname":"Hontomari",
    "gn:country_code":"JP",
    "gn:dem":13,
    "gn:feature_class":"P",
    "gn:feature_code":"PPL",
    "gn:name":"Hontomari",
    "gn:population":0,
    "gn:timezone":"Asia/Tokyo",
    "iso:country":"JP",
    "name:jpn_x_preferred":[
        "\u672c\u6cca"
    ],
    "name:jpn_x_variant":[
        "\u307b\u3093\u3068\u307e\u308a",
        "\u30db\u30f3\u30c8\u30de\u30ea"
    ],
    "name:und_x_variant":[
        "Motodomari",
        "Hontomari"
    ],
    "wof:name":"Hontomari",
    "wof:placetype":"locality"
},
  "geometry": {"coordinates":[141.18768,45.24917],"type":"Point"}
}