{
  "type": "Feature",
  "properties": {
    "gn:admin1_code":"26.0",
    "gn:admin2_code":"10629642.0",
    "gn:asciiname":"Minamiogura",
    "gn:country_code":"JP",
    "gn:dem":737,
    "gn:feature_class":"P",
    "gn:feature_code":"PPL",
    "gn:name":"Minamiogura",
    "gn:population":0,
    "gn:timezone":"Asia/Tokyo",
    "iso:country":"JP",
    "name:jpn_x_preferred":[
        "\u5357\u5c0f\u5009"
    ],
    "wof:name":"Minamiogura",
    "wof:placetype":"locality"
},
  "geometry": {"coordinates":[137.84201000000002,36.25679],"type":"Point"}
}