{
  "type": "Feature",
  "properties": {
    "gn:admin1_code":"19.0",
    "gn:admin2_code":"1848350.0",
    "gn:admin3_code":"14101.0",
    "gn:asciiname":"Ichiba-shimocho",
    "gn:country_code":"JP",
    "gn:dem":0,
    "gn:feature_class":"P",
    "gn:feature_code":"PPL",
    "gn:name":"Ichiba-shimoch\u014d",
    "gn:population":0,
    "gn:timezone":"Asia/Tokyo",
    "iso:country":"JP",
    "name:jpn_x_preferred":[
        "\u5e02\u5834\u4e0b\u753a"
    ],
    "name:und_x_variant":[
        "Ichiba-shimoch\u014d"
    ],
    "wof:name":"Ichiba-shimocho",
    "wof:placetype":"locality"
},
  "geometry": {"coordinates":[139.68428,35.51653],"type":"Point"}
}