{
  "type": "Feature",
  "properties": {
    "gn:admin1_code":"24.0",
    "gn:admin2_code":"2112074.0",
    "gn:admin3_code":"4422.0",
    "gn:asciiname":"Bessho",
    "gn:country_code":"JP",
    "gn:dem":41,
    "gn:feature_class":"P",
    "gn:feature_code":"PPL",
    "gn:name":"Bessho",
    "gn:population":0,
    "gn:timezone":"Asia/Tokyo",
    "iso:country":"JP",
    "name:jpn_x_preferred":[
        "\u5225\u6240"
    ],
    "name:jpn_x_variant":[
        "\u3079\u3063\u3057\u3087",
        "\u30d9\u30c3\u30b7\u30e7"
    ],
    "wof:name":"Bessho",
    "wof:placetype":"locality"
},
  "geometry": {"coordinates":[141.02786,38.40696],"type":"Point"}
}