{
  "type": "Feature",
  "properties": {
    "gn:admin1_code":"2.0",
    "gn:admin2_code":"2128783.0",
    "gn:asciiname":"Hinaimachi-shirasawa-mizusawa",
    "gn:country_code":"JP",
    "gn:dem":188,
    "gn:feature_class":"P",
    "gn:feature_code":"PPL",
    "gn:name":"Hinaimachi-shirasawa-mizusawa",
    "gn:population":0,
    "gn:timezone":"Asia/Tokyo",
    "iso:country":"JP",
    "name:jpn_x_preferred":[
        "\u6bd4\u5185\u753a\u767d\u6ca2\u6c34\u6ca2"
    ],
    "name:jpn_x_variant":[
        "\u3072\u306a\u3044\u307e\u3061\u3057\u3089\u3055\u308f\u307f\u305a\u3055\u308f",
        "\u30d2\u30ca\u30a4\u30de\u30c1\u30b7\u30e9\u30b5\u30ef\u30df\u30ba\u30b5\u30ef"
    ],
    "wof:name":"Hinaimachi-shirasawa-mizusawa",
    "wof:placetype":"locality"
},
  "geometry": {"coordinates":[140.51743000000002,40.18111],"type":"Point"}
}