{
  "type": "Feature",
  "properties": {
    "gn:admin1_code":"7.0",
    "gn:admin2_code":"1861834.0",
    "gn:asciiname":"Mita",
    "gn:country_code":"JP",
    "gn:dem":38,
    "gn:feature_class":"P",
    "gn:feature_code":"PPLL",
    "gn:name":"Mita",
    "gn:population":0,
    "gn:timezone":"Asia/Tokyo",
    "iso:country":"JP",
    "name:cat_x_preferred":[
        "Mita"
    ],
    "name:ceb_x_preferred":[
        "Mita"
    ],
    "name:deu_x_preferred":[
        "Mita"
    ],
    "name:fra_x_preferred":[
        "Mita"
    ],
    "name:ita_x_preferred":[
        "Mita"
    ],
    "name:jpn_x_preferred":[
        "\u898b\u7530"
    ],
    "name:rus_x_preferred":[
        "\u041c\u0438\u0442\u0430"
    ],
    "name:swe_x_preferred":[
        "Mita"
    ],
    "wof:name":"Mita",
    "wof:placetype":"locality"
},
  "geometry": {"coordinates":[130.64861999999999,33.60315],"type":"Point"}
}