{
  "type": "Feature",
  "properties": {
    "gn:admin1_code":"4.0",
    "gn:admin2_code":"2112330.0",
    "gn:asciiname":"Higashinakashinjuku",
    "gn:country_code":"JP",
    "gn:dem":30,
    "gn:feature_class":"P",
    "gn:feature_code":"PPL",
    "gn:name":"Higashinakashinjuku",
    "gn:population":0,
    "gn:timezone":"Asia/Tokyo",
    "iso:country":"JP",
    "name:jpn_x_preferred":[
        "\u6771\u4e2d\u65b0\u5bbf"
    ],
    "wof:name":"Higashinakashinjuku",
    "wof:placetype":"locality"
},
  "geometry": {"coordinates":[139.96106,35.83166],"type":"Point"}
}