{
  "type": "Feature",
  "properties": {
    "gn:admin1_code":"21.0",
    "gn:admin2_code":"1858418.0",
    "gn:admin3_code":"43104.0",
    "gn:asciiname":"Tomiaimachi-kamisugi",
    "gn:country_code":"JP",
    "gn:dem":3,
    "gn:feature_class":"P",
    "gn:feature_code":"PPL",
    "gn:name":"Tomiaimachi-kamisugi",
    "gn:population":0,
    "gn:timezone":"Asia/Tokyo",
    "iso:country":"JP",
    "name:jpn_x_preferred":[
        "\u5bcc\u5408\u753a\u4e0a\u6749"
    ],
    "name:jpn_x_variant":[
        "\u3068\u307f\u3042\u3044\u307e\u3061\u304b\u307f\u3059\u304e",
        "\u30c8\u30df\u30a2\u30a4\u30de\u30c1\u30ab\u30df\u30b9\u30ae"
    ],
    "wof:name":"Tomiaimachi-kamisugi",
    "wof:placetype":"locality"
},
  "geometry": {"coordinates":[130.6892,32.72774],"type":"Point"}
}