{
  "type": "Feature",
  "properties": {
    "gn:admin1_code":"35.0",
    "gn:admin2_code":"1858984.0",
    "gn:asciiname":"Tsuchiyamacho-okawara",
    "gn:country_code":"JP",
    "gn:dem":346,
    "gn:feature_class":"P",
    "gn:feature_code":"PPL",
    "gn:name":"Tsuchiyamach\u014d-\u014dkawara",
    "gn:population":0,
    "gn:timezone":"Asia/Tokyo",
    "iso:country":"JP",
    "name:jpn_x_preferred":[
        "\u571f\u5c71\u753a\u5927\u6cb3\u539f"
    ],
    "name:und_x_variant":[
        "Tsuchiyamach\u014d-\u014dkawara"
    ],
    "wof:name":"Tsuchiyamacho-okawara",
    "wof:placetype":"locality"
},
  "geometry": {"coordinates":[136.34603000000001,34.97632],"type":"Point"}
}