{
  "type": "Feature",
  "properties": {
    "gn:admin1_code":"46",
    "gn:admin2_code":"7415915.0",
    "gn:asciiname":"Owatari",
    "gn:country_code":"JP",
    "gn:dem":828,
    "gn:feature_class":"P",
    "gn:feature_code":"PPL",
    "gn:name":"\u014cwatari",
    "gn:population":0,
    "gn:timezone":"Asia/Tokyo",
    "iso:country":"JP",
    "name:und_x_variant":[
        "\u014cwatari"
    ],
    "wof:name":"Owatari",
    "wof:placetype":"locality"
},
  "geometry": {"coordinates":[138.48333,35.83333],"type":"Point"}
}