{
  "type": "Feature",
  "properties": {
    "iso:country":"JP",
    "name:eng_x_preferred":[
        "Nishimotomachi 1 Chome"
    ],
    "name:eng_x_variant":[
        "Nishimotomachi 1 Choume",
        "Nishimotomachi 1 Chome"
    ],
    "name:jpn_x_preferred":[
        "\uff11\u4e01\u76ee"
    ],
    "name:jpn_x_variant":[
        "\u306b\u3057\u3082\u3068\u307e\u3061 \uff11\u3061\u3087\u3046\u3081",
        "\u897f\u5143\u753a \uff11\u4e01\u76ee",
        "\uff11\u3061\u3087\u3046\u3081"
    ],
    "qs:gn_local":0,
    "qs:local_max":730,
    "qs:local_sum":2144,
    "qs:localhoods":9,
    "qs:name":"\uff11\u4e01\u76ee",
    "qs:name_adm0":"\u65e5\u672c",
    "qs:name_adm1":"\u6771\u4eac\u90fd",
    "qs:name_en":"Nishimotomachi 1 Chome",
    "qs:name_lau":"\u897f\u5143\u753a",
    "qs:name_local":"\u56fd\u5206\u5bfa\u5e02",
    "qs:photo_max":79,
    "qs:photo_sum":142,
    "qs:placetype":"Suburb",
    "qs:quad_count":8,
    "qs:woe_adm0":23424856,
    "qs:woe_adm1":2345889,
    "qs:woe_adm2":0,
    "qs:woe_lau":28415205,
    "qs:woe_local":1111004,
    "qs:woe_ver":"7.10.0",
    "wof:lang":[
        "jpn"
    ],
    "wof:name":"\uff11\u4e01\u76ee",
    "wof:placetype":"neighbourhood"
},
  "geometry": {"coordinates":[139.47173100000001,35.693249],"type":"Point"}
}