{
  "type": "Feature",
  "properties": {
    "gn:admin1_code":"21.0",
    "gn:admin2_code":"7413152.0",
    "gn:asciiname":"Nihonmatsu",
    "gn:country_code":"JP",
    "gn:dem":42,
    "gn:feature_class":"P",
    "gn:feature_code":"PPLL",
    "gn:name":"Nihonmatsu",
    "gn:population":0,
    "gn:timezone":"Asia/Tokyo",
    "iso:country":"JP",
    "name:jpn_x_preferred":[
        "\u4e8c\u672c\u677e"
    ],
    "name:jpn_x_variant":[
        "\u306b\u307b\u3093\u307e\u3064",
        "\u30cb\u30db\u30f3\u30de\u30c4"
    ],
    "wof:name":"Nihonmatsu",
    "wof:placetype":"locality"
},
  "geometry": {"coordinates":[130.63298,32.6356],"type":"Point"}
}