{
  "type": "Feature",
  "properties": {
    "gn:admin1_code":"13.0",
    "gn:admin2_code":"7370813.0",
    "gn:asciiname":"Shimoaono",
    "gn:country_code":"JP",
    "gn:dem":188,
    "gn:feature_class":"P",
    "gn:feature_code":"PPL",
    "gn:name":"Shimoaono",
    "gn:population":0,
    "gn:timezone":"Asia/Tokyo",
    "iso:country":"JP",
    "name:jpn_x_preferred":[
        "\u4e0b\u9752\u91ce"
    ],
    "wof:name":"Shimoaono",
    "wof:placetype":"locality"
},
  "geometry": {"coordinates":[135.20612,34.96069],"type":"Point"}
}