{
  "type": "Feature",
  "properties": {
    "gn:admin1_code":"37.0",
    "gn:admin2_code":"1864104.0",
    "gn:asciiname":"Yodogawacho",
    "gn:country_code":"JP",
    "gn:dem":137,
    "gn:feature_class":"P",
    "gn:feature_code":"PPL",
    "gn:name":"Yodogawach\u014d",
    "gn:population":0,
    "gn:timezone":"Asia/Tokyo",
    "iso:country":"JP",
    "name:jpn_x_preferred":[
        "\u6dc0\u5ddd\u753a"
    ],
    "name:und_x_variant":[
        "Yodogawach\u014d"
    ],
    "wof:name":"Yodogawacho",
    "wof:placetype":"locality"
},
  "geometry": {"coordinates":[138.60081,35.23268],"type":"Point"}
}