{
  "type": "Feature",
  "properties": {
    "gn:admin1_code":"21.0",
    "gn:admin2_code":"7412708.0",
    "gn:admin3_code":"43512.0",
    "gn:asciiname":"Uchinokoba",
    "gn:country_code":"JP",
    "gn:dem":552,
    "gn:feature_class":"P",
    "gn:feature_code":"PPLL",
    "gn:name":"Uchinokoba",
    "gn:population":0,
    "gn:timezone":"Asia/Tokyo",
    "iso:country":"JP",
    "name:jpn_x_preferred":[
        "\u5185\u7551"
    ],
    "name:jpn_x_variant":[
        "\u3046\u3061\u306e\u3053\u3070",
        "\u30a6\u30c1\u30ce\u30b3\u30d0"
    ],
    "wof:name":"Uchinokoba",
    "wof:placetype":"locality"
},
  "geometry": {"coordinates":[130.79684,32.30244],"type":"Point"}
}