{
  "type": "Feature",
  "properties": {
    "gn:admin1_code":"4.0",
    "gn:admin2_code":"9062338.0",
    "gn:asciiname":"Nakajima",
    "gn:country_code":"JP",
    "gn:dem":89,
    "gn:feature_class":"P",
    "gn:feature_code":"PPL",
    "gn:name":"Nakajima",
    "gn:population":0,
    "gn:timezone":"Asia/Tokyo",
    "iso:country":"JP",
    "name:jpn_x_preferred":[
        "\u4e2d\u5cf6"
    ],
    "name:jpn_x_variant":[
        "\u306a\u304b\u3058\u307e",
        "\u30ca\u30ab\u30b8\u30de"
    ],
    "wof:name":"Nakajima",
    "wof:placetype":"locality"
},
  "geometry": {"coordinates":[140.26039,35.1586],"type":"Point"}
}