{
  "type": "Feature",
  "properties": {
    "iso:country":"JP",
    "qs:name":"\u5b9d\u585a\u5e02",
    "qs:name_adm0":"\u65e5\u672c",
    "qs:name_adm1":"\u5175\u5eab\u770c",
    "qs:photos":233,
    "qs:photos_1k":47,
    "qs:photos_9k":6,
    "qs:photos_9r":7,
    "qs:photos_all":1356,
    "qs:photos_sr":4,
    "qs:placetype":"Town",
    "qs:pop_sr":"0",
    "wof:name":"\u5b9d\u585a\u5e02",
    "wof:placetype":"locality"
},
  "geometry": {"coordinates":[135.34378000000001,34.816481],"type":"Point"}
}