{
  "type": "Feature",
  "properties": {
    "gn:admin1_code":"07",
    "gn:admin2_code":"1864573.0",
    "gn:asciiname":"Ishizaki",
    "gn:country_code":"JP",
    "gn:dem":43,
    "gn:feature_class":"P",
    "gn:feature_code":"PPL",
    "gn:name":"Ishizaki",
    "gn:population":0,
    "gn:timezone":"Asia/Tokyo",
    "iso:country":"JP",
    "name:jpn_x_preferred":[
        "\u77f3\u5d0e"
    ],
    "wof:name":"Ishizaki",
    "wof:placetype":"locality"
},
  "geometry": {"coordinates":[130.53030999999999,33.48612],"type":"Point"}
}