{
  "type": "Feature",
  "properties": {
    "gn:admin1_code":"3.0",
    "gn:admin2_code":"2127674.0",
    "gn:asciiname":"Naganejiri",
    "gn:country_code":"JP",
    "gn:dem":78,
    "gn:feature_class":"P",
    "gn:feature_code":"PPL",
    "gn:name":"Naganejiri",
    "gn:population":0,
    "gn:timezone":"Asia/Tokyo",
    "iso:country":"JP",
    "name:jpn_x_preferred":[
        "\u9577\u6839\u5c3b"
    ],
    "name:jpn_x_variant":[
        "\u306a\u304c\u306d\u3058\u308a",
        "\u30ca\u30ac\u30cd\u30b8\u30ea"
    ],
    "wof:name":"Naganejiri",
    "wof:placetype":"locality"
},
  "geometry": {"coordinates":[141.1771,40.61758],"type":"Point"}
}