{
  "type": "Feature",
  "properties": {
    "gn:admin1_code":"40.0",
    "gn:admin2_code":"1863453.0",
    "gn:admin3_code":"13401.0",
    "gn:asciiname":"Hachijo",
    "gn:country_code":"JP",
    "gn:dem":23,
    "gn:feature_class":"P",
    "gn:feature_code":"PPLA2",
    "gn:name":"Hachij\u014d",
    "gn:population":0,
    "gn:timezone":"Asia/Tokyo",
    "iso:country":"JP",
    "name:jpn_x_preferred":[
        "\u516b\u4e08\u753a"
    ],
    "wof:name":"Hachijo",
    "wof:placetype":"locality"
},
  "geometry": {"coordinates":[139.77879999999999,33.10276],"type":"Point"}
}