{
  "type": "Feature",
  "properties": {
    "gn:admin1_code":"28.0",
    "gn:admin2_code":"1848164.0",
    "gn:admin3_code":"29446.0",
    "gn:asciiname":"Sawabara",
    "gn:country_code":"JP",
    "gn:dem":597,
    "gn:feature_class":"P",
    "gn:feature_code":"PPL",
    "gn:name":"Sawabara",
    "gn:population":0,
    "gn:timezone":"Asia/Tokyo",
    "iso:country":"JP",
    "name:jpn_x_preferred":[
        "\u6ca2\u539f"
    ],
    "wof:name":"Sawabara",
    "wof:placetype":"locality"
},
  "geometry": {"coordinates":[135.84726000000001,34.23501],"type":"Point"}
}