{
  "type": "Feature",
  "properties": {
    "gn:admin1_code":"21.0",
    "gn:admin2_code":"7412709.0",
    "gn:admin3_code":"43348.0",
    "gn:asciiname":"Shimobukura",
    "gn:country_code":"JP",
    "gn:dem":257,
    "gn:feature_class":"P",
    "gn:feature_code":"PPLL",
    "gn:name":"Shimobukura",
    "gn:population":0,
    "gn:timezone":"Asia/Tokyo",
    "iso:country":"JP",
    "name:jpn_x_preferred":[
        "\u4e0b\u798f\u826f"
    ],
    "name:jpn_x_variant":[
        "\u3057\u3082\u3076\u304f\u3089",
        "\u30b7\u30e2\u30d6\u30af\u30e9"
    ],
    "wof:name":"Shimobukura",
    "wof:placetype":"locality"
},
  "geometry": {"coordinates":[130.94377,32.63332],"type":"Point"}
}