{
  "type": "Feature",
  "properties": {
    "gn:admin1_code":"21.0",
    "gn:admin2_code":"1865358.0",
    "gn:asciiname":"Yamanokuchi",
    "gn:country_code":"JP",
    "gn:dem":226,
    "gn:feature_class":"P",
    "gn:feature_code":"PPLL",
    "gn:name":"Yamanokuchi",
    "gn:population":0,
    "gn:timezone":"Asia/Tokyo",
    "iso:country":"JP",
    "name:jpn_x_preferred":[
        "\u5c71\u306e\u53e3"
    ],
    "name:jpn_x_variant":[
        "\u3084\u307e\u306e\u304f\u3061",
        "\u30e4\u30de\u30ce\u30af\u30c1"
    ],
    "wof:name":"Yamanokuchi",
    "wof:placetype":"locality"
},
  "geometry": {"coordinates":[130.07896000000002,32.4069],"type":"Point"}
}