{
  "type": "Feature",
  "properties": {
    "gn:admin1_code":"32.0",
    "gn:admin2_code":"1862538.0",
    "gn:asciiname":"Hoshigaoka",
    "gn:country_code":"JP",
    "gn:dem":32,
    "gn:feature_class":"P",
    "gn:feature_code":"PPL",
    "gn:name":"Hoshigaoka",
    "gn:population":0,
    "gn:timezone":"Asia/Tokyo",
    "iso:country":"JP",
    "name:jpn_x_preferred":[
        "\u661f\u4e18"
    ],
    "wof:name":"Hoshigaoka",
    "wof:placetype":"locality"
},
  "geometry": {"coordinates":[135.66749999999999,34.80912],"type":"Point"}
}