{
  "type": "Feature",
  "properties": {
    "gn:admin1_code":"21.0",
    "gn:admin2_code":"7412706.0",
    "gn:admin3_code":"43447.0",
    "gn:asciiname":"Nakaomure",
    "gn:country_code":"JP",
    "gn:dem":556,
    "gn:feature_class":"P",
    "gn:feature_code":"PPLL",
    "gn:name":"Nakaomure",
    "gn:population":0,
    "gn:timezone":"Asia/Tokyo",
    "iso:country":"JP",
    "name:jpn_x_preferred":[
        "\u4e2d\u5c3e\u7fa4"
    ],
    "name:jpn_x_variant":[
        "\u306a\u304b\u304a\u3080\u308c",
        "\u30ca\u30ab\u30aa\u30e0\u30ec"
    ],
    "wof:name":"Nakaomure",
    "wof:placetype":"locality"
},
  "geometry": {"coordinates":[130.98958000000002,32.63287],"type":"Point"}
}