{
  "type": "Feature",
  "properties": {
    "gn:admin1_code":"18.0",
    "gn:admin2_code":"1865649.0",
    "gn:admin3_code":"46452.0",
    "gn:asciiname":"Haraguchimae",
    "gn:country_code":"JP",
    "gn:dem":257,
    "gn:feature_class":"P",
    "gn:feature_code":"PPLL",
    "gn:name":"Haraguchimae",
    "gn:population":0,
    "gn:timezone":"Asia/Tokyo",
    "iso:country":"JP",
    "name:jpn_x_preferred":[
        "\u539f\u53e3\u524d"
    ],
    "name:jpn_x_variant":[
        "\u306f\u3089\u3050\u3061\u307e\u3048",
        "\u30cf\u30e9\u30b0\u30c1\u30de\u30a8"
    ],
    "wof:name":"Haraguchimae",
    "wof:placetype":"locality"
},
  "geometry": {"coordinates":[130.75072,32.02542],"type":"Point"}
}