{
  "type": "Feature",
  "properties": {
    "gn:admin1_code":"3.0",
    "gn:admin2_code":"2129754.0",
    "gn:admin3_code":"2408.0",
    "gn:asciiname":"Numzaki-honson",
    "gn:country_code":"JP",
    "gn:dem":27,
    "gn:feature_class":"P",
    "gn:feature_code":"PPL",
    "gn:name":"Numzaki-honson",
    "gn:population":0,
    "gn:timezone":"Asia/Tokyo",
    "iso:country":"JP",
    "name:jpn_x_preferred":[
        "\u6cbc\u5d0e\u672c\u6751"
    ],
    "name:jpn_x_variant":[
        "\u306c\u307e\u3056\u304d\u307b\u3093\u305d\u3093",
        "\u30cc\u30de\u30b6\u30ad\u30db\u30f3\u30bd\u30f3"
    ],
    "wof:name":"Numzaki-honson",
    "wof:placetype":"locality"
},
  "geometry": {"coordinates":[141.28586000000001,40.72244],"type":"Point"}
}