{
  "type": "Feature",
  "properties": {
    "gn:admin1_code":"21.0",
    "gn:admin2_code":"7413152.0",
    "gn:asciiname":"Nakazono",
    "gn:country_code":"JP",
    "gn:dem":37,
    "gn:feature_class":"P",
    "gn:feature_code":"PPLL",
    "gn:name":"Nakazono",
    "gn:population":0,
    "gn:timezone":"Asia/Tokyo",
    "iso:country":"JP",
    "name:jpn_x_preferred":[
        "\u4e2d\u5712"
    ],
    "name:jpn_x_variant":[
        "\u306a\u304b\u305e\u306e",
        "\u30ca\u30ab\u30be\u30ce"
    ],
    "wof:name":"Nakazono",
    "wof:placetype":"locality"
},
  "geometry": {"coordinates":[130.73518999999999,32.58138],"type":"Point"}
}