{
  "type": "Feature",
  "properties": {
    "gn:admin1_code":"4.0",
    "gn:admin2_code":"2110982.0",
    "gn:asciiname":"Ozone",
    "gn:country_code":"JP",
    "gn:dem":18,
    "gn:feature_class":"P",
    "gn:feature_code":"PPL",
    "gn:name":"Ozone",
    "gn:population":0,
    "gn:timezone":"Asia/Tokyo",
    "iso:country":"JP",
    "name:jpn_x_preferred":[
        "\u5927\u66fd\u6839"
    ],
    "name:jpn_x_variant":[
        "\u304a\u305e\u306d",
        "\u30aa\u30be\u30cd"
    ],
    "wof:name":"Ozone",
    "wof:placetype":"locality"
},
  "geometry": {"coordinates":[140.01544999999999,35.41775],"type":"Point"}
}