{
  "type": "Feature",
  "properties": {
    "iso:country":"JP",
    "name:eng_x_preferred":[
        "Omotemachi 3 Chome"
    ],
    "name:eng_x_variant":[
        "Omotemachi 3 Choume",
        "Omotemachi 3 Chome"
    ],
    "name:jpn_x_preferred":[
        "\uff13\u4e01\u76ee"
    ],
    "name:jpn_x_variant":[
        "\u304a\u3082\u3066\u307e\u3061 \uff13\u3061\u3087\u3046\u3081",
        "\u8868\u753a \uff13\u4e01\u76ee",
        "\uff13\u3061\u3087\u3046\u3081"
    ],
    "name:unk_x_variant":[
        "\uff13\u4e01\u76ee"
    ],
    "qs:gn_adm0_cc":"JP",
    "qs:gn_local":2127733,
    "qs:local_max":48,
    "qs:local_sum":91,
    "qs:localhoods":5,
    "qs:name":"\uff13\u4e01\u76ee",
    "qs:name_adm0":"\u65e5\u672c",
    "qs:name_adm1":"\u5317\u6d77\u9053",
    "qs:name_en":"Omotemachi 3 Chome",
    "qs:name_lau":"\u8868\u753a",
    "qs:name_local":"\u82eb\u5c0f\u7267\u5e02",
    "qs:photo_max":23,
    "qs:photo_sum":48,
    "qs:placetype":"Suburb",
    "qs:quad_count":3,
    "qs:woe_adm0":23424856,
    "qs:woe_adm1":7153351,
    "qs:woe_adm2":0,
    "qs:woe_lau":28381650,
    "qs:woe_local":1118372,
    "qs:woe_ver":"7.10.0",
    "wof:lang":[
        "jpn"
    ],
    "wof:name":"\uff13\u4e01\u76ee",
    "wof:placetype":"neighbourhood"
},
  "geometry": {"coordinates":[141.59755699999999,42.637325],"type":"Point"}
}