{
  "type": "Feature",
  "properties": {
    "gn:country":"JP",
    "gn:fcode":"ADM3",
    "gn:population":0,
    "iso:country":"JP",
    "name:eng_x_preferred":[
        "Mori"
    ],
    "name:eng_x_variant":[
        "Mori-machi"
    ],
    "name:jpn_x_preferred":[
        "\u68ee\u753a"
    ],
    "name:jpn_x_variant":[
        "\u3082\u308a\u307e\u3061"
    ],
    "qs:name":"Mori-machi",
    "qs:photos_9r":0,
    "qs:photos_sr":0,
    "qs:pop_sr":"0",
    "wof:name":"Mori",
    "wof:placetype":"localadmin",
    "wof:population":0
},
  "geometry": {"coordinates":[137.94757000000001,34.88656],"type":"Point"}
}