{
  "type": "Feature",
  "properties": {
    "gn:admin1_code":"4.0",
    "gn:admin2_code":"2112997.0",
    "gn:admin3_code":"12423.0",
    "gn:asciiname":"Koizumi-hokubu",
    "gn:country_code":"JP",
    "gn:dem":1,
    "gn:feature_class":"P",
    "gn:feature_code":"PPLL",
    "gn:name":"Koizumi-hokubu",
    "gn:population":0,
    "gn:timezone":"Asia/Tokyo",
    "iso:country":"JP",
    "name:jpn_x_preferred":[
        "\u5c0f\u6cc9\u5317\u90e8"
    ],
    "name:jpn_x_variant":[
        "\u3053\u3044\u305a\u307f\u307b\u304f\u3076",
        "\u30b3\u30a4\u30ba\u30df\u30db\u30af\u30d6"
    ],
    "wof:name":"Koizumi-hokubu",
    "wof:placetype":"locality"
},
  "geometry": {"coordinates":[140.36867000000001,35.42114],"type":"Point"}
}