{
  "type": "Feature",
  "properties": {
    "gn:admin1_code":"19.0",
    "gn:admin2_code":"1848350.0",
    "gn:admin3_code":"14113.0",
    "gn:asciiname":"Aotocho",
    "gn:country_code":"JP",
    "gn:dem":16,
    "gn:feature_class":"P",
    "gn:feature_code":"PPL",
    "gn:name":"Aotoch\u014d",
    "gn:population":0,
    "gn:timezone":"Asia/Tokyo",
    "iso:country":"JP",
    "name:jpn_x_preferred":[
        "\u9752\u7825\u753a"
    ],
    "name:und_x_variant":[
        "Aotoch\u014d"
    ],
    "wof:name":"Aotocho",
    "wof:placetype":"locality"
},
  "geometry": {"coordinates":[139.54566,35.52063],"type":"Point"}
}