{
  "type": "Feature",
  "properties": {
    "gn:admin1_code":"22",
    "gn:admin2_code":"7412201.0",
    "gn:asciiname":"Kami-hiraya",
    "gn:cc2":"JP",
    "gn:country_code":"JP",
    "gn:dem":512,
    "gn:feature_class":"P",
    "gn:feature_code":"PPL",
    "gn:name":"Kami-hiraya",
    "gn:population":0,
    "gn:timezone":"Asia/Tokyo",
    "iso:country":"JP",
    "name:und_x_variant":[
        "Hiraya",
        "Kami-hiraya"
    ],
    "wof:name":"Kami-hiraya",
    "wof:placetype":"locality"
},
  "geometry": {"coordinates":[135.58333000000002,35.26667],"type":"Point"}
}