{
  "type": "Feature",
  "properties": {
    "gn:admin1_code":"42",
    "gn:admin2_code":"7391183.0",
    "gn:asciiname":"Kaimukura",
    "gn:country_code":"JP",
    "gn:dem":326,
    "gn:feature_class":"P",
    "gn:feature_code":"PPL",
    "gn:name":"Kaimukura",
    "gn:population":0,
    "gn:timezone":"Asia/Tokyo",
    "iso:country":"JP",
    "name:jpn_x_preferred":[
        "\u7686\u844e"
    ],
    "name:und_x_variant":[
        "Kaimugura"
    ],
    "wof:name":"Kaimukura",
    "wof:placetype":"locality"
},
  "geometry": {"coordinates":[136.92004,36.40233],"type":"Point"}
}