{
  "type": "Feature",
  "properties": {
    "gn:admin1_code":"25.0",
    "gn:admin2_code":"1864313.0",
    "gn:asciiname":"Nakauwae",
    "gn:country_code":"JP",
    "gn:dem":263,
    "gn:feature_class":"P",
    "gn:feature_code":"PPLL",
    "gn:name":"Nakauwae",
    "gn:population":0,
    "gn:timezone":"Asia/Tokyo",
    "iso:country":"JP",
    "name:jpn_x_preferred":[
        "\u4e2d\u4e0a\u6c5f"
    ],
    "name:jpn_x_variant":[
        "\u306a\u304b\u3046\u308f\u3048",
        "\u30ca\u30ab\u30a6\u30ef\u30a8"
    ],
    "wof:name":"Nakauwae",
    "wof:placetype":"locality"
},
  "geometry": {"coordinates":[130.85433,32.03075],"type":"Point"}
}