{
  "type": "Feature",
  "properties": {
    "gn:admin1_code":"37.0",
    "gn:admin2_code":"1864089.0",
    "gn:asciiname":"Motocho",
    "gn:country_code":"JP",
    "gn:dem":19,
    "gn:feature_class":"P",
    "gn:feature_code":"PPL",
    "gn:name":"Motoch\u014d",
    "gn:population":0,
    "gn:timezone":"Asia/Tokyo",
    "iso:country":"JP",
    "name:jpn_x_preferred":[
        "\u5143\u753a"
    ],
    "name:und_x_variant":[
        "Motoch\u014d"
    ],
    "wof:name":"Motocho",
    "wof:placetype":"locality"
},
  "geometry": {"coordinates":[138.64595,35.15341],"type":"Point"}
}