{
  "type": "Feature",
  "properties": {
    "iso:country":"JP",
    "name:eng_x_preferred":[
        "Shimizu Town"
    ],
    "name:jpn_x_preferred":[
        "\u6e05\u6c34\u753a"
    ],
    "qs:name":"\u6e05\u6c34\u753a",
    "qs:name_adm0":"\u65e5\u672c",
    "qs:name_adm1":"\u5317\u6d77\u9053",
    "qs:photos":71,
    "qs:photos_1k":14,
    "qs:photos_9k":1,
    "qs:photos_9r":3,
    "qs:photos_all":79,
    "qs:photos_sr":2,
    "qs:placetype":"Town",
    "qs:pop_sr":"0",
    "wof:name":"Shimizu Town",
    "wof:placetype":"locality"
},
  "geometry": {"coordinates":[142.869652,42.961489],"type":"Point"}
}