{
  "type": "Feature",
  "properties": {
    "gn:admin1_code":"12.0",
    "gn:admin2_code":"2129370.0",
    "gn:asciiname":"Tottori-odori",
    "gn:country_code":"JP",
    "gn:dem":8,
    "gn:feature_class":"P",
    "gn:feature_code":"PPL",
    "gn:name":"Tottori-\u014dd\u014dri",
    "gn:population":0,
    "gn:timezone":"Asia/Tokyo",
    "iso:country":"JP",
    "name:jpn_x_preferred":[
        "\u9ce5\u53d6\u5927\u901a"
    ],
    "name:jpn_x_variant":[
        "\u3068\u3063\u3068\u308a\u304a\u304a\u3069\u304a\u308a",
        "\u30c8\u30c3\u30c8\u30ea\u30aa\u30aa\u30c9\u30aa\u30ea"
    ],
    "name:und_x_variant":[
        "Tottori-machi",
        "Tottori",
        "Tottori-\u014dd\u014dri"
    ],
    "wof:name":"Tottori-odori",
    "wof:placetype":"locality"
},
  "geometry": {"coordinates":[144.34645,43.01395],"type":"Point"}
}