{
  "type": "Feature",
  "properties": {
    "gn:admin1_code":"21.0",
    "gn:admin2_code":"7412708.0",
    "gn:admin3_code":"43513.0",
    "gn:asciiname":"Kiyanosumi",
    "gn:country_code":"JP",
    "gn:dem":61,
    "gn:feature_class":"P",
    "gn:feature_code":"PPLL",
    "gn:name":"Kiyanosumi",
    "gn:population":0,
    "gn:timezone":"Asia/Tokyo",
    "iso:country":"JP",
    "name:jpn_x_preferred":[
        "\u6728\u5c4b\u89d2"
    ],
    "name:jpn_x_variant":[
        "\u304d\u3084\u306e\u3059\u307f",
        "\u30ad\u30e4\u30ce\u30b9\u30df"
    ],
    "wof:name":"Kiyanosumi",
    "wof:placetype":"locality"
},
  "geometry": {"coordinates":[130.61437000000001,32.31289],"type":"Point"}
}