{
  "type": "Feature",
  "properties": {
    "iso:country":"JP",
    "name:eng_x_preferred":[
        "Urakawa"
    ],
    "name:eng_x_variant":[
        "Urakawa Town"
    ],
    "name:jpn_x_preferred":[
        "\u6d66\u6cb3\u753a"
    ],
    "qs:name":"\u6d66\u6cb3\u753a",
    "qs:name_adm0":"\u65e5\u672c",
    "qs:name_adm1":"\u5317\u6d77\u9053",
    "qs:photos":376,
    "qs:photos_1k":76,
    "qs:photos_9k":2,
    "qs:photos_9r":5,
    "qs:photos_all":394,
    "qs:photos_sr":6,
    "qs:placetype":"Town",
    "qs:pop_sr":"0",
    "wof:name":"Urakawa",
    "wof:placetype":"locality"
},
  "geometry": {"coordinates":[142.828788,42.142627],"type":"Point"}
}