{
  "type": "Feature",
  "properties": {
    "gn:admin1_code":"21.0",
    "gn:admin2_code":"1858418.0",
    "gn:admin3_code":"43102.0",
    "gn:asciiname":"Suigen",
    "gn:country_code":"JP",
    "gn:dem":11,
    "gn:feature_class":"P",
    "gn:feature_code":"PPL",
    "gn:name":"Suigen",
    "gn:population":0,
    "gn:timezone":"Asia/Tokyo",
    "iso:country":"JP",
    "name:jpn_x_preferred":[
        "\u6c34\u6e90"
    ],
    "name:jpn_x_variant":[
        "\u3059\u3044\u3052\u3093",
        "\u30b9\u30a4\u30b2\u30f3"
    ],
    "wof:name":"Suigen",
    "wof:placetype":"locality"
},
  "geometry": {"coordinates":[130.75266999999999,32.77564],"type":"Point"}
}