{
  "type": "Feature",
  "properties": {
    "gn:admin1_code":"21.0",
    "gn:admin2_code":"7413152.0",
    "gn:asciiname":"Matsubasemachi-ryonakama",
    "gn:country_code":"JP",
    "gn:dem":9,
    "gn:feature_class":"P",
    "gn:feature_code":"PPL",
    "gn:name":"Matsubasemachi-ry\u014dnakama",
    "gn:population":0,
    "gn:timezone":"Asia/Tokyo",
    "iso:country":"JP",
    "name:jpn_x_preferred":[
        "\u677e\u6a4b\u753a\u4e21\u4ef2\u9593"
    ],
    "name:jpn_x_variant":[
        "\u307e\u3064\u3070\u305b\u307e\u3061\u308a\u3087\u3046\u306a\u304b\u307e",
        "\u30de\u30c4\u30d0\u30bb\u30de\u30c1\u30ea\u30e7\u30a6\u30ca\u30ab\u30de"
    ],
    "name:und_x_variant":[
        "Matsubasemachi-ry\u014dnakama"
    ],
    "wof:name":"Matsubasemachi-ryonakama",
    "wof:placetype":"locality"
},
  "geometry": {"coordinates":[130.69919999999999,32.62996],"type":"Point"}
}