{
  "type": "Feature",
  "properties": {
    "gn:admin1_code":"7.0",
    "gn:admin2_code":"1859306.0",
    "gn:admin3_code":"40103.0",
    "gn:asciiname":"Aobadai-nishi",
    "gn:country_code":"JP",
    "gn:dem":30,
    "gn:feature_class":"P",
    "gn:feature_code":"PPL",
    "gn:name":"Aobadai-nishi",
    "gn:population":0,
    "gn:timezone":"Asia/Tokyo",
    "iso:country":"JP",
    "name:jpn_x_preferred":[
        "\u9752\u8449\u53f0\u897f"
    ],
    "wof:name":"Aobadai-nishi",
    "wof:placetype":"locality"
},
  "geometry": {"coordinates":[130.68513999999999,33.90091],"type":"Point"}
}