{
  "type": "Feature",
  "properties": {
    "gn:admin1_code":"19.0",
    "gn:admin2_code":"1862461.0",
    "gn:asciiname":"Nakazato",
    "gn:country_code":"JP",
    "gn:dem":55,
    "gn:feature_class":"P",
    "gn:feature_code":"PPL",
    "gn:name":"Nakazato",
    "gn:population":0,
    "gn:timezone":"Asia/Tokyo",
    "iso:country":"JP",
    "name:jpn_x_preferred":[
        "\u4e2d\u91cc"
    ],
    "wof:name":"Nakazato",
    "wof:placetype":"locality"
},
  "geometry": {"coordinates":[139.25557000000001,35.34777000000001],"type":"Point"}
}