{
  "type": "Feature",
  "properties": {
    "gn:admin1_code":"21.0",
    "gn:admin2_code":"7413150.0",
    "gn:asciiname":"Kubaru",
    "gn:country_code":"JP",
    "gn:dem":55,
    "gn:feature_class":"P",
    "gn:feature_code":"PPL",
    "gn:name":"Kubaru",
    "gn:population":0,
    "gn:timezone":"Asia/Tokyo",
    "iso:country":"JP",
    "name:jpn_x_preferred":[
        "\u4e45\u539f"
    ],
    "name:jpn_x_variant":[
        "\u304f\u3070\u308b",
        "\u30af\u30d0\u30eb"
    ],
    "wof:name":"Kubaru",
    "wof:placetype":"locality"
},
  "geometry": {"coordinates":[130.72117,33.02998],"type":"Point"}
}