{
  "type": "Feature",
  "properties": {
    "gn:admin1_code":"4.0",
    "gn:admin2_code":"2112330.0",
    "gn:asciiname":"Sakasai-fujinodai",
    "gn:country_code":"JP",
    "gn:dem":28,
    "gn:feature_class":"P",
    "gn:feature_code":"PPL",
    "gn:name":"Sakasai-fujinodai",
    "gn:population":0,
    "gn:timezone":"Asia/Tokyo",
    "iso:country":"JP",
    "name:jpn_x_preferred":[
        "\u9006\u4e95\u85e4\u30ce\u53f0"
    ],
    "wof:name":"Sakasai-fujinodai",
    "wof:placetype":"locality"
},
  "geometry": {"coordinates":[139.98671999999999,35.82272000000001],"type":"Point"}
}