{
  "type": "Feature",
  "properties": {
    "iso:country":"JP",
    "name:eng_x_preferred":[
        "Kawakami"
    ],
    "name:eng_x_variant":[
        "Kawakami Village"
    ],
    "name:jpn_x_preferred":[
        "\u5ddd\u4e0a\u6751"
    ],
    "qs:name":"\u5ddd\u4e0a\u6751",
    "qs:name_adm0":"\u65e5\u672c",
    "qs:name_adm1":"\u5948\u826f\u770c",
    "qs:photos":114,
    "qs:photos_1k":23,
    "qs:photos_9k":1,
    "qs:photos_9r":3,
    "qs:photos_all":114,
    "qs:photos_sr":3,
    "qs:placetype":"Town",
    "qs:pop_sr":"0",
    "wof:name":"Kawakami",
    "wof:placetype":"locality"
},
  "geometry": {"coordinates":[136.09691599999999,34.190221],"type":"Point"}
}