{
  "type": "Feature",
  "properties": {
    "gn:admin1_code":"4.0",
    "gn:admin2_code":"2112386.0",
    "gn:asciiname":"Awato",
    "gn:country_code":"JP",
    "gn:dem":82,
    "gn:feature_class":"P",
    "gn:feature_code":"PPL",
    "gn:name":"Awato",
    "gn:population":0,
    "gn:timezone":"Asia/Tokyo",
    "iso:country":"JP",
    "name:jpn_x_preferred":[
        "\u7c9f\u6597"
    ],
    "name:jpn_x_variant":[
        "\u3042\u308f\u3068",
        "\u30a2\u30ef\u30c8"
    ],
    "wof:name":"Awato",
    "wof:placetype":"locality"
},
  "geometry": {"coordinates":[140.09208000000001,35.1313],"type":"Point"}
}