{
  "type": "Feature",
  "properties": {
    "gn:admin1_code":"37.0",
    "gn:admin2_code":"8301106.0",
    "gn:asciiname":"Hazu",
    "gn:country_code":"JP",
    "gn:dem":6,
    "gn:feature_class":"P",
    "gn:feature_code":"PPLL",
    "gn:name":"Hazu",
    "gn:population":0,
    "gn:timezone":"Asia/Tokyo",
    "iso:country":"JP",
    "name:jpn_x_preferred":[
        "\u521d\u6d25"
    ],
    "wof:name":"Hazu",
    "wof:placetype":"locality"
},
  "geometry": {"coordinates":[139.08141000000001,35.00191],"type":"Point"}
}