{
  "type": "Feature",
  "properties": {
    "gn:admin1_code":"21.0",
    "gn:admin2_code":"1858418.0",
    "gn:admin3_code":"43105.0",
    "gn:asciiname":"Komichi",
    "gn:country_code":"JP",
    "gn:dem":80,
    "gn:feature_class":"P",
    "gn:feature_code":"PPLL",
    "gn:name":"Komichi",
    "gn:population":0,
    "gn:timezone":"Asia/Tokyo",
    "iso:country":"JP",
    "name:jpn_x_preferred":[
        "\u5c0f\u9053"
    ],
    "name:jpn_x_variant":[
        "\u3053\u307f\u3061",
        "\u30b3\u30df\u30c1"
    ],
    "wof:name":"Komichi",
    "wof:placetype":"locality"
},
  "geometry": {"coordinates":[130.71216000000001,32.89979],"type":"Point"}
}