{
  "type": "Feature",
  "properties": {
    "gn:admin1_code":"19.0",
    "gn:admin2_code":"1859635.0",
    "gn:admin3_code":"14135.0",
    "gn:asciiname":"Teraodai",
    "gn:country_code":"JP",
    "gn:dem":47,
    "gn:feature_class":"P",
    "gn:feature_code":"PPL",
    "gn:name":"Teraodai",
    "gn:population":0,
    "gn:timezone":"Asia/Tokyo",
    "iso:country":"JP",
    "name:jpn_x_preferred":[
        "\u5bfa\u5c3e\u53f0"
    ],
    "wof:name":"Teraodai",
    "wof:placetype":"locality"
},
  "geometry": {"coordinates":[139.53566999999998,35.62134000000001],"type":"Point"}
}