{
  "type": "Feature",
  "properties": {
    "gn:admin1_code":"44",
    "gn:admin2_code":"2111805.0",
    "gn:asciiname":"Tateoka",
    "gn:country_code":"JP",
    "gn:dem":89,
    "gn:feature_class":"P",
    "gn:feature_code":"PPL",
    "gn:name":"Tateoka",
    "gn:population":0,
    "gn:timezone":"Asia/Tokyo",
    "iso:country":"JP",
    "name:jpn_x_preferred":[
        "\u696f\u5ca1"
    ],
    "wof:name":"Tateoka",
    "wof:placetype":"locality"
},
  "geometry": {"coordinates":[140.38889,38.47611],"type":"Point"}
}