{
  "type": "Feature",
  "properties": {
    "gn:admin1_code":"13.0",
    "gn:admin2_code":"7370813.0",
    "gn:asciiname":"Kitaura",
    "gn:country_code":"JP",
    "gn:dem":186,
    "gn:feature_class":"P",
    "gn:feature_code":"PPL",
    "gn:name":"Kitaura",
    "gn:population":0,
    "gn:timezone":"Asia/Tokyo",
    "iso:country":"JP",
    "name:jpn_x_preferred":[
        "\u5317\u6d66"
    ],
    "wof:name":"Kitaura",
    "wof:placetype":"locality"
},
  "geometry": {"coordinates":[135.20948000000001,34.95123],"type":"Point"}
}