{
  "type": "Feature",
  "properties": {
    "gn:admin1_code":"3.0",
    "gn:admin2_code":"2128134.0",
    "gn:admin3_code":"2426.0",
    "gn:asciiname":"Ushitaki",
    "gn:cc2":"JP",
    "gn:country_code":"JP",
    "gn:dem":149,
    "gn:feature_class":"P",
    "gn:feature_code":"PPL",
    "gn:name":"Ushitaki",
    "gn:population":0,
    "gn:timezone":"Asia/Tokyo",
    "iso:country":"JP",
    "name:und_x_variant":[
        "Usitaki",
        "Ushitaki"
    ],
    "wof:name":"Ushitaki",
    "wof:placetype":"locality"
},
  "geometry": {"coordinates":[140.80000000000001,41.28333],"type":"Point"}
}