{
  "type": "Feature",
  "properties": {
    "gn:admin1_code":"47",
    "gn:admin2_code":"1849184.0",
    "gn:asciiname":"Urazoe",
    "gn:country_code":"JP",
    "gn:dem":38,
    "gn:feature_class":"P",
    "gn:feature_code":"PPL",
    "gn:name":"Urazoe",
    "gn:population":0,
    "gn:timezone":"Asia/Tokyo",
    "iso:country":"JP",
    "wof:name":"Urazoe",
    "wof:placetype":"locality"
},
  "geometry": {"coordinates":[127.70638999999998,26.25444],"type":"Point"}
}