{
  "type": "Feature",
  "properties": {
    "iso:country":"JP",
    "name:eng_x_preferred":[
        "Yamazaki 1 Chome"
    ],
    "name:eng_x_variant":[
        "Yamazaki 1 Choume",
        "Yamazaki 1 Chome"
    ],
    "name:jpn_x_preferred":[
        "\uff11\u4e01\u76ee"
    ],
    "name:jpn_x_variant":[
        "\u3084\u307e\u3056\u304d \uff11\u3061\u3087\u3046\u3081",
        "\u5c71\u5d0e \uff11\u4e01\u76ee",
        "\uff11\u3061\u3087\u3046\u3081"
    ],
    "name:unk_x_variant":[
        "\uff11\u4e01\u76ee"
    ],
    "qs:gn_local":0,
    "qs:local_max":581,
    "qs:local_sum":587,
    "qs:localhoods":3,
    "qs:name":"\uff11\u4e01\u76ee",
    "qs:name_adm0":"\u65e5\u672c",
    "qs:name_adm1":"\u5927\u962a\u5e9c",
    "qs:name_adm2":"\u4e09\u5cf6\u90e1",
    "qs:name_en":"Yamazaki 1 Chome",
    "qs:name_lau":"\u5c71\u5d0e",
    "qs:name_local":"\u5cf6\u672c\u753a",
    "qs:photo_max":91,
    "qs:photo_sum":581,
    "qs:placetype":"Suburb",
    "qs:quad_count":29,
    "qs:woe_adm0":23424856,
    "qs:woe_adm1":2345881,
    "qs:woe_adm2":24857874,
    "qs:woe_lau":1116577,
    "qs:woe_local":24852727,
    "qs:woe_ver":"7.10.0",
    "wof:lang":[
        "jpn"
    ],
    "wof:name":"\uff11\u4e01\u76ee",
    "wof:placetype":"neighbourhood"
},
  "geometry": {"coordinates":[135.68133,34.892038],"type":"Point"}
}