{
  "type": "Feature",
  "properties": {
    "gn:admin1_code":"21.0",
    "gn:admin2_code":"1862350.0",
    "gn:asciiname":"Nagaha",
    "gn:country_code":"JP",
    "gn:dem":363,
    "gn:feature_class":"P",
    "gn:feature_code":"PPLL",
    "gn:name":"Nagaha",
    "gn:population":0,
    "gn:timezone":"Asia/Tokyo",
    "iso:country":"JP",
    "name:jpn_x_preferred":[
        "\u6c38\u8449"
    ],
    "name:jpn_x_variant":[
        "\u306a\u304c\u306f",
        "\u30ca\u30ac\u30cf"
    ],
    "wof:name":"Nagaha",
    "wof:placetype":"locality"
},
  "geometry": {"coordinates":[130.73398,32.16442],"type":"Point"}
}