{
  "type": "Feature",
  "properties": {
    "gn:admin1_code":"21.0",
    "gn:admin2_code":"7412706.0",
    "gn:admin3_code":"43447.0",
    "gn:asciiname":"Ogura",
    "gn:country_code":"JP",
    "gn:dem":641,
    "gn:feature_class":"P",
    "gn:feature_code":"PPLL",
    "gn:name":"Ogura",
    "gn:population":0,
    "gn:timezone":"Asia/Tokyo",
    "iso:country":"JP",
    "name:jpn_x_preferred":[
        "\u5c0f\u5009"
    ],
    "name:jpn_x_variant":[
        "\u304a\u3050\u3089",
        "\u30aa\u30b0\u30e9"
    ],
    "wof:name":"Ogura",
    "wof:placetype":"locality"
},
  "geometry": {"coordinates":[131.18285,32.77355],"type":"Point"}
}