{
  "type": "Feature",
  "properties": {
    "gn:admin1_code":"23.0",
    "gn:admin2_code":"1849544.0",
    "gn:asciiname":"Misugicho-hatemata",
    "gn:country_code":"JP",
    "gn:dem":194,
    "gn:feature_class":"P",
    "gn:feature_code":"PPL",
    "gn:name":"Misugich\u014d-hatemata",
    "gn:population":0,
    "gn:timezone":"Asia/Tokyo",
    "iso:country":"JP",
    "name:jpn_x_preferred":[
        "\u7f8e\u6749\u753a\u516b\u624b\u4fe3"
    ],
    "name:und_x_variant":[
        "Misugich\u014d-hatemata"
    ],
    "wof:name":"Misugicho-hatemata",
    "wof:placetype":"locality"
},
  "geometry": {"coordinates":[136.34323999999998,34.58321],"type":"Point"}
}