{
  "type": "Feature",
  "properties": {
    "gn:admin1_code":"23.0",
    "gn:admin2_code":"1857496.0",
    "gn:asciiname":"Iitakacho-otogurusu",
    "gn:country_code":"JP",
    "gn:dem":296,
    "gn:feature_class":"P",
    "gn:feature_code":"PPL",
    "gn:name":"Iitakach\u014d-otogurusu",
    "gn:population":0,
    "gn:timezone":"Asia/Tokyo",
    "iso:country":"JP",
    "name:jpn_x_preferred":[
        "\u98ef\u9ad8\u753a\u4e59\u6817\u5b50"
    ],
    "name:und_x_variant":[
        "Iitakach\u014d-otogurusu"
    ],
    "wof:name":"Iitakacho-otogurusu",
    "wof:placetype":"locality"
},
  "geometry": {"coordinates":[136.19198,34.40777],"type":"Point"}
}