{
  "type": "Feature",
  "properties": {
    "gn:admin1_code":"34.0",
    "gn:admin2_code":"1849187.0",
    "gn:admin3_code":"11106.0",
    "gn:asciiname":"Tsukamoto",
    "gn:country_code":"JP",
    "gn:dem":11,
    "gn:feature_class":"P",
    "gn:feature_code":"PPL",
    "gn:name":"Tsukamoto",
    "gn:population":0,
    "gn:timezone":"Asia/Tokyo",
    "iso:country":"JP",
    "name:jpn_x_preferred":[
        "\u585a\u672c"
    ],
    "name:jpn_x_variant":[
        "\u3064\u304b\u3082\u3068",
        "\u30c4\u30ab\u30e2\u30c8"
    ],
    "wof:name":"Tsukamoto",
    "wof:placetype":"locality"
},
  "geometry": {"coordinates":[139.59156000000002,35.87155999999999],"type":"Point"}
}