{
  "type": "Feature",
  "properties": {
    "gn:admin1_code":"33.0",
    "gn:admin2_code":"1850832.0",
    "gn:asciiname":"Tataro",
    "gn:country_code":"JP",
    "gn:dem":54,
    "gn:feature_class":"P",
    "gn:feature_code":"PPLL",
    "gn:name":"Tatar\u014d",
    "gn:population":0,
    "gn:timezone":"Asia/Tokyo",
    "iso:country":"JP",
    "name:jpn_x_preferred":[
        "\u591a\u3005\u826f"
    ],
    "name:und_x_variant":[
        "Tatar\u014d"
    ],
    "wof:name":"Tataro",
    "wof:placetype":"locality"
},
  "geometry": {"coordinates":[129.95762999999999,33.24926],"type":"Point"}
}