{
  "type": "Feature",
  "properties": {
    "gn:admin1_code":"35.0",
    "gn:admin2_code":"1858984.0",
    "gn:asciiname":"Uenogumi",
    "gn:country_code":"JP",
    "gn:dem":265,
    "gn:feature_class":"P",
    "gn:feature_code":"PPL",
    "gn:name":"Uenogumi",
    "gn:population":0,
    "gn:timezone":"Asia/Tokyo",
    "iso:country":"JP",
    "name:jpn_x_preferred":[
        "\u4e0a\u30ce\u7d44"
    ],
    "wof:name":"Uenogumi",
    "wof:placetype":"locality"
},
  "geometry": {"coordinates":[136.26727,34.89971],"type":"Point"}
}