{
  "type": "Feature",
  "properties": {
    "iso:country":"JP",
    "name:eng_x_preferred":[
        "Nishikaniya 3 Chome"
    ],
    "name:eng_x_variant":[
        "Nishikaniya 3 Choume",
        "Nishikaniya 3 Chome"
    ],
    "name:jpn_x_preferred":[
        "\uff13\u4e01\u76ee"
    ],
    "name:jpn_x_variant":[
        "\u306b\u3057\u304b\u306b\u3084 \uff13\u3061\u3087\u3046\u3081",
        "\u897f\u87f9\u5c4b \uff13\u4e01\u76ee",
        "\uff13\u3061\u3087\u3046\u3081"
    ],
    "qs:gn_adm0_cc":"JP",
    "qs:gn_local":1862415,
    "qs:gn_nam_loc":"\u5e83\u5cf6\u5e02, \u5e83\u5cf6\u770c, JP",
    "qs:gn_namadm1":"11",
    "qs:local_max":2245,
    "qs:local_sum":19695,
    "qs:localhoods":32,
    "qs:name":"\uff13\u4e01\u76ee",
    "qs:name_adm0":"\u65e5\u672c",
    "qs:name_adm1":"\u5e83\u5cf6\u770c",
    "qs:name_adm2":"\u5357\u533a",
    "qs:name_en":"Nishikaniya 3 Chome",
    "qs:name_lau":"\u897f\u87f9\u5c4b",
    "qs:name_local":"\u5e83\u5cf6\u5e02",
    "qs:photo_max":381,
    "qs:photo_sum":486,
    "qs:placetype":"Suburb",
    "qs:quad_count":8,
    "qs:woe_adm0":23424856,
    "qs:woe_adm1":2345861,
    "qs:woe_adm2":15015419,
    "qs:woe_lau":28473869,
    "qs:woe_local":1117227,
    "qs:woe_ver":"7.10.0",
    "wof:lang":[
        "jpn"
    ],
    "wof:name":"\uff13\u4e01\u76ee",
    "wof:placetype":"neighbourhood"
},
  "geometry": {"coordinates":[132.48502300000001,34.392128],"type":"Point"}
}