{
  "type": "Feature",
  "properties": {
    "gn:admin1_code":"37.0",
    "gn:admin2_code":"9036693.0",
    "gn:asciiname":"Kamishiraiwa",
    "gn:country_code":"JP",
    "gn:dem":128,
    "gn:feature_class":"P",
    "gn:feature_code":"PPL",
    "gn:name":"Kamishiraiwa",
    "gn:population":0,
    "gn:timezone":"Asia/Tokyo",
    "iso:country":"JP",
    "name:jpn_x_preferred":[
        "\u4e0a\u767d\u5ca9"
    ],
    "wof:name":"Kamishiraiwa",
    "wof:placetype":"locality"
},
  "geometry": {"coordinates":[138.98049,34.95893],"type":"Point"}
}