{
  "type": "Feature",
  "properties": {
    "gn:admin1_code":"2.0",
    "gn:admin2_code":"2128783.0",
    "gn:asciiname":"Minamishinmeicho",
    "gn:country_code":"JP",
    "gn:dem":67,
    "gn:feature_class":"P",
    "gn:feature_code":"PPL",
    "gn:name":"Minamishinmeich\u014d",
    "gn:population":0,
    "gn:timezone":"Asia/Tokyo",
    "iso:country":"JP",
    "name:jpn_x_preferred":[
        "\u5357\u65b0\u660e\u753a"
    ],
    "name:jpn_x_variant":[
        "\u307f\u306a\u307f\u3057\u3093\u3081\u3044\u3061\u3087\u3046",
        "\u30df\u30ca\u30df\u30b7\u30f3\u30e1\u30a4\u30c1\u30e7\u30a6"
    ],
    "name:und_x_variant":[
        "Minamishinmeich\u014d"
    ],
    "wof:name":"Minamishinmeicho",
    "wof:placetype":"locality"
},
  "geometry": {"coordinates":[140.55237,40.26451],"type":"Point"}
}