{
  "type": "Feature",
  "properties": {
    "gn:admin1_code":"4.0",
    "gn:admin2_code":"9062338.0",
    "gn:asciiname":"Ubara",
    "gn:country_code":"JP",
    "gn:dem":19,
    "gn:feature_class":"P",
    "gn:feature_code":"PPL",
    "gn:name":"Ubara",
    "gn:population":0,
    "gn:timezone":"Asia/Tokyo",
    "iso:country":"JP",
    "name:jpn_x_preferred":[
        "\u9d5c\u539f"
    ],
    "name:jpn_x_variant":[
        "\u3046\u3070\u3089",
        "\u30a6\u30d0\u30e9"
    ],
    "wof:name":"Ubara",
    "wof:placetype":"locality"
},
  "geometry": {"coordinates":[140.27337,35.14075],"type":"Point"}
}