{
  "type": "Feature",
  "properties": {
    "gn:admin1_code":"21.0",
    "gn:admin2_code":"1848441.0",
    "gn:asciiname":"Nichiko",
    "gn:country_code":"JP",
    "gn:dem":311,
    "gn:feature_class":"P",
    "gn:feature_code":"PPLL",
    "gn:name":"Nichik\u014d",
    "gn:population":0,
    "gn:timezone":"Asia/Tokyo",
    "iso:country":"JP",
    "name:jpn_x_preferred":[
        "\u65e5\u5149"
    ],
    "name:jpn_x_variant":[
        "\u306b\u3061\u3053\u3046",
        "\u30cb\u30c1\u30b3\u30a6"
    ],
    "name:und_x_variant":[
        "Nichik\u014d"
    ],
    "wof:name":"Nichiko",
    "wof:placetype":"locality"
},
  "geometry": {"coordinates":[130.70473000000001,32.44154],"type":"Point"}
}