{
  "type": "Feature",
  "properties": {
    "gn:admin1_code":"2.0",
    "gn:admin2_code":"2128783.0",
    "gn:asciiname":"Morikoshi",
    "gn:country_code":"JP",
    "gn:dem":192,
    "gn:feature_class":"P",
    "gn:feature_code":"PPLL",
    "gn:name":"Morikoshi",
    "gn:population":0,
    "gn:timezone":"Asia/Tokyo",
    "iso:country":"JP",
    "name:jpn_x_preferred":[
        "\u68ee\u8d8a"
    ],
    "wof:name":"Morikoshi",
    "wof:placetype":"locality"
},
  "geometry": {"coordinates":[140.65433000000002,40.13086],"type":"Point"}
}