{
  "type": "Feature",
  "properties": {
    "gn:admin1_code":"30",
    "gn:admin2_code":"1853234.0",
    "gn:asciiname":"Uematsu",
    "gn:country_code":"JP",
    "gn:dem":51,
    "gn:feature_class":"P",
    "gn:feature_code":"PPL",
    "gn:name":"Uematsu",
    "gn:population":0,
    "gn:timezone":"Asia/Tokyo",
    "iso:country":"JP",
    "name:ita_x_preferred":[
        "Uematsu"
    ],
    "wof:name":"Uematsu",
    "wof:placetype":"locality"
},
  "geometry": {"coordinates":[131.84999999999999,32.98333],"type":"Point"}
}