{
  "type": "Feature",
  "properties": {
    "gn:admin1_code":"23.0",
    "gn:admin2_code":"1856290.0",
    "gn:asciiname":"Minowa-nakamura",
    "gn:country_code":"JP",
    "gn:dem":209,
    "gn:feature_class":"P",
    "gn:feature_code":"PPL",
    "gn:name":"Minowa-nakamura",
    "gn:population":0,
    "gn:timezone":"Asia/Tokyo",
    "iso:country":"JP",
    "name:jpn_x_preferred":[
        "\u7b95\u66f2\u4e2d\u6751"
    ],
    "wof:name":"Minowa-nakamura",
    "wof:placetype":"locality"
},
  "geometry": {"coordinates":[136.08848,34.61063],"type":"Point"}
}