{
  "type": "Feature",
  "properties": {
    "gn:admin1_code":"44.0",
    "gn:admin2_code":"1849562.0",
    "gn:asciiname":"Yutagawa",
    "gn:country_code":"JP",
    "gn:dem":19,
    "gn:feature_class":"P",
    "gn:feature_code":"PPL",
    "gn:name":"Yutagawa",
    "gn:population":0,
    "gn:timezone":"Asia/Tokyo",
    "iso:country":"JP",
    "name:jpn_x_preferred":[
        "\u6e6f\u7530\u5ddd"
    ],
    "wof:name":"Yutagawa",
    "wof:placetype":"locality"
},
  "geometry": {"coordinates":[139.77227999999999,38.69649],"type":"Point"}
}