{
  "type": "Feature",
  "properties": {
    "gn:admin1_code":"15.0",
    "gn:admin2_code":"1860845.0",
    "gn:asciiname":"Shiohamamachi",
    "gn:country_code":"JP",
    "gn:dem":11,
    "gn:feature_class":"P",
    "gn:feature_code":"PPL",
    "gn:name":"Shiohamamachi",
    "gn:population":0,
    "gn:timezone":"Asia/Tokyo",
    "iso:country":"JP",
    "name:jpn_x_preferred":[
        "\u5869\u6d5c\u753a"
    ],
    "wof:name":"Shiohamamachi",
    "wof:placetype":"locality"
},
  "geometry": {"coordinates":[136.33340999999999,36.35517],"type":"Point"}
}