{
  "type": "Feature",
  "properties": {
    "gn:admin1_code":"7.0",
    "gn:admin2_code":"1859306.0",
    "gn:admin3_code":"40105.0",
    "gn:asciiname":"Kannonjicho",
    "gn:country_code":"JP",
    "gn:dem":19,
    "gn:feature_class":"P",
    "gn:feature_code":"PPL",
    "gn:name":"Kannonjich\u014d",
    "gn:population":0,
    "gn:timezone":"Asia/Tokyo",
    "iso:country":"JP",
    "name:jpn_x_preferred":[
        "\u89b3\u97f3\u5bfa\u753a"
    ],
    "name:und_x_variant":[
        "Kannonjich\u014d"
    ],
    "wof:name":"Kannonjicho",
    "wof:placetype":"locality"
},
  "geometry": {"coordinates":[130.83008000000001,33.88374],"type":"Point"}
}