{
  "type": "Feature",
  "properties": {
    "gn:admin1_code":"34.0",
    "gn:admin2_code":"1863058.0",
    "gn:asciiname":"Ayase",
    "gn:country_code":"JP",
    "gn:dem":13,
    "gn:feature_class":"P",
    "gn:feature_code":"PPL",
    "gn:name":"Ayase",
    "gn:population":0,
    "gn:timezone":"Asia/Tokyo",
    "iso:country":"JP",
    "name:ita_x_preferred":[
        "Ayase"
    ],
    "name:jpn_x_preferred":[
        "\u7dbe\u702c"
    ],
    "name:jpn_x_variant":[
        "\u3042\u3084\u305b",
        "\u30a2\u30e4\u30bb"
    ],
    "name:ukr_x_preferred":[
        "\u0410\u044f\u0441\u0435"
    ],
    "wof:name":"Ayase",
    "wof:placetype":"locality"
},
  "geometry": {"coordinates":[139.64507,35.98228],"type":"Point"}
}