{
  "type": "Feature",
  "properties": {
    "gn:admin1_code":"4.0",
    "gn:admin2_code":"2112386.0",
    "gn:asciiname":"Narigawa",
    "gn:country_code":"JP",
    "gn:dem":56,
    "gn:feature_class":"P",
    "gn:feature_code":"PPL",
    "gn:name":"Narigawa",
    "gn:population":0,
    "gn:timezone":"Asia/Tokyo",
    "iso:country":"JP",
    "name:jpn_x_preferred":[
        "\u6210\u5ddd"
    ],
    "name:jpn_x_variant":[
        "\u306a\u308a\u304c\u308f",
        "\u30ca\u30ea\u30ac\u30ef"
    ],
    "wof:name":"Narigawa",
    "wof:placetype":"locality"
},
  "geometry": {"coordinates":[140.03076999999999,35.13958],"type":"Point"}
}