{
  "type": "Feature",
  "properties": {
    "gn:admin1_code":"29.0",
    "gn:admin2_code":"1853313.0",
    "gn:asciiname":"Aono",
    "gn:country_code":"JP",
    "gn:dem":52,
    "gn:feature_class":"P",
    "gn:feature_code":"PPL",
    "gn:name":"Aono",
    "gn:population":0,
    "gn:timezone":"Asia/Tokyo",
    "iso:country":"JP",
    "name:jpn_x_preferred":[
        "\u9752\u91ce"
    ],
    "wof:name":"Aono",
    "wof:placetype":"locality"
},
  "geometry": {"coordinates":[138.30448999999999,38.01407],"type":"Point"}
}