{
  "type": "Feature",
  "properties": {
    "gn:admin1_code":"18.0",
    "gn:admin2_code":"1851576.0",
    "gn:admin3_code":"46468.0",
    "gn:asciiname":"Mochidome",
    "gn:country_code":"JP",
    "gn:dem":96,
    "gn:feature_class":"P",
    "gn:feature_code":"PPL",
    "gn:name":"Mochidome",
    "gn:population":0,
    "gn:timezone":"Asia/Tokyo",
    "iso:country":"JP",
    "name:jpn_x_preferred":[
        "\u6301\u7559"
    ],
    "wof:name":"Mochidome",
    "wof:placetype":"locality"
},
  "geometry": {"coordinates":[130.96231,31.46306],"type":"Point"}
}