{
  "type": "Feature",
  "properties": {
    "gn:admin1_code":"7.0",
    "gn:admin2_code":"1848086.0",
    "gn:asciiname":"Yoshikuni",
    "gn:country_code":"JP",
    "gn:dem":8,
    "gn:feature_class":"P",
    "gn:feature_code":"PPL",
    "gn:name":"Yoshikuni",
    "gn:population":0,
    "gn:timezone":"Asia/Tokyo",
    "iso:country":"JP",
    "name:jpn_x_preferred":[
        "\u5409\u56fd"
    ],
    "wof:name":"Yoshikuni",
    "wof:placetype":"locality"
},
  "geometry": {"coordinates":[130.94537,33.72237],"type":"Point"}
}