{
  "type": "Feature",
  "properties": {
    "gn:admin1_code":"28.0",
    "gn:admin2_code":"1848164.0",
    "gn:admin3_code":"29449.0",
    "gn:asciiname":"Kurihira",
    "gn:country_code":"JP",
    "gn:dem":403,
    "gn:feature_class":"P",
    "gn:feature_code":"PPLL",
    "gn:name":"Kurihira",
    "gn:population":0,
    "gn:timezone":"Asia/Tokyo",
    "iso:country":"JP",
    "name:jpn_x_preferred":[
        "\u6817\u5e73"
    ],
    "wof:name":"Kurihira",
    "wof:placetype":"locality"
},
  "geometry": {"coordinates":[135.81783999999999,34.0782],"type":"Point"}
}