{
  "type": "Feature",
  "properties": {
    "gn:admin1_code":"6.0",
    "gn:admin2_code":"1863982.0",
    "gn:asciiname":"Uenocho",
    "gn:country_code":"JP",
    "gn:dem":18,
    "gn:feature_class":"P",
    "gn:feature_code":"PPL",
    "gn:name":"Uenoch\u014d",
    "gn:population":0,
    "gn:timezone":"Asia/Tokyo",
    "iso:country":"JP",
    "name:jpn_x_preferred":[
        "\u4e0a\u91ce\u753a"
    ],
    "name:und_x_variant":[
        "Uenoch\u014d"
    ],
    "wof:name":"Uenocho",
    "wof:placetype":"locality"
},
  "geometry": {"coordinates":[136.14726000000002,36.14113],"type":"Point"}
}