{
  "type": "Feature",
  "properties": {
    "gn:admin1_code":"4.0",
    "gn:admin2_code":"1863711.0",
    "gn:asciiname":"Negata",
    "gn:country_code":"JP",
    "gn:dem":35,
    "gn:feature_class":"P",
    "gn:feature_code":"PPLL",
    "gn:name":"Negata",
    "gn:population":0,
    "gn:timezone":"Asia/Tokyo",
    "iso:country":"JP",
    "name:jpn_x_preferred":[
        "\u6839\u65b9"
    ],
    "name:jpn_x_variant":[
        "\u306d\u304c\u305f",
        "\u30cd\u30ac\u30bf"
    ],
    "wof:name":"Negata",
    "wof:placetype":"locality"
},
  "geometry": {"coordinates":[139.87913,35.29061],"type":"Point"}
}