{
  "type": "Feature",
  "properties": {
    "gn:admin1_code":"19.0",
    "gn:admin2_code":"1848350.0",
    "gn:admin3_code":"14111.0",
    "gn:asciiname":"Hinochuo",
    "gn:country_code":"JP",
    "gn:dem":24,
    "gn:feature_class":"P",
    "gn:feature_code":"PPL",
    "gn:name":"Hinoch\u016b\u014d",
    "gn:population":0,
    "gn:timezone":"Asia/Tokyo",
    "iso:country":"JP",
    "name:jpn_x_preferred":[
        "\u65e5\u91ce\u4e2d\u592e"
    ],
    "name:jpn_x_variant":[
        "\u3072\u306e\u3061\u3085\u3046\u304a\u3046",
        "\u30d2\u30ce\u30c1\u30e5\u30a6\u30aa\u30a6"
    ],
    "name:und_x_variant":[
        "Hinoch\u016b\u014d"
    ],
    "wof:name":"Hinochuo",
    "wof:placetype":"locality"
},
  "geometry": {"coordinates":[139.58446999999998,35.38476],"type":"Point"}
}