{
  "type": "Feature",
  "properties": {
    "gn:admin1_code":"4.0",
    "gn:admin2_code":"2112663.0",
    "gn:asciiname":"Nakatakane",
    "gn:country_code":"JP",
    "gn:dem":86,
    "gn:feature_class":"P",
    "gn:feature_code":"PPL",
    "gn:name":"Nakatakane",
    "gn:population":0,
    "gn:timezone":"Asia/Tokyo",
    "iso:country":"JP",
    "name:jpn_x_preferred":[
        "\u4e2d\u9ad8\u6839"
    ],
    "name:jpn_x_variant":[
        "\u306a\u304b\u305f\u304b\u306d",
        "\u30ca\u30ab\u30bf\u30ab\u30cd"
    ],
    "wof:name":"Nakatakane",
    "wof:placetype":"locality"
},
  "geometry": {"coordinates":[140.09645,35.43059],"type":"Point"}
}