{
  "type": "Feature",
  "properties": {
    "gn:admin1_code":"19.0",
    "gn:admin2_code":"1863429.0",
    "gn:asciiname":"Kitayana",
    "gn:country_code":"JP",
    "gn:dem":42,
    "gn:feature_class":"P",
    "gn:feature_code":"PPL",
    "gn:name":"Kitayana",
    "gn:population":0,
    "gn:timezone":"Asia/Tokyo",
    "iso:country":"JP",
    "name:jpn_x_preferred":[
        "\u5317\u77e2\u540d"
    ],
    "wof:name":"Kitayana",
    "wof:placetype":"locality"
},
  "geometry": {"coordinates":[139.26809,35.37617],"type":"Point"}
}