{
  "type": "Feature",
  "properties": {
    "gn:admin1_code":"29",
    "gn:admin2_code":"7468178.0",
    "gn:asciiname":"Hama-konoura",
    "gn:cc2":"JP",
    "gn:country_code":"JP",
    "gn:dem":76,
    "gn:feature_class":"P",
    "gn:feature_code":"PPL",
    "gn:name":"Hama-konoura",
    "gn:population":0,
    "gn:timezone":"Asia/Tokyo",
    "iso:country":"JP",
    "name:und_x_variant":[
        "Hama-konouya",
        "Hama-kiura",
        "Hama-konoura"
    ],
    "wof:name":"Hama-konoura",
    "wof:placetype":"locality"
},
  "geometry": {"coordinates":[137.96666999999999,37.08333],"type":"Point"}
}