{
  "type": "Feature",
  "properties": {
    "gn:admin1_code":"3.0",
    "gn:admin2_code":"2128134.0",
    "gn:admin3_code":"2423.0",
    "gn:asciiname":"Okoppe",
    "gn:country_code":"JP",
    "gn:dem":22,
    "gn:feature_class":"P",
    "gn:feature_code":"PPL",
    "gn:name":"Okoppe",
    "gn:population":0,
    "gn:timezone":"Asia/Tokyo",
    "iso:country":"JP",
    "name:jpn_x_preferred":[
        "\u5965\u6238"
    ],
    "name:jpn_x_variant":[
        "\u304a\u3053\u3063\u307a",
        "\u30aa\u30b3\u30c3\u30da"
    ],
    "wof:name":"Okoppe",
    "wof:placetype":"locality"
},
  "geometry": {"coordinates":[140.91246000000001,41.49158],"type":"Point"}
}