{
  "type": "Feature",
  "properties": {
    "gn:admin1_code":"46.0",
    "gn:asciiname":"Kamiyano",
    "gn:country_code":"JP",
    "gn:dem":234,
    "gn:feature_class":"P",
    "gn:feature_code":"PPLL",
    "gn:name":"Kamiyano",
    "gn:population":0,
    "gn:timezone":"Asia/Tokyo",
    "iso:country":"JP",
    "name:jpn_x_preferred":[
        "\u795e\u77e2\u91ce"
    ],
    "wof:name":"Kamiyano",
    "wof:placetype":"locality"
},
  "geometry": {"coordinates":[138.53213,35.26759000000001],"type":"Point"}
}