{
  "type": "Feature",
  "properties": {
    "iso:country":"JP",
    "name:eng_x_preferred":[
        "Hase 1 Chome"
    ],
    "name:eng_x_variant":[
        "Hase 1 Choume",
        "Hase 1 Chome"
    ],
    "name:jpn_x_preferred":[
        "\uff11\u4e01\u76ee"
    ],
    "name:jpn_x_variant":[
        "\u306f\u305b \uff11\u3061\u3087\u3046\u3081",
        "\u9577\u8c37 \uff11\u4e01\u76ee",
        "\uff11\u3061\u3087\u3046\u3081"
    ],
    "name:unk_x_variant":[
        "\uff11\u4e01\u76ee"
    ],
    "qs:gn_local":0,
    "qs:local_max":2484,
    "qs:local_sum":33815,
    "qs:localhoods":49,
    "qs:name":"\uff11\u4e01\u76ee",
    "qs:name_adm0":"\u65e5\u672c",
    "qs:name_adm1":"\u795e\u5948\u5ddd\u770c",
    "qs:name_en":"Hase 1 Chome",
    "qs:name_lau":"\u9577\u8c37",
    "qs:name_local":"\u938c\u5009\u5e02",
    "qs:photo_max":193,
    "qs:photo_sum":265,
    "qs:placetype":"Suburb",
    "qs:quad_count":2,
    "qs:woe_adm0":23424856,
    "qs:woe_adm1":2345868,
    "qs:woe_adm2":0,
    "qs:woe_lau":28416755,
    "qs:woe_local":1117401,
    "qs:woe_ver":"7.10.0",
    "wof:lang":[
        "jpn"
    ],
    "wof:name":"\uff11\u4e01\u76ee",
    "wof:placetype":"neighbourhood"
},
  "geometry": {"coordinates":[139.53873100000001,35.314609],"type":"Point"}
}