{
  "type": "Feature",
  "properties": {
    "iso:country":"JP",
    "name:eng_x_preferred":[
        "Haracho 6 Chome"
    ],
    "name:eng_x_variant":[
        "Harachou 6 Choume",
        "Haracho 6 Chome"
    ],
    "name:jpn_x_preferred":[
        "\uff16\u4e01\u76ee"
    ],
    "name:jpn_x_variant":[
        "\u306f\u3089\u3061\u3087\u3046 \uff16\u3061\u3087\u3046\u3081",
        "\u539f\u753a \uff16\u4e01\u76ee",
        "\uff16\u3061\u3087\u3046\u3081"
    ],
    "qs:gn_local":0,
    "qs:local_max":106,
    "qs:local_sum":156,
    "qs:localhoods":3,
    "qs:name":"\uff16\u4e01\u76ee",
    "qs:name_adm0":"\u65e5\u672c",
    "qs:name_adm1":"\u5927\u962a\u5e9c",
    "qs:name_en":"Haracho 6 Chome",
    "qs:name_lau":"\u539f\u753a",
    "qs:name_local":"\u6cb3\u5185\u9577\u91ce\u5e02",
    "qs:photo_max":20,
    "qs:photo_sum":47,
    "qs:placetype":"Suburb",
    "qs:quad_count":9,
    "qs:woe_adm0":23424856,
    "qs:woe_adm1":2345881,
    "qs:woe_adm2":0,
    "qs:woe_lau":28459608,
    "qs:woe_local":15015433,
    "qs:woe_ver":"7.10.0",
    "wof:lang":[
        "jpn"
    ],
    "wof:name":"\uff16\u4e01\u76ee",
    "wof:placetype":"neighbourhood"
},
  "geometry": {"coordinates":[135.56943799999999,34.451987],"type":"Point"}
}