{
  "type": "Feature",
  "properties": {
    "gn:admin1_code":"42.0",
    "gn:admin2_code":"1855873.0",
    "gn:admin3_code":"16323.0",
    "gn:asciiname":"Nagakura",
    "gn:country_code":"JP",
    "gn:dem":423,
    "gn:feature_class":"P",
    "gn:feature_code":"PPL",
    "gn:name":"Nagakura",
    "gn:population":0,
    "gn:timezone":"Asia/Tokyo",
    "iso:country":"JP",
    "name:deu_x_preferred":[
        "Nagakura"
    ],
    "name:jpn_x_preferred":[
        "\u9577\u5009"
    ],
    "wof:name":"Nagakura",
    "wof:placetype":"locality"
},
  "geometry": {"coordinates":[137.39122,36.61117],"type":"Point"}
}