{
  "type": "Feature",
  "properties": {
    "iso:country":"JP",
    "qs:name":"\u56fd\u982d\u6751",
    "qs:name_adm0":"\u65e5\u672c",
    "qs:name_adm1":"\u6c96\u7e04\u770c",
    "qs:photos":2087,
    "qs:photos_1k":423,
    "qs:photos_9k":9,
    "qs:photos_9r":9,
    "qs:photos_all":2087,
    "qs:photos_sr":16,
    "qs:placetype":"Town",
    "qs:pop_sr":"0",
    "wof:name":"\u56fd\u982d\u6751",
    "wof:placetype":"locality"
},
  "geometry": {"coordinates":[128.17438000000001,26.727777],"type":"Point"}
}