{
  "type": "Feature",
  "properties": {
    "gn:admin1_code":"09",
    "gn:admin2_code":"1863645.0",
    "gn:asciiname":"Hagiwara",
    "gn:country_code":"JP",
    "gn:dem":697,
    "gn:feature_class":"P",
    "gn:feature_code":"PPL",
    "gn:name":"Hagiwara",
    "gn:population":0,
    "gn:timezone":"Asia/Tokyo",
    "iso:country":"JP",
    "wof:name":"Hagiwara",
    "wof:placetype":"locality"
},
  "geometry": {"coordinates":[137.19999999999999,35.86667],"type":"Point"}
}