{
  "type": "Feature",
  "properties": {
    "gn:admin1_code":"3.0",
    "gn:admin2_code":"2130088.0",
    "gn:admin3_code":"2301.0",
    "gn:asciiname":"Tateishiko",
    "gn:country_code":"JP",
    "gn:dem":56,
    "gn:feature_class":"P",
    "gn:feature_code":"PPL",
    "gn:name":"Tateishiko",
    "gn:population":0,
    "gn:timezone":"Asia/Tokyo",
    "iso:country":"JP",
    "name:jpn_x_preferred":[
        "\u7acb\u77f3\u5b50"
    ],
    "name:jpn_x_variant":[
        "\u305f\u3066\u3044\u3057\u3053",
        "\u30bf\u30c6\u30a4\u30b7\u30b3"
    ],
    "wof:name":"Tateishiko",
    "wof:placetype":"locality"
},
  "geometry": {"coordinates":[140.91833,40.99118],"type":"Point"}
}