{
  "type": "Feature",
  "properties": {
    "gn:admin1_code":"21.0",
    "gn:admin2_code":"1848443.0",
    "gn:admin3_code":"43468.0",
    "gn:asciiname":"Haramakida",
    "gn:country_code":"JP",
    "gn:dem":40,
    "gn:feature_class":"P",
    "gn:feature_code":"PPLL",
    "gn:name":"Haramakida",
    "gn:population":0,
    "gn:timezone":"Asia/Tokyo",
    "iso:country":"JP",
    "name:jpn_x_preferred":[
        "\u8179\u5dfb\u7530"
    ],
    "name:jpn_x_variant":[
        "\u306f\u3089\u307e\u304d\u3060",
        "\u30cf\u30e9\u30de\u30ad\u30c0"
    ],
    "wof:name":"Haramakida",
    "wof:placetype":"locality"
},
  "geometry": {"coordinates":[130.68039999999999,32.54645],"type":"Point"}
}