{
  "type": "Feature",
  "properties": {
    "gn:admin1_code":"2.0",
    "gn:admin2_code":"1854681.0",
    "gn:asciiname":"Ishida-kawara",
    "gn:country_code":"JP",
    "gn:dem":8,
    "gn:feature_class":"P",
    "gn:feature_code":"PPLL",
    "gn:name":"Ishida-kawara",
    "gn:population":0,
    "gn:timezone":"Asia/Tokyo",
    "iso:country":"JP",
    "name:jpn_x_preferred":[
        "\u77f3\u7530\u5ddd\u539f"
    ],
    "wof:name":"Ishida-kawara",
    "wof:placetype":"locality"
},
  "geometry": {"coordinates":[139.94661000000002,40.04278],"type":"Point"}
}