{
  "type": "Feature",
  "properties": {
    "gn:admin1_code":"7.0",
    "gn:admin2_code":"1854081.0",
    "gn:asciiname":"Kubuki",
    "gn:country_code":"JP",
    "gn:dem":16,
    "gn:feature_class":"P",
    "gn:feature_code":"PPL",
    "gn:name":"Kubuki",
    "gn:population":0,
    "gn:timezone":"Asia/Tokyo",
    "iso:country":"JP",
    "name:jpn_x_preferred":[
        "\u4e45\u798f\u6728"
    ],
    "wof:name":"Kubuki",
    "wof:placetype":"locality"
},
  "geometry": {"coordinates":[130.48138,33.05658],"type":"Point"}
}