{
  "type": "Feature",
  "properties": {
    "gn:admin1_code":"4.0",
    "gn:admin2_code":"2111854.0",
    "gn:asciiname":"Senzawa",
    "gn:country_code":"JP",
    "gn:dem":6,
    "gn:feature_class":"P",
    "gn:feature_code":"PPL",
    "gn:name":"Senzawa",
    "gn:population":0,
    "gn:timezone":"Asia/Tokyo",
    "iso:country":"JP",
    "name:jpn_x_preferred":[
        "\u5343\u6ca2"
    ],
    "name:jpn_x_variant":[
        "\u305b\u3093\u3056\u308f",
        "\u30bb\u30f3\u30b6\u30ef"
    ],
    "wof:name":"Senzawa",
    "wof:placetype":"locality"
},
  "geometry": {"coordinates":[140.35319999999999,35.46927],"type":"Point"}
}