{
  "type": "Feature",
  "properties": {
    "gn:admin1_code":"4.0",
    "gn:admin2_code":"2112557.0",
    "gn:admin3_code":"12441.0",
    "gn:asciiname":"Komyo",
    "gn:country_code":"JP",
    "gn:dem":90,
    "gn:feature_class":"P",
    "gn:feature_code":"PPL",
    "gn:name":"Komy\u014d",
    "gn:population":0,
    "gn:timezone":"Asia/Tokyo",
    "iso:country":"JP",
    "name:jpn_x_preferred":[
        "\u5c0f\u82d7"
    ],
    "name:jpn_x_variant":[
        "\u3053\u307f\u3087\u3046",
        "\u30b3\u30df\u30e7\u30a6"
    ],
    "name:und_x_variant":[
        "Komy\u014d"
    ],
    "wof:name":"Komyo",
    "wof:placetype":"locality"
},
  "geometry": {"coordinates":[140.21388999999999,35.2603],"type":"Point"}
}