{
  "type": "Feature",
  "properties": {
    "gn:admin1_code":"24.0",
    "gn:admin2_code":"2112574.0",
    "gn:asciiname":"Kokucho",
    "gn:country_code":"JP",
    "gn:dem":6,
    "gn:feature_class":"P",
    "gn:feature_code":"PPL",
    "gn:name":"Kokuch\u014d",
    "gn:population":0,
    "gn:timezone":"Asia/Tokyo",
    "iso:country":"JP",
    "name:jpn_x_preferred":[
        "\u7a40\u753a"
    ],
    "name:jpn_x_variant":[
        "\u3053\u304f\u3061\u3087\u3046",
        "\u30b3\u30af\u30c1\u30e7\u30a6"
    ],
    "name:und_x_variant":[
        "Kokuch\u014d"
    ],
    "wof:name":"Kokucho",
    "wof:placetype":"locality"
},
  "geometry": {"coordinates":[141.30192,38.43348],"type":"Point"}
}