{
  "type": "Feature",
  "properties": {
    "gn:admin1_code":"21.0",
    "gn:admin2_code":"7413150.0",
    "gn:asciiname":"Kaomachi-niodo",
    "gn:country_code":"JP",
    "gn:dem":98,
    "gn:feature_class":"P",
    "gn:feature_code":"PPL",
    "gn:name":"Ka\u014dmachi-ni\u014dd\u014d",
    "gn:population":0,
    "gn:timezone":"Asia/Tokyo",
    "iso:country":"JP",
    "name:jpn_x_preferred":[
        "\u9e7f\u592e\u753a\u4ec1\u738b\u5802"
    ],
    "name:jpn_x_variant":[
        "\u304b\u304a\u3046\u307e\u3061\u306b\u304a\u3046\u3069\u3046",
        "\u30ab\u30aa\u30a6\u30de\u30c1\u30cb\u30aa\u30a6\u30c9\u30a6"
    ],
    "name:und_x_variant":[
        "Ka\u014dmachi-ni\u014dd\u014d"
    ],
    "wof:name":"Kaomachi-niodo",
    "wof:placetype":"locality"
},
  "geometry": {"coordinates":[130.65348999999998,32.94809],"type":"Point"}
}