{
  "type": "Feature",
  "properties": {
    "gn:admin1_code":"34.0",
    "gn:admin2_code":"1859726.0",
    "gn:asciiname":"Maekamicho",
    "gn:country_code":"JP",
    "gn:dem":8,
    "gn:feature_class":"P",
    "gn:feature_code":"PPL",
    "gn:name":"Maekamich\u014d",
    "gn:population":0,
    "gn:timezone":"Asia/Tokyo",
    "iso:country":"JP",
    "name:jpn_x_preferred":[
        "\u524d\u4e0a\u753a"
    ],
    "name:jpn_x_variant":[
        "\u307e\u3048\u304b\u307f\u3061\u3087\u3046",
        "\u30de\u30a8\u30ab\u30df\u30c1\u30e7\u30a6"
    ],
    "name:und_x_variant":[
        "Maekamich\u014d"
    ],
    "wof:name":"Maekamicho",
    "wof:placetype":"locality"
},
  "geometry": {"coordinates":[139.71509,35.83436],"type":"Point"}
}