{
  "type": "Feature",
  "properties": {
    "iso:country":"JP",
    "name:eng_x_preferred":[
        "Yurihama Town"
    ],
    "name:jpn_x_preferred":[
        "\u6e6f\u68a8\u6d5c\u753a"
    ],
    "qs:name":"\u6e6f\u68a8\u6d5c\u753a",
    "qs:name_adm0":"\u65e5\u672c",
    "qs:name_adm1":"\u9ce5\u53d6\u770c",
    "qs:photos":146,
    "qs:photos_1k":30,
    "qs:photos_9k":1,
    "qs:photos_9r":3,
    "qs:photos_all":146,
    "qs:photos_sr":3,
    "qs:placetype":"Town",
    "qs:pop_sr":"0",
    "wof:name":"Yurihama Town",
    "wof:placetype":"locality"
},
  "geometry": {"coordinates":[133.89166800000001,35.487511],"type":"Point"}
}