{
  "type": "Feature",
  "properties": {
    "gn:admin1_code":"21.0",
    "gn:admin2_code":"7413150.0",
    "gn:asciiname":"Shimohodata",
    "gn:country_code":"JP",
    "gn:dem":33,
    "gn:feature_class":"P",
    "gn:feature_code":"PPLL",
    "gn:name":"Shimohodata",
    "gn:population":0,
    "gn:timezone":"Asia/Tokyo",
    "iso:country":"JP",
    "name:jpn_x_preferred":[
        "\u4e0b\u4fdd\u591a\u7530"
    ],
    "name:jpn_x_variant":[
        "\u3057\u3082\u307b\u3060\u305f",
        "\u30b7\u30e2\u30db\u30c0\u30bf"
    ],
    "wof:name":"Shimohodata",
    "wof:placetype":"locality"
},
  "geometry": {"coordinates":[130.65471000000002,33.00728],"type":"Point"}
}