{
  "type": "Feature",
  "properties": {
    "gn:admin1_code":"04",
    "gn:admin2_code":"2110578.0",
    "gn:asciiname":"Shimadadai",
    "gn:country_code":"JP",
    "gn:dem":24,
    "gn:feature_class":"P",
    "gn:feature_code":"PPL",
    "gn:name":"Shimadadai",
    "gn:population":0,
    "gn:timezone":"Asia/Tokyo",
    "iso:country":"JP",
    "wof:name":"Shimadadai",
    "wof:placetype":"locality"
},
  "geometry": {"coordinates":[140.09999999999999,35.76667],"type":"Point"}
}