{
  "type": "Feature",
  "properties": {
    "gn:admin1_code":"7.0",
    "gn:admin2_code":"1854055.0",
    "gn:admin3_code":"40381.0",
    "gn:asciiname":"Hamayu",
    "gn:country_code":"JP",
    "gn:dem":9,
    "gn:feature_class":"P",
    "gn:feature_code":"PPLL",
    "gn:name":"Hamay\u016b",
    "gn:population":0,
    "gn:timezone":"Asia/Tokyo",
    "iso:country":"JP",
    "name:jpn_x_preferred":[
        "\u306f\u307e\u3086\u3046"
    ],
    "name:und_x_variant":[
        "Hamay\u016b"
    ],
    "wof:name":"Hamayu",
    "wof:placetype":"locality"
},
  "geometry": {"coordinates":[130.67182,33.91126],"type":"Point"}
}