{
  "type": "Feature",
  "properties": {
    "gn:admin1_code":"7.0",
    "gn:admin2_code":"1859306.0",
    "gn:admin3_code":"40101.0",
    "gn:asciiname":"Kurokawa-higshi",
    "gn:country_code":"JP",
    "gn:dem":23,
    "gn:feature_class":"P",
    "gn:feature_code":"PPL",
    "gn:name":"Kurokawa-higshi",
    "gn:population":0,
    "gn:timezone":"Asia/Tokyo",
    "iso:country":"JP",
    "name:jpn_x_preferred":[
        "\u9ed2\u5ddd\u6771"
    ],
    "wof:name":"Kurokawa-higshi",
    "wof:placetype":"locality"
},
  "geometry": {"coordinates":[130.98442,33.92812],"type":"Point"}
}