{
  "type": "Feature",
  "properties": {
    "gn:admin1_code":"8.0",
    "gn:admin2_code":"1859662.0",
    "gn:admin3_code":"7423.0",
    "gn:asciiname":"Biwakubi",
    "gn:country_code":"JP",
    "gn:dem":657,
    "gn:feature_class":"P",
    "gn:feature_code":"PPL",
    "gn:name":"Biwakubi",
    "gn:population":0,
    "gn:timezone":"Asia/Tokyo",
    "iso:country":"JP",
    "name:jpn_x_preferred":[
        "\u7435\u7436\u9996"
    ],
    "wof:name":"Biwakubi",
    "wof:placetype":"locality"
},
  "geometry": {"coordinates":[139.67403000000002,37.37027],"type":"Point"}
}