{
  "type": "Feature",
  "properties": {
    "gn:admin1_code":"2.0",
    "gn:admin2_code":"2113122.0",
    "gn:asciiname":"Niida",
    "gn:country_code":"JP",
    "gn:dem":9,
    "gn:feature_class":"P",
    "gn:feature_code":"PPL",
    "gn:name":"Niida",
    "gn:population":0,
    "gn:timezone":"Asia/Tokyo",
    "iso:country":"JP",
    "name:jpn_x_preferred":[
        "\u4ec1\u4e95\u7530"
    ],
    "name:jpn_x_variant":[
        "\u306b\u3044\u3060",
        "\u30cb\u30a4\u30c0"
    ],
    "wof:name":"Niida",
    "wof:placetype":"locality"
},
  "geometry": {"coordinates":[140.13592,39.68621],"type":"Point"}
}