{
  "type": "Feature",
  "properties": {
    "iso:country":"JP",
    "name:eng_x_preferred":[
        "Asahi 5 Chome"
    ],
    "name:eng_x_variant":[
        "Asahi 5 Choume",
        "Asahi 5 Chome"
    ],
    "name:jpn_x_preferred":[
        "\uff15\u4e01\u76ee"
    ],
    "name:jpn_x_variant":[
        "\u3042\u3055\u3072 \uff15\u3061\u3087\u3046\u3081",
        "\u65ed \uff15\u4e01\u76ee",
        "\uff15\u3061\u3087\u3046\u3081"
    ],
    "qs:gn_local":0,
    "qs:local_max":4707,
    "qs:local_sum":7429,
    "qs:localhoods":13,
    "qs:name":"\uff15\u4e01\u76ee",
    "qs:name_adm0":"\u65e5\u672c",
    "qs:name_adm1":"\u5c71\u68a8\u770c",
    "qs:name_en":"Asahi 5 Chome",
    "qs:name_lau":"\u65ed",
    "qs:name_local":"\u5bcc\u58eb\u5409\u7530\u5e02",
    "qs:photo_max":261,
    "qs:photo_sum":1202,
    "qs:placetype":"Suburb",
    "qs:quad_count":36,
    "qs:woe_adm0":23424856,
    "qs:woe_adm1":2345895,
    "qs:woe_adm2":0,
    "qs:woe_lau":28430546,
    "qs:woe_local":1117080,
    "qs:woe_ver":"7.10.0",
    "qs_pg:name":"\uff15\u4e01\u76ee",
    "qs_pg:name_adm0":"\u65e5\u672c",
    "qs_pg:name_adm1":"\u5c71\u68a8\u770c",
    "qs_pg:photos":927,
    "qs_pg:photos_1k":188,
    "qs_pg:photos_9k":4,
    "qs_pg:photos_9r":6,
    "qs_pg:photos_all":927,
    "qs_pg:photos_sr":10,
    "qs_pg:pop_sr":0,
    "qs_pg:qs_pg_placetype":"neighbourhood",
    "qs_pg:qs_pg_placetype_gp":"Suburb",
    "qs_pg:woe_adm0":23424856,
    "woe:adm0_id":23424856,
    "woe:name_adm0":"\u65e5\u672c",
    "woe:name_adm1":"\u5c71\u68a8\u770c",
    "woe:placetype":"Suburb",
    "wof:lang":[
        "jpn"
    ],
    "wof:name":"\uff15\u4e01\u76ee",
    "wof:placetype":"neighbourhood"
},
  "geometry": {"coordinates":[138.77316999999999,35.502739],"type":"Point"}
}