{
  "type": "Feature",
  "properties": {
    "gn:admin1_code":"21.0",
    "gn:admin2_code":"1864973.0",
    "gn:asciiname":"Uratani",
    "gn:country_code":"JP",
    "gn:dem":864,
    "gn:feature_class":"P",
    "gn:feature_code":"PPLL",
    "gn:name":"Uratani",
    "gn:population":0,
    "gn:timezone":"Asia/Tokyo",
    "iso:country":"JP",
    "name:jpn_x_preferred":[
        "\u6d66\u8c37"
    ],
    "name:jpn_x_variant":[
        "\u3046\u3089\u305f\u306b",
        "\u30a6\u30e9\u30bf\u30cb"
    ],
    "wof:name":"Uratani",
    "wof:placetype":"locality"
},
  "geometry": {"coordinates":[130.98478,33.01071],"type":"Point"}
}