{
  "type": "Feature",
  "properties": {
    "gn:admin1_code":"21.0",
    "gn:admin2_code":"1859488.0",
    "gn:asciiname":"Naga-minamiku",
    "gn:country_code":"JP",
    "gn:dem":115,
    "gn:feature_class":"P",
    "gn:feature_code":"PPLL",
    "gn:name":"Naga-minamiku",
    "gn:population":0,
    "gn:timezone":"Asia/Tokyo",
    "iso:country":"JP",
    "name:jpn_x_preferred":[
        "\u6c38\u5357\u533a"
    ],
    "name:jpn_x_variant":[
        "\u306a\u304c\u307f\u306a\u307f\u304f",
        "\u30ca\u30ac\u30df\u30ca\u30df\u30af"
    ],
    "wof:name":"Naga-minamiku",
    "wof:placetype":"locality"
},
  "geometry": {"coordinates":[130.82221000000001,32.91081],"type":"Point"}
}