{
  "type": "Feature",
  "properties": {
    "gn:admin1_code":"21.0",
    "gn:admin2_code":"7412705.0",
    "gn:admin3_code":"43482.0",
    "gn:asciiname":"Ono",
    "gn:country_code":"JP",
    "gn:dem":159,
    "gn:feature_class":"P",
    "gn:feature_code":"PPL",
    "gn:name":"\u014cno",
    "gn:population":0,
    "gn:timezone":"Asia/Tokyo",
    "iso:country":"JP",
    "name:jpn_x_preferred":[
        "\u5927\u91ce"
    ],
    "name:jpn_x_variant":[
        "\u304a\u304a\u306e",
        "\u30aa\u30aa\u30ce"
    ],
    "name:und_x_variant":[
        "\u014cno"
    ],
    "wof:name":"Ono",
    "wof:placetype":"locality"
},
  "geometry": {"coordinates":[130.56273000000002,32.25994],"type":"Point"}
}