{
  "type": "Feature",
  "properties": {
    "gn:admin1_code":"34.0",
    "gn:admin2_code":"1859726.0",
    "gn:asciiname":"Miyacho",
    "gn:country_code":"JP",
    "gn:dem":6,
    "gn:feature_class":"P",
    "gn:feature_code":"PPL",
    "gn:name":"Miyach\u014d",
    "gn:population":0,
    "gn:timezone":"Asia/Tokyo",
    "iso:country":"JP",
    "name:jpn_x_preferred":[
        "\u5bae\u753a"
    ],
    "name:jpn_x_variant":[
        "\u307f\u3084\u3061\u3087\u3046",
        "\u30df\u30e4\u30c1\u30e7\u30a6"
    ],
    "name:und_x_variant":[
        "Miyach\u014d"
    ],
    "wof:name":"Miyacho",
    "wof:placetype":"locality"
},
  "geometry": {"coordinates":[139.70101,35.80429],"type":"Point"}
}