{
  "type": "Feature",
  "properties": {
    "gn:admin1_code":"23.0",
    "gn:admin2_code":"1853513.0",
    "gn:asciiname":"Mukai",
    "gn:country_code":"JP",
    "gn:dem":25,
    "gn:feature_class":"P",
    "gn:feature_code":"PPL",
    "gn:name":"Mukai",
    "gn:population":0,
    "gn:timezone":"Asia/Tokyo",
    "iso:country":"JP",
    "name:jpn_x_preferred":[
        "\u5411\u4e95"
    ],
    "wof:name":"Mukai",
    "wof:placetype":"locality"
},
  "geometry": {"coordinates":[136.21278000000001,34.06],"type":"Point"}
}