{
  "type": "Feature",
  "properties": {
    "gn:admin1_code":"43",
    "gn:admin2_code":"1848936.0",
    "gn:asciiname":"Komatsubaradori",
    "gn:country_code":"JP",
    "gn:dem":8,
    "gn:feature_class":"P",
    "gn:feature_code":"PPL",
    "gn:name":"Komatsubarad\u014dri",
    "gn:population":0,
    "gn:timezone":"Asia/Tokyo",
    "iso:country":"JP",
    "name:jpn_x_preferred":[
        "\u5c0f\u677e\u539f\u901a"
    ],
    "name:und_x_variant":[
        "Komatsubarad\u014dri"
    ],
    "wof:name":"Komatsubaradori",
    "wof:placetype":"locality"
},
  "geometry": {"coordinates":[135.16838000000001,34.22319],"type":"Point"}
}