{
  "type": "Feature",
  "properties": {
    "gn:admin1_code":"16.0",
    "gn:admin2_code":"2112822.0",
    "gn:asciiname":"Akanuma",
    "gn:country_code":"JP",
    "gn:dem":120,
    "gn:feature_class":"P",
    "gn:feature_code":"PPL",
    "gn:name":"Akanuma",
    "gn:population":0,
    "gn:timezone":"Asia/Tokyo",
    "iso:country":"JP",
    "name:jpn_x_preferred":[
        "\u8d64\u6cbc"
    ],
    "name:jpn_x_variant":[
        "\u3042\u304b\u306c\u307e",
        "\u30a2\u30ab\u30cc\u30de"
    ],
    "wof:name":"Akanuma",
    "wof:placetype":"locality"
},
  "geometry": {"coordinates":[141.04903000000004,39.3964],"type":"Point"}
}