{
  "type": "Feature",
  "properties": {
    "gn:admin1_code":"21.0",
    "gn:admin2_code":"7412709.0",
    "gn:admin3_code":"43348.0",
    "gn:asciiname":"Yasukake",
    "gn:country_code":"JP",
    "gn:dem":173,
    "gn:feature_class":"P",
    "gn:feature_code":"PPLL",
    "gn:name":"Yasukake",
    "gn:population":0,
    "gn:timezone":"Asia/Tokyo",
    "iso:country":"JP",
    "name:jpn_x_preferred":[
        "\u5b89\u639b"
    ],
    "name:jpn_x_variant":[
        "\u3084\u3059\u304b\u3051",
        "\u30e4\u30b9\u30ab\u30b1"
    ],
    "wof:name":"Yasukake",
    "wof:placetype":"locality"
},
  "geometry": {"coordinates":[130.87701999999999,32.61391],"type":"Point"}
}