{
  "type": "Feature",
  "properties": {
    "gn:admin1_code":"4.0",
    "gn:admin2_code":"1859468.0",
    "gn:asciiname":"Osaka",
    "gn:country_code":"JP",
    "gn:dem":57,
    "gn:feature_class":"P",
    "gn:feature_code":"PPL",
    "gn:name":"Osaka",
    "gn:population":0,
    "gn:timezone":"Asia/Tokyo",
    "iso:country":"JP",
    "name:jpn_x_preferred":[
        "\u5927\u5742"
    ],
    "name:jpn_x_variant":[
        "\u304a\u3055\u304b",
        "\u30aa\u30b5\u30ab"
    ],
    "wof:name":"Osaka",
    "wof:placetype":"locality"
},
  "geometry": {"coordinates":[140.04733999999999,35.2576],"type":"Point"}
}