{
  "type": "Feature",
  "properties": {
    "gn:admin1_code":"26",
    "gn:admin2_code":"1856209.0",
    "gn:asciiname":"Aokijimamachi-Aokijima",
    "gn:cc2":"JP",
    "gn:country_code":"JP",
    "gn:dem":353,
    "gn:feature_class":"P",
    "gn:feature_code":"PPL",
    "gn:name":"Aokijimamachi-Aokijima",
    "gn:population":0,
    "gn:timezone":"Asia/Tokyo",
    "iso:country":"JP",
    "name:jpn_x_preferred":[
        "\u9752\u6728\u5cf6\u753a\u9752\u6728\u5cf6"
    ],
    "name:und_x_variant":[
        "Aokijima",
        "Aokijimamachi-Aokijima"
    ],
    "wof:name":"Aokijimamachi-Aokijima",
    "wof:placetype":"locality"
},
  "geometry": {"coordinates":[138.18333000000001,36.61667],"type":"Point"}
}