{
  "type": "Feature",
  "properties": {
    "gn:admin1_code":"19.0",
    "gn:admin2_code":"1855966.0",
    "gn:admin3_code":"14342.0",
    "gn:asciiname":"Kamicho",
    "gn:country_code":"JP",
    "gn:dem":24,
    "gn:feature_class":"P",
    "gn:feature_code":"PPLL",
    "gn:name":"Kamich\u014d",
    "gn:population":0,
    "gn:timezone":"Asia/Tokyo",
    "iso:country":"JP",
    "name:jpn_x_preferred":[
        "\u4e0a\u753a"
    ],
    "name:und_x_variant":[
        "Kamich\u014d"
    ],
    "wof:name":"Kamicho",
    "wof:placetype":"locality"
},
  "geometry": {"coordinates":[139.25898000000001,35.2973],"type":"Point"}
}