{
  "type": "Feature",
  "properties": {
    "gn:admin1_code":"34.0",
    "gn:admin2_code":"1864030.0",
    "gn:asciiname":"Shinden",
    "gn:country_code":"JP",
    "gn:dem":58,
    "gn:feature_class":"P",
    "gn:feature_code":"PPLL",
    "gn:name":"Shinden",
    "gn:population":0,
    "gn:timezone":"Asia/Tokyo",
    "iso:country":"JP",
    "name:jpn_x_preferred":[
        "\u65b0\u7530"
    ],
    "wof:name":"Shinden",
    "wof:placetype":"locality"
},
  "geometry": {"coordinates":[139.23421999999999,36.20869],"type":"Point"}
}