{
  "type": "Feature",
  "properties": {
    "gn:admin1_code":"06",
    "gn:admin2_code":"1854843.0",
    "gn:asciiname":"Onyu",
    "gn:country_code":"JP",
    "gn:dem":11,
    "gn:feature_class":"P",
    "gn:feature_code":"PPL",
    "gn:name":"Ony\u016b",
    "gn:population":0,
    "gn:timezone":"Asia/Tokyo",
    "iso:country":"JP",
    "wof:name":"Onyu",
    "wof:placetype":"locality"
},
  "geometry": {"coordinates":[135.77848,35.48402],"type":"Point"}
}