{
  "type": "Feature",
  "properties": {
    "gn:country":"JP",
    "gn:fcode":"ADM3",
    "gn:pop":0,
    "iso:country":"JP",
    "name:jpn_x_preferred":[
        "\u82c5\u7530\u753a"
    ],
    "name:jpn_x_variant":[
        "\u304b\u3093\u3060\u307e\u3061"
    ],
    "name:unk_x_variant":[
        "Kanda Machi"
    ],
    "qs:name":"Kanda-machi",
    "qs:photos_9r":0,
    "qs:photos_sr":0,
    "qs:pop_sr":"0",
    "wof:name":"Kanda-machi",
    "wof:placetype":"localadmin",
    "wof:population":0
},
  "geometry": {"coordinates":[130.96555000000001,33.7683],"type":"Point"}
}