{
  "type": "Feature",
  "properties": {
    "iso:country":"JP",
    "name:eng_x_preferred":[
        "Gobyo 3 Chome"
    ],
    "name:eng_x_variant":[
        "Gobyou 3 Choume",
        "Gobyo 3 Chome"
    ],
    "name:jpn_x_preferred":[
        "\uff13\u4e01\u76ee"
    ],
    "name:jpn_x_variant":[
        "\u3054\u3073\u3087\u3046 \uff13\u3061\u3087\u3046\u3081",
        "\u5fa1\u5edf \uff13\u4e01\u76ee",
        "\uff13\u3061\u3087\u3046\u3081"
    ],
    "qs:gn_local":0,
    "qs:local_max":247,
    "qs:local_sum":633,
    "qs:localhoods":7,
    "qs:name":"\uff13\u4e01\u76ee",
    "qs:name_adm0":"\u65e5\u672c",
    "qs:name_adm1":"\u5c71\u5f62\u770c",
    "qs:name_en":"Gobyo 3 Chome",
    "qs:name_lau":"\u5fa1\u5edf",
    "qs:name_local":"\u7c73\u6ca2\u5e02",
    "qs:photo_max":15,
    "qs:photo_sum":24,
    "qs:placetype":"Suburb",
    "qs:quad_count":3,
    "qs:woe_adm0":23424856,
    "qs:woe_adm1":2345893,
    "qs:woe_adm2":0,
    "qs:woe_lau":28396456,
    "qs:woe_local":1118558,
    "qs:woe_ver":"7.10.0",
    "wof:lang":[
        "jpn"
    ],
    "wof:name":"\uff13\u4e01\u76ee",
    "wof:placetype":"neighbourhood"
},
  "geometry": {"coordinates":[140.08941999999999,37.91184],"type":"Point"}
}