{
  "type": "Feature",
  "properties": {
    "gn:admin1_code":"23.0",
    "gn:admin2_code":"1849544.0",
    "gn:asciiname":"Hakuzancho-mitsugano",
    "gn:country_code":"JP",
    "gn:dem":72,
    "gn:feature_class":"P",
    "gn:feature_code":"PPL",
    "gn:name":"Hakuzanch\u014d-mitsugano",
    "gn:population":0,
    "gn:timezone":"Asia/Tokyo",
    "iso:country":"JP",
    "name:jpn_x_preferred":[
        "\u767d\u5c71\u753a\u4e09\u30f6\u91ce"
    ],
    "name:und_x_variant":[
        "Hakuzanch\u014d-mitsugano"
    ],
    "wof:name":"Hakuzancho-mitsugano",
    "wof:placetype":"locality"
},
  "geometry": {"coordinates":[136.38477,34.6705],"type":"Point"}
}