{
  "type": "Feature",
  "properties": {
    "gn:admin1_code":"19.0",
    "gn:admin2_code":"1856849.0",
    "gn:asciiname":"Koyato",
    "gn:country_code":"JP",
    "gn:dem":25,
    "gn:feature_class":"P",
    "gn:feature_code":"PPLL",
    "gn:name":"Koyato",
    "gn:population":0,
    "gn:timezone":"Asia/Tokyo",
    "iso:country":"JP",
    "name:jpn_x_preferred":[
        "\u5c0f\u8c37\u6238"
    ],
    "name:jpn_x_variant":[
        "\u3053\u3084\u3068",
        "\u30b3\u30e4\u30c8"
    ],
    "wof:name":"Koyato",
    "wof:placetype":"locality"
},
  "geometry": {"coordinates":[139.63873999999998,35.19252],"type":"Point"}
}