{
  "type": "Feature",
  "properties": {
    "gn:admin1_code":"4.0",
    "gn:admin2_code":"2112997.0",
    "gn:admin3_code":"12424.0",
    "gn:asciiname":"Kitanyuchi",
    "gn:country_code":"JP",
    "gn:dem":1,
    "gn:feature_class":"P",
    "gn:feature_code":"PPLL",
    "gn:name":"Kitany\u016bchi",
    "gn:population":0,
    "gn:timezone":"Asia/Tokyo",
    "iso:country":"JP",
    "name:jpn_x_preferred":[
        "\u5317\u5165\u5730"
    ],
    "name:jpn_x_variant":[
        "\u304d\u305f\u306b\u3085\u3046\u3061",
        "\u30ad\u30bf\u30cb\u30e5\u30a6\u30c1"
    ],
    "name:und_x_variant":[
        "Kitany\u016bchi"
    ],
    "wof:name":"Kitanyuchi",
    "wof:placetype":"locality"
},
  "geometry": {"coordinates":[140.39001999999999,35.47020999999999],"type":"Point"}
}