{
  "type": "Feature",
  "properties": {
    "gn:admin1_code":"21.0",
    "gn:admin2_code":"1857206.0",
    "gn:asciiname":"Hon'yashiki",
    "gn:country_code":"JP",
    "gn:dem":148,
    "gn:feature_class":"P",
    "gn:feature_code":"PPLL",
    "gn:name":"Hon\u2019yashiki",
    "gn:population":0,
    "gn:timezone":"Asia/Tokyo",
    "iso:country":"JP",
    "name:jpn_x_preferred":[
        "\u672c\u5c4b\u6577"
    ],
    "name:jpn_x_variant":[
        "\u307b\u3093\u3084\u3057\u304d",
        "\u30db\u30f3\u30e4\u30b7\u30ad"
    ],
    "name:und_x_variant":[
        "Hon\u2019yashiki"
    ],
    "wof:name":"Hon'yashiki",
    "wof:placetype":"locality"
},
  "geometry": {"coordinates":[130.48466000000002,32.18555],"type":"Point"}
}