{
  "type": "Feature",
  "properties": {
    "gn:admin1_code":"22",
    "gn:admin2_code":"1857764.0",
    "gn:asciiname":"Itsumori",
    "gn:cc2":"JP",
    "gn:country_code":"JP",
    "gn:dem":23,
    "gn:feature_class":"P",
    "gn:feature_code":"PPL",
    "gn:name":"Itsumori",
    "gn:population":0,
    "gn:timezone":"Asia/Tokyo",
    "iso:country":"JP",
    "name:und_x_variant":[
        "Itunomori",
        "Itsutsumori",
        "Itsumori"
    ],
    "wof:name":"Itsumori",
    "wof:placetype":"locality"
},
  "geometry": {"coordinates":[135.34999999999999,35.48333],"type":"Point"}
}