{
  "type": "Feature",
  "properties": {
    "gn:admin1_code":"21.0",
    "gn:admin2_code":"7412709.0",
    "gn:admin3_code":"43348.0",
    "gn:asciiname":"Nakagori",
    "gn:country_code":"JP",
    "gn:dem":87,
    "gn:feature_class":"P",
    "gn:feature_code":"PPL",
    "gn:name":"Nakag\u014dri",
    "gn:population":0,
    "gn:timezone":"Asia/Tokyo",
    "iso:country":"JP",
    "name:jpn_x_preferred":[
        "\u4e2d\u90e1"
    ],
    "name:jpn_x_variant":[
        "\u306a\u304b\u3054\u304a\u308a",
        "\u30ca\u30ab\u30b4\u30aa\u30ea"
    ],
    "name:und_x_variant":[
        "Nakag\u014dri"
    ],
    "wof:name":"Nakagori",
    "wof:placetype":"locality"
},
  "geometry": {"coordinates":[130.80043000000001,32.64396],"type":"Point"}
}