{
  "type": "Feature",
  "properties": {
    "iso:country":"JP",
    "label:eng_x_preferred_longname":[
        "Emukae Town"
    ],
    "label:eng_x_preferred_placetype":[
        "town"
    ],
    "name:eng_x_preferred":[
        "Emukae"
    ],
    "name:eng_x_variant":[
        "Emukae Town"
    ],
    "name:jpn_x_preferred":[
        "\u6c5f\u8fce\u753a"
    ],
    "qs:name":"\u6c5f\u8fce\u753a",
    "qs:name_adm0":"\u65e5\u672c",
    "qs:name_adm1":"\u9577\u5d0e\u770c",
    "qs:photos":18,
    "qs:photos_1k":4,
    "qs:photos_9k":1,
    "qs:photos_9r":1,
    "qs:photos_all":18,
    "qs:photos_sr":1,
    "qs:placetype":"Town",
    "qs:pop_sr":"0",
    "wof:name":"Emukae",
    "wof:placetype":"locality"
},
  "geometry": {"coordinates":[129.66192100000001,33.347314],"type":"Point"}
}