{
  "type": "Feature",
  "properties": {
    "gn:admin1_code":"31.0",
    "gn:admin2_code":"1864698.0",
    "gn:asciiname":"Bizen",
    "gn:country_code":"JP",
    "gn:dem":284,
    "gn:feature_class":"P",
    "gn:feature_code":"PPLA2",
    "gn:name":"Bizen",
    "gn:population":0,
    "gn:timezone":"Asia/Tokyo",
    "iso:country":"JP",
    "name:deu_x_preferred":[
        "Bizen"
    ],
    "name:fra_x_preferred":[
        "Bizen"
    ],
    "name:jpn_x_preferred":[
        "\u5099\u524d"
    ],
    "name:nld_x_preferred":[
        "Bizen"
    ],
    "name:slk_x_preferred":[
        "Bizen"
    ],
    "name:swe_x_preferred":[
        "Bizen"
    ],
    "wof:name":"Bizen",
    "wof:placetype":"locality"
},
  "geometry": {"coordinates":[134.23542,34.78674],"type":"Point"}
}