{
  "type": "Feature",
  "properties": {
    "gn:admin1_code":"37.0",
    "gn:admin2_code":"1863526.0",
    "gn:asciiname":"Ogoyama",
    "gn:country_code":"JP",
    "gn:dem":603,
    "gn:feature_class":"P",
    "gn:feature_code":"PPLL",
    "gn:name":"\u014cgoyama",
    "gn:population":0,
    "gn:timezone":"Asia/Tokyo",
    "iso:country":"JP",
    "name:jpn_x_preferred":[
        "\u5927\u5b50\u5c71"
    ],
    "name:und_x_variant":[
        "\u014cgoyama"
    ],
    "wof:name":"Ogoyama",
    "wof:placetype":"locality"
},
  "geometry": {"coordinates":[138.89068,35.31618],"type":"Point"}
}