{
  "type": "Feature",
  "properties": {
    "gn:admin1_code":"21.0",
    "gn:admin2_code":"1850744.0",
    "gn:admin3_code":"43367.0",
    "gn:asciiname":"Miyao",
    "gn:country_code":"JP",
    "gn:dem":87,
    "gn:feature_class":"P",
    "gn:feature_code":"PPL",
    "gn:name":"Miyao",
    "gn:population":0,
    "gn:timezone":"Asia/Tokyo",
    "iso:country":"JP",
    "name:jpn_x_preferred":[
        "\u5bae\u5c3e"
    ],
    "name:jpn_x_variant":[
        "\u307f\u3084\u304a",
        "\u30df\u30e4\u30aa"
    ],
    "wof:name":"Miyao",
    "wof:placetype":"locality"
},
  "geometry": {"coordinates":[130.52462,33.00602],"type":"Point"}
}