{
  "type": "Feature",
  "properties": {
    "gn:admin1_code":"04",
    "gn:admin2_code":"2110982.0",
    "gn:asciiname":"Yokota",
    "gn:country_code":"JP",
    "gn:dem":16,
    "gn:feature_class":"P",
    "gn:feature_code":"PPL",
    "gn:name":"Yokota",
    "gn:population":0,
    "gn:timezone":"Asia/Tokyo",
    "iso:country":"JP",
    "name:deu_x_preferred":[
        "Yokota"
    ],
    "name:fra_x_preferred":[
        "Yokota"
    ],
    "name:ita_x_preferred":[
        "Yokota"
    ],
    "name:jpn_x_preferred":[
        "\u6a2a\u7530"
    ],
    "name:jpn_x_variant":[
        "\u3088\u3053\u305f",
        "\u30e8\u30b3\u30bf"
    ],
    "name:kor_x_preferred":[
        "\uc694\ucf54\ud0c0"
    ],
    "wof:name":"Yokota",
    "wof:placetype":"locality"
},
  "geometry": {"coordinates":[140.02200000000002,35.38798],"type":"Point"}
}