{
  "type": "Feature",
  "properties": {
    "gn:admin1_code":"47",
    "gn:admin2_code":"7415821.0",
    "gn:asciiname":"Yonashiro-yakena",
    "gn:country_code":"JP",
    "gn:dem":8,
    "gn:feature_class":"P",
    "gn:feature_code":"PPL",
    "gn:name":"Yonashiro-yakena",
    "gn:population":0,
    "gn:timezone":"Asia/Tokyo",
    "iso:country":"JP",
    "name:jpn_x_preferred":[
        "\u4e0e\u90a3\u57ce\u5c4b\u6176\u540d"
    ],
    "name:und_x_variant":[
        "Yakina",
        "Yokena",
        "Yakena",
        "Yonashiro-yakena"
    ],
    "wof:name":"Yonashiro-yakena",
    "wof:placetype":"locality"
},
  "geometry": {"coordinates":[127.9079,26.32556],"type":"Point"}
}