{
  "type": "Feature",
  "properties": {
    "gn:admin1_code":"3.0",
    "gn:admin2_code":"2127674.0",
    "gn:asciiname":"Wajima",
    "gn:country_code":"JP",
    "gn:dem":57,
    "gn:feature_class":"P",
    "gn:feature_code":"PPL",
    "gn:name":"Wajima",
    "gn:population":0,
    "gn:timezone":"Asia/Tokyo",
    "iso:country":"JP",
    "name:ceb_x_preferred":[
        "Wajima"
    ],
    "name:deu_x_preferred":[
        "Wajima"
    ],
    "name:ita_x_preferred":[
        "Wajima"
    ],
    "name:jpn_x_preferred":[
        "\u548c\u5cf6"
    ],
    "name:jpn_x_variant":[
        "\u308f\u3058\u307e",
        "\u30ef\u30b8\u30de"
    ],
    "wof:name":"Wajima",
    "wof:placetype":"locality"
},
  "geometry": {"coordinates":[141.23701,40.57605],"type":"Point"}
}