{
  "type": "Feature",
  "properties": {
    "gn:admin1_code":"01",
    "gn:admin2_code":"1850183.0",
    "gn:asciiname":"Kume",
    "gn:country_code":"JP",
    "gn:dem":18,
    "gn:feature_class":"P",
    "gn:feature_code":"PPL",
    "gn:name":"Kume",
    "gn:population":0,
    "gn:timezone":"Asia/Tokyo",
    "iso:country":"JP",
    "wof:name":"Kume",
    "wof:placetype":"locality"
},
  "geometry": {"coordinates":[136.84999999999999,34.91667],"type":"Point"}
}