{
  "type": "Feature",
  "properties": {
    "iso:country":"JP",
    "name:eng_x_preferred":[
        "Chuocho 2 Chome"
    ],
    "name:eng_x_variant":[
        "Chuuouchou 2 Choume",
        "Chuocho 2 Chome"
    ],
    "name:jpn_x_preferred":[
        "\uff12\u4e01\u76ee"
    ],
    "name:jpn_x_variant":[
        "\u3061\u3085\u3046\u304a\u3046\u3061\u3087\u3046 \uff12\u3061\u3087\u3046\u3081",
        "\u4e2d\u592e\u753a \uff12\u4e01\u76ee",
        "\uff12\u3061\u3087\u3046\u3081"
    ],
    "qs:gn_local":0,
    "qs:local_max":524,
    "qs:local_sum":828,
    "qs:localhoods":6,
    "qs:name":"\uff12\u4e01\u76ee",
    "qs:name_adm0":"\u65e5\u672c",
    "qs:name_adm1":"\u9752\u68ee\u770c",
    "qs:name_en":"Chuocho 2 Chome",
    "qs:name_lau":"\u4e2d\u592e\u753a",
    "qs:name_local":"\u4e09\u6ca2\u5e02",
    "qs:photo_max":435,
    "qs:photo_sum":524,
    "qs:placetype":"Suburb",
    "qs:quad_count":7,
    "qs:woe_adm0":23424856,
    "qs:woe_adm1":2345853,
    "qs:woe_adm2":0,
    "qs:woe_lau":28387977,
    "qs:woe_local":1117733,
    "qs:woe_ver":"7.10.0",
    "wof:lang":[
        "jpn"
    ],
    "wof:name":"\uff12\u4e01\u76ee",
    "wof:placetype":"neighbourhood"
},
  "geometry": {"coordinates":[141.36268100000001,40.680278],"type":"Point"}
}