{
  "type": "Feature",
  "properties": {
    "gn:admin1_code":"2.0",
    "gn:admin2_code":"2111153.0",
    "gn:admin3_code":"5434.0",
    "gn:asciiname":"Utou",
    "gn:country_code":"JP",
    "gn:dem":178,
    "gn:feature_class":"P",
    "gn:feature_code":"PPL",
    "gn:name":"Utou",
    "gn:population":0,
    "gn:timezone":"Asia/Tokyo",
    "iso:country":"JP",
    "name:jpn_x_preferred":[
        "\u5584\u77e5\u9ce5"
    ],
    "wof:name":"Utou",
    "wof:placetype":"locality"
},
  "geometry": {"coordinates":[140.62069,39.44045],"type":"Point"}
}