{
  "type": "Feature",
  "properties": {
    "iso:country":"JP",
    "name:eng_x_preferred":[
        "Kosuganamimachi 1 Chome"
    ],
    "name:eng_x_variant":[
        "Kosuganamimachi 1 Choume",
        "Kosuganamimachi 1 Chome"
    ],
    "name:jpn_x_preferred":[
        "\uff11\u4e01\u76ee"
    ],
    "name:jpn_x_variant":[
        "\u3053\u3059\u304c\u306a\u307f\u307e\u3061 \uff11\u3061\u3087\u3046\u3081",
        "\u5c0f\u83c5\u6ce2\u753a \uff11\u4e01\u76ee",
        "\uff11\u3061\u3087\u3046\u3081"
    ],
    "qs:gn_local":0,
    "qs:local_max":86,
    "qs:local_sum":180,
    "qs:localhoods":3,
    "qs:name":"\uff11\u4e01\u76ee",
    "qs:name_adm0":"\u65e5\u672c",
    "qs:name_adm1":"\u77f3\u5ddd\u770c",
    "qs:name_en":"Kosuganamimachi 1 Chome",
    "qs:name_lau":"\u5c0f\u83c5\u6ce2\u753a",
    "qs:name_local":"\u52a0\u8cc0\u5e02",
    "qs:photo_max":19,
    "qs:photo_sum":49,
    "qs:placetype":"Suburb",
    "qs:quad_count":5,
    "qs:woe_adm0":23424856,
    "qs:woe_adm1":2345864,
    "qs:woe_adm2":0,
    "qs:woe_lau":28427095,
    "qs:woe_local":1117376,
    "qs:woe_ver":"7.10.0",
    "wof:lang":[
        "jpn"
    ],
    "wof:name":"\uff11\u4e01\u76ee",
    "wof:placetype":"neighbourhood"
},
  "geometry": {"coordinates":[136.35263599999999,36.319197],"type":"Point"}
}