{
  "type": "Feature",
  "properties": {
    "gn:admin1_code":"6.0",
    "gn:admin2_code":"7467387.0",
    "gn:asciiname":"Maruokacho-shimoyasuta",
    "gn:country_code":"JP",
    "gn:dem":14,
    "gn:feature_class":"P",
    "gn:feature_code":"PPL",
    "gn:name":"Maruokach\u014d-shimoyasuta",
    "gn:population":0,
    "gn:timezone":"Asia/Tokyo",
    "iso:country":"JP",
    "name:jpn_x_preferred":[
        "\u4e38\u5ca1\u753a\u4e0b\u5b89\u7530"
    ],
    "name:und_x_variant":[
        "Maruokach\u014d-shimoyasuta"
    ],
    "wof:name":"Maruokacho-shimoyasuta",
    "wof:placetype":"locality"
},
  "geometry": {"coordinates":[136.25720000000001,36.12688],"type":"Point"}
}