{
  "type": "Feature",
  "properties": {
    "gn:admin1_code":"35.0",
    "gn:admin2_code":"1858984.0",
    "gn:asciiname":"Shigarakicho-koyama",
    "gn:country_code":"JP",
    "gn:dem":313,
    "gn:feature_class":"P",
    "gn:feature_code":"PPL",
    "gn:name":"Shigarakich\u014d-k\u014dyama",
    "gn:population":0,
    "gn:timezone":"Asia/Tokyo",
    "iso:country":"JP",
    "name:jpn_x_preferred":[
        "\u4fe1\u697d\u753a\u795e\u5c71"
    ],
    "name:und_x_variant":[
        "Shigarakich\u014d-k\u014dyama"
    ],
    "wof:name":"Shigarakicho-koyama",
    "wof:placetype":"locality"
},
  "geometry": {"coordinates":[136.06091999999998,34.85755],"type":"Point"}
}