{
  "type": "Feature",
  "properties": {
    "gn:admin1_code":"43.0",
    "gn:admin2_code":"1860782.0",
    "gn:asciiname":"Shimotsucho-okubo",
    "gn:country_code":"JP",
    "gn:dem":235,
    "gn:feature_class":"P",
    "gn:feature_code":"PPL",
    "gn:name":"Shimotsuch\u014d-\u014dkubo",
    "gn:population":0,
    "gn:timezone":"Asia/Tokyo",
    "iso:country":"JP",
    "name:jpn_x_preferred":[
        "\u4e0b\u6d25\u753a\u5927\u7aaa"
    ],
    "name:und_x_variant":[
        "Shimotsuch\u014d-\u014dkubo"
    ],
    "wof:name":"Shimotsucho-okubo",
    "wof:placetype":"locality"
},
  "geometry": {"coordinates":[135.2081,34.11185],"type":"Point"}
}