{
  "type": "Feature",
  "properties": {
    "gn:admin1_code":"23.0",
    "gn:admin2_code":"7417711.0",
    "gn:asciiname":"Chomyojicho",
    "gn:country_code":"JP",
    "gn:dem":40,
    "gn:feature_class":"P",
    "gn:feature_code":"PPL",
    "gn:name":"Ch\u014dmy\u014djich\u014d",
    "gn:population":0,
    "gn:timezone":"Asia/Tokyo",
    "iso:country":"JP",
    "name:jpn_x_preferred":[
        "\u9577\u660e\u5bfa\u753a"
    ],
    "name:und_x_variant":[
        "Ch\u014dmy\u014djich\u014d"
    ],
    "wof:name":"Chomyojicho",
    "wof:placetype":"locality"
},
  "geometry": {"coordinates":[136.47721999999999,34.87860999999999],"type":"Point"}
}