{
  "type": "Feature",
  "properties": {
    "gn:admin1_code":"27",
    "gn:admin2_code":"1852895.0",
    "gn:asciiname":"Higashihamacho",
    "gn:country_code":"JP",
    "gn:dem":8,
    "gn:feature_class":"P",
    "gn:feature_code":"PPL",
    "gn:name":"Higashihamach\u014d",
    "gn:population":0,
    "gn:timezone":"Asia/Tokyo",
    "iso:country":"JP",
    "name:jpn_x_preferred":[
        "\u6771\u6d5c\u753a"
    ],
    "name:und_x_variant":[
        "Higashihama",
        "Higashinoura",
        "Higashinouramachi",
        "Higashihamach\u014d"
    ],
    "wof:name":"Higashihamacho",
    "wof:placetype":"locality"
},
  "geometry": {"coordinates":[129.74494999999999,33.1367],"type":"Point"}
}