{
  "type": "Feature",
  "properties": {
    "gn:admin1_code":"22",
    "gn:admin2_code":"1864872.0",
    "gn:asciiname":"Nobuchika",
    "gn:cc2":"JP",
    "gn:country_code":"JP",
    "gn:dem":133,
    "gn:feature_class":"P",
    "gn:feature_code":"PPL",
    "gn:name":"Nobuchika",
    "gn:population":0,
    "gn:timezone":"Asia/Tokyo",
    "iso:country":"JP",
    "name:und_x_variant":[
        "Uesugi",
        "Nobuchika"
    ],
    "wof:name":"Nobuchika",
    "wof:placetype":"locality"
},
  "geometry": {"coordinates":[135.31666999999999,35.35],"type":"Point"}
}