{
  "type": "Feature",
  "properties": {
    "gn:admin1_code":"36",
    "gn:admin2_code":"7392558.0",
    "gn:asciiname":"Hirosecho-hirose",
    "gn:country_code":"JP",
    "gn:dem":46,
    "gn:feature_class":"P",
    "gn:feature_code":"PPL",
    "gn:name":"Hirosech\u014d-hirose",
    "gn:population":0,
    "gn:timezone":"Asia/Tokyo",
    "iso:country":"JP",
    "name:jpn_x_preferred":[
        "\u5e83\u702c\u753a\u5e83\u702c"
    ],
    "name:und_x_variant":[
        "Hirosech\u014d-hirose",
        "Hirose"
    ],
    "wof:name":"Hirosecho-hirose",
    "wof:placetype":"locality"
},
  "geometry": {"coordinates":[133.16666999999998,35.36667],"type":"Point"}
}