{
  "type": "Feature",
  "properties": {
    "gn:admin1_code":"37",
    "gn:admin2_code":"1863288.0",
    "gn:admin3_code":"22133.0",
    "gn:asciiname":"Waji",
    "gn:cc2":"JP",
    "gn:country_code":"JP",
    "gn:dem":38,
    "gn:feature_class":"P",
    "gn:feature_code":"PPL",
    "gn:name":"Waji",
    "gn:population":0,
    "gn:timezone":"Asia/Tokyo",
    "iso:country":"JP",
    "name:und_x_variant":[
        "Wachi",
        "Waji"
    ],
    "wof:name":"Waji",
    "wof:placetype":"locality"
},
  "geometry": {"coordinates":[137.65000000000001,34.76667],"type":"Point"}
}