{
  "type": "Feature",
  "properties": {
    "gn:admin1_code":"37.0",
    "gn:admin2_code":"1860327.0",
    "gn:admin3_code":"22301.0",
    "gn:asciiname":"Naramoto",
    "gn:country_code":"JP",
    "gn:dem":192,
    "gn:feature_class":"P",
    "gn:feature_code":"PPL",
    "gn:name":"Naramoto",
    "gn:population":0,
    "gn:timezone":"Asia/Tokyo",
    "iso:country":"JP",
    "name:jpn_x_preferred":[
        "\u5948\u826f\u672c"
    ],
    "wof:name":"Naramoto",
    "wof:placetype":"locality"
},
  "geometry": {"coordinates":[139.06883999999999,34.8233],"type":"Point"}
}