{
  "type": "Feature",
  "properties": {
    "gn:admin1_code":"14.0",
    "gn:admin2_code":"2112399.0",
    "gn:asciiname":"Okunoya",
    "gn:country_code":"JP",
    "gn:dem":8,
    "gn:feature_class":"P",
    "gn:feature_code":"PPL",
    "gn:name":"Okunoya",
    "gn:population":0,
    "gn:timezone":"Asia/Tokyo",
    "iso:country":"JP",
    "wof:name":"Okunoya",
    "wof:placetype":"locality"
},
  "geometry": {"coordinates":[140.68333000000001,35.88333],"type":"Point"}
}