{
  "type": "Feature",
  "properties": {
    "gn:admin1_code":"21.0",
    "gn:admin2_code":"1865358.0",
    "gn:asciiname":"Ono",
    "gn:country_code":"JP",
    "gn:dem":252,
    "gn:feature_class":"P",
    "gn:feature_code":"PPLL",
    "gn:name":"\u014cno",
    "gn:population":0,
    "gn:timezone":"Asia/Tokyo",
    "iso:country":"JP",
    "name:bul_x_preferred":[
        "\u041e\u043d\u043e"
    ],
    "name:cat_x_preferred":[
        "Ono"
    ],
    "name:ceb_x_preferred":[
        "Ono"
    ],
    "name:ces_x_preferred":[
        "Ono"
    ],
    "name:deu_x_preferred":[
        "Ono"
    ],
    "name:fra_x_preferred":[
        "Ono"
    ],
    "name:heb_x_preferred":[
        "\u05d0\u05d5\u05e0\u05d5"
    ],
    "name:jpn_x_preferred":[
        "\u5927\u91ce"
    ],
    "name:jpn_x_variant":[
        "\u304a\u304a\u306e",
        "\u30aa\u30aa\u30ce"
    ],
    "name:nld_x_preferred":[
        "Ono"
    ],
    "name:pol_x_preferred":[
        "Ono"
    ],
    "name:por_x_preferred":[
        "Ono"
    ],
    "name:ron_x_preferred":[
        "Ono"
    ],
    "name:rus_x_preferred":[
        "\u041e\u043d\u043e"
    ],
    "name:swe_x_preferred":[
        "Ono"
    ],
    "name:ukr_x_preferred":[
        "\u041e\u043d\u043e"
    ],
    "name:und_x_variant":[
        "\u014cno"
    ],
    "name:vie_x_preferred":[
        "Ono"
    ],
    "wof:name":"Ono",
    "wof:placetype":"locality"
},
  "geometry": {"coordinates":[130.33803999999998,32.43165],"type":"Point"}
}