{
  "type": "Feature",
  "properties": {
    "gn:admin1_code":"05",
    "gn:admin2_code":"1857121.0",
    "gn:admin3_code":"38506.0",
    "gn:asciiname":"Nakatama",
    "gn:cc2":"JP",
    "gn:country_code":"JP",
    "gn:dem":18,
    "gn:feature_class":"P",
    "gn:feature_code":"PPL",
    "gn:name":"Nakatama",
    "gn:population":0,
    "gn:timezone":"Asia/Tokyo",
    "iso:country":"JP",
    "name:und_x_variant":[
        "Nakadama"
    ],
    "wof:name":"Nakatama",
    "wof:placetype":"locality"
},
  "geometry": {"coordinates":[132.62339,32.92286],"type":"Point"}
}