{
  "type": "Feature",
  "properties": {
    "gn:admin1_code":"27.0",
    "gn:admin2_code":"1852895.0",
    "gn:asciiname":"Kosazacho-kosaka",
    "gn:country_code":"JP",
    "gn:dem":78,
    "gn:feature_class":"P",
    "gn:feature_code":"PPL",
    "gn:name":"Kosazach\u014d-kosaka",
    "gn:population":0,
    "gn:timezone":"Asia/Tokyo",
    "iso:country":"JP",
    "name:jpn_x_preferred":[
        "\u5c0f\u4f50\u3005\u753a\u5c0f\u5742"
    ],
    "name:und_x_variant":[
        "Kosazach\u014d-kosaka"
    ],
    "wof:name":"Kosazacho-kosaka",
    "wof:placetype":"locality"
},
  "geometry": {"coordinates":[129.62627000000001,33.21339],"type":"Point"}
}