{
  "type": "Feature",
  "properties": {
    "gn:admin1_code":"21.0",
    "gn:admin2_code":"7412708.0",
    "gn:admin3_code":"43501.0",
    "gn:asciiname":"Yamanita",
    "gn:country_code":"JP",
    "gn:dem":173,
    "gn:feature_class":"P",
    "gn:feature_code":"PPLL",
    "gn:name":"Yamanita",
    "gn:population":0,
    "gn:timezone":"Asia/Tokyo",
    "iso:country":"JP",
    "name:jpn_x_preferred":[
        "\u5c71\u4ec1\u7530"
    ],
    "name:jpn_x_variant":[
        "\u3084\u307e\u306b\u305f",
        "\u30e4\u30de\u30cb\u30bf"
    ],
    "wof:name":"Yamanita",
    "wof:placetype":"locality"
},
  "geometry": {"coordinates":[130.86073000000002,32.20187],"type":"Point"}
}