{
  "type": "Feature",
  "properties": {
    "gn:admin1_code":"7.0",
    "gn:admin2_code":"1854055.0",
    "gn:admin3_code":"40384.0",
    "gn:asciiname":"Kamibefu",
    "gn:country_code":"JP",
    "gn:dem":48,
    "gn:feature_class":"P",
    "gn:feature_code":"PPL",
    "gn:name":"Kamibefu",
    "gn:population":0,
    "gn:timezone":"Asia/Tokyo",
    "iso:country":"JP",
    "name:jpn_x_preferred":[
        "\u4e0a\u5225\u5e9c"
    ],
    "wof:name":"Kamibefu",
    "wof:placetype":"locality"
},
  "geometry": {"coordinates":[130.65572,33.8321],"type":"Point"}
}