{
  "type": "Feature",
  "properties": {
    "gn:admin1_code":"34.0",
    "gn:admin2_code":"1849187.0",
    "gn:admin3_code":"11102.0",
    "gn:asciiname":"Torocho",
    "gn:country_code":"JP",
    "gn:dem":17,
    "gn:feature_class":"P",
    "gn:feature_code":"PPL",
    "gn:name":"Toroch\u014d",
    "gn:population":0,
    "gn:timezone":"Asia/Tokyo",
    "iso:country":"JP",
    "name:jpn_x_preferred":[
        "\u571f\u5442\u753a"
    ],
    "name:jpn_x_variant":[
        "\u3068\u308d\u3061\u3087\u3046",
        "\u30c8\u30ed\u30c1\u30e7\u30a6"
    ],
    "name:und_x_variant":[
        "Toroch\u014d"
    ],
    "wof:name":"Torocho",
    "wof:placetype":"locality"
},
  "geometry": {"coordinates":[139.63602,35.93206],"type":"Point"}
}