{
  "type": "Feature",
  "properties": {
    "iso:country":"JP",
    "name:eng_x_preferred":[
        "Akebonocho 1 Chome"
    ],
    "name:eng_x_variant":[
        "Akebonochou 1 Choume",
        "Akebonocho 1 Chome"
    ],
    "name:jpn_x_preferred":[
        "\uff11\u4e01\u76ee"
    ],
    "name:jpn_x_variant":[
        "\u3042\u3051\u307c\u306e\u3061\u3087\u3046 \uff11\u3061\u3087\u3046\u3081",
        "\u66d9\u753a \uff11\u4e01\u76ee",
        "\uff11\u3061\u3087\u3046\u3081"
    ],
    "qs:gn_local":0,
    "qs:local_max":2049,
    "qs:local_sum":5334,
    "qs:localhoods":10,
    "qs:name":"\uff11\u4e01\u76ee",
    "qs:name_adm0":"\u65e5\u672c",
    "qs:name_adm1":"\u6771\u4eac\u90fd",
    "qs:name_en":"Akebonocho 1 Chome",
    "qs:name_lau":"\u66d9\u753a",
    "qs:name_local":"\u7acb\u5ddd\u5e02",
    "qs:photo_max":260,
    "qs:photo_sum":263,
    "qs:placetype":"Suburb",
    "qs:quad_count":2,
    "qs:woe_adm0":23424856,
    "qs:woe_adm1":2345889,
    "qs:woe_adm2":0,
    "qs:woe_lau":28414908,
    "qs:woe_local":1118252,
    "qs:woe_ver":"7.10.0",
    "wof:lang":[
        "jpn"
    ],
    "wof:name":"\uff11\u4e01\u76ee",
    "wof:placetype":"neighbourhood"
},
  "geometry": {"coordinates":[139.40961200000001,35.700777],"type":"Point"}
}