{
  "type": "Feature",
  "properties": {
    "gn:admin1_code":"29.0",
    "gn:admin2_code":"1861238.0",
    "gn:admin3_code":"15581.0",
    "gn:asciiname":"Omi",
    "gn:country_code":"JP",
    "gn:dem":42,
    "gn:feature_class":"P",
    "gn:feature_code":"PPL",
    "gn:name":"Omi",
    "gn:population":0,
    "gn:timezone":"Asia/Tokyo",
    "iso:country":"JP",
    "name:jpn_x_preferred":[
        "\u5c0f\u898b"
    ],
    "wof:name":"Omi",
    "wof:placetype":"locality"
},
  "geometry": {"coordinates":[139.55017000000001,38.10347],"type":"Point"}
}