{
  "type": "Feature",
  "properties": {
    "gn:admin1_code":"19",
    "gn:admin2_code":"1863429.0",
    "gn:asciiname":"Toge",
    "gn:country_code":"JP",
    "gn:dem":212,
    "gn:feature_class":"P",
    "gn:feature_code":"PPL",
    "gn:name":"T\u014dge",
    "gn:population":0,
    "gn:timezone":"Asia/Tokyo",
    "iso:country":"JP",
    "name:jpn_x_preferred":[
        "\u5ce0"
    ],
    "name:und_x_variant":[
        "T\u014dge"
    ],
    "wof:name":"Toge",
    "wof:placetype":"locality"
},
  "geometry": {"coordinates":[139.17777000000001,35.35654],"type":"Point"}
}