{
  "type": "Feature",
  "properties": {
    "gn:admin1_code":"36",
    "gn:admin2_code":"7392548.0",
    "gn:admin3_code":"32343.0",
    "gn:asciiname":"Yanagidamen",
    "gn:cc2":"JP",
    "gn:country_code":"JP",
    "gn:dem":444,
    "gn:feature_class":"P",
    "gn:feature_code":"PPL",
    "gn:name":"Yanagidamen",
    "gn:population":0,
    "gn:timezone":"Asia/Tokyo",
    "iso:country":"JP",
    "name:und_x_variant":[
        "\u014cmaki",
        "Yatamo",
        "Yanagidamen"
    ],
    "wof:name":"Yanagidamen",
    "wof:placetype":"locality"
},
  "geometry": {"coordinates":[133.05000000000001,35.11667],"type":"Point"}
}