{
  "type": "Feature",
  "properties": {
    "gn:admin1_code":"19.0",
    "gn:admin2_code":"1848350.0",
    "gn:admin3_code":"14112.0",
    "gn:asciiname":"Kawai-shukucho",
    "gn:country_code":"JP",
    "gn:dem":56,
    "gn:feature_class":"P",
    "gn:feature_code":"PPL",
    "gn:name":"Kawai-shukuch\u014d",
    "gn:population":0,
    "gn:timezone":"Asia/Tokyo",
    "iso:country":"JP",
    "name:jpn_x_preferred":[
        "\u5ddd\u4e95\u5bbf\u753a"
    ],
    "name:jpn_x_variant":[
        "\u304b\u308f\u3044\u3057\u3085\u304f\u3061\u3087\u3046",
        "\u30ab\u30ef\u30a4\u30b7\u30e5\u30af\u30c1\u30e7\u30a6"
    ],
    "name:und_x_variant":[
        "Kawai-shukuch\u014d"
    ],
    "wof:name":"Kawai-shukucho",
    "wof:placetype":"locality"
},
  "geometry": {"coordinates":[139.51748000000001,35.49501],"type":"Point"}
}