{
  "type": "Feature",
  "properties": {
    "gn:admin1_code":"8.0",
    "gn:admin2_code":"7451502.0",
    "gn:admin3_code":"7505.0",
    "gn:asciiname":"Mizunuma",
    "gn:country_code":"JP",
    "gn:dem":245,
    "gn:feature_class":"P",
    "gn:feature_code":"PPLL",
    "gn:name":"Mizunuma",
    "gn:population":0,
    "gn:timezone":"Asia/Tokyo",
    "iso:country":"JP",
    "name:jpn_x_preferred":[
        "\u6c34\u6cbc"
    ],
    "wof:name":"Mizunuma",
    "wof:placetype":"locality"
},
  "geometry": {"coordinates":[140.61708999999999,37.04908],"type":"Point"}
}