{
  "type": "Feature",
  "properties": {
    "gn:admin1_code":"32.0",
    "gn:admin2_code":"1861089.0",
    "gn:asciiname":"Ichijoinco",
    "gn:country_code":"JP",
    "gn:dem":30,
    "gn:feature_class":"P",
    "gn:feature_code":"PPL",
    "gn:name":"Ichij\u014dinc\u014d",
    "gn:population":0,
    "gn:timezone":"Asia/Tokyo",
    "iso:country":"JP",
    "name:jpn_x_preferred":[
        "\u4e00\u6761\u9662\u753a"
    ],
    "name:und_x_variant":[
        "Ichij\u014dinc\u014d"
    ],
    "wof:name":"Ichijoinco",
    "wof:placetype":"locality"
},
  "geometry": {"coordinates":[135.44099,34.48157],"type":"Point"}
}