{
  "type": "Feature",
  "properties": {
    "gn:admin1_code":"46.0",
    "gn:admin2_code":"7415908.0",
    "gn:admin3_code":"19425.0",
    "gn:asciiname":"Koumihara",
    "gn:country_code":"JP",
    "gn:dem":1119,
    "gn:feature_class":"P",
    "gn:feature_code":"PPLL",
    "gn:name":"Koumihara",
    "gn:population":0,
    "gn:timezone":"Asia/Tokyo",
    "iso:country":"JP",
    "name:jpn_x_preferred":[
        "\u5c0f\u6d77\u539f"
    ],
    "wof:name":"Koumihara",
    "wof:placetype":"locality"
},
  "geometry": {"coordinates":[138.87926999999999,35.43386],"type":"Point"}
}