{
  "type": "Feature",
  "properties": {
    "gn:admin1_code":"3.0",
    "gn:admin2_code":"2130056.0",
    "gn:asciiname":"Sanbon'yanagi",
    "gn:country_code":"JP",
    "gn:dem":146,
    "gn:feature_class":"P",
    "gn:feature_code":"PPL",
    "gn:name":"Sanbon\u2019yanagi",
    "gn:population":0,
    "gn:timezone":"Asia/Tokyo",
    "iso:country":"JP",
    "name:jpn_x_preferred":[
        "\u4e09\u672c\u67f3"
    ],
    "name:jpn_x_variant":[
        "\u3055\u3093\u307c\u3093\u3084\u306a\u304e",
        "\u30b5\u30f3\u30dc\u30f3\u30e4\u30ca\u30ae"
    ],
    "name:und_x_variant":[
        "Sanbon\u2019yanagi"
    ],
    "wof:name":"Sanbon'yanagi",
    "wof:placetype":"locality"
},
  "geometry": {"coordinates":[140.35209,40.60955],"type":"Point"}
}