{
  "type": "Feature",
  "properties": {
    "gn:admin1_code":"18.0",
    "gn:admin2_code":"7383999.0",
    "gn:admin3_code":"46491.0",
    "gn:asciiname":"Minamikawachi",
    "gn:country_code":"JP",
    "gn:dem":191,
    "gn:feature_class":"P",
    "gn:feature_code":"PPLL",
    "gn:name":"Minamikawachi",
    "gn:population":0,
    "gn:timezone":"Asia/Tokyo",
    "iso:country":"JP",
    "name:jpn_x_preferred":[
        "\u5357\u5ddd\u5185"
    ],
    "wof:name":"Minamikawachi",
    "wof:placetype":"locality"
},
  "geometry": {"coordinates":[130.80081999999999,31.20706],"type":"Point"}
}