{
  "type": "Feature",
  "properties": {
    "gn:admin1_code":"28.0",
    "gn:admin2_code":"1861747.0",
    "gn:asciiname":"Yamasakicho",
    "gn:country_code":"JP",
    "gn:dem":140,
    "gn:feature_class":"P",
    "gn:feature_code":"PPL",
    "gn:name":"Yamasakich\u014d",
    "gn:population":0,
    "gn:timezone":"Asia/Tokyo",
    "iso:country":"JP",
    "name:jpn_x_preferred":[
        "\u5c71\u5d0e\u753a"
    ],
    "name:und_x_variant":[
        "Yamasakich\u014d"
    ],
    "wof:name":"Yamasakicho",
    "wof:placetype":"locality"
},
  "geometry": {"coordinates":[135.70653999999999,34.69028],"type":"Point"}
}