{
  "type": "Feature",
  "properties": {
    "gn:admin1_code":"4.0",
    "gn:admin2_code":"2112997.0",
    "gn:admin3_code":"12423.0",
    "gn:asciiname":"Mukaihara",
    "gn:country_code":"JP",
    "gn:dem":3,
    "gn:feature_class":"P",
    "gn:feature_code":"PPLL",
    "gn:name":"Mukaihara",
    "gn:population":0,
    "gn:timezone":"Asia/Tokyo",
    "iso:country":"JP",
    "name:jpn_x_preferred":[
        "\u5411\u539f"
    ],
    "name:jpn_x_variant":[
        "\u3080\u304b\u3044\u306f\u3089",
        "\u30e0\u30ab\u30a4\u30cf\u30e9"
    ],
    "wof:name":"Mukaihara",
    "wof:placetype":"locality"
},
  "geometry": {"coordinates":[140.37588,35.4004],"type":"Point"}
}