{
  "type": "Feature",
  "properties": {
    "gn:admin1_code":"21.0",
    "gn:admin2_code":"1850744.0",
    "gn:admin3_code":"43367.0",
    "gn:asciiname":"Sekishimo",
    "gn:country_code":"JP",
    "gn:dem":93,
    "gn:feature_class":"P",
    "gn:feature_code":"PPL",
    "gn:name":"Sekishimo",
    "gn:population":0,
    "gn:timezone":"Asia/Tokyo",
    "iso:country":"JP",
    "name:jpn_x_preferred":[
        "\u95a2\u4e0b"
    ],
    "name:jpn_x_variant":[
        "\u305b\u304d\u3057\u3082",
        "\u30bb\u30ad\u30b7\u30e2"
    ],
    "wof:name":"Sekishimo",
    "wof:placetype":"locality"
},
  "geometry": {"coordinates":[130.54275000000001,33.0521],"type":"Point"}
}