{
  "type": "Feature",
  "properties": {
    "iso:country":"JP",
    "name:eng_x_preferred":[
        "Shihoro"
    ],
    "name:eng_x_variant":[
        "Shihoro Town"
    ],
    "name:jpn_x_preferred":[
        "\u58eb\u5e4c\u753a"
    ],
    "qs:name":"\u58eb\u5e4c\u753a",
    "qs:name_adm0":"\u65e5\u672c",
    "qs:name_adm1":"\u5317\u6d77\u9053",
    "qs:photos":102,
    "qs:photos_1k":21,
    "qs:photos_9k":1,
    "qs:photos_9r":3,
    "qs:photos_all":102,
    "qs:photos_sr":3,
    "qs:placetype":"Town",
    "qs:pop_sr":"0",
    "wof:name":"Shihoro",
    "wof:placetype":"locality"
},
  "geometry": {"coordinates":[143.367197,43.138936],"type":"Point"}
}