{
  "type": "Feature",
  "properties": {
    "gn:admin1_code":"21.0",
    "gn:admin2_code":"7413151.0",
    "gn:asciiname":"Okoesaki",
    "gn:country_code":"JP",
    "gn:dem":-2,
    "gn:feature_class":"P",
    "gn:feature_code":"PPLL",
    "gn:name":"Okoesaki",
    "gn:population":0,
    "gn:timezone":"Asia/Tokyo",
    "iso:country":"JP",
    "name:jpn_x_preferred":[
        "\u5c3e\u8d8a\u5d0e"
    ],
    "name:jpn_x_variant":[
        "\u304a\u3053\u3048\u3055\u304d",
        "\u30aa\u30b3\u30a8\u30b5\u30ad"
    ],
    "wof:name":"Okoesaki",
    "wof:placetype":"locality"
},
  "geometry": {"coordinates":[130.44316000000001,32.58813],"type":"Point"}
}