{
  "type": "Feature",
  "properties": {
    "gn:admin1_code":"33.0",
    "gn:admin2_code":"7391355.0",
    "gn:asciiname":"Minamihatacho-komugiharu",
    "gn:country_code":"JP",
    "gn:dem":70,
    "gn:feature_class":"P",
    "gn:feature_code":"PPL",
    "gn:name":"Minamihatach\u014d-komugiharu",
    "gn:population":0,
    "gn:timezone":"Asia/Tokyo",
    "iso:country":"JP",
    "name:jpn_x_preferred":[
        "\u5357\u6ce2\u591a\u753a\u5c0f\u9ea6\u539f"
    ],
    "name:und_x_variant":[
        "Minamihatach\u014d-komugiharu"
    ],
    "wof:name":"Minamihatacho-komugiharu",
    "wof:placetype":"locality"
},
  "geometry": {"coordinates":[129.93406999999999,33.30346],"type":"Point"}
}