{
  "type": "Feature",
  "properties": {
    "gn:admin1_code":"21.0",
    "gn:admin2_code":"1850743.0",
    "gn:asciiname":"Funajima",
    "gn:country_code":"JP",
    "gn:dem":6,
    "gn:feature_class":"P",
    "gn:feature_code":"PPLL",
    "gn:name":"Funajima",
    "gn:population":0,
    "gn:timezone":"Asia/Tokyo",
    "iso:country":"JP",
    "name:jpn_x_preferred":[
        "\u821f\u5cf6"
    ],
    "name:jpn_x_variant":[
        "\u3075\u306a\u3058\u307e",
        "\u30d5\u30ca\u30b8\u30de"
    ],
    "wof:name":"Funajima",
    "wof:placetype":"locality"
},
  "geometry": {"coordinates":[130.59826000000001,32.92601],"type":"Point"}
}