{
  "type": "Feature",
  "properties": {
    "gn:admin1_code":"8.0",
    "gn:admin2_code":"2112535.0",
    "gn:asciiname":"Kishiuchi",
    "gn:country_code":"JP",
    "gn:dem":12,
    "gn:feature_class":"P",
    "gn:feature_code":"PPL",
    "gn:name":"Kishiuchi",
    "gn:population":0,
    "gn:timezone":"Asia/Tokyo",
    "iso:country":"JP",
    "name:jpn_x_preferred":[
        "\u5cb8\u5185"
    ],
    "wof:name":"Kishiuchi",
    "wof:placetype":"locality"
},
  "geometry": {"coordinates":[140.99796000000001,37.17369],"type":"Point"}
}