{
  "type": "Feature",
  "properties": {
    "gn:admin1_code":"21.0",
    "gn:admin2_code":"1850744.0",
    "gn:admin3_code":"43367.0",
    "gn:asciiname":"Fueroku",
    "gn:country_code":"JP",
    "gn:dem":97,
    "gn:feature_class":"P",
    "gn:feature_code":"PPLL",
    "gn:name":"Fueroku",
    "gn:population":0,
    "gn:timezone":"Asia/Tokyo",
    "iso:country":"JP",
    "name:jpn_x_preferred":[
        "\u7b1b\u9e7f"
    ],
    "name:jpn_x_variant":[
        "\u3075\u3048\u308d\u304f",
        "\u30d5\u30a8\u30ed\u30af"
    ],
    "wof:name":"Fueroku",
    "wof:placetype":"locality"
},
  "geometry": {"coordinates":[130.56091999999998,33.07347],"type":"Point"}
}