{
  "type": "Feature",
  "properties": {
    "gn:admin1_code":"12.0",
    "gn:admin2_code":"2130304.0",
    "gn:asciiname":"Yamabe",
    "gn:cc2":"JP",
    "gn:country_code":"JP",
    "gn:dem":214,
    "gn:feature_class":"P",
    "gn:feature_code":"PPL",
    "gn:name":"Yamabe",
    "gn:population":0,
    "gn:timezone":"Asia/Tokyo",
    "iso:country":"JP",
    "name:und_x_variant":[
        "Yamabe-shigai",
        "Yamabe"
    ],
    "wof:name":"Yamabe",
    "wof:placetype":"locality"
},
  "geometry": {"coordinates":[142.38556,43.23861],"type":"Point"}
}