{
  "type": "Feature",
  "properties": {
    "iso:country":"JP",
    "name:eng_x_preferred":[
        "Kitaodori 14 Chome"
    ],
    "name:eng_x_variant":[
        "Kitaoodoori 14 Choume",
        "Kitaodori 14 Chome"
    ],
    "name:jpn_x_preferred":[
        "\uff11\uff14\u4e01\u76ee"
    ],
    "name:jpn_x_variant":[
        "\u304d\u305f\u304a\u304a\u3069\u304a\u308a \uff11\uff14\u3061\u3087\u3046\u3081",
        "\u5317\u5927\u901a \uff11\uff14\u4e01\u76ee",
        "\uff11\uff14\u3061\u3087\u3046\u3081"
    ],
    "qs:gn_local":0,
    "qs:local_max":400,
    "qs:local_sum":812,
    "qs:localhoods":16,
    "qs:name":"\uff11\uff14\u4e01\u76ee",
    "qs:name_adm0":"\u65e5\u672c",
    "qs:name_adm1":"\u5317\u6d77\u9053",
    "qs:name_en":"Kitaodori 14 Chome",
    "qs:name_lau":"\u5317\u5927\u901a",
    "qs:name_local":"\u91e7\u8def\u5e02",
    "qs:photo_max":33,
    "qs:photo_sum":50,
    "qs:placetype":"Suburb",
    "qs:quad_count":4,
    "qs:woe_adm0":23424856,
    "qs:woe_adm1":7153351,
    "qs:woe_adm2":0,
    "qs:woe_lau":28380811,
    "qs:woe_local":1117640,
    "qs:woe_ver":"7.10.0",
    "wof:lang":[
        "jpn"
    ],
    "wof:name":"\uff11\uff14\u4e01\u76ee",
    "wof:placetype":"neighbourhood"
},
  "geometry": {"coordinates":[144.382935,42.991749],"type":"Point"}
}