{
  "type": "Feature",
  "properties": {
    "gn:admin1_code":"37.0",
    "gn:admin2_code":"7418320.0",
    "gn:asciiname":"Sakamoto",
    "gn:country_code":"JP",
    "gn:dem":17,
    "gn:feature_class":"P",
    "gn:feature_code":"PPLL",
    "gn:name":"Sakamoto",
    "gn:population":0,
    "gn:timezone":"Asia/Tokyo",
    "iso:country":"JP",
    "name:jpn_x_preferred":[
        "\u5742\u672c"
    ],
    "wof:name":"Sakamoto",
    "wof:placetype":"locality"
},
  "geometry": {"coordinates":[138.95085,35.03857],"type":"Point"}
}