{
  "type": "Feature",
  "properties": {
    "gn:admin1_code":"37.0",
    "gn:admin2_code":"7418320.0",
    "gn:asciiname":"Sakamoto",
    "gn:country_code":"JP",
    "gn:dem":17,
    "gn:feature_class":"P",
    "gn:feature_code":"PPLL",
    "gn:name":"Sakamoto",
    "gn:population":0,
    "gn:timezone":"Asia/Tokyo",
    "iso:country":"JP",
    "name:deu_x_preferred":[
        "Sakamoto"
    ],
    "name:fra_x_preferred":[
        "Sakamoto"
    ],
    "name:ita_x_preferred":[
        "Sakamoto"
    ],
    "name:jpn_x_preferred":[
        "\u5742\u672c"
    ],
    "name:kor_x_preferred":[
        "\uc0ac\uce74\ubaa8\ud1a0"
    ],
    "name:por_x_preferred":[
        "Sakamoto"
    ],
    "name:rus_x_preferred":[
        "\u0421\u0430\u043a\u0430\u043c\u043e\u0442\u043e"
    ],
    "name:ukr_x_preferred":[
        "\u0421\u0430\u043a\u0430\u043c\u043e\u0442\u043e"
    ],
    "name:zho_x_preferred":[
        "\u5742\u672c\u6c0f"
    ],
    "wof:name":"Sakamoto",
    "wof:placetype":"locality"
},
  "geometry": {"coordinates":[138.95085,35.03857],"type":"Point"}
}