{
  "type": "Feature",
  "properties": {
    "gn:admin1_code":"21.0",
    "gn:admin2_code":"1865358.0",
    "gn:asciiname":"Uto",
    "gn:country_code":"JP",
    "gn:dem":38,
    "gn:feature_class":"P",
    "gn:feature_code":"PPLL",
    "gn:name":"Uto",
    "gn:population":0,
    "gn:timezone":"Asia/Tokyo",
    "iso:country":"JP",
    "name:ceb_x_preferred":[
        "Uto"
    ],
    "name:deu_x_preferred":[
        "Uto"
    ],
    "name:jpn_x_preferred":[
        "\u5b87\u571f"
    ],
    "name:jpn_x_variant":[
        "\u3046\u3068",
        "\u30a6\u30c8"
    ],
    "name:mlg_x_preferred":[
        "Uto"
    ],
    "name:nld_x_preferred":[
        "Uto"
    ],
    "name:pol_x_preferred":[
        "Uto"
    ],
    "name:swe_x_preferred":[
        "Uto"
    ],
    "wof:name":"Uto",
    "wof:placetype":"locality"
},
  "geometry": {"coordinates":[130.17349999999999,32.42658],"type":"Point"}
}