{
  "type": "Feature",
  "properties": {
    "gn:admin1_code":"38",
    "gn:admin2_code":"1853473.0",
    "gn:asciiname":"Mamada",
    "gn:country_code":"JP",
    "gn:dem":33,
    "gn:feature_class":"P",
    "gn:feature_code":"PPL",
    "gn:name":"Mamada",
    "gn:population":0,
    "gn:timezone":"Asia/Tokyo",
    "iso:country":"JP",
    "wof:name":"Mamada",
    "wof:placetype":"locality"
},
  "geometry": {"coordinates":[139.76667,36.26667],"type":"Point"}
}