{
  "type": "Feature",
  "properties": {
    "gn:admin1_code":"23.0",
    "gn:admin2_code":"1861901.0",
    "gn:asciiname":"Nogahira",
    "gn:country_code":"JP",
    "gn:dem":221,
    "gn:feature_class":"P",
    "gn:feature_code":"PPL",
    "gn:name":"Nogahira",
    "gn:population":0,
    "gn:timezone":"Asia/Tokyo",
    "iso:country":"JP",
    "name:jpn_x_preferred":[
        "\u91ce\u30f6\u5e73"
    ],
    "wof:name":"Nogahira",
    "wof:placetype":"locality"
},
  "geometry": {"coordinates":[136.13123999999999,34.87255],"type":"Point"}
}