{
  "type": "Feature",
  "properties": {
    "gn:admin1_code":"7.0",
    "gn:admin2_code":"1858087.0",
    "gn:asciiname":"Daizenjimachi-miyamoto",
    "gn:country_code":"JP",
    "gn:dem":3,
    "gn:feature_class":"P",
    "gn:feature_code":"PPL",
    "gn:name":"Daizenjimachi-miyamoto",
    "gn:population":0,
    "gn:timezone":"Asia/Tokyo",
    "iso:country":"JP",
    "name:jpn_x_preferred":[
        "\u5927\u5584\u5bfa\u753a\u5bae\u672c"
    ],
    "wof:name":"Daizenjimachi-miyamoto",
    "wof:placetype":"locality"
},
  "geometry": {"coordinates":[130.47954999999999,33.27794],"type":"Point"}
}