{
  "type": "Feature",
  "properties": {
    "gn:admin1_code":"16.0",
    "gn:admin2_code":"7441817.0",
    "gn:asciiname":"Yanoura",
    "gn:country_code":"JP",
    "gn:dem":41,
    "gn:feature_class":"P",
    "gn:feature_code":"PPL",
    "gn:name":"Yanoura",
    "gn:population":0,
    "gn:timezone":"Asia/Tokyo",
    "iso:country":"JP",
    "name:jpn_x_preferred":[
        "\u77e2\u306e\u6d66"
    ],
    "name:jpn_x_variant":[
        "\u3084\u306e\u3046\u3089",
        "\u30e4\u30ce\u30a6\u30e9"
    ],
    "wof:name":"Yanoura",
    "wof:placetype":"locality"
},
  "geometry": {"coordinates":[141.67296000000005,38.98929],"type":"Point"}
}