{
  "type": "Feature",
  "properties": {
    "gn:admin1_code":"37.0",
    "gn:admin2_code":"1854900.0",
    "gn:asciiname":"Takasagocho",
    "gn:country_code":"JP",
    "gn:dem":61,
    "gn:feature_class":"P",
    "gn:feature_code":"PPL",
    "gn:name":"Takasagoch\u014d",
    "gn:population":0,
    "gn:timezone":"Asia/Tokyo",
    "iso:country":"JP",
    "name:jpn_x_preferred":[
        "\u9ad8\u7802\u753a"
    ],
    "name:und_x_variant":[
        "Takasagoch\u014d"
    ],
    "wof:name":"Takasagocho",
    "wof:placetype":"locality"
},
  "geometry": {"coordinates":[138.85798,35.1324],"type":"Point"}
}