{
  "type": "Feature",
  "properties": {
    "gn:admin1_code":"21.0",
    "gn:admin2_code":"1858418.0",
    "gn:admin3_code":"43101.0",
    "gn:asciiname":"Kosen",
    "gn:country_code":"JP",
    "gn:dem":10,
    "gn:feature_class":"P",
    "gn:feature_code":"PPL",
    "gn:name":"Kosen",
    "gn:population":0,
    "gn:timezone":"Asia/Tokyo",
    "iso:country":"JP",
    "name:jpn_x_preferred":[
        "\u58fa\u5ddd"
    ],
    "name:jpn_x_variant":[
        "\u3053\u305b\u3093",
        "\u30b3\u30bb\u30f3"
    ],
    "wof:name":"Kosen",
    "wof:placetype":"locality"
},
  "geometry": {"coordinates":[130.70911000000001,32.81697],"type":"Point"}
}