{
  "type": "Feature",
  "properties": {
    "gn:admin1_code":"24.0",
    "gn:admin2_code":"2112261.0",
    "gn:asciiname":"Sakihama",
    "gn:country_code":"JP",
    "gn:dem":32,
    "gn:feature_class":"P",
    "gn:feature_code":"PPL",
    "gn:name":"Sakihama",
    "gn:population":0,
    "gn:timezone":"Asia/Tokyo",
    "iso:country":"JP",
    "name:jpn_x_preferred":[
        "\u5d0e\u6d5c"
    ],
    "name:jpn_x_variant":[
        "\u3055\u304d\u306f\u307e",
        "\u30b5\u30ad\u30cf\u30de"
    ],
    "wof:name":"Sakihama",
    "wof:placetype":"locality"
},
  "geometry": {"coordinates":[141.62361999999999,38.84008],"type":"Point"}
}