{
  "type": "Feature",
  "properties": {
    "gn:admin1_code":"7.0",
    "gn:admin2_code":"1861834.0",
    "gn:asciiname":"Taromaru-niku",
    "gn:country_code":"JP",
    "gn:dem":26,
    "gn:feature_class":"P",
    "gn:feature_code":"PPLL",
    "gn:name":"Tar\u014dmaru-niku",
    "gn:population":0,
    "gn:timezone":"Asia/Tokyo",
    "iso:country":"JP",
    "name:jpn_x_preferred":[
        "\u592a\u90ce\u4e38\u4e8c\u533a"
    ],
    "name:und_x_variant":[
        "Tar\u014dmaru-niku"
    ],
    "wof:name":"Taromaru-niku",
    "wof:placetype":"locality"
},
  "geometry": {"coordinates":[130.66810000000001,33.61026],"type":"Point"}
}