{
  "type": "Feature",
  "properties": {
    "iso:country":"JP",
    "label:eng_x_preferred_longname":[
        "Hokuei Town"
    ],
    "label:eng_x_preferred_placetype":[
        "town"
    ],
    "name:eng_x_preferred":[
        "Hokuei"
    ],
    "name:eng_x_variant":[
        "Hokuei Town"
    ],
    "name:jpn_x_preferred":[
        "\u5317\u6804\u753a"
    ],
    "qs:name":"\u5317\u6804\u753a",
    "qs:name_adm0":"\u65e5\u672c",
    "qs:name_adm1":"\u9ce5\u53d6\u770c",
    "qs:photos":98,
    "qs:photos_1k":20,
    "qs:photos_9k":1,
    "qs:photos_9r":3,
    "qs:photos_all":98,
    "qs:photos_sr":3,
    "qs:placetype":"Town",
    "qs:pop_sr":"0",
    "wof:name":"Hokuei",
    "wof:placetype":"locality"
},
  "geometry": {"coordinates":[133.76184900000001,35.499915],"type":"Point"}
}