{
  "type": "Feature",
  "properties": {
    "gn:admin1_code":"3.0",
    "gn:admin2_code":"2130056.0",
    "gn:asciiname":"Inada",
    "gn:country_code":"JP",
    "gn:dem":32,
    "gn:feature_class":"P",
    "gn:feature_code":"PPL",
    "gn:name":"Inada",
    "gn:population":0,
    "gn:timezone":"Asia/Tokyo",
    "iso:country":"JP",
    "name:jpn_x_preferred":[
        "\u7a32\u7530"
    ],
    "name:jpn_x_variant":[
        "\u3044\u306a\u3060",
        "\u30a4\u30ca\u30c0"
    ],
    "wof:name":"Inada",
    "wof:placetype":"locality"
},
  "geometry": {"coordinates":[140.48806000000002,40.60361],"type":"Point"}
}