{
  "type": "Feature",
  "properties": {
    "gn:admin1_code":"2.0",
    "gn:admin2_code":"2127468.0",
    "gn:admin3_code":"5348.0",
    "gn:asciiname":"Toka",
    "gn:country_code":"JP",
    "gn:dem":44,
    "gn:feature_class":"P",
    "gn:feature_code":"PPL",
    "gn:name":"T\u014dka",
    "gn:population":0,
    "gn:timezone":"Asia/Tokyo",
    "iso:country":"JP",
    "wof:name":"Toka",
    "wof:placetype":"locality"
},
  "geometry": {"coordinates":[140.09999999999999,40.05],"type":"Point"}
}