{
  "type": "Feature",
  "properties": {
    "gn:admin1_code":"36",
    "gn:admin2_code":"1854361.0",
    "gn:admin3_code":"32526.0",
    "gn:asciiname":"Funagoshi",
    "gn:country_code":"JP",
    "gn:dem":7,
    "gn:feature_class":"P",
    "gn:feature_code":"PPL",
    "gn:name":"Funagoshi",
    "gn:population":0,
    "gn:timezone":"Asia/Tokyo",
    "iso:country":"JP",
    "name:jpn_x_preferred":[
        "\u8239\u8d8a"
    ],
    "name:und_x_variant":[
        "Funakoshi"
    ],
    "wof:name":"Funagoshi",
    "wof:placetype":"locality"
},
  "geometry": {"coordinates":[133.00928000000002,36.10533],"type":"Point"}
}