{
  "type": "Feature",
  "properties": {
    "gn:admin1_code":"43",
    "gn:admin2_code":"1862767.0",
    "gn:asciiname":"Nishi-shikiya",
    "gn:country_code":"JP",
    "gn:dem":257,
    "gn:feature_class":"P",
    "gn:feature_code":"PPL",
    "gn:name":"Nishi-shikiya",
    "gn:population":0,
    "gn:timezone":"Asia/Tokyo",
    "iso:country":"JP",
    "wof:name":"Nishi-shikiya",
    "wof:placetype":"locality"
},
  "geometry": {"coordinates":[135.80000000000001,33.85],"type":"Point"}
}