{
  "type": "Feature",
  "properties": {
    "gn:admin1_code":"29.0",
    "gn:admin2_code":"1855427.0",
    "gn:admin3_code":"15107.0",
    "gn:asciiname":"Nakano-koya",
    "gn:country_code":"JP",
    "gn:dem":0,
    "gn:feature_class":"P",
    "gn:feature_code":"PPL",
    "gn:name":"Nakano-koya",
    "gn:population":0,
    "gn:timezone":"Asia/Tokyo",
    "iso:country":"JP",
    "name:jpn_x_preferred":[
        "\u4e2d\u91ce\u5c0f\u5c4b"
    ],
    "wof:name":"Nakano-koya",
    "wof:placetype":"locality"
},
  "geometry": {"coordinates":[138.93453,37.8235],"type":"Point"}
}