{
  "type": "Feature",
  "properties": {
    "gn:admin1_code":"4.0",
    "gn:admin2_code":"1855071.0",
    "gn:asciiname":"Haige",
    "gn:country_code":"JP",
    "gn:dem":19,
    "gn:feature_class":"P",
    "gn:feature_code":"PPLL",
    "gn:name":"Haige",
    "gn:population":0,
    "gn:timezone":"Asia/Tokyo",
    "iso:country":"JP",
    "name:jpn_x_preferred":[
        "\u7070\u6bdb\u3000"
    ],
    "wof:name":"Haige",
    "wof:placetype":"locality"
},
  "geometry": {"coordinates":[139.91276000000002,35.94471],"type":"Point"}
}