{
  "type": "Feature",
  "properties": {
    "gn:admin1_code":"32",
    "gn:admin2_code":"1853897.0",
    "gn:admin3_code":"27107.0",
    "gn:asciiname":"Fukuzaki",
    "gn:country_code":"JP",
    "gn:dem":2,
    "gn:feature_class":"P",
    "gn:feature_code":"PPL",
    "gn:name":"Fukuzaki",
    "gn:population":0,
    "gn:timezone":"Asia/Tokyo",
    "iso:country":"JP",
    "name:jpn_x_preferred":[
        "\u798f\u5d0e"
    ],
    "name:und_x_variant":[
        "Kita-fukusaki-nishinoch\u014d",
        "Kitafukuzaki-nishinoch\u014d",
        "Fukuzaki",
        "Kitafukusaki",
        "Minami-fukuzakich\u014d",
        "Minami-fukusakicho",
        "Kitfukuzaki-higashinoch\u014d"
    ],
    "wof:name":"Fukuzaki",
    "wof:placetype":"locality"
},
  "geometry": {"coordinates":[135.45582999999999,34.6538],"type":"Point"}
}