{
  "type": "Feature",
  "properties": {
    "gn:admin1_code":"21.0",
    "gn:admin2_code":"1864975.0",
    "gn:admin3_code":"43428.0",
    "gn:asciiname":"Kawara",
    "gn:country_code":"JP",
    "gn:dem":712,
    "gn:feature_class":"P",
    "gn:feature_code":"PPLL",
    "gn:name":"Kawara",
    "gn:population":0,
    "gn:timezone":"Asia/Tokyo",
    "iso:country":"JP",
    "name:jpn_x_preferred":[
        "\u6cb3\u539f"
    ],
    "name:jpn_x_variant":[
        "\u304b\u308f\u3089",
        "\u30ab\u30ef\u30e9"
    ],
    "wof:name":"Kawara",
    "wof:placetype":"locality"
},
  "geometry": {"coordinates":[131.24014,32.88236],"type":"Point"}
}