{
  "type": "Feature",
  "properties": {
    "gn:admin1_code":"16",
    "gn:admin2_code":"2111883.0",
    "gn:asciiname":"Tsugaruishi",
    "gn:country_code":"JP",
    "gn:dem":9,
    "gn:feature_class":"P",
    "gn:feature_code":"PPL",
    "gn:name":"Tsugaruishi",
    "gn:population":0,
    "gn:timezone":"Asia/Tokyo",
    "iso:country":"JP",
    "wof:name":"Tsugaruishi",
    "wof:placetype":"locality"
},
  "geometry": {"coordinates":[141.93333000000001,39.56667],"type":"Point"}
}