{
  "type": "Feature",
  "properties": {
    "gn:admin1_code":"2.0",
    "gn:admin2_code":"2128783.0",
    "gn:asciiname":"Nekohana",
    "gn:country_code":"JP",
    "gn:dem":84,
    "gn:feature_class":"P",
    "gn:feature_code":"PPLL",
    "gn:name":"Nekohana",
    "gn:population":0,
    "gn:timezone":"Asia/Tokyo",
    "iso:country":"JP",
    "name:jpn_x_preferred":[
        "\u732b\u9f3b"
    ],
    "name:jpn_x_variant":[
        "\u306d\u3053\u306f\u306a",
        "\u30cd\u30b3\u30cf\u30ca"
    ],
    "wof:name":"Nekohana",
    "wof:placetype":"locality"
},
  "geometry": {"coordinates":[140.55126999999999,40.32001],"type":"Point"}
}