{
  "type": "Feature",
  "properties": {
    "gn:admin1_code":"19.0",
    "gn:admin2_code":"1864091.0",
    "gn:asciiname":"Zendana",
    "gn:country_code":"JP",
    "gn:dem":54,
    "gn:feature_class":"P",
    "gn:feature_code":"PPLL",
    "gn:name":"Zendana",
    "gn:population":0,
    "gn:timezone":"Asia/Tokyo",
    "iso:country":"JP",
    "name:jpn_x_preferred":[
        "\u81b3\u68da"
    ],
    "wof:name":"Zendana",
    "wof:placetype":"locality"
},
  "geometry": {"coordinates":[139.49061,35.35665],"type":"Point"}
}