{
  "type": "Feature",
  "properties": {
    "gn:admin1_code":"7.0",
    "gn:admin2_code":"1858305.0",
    "gn:admin3_code":"40401.0",
    "gn:asciiname":"Niida",
    "gn:country_code":"JP",
    "gn:dem":48,
    "gn:feature_class":"P",
    "gn:feature_code":"PPL",
    "gn:name":"Niida",
    "gn:population":0,
    "gn:timezone":"Asia/Tokyo",
    "iso:country":"JP",
    "name:jpn_x_preferred":[
        "\u65b0\u591a"
    ],
    "wof:name":"Niida",
    "wof:placetype":"locality"
},
  "geometry": {"coordinates":[130.68812,33.69721],"type":"Point"}
}