{
  "type": "Feature",
  "properties": {
    "gn:admin1_code":"37.0",
    "gn:admin2_code":"1854900.0",
    "gn:asciiname":"Oi",
    "gn:country_code":"JP",
    "gn:dem":18,
    "gn:feature_class":"P",
    "gn:feature_code":"PPLL",
    "gn:name":"\u014ci",
    "gn:population":0,
    "gn:timezone":"Asia/Tokyo",
    "iso:country":"JP",
    "name:jpn_x_preferred":[
        "\u5927\u4e95"
    ],
    "name:und_x_variant":[
        "\u014ci"
    ],
    "wof:name":"Oi",
    "wof:placetype":"locality"
},
  "geometry": {"coordinates":[138.89246,35.07156],"type":"Point"}
}