{
  "type": "Feature",
  "properties": {
    "gn:admin1_code":"28.0",
    "gn:admin2_code":"7412212.0",
    "gn:asciiname":"Murou-taguchi-mototsunogawa",
    "gn:country_code":"JP",
    "gn:dem":508,
    "gn:feature_class":"P",
    "gn:feature_code":"PPL",
    "gn:name":"Murou-taguchi-mototsunogawa",
    "gn:population":0,
    "gn:timezone":"Asia/Tokyo",
    "iso:country":"JP",
    "name:jpn_x_preferred":[
        "\u5ba4\u751f\u7530\u53e3\u5143\u89d2\u5ddd"
    ],
    "wof:name":"Murou-taguchi-mototsunogawa",
    "wof:placetype":"locality"
},
  "geometry": {"coordinates":[136.0498,34.50957],"type":"Point"}
}