{
  "type": "Feature",
  "properties": {
    "gn:admin1_code":"34.0",
    "gn:admin2_code":"1861470.0",
    "gn:admin3_code":"11324.0",
    "gn:asciiname":"Fujikubo",
    "gn:country_code":"JP",
    "gn:dem":30,
    "gn:feature_class":"P",
    "gn:feature_code":"PPL",
    "gn:name":"Fujikubo",
    "gn:population":0,
    "gn:timezone":"Asia/Tokyo",
    "iso:country":"JP",
    "name:jpn_x_preferred":[
        "\u85e4\u4e45\u4fdd"
    ],
    "name:jpn_x_variant":[
        "\u3075\u3058\u304f\u307c",
        "\u30d5\u30b8\u30af\u30dc"
    ],
    "wof:name":"Fujikubo",
    "wof:placetype":"locality"
},
  "geometry": {"coordinates":[139.53124,35.83568],"type":"Point"}
}