{
  "type": "Feature",
  "properties": {
    "gn:admin1_code":"19.0",
    "gn:admin2_code":"1864622.0",
    "gn:asciiname":"Murota",
    "gn:country_code":"JP",
    "gn:dem":8,
    "gn:feature_class":"P",
    "gn:feature_code":"PPL",
    "gn:name":"Murota",
    "gn:population":0,
    "gn:timezone":"Asia/Tokyo",
    "iso:country":"JP",
    "name:jpn_x_preferred":[
        "\u5ba4\u7530"
    ],
    "wof:name":"Murota",
    "wof:placetype":"locality"
},
  "geometry": {"coordinates":[139.41998000000001,35.34356],"type":"Point"}
}