{
  "type": "Feature",
  "properties": {
    "gn:admin1_code":"27.0",
    "gn:admin2_code":"1862734.0",
    "gn:admin3_code":"42322.0",
    "gn:asciiname":"Shingaego",
    "gn:country_code":"JP",
    "gn:dem":6,
    "gn:feature_class":"P",
    "gn:feature_code":"PPL",
    "gn:name":"Shingaeg\u014d",
    "gn:population":0,
    "gn:timezone":"Asia/Tokyo",
    "iso:country":"JP",
    "name:jpn_x_preferred":[
        "\u65b0\u8c37\u90f7"
    ],
    "name:und_x_variant":[
        "Shingaeg\u014d"
    ],
    "wof:name":"Shingaego",
    "wof:placetype":"locality"
},
  "geometry": {"coordinates":[129.82373999999999,33.07003],"type":"Point"}
}