{
  "type": "Feature",
  "properties": {
    "gn:admin1_code":"47",
    "gn:admin2_code":"1849184.0",
    "gn:asciiname":"Ahacha",
    "gn:cc2":"JP",
    "gn:country_code":"JP",
    "gn:dem":50,
    "gn:feature_class":"P",
    "gn:feature_code":"PPL",
    "gn:name":"Ahacha",
    "gn:population":0,
    "gn:timezone":"Asia/Tokyo",
    "iso:country":"JP",
    "name:jpn_x_preferred":[
        "\u5b89\u6ce2\u8336"
    ],
    "name:und_x_variant":[
        "Afuwacha",
        "Awacha",
        "Ahacha"
    ],
    "wof:name":"Ahacha",
    "wof:placetype":"locality"
},
  "geometry": {"coordinates":[127.72194,26.24278],"type":"Point"}
}