{
  "type": "Feature",
  "properties": {
    "gn:admin1_code":"37.0",
    "gn:admin2_code":"1851714.0",
    "gn:admin3_code":"22103.0",
    "gn:asciiname":"Kanbaranaka",
    "gn:country_code":"JP",
    "gn:dem":13,
    "gn:feature_class":"P",
    "gn:feature_code":"PPL",
    "gn:name":"Kanbaranaka",
    "gn:population":0,
    "gn:timezone":"Asia/Tokyo",
    "iso:country":"JP",
    "name:jpn_x_preferred":[
        "\u84b2\u539f\u4e2d"
    ],
    "wof:name":"Kanbaranaka",
    "wof:placetype":"locality"
},
  "geometry": {"coordinates":[138.58652000000001,35.1157],"type":"Point"}
}