{
  "type": "Feature",
  "properties": {
    "iso:country":"JP",
    "label:eng_x_preferred_longname":[
        "Takashima City"
    ],
    "label:eng_x_preferred_placetype":[
        "city"
    ],
    "name:eng_x_preferred":[
        "Takashima"
    ],
    "name:eng_x_variant":[
        "Takashima City"
    ],
    "name:jpn_x_preferred":[
        "\u9ad8\u5cf6\u5e02"
    ],
    "qs:name":"\u9ad8\u5cf6\u5e02",
    "qs:name_adm0":"\u65e5\u672c",
    "qs:name_adm1":"\u6ecb\u8cc0\u770c",
    "qs:photos":712,
    "qs:photos_1k":144,
    "qs:photos_9k":5,
    "qs:photos_9r":7,
    "qs:photos_all":1147,
    "qs:photos_sr":8,
    "qs:placetype":"Town",
    "qs:pop_sr":"0",
    "wof:name":"Takashima",
    "wof:placetype":"locality"
},
  "geometry": {"coordinates":[136.03580400000001,35.393439],"type":"Point"}
}