{
  "type": "Feature",
  "properties": {
    "gn:admin1_code":"3.0",
    "gn:admin2_code":"2130056.0",
    "gn:asciiname":"Hirayama",
    "gn:country_code":"JP",
    "gn:dem":94,
    "gn:feature_class":"P",
    "gn:feature_code":"PPL",
    "gn:name":"Hirayama",
    "gn:population":0,
    "gn:timezone":"Asia/Tokyo",
    "iso:country":"JP",
    "name:ces_x_preferred":[
        "Hirajama"
    ],
    "name:jpn_x_preferred":[
        "\u5e73\u5c71"
    ],
    "name:jpn_x_variant":[
        "\u3072\u3089\u3084\u307e",
        "\u30d2\u30e9\u30e4\u30de"
    ],
    "wof:name":"Hirayama",
    "wof:placetype":"locality"
},
  "geometry": {"coordinates":[140.33338999999998,40.58607],"type":"Point"}
}