{
  "type": "Feature",
  "properties": {
    "gn:admin1_code":"21.0",
    "gn:admin2_code":"1848441.0",
    "gn:asciiname":"Otemachi",
    "gn:country_code":"JP",
    "gn:dem":6,
    "gn:feature_class":"P",
    "gn:feature_code":"PPL",
    "gn:name":"\u014ctemachi",
    "gn:population":0,
    "gn:timezone":"Asia/Tokyo",
    "iso:country":"JP",
    "name:jpn_x_preferred":[
        "\u5927\u624b\u753a"
    ],
    "name:jpn_x_variant":[
        "\u304a\u304a\u3066\u307e\u3061",
        "\u30aa\u30aa\u30c6\u30de\u30c1"
    ],
    "name:und_x_variant":[
        "\u014ctemachi"
    ],
    "wof:name":"Otemachi",
    "wof:placetype":"locality"
},
  "geometry": {"coordinates":[130.61274,32.50866],"type":"Point"}
}