{
  "type": "Feature",
  "properties": {
    "gn:admin1_code":"32.0",
    "gn:admin2_code":"1860764.0",
    "gn:asciiname":"Kibitani",
    "gn:country_code":"JP",
    "gn:dem":167,
    "gn:feature_class":"P",
    "gn:feature_code":"PPL",
    "gn:name":"Kibitani",
    "gn:population":0,
    "gn:timezone":"Asia/Tokyo",
    "iso:country":"JP",
    "name:jpn_x_preferred":[
        "\u79ec\u8c37"
    ],
    "wof:name":"Kibitani",
    "wof:placetype":"locality"
},
  "geometry": {"coordinates":[135.38978999999998,34.36505],"type":"Point"}
}