{
  "type": "Feature",
  "properties": {
    "gn:admin1_code":"19.0",
    "gn:admin2_code":"1854744.0",
    "gn:asciiname":"Soga-kishi",
    "gn:country_code":"JP",
    "gn:dem":28,
    "gn:feature_class":"P",
    "gn:feature_code":"PPL",
    "gn:name":"Soga-kishi",
    "gn:population":0,
    "gn:timezone":"Asia/Tokyo",
    "iso:country":"JP",
    "name:jpn_x_preferred":[
        "\u66fd\u6211\u5cb8"
    ],
    "wof:name":"Soga-kishi",
    "wof:placetype":"locality"
},
  "geometry": {"coordinates":[139.18498,35.30448],"type":"Point"}
}