{
  "type": "Feature",
  "properties": {
    "gn:admin1_code":"3.0",
    "gn:admin2_code":"2129525.0",
    "gn:admin3_code":"2384.0",
    "gn:asciiname":"Nogi",
    "gn:country_code":"JP",
    "gn:dem":12,
    "gn:feature_class":"P",
    "gn:feature_code":"PPL",
    "gn:name":"Nogi",
    "gn:population":0,
    "gn:timezone":"Asia/Tokyo",
    "iso:country":"JP",
    "name:jpn_x_preferred":[
        "\u91ce\u6728"
    ],
    "name:jpn_x_variant":[
        "\u306e\u304e",
        "\u30ce\u30ae"
    ],
    "wof:name":"Nogi",
    "wof:placetype":"locality"
},
  "geometry": {"coordinates":[140.41136,40.74424000000001],"type":"Point"}
}