{
  "type": "Feature",
  "properties": {
    "gn:admin1_code":"24.0",
    "gn:admin2_code":"7447001.0",
    "gn:asciiname":"Onikobe",
    "gn:country_code":"JP",
    "gn:dem":387,
    "gn:feature_class":"P",
    "gn:feature_code":"PPL",
    "gn:name":"Onik\u014dbe",
    "gn:population":0,
    "gn:timezone":"Asia/Tokyo",
    "iso:country":"JP",
    "name:jpn_x_preferred":[
        "\u9b3c\u9996"
    ],
    "name:jpn_x_variant":[
        "\u304a\u306b\u3053\u3046\u3079",
        "\u30aa\u30cb\u30b3\u30a6\u30d9"
    ],
    "name:und_x_variant":[
        "Onik\u014dbe"
    ],
    "wof:name":"Onikobe",
    "wof:placetype":"locality"
},
  "geometry": {"coordinates":[140.66392999999999,38.80962],"type":"Point"}
}