{
  "type": "Feature",
  "properties": {
    "gn:admin1_code":"25.0",
    "gn:admin2_code":"1864313.0",
    "gn:asciiname":"Chiyotanda",
    "gn:country_code":"JP",
    "gn:dem":248,
    "gn:feature_class":"P",
    "gn:feature_code":"PPLL",
    "gn:name":"Chiyotanda",
    "gn:population":0,
    "gn:timezone":"Asia/Tokyo",
    "iso:country":"JP",
    "name:jpn_x_preferred":[
        "\u5343\u4ee3\u53cd\u7530"
    ],
    "name:jpn_x_variant":[
        "\u3061\u3088\u305f\u3093\u3060",
        "\u30c1\u30e8\u30bf\u30f3\u30c0"
    ],
    "wof:name":"Chiyotanda",
    "wof:placetype":"locality"
},
  "geometry": {"coordinates":[130.81700000000001,32.01976],"type":"Point"}
}