{
  "type": "Feature",
  "properties": {
    "gn:admin1_code":"4.0",
    "gn:admin2_code":"7465521.0",
    "gn:asciiname":"Kawamata",
    "gn:country_code":"JP",
    "gn:dem":48,
    "gn:feature_class":"P",
    "gn:feature_code":"PPLL",
    "gn:name":"Kawamata",
    "gn:population":0,
    "gn:timezone":"Asia/Tokyo",
    "iso:country":"JP",
    "name:jpn_x_preferred":[
        "\u5ddd\u53c8"
    ],
    "name:jpn_x_variant":[
        "\u304b\u308f\u307e\u305f",
        "\u30ab\u30ef\u30de\u30bf"
    ],
    "wof:name":"Kawamata",
    "wof:placetype":"locality"
},
  "geometry": {"coordinates":[139.89756,35.06302],"type":"Point"}
}