{
  "type": "Feature",
  "properties": {
    "gn:admin1_code":"4.0",
    "gn:admin2_code":"1863711.0",
    "gn:asciiname":"Yatanuma",
    "gn:country_code":"JP",
    "gn:dem":36,
    "gn:feature_class":"P",
    "gn:feature_code":"PPL",
    "gn:name":"Yatanuma",
    "gn:population":0,
    "gn:timezone":"Asia/Tokyo",
    "iso:country":"JP",
    "name:jpn_x_preferred":[
        "\u516b\u7530\u6cbc"
    ],
    "name:jpn_x_variant":[
        "\u3084\u305f\u306c\u307e",
        "\u30e4\u30bf\u30cc\u30de"
    ],
    "wof:name":"Yatanuma",
    "wof:placetype":"locality"
},
  "geometry": {"coordinates":[139.87791999999999,35.28169000000001],"type":"Point"}
}