{
  "type": "Feature",
  "properties": {
    "gn:admin1_code":"34.0",
    "gn:admin2_code":"1859739.0",
    "gn:asciiname":"Zone",
    "gn:country_code":"JP",
    "gn:dem":11,
    "gn:feature_class":"P",
    "gn:feature_code":"PPLL",
    "gn:name":"Z\u014dne",
    "gn:population":0,
    "gn:timezone":"Asia/Tokyo",
    "iso:country":"JP",
    "name:ceb_x_preferred":[
        "Zone"
    ],
    "name:dan_x_preferred":[
        "Zone"
    ],
    "name:deu_x_preferred":[
        "Zone"
    ],
    "name:fra_x_preferred":[
        "Zone"
    ],
    "name:hun_x_preferred":[
        "Z\u00f3na"
    ],
    "name:jpn_x_preferred":[
        "\u8535\u6839"
    ],
    "name:jpn_x_variant":[
        "\u30be\u30fc\u30f3"
    ],
    "name:nep_x_preferred":[
        "\u0905\u091e\u094d\u091a\u0932"
    ],
    "name:nld_x_preferred":[
        "Zone"
    ],
    "name:por_x_preferred":[
        "Zone"
    ],
    "name:ron_x_preferred":[
        "Zone"
    ],
    "name:swe_x_preferred":[
        "Zone"
    ],
    "name:tgl_x_preferred":[
        "Zone"
    ],
    "name:und_x_variant":[
        "Z\u014dne"
    ],
    "name:vie_x_preferred":[
        "Zone"
    ],
    "name:zho_x_preferred":[
        "Zone"
    ],
    "wof:name":"Zone",
    "wof:placetype":"locality"
},
  "geometry": {"coordinates":[139.53283000000002,35.92091],"type":"Point"}
}