{
  "type": "Feature",
  "properties": {
    "gn:admin1_code":"4.0",
    "gn:admin2_code":"1855071.0",
    "gn:asciiname":"Goki-shinden",
    "gn:country_code":"JP",
    "gn:dem":19,
    "gn:feature_class":"P",
    "gn:feature_code":"PPL",
    "gn:name":"Goki-shinden",
    "gn:population":0,
    "gn:timezone":"Asia/Tokyo",
    "iso:country":"JP",
    "name:jpn_x_preferred":[
        "\u4e94\u6728\u65b0\u7530"
    ],
    "wof:name":"Goki-shinden",
    "wof:placetype":"locality"
},
  "geometry": {"coordinates":[139.83776,35.9796],"type":"Point"}
}