{
  "type": "Feature",
  "properties": {
    "gn:admin1_code":"21.0",
    "gn:admin2_code":"1850743.0",
    "gn:asciiname":"Taimeimachi-shoyama",
    "gn:country_code":"JP",
    "gn:dem":15,
    "gn:feature_class":"P",
    "gn:feature_code":"PPL",
    "gn:name":"Taimeimachi-sh\u014dyama",
    "gn:population":0,
    "gn:timezone":"Asia/Tokyo",
    "iso:country":"JP",
    "name:jpn_x_preferred":[
        "\u5cb1\u660e\u753a\u5e84\u5c71"
    ],
    "name:jpn_x_variant":[
        "\u305f\u3044\u3081\u3044\u307e\u3061\u3057\u3087\u3046\u3084\u307e",
        "\u30bf\u30a4\u30e1\u30a4\u30de\u30c1\u30b7\u30e7\u30a6\u30e4\u30de"
    ],
    "name:und_x_variant":[
        "Taimeimachi-sh\u014dyama"
    ],
    "wof:name":"Taimeimachi-shoyama",
    "wof:placetype":"locality"
},
  "geometry": {"coordinates":[130.51823999999999,32.93055],"type":"Point"}
}