{
  "type": "Feature",
  "properties": {
    "gn:admin1_code":"29",
    "gn:admin2_code":"7468177.0",
    "gn:asciiname":"Murakamimoto",
    "gn:cc2":"JP",
    "gn:country_code":"JP",
    "gn:dem":10,
    "gn:feature_class":"P",
    "gn:feature_code":"PPL",
    "gn:name":"Murakamimoto",
    "gn:population":0,
    "gn:timezone":"Asia/Tokyo",
    "iso:country":"JP",
    "name:und_x_variant":[
        "Murakami-hommachi",
        "Murakami-motomachi",
        "Murakamimoto"
    ],
    "wof:name":"Murakamimoto",
    "wof:placetype":"locality"
},
  "geometry": {"coordinates":[139.46666999999999,38.21667],"type":"Point"}
}