{
  "type": "Feature",
  "properties": {
    "gn:admin1_code":"8.0",
    "gn:admin2_code":"1857203.0",
    "gn:admin3_code":"7367.0",
    "gn:asciiname":"Mamarukai",
    "gn:country_code":"JP",
    "gn:dem":519,
    "gn:feature_class":"P",
    "gn:feature_code":"PPLL",
    "gn:name":"Mamarukai",
    "gn:population":0,
    "gn:timezone":"Asia/Tokyo",
    "iso:country":"JP",
    "name:jpn_x_preferred":[
        "\u9593\u4e38\u8c9d"
    ],
    "wof:name":"Mamarukai",
    "wof:placetype":"locality"
},
  "geometry": {"coordinates":[139.46048000000002,37.25808],"type":"Point"}
}