{
  "type": "Feature",
  "properties": {
    "gn:admin1_code":"09",
    "gn:admin2_code":"1863645.0",
    "gn:asciiname":"Kanayamacho-sugata-kirihora",
    "gn:country_code":"JP",
    "gn:dem":490,
    "gn:feature_class":"P",
    "gn:feature_code":"PPL",
    "gn:name":"Kanayamach\u014d-sugata-kirihora",
    "gn:population":0,
    "gn:timezone":"Asia/Tokyo",
    "iso:country":"JP",
    "name:und_x_variant":[
        "Kanayamach\u014d-sugata-kirihora"
    ],
    "wof:name":"Kanayamacho-sugata-kirihora",
    "wof:placetype":"locality"
},
  "geometry": {"coordinates":[137.13333,35.63333],"type":"Point"}
}