{
  "type": "Feature",
  "properties": {
    "gn:country":"JP",
    "gn:fcode":"ADM3",
    "gn:population":0,
    "iso:country":"JP",
    "name:jpn_x_preferred":[
        "\u718a\u91ce\u753a"
    ],
    "name:jpn_x_variant":[
        "\u304f\u307e\u306e\u3061\u3087\u3046"
    ],
    "qs:name":"Kumano-ch\u014d",
    "qs:photos_9r":0,
    "qs:photos_sr":0,
    "qs:pop_sr":"0",
    "wof:name":"Kumano-ch\u014d",
    "wof:placetype":"localadmin",
    "wof:population":0
},
  "geometry": {"coordinates":[132.58968999999999,34.3474],"type":"Point"}
}