{
  "type": "Feature",
  "properties": {
    "gn:admin1_code":"34.0",
    "gn:admin2_code":"7464127.0",
    "gn:asciiname":"Tomishinden",
    "gn:country_code":"JP",
    "gn:dem":3,
    "gn:feature_class":"P",
    "gn:feature_code":"PPL",
    "gn:name":"Tomishinden",
    "gn:population":0,
    "gn:timezone":"Asia/Tokyo",
    "iso:country":"JP",
    "name:jpn_x_preferred":[
        "\u5bcc\u65b0\u7530"
    ],
    "wof:name":"Tomishinden",
    "wof:placetype":"locality"
},
  "geometry": {"coordinates":[139.86321000000001,35.87587],"type":"Point"}
}