{
  "type": "Feature",
  "properties": {
    "gn:admin1_code":"30.0",
    "gn:admin2_code":"1859233.0",
    "gn:asciiname":"Yamagamachi-kugino'o",
    "gn:country_code":"JP",
    "gn:dem":275,
    "gn:feature_class":"P",
    "gn:feature_code":"PPL",
    "gn:name":"Yamagamachi-kugino\u2019o",
    "gn:population":0,
    "gn:timezone":"Asia/Tokyo",
    "iso:country":"JP",
    "name:jpn_x_preferred":[
        "\u5c71\u9999\u753a\u4e45\u6728\u91ce\u5c3e"
    ],
    "name:und_x_variant":[
        "Yamagamachi-kugino\u2019o"
    ],
    "wof:name":"Yamagamachi-kugino'o",
    "wof:placetype":"locality"
},
  "geometry": {"coordinates":[131.42875000000001,33.39597],"type":"Point"}
}