{
  "type": "Feature",
  "properties": {
    "gn:admin1_code":"11",
    "gn:admin2_code":"1858288.0",
    "gn:asciiname":"Shimokamagaricho-sannose",
    "gn:country_code":"JP",
    "gn:dem":58,
    "gn:feature_class":"P",
    "gn:feature_code":"PPL",
    "gn:name":"Shimokamagarich\u014d-sannose",
    "gn:population":0,
    "gn:timezone":"Asia/Tokyo",
    "iso:country":"JP",
    "name:jpn_x_preferred":[
        "\u4e0b\u84b2\u5208\u753a\u4e09\u4e4b\u702c"
    ],
    "name:und_x_variant":[
        "Shimokamagarich\u014d-sannose",
        "Sannose"
    ],
    "wof:name":"Shimokamagaricho-sannose",
    "wof:placetype":"locality"
},
  "geometry": {"coordinates":[132.68135000000001,34.18919],"type":"Point"}
}