{
  "type": "Feature",
  "properties": {
    "gn:admin1_code":"18",
    "gn:admin2_code":"8714932.0",
    "gn:admin3_code":"46505.0",
    "gn:asciiname":"Mukio",
    "gn:country_code":"JP",
    "gn:dem":32,
    "gn:feature_class":"P",
    "gn:feature_code":"PPL",
    "gn:name":"Mukio",
    "gn:population":0,
    "gn:timezone":"Asia/Tokyo",
    "iso:country":"JP",
    "wof:name":"Mukio",
    "wof:placetype":"locality"
},
  "geometry": {"coordinates":[130.6001,30.25608],"type":"Point"}
}