{
  "type": "Feature",
  "properties": {
    "iso:country":"JP",
    "name:eng_x_preferred":[
        "Aza Mikanyama"
    ],
    "name:jpn_x_preferred":[
        "\u5b57\u5bc6\u67d1\u5c71"
    ],
    "qs:name":"\u5b57\u5bc6\u67d1\u5c71",
    "qs:name_adm0":"\u65e5\u672c",
    "qs:name_adm1":"\u611b\u77e5\u770c",
    "qs:photos":1,
    "qs:photos_1k":1,
    "qs:photos_9k":1,
    "qs:photos_9r":1,
    "qs:photos_all":1,
    "qs:photos_sr":1,
    "qs:placetype":"Suburb",
    "qs:pop_sr":"0",
    "wof:name":"Aza Mikanyama",
    "wof:placetype":"neighbourhood"
},
  "geometry": {"coordinates":[136.95233099999999,35.129966],"type":"Point"}
}