{
  "type": "Feature",
  "properties": {
    "iso:country":"JP",
    "name:eng_x_preferred":[
        "Okadai 1 Chome"
    ],
    "name:eng_x_variant":[
        "Oukadai 1 Choume",
        "Okadai 1 Chome"
    ],
    "name:jpn_x_preferred":[
        "\uff11\u4e01\u76ee"
    ],
    "name:jpn_x_variant":[
        "\u304a\u3046\u304b\u3060\u3044 \uff11\u3061\u3087\u3046\u3081",
        "\u685c\u82b1\u53f0 \uff11\u4e01\u76ee",
        "\uff11\u3061\u3087\u3046\u3081"
    ],
    "qs:gn_local":0,
    "qs:local_max":87,
    "qs:local_sum":321,
    "qs:localhoods":7,
    "qs:name":"\uff11\u4e01\u76ee",
    "qs:name_adm0":"\u65e5\u672c",
    "qs:name_adm1":"\u4e09\u91cd\u770c",
    "qs:name_en":"Okadai 1 Chome",
    "qs:name_lau":"\u685c\u82b1\u53f0",
    "qs:name_local":"\u56db\u65e5\u5e02\u5e02",
    "qs:photo_max":19,
    "qs:photo_sum":19,
    "qs:placetype":"Suburb",
    "qs:quad_count":1,
    "qs:woe_adm0":23424856,
    "qs:woe_adm1":2345872,
    "qs:woe_adm2":0,
    "qs:woe_lau":28446094,
    "qs:woe_local":1118548,
    "qs:woe_ver":"7.10.0",
    "wof:lang":[
        "jpn"
    ],
    "wof:name":"\uff11\u4e01\u76ee",
    "wof:placetype":"neighbourhood"
},
  "geometry": {"coordinates":[136.52984599999999,35.005253],"type":"Point"}
}