{
  "type": "Feature",
  "properties": {
    "gn:admin1_code":"46",
    "gn:admin2_code":"1849406.0",
    "gn:asciiname":"Shimoiwa",
    "gn:country_code":"JP",
    "gn:dem":360,
    "gn:feature_class":"P",
    "gn:feature_code":"PPL",
    "gn:name":"Shimoiwa",
    "gn:population":0,
    "gn:timezone":"Asia/Tokyo",
    "iso:country":"JP",
    "wof:name":"Shimoiwa",
    "wof:placetype":"locality"
},
  "geometry": {"coordinates":[139.11888999999999,35.65194],"type":"Point"}
}