{
  "type": "Feature",
  "properties": {
    "gn:admin1_code":"16.0",
    "gn:admin2_code":"2112223.0",
    "gn:asciiname":"Tsukidate",
    "gn:country_code":"JP",
    "gn:dem":85,
    "gn:feature_class":"P",
    "gn:feature_code":"PPL",
    "gn:name":"Tsukidate",
    "gn:population":0,
    "gn:timezone":"Asia/Tokyo",
    "iso:country":"JP",
    "name:jpn_x_preferred":[
        "\u7bc9\u8218"
    ],
    "name:jpn_x_variant":[
        "\u3064\u304d\u3060\u3066",
        "\u30c4\u30ad\u30c0\u30c6"
    ],
    "wof:name":"Tsukidate",
    "wof:placetype":"locality"
},
  "geometry": {"coordinates":[141.12828999999999,39.32498],"type":"Point"}
}