{
  "type": "Feature",
  "properties": {
    "gn:admin1_code":"8.0",
    "gn:admin2_code":"9035647.0",
    "gn:asciiname":"Negishi",
    "gn:country_code":"JP",
    "gn:dem":453,
    "gn:feature_class":"P",
    "gn:feature_code":"PPLL",
    "gn:name":"Negishi",
    "gn:population":0,
    "gn:timezone":"Asia/Tokyo",
    "iso:country":"JP",
    "name:deu_x_preferred":[
        "Negishi"
    ],
    "name:jpn_x_preferred":[
        "\u6839\u5cb8"
    ],
    "name:kor_x_preferred":[
        "\ub124\uae30\uc2dc"
    ],
    "name:rus_x_preferred":[
        "\u041d\u044d\u0433\u0438\u0441\u0438"
    ],
    "wof:name":"Negishi",
    "wof:placetype":"locality"
},
  "geometry": {"coordinates":[140.64986999999999,37.5154],"type":"Point"}
}