{
  "type": "Feature",
  "properties": {
    "gn:admin1_code":"26.0",
    "gn:admin2_code":"1851356.0",
    "gn:asciiname":"Toyooka",
    "gn:country_code":"JP",
    "gn:dem":566,
    "gn:feature_class":"P",
    "gn:feature_code":"PPL",
    "gn:name":"Toyooka",
    "gn:population":0,
    "gn:timezone":"Asia/Tokyo",
    "iso:country":"JP",
    "name:jpn_x_preferred":[
        "\u8c4a\u4e18"
    ],
    "wof:name":"Toyooka",
    "wof:placetype":"locality"
},
  "geometry": {"coordinates":[138.34696,36.6364],"type":"Point"}
}