{
  "type": "Feature",
  "properties": {
    "gn:admin1_code":"4.0",
    "gn:admin2_code":"1863711.0",
    "gn:asciiname":"Okuhara",
    "gn:country_code":"JP",
    "gn:dem":134,
    "gn:feature_class":"P",
    "gn:feature_code":"PPLL",
    "gn:name":"Okuhara",
    "gn:population":0,
    "gn:timezone":"Asia/Tokyo",
    "iso:country":"JP",
    "name:jpn_x_preferred":[
        "\u5965\u539f"
    ],
    "name:jpn_x_variant":[
        "\u304a\u304f\u306f\u3089",
        "\u30aa\u30af\u30cf\u30e9"
    ],
    "wof:name":"Okuhara",
    "wof:placetype":"locality"
},
  "geometry": {"coordinates":[139.92526000000001,35.16558],"type":"Point"}
}