{
  "type": "Feature",
  "properties": {
    "gn:admin1_code":"37.0",
    "gn:admin2_code":"1856971.0",
    "gn:asciiname":"Okuyama",
    "gn:country_code":"JP",
    "gn:dem":216,
    "gn:feature_class":"P",
    "gn:feature_code":"PPLL",
    "gn:name":"Okuyama",
    "gn:population":0,
    "gn:timezone":"Asia/Tokyo",
    "iso:country":"JP",
    "name:jpn_x_preferred":[
        "\u5965\u5c71"
    ],
    "name:kor_x_preferred":[
        "\uc624\ucfe0\uc57c\ub9c8"
    ],
    "wof:name":"Okuyama",
    "wof:placetype":"locality"
},
  "geometry": {"coordinates":[138.96878999999998,35.13177],"type":"Point"}
}