{
  "type": "Feature",
  "properties": {
    "gn:admin1_code":"28.0",
    "gn:admin2_code":"1853062.0",
    "gn:asciiname":"Daifuku",
    "gn:country_code":"JP",
    "gn:dem":63,
    "gn:feature_class":"P",
    "gn:feature_code":"PPL",
    "gn:name":"Daifuku",
    "gn:population":0,
    "gn:timezone":"Asia/Tokyo",
    "iso:country":"JP",
    "name:jpn_x_preferred":[
        "\u5927\u798f"
    ],
    "wof:name":"Daifuku",
    "wof:placetype":"locality"
},
  "geometry": {"coordinates":[135.82685000000001,34.51471],"type":"Point"}
}