{
  "type": "Feature",
  "properties": {
    "gn:admin1_code":"28.0",
    "gn:admin2_code":"1853062.0",
    "gn:asciiname":"Daifuku",
    "gn:country_code":"JP",
    "gn:dem":63,
    "gn:feature_class":"P",
    "gn:feature_code":"PPL",
    "gn:name":"Daifuku",
    "gn:population":0,
    "gn:timezone":"Asia/Tokyo",
    "iso:country":"JP",
    "name:ara_x_preferred":[
        "\u062f\u0627\u064a\u0641\u0648\u0643\u0648"
    ],
    "name:ces_x_preferred":[
        "Daifuku"
    ],
    "name:dan_x_preferred":[
        "Daifuku"
    ],
    "name:deu_x_preferred":[
        "Daifuku"
    ],
    "name:epo_x_preferred":[
        "Daifuku"
    ],
    "name:fas_x_preferred":[
        "\u062f\u0627\u06cc\u0641\u0648\u06a9\u0648"
    ],
    "name:fra_x_preferred":[
        "Daifuku"
    ],
    "name:glg_x_preferred":[
        "Daifuku"
    ],
    "name:ind_x_preferred":[
        "Daifuku"
    ],
    "name:ita_x_preferred":[
        "Daifuku"
    ],
    "name:jpn_x_preferred":[
        "\u5927\u798f"
    ],
    "name:kor_x_preferred":[
        "\ub2e4\uc774\ud6c4\ucfe0"
    ],
    "name:nor_x_preferred":[
        "Daifuku"
    ],
    "name:pan_x_preferred":[
        "\u0a26\u0a3e\u0a08\u0a2b\u0a3c\u0a41\u0a15\u0a41"
    ],
    "name:por_x_preferred":[
        "Daifuku"
    ],
    "name:rus_x_preferred":[
        "\u0414\u0430\u0439\u0444\u0443\u043a\u0443"
    ],
    "name:spa_x_preferred":[
        "Daifuku"
    ],
    "name:swe_x_preferred":[
        "Daifuku"
    ],
    "name:tur_x_preferred":[
        "Daifuku"
    ],
    "name:ukr_x_preferred":[
        "\u0414\u0430\u0439\u0444\u0443\u043a\u0443"
    ],
    "name:vie_x_preferred":[
        "Daifuku"
    ],
    "name:zho_x_preferred":[
        "\u5927\u798f"
    ],
    "wof:name":"Daifuku",
    "wof:placetype":"locality"
},
  "geometry": {"coordinates":[135.82685000000001,34.51471],"type":"Point"}
}