{
  "type": "Feature",
  "properties": {
    "gn:admin1_code":"4.0",
    "gn:admin2_code":"1864901.0",
    "gn:admin3_code":"12463.0",
    "gn:asciiname":"Hara",
    "gn:country_code":"JP",
    "gn:dem":40,
    "gn:feature_class":"P",
    "gn:feature_code":"PPLL",
    "gn:name":"Hara",
    "gn:population":0,
    "gn:timezone":"Asia/Tokyo",
    "iso:country":"JP",
    "name:jpn_x_preferred":[
        "\u539f"
    ],
    "name:jpn_x_variant":[
        "\u306f\u3089",
        "\u30cf\u30e9"
    ],
    "wof:name":"Hara",
    "wof:placetype":"locality"
},
  "geometry": {"coordinates":[139.84041999999999,35.12182],"type":"Point"}
}