{
  "type": "Feature",
  "properties": {
    "iso:country":"JP",
    "qs:name":"\uff13\u4e01\u76ee",
    "qs:name_adm0":"\u65e5\u672c",
    "qs:name_adm1":"\u57fc\u7389\u770c",
    "qs:photos":14,
    "qs:photos_1k":3,
    "qs:photos_9k":1,
    "qs:photos_9r":1,
    "qs:photos_all":14,
    "qs:photos_sr":1,
    "qs:placetype":"Suburb",
    "qs:pop_sr":"0",
    "wof:name":"\uff13\u4e01\u76ee",
    "wof:placetype":"neighbourhood"
},
  "geometry": {"coordinates":[139.868842,35.802163],"type":"Point"}
}