{
  "type": "Feature",
  "properties": {
    "gn:admin1_code":"33.0",
    "gn:admin2_code":"8300623.0",
    "gn:asciiname":"Takekoba",
    "gn:country_code":"JP",
    "gn:dem":208,
    "gn:feature_class":"P",
    "gn:feature_code":"PPL",
    "gn:name":"Takekoba",
    "gn:population":0,
    "gn:timezone":"Asia/Tokyo",
    "iso:country":"JP",
    "name:jpn_x_preferred":[
        "\u7af9\u6728\u5834"
    ],
    "wof:name":"Takekoba",
    "wof:placetype":"locality"
},
  "geometry": {"coordinates":[129.92116999999999,33.42454],"type":"Point"}
}