{
  "type": "Feature",
  "properties": {
    "gn:admin1_code":"25",
    "gn:admin2_code":"1853223.0",
    "gn:asciiname":"Tonokorimachi",
    "gn:country_code":"JP",
    "gn:dem":31,
    "gn:feature_class":"P",
    "gn:feature_code":"PPL",
    "gn:name":"Tonok\u014drimachi",
    "gn:population":0,
    "gn:timezone":"Asia/Tokyo",
    "iso:country":"JP",
    "name:jpn_x_preferred":[
        "\u90fd\u65bc\u90e1\u753a"
    ],
    "name:und_x_variant":[
        "Tonokori",
        "Tonok\u014drimachi"
    ],
    "wof:name":"Tonokorimachi",
    "wof:placetype":"locality"
},
  "geometry": {"coordinates":[131.38333,32.06667],"type":"Point"}
}