{
  "type": "Feature",
  "properties": {
    "gn:admin1_code":"4.0",
    "gn:admin2_code":"2110982.0",
    "gn:asciiname":"Oguradai",
    "gn:country_code":"JP",
    "gn:dem":76,
    "gn:feature_class":"P",
    "gn:feature_code":"PPLL",
    "gn:name":"Oguradai",
    "gn:population":0,
    "gn:timezone":"Asia/Tokyo",
    "iso:country":"JP",
    "name:jpn_x_preferred":[
        "\u5c0f\u5009\u53f0"
    ],
    "name:jpn_x_variant":[
        "\u304a\u3050\u3089\u3060\u3044",
        "\u30aa\u30b0\u30e9\u30c0\u30a4"
    ],
    "wof:name":"Oguradai",
    "wof:placetype":"locality"
},
  "geometry": {"coordinates":[140.07435000000001,35.39463],"type":"Point"}
}