{
  "type": "Feature",
  "properties": {
    "gn:admin1_code":"3.0",
    "gn:admin2_code":"2130088.0",
    "gn:admin3_code":"2301.0",
    "gn:asciiname":"Fukushima",
    "gn:country_code":"JP",
    "gn:dem":25,
    "gn:feature_class":"P",
    "gn:feature_code":"PPL",
    "gn:name":"Fukushima",
    "gn:population":0,
    "gn:timezone":"Asia/Tokyo",
    "iso:country":"JP",
    "name:jpn_x_preferred":[
        "\u798f\u5cf6"
    ],
    "name:jpn_x_variant":[
        "\u3075\u304f\u3057\u307e",
        "\u30d5\u30af\u30b7\u30de"
    ],
    "wof:name":"Fukushima",
    "wof:placetype":"locality"
},
  "geometry": {"coordinates":[140.95419999999999,40.9374],"type":"Point"}
}