{
  "type": "Feature",
  "properties": {
    "iso:country":"JP",
    "name:eng_x_preferred":[
        "Katsutadaiminami 3 Chome"
    ],
    "name:eng_x_variant":[
        "Katsutadaiminami 3 Choume",
        "Katsutadaiminami 3 Chome"
    ],
    "name:jpn_x_preferred":[
        "\uff13\u4e01\u76ee"
    ],
    "name:jpn_x_variant":[
        "\u304b\u3064\u305f\u3060\u3044\u307f\u306a\u307f \uff13\u3061\u3087\u3046\u3081",
        "\u52dd\u7530\u53f0\u5357 \uff13\u4e01\u76ee",
        "\uff13\u3061\u3087\u3046\u3081"
    ],
    "qs:gn_local":0,
    "qs:local_max":870,
    "qs:local_sum":1262,
    "qs:localhoods":8,
    "qs:name":"\uff13\u4e01\u76ee",
    "qs:name_adm0":"\u65e5\u672c",
    "qs:name_adm1":"\u5343\u8449\u770c",
    "qs:name_en":"Katsutadaiminami 3 Chome",
    "qs:name_lau":"\u52dd\u7530\u53f0\u5357",
    "qs:name_local":"\u516b\u5343\u4ee3\u5e02",
    "qs:photo_max":59,
    "qs:photo_sum":86,
    "qs:placetype":"Suburb",
    "qs:quad_count":4,
    "qs:woe_adm0":23424856,
    "qs:woe_adm1":2345854,
    "qs:woe_adm2":0,
    "qs:woe_lau":28412349,
    "qs:woe_local":15015404,
    "qs:woe_ver":"7.10.0",
    "wof:lang":[
        "jpn"
    ],
    "wof:name":"\uff13\u4e01\u76ee",
    "wof:placetype":"neighbourhood"
},
  "geometry": {"coordinates":[140.115634,35.710639],"type":"Point"}
}