{
  "type": "Feature",
  "properties": {
    "gn:admin1_code":"27.0",
    "gn:admin2_code":"7418810.0",
    "gn:asciiname":"Kamiagatacho-seta",
    "gn:country_code":"JP",
    "gn:dem":17,
    "gn:feature_class":"P",
    "gn:feature_code":"PPL",
    "gn:name":"Kamiagatach\u014d-seta",
    "gn:population":0,
    "gn:timezone":"Asia/Tokyo",
    "iso:country":"JP",
    "name:jpn_x_preferred":[
        "\u4e0a\u770c\u753a\u702c\u7530"
    ],
    "name:und_x_variant":[
        "Kamiagatach\u014d-seta"
    ],
    "wof:name":"Kamiagatacho-seta",
    "wof:placetype":"locality"
},
  "geometry": {"coordinates":[129.35549,34.53949],"type":"Point"}
}