{
  "type": "Feature",
  "properties": {
    "gn:admin1_code":"11",
    "gn:admin2_code":"8740425.0",
    "gn:asciiname":"Koyo",
    "gn:country_code":"JP",
    "gn:dem":73,
    "gn:feature_class":"P",
    "gn:feature_code":"PPL",
    "gn:name":"Koy\u014d",
    "gn:population":0,
    "gn:timezone":"Asia/Tokyo",
    "iso:country":"JP",
    "name:und_x_variant":[
        "Koy\u014d"
    ],
    "wof:name":"Koyo",
    "wof:placetype":"locality"
},
  "geometry": {"coordinates":[132.48333,34.25],"type":"Point"}
}