{
  "type": "Feature",
  "properties": {
    "gn:admin1_code":"26.0",
    "gn:admin2_code":"1860552.0",
    "gn:admin3_code":"20382.0",
    "gn:asciiname":"Shimomura",
    "gn:country_code":"JP",
    "gn:dem":862,
    "gn:feature_class":"P",
    "gn:feature_code":"PPL",
    "gn:name":"Shimomura",
    "gn:population":0,
    "gn:timezone":"Asia/Tokyo",
    "iso:country":"JP",
    "name:jpn_x_preferred":[
        "\u4e0b\u6751"
    ],
    "wof:name":"Shimomura",
    "wof:placetype":"locality"
},
  "geometry": {"coordinates":[137.94648000000001,36.03438],"type":"Point"}
}