{
  "type": "Feature",
  "properties": {
    "gn:admin1_code":"3.0",
    "gn:admin2_code":"2130654.0",
    "gn:asciiname":"Kodate",
    "gn:country_code":"JP",
    "gn:dem":93,
    "gn:feature_class":"P",
    "gn:feature_code":"PPL",
    "gn:name":"Kodate",
    "gn:population":0,
    "gn:timezone":"Asia/Tokyo",
    "iso:country":"JP",
    "name:jpn_x_preferred":[
        "\u5c0f\u9928"
    ],
    "name:jpn_x_variant":[
        "\u3053\u3060\u3066",
        "\u30b3\u30c0\u30c6"
    ],
    "wof:name":"Kodate",
    "wof:placetype":"locality"
},
  "geometry": {"coordinates":[140.72210999999999,40.743],"type":"Point"}
}