{
  "type": "Feature",
  "properties": {
    "iso:country":"JP",
    "name:eng_x_preferred":[
        "Otsuka 2 Chome"
    ],
    "name:eng_x_variant":[
        "Ootsuka 2 Choume",
        "Otsuka 2 Chome"
    ],
    "name:jpn_x_preferred":[
        "\uff12\u4e01\u76ee"
    ],
    "name:jpn_x_variant":[
        "\u304a\u304a\u3064\u304b \uff12\u3061\u3087\u3046\u3081",
        "\u5927\u585a \uff12\u4e01\u76ee",
        "\uff12\u3061\u3087\u3046\u3081"
    ],
    "qs:gn_local":0,
    "qs:local_max":166,
    "qs:local_sum":380,
    "qs:localhoods":6,
    "qs:name":"\uff12\u4e01\u76ee",
    "qs:name_adm0":"\u65e5\u672c",
    "qs:name_adm1":"\u798f\u5cf6\u770c",
    "qs:name_en":"Otsuka 2 Chome",
    "qs:name_lau":"\u5927\u585a",
    "qs:name_local":"\u4f1a\u6d25\u82e5\u677e\u5e02",
    "qs:photo_max":18,
    "qs:photo_sum":36,
    "qs:placetype":"Suburb",
    "qs:quad_count":6,
    "qs:woe_adm0":23424856,
    "qs:woe_adm1":2345858,
    "qs:woe_adm2":0,
    "qs:woe_lau":28398334,
    "qs:woe_local":1116932,
    "qs:woe_ver":"7.10.0",
    "wof:lang":[
        "jpn"
    ],
    "wof:name":"\uff12\u4e01\u76ee",
    "wof:placetype":"neighbourhood"
},
  "geometry": {"coordinates":[139.93872400000001,37.523092],"type":"Point"}
}