{
  "type": "Feature",
  "properties": {
    "gn:admin1_code":"33.0",
    "gn:admin2_code":"7391355.0",
    "gn:asciiname":"Okawachicho-ko",
    "gn:country_code":"JP",
    "gn:dem":160,
    "gn:feature_class":"P",
    "gn:feature_code":"PPL",
    "gn:name":"\u014ckawachich\u014d-k\u014d",
    "gn:population":0,
    "gn:timezone":"Asia/Tokyo",
    "iso:country":"JP",
    "name:jpn_x_preferred":[
        "\u5927\u5ddd\u5185\u753a\u7532"
    ],
    "name:und_x_variant":[
        "\u014ckawachich\u014d-k\u014d"
    ],
    "wof:name":"Okawachicho-ko",
    "wof:placetype":"locality"
},
  "geometry": {"coordinates":[129.90861000000001,33.24271],"type":"Point"}
}