{
  "type": "Feature",
  "properties": {
    "gn:admin1_code":"18.0",
    "gn:admin2_code":"7383999.0",
    "gn:admin3_code":"46490.0",
    "gn:asciiname":"Kukino",
    "gn:country_code":"JP",
    "gn:dem":272,
    "gn:feature_class":"P",
    "gn:feature_code":"PPLL",
    "gn:name":"Kukino",
    "gn:population":0,
    "gn:timezone":"Asia/Tokyo",
    "iso:country":"JP",
    "name:jpn_x_preferred":[
        "\u4e45\u6728\u91ce"
    ],
    "wof:name":"Kukino",
    "wof:placetype":"locality"
},
  "geometry": {"coordinates":[130.86642000000001,31.15698],"type":"Point"}
}