{
  "type": "Feature",
  "properties": {
    "gn:admin1_code":"37.0",
    "gn:admin2_code":"1864104.0",
    "gn:asciiname":"Kandagawacho",
    "gn:country_code":"JP",
    "gn:dem":115,
    "gn:feature_class":"P",
    "gn:feature_code":"PPL",
    "gn:name":"Kandagawach\u014d",
    "gn:population":0,
    "gn:timezone":"Asia/Tokyo",
    "iso:country":"JP",
    "name:jpn_x_preferred":[
        "\u795e\u7530\u5ddd\u753a"
    ],
    "name:und_x_variant":[
        "Kandagawach\u014d"
    ],
    "wof:name":"Kandagawacho",
    "wof:placetype":"locality"
},
  "geometry": {"coordinates":[138.60778999999999,35.22168],"type":"Point"}
}