{
  "type": "Feature",
  "properties": {
    "gn:admin1_code":"7.0",
    "gn:admin2_code":"1854055.0",
    "gn:admin3_code":"40381.0",
    "gn:asciiname":"Shozugahama",
    "gn:country_code":"JP",
    "gn:dem":6,
    "gn:feature_class":"P",
    "gn:feature_code":"PPLL",
    "gn:name":"Sh\u014dzugahama",
    "gn:population":0,
    "gn:timezone":"Asia/Tokyo",
    "iso:country":"JP",
    "name:jpn_x_preferred":[
        "\u6b63\u6d25\u30f6\u6d5c"
    ],
    "name:und_x_variant":[
        "Sh\u014dzugahama"
    ],
    "wof:name":"Shozugahama",
    "wof:placetype":"locality"
},
  "geometry": {"coordinates":[130.66839999999999,33.90617],"type":"Point"}
}