{
  "type": "Feature",
  "properties": {
    "gn:admin1_code":"33.0",
    "gn:admin2_code":"1856784.0",
    "gn:admin3_code":"41346.0",
    "gn:asciiname":"Higashioshima",
    "gn:country_code":"JP",
    "gn:dem":5,
    "gn:feature_class":"P",
    "gn:feature_code":"PPLL",
    "gn:name":"Higashi\u014dshima",
    "gn:population":0,
    "gn:timezone":"Asia/Tokyo",
    "iso:country":"JP",
    "name:jpn_x_preferred":[
        "\u6771\u5927\u5cf6"
    ],
    "name:und_x_variant":[
        "Higashi\u014dshima"
    ],
    "wof:name":"Higashioshima",
    "wof:placetype":"locality"
},
  "geometry": {"coordinates":[130.47197,33.31479],"type":"Point"}
}