{
  "type": "Feature",
  "properties": {
    "iso:country":"JP",
    "qs:name":"\u4e45\u4e07\u9ad8\u539f\u753a",
    "qs:name_adm0":"\u65e5\u672c",
    "qs:name_adm1":"\u611b\u5a9b\u770c",
    "qs:photos":128,
    "qs:photos_1k":26,
    "qs:photos_9k":1,
    "qs:photos_9r":3,
    "qs:photos_all":128,
    "qs:photos_sr":3,
    "qs:placetype":"Town",
    "qs:pop_sr":"0",
    "wof:name":"\u4e45\u4e07\u9ad8\u539f\u753a",
    "wof:placetype":"locality"
},
  "geometry": {"coordinates":[132.98288049999999,33.68721],"type":"Point"}
}