{
  "type": "Feature",
  "properties": {
    "gn:admin1_code":"18.0",
    "gn:admin2_code":"1860823.0",
    "gn:asciiname":"Yoshimi",
    "gn:country_code":"JP",
    "gn:dem":355,
    "gn:feature_class":"P",
    "gn:feature_code":"PPLL",
    "gn:name":"Yoshimi",
    "gn:population":0,
    "gn:timezone":"Asia/Tokyo",
    "iso:country":"JP",
    "name:jpn_x_preferred":[
        "\u5409\u898b"
    ],
    "wof:name":"Yoshimi",
    "wof:placetype":"locality"
},
  "geometry": {"coordinates":[130.54008999999999,31.31146],"type":"Point"}
}