{
  "type": "Feature",
  "properties": {
    "gn:admin1_code":"23.0",
    "gn:admin2_code":"1861901.0",
    "gn:asciiname":"Shimoawa",
    "gn:country_code":"JP",
    "gn:dem":252,
    "gn:feature_class":"P",
    "gn:feature_code":"PPL",
    "gn:name":"Shimoawa",
    "gn:population":0,
    "gn:timezone":"Asia/Tokyo",
    "iso:country":"JP",
    "name:jpn_x_preferred":[
        "\u4e0b\u963f\u6ce2"
    ],
    "wof:name":"Shimoawa",
    "wof:placetype":"locality"
},
  "geometry": {"coordinates":[136.25724,34.75423],"type":"Point"}
}