{
  "type": "Feature",
  "properties": {
    "gn:admin1_code":"23.0",
    "gn:admin2_code":"1861901.0",
    "gn:asciiname":"Mashino",
    "gn:country_code":"JP",
    "gn:dem":282,
    "gn:feature_class":"P",
    "gn:feature_code":"PPL",
    "gn:name":"Mashino",
    "gn:population":0,
    "gn:timezone":"Asia/Tokyo",
    "iso:country":"JP",
    "name:jpn_x_preferred":[
        "\u733f\u91ce"
    ],
    "wof:name":"Mashino",
    "wof:placetype":"locality"
},
  "geometry": {"coordinates":[136.28028,34.76414],"type":"Point"}
}