{
  "type": "Feature",
  "properties": {
    "gn:admin1_code":"7.0",
    "gn:admin2_code":"1863955.0",
    "gn:admin3_code":"40135.0",
    "gn:asciiname":"Miyanoura",
    "gn:country_code":"JP",
    "gn:dem":25,
    "gn:feature_class":"P",
    "gn:feature_code":"PPL",
    "gn:name":"Miyanoura",
    "gn:population":0,
    "gn:timezone":"Asia/Tokyo",
    "iso:country":"JP",
    "name:jpn_x_preferred":[
        "\u5bae\u6d66"
    ],
    "wof:name":"Miyanoura",
    "wof:placetype":"locality"
},
  "geometry": {"coordinates":[130.22718,33.64343],"type":"Point"}
}