{
  "type": "Feature",
  "properties": {
    "gn:admin1_code":"37",
    "gn:admin2_code":"8301106.0",
    "gn:asciiname":"Ogi",
    "gn:country_code":"JP",
    "gn:dem":177,
    "gn:feature_class":"P",
    "gn:feature_code":"PPL",
    "gn:name":"Ogi",
    "gn:population":0,
    "gn:timezone":"Asia/Tokyo",
    "iso:country":"JP",
    "name:deu_x_preferred":[
        "Ogi"
    ],
    "name:fra_x_preferred":[
        "Ogi"
    ],
    "name:ita_x_preferred":[
        "Ogi"
    ],
    "name:jpn_x_preferred":[
        "\u837b"
    ],
    "name:pol_x_preferred":[
        "Ogi"
    ],
    "name:rus_x_preferred":[
        "\u041e\u0433\u0438"
    ],
    "name:spa_x_preferred":[
        "Ogi"
    ],
    "name:swe_x_preferred":[
        "Ogi"
    ],
    "wof:name":"Ogi",
    "wof:placetype":"locality"
},
  "geometry": {"coordinates":[139.09056000000001,34.94024],"type":"Point"}
}