{
  "type": "Feature",
  "properties": {
    "iso:country":"JP",
    "name:eng_x_preferred":[
        "Imamachi 2 Chome"
    ],
    "name:eng_x_variant":[
        "Imamachi 2 Choume",
        "Imamachi 2 Chome"
    ],
    "name:jpn_x_preferred":[
        "\uff12\u4e01\u76ee"
    ],
    "name:jpn_x_variant":[
        "\u3044\u307e\u307e\u3061 \uff12\u3061\u3087\u3046\u3081",
        "\u4eca\u753a \uff12\u4e01\u76ee",
        "\uff12\u3061\u3087\u3046\u3081"
    ],
    "name:unk_x_variant":[
        "\uff12\u4e01\u76ee"
    ],
    "qs:gn_adm0_cc":"JP",
    "qs:gn_local":1849892,
    "qs:local_max":591,
    "qs:local_sum":723,
    "qs:localhoods":5,
    "qs:name":"\uff12\u4e01\u76ee",
    "qs:name_adm0":"\u65e5\u672c",
    "qs:name_adm1":"\u9ce5\u53d6\u770c",
    "qs:name_en":"Imamachi 2 Chome",
    "qs:name_lau":"\u4eca\u753a",
    "qs:name_local":"\u9ce5\u53d6\u5e02",
    "qs:photo_max":53,
    "qs:photo_sum":95,
    "qs:placetype":"Suburb",
    "qs:quad_count":4,
    "qs:woe_adm0":23424856,
    "qs:woe_adm1":2345890,
    "qs:woe_adm2":0,
    "qs:woe_lau":28469092,
    "qs:woe_local":1118395,
    "qs:woe_ver":"7.10.0",
    "wof:lang":[
        "jpn"
    ],
    "wof:name":"\uff12\u4e01\u76ee",
    "wof:placetype":"neighbourhood"
},
  "geometry": {"coordinates":[134.226215,35.494549],"type":"Point"}
}