{
  "type": "Feature",
  "properties": {
    "gn:admin1_code":"19",
    "gn:admin2_code":"1862461.0",
    "gn:asciiname":"Kitaona",
    "gn:country_code":"JP",
    "gn:dem":13,
    "gn:feature_class":"P",
    "gn:feature_code":"PPL",
    "gn:name":"Kita\u014dna",
    "gn:population":0,
    "gn:timezone":"Asia/Tokyo",
    "iso:country":"JP",
    "name:und_x_variant":[
        "Kita\u014dna"
    ],
    "wof:name":"Kitaona",
    "wof:placetype":"locality"
},
  "geometry": {"coordinates":[139.30694,35.36889],"type":"Point"}
}