{
  "type": "Feature",
  "properties": {
    "gn:admin1_code":"8.0",
    "gn:admin2_code":"2110958.0",
    "gn:asciiname":"Shioda",
    "gn:country_code":"JP",
    "gn:dem":277,
    "gn:feature_class":"P",
    "gn:feature_code":"PPL",
    "gn:name":"Shioda",
    "gn:population":0,
    "gn:timezone":"Asia/Tokyo",
    "iso:country":"JP",
    "name:jpn_x_preferred":[
        "\u5869\u7530"
    ],
    "wof:name":"Shioda",
    "wof:placetype":"locality"
},
  "geometry": {"coordinates":[140.42871,37.29724],"type":"Point"}
}