{
  "type": "Feature",
  "properties": {
    "gn:admin1_code":"3.0",
    "gn:admin2_code":"2130056.0",
    "gn:asciiname":"Jigata",
    "gn:country_code":"JP",
    "gn:dem":54,
    "gn:feature_class":"P",
    "gn:feature_code":"PPL",
    "gn:name":"Jigata",
    "gn:population":0,
    "gn:timezone":"Asia/Tokyo",
    "iso:country":"JP",
    "name:jpn_x_preferred":[
        "\u5730\u5f62"
    ],
    "name:jpn_x_variant":[
        "\u3058\u304c\u305f",
        "\u30b8\u30ac\u30bf"
    ],
    "wof:name":"Jigata",
    "wof:placetype":"locality"
},
  "geometry": {"coordinates":[140.38952,40.58714000000001],"type":"Point"}
}