{
  "type": "Feature",
  "properties": {
    "gn:admin1_code":"43",
    "gn:asciiname":"Nachika",
    "gn:cc2":"JP",
    "gn:country_code":"JP",
    "gn:dem":-9999,
    "gn:feature_class":"P",
    "gn:feature_code":"PPL",
    "gn:name":"Nachika",
    "gn:population":0,
    "gn:timezone":"Asia/Tokyo",
    "iso:country":"JP",
    "name:und_x_variant":[
        "Najika",
        "Nachika"
    ],
    "wof:name":"Nachika",
    "wof:placetype":"locality"
},
  "geometry": {"coordinates":[135.73333,33.46667],"type":"Point"}
}