{
  "type": "Feature",
  "properties": {
    "gn:admin1_code":"2.0",
    "gn:admin2_code":"7443156.0",
    "gn:asciiname":"Akarimata",
    "gn:country_code":"JP",
    "gn:dem":168,
    "gn:feature_class":"P",
    "gn:feature_code":"PPLL",
    "gn:name":"Akarimata",
    "gn:population":0,
    "gn:timezone":"Asia/Tokyo",
    "iso:country":"JP",
    "name:jpn_x_preferred":[
        "\u660e\u5229\u53c8"
    ],
    "wof:name":"Akarimata",
    "wof:placetype":"locality"
},
  "geometry": {"coordinates":[140.50538999999998,40.10494],"type":"Point"}
}