{
  "type": "Feature",
  "properties": {
    "gn:admin1_code":"17.0",
    "gn:admin2_code":"1856906.0",
    "gn:asciiname":"Motomura",
    "gn:country_code":"JP",
    "gn:dem":10,
    "gn:feature_class":"P",
    "gn:feature_code":"PPLL",
    "gn:name":"Motomura",
    "gn:population":0,
    "gn:timezone":"Asia/Tokyo",
    "iso:country":"JP",
    "name:jpn_x_preferred":[
        "\u672c\u6751"
    ],
    "name:und_x_variant":[
        "Honmura"
    ],
    "wof:name":"Motomura",
    "wof:placetype":"locality"
},
  "geometry": {"coordinates":[133.68204,34.27065],"type":"Point"}
}