{
  "type": "Feature",
  "properties": {
    "gn:admin1_code":"13.0",
    "gn:admin2_code":"7370811.0",
    "gn:asciiname":"Yokawacho-mizukami",
    "gn:country_code":"JP",
    "gn:dem":158,
    "gn:feature_class":"P",
    "gn:feature_code":"PPL",
    "gn:name":"Yokawach\u014d-mizukami",
    "gn:population":0,
    "gn:timezone":"Asia/Tokyo",
    "iso:country":"JP",
    "name:jpn_x_preferred":[
        "\u5409\u5ddd\u753a\u6c34\u4e0a"
    ],
    "name:und_x_variant":[
        "Yokawach\u014d-mizukami"
    ],
    "wof:name":"Yokawacho-mizukami",
    "wof:placetype":"locality"
},
  "geometry": {"coordinates":[135.13756000000001,34.85136],"type":"Point"}
}