{
  "type": "Feature",
  "properties": {
    "gn:admin1_code":"2.0",
    "gn:admin2_code":"2113122.0",
    "gn:asciiname":"Kurokawa",
    "gn:country_code":"JP",
    "gn:dem":25,
    "gn:feature_class":"P",
    "gn:feature_code":"PPL",
    "gn:name":"Kurokawa",
    "gn:population":0,
    "gn:timezone":"Asia/Tokyo",
    "iso:country":"JP",
    "name:deu_x_preferred":[
        "Kurokawa"
    ],
    "name:jpn_x_preferred":[
        "\u9ed2\u5ddd"
    ],
    "name:jpn_x_variant":[
        "\u304f\u308d\u304b\u308f",
        "\u30af\u30ed\u30ab\u30ef"
    ],
    "wof:name":"Kurokawa",
    "wof:placetype":"locality"
},
  "geometry": {"coordinates":[140.10847999999999,39.83849],"type":"Point"}
}