{
  "type": "Feature",
  "properties": {
    "gn:admin1_code":"33",
    "gn:admin2_code":"1853274.0",
    "gn:asciiname":"Matsubara",
    "gn:country_code":"JP",
    "gn:dem":10,
    "gn:feature_class":"P",
    "gn:feature_code":"PPL",
    "gn:name":"Matsubara",
    "gn:population":0,
    "gn:timezone":"Asia/Tokyo",
    "iso:country":"JP",
    "name:jpn_x_preferred":[
        "\u677e\u539f"
    ],
    "name:und_x_variant":[
        "Matsubarach\u014d",
        "Matsubaramachi",
        "Matsubara"
    ],
    "wof:name":"Matsubara",
    "wof:placetype":"locality"
},
  "geometry": {"coordinates":[130.29920000000001,33.25233],"type":"Point"}
}