{
  "type": "Feature",
  "properties": {
    "gn:admin1_code":"6.0",
    "gn:admin2_code":"1863982.0",
    "gn:asciiname":"Imaichicho",
    "gn:country_code":"JP",
    "gn:dem":8,
    "gn:feature_class":"P",
    "gn:feature_code":"PPL",
    "gn:name":"Imaichich\u014d",
    "gn:population":0,
    "gn:timezone":"Asia/Tokyo",
    "iso:country":"JP",
    "name:jpn_x_preferred":[
        "\u4eca\u5e02\u753a"
    ],
    "name:und_x_variant":[
        "Imaichich\u014d"
    ],
    "wof:name":"Imaichicho",
    "wof:placetype":"locality"
},
  "geometry": {"coordinates":[136.20238000000001,36.01275],"type":"Point"}
}