{
  "type": "Feature",
  "properties": {
    "gn:admin1_code":"8.0",
    "gn:admin2_code":"2112921.0",
    "gn:asciiname":"Iinomachi",
    "gn:country_code":"JP",
    "gn:dem":194,
    "gn:feature_class":"P",
    "gn:feature_code":"PPL",
    "gn:name":"Iinomachi",
    "gn:population":0,
    "gn:timezone":"Asia/Tokyo",
    "iso:country":"JP",
    "name:hrv_x_preferred":[
        "Iino"
    ],
    "name:jpn_x_preferred":[
        "\u98ef\u91ce\u753a"
    ],
    "name:und_x_variant":[
        "Iino"
    ],
    "name:zho_x_preferred":[
        "\u98ef\u91ce\u753a"
    ],
    "wof:name":"Iinomachi",
    "wof:placetype":"locality"
},
  "geometry": {"coordinates":[140.53728999999998,37.65284000000001],"type":"Point"}
}