{
  "type": "Feature",
  "properties": {
    "gn:admin1_code":"33.0",
    "gn:admin2_code":"1850832.0",
    "gn:asciiname":"Niwaki",
    "gn:country_code":"JP",
    "gn:dem":76,
    "gn:feature_class":"P",
    "gn:feature_code":"PPLL",
    "gn:name":"Niwaki",
    "gn:population":0,
    "gn:timezone":"Asia/Tokyo",
    "iso:country":"JP",
    "name:bre_x_preferred":[
        "Niwaki"
    ],
    "name:fra_x_preferred":[
        "Niwaki"
    ],
    "name:jpn_x_preferred":[
        "\u5ead\u6728"
    ],
    "name:rus_x_preferred":[
        "\u041d\u0438\u0432\u0430\u043a\u0438"
    ],
    "name:zho_x_preferred":[
        "\u5ead\u5712\u6a39\u6728"
    ],
    "wof:name":"Niwaki",
    "wof:placetype":"locality"
},
  "geometry": {"coordinates":[129.96661,33.13327],"type":"Point"}
}