{
  "type": "Feature",
  "properties": {
    "gn:admin1_code":"3.0",
    "gn:admin2_code":"2130225.0",
    "gn:asciiname":"Midoricho",
    "gn:country_code":"JP",
    "gn:dem":11,
    "gn:feature_class":"P",
    "gn:feature_code":"PPL",
    "gn:name":"Midorich\u014d",
    "gn:population":0,
    "gn:timezone":"Asia/Tokyo",
    "iso:country":"JP",
    "name:jpn_x_preferred":[
        "\u307f\u3069\u308a\u753a"
    ],
    "name:jpn_x_variant":[
        "\u307f\u3069\u308a\u3061\u3087\u3046",
        "\u30df\u30c9\u30ea\u30c1\u30e7\u30a6"
    ],
    "name:und_x_variant":[
        "Midorich\u014d"
    ],
    "wof:name":"Midoricho",
    "wof:placetype":"locality"
},
  "geometry": {"coordinates":[140.45748999999998,40.78407],"type":"Point"}
}