{
  "type": "Feature",
  "properties": {
    "gn:admin1_code":"37.0",
    "gn:admin2_code":"1864104.0",
    "gn:asciiname":"Osaki",
    "gn:country_code":"JP",
    "gn:dem":72,
    "gn:feature_class":"P",
    "gn:feature_code":"PPLL",
    "gn:name":"Osaki",
    "gn:population":0,
    "gn:timezone":"Asia/Tokyo",
    "iso:country":"JP",
    "name:jpn_x_preferred":[
        "\u5c3e\u5d0e"
    ],
    "name:jpn_x_variant":[
        "\u30aa\u30b5\u30ad"
    ],
    "wof:name":"Osaki",
    "wof:placetype":"locality"
},
  "geometry": {"coordinates":[138.55077,35.20225],"type":"Point"}
}