{
  "type": "Feature",
  "properties": {
    "iso:country":"JP",
    "label:eng_x_preferred_longname":[
        "Taga Town"
    ],
    "label:eng_x_preferred_placetype":[
        "town"
    ],
    "name:eng_x_preferred":[
        "Taga"
    ],
    "name:eng_x_variant":[
        "Taga Town"
    ],
    "name:jpn_x_preferred":[
        "\u591a\u8cc0\u753a"
    ],
    "qs:name":"\u591a\u8cc0\u753a",
    "qs:name_adm0":"\u65e5\u672c",
    "qs:name_adm1":"\u6ecb\u8cc0\u770c",
    "qs:photos":192,
    "qs:photos_1k":39,
    "qs:photos_9k":1,
    "qs:photos_9r":4,
    "qs:photos_all":192,
    "qs:photos_sr":4,
    "qs:placetype":"Town",
    "qs:pop_sr":"0",
    "wof:name":"Taga",
    "wof:placetype":"locality"
},
  "geometry": {"coordinates":[136.287803,35.225279],"type":"Point"}
}