{
  "type": "Feature",
  "properties": {
    "gn:country":"JP",
    "iso:country":"JP",
    "qs:name":"\u6d25\u4e45\u898b\u5e02",
    "qs:name_adm0":"\u65e5\u672c",
    "qs:name_adm1":"\u5927\u5206\u770c",
    "qs:photos":42,
    "qs:photos_1k":9,
    "qs:photos_9k":1,
    "qs:photos_9r":2,
    "qs:photos_all":42,
    "qs:photos_sr":2,
    "qs:placetype":"Town",
    "qs:pop_sr":"0",
    "wof:name":"\u6d25\u4e45\u898b\u5e02",
    "wof:placetype":"locality"
},
  "geometry": {"coordinates":[131.87820500000001,33.0906105],"type":"Point"}
}