{
  "type": "Feature",
  "properties": {
    "gn:admin1_code":"33.0",
    "gn:admin2_code":"7391358.0",
    "gn:admin3_code":"41424.0",
    "gn:asciiname":"Hirayamamachi",
    "gn:country_code":"JP",
    "gn:dem":54,
    "gn:feature_class":"P",
    "gn:feature_code":"PPLL",
    "gn:name":"Hirayamamachi",
    "gn:population":0,
    "gn:timezone":"Asia/Tokyo",
    "iso:country":"JP",
    "name:jpn_x_preferred":[
        "\u5e73\u5c71\u753a"
    ],
    "wof:name":"Hirayamamachi",
    "wof:placetype":"locality"
},
  "geometry": {"coordinates":[130.13977,33.23445],"type":"Point"}
}