{
  "type": "Feature",
  "properties": {
    "gn:admin1_code":"26",
    "gn:admin2_code":"1853055.0",
    "gn:asciiname":"Iwamurada",
    "gn:country_code":"JP",
    "gn:dem":708,
    "gn:feature_class":"P",
    "gn:feature_code":"PPL",
    "gn:name":"Iwamurada",
    "gn:population":0,
    "gn:timezone":"Asia/Tokyo",
    "iso:country":"JP",
    "name:jpn_x_preferred":[
        "\u5ca9\u6751\u7530"
    ],
    "name:und_x_variant":[
        "Iwamurata",
        "Iwamurada"
    ],
    "wof:name":"Iwamurada",
    "wof:placetype":"locality"
},
  "geometry": {"coordinates":[138.48147,36.27361],"type":"Point"}
}