{
  "type": "Feature",
  "properties": {
    "gn:admin1_code":"14.0",
    "gn:admin2_code":"2111741.0",
    "gn:asciiname":"Nukada-kitago",
    "gn:country_code":"JP",
    "gn:dem":33,
    "gn:feature_class":"P",
    "gn:feature_code":"PPL",
    "gn:name":"Nukada-kitag\u014d",
    "gn:population":0,
    "gn:timezone":"Asia/Tokyo",
    "iso:country":"JP",
    "name:und_x_variant":[
        "Nukada-higashig\u014d",
        "Nukada",
        "Nukada-kitag\u014d"
    ],
    "wof:name":"Nukada-kitago",
    "wof:placetype":"locality"
},
  "geometry": {"coordinates":[140.51118,36.49502],"type":"Point"}
}