{
  "type": "Feature",
  "properties": {
    "gn:admin1_code":"37.0",
    "gn:admin2_code":"1864089.0",
    "gn:asciiname":"Nishihinacho",
    "gn:country_code":"JP",
    "gn:dem":9,
    "gn:feature_class":"P",
    "gn:feature_code":"PPLL",
    "gn:name":"Nishihinach\u014d",
    "gn:population":0,
    "gn:timezone":"Asia/Tokyo",
    "iso:country":"JP",
    "name:jpn_x_preferred":[
        "\u897f\u6bd4\u5948\u753a"
    ],
    "name:und_x_variant":[
        "Nishihinach\u014d"
    ],
    "wof:name":"Nishihinacho",
    "wof:placetype":"locality"
},
  "geometry": {"coordinates":[138.71368000000001,35.16303],"type":"Point"}
}