{
  "type": "Feature",
  "properties": {
    "gn:admin1_code":"12.0",
    "gn:admin2_code":"2129370.0",
    "gn:asciiname":"Oriyomappu Gawa",
    "gn:country_code":"JP",
    "gn:dem":29,
    "gn:feature_class":"P",
    "gn:feature_code":"PPL",
    "gn:name":"Oriyomappu Gawa",
    "gn:population":0,
    "gn:timezone":"Asia/Tokyo",
    "iso:country":"JP",
    "name:jpn_x_preferred":[
        "\u30aa\u30ea\u30e8\u30de\u30c3\u30d7\u5ddd"
    ],
    "name:jpn_x_variant":[
        "\u304a\u308a\u3088\u307e\u3063\u3077\u304c\u308f",
        "\u30aa\u30ea\u30e8\u30de\u30c3\u30d7\u30ac\u30ef"
    ],
    "wof:name":"Oriyomappu Gawa",
    "wof:placetype":"locality"
},
  "geometry": {"coordinates":[144.22178,43.1461],"type":"Point"}
}