{
  "type": "Feature",
  "properties": {
    "iso:country":"JP",
    "label:eng_x_preferred_longname":[
        "Kitahiroshima City"
    ],
    "label:eng_x_preferred_placetype":[
        "city"
    ],
    "name:eng_x_preferred":[
        "Kitahiroshima"
    ],
    "name:eng_x_variant":[
        "Kitahiroshima City"
    ],
    "name:jpn_x_preferred":[
        "\u5317\u5e83\u5cf6\u5e02"
    ],
    "qs:name":"\u5317\u5e83\u5cf6\u5e02",
    "qs:name_adm0":"\u65e5\u672c",
    "qs:name_adm1":"\u5317\u6d77\u9053",
    "qs:photos":66,
    "qs:photos_1k":13,
    "qs:photos_9k":1,
    "qs:photos_9r":4,
    "qs:photos_all":286,
    "qs:photos_sr":2,
    "qs:placetype":"Town",
    "qs:pop_sr":"0",
    "wof:name":"Kitahiroshima",
    "wof:placetype":"locality"
},
  "geometry": {"coordinates":[141.530777,42.998194],"type":"Point"}
}