{
  "type": "Feature",
  "properties": {
    "gn:admin1_code":"47",
    "gn:admin2_code":"1848816.0",
    "gn:admin3_code":"47381.0",
    "gn:asciiname":"Shitaji",
    "gn:country_code":"JP",
    "gn:dem":13,
    "gn:feature_class":"P",
    "gn:feature_code":"PPL",
    "gn:name":"Shitaji",
    "gn:population":0,
    "gn:timezone":"Asia/Tokyo",
    "iso:country":"JP",
    "name:jpn_x_preferred":[
        "\u4e0b\u5730"
    ],
    "name:jpn_x_variant":[
        "\u3057\u3082\u3058"
    ],
    "name:und_x_variant":[
        "Shimoji",
        "Shimojishima",
        "Shitaji"
    ],
    "wof:name":"Shitaji",
    "wof:placetype":"locality"
},
  "geometry": {"coordinates":[123.9293,24.21809],"type":"Point"}
}