{
  "type": "Feature",
  "properties": {
    "gn:admin1_code":"2.0",
    "gn:admin2_code":"2112235.0",
    "gn:admin3_code":"5327.0",
    "gn:asciiname":"Kosawada",
    "gn:country_code":"JP",
    "gn:dem":57,
    "gn:feature_class":"P",
    "gn:feature_code":"PPL",
    "gn:name":"Kosawada",
    "gn:population":0,
    "gn:timezone":"Asia/Tokyo",
    "iso:country":"JP",
    "name:jpn_x_preferred":[
        "\u5c0f\u6ca2\u7530"
    ],
    "wof:name":"Kosawada",
    "wof:placetype":"locality"
},
  "geometry": {"coordinates":[140.29092,40.06449],"type":"Point"}
}