{
  "type": "Feature",
  "properties": {
    "gn:admin1_code":"3.0",
    "gn:admin2_code":"2128302.0",
    "gn:admin3_code":"2445.0",
    "gn:asciiname":"Shojuji",
    "gn:country_code":"JP",
    "gn:dem":87,
    "gn:feature_class":"P",
    "gn:feature_code":"PPL",
    "gn:name":"Sh\u014djuji",
    "gn:population":0,
    "gn:timezone":"Asia/Tokyo",
    "iso:country":"JP",
    "name:jpn_x_preferred":[
        "\u6b63\u5bff\u5bfa"
    ],
    "name:jpn_x_variant":[
        "\u3057\u3087\u3046\u3058\u3085\u3058",
        "\u30b7\u30e7\u30a6\u30b8\u30e5\u30b8"
    ],
    "name:und_x_variant":[
        "Sh\u014djuji"
    ],
    "wof:name":"Shojuji",
    "wof:placetype":"locality"
},
  "geometry": {"coordinates":[141.26879,40.41617],"type":"Point"}
}