{
  "type": "Feature",
  "properties": {
    "gn:admin1_code":"4.0",
    "gn:admin2_code":"1850520.0",
    "gn:asciiname":"Masakioka",
    "gn:country_code":"JP",
    "gn:dem":28,
    "gn:feature_class":"P",
    "gn:feature_code":"PPLL",
    "gn:name":"Masakioka",
    "gn:population":0,
    "gn:timezone":"Asia/Tokyo",
    "iso:country":"JP",
    "name:jpn_x_preferred":[
        "\u6b63\u6728\u5ca1"
    ],
    "name:jpn_x_variant":[
        "\u307e\u3055\u304d\u304a\u304b",
        "\u30de\u30b5\u30ad\u30aa\u30ab"
    ],
    "wof:name":"Masakioka",
    "wof:placetype":"locality"
},
  "geometry": {"coordinates":[139.87809999999999,35.02833],"type":"Point"}
}