{
  "type": "Feature",
  "properties": {
    "gn:country":"JP",
    "gn:fcode":"ADM3",
    "gn:population":0,
    "iso:country":"JP",
    "name:eng_x_preferred":[
        "Miho"
    ],
    "name:eng_x_variant":[
        "Miho-mura"
    ],
    "name:jpn_x_preferred":[
        "\u7f8e\u6d66\u6751"
    ],
    "name:jpn_x_variant":[
        "\u307f\u307b\u3080\u3089"
    ],
    "qs:name":"Miho-mura",
    "qs:photos_9r":0,
    "qs:photos_sr":0,
    "qs:pop_sr":"0",
    "wof:name":"Miho",
    "wof:placetype":"localadmin",
    "wof:population":0
},
  "geometry": {"coordinates":[140.34512000000001,36.01886],"type":"Point"}
}