{
  "type": "Feature",
  "properties": {
    "gn:admin1_code":"4.0",
    "gn:admin2_code":"2112386.0",
    "gn:asciiname":"Sonbo",
    "gn:country_code":"JP",
    "gn:dem":96,
    "gn:feature_class":"P",
    "gn:feature_code":"PPLL",
    "gn:name":"Sonb\u014d",
    "gn:population":0,
    "gn:timezone":"Asia/Tokyo",
    "iso:country":"JP",
    "name:jpn_x_preferred":[
        "\u5c0a\u623f"
    ],
    "name:jpn_x_variant":[
        "\u305d\u3093\u307c\u3046",
        "\u30bd\u30f3\u30dc\u30a6"
    ],
    "name:und_x_variant":[
        "Sonb\u014d"
    ],
    "wof:name":"Sonbo",
    "wof:placetype":"locality"
},
  "geometry": {"coordinates":[140.05744999999999,35.08959],"type":"Point"}
}