{
  "type": "Feature",
  "properties": {
    "gn:admin1_code":"22",
    "gn:admin2_code":"1856196.0",
    "gn:asciiname":"Kotari",
    "gn:country_code":"JP",
    "gn:dem":17,
    "gn:feature_class":"P",
    "gn:feature_code":"PPL",
    "gn:name":"K\u014dtari",
    "gn:population":0,
    "gn:timezone":"Asia/Tokyo",
    "iso:country":"JP",
    "name:bos_x_preferred":[
        "Kotari"
    ],
    "name:hrv_x_preferred":[
        "Kotari"
    ],
    "name:hun_x_preferred":[
        "Kotari"
    ],
    "name:jpn_x_preferred":[
        "\u795e\u8db3"
    ],
    "name:nld_x_preferred":[
        "Kotari"
    ],
    "name:slv_x_preferred":[
        "Kotari"
    ],
    "name:ukr_x_preferred":[
        "\u041a\u043e\u0442\u0430\u0440\u0438"
    ],
    "name:und_x_variant":[
        "K\u014dtari"
    ],
    "wof:name":"Kotari",
    "wof:placetype":"locality"
},
  "geometry": {"coordinates":[135.70546999999999,34.92097],"type":"Point"}
}