{
  "type": "Feature",
  "properties": {
    "gn:admin1_code":"21.0",
    "gn:admin2_code":"1865360.0",
    "gn:admin3_code":"43531.0",
    "gn:asciiname":"Kotsu-fukae",
    "gn:country_code":"JP",
    "gn:dem":24,
    "gn:feature_class":"P",
    "gn:feature_code":"PPL",
    "gn:name":"K\u014dtsu-fukae",
    "gn:population":0,
    "gn:timezone":"Asia/Tokyo",
    "iso:country":"JP",
    "name:jpn_x_preferred":[
        "\u4e0a\u6d25\u6df1\u6c5f"
    ],
    "name:jpn_x_variant":[
        "\u3053\u3046\u3064\u3075\u304b\u3048",
        "\u30b3\u30a6\u30c4\u30d5\u30ab\u30a8"
    ],
    "name:und_x_variant":[
        "K\u014dtsu-fukae"
    ],
    "wof:name":"Kotsu-fukae",
    "wof:placetype":"locality"
},
  "geometry": {"coordinates":[130.07456000000002,32.51448],"type":"Point"}
}