{
  "type": "Feature",
  "properties": {
    "gn:admin1_code":"12.0",
    "gn:admin2_code":"2128971.0",
    "gn:asciiname":"Choboshi",
    "gn:country_code":"JP",
    "gn:dem":4,
    "gn:feature_class":"P",
    "gn:feature_code":"PPL",
    "gn:name":"Ch\u014dboshi",
    "gn:population":0,
    "gn:timezone":"Asia/Tokyo",
    "iso:country":"JP",
    "name:jpn_x_preferred":[
        "\u9577\u7bc0"
    ],
    "name:jpn_x_variant":[
        "\u3061\u3087\u3046\u307c\u3057",
        "\u30c1\u30e7\u30a6\u30dc\u30b7"
    ],
    "name:und_x_variant":[
        "Nagafushi",
        "Ch\u014dbushi",
        "Nagabushi",
        "Ch\u014dboshi"
    ],
    "wof:name":"Choboshi",
    "wof:placetype":"locality"
},
  "geometry": {"coordinates":[145.55418999999995,43.252],"type":"Point"}
}