{
  "type": "Feature",
  "properties": {
    "gn:admin1_code":"21.0",
    "gn:admin2_code":"1865360.0",
    "gn:admin3_code":"43531.0",
    "gn:asciiname":"Yananosako",
    "gn:country_code":"JP",
    "gn:dem":26,
    "gn:feature_class":"P",
    "gn:feature_code":"PPLL",
    "gn:name":"Yananosako",
    "gn:population":0,
    "gn:timezone":"Asia/Tokyo",
    "iso:country":"JP",
    "name:jpn_x_preferred":[
        "\u67f3\u306e\u8feb"
    ],
    "name:jpn_x_variant":[
        "\u3084\u306a\u306e\u3055\u3053",
        "\u30e4\u30ca\u30ce\u30b5\u30b3"
    ],
    "wof:name":"Yananosako",
    "wof:placetype":"locality"
},
  "geometry": {"coordinates":[130.03779,32.46399],"type":"Point"}
}