{
  "type": "Feature",
  "properties": {
    "gn:admin1_code":"19.0",
    "gn:admin2_code":"1863429.0",
    "gn:asciiname":"Shibusawakami",
    "gn:country_code":"JP",
    "gn:dem":189,
    "gn:feature_class":"P",
    "gn:feature_code":"PPL",
    "gn:name":"Shibusawakami",
    "gn:population":0,
    "gn:timezone":"Asia/Tokyo",
    "iso:country":"JP",
    "name:jpn_x_preferred":[
        "\u6e0b\u6ca2\u4e0a"
    ],
    "wof:name":"Shibusawakami",
    "wof:placetype":"locality"
},
  "geometry": {"coordinates":[139.1797,35.36861],"type":"Point"}
}