{
  "type": "Feature",
  "properties": {
    "gn:admin1_code":"19.0",
    "gn:admin2_code":"7468160.0",
    "gn:admin3_code":"14402.0",
    "gn:asciiname":"Ryubai",
    "gn:country_code":"JP",
    "gn:dem":112,
    "gn:feature_class":"P",
    "gn:feature_code":"PPLL",
    "gn:name":"Ry\u016bbai",
    "gn:population":0,
    "gn:timezone":"Asia/Tokyo",
    "iso:country":"JP",
    "name:jpn_x_preferred":[
        "\u67f3\u6885"
    ],
    "name:und_x_variant":[
        "Ry\u016bbai"
    ],
    "wof:name":"Ryubai",
    "wof:placetype":"locality"
},
  "geometry": {"coordinates":[139.28691000000001,35.47528],"type":"Point"}
}