{
  "type": "Feature",
  "properties": {
    "gn:admin1_code":"4.0",
    "gn:admin2_code":"2110982.0",
    "gn:asciiname":"Nishihagiwara",
    "gn:country_code":"JP",
    "gn:dem":52,
    "gn:feature_class":"P",
    "gn:feature_code":"PPLL",
    "gn:name":"Nishihagiwara",
    "gn:population":0,
    "gn:timezone":"Asia/Tokyo",
    "iso:country":"JP",
    "name:jpn_x_preferred":[
        "\u897f\u8429\u539f"
    ],
    "name:jpn_x_variant":[
        "\u306b\u3057\u306f\u304e\u308f\u3089",
        "\u30cb\u30b7\u30cf\u30ae\u30ef\u30e9"
    ],
    "wof:name":"Nishihagiwara",
    "wof:placetype":"locality"
},
  "geometry": {"coordinates":[140.04543000000001,35.42142],"type":"Point"}
}