{
  "type": "Feature",
  "properties": {
    "gn:admin1_code":"18",
    "gn:admin2_code":"1853737.0",
    "gn:admin3_code":"46524.0",
    "gn:asciiname":"Ikegachi",
    "gn:country_code":"JP",
    "gn:dem":72,
    "gn:feature_class":"P",
    "gn:feature_code":"PPL",
    "gn:name":"Ikegachi",
    "gn:population":0,
    "gn:timezone":"Asia/Tokyo",
    "iso:country":"JP",
    "name:jpn_x_preferred":[
        "\u751f\u52dd"
    ],
    "name:und_x_variant":[
        "Ikekachi",
        "Ikegachi"
    ],
    "wof:name":"Ikegachi",
    "wof:placetype":"locality"
},
  "geometry": {"coordinates":[129.24545000000001,28.28535],"type":"Point"}
}