{
  "type": "Feature",
  "properties": {
    "gn:admin1_code":"24.0",
    "gn:admin2_code":"2112261.0",
    "gn:asciiname":"Arayashiki",
    "gn:country_code":"JP",
    "gn:dem":42,
    "gn:feature_class":"P",
    "gn:feature_code":"PPL",
    "gn:name":"Arayashiki",
    "gn:population":0,
    "gn:timezone":"Asia/Tokyo",
    "iso:country":"JP",
    "name:jpn_x_preferred":[
        "\u8352\u5c4b\u6577"
    ],
    "name:jpn_x_variant":[
        "\u3042\u3089\u3084\u3057\u304d",
        "\u30a2\u30e9\u30e4\u30b7\u30ad"
    ],
    "wof:name":"Arayashiki",
    "wof:placetype":"locality"
},
  "geometry": {"coordinates":[141.65153000000001,38.88464000000001],"type":"Point"}
}