{
  "type": "Feature",
  "properties": {
    "gn:admin1_code":"37.0",
    "gn:admin2_code":"1864089.0",
    "gn:asciiname":"Osu",
    "gn:country_code":"JP",
    "gn:dem":5,
    "gn:feature_class":"P",
    "gn:feature_code":"PPLL",
    "gn:name":"Osu",
    "gn:population":0,
    "gn:timezone":"Asia/Tokyo",
    "iso:country":"JP",
    "name:jpn_x_preferred":[
        "\u5c0f\u9808"
    ],
    "name:zho_x_preferred":[
        "Osu"
    ],
    "wof:name":"Osu",
    "wof:placetype":"locality"
},
  "geometry": {"coordinates":[138.68053,35.13623],"type":"Point"}
}