{
  "type": "Feature",
  "properties": {
    "gn:country":"JP",
    "gn:fcode":"ADM3",
    "gn:population":0,
    "iso:country":"JP",
    "name:ara_x_preferred":[
        "\u0633\u0648\u062a\u0648\u063a\u0627\u0647\u0627\u0645\u0627"
    ],
    "name:ast_x_preferred":[
        "Sotogahama"
    ],
    "name:bul_x_preferred":[
        "\u0421\u043e\u0442\u043e\u0433\u0430\u0445\u0430\u043c\u0430"
    ],
    "name:ceb_x_preferred":[
        "Sotogahama-machi"
    ],
    "name:deu_x_preferred":[
        "Sotogahama"
    ],
    "name:eng_x_preferred":[
        "Sotogahama"
    ],
    "name:fas_x_preferred":[
        "\u0633\u0648\u062a\u0648\u06af\u0627\u0647\u0627\u0645\u0627"
    ],
    "name:fra_x_preferred":[
        "Sotogahama"
    ],
    "name:ita_x_preferred":[
        "Sotogahama"
    ],
    "name:jpn_x_preferred":[
        "\u5916\u30f6\u6d5c\u753a"
    ],
    "name:jpn_x_variant":[
        "\u305d\u3068\u304c\u306f\u307e\u307e\u3061"
    ],
    "name:kat_x_preferred":[
        "\u10e1\u10dd\u10e2\u10dd\u10d2\u10d0\u10f0\u10d0\u10db\u10d0"
    ],
    "name:kor_x_preferred":[
        "\uc18c\ud1a0\uac00\ud558\ub9c8\uc815"
    ],
    "name:msa_x_preferred":[
        "Sotogahama"
    ],
    "name:mya_x_preferred":[
        "\u1006\u102d\u102f\u1010\u102d\u102f\u1002\u102b\u101f\u102c\u1019\u1019\u103c\u102d\u102f\u1037\u104a \u1021\u1021\u102d\u102f\u1019\u102d\u102f\u101b\u102d"
    ],
    "name:nld_x_preferred":[
        "Sotogahama"
    ],
    "name:pol_x_preferred":[
        "Sotogahama"
    ],
    "name:por_x_preferred":[
        "Sotogahama"
    ],
    "name:rus_x_preferred":[
        "\u0421\u043e\u0442\u043e\u0433\u0430\u0445\u0430\u043c\u0430"
    ],
    "name:spa_x_preferred":[
        "Sotogahama"
    ],
    "name:tgl_x_preferred":[
        "Sotogahama"
    ],
    "name:ukr_x_preferred":[
        "\u0421\u043e\u0442\u043e\u0491\u0430\u0445\u0430\u043c\u0430"
    ],
    "name:urd_x_preferred":[
        "\u06af\u0648\u062a\u0648\u06af\u0627\u06c1\u0627\u0645\u0627"
    ],
    "name:zho_x_preferred":[
        "\u5916\u6ff1\u753a"
    ],
    "qs:name":"Sotogahama-machi",
    "qs:photos_9r":0,
    "qs:photos_sr":0,
    "qs:pop_sr":"0",
    "wd:wordcount":348,
    "wof:name":"Sotogahama-machi",
    "wof:placetype":"localadmin",
    "wof:population":0
},
  "geometry": {"coordinates":[140.52443,41.12076],"type":"Point"}
}