{
  "type": "Feature",
  "properties": {
    "gn:country":"JP",
    "gn:fcode":"ADM3",
    "gn:pop":0,
    "iso:country":"JP",
    "name:jpn_x_preferred":[
        "\u5916\u30f6\u6d5c\u753a"
    ],
    "name:jpn_x_variant":[
        "\u305d\u3068\u304c\u306f\u307e\u307e\u3061"
    ],
    "qs:name":"Sotogahama-machi",
    "qs:photos_9r":0,
    "qs:photos_sr":0,
    "qs:pop_sr":"0",
    "wd:wordcount":348,
    "wof:name":"Sotogahama-machi",
    "wof:placetype":"localadmin",
    "wof:population":0
},
  "geometry": {"coordinates":[140.52443,41.12076],"type":"Point"}
}