{
  "type": "Feature",
  "properties": {
    "gn:country":"JP",
    "gn:fcode":"ADM3",
    "gn:population":0,
    "iso:country":"JP",
    "name:eng_x_preferred":[
        "Okinoshima"
    ],
    "name:eng_x_variant":[
        "Okinoshima-ch\u014d"
    ],
    "name:jpn_x_preferred":[
        "\u96a0\u5c90\u306e\u5cf6\u753a"
    ],
    "name:jpn_x_variant":[
        "\u304a\u304d\u306e\u3057\u307e\u3061\u3087\u3046"
    ],
    "name:und_x_variant":[
        "Okinoshima Ch\u014d"
    ],
    "qs:name":"Okinoshima-ch\u014d",
    "qs:photos_9r":0,
    "qs:photos_sr":0,
    "qs:pop_sr":"0",
    "wof:name":"Okinoshima",
    "wof:placetype":"localadmin",
    "wof:population":0
},
  "geometry": {"coordinates":[133.27835999999999,36.25285],"type":"Point"}
}