{
  "type": "Feature",
  "properties": {
    "gn:admin1_code":"19.0",
    "gn:admin2_code":"1848595.0",
    "gn:asciiname":"Daikan",
    "gn:country_code":"JP",
    "gn:dem":50,
    "gn:feature_class":"P",
    "gn:feature_code":"PPL",
    "gn:name":"Daikan",
    "gn:population":0,
    "gn:timezone":"Asia/Tokyo",
    "iso:country":"JP",
    "name:jpn_x_preferred":[
        "\u4ee3\u5b98"
    ],
    "wof:name":"Daikan",
    "wof:placetype":"locality"
},
  "geometry": {"coordinates":[139.45605,35.44186],"type":"Point"}
}