{
  "type": "Feature",
  "properties": {
    "gn:admin1_code":"16.0",
    "gn:admin2_code":"2112223.0",
    "gn:asciiname":"Kozaike",
    "gn:country_code":"JP",
    "gn:dem":88,
    "gn:feature_class":"P",
    "gn:feature_code":"PPL",
    "gn:name":"Kozaike",
    "gn:population":0,
    "gn:timezone":"Asia/Tokyo",
    "iso:country":"JP",
    "name:jpn_x_preferred":[
        "\u5c0f\u5728\u5bb6"
    ],
    "name:jpn_x_variant":[
        "\u3053\u3056\u3044\u3051",
        "\u30b3\u30b6\u30a4\u30b1"
    ],
    "wof:name":"Kozaike",
    "wof:placetype":"locality"
},
  "geometry": {"coordinates":[141.12683999999999,39.34687],"type":"Point"}
}