{
  "type": "Feature",
  "properties": {
    "gn:admin1_code":"23.0",
    "gn:admin2_code":"1848873.0",
    "gn:admin3_code":"24471.0",
    "gn:asciiname":"Misegawa",
    "gn:country_code":"JP",
    "gn:dem":84,
    "gn:feature_class":"P",
    "gn:feature_code":"PPL",
    "gn:name":"Misegawa",
    "gn:population":0,
    "gn:timezone":"Asia/Tokyo",
    "iso:country":"JP",
    "name:jpn_x_preferred":[
        "\u4e09\u702c\u5ddd"
    ],
    "wof:name":"Misegawa",
    "wof:placetype":"locality"
},
  "geometry": {"coordinates":[136.43029999999999,34.39237],"type":"Point"}
}