{
  "type": "Feature",
  "properties": {
    "gn:admin1_code":"28.0",
    "gn:admin2_code":"1855604.0",
    "gn:asciiname":"Higashinarukawacho",
    "gn:country_code":"JP",
    "gn:dem":221,
    "gn:feature_class":"P",
    "gn:feature_code":"PPL",
    "gn:name":"Higashinarukawach\u014d",
    "gn:population":0,
    "gn:timezone":"Asia/Tokyo",
    "iso:country":"JP",
    "name:jpn_x_preferred":[
        "\u6771\u9cf4\u5ddd\u753a"
    ],
    "name:und_x_variant":[
        "Higashinarukawach\u014d"
    ],
    "wof:name":"Higashinarukawacho",
    "wof:placetype":"locality"
},
  "geometry": {"coordinates":[135.88124999999999,34.71205],"type":"Point"}
}