{
  "type": "Feature",
  "properties": {
    "gn:admin1_code":"2.0",
    "gn:admin2_code":"2110459.0",
    "gn:asciiname":"Shimoshinden",
    "gn:country_code":"JP",
    "gn:dem":422,
    "gn:feature_class":"P",
    "gn:feature_code":"PPL",
    "gn:name":"Shimoshinden",
    "gn:population":0,
    "gn:timezone":"Asia/Tokyo",
    "iso:country":"JP",
    "name:jpn_x_preferred":[
        "\u4e0b\u65b0\u7530"
    ],
    "wof:name":"Shimoshinden",
    "wof:placetype":"locality"
},
  "geometry": {"coordinates":[140.59581,39.01968],"type":"Point"}
}