{
  "type": "Feature",
  "properties": {
    "gn:admin1_code":"7.0",
    "gn:admin2_code":"1859306.0",
    "gn:admin3_code":"40107.0",
    "gn:asciiname":"Fujimi",
    "gn:country_code":"JP",
    "gn:dem":10,
    "gn:feature_class":"P",
    "gn:feature_code":"PPL",
    "gn:name":"Fujimi",
    "gn:population":0,
    "gn:timezone":"Asia/Tokyo",
    "iso:country":"JP",
    "name:jpn_x_preferred":[
        "\u5bcc\u58eb\u898b"
    ],
    "name:kor_x_preferred":[
        "\ud6c4\uc9c0\ubbf8"
    ],
    "name:rus_x_preferred":[
        "\u0424\u0443\u0434\u0437\u0438\u043c\u0438"
    ],
    "name:spa_x_preferred":[
        "Fujimi"
    ],
    "name:ukr_x_preferred":[
        "\u0424\u0443\u0434\u0437\u0456\u043c\u0456"
    ],
    "wof:name":"Fujimi",
    "wof:placetype":"locality"
},
  "geometry": {"coordinates":[130.88018,33.85720999999999],"type":"Point"}
}