{
  "type": "Feature",
  "properties": {
    "gn:admin1_code":"37.0",
    "gn:admin2_code":"1864104.0",
    "gn:asciiname":"Magisawa",
    "gn:country_code":"JP",
    "gn:dem":187,
    "gn:feature_class":"P",
    "gn:feature_code":"PPLL",
    "gn:name":"Magisawa",
    "gn:population":0,
    "gn:timezone":"Asia/Tokyo",
    "iso:country":"JP",
    "name:jpn_x_preferred":[
        "\u99ac\u6728\u6ca2"
    ],
    "wof:name":"Magisawa",
    "wof:placetype":"locality"
},
  "geometry": {"coordinates":[138.55571,35.24594000000001],"type":"Point"}
}