{
  "type": "Feature",
  "properties": {
    "gn:admin1_code":"7.0",
    "gn:admin2_code":"1859306.0",
    "gn:admin3_code":"40107.0",
    "gn:asciiname":"Tsudashinmachi",
    "gn:country_code":"JP",
    "gn:dem":4,
    "gn:feature_class":"P",
    "gn:feature_code":"PPL",
    "gn:name":"Tsudashinmachi",
    "gn:population":0,
    "gn:timezone":"Asia/Tokyo",
    "iso:country":"JP",
    "name:jpn_x_preferred":[
        "\u6d25\u7530\u65b0\u753a"
    ],
    "wof:name":"Tsudashinmachi",
    "wof:placetype":"locality"
},
  "geometry": {"coordinates":[130.92478,33.8336],"type":"Point"}
}