{
  "type": "Feature",
  "properties": {
    "gn:admin1_code":"12.0",
    "gn:admin2_code":"7428097.0",
    "gn:admin3_code":"1643.0",
    "gn:asciiname":"Midorimachi",
    "gn:country_code":"JP",
    "gn:dem":35,
    "gn:feature_class":"P",
    "gn:feature_code":"PPL",
    "gn:name":"Midorimachi",
    "gn:population":0,
    "gn:timezone":"Asia/Tokyo",
    "iso:country":"JP",
    "name:jpn_x_preferred":[
        "\u7dd1\u753a"
    ],
    "name:jpn_x_variant":[
        "\u307f\u3069\u308a\u307e\u3061",
        "\u30df\u30c9\u30ea\u30de\u30c1"
    ],
    "wof:name":"Midorimachi",
    "wof:placetype":"locality"
},
  "geometry": {"coordinates":[143.36664999999999,42.90434000000001],"type":"Point"}
}