{
  "type": "Feature",
  "properties": {
    "gn:admin1_code":"24.0",
    "gn:admin2_code":"2112092.0",
    "gn:asciiname":"Kurikoma-iwagasaki",
    "gn:country_code":"JP",
    "gn:dem":25,
    "gn:feature_class":"P",
    "gn:feature_code":"PPL",
    "gn:name":"Kurikoma-iwagasaki",
    "gn:population":0,
    "gn:timezone":"Asia/Tokyo",
    "iso:country":"JP",
    "name:jpn_x_preferred":[
        "\u6817\u99d2\u5ca9\u30f6\u5d0e"
    ],
    "name:und_x_variant":[
        "Iwagasaki"
    ],
    "wof:name":"Kurikoma-iwagasaki",
    "wof:placetype":"locality"
},
  "geometry": {"coordinates":[140.98861000000005,38.82556],"type":"Point"}
}