{
  "type": "Feature",
  "properties": {
    "iso:country":"JP",
    "name:jpn_x_preferred":[
        "\uff08\u4e01\u76ee\u306a\u3057\uff09"
    ],
    "qs:gn_local":0,
    "qs:local_max":179,
    "qs:local_sum":475,
    "qs:localhoods":11,
    "qs:name":"\uff08\u4e01\u76ee\u306a\u3057\uff09",
    "qs:name_adm0":"\u65e5\u672c",
    "qs:name_adm1":"\u9759\u5ca1\u770c",
    "qs:name_lau":"\u4eca\u4e95",
    "qs:name_local":"\u5bcc\u58eb\u5e02",
    "qs:photo_max":15,
    "qs:photo_sum":89,
    "qs:placetype":"Suburb",
    "qs:quad_count":25,
    "qs:woe_adm0":23424856,
    "qs:woe_adm1":2345886,
    "qs:woe_adm2":0,
    "qs:woe_lau":28437640,
    "qs:woe_local":1117079,
    "qs:woe_ver":"7.10.0",
    "wof:lang":[
        "jpn"
    ],
    "wof:name":"\uff08\u4e01\u76ee\u306a\u3057\uff09",
    "wof:placetype":"neighbourhood"
},
  "geometry": {"coordinates":[138.72051999999999,35.15345],"type":"Point"}
}