{
  "type": "Feature",
  "properties": {
    "gn:admin1_code":"06",
    "gn:admin2_code":"7465772.0",
    "gn:admin3_code":"18442.0",
    "gn:asciiname":"Sugahama",
    "gn:cc2":"JP",
    "gn:country_code":"JP",
    "gn:dem":0,
    "gn:feature_class":"P",
    "gn:feature_code":"PPL",
    "gn:name":"Sugahama",
    "gn:population":0,
    "gn:timezone":"Asia/Tokyo",
    "iso:country":"JP",
    "name:und_x_variant":[
        "Sougahama"
    ],
    "wof:name":"Sugahama",
    "wof:placetype":"locality"
},
  "geometry": {"coordinates":[135.97298000000001,35.65604000000001],"type":"Point"}
}