{
  "type": "Feature",
  "properties": {
    "gn:admin1_code":"12.0",
    "gn:admin2_code":"7428100.0",
    "gn:admin3_code":"1691.0",
    "gn:asciiname":"Honbetsukai",
    "gn:country_code":"JP",
    "gn:dem":11,
    "gn:feature_class":"P",
    "gn:feature_code":"PPL",
    "gn:name":"Honbetsukai",
    "gn:population":0,
    "gn:timezone":"Asia/Tokyo",
    "iso:country":"JP",
    "name:jpn_x_preferred":[
        "\u672c\u5225\u6d77"
    ],
    "name:jpn_x_variant":[
        "\u307b\u3093\u3079\u3064\u304b\u3044",
        "\u30db\u30f3\u30d9\u30c4\u30ab\u30a4"
    ],
    "wof:name":"Honbetsukai",
    "wof:placetype":"locality"
},
  "geometry": {"coordinates":[145.21763000000001,43.37834],"type":"Point"}
}