{
  "type": "Feature",
  "properties": {
    "gn:admin1_code":"3.0",
    "gn:admin2_code":"7439944.0",
    "gn:asciiname":"Kizukuri-fukihara",
    "gn:country_code":"JP",
    "gn:dem":4,
    "gn:feature_class":"P",
    "gn:feature_code":"PPL",
    "gn:name":"Kizukuri-fukihara",
    "gn:population":0,
    "gn:timezone":"Asia/Tokyo",
    "iso:country":"JP",
    "name:jpn_x_preferred":[
        "\u6728\u9020\u5439\u539f"
    ],
    "name:jpn_x_variant":[
        "\u304d\u3065\u304f\u308a\u3075\u304d\u306f\u3089",
        "\u30ad\u30c5\u30af\u30ea\u30d5\u30ad\u30cf\u30e9"
    ],
    "wof:name":"Kizukuri-fukihara",
    "wof:placetype":"locality"
},
  "geometry": {"coordinates":[140.30636000000001,40.82025],"type":"Point"}
}