{
  "type": "Feature",
  "properties": {
    "gn:admin1_code":"05",
    "gn:admin2_code":"1849041.0",
    "gn:asciiname":"Nakaura",
    "gn:country_code":"JP",
    "gn:dem":41,
    "gn:feature_class":"P",
    "gn:feature_code":"PPL",
    "gn:name":"Nakaura",
    "gn:population":0,
    "gn:timezone":"Asia/Tokyo",
    "iso:country":"JP",
    "wof:name":"Nakaura",
    "wof:placetype":"locality"
},
  "geometry": {"coordinates":[132.48570000000001,33.27578],"type":"Point"}
}