{
  "type": "Feature",
  "properties": {
    "gn:admin1_code":"12.0",
    "gn:admin2_code":"7428100.0",
    "gn:admin3_code":"1691.0",
    "gn:asciiname":"bekkai",
    "gn:country_code":"JP",
    "gn:dem":23,
    "gn:feature_class":"P",
    "gn:feature_code":"PPL",
    "gn:name":"bekkai",
    "gn:population":0,
    "gn:timezone":"Asia/Tokyo",
    "iso:country":"JP",
    "name:ceb_x_preferred":[
        "Betsukai-ch\u014d"
    ],
    "name:fas_x_preferred":[
        "\u0628\u062a\u0633\u0648\u06a9\u0627\u06cc"
    ],
    "name:fra_x_preferred":[
        "Betsukai"
    ],
    "name:ita_x_preferred":[
        "Betsukai"
    ],
    "name:jpn_x_preferred":[
        "\u5225\u6d77"
    ],
    "name:jpn_x_variant":[
        "\u5225\u6d77\u753a"
    ],
    "name:kor_x_preferred":[
        "\ubca0\uc4f0\uce74\uc774\uc815"
    ],
    "name:msa_x_preferred":[
        "Betsukai"
    ],
    "name:mya_x_preferred":[
        "\u1018\u1032\u1006\u103d\u1010\u103a\u1001\u102d\u102f\u1004\u103a\u104a \u101f\u1031\u102c\u1037\u1000\u102d\u102f\u1004\u103a\u1038\u1012\u102d\u102f\u1038"
    ],
    "name:rus_x_preferred":[
        "\u0411\u0435\u0446\u0443\u043a\u0430\u0439"
    ],
    "name:ukr_x_preferred":[
        "\u0411\u0435\u0446\u0443\u043a\u0430\u0439"
    ],
    "name:zho_x_preferred":[
        "\u5225\u6d77\u753a"
    ],
    "wof:name":"bekkai",
    "wof:placetype":"locality"
},
  "geometry": {"coordinates":[145.11738,43.39357],"type":"Point"}
}