{
  "type": "Feature",
  "properties": {
    "iso:country":"JP",
    "name:eng_x_preferred":[
        "Nakaminato 6 Chome"
    ],
    "name:eng_x_variant":[
        "Nakaminato 6 Choume",
        "Nakaminato 6 Chome"
    ],
    "name:jpn_x_preferred":[
        "\uff16\u4e01\u76ee"
    ],
    "name:jpn_x_variant":[
        "\u306a\u304b\u307f\u306a\u3068 \uff16\u3061\u3087\u3046\u3081",
        "\u4e2d\u6e2f \uff16\u4e01\u76ee",
        "\uff16\u3061\u3087\u3046\u3081"
    ],
    "name:unk_x_variant":[
        "\uff16\u4e01\u76ee"
    ],
    "qs:gn_local":0,
    "qs:local_max":21,
    "qs:local_sum":33,
    "qs:localhoods":3,
    "qs:name":"\uff16\u4e01\u76ee",
    "qs:name_adm0":"\u65e5\u672c",
    "qs:name_adm1":"\u9759\u5ca1\u770c",
    "qs:name_en":"Nakaminato 6 Chome",
    "qs:name_lau":"\u4e2d\u6e2f",
    "qs:name_local":"\u713c\u6d25\u5e02",
    "qs:photo_max":18,
    "qs:photo_sum":21,
    "qs:placetype":"Suburb",
    "qs:quad_count":4,
    "qs:woe_adm0":23424856,
    "qs:woe_adm1":2345886,
    "qs:woe_adm2":0,
    "qs:woe_lau":28437986,
    "qs:woe_local":1118508,
    "qs:woe_ver":"7.10.0",
    "wof:lang":[
        "jpn"
    ],
    "wof:name":"\uff16\u4e01\u76ee",
    "wof:placetype":"neighbourhood"
},
  "geometry": {"coordinates":[138.33134200000001,34.870159],"type":"Point"}
}