{
  "type": "Feature",
  "properties": {
    "gn:admin1_code":"4.0",
    "gn:admin2_code":"1857552.0",
    "gn:asciiname":"Nakawagura",
    "gn:country_code":"JP",
    "gn:dem":30,
    "gn:feature_class":"P",
    "gn:feature_code":"PPL",
    "gn:name":"Nakawagura",
    "gn:population":0,
    "gn:timezone":"Asia/Tokyo",
    "iso:country":"JP",
    "name:jpn_x_preferred":[
        "\u4e2d\u548c\u5009"
    ],
    "wof:name":"Nakawagura",
    "wof:placetype":"locality"
},
  "geometry": {"coordinates":[139.92400000000001,35.80408],"type":"Point"}
}