{
  "type": "Feature",
  "properties": {
    "iso:country":"JP",
    "name:eng_x_preferred":[
        "Kamikawahigashi 4 Chome"
    ],
    "name:eng_x_variant":[
        "Kamikawahigashi 4 Choume",
        "Kamikawahigashi 4 Chome"
    ],
    "name:jpn_x_preferred":[
        "\uff14\u4e01\u76ee"
    ],
    "name:jpn_x_variant":[
        "\u304b\u307f\u304b\u308f\u3072\u304c\u3057 \uff14\u3061\u3087\u3046\u3081",
        "\u4e0a\u5ddd\u6771 \uff14\u4e01\u76ee",
        "\uff14\u3061\u3087\u3046\u3081"
    ],
    "qs:gn_local":0,
    "qs:local_max":10,
    "qs:local_sum":10,
    "qs:localhoods":1,
    "qs:name":"\uff14\u4e01\u76ee",
    "qs:name_adm0":"\u65e5\u672c",
    "qs:name_adm1":"\u5bae\u5d0e\u770c",
    "qs:name_en":"Kamikawahigashi 4 Chome",
    "qs:name_lau":"\u4e0a\u5ddd\u6771",
    "qs:name_local":"\u90fd\u57ce\u5e02",
    "qs:photo_max":8,
    "qs:photo_sum":10,
    "qs:placetype":"Suburb",
    "qs:quad_count":3,
    "qs:woe_adm0":23424856,
    "qs:woe_adm1":2345874,
    "qs:woe_adm2":0,
    "qs:woe_lau":28491822,
    "qs:woe_local":15015420,
    "qs:woe_ver":"7.10.0",
    "wof:lang":[
        "jpn"
    ],
    "wof:name":"\uff14\u4e01\u76ee",
    "wof:placetype":"neighbourhood"
},
  "geometry": {"coordinates":[131.081726,31.755261],"type":"Point"}
}