{
  "type": "Feature",
  "properties": {
    "gn:admin1_code":"21.0",
    "gn:admin2_code":"7412705.0",
    "gn:admin3_code":"43484.0",
    "gn:asciiname":"Shinkawa",
    "gn:country_code":"JP",
    "gn:dem":1,
    "gn:feature_class":"P",
    "gn:feature_code":"PPLL",
    "gn:name":"Shinkawa",
    "gn:population":0,
    "gn:timezone":"Asia/Tokyo",
    "iso:country":"JP",
    "name:deu_x_preferred":[
        "Shinkawa"
    ],
    "name:jpn_x_preferred":[
        "\u65b0\u5ddd"
    ],
    "name:jpn_x_variant":[
        "\u3057\u3093\u304b\u308f",
        "\u30b7\u30f3\u30ab\u30ef"
    ],
    "wof:name":"Shinkawa",
    "wof:placetype":"locality"
},
  "geometry": {"coordinates":[130.44741000000002,32.2352],"type":"Point"}
}