{
  "type": "Feature",
  "properties": {
    "gn:admin1_code":"35.0",
    "gn:admin2_code":"1858984.0",
    "gn:asciiname":"Kokacho-oki",
    "gn:country_code":"JP",
    "gn:dem":203,
    "gn:feature_class":"P",
    "gn:feature_code":"PPL",
    "gn:name":"K\u014dkach\u014d-oki",
    "gn:population":0,
    "gn:timezone":"Asia/Tokyo",
    "iso:country":"JP",
    "name:jpn_x_preferred":[
        "\u7532\u8cc0\u753a\u96a0\u5c90"
    ],
    "name:und_x_variant":[
        "K\u014dkach\u014d-oki"
    ],
    "wof:name":"Kokacho-oki",
    "wof:placetype":"locality"
},
  "geometry": {"coordinates":[136.19551000000001,34.93255],"type":"Point"}
}