{
  "type": "Feature",
  "properties": {
    "gn:admin1_code":"3.0",
    "gn:admin2_code":"2128302.0",
    "gn:admin3_code":"2445.0",
    "gn:asciiname":"Makinotaira",
    "gn:country_code":"JP",
    "gn:dem":98,
    "gn:feature_class":"P",
    "gn:feature_code":"PPL",
    "gn:name":"Makinotaira",
    "gn:population":0,
    "gn:timezone":"Asia/Tokyo",
    "iso:country":"JP",
    "name:jpn_x_preferred":[
        "\u7267\u91ce\u5e73"
    ],
    "name:jpn_x_variant":[
        "\u307e\u304d\u306e\u305f\u3044\u3089",
        "\u30de\u30ad\u30ce\u30bf\u30a4\u30e9"
    ],
    "wof:name":"Makinotaira",
    "wof:placetype":"locality"
},
  "geometry": {"coordinates":[141.28328999999999,40.39999],"type":"Point"}
}