{
  "type": "Feature",
  "properties": {
    "gn:admin1_code":"3.0",
    "gn:admin2_code":"2130654.0",
    "gn:asciiname":"Nakaaizawa",
    "gn:country_code":"JP",
    "gn:dem":121,
    "gn:feature_class":"P",
    "gn:feature_code":"PPL",
    "gn:name":"Nakaaizawa",
    "gn:population":0,
    "gn:timezone":"Asia/Tokyo",
    "iso:country":"JP",
    "name:jpn_x_preferred":[
        "\u4e2d\u76f8\u6ca2"
    ],
    "name:jpn_x_variant":[
        "\u306a\u304b\u3042\u3044\u3056\u308f",
        "\u30ca\u30ab\u30a2\u30a4\u30b6\u30ef"
    ],
    "wof:name":"Nakaaizawa",
    "wof:placetype":"locality"
},
  "geometry": {"coordinates":[140.66163,40.69397],"type":"Point"}
}