{
  "type": "Feature",
  "properties": {
    "gn:admin1_code":"8.0",
    "gn:admin2_code":"2111029.0",
    "gn:asciiname":"Tokaichi",
    "gn:country_code":"JP",
    "gn:dem":387,
    "gn:feature_class":"P",
    "gn:feature_code":"PPLL",
    "gn:name":"T\u014dkaichi",
    "gn:population":0,
    "gn:timezone":"Asia/Tokyo",
    "iso:country":"JP",
    "name:jpn_x_preferred":[
        "\u5341\u65e5\u5e02"
    ],
    "name:und_x_variant":[
        "T\u014dkaichi"
    ],
    "wof:name":"Tokaichi",
    "wof:placetype":"locality"
},
  "geometry": {"coordinates":[140.17695000000001,37.23519],"type":"Point"}
}