{
  "type": "Feature",
  "properties": {
    "gn:admin1_code":"43",
    "gn:admin2_code":"1862875.0",
    "gn:admin3_code":"30392.0",
    "gn:asciiname":"Kami-ubuyukawa",
    "gn:cc2":"JP",
    "gn:country_code":"JP",
    "gn:dem":533,
    "gn:feature_class":"P",
    "gn:feature_code":"PPL",
    "gn:name":"Kami-ubuyukawa",
    "gn:population":0,
    "gn:timezone":"Asia/Tokyo",
    "iso:country":"JP",
    "name:und_x_variant":[
        "Ubuyu",
        "Kami-ubuyu-gawa",
        "Kami-ubuyugawa",
        "Kami-ubuyukawa"
    ],
    "wof:name":"Kami-ubuyukawa",
    "wof:placetype":"locality"
},
  "geometry": {"coordinates":[135.41666999999998,33.98333],"type":"Point"}
}