{
  "type": "Feature",
  "properties": {
    "gn:admin1_code":"22",
    "gn:admin2_code":"1864008.0",
    "gn:asciiname":"Kazuka",
    "gn:cc2":"JP",
    "gn:country_code":"JP",
    "gn:dem":147,
    "gn:feature_class":"P",
    "gn:feature_code":"PPL",
    "gn:name":"Kazuka",
    "gn:population":0,
    "gn:timezone":"Asia/Tokyo",
    "iso:country":"JP",
    "name:und_x_variant":[
        "Nomi",
        "Kazuka"
    ],
    "wof:name":"Kazuka",
    "wof:placetype":"locality"
},
  "geometry": {"coordinates":[134.94999999999999,35.35],"type":"Point"}
}