{
  "type": "Feature",
  "properties": {
    "gn:admin1_code":"37.0",
    "gn:admin2_code":"1864943.0",
    "gn:asciiname":"Higashiizusan",
    "gn:country_code":"JP",
    "gn:dem":148,
    "gn:feature_class":"P",
    "gn:feature_code":"PPLL",
    "gn:name":"Higashiizusan",
    "gn:population":0,
    "gn:timezone":"Asia/Tokyo",
    "iso:country":"JP",
    "name:jpn_x_preferred":[
        "\u6771\u4f0a\u8c46\u5c71"
    ],
    "wof:name":"Higashiizusan",
    "wof:placetype":"locality"
},
  "geometry": {"coordinates":[139.10165000000001,35.12858],"type":"Point"}
}