{
  "type": "Feature",
  "properties": {
    "gn:admin1_code":"4.0",
    "gn:admin2_code":"2110982.0",
    "gn:asciiname":"Mamego",
    "gn:country_code":"JP",
    "gn:dem":35,
    "gn:feature_class":"P",
    "gn:feature_code":"PPLL",
    "gn:name":"Mameg\u014d",
    "gn:population":0,
    "gn:timezone":"Asia/Tokyo",
    "iso:country":"JP",
    "name:jpn_x_preferred":[
        "\u8c46\u90f7"
    ],
    "name:jpn_x_variant":[
        "\u307e\u3081\u3054\u3046",
        "\u30de\u30e1\u30b4\u30a6"
    ],
    "name:und_x_variant":[
        "Mameg\u014d"
    ],
    "wof:name":"Mamego",
    "wof:placetype":"locality"
},
  "geometry": {"coordinates":[140.05882,35.38809000000001],"type":"Point"}
}