{
  "type": "Feature",
  "properties": {
    "gn:admin1_code":"21",
    "gn:admin2_code":"1864975.0",
    "gn:admin3_code":"43428.0",
    "gn:asciiname":"Kusakabe",
    "gn:country_code":"JP",
    "gn:dem":671,
    "gn:feature_class":"P",
    "gn:feature_code":"PPL",
    "gn:name":"Kusakabe",
    "gn:population":0,
    "gn:timezone":"Asia/Tokyo",
    "iso:country":"JP",
    "name:jpn_x_preferred":[
        "\u8349\u90e8"
    ],
    "name:jpn_x_variant":[
        "\u304f\u3055\u304b\u3079",
        "\u30af\u30b5\u30ab\u30d9"
    ],
    "name:kor_x_preferred":[
        "\uad6c\uc0ac\uce74\ubca0"
    ],
    "wof:name":"Kusakabe",
    "wof:placetype":"locality"
},
  "geometry": {"coordinates":[131.21188000000001,32.79525],"type":"Point"}
}