{
  "type": "Feature",
  "properties": {
    "gn:admin1_code":"12.0",
    "gn:admin2_code":"7428078.0",
    "gn:admin3_code":"1663.0",
    "gn:asciiname":"Hamanaka-sakukranishi",
    "gn:country_code":"JP",
    "gn:dem":78,
    "gn:feature_class":"P",
    "gn:feature_code":"PPL",
    "gn:name":"Hamanaka-sakukranishi",
    "gn:population":0,
    "gn:timezone":"Asia/Tokyo",
    "iso:country":"JP",
    "name:jpn_x_preferred":[
        "\u6d5c\u4e2d\u685c\u897f"
    ],
    "name:jpn_x_variant":[
        "\u306f\u307e\u306a\u304b\u3055\u304f\u3089\u306b\u3057",
        "\u30cf\u30de\u30ca\u30ab\u30b5\u30af\u30e9\u30cb\u30b7"
    ],
    "wof:name":"Hamanaka-sakukranishi",
    "wof:placetype":"locality"
},
  "geometry": {"coordinates":[145.09931,43.15478],"type":"Point"}
}