{
  "type": "Feature",
  "properties": {
    "gn:admin1_code":"27",
    "gn:admin2_code":"1857159.0",
    "gn:admin3_code":"42411.0",
    "gn:asciiname":"Fukumi",
    "gn:country_code":"JP",
    "gn:dem":6,
    "gn:feature_class":"P",
    "gn:feature_code":"PPL",
    "gn:name":"Fukumi",
    "gn:population":0,
    "gn:timezone":"Asia/Tokyo",
    "iso:country":"JP",
    "wof:name":"Fukumi",
    "wof:placetype":"locality"
},
  "geometry": {"coordinates":[129.07733999999999,32.86297],"type":"Point"}
}