{
  "type": "Feature",
  "properties": {
    "gn:admin1_code":"7.0",
    "gn:admin2_code":"1851269.0",
    "gn:admin3_code":"40609.0",
    "gn:asciiname":"Obaru",
    "gn:country_code":"JP",
    "gn:dem":118,
    "gn:feature_class":"P",
    "gn:feature_code":"PPLL",
    "gn:name":"\u014cbaru",
    "gn:population":0,
    "gn:timezone":"Asia/Tokyo",
    "iso:country":"JP",
    "name:jpn_x_preferred":[
        "\u5927\u539f"
    ],
    "name:und_x_variant":[
        "\u014cbaru"
    ],
    "wof:name":"Obaru",
    "wof:placetype":"locality"
},
  "geometry": {"coordinates":[130.89205000000001,33.59012],"type":"Point"}
}