{
  "type": "Feature",
  "properties": {
    "gn:admin1_code":"27",
    "gn:admin2_code":"1856152.0",
    "gn:asciiname":"Nishi-kotohiramachi",
    "gn:cc2":"JP",
    "gn:country_code":"JP",
    "gn:dem":5,
    "gn:feature_class":"P",
    "gn:feature_code":"PPL",
    "gn:name":"Nishi-kotohiramachi",
    "gn:population":0,
    "gn:timezone":"Asia/Tokyo",
    "iso:country":"JP",
    "name:und_x_variant":[
        "Nishi-kotohirach\u014d",
        "Nishi-kotohiramachi"
    ],
    "wof:name":"Nishi-kotohiramachi",
    "wof:placetype":"locality"
},
  "geometry": {"coordinates":[129.86667,32.73333],"type":"Point"}
}