{
  "type": "Feature",
  "properties": {
    "gn:admin1_code":"12.0",
    "gn:admin2_code":"2129370.0",
    "gn:asciiname":"Hokuto",
    "gn:country_code":"JP",
    "gn:dem":10,
    "gn:feature_class":"P",
    "gn:feature_code":"PPL",
    "gn:name":"Hokuto",
    "gn:population":0,
    "gn:timezone":"Asia/Tokyo",
    "iso:country":"JP",
    "name:jpn_x_preferred":[
        "\u5317\u6597"
    ],
    "name:jpn_x_variant":[
        "\u307b\u304f\u3068",
        "\u30db\u30af\u30c8"
    ],
    "wof:name":"Hokuto",
    "wof:placetype":"locality"
},
  "geometry": {"coordinates":[144.29436999999999,43.05796],"type":"Point"}
}