{
  "type": "Feature",
  "properties": {
    "gn:admin1_code":"12.0",
    "gn:admin2_code":"2129370.0",
    "gn:asciiname":"Hokuto",
    "gn:country_code":"JP",
    "gn:dem":10,
    "gn:feature_class":"P",
    "gn:feature_code":"PPL",
    "gn:name":"Hokuto",
    "gn:population":0,
    "gn:timezone":"Asia/Tokyo",
    "iso:country":"JP",
    "name:ceb_x_preferred":[
        "Hokuto"
    ],
    "name:deu_x_preferred":[
        "Hokuto"
    ],
    "name:epo_x_preferred":[
        "Hokuto"
    ],
    "name:fra_x_preferred":[
        "Hokuto"
    ],
    "name:ita_x_preferred":[
        "Hokuto"
    ],
    "name:jpn_x_preferred":[
        "\u5317\u6597"
    ],
    "name:jpn_x_variant":[
        "\u307b\u304f\u3068",
        "\u30db\u30af\u30c8"
    ],
    "name:kor_x_preferred":[
        "\ud638\ucfe0\ud1a0"
    ],
    "name:ltz_x_preferred":[
        "Hokuto"
    ],
    "name:mlg_x_preferred":[
        "Hokuto"
    ],
    "name:nld_x_preferred":[
        "Hokuto"
    ],
    "name:pol_x_preferred":[
        "Hokuto"
    ],
    "name:por_x_preferred":[
        "Hokuto"
    ],
    "name:ron_x_preferred":[
        "Hokuto"
    ],
    "name:rus_x_preferred":[
        "\u0425\u043e\u043a\u0443\u0442\u043e"
    ],
    "name:swe_x_preferred":[
        "Hokuto"
    ],
    "name:ukr_x_preferred":[
        "\u0425\u043e\u043a\u0443\u0442\u043e"
    ],
    "wof:name":"Hokuto",
    "wof:placetype":"locality"
},
  "geometry": {"coordinates":[144.29436999999999,43.05796],"type":"Point"}
}