{
  "type": "Feature",
  "properties": {
    "gn:admin1_code":"45",
    "gn:admin2_code":"1852222.0",
    "gn:asciiname":"Waku",
    "gn:country_code":"JP",
    "gn:dem":17,
    "gn:feature_class":"P",
    "gn:feature_code":"PPL",
    "gn:name":"Waku",
    "gn:population":0,
    "gn:timezone":"Asia/Tokyo",
    "iso:country":"JP",
    "name:jpn_x_preferred":[
        "\u548c\u4e45"
    ],
    "wof:name":"Waku",
    "wof:placetype":"locality"
},
  "geometry": {"coordinates":[130.88866000000002,34.30749],"type":"Point"}
}