{
  "type": "Feature",
  "properties": {
    "gn:admin1_code":"43",
    "gn:admin2_code":"1860782.0",
    "gn:asciiname":"Nataka",
    "gn:country_code":"JP",
    "gn:dem":319,
    "gn:feature_class":"P",
    "gn:feature_code":"PPL",
    "gn:name":"Nataka",
    "gn:population":0,
    "gn:timezone":"Asia/Tokyo",
    "iso:country":"JP",
    "wof:name":"Nataka",
    "wof:placetype":"locality"
},
  "geometry": {"coordinates":[135.21666999999999,34.13333],"type":"Point"}
}