{
  "type": "Feature",
  "properties": {
    "gn:admin1_code":"25.0",
    "gn:admin2_code":"7413970.0",
    "gn:asciiname":"Kuronita",
    "gn:country_code":"JP",
    "gn:dem":258,
    "gn:feature_class":"P",
    "gn:feature_code":"PPLL",
    "gn:name":"Kuronita",
    "gn:population":0,
    "gn:timezone":"Asia/Tokyo",
    "iso:country":"JP",
    "name:jpn_x_preferred":[
        "\u9ed2\u4ec1\u7530"
    ],
    "name:jpn_x_variant":[
        "\u304f\u308d\u306b\u305f",
        "\u30af\u30ed\u30cb\u30bf"
    ],
    "wof:name":"Kuronita",
    "wof:placetype":"locality"
},
  "geometry": {"coordinates":[130.97295,32.02822],"type":"Point"}
}