{
  "type": "Feature",
  "properties": {
    "gn:admin1_code":"2.0",
    "gn:admin2_code":"7443149.0",
    "gn:asciiname":"Shonai",
    "gn:country_code":"JP",
    "gn:dem":134,
    "gn:feature_class":"P",
    "gn:feature_code":"PPL",
    "gn:name":"Sh\u014dnai",
    "gn:population":0,
    "gn:timezone":"Asia/Tokyo",
    "iso:country":"JP",
    "name:jpn_x_preferred":[
        "\u5e84\u5185"
    ],
    "name:und_x_variant":[
        "Sh\u014dnai"
    ],
    "wof:name":"Shonai",
    "wof:placetype":"locality"
},
  "geometry": {"coordinates":[140.38475,39.68104],"type":"Point"}
}