{
  "type": "Feature",
  "properties": {
    "gn:admin1_code":"21.0",
    "gn:admin2_code":"7412706.0",
    "gn:admin3_code":"43447.0",
    "gn:asciiname":"Yokono",
    "gn:country_code":"JP",
    "gn:dem":467,
    "gn:feature_class":"P",
    "gn:feature_code":"PPLL",
    "gn:name":"Yokono",
    "gn:population":0,
    "gn:timezone":"Asia/Tokyo",
    "iso:country":"JP",
    "name:jpn_x_preferred":[
        "\u6a2a\u91ce"
    ],
    "name:jpn_x_variant":[
        "\u3088\u3053\u306e",
        "\u30e8\u30b3\u30ce"
    ],
    "wof:name":"Yokono",
    "wof:placetype":"locality"
},
  "geometry": {"coordinates":[131.02813999999998,32.67545],"type":"Point"}
}