{
  "type": "Feature",
  "properties": {
    "gn:admin1_code":"23.0",
    "gn:admin2_code":"1859297.0",
    "gn:admin3_code":"24543.0",
    "gn:asciiname":"Kii-nagashimaku-jusu",
    "gn:country_code":"JP",
    "gn:dem":141,
    "gn:feature_class":"P",
    "gn:feature_code":"PPL",
    "gn:name":"Kii-nagashimaku-j\u016bsu",
    "gn:population":0,
    "gn:timezone":"Asia/Tokyo",
    "iso:country":"JP",
    "name:jpn_x_preferred":[
        "\u7d00\u4f0a\u9577\u5cf6\u533a\u5341\u9808"
    ],
    "name:und_x_variant":[
        "Kii-nagashimaku-j\u016bsu"
    ],
    "wof:name":"Kii-nagashimaku-jusu",
    "wof:placetype":"locality"
},
  "geometry": {"coordinates":[136.27819,34.23388],"type":"Point"}
}