{
  "type": "Feature",
  "properties": {
    "gn:admin1_code":"23.0",
    "gn:admin2_code":"1861901.0",
    "gn:asciiname":"Yamade",
    "gn:country_code":"JP",
    "gn:dem":161,
    "gn:feature_class":"P",
    "gn:feature_code":"PPL",
    "gn:name":"Yamade",
    "gn:population":0,
    "gn:timezone":"Asia/Tokyo",
    "iso:country":"JP",
    "name:jpn_x_preferred":[
        "\u5c71\u51fa"
    ],
    "wof:name":"Yamade",
    "wof:placetype":"locality"
},
  "geometry": {"coordinates":[136.12835000000001,34.71989],"type":"Point"}
}