{
  "type": "Feature",
  "properties": {
    "gn:admin1_code":"44.0",
    "gn:admin2_code":"2111850.0",
    "gn:admin3_code":"6365.0",
    "gn:asciiname":"Kumataka",
    "gn:country_code":"JP",
    "gn:dem":73,
    "gn:feature_class":"P",
    "gn:feature_code":"PPL",
    "gn:name":"Kumataka",
    "gn:population":0,
    "gn:timezone":"Asia/Tokyo",
    "iso:country":"JP",
    "name:jpn_x_preferred":[
        "\u718a\u9ad8"
    ],
    "name:und_x_variant":[
        "Kumadaka"
    ],
    "wof:name":"Kumataka",
    "wof:placetype":"locality"
},
  "geometry": {"coordinates":[140.21693999999999,38.67278],"type":"Point"}
}