{
  "type": "Feature",
  "properties": {
    "gn:admin1_code":"7.0",
    "gn:admin2_code":"1856443.0",
    "gn:asciiname":"Nosaka",
    "gn:country_code":"JP",
    "gn:dem":33,
    "gn:feature_class":"P",
    "gn:feature_code":"PPL",
    "gn:name":"Nosaka",
    "gn:population":0,
    "gn:timezone":"Asia/Tokyo",
    "iso:country":"JP",
    "name:jpn_x_preferred":[
        "\u91ce\u5742"
    ],
    "wof:name":"Nosaka",
    "wof:placetype":"locality"
},
  "geometry": {"coordinates":[130.56129000000001,33.77442],"type":"Point"}
}