{
  "type": "Feature",
  "properties": {
    "gn:admin1_code":"26.0",
    "gn:admin2_code":"7416552.0",
    "gn:admin3_code":"20588.0",
    "gn:asciiname":"Kaguraoka",
    "gn:country_code":"JP",
    "gn:dem":860,
    "gn:feature_class":"P",
    "gn:feature_code":"PPL",
    "gn:name":"Kaguraoka",
    "gn:population":0,
    "gn:timezone":"Asia/Tokyo",
    "iso:country":"JP",
    "name:jpn_x_preferred":[
        "\u795e\u697d\u5ca1"
    ],
    "wof:name":"Kaguraoka",
    "wof:placetype":"locality"
},
  "geometry": {"coordinates":[137.93143999999998,36.65113],"type":"Point"}
}