{
  "type": "Feature",
  "properties": {
    "gn:admin1_code":"37",
    "gn:admin2_code":"1860327.0",
    "gn:admin3_code":"22306.0",
    "gn:asciiname":"Ugusu",
    "gn:country_code":"JP",
    "gn:dem":83,
    "gn:feature_class":"P",
    "gn:feature_code":"PPL",
    "gn:name":"Ugusu",
    "gn:population":0,
    "gn:timezone":"Asia/Tokyo",
    "iso:country":"JP",
    "name:jpn_x_preferred":[
        "\u5b87\u4e45\u9808"
    ],
    "name:und_x_variant":[
        "Ukusu",
        "Ugusu"
    ],
    "wof:name":"Ugusu",
    "wof:placetype":"locality"
},
  "geometry": {"coordinates":[138.77677,34.84455],"type":"Point"}
}