{
  "type": "Feature",
  "properties": {
    "iso:country":"JP",
    "name:eng_x_preferred":[
        "Takasu 5 Chome"
    ],
    "name:eng_x_variant":[
        "Takasu 5 Choume",
        "Takasu 5 Chome"
    ],
    "name:jpn_x_preferred":[
        "\uff15\u4e01\u76ee"
    ],
    "name:jpn_x_variant":[
        "\u305f\u304b\u3059 \uff15\u3061\u3087\u3046\u3081",
        "\u9ad8\u6d32 \uff15\u4e01\u76ee",
        "\uff15\u3061\u3087\u3046\u3081"
    ],
    "qs:gn_local":0,
    "qs:local_max":28643,
    "qs:local_sum":29847,
    "qs:localhoods":14,
    "qs:name":"\uff15\u4e01\u76ee",
    "qs:name_adm0":"\u65e5\u672c",
    "qs:name_adm1":"\u5343\u8449\u770c",
    "qs:name_en":"Takasu 5 Chome",
    "qs:name_lau":"\u9ad8\u6d32",
    "qs:name_local":"\u6d66\u5b89\u5e02",
    "qs:photo_max":30,
    "qs:photo_sum":96,
    "qs:placetype":"Suburb",
    "qs:quad_count":11,
    "qs:woe_adm0":23424856,
    "qs:woe_adm1":2345854,
    "qs:woe_adm2":0,
    "qs:woe_lau":28412745,
    "qs:woe_local":1116236,
    "qs:woe_ver":"7.10.0",
    "qs_pg:name":"\uff15\u4e01\u76ee",
    "qs_pg:name_adm0":"\u65e5\u672c",
    "qs_pg:name_adm1":"\u5343\u8449\u770c",
    "qs_pg:photos":41,
    "qs_pg:photos_1k":8,
    "qs_pg:photos_9k":1,
    "qs_pg:photos_9r":2,
    "qs_pg:photos_all":41,
    "qs_pg:photos_sr":2,
    "qs_pg:pop_sr":0,
    "qs_pg:qs_pg_placetype":"neighbourhood",
    "qs_pg:qs_pg_placetype_gp":"Suburb",
    "qs_pg:woe_adm0":23424856,
    "woe:adm0_id":23424856,
    "woe:name_adm0":"\u65e5\u672c",
    "woe:name_adm1":"\u5343\u8449\u770c",
    "woe:placetype":"Suburb",
    "wof:lang":[
        "jpn"
    ],
    "wof:name":"\uff15\u4e01\u76ee",
    "wof:placetype":"neighbourhood"
},
  "geometry": {"coordinates":[139.91956500000001,35.636449],"type":"Point"}
}