{
  "type": "Feature",
  "properties": {
    "gn:admin1_code":"2.0",
    "gn:admin2_code":"2113122.0",
    "gn:asciiname":"Shimokitate-sakura",
    "gn:country_code":"JP",
    "gn:dem":27,
    "gn:feature_class":"P",
    "gn:feature_code":"PPL",
    "gn:name":"Shimokitate-sakura",
    "gn:population":0,
    "gn:timezone":"Asia/Tokyo",
    "iso:country":"JP",
    "name:jpn_x_preferred":[
        "\u4e0b\u5317\u624b\u685c"
    ],
    "name:jpn_x_variant":[
        "\u3057\u3082\u304d\u305f\u3066\u3055\u304f\u3089",
        "\u30b7\u30e2\u30ad\u30bf\u30c6\u30b5\u30af\u30e9"
    ],
    "wof:name":"Shimokitate-sakura",
    "wof:placetype":"locality"
},
  "geometry": {"coordinates":[140.16468,39.71687],"type":"Point"}
}