{
  "type": "Feature",
  "properties": {
    "iso:country":"JP",
    "name:eng_x_preferred":[
        "Yugawashinmachi 4 Chome"
    ],
    "name:eng_x_variant":[
        "Yugawashinmachi 4 Choume",
        "Yugawashinmachi 4 Chome"
    ],
    "name:jpn_x_preferred":[
        "\uff14\u4e01\u76ee"
    ],
    "name:jpn_x_variant":[
        "\u3086\u304c\u308f\u3057\u3093\u307e\u3061 \uff14\u3061\u3087\u3046\u3081",
        "\u6e6f\u5ddd\u65b0\u753a \uff14\u4e01\u76ee",
        "\uff14\u3061\u3087\u3046\u3081"
    ],
    "name:unk_x_variant":[
        "\uff14\u4e01\u76ee"
    ],
    "qs:gn_local":0,
    "qs:local_max":819,
    "qs:local_sum":3269,
    "qs:localhoods":25,
    "qs:name":"\uff14\u4e01\u76ee",
    "qs:name_adm0":"\u65e5\u672c",
    "qs:name_adm1":"\u798f\u5ca1\u770c",
    "qs:name_adm2":"\u5c0f\u5009\u5357\u533a",
    "qs:name_en":"Yugawashinmachi 4 Chome",
    "qs:name_lau":"\u6e6f\u5ddd\u65b0\u753a",
    "qs:name_local":"\u5317\u4e5d\u5dde\u5e02",
    "qs:photo_max":19,
    "qs:photo_sum":19,
    "qs:placetype":"Suburb",
    "qs:quad_count":1,
    "qs:woe_adm0":23424856,
    "qs:woe_adm1":58646425,
    "qs:woe_adm2":15015395,
    "qs:woe_lau":28482723,
    "qs:woe_local":1110809,
    "qs:woe_ver":"7.10.0",
    "wof:lang":[
        "jpn"
    ],
    "wof:name":"\uff14\u4e01\u76ee",
    "wof:placetype":"neighbourhood"
},
  "geometry": {"coordinates":[130.90484599999999,33.840763],"type":"Point"}
}