{
  "type": "Feature",
  "properties": {
    "gn:admin1_code":"46.0",
    "gn:admin2_code":"1864076.0",
    "gn:asciiname":"Shinnishihara",
    "gn:country_code":"JP",
    "gn:dem":829,
    "gn:feature_class":"P",
    "gn:feature_code":"PPL",
    "gn:name":"Shinnishihara",
    "gn:population":0,
    "gn:timezone":"Asia/Tokyo",
    "iso:country":"JP",
    "name:jpn_x_preferred":[
        "\u65b0\u897f\u539f"
    ],
    "wof:name":"Shinnishihara",
    "wof:placetype":"locality"
},
  "geometry": {"coordinates":[138.78756000000001,35.48232],"type":"Point"}
}