{
  "type": "Feature",
  "properties": {
    "gn:admin1_code":"3.0",
    "gn:admin2_code":"2129754.0",
    "gn:admin3_code":"2405.0",
    "gn:asciiname":"Shichihyaku",
    "gn:country_code":"JP",
    "gn:dem":70,
    "gn:feature_class":"P",
    "gn:feature_code":"PPL",
    "gn:name":"Shichihyaku",
    "gn:population":0,
    "gn:timezone":"Asia/Tokyo",
    "iso:country":"JP",
    "name:jpn_x_preferred":[
        "\u4e03\u767e"
    ],
    "name:jpn_x_variant":[
        "\u3057\u3061\u3072\u3083\u304f",
        "\u30b7\u30c1\u30d2\u30e3\u30af"
    ],
    "wof:name":"Shichihyaku",
    "wof:placetype":"locality"
},
  "geometry": {"coordinates":[141.30241000000001,40.64176],"type":"Point"}
}