{
  "type": "Feature",
  "properties": {
    "gn:admin1_code":"34.0",
    "gn:admin2_code":"1849187.0",
    "gn:admin3_code":"11106.0",
    "gn:asciiname":"Zaike",
    "gn:country_code":"JP",
    "gn:dem":10,
    "gn:feature_class":"P",
    "gn:feature_code":"PPL",
    "gn:name":"Zaike",
    "gn:population":0,
    "gn:timezone":"Asia/Tokyo",
    "iso:country":"JP",
    "name:jpn_x_preferred":[
        "\u5728\u5bb6"
    ],
    "name:jpn_x_variant":[
        "\u3056\u3044\u3051",
        "\u30b6\u30a4\u30b1"
    ],
    "wof:name":"Zaike",
    "wof:placetype":"locality"
},
  "geometry": {"coordinates":[139.59936999999999,35.87862],"type":"Point"}
}