{
  "type": "Feature",
  "properties": {
    "gn:admin1_code":"21.0",
    "gn:admin2_code":"1865358.0",
    "gn:asciiname":"Hiratoko",
    "gn:country_code":"JP",
    "gn:dem":106,
    "gn:feature_class":"P",
    "gn:feature_code":"PPLL",
    "gn:name":"Hiratoko",
    "gn:population":0,
    "gn:timezone":"Asia/Tokyo",
    "iso:country":"JP",
    "name:jpn_x_preferred":[
        "\u5e73\u5e8a"
    ],
    "name:jpn_x_variant":[
        "\u3072\u3089\u3068\u3053",
        "\u30d2\u30e9\u30c8\u30b3"
    ],
    "wof:name":"Hiratoko",
    "wof:placetype":"locality"
},
  "geometry": {"coordinates":[130.14531000000002,32.43118],"type":"Point"}
}