{
  "type": "Feature",
  "properties": {
    "gn:admin1_code":"44.0",
    "gn:admin2_code":"2112756.0",
    "gn:admin3_code":"6381.0",
    "gn:asciiname":"Natsumo",
    "gn:country_code":"JP",
    "gn:dem":216,
    "gn:feature_class":"P",
    "gn:feature_code":"PPL",
    "gn:name":"Natsumo",
    "gn:population":0,
    "gn:timezone":"Asia/Tokyo",
    "iso:country":"JP",
    "name:jpn_x_preferred":[
        "\u590f\u8302"
    ],
    "wof:name":"Natsumo",
    "wof:placetype":"locality"
},
  "geometry": {"coordinates":[140.14753000000002,38.00179],"type":"Point"}
}