{
  "type": "Feature",
  "properties": {
    "gn:admin1_code":"21.0",
    "gn:admin2_code":"7413152.0",
    "gn:asciiname":"Ideguchi",
    "gn:country_code":"JP",
    "gn:dem":5,
    "gn:feature_class":"P",
    "gn:feature_code":"PPLL",
    "gn:name":"Ideguchi",
    "gn:population":0,
    "gn:timezone":"Asia/Tokyo",
    "iso:country":"JP",
    "name:jpn_x_preferred":[
        "\u4e95\u624b\u53e3"
    ],
    "name:jpn_x_variant":[
        "\u3044\u3067\u3050\u3061",
        "\u30a4\u30c7\u30b0\u30c1"
    ],
    "wof:name":"Ideguchi",
    "wof:placetype":"locality"
},
  "geometry": {"coordinates":[130.70230000000001,32.58442],"type":"Point"}
}