{
  "type": "Feature",
  "properties": {
    "gn:admin1_code":"8.0",
    "gn:admin2_code":"2111029.0",
    "gn:asciiname":"Taishin-masumi",
    "gn:country_code":"JP",
    "gn:dem":302,
    "gn:feature_class":"P",
    "gn:feature_code":"PPL",
    "gn:name":"Taishin-masumi",
    "gn:population":0,
    "gn:timezone":"Asia/Tokyo",
    "iso:country":"JP",
    "name:jpn_x_preferred":[
        "\u5927\u4fe1\u5897\u898b"
    ],
    "wof:name":"Taishin-masumi",
    "wof:placetype":"locality"
},
  "geometry": {"coordinates":[140.24403999999998,37.19905],"type":"Point"}
}