{
  "type": "Feature",
  "properties": {
    "gn:admin1_code":"44",
    "gn:admin2_code":"1849562.0",
    "gn:asciiname":"Makidai",
    "gn:country_code":"JP",
    "gn:dem":67,
    "gn:feature_class":"P",
    "gn:feature_code":"PPL",
    "gn:name":"Makidai",
    "gn:population":0,
    "gn:timezone":"Asia/Tokyo",
    "iso:country":"JP",
    "name:jpn_x_preferred":[
        "\u69d9\u4ee3"
    ],
    "name:und_x_variant":[
        "Makitai",
        "Makidai",
        "Makinodai"
    ],
    "wof:name":"Makidai",
    "wof:placetype":"locality"
},
  "geometry": {"coordinates":[139.60391000000001,38.59176],"type":"Point"}
}