{
  "type": "Feature",
  "properties": {
    "gn:admin1_code":"45",
    "gn:asciiname":"Kasado",
    "gn:cc2":"JP",
    "gn:country_code":"JP",
    "gn:dem":38,
    "gn:feature_class":"P",
    "gn:feature_code":"PPL",
    "gn:name":"Kasado",
    "gn:population":0,
    "gn:timezone":"Asia/Tokyo",
    "iso:country":"JP",
    "name:und_x_variant":[
        "Kasadoshima",
        "Kasado-jima",
        "Kasado"
    ],
    "wof:name":"Kasado",
    "wof:placetype":"locality"
},
  "geometry": {"coordinates":[131.86667,33.96667],"type":"Point"}
}