{
  "type": "Feature",
  "properties": {
    "gn:admin1_code":"21.0",
    "gn:admin2_code":"1857206.0",
    "gn:asciiname":"Hakeai",
    "gn:country_code":"JP",
    "gn:dem":308,
    "gn:feature_class":"P",
    "gn:feature_code":"PPLL",
    "gn:name":"Hakeai",
    "gn:population":0,
    "gn:timezone":"Asia/Tokyo",
    "iso:country":"JP",
    "name:jpn_x_preferred":[
        "\u5410\u5408"
    ],
    "name:jpn_x_variant":[
        "\u306f\u3051\u3042\u3044",
        "\u30cf\u30b1\u30a2\u30a4"
    ],
    "wof:name":"Hakeai",
    "wof:placetype":"locality"
},
  "geometry": {"coordinates":[130.48535000000001,32.19797],"type":"Point"}
}