{
  "type": "Feature",
  "properties": {
    "gn:admin1_code":"21.0",
    "gn:admin2_code":"7412708.0",
    "gn:admin3_code":"43512.0",
    "gn:asciiname":"Nishinokochi",
    "gn:country_code":"JP",
    "gn:dem":253,
    "gn:feature_class":"P",
    "gn:feature_code":"PPLL",
    "gn:name":"Nishinok\u014dchi",
    "gn:population":0,
    "gn:timezone":"Asia/Tokyo",
    "iso:country":"JP",
    "name:jpn_x_preferred":[
        "\u897f\u30ce\u5c0f\u8def"
    ],
    "name:jpn_x_variant":[
        "\u306b\u3057\u306e\u3053\u3046\u3061",
        "\u30cb\u30b7\u30ce\u30b3\u30a6\u30c1"
    ],
    "name:und_x_variant":[
        "Nishinok\u014dchi"
    ],
    "wof:name":"Nishinokochi",
    "wof:placetype":"locality"
},
  "geometry": {"coordinates":[130.77938,32.27835],"type":"Point"}
}