{
  "type": "Feature",
  "properties": {
    "gn:admin1_code":"19.0",
    "gn:admin2_code":"1848308.0",
    "gn:asciiname":"Akiya",
    "gn:country_code":"JP",
    "gn:dem":19,
    "gn:feature_class":"P",
    "gn:feature_code":"PPL",
    "gn:name":"Akiya",
    "gn:population":0,
    "gn:timezone":"Asia/Tokyo",
    "iso:country":"JP",
    "name:ind_x_preferred":[
        "Akiya"
    ],
    "name:jpn_x_preferred":[
        "\u79cb\u8c37"
    ],
    "name:jpn_x_variant":[
        "\u3042\u304d\u3084",
        "\u30a2\u30ad\u30e4"
    ],
    "wof:name":"Akiya",
    "wof:placetype":"locality"
},
  "geometry": {"coordinates":[139.60363999999998,35.23754],"type":"Point"}
}