{
  "type": "Feature",
  "properties": {
    "gn:admin1_code":"4.0",
    "gn:admin2_code":"2112997.0",
    "gn:admin3_code":"12423.0",
    "gn:asciiname":"Hitotsumatsu-otsu",
    "gn:country_code":"JP",
    "gn:dem":1,
    "gn:feature_class":"P",
    "gn:feature_code":"PPLL",
    "gn:name":"Hitotsumatsu-otsu",
    "gn:population":0,
    "gn:timezone":"Asia/Tokyo",
    "iso:country":"JP",
    "name:jpn_x_preferred":[
        "\u4e00\u677e\u4e59"
    ],
    "name:jpn_x_variant":[
        "\u3072\u3068\u3064\u307e\u3064\u304a\u3064",
        "\u30d2\u30c8\u30c4\u30de\u30c4\u30aa\u30c4"
    ],
    "wof:name":"Hitotsumatsu-otsu",
    "wof:placetype":"locality"
},
  "geometry": {"coordinates":[140.38003999999998,35.39152],"type":"Point"}
}