{
  "type": "Feature",
  "properties": {
    "gn:admin1_code":"26",
    "gn:admin2_code":"1849427.0",
    "gn:asciiname":"Sugadaira",
    "gn:country_code":"JP",
    "gn:dem":1250,
    "gn:feature_class":"P",
    "gn:feature_code":"PPLL",
    "gn:name":"Sugadaira",
    "gn:population":0,
    "gn:timezone":"Asia/Tokyo",
    "iso:country":"JP",
    "name:jpn_x_preferred":[
        "\u83c5\u5e73"
    ],
    "wof:name":"Sugadaira",
    "wof:placetype":"locality"
},
  "geometry": {"coordinates":[138.32991000000001,36.52454],"type":"Point"}
}