{
  "type": "Feature",
  "properties": {
    "gn:admin1_code":"37",
    "gn:admin2_code":"1864089.0",
    "gn:asciiname":"Iwamoto",
    "gn:country_code":"JP",
    "gn:dem":26,
    "gn:feature_class":"P",
    "gn:feature_code":"PPL",
    "gn:name":"Iwamoto",
    "gn:population":0,
    "gn:timezone":"Asia/Tokyo",
    "iso:country":"JP",
    "name:deu_x_preferred":[
        "Iwamoto"
    ],
    "name:jpn_x_preferred":[
        "\u5ca9\u672c"
    ],
    "name:rus_x_preferred":[
        "\u0418\u0432\u0430\u043c\u043e\u0442\u043e"
    ],
    "wof:name":"Iwamoto",
    "wof:placetype":"locality"
},
  "geometry": {"coordinates":[138.62992,35.1737],"type":"Point"}
}