{
  "type": "Feature",
  "properties": {
    "gn:admin1_code":"43.0",
    "gn:admin2_code":"1865123.0",
    "gn:admin3_code":"30366.0",
    "gn:asciiname":"Osono",
    "gn:country_code":"JP",
    "gn:dem":184,
    "gn:feature_class":"P",
    "gn:feature_code":"PPL",
    "gn:name":"\u014csono",
    "gn:population":0,
    "gn:timezone":"Asia/Tokyo",
    "iso:country":"JP",
    "name:jpn_x_preferred":[
        "\u5927\u8597"
    ],
    "name:und_x_variant":[
        "\u014csono"
    ],
    "wof:name":"Osono",
    "wof:placetype":"locality"
},
  "geometry": {"coordinates":[135.3107,34.08031],"type":"Point"}
}