{
  "type": "Feature",
  "properties": {
    "gn:admin1_code":"19.0",
    "gn:admin2_code":"1848350.0",
    "gn:admin3_code":"14105.0",
    "gn:asciiname":"Nakazato",
    "gn:country_code":"JP",
    "gn:dem":20,
    "gn:feature_class":"P",
    "gn:feature_code":"PPL",
    "gn:name":"Nakazato",
    "gn:population":0,
    "gn:timezone":"Asia/Tokyo",
    "iso:country":"JP",
    "name:deu_x_preferred":[
        "Nakazato"
    ],
    "name:jpn_x_preferred":[
        "\u4e2d\u91cc"
    ],
    "name:jpn_x_variant":[
        "\u306a\u304b\u3056\u3068",
        "\u30ca\u30ab\u30b6\u30c8"
    ],
    "wof:name":"Nakazato",
    "wof:placetype":"locality"
},
  "geometry": {"coordinates":[139.59336000000002,35.42071],"type":"Point"}
}