{
  "type": "Feature",
  "properties": {
    "gn:admin1_code":"34",
    "gn:admin2_code":"1864030.0",
    "gn:asciiname":"Nakaze",
    "gn:country_code":"JP",
    "gn:dem":37,
    "gn:feature_class":"P",
    "gn:feature_code":"PPL",
    "gn:name":"Nakaze",
    "gn:population":0,
    "gn:timezone":"Asia/Tokyo",
    "iso:country":"JP",
    "name:jpn_x_preferred":[
        "\u4e2d\u702c"
    ],
    "wof:name":"Nakaze",
    "wof:placetype":"locality"
},
  "geometry": {"coordinates":[139.27258999999998,36.2405],"type":"Point"}
}