{
  "type": "Feature",
  "properties": {
    "gn:admin1_code":"36.0",
    "gn:admin2_code":"1854361.0",
    "gn:admin3_code":"32528.0",
    "gn:asciiname":"Kumi",
    "gn:country_code":"JP",
    "gn:dem":0,
    "gn:feature_class":"P",
    "gn:feature_code":"PPL",
    "gn:name":"Kumi",
    "gn:population":0,
    "gn:timezone":"Asia/Tokyo",
    "iso:country":"JP",
    "name:ceb_x_preferred":[
        "Kumi"
    ],
    "name:deu_x_preferred":[
        "Kumi"
    ],
    "name:fra_x_preferred":[
        "Kumi"
    ],
    "name:jpn_x_preferred":[
        "\u4e45\u898b"
    ],
    "name:nds_x_preferred":[
        "Kumi"
    ],
    "name:swa_x_preferred":[
        "Kumi"
    ],
    "name:swe_x_preferred":[
        "Kumi"
    ],
    "wof:name":"Kumi",
    "wof:placetype":"locality"
},
  "geometry": {"coordinates":[133.23258000000001,36.31957],"type":"Point"}
}