{
  "type": "Feature",
  "properties": {
    "gn:admin1_code":"36.0",
    "gn:admin2_code":"1854361.0",
    "gn:admin3_code":"32528.0",
    "gn:asciiname":"Kumi",
    "gn:country_code":"JP",
    "gn:dem":0,
    "gn:feature_class":"P",
    "gn:feature_code":"PPL",
    "gn:name":"Kumi",
    "gn:population":0,
    "gn:timezone":"Asia/Tokyo",
    "iso:country":"JP",
    "name:ara_x_preferred":[
        "\u0643\u0648\u0645\u064a"
    ],
    "name:ben_x_preferred":[
        "\u0995\u09c1\u09ae\u09bf"
    ],
    "name:ceb_x_preferred":[
        "Kumi"
    ],
    "name:deu_x_preferred":[
        "Kumi"
    ],
    "name:ell_x_preferred":[
        "\u039a\u03bf\u03cd\u03bc\u03b9"
    ],
    "name:fas_x_preferred":[
        "\u06a9\u0648\u0645\u06cc"
    ],
    "name:fra_x_preferred":[
        "Kumi"
    ],
    "name:heb_x_preferred":[
        "\u05e7\u05d5\u05de\u05d9"
    ],
    "name:hin_x_preferred":[
        "\u0915\u0942\u092e\u0940"
    ],
    "name:hun_x_preferred":[
        "Kumi"
    ],
    "name:ind_x_preferred":[
        "Kumi"
    ],
    "name:ita_x_preferred":[
        "Kumi"
    ],
    "name:jpn_x_preferred":[
        "\u4e45\u898b"
    ],
    "name:kor_x_preferred":[
        "\ucfe0\ubbf8"
    ],
    "name:nds_x_preferred":[
        "Kumi"
    ],
    "name:por_x_preferred":[
        "Kumi"
    ],
    "name:rus_x_preferred":[
        "\u041a\u0443\u043c\u0438"
    ],
    "name:spa_x_preferred":[
        "Kumi"
    ],
    "name:swa_x_preferred":[
        "Kumi"
    ],
    "name:swe_x_preferred":[
        "Kumi"
    ],
    "name:tur_x_preferred":[
        "Kumi"
    ],
    "name:ukr_x_preferred":[
        "\u041a\u0443\u043c\u0456"
    ],
    "name:vie_x_preferred":[
        "Kumi"
    ],
    "name:zho_cn_x_preferred":[
        "\u5e93\u7c73"
    ],
    "name:zho_tw_x_preferred":[
        "\u5eab\u7c73"
    ],
    "wof:name":"Kumi",
    "wof:placetype":"locality"
},
  "geometry": {"coordinates":[133.23258000000001,36.31957],"type":"Point"}
}