{
  "type": "Feature",
  "properties": {
    "iso:country":"JP",
    "name:eng_x_preferred":[
        "Sannomaru 3 Chome"
    ],
    "name:eng_x_variant":[
        "Sannomaru 3 Choume",
        "Sannomaru 3 Chome"
    ],
    "name:jpn_x_preferred":[
        "\uff13\u4e01\u76ee"
    ],
    "name:jpn_x_variant":[
        "\u3055\u3093\u306e\u307e\u308b \uff13\u3061\u3087\u3046\u3081",
        "\u4e09\u306e\u4e38 \uff13\u4e01\u76ee",
        "\uff13\u3061\u3087\u3046\u3081"
    ],
    "name:unk_x_variant":[
        "\uff13\u4e01\u76ee"
    ],
    "qs:gn_local":0,
    "qs:local_max":3194,
    "qs:local_sum":30209,
    "qs:localhoods":92,
    "qs:name":"\uff13\u4e01\u76ee",
    "qs:name_adm0":"\u65e5\u672c",
    "qs:name_adm1":"\u611b\u77e5\u770c",
    "qs:name_adm2":"\u4e2d\u533a",
    "qs:name_en":"Sannomaru 3 Chome",
    "qs:name_lau":"\u4e09\u306e\u4e38",
    "qs:name_local":"\u540d\u53e4\u5c4b\u5e02",
    "qs:photo_max":437,
    "qs:photo_sum":833,
    "qs:placetype":"Suburb",
    "qs:quad_count":4,
    "qs:woe_adm0":23424856,
    "qs:woe_adm1":2345851,
    "qs:woe_adm2":15015556,
    "qs:woe_lau":28439387,
    "qs:woe_local":1117817,
    "qs:woe_ver":"7.10.0",
    "wof:lang":[
        "jpn"
    ],
    "wof:name":"\uff13\u4e01\u76ee",
    "wof:placetype":"neighbourhood"
},
  "geometry": {"coordinates":[136.90592100000001,35.181716],"type":"Point"}
}