{
  "type": "Feature",
  "properties": {
    "gn:admin1_code":"09",
    "gn:admin2_code":"1863645.0",
    "gn:asciiname":"Shimohara",
    "gn:cc2":"JP",
    "gn:country_code":"JP",
    "gn:dem":236,
    "gn:feature_class":"P",
    "gn:feature_code":"PPL",
    "gn:name":"Shimohara",
    "gn:population":0,
    "gn:timezone":"Asia/Tokyo",
    "iso:country":"JP",
    "name:und_x_variant":[
        "Shimoharamachi",
        "Shimohara"
    ],
    "wof:name":"Shimohara",
    "wof:placetype":"locality"
},
  "geometry": {"coordinates":[137.16666999999998,35.66667],"type":"Point"}
}