{
  "type": "Feature",
  "properties": {
    "gn:country":"JP",
    "gn:fcode":"ADM3",
    "gn:population":0,
    "iso:country":"JP",
    "name:eng_x_preferred":[
        "\u014cgawara"
    ],
    "name:eng_x_variant":[
        "\u014cgawara-machi"
    ],
    "name:jpn_x_preferred":[
        "\u5927\u6cb3\u539f\u753a"
    ],
    "name:jpn_x_variant":[
        "\u304a\u304a\u304c\u308f\u3089\u307e\u3061"
    ],
    "name:und_x_variant":[
        "\u014cgawara Machi"
    ],
    "qs:name":"\u014cgawara-machi",
    "qs:photos_9r":0,
    "qs:photos_sr":0,
    "qs:pop_sr":"0",
    "wof:name":"\u014cgawara",
    "wof:placetype":"localadmin",
    "wof:population":0
},
  "geometry": {"coordinates":[140.71512999999999,38.05209],"type":"Point"}
}