{
  "type": "Feature",
  "properties": {
    "gn:admin1_code":"17.0",
    "gn:admin2_code":"1857664.0",
    "gn:asciiname":"Nakazucho",
    "gn:country_code":"JP",
    "gn:dem":9,
    "gn:feature_class":"P",
    "gn:feature_code":"PPL",
    "gn:name":"Nakazuch\u014d",
    "gn:population":0,
    "gn:timezone":"Asia/Tokyo",
    "iso:country":"JP",
    "name:jbn_x_preferred":[
        "Nakazu"
    ],
    "name:jpn_x_preferred":[
        "\u4e2d\u6d25\u753a"
    ],
    "name:und_x_variant":[
        "Nakazuch\u014d"
    ],
    "wof:name":"Nakazucho",
    "wof:placetype":"locality"
},
  "geometry": {"coordinates":[133.77361999999999,34.2776],"type":"Point"}
}