{
  "type": "Feature",
  "properties": {
    "gn:admin1_code":"21.0",
    "gn:admin2_code":"1858418.0",
    "gn:admin3_code":"43103.0",
    "gn:asciiname":"Ikenouemachi",
    "gn:country_code":"JP",
    "gn:dem":3,
    "gn:feature_class":"P",
    "gn:feature_code":"PPL",
    "gn:name":"Ikenouemachi",
    "gn:population":0,
    "gn:timezone":"Asia/Tokyo",
    "iso:country":"JP",
    "name:jpn_x_preferred":[
        "\u6c60\u4e0a\u753a"
    ],
    "name:jpn_x_variant":[
        "\u3044\u3051\u306e\u3046\u3048\u307e\u3061",
        "\u30a4\u30b1\u30ce\u30a6\u30a8\u30de\u30c1"
    ],
    "wof:name":"Ikenouemachi",
    "wof:placetype":"locality"
},
  "geometry": {"coordinates":[130.66843,32.79382],"type":"Point"}
}