{
  "type": "Feature",
  "properties": {
    "iso:country":"JP",
    "name:eng_x_preferred":[
        "Kojo 3 Chome"
    ],
    "name:eng_x_variant":[
        "Kojou 3 Choume",
        "Kojo 3 Chome"
    ],
    "name:jpn_x_preferred":[
        "\uff13\u4e01\u76ee"
    ],
    "name:jpn_x_variant":[
        "\u3053\u3058\u3087\u3046 \uff13\u3061\u3087\u3046\u3081",
        "\u53e4\u57ce \uff13\u4e01\u76ee",
        "\uff13\u3061\u3087\u3046\u3081"
    ],
    "qs:gn_local":0,
    "qs:local_max":11,
    "qs:local_sum":17,
    "qs:localhoods":2,
    "qs:name":"\uff13\u4e01\u76ee",
    "qs:name_adm0":"\u65e5\u672c",
    "qs:name_adm1":"\u718a\u672c\u770c",
    "qs:name_en":"Kojo 3 Chome",
    "qs:name_lau":"\u53e4\u57ce",
    "qs:name_local":"\u6c34\u4fe3\u5e02",
    "qs:photo_max":6,
    "qs:photo_sum":6,
    "qs:placetype":"Suburb",
    "qs:quad_count":1,
    "qs:woe_adm0":23424856,
    "qs:woe_adm1":2345870,
    "qs:woe_adm2":0,
    "qs:woe_lau":28488763,
    "qs:woe_local":1117716,
    "qs:woe_ver":"7.10.0",
    "wof:lang":[
        "jpn"
    ],
    "wof:name":"\uff13\u4e01\u76ee",
    "wof:placetype":"neighbourhood"
},
  "geometry": {"coordinates":[130.426941,32.210476],"type":"Point"}
}