{
  "type": "Feature",
  "properties": {
    "gn:admin1_code":"3.0",
    "gn:admin2_code":"7439944.0",
    "gn:asciiname":"Enoshima",
    "gn:country_code":"JP",
    "gn:dem":13,
    "gn:feature_class":"P",
    "gn:feature_code":"PPL",
    "gn:name":"Enoshima",
    "gn:population":0,
    "gn:timezone":"Asia/Tokyo",
    "iso:country":"JP",
    "name:jbn_x_preferred":[
        "Enoshima"
    ],
    "name:jpn_x_preferred":[
        "\u6c5f\u91ce\u5cf6"
    ],
    "name:jpn_x_variant":[
        "\u3048\u306e\u3057\u307e",
        "\u30a8\u30ce\u30b7\u30de"
    ],
    "wof:name":"Enoshima",
    "wof:placetype":"locality"
},
  "geometry": {"coordinates":[140.33234999999999,40.86064],"type":"Point"}
}