{
  "type": "Feature",
  "properties": {
    "gn:admin1_code":"3.0",
    "gn:admin2_code":"7439944.0",
    "gn:asciiname":"Enoshima",
    "gn:country_code":"JP",
    "gn:dem":13,
    "gn:feature_class":"P",
    "gn:feature_code":"PPL",
    "gn:name":"Enoshima",
    "gn:population":0,
    "gn:timezone":"Asia/Tokyo",
    "iso:country":"JP",
    "name:aze_x_preferred":[
        "Eno\u015fima"
    ],
    "name:ceb_x_preferred":[
        "Eno-shima"
    ],
    "name:deu_x_preferred":[
        "Enoshima"
    ],
    "name:est_x_preferred":[
        "Enoshima"
    ],
    "name:fas_x_preferred":[
        "\u0627\u0646\u0648\u0634\u06cc\u0645\u0627"
    ],
    "name:fra_x_preferred":[
        "Eno-shima"
    ],
    "name:hun_x_preferred":[
        "Enosima"
    ],
    "name:ita_x_preferred":[
        "Enoshima"
    ],
    "name:jbn_x_preferred":[
        "Enoshima"
    ],
    "name:jpn_x_preferred":[
        "\u6c5f\u91ce\u5cf6"
    ],
    "name:jpn_x_variant":[
        "\u3048\u306e\u3057\u307e",
        "\u30a8\u30ce\u30b7\u30de",
        "\u6c5f\u306e\u5cf6"
    ],
    "name:kor_x_preferred":[
        "\uc5d0\ub178\uc12c"
    ],
    "name:lit_x_preferred":[
        "Eno\u0161ima"
    ],
    "name:nor_x_preferred":[
        "Enoshima"
    ],
    "name:ron_x_preferred":[
        "Enoshima"
    ],
    "name:rus_x_preferred":[
        "\u042d\u043d\u043e\u0441\u0438\u043c\u0430"
    ],
    "name:spa_x_preferred":[
        "Enoshima"
    ],
    "name:tha_x_preferred":[
        "\u0e40\u0e2d\u0e42\u0e19\u0e0a\u0e34\u0e21\u0e30"
    ],
    "name:tur_x_preferred":[
        "Enoshima"
    ],
    "name:zho_x_preferred":[
        "\u6c5f\u4e4b\u5cf6"
    ],
    "wof:name":"Enoshima",
    "wof:placetype":"locality"
},
  "geometry": {"coordinates":[140.33234999999999,40.86064],"type":"Point"}
}