{
  "type": "Feature",
  "properties": {
    "gn:admin1_code":"13",
    "gn:admin2_code":"1862625.0",
    "gn:asciiname":"Shikamaku-miya",
    "gn:country_code":"JP",
    "gn:dem":4,
    "gn:feature_class":"P",
    "gn:feature_code":"PPL",
    "gn:name":"Shikamaku-miya",
    "gn:population":0,
    "gn:timezone":"Asia/Tokyo",
    "iso:country":"JP",
    "name:jpn_x_preferred":[
        "\u98fe\u78e8\u533a\u5bae"
    ],
    "name:und_x_variant":[
        "Shikama",
        "Shikamach\u014d",
        "Miya",
        "Shikamaku-miya"
    ],
    "wof:name":"Shikamaku-miya",
    "wof:placetype":"locality"
},
  "geometry": {"coordinates":[134.6694,34.79465],"type":"Point"}
}