{
  "type": "Feature",
  "properties": {
    "gn:admin1_code":"6.0",
    "gn:admin2_code":"1863982.0",
    "gn:asciiname":"Takayanagicho",
    "gn:country_code":"JP",
    "gn:dem":13,
    "gn:feature_class":"P",
    "gn:feature_code":"PPL",
    "gn:name":"Takayanagich\u014d",
    "gn:population":0,
    "gn:timezone":"Asia/Tokyo",
    "iso:country":"JP",
    "name:jpn_x_preferred":[
        "\u9ad8\u67f3\u753a"
    ],
    "name:und_x_variant":[
        "Takayanagich\u014d"
    ],
    "wof:name":"Takayanagicho",
    "wof:placetype":"locality"
},
  "geometry": {"coordinates":[136.24191999999999,36.09614000000001],"type":"Point"}
}