{
  "type": "Feature",
  "properties": {
    "gn:admin1_code":"34.0",
    "gn:admin2_code":"1849187.0",
    "gn:admin3_code":"11104.0",
    "gn:asciiname":"Sasamaru",
    "gn:country_code":"JP",
    "gn:dem":13,
    "gn:feature_class":"P",
    "gn:feature_code":"PPL",
    "gn:name":"Sasamaru",
    "gn:population":0,
    "gn:timezone":"Asia/Tokyo",
    "iso:country":"JP",
    "name:jpn_x_preferred":[
        "\u7b39\u4e38"
    ],
    "name:jpn_x_variant":[
        "\u3055\u3055\u307e\u308b",
        "\u30b5\u30b5\u30de\u30eb"
    ],
    "wof:name":"Sasamaru",
    "wof:placetype":"locality"
},
  "geometry": {"coordinates":[139.67601000000002,35.91251],"type":"Point"}
}