{
  "type": "Feature",
  "properties": {
    "gn:admin1_code":"40.0",
    "gn:admin2_code":"1851451.0",
    "gn:asciiname":"Kotobashi",
    "gn:country_code":"JP",
    "gn:dem":9,
    "gn:feature_class":"P",
    "gn:feature_code":"PPL",
    "gn:name":"K\u014dt\u014dbashi",
    "gn:population":0,
    "gn:timezone":"Asia/Tokyo",
    "iso:country":"JP",
    "name:jpn_x_preferred":[
        "\u6c5f\u6771\u6a4b"
    ],
    "name:und_x_variant":[
        "K\u014dt\u014dbashi"
    ],
    "wof:name":"Kotobashi",
    "wof:placetype":"locality"
},
  "geometry": {"coordinates":[139.81083000000001,35.69341],"type":"Point"}
}