{
  "type": "Feature",
  "properties": {
    "gn:admin1_code":"21.0",
    "gn:admin2_code":"7413150.0",
    "gn:asciiname":"Sabaru",
    "gn:country_code":"JP",
    "gn:dem":292,
    "gn:feature_class":"P",
    "gn:feature_code":"PPLL",
    "gn:name":"Sabaru",
    "gn:population":0,
    "gn:timezone":"Asia/Tokyo",
    "iso:country":"JP",
    "name:jpn_x_preferred":[
        "\u4f50\u539f"
    ],
    "name:jpn_x_variant":[
        "\u3055\u3070\u308b",
        "\u30b5\u30d0\u30eb"
    ],
    "wof:name":"Sabaru",
    "wof:placetype":"locality"
},
  "geometry": {"coordinates":[130.79353999999998,33.07549],"type":"Point"}
}