{
  "type": "Feature",
  "properties": {
    "gn:admin1_code":"07",
    "gn:admin2_code":"1848578.0",
    "gn:asciiname":"Miyano'o",
    "gn:country_code":"JP",
    "gn:dem":342,
    "gn:feature_class":"P",
    "gn:feature_code":"PPL",
    "gn:name":"Miyano\u2019o",
    "gn:population":0,
    "gn:timezone":"Asia/Tokyo",
    "iso:country":"JP",
    "name:jpn_x_preferred":[
        "\u5bae\u30ce\u5c3e"
    ],
    "name:und_x_variant":[
        "Kitayabe",
        "Miyanoo",
        "Miyano\u2019o"
    ],
    "wof:name":"Miyano'o",
    "wof:placetype":"locality"
},
  "geometry": {"coordinates":[130.82254,33.15016],"type":"Point"}
}