{
  "type": "Feature",
  "properties": {
    "gn:admin1_code":"19.0",
    "gn:admin2_code":"1862461.0",
    "gn:asciiname":"Hitofue",
    "gn:country_code":"JP",
    "gn:dem":80,
    "gn:feature_class":"P",
    "gn:feature_code":"PPLL",
    "gn:name":"Hitofue",
    "gn:population":0,
    "gn:timezone":"Asia/Tokyo",
    "iso:country":"JP",
    "name:jpn_x_preferred":[
        "\u4eba\u5897"
    ],
    "wof:name":"Hitofue",
    "wof:placetype":"locality"
},
  "geometry": {"coordinates":[139.27194,35.34697],"type":"Point"}
}