{
  "type": "Feature",
  "properties": {
    "gn:admin1_code":"25",
    "gn:admin2_code":"1858599.0",
    "gn:admin3_code":"45403.0",
    "gn:asciiname":"Yokodani",
    "gn:cc2":"JP",
    "gn:country_code":"JP",
    "gn:dem":949,
    "gn:feature_class":"P",
    "gn:feature_code":"PPL",
    "gn:name":"Yokodani",
    "gn:population":0,
    "gn:timezone":"Asia/Tokyo",
    "iso:country":"JP",
    "name:und_x_variant":[
        "Yunotani",
        "Yokotani",
        "Yokodani"
    ],
    "wof:name":"Yokodani",
    "wof:placetype":"locality"
},
  "geometry": {"coordinates":[131.05000000000001,32.25],"type":"Point"}
}