{
  "type": "Feature",
  "properties": {
    "gn:admin1_code":"47",
    "gn:admin2_code":"1855990.0",
    "gn:admin3_code":"47324.0",
    "gn:asciiname":"Takashiho",
    "gn:country_code":"JP",
    "gn:dem":89,
    "gn:feature_class":"P",
    "gn:feature_code":"PPL",
    "gn:name":"Takashiho",
    "gn:population":0,
    "gn:timezone":"Asia/Tokyo",
    "iso:country":"JP",
    "name:jpn_x_preferred":[
        "\u9ad8\u5fd7\u4fdd"
    ],
    "name:und_x_variant":[
        "Takashipo",
        "Takashippo",
        "Takashippu"
    ],
    "wof:name":"Takashiho",
    "wof:placetype":"locality"
},
  "geometry": {"coordinates":[127.73439999999999,26.41134000000001],"type":"Point"}
}