{
  "type": "Feature",
  "properties": {
    "gn:admin1_code":"8.0",
    "gn:admin2_code":"7451488.0",
    "gn:admin3_code":"7547.0",
    "gn:asciiname":"Sakai",
    "gn:country_code":"JP",
    "gn:dem":21,
    "gn:feature_class":"P",
    "gn:feature_code":"PPL",
    "gn:name":"Sakai",
    "gn:population":0,
    "gn:timezone":"Asia/Tokyo",
    "iso:country":"JP",
    "name:jpn_x_preferred":[
        "\u9152\u4e95"
    ],
    "wof:name":"Sakai",
    "wof:placetype":"locality"
},
  "geometry": {"coordinates":[140.98740000000001,37.4791],"type":"Point"}
}