{
  "type": "Feature",
  "properties": {
    "gn:admin1_code":"8.0",
    "gn:admin2_code":"7451488.0",
    "gn:admin3_code":"7547.0",
    "gn:asciiname":"Sakai",
    "gn:country_code":"JP",
    "gn:dem":21,
    "gn:feature_class":"P",
    "gn:feature_code":"PPL",
    "gn:name":"Sakai",
    "gn:population":0,
    "gn:timezone":"Asia/Tokyo",
    "iso:country":"JP",
    "name:ara_x_preferred":[
        "\u0633\u0627\u0643\u0627\u064a"
    ],
    "name:bel_x_preferred":[
        "\u0421\u0430\u043a\u0430\u0456"
    ],
    "name:bre_x_preferred":[
        "Sakai"
    ],
    "name:bul_x_preferred":[
        "\u0421\u0430\u043a\u0430\u0438"
    ],
    "name:cat_x_preferred":[
        "Sakai"
    ],
    "name:ceb_x_preferred":[
        "Sakai Ku"
    ],
    "name:ces_x_preferred":[
        "Sakai"
    ],
    "name:cym_x_preferred":[
        "Sakai"
    ],
    "name:deu_x_preferred":[
        "Sakai"
    ],
    "name:epo_x_preferred":[
        "Sakaj"
    ],
    "name:est_x_preferred":[
        "Sakai"
    ],
    "name:eus_x_preferred":[
        "Sakai"
    ],
    "name:fas_x_preferred":[
        "\u0633\u0627\u06a9\u0627\u06cc"
    ],
    "name:fin_x_preferred":[
        "Sakai"
    ],
    "name:fra_x_preferred":[
        "Sakai"
    ],
    "name:gle_x_preferred":[
        "Sakai"
    ],
    "name:glg_x_preferred":[
        "Sakai"
    ],
    "name:heb_x_preferred":[
        "\u05e1\u05d0\u05e7\u05d0\u05d9"
    ],
    "name:hye_x_preferred":[
        "\u054d\u0561\u056f\u0561\u056b"
    ],
    "name:ind_x_preferred":[
        "Sakai"
    ],
    "name:ita_x_preferred":[
        "Sakai"
    ],
    "name:jpn_x_preferred":[
        "\u9152\u4e95"
    ],
    "name:kik_x_preferred":[
        "Sakai"
    ],
    "name:kor_x_preferred":[
        "\uc0ac\uce74\uc774\uc2dc"
    ],
    "name:lat_x_preferred":[
        "Sacaium"
    ],
    "name:lit_x_preferred":[
        "Sakajus"
    ],
    "name:mlg_x_preferred":[
        "Sakai"
    ],
    "name:mon_x_preferred":[
        "\u0421\u0430\u043a\u0430\u0439"
    ],
    "name:msa_x_preferred":[
        "Sakai"
    ],
    "name:nld_x_preferred":[
        "Sakai"
    ],
    "name:nor_x_preferred":[
        "Sakai"
    ],
    "name:pol_x_preferred":[
        "Sakai"
    ],
    "name:por_x_preferred":[
        "Sakai"
    ],
    "name:ron_x_preferred":[
        "Sakai"
    ],
    "name:rus_x_preferred":[
        "\u0421\u0430\u043a\u0430\u0438"
    ],
    "name:sah_x_preferred":[
        "\u0421\u0430\u043a\u0430\u0438"
    ],
    "name:sco_x_preferred":[
        "Sakai"
    ],
    "name:slk_x_preferred":[
        "Sakai"
    ],
    "name:spa_x_preferred":[
        "Sakai"
    ],
    "name:srp_x_preferred":[
        "\u0421\u0430\u043a\u0430\u0458"
    ],
    "name:sun_x_preferred":[
        "Sakai"
    ],
    "name:swe_x_preferred":[
        "Sakai"
    ],
    "name:tgk_x_preferred":[
        "\u0421\u0430\u043a\u0430\u0438"
    ],
    "name:tgl_x_preferred":[
        "Sakai"
    ],
    "name:tha_x_preferred":[
        "\u0e0b\u0e32\u0e44\u0e01"
    ],
    "name:tum_x_preferred":[
        "Sakai"
    ],
    "name:tur_x_preferred":[
        "Sakai"
    ],
    "name:ukr_x_preferred":[
        "\u0421\u0430\u043a\u0430\u0439"
    ],
    "name:urd_x_preferred":[
        "\u0633\u0627\u06a9\u0627\u0626\u06cc"
    ],
    "name:vie_x_preferred":[
        "Sakai"
    ],
    "name:war_x_preferred":[
        "Sakai"
    ],
    "wof:name":"Sakai",
    "wof:placetype":"locality"
},
  "geometry": {"coordinates":[140.98740000000001,37.4791],"type":"Point"}
}