{
  "type": "Feature",
  "properties": {
    "gn:admin1_code":"9.0",
    "gn:admin2_code":"7418820.0",
    "gn:admin3_code":"21604.0",
    "gn:asciiname":"Hatotani",
    "gn:country_code":"JP",
    "gn:dem":483,
    "gn:feature_class":"P",
    "gn:feature_code":"PPL",
    "gn:name":"Hatotani",
    "gn:population":0,
    "gn:timezone":"Asia/Tokyo",
    "iso:country":"JP",
    "name:jpn_x_preferred":[
        "\u9ce9\u8c37"
    ],
    "wof:name":"Hatotani",
    "wof:placetype":"locality"
},
  "geometry": {"coordinates":[136.89926,36.26878],"type":"Point"}
}