{
  "type": "Feature",
  "properties": {
    "gn:admin1_code":"21.0",
    "gn:admin2_code":"1850743.0",
    "gn:asciiname":"Choho",
    "gn:country_code":"JP",
    "gn:dem":1,
    "gn:feature_class":"P",
    "gn:feature_code":"PPLL",
    "gn:name":"Ch\u014dho",
    "gn:population":0,
    "gn:timezone":"Asia/Tokyo",
    "iso:country":"JP",
    "name:jpn_x_preferred":[
        "\u9577\u4fdd"
    ],
    "name:jpn_x_variant":[
        "\u3061\u3087\u3046\u307b",
        "\u30c1\u30e7\u30a6\u30db"
    ],
    "name:und_x_variant":[
        "Ch\u014dho"
    ],
    "wof:name":"Choho",
    "wof:placetype":"locality"
},
  "geometry": {"coordinates":[130.50683000000001,32.8987],"type":"Point"}
}