{
  "type": "Feature",
  "properties": {
    "gn:admin1_code":"29.0",
    "gn:admin2_code":"7468177.0",
    "gn:asciiname":"Nukuide",
    "gn:country_code":"JP",
    "gn:dem":15,
    "gn:feature_class":"P",
    "gn:feature_code":"PPL",
    "gn:name":"Nukuide",
    "gn:population":0,
    "gn:timezone":"Asia/Tokyo",
    "iso:country":"JP",
    "name:jpn_x_preferred":[
        "\u6e29\u51fa"
    ],
    "wof:name":"Nukuide",
    "wof:placetype":"locality"
},
  "geometry": {"coordinates":[139.55301,38.51406],"type":"Point"}
}