{
  "type": "Feature",
  "properties": {
    "gn:admin1_code":"16.0",
    "gn:admin2_code":"2111883.0",
    "gn:asciiname":"Kanehama",
    "gn:country_code":"JP",
    "gn:dem":10,
    "gn:feature_class":"P",
    "gn:feature_code":"PPL",
    "gn:name":"Kanehama",
    "gn:population":0,
    "gn:timezone":"Asia/Tokyo",
    "iso:country":"JP",
    "wof:name":"Kanehama",
    "wof:placetype":"locality"
},
  "geometry": {"coordinates":[141.95500000000001,39.58333],"type":"Point"}
}