{
  "type": "Feature",
  "properties": {
    "gn:admin1_code":"3.0",
    "gn:admin2_code":"8534376.0",
    "gn:admin3_code":"2323.0",
    "gn:asciiname":"Naeshirozawa",
    "gn:country_code":"JP",
    "gn:dem":22,
    "gn:feature_class":"P",
    "gn:feature_code":"PPLL",
    "gn:name":"Naeshirozawa",
    "gn:population":0,
    "gn:timezone":"Asia/Tokyo",
    "iso:country":"JP",
    "name:jpn_x_preferred":[
        "\u82d7\u4ee3\u6ca2"
    ],
    "name:jpn_x_variant":[
        "\u306a\u3048\u3057\u308d\u3056\u308f",
        "\u30ca\u30a8\u30b7\u30ed\u30b6\u30ef"
    ],
    "wof:name":"Naeshirozawa",
    "wof:placetype":"locality"
},
  "geometry": {"coordinates":[139.93221,40.65255],"type":"Point"}
}