{
  "type": "Feature",
  "properties": {
    "gn:admin1_code":"12.0",
    "gn:admin2_code":"7428103.0",
    "gn:admin3_code":"1602.0",
    "gn:asciiname":"Asahi",
    "gn:country_code":"JP",
    "gn:dem":154,
    "gn:feature_class":"P",
    "gn:feature_code":"PPL",
    "gn:name":"Asahi",
    "gn:population":0,
    "gn:timezone":"Asia/Tokyo",
    "iso:country":"JP",
    "name:jpn_x_preferred":[
        "\u65ed"
    ],
    "wof:name":"Asahi",
    "wof:placetype":"locality"
},
  "geometry": {"coordinates":[142.35085000000001,42.64755],"type":"Point"}
}