{
  "type": "Feature",
  "properties": {
    "gn:admin1_code":"21.0",
    "gn:admin2_code":"1865358.0",
    "gn:asciiname":"Amakusamachi-takahamaminami",
    "gn:country_code":"JP",
    "gn:dem":74,
    "gn:feature_class":"P",
    "gn:feature_code":"PPL",
    "gn:name":"Amakusamachi-takahamaminami",
    "gn:population":0,
    "gn:timezone":"Asia/Tokyo",
    "iso:country":"JP",
    "name:jpn_x_preferred":[
        "\u5929\u8349\u753a\u9ad8\u6d5c\u5357"
    ],
    "name:jpn_x_variant":[
        "\u3042\u307e\u304f\u3055\u307e\u3061\u305f\u304b\u306f\u307e\u307f\u306a\u307f",
        "\u30a2\u30de\u30af\u30b5\u30de\u30c1\u30bf\u30ab\u30cf\u30de\u30df\u30ca\u30df"
    ],
    "wof:name":"Amakusamachi-takahamaminami",
    "wof:placetype":"locality"
},
  "geometry": {"coordinates":[129.99771999999999,32.36795],"type":"Point"}
}