{
  "type": "Feature",
  "properties": {
    "gn:admin1_code":"19.0",
    "gn:admin2_code":"1864864.0",
    "gn:asciiname":"Kitayama",
    "gn:country_code":"JP",
    "gn:dem":43,
    "gn:feature_class":"P",
    "gn:feature_code":"PPLL",
    "gn:name":"Kitayama",
    "gn:population":0,
    "gn:timezone":"Asia/Tokyo",
    "iso:country":"JP",
    "name:jpn_x_preferred":[
        "\u5317\u5c71"
    ],
    "wof:name":"Kitayama",
    "wof:placetype":"locality"
},
  "geometry": {"coordinates":[139.42032,35.43067],"type":"Point"}
}