{
  "type": "Feature",
  "properties": {
    "iso:country":"JP",
    "name:eng_x_preferred":[
        "Azuchimachi 1 Chome"
    ],
    "name:eng_x_variant":[
        "Azuchimachi 1 Choume",
        "Azuchimachi 1 Chome"
    ],
    "name:jpn_x_preferred":[
        "\uff11\u4e01\u76ee"
    ],
    "name:jpn_x_variant":[
        "\u3042\u3065\u3061\u307e\u3061 \uff11\u3061\u3087\u3046\u3081",
        "\u5b89\u571f\u753a \uff11\u4e01\u76ee",
        "\uff11\u3061\u3087\u3046\u3081"
    ],
    "qs:gn_local":0,
    "qs:local_max":5466,
    "qs:local_sum":82256,
    "qs:localhoods":141,
    "qs:name":"\uff11\u4e01\u76ee",
    "qs:name_adm0":"\u65e5\u672c",
    "qs:name_adm1":"\u5927\u962a\u5e9c",
    "qs:name_adm2":"\u4e2d\u592e\u533a",
    "qs:name_en":"Azuchimachi 1 Chome",
    "qs:name_lau":"\u5b89\u571f\u753a",
    "qs:name_local":"\u5927\u962a\u5e02",
    "qs:photo_max":326,
    "qs:photo_sum":723,
    "qs:photos":389,
    "qs:photos_1k":79,
    "qs:photos_9k":2,
    "qs:photos_9r":5,
    "qs:photos_all":389,
    "qs:photos_sr":6,
    "qs:placetype":"Suburb",
    "qs:pop_sr":"0",
    "qs:quad_count":19,
    "qs:woe_adm0":23424856,
    "qs:woe_adm1":2345881,
    "qs:woe_adm2":1118622,
    "qs:woe_lau":28457609,
    "qs:woe_local":15015370,
    "qs:woe_ver":"7.10.0",
    "qs_pg:name":"\uff11\u4e01\u76ee",
    "qs_pg:name_adm0":"\u65e5\u672c",
    "qs_pg:name_adm1":"\u5927\u962a\u5e9c",
    "qs_pg:photos":32,
    "qs_pg:photos_1k":6,
    "qs_pg:photos_9k":1,
    "qs_pg:photos_9r":2,
    "qs_pg:photos_all":32,
    "qs_pg:photos_sr":2,
    "qs_pg:pop_sr":0,
    "qs_pg:qs_pg_placetype":"neighbourhood",
    "qs_pg:qs_pg_placetype_gp":"Suburb",
    "qs_pg:woe_adm0":23424856,
    "woe:adm0_id":23424856,
    "woe:name_adm0":"\u65e5\u672c",
    "woe:name_adm1":"\u5927\u962a\u5e9c",
    "woe:placetype":"Suburb",
    "wof:lang":[
        "jpn"
    ],
    "wof:name":"\uff11\u4e01\u76ee",
    "wof:placetype":"neighbourhood"
},
  "geometry": {"coordinates":[135.50839300000001,34.683055],"type":"Point"}
}