{
  "type": "Feature",
  "properties": {
    "gn:admin1_code":"8.0",
    "gn:admin2_code":"7451502.0",
    "gn:admin3_code":"7504.0",
    "gn:asciiname":"Satoshiraishi",
    "gn:country_code":"JP",
    "gn:dem":323,
    "gn:feature_class":"P",
    "gn:feature_code":"PPL",
    "gn:name":"Satoshiraishi",
    "gn:population":0,
    "gn:timezone":"Asia/Tokyo",
    "iso:country":"JP",
    "name:jpn_x_preferred":[
        "\u91cc\u767d\u77f3"
    ],
    "wof:name":"Satoshiraishi",
    "wof:placetype":"locality"
},
  "geometry": {"coordinates":[140.42216999999999,37.10565],"type":"Point"}
}