{
  "type": "Feature",
  "properties": {
    "gn:admin1_code":"3.0",
    "gn:admin2_code":"2130654.0",
    "gn:asciiname":"Midori",
    "gn:country_code":"JP",
    "gn:dem":5,
    "gn:feature_class":"P",
    "gn:feature_code":"PPL",
    "gn:name":"Midori",
    "gn:population":0,
    "gn:timezone":"Asia/Tokyo",
    "iso:country":"JP",
    "name:jpn_x_preferred":[
        "\u7dd1"
    ],
    "name:jpn_x_variant":[
        "\u307f\u3069\u308a",
        "\u30df\u30c9\u30ea"
    ],
    "wof:name":"Midori",
    "wof:placetype":"locality"
},
  "geometry": {"coordinates":[140.74847,40.80689],"type":"Point"}
}