{
  "type": "Feature",
  "properties": {
    "gn:admin1_code":"09",
    "gn:admin2_code":"1863645.0",
    "gn:asciiname":"Osaka",
    "gn:cc2":"JP",
    "gn:country_code":"JP",
    "gn:dem":568,
    "gn:feature_class":"P",
    "gn:feature_code":"PPL",
    "gn:name":"Osaka",
    "gn:population":0,
    "gn:timezone":"Asia/Tokyo",
    "iso:country":"JP",
    "name:und_x_variant":[
        "Kosaka",
        "Osaka"
    ],
    "wof:name":"Osaka",
    "wof:placetype":"locality"
},
  "geometry": {"coordinates":[137.26667,35.95],"type":"Point"}
}