{
  "type": "Feature",
  "properties": {
    "gn:admin1_code":"32.0",
    "gn:admin2_code":"1862751.0",
    "gn:asciiname":"Shijocho",
    "gn:country_code":"JP",
    "gn:dem":22,
    "gn:feature_class":"P",
    "gn:feature_code":"PPL",
    "gn:name":"Shij\u014dch\u014d",
    "gn:population":0,
    "gn:timezone":"Asia/Tokyo",
    "iso:country":"JP",
    "name:jpn_x_preferred":[
        "\u56db\u6761\u753a"
    ],
    "name:und_x_variant":[
        "Shij\u014dch\u014d"
    ],
    "wof:name":"Shijocho",
    "wof:placetype":"locality"
},
  "geometry": {"coordinates":[135.64285000000001,34.65804],"type":"Point"}
}