{
  "type": "Feature",
  "properties": {
    "iso:country":"JP",
    "name:eng_x_preferred":[
        "Tachibana 1 Chome"
    ],
    "name:eng_x_variant":[
        "Tachibana 1 Choume",
        "Tachibana 1 Chome"
    ],
    "name:jpn_x_preferred":[
        "\uff11\u4e01\u76ee"
    ],
    "name:jpn_x_variant":[
        "\u305f\u3061\u3070\u306a \uff11\u3061\u3087\u3046\u3081",
        "\u7acb\u82b1 \uff11\u4e01\u76ee",
        "\uff11\u3061\u3087\u3046\u3081"
    ],
    "name:unk_x_variant":[
        "\uff11\u4e01\u76ee"
    ],
    "qs:gn_local":0,
    "qs:local_max":8,
    "qs:local_sum":8,
    "qs:localhoods":1,
    "qs:name":"\uff11\u4e01\u76ee",
    "qs:name_adm0":"\u65e5\u672c",
    "qs:name_adm1":"\u9759\u5ca1\u770c",
    "qs:name_en":"Tachibana 1 Chome",
    "qs:name_lau":"\u7acb\u82b1",
    "qs:name_local":"\u4f0a\u8c46\u306e\u56fd\u5e02",
    "qs:photo_max":3,
    "qs:photo_sum":8,
    "qs:placetype":"Suburb",
    "qs:quad_count":6,
    "qs:woe_adm0":23424856,
    "qs:woe_adm1":2345886,
    "qs:woe_adm2":0,
    "qs:woe_lau":28438572,
    "qs:woe_local":28379227,
    "qs:woe_ver":"7.10.0",
    "wof:lang":[
        "jpn"
    ],
    "wof:name":"\uff11\u4e01\u76ee",
    "wof:placetype":"neighbourhood"
},
  "geometry": {"coordinates":[138.93997200000001,35.023811],"type":"Point"}
}