{
  "type": "Feature",
  "properties": {
    "gn:admin1_code":"21.0",
    "gn:admin2_code":"1850744.0",
    "gn:admin3_code":"43369.0",
    "gn:asciiname":"Okubo",
    "gn:country_code":"JP",
    "gn:dem":37,
    "gn:feature_class":"P",
    "gn:feature_code":"PPLL",
    "gn:name":"\u014ckubo",
    "gn:population":0,
    "gn:timezone":"Asia/Tokyo",
    "iso:country":"JP",
    "name:jpn_x_preferred":[
        "\u5927\u4e45\u4fdd"
    ],
    "name:jpn_x_variant":[
        "\u304a\u304a\u304f\u307c",
        "\u30aa\u30aa\u30af\u30dc"
    ],
    "name:und_x_variant":[
        "\u014ckubo"
    ],
    "wof:name":"Okubo",
    "wof:placetype":"locality"
},
  "geometry": {"coordinates":[130.61635000000001,33.00789],"type":"Point"}
}