{
  "type": "Feature",
  "properties": {
    "gn:admin1_code":"25",
    "gn:admin2_code":"1862036.0",
    "gn:asciiname":"Nakazaki",
    "gn:cc2":"JP",
    "gn:country_code":"JP",
    "gn:dem":199,
    "gn:feature_class":"P",
    "gn:feature_code":"PPL",
    "gn:name":"Nakazaki",
    "gn:population":0,
    "gn:timezone":"Asia/Tokyo",
    "iso:country":"JP",
    "name:und_x_variant":[
        "Nakasaki",
        "Nakazaki"
    ],
    "wof:name":"Nakazaki",
    "wof:placetype":"locality"
},
  "geometry": {"coordinates":[131.43333000000001,32.35],"type":"Point"}
}