{
  "type": "Feature",
  "properties": {
    "gn:admin1_code":"5.0",
    "gn:admin2_code":"1855138.0",
    "gn:admin3_code":"38442.0",
    "gn:asciiname":"Inoura",
    "gn:country_code":"JP",
    "gn:dem":10,
    "gn:feature_class":"P",
    "gn:feature_code":"PPL",
    "gn:name":"Inoura",
    "gn:population":0,
    "gn:timezone":"Asia/Tokyo",
    "iso:country":"JP",
    "wof:name":"Inoura",
    "wof:placetype":"locality"
},
  "geometry": {"coordinates":[132.11158,33.37082],"type":"Point"}
}