{
  "type": "Feature",
  "properties": {
    "gn:admin1_code":"12.0",
    "gn:admin2_code":"7428115.0",
    "gn:admin3_code":"1552.0",
    "gn:asciiname":"Eidaicho",
    "gn:country_code":"JP",
    "gn:dem":33,
    "gn:feature_class":"P",
    "gn:feature_code":"PPL",
    "gn:name":"Eidaich\u014d",
    "gn:population":0,
    "gn:timezone":"Asia/Tokyo",
    "iso:country":"JP",
    "name:eng_x_preferred":[
        "Naka-saroma"
    ],
    "name:jpn_x_preferred":[
        "\u6c38\u4ee3\u753a"
    ],
    "name:jpn_x_variant":[
        "\u3048\u3044\u3060\u3044\u3061\u3087\u3046",
        "\u30a8\u30a4\u30c0\u30a4\u30c1\u30e7\u30a6"
    ],
    "name:rus_x_preferred":[
        "\u0421\u0430\u0440\u043e\u043c\u0430"
    ],
    "name:und_x_variant":[
        "Eidaich\u014d",
        "Saroma",
        "Naka-saroma"
    ],
    "wof:name":"Eidaicho",
    "wof:placetype":"locality"
},
  "geometry": {"coordinates":[143.77444,44.00944000000001],"type":"Point"}
}