{
  "type": "Feature",
  "properties": {
    "gn:admin1_code":"12.0",
    "gn:admin2_code":"7428115.0",
    "gn:admin3_code":"1552.0",
    "gn:asciiname":"Eidaicho",
    "gn:country_code":"JP",
    "gn:dem":33,
    "gn:feature_class":"P",
    "gn:feature_code":"PPL",
    "gn:name":"Eidaich\u014d",
    "gn:population":0,
    "gn:timezone":"Asia/Tokyo",
    "iso:country":"JP",
    "name:ceb_x_preferred":[
        "Saroma Ch\u014d"
    ],
    "name:eng_x_preferred":[
        "Naka-saroma"
    ],
    "name:fas_x_preferred":[
        "\u0633\u0627\u0631\u0648\u0645\u0627"
    ],
    "name:fra_x_preferred":[
        "Saroma"
    ],
    "name:ido_x_preferred":[
        "Saroma"
    ],
    "name:ita_x_preferred":[
        "Saroma"
    ],
    "name:jpn_x_preferred":[
        "\u6c38\u4ee3\u753a"
    ],
    "name:jpn_x_variant":[
        "\u3048\u3044\u3060\u3044\u3061\u3087\u3046",
        "\u30a8\u30a4\u30c0\u30a4\u30c1\u30e7\u30a6",
        "\u4f50\u5442\u9593\u753a"
    ],
    "name:kor_x_preferred":[
        "\uc0ac\ub85c\ub9c8\uc815"
    ],
    "name:msa_x_preferred":[
        "Saroma"
    ],
    "name:mya_x_preferred":[
        "\u1006\u101b\u102d\u102f\u1019\u1019\u103c\u102d\u102f\u1037\u104a \u101f\u1031\u102c\u1037\u1000\u102d\u102f\u1004\u103a\u1038\u1012\u102d\u102f\u1038"
    ],
    "name:rus_x_preferred":[
        "\u0421\u0430\u0440\u043e\u043c\u0430"
    ],
    "name:tgl_x_preferred":[
        "Saroma"
    ],
    "name:ukr_x_preferred":[
        "\u0421\u0430\u0440\u043e\u043c\u0430"
    ],
    "name:und_x_variant":[
        "Eidaich\u014d",
        "Saroma",
        "Naka-saroma"
    ],
    "name:zho_x_preferred":[
        "\u4f50\u5442\u9593\u753a"
    ],
    "wof:name":"Eidaicho",
    "wof:placetype":"locality"
},
  "geometry": {"coordinates":[143.77444,44.00944000000001],"type":"Point"}
}