{
  "type": "Feature",
  "properties": {
    "gn:admin1_code":"3.0",
    "gn:admin2_code":"2129754.0",
    "gn:admin3_code":"2405.0",
    "gn:asciiname":"Niguchi",
    "gn:country_code":"JP",
    "gn:dem":39,
    "gn:feature_class":"P",
    "gn:feature_code":"PPL",
    "gn:name":"Niguchi",
    "gn:population":0,
    "gn:timezone":"Asia/Tokyo",
    "iso:country":"JP",
    "name:jpn_x_preferred":[
        "\u5165\u53e3"
    ],
    "name:jpn_x_variant":[
        "\u306b\u3050\u3061",
        "\u30cb\u30b0\u30c1"
    ],
    "wof:name":"Niguchi",
    "wof:placetype":"locality"
},
  "geometry": {"coordinates":[141.32494,40.57252],"type":"Point"}
}