{
  "type": "Feature",
  "properties": {
    "gn:admin1_code":"33.0",
    "gn:admin2_code":"7391355.0",
    "gn:asciiname":"Tsutsumiishi",
    "gn:country_code":"JP",
    "gn:dem":200,
    "gn:feature_class":"P",
    "gn:feature_code":"PPLL",
    "gn:name":"Tsutsumiishi",
    "gn:population":0,
    "gn:timezone":"Asia/Tokyo",
    "iso:country":"JP",
    "name:jpn_x_preferred":[
        "\u5305\u77f3"
    ],
    "wof:name":"Tsutsumiishi",
    "wof:placetype":"locality"
},
  "geometry": {"coordinates":[129.88058999999998,33.32496],"type":"Point"}
}