{
  "type": "Feature",
  "properties": {
    "gn:admin1_code":"25.0",
    "gn:admin2_code":"7413970.0",
    "gn:asciiname":"Taneda",
    "gn:country_code":"JP",
    "gn:dem":240,
    "gn:feature_class":"P",
    "gn:feature_code":"PPLL",
    "gn:name":"Taneda",
    "gn:population":0,
    "gn:timezone":"Asia/Tokyo",
    "iso:country":"JP",
    "name:jpn_x_preferred":[
        "\u7a2e\u5b50\u7530"
    ],
    "name:jpn_x_variant":[
        "\u305f\u306d\u3060",
        "\u30bf\u30cd\u30c0"
    ],
    "wof:name":"Taneda",
    "wof:placetype":"locality"
},
  "geometry": {"coordinates":[130.95639,32.0093],"type":"Point"}
}