{
  "type": "Feature",
  "properties": {
    "gn:admin1_code":"19.0",
    "gn:admin2_code":"1859635.0",
    "gn:admin3_code":"14131.0",
    "gn:asciiname":"Asada",
    "gn:country_code":"JP",
    "gn:dem":2,
    "gn:feature_class":"P",
    "gn:feature_code":"PPL",
    "gn:name":"Asada",
    "gn:population":0,
    "gn:timezone":"Asia/Tokyo",
    "iso:country":"JP",
    "name:ceb_x_preferred":[
        "Asada"
    ],
    "name:deu_x_preferred":[
        "Asada"
    ],
    "name:fra_x_preferred":[
        "Asada"
    ],
    "name:jpn_x_preferred":[
        "\u6d45\u7530"
    ],
    "name:rus_x_preferred":[
        "\u0410\u0441\u0430\u0434\u0430"
    ],
    "name:swe_x_preferred":[
        "Asada"
    ],
    "name:tgl_x_preferred":[
        "Asada"
    ],
    "wof:name":"Asada",
    "wof:placetype":"locality"
},
  "geometry": {"coordinates":[139.70141999999998,35.5068],"type":"Point"}
}