{
  "type": "Feature",
  "properties": {
    "gn:admin1_code":"3.0",
    "gn:admin2_code":"2128302.0",
    "gn:admin3_code":"2441.0",
    "gn:asciiname":"Toyokawa",
    "gn:country_code":"JP",
    "gn:dem":70,
    "gn:feature_class":"P",
    "gn:feature_code":"PPL",
    "gn:name":"Toyokawa",
    "gn:population":0,
    "gn:timezone":"Asia/Tokyo",
    "iso:country":"JP",
    "name:jpn_x_preferred":[
        "\u8c4a\u5ddd"
    ],
    "name:jpn_x_variant":[
        "\u3068\u3088\u304b\u308f",
        "\u30c8\u30e8\u30ab\u30ef"
    ],
    "wof:name":"Toyokawa",
    "wof:placetype":"locality"
},
  "geometry": {"coordinates":[141.22971000000001,40.36681],"type":"Point"}
}