{
  "type": "Feature",
  "properties": {
    "gn:admin1_code":"17",
    "gn:admin2_code":"1856906.0",
    "gn:asciiname":"Niocho-nio",
    "gn:country_code":"JP",
    "gn:dem":6,
    "gn:feature_class":"P",
    "gn:feature_code":"PPL",
    "gn:name":"Nioch\u014d-nio",
    "gn:population":0,
    "gn:timezone":"Asia/Tokyo",
    "iso:country":"JP",
    "name:jpn_x_preferred":[
        "\u4ec1\u5c3e\u753a\u4ec1\u5c3e"
    ],
    "name:und_x_variant":[
        "Nioch\u014d-nio",
        "Nio"
    ],
    "wof:name":"Niocho-nio",
    "wof:placetype":"locality"
},
  "geometry": {"coordinates":[133.65156000000002,34.19792],"type":"Point"}
}