{
  "type": "Feature",
  "properties": {
    "gn:admin1_code":"37.0",
    "gn:admin2_code":"1851401.0",
    "gn:admin3_code":"22342.0",
    "gn:asciiname":"Hattanda",
    "gn:country_code":"JP",
    "gn:dem":86,
    "gn:feature_class":"P",
    "gn:feature_code":"PPLL",
    "gn:name":"Hattanda",
    "gn:population":0,
    "gn:timezone":"Asia/Tokyo",
    "iso:country":"JP",
    "name:jpn_x_preferred":[
        "\u516b\u53cd\u7530"
    ],
    "wof:name":"Hattanda",
    "wof:placetype":"locality"
},
  "geometry": {"coordinates":[138.88425000000001,35.14248],"type":"Point"}
}