{
  "type": "Feature",
  "properties": {
    "gn:admin1_code":"21.0",
    "gn:admin2_code":"1864973.0",
    "gn:asciiname":"Shioi",
    "gn:country_code":"JP",
    "gn:dem":531,
    "gn:feature_class":"P",
    "gn:feature_code":"PPLL",
    "gn:name":"Shioi",
    "gn:population":0,
    "gn:timezone":"Asia/Tokyo",
    "iso:country":"JP",
    "name:jpn_x_preferred":[
        "\u5869\u4e95"
    ],
    "name:jpn_x_variant":[
        "\u3057\u304a\u3044",
        "\u30b7\u30aa\u30a4"
    ],
    "wof:name":"Shioi",
    "wof:placetype":"locality"
},
  "geometry": {"coordinates":[131.15108999999998,32.96359],"type":"Point"}
}