{
  "type": "Feature",
  "properties": {
    "gn:admin1_code":"40",
    "gn:admin2_code":"1856786.0",
    "gn:admin3_code":"13382.0",
    "gn:asciiname":"Nango",
    "gn:country_code":"JP",
    "gn:dem":563,
    "gn:feature_class":"P",
    "gn:feature_code":"PPL",
    "gn:name":"Nang\u014d",
    "gn:population":0,
    "gn:timezone":"Asia/Tokyo",
    "iso:country":"JP",
    "name:cat_x_preferred":[
        "Nango"
    ],
    "name:ceb_x_preferred":[
        "Nango"
    ],
    "name:deu_x_preferred":[
        "Nango"
    ],
    "name:fra_x_preferred":[
        "Nang\u014d"
    ],
    "name:swe_x_preferred":[
        "Nango"
    ],
    "wof:name":"Nango",
    "wof:placetype":"locality"
},
  "geometry": {"coordinates":[139.61667,33.86667],"type":"Point"}
}