{
  "type": "Feature",
  "properties": {
    "gn:admin1_code":"2.0",
    "gn:admin2_code":"2113122.0",
    "gn:asciiname":"Jizaiyama",
    "gn:country_code":"JP",
    "gn:dem":17,
    "gn:feature_class":"P",
    "gn:feature_code":"PPL",
    "gn:name":"Jizaiyama",
    "gn:population":0,
    "gn:timezone":"Asia/Tokyo",
    "iso:country":"JP",
    "name:jpn_x_preferred":[
        "\u81ea\u5728\u5c71"
    ],
    "name:jpn_x_variant":[
        "\u3058\u3056\u3044\u3084\u307e",
        "\u30b8\u30b6\u30a4\u30e4\u30de"
    ],
    "wof:name":"Jizaiyama",
    "wof:placetype":"locality"
},
  "geometry": {"coordinates":[140.06489999999999,39.66717],"type":"Point"}
}