{
  "type": "Feature",
  "properties": {
    "gn:admin1_code":"22",
    "gn:admin2_code":"1864872.0",
    "gn:asciiname":"Takanosu",
    "gn:cc2":"JP",
    "gn:country_code":"JP",
    "gn:dem":121,
    "gn:feature_class":"P",
    "gn:feature_code":"PPL",
    "gn:name":"Takanosu",
    "gn:population":0,
    "gn:timezone":"Asia/Tokyo",
    "iso:country":"JP",
    "name:und_x_variant":[
        "Takasu",
        "Takanosu"
    ],
    "wof:name":"Takanosu",
    "wof:placetype":"locality"
},
  "geometry": {"coordinates":[135.31666999999999,35.31667],"type":"Point"}
}