{
  "type": "Feature",
  "properties": {
    "gn:admin1_code":"10.0",
    "gn:admin2_code":"7453841.0",
    "gn:asciiname":"Azumacho-sori",
    "gn:country_code":"JP",
    "gn:dem":562,
    "gn:feature_class":"P",
    "gn:feature_code":"PPL",
    "gn:name":"Azumach\u014d-s\u014dri",
    "gn:population":0,
    "gn:timezone":"Asia/Tokyo",
    "iso:country":"JP",
    "name:jpn_x_preferred":[
        "\u6771\u753a\u6ca2\u5165"
    ],
    "name:und_x_variant":[
        "Azumach\u014d-s\u014dri"
    ],
    "wof:name":"Azumacho-sori",
    "wof:placetype":"locality"
},
  "geometry": {"coordinates":[139.39786999999998,36.58707],"type":"Point"}
}