{
  "type": "Feature",
  "properties": {
    "gn:admin1_code":"32",
    "gn:admin2_code":"1853897.0",
    "gn:admin3_code":"27127.0",
    "gn:asciiname":"Dojima",
    "gn:country_code":"JP",
    "gn:dem":17,
    "gn:feature_class":"P",
    "gn:feature_code":"PPL",
    "gn:name":"D\u014djima",
    "gn:population":0,
    "gn:timezone":"Asia/Tokyo",
    "iso:country":"JP",
    "name:jpn_x_preferred":[
        "\u5802\u5cf6"
    ],
    "name:und_x_variant":[
        "D\u014djima",
        "D\u014djima-nishimachi"
    ],
    "wof:name":"Dojima",
    "wof:placetype":"locality"
},
  "geometry": {"coordinates":[135.49605,34.69682],"type":"Point"}
}