{
  "type": "Feature",
  "properties": {
    "gn:admin1_code":"44.0",
    "gn:admin2_code":"2111850.0",
    "gn:admin3_code":"6364.0",
    "gn:asciiname":"Kamabuchi",
    "gn:country_code":"JP",
    "gn:dem":179,
    "gn:feature_class":"P",
    "gn:feature_code":"PPL",
    "gn:name":"Kamabuchi",
    "gn:population":0,
    "gn:timezone":"Asia/Tokyo",
    "iso:country":"JP",
    "name:jpn_x_preferred":[
        "\u91dc\u6e15"
    ],
    "wof:name":"Kamabuchi",
    "wof:placetype":"locality"
},
  "geometry": {"coordinates":[140.25888999999998,38.93389000000001],"type":"Point"}
}