{
  "type": "Feature",
  "properties": {
    "gn:admin1_code":"44",
    "gn:admin2_code":"1853136.0",
    "gn:asciiname":"Hamanaka",
    "gn:country_code":"JP",
    "gn:dem":8,
    "gn:feature_class":"P",
    "gn:feature_code":"PPL",
    "gn:name":"Hamanaka",
    "gn:population":0,
    "gn:timezone":"Asia/Tokyo",
    "iso:country":"JP",
    "name:jpn_x_preferred":[
        "\u6d5c\u4e2d"
    ],
    "wof:name":"Hamanaka",
    "wof:placetype":"locality"
},
  "geometry": {"coordinates":[139.78073999999998,38.82803],"type":"Point"}
}