{
  "type": "Feature",
  "properties": {
    "gn:admin1_code":"16.0",
    "gn:admin2_code":"2112822.0",
    "gn:asciiname":"Yagi",
    "gn:country_code":"JP",
    "gn:dem":109,
    "gn:feature_class":"P",
    "gn:feature_code":"PPL",
    "gn:name":"Yagi",
    "gn:population":0,
    "gn:timezone":"Asia/Tokyo",
    "iso:country":"JP",
    "name:deu_x_preferred":[
        "Yagi"
    ],
    "name:fra_x_preferred":[
        "Yagi"
    ],
    "name:ita_x_preferred":[
        "Yagi"
    ],
    "name:jpn_x_preferred":[
        "\u516b\u6728"
    ],
    "name:jpn_x_variant":[
        "\u3084\u304e",
        "\u30e4\u30ae"
    ],
    "name:nld_x_preferred":[
        "Yagi"
    ],
    "name:nor_x_preferred":[
        "Yagi"
    ],
    "wof:name":"Yagi",
    "wof:placetype":"locality"
},
  "geometry": {"coordinates":[141.04606999999999,39.3485],"type":"Point"}
}