{
  "type": "Feature",
  "properties": {
    "gn:admin1_code":"7.0",
    "gn:admin2_code":"1856443.0",
    "gn:asciiname":"Shakain",
    "gn:country_code":"JP",
    "gn:dem":45,
    "gn:feature_class":"P",
    "gn:feature_code":"PPLL",
    "gn:name":"Shakain",
    "gn:population":0,
    "gn:timezone":"Asia/Tokyo",
    "iso:country":"JP",
    "name:jpn_x_preferred":[
        "\u91c8\u8fe6\u9662"
    ],
    "wof:name":"Shakain",
    "wof:placetype":"locality"
},
  "geometry": {"coordinates":[130.51331000000002,33.78937],"type":"Point"}
}