{
  "type": "Feature",
  "properties": {
    "gn:admin1_code":"4.0",
    "gn:admin2_code":"1859468.0",
    "gn:asciiname":"Shin'oimae",
    "gn:country_code":"JP",
    "gn:dem":23,
    "gn:feature_class":"P",
    "gn:feature_code":"PPLL",
    "gn:name":"Shin\u2019oimae",
    "gn:population":0,
    "gn:timezone":"Asia/Tokyo",
    "iso:country":"JP",
    "name:jpn_x_preferred":[
        "\u65b0\u8ffd\u524d"
    ],
    "name:jpn_x_variant":[
        "\u3057\u3093\u304a\u3044\u307e\u3048",
        "\u30b7\u30f3\u30aa\u30a4\u30de\u30a8"
    ],
    "name:und_x_variant":[
        "Shin\u2019oimae"
    ],
    "wof:name":"Shin'oimae",
    "wof:placetype":"locality"
},
  "geometry": {"coordinates":[140.04488000000001,35.33964],"type":"Point"}
}