{
  "type": "Feature",
  "properties": {
    "gn:admin1_code":"21.0",
    "gn:admin2_code":"1864975.0",
    "gn:admin3_code":"43433.0",
    "gn:asciiname":"Shiramizu",
    "gn:country_code":"JP",
    "gn:dem":501,
    "gn:feature_class":"P",
    "gn:feature_code":"PPL",
    "gn:name":"Shiramizu",
    "gn:population":0,
    "gn:timezone":"Asia/Tokyo",
    "iso:country":"JP",
    "name:jpn_x_preferred":[
        "\u767d\u6c34"
    ],
    "name:jpn_x_variant":[
        "\u3057\u3089\u307f\u305a",
        "\u30b7\u30e9\u30df\u30ba"
    ],
    "wof:name":"Shiramizu",
    "wof:placetype":"locality"
},
  "geometry": {"coordinates":[131.09796,32.82685],"type":"Point"}
}