{
  "type": "Feature",
  "properties": {
    "gn:admin1_code":"43.0",
    "gn:admin2_code":"7411114.0",
    "gn:asciiname":"Shimotomobuchi",
    "gn:country_code":"JP",
    "gn:dem":280,
    "gn:feature_class":"P",
    "gn:feature_code":"PPL",
    "gn:name":"Shimotomobuchi",
    "gn:population":0,
    "gn:timezone":"Asia/Tokyo",
    "iso:country":"JP",
    "name:jpn_x_preferred":[
        "\u4e0b\u9786\u6e15"
    ],
    "wof:name":"Shimotomobuchi",
    "wof:placetype":"locality"
},
  "geometry": {"coordinates":[135.43279999999999,34.21404],"type":"Point"}
}