{
  "type": "Feature",
  "properties": {
    "gn:admin1_code":"46.0",
    "gn:admin2_code":"1857168.0",
    "gn:admin3_code":"19366.0",
    "gn:asciiname":"Sawagami",
    "gn:country_code":"JP",
    "gn:dem":155,
    "gn:feature_class":"P",
    "gn:feature_code":"PPLL",
    "gn:name":"Sawagami",
    "gn:population":0,
    "gn:timezone":"Asia/Tokyo",
    "iso:country":"JP",
    "name:jpn_x_preferred":[
        "\u6ca2\u4e0a"
    ],
    "wof:name":"Sawagami",
    "wof:placetype":"locality"
},
  "geometry": {"coordinates":[138.50863000000001,35.21673],"type":"Point"}
}