{
  "type": "Feature",
  "properties": {
    "gn:admin1_code":"4.0",
    "gn:admin2_code":"1859468.0",
    "gn:asciiname":"Koyamano",
    "gn:country_code":"JP",
    "gn:dem":29,
    "gn:feature_class":"P",
    "gn:feature_code":"PPL",
    "gn:name":"Koyamano",
    "gn:population":0,
    "gn:timezone":"Asia/Tokyo",
    "iso:country":"JP",
    "name:jpn_x_preferred":[
        "\u5c0f\u5c71\u91ce"
    ],
    "name:jpn_x_variant":[
        "\u3053\u3084\u307e\u306e",
        "\u30b3\u30e4\u30de\u30ce"
    ],
    "wof:name":"Koyamano",
    "wof:placetype":"locality"
},
  "geometry": {"coordinates":[139.91550000000001,35.29366],"type":"Point"}
}