{
  "type": "Feature",
  "properties": {
    "gn:admin1_code":"05",
    "gn:admin2_code":"10861187.0",
    "gn:asciiname":"Mikame",
    "gn:country_code":"JP",
    "gn:dem":15,
    "gn:feature_class":"P",
    "gn:feature_code":"PPL",
    "gn:name":"Mikame",
    "gn:population":0,
    "gn:timezone":"Asia/Tokyo",
    "iso:country":"JP",
    "wof:name":"Mikame",
    "wof:placetype":"locality"
},
  "geometry": {"coordinates":[132.42353,33.38465],"type":"Point"}
}