{
  "type": "Feature",
  "properties": {
    "gn:admin1_code":"36",
    "gn:admin2_code":"1863308.0",
    "gn:asciiname":"Shimokocho",
    "gn:country_code":"JP",
    "gn:dem":8,
    "gn:feature_class":"P",
    "gn:feature_code":"PPL",
    "gn:name":"Shimok\u014dch\u014d",
    "gn:population":0,
    "gn:timezone":"Asia/Tokyo",
    "iso:country":"JP",
    "name:jpn_x_preferred":[
        "\u4e0b\u5e9c\u753a"
    ],
    "name:und_x_variant":[
        "Shimo-kofu",
        "Shimok\u014d",
        "Shimok\u014dch\u014d"
    ],
    "wof:name":"Shimokocho",
    "wof:placetype":"locality"
},
  "geometry": {"coordinates":[132.11118000000002,34.92232],"type":"Point"}
}