{
  "type": "Feature",
  "properties": {
    "gn:admin1_code":"33",
    "gn:admin2_code":"8300623.0",
    "gn:asciiname":"Tobo",
    "gn:country_code":"JP",
    "gn:dem":1,
    "gn:feature_class":"P",
    "gn:feature_code":"PPL",
    "gn:name":"T\u014db\u014d",
    "gn:population":0,
    "gn:timezone":"Asia/Tokyo",
    "iso:country":"JP",
    "name:jpn_x_preferred":[
        "\u5510\u623f"
    ],
    "name:und_x_variant":[
        "T\u014dh\u014d",
        "T\u014db\u014d"
    ],
    "wof:name":"Tobo",
    "wof:placetype":"locality"
},
  "geometry": {"coordinates":[129.93956,33.48499],"type":"Point"}
}