{
  "type": "Feature",
  "properties": {
    "gn:admin1_code":"3.0",
    "gn:admin2_code":"2129754.0",
    "gn:admin3_code":"2412.0",
    "gn:asciiname":"Wakabamachi",
    "gn:country_code":"JP",
    "gn:dem":51,
    "gn:feature_class":"P",
    "gn:feature_code":"PPL",
    "gn:name":"Wakabamachi",
    "gn:population":0,
    "gn:timezone":"Asia/Tokyo",
    "iso:country":"JP",
    "name:jpn_x_preferred":[
        "\u82e5\u8449\u753a"
    ],
    "name:jpn_x_variant":[
        "\u308f\u304b\u3070\u307e\u3061",
        "\u30ef\u30ab\u30d0\u30de\u30c1"
    ],
    "wof:name":"Wakabamachi",
    "wof:placetype":"locality"
},
  "geometry": {"coordinates":[141.36321000000001,40.66307000000001],"type":"Point"}
}