{
  "type": "Feature",
  "properties": {
    "gn:admin1_code":"3.0",
    "gn:admin2_code":"2130056.0",
    "gn:asciiname":"Tominocho",
    "gn:country_code":"JP",
    "gn:dem":52,
    "gn:feature_class":"P",
    "gn:feature_code":"PPL",
    "gn:name":"Tominoch\u014d",
    "gn:population":0,
    "gn:timezone":"Asia/Tokyo",
    "iso:country":"JP",
    "name:jpn_x_preferred":[
        "\u5bcc\u91ce\u753a"
    ],
    "name:jpn_x_variant":[
        "\u3068\u307f\u306e\u3061\u3087\u3046",
        "\u30c8\u30df\u30ce\u30c1\u30e7\u30a6"
    ],
    "name:und_x_variant":[
        "Tominoch\u014d"
    ],
    "wof:name":"Tominocho",
    "wof:placetype":"locality"
},
  "geometry": {"coordinates":[140.47528,40.58797],"type":"Point"}
}