{
  "type": "Feature",
  "properties": {
    "gn:admin1_code":"4.0",
    "gn:admin2_code":"2112386.0",
    "gn:asciiname":"Nakashiba",
    "gn:country_code":"JP",
    "gn:dem":81,
    "gn:feature_class":"P",
    "gn:feature_code":"PPLL",
    "gn:name":"Nakashiba",
    "gn:population":0,
    "gn:timezone":"Asia/Tokyo",
    "iso:country":"JP",
    "name:jpn_x_preferred":[
        "\u4e2d\u829d"
    ],
    "name:jpn_x_variant":[
        "\u306a\u304b\u3057\u3070",
        "\u30ca\u30ab\u30b7\u30d0"
    ],
    "wof:name":"Nakashiba",
    "wof:placetype":"locality"
},
  "geometry": {"coordinates":[139.97307000000001,35.13715999999999],"type":"Point"}
}