{
  "type": "Feature",
  "properties": {
    "gn:admin1_code":"06",
    "gn:admin2_code":"7465771.0",
    "gn:admin3_code":"18404.0",
    "gn:asciiname":"Iwaya",
    "gn:country_code":"JP",
    "gn:dem":537,
    "gn:feature_class":"P",
    "gn:feature_code":"PPL",
    "gn:name":"Iwaya",
    "gn:population":0,
    "gn:timezone":"Asia/Tokyo",
    "iso:country":"JP",
    "wof:name":"Iwaya",
    "wof:placetype":"locality"
},
  "geometry": {"coordinates":[136.27184,35.67759],"type":"Point"}
}