{
  "type": "Feature",
  "properties": {
    "gn:admin1_code":"10",
    "gn:admin2_code":"7453748.0",
    "gn:admin3_code":"10449.0",
    "gn:asciiname":"Sarugakyo-onsen",
    "gn:country_code":"JP",
    "gn:dem":699,
    "gn:feature_class":"P",
    "gn:feature_code":"PPL",
    "gn:name":"Sarugaky\u014d-onsen",
    "gn:population":0,
    "gn:timezone":"Asia/Tokyo",
    "iso:country":"JP",
    "name:jpn_x_preferred":[
        "\u733f\u30f6\u4eac\u6e29\u6cc9"
    ],
    "name:und_x_variant":[
        "Sarugaky\u014d-onsen",
        "Sarugaky\u014d"
    ],
    "wof:name":"Sarugakyo-onsen",
    "wof:placetype":"locality"
},
  "geometry": {"coordinates":[138.88155,36.72983],"type":"Point"}
}