{
  "type": "Feature",
  "properties": {
    "gn:admin1_code":"34.0",
    "gn:admin2_code":"8304213.0",
    "gn:asciiname":"Tateyama",
    "gn:country_code":"JP",
    "gn:dem":14,
    "gn:feature_class":"P",
    "gn:feature_code":"PPLL",
    "gn:name":"Tateyama",
    "gn:population":0,
    "gn:timezone":"Asia/Tokyo",
    "iso:country":"JP",
    "name:ceb_x_preferred":[
        "Tateyama"
    ],
    "name:deu_x_preferred":[
        "Tateyama"
    ],
    "name:fra_x_preferred":[
        "Tateyama"
    ],
    "name:jpn_x_preferred":[
        "\u7acb\u5c71"
    ],
    "name:jpn_x_variant":[
        "\u305f\u3066\u3084\u307e",
        "\u30bf\u30c6\u30e4\u30de"
    ],
    "name:mlg_x_preferred":[
        "Tateyama"
    ],
    "name:nld_x_preferred":[
        "Tateyama"
    ],
    "name:ron_x_preferred":[
        "Tateyama"
    ],
    "name:rus_x_preferred":[
        "\u0422\u0430\u0442\u0435\u044f\u043c\u0430"
    ],
    "name:ukr_x_preferred":[
        "\u0422\u0430\u0442\u0435\u044f\u043c\u0430"
    ],
    "wof:name":"Tateyama",
    "wof:placetype":"locality"
},
  "geometry": {"coordinates":[139.71961999999999,35.9929],"type":"Point"}
}