{
  "type": "Feature",
  "properties": {
    "gn:admin1_code":"24.0",
    "gn:admin2_code":"2112261.0",
    "gn:asciiname":"Urahama",
    "gn:country_code":"JP",
    "gn:dem":14,
    "gn:feature_class":"P",
    "gn:feature_code":"PPL",
    "gn:name":"Urahama",
    "gn:population":0,
    "gn:timezone":"Asia/Tokyo",
    "iso:country":"JP",
    "name:jpn_x_preferred":[
        "\u6d66\u6d5c"
    ],
    "name:jpn_x_variant":[
        "\u3046\u3089\u306f\u307e",
        "\u30a6\u30e9\u30cf\u30de"
    ],
    "wof:name":"Urahama",
    "wof:placetype":"locality"
},
  "geometry": {"coordinates":[141.61345,38.8666],"type":"Point"}
}