{
  "type": "Feature",
  "properties": {
    "gn:admin1_code":"13",
    "gn:admin2_code":"7370819.0",
    "gn:asciiname":"Ikuho",
    "gn:country_code":"JP",
    "gn:dem":9,
    "gn:feature_class":"P",
    "gn:feature_code":"PPL",
    "gn:name":"Ikuho",
    "gn:population":0,
    "gn:timezone":"Asia/Tokyo",
    "iso:country":"JP",
    "name:jpn_x_preferred":[
        "\u751f\u7a42"
    ],
    "name:und_x_variant":[
        "Namariho",
        "Ikuho"
    ],
    "wof:name":"Ikuho",
    "wof:placetype":"locality"
},
  "geometry": {"coordinates":[134.91758000000002,34.45313],"type":"Point"}
}