{
  "type": "Feature",
  "properties": {
    "iso:country":"JP",
    "name:eng_x_preferred":[
        "Higashihonjicho 3 Chome"
    ],
    "name:eng_x_variant":[
        "Higashihonjichou 3 Choume",
        "Higashihonjicho 3 Chome"
    ],
    "name:jpn_x_preferred":[
        "\uff13\u4e01\u76ee"
    ],
    "name:jpn_x_variant":[
        "\u3072\u304c\u3057\u307b\u3093\u3058\u3061\u3087\u3046 \uff13\u3061\u3087\u3046\u3081",
        "\u6771\u672c\u5730\u753a \uff13\u4e01\u76ee",
        "\uff13\u3061\u3087\u3046\u3081"
    ],
    "qs:gn_local":0,
    "qs:local_max":745,
    "qs:local_sum":874,
    "qs:localhoods":3,
    "qs:name":"\uff13\u4e01\u76ee",
    "qs:name_adm0":"\u65e5\u672c",
    "qs:name_adm1":"\u611b\u77e5\u770c",
    "qs:name_en":"Higashihonjicho 3 Chome",
    "qs:name_lau":"\u6771\u672c\u5730\u753a",
    "qs:name_local":"\u702c\u6238\u5e02",
    "qs:photo_max":23,
    "qs:photo_sum":53,
    "qs:placetype":"Suburb",
    "qs:quad_count":3,
    "qs:woe_adm0":23424856,
    "qs:woe_adm1":2345851,
    "qs:woe_adm2":0,
    "qs:woe_lau":28441384,
    "qs:woe_local":1118140,
    "qs:woe_ver":"7.10.0",
    "qs_pg:name":"\uff13\u4e01\u76ee",
    "qs_pg:name_adm0":"\u65e5\u672c",
    "qs_pg:name_adm1":"\u611b\u77e5\u770c",
    "qs_pg:photos":30,
    "qs_pg:photos_1k":6,
    "qs_pg:photos_9k":1,
    "qs_pg:photos_9r":2,
    "qs_pg:photos_all":30,
    "qs_pg:photos_sr":2,
    "qs_pg:pop_sr":0,
    "qs_pg:qs_pg_placetype":"neighbourhood",
    "qs_pg:qs_pg_placetype_gp":"Suburb",
    "qs_pg:woe_adm0":23424856,
    "woe:adm0_id":23424856,
    "woe:name_adm0":"\u65e5\u672c",
    "woe:name_adm1":"\u611b\u77e5\u770c",
    "woe:placetype":"Suburb",
    "wof:lang":[
        "jpn"
    ],
    "wof:name":"\uff13\u4e01\u76ee",
    "wof:placetype":"neighbourhood"
},
  "geometry": {"coordinates":[137.06413699999999,35.188167],"type":"Point"}
}