{
  "type": "Feature",
  "properties": {
    "gn:admin1_code":"21.0",
    "gn:admin2_code":"1859488.0",
    "gn:asciiname":"Hebitsuka",
    "gn:country_code":"JP",
    "gn:dem":32,
    "gn:feature_class":"P",
    "gn:feature_code":"PPLL",
    "gn:name":"Hebitsuka",
    "gn:population":0,
    "gn:timezone":"Asia/Tokyo",
    "iso:country":"JP",
    "name:jpn_x_preferred":[
        "\u86c7\u585a"
    ],
    "name:jpn_x_variant":[
        "\u3078\u3073\u3064\u304b",
        "\u30d8\u30d3\u30c4\u30ab"
    ],
    "wof:name":"Hebitsuka",
    "wof:placetype":"locality"
},
  "geometry": {"coordinates":[130.75122999999999,32.96165],"type":"Point"}
}