{
  "type": "Feature",
  "properties": {
    "gn:admin1_code":"21.0",
    "gn:admin2_code":"7412706.0",
    "gn:admin3_code":"43444.0",
    "gn:asciiname":"Tsushida",
    "gn:country_code":"JP",
    "gn:dem":15,
    "gn:feature_class":"P",
    "gn:feature_code":"PPL",
    "gn:name":"Tsushida",
    "gn:population":0,
    "gn:timezone":"Asia/Tokyo",
    "iso:country":"JP",
    "name:jpn_x_preferred":[
        "\u6d25\u5fd7\u7530"
    ],
    "name:jpn_x_variant":[
        "\u3064\u3057\u3060",
        "\u30c4\u30b7\u30c0"
    ],
    "wof:name":"Tsushida",
    "wof:placetype":"locality"
},
  "geometry": {"coordinates":[130.78424999999999,32.68889],"type":"Point"}
}