{
  "type": "Feature",
  "properties": {
    "gn:admin1_code":"4.0",
    "gn:admin2_code":"2112997.0",
    "gn:admin3_code":"12423.0",
    "gn:asciiname":"Miyoguchi",
    "gn:country_code":"JP",
    "gn:dem":8,
    "gn:feature_class":"P",
    "gn:feature_code":"PPL",
    "gn:name":"Miyoguchi",
    "gn:population":0,
    "gn:timezone":"Asia/Tokyo",
    "iso:country":"JP",
    "name:jpn_x_preferred":[
        "\u6c34\u53e3"
    ],
    "name:jpn_x_variant":[
        "\u307f\u3088\u3050\u3061",
        "\u30df\u30e8\u30b0\u30c1"
    ],
    "wof:name":"Miyoguchi",
    "wof:placetype":"locality"
},
  "geometry": {"coordinates":[140.34184999999999,35.40142],"type":"Point"}
}