{
  "type": "Feature",
  "properties": {
    "gn:admin1_code":"12.0",
    "gn:admin2_code":"7428097.0",
    "gn:admin3_code":"1643.0",
    "gn:asciiname":"Churui-asahi",
    "gn:country_code":"JP",
    "gn:dem":138,
    "gn:feature_class":"P",
    "gn:feature_code":"PPL",
    "gn:name":"Ch\u016brui-asahi",
    "gn:population":0,
    "gn:timezone":"Asia/Tokyo",
    "iso:country":"JP",
    "name:jpn_x_preferred":[
        "\u5fe0\u985e\u671d\u65e5"
    ],
    "name:jpn_x_variant":[
        "\u3061\u3085\u3046\u308b\u3044\u3042\u3055\u3072",
        "\u30c1\u30e5\u30a6\u30eb\u30a4\u30a2\u30b5\u30d2"
    ],
    "name:und_x_variant":[
        "Ch\u016brui-asahi"
    ],
    "wof:name":"Churui-asahi",
    "wof:placetype":"locality"
},
  "geometry": {"coordinates":[143.26381999999995,42.57729000000001],"type":"Point"}
}