{
  "type": "Feature",
  "properties": {
    "gn:admin1_code":"46.0",
    "gn:admin2_code":"7415908.0",
    "gn:admin3_code":"19425.0",
    "gn:asciiname":"Shimohara",
    "gn:country_code":"JP",
    "gn:dem":998,
    "gn:feature_class":"P",
    "gn:feature_code":"PPLL",
    "gn:name":"Shimohara",
    "gn:population":0,
    "gn:timezone":"Asia/Tokyo",
    "iso:country":"JP",
    "name:jpn_x_preferred":[
        "\u4e0b\u539f"
    ],
    "wof:name":"Shimohara",
    "wof:placetype":"locality"
},
  "geometry": {"coordinates":[138.91107,35.42858],"type":"Point"}
}