{
  "type": "Feature",
  "properties": {
    "iso:country":"JP",
    "name:eng_x_preferred":[
        "Suehirocho 2 Chome"
    ],
    "name:eng_x_variant":[
        "Suehirochou 2 Choume",
        "Suehirocho 2 Chome"
    ],
    "name:jpn_x_preferred":[
        "\uff12\u4e01\u76ee"
    ],
    "name:jpn_x_variant":[
        "\u3059\u3048\u3072\u308d\u3061\u3087\u3046 \uff12\u3061\u3087\u3046\u3081",
        "\u672b\u5e83\u753a \uff12\u4e01\u76ee",
        "\uff12\u3061\u3087\u3046\u3081"
    ],
    "qs:gn_local":0,
    "qs:local_max":653,
    "qs:local_sum":2188,
    "qs:localhoods":17,
    "qs:name":"\uff12\u4e01\u76ee",
    "qs:name_adm0":"\u65e5\u672c",
    "qs:name_adm1":"\u6771\u4eac\u90fd",
    "qs:name_en":"Suehirocho 2 Chome",
    "qs:name_lau":"\u672b\u5e83\u753a",
    "qs:name_local":"\u9752\u6885\u5e02",
    "qs:photo_max":2,
    "qs:photo_sum":2,
    "qs:placetype":"Suburb",
    "qs:quad_count":1,
    "qs:woe_adm0":23424856,
    "qs:woe_adm1":2345889,
    "qs:woe_adm2":0,
    "qs:woe_lau":28414959,
    "qs:woe_local":1113567,
    "qs:woe_ver":"7.10.0",
    "wof:lang":[
        "jpn"
    ],
    "wof:name":"\uff12\u4e01\u76ee",
    "wof:placetype":"neighbourhood"
},
  "geometry": {"coordinates":[139.30938699999999,35.784397],"type":"Point"}
}