{
  "type": "Feature",
  "properties": {
    "gn:admin1_code":"24.0",
    "gn:admin2_code":"2112574.0",
    "gn:asciiname":"Naka",
    "gn:country_code":"JP",
    "gn:dem":6,
    "gn:feature_class":"P",
    "gn:feature_code":"PPL",
    "gn:name":"Naka",
    "gn:population":0,
    "gn:timezone":"Asia/Tokyo",
    "iso:country":"JP",
    "name:jpn_x_preferred":[
        "\u4ef2"
    ],
    "name:jpn_x_variant":[
        "\u306a\u304b",
        "\u30ca\u30ab"
    ],
    "wof:name":"Naka",
    "wof:placetype":"locality"
},
  "geometry": {"coordinates":[141.25673,38.45359000000001],"type":"Point"}
}