{
  "type": "Feature",
  "properties": {
    "gn:admin1_code":"5.0",
    "gn:admin2_code":"1855138.0",
    "gn:admin3_code":"38442.0",
    "gn:asciiname":"Kameura",
    "gn:country_code":"JP",
    "gn:dem":85,
    "gn:feature_class":"P",
    "gn:feature_code":"PPL",
    "gn:name":"Kameura",
    "gn:population":0,
    "gn:timezone":"Asia/Tokyo",
    "iso:country":"JP",
    "wof:name":"Kameura",
    "wof:placetype":"locality"
},
  "geometry": {"coordinates":[132.33018999999999,33.49932],"type":"Point"}
}