{
  "type": "Feature",
  "properties": {
    "iso:country":"JP",
    "name:eng_x_preferred":[
        "Nishihara Town"
    ],
    "name:jpn_x_preferred":[
        "\u897f\u539f\u753a"
    ],
    "qs:name":"\u897f\u539f\u753a",
    "qs:name_adm0":"\u65e5\u672c",
    "qs:name_adm1":"\u6c96\u7e04\u770c",
    "qs:photos":240,
    "qs:photos_1k":49,
    "qs:photos_9k":1,
    "qs:photos_9r":4,
    "qs:photos_all":240,
    "qs:photos_sr":4,
    "qs:placetype":"Town",
    "qs:pop_sr":"0",
    "wof:name":"Nishihara Town",
    "wof:placetype":"locality"
},
  "geometry": {"coordinates":[127.768198,26.22768],"type":"Point"}
}