{
  "type": "Feature",
  "properties": {
    "gn:admin1_code":"33.0",
    "gn:admin2_code":"8300623.0",
    "gn:asciiname":"Ochicho-senzoku",
    "gn:country_code":"JP",
    "gn:dem":39,
    "gn:feature_class":"P",
    "gn:feature_code":"PPL",
    "gn:name":"\u014cchich\u014d-senzoku",
    "gn:population":0,
    "gn:timezone":"Asia/Tokyo",
    "iso:country":"JP",
    "name:jpn_x_preferred":[
        "\u76f8\u77e5\u753a\u5343\u675f"
    ],
    "name:und_x_variant":[
        "\u014cchich\u014d-senzoku"
    ],
    "wof:name":"Ochicho-senzoku",
    "wof:placetype":"locality"
},
  "geometry": {"coordinates":[130.03155000000001,33.35131],"type":"Point"}
}