{
  "type": "Feature",
  "properties": {
    "gn:admin1_code":"47",
    "gn:admin2_code":"1858371.0",
    "gn:admin3_code":"47302.0",
    "gn:asciiname":"Hentona",
    "gn:country_code":"JP",
    "gn:dem":7,
    "gn:feature_class":"P",
    "gn:feature_code":"PPL",
    "gn:name":"Hentona",
    "gn:population":0,
    "gn:timezone":"Asia/Tokyo",
    "iso:country":"JP",
    "name:jpn_x_preferred":[
        "\u8fba\u571f\u540d"
    ],
    "name:jpn_x_variant":[
        "\u3078\u3093\u3068\u306a"
    ],
    "name:und_x_variant":[
        "Fintona",
        "Hetona",
        "Hedona",
        "Hentona"
    ],
    "wof:name":"Hentona",
    "wof:placetype":"locality"
},
  "geometry": {"coordinates":[128.1754,26.74501],"type":"Point"}
}