{
  "type": "Feature",
  "properties": {
    "iso:country":"JP",
    "name:eng_x_preferred":[
        "Kitashinyokohama 2 Chome"
    ],
    "name:eng_x_variant":[
        "Kitashinyokohama 2 Choume",
        "Kitashinyokohama 2 Chome"
    ],
    "name:jpn_x_preferred":[
        "\uff12\u4e01\u76ee"
    ],
    "name:jpn_x_variant":[
        "\u304d\u305f\u3057\u3093\u3088\u3053\u306f\u307e \uff12\u3061\u3087\u3046\u3081",
        "\u5317\u65b0\u6a2a\u6d5c \uff12\u4e01\u76ee",
        "\uff12\u3061\u3087\u3046\u3081"
    ],
    "qs:gn_local":0,
    "qs:local_max":6208,
    "qs:local_sum":82309,
    "qs:localhoods":190,
    "qs:name":"\uff12\u4e01\u76ee",
    "qs:name_adm0":"\u65e5\u672c",
    "qs:name_adm1":"\u795e\u5948\u5ddd\u770c",
    "qs:name_adm2":"\u6e2f\u5317\u533a",
    "qs:name_en":"Kitashinyokohama 2 Chome",
    "qs:name_lau":"\u5317\u65b0\u6a2a\u6d5c",
    "qs:name_local":"\u6a2a\u6d5c\u5e02",
    "qs:photo_max":509,
    "qs:photo_sum":813,
    "qs:placetype":"Suburb",
    "qs:quad_count":14,
    "qs:woe_adm0":23424856,
    "qs:woe_adm1":2345868,
    "qs:woe_adm2":15015537,
    "qs:woe_lau":28415997,
    "qs:woe_local":1118550,
    "qs:woe_ver":"7.10.0",
    "wof:lang":[
        "jpn"
    ],
    "wof:name":"\uff12\u4e01\u76ee",
    "wof:placetype":"neighbourhood"
},
  "geometry": {"coordinates":[139.60656900000001,35.511711],"type":"Point"}
}