{
  "type": "Feature",
  "properties": {
    "gn:admin1_code":"12",
    "gn:admin2_code":"2038726.0",
    "gn:admin3_code":"1367.0",
    "gn:asciiname":"Katsuma",
    "gn:country_code":"JP",
    "gn:dem":185,
    "gn:feature_class":"P",
    "gn:feature_code":"PPL",
    "gn:name":"Katsuma",
    "gn:population":0,
    "gn:timezone":"Asia/Tokyo",
    "iso:country":"JP",
    "wof:name":"Katsuma",
    "wof:placetype":"locality"
},
  "geometry": {"coordinates":[139.46888999999999,42.20722],"type":"Point"}
}