{
  "type": "Feature",
  "properties": {
    "gn:admin1_code":"21.0",
    "gn:admin2_code":"1865358.0",
    "gn:asciiname":"Hondomachi-hirose",
    "gn:country_code":"JP",
    "gn:dem":26,
    "gn:feature_class":"P",
    "gn:feature_code":"PPL",
    "gn:name":"Hondomachi-hirose",
    "gn:population":0,
    "gn:timezone":"Asia/Tokyo",
    "iso:country":"JP",
    "name:jpn_x_preferred":[
        "\u672c\u6e21\u753a\u5e83\u702c"
    ],
    "name:jpn_x_variant":[
        "\u307b\u3093\u3069\u307e\u3061\u3072\u308d\u305b",
        "\u30db\u30f3\u30c9\u30de\u30c1\u30d2\u30ed\u30bb"
    ],
    "wof:name":"Hondomachi-hirose",
    "wof:placetype":"locality"
},
  "geometry": {"coordinates":[130.19691,32.47047],"type":"Point"}
}