{
  "type": "Feature",
  "properties": {
    "gn:admin1_code":"21.0",
    "gn:admin2_code":"1859490.0",
    "gn:admin3_code":"43403.0",
    "gn:asciiname":"Maki",
    "gn:country_code":"JP",
    "gn:dem":318,
    "gn:feature_class":"P",
    "gn:feature_code":"PPL",
    "gn:name":"Maki",
    "gn:population":0,
    "gn:timezone":"Asia/Tokyo",
    "iso:country":"JP",
    "name:jpn_x_preferred":[
        "\u771f\u6728"
    ],
    "name:jpn_x_variant":[
        "\u307e\u304d",
        "\u30de\u30ad"
    ],
    "wof:name":"Maki",
    "wof:placetype":"locality"
},
  "geometry": {"coordinates":[130.91391999999999,32.91686],"type":"Point"}
}