{
  "type": "Feature",
  "properties": {
    "gn:admin1_code":"13.0",
    "gn:admin2_code":"7370811.0",
    "gn:asciiname":"Yokawacho-toyooka",
    "gn:country_code":"JP",
    "gn:dem":177,
    "gn:feature_class":"P",
    "gn:feature_code":"PPL",
    "gn:name":"Yokawach\u014d-toyooka",
    "gn:population":0,
    "gn:timezone":"Asia/Tokyo",
    "iso:country":"JP",
    "name:jpn_x_preferred":[
        "\u5409\u5ddd\u753a\u8c4a\u5ca1"
    ],
    "name:und_x_variant":[
        "Yokawach\u014d-toyooka"
    ],
    "wof:name":"Yokawacho-toyooka",
    "wof:placetype":"locality"
},
  "geometry": {"coordinates":[135.14726999999999,34.85599000000001],"type":"Point"}
}