{
  "type": "Feature",
  "properties": {
    "gn:admin1_code":"40.0",
    "gn:admin2_code":"1852140.0",
    "gn:asciiname":"Hiromachi",
    "gn:country_code":"JP",
    "gn:dem":13,
    "gn:feature_class":"P",
    "gn:feature_code":"PPL",
    "gn:name":"Hiromachi",
    "gn:population":0,
    "gn:timezone":"Asia/Tokyo",
    "iso:country":"JP",
    "name:jpn_x_preferred":[
        "\u5e83\u753a"
    ],
    "wof:name":"Hiromachi",
    "wof:placetype":"locality"
},
  "geometry": {"coordinates":[139.73383999999999,35.61593],"type":"Point"}
}