{
  "type": "Feature",
  "properties": {
    "gn:admin1_code":"4.0",
    "gn:admin2_code":"1859468.0",
    "gn:asciiname":"Hikotadai",
    "gn:country_code":"JP",
    "gn:dem":56,
    "gn:feature_class":"P",
    "gn:feature_code":"PPLL",
    "gn:name":"Hikotadai",
    "gn:population":0,
    "gn:timezone":"Asia/Tokyo",
    "iso:country":"JP",
    "name:jpn_x_preferred":[
        "\u5f66\u592a\u53f0"
    ],
    "name:jpn_x_variant":[
        "\u3072\u3053\u305f\u3060\u3044",
        "\u30d2\u30b3\u30bf\u30c0\u30a4"
    ],
    "wof:name":"Hikotadai",
    "wof:placetype":"locality"
},
  "geometry": {"coordinates":[140.03451000000001,35.32845],"type":"Point"}
}