{
  "type": "Feature",
  "properties": {
    "gn:admin1_code":"34.0",
    "gn:admin2_code":"11668552.0",
    "gn:asciiname":"Oze",
    "gn:country_code":"JP",
    "gn:dem":1,
    "gn:feature_class":"P",
    "gn:feature_code":"PPL",
    "gn:name":"\u014cze",
    "gn:population":0,
    "gn:timezone":"Asia/Tokyo",
    "iso:country":"JP",
    "name:bug_x_preferred":[
        "Oze"
    ],
    "name:cat_x_preferred":[
        "Auza"
    ],
    "name:ceb_x_preferred":[
        "Oze"
    ],
    "name:deu_x_preferred":[
        "Oze"
    ],
    "name:eus_x_preferred":[
        "Oze"
    ],
    "name:fra_x_preferred":[
        "Oze"
    ],
    "name:hun_x_preferred":[
        "Oze"
    ],
    "name:ita_x_preferred":[
        "Oze"
    ],
    "name:jpn_x_preferred":[
        "\u5927\u702c"
    ],
    "name:lat_x_preferred":[
        "Oze"
    ],
    "name:lmo_x_preferred":[
        "Oze"
    ],
    "name:ltz_x_preferred":[
        "Oze"
    ],
    "name:msa_x_preferred":[
        "Oze"
    ],
    "name:nld_x_preferred":[
        "Oze"
    ],
    "name:oci_x_preferred":[
        "Auza"
    ],
    "name:pms_x_preferred":[
        "Oze"
    ],
    "name:pol_x_preferred":[
        "Oze"
    ],
    "name:por_x_preferred":[
        "Oze"
    ],
    "name:ron_x_preferred":[
        "Oze"
    ],
    "name:rus_x_preferred":[
        "\u041e\u0437"
    ],
    "name:slk_x_preferred":[
        "Oze"
    ],
    "name:spa_x_preferred":[
        "Oze"
    ],
    "name:sqi_x_preferred":[
        "Oze"
    ],
    "name:swe_x_preferred":[
        "Oze"
    ],
    "name:ukr_x_preferred":[
        "\u041e\u0437"
    ],
    "name:und_x_variant":[
        "\u014cze"
    ],
    "name:vie_x_preferred":[
        "Oze"
    ],
    "name:vol_x_preferred":[
        "Oze"
    ],
    "name:war_x_preferred":[
        "Oze"
    ],
    "name:zho_x_preferred":[
        "\u5965\u5179"
    ],
    "wof:name":"Oze",
    "wof:placetype":"locality"
},
  "geometry": {"coordinates":[139.84621999999999,35.80622],"type":"Point"}
}