{
  "type": "Feature",
  "properties": {
    "gn:admin1_code":"2.0",
    "gn:admin2_code":"2110504.0",
    "gn:asciiname":"Sodeyama",
    "gn:country_code":"JP",
    "gn:dem":275,
    "gn:feature_class":"P",
    "gn:feature_code":"PPL",
    "gn:name":"Sodeyama",
    "gn:population":0,
    "gn:timezone":"Asia/Tokyo",
    "iso:country":"JP",
    "name:jpn_x_preferred":[
        "\u5916\u5c71"
    ],
    "wof:name":"Sodeyama",
    "wof:placetype":"locality"
},
  "geometry": {"coordinates":[140.66323,39.35312],"type":"Point"}
}