{
  "type": "Feature",
  "properties": {
    "gn:admin1_code":"30",
    "gn:admin2_code":"1855742.0",
    "gn:asciiname":"Imazu",
    "gn:country_code":"JP",
    "gn:dem":0,
    "gn:feature_class":"P",
    "gn:feature_code":"PPL",
    "gn:name":"Imazu",
    "gn:population":0,
    "gn:timezone":"Asia/Tokyo",
    "iso:country":"JP",
    "name:jpn_x_preferred":[
        "\u4eca\u6d25"
    ],
    "wof:name":"Imazu",
    "wof:placetype":"locality"
},
  "geometry": {"coordinates":[131.26442,33.58222],"type":"Point"}
}