{
  "type": "Feature",
  "properties": {
    "gn:admin1_code":"21.0",
    "gn:admin2_code":"1864975.0",
    "gn:admin3_code":"43428.0",
    "gn:asciiname":"Naganoharu",
    "gn:country_code":"JP",
    "gn:dem":628,
    "gn:feature_class":"P",
    "gn:feature_code":"PPL",
    "gn:name":"Naganoharu",
    "gn:population":0,
    "gn:timezone":"Asia/Tokyo",
    "iso:country":"JP",
    "name:jpn_x_preferred":[
        "\u6c38\u91ce\u539f"
    ],
    "name:jpn_x_variant":[
        "\u306a\u304c\u306e\u306f\u308b",
        "\u30ca\u30ac\u30ce\u30cf\u30eb"
    ],
    "wof:name":"Naganoharu",
    "wof:placetype":"locality"
},
  "geometry": {"coordinates":[131.22386,32.78713],"type":"Point"}
}