{
  "type": "Feature",
  "properties": {
    "gn:country":"JP",
    "gn:fcode":"ADM3",
    "gn:population":0,
    "iso:country":"JP",
    "name:eng_x_preferred":[
        "Y\u014dr\u014d"
    ],
    "name:eng_x_variant":[
        "Y\u014dr\u014d-ch\u014d"
    ],
    "name:jpn_x_preferred":[
        "Y\u014dr\u014d-ch\u014d"
    ],
    "name:jpn_x_variant":[
        "\u990a\u8001\u753a",
        "\u3088\u3046\u308d\u3046\u3061\u3087\u3046"
    ],
    "qs:name":"Y\u014dr\u014d-ch\u014d",
    "qs:photos_9r":0,
    "qs:photos_sr":0,
    "qs:pop_sr":"0",
    "wof:name":"Y\u014dr\u014d",
    "wof:placetype":"localadmin",
    "wof:population":0
},
  "geometry": {"coordinates":[136.56444999999999,35.29112],"type":"Point"}
}