{
  "type": "Feature",
  "properties": {
    "gn:admin1_code":"4.0",
    "gn:admin2_code":"7465524.0",
    "gn:asciiname":"Nagasaka",
    "gn:country_code":"JP",
    "gn:dem":37,
    "gn:feature_class":"P",
    "gn:feature_code":"PPLL",
    "gn:name":"Nagasaka",
    "gn:population":0,
    "gn:timezone":"Asia/Tokyo",
    "iso:country":"JP",
    "name:jpn_x_preferred":[
        "\u9577\u5742"
    ],
    "name:jpn_x_variant":[
        "\u306a\u304c\u3055\u304b",
        "\u30ca\u30ac\u30b5\u30ab"
    ],
    "wof:name":"Nagasaka",
    "wof:placetype":"locality"
},
  "geometry": {"coordinates":[140.30058,35.26258],"type":"Point"}
}