{
  "type": "Feature",
  "properties": {
    "gn:admin1_code":"12.0",
    "gn:admin2_code":"2128405.0",
    "gn:admin3_code":"1518.0",
    "gn:asciiname":"Kuzure",
    "gn:country_code":"JP",
    "gn:dem":49,
    "gn:feature_class":"P",
    "gn:feature_code":"PPLL",
    "gn:name":"Kuzure",
    "gn:population":0,
    "gn:timezone":"Asia/Tokyo",
    "iso:country":"JP",
    "name:jpn_x_preferred":[
        "\u4e45\u9023"
    ],
    "name:jpn_x_variant":[
        "\u304f\u3065\u308c",
        "\u30af\u30c5\u30ec"
    ],
    "name:und_x_variant":[
        "Kutsure",
        "Kuzure"
    ],
    "wof:name":"Kuzure",
    "wof:placetype":"locality"
},
  "geometry": {"coordinates":[141.16394,45.14641],"type":"Point"}
}