{
  "type": "Feature",
  "properties": {
    "gn:admin1_code":"21.0",
    "gn:admin2_code":"1848441.0",
    "gn:asciiname":"Hamamuta",
    "gn:country_code":"JP",
    "gn:dem":8,
    "gn:feature_class":"P",
    "gn:feature_code":"PPLL",
    "gn:name":"Hamamuta",
    "gn:population":0,
    "gn:timezone":"Asia/Tokyo",
    "iso:country":"JP",
    "name:jpn_x_preferred":[
        "\u6d5c\u725f\u7530"
    ],
    "name:jpn_x_variant":[
        "\u306f\u307e\u3080\u305f",
        "\u30cf\u30de\u30e0\u30bf"
    ],
    "wof:name":"Hamamuta",
    "wof:placetype":"locality"
},
  "geometry": {"coordinates":[130.66269,32.57482],"type":"Point"}
}