{
  "type": "Feature",
  "properties": {
    "iso:country":"JP",
    "name:eng_x_preferred":[
        "Ekinan 4 Chome"
    ],
    "name:eng_x_variant":[
        "Ekinan 4 Choume",
        "Ekinan 4 Chome"
    ],
    "name:jpn_x_preferred":[
        "\uff14\u4e01\u76ee"
    ],
    "name:jpn_x_variant":[
        "\u3048\u304d\u306a\u3093 \uff14\u3061\u3087\u3046\u3081",
        "\u99c5\u5357 \uff14\u4e01\u76ee",
        "\uff14\u3061\u3087\u3046\u3081"
    ],
    "name:unk_x_variant":[
        "\uff14\u4e01\u76ee"
    ],
    "qs:gn_local":0,
    "qs:local_max":167,
    "qs:local_sum":381,
    "qs:localhoods":5,
    "qs:name":"\uff14\u4e01\u76ee",
    "qs:name_adm0":"\u65e5\u672c",
    "qs:name_adm1":"\u5bcc\u5c71\u770c",
    "qs:name_en":"Ekinan 4 Chome",
    "qs:name_lau":"\u99c5\u5357",
    "qs:name_local":"\u9ad8\u5ca1\u5e02",
    "qs:photo_max":54,
    "qs:photo_sum":57,
    "qs:placetype":"Suburb",
    "qs:quad_count":3,
    "qs:woe_adm0":23424856,
    "qs:woe_adm1":2345891,
    "qs:woe_adm2":0,
    "qs:woe_lau":28423963,
    "qs:woe_local":1118292,
    "qs:woe_ver":"7.10.0",
    "wof:lang":[
        "jpn"
    ],
    "wof:name":"\uff14\u4e01\u76ee",
    "wof:placetype":"neighbourhood"
},
  "geometry": {"coordinates":[137.01199199999999,36.735448],"type":"Point"}
}