{
  "type": "Feature",
  "properties": {
    "gn:admin1_code":"12.0",
    "gn:admin2_code":"2128405.0",
    "gn:admin3_code":"1518.0",
    "gn:asciiname":"Sakaehama",
    "gn:country_code":"JP",
    "gn:dem":13,
    "gn:feature_class":"P",
    "gn:feature_code":"PPLL",
    "gn:name":"Sakaehama",
    "gn:population":0,
    "gn:timezone":"Asia/Tokyo",
    "iso:country":"JP",
    "name:jpn_x_preferred":[
        "\u6804\u6d5c"
    ],
    "name:jpn_x_variant":[
        "\u3055\u304b\u3048\u306f\u307e",
        "\u30b5\u30ab\u30a8\u30cf\u30de"
    ],
    "name:und_x_variant":[
        "Hinaka",
        "Sakaehama"
    ],
    "wof:name":"Sakaehama",
    "wof:placetype":"locality"
},
  "geometry": {"coordinates":[141.14233000000004,45.21847],"type":"Point"}
}