{
  "type": "Feature",
  "properties": {
    "iso:country":"JP",
    "qs:name":"\u5927\u6d17\u753a",
    "qs:name_adm0":"\u65e5\u672c",
    "qs:name_adm1":"\u8328\u57ce\u770c",
    "qs:photos":448,
    "qs:photos_1k":91,
    "qs:photos_9k":2,
    "qs:photos_9r":5,
    "qs:photos_all":448,
    "qs:photos_sr":6,
    "qs:placetype":"Town",
    "qs:pop_sr":"0",
    "wof:name":"\u5927\u6d17\u753a",
    "wof:placetype":"locality"
},
  "geometry": {"coordinates":[140.56818000000001,36.310975],"type":"Point"}
}