{
  "type": "Feature",
  "properties": {
    "iso:country":"JP",
    "name:eng_x_preferred":[
        "Akatsukidai 1 Chome"
    ],
    "name:eng_x_variant":[
        "Akatsukidai 1 Choume",
        "Akatsukidai 1 Chome"
    ],
    "name:jpn_x_preferred":[
        "\uff11\u4e01\u76ee"
    ],
    "name:jpn_x_variant":[
        "\u3042\u304b\u3064\u304d\u3060\u3044 \uff11\u3061\u3087\u3046\u3081",
        "\u3042\u304b\u3064\u304d\u53f0 \uff11\u4e01\u76ee",
        "\uff11\u3061\u3087\u3046\u3081"
    ],
    "qs:gn_local":0,
    "qs:local_max":87,
    "qs:local_sum":321,
    "qs:localhoods":7,
    "qs:name":"\uff11\u4e01\u76ee",
    "qs:name_adm0":"\u65e5\u672c",
    "qs:name_adm1":"\u4e09\u91cd\u770c",
    "qs:name_en":"Akatsukidai 1 Chome",
    "qs:name_lau":"\u3042\u304b\u3064\u304d\u53f0",
    "qs:name_local":"\u56db\u65e5\u5e02\u5e02",
    "qs:photo_max":25,
    "qs:photo_sum":47,
    "qs:placetype":"Suburb",
    "qs:quad_count":4,
    "qs:woe_adm0":23424856,
    "qs:woe_adm1":2345872,
    "qs:woe_adm2":0,
    "qs:woe_lau":28445834,
    "qs:woe_local":1118548,
    "qs:woe_ver":"7.10.0",
    "wof:lang":[
        "jpn"
    ],
    "wof:name":"\uff11\u4e01\u76ee",
    "wof:placetype":"neighbourhood"
},
  "geometry": {"coordinates":[136.59284,35.018558],"type":"Point"}
}