{
  "type": "Feature",
  "properties": {
    "gn:admin1_code":"13",
    "gn:admin2_code":"7370819.0",
    "gn:asciiname":"Nojima-hikinoura",
    "gn:country_code":"JP",
    "gn:dem":10,
    "gn:feature_class":"P",
    "gn:feature_code":"PPL",
    "gn:name":"Nojima-hikinoura",
    "gn:population":0,
    "gn:timezone":"Asia/Tokyo",
    "iso:country":"JP",
    "name:jpn_x_preferred":[
        "\u91ce\u5cf6\u87c7\u6d66"
    ],
    "name:und_x_variant":[
        "Nojima",
        "Hikiura",
        "Hikinoura",
        "Nojima-hikinoura"
    ],
    "wof:name":"Nojima-hikinoura",
    "wof:placetype":"locality"
},
  "geometry": {"coordinates":[134.94589999999999,34.55594],"type":"Point"}
}