{
  "type": "Feature",
  "properties": {
    "gn:admin1_code":"21.0",
    "gn:admin2_code":"1865358.0",
    "gn:asciiname":"Naka",
    "gn:country_code":"JP",
    "gn:dem":30,
    "gn:feature_class":"P",
    "gn:feature_code":"PPLL",
    "gn:name":"Naka",
    "gn:population":0,
    "gn:timezone":"Asia/Tokyo",
    "iso:country":"JP",
    "name:ceb_x_preferred":[
        "Naka"
    ],
    "name:deu_x_preferred":[
        "Naka"
    ],
    "name:fin_x_preferred":[
        "Naka"
    ],
    "name:fra_x_preferred":[
        "Naka"
    ],
    "name:hun_x_preferred":[
        "Naka"
    ],
    "name:jpn_x_preferred":[
        "\u4e2d"
    ],
    "name:jpn_x_variant":[
        "\u306a\u304b",
        "\u30ca\u30ab"
    ],
    "name:mlg_x_preferred":[
        "Naka"
    ],
    "name:nep_x_preferred":[
        "\u0928\u093e\u0915"
    ],
    "name:nld_x_preferred":[
        "Naka"
    ],
    "name:pol_x_preferred":[
        "Naka"
    ],
    "name:ron_x_preferred":[
        "Naka"
    ],
    "name:rus_x_preferred":[
        "\u041d\u0430\u043a\u0430"
    ],
    "name:spa_x_preferred":[
        "Naka"
    ],
    "name:swe_x_preferred":[
        "Naka"
    ],
    "name:ukr_x_preferred":[
        "\u041d\u0430\u043a\u0430"
    ],
    "wof:name":"Naka",
    "wof:placetype":"locality"
},
  "geometry": {"coordinates":[130.28440000000001,32.41107],"type":"Point"}
}