{
  "type": "Feature",
  "properties": {
    "gn:admin1_code":"21",
    "gn:admin2_code":"1858418.0",
    "gn:admin3_code":"43105.0",
    "gn:asciiname":"Yuge",
    "gn:country_code":"JP",
    "gn:dem":66,
    "gn:feature_class":"P",
    "gn:feature_code":"PPLL",
    "gn:name":"Yuge",
    "gn:population":0,
    "gn:timezone":"Asia/Tokyo",
    "iso:country":"JP",
    "name:ceb_x_preferred":[
        "Yuge"
    ],
    "name:jpn_x_preferred":[
        "\u5f13\u524a"
    ],
    "name:jpn_x_variant":[
        "\u3086\u3052",
        "\u30e6\u30b2"
    ],
    "wof:name":"Yuge",
    "wof:placetype":"locality"
},
  "geometry": {"coordinates":[130.77673999999999,32.84979000000001],"type":"Point"}
}