{
  "type": "Feature",
  "properties": {
    "gn:country":"JP",
    "gn:fcode":"PPL",
    "gn:population":19575,
    "iso:country":"JP",
    "name:ara_x_preferred":[
        "\u0645\u0648\u062a\u064a\u062c\u064a"
    ],
    "name:ast_x_preferred":[
        "Motegi"
    ],
    "name:ceb_x_preferred":[
        "Motegi"
    ],
    "name:ces_x_preferred":[
        "Motegi"
    ],
    "name:deu_x_preferred":[
        "Motegi"
    ],
    "name:eng_x_preferred":[
        "Motegi"
    ],
    "name:fas_x_preferred":[
        "\u0645\u0648\u062a\u06af\u06cc"
    ],
    "name:fra_x_preferred":[
        "Motegi"
    ],
    "name:ita_x_preferred":[
        "Motegi"
    ],
    "name:jpn_x_preferred":[
        "\u8302\u6728\u753a"
    ],
    "name:kor_x_preferred":[
        "\ubaa8\ud14c\uae30 \uc815"
    ],
    "name:kor_x_variant":[
        "\ubaa8\ud14c\uae30\uc815"
    ],
    "name:msa_x_preferred":[
        "Motegi"
    ],
    "name:mya_x_preferred":[
        "\u1019\u102d\u102f\u1010\u1032\u1002\u102d\u1019\u103c\u102d\u102f\u1037\u104a \u1010\u102d\u102f\u1001\u103b\u102d\u1002\u102d"
    ],
    "name:nld_x_preferred":[
        "Motegi"
    ],
    "name:por_x_preferred":[
        "Motegi"
    ],
    "name:rus_x_preferred":[
        "\u041c\u043e\u0442\u0435\u0433\u0438"
    ],
    "name:spa_x_preferred":[
        "Motegi"
    ],
    "name:tgl_x_preferred":[
        "Motegi"
    ],
    "name:ukr_x_preferred":[
        "\u041c\u043e\u0442\u0435\u0491\u0456"
    ],
    "name:zho_x_preferred":[
        "\u8302\u6728\u753a"
    ],
    "qs:name":"Motegi",
    "qs:photos_9r":0,
    "qs:photos_sr":0,
    "qs:pop_sr":"6",
    "wof:name":"Motegi",
    "wof:placetype":"locality",
    "wof:population":19575
},
  "geometry": {"coordinates":[140.18333000000001,36.51667],"type":"Point"}
}