{
  "type": "Feature",
  "properties": {
    "gn:admin1_code":"35",
    "gn:admin2_code":"1858063.0",
    "gn:asciiname":"Kataoka",
    "gn:country_code":"JP",
    "gn:dem":84,
    "gn:feature_class":"P",
    "gn:feature_code":"PPL",
    "gn:name":"Kataoka",
    "gn:population":0,
    "gn:timezone":"Asia/Tokyo",
    "iso:country":"JP",
    "wof:name":"Kataoka",
    "wof:placetype":"locality"
},
  "geometry": {"coordinates":[135.93333000000001,35.05],"type":"Point"}
}