{
  "type": "Feature",
  "properties": {
    "gn:admin1_code":"7.0",
    "gn:admin2_code":"1851269.0",
    "gn:admin3_code":"40610.0",
    "gn:asciiname":"Oura",
    "gn:country_code":"JP",
    "gn:dem":30,
    "gn:feature_class":"P",
    "gn:feature_code":"PPL",
    "gn:name":"\u014cura",
    "gn:population":0,
    "gn:timezone":"Asia/Tokyo",
    "iso:country":"JP",
    "name:ceb_x_preferred":[
        "Oura"
    ],
    "name:fra_x_preferred":[
        "Oura"
    ],
    "name:jpn_x_preferred":[
        "\u5927\u6d66"
    ],
    "name:swe_x_preferred":[
        "Oura"
    ],
    "name:und_x_variant":[
        "\u014cura"
    ],
    "wof:name":"Oura",
    "wof:placetype":"locality"
},
  "geometry": {"coordinates":[130.76929999999999,33.72027],"type":"Point"}
}