{
  "type": "Feature",
  "properties": {
    "gn:admin1_code":"15.0",
    "gn:admin2_code":"1860845.0",
    "gn:asciiname":"Kumasakamachi",
    "gn:country_code":"JP",
    "gn:dem":15,
    "gn:feature_class":"P",
    "gn:feature_code":"PPL",
    "gn:name":"Kumasakamachi",
    "gn:population":0,
    "gn:timezone":"Asia/Tokyo",
    "iso:country":"JP",
    "name:jpn_x_preferred":[
        "\u718a\u5742\u753a"
    ],
    "wof:name":"Kumasakamachi",
    "wof:placetype":"locality"
},
  "geometry": {"coordinates":[136.29828999999998,36.29089000000001],"type":"Point"}
}