{
  "type": "Feature",
  "properties": {
    "gn:admin1_code":"19.0",
    "gn:admin2_code":"1848350.0",
    "gn:admin3_code":"14104.0",
    "gn:asciiname":"Negishi-asahidai",
    "gn:country_code":"JP",
    "gn:dem":54,
    "gn:feature_class":"P",
    "gn:feature_code":"PPL",
    "gn:name":"Negishi-asahidai",
    "gn:population":0,
    "gn:timezone":"Asia/Tokyo",
    "iso:country":"JP",
    "name:jpn_x_preferred":[
        "\u6839\u5cb8\u65ed\u53f0"
    ],
    "name:jpn_x_variant":[
        "\u306d\u304e\u3057\u3042\u3055\u3072\u3060\u3044",
        "\u30cd\u30ae\u30b7\u30a2\u30b5\u30d2\u30c0\u30a4"
    ],
    "wof:name":"Negishi-asahidai",
    "wof:placetype":"locality"
},
  "geometry": {"coordinates":[139.63486,35.41959],"type":"Point"}
}