{
  "type": "Feature",
  "properties": {
    "gn:admin1_code":"4.0",
    "gn:admin2_code":"1861964.0",
    "gn:asciiname":"Osu",
    "gn:country_code":"JP",
    "gn:dem":4,
    "gn:feature_class":"P",
    "gn:feature_code":"PPL",
    "gn:name":"\u014csu",
    "gn:population":0,
    "gn:timezone":"Asia/Tokyo",
    "iso:country":"JP",
    "name:jpn_x_preferred":[
        "\u5927\u6d32"
    ],
    "name:und_x_variant":[
        "\u014csu"
    ],
    "name:zho_x_preferred":[
        "Osu"
    ],
    "wof:name":"Osu",
    "wof:placetype":"locality"
},
  "geometry": {"coordinates":[139.90941000000001,35.72018],"type":"Point"}
}