{
  "type": "Feature",
  "properties": {
    "gn:admin1_code":"23",
    "gn:admin2_code":"1850342.0",
    "gn:asciiname":"Toshi",
    "gn:country_code":"JP",
    "gn:dem":0,
    "gn:feature_class":"P",
    "gn:feature_code":"PPL",
    "gn:name":"T\u014dshi",
    "gn:population":0,
    "gn:timezone":"Asia/Tokyo",
    "iso:country":"JP",
    "name:fra_x_preferred":[
        "Toshi"
    ],
    "name:jpn_x_preferred":[
        "\u30c8\u30b7"
    ],
    "name:und_x_variant":[
        "T\u014dshi"
    ],
    "wof:name":"Toshi",
    "wof:placetype":"locality"
},
  "geometry": {"coordinates":[136.89895000000001,34.5232],"type":"Point"}
}