{
  "type": "Feature",
  "properties": {
    "gn:admin1_code":"24.0",
    "gn:admin2_code":"2112074.0",
    "gn:admin3_code":"4422.0",
    "gn:asciiname":"Tabuse",
    "gn:country_code":"JP",
    "gn:dem":20,
    "gn:feature_class":"P",
    "gn:feature_code":"PPL",
    "gn:name":"Tabuse",
    "gn:population":0,
    "gn:timezone":"Asia/Tokyo",
    "iso:country":"JP",
    "name:jpn_x_preferred":[
        "\u7530\u5e03\u65bd"
    ],
    "name:jpn_x_variant":[
        "\u305f\u3076\u305b",
        "\u30bf\u30d6\u30bb"
    ],
    "wof:name":"Tabuse",
    "wof:placetype":"locality"
},
  "geometry": {"coordinates":[141.03419,38.41065],"type":"Point"}
}