{
  "type": "Feature",
  "properties": {
    "gn:admin1_code":"42.0",
    "gn:admin2_code":"1851028.0",
    "gn:asciiname":"Nodewara",
    "gn:country_code":"JP",
    "gn:dem":137,
    "gn:feature_class":"P",
    "gn:feature_code":"PPL",
    "gn:name":"Nodewara",
    "gn:population":0,
    "gn:timezone":"Asia/Tokyo",
    "iso:country":"JP",
    "name:jpn_x_preferred":[
        "\u52dd\u6728\u539f"
    ],
    "wof:name":"Nodewara",
    "wof:placetype":"locality"
},
  "geometry": {"coordinates":[136.90894,36.77132],"type":"Point"}
}