{
  "type": "Feature",
  "properties": {
    "iso:country":"JP",
    "qs:name":"\uff11\u4e01\u76ee",
    "qs:name_adm0":"\u65e5\u672c",
    "qs:name_adm1":"\u798f\u5ca1\u770c",
    "qs:photos":673,
    "qs:photos_1k":136,
    "qs:photos_9k":3,
    "qs:photos_9r":5,
    "qs:photos_all":673,
    "qs:photos_sr":8,
    "qs:placetype":"Suburb",
    "qs:pop_sr":"0",
    "wof:name":"\uff11\u4e01\u76ee",
    "wof:placetype":"neighbourhood"
},
  "geometry": {"coordinates":[130.42065500000001,33.590114],"type":"Point"}
}