{
  "type": "Feature",
  "properties": {
    "gn:admin1_code":"19.0",
    "gn:admin2_code":"1848350.0",
    "gn:admin3_code":"14104.0",
    "gn:asciiname":"Onoecho",
    "gn:country_code":"JP",
    "gn:dem":15,
    "gn:feature_class":"P",
    "gn:feature_code":"PPL",
    "gn:name":"Onoech\u014d",
    "gn:population":0,
    "gn:timezone":"Asia/Tokyo",
    "iso:country":"JP",
    "name:jpn_x_preferred":[
        "\u5c3e\u4e0a\u753a"
    ],
    "name:jpn_x_variant":[
        "\u304a\u306e\u3048\u3061\u3087\u3046",
        "\u30aa\u30ce\u30a8\u30c1\u30e7\u30a6"
    ],
    "name:und_x_variant":[
        "Onoech\u014d"
    ],
    "wof:name":"Onoecho",
    "wof:placetype":"locality"
},
  "geometry": {"coordinates":[139.63378,35.44784],"type":"Point"}
}