{
  "type": "Feature",
  "properties": {
    "gn:admin1_code":"6.0",
    "gn:admin2_code":"1863982.0",
    "gn:asciiname":"Miyama-otanicho",
    "gn:country_code":"JP",
    "gn:dem":191,
    "gn:feature_class":"P",
    "gn:feature_code":"PPL",
    "gn:name":"Miyama-\u014dtanich\u014d",
    "gn:population":0,
    "gn:timezone":"Asia/Tokyo",
    "iso:country":"JP",
    "name:jpn_x_preferred":[
        "\u7f8e\u5c71\u5927\u8c37\u753a"
    ],
    "name:und_x_variant":[
        "Miyama-\u014dtanich\u014d"
    ],
    "wof:name":"Miyama-otanicho",
    "wof:placetype":"locality"
},
  "geometry": {"coordinates":[136.39598000000001,36.02813],"type":"Point"}
}