{
  "type": "Feature",
  "properties": {
    "gn:admin1_code":"43.0",
    "gn:admin2_code":"1860782.0",
    "gn:asciiname":"Shimotsucho-momogaito",
    "gn:country_code":"JP",
    "gn:dem":124,
    "gn:feature_class":"P",
    "gn:feature_code":"PPL",
    "gn:name":"Shimotsuch\u014d-momogaito",
    "gn:population":0,
    "gn:timezone":"Asia/Tokyo",
    "iso:country":"JP",
    "name:jpn_x_preferred":[
        "\u4e0b\u6d25\u753a\u767e\u57a3\u5185"
    ],
    "name:und_x_variant":[
        "Shimotsuch\u014d-momogaito"
    ],
    "wof:name":"Shimotsucho-momogaito",
    "wof:placetype":"locality"
},
  "geometry": {"coordinates":[135.18812,34.11862],"type":"Point"}
}