{
  "type": "Feature",
  "properties": {
    "gn:country":"JP",
    "iso:country":"JP",
    "label:eng_x_preferred_longname":[
        "Tomigusuku City"
    ],
    "label:eng_x_preferred_placetype":[
        "city"
    ],
    "name:eng_x_preferred":[
        "Tomigusuku"
    ],
    "name:eng_x_variant":[
        "Tomigusuku City"
    ],
    "name:jpn_x_preferred":[
        "\u8c4a\u898b\u57ce\u5e02"
    ],
    "qs:name":"\u8c4a\u898b\u57ce\u5e02",
    "qs:name_adm0":"\u65e5\u672c",
    "qs:name_adm1":"\u6c96\u7e04\u770c",
    "qs:photos":5000,
    "qs:photos_1k":1000,
    "qs:photos_9k":22,
    "qs:photos_9r":14,
    "qs:photos_all":5000,
    "qs:photos_sr":24,
    "qs:placetype":"Town",
    "qs:pop_sr":"0",
    "wof:name":"Tomigusuku",
    "wof:placetype":"locality"
},
  "geometry": {"coordinates":[127.662442,26.144931],"type":"Point"}
}