{
  "type": "Feature",
  "properties": {
    "iso:country":"JP",
    "label:eng_x_preferred_longname":[
        "Yamazoe Village"
    ],
    "label:eng_x_preferred_placetype":[
        "village"
    ],
    "name:eng_x_preferred":[
        "Yamazoe"
    ],
    "name:eng_x_variant":[
        "Yamazoe Village"
    ],
    "name:jpn_x_preferred":[
        "\u5c71\u6dfb\u6751"
    ],
    "qs:name":"\u5c71\u6dfb\u6751",
    "qs:name_adm0":"\u65e5\u672c",
    "qs:name_adm1":"\u5948\u826f\u770c",
    "qs:photos":50,
    "qs:photos_1k":10,
    "qs:photos_9k":1,
    "qs:photos_9r":2,
    "qs:photos_all":50,
    "qs:photos_sr":2,
    "qs:placetype":"Town",
    "qs:pop_sr":"0",
    "wof:name":"Yamazoe",
    "wof:placetype":"locality"
},
  "geometry": {"coordinates":[136.03559999999999,34.674511],"type":"Point"}
}