{
  "type": "Feature",
  "properties": {
    "gn:admin1_code":"37.0",
    "gn:admin2_code":"1864104.0",
    "gn:asciiname":"Mitsumuro",
    "gn:country_code":"JP",
    "gn:dem":182,
    "gn:feature_class":"P",
    "gn:feature_code":"PPLL",
    "gn:name":"Mitsumuro",
    "gn:population":0,
    "gn:timezone":"Asia/Tokyo",
    "iso:country":"JP",
    "name:jpn_x_preferred":[
        "\u4e09\u5ba4\u3000"
    ],
    "wof:name":"Mitsumuro",
    "wof:placetype":"locality"
},
  "geometry": {"coordinates":[138.63768000000002,35.23121],"type":"Point"}
}