{
  "type": "Feature",
  "properties": {
    "iso:country":"JP",
    "name:eng_x_preferred":[
        "Ichiwaki 3 Chome"
    ],
    "name:eng_x_variant":[
        "Ichiwaki 3 Choume",
        "Ichiwaki 3 Chome"
    ],
    "name:jpn_x_preferred":[
        "\uff13\u4e01\u76ee"
    ],
    "name:jpn_x_variant":[
        "\u3044\u3061\u308f\u304d \uff13\u3061\u3087\u3046\u3081",
        "\u5e02\u8107 \uff13\u4e01\u76ee",
        "\uff13\u3061\u3087\u3046\u3081"
    ],
    "qs:gn_local":0,
    "qs:local_max":12,
    "qs:local_sum":14,
    "qs:localhoods":2,
    "qs:name":"\uff13\u4e01\u76ee",
    "qs:name_adm0":"\u65e5\u672c",
    "qs:name_adm1":"\u548c\u6b4c\u5c71\u770c",
    "qs:name_en":"Ichiwaki 3 Chome",
    "qs:name_lau":"\u5e02\u8107",
    "qs:name_local":"\u6a4b\u672c\u5e02",
    "qs:photo_max":2,
    "qs:photo_sum":2,
    "qs:placetype":"Suburb",
    "qs:quad_count":1,
    "qs:woe_adm0":23424856,
    "qs:woe_adm1":2345892,
    "qs:woe_adm2":0,
    "qs:woe_lau":28468032,
    "qs:woe_local":1117171,
    "qs:woe_ver":"7.10.0",
    "wof:lang":[
        "jpn"
    ],
    "wof:name":"\uff13\u4e01\u76ee",
    "wof:placetype":"neighbourhood"
},
  "geometry": {"coordinates":[135.59051500000001,34.300339],"type":"Point"}
}