{
  "type": "Feature",
  "properties": {
    "gn:admin1_code":"40.0",
    "gn:admin2_code":"1864514.0",
    "gn:asciiname":"Kikunodai",
    "gn:country_code":"JP",
    "gn:dem":35,
    "gn:feature_class":"P",
    "gn:feature_code":"PPL",
    "gn:name":"Kikunodai",
    "gn:population":0,
    "gn:timezone":"Asia/Tokyo",
    "iso:country":"JP",
    "name:jpn_x_preferred":[
        "\u83ca\u91ce\u53f0"
    ],
    "wof:name":"Kikunodai",
    "wof:placetype":"locality"
},
  "geometry": {"coordinates":[139.56826999999998,35.65252],"type":"Point"}
}