{
  "type": "Feature",
  "properties": {
    "gn:admin1_code":"21.0",
    "gn:admin2_code":"1864975.0",
    "gn:admin3_code":"43425.0",
    "gn:asciiname":"Ori-himuki",
    "gn:country_code":"JP",
    "gn:dem":554,
    "gn:feature_class":"P",
    "gn:feature_code":"PPLL",
    "gn:name":"\u014cri-himuki",
    "gn:population":0,
    "gn:timezone":"Asia/Tokyo",
    "iso:country":"JP",
    "name:jpn_x_preferred":[
        "\u5927\u5229\u65e5\u5411"
    ],
    "name:jpn_x_variant":[
        "\u304a\u304a\u308a\u3072\u3080\u304d",
        "\u30aa\u30aa\u30ea\u30d2\u30e0\u30ad"
    ],
    "name:und_x_variant":[
        "\u014cri-himuki"
    ],
    "wof:name":"Ori-himuki",
    "wof:placetype":"locality"
},
  "geometry": {"coordinates":[131.23795000000001,32.97854],"type":"Point"}
}