{
  "type": "Feature",
  "properties": {
    "iso:country":"JP",
    "name:eng_x_preferred":[
        "Aobadai 1 Chome"
    ],
    "name:eng_x_variant":[
        "Aobadai 1 Choume",
        "Aobadai 1 Chome"
    ],
    "name:jpn_x_preferred":[
        "\uff11\u4e01\u76ee"
    ],
    "name:jpn_x_variant":[
        "\u3042\u304a\u3070\u3060\u3044 \uff11\u3061\u3087\u3046\u3081",
        "\u9752\u8449\u53f0 \uff11\u4e01\u76ee",
        "\uff11\u3061\u3087\u3046\u3081"
    ],
    "name:unk_x_variant":[
        "\uff11\u4e01\u76ee"
    ],
    "qs:gn_adm0_cc":"JP",
    "qs:gn_local":1855207,
    "qs:gn_nam_loc":"\u897f\u5bae\u5e02, \u5175\u5eab\u770c, JP",
    "qs:gn_namadm1":"13",
    "qs:local_max":870,
    "qs:local_sum":3110,
    "qs:localhoods":22,
    "qs:name":"\uff11\u4e01\u76ee",
    "qs:name_adm0":"\u65e5\u672c",
    "qs:name_adm1":"\u5175\u5eab\u770c",
    "qs:name_en":"Aobadai 1 Chome",
    "qs:name_lau":"\u9752\u8449\u53f0",
    "qs:name_local":"\u897f\u5bae\u5e02",
    "qs:photo_max":6,
    "qs:photo_sum":18,
    "qs:placetype":"Suburb",
    "qs:quad_count":5,
    "qs:woe_adm0":23424856,
    "qs:woe_adm1":2345862,
    "qs:woe_adm2":0,
    "qs:woe_lau":28462438,
    "qs:woe_local":1112962,
    "qs:woe_ver":"7.10.0",
    "wof:lang":[
        "jpn"
    ],
    "wof:name":"\uff11\u4e01\u76ee",
    "wof:placetype":"neighbourhood"
},
  "geometry": {"coordinates":[135.31616199999999,34.823825],"type":"Point"}
}