{
  "type": "Feature",
  "properties": {
    "gn:admin1_code":"21.0",
    "gn:admin2_code":"1850743.0",
    "gn:asciiname":"Yokoshimamachi-ozono",
    "gn:country_code":"JP",
    "gn:dem":3,
    "gn:feature_class":"P",
    "gn:feature_code":"PPL",
    "gn:name":"Yokoshimamachi-\u014dzono",
    "gn:population":0,
    "gn:timezone":"Asia/Tokyo",
    "iso:country":"JP",
    "name:jpn_x_preferred":[
        "\u6a2a\u5cf6\u753a\u5927\u5712"
    ],
    "name:jpn_x_variant":[
        "\u3088\u3053\u3057\u307e\u307e\u3061\u304a\u304a\u305e\u306e",
        "\u30e8\u30b3\u30b7\u30de\u30de\u30c1\u30aa\u30aa\u30be\u30ce"
    ],
    "name:und_x_variant":[
        "Yokoshimamachi-\u014dzono"
    ],
    "wof:name":"Yokoshimamachi-ozono",
    "wof:placetype":"locality"
},
  "geometry": {"coordinates":[130.55850000000001,32.88638],"type":"Point"}
}