{
  "type": "Feature",
  "properties": {
    "gn:admin1_code":"17.0",
    "gn:admin2_code":"1851095.0",
    "gn:asciiname":"Shionoe-yasuhara-kamihigashi",
    "gn:country_code":"JP",
    "gn:dem":308,
    "gn:feature_class":"P",
    "gn:feature_code":"PPL",
    "gn:name":"Shionoe-yasuhara-kamihigashi",
    "gn:population":0,
    "gn:timezone":"Asia/Tokyo",
    "iso:country":"JP",
    "name:jpn_x_preferred":[
        "\u5869\u6c5f\u5b89\u539f\u4e0a\u6771"
    ],
    "wof:name":"Shionoe-yasuhara-kamihigashi",
    "wof:placetype":"locality"
},
  "geometry": {"coordinates":[134.09607,34.17298],"type":"Point"}
}