{
  "type": "Feature",
  "properties": {
    "gn:admin1_code":"21.0",
    "gn:admin2_code":"1865358.0",
    "gn:asciiname":"Ochi",
    "gn:country_code":"JP",
    "gn:dem":63,
    "gn:feature_class":"P",
    "gn:feature_code":"PPLL",
    "gn:name":"\u014cchi",
    "gn:population":0,
    "gn:timezone":"Asia/Tokyo",
    "iso:country":"JP",
    "name:jpn_x_preferred":[
        "\u5927\u5730"
    ],
    "name:jpn_x_variant":[
        "\u304a\u304a\u3061",
        "\u30aa\u30aa\u30c1"
    ],
    "name:und_x_variant":[
        "\u014cchi"
    ],
    "wof:name":"Ochi",
    "wof:placetype":"locality"
},
  "geometry": {"coordinates":[130.15518,32.43697],"type":"Point"}
}