{
  "type": "Feature",
  "properties": {
    "gn:admin1_code":"3.0",
    "gn:admin2_code":"2130654.0",
    "gn:asciiname":"Sentomicho",
    "gn:country_code":"JP",
    "gn:dem":8,
    "gn:feature_class":"P",
    "gn:feature_code":"PPL",
    "gn:name":"Sentomich\u014d",
    "gn:population":0,
    "gn:timezone":"Asia/Tokyo",
    "iso:country":"JP",
    "name:jpn_x_preferred":[
        "\u5343\u5bcc\u753a"
    ],
    "name:jpn_x_variant":[
        "\u305b\u3093\u3068\u307f\u3061\u3087\u3046",
        "\u30bb\u30f3\u30c8\u30df\u30c1\u30e7\u30a6"
    ],
    "name:und_x_variant":[
        "Sentomich\u014d"
    ],
    "wof:name":"Sentomicho",
    "wof:placetype":"locality"
},
  "geometry": {"coordinates":[140.72645,40.8157],"type":"Point"}
}