{
  "type": "Feature",
  "properties": {
    "iso:country":"JP",
    "qs:name":"\u5927\u548c\u9ad8\u7530\u5e02",
    "qs:name_adm0":"\u65e5\u672c",
    "qs:name_adm1":"\u5948\u826f\u770c",
    "qs:photos":17,
    "qs:photos_1k":3,
    "qs:photos_9k":1,
    "qs:photos_9r":2,
    "qs:photos_all":58,
    "qs:photos_sr":1,
    "qs:placetype":"Town",
    "qs:pop_sr":"0",
    "wof:name":"\u5927\u548c\u9ad8\u7530\u5e02",
    "wof:placetype":"locality"
},
  "geometry": {"coordinates":[135.75462300000001,34.516573],"type":"Point"}
}