{
  "type": "Feature",
  "properties": {
    "gn:admin1_code":"19.0",
    "gn:admin2_code":"1863429.0",
    "gn:asciiname":"Shimojuku",
    "gn:country_code":"JP",
    "gn:dem":153,
    "gn:feature_class":"P",
    "gn:feature_code":"PPLL",
    "gn:name":"Shimojuku",
    "gn:population":0,
    "gn:timezone":"Asia/Tokyo",
    "iso:country":"JP",
    "name:jpn_x_preferred":[
        "\u4e0b\u5bbf"
    ],
    "wof:name":"Shimojuku",
    "wof:placetype":"locality"
},
  "geometry": {"coordinates":[139.21746000000002,35.38828],"type":"Point"}
}