{
  "type": "Feature",
  "properties": {
    "gn:admin1_code":"46.0",
    "gn:admin2_code":"1857168.0",
    "gn:admin3_code":"19366.0",
    "gn:asciiname":"Yokozawa",
    "gn:country_code":"JP",
    "gn:dem":131,
    "gn:feature_class":"P",
    "gn:feature_code":"PPLL",
    "gn:name":"Yokozawa",
    "gn:population":0,
    "gn:timezone":"Asia/Tokyo",
    "iso:country":"JP",
    "name:jpn_x_preferred":[
        "\u6a2a\u6ca2"
    ],
    "wof:name":"Yokozawa",
    "wof:placetype":"locality"
},
  "geometry": {"coordinates":[138.51107999999999,35.22161],"type":"Point"}
}