{
  "type": "Feature",
  "properties": {
    "gn:admin1_code":"8.0",
    "gn:admin2_code":"9035647.0",
    "gn:asciiname":"Funehikimachi-kitautsushi",
    "gn:country_code":"JP",
    "gn:dem":502,
    "gn:feature_class":"P",
    "gn:feature_code":"PPL",
    "gn:name":"Funehikimachi-kitautsushi",
    "gn:population":0,
    "gn:timezone":"Asia/Tokyo",
    "iso:country":"JP",
    "name:jpn_x_preferred":[
        "\u8239\u5f15\u753a\u5317\u79fb"
    ],
    "wof:name":"Funehikimachi-kitautsushi",
    "wof:placetype":"locality"
},
  "geometry": {"coordinates":[140.63464999999999,37.51876],"type":"Point"}
}