{
  "type": "Feature",
  "properties": {
    "gn:admin1_code":"39",
    "gn:admin2_code":"1850156.0",
    "gn:asciiname":"Shomachi",
    "gn:country_code":"JP",
    "gn:dem":7,
    "gn:feature_class":"P",
    "gn:feature_code":"PPL",
    "gn:name":"Sh\u014dmachi",
    "gn:population":0,
    "gn:timezone":"Asia/Tokyo",
    "iso:country":"JP",
    "name:jpn_x_preferred":[
        "\u5e84\u753a"
    ],
    "name:und_x_variant":[
        "Sh\u014d",
        "Sho-cho",
        "Sh\u014dmachi"
    ],
    "wof:name":"Shomachi",
    "wof:placetype":"locality"
},
  "geometry": {"coordinates":[134.51023999999998,34.07662],"type":"Point"}
}