{
  "type": "Feature",
  "properties": {
    "gn:admin1_code":"19.0",
    "gn:admin2_code":"1848350.0",
    "gn:admin3_code":"14104.0",
    "gn:asciiname":"Uchikoshi",
    "gn:country_code":"JP",
    "gn:dem":32,
    "gn:feature_class":"P",
    "gn:feature_code":"PPL",
    "gn:name":"Uchikoshi",
    "gn:population":0,
    "gn:timezone":"Asia/Tokyo",
    "iso:country":"JP",
    "name:jpn_x_preferred":[
        "\u6253\u8d8a"
    ],
    "name:jpn_x_variant":[
        "\u3046\u3061\u3053\u3057",
        "\u30a6\u30c1\u30b3\u30b7"
    ],
    "wof:name":"Uchikoshi",
    "wof:placetype":"locality"
},
  "geometry": {"coordinates":[139.63799,35.43447000000001],"type":"Point"}
}