{
  "type": "Feature",
  "properties": {
    "gn:admin1_code":"2.0",
    "gn:admin2_code":"2113122.0",
    "gn:asciiname":"Gyoninzawa",
    "gn:country_code":"JP",
    "gn:dem":58,
    "gn:feature_class":"P",
    "gn:feature_code":"PPL",
    "gn:name":"Gy\u014dninzawa",
    "gn:population":0,
    "gn:timezone":"Asia/Tokyo",
    "iso:country":"JP",
    "name:jpn_x_preferred":[
        "\u884c\u4eba\u6ca2"
    ],
    "name:jpn_x_variant":[
        "\u304e\u3087\u3046\u306b\u3093\u3056\u308f",
        "\u30ae\u30e7\u30a6\u30cb\u30f3\u30b6\u30ef",
        "\u4e0b\u5c0f\u53c8"
    ],
    "name:und_x_variant":[
        "Gy\u014dninzawa",
        "Shimoomata"
    ],
    "wof:name":"Gyoninzawa",
    "wof:placetype":"locality"
},
  "geometry": {"coordinates":[140.13543999999999,39.80978],"type":"Point"}
}