{
  "type": "Feature",
  "properties": {
    "iso:country":"JP",
    "qs:name":"\u963f\u898b\u753a",
    "qs:name_adm0":"\u65e5\u672c",
    "qs:name_adm1":"\u8328\u57ce\u770c",
    "qs:photos":130,
    "qs:photos_1k":26,
    "qs:photos_9k":4,
    "qs:photos_9r":6,
    "qs:photos_all":873,
    "qs:photos_sr":3,
    "qs:placetype":"Town",
    "qs:pop_sr":"0",
    "wof:name":"\u963f\u898b\u753a",
    "wof:placetype":"locality"
},
  "geometry": {"coordinates":[140.22030649999999,35.983006],"type":"Point"}
}