{
  "type": "Feature",
  "properties": {
    "gn:admin1_code":"26.0",
    "gn:admin2_code":"1853055.0",
    "gn:asciiname":"Hirogawara",
    "gn:country_code":"JP",
    "gn:dem":761,
    "gn:feature_class":"P",
    "gn:feature_code":"PPLL",
    "gn:name":"Hirogawara",
    "gn:population":0,
    "gn:timezone":"Asia/Tokyo",
    "iso:country":"JP",
    "name:jpn_x_preferred":[
        "\u5e83\u5ddd\u539f"
    ],
    "wof:name":"Hirogawara",
    "wof:placetype":"locality"
},
  "geometry": {"coordinates":[138.61474999999999,36.17806],"type":"Point"}
}