{
  "type": "Feature",
  "properties": {
    "gn:admin1_code":"2.0",
    "gn:admin2_code":"2113122.0",
    "gn:asciiname":"Narayama-jonanmachi",
    "gn:country_code":"JP",
    "gn:dem":17,
    "gn:feature_class":"P",
    "gn:feature_code":"PPL",
    "gn:name":"Narayama-j\u014dnanmachi",
    "gn:population":0,
    "gn:timezone":"Asia/Tokyo",
    "iso:country":"JP",
    "name:jpn_x_preferred":[
        "\u6962\u5c71\u57ce\u5357\u753a"
    ],
    "name:jpn_x_variant":[
        "\u306a\u3089\u3084\u307e\u3058\u3087\u3046\u306a\u3093\u307e\u3061",
        "\u30ca\u30e9\u30e4\u30de\u30b8\u30e7\u30a6\u30ca\u30f3\u30de\u30c1"
    ],
    "name:und_x_variant":[
        "Narayama-j\u014dnanmachi"
    ],
    "wof:name":"Narayama-jonanmachi",
    "wof:placetype":"locality"
},
  "geometry": {"coordinates":[140.12629999999999,39.69974000000001],"type":"Point"}
}