{
  "type": "Feature",
  "properties": {
    "gn:admin1_code":"40.0",
    "gn:admin2_code":"1864148.0",
    "gn:asciiname":"Momijigaoka",
    "gn:country_code":"JP",
    "gn:dem":50,
    "gn:feature_class":"P",
    "gn:feature_code":"PPL",
    "gn:name":"Momijigaoka",
    "gn:population":0,
    "gn:timezone":"Asia/Tokyo",
    "iso:country":"JP",
    "name:jpn_x_preferred":[
        "\u7d05\u8449\u4e18"
    ],
    "wof:name":"Momijigaoka",
    "wof:placetype":"locality"
},
  "geometry": {"coordinates":[139.51143000000002,35.67527000000001],"type":"Point"}
}