{
  "type": "Feature",
  "properties": {
    "gn:admin1_code":"21.0",
    "gn:admin2_code":"7412706.0",
    "gn:admin3_code":"43447.0",
    "gn:asciiname":"Sendaki",
    "gn:country_code":"JP",
    "gn:dem":444,
    "gn:feature_class":"P",
    "gn:feature_code":"PPL",
    "gn:name":"Sendaki",
    "gn:population":0,
    "gn:timezone":"Asia/Tokyo",
    "iso:country":"JP",
    "name:jpn_x_preferred":[
        "\u5343\u6edd"
    ],
    "name:jpn_x_variant":[
        "\u305b\u3093\u3060\u304d",
        "\u30bb\u30f3\u30c0\u30ad"
    ],
    "wof:name":"Sendaki",
    "wof:placetype":"locality"
},
  "geometry": {"coordinates":[130.98273999999998,32.6795],"type":"Point"}
}