{
  "type": "Feature",
  "properties": {
    "gn:admin1_code":"12.0",
    "gn:admin2_code":"7428078.0",
    "gn:admin3_code":"1662.0",
    "gn:asciiname":"Wakatake",
    "gn:country_code":"JP",
    "gn:dem":4,
    "gn:feature_class":"P",
    "gn:feature_code":"PPL",
    "gn:name":"Wakatake",
    "gn:population":0,
    "gn:timezone":"Asia/Tokyo",
    "iso:country":"JP",
    "name:jpn_x_preferred":[
        "\u82e5\u7af9"
    ],
    "name:jpn_x_variant":[
        "\u308f\u304b\u305f\u3051",
        "\u30ef\u30ab\u30bf\u30b1"
    ],
    "wof:name":"Wakatake",
    "wof:placetype":"locality"
},
  "geometry": {"coordinates":[144.84604999999999,43.04071],"type":"Point"}
}