{
  "type": "Feature",
  "properties": {
    "gn:admin1_code":"3.0",
    "gn:admin2_code":"2130200.0",
    "gn:asciiname":"Nagane",
    "gn:country_code":"JP",
    "gn:dem":12,
    "gn:feature_class":"P",
    "gn:feature_code":"PPL",
    "gn:name":"Nagane",
    "gn:population":0,
    "gn:timezone":"Asia/Tokyo",
    "iso:country":"JP",
    "name:jpn_x_preferred":[
        "\u9577\u6839"
    ],
    "name:jpn_x_variant":[
        "\u306a\u304c\u306d",
        "\u30ca\u30ac\u30cd"
    ],
    "wof:name":"Nagane",
    "wof:placetype":"locality"
},
  "geometry": {"coordinates":[141.48088999999999,40.51443],"type":"Point"}
}