{
  "type": "Feature",
  "properties": {
    "gn:admin1_code":"19.0",
    "gn:admin2_code":"7470889.0",
    "gn:asciiname":"Sugikubokita",
    "gn:country_code":"JP",
    "gn:dem":38,
    "gn:feature_class":"P",
    "gn:feature_code":"PPL",
    "gn:name":"Sugikubokita",
    "gn:population":0,
    "gn:timezone":"Asia/Tokyo",
    "iso:country":"JP",
    "name:jpn_x_preferred":[
        "\u6749\u4e45\u4fdd\u5317"
    ],
    "wof:name":"Sugikubokita",
    "wof:placetype":"locality"
},
  "geometry": {"coordinates":[139.40178,35.42832999999999],"type":"Point"}
}