{
  "type": "Feature",
  "properties": {
    "iso:country":"JP",
    "label:eng_x_preferred_longname":[
        "Date City"
    ],
    "label:eng_x_preferred_placetype":[
        "city"
    ],
    "name:eng_x_preferred":[
        "Date"
    ],
    "name:eng_x_variant":[
        "Date City"
    ],
    "name:jpn_x_preferred":[
        "\u4f0a\u9054\u5e02"
    ],
    "qs:name":"\u4f0a\u9054\u5e02",
    "qs:name_adm0":"\u65e5\u672c",
    "qs:name_adm1":"\u5317\u6d77\u9053",
    "qs:photos":220,
    "qs:photos_1k":45,
    "qs:photos_9k":1,
    "qs:photos_9r":4,
    "qs:photos_all":220,
    "qs:photos_sr":4,
    "qs:placetype":"Town",
    "qs:pop_sr":"0",
    "wof:name":"Date",
    "wof:placetype":"locality"
},
  "geometry": {"coordinates":[141.02463800000001,42.625437],"type":"Point"}
}