{
  "type": "Feature",
  "properties": {
    "gn:admin1_code":"06",
    "gn:admin2_code":"1849587.0",
    "gn:asciiname":"Kutsu",
    "gn:country_code":"JP",
    "gn:dem":4,
    "gn:feature_class":"P",
    "gn:feature_code":"PPL",
    "gn:name":"Kutsu",
    "gn:population":0,
    "gn:timezone":"Asia/Tokyo",
    "iso:country":"JP",
    "name:und_x_variant":[
        "Kutu",
        "Kutsu"
    ],
    "wof:name":"Kutsu",
    "wof:placetype":"locality"
},
  "geometry": {"coordinates":[136.03666000000001,35.69578],"type":"Point"}
}