{
  "type": "Feature",
  "properties": {
    "gn:admin1_code":"26.0",
    "gn:admin2_code":"1858856.0",
    "gn:asciiname":"Hachiman",
    "gn:country_code":"JP",
    "gn:dem":789,
    "gn:feature_class":"P",
    "gn:feature_code":"PPL",
    "gn:name":"Hachiman",
    "gn:population":0,
    "gn:timezone":"Asia/Tokyo",
    "iso:country":"JP",
    "name:jpn_x_preferred":[
        "\u516b\u5e61"
    ],
    "wof:name":"Hachiman",
    "wof:placetype":"locality"
},
  "geometry": {"coordinates":[138.46509,36.32509],"type":"Point"}
}