{
  "type": "Feature",
  "properties": {
    "gn:admin1_code":"32.0",
    "gn:admin2_code":"1859382.0",
    "gn:asciiname":"Midorocho",
    "gn:country_code":"JP",
    "gn:dem":15,
    "gn:feature_class":"P",
    "gn:feature_code":"PPL",
    "gn:name":"Midoroch\u014d",
    "gn:population":0,
    "gn:timezone":"Asia/Tokyo",
    "iso:country":"JP",
    "name:jpn_x_preferred":[
        "\u7b95\u571f\u8def\u753a"
    ],
    "name:und_x_variant":[
        "Midoroch\u014d"
    ],
    "wof:name":"Midorocho",
    "wof:placetype":"locality"
},
  "geometry": {"coordinates":[135.40871999999999,34.47598],"type":"Point"}
}