{
  "type": "Feature",
  "properties": {
    "gn:admin1_code":"19.0",
    "gn:admin2_code":"1864622.0",
    "gn:asciiname":"Nakamura",
    "gn:country_code":"JP",
    "gn:dem":19,
    "gn:feature_class":"P",
    "gn:feature_code":"PPLL",
    "gn:name":"Nakamura",
    "gn:population":0,
    "gn:timezone":"Asia/Tokyo",
    "iso:country":"JP",
    "name:jpn_x_preferred":[
        "\u4e2d\u6751"
    ],
    "wof:name":"Nakamura",
    "wof:placetype":"locality"
},
  "geometry": {"coordinates":[139.41603000000001,35.35339000000001],"type":"Point"}
}