{
  "type": "Feature",
  "properties": {
    "gn:admin1_code":"34.0",
    "gn:admin2_code":"1856987.0",
    "gn:asciiname":"Takasu",
    "gn:country_code":"JP",
    "gn:dem":3,
    "gn:feature_class":"P",
    "gn:feature_code":"PPL",
    "gn:name":"Takasu",
    "gn:population":0,
    "gn:timezone":"Asia/Tokyo",
    "iso:country":"JP",
    "name:jpn_x_preferred":[
        "\u9ad8\u5dde"
    ],
    "wof:name":"Takasu",
    "wof:placetype":"locality"
},
  "geometry": {"coordinates":[139.87960000000001,35.7875],"type":"Point"}
}