{
  "type": "Feature",
  "properties": {
    "gn:admin1_code":"6.0",
    "gn:admin2_code":"7467387.0",
    "gn:asciiname":"Sakaicho-gohon",
    "gn:country_code":"JP",
    "gn:dem":7,
    "gn:feature_class":"P",
    "gn:feature_code":"PPL",
    "gn:name":"Sakaich\u014d-gohon",
    "gn:population":0,
    "gn:timezone":"Asia/Tokyo",
    "iso:country":"JP",
    "name:jpn_x_preferred":[
        "\u5742\u4e95\u753a\u4e94\u672c"
    ],
    "name:und_x_variant":[
        "Sakaich\u014d-gohon"
    ],
    "wof:name":"Sakaicho-gohon",
    "wof:placetype":"locality"
},
  "geometry": {"coordinates":[136.22883000000002,36.17381],"type":"Point"}
}