{
  "type": "Feature",
  "properties": {
    "gn:admin1_code":"7.0",
    "gn:admin2_code":"1858305.0",
    "gn:admin3_code":"40402.0",
    "gn:asciiname":"Ninobu-funagawa",
    "gn:country_code":"JP",
    "gn:dem":6,
    "gn:feature_class":"P",
    "gn:feature_code":"PPLL",
    "gn:name":"Ninobu-funagawa",
    "gn:population":0,
    "gn:timezone":"Asia/Tokyo",
    "iso:country":"JP",
    "name:jpn_x_preferred":[
        "\u65b0\u5ef6\u821f\u5ddd"
    ],
    "wof:name":"Ninobu-funagawa",
    "wof:placetype":"locality"
},
  "geometry": {"coordinates":[130.67143000000002,33.79255999999999],"type":"Point"}
}