{
  "type": "Feature",
  "properties": {
    "gn:admin1_code":"4.0",
    "gn:admin2_code":"7465524.0",
    "gn:asciiname":"Taikobashi",
    "gn:country_code":"JP",
    "gn:dem":6,
    "gn:feature_class":"P",
    "gn:feature_code":"PPLL",
    "gn:name":"Taikobashi",
    "gn:population":0,
    "gn:timezone":"Asia/Tokyo",
    "iso:country":"JP",
    "name:jpn_x_preferred":[
        "\u592a\u53e4\u6a4b"
    ],
    "name:jpn_x_variant":[
        "\u305f\u3044\u3053\u3070\u3057",
        "\u30bf\u30a4\u30b3\u30d0\u30b7"
    ],
    "wof:name":"Taikobashi",
    "wof:placetype":"locality"
},
  "geometry": {"coordinates":[140.37291999999999,35.31683],"type":"Point"}
}