{
  "type": "Feature",
  "properties": {
    "gn:admin1_code":"34.0",
    "gn:admin2_code":"8304213.0",
    "gn:asciiname":"Jiroemon",
    "gn:country_code":"JP",
    "gn:dem":5,
    "gn:feature_class":"P",
    "gn:feature_code":"PPLL",
    "gn:name":"Jir\u014demon",
    "gn:population":0,
    "gn:timezone":"Asia/Tokyo",
    "iso:country":"JP",
    "name:jpn_x_preferred":[
        "\u6b21\u90ce\u53f3\u885b\u9580"
    ],
    "name:und_x_variant":[
        "Jir\u014demon"
    ],
    "wof:name":"Jiroemon",
    "wof:placetype":"locality"
},
  "geometry": {"coordinates":[139.75988999999998,35.99921],"type":"Point"}
}