{
  "type": "Feature",
  "properties": {
    "gn:admin1_code":"3.0",
    "gn:admin2_code":"2130225.0",
    "gn:asciiname":"Toyonari",
    "gn:country_code":"JP",
    "gn:dem":22,
    "gn:feature_class":"P",
    "gn:feature_code":"PPL",
    "gn:name":"Toyonari",
    "gn:population":0,
    "gn:timezone":"Asia/Tokyo",
    "iso:country":"JP",
    "name:jpn_x_preferred":[
        "\u8c4a\u6210"
    ],
    "name:jpn_x_variant":[
        "\u3068\u3088\u306a\u308a",
        "\u30c8\u30e8\u30ca\u30ea"
    ],
    "wof:name":"Toyonari",
    "wof:placetype":"locality"
},
  "geometry": {"coordinates":[140.51588000000001,40.7761],"type":"Point"}
}