{
  "type": "Feature",
  "properties": {
    "gn:admin1_code":"7.0",
    "gn:admin2_code":"1858305.0",
    "gn:admin3_code":"40402.0",
    "gn:asciiname":"Sensui",
    "gn:country_code":"JP",
    "gn:dem":25,
    "gn:feature_class":"P",
    "gn:feature_code":"PPLL",
    "gn:name":"Sensui",
    "gn:population":0,
    "gn:timezone":"Asia/Tokyo",
    "iso:country":"JP",
    "name:jpn_x_preferred":[
        "\u6cc9\u6c34"
    ],
    "wof:name":"Sensui",
    "wof:placetype":"locality"
},
  "geometry": {"coordinates":[130.65451999999999,33.78339],"type":"Point"}
}