{
  "type": "Feature",
  "properties": {
    "gn:admin1_code":"47",
    "gn:admin2_code":"1850107.0",
    "gn:asciiname":"Takanoha",
    "gn:cc2":"JP",
    "gn:country_code":"JP",
    "gn:dem":25,
    "gn:feature_class":"P",
    "gn:feature_code":"PPL",
    "gn:name":"Takanoha",
    "gn:population":0,
    "gn:timezone":"Asia/Tokyo",
    "iso:country":"JP",
    "name:und_x_variant":[
        "Takany\u016bta",
        "Takany\u016bha",
        "Takanoha"
    ],
    "wof:name":"Takanoha",
    "wof:placetype":"locality"
},
  "geometry": {"coordinates":[127.68333,26.16667],"type":"Point"}
}