{
  "type": "Feature",
  "properties": {
    "gn:admin1_code":"33.0",
    "gn:admin2_code":"1854650.0",
    "gn:asciiname":"Ushiocho-otoyanagi",
    "gn:country_code":"JP",
    "gn:dem":2,
    "gn:feature_class":"P",
    "gn:feature_code":"PPL",
    "gn:name":"Ushioch\u014d-otoyanagi",
    "gn:population":0,
    "gn:timezone":"Asia/Tokyo",
    "iso:country":"JP",
    "name:jpn_x_preferred":[
        "\u725b\u6d25\u753a\u4e59\u67f3"
    ],
    "name:und_x_variant":[
        "Ushioch\u014d-otoyanagi"
    ],
    "wof:name":"Ushiocho-otoyanagi",
    "wof:placetype":"locality"
},
  "geometry": {"coordinates":[130.20572000000001,33.26714],"type":"Point"}
}