{
  "type": "Feature",
  "properties": {
    "gn:admin1_code":"3.0",
    "gn:admin2_code":"2128302.0",
    "gn:admin3_code":"2441.0",
    "gn:asciiname":"Sakaisawa",
    "gn:country_code":"JP",
    "gn:dem":49,
    "gn:feature_class":"P",
    "gn:feature_code":"PPL",
    "gn:name":"Sakaisawa",
    "gn:population":0,
    "gn:timezone":"Asia/Tokyo",
    "iso:country":"JP",
    "name:jpn_x_preferred":[
        "\u5883\u6ca2"
    ],
    "name:jpn_x_variant":[
        "\u3055\u304b\u3044\u3055\u308f",
        "\u30b5\u30ab\u30a4\u30b5\u30ef"
    ],
    "wof:name":"Sakaisawa",
    "wof:placetype":"locality"
},
  "geometry": {"coordinates":[141.24171999999999,40.37146],"type":"Point"}
}