{
  "type": "Feature",
  "properties": {
    "iso:country":"JP",
    "name:eng_x_preferred":[
        "Sakaecho 3 Chome"
    ],
    "name:eng_x_variant":[
        "Sakaechou 3 Choume",
        "Sakaecho 3 Chome"
    ],
    "name:jpn_x_preferred":[
        "\uff13\u4e01\u76ee"
    ],
    "name:jpn_x_variant":[
        "\u3055\u304b\u3048\u3061\u3087\u3046 \uff13\u3061\u3087\u3046\u3081",
        "\u6804\u753a \uff13\u4e01\u76ee",
        "\uff13\u3061\u3087\u3046\u3081"
    ],
    "qs:gn_adm0_cc":"JP",
    "qs:gn_local":1859730,
    "qs:gn_nam_loc":"\u5ddd\u53e3\u5e02, \u57fc\u7389\u770c, JP",
    "qs:gn_namadm1":"34",
    "qs:local_max":338,
    "qs:local_sum":867,
    "qs:localhoods":12,
    "qs:name":"\uff13\u4e01\u76ee",
    "qs:name_adm0":"\u65e5\u672c",
    "qs:name_adm1":"\u57fc\u7389\u770c",
    "qs:name_en":"Sakaecho 3 Chome",
    "qs:name_lau":"\u6804\u753a",
    "qs:name_local":"\u5ddd\u53e3\u5e02",
    "qs:photo_max":243,
    "qs:photo_sum":338,
    "qs:placetype":"Suburb",
    "qs:quad_count":8,
    "qs:woe_adm0":23424856,
    "qs:woe_adm1":2345883,
    "qs:woe_adm2":0,
    "qs:woe_lau":28408231,
    "qs:woe_local":1117494,
    "qs:woe_ver":"7.10.0",
    "wof:lang":[
        "jpn"
    ],
    "wof:name":"\uff13\u4e01\u76ee",
    "wof:placetype":"neighbourhood"
},
  "geometry": {"coordinates":[139.722971,35.804764],"type":"Point"}
}