{
  "type": "Feature",
  "properties": {
    "gn:admin1_code":"24.0",
    "gn:admin2_code":"2112574.0",
    "gn:asciiname":"Iwaida",
    "gn:country_code":"JP",
    "gn:dem":30,
    "gn:feature_class":"P",
    "gn:feature_code":"PPL",
    "gn:name":"Iwaida",
    "gn:population":0,
    "gn:timezone":"Asia/Tokyo",
    "iso:country":"JP",
    "name:jpn_x_preferred":[
        "\u795d\u7530"
    ],
    "name:jpn_x_variant":[
        "\u3044\u308f\u3044\u3060",
        "\u30a4\u30ef\u30a4\u30c0"
    ],
    "wof:name":"Iwaida",
    "wof:placetype":"locality"
},
  "geometry": {"coordinates":[141.37225000000001,38.41421],"type":"Point"}
}