{
  "type": "Feature",
  "properties": {
    "gn:admin1_code":"4.0",
    "gn:admin2_code":"1863711.0",
    "gn:asciiname":"Okamado",
    "gn:country_code":"JP",
    "gn:dem":17,
    "gn:feature_class":"P",
    "gn:feature_code":"PPLL",
    "gn:name":"\u014ckamado",
    "gn:population":0,
    "gn:timezone":"Asia/Tokyo",
    "iso:country":"JP",
    "name:jpn_x_preferred":[
        "\u5927\u91dc\u6238"
    ],
    "name:jpn_x_variant":[
        "\u304a\u304a\u304b\u307e\u3069",
        "\u30aa\u30aa\u30ab\u30de\u30c9"
    ],
    "name:und_x_variant":[
        "\u014ckamado"
    ],
    "wof:name":"Okamado",
    "wof:placetype":"locality"
},
  "geometry": {"coordinates":[139.85706999999999,35.19687000000001],"type":"Point"}
}