{
  "type": "Feature",
  "properties": {
    "gn:admin1_code":"27.0",
    "gn:admin2_code":"1852895.0",
    "gn:asciiname":"Shigeocho",
    "gn:country_code":"JP",
    "gn:dem":57,
    "gn:feature_class":"P",
    "gn:feature_code":"PPL",
    "gn:name":"Shigeoch\u014d",
    "gn:population":0,
    "gn:timezone":"Asia/Tokyo",
    "iso:country":"JP",
    "name:jpn_x_preferred":[
        "\u91cd\u5c3e\u753a"
    ],
    "name:und_x_variant":[
        "Shigeoch\u014d"
    ],
    "wof:name":"Shigeocho",
    "wof:placetype":"locality"
},
  "geometry": {"coordinates":[129.82013999999998,33.11877],"type":"Point"}
}