{
  "type": "Feature",
  "properties": {
    "gn:admin1_code":"19.0",
    "gn:admin2_code":"7468160.0",
    "gn:admin3_code":"14402.0",
    "gn:asciiname":"Funesawa",
    "gn:country_code":"JP",
    "gn:dem":108,
    "gn:feature_class":"P",
    "gn:feature_code":"PPLL",
    "gn:name":"Funesawa",
    "gn:population":0,
    "gn:timezone":"Asia/Tokyo",
    "iso:country":"JP",
    "name:jpn_x_preferred":[
        "\u821f\u6ca2"
    ],
    "wof:name":"Funesawa",
    "wof:placetype":"locality"
},
  "geometry": {"coordinates":[139.29476,35.47884000000001],"type":"Point"}
}