{
  "type": "Feature",
  "properties": {
    "gn:admin1_code":"26.0",
    "gn:admin2_code":"1854184.0",
    "gn:asciiname":"Sonebara",
    "gn:country_code":"JP",
    "gn:dem":691,
    "gn:feature_class":"P",
    "gn:feature_code":"PPL",
    "gn:name":"Sonebara",
    "gn:population":0,
    "gn:timezone":"Asia/Tokyo",
    "iso:country":"JP",
    "name:jpn_x_preferred":[
        "\u66fd\u6839\u539f"
    ],
    "wof:name":"Sonebara",
    "wof:placetype":"locality"
},
  "geometry": {"coordinates":[137.87171000000001,36.45802],"type":"Point"}
}