{
  "type": "Feature",
  "properties": {
    "gn:admin1_code":"28.0",
    "gn:admin2_code":"1863590.0",
    "gn:asciiname":"Kitayamacho",
    "gn:country_code":"JP",
    "gn:dem":300,
    "gn:feature_class":"P",
    "gn:feature_code":"PPL",
    "gn:name":"Kitayamach\u014d",
    "gn:population":0,
    "gn:timezone":"Asia/Tokyo",
    "iso:country":"JP",
    "name:jpn_x_preferred":[
        "\u5317\u5c71\u753a"
    ],
    "name:und_x_variant":[
        "Kitayamach\u014d"
    ],
    "wof:name":"Kitayamacho",
    "wof:placetype":"locality"
},
  "geometry": {"coordinates":[135.68348999999998,34.38122],"type":"Point"}
}