{
  "type": "Feature",
  "properties": {
    "iso:country":"JP",
    "name:jpn_x_preferred":[
        "\uff08\u4e01\u76ee\u306a\u3057\uff09"
    ],
    "qs:gn_local":0,
    "qs:local_max":123,
    "qs:local_sum":123,
    "qs:localhoods":1,
    "qs:name":"\uff08\u4e01\u76ee\u306a\u3057\uff09",
    "qs:name_adm0":"\u65e5\u672c",
    "qs:name_adm1":"\u798f\u5cf6\u770c",
    "qs:name_lau":"\u6c38\u7530",
    "qs:name_local":"\u4e8c\u672c\u677e\u5e02",
    "qs:photo_max":24,
    "qs:photo_sum":123,
    "qs:placetype":"Suburb",
    "qs:quad_count":17,
    "qs:woe_adm0":23424856,
    "qs:woe_adm1":2345858,
    "qs:woe_adm2":0,
    "qs:woe_lau":28399649,
    "qs:woe_local":1117879,
    "qs:woe_ver":"7.10.0",
    "wof:lang":[
        "jpn"
    ],
    "wof:name":"\uff08\u4e01\u76ee\u306a\u3057\uff09",
    "wof:placetype":"neighbourhood"
},
  "geometry": {"coordinates":[140.29757599999999,37.623942],"type":"Point"}
}