{
  "type": "Feature",
  "properties": {
    "gn:admin1_code":"4.0",
    "gn:admin2_code":"2112330.0",
    "gn:asciiname":"Fujigokoro",
    "gn:country_code":"JP",
    "gn:dem":25,
    "gn:feature_class":"P",
    "gn:feature_code":"PPL",
    "gn:name":"Fujigokoro",
    "gn:population":0,
    "gn:timezone":"Asia/Tokyo",
    "iso:country":"JP",
    "name:jpn_x_preferred":[
        "\u85e4\u5fc3"
    ],
    "wof:name":"Fujigokoro",
    "wof:placetype":"locality"
},
  "geometry": {"coordinates":[139.99019999999999,35.82665],"type":"Point"}
}