{
  "type": "Feature",
  "properties": {
    "gn:admin1_code":"21.0",
    "gn:admin2_code":"1850744.0",
    "gn:admin3_code":"43367.0",
    "gn:asciiname":"Tsukuibaru",
    "gn:country_code":"JP",
    "gn:dem":91,
    "gn:feature_class":"P",
    "gn:feature_code":"PPLL",
    "gn:name":"Tsukuibaru",
    "gn:population":0,
    "gn:timezone":"Asia/Tokyo",
    "iso:country":"JP",
    "name:jpn_x_preferred":[
        "\u7bc9\u4e95\u539f"
    ],
    "name:jpn_x_variant":[
        "\u3064\u304f\u3044\u3070\u308b",
        "\u30c4\u30af\u30a4\u30d0\u30eb"
    ],
    "wof:name":"Tsukuibaru",
    "wof:placetype":"locality"
},
  "geometry": {"coordinates":[130.53706,33.07682],"type":"Point"}
}