{
  "type": "Feature",
  "properties": {
    "gn:admin1_code":"26",
    "gn:admin2_code":"1856209.0",
    "gn:asciiname":"Matsushiromachi-higashijo",
    "gn:country_code":"JP",
    "gn:dem":374,
    "gn:feature_class":"P",
    "gn:feature_code":"PPL",
    "gn:name":"Matsushiromachi-higashij\u014d",
    "gn:population":0,
    "gn:timezone":"Asia/Tokyo",
    "iso:country":"JP",
    "name:jpn_x_preferred":[
        "\u677e\u4ee3\u753a\u6771\u6761"
    ],
    "name:und_x_variant":[
        "Higashi-jo-mura",
        "Higashi-j\u014d",
        "Matsushiromachi-higashij\u014d"
    ],
    "wof:name":"Matsushiromachi-higashijo",
    "wof:placetype":"locality"
},
  "geometry": {"coordinates":[138.22163999999998,36.56319000000001],"type":"Point"}
}