{
  "type": "Feature",
  "properties": {
    "gn:admin1_code":"16.0",
    "gn:admin2_code":"7441804.0",
    "gn:admin3_code":"3302.0",
    "gn:asciiname":"Mattatsu",
    "gn:country_code":"JP",
    "gn:dem":508,
    "gn:feature_class":"P",
    "gn:feature_code":"PPL",
    "gn:name":"Mattatsu",
    "gn:population":0,
    "gn:timezone":"Asia/Tokyo",
    "iso:country":"JP",
    "name:und_x_variant":[
        "M\u0101tatsu",
        "Mattatsu"
    ],
    "wof:name":"Mattatsu",
    "wof:placetype":"locality"
},
  "geometry": {"coordinates":[141.40541000000005,39.98137],"type":"Point"}
}