{
  "type": "Feature",
  "properties": {
    "gn:admin1_code":"21.0",
    "gn:admin2_code":"7412706.0",
    "gn:admin3_code":"43441.0",
    "gn:asciiname":"Karasako",
    "gn:country_code":"JP",
    "gn:dem":521,
    "gn:feature_class":"P",
    "gn:feature_code":"PPLL",
    "gn:name":"Karasako",
    "gn:population":0,
    "gn:timezone":"Asia/Tokyo",
    "iso:country":"JP",
    "name:jpn_x_preferred":[
        "\u6a3a\u8feb"
    ],
    "name:jpn_x_variant":[
        "\u304b\u3089\u3055\u3053",
        "\u30ab\u30e9\u30b5\u30b3"
    ],
    "wof:name":"Karasako",
    "wof:placetype":"locality"
},
  "geometry": {"coordinates":[130.91171,32.78403],"type":"Point"}
}