{
  "type": "Feature",
  "properties": {
    "gn:admin1_code":"21.0",
    "gn:admin2_code":"1858418.0",
    "gn:admin3_code":"43102.0",
    "gn:asciiname":"Goryo",
    "gn:country_code":"JP",
    "gn:dem":63,
    "gn:feature_class":"P",
    "gn:feature_code":"PPL",
    "gn:name":"Gory\u014d",
    "gn:population":0,
    "gn:timezone":"Asia/Tokyo",
    "iso:country":"JP",
    "name:jpn_x_preferred":[
        "\u5fa1\u9818"
    ],
    "name:jpn_x_variant":[
        "\u3054\u308a\u3087\u3046",
        "\u30b4\u30ea\u30e7\u30a6"
    ],
    "name:und_x_variant":[
        "Gory\u014d"
    ],
    "wof:name":"Goryo",
    "wof:placetype":"locality"
},
  "geometry": {"coordinates":[130.76803000000001,32.82571],"type":"Point"}
}