{
  "type": "Feature",
  "properties": {
    "gn:admin1_code":"42.0",
    "gn:admin2_code":"7391183.0",
    "gn:asciiname":"Kozu",
    "gn:country_code":"JP",
    "gn:dem":365,
    "gn:feature_class":"P",
    "gn:feature_code":"PPL",
    "gn:name":"K\u014dzu",
    "gn:population":0,
    "gn:timezone":"Asia/Tokyo",
    "iso:country":"JP",
    "name:jpn_x_preferred":[
        "\u696e"
    ],
    "name:und_x_variant":[
        "K\u014dzu"
    ],
    "wof:name":"Kozu",
    "wof:placetype":"locality"
},
  "geometry": {"coordinates":[136.87482,36.36273],"type":"Point"}
}