{
  "type": "Feature",
  "properties": {
    "gn:admin1_code":"28.0",
    "gn:admin2_code":"7411375.0",
    "gn:admin3_code":"29427.0",
    "gn:asciiname":"Ikebe",
    "gn:country_code":"JP",
    "gn:dem":58,
    "gn:feature_class":"P",
    "gn:feature_code":"PPL",
    "gn:name":"Ikebe",
    "gn:population":0,
    "gn:timezone":"Asia/Tokyo",
    "iso:country":"JP",
    "name:jpn_x_preferred":[
        "\u6c60\u90e8"
    ],
    "wof:name":"Ikebe",
    "wof:placetype":"locality"
},
  "geometry": {"coordinates":[135.73668000000001,34.57923],"type":"Point"}
}