{
  "type": "Feature",
  "properties": {
    "gn:admin1_code":"21.0",
    "gn:admin2_code":"7412708.0",
    "gn:admin3_code":"43514.0",
    "gn:asciiname":"Hamanoue",
    "gn:country_code":"JP",
    "gn:dem":167,
    "gn:feature_class":"P",
    "gn:feature_code":"PPLL",
    "gn:name":"Hamanoue",
    "gn:population":0,
    "gn:timezone":"Asia/Tokyo",
    "iso:country":"JP",
    "name:jpn_x_preferred":[
        "\u6d5c\u30ce\u4e0a"
    ],
    "name:jpn_x_variant":[
        "\u306f\u307e\u306e\u3046\u3048",
        "\u30cf\u30de\u30ce\u30a6\u30a8"
    ],
    "wof:name":"Hamanoue",
    "wof:placetype":"locality"
},
  "geometry": {"coordinates":[130.91477,32.26611],"type":"Point"}
}