{
  "type": "Feature",
  "properties": {
    "gn:admin1_code":"19.0",
    "gn:admin2_code":"1864091.0",
    "gn:asciiname":"Yamada",
    "gn:country_code":"JP",
    "gn:dem":22,
    "gn:feature_class":"P",
    "gn:feature_code":"PPLL",
    "gn:name":"Yamada",
    "gn:population":0,
    "gn:timezone":"Asia/Tokyo",
    "iso:country":"JP",
    "name:jpn_x_preferred":[
        "\u5c71\u7530"
    ],
    "name:kor_x_preferred":[
        "\uc57c\ub9c8\ub2e4"
    ],
    "name:mlg_x_preferred":[
        "Yamada"
    ],
    "wof:name":"Yamada",
    "wof:placetype":"locality"
},
  "geometry": {"coordinates":[139.45866999999998,35.38272],"type":"Point"}
}