{
  "type": "Feature",
  "properties": {
    "iso:country":"JP",
    "name:eng_x_preferred":[
        "Isehara"
    ],
    "name:eng_x_variant":[
        "Isehara City"
    ],
    "name:jpn_x_preferred":[
        "\u4f0a\u52e2\u539f\u5e02"
    ],
    "qs:name":"\u4f0a\u52e2\u539f\u5e02",
    "qs:name_adm0":"\u65e5\u672c",
    "qs:name_adm1":"\u795e\u5948\u5ddd\u770c",
    "qs:photos":1394,
    "qs:photos_1k":282,
    "qs:photos_9k":10,
    "qs:photos_9r":9,
    "qs:photos_all":2297,
    "qs:photos_sr":12,
    "qs:placetype":"Town",
    "qs:pop_sr":"0",
    "wof:name":"Isehara",
    "wof:placetype":"locality"
},
  "geometry": {"coordinates":[139.249166,35.4315],"type":"Point"}
}