{
  "type": "Feature",
  "properties": {
    "gn:admin1_code":"37.0",
    "gn:admin2_code":"1860327.0",
    "gn:admin3_code":"22306.0",
    "gn:asciiname":"Nobata",
    "gn:country_code":"JP",
    "gn:dem":134,
    "gn:feature_class":"P",
    "gn:feature_code":"PPL",
    "gn:name":"Nobata",
    "gn:population":0,
    "gn:timezone":"Asia/Tokyo",
    "iso:country":"JP",
    "name:jpn_x_preferred":[
        "\u91ce\u7551"
    ],
    "wof:name":"Nobata",
    "wof:placetype":"locality"
},
  "geometry": {"coordinates":[138.77986999999999,34.78498],"type":"Point"}
}