{
  "type": "Feature",
  "properties": {
    "gn:admin1_code":"4.0",
    "gn:admin2_code":"2112997.0",
    "gn:admin3_code":"12421.0",
    "gn:asciiname":"Yabata",
    "gn:country_code":"JP",
    "gn:dem":7,
    "gn:feature_class":"P",
    "gn:feature_code":"PPLL",
    "gn:name":"Yabata",
    "gn:population":0,
    "gn:timezone":"Asia/Tokyo",
    "iso:country":"JP",
    "name:jpn_x_preferred":[
        "\u77e2\u7551"
    ],
    "name:jpn_x_variant":[
        "\u3084\u3070\u305f",
        "\u30e4\u30d0\u30bf"
    ],
    "wof:name":"Yabata",
    "wof:placetype":"locality"
},
  "geometry": {"coordinates":[140.37291999999999,35.3582],"type":"Point"}
}