{
  "type": "Feature",
  "properties": {
    "gn:admin1_code":"7.0",
    "gn:admin2_code":"1851269.0",
    "gn:admin3_code":"40602.0",
    "gn:asciiname":"Shimochuganji",
    "gn:country_code":"JP",
    "gn:dem":141,
    "gn:feature_class":"P",
    "gn:feature_code":"PPL",
    "gn:name":"Shimoch\u016bganji",
    "gn:population":0,
    "gn:timezone":"Asia/Tokyo",
    "iso:country":"JP",
    "name:jpn_x_preferred":[
        "\u4e0b\u4e2d\u5143\u5bfa"
    ],
    "name:und_x_variant":[
        "Shimoch\u016bganji"
    ],
    "wof:name":"Shimochuganji",
    "wof:placetype":"locality"
},
  "geometry": {"coordinates":[130.84221000000002,33.54855],"type":"Point"}
}