{
  "type": "Feature",
  "properties": {
    "gn:admin1_code":"21.0",
    "gn:admin2_code":"1864975.0",
    "gn:admin3_code":"43433.0",
    "gn:asciiname":"Shinsho",
    "gn:country_code":"JP",
    "gn:dem":358,
    "gn:feature_class":"P",
    "gn:feature_code":"PPLL",
    "gn:name":"Shinsho",
    "gn:population":0,
    "gn:timezone":"Asia/Tokyo",
    "iso:country":"JP",
    "name:jpn_x_preferred":[
        "\u65b0\u6240"
    ],
    "name:jpn_x_variant":[
        "\u3057\u3093\u3057\u3087",
        "\u30b7\u30f3\u30b7\u30e7"
    ],
    "wof:name":"Shinsho",
    "wof:placetype":"locality"
},
  "geometry": {"coordinates":[130.96827999999999,32.88177],"type":"Point"}
}