{
  "type": "Feature",
  "properties": {
    "gn:admin1_code":"4.0",
    "gn:admin2_code":"2112997.0",
    "gn:admin3_code":"12427.0",
    "gn:asciiname":"Kawamukai",
    "gn:country_code":"JP",
    "gn:dem":11,
    "gn:feature_class":"P",
    "gn:feature_code":"PPLL",
    "gn:name":"Kawamukai",
    "gn:population":0,
    "gn:timezone":"Asia/Tokyo",
    "iso:country":"JP",
    "name:jpn_x_preferred":[
        "\u5ddd\u5411"
    ],
    "name:jpn_x_variant":[
        "\u304b\u308f\u3080\u304b\u3044",
        "\u30ab\u30ef\u30e0\u30ab\u30a4"
    ],
    "wof:name":"Kawamukai",
    "wof:placetype":"locality"
},
  "geometry": {"coordinates":[140.29953,35.36972],"type":"Point"}
}