{
  "type": "Feature",
  "properties": {
    "gn:admin1_code":"21.0",
    "gn:admin2_code":"7412706.0",
    "gn:admin3_code":"43447.0",
    "gn:asciiname":"Hachiboku",
    "gn:country_code":"JP",
    "gn:dem":618,
    "gn:feature_class":"P",
    "gn:feature_code":"PPL",
    "gn:name":"Hachiboku",
    "gn:population":0,
    "gn:timezone":"Asia/Tokyo",
    "iso:country":"JP",
    "name:jpn_x_preferred":[
        "\u516b\u6728"
    ],
    "name:jpn_x_variant":[
        "\u306f\u3061\u307c\u304f",
        "\u30cf\u30c1\u30dc\u30af"
    ],
    "wof:name":"Hachiboku",
    "wof:placetype":"locality"
},
  "geometry": {"coordinates":[131.15303,32.73655],"type":"Point"}
}