{
  "type": "Feature",
  "properties": {
    "gn:admin1_code":"12.0",
    "gn:admin2_code":"2130385.0",
    "gn:asciiname":"Mo-izari",
    "gn:cc2":"JP",
    "gn:country_code":"JP",
    "gn:dem":37,
    "gn:feature_class":"P",
    "gn:feature_code":"PPL",
    "gn:name":"Mo-izari",
    "gn:population":0,
    "gn:timezone":"Asia/Tokyo",
    "iso:country":"JP",
    "name:und_x_variant":[
        "Moasari",
        "Izari",
        "Mo-izari"
    ],
    "wof:name":"Mo-izari",
    "wof:placetype":"locality"
},
  "geometry": {"coordinates":[141.56666999999999,42.88333],"type":"Point"}
}