{
  "type": "Feature",
  "properties": {
    "gn:admin1_code":"21.0",
    "gn:admin2_code":"7412705.0",
    "gn:admin3_code":"43482.0",
    "gn:asciiname":"Mitsuto",
    "gn:country_code":"JP",
    "gn:dem":12,
    "gn:feature_class":"P",
    "gn:feature_code":"PPLL",
    "gn:name":"Mitsut\u014d",
    "gn:population":0,
    "gn:timezone":"Asia/Tokyo",
    "iso:country":"JP",
    "name:jpn_x_preferred":[
        "\u6c34\u9053"
    ],
    "name:und_x_variant":[
        "Mitsut\u014d"
    ],
    "wof:name":"Mitsuto",
    "wof:placetype":"locality"
},
  "geometry": {"coordinates":[130.50838999999999,32.35641],"type":"Point"}
}