{
  "type": "Feature",
  "properties": {
    "gn:admin1_code":"35.0",
    "gn:admin2_code":"1858984.0",
    "gn:asciiname":"Imajuku",
    "gn:country_code":"JP",
    "gn:dem":197,
    "gn:feature_class":"P",
    "gn:feature_code":"PPLL",
    "gn:name":"Imajuku",
    "gn:population":0,
    "gn:timezone":"Asia/Tokyo",
    "iso:country":"JP",
    "name:jpn_x_preferred":[
        "\u4eca\u5bbf"
    ],
    "wof:name":"Imajuku",
    "wof:placetype":"locality"
},
  "geometry": {"coordinates":[136.22201000000001,34.95526],"type":"Point"}
}