{
  "type": "Feature",
  "properties": {
    "gn:admin1_code":"10",
    "gn:admin2_code":"1857842.0",
    "gn:asciiname":"Ogomachi",
    "gn:country_code":"JP",
    "gn:dem":180,
    "gn:feature_class":"P",
    "gn:feature_code":"PPL",
    "gn:name":"\u014cgomachi",
    "gn:population":0,
    "gn:timezone":"Asia/Tokyo",
    "iso:country":"JP",
    "name:jpn_x_preferred":[
        "\u5927\u80e1\u753a"
    ],
    "name:und_x_variant":[
        "\u014cgomachi",
        "\u014cgo"
    ],
    "wof:name":"Ogomachi",
    "wof:placetype":"locality"
},
  "geometry": {"coordinates":[139.16666999999998,36.41667],"type":"Point"}
}