{
  "type": "Feature",
  "properties": {
    "gn:admin1_code":"29",
    "gn:admin2_code":"1860992.0",
    "gn:asciiname":"Takehira",
    "gn:cc2":"JP",
    "gn:country_code":"JP",
    "gn:dem":354,
    "gn:feature_class":"P",
    "gn:feature_code":"PPL",
    "gn:name":"Takehira",
    "gn:population":0,
    "gn:timezone":"Asia/Tokyo",
    "iso:country":"JP",
    "name:und_x_variant":[
        "Taketaira",
        "Takehira"
    ],
    "wof:name":"Takehira",
    "wof:placetype":"locality"
},
  "geometry": {"coordinates":[138.55000000000001,37.16667],"type":"Point"}
}