{
  "type": "Feature",
  "properties": {
    "gn:admin1_code":"23",
    "gn:admin2_code":"1861434.0",
    "gn:asciiname":"Uji",
    "gn:country_code":"JP",
    "gn:dem":29,
    "gn:feature_class":"P",
    "gn:feature_code":"PPL",
    "gn:name":"Uji",
    "gn:population":0,
    "gn:timezone":"Asia/Tokyo",
    "iso:country":"JP",
    "name:ara_x_preferred":[
        "\u064a\u0648\u062c\u064a"
    ],
    "name:azb_x_preferred":[
        "\u0627\u0648\u062c\u06cc"
    ],
    "name:ben_x_preferred":[
        "\u0989\u099c\u09bf"
    ],
    "name:cat_x_preferred":[
        "Uji"
    ],
    "name:ces_x_preferred":[
        "Ud\u017ei"
    ],
    "name:deu_x_preferred":[
        "Uji"
    ],
    "name:epo_x_preferred":[
        "U\u011di"
    ],
    "name:eus_x_preferred":[
        "Uji"
    ],
    "name:fas_x_preferred":[
        "\u0627\u0648\u062c\u06cc"
    ],
    "name:fin_x_preferred":[
        "Uji"
    ],
    "name:fra_x_preferred":[
        "Uji"
    ],
    "name:glg_x_preferred":[
        "Uji"
    ],
    "name:hrv_x_preferred":[
        "Uji"
    ],
    "name:hun_x_preferred":[
        "Udzsi"
    ],
    "name:hye_x_preferred":[
        "\u0548\u0582\u0571\u056b"
    ],
    "name:ita_x_preferred":[
        "Uji"
    ],
    "name:jpn_x_preferred":[
        "\u5b87\u6cbb\u5e02"
    ],
    "name:kor_x_preferred":[
        "\uc6b0\uc9c0\uc2dc"
    ],
    "name:lit_x_preferred":[
        "Ud\u017eis"
    ],
    "name:mlg_x_preferred":[
        "Uji"
    ],
    "name:mon_x_preferred":[
        "\u04ae\u0436\u0438"
    ],
    "name:msa_x_preferred":[
        "Uji"
    ],
    "name:mzn_x_preferred":[
        "\u0627\u0648\u062c\u06cc"
    ],
    "name:nld_x_preferred":[
        "Uji"
    ],
    "name:pol_x_preferred":[
        "Uji"
    ],
    "name:por_x_preferred":[
        "Uji"
    ],
    "name:ron_x_preferred":[
        "Uji"
    ],
    "name:rus_x_preferred":[
        "\u0423\u0434\u0437\u0438"
    ],
    "name:spa_x_preferred":[
        "Uji"
    ],
    "name:srp_x_preferred":[
        "\u0423\u045f\u0438"
    ],
    "name:swe_x_preferred":[
        "Uji"
    ],
    "name:tgk_x_preferred":[
        "\u0423\u04b7\u0438"
    ],
    "name:tgl_x_preferred":[
        "Uji"
    ],
    "name:tha_x_preferred":[
        "\u0e2d\u0e39\u0e08\u0e34"
    ],
    "name:tur_x_preferred":[
        "Uji"
    ],
    "name:ukr_x_preferred":[
        "\u0423\u0434\u0436\u0456"
    ],
    "name:vie_x_preferred":[
        "Uji"
    ],
    "name:war_x_preferred":[
        "Uji"
    ],
    "name:zho_x_preferred":[
        "\u5b87\u6cbb\u5e02"
    ],
    "wof:name":"Uji",
    "wof:placetype":"locality"
},
  "geometry": {"coordinates":[136.71666999999999,34.46667],"type":"Point"}
}