{
  "type": "Feature",
  "properties": {
    "gn:admin1_code":"23",
    "gn:admin2_code":"1861434.0",
    "gn:asciiname":"Uji",
    "gn:country_code":"JP",
    "gn:dem":29,
    "gn:feature_class":"P",
    "gn:feature_code":"PPL",
    "gn:name":"Uji",
    "gn:population":0,
    "gn:timezone":"Asia/Tokyo",
    "iso:country":"JP",
    "wof:name":"Uji",
    "wof:placetype":"locality"
},
  "geometry": {"coordinates":[136.71666999999999,34.46667],"type":"Point"}
}