{
  "type": "Feature",
  "properties": {
    "gn:admin1_code":"37.0",
    "gn:admin2_code":"1864104.0",
    "gn:asciiname":"Onakazato",
    "gn:country_code":"JP",
    "gn:dem":128,
    "gn:feature_class":"P",
    "gn:feature_code":"PPL",
    "gn:name":"\u014cnakazato",
    "gn:population":0,
    "gn:timezone":"Asia/Tokyo",
    "iso:country":"JP",
    "name:jpn_x_preferred":[
        "\u5927\u4e2d\u91cc"
    ],
    "name:und_x_variant":[
        "\u014cnakazato"
    ],
    "wof:name":"Onakazato",
    "wof:placetype":"locality"
},
  "geometry": {"coordinates":[138.59253000000001,35.22662000000001],"type":"Point"}
}