{
  "type": "Feature",
  "properties": {
    "gn:admin1_code":"43.0",
    "gn:admin2_code":"1865123.0",
    "gn:admin3_code":"30366.0",
    "gn:asciiname":"Kamiyukawa",
    "gn:country_code":"JP",
    "gn:dem":553,
    "gn:feature_class":"P",
    "gn:feature_code":"PPL",
    "gn:name":"Kamiyukawa",
    "gn:population":0,
    "gn:timezone":"Asia/Tokyo",
    "iso:country":"JP",
    "name:jpn_x_preferred":[
        "\u4e0a\u6e6f\u5ddd"
    ],
    "wof:name":"Kamiyukawa",
    "wof:placetype":"locality"
},
  "geometry": {"coordinates":[135.49574999999999,34.06351],"type":"Point"}
}