{
  "type": "Feature",
  "properties": {
    "iso:country":"JP",
    "name:eng_x_preferred":[
        "Azakita 1 Chome"
    ],
    "name:eng_x_variant":[
        "Azakita 1 Choume",
        "Azakita 1 Chome"
    ],
    "name:jpn_x_preferred":[
        "\uff11\u4e01\u76ee"
    ],
    "name:jpn_x_variant":[
        "\u3042\u3056\u304d\u305f \uff11\u3061\u3087\u3046\u3081",
        "\u5b57\u5317 \uff11\u4e01\u76ee",
        "\uff11\u3061\u3087\u3046\u3081"
    ],
    "qs:gn_local":0,
    "qs:local_max":11,
    "qs:local_sum":17,
    "qs:localhoods":2,
    "qs:name":"\uff11\u4e01\u76ee",
    "qs:name_adm0":"\u65e5\u672c",
    "qs:name_adm1":"\u79cb\u7530\u770c",
    "qs:name_adm2":"\u5357\u79cb\u7530\u90e1",
    "qs:name_en":"Azakita 1 Chome",
    "qs:name_lau":"\u5b57\u5317",
    "qs:name_local":"\u5927\u6f5f\u6751",
    "qs:photo_max":9,
    "qs:photo_sum":11,
    "qs:placetype":"Suburb",
    "qs:quad_count":3,
    "qs:woe_adm0":23424856,
    "qs:woe_adm1":2345852,
    "qs:woe_adm2":24849033,
    "qs:woe_lau":28395951,
    "qs:woe_local":24848931,
    "qs:woe_ver":"7.10.0",
    "wof:lang":[
        "jpn"
    ],
    "wof:name":"\uff11\u4e01\u76ee",
    "wof:placetype":"neighbourhood"
},
  "geometry": {"coordinates":[139.953588,40.029335],"type":"Point"}
}