{
  "type": "Feature",
  "properties": {
    "gn:admin1_code":"19.0",
    "gn:admin2_code":"1864864.0",
    "gn:asciiname":"Kitayamakami",
    "gn:country_code":"JP",
    "gn:dem":40,
    "gn:feature_class":"P",
    "gn:feature_code":"PPLL",
    "gn:name":"Kitayamakami",
    "gn:population":0,
    "gn:timezone":"Asia/Tokyo",
    "iso:country":"JP",
    "name:jpn_x_preferred":[
        "\u5317\u5c71\u4e0a"
    ],
    "wof:name":"Kitayamakami",
    "wof:placetype":"locality"
},
  "geometry": {"coordinates":[139.42861000000002,35.42697000000001],"type":"Point"}
}