{
  "type": "Feature",
  "properties": {
    "gn:admin1_code":"12.0",
    "gn:admin2_code":"7428106.0",
    "gn:admin3_code":"1545.0",
    "gn:asciiname":"Chibusuke",
    "gn:country_code":"JP",
    "gn:dem":60,
    "gn:feature_class":"P",
    "gn:feature_code":"PPL",
    "gn:name":"Chibusuke",
    "gn:population":0,
    "gn:timezone":"Asia/Tokyo",
    "iso:country":"JP",
    "name:eng_x_preferred":[
        "Chibusuke"
    ],
    "name:rus_x_preferred":[
        "\u0422\u0438\u0431\u0443\u0441\u0443\u043a\u0435"
    ],
    "name:und_x_variant":[
        "Koiseboi",
        "Chibuske"
    ],
    "wof:name":"Chibusuke",
    "wof:placetype":"locality"
},
  "geometry": {"coordinates":[144.83288000000005,43.94627],"type":"Point"}
}