{
  "type": "Feature",
  "properties": {
    "gn:admin1_code":"4.0",
    "gn:admin2_code":"8304237.0",
    "gn:asciiname":"Oine",
    "gn:country_code":"JP",
    "gn:dem":29,
    "gn:feature_class":"P",
    "gn:feature_code":"PPL",
    "gn:name":"\u014cine",
    "gn:population":0,
    "gn:timezone":"Asia/Tokyo",
    "iso:country":"JP",
    "name:jpn_x_preferred":[
        "\u5927\u7a32"
    ],
    "name:jpn_x_variant":[
        "\u304a\u304a\u3044\u306d",
        "\u30aa\u30aa\u30a4\u30cd"
    ],
    "name:und_x_variant":[
        "\u014cine"
    ],
    "wof:name":"Oine",
    "wof:placetype":"locality"
},
  "geometry": {"coordinates":[140.06051000000002,35.37722],"type":"Point"}
}