{
  "type": "Feature",
  "properties": {
    "gn:admin1_code":"3.0",
    "gn:admin2_code":"2128302.0",
    "gn:admin3_code":"2441.0",
    "gn:asciiname":"Yokomichi",
    "gn:country_code":"JP",
    "gn:dem":43,
    "gn:feature_class":"P",
    "gn:feature_code":"PPL",
    "gn:name":"Yokomichi",
    "gn:population":0,
    "gn:timezone":"Asia/Tokyo",
    "iso:country":"JP",
    "name:jpn_x_preferred":[
        "\u6a2a\u9053"
    ],
    "name:jpn_x_variant":[
        "\u3088\u3053\u307f\u3061",
        "\u30e8\u30b3\u30df\u30c1"
    ],
    "wof:name":"Yokomichi",
    "wof:placetype":"locality"
},
  "geometry": {"coordinates":[141.25769,40.38294000000001],"type":"Point"}
}