{
  "type": "Feature",
  "properties": {
    "gn:admin1_code":"13",
    "gn:admin2_code":"1849826.0",
    "gn:asciiname":"Kinosaki",
    "gn:country_code":"JP",
    "gn:dem":11,
    "gn:feature_class":"P",
    "gn:feature_code":"PPL",
    "gn:name":"Kinosaki",
    "gn:population":0,
    "gn:timezone":"Asia/Tokyo",
    "iso:country":"JP",
    "wof:name":"Kinosaki",
    "wof:placetype":"locality"
},
  "geometry": {"coordinates":[134.81666999999999,35.61667],"type":"Point"}
}