{
  "type": "Feature",
  "properties": {
    "gn:country":"JP",
    "gn:fcode":"ADM3",
    "gn:population":0,
    "iso:country":"JP",
    "name:eng_x_preferred":[
        "Ainan"
    ],
    "name:eng_x_variant":[
        "Ainan-ch\u014d"
    ],
    "name:jpn_x_preferred":[
        "\u611b\u5357\u753a"
    ],
    "qs:name":"Ainan-ch\u014d",
    "qs:photos_9r":0,
    "qs:photos_sr":0,
    "qs:pop_sr":"0",
    "wof:name":"Ainan",
    "wof:placetype":"localadmin",
    "wof:population":0
},
  "geometry": {"coordinates":[132.58403999999999,32.96201],"type":"Point"}
}