{
  "type": "Feature",
  "properties": {
    "gn:admin1_code":"05",
    "gn:admin2_code":"1853424.0",
    "gn:asciiname":"Niiya",
    "gn:cc2":"JP",
    "gn:country_code":"JP",
    "gn:dem":18,
    "gn:feature_class":"P",
    "gn:feature_code":"PPL",
    "gn:name":"Niiya",
    "gn:population":0,
    "gn:timezone":"Asia/Tokyo",
    "iso:country":"JP",
    "wof:name":"Niiya",
    "wof:placetype":"locality"
},
  "geometry": {"coordinates":[132.60443999999998,33.53662],"type":"Point"}
}