{
  "type": "Feature",
  "properties": {
    "gn:admin1_code":"41",
    "gn:admin2_code":"1849887.0",
    "gn:asciiname":"Funaoka",
    "gn:country_code":"JP",
    "gn:dem":187,
    "gn:feature_class":"P",
    "gn:feature_code":"PPL",
    "gn:name":"Funaoka",
    "gn:population":0,
    "gn:timezone":"Asia/Tokyo",
    "iso:country":"JP",
    "wof:name":"Funaoka",
    "wof:placetype":"locality"
},
  "geometry": {"coordinates":[134.23333,35.38333],"type":"Point"}
}