{
  "type": "Feature",
  "properties": {
    "gn:admin1_code":"4.0",
    "gn:admin2_code":"7465524.0",
    "gn:asciiname":"Yamada-rokuku",
    "gn:country_code":"JP",
    "gn:dem":64,
    "gn:feature_class":"P",
    "gn:feature_code":"PPLL",
    "gn:name":"Yamada-rokuku",
    "gn:population":0,
    "gn:timezone":"Asia/Tokyo",
    "iso:country":"JP",
    "name:jpn_x_preferred":[
        "\u5c71\u7530\u516d\u533a"
    ],
    "name:jpn_x_variant":[
        "\u3084\u307e\u3060\u308d\u304f\u304f",
        "\u30e4\u30de\u30c0\u30ed\u30af\u30af"
    ],
    "wof:name":"Yamada-rokuku",
    "wof:placetype":"locality"
},
  "geometry": {"coordinates":[140.31429,35.24686],"type":"Point"}
}