{
  "type": "Feature",
  "properties": {
    "iso:country":"JP",
    "qs:name":"\uff11\u4e01\u76ee",
    "qs:name_adm0":"\u65e5\u672c",
    "qs:name_adm1":"\u9759\u5ca1\u770c",
    "qs:photos":53,
    "qs:photos_1k":11,
    "qs:photos_9k":1,
    "qs:photos_9r":2,
    "qs:photos_all":53,
    "qs:photos_sr":2,
    "qs:placetype":"Suburb",
    "qs:pop_sr":"0",
    "wof:name":"\uff11\u4e01\u76ee",
    "wof:placetype":"neighbourhood"
},
  "geometry": {"coordinates":[138.388724,34.971328],"type":"Point"}
}