{
  "type": "Feature",
  "properties": {
    "gn:admin1_code":"7.0",
    "gn:admin2_code":"7407416.0",
    "gn:asciiname":"Serida",
    "gn:country_code":"JP",
    "gn:dem":84,
    "gn:feature_class":"P",
    "gn:feature_code":"PPL",
    "gn:name":"Serida",
    "gn:population":0,
    "gn:timezone":"Asia/Tokyo",
    "iso:country":"JP",
    "name:jpn_x_preferred":[
        "\u82b9\u7530"
    ],
    "wof:name":"Serida",
    "wof:placetype":"locality"
},
  "geometry": {"coordinates":[130.63634999999999,33.74497],"type":"Point"}
}