{
  "type": "Feature",
  "properties": {
    "gn:admin1_code":"2.0",
    "gn:admin2_code":"7443160.0",
    "gn:asciiname":"Iwaki-uchimichikawa",
    "gn:country_code":"JP",
    "gn:dem":12,
    "gn:feature_class":"P",
    "gn:feature_code":"PPL",
    "gn:name":"Iwaki-uchimichikawa",
    "gn:population":0,
    "gn:timezone":"Asia/Tokyo",
    "iso:country":"JP",
    "name:jpn_x_preferred":[
        "\u5ca9\u57ce\u5185\u9053\u5ddd"
    ],
    "wof:name":"Iwaki-uchimichikawa",
    "wof:placetype":"locality"
},
  "geometry": {"coordinates":[140.05823999999998,39.55296],"type":"Point"}
}