{
  "type": "Feature",
  "properties": {
    "gn:admin1_code":"7.0",
    "gn:admin2_code":"1864394.0",
    "gn:asciiname":"Tadagoe",
    "gn:country_code":"JP",
    "gn:dem":112,
    "gn:feature_class":"P",
    "gn:feature_code":"PPLL",
    "gn:name":"Tadagoe",
    "gn:population":0,
    "gn:timezone":"Asia/Tokyo",
    "iso:country":"JP",
    "name:jpn_x_preferred":[
        "\u53ea\u8d8a"
    ],
    "wof:name":"Tadagoe",
    "wof:placetype":"locality"
},
  "geometry": {"coordinates":[130.54166999999998,33.54619],"type":"Point"}
}