{
  "type": "Feature",
  "properties": {
    "gn:admin1_code":"21.0",
    "gn:admin2_code":"7412706.0",
    "gn:admin3_code":"43442.0",
    "gn:asciiname":"Takikawara",
    "gn:country_code":"JP",
    "gn:dem":8,
    "gn:feature_class":"P",
    "gn:feature_code":"PPLL",
    "gn:name":"Takikawara",
    "gn:population":0,
    "gn:timezone":"Asia/Tokyo",
    "iso:country":"JP",
    "name:jpn_x_preferred":[
        "\u6edd\u6cb3\u539f"
    ],
    "name:jpn_x_variant":[
        "\u305f\u304d\u304b\u308f\u3089",
        "\u30bf\u30ad\u30ab\u30ef\u30e9"
    ],
    "wof:name":"Takikawara",
    "wof:placetype":"locality"
},
  "geometry": {"coordinates":[130.74108000000001,32.74365],"type":"Point"}
}