{
  "type": "Feature",
  "properties": {
    "gn:country":"JP",
    "gn:fcode":"PPL",
    "gn:pop":21156,
    "iso:country":"JP",
    "name:eng_x_preferred":[
        "Tanushimaru"
    ],
    "name:fra_x_preferred":[
        "Tanushimaru"
    ],
    "name:jpn_x_preferred":[
        "\u7530\u4e3b\u4e38\u753a\u8c4a\u57ce"
    ],
    "name:jpn_x_variant":[
        "\u7530\u4e3b\u4e38\u753a"
    ],
    "name:unk_x_variant":[
        "Tanushimarumachi-toyoki"
    ],
    "qs:name":"Tanushimaru",
    "qs:photos_9r":0,
    "qs:photos_sr":0,
    "qs:pop_sr":"7",
    "wof:name":"Tanushimaru",
    "wof:placetype":"locality",
    "wof:population":21156
},
  "geometry": {"coordinates":[130.68333000000001,33.35],"type":"Point"}
}