{
  "type": "Feature",
  "properties": {
    "gn:admin1_code":"16.0",
    "gn:admin2_code":"2112822.0",
    "gn:asciiname":"Towacho-ahyo",
    "gn:country_code":"JP",
    "gn:dem":100,
    "gn:feature_class":"P",
    "gn:feature_code":"PPL",
    "gn:name":"T\u014dwach\u014d-ahy\u014d",
    "gn:population":0,
    "gn:timezone":"Asia/Tokyo",
    "iso:country":"JP",
    "name:jpn_x_preferred":[
        "\u6771\u548c\u753a\u5b89\u4ff5"
    ],
    "name:jpn_x_variant":[
        "\u3068\u3046\u308f\u3061\u3087\u3046\u3042\u3072\u3087\u3046",
        "\u30c8\u30a6\u30ef\u30c1\u30e7\u30a6\u30a2\u30d2\u30e7\u30a6"
    ],
    "name:und_x_variant":[
        "T\u014dwach\u014d-ahy\u014d"
    ],
    "wof:name":"Towacho-ahyo",
    "wof:placetype":"locality"
},
  "geometry": {"coordinates":[141.21951999999999,39.38051],"type":"Point"}
}