{
  "type": "Feature",
  "properties": {
    "gn:admin1_code":"23",
    "gn:admin2_code":"1849544.0",
    "gn:asciiname":"Hakusancho-nihongi",
    "gn:country_code":"JP",
    "gn:dem":38,
    "gn:feature_class":"P",
    "gn:feature_code":"PPL",
    "gn:name":"Hakusanch\u014d-nihongi",
    "gn:population":0,
    "gn:timezone":"Asia/Tokyo",
    "iso:country":"JP",
    "name:jpn_x_preferred":[
        "\u767d\u5c71\u753a\u4e8c\u672c\u6728"
    ],
    "name:und_x_variant":[
        "Hakusanch\u014d-nihongi",
        "Nihongi"
    ],
    "wof:name":"Hakusancho-nihongi",
    "wof:placetype":"locality"
},
  "geometry": {"coordinates":[136.37118999999998,34.66126],"type":"Point"}
}