{
  "type": "Feature",
  "properties": {
    "gn:admin1_code":"47",
    "gn:admin2_code":"1861279.0",
    "gn:asciiname":"Arakaki",
    "gn:country_code":"JP",
    "gn:dem":81,
    "gn:feature_class":"P",
    "gn:feature_code":"PPL",
    "gn:name":"Arakaki",
    "gn:population":0,
    "gn:timezone":"Asia/Tokyo",
    "iso:country":"JP",
    "name:jpn_x_preferred":[
        "\u65b0\u57a3"
    ],
    "name:und_x_variant":[
        "Aragachi",
        "Arakachi",
        "Aragaki",
        "Arakaki"
    ],
    "wof:name":"Arakaki",
    "wof:placetype":"locality"
},
  "geometry": {"coordinates":[127.69634000000001,26.11779],"type":"Point"}
}