{
  "type": "Feature",
  "properties": {
    "gn:admin1_code":"09",
    "gn:admin2_code":"7419032.0",
    "gn:asciiname":"Furukawa",
    "gn:cc2":"JP",
    "gn:country_code":"JP",
    "gn:dem":491,
    "gn:feature_class":"P",
    "gn:feature_code":"PPL",
    "gn:name":"Furukawa",
    "gn:population":0,
    "gn:timezone":"Asia/Tokyo",
    "iso:country":"JP",
    "name:ara_x_preferred":[
        "\u0647\u064a\u062f\u0627 \u063a\u064a\u0641\u0648"
    ],
    "name:azb_x_preferred":[
        "\u0647\u06cc\u062f\u0627"
    ],
    "name:aze_x_preferred":[
        "Hida"
    ],
    "name:ceb_x_preferred":[
        "Hida"
    ],
    "name:ces_x_preferred":[
        "Hida"
    ],
    "name:deu_x_preferred":[
        "Hida"
    ],
    "name:epo_x_preferred":[
        "Hida"
    ],
    "name:fas_x_preferred":[
        "\u0647\u06cc\u062f\u0627"
    ],
    "name:fra_x_preferred":[
        "Hida"
    ],
    "name:ita_x_preferred":[
        "Hida"
    ],
    "name:jpn_x_preferred":[
        "\u98db\u9a28"
    ],
    "name:jpn_x_variant":[
        "\u98db\u9a28\u5e02"
    ],
    "name:kor_x_preferred":[
        "\ud788\ub2e4\uc2dc"
    ],
    "name:mzn_x_preferred":[
        "\u0647\u06cc\u062f\u0627"
    ],
    "name:nld_x_preferred":[
        "Hida"
    ],
    "name:pol_x_preferred":[
        "Hida"
    ],
    "name:por_x_preferred":[
        "Hida"
    ],
    "name:ron_x_preferred":[
        "Hida"
    ],
    "name:rus_x_preferred":[
        "\u0425\u0438\u0434\u0430"
    ],
    "name:spa_x_preferred":[
        "Hida"
    ],
    "name:sun_x_preferred":[
        "Hida"
    ],
    "name:swe_x_preferred":[
        "Hida"
    ],
    "name:tgk_x_preferred":[
        "\u04b2\u0438\u0434\u0430"
    ],
    "name:tgl_x_preferred":[
        "Hida"
    ],
    "name:tha_x_preferred":[
        "\u0e2e\u0e34\u0e14\u0e30"
    ],
    "name:tur_x_preferred":[
        "Hida"
    ],
    "name:ukr_x_preferred":[
        "\u0425\u0456\u0434\u0430"
    ],
    "name:und_x_variant":[
        "Furukawach\u014d",
        "Furukawa",
        "Hida"
    ],
    "name:vie_x_preferred":[
        "Hida"
    ],
    "name:war_x_preferred":[
        "Hida"
    ],
    "name:zho_x_preferred":[
        "\u98db\u9a52\u5e02"
    ],
    "wof:name":"Furukawa",
    "wof:placetype":"locality"
},
  "geometry": {"coordinates":[137.18333000000001,36.23333],"type":"Point"}
}