{
  "type": "Feature",
  "properties": {
    "gn:admin1_code":"09",
    "gn:admin2_code":"7419032.0",
    "gn:asciiname":"Furukawa",
    "gn:cc2":"JP",
    "gn:country_code":"JP",
    "gn:dem":491,
    "gn:feature_class":"P",
    "gn:feature_code":"PPL",
    "gn:name":"Furukawa",
    "gn:population":0,
    "gn:timezone":"Asia/Tokyo",
    "iso:country":"JP",
    "name:jpn_x_preferred":[
        "\u98db\u9a28"
    ],
    "name:und_x_variant":[
        "Furukawach\u014d",
        "Furukawa",
        "Hida"
    ],
    "wof:name":"Furukawa",
    "wof:placetype":"locality"
},
  "geometry": {"coordinates":[137.18333000000001,36.23333],"type":"Point"}
}