{
  "type": "Feature",
  "properties": {
    "gn:admin1_code":"21.0",
    "gn:admin2_code":"1859490.0",
    "gn:admin3_code":"43403.0",
    "gn:asciiname":"Nishikino",
    "gn:country_code":"JP",
    "gn:dem":111,
    "gn:feature_class":"P",
    "gn:feature_code":"PPL",
    "gn:name":"Nishikino",
    "gn:population":0,
    "gn:timezone":"Asia/Tokyo",
    "iso:country":"JP",
    "name:jpn_x_preferred":[
        "\u9326\u91ce"
    ],
    "name:jpn_x_variant":[
        "\u306b\u3057\u304d\u306e",
        "\u30cb\u30b7\u30ad\u30ce"
    ],
    "wof:name":"Nishikino",
    "wof:placetype":"locality"
},
  "geometry": {"coordinates":[130.90683999999999,32.86317],"type":"Point"}
}