{
  "type": "Feature",
  "properties": {
    "iso:country":"JP",
    "name:eng_x_preferred":[
        "Honcho 5 Chome"
    ],
    "name:eng_x_variant":[
        "Honchou 5 Choume",
        "Honcho 5 Chome"
    ],
    "name:jpn_x_preferred":[
        "\uff15\u4e01\u76ee"
    ],
    "name:jpn_x_variant":[
        "\u307b\u3093\u3061\u3087\u3046 \uff15\u3061\u3087\u3046\u3081",
        "\u672c\u753a \uff15\u4e01\u76ee",
        "\uff15\u3061\u3087\u3046\u3081"
    ],
    "qs:gn_local":0,
    "qs:local_max":6208,
    "qs:local_sum":82309,
    "qs:localhoods":190,
    "qs:name":"\uff15\u4e01\u76ee",
    "qs:name_adm0":"\u65e5\u672c",
    "qs:name_adm1":"\u795e\u5948\u5ddd\u770c",
    "qs:name_adm2":"\u4e2d\u533a",
    "qs:name_en":"Honcho 5 Chome",
    "qs:name_lau":"\u672c\u753a",
    "qs:name_local":"\u6a2a\u6d5c\u5e02",
    "qs:photo_max":37,
    "qs:photo_sum":37,
    "qs:placetype":"Suburb",
    "qs:quad_count":1,
    "qs:woe_adm0":23424856,
    "qs:woe_adm1":2345868,
    "qs:woe_adm2":15015441,
    "qs:woe_lau":28415751,
    "qs:woe_local":1118550,
    "qs:woe_ver":"7.10.0",
    "wof:lang":[
        "jpn"
    ],
    "wof:name":"\uff15\u4e01\u76ee",
    "wof:placetype":"neighbourhood"
},
  "geometry": {"coordinates":[139.63760400000001,35.448364],"type":"Point"}
}