{
  "type": "Feature",
  "properties": {
    "gn:admin1_code":"06",
    "gn:admin2_code":"1863982.0",
    "gn:asciiname":"Morita",
    "gn:country_code":"JP",
    "gn:dem":10,
    "gn:feature_class":"P",
    "gn:feature_code":"PPL",
    "gn:name":"Morita",
    "gn:population":0,
    "gn:timezone":"Asia/Tokyo",
    "iso:country":"JP",
    "wof:name":"Morita",
    "wof:placetype":"locality"
},
  "geometry": {"coordinates":[136.22677999999999,36.10855],"type":"Point"}
}