{
  "type": "Feature",
  "properties": {
    "iso:country":"JP",
    "label:eng_x_preferred_longname":[
        "Tanohata Village"
    ],
    "label:eng_x_preferred_placetype":[
        "village"
    ],
    "name:eng_x_preferred":[
        "Tanohata"
    ],
    "name:eng_x_variant":[
        "Tanohata Village"
    ],
    "name:jpn_x_preferred":[
        "\u7530\u91ce\u7551\u6751"
    ],
    "qs:name":"\u7530\u91ce\u7551\u6751",
    "qs:name_adm0":"\u65e5\u672c",
    "qs:name_adm1":"\u5ca9\u624b\u770c",
    "qs:photos":163,
    "qs:photos_1k":33,
    "qs:photos_9k":1,
    "qs:photos_9r":4,
    "qs:photos_all":163,
    "qs:photos_sr":4,
    "qs:placetype":"Town",
    "qs:pop_sr":"0",
    "wof:name":"Tanohata",
    "wof:placetype":"locality"
},
  "geometry": {"coordinates":[141.93692200000001,39.92718],"type":"Point"}
}