{
  "type": "Feature",
  "properties": {
    "gn:admin1_code":"43.0",
    "gn:admin2_code":"1865123.0",
    "gn:admin3_code":"30366.0",
    "gn:asciiname":"Nishihara",
    "gn:country_code":"JP",
    "gn:dem":276,
    "gn:feature_class":"P",
    "gn:feature_code":"PPL",
    "gn:name":"Nishihara",
    "gn:population":0,
    "gn:timezone":"Asia/Tokyo",
    "iso:country":"JP",
    "name:jpn_x_preferred":[
        "\u897f\u539f"
    ],
    "wof:name":"Nishihara",
    "wof:placetype":"locality"
},
  "geometry": {"coordinates":[135.42179999999999,34.0855],"type":"Point"}
}