{
  "type": "Feature",
  "properties": {
    "gn:admin1_code":"19.0",
    "gn:admin2_code":"1848350.0",
    "gn:admin3_code":"14113.0",
    "gn:asciiname":"Hakusan",
    "gn:country_code":"JP",
    "gn:dem":35,
    "gn:feature_class":"P",
    "gn:feature_code":"PPL",
    "gn:name":"Hakusan",
    "gn:population":0,
    "gn:timezone":"Asia/Tokyo",
    "iso:country":"JP",
    "name:jpn_x_preferred":[
        "\u767d\u5c71"
    ],
    "wof:name":"Hakusan",
    "wof:placetype":"locality"
},
  "geometry": {"coordinates":[139.55307999999999,35.50393],"type":"Point"}
}