{
  "type": "Feature",
  "properties": {
    "gn:admin1_code":"2.0",
    "gn:admin2_code":"2128783.0",
    "gn:asciiname":"Koso",
    "gn:country_code":"JP",
    "gn:dem":131,
    "gn:feature_class":"P",
    "gn:feature_code":"PPL",
    "gn:name":"K\u014dso",
    "gn:population":0,
    "gn:timezone":"Asia/Tokyo",
    "iso:country":"JP",
    "name:ceb_x_preferred":[
        "Koso"
    ],
    "name:jpn_x_preferred":[
        "\u9ad8\u5ca8"
    ],
    "name:swe_x_preferred":[
        "Koso"
    ],
    "name:und_x_variant":[
        "K\u014dso",
        "K\u014dso-j\u014ddan"
    ],
    "wof:name":"Koso",
    "wof:placetype":"locality"
},
  "geometry": {"coordinates":[140.38040000000001,40.35093],"type":"Point"}
}