{
  "type": "Feature",
  "properties": {
    "gn:admin1_code":"21.0",
    "gn:admin2_code":"7413152.0",
    "gn:asciiname":"Yazaki",
    "gn:country_code":"JP",
    "gn:dem":22,
    "gn:feature_class":"P",
    "gn:feature_code":"PPLL",
    "gn:name":"Yazaki",
    "gn:population":0,
    "gn:timezone":"Asia/Tokyo",
    "iso:country":"JP",
    "name:bul_x_preferred":[
        "\u042f\u0437\u0430\u043a\u0438"
    ],
    "name:deu_x_preferred":[
        "Yazaki S\u014dgy\u014d"
    ],
    "name:fra_x_preferred":[
        "Yazaki"
    ],
    "name:ind_x_preferred":[
        "Yazaki Corporation"
    ],
    "name:jpn_x_preferred":[
        "\u77e2\u5d0e"
    ],
    "name:jpn_x_variant":[
        "\u3084\u3056\u304d",
        "\u30e4\u30b6\u30ad",
        "\u77e2\u5d0e\u7dcf\u696d"
    ],
    "name:msa_x_preferred":[
        "Yazaki"
    ],
    "name:por_x_preferred":[
        "Yazaki"
    ],
    "name:ron_x_preferred":[
        "Yazaki"
    ],
    "wof:name":"Yazaki",
    "wof:placetype":"locality"
},
  "geometry": {"coordinates":[130.53538999999998,32.62512],"type":"Point"}
}