{
  "type": "Feature",
  "properties": {
    "gn:admin1_code":"37",
    "gn:admin2_code":"1863288.0",
    "gn:admin3_code":"22133.0",
    "gn:asciiname":"Mangori",
    "gn:cc2":"JP",
    "gn:country_code":"JP",
    "gn:dem":4,
    "gn:feature_class":"P",
    "gn:feature_code":"PPL",
    "gn:name":"Mang\u014dri",
    "gn:population":0,
    "gn:timezone":"Asia/Tokyo",
    "iso:country":"JP",
    "name:und_x_variant":[
        "Mak\u014dri",
        "Mag\u014dri",
        "Mang\u014dri"
    ],
    "wof:name":"Mangori",
    "wof:placetype":"locality"
},
  "geometry": {"coordinates":[137.63333,34.68333],"type":"Point"}
}