{
  "type": "Feature",
  "properties": {
    "gn:admin1_code":"47",
    "gn:admin2_code":"1854344.0",
    "gn:asciiname":"Yogi",
    "gn:country_code":"JP",
    "gn:dem":34,
    "gn:feature_class":"P",
    "gn:feature_code":"PPL",
    "gn:name":"Yogi",
    "gn:population":0,
    "gn:timezone":"Asia/Tokyo",
    "iso:country":"JP",
    "name:jpn_x_preferred":[
        "\u4e0e\u5100"
    ],
    "name:und_x_variant":[
        "Y\u016bji",
        "Yogi"
    ],
    "wof:name":"Yogi",
    "wof:placetype":"locality"
},
  "geometry": {"coordinates":[127.81305,26.31304],"type":"Point"}
}