{
  "type": "Feature",
  "properties": {
    "gn:admin1_code":"47",
    "gn:admin2_code":"1854344.0",
    "gn:asciiname":"Yogi",
    "gn:country_code":"JP",
    "gn:dem":34,
    "gn:feature_class":"P",
    "gn:feature_code":"PPL",
    "gn:name":"Yogi",
    "gn:population":0,
    "gn:timezone":"Asia/Tokyo",
    "iso:country":"JP",
    "name:ben_x_preferred":[
        "\u09af\u09cb\u0997\u09c0"
    ],
    "name:fas_x_preferred":[
        "\u06cc\u0648\u06af\u06cc"
    ],
    "name:hin_x_preferred":[
        "\u092f\u094b\u0917\u0940"
    ],
    "name:hun_x_preferred":[
        "J\u00f3gi"
    ],
    "name:hye_x_preferred":[
        "\u0545\u0578\u0563\u0565\u0580"
    ],
    "name:ind_x_preferred":[
        "Yogi"
    ],
    "name:jpn_x_preferred":[
        "\u4e0e\u5100"
    ],
    "name:kan_x_preferred":[
        "\u0caf\u0ccb\u0c97\u0cbf"
    ],
    "name:mar_x_preferred":[
        "\u092f\u094b\u0917\u0940"
    ],
    "name:mya_x_preferred":[
        "\u101a\u1031\u102c\u1002\u102e"
    ],
    "name:nld_x_preferred":[
        "Yogi"
    ],
    "name:por_x_preferred":[
        "Iogue"
    ],
    "name:spa_x_preferred":[
        "Yogui"
    ],
    "name:srp_x_preferred":[
        "\u0408\u043e\u0433\u0438"
    ],
    "name:swa_x_preferred":[
        "Yogi"
    ],
    "name:tha_x_preferred":[
        "\u0e42\u0e22\u0e04\u0e35"
    ],
    "name:und_x_variant":[
        "Y\u016bji",
        "Yogi"
    ],
    "name:urd_x_preferred":[
        "\u06cc\u0648\u06af\u06cc"
    ],
    "name:vie_x_preferred":[
        "Yogi"
    ],
    "name:zho_x_preferred":[
        "\u745c\u4f3d\u58eb"
    ],
    "wof:name":"Yogi",
    "wof:placetype":"locality"
},
  "geometry": {"coordinates":[127.81305,26.31304],"type":"Point"}
}