{
  "type": "Feature",
  "properties": {
    "iso:country":"JP",
    "label:eng_x_preferred_longname":[
        "Fujioka Town"
    ],
    "label:eng_x_preferred_placetype":[
        "town"
    ],
    "name:eng_x_preferred":[
        "Fujioka"
    ],
    "name:eng_x_variant":[
        "Fujioka Town"
    ],
    "name:jpn_x_preferred":[
        "\u85e4\u5ca1\u753a"
    ],
    "qs:name":"\u85e4\u5ca1\u753a",
    "qs:name_adm0":"\u65e5\u672c",
    "qs:name_adm1":"\u6803\u6728\u770c",
    "qs:photos":137,
    "qs:photos_1k":28,
    "qs:photos_9k":1,
    "qs:photos_9r":3,
    "qs:photos_all":137,
    "qs:photos_sr":3,
    "qs:placetype":"Town",
    "qs:pop_sr":"0",
    "wof:name":"Fujioka",
    "wof:placetype":"locality"
},
  "geometry": {"coordinates":[139.67760000000001,36.220171],"type":"Point"}
}