{
  "type": "Feature",
  "properties": {
    "gn:admin1_code":"21.0",
    "gn:admin2_code":"1858418.0",
    "gn:admin3_code":"43105.0",
    "gn:asciiname":"Mukaibaru",
    "gn:country_code":"JP",
    "gn:dem":89,
    "gn:feature_class":"P",
    "gn:feature_code":"PPLL",
    "gn:name":"Mukaibaru",
    "gn:population":0,
    "gn:timezone":"Asia/Tokyo",
    "iso:country":"JP",
    "name:jpn_x_preferred":[
        "\u5411\u539f"
    ],
    "name:jpn_x_variant":[
        "\u3080\u304b\u3044\u3070\u308b",
        "\u30e0\u30ab\u30a4\u30d0\u30eb"
    ],
    "wof:name":"Mukaibaru",
    "wof:placetype":"locality"
},
  "geometry": {"coordinates":[130.68688,32.92248],"type":"Point"}
}