{
  "type": "Feature",
  "properties": {
    "iso:country":"JP",
    "name:eng_x_preferred":[
        "Urahoro Town"
    ],
    "name:jpn_x_preferred":[
        "\u6d66\u5e4c\u753a"
    ],
    "qs:name":"\u6d66\u5e4c\u753a",
    "qs:name_adm0":"\u65e5\u672c",
    "qs:name_adm1":"\u5317\u6d77\u9053",
    "qs:photos":21,
    "qs:photos_1k":4,
    "qs:photos_9k":1,
    "qs:photos_9r":2,
    "qs:photos_all":28,
    "qs:photos_sr":1,
    "qs:placetype":"Town",
    "qs:pop_sr":"0",
    "wof:name":"Urahoro Town",
    "wof:placetype":"locality"
},
  "geometry": {"coordinates":[143.66863799999999,42.814],"type":"Point"}
}