{
  "type": "Feature",
  "properties": {
    "gn:admin1_code":"21.0",
    "gn:admin2_code":"7413152.0",
    "gn:asciiname":"Hatonohira",
    "gn:country_code":"JP",
    "gn:dem":68,
    "gn:feature_class":"P",
    "gn:feature_code":"PPLL",
    "gn:name":"Hatonohira",
    "gn:population":0,
    "gn:timezone":"Asia/Tokyo",
    "iso:country":"JP",
    "name:jpn_x_preferred":[
        "\u9ce9\u30ce\u5e73"
    ],
    "name:jpn_x_variant":[
        "\u306f\u3068\u306e\u3072\u3089",
        "\u30cf\u30c8\u30ce\u30d2\u30e9"
    ],
    "wof:name":"Hatonohira",
    "wof:placetype":"locality"
},
  "geometry": {"coordinates":[130.75484,32.59338],"type":"Point"}
}