{
  "type": "Feature",
  "properties": {
    "gn:admin1_code":"23.0",
    "gn:admin2_code":"1861901.0",
    "gn:asciiname":"Higashiyubune",
    "gn:country_code":"JP",
    "gn:dem":222,
    "gn:feature_class":"P",
    "gn:feature_code":"PPL",
    "gn:name":"Higashiyubune",
    "gn:population":0,
    "gn:timezone":"Asia/Tokyo",
    "iso:country":"JP",
    "name:jpn_x_preferred":[
        "\u6771\u6e6f\u821f"
    ],
    "wof:name":"Higashiyubune",
    "wof:placetype":"locality"
},
  "geometry": {"coordinates":[136.21046000000001,34.8634],"type":"Point"}
}