{
  "type": "Feature",
  "properties": {
    "gn:admin1_code":"21.0",
    "gn:admin2_code":"1864975.0",
    "gn:admin3_code":"43433.0",
    "gn:asciiname":"Kita",
    "gn:country_code":"JP",
    "gn:dem":378,
    "gn:feature_class":"P",
    "gn:feature_code":"PPLL",
    "gn:name":"Kita",
    "gn:population":0,
    "gn:timezone":"Asia/Tokyo",
    "iso:country":"JP",
    "name:jpn_x_preferred":[
        "\u559c\u591a"
    ],
    "name:jpn_x_variant":[
        "\u304d\u305f",
        "\u30ad\u30bf"
    ],
    "wof:name":"Kita",
    "wof:placetype":"locality"
},
  "geometry": {"coordinates":[131.00552999999999,32.85693],"type":"Point"}
}