{
  "type": "Feature",
  "properties": {
    "gn:admin1_code":"21.0",
    "gn:admin2_code":"1864975.0",
    "gn:admin3_code":"43433.0",
    "gn:asciiname":"Kita",
    "gn:country_code":"JP",
    "gn:dem":378,
    "gn:feature_class":"P",
    "gn:feature_code":"PPLL",
    "gn:name":"Kita",
    "gn:population":0,
    "gn:timezone":"Asia/Tokyo",
    "iso:country":"JP",
    "name:ara_x_preferred":[
        "\u0643\u064a\u062a\u0627"
    ],
    "name:ceb_x_preferred":[
        "Kita"
    ],
    "name:dan_x_preferred":[
        "Kita"
    ],
    "name:deu_x_preferred":[
        "Kita"
    ],
    "name:est_x_preferred":[
        "Kita"
    ],
    "name:fin_x_preferred":[
        "Kita"
    ],
    "name:fra_x_preferred":[
        "Kita"
    ],
    "name:heb_x_preferred":[
        "\u05db\u05d9\u05ea\u05d4"
    ],
    "name:ita_x_preferred":[
        "Kita"
    ],
    "name:jpn_x_preferred":[
        "\u559c\u591a"
    ],
    "name:jpn_x_variant":[
        "\u304d\u305f",
        "\u30ad\u30bf"
    ],
    "name:lav_x_preferred":[
        "Kita"
    ],
    "name:lit_x_preferred":[
        "Kita"
    ],
    "name:nld_x_preferred":[
        "Kita"
    ],
    "name:pol_x_preferred":[
        "Kita"
    ],
    "name:por_x_preferred":[
        "Kita"
    ],
    "name:ron_x_preferred":[
        "Kita"
    ],
    "name:sco_x_preferred":[
        "Kita"
    ],
    "name:slk_x_preferred":[
        "Kita"
    ],
    "name:slv_x_preferred":[
        "Kita"
    ],
    "name:swe_x_preferred":[
        "Kita"
    ],
    "name:ukr_x_preferred":[
        "\u041a\u0456\u0442\u0430"
    ],
    "wof:name":"Kita",
    "wof:placetype":"locality"
},
  "geometry": {"coordinates":[131.00552999999999,32.85693],"type":"Point"}
}