{
  "type": "Feature",
  "properties": {
    "gn:admin1_code":"7.0",
    "gn:admin2_code":"7406950.0",
    "gn:admin3_code":"40625.0",
    "gn:asciiname":"Saigawa-hobashira",
    "gn:country_code":"JP",
    "gn:dem":432,
    "gn:feature_class":"P",
    "gn:feature_code":"PPL",
    "gn:name":"Saigawa-hobashira",
    "gn:population":0,
    "gn:timezone":"Asia/Tokyo",
    "iso:country":"JP",
    "name:jpn_x_preferred":[
        "\u7280\u5ddd\u5e06\u67f1"
    ],
    "wof:name":"Saigawa-hobashira",
    "wof:placetype":"locality"
},
  "geometry": {"coordinates":[130.95533,33.52019],"type":"Point"}
}