{
  "type": "Feature",
  "properties": {
    "iso:country":"JP",
    "name:eng_x_preferred":[
        "Katashima 3 Chome"
    ],
    "name:eng_x_variant":[
        "Katashima 3 Choume",
        "Katashima 3 Chome"
    ],
    "name:jpn_x_preferred":[
        "\uff13\u4e01\u76ee"
    ],
    "name:jpn_x_variant":[
        "\u304b\u305f\u3057\u307e \uff13\u3061\u3087\u3046\u3081",
        "\u7247\u5cf6 \uff13\u4e01\u76ee",
        "\uff13\u3061\u3087\u3046\u3081"
    ],
    "qs:gn_local":0,
    "qs:local_max":844,
    "qs:local_sum":2732,
    "qs:localhoods":8,
    "qs:name":"\uff13\u4e01\u76ee",
    "qs:name_adm0":"\u65e5\u672c",
    "qs:name_adm1":"\u798f\u5ca1\u770c",
    "qs:name_en":"Katashima 3 Chome",
    "qs:name_lau":"\u7247\u5cf6",
    "qs:name_local":"\u98ef\u585a\u5e02",
    "qs:photo_max":85,
    "qs:photo_sum":231,
    "qs:placetype":"Suburb",
    "qs:quad_count":19,
    "qs:woe_adm0":23424856,
    "qs:woe_adm1":58646425,
    "qs:woe_adm2":0,
    "qs:woe_lau":28483796,
    "qs:woe_local":1109368,
    "qs:woe_ver":"7.10.0",
    "wof:lang":[
        "jpn"
    ],
    "wof:name":"\uff13\u4e01\u76ee",
    "wof:placetype":"neighbourhood"
},
  "geometry": {"coordinates":[130.67280099999999,33.654949],"type":"Point"}
}