{
  "type": "Feature",
  "properties": {
    "iso:country":"JP",
    "name:eng_x_preferred":[
        "Sawai 3 Chome"
    ],
    "name:eng_x_variant":[
        "Sawai 3 Choume",
        "Sawai 3 Chome"
    ],
    "name:jpn_x_preferred":[
        "\uff13\u4e01\u76ee"
    ],
    "name:jpn_x_variant":[
        "\u3055\u308f\u3044 \uff13\u3061\u3087\u3046\u3081",
        "\u6ca2\u4e95 \uff13\u4e01\u76ee",
        "\uff13\u3061\u3087\u3046\u3081"
    ],
    "qs:gn_local":0,
    "qs:local_max":653,
    "qs:local_sum":2188,
    "qs:localhoods":17,
    "qs:name":"\uff13\u4e01\u76ee",
    "qs:name_adm0":"\u65e5\u672c",
    "qs:name_adm1":"\u6771\u4eac\u90fd",
    "qs:name_en":"Sawai 3 Chome",
    "qs:name_lau":"\u6ca2\u4e95",
    "qs:name_local":"\u9752\u6885\u5e02",
    "qs:photo_max":7,
    "qs:photo_sum":19,
    "qs:placetype":"Suburb",
    "qs:quad_count":5,
    "qs:woe_adm0":23424856,
    "qs:woe_adm1":2345889,
    "qs:woe_adm2":0,
    "qs:woe_lau":28414956,
    "qs:woe_local":1113567,
    "qs:woe_ver":"7.10.0",
    "wof:lang":[
        "jpn"
    ],
    "wof:name":"\uff13\u4e01\u76ee",
    "wof:placetype":"neighbourhood"
},
  "geometry": {"coordinates":[139.16743199999999,35.813006],"type":"Point"}
}