{
  "type": "Feature",
  "properties": {
    "gn:admin1_code":"23.0",
    "gn:admin2_code":"1856290.0",
    "gn:asciiname":"Ryuguchi",
    "gn:country_code":"JP",
    "gn:dem":325,
    "gn:feature_class":"P",
    "gn:feature_code":"PPL",
    "gn:name":"Ry\u016bguchi",
    "gn:population":0,
    "gn:timezone":"Asia/Tokyo",
    "iso:country":"JP",
    "name:jpn_x_preferred":[
        "\u7adc\u53e3"
    ],
    "name:und_x_variant":[
        "Ry\u016bguchi"
    ],
    "wof:name":"Ryuguchi",
    "wof:placetype":"locality"
},
  "geometry": {"coordinates":[136.06667999999999,34.5721],"type":"Point"}
}