{
  "type": "Feature",
  "properties": {
    "gn:admin1_code":"19.0",
    "gn:admin2_code":"1855966.0",
    "gn:admin3_code":"14341.0",
    "gn:asciiname":"Koma",
    "gn:country_code":"JP",
    "gn:dem":9,
    "gn:feature_class":"P",
    "gn:feature_code":"PPL",
    "gn:name":"Koma",
    "gn:population":0,
    "gn:timezone":"Asia/Tokyo",
    "iso:country":"JP",
    "name:jpn_x_preferred":[
        "\u9ad8\u9e97"
    ],
    "name:jpn_x_variant":[
        "\u3053\u307e"
    ],
    "wof:name":"Koma",
    "wof:placetype":"locality"
},
  "geometry": {"coordinates":[139.32624999999999,35.32255],"type":"Point"}
}