{
  "type": "Feature",
  "properties": {
    "gn:admin1_code":"37.0",
    "gn:admin2_code":"1854900.0",
    "gn:asciiname":"Uchiura-omosu",
    "gn:country_code":"JP",
    "gn:dem":7,
    "gn:feature_class":"P",
    "gn:feature_code":"PPL",
    "gn:name":"Uchiura-omosu",
    "gn:population":0,
    "gn:timezone":"Asia/Tokyo",
    "iso:country":"JP",
    "name:jpn_x_preferred":[
        "\u5185\u6d66\u91cd\u9808"
    ],
    "wof:name":"Uchiura-omosu",
    "wof:placetype":"locality"
},
  "geometry": {"coordinates":[138.8869,35.0164],"type":"Point"}
}