{
  "type": "Feature",
  "properties": {
    "gn:admin1_code":"37.0",
    "gn:admin2_code":"1851376.0",
    "gn:asciiname":"Shimojo",
    "gn:country_code":"JP",
    "gn:dem":202,
    "gn:feature_class":"P",
    "gn:feature_code":"PPLL",
    "gn:name":"Shimoj\u014d",
    "gn:population":0,
    "gn:timezone":"Asia/Tokyo",
    "iso:country":"JP",
    "name:jpn_x_preferred":[
        "\u4e0b\u6761"
    ],
    "name:und_x_variant":[
        "Shimoj\u014d"
    ],
    "wof:name":"Shimojo",
    "wof:placetype":"locality"
},
  "geometry": {"coordinates":[138.89861999999999,35.20376],"type":"Point"}
}