{
  "type": "Feature",
  "properties": {
    "iso:country":"JP",
    "label:eng_x_preferred_longname":[
        "Kasaoka City"
    ],
    "label:eng_x_preferred_placetype":[
        "city"
    ],
    "name:eng_x_preferred":[
        "Kasaoka"
    ],
    "name:eng_x_variant":[
        "Kasaoka City"
    ],
    "name:jpn_x_preferred":[
        "\u7b20\u5ca1\u5e02"
    ],
    "qs:name":"\u7b20\u5ca1\u5e02",
    "qs:name_adm0":"\u65e5\u672c",
    "qs:name_adm1":"\u5ca1\u5c71\u770c",
    "qs:photos":577,
    "qs:photos_1k":117,
    "qs:photos_9k":3,
    "qs:photos_9r":5,
    "qs:photos_all":577,
    "qs:photos_sr":8,
    "qs:placetype":"Town",
    "qs:pop_sr":"0",
    "wof:name":"Kasaoka",
    "wof:placetype":"locality"
},
  "geometry": {"coordinates":[133.51959199999999,34.398978],"type":"Point"}
}