{
  "type": "Feature",
  "properties": {
    "gn:admin1_code":"18",
    "gn:admin2_code":"1853737.0",
    "gn:admin3_code":"46532.0",
    "gn:asciiname":"Itokina",
    "gn:country_code":"JP",
    "gn:dem":185,
    "gn:feature_class":"P",
    "gn:feature_code":"PPL",
    "gn:name":"Itokina",
    "gn:population":0,
    "gn:timezone":"Asia/Tokyo",
    "iso:country":"JP",
    "name:jpn_x_preferred":[
        "\u7cf8\u6728\u540d"
    ],
    "wof:name":"Itokina",
    "wof:placetype":"locality"
},
  "geometry": {"coordinates":[128.92394999999999,27.7319],"type":"Point"}
}