{
  "type": "Feature",
  "properties": {
    "gn:admin1_code":"2.0",
    "gn:admin2_code":"2128783.0",
    "gn:asciiname":"Karuizawa",
    "gn:country_code":"JP",
    "gn:dem":86,
    "gn:feature_class":"P",
    "gn:feature_code":"PPL",
    "gn:name":"Karuizawa",
    "gn:population":0,
    "gn:timezone":"Asia/Tokyo",
    "iso:country":"JP",
    "name:jpn_x_preferred":[
        "\u8efd\u4e95\u6ca2"
    ],
    "name:jpn_x_variant":[
        "\u304b\u308b\u3044\u3056\u308f",
        "\u30ab\u30eb\u30a4\u30b6\u30ef"
    ],
    "wof:name":"Karuizawa",
    "wof:placetype":"locality"
},
  "geometry": {"coordinates":[140.65181000000001,40.22203],"type":"Point"}
}