{
  "type": "Feature",
  "properties": {
    "gn:admin1_code":"32.0",
    "gn:admin2_code":"1859747.0",
    "gn:asciiname":"Ishimigawa",
    "gn:country_code":"JP",
    "gn:dem":433,
    "gn:feature_class":"P",
    "gn:feature_code":"PPL",
    "gn:name":"Ishimigawa",
    "gn:population":0,
    "gn:timezone":"Asia/Tokyo",
    "iso:country":"JP",
    "name:jpn_x_preferred":[
        "\u77f3\u898b\u5ddd"
    ],
    "wof:name":"Ishimigawa",
    "wof:placetype":"locality"
},
  "geometry": {"coordinates":[135.63596000000001,34.39497],"type":"Point"}
}