{
  "type": "Feature",
  "properties": {
    "gn:admin1_code":"12.0",
    "gn:admin2_code":"2129373.0",
    "gn:admin3_code":"1661.0",
    "gn:asciiname":"Wakacharase",
    "gn:country_code":"JP",
    "gn:dem":90,
    "gn:feature_class":"P",
    "gn:feature_code":"PPLL",
    "gn:name":"Wakacharase",
    "gn:population":0,
    "gn:timezone":"Asia/Tokyo",
    "iso:country":"JP",
    "name:jpn_x_preferred":[
        "\u5206\u9063\u702c"
    ],
    "name:jpn_x_variant":[
        "\u308f\u304b\u3061\u3083\u3089\u305b",
        "\u30ef\u30ab\u30c1\u30e3\u30e9\u30bb"
    ],
    "wof:name":"Wakacharase",
    "wof:placetype":"locality"
},
  "geometry": {"coordinates":[144.70282,42.94007],"type":"Point"}
}