{
  "type": "Feature",
  "properties": {
    "iso:country":"JP",
    "name:eng_x_preferred":[
        "Masugata 7 Chome"
    ],
    "name:eng_x_variant":[
        "Masugata 7 Choume",
        "Masugata 7 Chome"
    ],
    "name:jpn_x_preferred":[
        "\uff17\u4e01\u76ee"
    ],
    "name:jpn_x_variant":[
        "\u307e\u3059\u304c\u305f \uff17\u3061\u3087\u3046\u3081",
        "\u67a1\u5f62 \uff17\u4e01\u76ee",
        "\uff17\u3061\u3087\u3046\u3081"
    ],
    "qs:gn_adm0_cc":"JP",
    "qs:gn_local":1859642,
    "qs:local_max":4758,
    "qs:local_sum":25395,
    "qs:localhoods":83,
    "qs:name":"\uff17\u4e01\u76ee",
    "qs:name_adm0":"\u65e5\u672c",
    "qs:name_adm1":"\u795e\u5948\u5ddd\u770c",
    "qs:name_adm2":"\u591a\u6469\u533a",
    "qs:name_en":"Masugata 7 Chome",
    "qs:name_lau":"\u67a1\u5f62",
    "qs:name_local":"\u5ddd\u5d0e\u5e02",
    "qs:photo_max":106,
    "qs:photo_sum":458,
    "qs:placetype":"Suburb",
    "qs:quad_count":10,
    "qs:woe_adm0":23424856,
    "qs:woe_adm1":2345868,
    "qs:woe_adm2":1109419,
    "qs:woe_lau":28416447,
    "qs:woe_local":1117502,
    "qs:woe_ver":"7.10.0",
    "wof:lang":[
        "jpn"
    ],
    "wof:name":"\uff17\u4e01\u76ee",
    "wof:placetype":"neighbourhood"
},
  "geometry": {"coordinates":[139.560214,35.608569],"type":"Point"}
}