{
  "type": "Feature",
  "properties": {
    "gn:admin1_code":"21.0",
    "gn:admin2_code":"1864975.0",
    "gn:admin3_code":"43423.0",
    "gn:asciiname":"Ogi",
    "gn:country_code":"JP",
    "gn:dem":607,
    "gn:feature_class":"P",
    "gn:feature_code":"PPLL",
    "gn:name":"\u014cgi",
    "gn:population":0,
    "gn:timezone":"Asia/Tokyo",
    "iso:country":"JP",
    "name:jpn_x_preferred":[
        "\u6247"
    ],
    "name:jpn_x_variant":[
        "\u304a\u3046\u304e",
        "\u30aa\u30a6\u30ae"
    ],
    "name:und_x_variant":[
        "\u014cgi"
    ],
    "wof:name":"Ogi",
    "wof:placetype":"locality"
},
  "geometry": {"coordinates":[131.10741000000002,33.07178],"type":"Point"}
}