{
  "type": "Feature",
  "properties": {
    "gn:admin1_code":"21.0",
    "gn:admin2_code":"7412709.0",
    "gn:admin3_code":"43348.0",
    "gn:asciiname":"Tsurugino",
    "gn:country_code":"JP",
    "gn:dem":128,
    "gn:feature_class":"P",
    "gn:feature_code":"PPLL",
    "gn:name":"Tsurugino",
    "gn:population":0,
    "gn:timezone":"Asia/Tokyo",
    "iso:country":"JP",
    "name:jpn_x_preferred":[
        "\u9db4\u6728\u91ce"
    ],
    "name:jpn_x_variant":[
        "\u3064\u308b\u304e\u306e",
        "\u30c4\u30eb\u30ae\u30ce"
    ],
    "wof:name":"Tsurugino",
    "wof:placetype":"locality"
},
  "geometry": {"coordinates":[130.81926999999999,32.61597],"type":"Point"}
}