{
  "type": "Feature",
  "properties": {
    "gn:admin1_code":"21.0",
    "gn:admin2_code":"1864975.0",
    "gn:admin3_code":"43433.0",
    "gn:asciiname":"Hakamano",
    "gn:country_code":"JP",
    "gn:dem":542,
    "gn:feature_class":"P",
    "gn:feature_code":"PPLL",
    "gn:name":"Hakamano",
    "gn:population":0,
    "gn:timezone":"Asia/Tokyo",
    "iso:country":"JP",
    "name:jpn_x_preferred":[
        "\u88b4\u91ce"
    ],
    "name:jpn_x_variant":[
        "\u306f\u304b\u307e\u306e",
        "\u30cf\u30ab\u30de\u30ce"
    ],
    "wof:name":"Hakamano",
    "wof:placetype":"locality"
},
  "geometry": {"coordinates":[131.02698000000001,32.8605],"type":"Point"}
}