{
  "type": "Feature",
  "properties": {
    "gn:admin1_code":"12.0",
    "gn:admin2_code":"2128971.0",
    "gn:asciiname":"Onneto",
    "gn:country_code":"JP",
    "gn:dem":16,
    "gn:feature_class":"P",
    "gn:feature_code":"PPL",
    "gn:name":"Onnet\u014d",
    "gn:population":0,
    "gn:timezone":"Asia/Tokyo",
    "iso:country":"JP",
    "name:jpn_x_preferred":[
        "\u6e29\u6839\u6cbc"
    ],
    "name:jpn_x_variant":[
        "\u304a\u3093\u306d\u3068\u3046",
        "\u30aa\u30f3\u30cd\u30c8\u30a6"
    ],
    "name:und_x_variant":[
        "Onnet\u014d"
    ],
    "wof:name":"Onneto",
    "wof:placetype":"locality"
},
  "geometry": {"coordinates":[145.50546,43.27889],"type":"Point"}
}