{
  "type": "Feature",
  "properties": {
    "gn:admin1_code":"4.0",
    "gn:admin2_code":"1859468.0",
    "gn:asciiname":"Uehara",
    "gn:country_code":"JP",
    "gn:dem":40,
    "gn:feature_class":"P",
    "gn:feature_code":"PPLL",
    "gn:name":"Uehara",
    "gn:population":0,
    "gn:timezone":"Asia/Tokyo",
    "iso:country":"JP",
    "name:jpn_x_preferred":[
        "\u4e0a\u539f"
    ],
    "name:jpn_x_variant":[
        "\u3046\u3048\u306f\u3089",
        "\u30a6\u30a8\u30cf\u30e9"
    ],
    "name:kor_x_preferred":[
        "\uc6b0\uc5d0\ud558\ub77c"
    ],
    "wof:name":"Uehara",
    "wof:placetype":"locality"
},
  "geometry": {"coordinates":[140.04292000000001,35.31825999999999],"type":"Point"}
}