{
  "type": "Feature",
  "properties": {
    "gn:admin1_code":"18.0",
    "gn:admin2_code":"1862007.0",
    "gn:asciiname":"Yamagawa-irifunecho",
    "gn:country_code":"JP",
    "gn:dem":4,
    "gn:feature_class":"P",
    "gn:feature_code":"PPL",
    "gn:name":"Yamagawa-irifunech\u014d",
    "gn:population":0,
    "gn:timezone":"Asia/Tokyo",
    "iso:country":"JP",
    "name:jpn_x_preferred":[
        "\u5c71\u5ddd\u5165\u8239\u753a"
    ],
    "name:und_x_variant":[
        "Yamagawa-irifunech\u014d"
    ],
    "wof:name":"Yamagawa-irifunecho",
    "wof:placetype":"locality"
},
  "geometry": {"coordinates":[130.63693000000001,31.20526],"type":"Point"}
}