{
  "type": "Feature",
  "properties": {
    "gn:admin1_code":"37.0",
    "gn:admin2_code":"1854900.0",
    "gn:asciiname":"Shimogawaracho",
    "gn:country_code":"JP",
    "gn:dem":4,
    "gn:feature_class":"P",
    "gn:feature_code":"PPL",
    "gn:name":"Shimogawarach\u014d",
    "gn:population":0,
    "gn:timezone":"Asia/Tokyo",
    "iso:country":"JP",
    "name:jpn_x_preferred":[
        "\u4e0b\u6cb3\u539f\u753a"
    ],
    "name:und_x_variant":[
        "Shimogawarach\u014d"
    ],
    "wof:name":"Shimogawaracho",
    "wof:placetype":"locality"
},
  "geometry": {"coordinates":[138.85809,35.08843],"type":"Point"}
}