{
  "type": "Feature",
  "properties": {
    "gn:admin1_code":"4.0",
    "gn:admin2_code":"7465524.0",
    "gn:asciiname":"Kobukuwara",
    "gn:country_code":"JP",
    "gn:dem":2,
    "gn:feature_class":"P",
    "gn:feature_code":"PPLL",
    "gn:name":"Kobukuwara",
    "gn:population":0,
    "gn:timezone":"Asia/Tokyo",
    "iso:country":"JP",
    "name:jpn_x_preferred":[
        "\u5c0f\u798f\u539f"
    ],
    "name:jpn_x_variant":[
        "\u3053\u3076\u304f\u308f\u3089",
        "\u30b3\u30d6\u30af\u30ef\u30e9"
    ],
    "wof:name":"Kobukuwara",
    "wof:placetype":"locality"
},
  "geometry": {"coordinates":[140.38508000000002,35.3064],"type":"Point"}
}