{
  "type": "Feature",
  "properties": {
    "gn:admin1_code":"4.0",
    "gn:admin2_code":"7465524.0",
    "gn:asciiname":"Kamigumi",
    "gn:country_code":"JP",
    "gn:dem":42,
    "gn:feature_class":"P",
    "gn:feature_code":"PPLL",
    "gn:name":"Kamigumi",
    "gn:population":0,
    "gn:timezone":"Asia/Tokyo",
    "iso:country":"JP",
    "name:jpn_x_preferred":[
        "\u4e0a\u7d44"
    ],
    "name:jpn_x_variant":[
        "\u304b\u307f\u3050\u307f",
        "\u30ab\u30df\u30b0\u30df"
    ],
    "wof:name":"Kamigumi",
    "wof:placetype":"locality"
},
  "geometry": {"coordinates":[140.32148999999998,35.34277],"type":"Point"}
}