{
  "type": "Feature",
  "properties": {
    "iso:country":"JP",
    "name:eng_x_preferred":[
        "Kiyosumi 2 Chome"
    ],
    "name:eng_x_variant":[
        "Kiyosumi 2 Choume",
        "Kiyosumi 2 Chome"
    ],
    "name:jpn_x_preferred":[
        "\uff12\u4e01\u76ee"
    ],
    "name:jpn_x_variant":[
        "\u304d\u3088\u3059\u307f \uff12\u3061\u3087\u3046\u3081",
        "\u6e05\u4f4f \uff12\u4e01\u76ee",
        "\uff12\u3061\u3087\u3046\u3081"
    ],
    "qs:gn_adm0_cc":"JP",
    "qs:gn_local":1926099,
    "qs:gn_nam_loc":"\u677e\u5c71\u5e02, \u611b\u5a9b\u770c, JP",
    "qs:gn_namadm1":"05",
    "qs:local_max":845,
    "qs:local_sum":2298,
    "qs:localhoods":15,
    "qs:name":"\uff12\u4e01\u76ee",
    "qs:name_adm0":"\u65e5\u672c",
    "qs:name_adm1":"\u611b\u5a9b\u770c",
    "qs:name_en":"Kiyosumi 2 Chome",
    "qs:name_lau":"\u6e05\u4f4f",
    "qs:name_local":"\u677e\u5c71\u5e02",
    "qs:photo_max":9,
    "qs:photo_sum":9,
    "qs:placetype":"Suburb",
    "qs:quad_count":1,
    "qs:woe_adm0":23424856,
    "qs:woe_adm1":2345855,
    "qs:woe_adm2":0,
    "qs:woe_lau":28479089,
    "qs:woe_local":1117690,
    "qs:woe_ver":"7.10.0",
    "wof:lang":[
        "jpn"
    ],
    "wof:name":"\uff12\u4e01\u76ee",
    "wof:placetype":"neighbourhood"
},
  "geometry": {"coordinates":[132.71759,33.849888],"type":"Point"}
}