{
  "type": "Feature",
  "properties": {
    "gn:admin1_code":"4.0",
    "gn:admin2_code":"1863711.0",
    "gn:asciiname":"Uruzu",
    "gn:country_code":"JP",
    "gn:dem":11,
    "gn:feature_class":"P",
    "gn:feature_code":"PPL",
    "gn:name":"Uruzu",
    "gn:population":0,
    "gn:timezone":"Asia/Tokyo",
    "iso:country":"JP",
    "name:jpn_x_preferred":[
        "\u58f2\u6d25"
    ],
    "name:jpn_x_variant":[
        "\u3046\u308b\u3065",
        "\u30a6\u30eb\u30c5"
    ],
    "wof:name":"Uruzu",
    "wof:placetype":"locality"
},
  "geometry": {"coordinates":[139.87792999999999,35.21306],"type":"Point"}
}