{
  "type": "Feature",
  "properties": {
    "iso:country":"JP",
    "name:eng_x_preferred":[
        "Minogawashinmachi 1 Chome"
    ],
    "name:eng_x_variant":[
        "Minogawashinmachi 1 Choume",
        "Minogawashinmachi 1 Chome"
    ],
    "name:jpn_x_preferred":[
        "\uff11\u4e01\u76ee"
    ],
    "name:jpn_x_variant":[
        "\u307f\u306e\u304c\u308f\u3057\u3093\u307e\u3061 \uff11\u3061\u3087\u3046\u3081",
        "\u84d1\u5ddd\u65b0\u753a \uff11\u4e01\u76ee",
        "\uff11\u3061\u3087\u3046\u3081"
    ],
    "name:unk_x_variant":[
        "\uff11\u4e01\u76ee"
    ],
    "qs:gn_local":0,
    "qs:local_max":478,
    "qs:local_sum":1073,
    "qs:localhoods":9,
    "qs:name":"\uff11\u4e01\u76ee",
    "qs:name_adm0":"\u65e5\u672c",
    "qs:name_adm1":"\u611b\u77e5\u770c",
    "qs:name_en":"Minogawashinmachi 1 Chome",
    "qs:name_lau":"\u84d1\u5ddd\u65b0\u753a",
    "qs:name_local":"\u5ca1\u5d0e\u5e02",
    "qs:photo_max":3,
    "qs:photo_sum":8,
    "qs:placetype":"Suburb",
    "qs:quad_count":5,
    "qs:woe_adm0":23424856,
    "qs:woe_adm1":2345851,
    "qs:woe_adm2":0,
    "qs:woe_lau":28440935,
    "qs:woe_local":1117966,
    "qs:woe_ver":"7.10.0",
    "wof:lang":[
        "jpn"
    ],
    "wof:name":"\uff11\u4e01\u76ee",
    "wof:placetype":"neighbourhood"
},
  "geometry": {"coordinates":[137.19863899999999,34.93098],"type":"Point"}
}