{
  "type": "Feature",
  "properties": {
    "gn:admin1_code":"12.0",
    "gn:admin2_code":"2127817.0",
    "gn:admin3_code":"1520.0",
    "gn:asciiname":"Mizuguchibokujo",
    "gn:cc2":"JP",
    "gn:country_code":"JP",
    "gn:dem":1,
    "gn:feature_class":"P",
    "gn:feature_code":"PPL",
    "gn:name":"Mizuguchibokuj\u014d",
    "gn:population":0,
    "gn:timezone":"Asia/Tokyo",
    "iso:country":"JP",
    "name:und_x_variant":[
        "Hamasato",
        "Minakuchi",
        "Mizuguchi",
        "Minaguchi",
        "Mizuguchibokuj\u014d"
    ],
    "wof:name":"Mizuguchibokujo",
    "wof:placetype":"locality"
},
  "geometry": {"coordinates":[141.66666999999995,45.03333],"type":"Point"}
}