{
  "type": "Feature",
  "properties": {
    "gn:admin1_code":"7.0",
    "gn:admin2_code":"1859306.0",
    "gn:admin3_code":"40106.0",
    "gn:asciiname":"Konomimachi",
    "gn:country_code":"JP",
    "gn:dem":6,
    "gn:feature_class":"P",
    "gn:feature_code":"PPL",
    "gn:name":"Konomimachi",
    "gn:population":0,
    "gn:timezone":"Asia/Tokyo",
    "iso:country":"JP",
    "name:jpn_x_preferred":[
        "\u8a31\u6590\u753a"
    ],
    "wof:name":"Konomimachi",
    "wof:placetype":"locality"
},
  "geometry": {"coordinates":[130.87783999999999,33.89407],"type":"Point"}
}