{
  "type": "Feature",
  "properties": {
    "gn:admin1_code":"37.0",
    "gn:admin2_code":"1864104.0",
    "gn:asciiname":"Shibayama",
    "gn:country_code":"JP",
    "gn:dem":506,
    "gn:feature_class":"P",
    "gn:feature_code":"PPLL",
    "gn:name":"Shibayama",
    "gn:population":0,
    "gn:timezone":"Asia/Tokyo",
    "iso:country":"JP",
    "name:jpn_x_preferred":[
        "\u829d\u5c71"
    ],
    "wof:name":"Shibayama",
    "wof:placetype":"locality"
},
  "geometry": {"coordinates":[138.58944,35.31702999999999],"type":"Point"}
}