{
  "type": "Feature",
  "properties": {
    "gn:admin1_code":"13.0",
    "gn:admin2_code":"1855204.0",
    "gn:asciiname":"Yamaguchicho-kamiyamaguchi",
    "gn:country_code":"JP",
    "gn:dem":260,
    "gn:feature_class":"P",
    "gn:feature_code":"PPL",
    "gn:name":"Yamaguchich\u014d-kamiyamaguchi",
    "gn:population":0,
    "gn:timezone":"Asia/Tokyo",
    "iso:country":"JP",
    "name:jpn_x_preferred":[
        "\u5c71\u53e3\u753a\u4e0a\u5c71\u53e3"
    ],
    "name:und_x_variant":[
        "Yamaguchich\u014d-kamiyamaguchi"
    ],
    "wof:name":"Yamaguchicho-kamiyamaguchi",
    "wof:placetype":"locality"
},
  "geometry": {"coordinates":[135.24866,34.82416],"type":"Point"}
}