{
  "type": "Feature",
  "properties": {
    "gn:admin1_code":"21.0",
    "gn:admin2_code":"1865358.0",
    "gn:asciiname":"Hajinohara",
    "gn:country_code":"JP",
    "gn:dem":52,
    "gn:feature_class":"P",
    "gn:feature_code":"PPLL",
    "gn:name":"Hajinohara",
    "gn:population":0,
    "gn:timezone":"Asia/Tokyo",
    "iso:country":"JP",
    "name:jpn_x_preferred":[
        "\u67a6\u306e\u539f"
    ],
    "name:jpn_x_variant":[
        "\u306f\u3058\u306e\u306f\u3089",
        "\u30cf\u30b8\u30ce\u30cf\u30e9"
    ],
    "wof:name":"Hajinohara",
    "wof:placetype":"locality"
},
  "geometry": {"coordinates":[130.15563,32.47822],"type":"Point"}
}