{
  "type": "Feature",
  "properties": {
    "gn:admin1_code":"45.0",
    "gn:admin2_code":"1852222.0",
    "gn:asciiname":"Mukunocho",
    "gn:country_code":"JP",
    "gn:dem":21,
    "gn:feature_class":"P",
    "gn:feature_code":"PPL",
    "gn:name":"Mukunoch\u014d",
    "gn:population":0,
    "gn:timezone":"Asia/Tokyo",
    "iso:country":"JP",
    "name:jpn_x_preferred":[
        "\u690b\u91ce\u753a"
    ],
    "name:und_x_variant":[
        "Mukunoch\u014d"
    ],
    "wof:name":"Mukunocho",
    "wof:placetype":"locality"
},
  "geometry": {"coordinates":[130.94607999999999,33.97828],"type":"Point"}
}