{
  "type": "Feature",
  "properties": {
    "gn:admin1_code":"12.0",
    "gn:admin2_code":"7428083.0",
    "gn:admin3_code":"1610.0",
    "gn:asciiname":"Mitsuishi-tomisawa",
    "gn:country_code":"JP",
    "gn:dem":56,
    "gn:feature_class":"P",
    "gn:feature_code":"PPL",
    "gn:name":"Mitsuishi-tomisawa",
    "gn:population":0,
    "gn:timezone":"Asia/Tokyo",
    "iso:country":"JP",
    "name:jpn_x_preferred":[
        "\u4e09\u77f3\u5bcc\u6ca2"
    ],
    "wof:name":"Mitsuishi-tomisawa",
    "wof:placetype":"locality"
},
  "geometry": {"coordinates":[142.62176000000005,42.30825],"type":"Point"}
}