{
  "type": "Feature",
  "properties": {
    "iso:country":"JP",
    "name:eng_x_preferred":[
        "Asakura Ko"
    ],
    "name:eng_x_variant":[
        "Asakura Kou",
        "Asakura Ko"
    ],
    "name:jpn_x_preferred":[
        "\u7532"
    ],
    "name:jpn_x_variant":[
        "\u3042\u3055\u304f\u3089 \u3053\u3046",
        "\u3053\u3046",
        "\u671d\u5009 \u7532"
    ],
    "name:unk_x_variant":[
        "\u7532"
    ],
    "qs:gn_local":0,
    "qs:local_max":565,
    "qs:local_sum":1354,
    "qs:localhoods":19,
    "qs:name":"\u7532",
    "qs:name_adm0":"\u65e5\u672c",
    "qs:name_adm1":"\u9ad8\u77e5\u770c",
    "qs:name_en":"Asakura Ko",
    "qs:name_lau":"\u671d\u5009",
    "qs:name_local":"\u9ad8\u77e5\u5e02",
    "qs:photo_max":11,
    "qs:photo_sum":21,
    "qs:placetype":"Suburb",
    "qs:quad_count":4,
    "qs:woe_adm0":23424856,
    "qs:woe_adm1":2345869,
    "qs:woe_adm2":0,
    "qs:woe_lau":28480735,
    "qs:woe_local":1117548,
    "qs:woe_ver":"7.10.0",
    "wof:lang":[
        "jpn"
    ],
    "wof:name":"\u7532",
    "wof:placetype":"neighbourhood"
},
  "geometry": {"coordinates":[133.49052399999999,33.552269],"type":"Point"}
}