{
  "type": "Feature",
  "properties": {
    "gn:admin1_code":"21.0",
    "gn:admin2_code":"1865168.0",
    "gn:asciiname":"Ushinomizu-shimo",
    "gn:country_code":"JP",
    "gn:dem":4,
    "gn:feature_class":"P",
    "gn:feature_code":"PPLL",
    "gn:name":"Ushinomizu-shimo",
    "gn:population":0,
    "gn:timezone":"Asia/Tokyo",
    "iso:country":"JP",
    "name:jpn_x_preferred":[
        "\u725b\u6c34\u4e0b"
    ],
    "name:jpn_x_variant":[
        "\u3046\u3057\u306e\u307f\u305a\u3057\u3082",
        "\u30a6\u30b7\u30ce\u30df\u30ba\u30b7\u30e2"
    ],
    "wof:name":"Ushinomizu-shimo",
    "wof:placetype":"locality"
},
  "geometry": {"coordinates":[130.43932000000001,32.94514],"type":"Point"}
}