{
  "type": "Feature",
  "properties": {
    "gn:admin1_code":"2.0",
    "gn:admin2_code":"2128783.0",
    "gn:asciiname":"Jusanmori",
    "gn:country_code":"JP",
    "gn:dem":94,
    "gn:feature_class":"P",
    "gn:feature_code":"PPL",
    "gn:name":"J\u016bsanmori",
    "gn:population":0,
    "gn:timezone":"Asia/Tokyo",
    "iso:country":"JP",
    "name:jpn_x_preferred":[
        "\u5341\u4e09\u68ee"
    ],
    "name:jpn_x_variant":[
        "\u3058\u3085\u3046\u3055\u3093\u3082\u308a",
        "\u30b8\u30e5\u30a6\u30b5\u30f3\u30e2\u30ea"
    ],
    "name:und_x_variant":[
        "J\u016bsanmori"
    ],
    "wof:name":"Jusanmori",
    "wof:placetype":"locality"
},
  "geometry": {"coordinates":[140.55791000000002,40.33406],"type":"Point"}
}