{
  "type": "Feature",
  "properties": {
    "gn:admin1_code":"4.0",
    "gn:admin2_code":"1863711.0",
    "gn:asciiname":"Nishinoyatsu",
    "gn:country_code":"JP",
    "gn:dem":13,
    "gn:feature_class":"P",
    "gn:feature_code":"PPLL",
    "gn:name":"Nishinoyatsu",
    "gn:population":0,
    "gn:timezone":"Asia/Tokyo",
    "iso:country":"JP",
    "name:jpn_x_preferred":[
        "\u897f\u30ce\u8c37"
    ],
    "name:jpn_x_variant":[
        "\u306b\u3057\u306e\u3084\u3064",
        "\u30cb\u30b7\u30ce\u30e4\u30c4"
    ],
    "wof:name":"Nishinoyatsu",
    "wof:placetype":"locality"
},
  "geometry": {"coordinates":[139.86282,35.28511],"type":"Point"}
}