{
  "type": "Feature",
  "properties": {
    "gn:admin1_code":"21.0",
    "gn:admin2_code":"1848441.0",
    "gn:asciiname":"Hinagu-otsubomachi",
    "gn:country_code":"JP",
    "gn:dem":2,
    "gn:feature_class":"P",
    "gn:feature_code":"PPL",
    "gn:name":"Hinagu-\u014dtsubomachi",
    "gn:population":0,
    "gn:timezone":"Asia/Tokyo",
    "iso:country":"JP",
    "name:jpn_x_preferred":[
        "\u65e5\u5948\u4e45\u5927\u576a\u753a"
    ],
    "name:und_x_variant":[
        "Hinagu-\u014dtsubomachi"
    ],
    "wof:name":"Hinagu-otsubomachi",
    "wof:placetype":"locality"
},
  "geometry": {"coordinates":[130.58551,32.44689],"type":"Point"}
}