{
  "type": "Feature",
  "properties": {
    "gn:admin1_code":"14.0",
    "gn:admin2_code":"7452799.0",
    "gn:asciiname":"Fuda",
    "gn:country_code":"JP",
    "gn:dem":23,
    "gn:feature_class":"P",
    "gn:feature_code":"PPL",
    "gn:name":"Fuda",
    "gn:population":0,
    "gn:timezone":"Asia/Tokyo",
    "iso:country":"JP",
    "name:ceb_x_preferred":[
        "Fuda"
    ],
    "name:swe_x_preferred":[
        "Fuda"
    ],
    "wof:name":"Fuda",
    "wof:placetype":"locality"
},
  "geometry": {"coordinates":[140.55000000000001,36.08333],"type":"Point"}
}