{
  "type": "Feature",
  "properties": {
    "gn:admin1_code":"13.0",
    "gn:admin2_code":"7370813.0",
    "gn:asciiname":"Nagasaka",
    "gn:country_code":"JP",
    "gn:dem":178,
    "gn:feature_class":"P",
    "gn:feature_code":"PPL",
    "gn:name":"Nagasaka",
    "gn:population":0,
    "gn:timezone":"Asia/Tokyo",
    "iso:country":"JP",
    "name:jpn_x_preferred":[
        "\u9577\u5742"
    ],
    "wof:name":"Nagasaka",
    "wof:placetype":"locality"
},
  "geometry": {"coordinates":[135.18093000000002,34.94242],"type":"Point"}
}