{
  "type": "Feature",
  "properties": {
    "gn:admin1_code":"4.0",
    "gn:admin2_code":"2112997.0",
    "gn:admin3_code":"12422.0",
    "gn:asciiname":"Aragami",
    "gn:country_code":"JP",
    "gn:dem":39,
    "gn:feature_class":"P",
    "gn:feature_code":"PPLL",
    "gn:name":"Aragami",
    "gn:population":0,
    "gn:timezone":"Asia/Tokyo",
    "iso:country":"JP",
    "name:jpn_x_preferred":[
        "\u8352\u4e0a"
    ],
    "name:jpn_x_variant":[
        "\u3042\u3089\u304c\u307f",
        "\u30a2\u30e9\u30ac\u30df"
    ],
    "wof:name":"Aragami",
    "wof:placetype":"locality"
},
  "geometry": {"coordinates":[140.27597,35.33331],"type":"Point"}
}