{
  "type": "Feature",
  "properties": {
    "gn:admin1_code":"44",
    "gn:admin2_code":"1862730.0",
    "gn:admin3_code":"6428.0",
    "gn:asciiname":"Soezu",
    "gn:country_code":"JP",
    "gn:dem":13,
    "gn:feature_class":"P",
    "gn:feature_code":"PPL",
    "gn:name":"Soezu",
    "gn:population":0,
    "gn:timezone":"Asia/Tokyo",
    "iso:country":"JP",
    "name:jpn_x_preferred":[
        "\u6dfb\u6d25"
    ],
    "name:und_x_variant":[
        "Soetsu",
        "Soezu"
    ],
    "wof:name":"Soezu",
    "wof:placetype":"locality"
},
  "geometry": {"coordinates":[139.95820000000001,38.76655],"type":"Point"}
}