{
  "type": "Feature",
  "properties": {
    "gn:admin1_code":"21.0",
    "gn:admin2_code":"1859488.0",
    "gn:asciiname":"Takenomaki",
    "gn:country_code":"JP",
    "gn:dem":432,
    "gn:feature_class":"P",
    "gn:feature_code":"PPLL",
    "gn:name":"Takenomaki",
    "gn:population":0,
    "gn:timezone":"Asia/Tokyo",
    "iso:country":"JP",
    "name:jpn_x_preferred":[
        "\u7af9\u4e4b\u7267"
    ],
    "name:jpn_x_variant":[
        "\u305f\u3051\u306e\u307e\u304d",
        "\u30bf\u30b1\u30ce\u30de\u30ad"
    ],
    "wof:name":"Takenomaki",
    "wof:placetype":"locality"
},
  "geometry": {"coordinates":[130.90804,33.01485],"type":"Point"}
}