{
  "type": "Feature",
  "properties": {
    "gn:admin1_code":"19.0",
    "gn:admin2_code":"1848308.0",
    "gn:asciiname":"Green Heights",
    "gn:country_code":"JP",
    "gn:dem":35,
    "gn:feature_class":"P",
    "gn:feature_code":"PPL",
    "gn:name":"Green Heights",
    "gn:population":0,
    "gn:timezone":"Asia/Tokyo",
    "iso:country":"JP",
    "name:jpn_x_preferred":[
        "\u30b0\u30ea\u30fc\u30f3\u30cf\u30a4\u30c4"
    ],
    "name:jpn_x_variant":[
        "\u3050\u308a\u30fc\u3093\u306f\u3044\u3064"
    ],
    "wof:name":"Green Heights",
    "wof:placetype":"locality"
},
  "geometry": {"coordinates":[139.67161000000002,35.20606],"type":"Point"}
}