{
  "type": "Feature",
  "properties": {
    "gn:country":"JP",
    "gn:fcode":"ADM3",
    "gn:pop":0,
    "iso:country":"JP",
    "name:jpn_x_preferred":[
        "\u7f8e\u745b\u753a"
    ],
    "name:jpn_x_variant":[
        "\u3073\u3048\u3044\u3061\u3087\u3046"
    ],
    "qs:name":"Biei-ch\u014d",
    "qs:photos_9r":0,
    "qs:photos_sr":0,
    "qs:pop_sr":"0",
    "wof:name":"Biei-ch\u014d",
    "wof:placetype":"localadmin",
    "wof:population":0
},
  "geometry": {"coordinates":[142.61188999999999,43.55801],"type":"Point"}
}