{
  "type": "Feature",
  "properties": {
    "iso:country":"JP",
    "name:eng_x_preferred":[
        "Otemae 3 Chome"
    ],
    "name:eng_x_variant":[
        "Ootemae 3 Choume",
        "Otemae 3 Chome"
    ],
    "name:jpn_x_preferred":[
        "\uff13\u4e01\u76ee"
    ],
    "name:jpn_x_variant":[
        "\u304a\u304a\u3066\u307e\u3048 \uff13\u3061\u3087\u3046\u3081",
        "\u5927\u624b\u524d \uff13\u4e01\u76ee",
        "\uff13\u3061\u3087\u3046\u3081"
    ],
    "qs:gn_local":0,
    "qs:local_max":5466,
    "qs:local_sum":82256,
    "qs:localhoods":141,
    "qs:name":"\uff13\u4e01\u76ee",
    "qs:name_adm0":"\u65e5\u672c",
    "qs:name_adm1":"\u5927\u962a\u5e9c",
    "qs:name_adm2":"\u4e2d\u592e\u533a",
    "qs:name_en":"Otemae 3 Chome",
    "qs:name_lau":"\u5927\u624b\u524d",
    "qs:name_local":"\u5927\u962a\u5e02",
    "qs:photo_max":111,
    "qs:photo_sum":111,
    "qs:placetype":"Suburb",
    "qs:quad_count":1,
    "qs:woe_adm0":23424856,
    "qs:woe_adm1":2345881,
    "qs:woe_adm2":1118622,
    "qs:woe_lau":28457621,
    "qs:woe_local":15015370,
    "qs:woe_ver":"7.10.0",
    "wof:lang":[
        "jpn"
    ],
    "wof:name":"\uff13\u4e01\u76ee",
    "wof:placetype":"neighbourhood"
},
  "geometry": {"coordinates":[135.525284,34.684605],"type":"Point"}
}