{
  "type": "Feature",
  "properties": {
    "gn:admin1_code":"19.0",
    "gn:admin2_code":"1848350.0",
    "gn:admin3_code":"14112.0",
    "gn:asciiname":"Kamikawaicho",
    "gn:country_code":"JP",
    "gn:dem":87,
    "gn:feature_class":"P",
    "gn:feature_code":"PPL",
    "gn:name":"Kamikawaich\u014d",
    "gn:population":0,
    "gn:timezone":"Asia/Tokyo",
    "iso:country":"JP",
    "name:jpn_x_preferred":[
        "\u4e0a\u5ddd\u4e95\u753a"
    ],
    "name:jpn_x_variant":[
        "\u304b\u307f\u304b\u308f\u3044\u3061\u3087\u3046",
        "\u30ab\u30df\u30ab\u30ef\u30a4\u30c1\u30e7\u30a6"
    ],
    "name:und_x_variant":[
        "Kamikawaich\u014d"
    ],
    "wof:name":"Kamikawaicho",
    "wof:placetype":"locality"
},
  "geometry": {"coordinates":[139.50486999999998,35.49808],"type":"Point"}
}