{
  "type": "Feature",
  "properties": {
    "gn:admin1_code":"2.0",
    "gn:admin2_code":"2129593.0",
    "gn:asciiname":"Towada-kusagi",
    "gn:country_code":"JP",
    "gn:dem":174,
    "gn:feature_class":"P",
    "gn:feature_code":"PPL",
    "gn:name":"Towada-kusagi",
    "gn:population":0,
    "gn:timezone":"Asia/Tokyo",
    "iso:country":"JP",
    "name:jpn_x_preferred":[
        "\u5341\u548c\u7530\u8349\u6728"
    ],
    "wof:name":"Towada-kusagi",
    "wof:placetype":"locality"
},
  "geometry": {"coordinates":[140.82408000000001,40.26707],"type":"Point"}
}