{
  "type": "Feature",
  "properties": {
    "gn:admin1_code":"41.0",
    "gn:admin2_code":"1862590.0",
    "gn:admin3_code":"31403.0",
    "gn:asciiname":"Muko",
    "gn:country_code":"JP",
    "gn:dem":165,
    "gn:feature_class":"P",
    "gn:feature_code":"PPL",
    "gn:name":"Muko",
    "gn:population":0,
    "gn:timezone":"Asia/Tokyo",
    "iso:country":"JP",
    "name:ceb_x_preferred":[
        "Muko"
    ],
    "name:deu_x_preferred":[
        "Muko"
    ],
    "name:ita_x_preferred":[
        "Muko"
    ],
    "name:jpn_x_preferred":[
        "\u6b66\u5eab"
    ],
    "name:nld_x_preferred":[
        "Muko"
    ],
    "name:swe_x_preferred":[
        "Muko"
    ],
    "wof:name":"Muko",
    "wof:placetype":"locality"
},
  "geometry": {"coordinates":[133.47987000000001,35.26386],"type":"Point"}
}