{
  "type": "Feature",
  "properties": {
    "gn:admin1_code":"33.0",
    "gn:admin2_code":"1859936.0",
    "gn:asciiname":"Omiyado",
    "gn:country_code":"JP",
    "gn:dem":5,
    "gn:feature_class":"P",
    "gn:feature_code":"PPLL",
    "gn:name":"\u014cmiyad\u014d",
    "gn:population":0,
    "gn:timezone":"Asia/Tokyo",
    "iso:country":"JP",
    "name:jpn_x_preferred":[
        "\u5927\u5bae\u7530\u5c3e"
    ],
    "name:und_x_variant":[
        "\u014cmiyad\u014d"
    ],
    "wof:name":"Omiyado",
    "wof:placetype":"locality"
},
  "geometry": {"coordinates":[130.14352,33.0768],"type":"Point"}
}