{
  "type": "Feature",
  "properties": {
    "gn:admin1_code":"7.0",
    "gn:admin2_code":"1859306.0",
    "gn:admin3_code":"40109.0",
    "gn:asciiname":"Higuchimachi",
    "gn:country_code":"JP",
    "gn:dem":5,
    "gn:feature_class":"P",
    "gn:feature_code":"PPL",
    "gn:name":"Higuchimachi",
    "gn:population":0,
    "gn:timezone":"Asia/Tokyo",
    "iso:country":"JP",
    "name:jpn_x_preferred":[
        "\u6a0b\u53e3\u753a"
    ],
    "wof:name":"Higuchimachi",
    "wof:placetype":"locality"
},
  "geometry": {"coordinates":[130.73976999999999,33.86065],"type":"Point"}
}