{
  "type": "Feature",
  "properties": {
    "iso:country":"JP",
    "name:eng_x_preferred":[
        "Shiba 2 Chome"
    ],
    "name:eng_x_variant":[
        "Shiba 2 Choume",
        "Shiba 2 Chome"
    ],
    "name:jpn_x_preferred":[
        "\uff12\u4e01\u76ee"
    ],
    "name:jpn_x_variant":[
        "\u3057\u3070 \uff12\u3061\u3087\u3046\u3081",
        "\u829d \uff12\u4e01\u76ee",
        "\uff12\u3061\u3087\u3046\u3081"
    ],
    "qs:gn_adm0_cc":"JP",
    "qs:gn_local":1850147,
    "qs:local_max":18112,
    "qs:local_sum":895907,
    "qs:localhoods":857,
    "qs:name":"\uff12\u4e01\u76ee",
    "qs:name_adm0":"\u65e5\u672c",
    "qs:name_adm1":"\u6771\u4eac\u90fd",
    "qs:name_adm2":"\u6e2f\u533a",
    "qs:name_en":"Shiba 2 Chome",
    "qs:name_lau":"\u829d",
    "qs:name_local":"\u6771\u4eac",
    "qs:photo_max":2,
    "qs:photo_sum":2,
    "qs:placetype":"Suburb",
    "qs:quad_count":1,
    "qs:woe_adm0":23424856,
    "qs:woe_adm1":2345889,
    "qs:woe_adm2":15015406,
    "qs:woe_lau":1114321,
    "qs:woe_local":1118370,
    "qs:woe_ver":"7.10.0",
    "qs_pg:name":"\uff12\u4e01\u76ee",
    "qs_pg:name_adm0":"\u65e5\u672c",
    "qs_pg:name_adm1":"\u6771\u4eac\u90fd",
    "qs_pg:photos":106,
    "qs_pg:photos_1k":21,
    "qs_pg:photos_9k":1,
    "qs_pg:photos_9r":3,
    "qs_pg:photos_all":106,
    "qs_pg:photos_sr":3,
    "qs_pg:pop_sr":0,
    "qs_pg:qs_pg_placetype":"neighbourhood",
    "qs_pg:qs_pg_placetype_gp":"Suburb",
    "qs_pg:woe_adm0":23424856,
    "woe:adm0_id":23424856,
    "woe:name_adm0":"\u65e5\u672c",
    "woe:name_adm1":"\u6771\u4eac\u90fd",
    "woe:placetype":"Suburb",
    "wof:lang":[
        "jpn"
    ],
    "wof:name":"\uff12\u4e01\u76ee",
    "wof:placetype":"neighbourhood"
},
  "geometry": {"coordinates":[139.7509,35.651157],"type":"Point"}
}