{
  "type": "Feature",
  "properties": {
    "iso:country":"JP",
    "name:eng_x_preferred":[
        "Suzuya 9 Chome"
    ],
    "name:eng_x_variant":[
        "Suzuya 9 Choume",
        "Suzuya 9 Chome"
    ],
    "name:jpn_x_preferred":[
        "\uff19\u4e01\u76ee"
    ],
    "name:jpn_x_variant":[
        "\u3059\u305a\u3084 \uff19\u3061\u3087\u3046\u3081",
        "\u9234\u8c37 \uff19\u4e01\u76ee",
        "\uff19\u3061\u3087\u3046\u3081"
    ],
    "qs:gn_local":0,
    "qs:local_max":581,
    "qs:local_sum":6772,
    "qs:localhoods":52,
    "qs:name":"\uff19\u4e01\u76ee",
    "qs:name_adm0":"\u65e5\u672c",
    "qs:name_adm1":"\u57fc\u7389\u770c",
    "qs:name_adm2":"\u4e2d\u592e\u533a",
    "qs:name_en":"Suzuya 9 Chome",
    "qs:name_lau":"\u9234\u8c37",
    "qs:name_local":"\u3055\u3044\u305f\u307e\u5e02",
    "qs:photo_max":7,
    "qs:photo_sum":7,
    "qs:placetype":"Suburb",
    "qs:quad_count":1,
    "qs:woe_adm0":23424856,
    "qs:woe_adm1":2345883,
    "qs:woe_adm2":24851609,
    "qs:woe_lau":28407729,
    "qs:woe_local":1116753,
    "qs:woe_ver":"7.10.0",
    "wof:lang":[
        "jpn"
    ],
    "wof:name":"\uff19\u4e01\u76ee",
    "wof:placetype":"neighbourhood"
},
  "geometry": {"coordinates":[139.62799100000001,35.877922],"type":"Point"}
}