{
  "type": "Feature",
  "properties": {
    "gn:admin1_code":"3.0",
    "gn:admin2_code":"2129224.0",
    "gn:admin3_code":"2361.0",
    "gn:asciiname":"Mizunuma",
    "gn:country_code":"JP",
    "gn:dem":19,
    "gn:feature_class":"P",
    "gn:feature_code":"PPL",
    "gn:name":"Mizunuma",
    "gn:population":0,
    "gn:timezone":"Asia/Tokyo",
    "iso:country":"JP",
    "name:jpn_x_preferred":[
        "\u6c34\u6cbc"
    ],
    "name:jpn_x_variant":[
        "\u307f\u305a\u306c\u307e",
        "\u30df\u30ba\u30cc\u30de"
    ],
    "wof:name":"Mizunuma",
    "wof:placetype":"locality"
},
  "geometry": {"coordinates":[140.50514999999999,40.66634000000001],"type":"Point"}
}