{
  "type": "Feature",
  "properties": {
    "gn:admin1_code":"33.0",
    "gn:admin2_code":"7391355.0",
    "gn:asciiname":"Otsubocho-otsu",
    "gn:country_code":"JP",
    "gn:dem":90,
    "gn:feature_class":"P",
    "gn:feature_code":"PPL",
    "gn:name":"\u014ctsuboch\u014d-otsu",
    "gn:population":0,
    "gn:timezone":"Asia/Tokyo",
    "iso:country":"JP",
    "name:jpn_x_preferred":[
        "\u5927\u576a\u753a\u4e59"
    ],
    "name:und_x_variant":[
        "\u014ctsuboch\u014d-otsu"
    ],
    "wof:name":"Otsubocho-otsu",
    "wof:placetype":"locality"
},
  "geometry": {"coordinates":[129.90423000000001,33.27961],"type":"Point"}
}