{
  "type": "Feature",
  "properties": {
    "gn:admin1_code":"27",
    "gn:admin2_code":"8301120.0",
    "gn:asciiname":"Keya",
    "gn:country_code":"JP",
    "gn:dem":0,
    "gn:feature_class":"P",
    "gn:feature_code":"PPL",
    "gn:name":"Keya",
    "gn:population":0,
    "gn:timezone":"Asia/Tokyo",
    "iso:country":"JP",
    "wof:name":"Keya",
    "wof:placetype":"locality"
},
  "geometry": {"coordinates":[129.98333,32.83333],"type":"Point"}
}