{
  "type": "Feature",
  "properties": {
    "gn:admin1_code":"33.0",
    "gn:admin2_code":"1862779.0",
    "gn:admin3_code":"41387.0",
    "gn:asciiname":"Kogakura",
    "gn:country_code":"JP",
    "gn:dem":136,
    "gn:feature_class":"P",
    "gn:feature_code":"PPL",
    "gn:name":"Kogakura",
    "gn:population":0,
    "gn:timezone":"Asia/Tokyo",
    "iso:country":"JP",
    "name:jpn_x_preferred":[
        "\u5c0f\u52a0\u5009"
    ],
    "wof:name":"Kogakura",
    "wof:placetype":"locality"
},
  "geometry": {"coordinates":[129.88272000000001,33.49456],"type":"Point"}
}