{
  "type": "Feature",
  "properties": {
    "gn:admin1_code":"7.0",
    "gn:admin2_code":"9035649.0",
    "gn:asciiname":"Ura",
    "gn:country_code":"JP",
    "gn:dem":43,
    "gn:feature_class":"P",
    "gn:feature_code":"PPLL",
    "gn:name":"Ura",
    "gn:population":0,
    "gn:timezone":"Asia/Tokyo",
    "iso:country":"JP",
    "name:jpn_x_preferred":[
        "\u6d66"
    ],
    "wof:name":"Ura",
    "wof:placetype":"locality"
},
  "geometry": {"coordinates":[130.20043000000001,33.6313],"type":"Point"}
}