{
  "type": "Feature",
  "properties": {
    "gn:admin1_code":"34.0",
    "gn:admin2_code":"1849187.0",
    "gn:admin3_code":"11109.0",
    "gn:asciiname":"Mamiya",
    "gn:country_code":"JP",
    "gn:dem":13,
    "gn:feature_class":"P",
    "gn:feature_code":"PPL",
    "gn:name":"Mamiya",
    "gn:population":0,
    "gn:timezone":"Asia/Tokyo",
    "iso:country":"JP",
    "name:dan_x_preferred":[
        "Mamiya"
    ],
    "name:fas_x_preferred":[
        "\u0645\u0627\u0645\u06cc\u0627"
    ],
    "name:fin_x_preferred":[
        "Mamiya"
    ],
    "name:fra_x_preferred":[
        "Mamiya"
    ],
    "name:ind_x_preferred":[
        "Mamiya"
    ],
    "name:ita_x_preferred":[
        "Mamiya"
    ],
    "name:jpn_x_preferred":[
        "\u9593\u5bae"
    ],
    "name:jpn_x_variant":[
        "\u307e\u307f\u3084",
        "\u30de\u30df\u30e4",
        "\u30de\u30df\u30e4\u30fb\u30c7\u30b8\u30bf\u30eb\u30fb\u30a4\u30e1\u30fc\u30b8\u30f3\u30b0"
    ],
    "name:lit_x_preferred":[
        "Mamiya"
    ],
    "name:msa_x_preferred":[
        "Mamiya"
    ],
    "name:pol_x_preferred":[
        "Mamiya"
    ],
    "name:rus_x_preferred":[
        "Mamiya"
    ],
    "name:swe_x_preferred":[
        "Mamiya"
    ],
    "name:tur_x_preferred":[
        "Mamiya"
    ],
    "name:ukr_x_preferred":[
        "Mamiya"
    ],
    "name:zho_x_preferred":[
        "\u739b\u7c73\u4e9a"
    ],
    "wof:name":"Mamiya",
    "wof:placetype":"locality"
},
  "geometry": {"coordinates":[139.72361000000001,35.88197],"type":"Point"}
}