{
  "type": "Feature",
  "properties": {
    "gn:admin1_code":"28.0",
    "gn:admin2_code":"7412212.0",
    "gn:asciiname":"Ouda-tawara",
    "gn:country_code":"JP",
    "gn:dem":384,
    "gn:feature_class":"P",
    "gn:feature_code":"PPL",
    "gn:name":"\u014cuda-tawara",
    "gn:population":0,
    "gn:timezone":"Asia/Tokyo",
    "iso:country":"JP",
    "name:jpn_x_preferred":[
        "\u5927\u5b87\u9640\u7530\u539f"
    ],
    "name:und_x_variant":[
        "\u014cuda-tawara"
    ],
    "wof:name":"Ouda-tawara",
    "wof:placetype":"locality"
},
  "geometry": {"coordinates":[135.94956000000002,34.4444],"type":"Point"}
}