{
  "type": "Feature",
  "properties": {
    "gn:admin1_code":"23",
    "gn:admin2_code":"1850342.0",
    "gn:asciiname":"Matsuo",
    "gn:country_code":"JP",
    "gn:dem":208,
    "gn:feature_class":"P",
    "gn:feature_code":"PPL",
    "gn:name":"Matsuo",
    "gn:population":0,
    "gn:timezone":"Asia/Tokyo",
    "iso:country":"JP",
    "name:deu_x_preferred":[
        "Matsuo"
    ],
    "name:kor_x_preferred":[
        "\ub9c8\uc4f0\uc624"
    ],
    "wof:name":"Matsuo",
    "wof:placetype":"locality"
},
  "geometry": {"coordinates":[136.83333000000002,34.41667],"type":"Point"}
}