{
  "type": "Feature",
  "properties": {
    "gn:admin1_code":"21.0",
    "gn:admin2_code":"7412708.0",
    "gn:admin3_code":"43512.0",
    "gn:asciiname":"Nishigochi",
    "gn:country_code":"JP",
    "gn:dem":160,
    "gn:feature_class":"P",
    "gn:feature_code":"PPLL",
    "gn:name":"Nishig\u014dchi",
    "gn:population":0,
    "gn:timezone":"Asia/Tokyo",
    "iso:country":"JP",
    "name:jpn_x_preferred":[
        "\u897f\u5ddd\u5185"
    ],
    "name:und_x_variant":[
        "Nishig\u014dchi"
    ],
    "wof:name":"Nishigochi",
    "wof:placetype":"locality"
},
  "geometry": {"coordinates":[130.76917,32.26413],"type":"Point"}
}