{
  "type": "Feature",
  "properties": {
    "gn:admin1_code":"19.0",
    "gn:admin2_code":"1848350.0",
    "gn:admin3_code":"14106.0",
    "gn:asciiname":"Sakamotocho",
    "gn:country_code":"JP",
    "gn:dem":25,
    "gn:feature_class":"P",
    "gn:feature_code":"PPL",
    "gn:name":"Sakamotoch\u014d",
    "gn:population":0,
    "gn:timezone":"Asia/Tokyo",
    "iso:country":"JP",
    "name:jpn_x_preferred":[
        "\u5742\u672c\u753a"
    ],
    "name:jpn_x_variant":[
        "\u3055\u304b\u3082\u3068\u3061\u3087\u3046",
        "\u30b5\u30ab\u30e2\u30c8\u30c1\u30e7\u30a6"
    ],
    "name:und_x_variant":[
        "Sakamotoch\u014d"
    ],
    "wof:name":"Sakamotocho",
    "wof:placetype":"locality"
},
  "geometry": {"coordinates":[139.57851000000002,35.46465999999999],"type":"Point"}
}