{
  "type": "Feature",
  "properties": {
    "gn:admin1_code":"3.0",
    "gn:admin2_code":"2129525.0",
    "gn:admin3_code":"2384.0",
    "gn:asciiname":"Aihara",
    "gn:country_code":"JP",
    "gn:dem":12,
    "gn:feature_class":"P",
    "gn:feature_code":"PPL",
    "gn:name":"Aihara",
    "gn:population":0,
    "gn:timezone":"Asia/Tokyo",
    "iso:country":"JP",
    "name:deu_x_preferred":[
        "Aihara"
    ],
    "name:jpn_x_preferred":[
        "\u76f8\u539f"
    ],
    "name:jpn_x_variant":[
        "\u3042\u3044\u306f\u3089",
        "\u30a2\u30a4\u30cf\u30e9"
    ],
    "name:kor_x_preferred":[
        "\uc544\uc774\ud558\ub77c"
    ],
    "wof:name":"Aihara",
    "wof:placetype":"locality"
},
  "geometry": {"coordinates":[140.43384,40.76019],"type":"Point"}
}