{
  "type": "Feature",
  "properties": {
    "gn:admin1_code":"19.0",
    "gn:admin2_code":"1848350.0",
    "gn:admin3_code":"14108.0",
    "gn:asciiname":"Machiyacho",
    "gn:country_code":"JP",
    "gn:dem":1,
    "gn:feature_class":"P",
    "gn:feature_code":"PPL",
    "gn:name":"Machiyach\u014d",
    "gn:population":0,
    "gn:timezone":"Asia/Tokyo",
    "iso:country":"JP",
    "name:jpn_x_preferred":[
        "\u753a\u5c4b\u753a"
    ],
    "name:jpn_x_variant":[
        "\u307e\u3061\u3084\u3061\u3087\u3046",
        "\u30de\u30c1\u30e4\u30c1\u30e7\u30a6"
    ],
    "name:und_x_variant":[
        "Machiyach\u014d"
    ],
    "wof:name":"Machiyacho",
    "wof:placetype":"locality"
},
  "geometry": {"coordinates":[139.62916999999999,35.33491],"type":"Point"}
}