{
  "type": "Feature",
  "properties": {
    "gn:admin1_code":"21.0",
    "gn:admin2_code":"7413153.0",
    "gn:asciiname":"Jo",
    "gn:country_code":"JP",
    "gn:dem":61,
    "gn:feature_class":"P",
    "gn:feature_code":"PPLL",
    "gn:name":"J\u014d",
    "gn:population":0,
    "gn:timezone":"Asia/Tokyo",
    "iso:country":"JP",
    "name:jpn_x_preferred":[
        "\u57ce"
    ],
    "name:jpn_x_variant":[
        "\u3058\u3087\u3046",
        "\u30b8\u30e7\u30a6"
    ],
    "name:und_x_variant":[
        "J\u014d"
    ],
    "wof:name":"Jo",
    "wof:placetype":"locality"
},
  "geometry": {"coordinates":[130.73119,32.91794],"type":"Point"}
}