{
  "type": "Feature",
  "properties": {
    "gn:admin1_code":"19.0",
    "gn:admin2_code":"1862461.0",
    "gn:asciiname":"Yamanokami",
    "gn:country_code":"JP",
    "gn:dem":107,
    "gn:feature_class":"P",
    "gn:feature_code":"PPLL",
    "gn:name":"Yamanokami",
    "gn:population":0,
    "gn:timezone":"Asia/Tokyo",
    "iso:country":"JP",
    "name:jpn_x_preferred":[
        "\u5c71\u306e\u795e"
    ],
    "wof:name":"Yamanokami",
    "wof:placetype":"locality"
},
  "geometry": {"coordinates":[139.28128000000001,35.34016],"type":"Point"}
}