{
  "type": "Feature",
  "properties": {
    "gn:admin1_code":"21.0",
    "gn:admin2_code":"1859488.0",
    "gn:asciiname":"Gokai",
    "gn:country_code":"JP",
    "gn:dem":31,
    "gn:feature_class":"P",
    "gn:feature_code":"PPLL",
    "gn:name":"Gokai",
    "gn:population":0,
    "gn:timezone":"Asia/Tokyo",
    "iso:country":"JP",
    "name:jpn_x_preferred":[
        "\u4e94\u6d77"
    ],
    "name:jpn_x_variant":[
        "\u3054\u304b\u3044",
        "\u30b4\u30ab\u30a4"
    ],
    "wof:name":"Gokai",
    "wof:placetype":"locality"
},
  "geometry": {"coordinates":[130.76222000000001,32.97144],"type":"Point"}
}