{
  "type": "Feature",
  "properties": {
    "gn:admin1_code":"19.0",
    "gn:admin2_code":"1848350.0",
    "gn:admin3_code":"14105.0",
    "gn:asciiname":"Miharudai",
    "gn:country_code":"JP",
    "gn:dem":43,
    "gn:feature_class":"P",
    "gn:feature_code":"PPL",
    "gn:name":"Miharudai",
    "gn:population":0,
    "gn:timezone":"Asia/Tokyo",
    "iso:country":"JP",
    "name:jpn_x_preferred":[
        "\u4e09\u6625\u53f0"
    ],
    "name:jpn_x_variant":[
        "\u307f\u306f\u308b\u3060\u3044",
        "\u30df\u30cf\u30eb\u30c0\u30a4"
    ],
    "wof:name":"Miharudai",
    "wof:placetype":"locality"
},
  "geometry": {"coordinates":[139.61785,35.44145],"type":"Point"}
}