{
  "type": "Feature",
  "properties": {
    "gn:admin1_code":"21.0",
    "gn:admin2_code":"1865168.0",
    "gn:asciiname":"Arao",
    "gn:country_code":"JP",
    "gn:dem":28,
    "gn:feature_class":"P",
    "gn:feature_code":"PPLA2",
    "gn:name":"Arao",
    "gn:population":0,
    "gn:timezone":"Asia/Tokyo",
    "iso:country":"JP",
    "name:jpn_x_preferred":[
        "\u8352\u5c3e"
    ],
    "name:jpn_x_variant":[
        "\u3042\u3089\u304a",
        "\u30a2\u30e9\u30aa"
    ],
    "wof:name":"Arao",
    "wof:placetype":"locality"
},
  "geometry": {"coordinates":[130.44571999999999,32.97888],"type":"Point"}
}