{
  "type": "Feature",
  "properties": {
    "gn:admin1_code":"4.0",
    "gn:admin2_code":"2112663.0",
    "gn:asciiname":"Umatate",
    "gn:country_code":"JP",
    "gn:dem":18,
    "gn:feature_class":"P",
    "gn:feature_code":"PPL",
    "gn:name":"Umatate",
    "gn:population":0,
    "gn:timezone":"Asia/Tokyo",
    "iso:country":"JP",
    "name:jpn_x_preferred":[
        "\u99ac\u7acb"
    ],
    "name:jpn_x_variant":[
        "\u3046\u307e\u305f\u3066",
        "\u30a6\u30de\u30bf\u30c6"
    ],
    "wof:name":"Umatate",
    "wof:placetype":"locality"
},
  "geometry": {"coordinates":[140.11668999999998,35.43048],"type":"Point"}
}