{
  "type": "Feature",
  "properties": {
    "iso:country":"JP",
    "name:eng_x_preferred":[
        "Kitano 1 Chome"
    ],
    "name:eng_x_variant":[
        "Kitano 1 Choume",
        "Kitano 1 Chome"
    ],
    "name:jpn_x_preferred":[
        "\uff11\u4e01\u76ee"
    ],
    "name:jpn_x_variant":[
        "\u304d\u305f\u306e \uff11\u3061\u3087\u3046\u3081",
        "\u5317\u91ce \uff11\u4e01\u76ee",
        "\uff11\u3061\u3087\u3046\u3081"
    ],
    "name:unk_x_variant":[
        "\uff11\u4e01\u76ee"
    ],
    "qs:gn_local":0,
    "qs:local_max":509,
    "qs:local_sum":632,
    "qs:localhoods":5,
    "qs:name":"\uff11\u4e01\u76ee",
    "qs:name_adm0":"\u65e5\u672c",
    "qs:name_adm1":"\u57fc\u7389\u770c",
    "qs:name_en":"Kitano 1 Chome",
    "qs:name_lau":"\u5317\u91ce",
    "qs:name_local":"\u65b0\u5ea7\u5e02",
    "qs:photo_max":29,
    "qs:photo_sum":54,
    "qs:placetype":"Suburb",
    "qs:quad_count":7,
    "qs:woe_adm0":23424856,
    "qs:woe_adm1":2345883,
    "qs:woe_adm2":0,
    "qs:woe_lau":28409416,
    "qs:woe_local":15015488,
    "qs:woe_ver":"7.10.0",
    "wof:lang":[
        "jpn"
    ],
    "wof:name":"\uff11\u4e01\u76ee",
    "wof:placetype":"neighbourhood"
},
  "geometry": {"coordinates":[139.567564,35.812855],"type":"Point"}
}