{
  "type": "Feature",
  "properties": {
    "iso:country":"JP",
    "name:eng_x_preferred":[
        "Honan 2 Chome"
    ],
    "name:eng_x_variant":[
        "Hounan 2 Choume",
        "Honan 2 Chome"
    ],
    "name:jpn_x_preferred":[
        "\uff12\u4e01\u76ee"
    ],
    "name:jpn_x_variant":[
        "\u307b\u3046\u306a\u3093 \uff12\u3061\u3087\u3046\u3081",
        "\u65b9\u5357 \uff12\u4e01\u76ee",
        "\uff12\u3061\u3087\u3046\u3081"
    ],
    "qs:gn_adm0_cc":"JP",
    "qs:gn_local":1850147,
    "qs:local_max":18112,
    "qs:local_sum":895907,
    "qs:localhoods":857,
    "qs:name":"\uff12\u4e01\u76ee",
    "qs:name_adm0":"\u65e5\u672c",
    "qs:name_adm1":"\u6771\u4eac\u90fd",
    "qs:name_adm2":"\u6749\u4e26\u533a",
    "qs:name_en":"Honan 2 Chome",
    "qs:name_lau":"\u65b9\u5357",
    "qs:name_local":"\u6771\u4eac",
    "qs:photo_max":36,
    "qs:photo_sum":86,
    "qs:placetype":"Suburb",
    "qs:quad_count":6,
    "qs:woe_adm0":23424856,
    "qs:woe_adm1":2345889,
    "qs:woe_adm2":15015379,
    "qs:woe_lau":28414469,
    "qs:woe_local":1118370,
    "qs:woe_ver":"7.10.0",
    "wof:lang":[
        "jpn"
    ],
    "wof:name":"\uff12\u4e01\u76ee",
    "wof:placetype":"neighbourhood"
},
  "geometry": {"coordinates":[139.65573499999999,35.683365],"type":"Point"}
}