{
  "type": "Feature",
  "properties": {
    "gn:country":"JP",
    "gn:fcode":"ADM3",
    "gn:population":0,
    "iso:country":"JP",
    "name:jpn_x_preferred":[
        "\u9df9\u6816\u753a"
    ],
    "name:jpn_x_variant":[
        "\u305f\u304b\u3059\u3061\u3087\u3046"
    ],
    "qs:name":"Takasu-ch\u014d",
    "qs:photos_9r":0,
    "qs:photos_sr":0,
    "qs:pop_sr":"0",
    "wof:name":"Takasu-ch\u014d",
    "wof:placetype":"localadmin",
    "wof:population":0
},
  "geometry": {"coordinates":[142.3365,43.88928],"type":"Point"}
}