{
  "type": "Feature",
  "properties": {
    "gn:admin1_code":"1.0",
    "gn:admin2_code":"1864539.0",
    "gn:asciiname":"Chita",
    "gn:country_code":"JP",
    "gn:dem":9,
    "gn:feature_class":"P",
    "gn:feature_code":"PPLA2",
    "gn:name":"Chita",
    "gn:population":0,
    "gn:timezone":"Asia/Tokyo",
    "iso:country":"JP",
    "name:ara_x_preferred":[
        "\u062a\u0634\u064a\u062a\u0627"
    ],
    "name:azb_x_preferred":[
        "\u0686\u06cc\u062a\u0627"
    ],
    "name:cat_x_preferred":[
        "Chita"
    ],
    "name:ceb_x_preferred":[
        "Chita"
    ],
    "name:ces_x_preferred":[
        "\u010cita"
    ],
    "name:deu_x_preferred":[
        "Chita"
    ],
    "name:epo_x_preferred":[
        "\u0108ita"
    ],
    "name:fas_x_preferred":[
        "\u0686\u06cc\u062a\u0627\u060c \u0622\u06cc\u0686\u06cc"
    ],
    "name:fas_x_variant":[
        "\u0686\u06cc\u062a\u0627"
    ],
    "name:fin_x_preferred":[
        "Chita"
    ],
    "name:fra_x_preferred":[
        "Chita"
    ],
    "name:glg_x_preferred":[
        "Chita"
    ],
    "name:ita_x_preferred":[
        "Chita"
    ],
    "name:jpn_x_preferred":[
        "\u77e5\u591a"
    ],
    "name:jpn_x_variant":[
        "\u77e5\u591a\u5e02",
        "\u3061\u305f\u3057"
    ],
    "name:kor_x_preferred":[
        "\uc9c0\ud0c0 \uc2dc"
    ],
    "name:kor_x_variant":[
        "\uc9c0\ud0c0\uc2dc"
    ],
    "name:mzn_x_preferred":[
        "\u0686\u06cc\u062a\u0627\u060c \u0622\u06cc\u0686\u06cc"
    ],
    "name:mzn_x_variant":[
        "\u0686\u06cc\u062a\u0627"
    ],
    "name:nan_x_preferred":[
        "Tita-chh\u012b"
    ],
    "name:nld_x_preferred":[
        "Chita"
    ],
    "name:pol_x_preferred":[
        "Chita"
    ],
    "name:por_x_preferred":[
        "Chita"
    ],
    "name:ron_x_preferred":[
        "Chita"
    ],
    "name:rus_x_preferred":[
        "\u0422\u0438\u0442\u0430"
    ],
    "name:sco_x_preferred":[
        "Chita"
    ],
    "name:spa_x_preferred":[
        "Chita"
    ],
    "name:swe_x_preferred":[
        "Chita"
    ],
    "name:szl_x_preferred":[
        "Czita"
    ],
    "name:tgk_x_preferred":[
        "\u0427\u0438\u0442\u0430"
    ],
    "name:tgl_x_preferred":[
        "Chita"
    ],
    "name:tur_x_preferred":[
        "Chita"
    ],
    "name:ukr_x_preferred":[
        "\u0422\u0456\u0442\u0430"
    ],
    "name:urd_x_preferred":[
        "\u0686\u06cc\u062a\u0627\u060c \u0627\u06cc\u0686\u06cc"
    ],
    "name:urd_x_variant":[
        "\u0686\u06cc\u062a\u0627"
    ],
    "name:vie_x_preferred":[
        "Chita"
    ],
    "name:war_x_preferred":[
        "Chita"
    ],
    "name:zho_x_preferred":[
        "\u77e5\u591a\u5e02"
    ],
    "wof:name":"Chita",
    "wof:placetype":"locality"
},
  "geometry": {"coordinates":[136.86420000000001,35.00267],"type":"Point"}
}