{
  "type": "Feature",
  "properties": {
    "gn:admin1_code":"12.0",
    "gn:admin2_code":"2127513.0",
    "gn:asciiname":"Kami-yuchi",
    "gn:cc2":"JP",
    "gn:country_code":"JP",
    "gn:dem":33,
    "gn:feature_class":"P",
    "gn:feature_code":"PPL",
    "gn:name":"Kami-y\u016bchi",
    "gn:population":0,
    "gn:timezone":"Asia/Tokyo",
    "iso:country":"JP",
    "name:und_x_variant":[
        "Kami-yuta",
        "Kami-y\u016bshiri",
        "Kami-y\u016bchi"
    ],
    "wof:name":"Kami-yuchi",
    "wof:placetype":"locality"
},
  "geometry": {"coordinates":[141.73333,45.28333],"type":"Point"}
}