{
  "type": "Feature",
  "properties": {
    "gn:admin1_code":"3.0",
    "gn:admin2_code":"2130056.0",
    "gn:asciiname":"Kaizawa",
    "gn:country_code":"JP",
    "gn:dem":39,
    "gn:feature_class":"P",
    "gn:feature_code":"PPL",
    "gn:name":"Kaizawa",
    "gn:population":0,
    "gn:timezone":"Asia/Tokyo",
    "iso:country":"JP",
    "name:jpn_x_preferred":[
        "\u8c9d\u6ca2"
    ],
    "name:jpn_x_variant":[
        "\u304b\u3044\u3056\u308f",
        "\u30ab\u30a4\u30b6\u30ef"
    ],
    "wof:name":"Kaizawa",
    "wof:placetype":"locality"
},
  "geometry": {"coordinates":[140.39283999999998,40.70923],"type":"Point"}
}