{
  "type": "Feature",
  "properties": {
    "gn:admin1_code":"38",
    "gn:admin2_code":"7453590.0",
    "gn:asciiname":"Tomida",
    "gn:cc2":"JP",
    "gn:country_code":"JP",
    "gn:dem":38,
    "gn:feature_class":"P",
    "gn:feature_code":"PPL",
    "gn:name":"Tomida",
    "gn:population":0,
    "gn:timezone":"Asia/Tokyo",
    "iso:country":"JP",
    "name:und_x_variant":[
        "Tomita",
        "Tomida"
    ],
    "wof:name":"Tomida",
    "wof:placetype":"locality"
},
  "geometry": {"coordinates":[139.69999999999999,36.33333],"type":"Point"}
}