{
  "type": "Feature",
  "properties": {
    "gn:admin1_code":"23.0",
    "gn:admin2_code":"1848873.0",
    "gn:admin3_code":"24471.0",
    "gn:asciiname":"Ouchiyama-mayumi",
    "gn:country_code":"JP",
    "gn:dem":212,
    "gn:feature_class":"P",
    "gn:feature_code":"PPL",
    "gn:name":"\u014cuchiyama-mayumi",
    "gn:population":0,
    "gn:timezone":"Asia/Tokyo",
    "iso:country":"JP",
    "name:jpn_x_preferred":[
        "\u5927\u5185\u5c71\u9593\u5f13"
    ],
    "name:und_x_variant":[
        "\u014cuchiyama-mayumi"
    ],
    "wof:name":"Ouchiyama-mayumi",
    "wof:placetype":"locality"
},
  "geometry": {"coordinates":[136.36356000000001,34.2817],"type":"Point"}
}