{
  "type": "Feature",
  "properties": {
    "gn:admin1_code":"26.0",
    "gn:admin2_code":"1856209.0",
    "gn:asciiname":"Tsuchikura",
    "gn:country_code":"JP",
    "gn:dem":854,
    "gn:feature_class":"P",
    "gn:feature_code":"PPL",
    "gn:name":"Tsuchikura",
    "gn:population":0,
    "gn:timezone":"Asia/Tokyo",
    "iso:country":"JP",
    "name:jpn_x_preferred":[
        "\u571f\u5009"
    ],
    "wof:name":"Tsuchikura",
    "wof:placetype":"locality"
},
  "geometry": {"coordinates":[137.96611999999999,36.71477],"type":"Point"}
}