{
  "type": "Feature",
  "properties": {
    "iso:country":"JP",
    "name:eng_x_preferred":[
        "Minamiodori 2 Chome"
    ],
    "name:eng_x_variant":[
        "Minamioodoori 2 Choume",
        "Minamiodori 2 Chome"
    ],
    "name:jpn_x_preferred":[
        "\uff12\u4e01\u76ee"
    ],
    "name:jpn_x_variant":[
        "\u307f\u306a\u307f\u304a\u304a\u3069\u304a\u308a \uff12\u3061\u3087\u3046\u3081",
        "\u5357\u5927\u901a \uff12\u4e01\u76ee",
        "\uff12\u3061\u3087\u3046\u3081"
    ],
    "qs:gn_adm0_cc":"JP",
    "qs:gn_local":2111834,
    "qs:gn_nam_loc":"\u76db\u5ca1\u5e02, \u5ca9\u624b\u770c, JP",
    "qs:gn_namadm1":"16",
    "qs:local_max":736,
    "qs:local_sum":1250,
    "qs:localhoods":8,
    "qs:name":"\uff12\u4e01\u76ee",
    "qs:name_adm0":"\u65e5\u672c",
    "qs:name_adm1":"\u5ca9\u624b\u770c",
    "qs:name_en":"Minamiodori 2 Chome",
    "qs:name_lau":"\u5357\u5927\u901a",
    "qs:name_local":"\u76db\u5ca1\u5e02",
    "qs:photo_max":16,
    "qs:photo_sum":16,
    "qs:placetype":"Suburb",
    "qs:quad_count":1,
    "qs:woe_adm0":23424856,
    "qs:woe_adm1":2345865,
    "qs:woe_adm2":0,
    "qs:woe_lau":28389507,
    "qs:woe_local":1117776,
    "qs:woe_ver":"7.10.0",
    "wof:lang":[
        "jpn"
    ],
    "wof:name":"\uff12\u4e01\u76ee",
    "wof:placetype":"neighbourhood"
},
  "geometry": {"coordinates":[141.149597,39.688168],"type":"Point"}
}