{
  "type": "Feature",
  "properties": {
    "gn:admin1_code":"35.0",
    "gn:admin2_code":"1858984.0",
    "gn:asciiname":"Tsuchiyamacho-akebihara",
    "gn:country_code":"JP",
    "gn:dem":355,
    "gn:feature_class":"P",
    "gn:feature_code":"PPL",
    "gn:name":"Tsuchiyamach\u014d-akebihara",
    "gn:population":0,
    "gn:timezone":"Asia/Tokyo",
    "iso:country":"JP",
    "name:jpn_x_preferred":[
        "\u571f\u5c71\u753a\u5c71\u5973\u539f"
    ],
    "name:und_x_variant":[
        "Tsuchiyamach\u014d-akebihara"
    ],
    "wof:name":"Tsuchiyamacho-akebihara",
    "wof:placetype":"locality"
},
  "geometry": {"coordinates":[136.35096999999999,34.91825],"type":"Point"}
}