{
  "type": "Feature",
  "properties": {
    "gn:admin1_code":"12.0",
    "gn:admin2_code":"2130058.0",
    "gn:admin3_code":"1642.0",
    "gn:asciiname":"Kamitoyoni",
    "gn:country_code":"JP",
    "gn:dem":185,
    "gn:feature_class":"P",
    "gn:feature_code":"PPL",
    "gn:name":"Kamitoyoni",
    "gn:population":0,
    "gn:timezone":"Asia/Tokyo",
    "iso:country":"JP",
    "name:jpn_x_preferred":[
        "\u4e0a\u8c4a\u4f3c"
    ],
    "name:jpn_x_variant":[
        "\u304b\u307f\u3068\u3088\u306b",
        "\u30ab\u30df\u30c8\u30e8\u30cb"
    ],
    "wof:name":"Kamitoyoni",
    "wof:placetype":"locality"
},
  "geometry": {"coordinates":[143.15575999999999,42.41387],"type":"Point"}
}