{
  "type": "Feature",
  "properties": {
    "gn:admin1_code":"5.0",
    "gn:admin2_code":"1926135.0",
    "gn:asciiname":"Ohama",
    "gn:country_code":"JP",
    "gn:dem":6,
    "gn:feature_class":"P",
    "gn:feature_code":"PPL",
    "gn:name":"\u014chama",
    "gn:population":0,
    "gn:timezone":"Asia/Tokyo",
    "iso:country":"JP",
    "name:deu_x_preferred":[
        "Ohama"
    ],
    "wof:name":"Ohama",
    "wof:placetype":"locality"
},
  "geometry": {"coordinates":[132.98331999999999,34.09883],"type":"Point"}
}