{
  "type": "Feature",
  "properties": {
    "gn:admin1_code":"7.0",
    "gn:admin2_code":"1864573.0",
    "gn:asciiname":"Yamae-ikku",
    "gn:country_code":"JP",
    "gn:dem":273,
    "gn:feature_class":"P",
    "gn:feature_code":"PPLL",
    "gn:name":"Yamae-ikku",
    "gn:population":0,
    "gn:timezone":"Asia/Tokyo",
    "iso:country":"JP",
    "name:jpn_x_preferred":[
        "\u5c71\u5bb6\u4e00\u533a"
    ],
    "wof:name":"Yamae-ikku",
    "wof:placetype":"locality"
},
  "geometry": {"coordinates":[130.60741999999999,33.50887],"type":"Point"}
}