{
  "type": "Feature",
  "properties": {
    "gn:admin1_code":"21.0",
    "gn:admin2_code":"1848441.0",
    "gn:asciiname":"Tarumizu",
    "gn:country_code":"JP",
    "gn:dem":622,
    "gn:feature_class":"P",
    "gn:feature_code":"PPLL",
    "gn:name":"Tarumizu",
    "gn:population":0,
    "gn:timezone":"Asia/Tokyo",
    "iso:country":"JP",
    "name:jpn_x_preferred":[
        "\u6a3d\u6c34"
    ],
    "name:jpn_x_variant":[
        "\u305f\u308b\u307f\u305a",
        "\u30bf\u30eb\u30df\u30ba"
    ],
    "wof:name":"Tarumizu",
    "wof:placetype":"locality"
},
  "geometry": {"coordinates":[130.91908999999998,32.51177],"type":"Point"}
}