{
  "type": "Feature",
  "properties": {
    "gn:admin1_code":"26.0",
    "gn:admin2_code":"1859364.0",
    "gn:admin3_code":"20485.0",
    "gn:asciiname":"Sawado",
    "gn:country_code":"JP",
    "gn:dem":740,
    "gn:feature_class":"P",
    "gn:feature_code":"PPL",
    "gn:name":"Sawado",
    "gn:population":0,
    "gn:timezone":"Asia/Tokyo",
    "iso:country":"JP",
    "name:jpn_x_preferred":[
        "\u6ca2\u6e21"
    ],
    "wof:name":"Sawado",
    "wof:placetype":"locality"
},
  "geometry": {"coordinates":[137.84637000000001,36.64215],"type":"Point"}
}