{
  "type": "Feature",
  "properties": {
    "iso:country":"JP",
    "name:eng_x_preferred":[
        "Iwabuchi 3 Chome"
    ],
    "name:eng_x_variant":[
        "Iwabuchi 3 Choume",
        "Iwabuchi 3 Chome"
    ],
    "name:jpn_x_preferred":[
        "\uff13\u4e01\u76ee"
    ],
    "name:jpn_x_variant":[
        "\u3044\u308f\u3076\u3061 \uff13\u3061\u3087\u3046\u3081",
        "\u5ca9\u6e15 \uff13\u4e01\u76ee",
        "\uff13\u3061\u3087\u3046\u3081"
    ],
    "name:unk_x_variant":[
        "\uff13\u4e01\u76ee"
    ],
    "qs:gn_local":0,
    "qs:local_max":2130,
    "qs:local_sum":2937,
    "qs:localhoods":7,
    "qs:name":"\uff13\u4e01\u76ee",
    "qs:name_adm0":"\u65e5\u672c",
    "qs:name_adm1":"\u4e09\u91cd\u770c",
    "qs:name_en":"Iwabuchi 3 Chome",
    "qs:name_lau":"\u5ca9\u6e15",
    "qs:name_local":"\u4f0a\u52e2\u5e02",
    "qs:photo_max":3,
    "qs:photo_sum":7,
    "qs:placetype":"Suburb",
    "qs:quad_count":4,
    "qs:woe_adm0":23424856,
    "qs:woe_adm1":2345872,
    "qs:woe_adm2":0,
    "qs:woe_lau":28446122,
    "qs:woe_local":1117319,
    "qs:woe_ver":"7.10.0",
    "wof:lang":[
        "jpn"
    ],
    "wof:name":"\uff13\u4e01\u76ee",
    "wof:placetype":"neighbourhood"
},
  "geometry": {"coordinates":[136.73152400000001,34.482301],"type":"Point"}
}