{
  "type": "Feature",
  "properties": {
    "gn:admin1_code":"3.0",
    "gn:admin2_code":"2130056.0",
    "gn:asciiname":"Ichibancho",
    "gn:country_code":"JP",
    "gn:dem":46,
    "gn:feature_class":"P",
    "gn:feature_code":"PPL",
    "gn:name":"Ichibanch\u014d",
    "gn:population":0,
    "gn:timezone":"Asia/Tokyo",
    "iso:country":"JP",
    "name:jpn_x_preferred":[
        "\u4e00\u756a\u753a"
    ],
    "name:jpn_x_variant":[
        "\u3044\u3061\u3070\u3093\u3061\u3087\u3046",
        "\u30a4\u30c1\u30d0\u30f3\u30c1\u30e7\u30a6"
    ],
    "name:und_x_variant":[
        "Ichibanch\u014d"
    ],
    "wof:name":"Ichibancho",
    "wof:placetype":"locality"
},
  "geometry": {"coordinates":[140.46843999999999,40.60256],"type":"Point"}
}