{
  "type": "Feature",
  "properties": {
    "gn:admin1_code":"21.0",
    "gn:admin2_code":"7412706.0",
    "gn:admin3_code":"43447.0",
    "gn:asciiname":"Hinokuchi",
    "gn:country_code":"JP",
    "gn:dem":541,
    "gn:feature_class":"P",
    "gn:feature_code":"PPLL",
    "gn:name":"Hinokuchi",
    "gn:population":0,
    "gn:timezone":"Asia/Tokyo",
    "iso:country":"JP",
    "name:jpn_x_preferred":[
        "\u6a0b\u306e\u53e3"
    ],
    "name:jpn_x_variant":[
        "\u3072\u306e\u304f\u3061",
        "\u30d2\u30ce\u30af\u30c1"
    ],
    "wof:name":"Hinokuchi",
    "wof:placetype":"locality"
},
  "geometry": {"coordinates":[131.00357,32.72707],"type":"Point"}
}