{
  "type": "Feature",
  "properties": {
    "gn:admin1_code":"21.0",
    "gn:admin2_code":"1850744.0",
    "gn:admin3_code":"43367.0",
    "gn:asciiname":"Hanayama",
    "gn:country_code":"JP",
    "gn:dem":49,
    "gn:feature_class":"P",
    "gn:feature_code":"PPLL",
    "gn:name":"Hanayama",
    "gn:population":0,
    "gn:timezone":"Asia/Tokyo",
    "iso:country":"JP",
    "name:jpn_x_preferred":[
        "\u82b1\u5c71"
    ],
    "name:jpn_x_variant":[
        "\u306f\u306a\u3084\u307e",
        "\u30cf\u30ca\u30e4\u30de"
    ],
    "wof:name":"Hanayama",
    "wof:placetype":"locality"
},
  "geometry": {"coordinates":[130.52741,33.05616],"type":"Point"}
}