{
  "type": "Feature",
  "properties": {
    "gn:admin1_code":"21.0",
    "gn:admin2_code":"1848441.0",
    "gn:asciiname":"Hinagu-shinkaimachi",
    "gn:country_code":"JP",
    "gn:dem":-1,
    "gn:feature_class":"P",
    "gn:feature_code":"PPL",
    "gn:name":"Hinagu-shinkaimachi",
    "gn:population":0,
    "gn:timezone":"Asia/Tokyo",
    "iso:country":"JP",
    "name:jpn_x_preferred":[
        "\u65e5\u5948\u4e45\u65b0\u958b\u753a"
    ],
    "wof:name":"Hinagu-shinkaimachi",
    "wof:placetype":"locality"
},
  "geometry": {"coordinates":[130.57556,32.45215],"type":"Point"}
}