{
  "type": "Feature",
  "properties": {
    "gn:admin1_code":"21.0",
    "gn:admin2_code":"1858418.0",
    "gn:admin3_code":"43103.0",
    "gn:asciiname":"Nakamatsuomachi",
    "gn:country_code":"JP",
    "gn:dem":84,
    "gn:feature_class":"P",
    "gn:feature_code":"PPL",
    "gn:name":"Nakamatsuomachi",
    "gn:population":0,
    "gn:timezone":"Asia/Tokyo",
    "iso:country":"JP",
    "name:jpn_x_preferred":[
        "\u4e2d\u677e\u5c3e\u753a"
    ],
    "name:jpn_x_variant":[
        "\u306a\u304b\u307e\u3064\u304a\u307e\u3061",
        "\u30ca\u30ab\u30de\u30c4\u30aa\u30de\u30c1"
    ],
    "wof:name":"Nakamatsuomachi",
    "wof:placetype":"locality"
},
  "geometry": {"coordinates":[130.64444,32.79097],"type":"Point"}
}