{
  "type": "Feature",
  "properties": {
    "iso:country":"JP",
    "qs:name":"\uff11\u4e01\u76ee",
    "qs:name_adm0":"\u65e5\u672c",
    "qs:name_adm1":"\u9577\u91ce\u770c",
    "qs:photos":12,
    "qs:photos_1k":2,
    "qs:photos_9k":1,
    "qs:photos_9r":1,
    "qs:photos_all":12,
    "qs:photos_sr":1,
    "qs:placetype":"Suburb",
    "qs:pop_sr":"0",
    "wof:name":"\uff11\u4e01\u76ee",
    "wof:placetype":"neighbourhood"
},
  "geometry": {"coordinates":[138.21691150000001,36.633837],"type":"Point"}
}