{
  "type": "Feature",
  "properties": {
    "gn:admin1_code":"27.0",
    "gn:admin2_code":"1852895.0",
    "gn:asciiname":"Emukaecho-tanomoto",
    "gn:country_code":"JP",
    "gn:dem":82,
    "gn:feature_class":"P",
    "gn:feature_code":"PPL",
    "gn:name":"Emukaech\u014d-tanomoto",
    "gn:population":0,
    "gn:timezone":"Asia/Tokyo",
    "iso:country":"JP",
    "name:jpn_x_preferred":[
        "\u6c5f\u8fce\u753a\u7530\u30ce\u5143"
    ],
    "name:und_x_variant":[
        "Emukaech\u014d-tanomoto"
    ],
    "wof:name":"Emukaecho-tanomoto",
    "wof:placetype":"locality"
},
  "geometry": {"coordinates":[129.68684999999999,33.27905],"type":"Point"}
}