{
  "type": "Feature",
  "properties": {
    "gn:admin1_code":"37.0",
    "gn:admin2_code":"1864104.0",
    "gn:asciiname":"Asahicho",
    "gn:country_code":"JP",
    "gn:dem":147,
    "gn:feature_class":"P",
    "gn:feature_code":"PPL",
    "gn:name":"Asahich\u014d",
    "gn:population":0,
    "gn:timezone":"Asia/Tokyo",
    "iso:country":"JP",
    "name:jpn_x_preferred":[
        "\u671d\u65e5\u753a"
    ],
    "name:und_x_variant":[
        "Asahich\u014d"
    ],
    "wof:name":"Asahicho",
    "wof:placetype":"locality"
},
  "geometry": {"coordinates":[138.60626000000002,35.23318],"type":"Point"}
}