{
  "type": "Feature",
  "properties": {
    "gn:admin1_code":"33.0",
    "gn:admin2_code":"8300623.0",
    "gn:asciiname":"Nanayama-manokawa",
    "gn:country_code":"JP",
    "gn:dem":281,
    "gn:feature_class":"P",
    "gn:feature_code":"PPL",
    "gn:name":"Nanayama-manokawa",
    "gn:population":0,
    "gn:timezone":"Asia/Tokyo",
    "iso:country":"JP",
    "name:jpn_x_preferred":[
        "\u4e03\u5c71\u99ac\u5ddd"
    ],
    "wof:name":"Nanayama-manokawa",
    "wof:placetype":"locality"
},
  "geometry": {"coordinates":[130.14373999999998,33.44364],"type":"Point"}
}