{
  "type": "Feature",
  "properties": {
    "gn:admin1_code":"26",
    "gn:admin2_code":"1857141.0",
    "gn:admin3_code":"20304.0",
    "gn:asciiname":"Azusayama",
    "gn:cc2":"JP",
    "gn:country_code":"JP",
    "gn:dem":1401,
    "gn:feature_class":"P",
    "gn:feature_code":"PPL",
    "gn:name":"Azusayama",
    "gn:population":0,
    "gn:timezone":"Asia/Tokyo",
    "iso:country":"JP",
    "name:und_x_variant":[
        "Atsusayama",
        "Azusayama"
    ],
    "wof:name":"Azusayama",
    "wof:placetype":"locality"
},
  "geometry": {"coordinates":[138.66666999999998,35.96667],"type":"Point"}
}