{
  "type": "Feature",
  "properties": {
    "gn:admin1_code":"44.0",
    "gn:admin2_code":"1849562.0",
    "gn:asciiname":"Haguromachi-noaramachi",
    "gn:country_code":"JP",
    "gn:dem":52,
    "gn:feature_class":"P",
    "gn:feature_code":"PPL",
    "gn:name":"Haguromachi-noaramachi",
    "gn:population":0,
    "gn:timezone":"Asia/Tokyo",
    "iso:country":"JP",
    "name:jpn_x_preferred":[
        "\u7fbd\u9ed2\u753a\u91ce\u8352\u753a"
    ],
    "wof:name":"Haguromachi-noaramachi",
    "wof:placetype":"locality"
},
  "geometry": {"coordinates":[139.91834,38.71741],"type":"Point"}
}