{
  "type": "Feature",
  "properties": {
    "gn:admin1_code":"3.0",
    "gn:admin2_code":"2130200.0",
    "gn:asciiname":"Takiyazawa",
    "gn:country_code":"JP",
    "gn:dem":32,
    "gn:feature_class":"P",
    "gn:feature_code":"PPL",
    "gn:name":"Takiyazawa",
    "gn:population":0,
    "gn:timezone":"Asia/Tokyo",
    "iso:country":"JP",
    "name:jpn_x_preferred":[
        "\u6edd\u8c37\u6ca2"
    ],
    "name:jpn_x_variant":[
        "\u305f\u304d\u3084\u3056\u308f",
        "\u30bf\u30ad\u30e4\u30b6\u30ef"
    ],
    "wof:name":"Takiyazawa",
    "wof:placetype":"locality"
},
  "geometry": {"coordinates":[141.41283000000001,40.51983],"type":"Point"}
}