{
  "type": "Feature",
  "properties": {
    "gn:admin1_code":"9.0",
    "gn:admin2_code":"1850890.0",
    "gn:asciiname":"Takanemachi-nomugi",
    "gn:country_code":"JP",
    "gn:dem":1347,
    "gn:feature_class":"P",
    "gn:feature_code":"PPL",
    "gn:name":"Takanemachi-nomugi",
    "gn:population":0,
    "gn:timezone":"Asia/Tokyo",
    "iso:country":"JP",
    "name:jpn_x_preferred":[
        "\u9ad8\u6839\u753a\u91ce\u9ea6"
    ],
    "wof:name":"Takanemachi-nomugi",
    "wof:placetype":"locality"
},
  "geometry": {"coordinates":[137.56658999999999,36.05052],"type":"Point"}
}