{
  "type": "Feature",
  "properties": {
    "gn:admin1_code":"43.0",
    "gn:admin2_code":"1865121.0",
    "gn:asciiname":"Chida",
    "gn:country_code":"JP",
    "gn:dem":5,
    "gn:feature_class":"P",
    "gn:feature_code":"PPL",
    "gn:name":"Chida",
    "gn:population":0,
    "gn:timezone":"Asia/Tokyo",
    "iso:country":"JP",
    "name:jpn_x_preferred":[
        "\u5343\u7530"
    ],
    "wof:name":"Chida",
    "wof:placetype":"locality"
},
  "geometry": {"coordinates":[135.14393000000001,34.06849],"type":"Point"}
}