{
  "type": "Feature",
  "properties": {
    "gn:admin1_code":"21.0",
    "gn:admin2_code":"7412706.0",
    "gn:admin3_code":"43447.0",
    "gn:asciiname":"Kakuage",
    "gn:country_code":"JP",
    "gn:dem":668,
    "gn:feature_class":"P",
    "gn:feature_code":"PPLL",
    "gn:name":"Kakuage",
    "gn:population":0,
    "gn:timezone":"Asia/Tokyo",
    "iso:country":"JP",
    "name:jpn_x_preferred":[
        "\u89d2\u4e0a"
    ],
    "name:jpn_x_variant":[
        "\u304b\u304f\u3042\u3052",
        "\u30ab\u30af\u30a2\u30b2"
    ],
    "wof:name":"Kakuage",
    "wof:placetype":"locality"
},
  "geometry": {"coordinates":[130.99146999999999,32.61436],"type":"Point"}
}