{
  "type": "Feature",
  "properties": {
    "gn:admin1_code":"34",
    "gn:admin2_code":"1863182.0",
    "gn:asciiname":"Hachikabara",
    "gn:country_code":"JP",
    "gn:dem":753,
    "gn:feature_class":"P",
    "gn:feature_code":"PPL",
    "gn:name":"Hachikabara",
    "gn:population":0,
    "gn:timezone":"Asia/Tokyo",
    "iso:country":"JP",
    "wof:name":"Hachikabara",
    "wof:placetype":"locality"
},
  "geometry": {"coordinates":[139.1225,35.90806],"type":"Point"}
}