{
  "type": "Feature",
  "properties": {
    "gn:admin1_code":"7.0",
    "gn:admin2_code":"1863955.0",
    "gn:admin3_code":"40131.0",
    "gn:asciiname":"Chihaya",
    "gn:country_code":"JP",
    "gn:dem":4,
    "gn:feature_class":"P",
    "gn:feature_code":"PPL",
    "gn:name":"Chihaya",
    "gn:population":0,
    "gn:timezone":"Asia/Tokyo",
    "iso:country":"JP",
    "name:jpn_x_preferred":[
        "\u5343\u65e9"
    ],
    "name:kor_x_preferred":[
        "\uc9c0\ud558\uc57c"
    ],
    "wof:name":"Chihaya",
    "wof:placetype":"locality"
},
  "geometry": {"coordinates":[130.43223,33.64749],"type":"Point"}
}