{
  "type": "Feature",
  "properties": {
    "gn:admin1_code":"21.0",
    "gn:admin2_code":"1864975.0",
    "gn:admin3_code":"43425.0",
    "gn:asciiname":"Katamata",
    "gn:country_code":"JP",
    "gn:dem":639,
    "gn:feature_class":"P",
    "gn:feature_code":"PPL",
    "gn:name":"Katamata",
    "gn:population":0,
    "gn:timezone":"Asia/Tokyo",
    "iso:country":"JP",
    "name:jpn_x_preferred":[
        "\u7247\u4fe3"
    ],
    "name:jpn_x_variant":[
        "\u304b\u305f\u307e\u305f",
        "\u30ab\u30bf\u30de\u30bf"
    ],
    "wof:name":"Katamata",
    "wof:placetype":"locality"
},
  "geometry": {"coordinates":[131.24421999999998,32.96946],"type":"Point"}
}