{
  "type": "Feature",
  "properties": {
    "gn:admin1_code":"45",
    "gn:admin2_code":"1849494.0",
    "gn:asciiname":"Maruo",
    "gn:country_code":"JP",
    "gn:dem":5,
    "gn:feature_class":"P",
    "gn:feature_code":"PPL",
    "gn:name":"Maruo",
    "gn:population":0,
    "gn:timezone":"Asia/Tokyo",
    "iso:country":"JP",
    "name:jpn_x_preferred":[
        "\u4e38\u5c3e"
    ],
    "wof:name":"Maruo",
    "wof:placetype":"locality"
},
  "geometry": {"coordinates":[131.35088000000002,33.9676],"type":"Point"}
}