{
  "type": "Feature",
  "properties": {
    "gn:admin1_code":"16.0",
    "gn:admin2_code":"2128941.0",
    "gn:admin3_code":"3524.0",
    "gn:asciiname":"Dateyashiki",
    "gn:country_code":"JP",
    "gn:dem":360,
    "gn:feature_class":"P",
    "gn:feature_code":"PPL",
    "gn:name":"Dateyashiki",
    "gn:population":0,
    "gn:timezone":"Asia/Tokyo",
    "iso:country":"JP",
    "name:jpn_x_preferred":[
        "\u8218\u5c4b\u6577"
    ],
    "name:jpn_x_variant":[
        "\u3060\u3066\u3084\u3057\u304d",
        "\u30c0\u30c6\u30e4\u30b7\u30ad"
    ],
    "wof:name":"Dateyashiki",
    "wof:placetype":"locality"
},
  "geometry": {"coordinates":[141.36273,40.21435],"type":"Point"}
}