{
  "type": "Feature",
  "properties": {
    "gn:admin1_code":"16",
    "gn:admin2_code":"7441817.0",
    "gn:asciiname":"Tomari",
    "gn:country_code":"JP",
    "gn:dem":33,
    "gn:feature_class":"P",
    "gn:feature_code":"PPL",
    "gn:name":"Tomari",
    "gn:population":0,
    "gn:timezone":"Asia/Tokyo",
    "iso:country":"JP",
    "name:deu_x_preferred":[
        "Tomari"
    ],
    "name:ita_x_preferred":[
        "Tomari"
    ],
    "name:jpn_x_preferred":[
        "\u6cca"
    ],
    "name:jpn_x_variant":[
        "\u3068\u307e\u308a",
        "\u30c8\u30de\u30ea"
    ],
    "name:nld_x_preferred":[
        "Tomari"
    ],
    "name:rus_x_preferred":[
        "\u0422\u043e\u043c\u0430\u0440\u0438"
    ],
    "name:ukr_x_preferred":[
        "\u0422\u043e\u043c\u0430\u0440\u0456"
    ],
    "name:und_x_variant":[
        "Hirota"
    ],
    "wof:name":"Tomari",
    "wof:placetype":"locality"
},
  "geometry": {"coordinates":[141.69104999999999,38.96004],"type":"Point"}
}