{
  "type": "Feature",
  "properties": {
    "gn:admin1_code":"21.0",
    "gn:admin2_code":"1865358.0",
    "gn:asciiname":"Egawa-funae",
    "gn:country_code":"JP",
    "gn:dem":1,
    "gn:feature_class":"P",
    "gn:feature_code":"PPLL",
    "gn:name":"Egawa-funae",
    "gn:population":0,
    "gn:timezone":"Asia/Tokyo",
    "iso:country":"JP",
    "name:jpn_x_preferred":[
        "\u6c5f\u5ddd\u821f\u6c5f"
    ],
    "name:jpn_x_variant":[
        "\u3048\u304c\u308f\u3075\u306a\u3048",
        "\u30a8\u30ac\u30ef\u30d5\u30ca\u30a8"
    ],
    "wof:name":"Egawa-funae",
    "wof:placetype":"locality"
},
  "geometry": {"coordinates":[130.23882,32.46113],"type":"Point"}
}