{
  "type": "Feature",
  "properties": {
    "gn:admin1_code":"38.0",
    "gn:admin2_code":"1865004.0",
    "gn:asciiname":"Nagusa-nakacho",
    "gn:country_code":"JP",
    "gn:dem":83,
    "gn:feature_class":"P",
    "gn:feature_code":"PPL",
    "gn:name":"Nagusa-nakach\u014d",
    "gn:population":0,
    "gn:timezone":"Asia/Tokyo",
    "iso:country":"JP",
    "name:jpn_x_preferred":[
        "\u540d\u8349\u4e2d\u753a"
    ],
    "name:und_x_variant":[
        "Nagusa-nakach\u014d"
    ],
    "wof:name":"Nagusa-nakacho",
    "wof:placetype":"locality"
},
  "geometry": {"coordinates":[139.47818999999998,36.38924],"type":"Point"}
}