{
  "type": "Feature",
  "properties": {
    "gn:admin1_code":"3.0",
    "gn:admin2_code":"2128302.0",
    "gn:admin3_code":"2450.0",
    "gn:asciiname":"Kitakabanoki",
    "gn:country_code":"JP",
    "gn:dem":252,
    "gn:feature_class":"P",
    "gn:feature_code":"PPL",
    "gn:name":"Kitakabanoki",
    "gn:population":0,
    "gn:timezone":"Asia/Tokyo",
    "iso:country":"JP",
    "name:jpn_x_preferred":[
        "\u5317\u691b\u30ce\u6728"
    ],
    "name:jpn_x_variant":[
        "\u304d\u305f\u304b\u3070\u306e\u304d",
        "\u30ad\u30bf\u30ab\u30d0\u30ce\u30ad"
    ],
    "wof:name":"Kitakabanoki",
    "wof:placetype":"locality"
},
  "geometry": {"coordinates":[141.11263,40.47727],"type":"Point"}
}