{
  "type": "Feature",
  "properties": {
    "gn:admin1_code":"24.0",
    "gn:admin2_code":"7446990.0",
    "gn:asciiname":"Togaimatsu",
    "gn:country_code":"JP",
    "gn:dem":16,
    "gn:feature_class":"P",
    "gn:feature_code":"PPL",
    "gn:name":"Togaimatsu",
    "gn:population":0,
    "gn:timezone":"Asia/Tokyo",
    "iso:country":"JP",
    "name:jpn_x_preferred":[
        "\u5341\u968e\u677e"
    ],
    "name:jpn_x_variant":[
        "\u3068\u304c\u3044\u307e\u3064",
        "\u30c8\u30ac\u30a4\u30de\u30c4"
    ],
    "wof:name":"Togaimatsu",
    "wof:placetype":"locality"
},
  "geometry": {"coordinates":[141.13758999999999,38.42132],"type":"Point"}
}