{
  "type": "Feature",
  "properties": {
    "gn:admin1_code":"28.0",
    "gn:admin2_code":"7412212.0",
    "gn:asciiname":"Haibara-nukai",
    "gn:country_code":"JP",
    "gn:dem":433,
    "gn:feature_class":"P",
    "gn:feature_code":"PPL",
    "gn:name":"Haibara-nukai",
    "gn:population":0,
    "gn:timezone":"Asia/Tokyo",
    "iso:country":"JP",
    "name:jpn_x_preferred":[
        "\u699b\u539f\u984d\u4e95"
    ],
    "wof:name":"Haibara-nukai",
    "wof:placetype":"locality"
},
  "geometry": {"coordinates":[135.97325000000001,34.55144],"type":"Point"}
}