{
  "type": "Feature",
  "properties": {
    "gn:admin1_code":"24.0",
    "gn:admin2_code":"2110755.0",
    "gn:asciiname":"Oinokawara",
    "gn:cc2":"JP",
    "gn:country_code":"JP",
    "gn:dem":16,
    "gn:feature_class":"P",
    "gn:feature_code":"PPL",
    "gn:name":"Oinokawara",
    "gn:population":0,
    "gn:timezone":"Asia/Tokyo",
    "iso:country":"JP",
    "name:und_x_variant":[
        "Oenokawara",
        "Oinugawara",
        "Oinokawara"
    ],
    "wof:name":"Oinokawara",
    "wof:placetype":"locality"
},
  "geometry": {"coordinates":[141.33333000000005,38.76667],"type":"Point"}
}