{
  "type": "Feature",
  "properties": {
    "gn:admin1_code":"34.0",
    "gn:admin2_code":"8304213.0",
    "gn:asciiname":"Kazahaya",
    "gn:country_code":"JP",
    "gn:dem":13,
    "gn:feature_class":"P",
    "gn:feature_code":"PPLL",
    "gn:name":"Kazahaya",
    "gn:population":0,
    "gn:timezone":"Asia/Tokyo",
    "iso:country":"JP",
    "name:jpn_x_preferred":[
        "\u98a8\u65e9"
    ],
    "wof:name":"Kazahaya",
    "wof:placetype":"locality"
},
  "geometry": {"coordinates":[139.80503999999999,35.98684],"type":"Point"}
}