{
  "type": "Feature",
  "properties": {
    "gn:admin1_code":"24.0",
    "gn:admin2_code":"2112092.0",
    "gn:asciiname":"Kurikoma-monji",
    "gn:country_code":"JP",
    "gn:dem":217,
    "gn:feature_class":"P",
    "gn:feature_code":"PPL",
    "gn:name":"Kurikoma-monji",
    "gn:population":0,
    "gn:timezone":"Asia/Tokyo",
    "iso:country":"JP",
    "name:jpn_x_preferred":[
        "\u6817\u99d2\u6587\u5b57"
    ],
    "wof:name":"Kurikoma-monji",
    "wof:placetype":"locality"
},
  "geometry": {"coordinates":[140.89863,38.85936],"type":"Point"}
}