{
  "type": "Feature",
  "properties": {
    "gn:admin1_code":"21.0",
    "gn:admin2_code":"1848441.0",
    "gn:asciiname":"Gunchiku-nibancho",
    "gn:country_code":"JP",
    "gn:dem":-1,
    "gn:feature_class":"P",
    "gn:feature_code":"PPL",
    "gn:name":"Gunchiku-nibanch\u014d",
    "gn:population":0,
    "gn:timezone":"Asia/Tokyo",
    "iso:country":"JP",
    "name:jpn_x_preferred":[
        "\u90e1\u7bc9\u4e8c\u756a\u753a"
    ],
    "name:jpn_x_variant":[
        "\u3050\u3093\u3061\u304f\u306b\u3070\u3093\u3061\u3087\u3046",
        "\u30b0\u30f3\u30c1\u30af\u30cb\u30d0\u30f3\u30c1\u30e7\u30a6"
    ],
    "name:und_x_variant":[
        "Gunchiku-nibanch\u014d"
    ],
    "wof:name":"Gunchiku-nibancho",
    "wof:placetype":"locality"
},
  "geometry": {"coordinates":[130.56412,32.52200999999999],"type":"Point"}
}