{
  "type": "Feature",
  "properties": {
    "gn:admin1_code":"26",
    "gn:admin2_code":"1849427.0",
    "gn:asciiname":"Higashigumi",
    "gn:country_code":"JP",
    "gn:dem":1275,
    "gn:feature_class":"P",
    "gn:feature_code":"PPL",
    "gn:name":"Higashigumi",
    "gn:population":0,
    "gn:timezone":"Asia/Tokyo",
    "iso:country":"JP",
    "name:jpn_x_preferred":[
        "\u6771\u7d44"
    ],
    "name:und_x_variant":[
        "Higashi-gumi"
    ],
    "wof:name":"Higashigumi",
    "wof:placetype":"locality"
},
  "geometry": {"coordinates":[138.33643000000001,36.52957],"type":"Point"}
}