{
  "type": "Feature",
  "properties": {
    "gn:admin1_code":"3.0",
    "gn:admin2_code":"2130056.0",
    "gn:asciiname":"Akudo",
    "gn:country_code":"JP",
    "gn:dem":43,
    "gn:feature_class":"P",
    "gn:feature_code":"PPL",
    "gn:name":"Akudo",
    "gn:population":0,
    "gn:timezone":"Asia/Tokyo",
    "iso:country":"JP",
    "name:jpn_x_preferred":[
        "\u60aa\u6238"
    ],
    "name:jpn_x_variant":[
        "\u3042\u304f\u3069",
        "\u30a2\u30af\u30c9"
    ],
    "wof:name":"Akudo",
    "wof:placetype":"locality"
},
  "geometry": {"coordinates":[140.43101999999999,40.59349],"type":"Point"}
}