{
  "type": "Feature",
  "properties": {
    "iso:country":"JP",
    "name:eng_x_preferred":[
        "Gumizawa 1 Chome"
    ],
    "name:eng_x_variant":[
        "Gumizawa 1 Choume",
        "Gumizawa 1 Chome"
    ],
    "name:jpn_x_preferred":[
        "\uff11\u4e01\u76ee"
    ],
    "name:jpn_x_variant":[
        "\u3050\u307f\u3056\u308f \uff11\u3061\u3087\u3046\u3081",
        "\u6c72\u6ca2 \uff11\u4e01\u76ee",
        "\uff11\u3061\u3087\u3046\u3081"
    ],
    "qs:gn_local":0,
    "qs:local_max":6208,
    "qs:local_sum":82309,
    "qs:localhoods":190,
    "qs:name":"\uff11\u4e01\u76ee",
    "qs:name_adm0":"\u65e5\u672c",
    "qs:name_adm1":"\u795e\u5948\u5ddd\u770c",
    "qs:name_adm2":"\u6238\u585a\u533a",
    "qs:name_en":"Gumizawa 1 Chome",
    "qs:name_lau":"\u6c72\u6ca2",
    "qs:name_local":"\u6a2a\u6d5c\u5e02",
    "qs:photo_max":304,
    "qs:photo_sum":741,
    "qs:placetype":"Suburb",
    "qs:quad_count":23,
    "qs:woe_adm0":23424856,
    "qs:woe_adm1":2345868,
    "qs:woe_adm2":1118393,
    "qs:woe_lau":28416021,
    "qs:woe_local":1118550,
    "qs:woe_ver":"7.10.0",
    "wof:lang":[
        "jpn"
    ],
    "wof:name":"\uff11\u4e01\u76ee",
    "wof:placetype":"neighbourhood"
},
  "geometry": {"coordinates":[139.53285399999999,35.39969],"type":"Point"}
}