{
  "type": "Feature",
  "properties": {
    "gn:admin1_code":"27",
    "gn:admin2_code":"7418804.0",
    "gn:asciiname":"Ikkuyama",
    "gn:cc2":"JP",
    "gn:country_code":"JP",
    "gn:dem":220,
    "gn:feature_class":"P",
    "gn:feature_code":"PPL",
    "gn:name":"Ikkuyama",
    "gn:population":0,
    "gn:timezone":"Asia/Tokyo",
    "iso:country":"JP",
    "name:und_x_variant":[
        "Ikkiyama",
        "Ikutsuyama",
        "Ikkuyama"
    ],
    "wof:name":"Ikkuyama",
    "wof:placetype":"locality"
},
  "geometry": {"coordinates":[128.69999999999999,32.63333],"type":"Point"}
}