{
  "type": "Feature",
  "properties": {
    "gn:admin1_code":"21.0",
    "gn:admin2_code":"1848443.0",
    "gn:admin3_code":"43468.0",
    "gn:asciiname":"Nakaono",
    "gn:country_code":"JP",
    "gn:dem":43,
    "gn:feature_class":"P",
    "gn:feature_code":"PPLL",
    "gn:name":"Naka\u014dno",
    "gn:population":0,
    "gn:timezone":"Asia/Tokyo",
    "iso:country":"JP",
    "name:jpn_x_preferred":[
        "\u4e2d\u5927\u91ce"
    ],
    "name:jpn_x_variant":[
        "\u306a\u304b\u304a\u304a\u306e",
        "\u30ca\u30ab\u30aa\u30aa\u30ce"
    ],
    "name:und_x_variant":[
        "Naka\u014dno"
    ],
    "wof:name":"Nakaono",
    "wof:placetype":"locality"
},
  "geometry": {"coordinates":[130.7022,32.56573],"type":"Point"}
}