{
  "type": "Feature",
  "properties": {
    "gn:admin1_code":"23.0",
    "gn:admin2_code":"1861901.0",
    "gn:asciiname":"Ho'ojiro",
    "gn:country_code":"JP",
    "gn:dem":254,
    "gn:feature_class":"P",
    "gn:feature_code":"PPL",
    "gn:name":"Ho\u2019ojiro",
    "gn:population":0,
    "gn:timezone":"Asia/Tokyo",
    "iso:country":"JP",
    "name:jpn_x_preferred":[
        "\u55b0\u4ee3"
    ],
    "name:und_x_variant":[
        "Ho\u2019ojiro"
    ],
    "wof:name":"Ho'ojiro",
    "wof:placetype":"locality"
},
  "geometry": {"coordinates":[136.21736999999999,34.74024],"type":"Point"}
}