{
  "type": "Feature",
  "properties": {
    "iso:country":"JP",
    "name:eng_x_preferred":[
        "Chuominami 1 Chome"
    ],
    "name:eng_x_variant":[
        "Chuuouminami 1 Choume",
        "Chuominami 1 Chome"
    ],
    "name:jpn_x_preferred":[
        "\uff11\u4e01\u76ee"
    ],
    "name:jpn_x_variant":[
        "\u3061\u3085\u3046\u304a\u3046\u307f\u306a\u307f \uff11\u3061\u3087\u3046\u3081",
        "\u4e2d\u592e\u5357 \uff11\u4e01\u76ee",
        "\uff11\u3061\u3087\u3046\u3081"
    ],
    "qs:gn_local":0,
    "qs:local_max":79,
    "qs:local_sum":88,
    "qs:localhoods":2,
    "qs:name":"\uff11\u4e01\u76ee",
    "qs:name_adm0":"\u65e5\u672c",
    "qs:name_adm1":"\u5343\u8449\u770c",
    "qs:name_en":"Chuominami 1 Chome",
    "qs:name_lau":"\u4e2d\u592e\u5357",
    "qs:name_local":"\u5370\u897f\u5e02",
    "qs:photo_max":5,
    "qs:photo_sum":9,
    "qs:placetype":"Suburb",
    "qs:quad_count":3,
    "qs:woe_adm0":23424856,
    "qs:woe_adm1":2345854,
    "qs:woe_adm2":0,
    "qs:woe_lau":28412906,
    "qs:woe_local":15015457,
    "qs:woe_ver":"7.10.0",
    "wof:lang":[
        "jpn"
    ],
    "wof:name":"\uff11\u4e01\u76ee",
    "wof:placetype":"neighbourhood"
},
  "geometry": {"coordinates":[140.117493,35.800243],"type":"Point"}
}