{
  "type": "Feature",
  "properties": {
    "gn:admin1_code":"18",
    "gn:admin2_code":"7383987.0",
    "gn:asciiname":"Akagina",
    "gn:cc2":"JP",
    "gn:country_code":"JP",
    "gn:dem":4,
    "gn:feature_class":"P",
    "gn:feature_code":"PPL",
    "gn:name":"Akagina",
    "gn:population":0,
    "gn:timezone":"Asia/Tokyo",
    "iso:country":"JP",
    "name:und_x_variant":[
        "Naka-kaneku",
        "Akakina",
        "Nakaganeku",
        "Akagina"
    ],
    "wof:name":"Akagina",
    "wof:placetype":"locality"
},
  "geometry": {"coordinates":[129.68333000000001,28.45],"type":"Point"}
}