{
  "type": "Feature",
  "properties": {
    "gn:admin1_code":"16.0",
    "gn:admin2_code":"2112822.0",
    "gn:asciiname":"Kunugiyama",
    "gn:country_code":"JP",
    "gn:dem":145,
    "gn:feature_class":"P",
    "gn:feature_code":"PPL",
    "gn:name":"Kunugiyama",
    "gn:population":0,
    "gn:timezone":"Asia/Tokyo",
    "iso:country":"JP",
    "name:jpn_x_preferred":[
        "\u691a\u5c71"
    ],
    "name:jpn_x_variant":[
        "\u304f\u306c\u304e\u3084\u307e",
        "\u30af\u30cc\u30ae\u30e4\u30de"
    ],
    "wof:name":"Kunugiyama",
    "wof:placetype":"locality"
},
  "geometry": {"coordinates":[141.18180000000001,39.36211],"type":"Point"}
}