{
  "type": "Feature",
  "properties": {
    "gn:admin1_code":"18.0",
    "gn:admin2_code":"1853737.0",
    "gn:admin3_code":"46525.0",
    "gn:asciiname":"Sachikatsu",
    "gn:country_code":"JP",
    "gn:dem":11,
    "gn:feature_class":"P",
    "gn:feature_code":"PPL",
    "gn:name":"Sachikatsu",
    "gn:population":0,
    "gn:timezone":"Asia/Tokyo",
    "iso:country":"JP",
    "name:jpn_x_preferred":[
        "\u4f50\u77e5\u514b"
    ],
    "wof:name":"Sachikatsu",
    "wof:placetype":"locality"
},
  "geometry": {"coordinates":[129.26684,28.08745],"type":"Point"}
}