{
  "type": "Feature",
  "properties": {
    "iso:country":"JP",
    "name:eng_x_preferred":[
        "Daimon 1 Chome"
    ],
    "name:eng_x_variant":[
        "Daimon 1 Choume",
        "Daimon 1 Chome"
    ],
    "name:jpn_x_preferred":[
        "\uff11\u4e01\u76ee"
    ],
    "name:jpn_x_variant":[
        "\u3060\u3044\u3082\u3093 \uff11\u3061\u3087\u3046\u3081",
        "\u5927\u9580 \uff11\u4e01\u76ee",
        "\uff11\u3061\u3087\u3046\u3081"
    ],
    "qs:gn_local":0,
    "qs:local_max":819,
    "qs:local_sum":3269,
    "qs:localhoods":25,
    "qs:name":"\uff11\u4e01\u76ee",
    "qs:name_adm0":"\u65e5\u672c",
    "qs:name_adm1":"\u798f\u5ca1\u770c",
    "qs:name_adm2":"\u5c0f\u5009\u5317\u533a",
    "qs:name_en":"Daimon 1 Chome",
    "qs:name_lau":"\u5927\u9580",
    "qs:name_local":"\u5317\u4e5d\u5dde\u5e02",
    "qs:photo_max":118,
    "qs:photo_sum":499,
    "qs:placetype":"Suburb",
    "qs:quad_count":26,
    "qs:woe_adm0":23424856,
    "qs:woe_adm1":58646425,
    "qs:woe_adm2":15015396,
    "qs:woe_lau":28482630,
    "qs:woe_local":1110809,
    "qs:woe_ver":"7.10.0",
    "wof:lang":[
        "jpn"
    ],
    "wof:name":"\uff11\u4e01\u76ee",
    "wof:placetype":"neighbourhood"
},
  "geometry": {"coordinates":[130.875122,33.88344],"type":"Point"}
}