{
  "type": "Feature",
  "properties": {
    "gn:admin1_code":"19.0",
    "gn:admin2_code":"1848350.0",
    "gn:admin3_code":"14117.0",
    "gn:asciiname":"Kakinokidai",
    "gn:country_code":"JP",
    "gn:dem":45,
    "gn:feature_class":"P",
    "gn:feature_code":"PPL",
    "gn:name":"Kakinokidai",
    "gn:population":0,
    "gn:timezone":"Asia/Tokyo",
    "iso:country":"JP",
    "name:jpn_x_preferred":[
        "\u67ff\u306e\u6728\u53f0"
    ],
    "wof:name":"Kakinokidai",
    "wof:placetype":"locality"
},
  "geometry": {"coordinates":[139.52833999999999,35.55126],"type":"Point"}
}