{
  "type": "Feature",
  "properties": {
    "iso:country":"JP",
    "name:eng_x_preferred":[
        "Ohmu"
    ],
    "name:eng_x_variant":[
        "Ohmu Town"
    ],
    "name:jpn_x_preferred":[
        "\u96c4\u6b66\u753a"
    ],
    "qs:name":"\u96c4\u6b66\u753a",
    "qs:name_adm0":"\u65e5\u672c",
    "qs:name_adm1":"\u5317\u6d77\u9053",
    "qs:photos":49,
    "qs:photos_1k":10,
    "qs:photos_9k":1,
    "qs:photos_9r":2,
    "qs:photos_all":49,
    "qs:photos_sr":2,
    "qs:placetype":"Town",
    "qs:pop_sr":"0",
    "wof:name":"Ohmu",
    "wof:placetype":"locality"
},
  "geometry": {"coordinates":[143.06043299999999,44.52855],"type":"Point"}
}