{
  "type": "Feature",
  "properties": {
    "gn:admin1_code":"43.0",
    "gn:admin2_code":"1860774.0",
    "gn:admin3_code":"30304.0",
    "gn:asciiname":"Fukui",
    "gn:country_code":"JP",
    "gn:dem":123,
    "gn:feature_class":"P",
    "gn:feature_code":"PPL",
    "gn:name":"Fukui",
    "gn:population":0,
    "gn:timezone":"Asia/Tokyo",
    "iso:country":"JP",
    "name:ces_x_preferred":[
        "Fukui"
    ],
    "name:deu_x_preferred":[
        "Fukui"
    ],
    "name:epo_x_preferred":[
        "Fukui"
    ],
    "name:fas_x_preferred":[
        "\u0641\u0648\u06a9\u0648\u0626\u06cc"
    ],
    "name:ita_x_preferred":[
        "Fukui"
    ],
    "name:jpn_x_preferred":[
        "\u798f\u4e95"
    ],
    "name:kor_x_preferred":[
        "\ud6c4\ucfe0\uc774"
    ],
    "name:nld_x_preferred":[
        "Fukui"
    ],
    "name:nor_x_preferred":[
        "Fukui"
    ],
    "name:por_x_preferred":[
        "Fukui"
    ],
    "name:ron_x_preferred":[
        "Fukui"
    ],
    "name:rus_x_preferred":[
        "\u0424\u0443\u043a\u0443\u0438"
    ],
    "name:slk_x_preferred":[
        "Fukui"
    ],
    "name:spa_x_preferred":[
        "Fukui"
    ],
    "name:swa_x_preferred":[
        "Fukui"
    ],
    "name:ukr_x_preferred":[
        "\u0424\u0443\u043a\u0443\u0439"
    ],
    "wof:name":"Fukui",
    "wof:placetype":"locality"
},
  "geometry": {"coordinates":[135.32536000000002,34.14374],"type":"Point"}
}