{
  "type": "Feature",
  "properties": {
    "gn:admin1_code":"18.0",
    "gn:admin2_code":"7383999.0",
    "gn:admin3_code":"46490.0",
    "gn:asciiname":"Orikono",
    "gn:country_code":"JP",
    "gn:dem":260,
    "gn:feature_class":"P",
    "gn:feature_code":"PPLL",
    "gn:name":"Orikono",
    "gn:population":0,
    "gn:timezone":"Asia/Tokyo",
    "iso:country":"JP",
    "name:jpn_x_preferred":[
        "\u6298\u5c0f\u91ce"
    ],
    "wof:name":"Orikono",
    "wof:placetype":"locality"
},
  "geometry": {"coordinates":[130.87723,31.20152],"type":"Point"}
}