{
  "type": "Feature",
  "properties": {
    "iso:country":"JP",
    "name:eng_x_preferred":[
        "Nekozane 1 Chome"
    ],
    "name:eng_x_variant":[
        "Nekozane 1 Choume",
        "Nekozane 1 Chome"
    ],
    "name:jpn_x_preferred":[
        "\uff11\u4e01\u76ee"
    ],
    "name:jpn_x_variant":[
        "\u306d\u3053\u3056\u306d \uff11\u3061\u3087\u3046\u3081",
        "\u732b\u5b9f \uff11\u4e01\u76ee",
        "\uff11\u3061\u3087\u3046\u3081"
    ],
    "qs:gn_local":0,
    "qs:local_max":28643,
    "qs:local_sum":29847,
    "qs:localhoods":14,
    "qs:name":"\uff11\u4e01\u76ee",
    "qs:name_adm0":"\u65e5\u672c",
    "qs:name_adm1":"\u5343\u8449\u770c",
    "qs:name_en":"Nekozane 1 Chome",
    "qs:name_lau":"\u732b\u5b9f",
    "qs:name_local":"\u6d66\u5b89\u5e02",
    "qs:photo_max":59,
    "qs:photo_sum":227,
    "qs:placetype":"Suburb",
    "qs:quad_count":14,
    "qs:woe_adm0":23424856,
    "qs:woe_adm1":2345854,
    "qs:woe_adm2":0,
    "qs:woe_lau":28412750,
    "qs:woe_local":1116236,
    "qs:woe_ver":"7.10.0",
    "wof:lang":[
        "jpn"
    ],
    "wof:name":"\uff11\u4e01\u76ee",
    "wof:placetype":"neighbourhood"
},
  "geometry": {"coordinates":[139.910258,35.652138],"type":"Point"}
}