{
  "type": "Feature",
  "properties": {
    "gn:admin1_code":"21.0",
    "gn:admin2_code":"1864975.0",
    "gn:admin3_code":"43424.0",
    "gn:asciiname":"Kitazato",
    "gn:country_code":"JP",
    "gn:dem":523,
    "gn:feature_class":"P",
    "gn:feature_code":"PPL",
    "gn:name":"Kitazato",
    "gn:population":0,
    "gn:timezone":"Asia/Tokyo",
    "iso:country":"JP",
    "name:jpn_x_preferred":[
        "\u5317\u91cc"
    ],
    "name:jpn_x_variant":[
        "\u304d\u305f\u3056\u3068",
        "\u30ad\u30bf\u30b6\u30c8"
    ],
    "wof:name":"Kitazato",
    "wof:placetype":"locality"
},
  "geometry": {"coordinates":[131.09777,33.14530999999999],"type":"Point"}
}