{
  "type": "Feature",
  "properties": {
    "gn:admin1_code":"44",
    "gn:admin2_code":"1862730.0",
    "gn:admin3_code":"6428.0",
    "gn:asciiname":"Karikawa",
    "gn:country_code":"JP",
    "gn:dem":15,
    "gn:feature_class":"P",
    "gn:feature_code":"PPL",
    "gn:name":"Karikawa",
    "gn:population":0,
    "gn:timezone":"Asia/Tokyo",
    "iso:country":"JP",
    "name:jpn_x_preferred":[
        "\u72e9\u5ddd"
    ],
    "wof:name":"Karikawa",
    "wof:placetype":"locality"
},
  "geometry": {"coordinates":[139.96555000000001,38.79231],"type":"Point"}
}