{
  "type": "Feature",
  "properties": {
    "gn:admin1_code":"16.0",
    "gn:admin2_code":"2112822.0",
    "gn:asciiname":"Shimizuno",
    "gn:country_code":"JP",
    "gn:dem":153,
    "gn:feature_class":"P",
    "gn:feature_code":"PPL",
    "gn:name":"Shimizuno",
    "gn:population":0,
    "gn:timezone":"Asia/Tokyo",
    "iso:country":"JP",
    "name:jpn_x_preferred":[
        "\u6e05\u6c34\u91ce"
    ],
    "name:jpn_x_variant":[
        "\u3057\u307f\u305a\u306e",
        "\u30b7\u30df\u30ba\u30ce"
    ],
    "wof:name":"Shimizuno",
    "wof:placetype":"locality"
},
  "geometry": {"coordinates":[141.01079999999999,39.36719],"type":"Point"}
}