{
  "type": "Feature",
  "properties": {
    "gn:admin1_code":"24.0",
    "gn:admin2_code":"2111889.0",
    "gn:admin3_code":"4401.0",
    "gn:asciiname":"Hosoyamasaki",
    "gn:country_code":"JP",
    "gn:dem":15,
    "gn:feature_class":"P",
    "gn:feature_code":"PPL",
    "gn:name":"Hosoyamasaki",
    "gn:population":0,
    "gn:timezone":"Asia/Tokyo",
    "iso:country":"JP",
    "name:jpn_x_preferred":[
        "\u7d30\u5c71\u5d0e"
    ],
    "name:jpn_x_variant":[
        "\u307b\u305d\u3084\u307e\u3055\u304d",
        "\u30db\u30bd\u30e4\u30de\u30b5\u30ad"
    ],
    "wof:name":"Hosoyamasaki",
    "wof:placetype":"locality"
},
  "geometry": {"coordinates":[141.08807999999999,38.42768],"type":"Point"}
}