{
  "type": "Feature",
  "properties": {
    "gn:admin1_code":"24.0",
    "gn:admin2_code":"2112574.0",
    "gn:asciiname":"Gankita",
    "gn:country_code":"JP",
    "gn:dem":3,
    "gn:feature_class":"P",
    "gn:feature_code":"PPL",
    "gn:name":"Gankita",
    "gn:population":0,
    "gn:timezone":"Asia/Tokyo",
    "iso:country":"JP",
    "name:jpn_x_preferred":[
        "\u96c1\u5317"
    ],
    "name:jpn_x_variant":[
        "\u304c\u3093\u304d\u305f",
        "\u30ac\u30f3\u30ad\u30bf"
    ],
    "wof:name":"Gankita",
    "wof:placetype":"locality"
},
  "geometry": {"coordinates":[141.19392999999999,38.47029000000001],"type":"Point"}
}