{
  "type": "Feature",
  "properties": {
    "gn:admin1_code":"6.0",
    "gn:admin2_code":"1863982.0",
    "gn:asciiname":"Miyama",
    "gn:country_code":"JP",
    "gn:dem":51,
    "gn:elevation":"55.0",
    "gn:feature_class":"P",
    "gn:feature_code":"PPLL",
    "gn:name":"Miyama",
    "gn:population":0,
    "gn:timezone":"Asia/Tokyo",
    "iso:country":"JP",
    "name:deu_x_preferred":[
        "Miyama"
    ],
    "name:sco_x_preferred":[
        "Miyama"
    ],
    "wof:name":"Miyama",
    "wof:placetype":"locality"
},
  "geometry": {"coordinates":[136.32822999999999,36.01891],"type":"Point"}
}