{
  "type": "Feature",
  "properties": {
    "gn:admin1_code":"21.0",
    "gn:admin2_code":"1848441.0",
    "gn:asciiname":"Wakakusacho",
    "gn:country_code":"JP",
    "gn:dem":7,
    "gn:feature_class":"P",
    "gn:feature_code":"PPL",
    "gn:name":"Wakakusach\u014d",
    "gn:population":0,
    "gn:timezone":"Asia/Tokyo",
    "iso:country":"JP",
    "name:jpn_x_preferred":[
        "\u82e5\u8349\u753a"
    ],
    "name:jpn_x_variant":[
        "\u308f\u304b\u304f\u3055\u3061\u3087\u3046",
        "\u30ef\u30ab\u30af\u30b5\u30c1\u30e7\u30a6"
    ],
    "name:und_x_variant":[
        "Wakakusach\u014d"
    ],
    "wof:name":"Wakakusacho",
    "wof:placetype":"locality"
},
  "geometry": {"coordinates":[130.61376999999999,32.50366],"type":"Point"}
}