{
  "type": "Feature",
  "properties": {
    "gn:admin1_code":"16.0",
    "gn:admin2_code":"2112264.0",
    "gn:admin3_code":"3441.0",
    "gn:asciiname":"Kawaguchi",
    "gn:cc2":"JP",
    "gn:country_code":"JP",
    "gn:dem":203,
    "gn:feature_class":"P",
    "gn:feature_code":"PPL",
    "gn:name":"Kawaguchi",
    "gn:population":0,
    "gn:timezone":"Asia/Tokyo",
    "iso:country":"JP",
    "name:ceb_x_preferred":[
        "Kawaguchi"
    ],
    "name:ces_x_preferred":[
        "Kawagu\u010di"
    ],
    "name:deu_x_preferred":[
        "Kawaguchi"
    ],
    "name:fra_x_preferred":[
        "Kawaguchi"
    ],
    "name:kor_x_preferred":[
        "\uac00\uc640\uad6c\uce58"
    ],
    "name:mlg_x_preferred":[
        "Kawaguchi"
    ],
    "name:rus_x_preferred":[
        "\u041a\u0430\u0432\u0430\u0433\u0443\u0442\u0438"
    ],
    "name:und_x_variant":[
        "Kawakuchi"
    ],
    "wof:name":"Kawaguchi",
    "wof:placetype":"locality"
},
  "geometry": {"coordinates":[141.53333000000001,39.15],"type":"Point"}
}