{
  "type": "Feature",
  "properties": {
    "gn:admin1_code":"16.0",
    "gn:admin2_code":"2112264.0",
    "gn:admin3_code":"3441.0",
    "gn:asciiname":"Kawaguchi",
    "gn:cc2":"JP",
    "gn:country_code":"JP",
    "gn:dem":203,
    "gn:feature_class":"P",
    "gn:feature_code":"PPL",
    "gn:name":"Kawaguchi",
    "gn:population":0,
    "gn:timezone":"Asia/Tokyo",
    "iso:country":"JP",
    "name:und_x_variant":[
        "Kawakuchi",
        "Kawaguchi"
    ],
    "wof:name":"Kawaguchi",
    "wof:placetype":"locality"
},
  "geometry": {"coordinates":[141.53333000000001,39.15],"type":"Point"}
}