{
  "type": "Feature",
  "properties": {
    "gn:admin1_code":"32.0",
    "gn:admin2_code":"1853897.0",
    "gn:admin3_code":"27119.0",
    "gn:asciiname":"Showacho",
    "gn:country_code":"JP",
    "gn:dem":10,
    "gn:feature_class":"P",
    "gn:feature_code":"PPL",
    "gn:name":"Sh\u014dwach\u014d",
    "gn:population":0,
    "gn:timezone":"Asia/Tokyo",
    "iso:country":"JP",
    "name:jpn_x_preferred":[
        "\u662d\u548c\u753a"
    ],
    "name:und_x_variant":[
        "Sh\u014dwach\u014d"
    ],
    "wof:name":"Showacho",
    "wof:placetype":"locality"
},
  "geometry": {"coordinates":[135.51819,34.62625],"type":"Point"}
}