{
  "type": "Feature",
  "properties": {
    "gn:admin1_code":"37.0",
    "gn:admin2_code":"1851401.0",
    "gn:admin3_code":"22341.0",
    "gn:asciiname":"Matoba",
    "gn:country_code":"JP",
    "gn:dem":11,
    "gn:feature_class":"P",
    "gn:feature_code":"PPL",
    "gn:name":"Matoba",
    "gn:population":0,
    "gn:timezone":"Asia/Tokyo",
    "iso:country":"JP",
    "name:jpn_x_preferred":[
        "\u7684\u5834"
    ],
    "wof:name":"Matoba",
    "wof:placetype":"locality"
},
  "geometry": {"coordinates":[138.90801000000002,35.08898],"type":"Point"}
}