{
  "type": "Feature",
  "properties": {
    "gn:admin1_code":"33.0",
    "gn:admin2_code":"7391357.0",
    "gn:asciiname":"Mitani",
    "gn:country_code":"JP",
    "gn:dem":140,
    "gn:feature_class":"P",
    "gn:feature_code":"PPLL",
    "gn:name":"Mitani",
    "gn:population":0,
    "gn:timezone":"Asia/Tokyo",
    "iso:country":"JP",
    "name:ceb_x_preferred":[
        "Mitani"
    ],
    "name:deu_x_preferred":[
        "Mitani"
    ],
    "name:jpn_x_preferred":[
        "\u4e09\u8c37"
    ],
    "name:swe_x_preferred":[
        "Mitani"
    ],
    "wof:name":"Mitani",
    "wof:placetype":"locality"
},
  "geometry": {"coordinates":[130.36997,33.36051],"type":"Point"}
}