{
  "type": "Feature",
  "properties": {
    "gn:admin1_code":"37.0",
    "gn:admin2_code":"1864089.0",
    "gn:asciiname":"Suijin",
    "gn:country_code":"JP",
    "gn:dem":24,
    "gn:feature_class":"P",
    "gn:feature_code":"PPLL",
    "gn:name":"Suijin",
    "gn:population":0,
    "gn:timezone":"Asia/Tokyo",
    "iso:country":"JP",
    "name:fin_x_preferred":[
        "Suijin"
    ],
    "name:fra_x_preferred":[
        "Suijin"
    ],
    "name:jpn_x_preferred":[
        "\u6c34\u795e"
    ],
    "name:nld_x_preferred":[
        "Suijin"
    ],
    "name:spa_x_preferred":[
        "Suijin"
    ],
    "name:zho_x_preferred":[
        "\u6c34\u795e"
    ],
    "wof:name":"Suijin",
    "wof:placetype":"locality"
},
  "geometry": {"coordinates":[138.62953999999999,35.15455],"type":"Point"}
}