{
  "type": "Feature",
  "properties": {
    "gn:admin1_code":"19",
    "gn:admin2_code":"1865011.0",
    "gn:admin3_code":"14363.0",
    "gn:asciiname":"Tashiro",
    "gn:country_code":"JP",
    "gn:dem":283,
    "gn:feature_class":"P",
    "gn:feature_code":"PPL",
    "gn:name":"Tashiro",
    "gn:population":0,
    "gn:timezone":"Asia/Tokyo",
    "iso:country":"JP",
    "name:jpn_x_preferred":[
        "\u7530\u4ee3"
    ],
    "wof:name":"Tashiro",
    "wof:placetype":"locality"
},
  "geometry": {"coordinates":[139.13333,35.38333],"type":"Point"}
}