{
  "type": "Feature",
  "properties": {
    "gn:admin1_code":"24.0",
    "gn:admin2_code":"2112074.0",
    "gn:admin3_code":"4424.0",
    "gn:asciiname":"Zafu",
    "gn:country_code":"JP",
    "gn:dem":31,
    "gn:feature_class":"P",
    "gn:feature_code":"PPLL",
    "gn:name":"Zafu",
    "gn:population":0,
    "gn:timezone":"Asia/Tokyo",
    "iso:country":"JP",
    "name:cat_x_preferred":[
        "Zafu"
    ],
    "name:deu_x_preferred":[
        "Zafu"
    ],
    "name:fra_x_preferred":[
        "Zafu"
    ],
    "name:ita_x_preferred":[
        "Zafu"
    ],
    "name:jpn_x_preferred":[
        "\u5ea7\u5e9c"
    ],
    "name:pol_x_preferred":[
        "Zafu"
    ],
    "name:por_x_preferred":[
        "Zafu"
    ],
    "name:rus_x_preferred":[
        "\u0414\u0437\u0430\u0444\u0443"
    ],
    "name:spa_x_preferred":[
        "Zafu"
    ],
    "wof:name":"Zafu",
    "wof:placetype":"locality"
},
  "geometry": {"coordinates":[140.87556000000001,38.48806],"type":"Point"}
}