{
  "type": "Feature",
  "properties": {
    "gn:admin1_code":"40.0",
    "gn:admin2_code":"1852083.0",
    "gn:asciiname":"Wakabamachi",
    "gn:country_code":"JP",
    "gn:dem":32,
    "gn:feature_class":"P",
    "gn:feature_code":"PPL",
    "gn:name":"Wakabamachi",
    "gn:population":0,
    "gn:timezone":"Asia/Tokyo",
    "iso:country":"JP",
    "name:jpn_x_preferred":[
        "\u82e5\u8449\u753a"
    ],
    "wof:name":"Wakabamachi",
    "wof:placetype":"locality"
},
  "geometry": {"coordinates":[139.72636,35.68416],"type":"Point"}
}