{
  "type": "Feature",
  "properties": {
    "gn:admin1_code":"37.0",
    "gn:admin2_code":"1864089.0",
    "gn:asciiname":"Kawanarijima",
    "gn:country_code":"JP",
    "gn:dem":8,
    "gn:feature_class":"P",
    "gn:feature_code":"PPL",
    "gn:name":"Kawanarijima",
    "gn:population":0,
    "gn:timezone":"Asia/Tokyo",
    "iso:country":"JP",
    "name:jpn_x_preferred":[
        "\u5ddd\u6210\u5cf6"
    ],
    "wof:name":"Kawanarijima",
    "wof:placetype":"locality"
},
  "geometry": {"coordinates":[138.66466,35.13598],"type":"Point"}
}