{
  "type": "Feature",
  "properties": {
    "gn:admin1_code":"29",
    "gn:admin2_code":"7468177.0",
    "gn:asciiname":"Arakawa",
    "gn:country_code":"JP",
    "gn:dem":12,
    "gn:feature_class":"P",
    "gn:feature_code":"PPL",
    "gn:name":"Arakawa",
    "gn:population":0,
    "gn:timezone":"Asia/Tokyo",
    "iso:country":"JP",
    "wof:name":"Arakawa",
    "wof:placetype":"locality"
},
  "geometry": {"coordinates":[139.45500000000001,38.11667],"type":"Point"}
}