{
  "type": "Feature",
  "properties": {
    "gn:admin1_code":"29",
    "gn:admin2_code":"7468177.0",
    "gn:asciiname":"Arakawa",
    "gn:country_code":"JP",
    "gn:dem":12,
    "gn:feature_class":"P",
    "gn:feature_code":"PPL",
    "gn:name":"Arakawa",
    "gn:population":0,
    "gn:timezone":"Asia/Tokyo",
    "iso:country":"JP",
    "name:fas_x_preferred":[
        "\u0622\u0631\u0627\u06a9\u0627\u0648\u0627"
    ],
    "name:jpn_x_preferred":[
        "\u8352\u5ddd\u753a"
    ],
    "name:zho_x_preferred":[
        "\u8352\u5ddd\u753a"
    ],
    "wof:name":"Arakawa",
    "wof:placetype":"locality"
},
  "geometry": {"coordinates":[139.45500000000001,38.11667],"type":"Point"}
}