{
  "type": "Feature",
  "properties": {
    "gn:admin1_code":"19.0",
    "gn:admin2_code":"1860670.0",
    "gn:asciiname":"Yukinoshita",
    "gn:country_code":"JP",
    "gn:dem":12,
    "gn:feature_class":"P",
    "gn:feature_code":"PPL",
    "gn:name":"Yukinoshita",
    "gn:population":0,
    "gn:timezone":"Asia/Tokyo",
    "iso:country":"JP",
    "name:jpn_x_preferred":[
        "\u96ea\u306e\u4e0b"
    ],
    "name:jpn_x_variant":[
        "\u3086\u304d\u306e\u3057\u305f",
        "\u30e6\u30ad\u30ce\u30b7\u30bf"
    ],
    "wof:name":"Yukinoshita",
    "wof:placetype":"locality"
},
  "geometry": {"coordinates":[139.55518000000001,35.32344000000001],"type":"Point"}
}