{
  "type": "Feature",
  "properties": {
    "iso:country":"JP",
    "name:eng_x_preferred":[
        "Hikoshimaenoracho 6 Chome"
    ],
    "name:eng_x_variant":[
        "Hikoshimaenourachou 6 Choume",
        "Hikoshimaenoracho 6 Chome"
    ],
    "name:jpn_x_preferred":[
        "\uff16\u4e01\u76ee"
    ],
    "name:jpn_x_variant":[
        "\u3072\u3053\u3057\u307e\u3048\u306e\u3046\u3089\u3061\u3087\u3046 \uff16\u3061\u3087\u3046\u3081",
        "\u5f66\u5cf6\u6c5f\u306e\u6d66\u753a \uff16\u4e01\u76ee",
        "\uff16\u3061\u3087\u3046\u3081"
    ],
    "qs:gn_local":0,
    "qs:local_max":468,
    "qs:local_sum":1422,
    "qs:localhoods":12,
    "qs:name":"\uff16\u4e01\u76ee",
    "qs:name_adm0":"\u65e5\u672c",
    "qs:name_adm1":"\u5c71\u53e3\u770c",
    "qs:name_en":"Hikoshimaenoracho 6 Chome",
    "qs:name_lau":"\u5f66\u5cf6\u6c5f\u306e\u6d66\u753a",
    "qs:name_local":"\u4e0b\u95a2\u5e02",
    "qs:photo_max":28,
    "qs:photo_sum":29,
    "qs:placetype":"Suburb",
    "qs:quad_count":2,
    "qs:woe_adm0":23424856,
    "qs:woe_adm1":2345894,
    "qs:woe_adm2":0,
    "qs:woe_lau":28475905,
    "qs:woe_local":1118179,
    "qs:woe_ver":"7.10.0",
    "wof:lang":[
        "jpn"
    ],
    "wof:name":"\uff16\u4e01\u76ee",
    "wof:placetype":"neighbourhood"
},
  "geometry": {"coordinates":[130.92132799999999,33.936368],"type":"Point"}
}