{
  "type": "Feature",
  "properties": {
    "gn:admin1_code":"12.0",
    "gn:admin2_code":"7428106.0",
    "gn:admin3_code":"1547.0",
    "gn:asciiname":"Mizukami",
    "gn:country_code":"JP",
    "gn:dem":83,
    "gn:feature_class":"P",
    "gn:feature_code":"PPL",
    "gn:name":"Mizukami",
    "gn:population":0,
    "gn:timezone":"Asia/Tokyo",
    "iso:country":"JP",
    "name:jpn_x_preferred":[
        "\u6c34\u4e0a"
    ],
    "name:jpn_x_variant":[
        "\u307f\u305a\u304b\u307f",
        "\u30df\u30ba\u30ab\u30df"
    ],
    "name:und_x_variant":[
        "Minakami",
        "Mizukami"
    ],
    "wof:name":"Mizukami",
    "wof:placetype":"locality"
},
  "geometry": {"coordinates":[144.49723,43.80107],"type":"Point"}
}