{
  "type": "Feature",
  "properties": {
    "gn:admin1_code":"12.0",
    "gn:admin2_code":"2129370.0",
    "gn:asciiname":"Shinfujicho",
    "gn:country_code":"JP",
    "gn:dem":4,
    "gn:feature_class":"P",
    "gn:feature_code":"PPL",
    "gn:name":"Shinfujich\u014d",
    "gn:population":0,
    "gn:timezone":"Asia/Tokyo",
    "iso:country":"JP",
    "name:jpn_x_preferred":[
        "\u65b0\u5bcc\u58eb\u753a"
    ],
    "name:jpn_x_variant":[
        "\u3057\u3093\u3075\u3058\u3061\u3087\u3046",
        "\u30b7\u30f3\u30d5\u30b8\u30c1\u30e7\u30a6"
    ],
    "name:und_x_variant":[
        "Shinfujich\u014d"
    ],
    "wof:name":"Shinfujicho",
    "wof:placetype":"locality"
},
  "geometry": {"coordinates":[144.34958,43.00466],"type":"Point"}
}