{
  "type": "Feature",
  "properties": {
    "gn:admin1_code":"44.0",
    "gn:admin2_code":"7450018.0",
    "gn:asciiname":"Aramachi",
    "gn:country_code":"JP",
    "gn:dem":174,
    "gn:feature_class":"P",
    "gn:feature_code":"PPLL",
    "gn:name":"Aramachi",
    "gn:population":0,
    "gn:timezone":"Asia/Tokyo",
    "iso:country":"JP",
    "name:jpn_x_preferred":[
        "\u8352\u753a"
    ],
    "wof:name":"Aramachi",
    "wof:placetype":"locality"
},
  "geometry": {"coordinates":[140.45211,38.56235],"type":"Point"}
}