{
  "type": "Feature",
  "properties": {
    "gn:admin1_code":"21.0",
    "gn:admin2_code":"1858418.0",
    "gn:admin3_code":"43104.0",
    "gn:asciiname":"Rokucho-shinkai",
    "gn:country_code":"JP",
    "gn:dem":-2,
    "gn:feature_class":"P",
    "gn:feature_code":"PPLL",
    "gn:name":"Rokuch\u014d-shinkai",
    "gn:population":0,
    "gn:timezone":"Asia/Tokyo",
    "iso:country":"JP",
    "name:jpn_x_preferred":[
        "\u516d\u753a\u65b0\u958b"
    ],
    "name:jpn_x_variant":[
        "\u308d\u304f\u3061\u3087\u3046\u3057\u3093\u304b\u3044",
        "\u30ed\u30af\u30c1\u30e7\u30a6\u30b7\u30f3\u30ab\u30a4"
    ],
    "name:und_x_variant":[
        "Rokuch\u014d-shinkai"
    ],
    "wof:name":"Rokucho-shinkai",
    "wof:placetype":"locality"
},
  "geometry": {"coordinates":[130.63874999999999,32.73468],"type":"Point"}
}