{
  "type": "Feature",
  "properties": {
    "gn:admin1_code":"25.0",
    "gn:admin2_code":"1864313.0",
    "gn:asciiname":"Fukino",
    "gn:country_code":"JP",
    "gn:dem":391,
    "gn:feature_class":"P",
    "gn:feature_code":"PPLL",
    "gn:name":"Fukino",
    "gn:population":0,
    "gn:timezone":"Asia/Tokyo",
    "iso:country":"JP",
    "name:jpn_x_preferred":[
        "\u67ca\u91ce"
    ],
    "name:jpn_x_variant":[
        "\u3075\u304d\u306e",
        "\u30d5\u30ad\u30ce"
    ],
    "wof:name":"Fukino",
    "wof:placetype":"locality"
},
  "geometry": {"coordinates":[130.89269999999999,32.0719],"type":"Point"}
}