{
  "type": "Feature",
  "properties": {
    "iso:country":"JP",
    "name:eng_x_preferred":[
        "Makurazaki"
    ],
    "name:eng_x_variant":[
        "Makurazaki City"
    ],
    "name:jpn_x_preferred":[
        "\u6795\u5d0e\u5e02"
    ],
    "qs:name":"\u6795\u5d0e\u5e02",
    "qs:name_adm0":"\u65e5\u672c",
    "qs:name_adm1":"\u9e7f\u5150\u5cf6\u770c",
    "qs:photos":56,
    "qs:photos_1k":11,
    "qs:photos_9k":1,
    "qs:photos_9r":2,
    "qs:photos_all":56,
    "qs:photos_sr":2,
    "qs:placetype":"Town",
    "qs:pop_sr":"0",
    "wof:name":"Makurazaki",
    "wof:placetype":"locality"
},
  "geometry": {"coordinates":[130.28617800000001,31.271508],"type":"Point"}
}