{
  "type": "Feature",
  "properties": {
    "gn:admin1_code":"21.0",
    "gn:admin2_code":"1864975.0",
    "gn:admin3_code":"43425.0",
    "gn:asciiname":"Ishiono",
    "gn:country_code":"JP",
    "gn:dem":552,
    "gn:feature_class":"P",
    "gn:feature_code":"PPLL",
    "gn:name":"Ishiono",
    "gn:population":0,
    "gn:timezone":"Asia/Tokyo",
    "iso:country":"JP",
    "name:jpn_x_preferred":[
        "\u77f3\u5c3e\u91ce"
    ],
    "name:jpn_x_variant":[
        "\u3044\u3057\u304a\u306e",
        "\u30a4\u30b7\u30aa\u30ce"
    ],
    "wof:name":"Ishiono",
    "wof:placetype":"locality"
},
  "geometry": {"coordinates":[131.23588999999998,32.99972],"type":"Point"}
}