{
  "type": "Feature",
  "properties": {
    "gn:admin1_code":"43.0",
    "gn:admin2_code":"1860774.0",
    "gn:admin3_code":"30304.0",
    "gn:asciiname":"Iseki",
    "gn:country_code":"JP",
    "gn:dem":106,
    "gn:feature_class":"P",
    "gn:feature_code":"PPL",
    "gn:name":"Iseki",
    "gn:population":0,
    "gn:timezone":"Asia/Tokyo",
    "iso:country":"JP",
    "name:jbn_x_preferred":[
        "Iseki"
    ],
    "name:jpn_x_preferred":[
        "\u4e95\u5830"
    ],
    "wof:name":"Iseki",
    "wof:placetype":"locality"
},
  "geometry": {"coordinates":[135.36521999999999,34.17119],"type":"Point"}
}