{
  "type": "Feature",
  "properties": {
    "iso:country":"JP",
    "name:eng_x_preferred":[
        "Akasaka 1 Chome"
    ],
    "name:eng_x_variant":[
        "Akasaka 1 Choume",
        "Akasaka 1 Chome"
    ],
    "name:jpn_x_preferred":[
        "\uff11\u4e01\u76ee"
    ],
    "name:jpn_x_variant":[
        "\u3042\u304b\u3055\u304b \uff11\u3061\u3087\u3046\u3081",
        "\u8d64\u5742 \uff11\u4e01\u76ee",
        "\uff11\u3061\u3087\u3046\u3081"
    ],
    "qs:gn_adm0_cc":"JP",
    "qs:gn_local":1850147,
    "qs:local_max":18112,
    "qs:local_sum":895907,
    "qs:localhoods":857,
    "qs:name":"\uff11\u4e01\u76ee",
    "qs:name_adm0":"\u65e5\u672c",
    "qs:name_adm1":"\u6771\u4eac\u90fd",
    "qs:name_adm2":"\u6e2f\u533a",
    "qs:name_en":"Akasaka 1 Chome",
    "qs:name_lau":"\u8d64\u5742",
    "qs:name_local":"\u6771\u4eac",
    "qs:photo_max":304,
    "qs:photo_sum":1038,
    "qs:placetype":"Suburb",
    "qs:quad_count":20,
    "qs:woe_adm0":23424856,
    "qs:woe_adm1":2345889,
    "qs:woe_adm2":15015406,
    "qs:woe_lau":1107355,
    "qs:woe_local":1118370,
    "qs:woe_ver":"7.10.0",
    "wof:lang":[
        "jpn"
    ],
    "wof:name":"\uff11\u4e01\u76ee",
    "wof:placetype":"neighbourhood"
},
  "geometry": {"coordinates":[139.74322699999999,35.668405],"type":"Point"}
}