{
  "type": "Feature",
  "properties": {
    "gn:admin1_code":"19.0",
    "gn:admin2_code":"7470890.0",
    "gn:asciiname":"Daiyucho",
    "gn:country_code":"JP",
    "gn:dem":151,
    "gn:feature_class":"P",
    "gn:feature_code":"PPL",
    "gn:name":"Daiy\u016bch\u014d",
    "gn:population":0,
    "gn:timezone":"Asia/Tokyo",
    "iso:country":"JP",
    "name:jpn_x_preferred":[
        "\u5927\u96c4\u753a"
    ],
    "name:und_x_variant":[
        "Daiy\u016bch\u014d"
    ],
    "wof:name":"Daiyucho",
    "wof:placetype":"locality"
},
  "geometry": {"coordinates":[139.08867000000001,35.31232],"type":"Point"}
}