{
  "type": "Feature",
  "properties": {
    "gn:admin1_code":"21",
    "gn:admin2_code":"7412706.0",
    "gn:admin3_code":"43443.0",
    "gn:asciiname":"Kiyama",
    "gn:country_code":"JP",
    "gn:dem":32,
    "gn:feature_class":"P",
    "gn:feature_code":"PPL",
    "gn:name":"Kiyama",
    "gn:population":0,
    "gn:timezone":"Asia/Tokyo",
    "iso:country":"JP",
    "name:jpn_x_preferred":[
        "\u6728\u5c71"
    ],
    "name:jpn_x_variant":[
        "\u304d\u3084\u307e",
        "\u30ad\u30e4\u30de"
    ],
    "name:rus_x_preferred":[
        "\u041a\u0438\u044f\u043c\u0430"
    ],
    "wof:name":"Kiyama",
    "wof:placetype":"locality"
},
  "geometry": {"coordinates":[130.81926999999999,32.79177],"type":"Point"}
}