{
  "type": "Feature",
  "properties": {
    "gn:admin1_code":"7.0",
    "gn:admin2_code":"7407413.0",
    "gn:asciiname":"Ushikuma-kitaku",
    "gn:country_code":"JP",
    "gn:dem":48,
    "gn:feature_class":"P",
    "gn:feature_code":"PPLL",
    "gn:name":"Ushikuma-kitaku",
    "gn:population":0,
    "gn:timezone":"Asia/Tokyo",
    "iso:country":"JP",
    "name:jpn_x_preferred":[
        "\u725b\u9688\u5317\u533a"
    ],
    "wof:name":"Ushikuma-kitaku",
    "wof:placetype":"locality"
},
  "geometry": {"coordinates":[130.72256000000002,33.57505],"type":"Point"}
}