{
  "type": "Feature",
  "properties": {
    "iso:country":"JP",
    "name:jpn_x_preferred":[
        "\uff08\u4e01\u76ee\u306a\u3057\uff09"
    ],
    "qs:gn_local":0,
    "qs:local_max":4429,
    "qs:local_sum":11099,
    "qs:localhoods":16,
    "qs:name":"\uff08\u4e01\u76ee\u306a\u3057\uff09",
    "qs:name_adm0":"\u65e5\u672c",
    "qs:name_adm1":"\u5175\u5eab\u770c",
    "qs:name_lau":"\u795e\u5c4b\u753a",
    "qs:name_local":"\u59eb\u8def\u5e02",
    "qs:photo_max":100,
    "qs:photo_sum":1087,
    "qs:placetype":"Suburb",
    "qs:quad_count":30,
    "qs:woe_adm0":23424856,
    "qs:woe_adm1":2345862,
    "qs:woe_adm2":0,
    "qs:woe_lau":28461431,
    "qs:woe_local":1117200,
    "qs:woe_ver":"7.10.0",
    "wof:lang":[
        "jpn"
    ],
    "wof:name":"\uff08\u4e01\u76ee\u306a\u3057\uff09",
    "wof:placetype":"neighbourhood"
},
  "geometry": {"coordinates":[134.69432399999999,34.829827],"type":"Point"}
}