{
  "type": "Feature",
  "properties": {
    "gn:admin1_code":"26",
    "gn:admin2_code":"1856209.0",
    "gn:asciiname":"Nakajo",
    "gn:country_code":"JP",
    "gn:dem":452,
    "gn:feature_class":"P",
    "gn:feature_code":"PPL",
    "gn:name":"Nakaj\u014d",
    "gn:population":0,
    "gn:timezone":"Asia/Tokyo",
    "iso:country":"JP",
    "name:jpn_x_preferred":[
        "\u4e2d\u6761"
    ],
    "name:und_x_variant":[
        "Kakaj\u014d",
        "Nakaj\u014d"
    ],
    "wof:name":"Nakajo",
    "wof:placetype":"locality"
},
  "geometry": {"coordinates":[138.03327999999999,36.60853],"type":"Point"}
}