{
  "type": "Feature",
  "properties": {
    "gn:admin1_code":"27",
    "gn:admin2_code":"1852895.0",
    "gn:asciiname":"Haiki",
    "gn:country_code":"JP",
    "gn:dem":7,
    "gn:feature_class":"P",
    "gn:feature_code":"PPL",
    "gn:name":"Haiki",
    "gn:population":0,
    "gn:timezone":"Asia/Tokyo",
    "iso:country":"JP",
    "name:jpn_x_preferred":[
        "\u65e9\u5c90"
    ],
    "name:und_x_variant":[
        "Hayaki",
        "Haikich\u014d",
        "Haiki"
    ],
    "wof:name":"Haiki",
    "wof:placetype":"locality"
},
  "geometry": {"coordinates":[129.79499999999999,33.13952],"type":"Point"}
}