{
  "type": "Feature",
  "properties": {
    "gn:admin1_code":"31",
    "gn:admin2_code":"1850741.0",
    "gn:asciiname":"Hachihamacho-hachihama",
    "gn:country_code":"JP",
    "gn:dem":3,
    "gn:feature_class":"P",
    "gn:feature_code":"PPL",
    "gn:name":"Hachihamach\u014d-hachihama",
    "gn:population":0,
    "gn:timezone":"Asia/Tokyo",
    "iso:country":"JP",
    "name:jpn_x_preferred":[
        "\u516b\u6d5c\u753a\u516b\u6d5c"
    ],
    "name:und_x_variant":[
        "Hachibama",
        "Hachihama",
        "Hachihamach\u014d-hachihama"
    ],
    "wof:name":"Hachihamacho-hachihama",
    "wof:placetype":"locality"
},
  "geometry": {"coordinates":[133.94361000000001,34.55286],"type":"Point"}
}