{
  "type": "Feature",
  "properties": {
    "iso:country":"JP",
    "label:eng_x_preferred_longname":[
        "Shobu Town"
    ],
    "label:eng_x_preferred_placetype":[
        "town"
    ],
    "name:eng_x_preferred":[
        "Shobu"
    ],
    "name:eng_x_variant":[
        "Shobu Town"
    ],
    "name:jpn_x_preferred":[
        "\u83d6\u84b2\u753a"
    ],
    "qs:name":"\u83d6\u84b2\u753a",
    "qs:name_adm0":"\u65e5\u672c",
    "qs:name_adm1":"\u57fc\u7389\u770c",
    "qs:photos":101,
    "qs:photos_1k":20,
    "qs:photos_9k":1,
    "qs:photos_9r":3,
    "qs:photos_all":101,
    "qs:photos_sr":3,
    "qs:placetype":"Town",
    "qs:pop_sr":"0",
    "wof:name":"Shobu",
    "wof:placetype":"locality"
},
  "geometry": {"coordinates":[139.600021,36.058181],"type":"Point"}
}