{
  "type": "Feature",
  "properties": {
    "gn:admin1_code":"34.0",
    "gn:admin2_code":"1864030.0",
    "gn:asciiname":"Kokusaiji",
    "gn:country_code":"JP",
    "gn:dem":41,
    "gn:feature_class":"P",
    "gn:feature_code":"PPL",
    "gn:name":"Kokusaiji",
    "gn:population":0,
    "gn:timezone":"Asia/Tokyo",
    "iso:country":"JP",
    "name:jpn_x_preferred":[
        "\u56fd\u6e08\u5bfa"
    ],
    "wof:name":"Kokusaiji",
    "wof:placetype":"locality"
},
  "geometry": {"coordinates":[139.30151000000001,36.19008],"type":"Point"}
}