{
  "type": "Feature",
  "properties": {
    "gn:admin1_code":"29.0",
    "gn:admin2_code":"1855427.0",
    "gn:admin3_code":"15102.0",
    "gn:asciiname":"Matsusaki",
    "gn:country_code":"JP",
    "gn:dem":1,
    "gn:feature_class":"P",
    "gn:feature_code":"PPL",
    "gn:name":"Matsusaki",
    "gn:population":0,
    "gn:timezone":"Asia/Tokyo",
    "iso:country":"JP",
    "name:jpn_x_preferred":[
        "\u677e\u5d0e"
    ],
    "wof:name":"Matsusaki",
    "wof:placetype":"locality"
},
  "geometry": {"coordinates":[139.1164,37.93567],"type":"Point"}
}