{
  "type": "Feature",
  "properties": {
    "gn:admin1_code":"12.0",
    "gn:admin2_code":"7428076.0",
    "gn:admin3_code":"1564.0",
    "gn:asciiname":"Memanbetsu-daito",
    "gn:country_code":"JP",
    "gn:dem":35,
    "gn:feature_class":"P",
    "gn:feature_code":"PPL",
    "gn:name":"Memanbetsu-dait\u014d",
    "gn:population":0,
    "gn:timezone":"Asia/Tokyo",
    "iso:country":"JP",
    "name:jpn_x_preferred":[
        "\u5973\u6e80\u5225\u5927\u6771"
    ],
    "name:jpn_x_variant":[
        "\u3081\u307e\u3093\u3079\u3064\u3060\u3044\u3068\u3046",
        "\u30e1\u30de\u30f3\u30d9\u30c4\u30c0\u30a4\u30c8\u30a6"
    ],
    "name:und_x_variant":[
        "Higashi-memabetsu",
        "Higashi-memambetsu",
        "Dait\u014d",
        "Memanbetsu-dait\u014d"
    ],
    "wof:name":"Memanbetsu-daito",
    "wof:placetype":"locality"
},
  "geometry": {"coordinates":[144.18029999999999,43.88201],"type":"Point"}
}