{
  "type": "Feature",
  "properties": {
    "gn:admin1_code":"7.0",
    "gn:admin2_code":"1859874.0",
    "gn:admin3_code":"40342.0",
    "gn:asciiname":"Jinnoki",
    "gn:country_code":"JP",
    "gn:dem":33,
    "gn:feature_class":"P",
    "gn:feature_code":"PPLL",
    "gn:name":"Jinnoki",
    "gn:population":0,
    "gn:timezone":"Asia/Tokyo",
    "iso:country":"JP",
    "name:jpn_x_preferred":[
        "\u795e\u30ce\u6728"
    ],
    "wof:name":"Jinnoki",
    "wof:placetype":"locality"
},
  "geometry": {"coordinates":[130.50816,33.61662],"type":"Point"}
}