{
  "type": "Feature",
  "properties": {
    "gn:admin1_code":"13",
    "gn:admin2_code":"1862625.0",
    "gn:asciiname":"Nibuno",
    "gn:country_code":"JP",
    "gn:dem":34,
    "gn:feature_class":"P",
    "gn:feature_code":"PPL",
    "gn:name":"Nibuno",
    "gn:population":0,
    "gn:timezone":"Asia/Tokyo",
    "iso:country":"JP",
    "name:jpn_x_preferred":[
        "\u4ec1\u8c4a\u91ce"
    ],
    "wof:name":"Nibuno",
    "wof:placetype":"locality"
},
  "geometry": {"coordinates":[134.72799999999998,34.88315],"type":"Point"}
}