{
  "type": "Feature",
  "properties": {
    "gn:admin1_code":"2.0",
    "gn:admin2_code":"2113122.0",
    "gn:asciiname":"Hiroomote",
    "gn:country_code":"JP",
    "gn:dem":10,
    "gn:feature_class":"P",
    "gn:feature_code":"PPL",
    "gn:name":"Hiroomote",
    "gn:population":0,
    "gn:timezone":"Asia/Tokyo",
    "iso:country":"JP",
    "name:jpn_x_preferred":[
        "\u5e83\u9762"
    ],
    "name:jpn_x_variant":[
        "\u3072\u308d\u304a\u3082\u3066",
        "\u30d2\u30ed\u30aa\u30e2\u30c6"
    ],
    "wof:name":"Hiroomote",
    "wof:placetype":"locality"
},
  "geometry": {"coordinates":[140.14578999999998,39.7176],"type":"Point"}
}