{
  "type": "Feature",
  "properties": {
    "gn:admin1_code":"21.0",
    "gn:admin2_code":"1864975.0",
    "gn:admin3_code":"43424.0",
    "gn:asciiname":"Sakashita",
    "gn:country_code":"JP",
    "gn:dem":405,
    "gn:feature_class":"P",
    "gn:feature_code":"PPLL",
    "gn:name":"Sakashita",
    "gn:population":0,
    "gn:timezone":"Asia/Tokyo",
    "iso:country":"JP",
    "name:jpn_x_preferred":[
        "\u5742\u4e0b"
    ],
    "name:jpn_x_variant":[
        "\u3055\u304b\u3057\u305f",
        "\u30b5\u30ab\u30b7\u30bf"
    ],
    "wof:name":"Sakashita",
    "wof:placetype":"locality"
},
  "geometry": {"coordinates":[131.05674999999999,33.14943],"type":"Point"}
}