{
  "type": "Feature",
  "properties": {
    "gn:admin1_code":"34.0",
    "gn:admin2_code":"1849187.0",
    "gn:admin3_code":"11110.0",
    "gn:asciiname":"Higashiiwatsuki",
    "gn:country_code":"JP",
    "gn:dem":10,
    "gn:feature_class":"P",
    "gn:feature_code":"PPL",
    "gn:name":"Higashiiwatsuki",
    "gn:population":0,
    "gn:timezone":"Asia/Tokyo",
    "iso:country":"JP",
    "name:jpn_x_preferred":[
        "\u6771\u5ca9\u69fb"
    ],
    "name:jpn_x_variant":[
        "\u3072\u304c\u3057\u3044\u308f\u3064\u304d",
        "\u30d2\u30ac\u30b7\u30a4\u30ef\u30c4\u30ad"
    ],
    "wof:name":"Higashiiwatsuki",
    "wof:placetype":"locality"
},
  "geometry": {"coordinates":[139.71095,35.9621],"type":"Point"}
}