{
  "type": "Feature",
  "properties": {
    "gn:admin1_code":"13",
    "gn:admin2_code":"1865406.0",
    "gn:asciiname":"Nakahiro",
    "gn:country_code":"JP",
    "gn:dem":5,
    "gn:feature_class":"P",
    "gn:feature_code":"PPL",
    "gn:name":"Nakahiro",
    "gn:population":0,
    "gn:timezone":"Asia/Tokyo",
    "iso:country":"JP",
    "name:jpn_x_preferred":[
        "\u4e2d\u5e83"
    ],
    "wof:name":"Nakahiro",
    "wof:placetype":"locality"
},
  "geometry": {"coordinates":[134.39478,34.74882],"type":"Point"}
}