{
  "type": "Feature",
  "properties": {
    "gn:admin1_code":"47",
    "gn:admin2_code":"1852456.0",
    "gn:admin3_code":"47361.0",
    "gn:asciiname":"Nakachi",
    "gn:country_code":"JP",
    "gn:dem":78,
    "gn:feature_class":"P",
    "gn:feature_code":"PPL",
    "gn:name":"Nakachi",
    "gn:population":0,
    "gn:timezone":"Asia/Tokyo",
    "iso:country":"JP",
    "name:jpn_x_preferred":[
        "\u4ef2\u5730"
    ],
    "name:jpn_x_variant":[
        "\u306a\u304b\u3061",
        "\u30ca\u30ab\u30c1"
    ],
    "wof:name":"Nakachi",
    "wof:placetype":"locality"
},
  "geometry": {"coordinates":[126.74478999999999,26.3655],"type":"Point"}
}