{
  "type": "Feature",
  "properties": {
    "gn:admin1_code":"29.0",
    "gn:admin2_code":"1859907.0",
    "gn:asciiname":"Nishiyamacho-sakata",
    "gn:country_code":"JP",
    "gn:dem":35,
    "gn:feature_class":"P",
    "gn:feature_code":"PPL",
    "gn:name":"Nishiyamach\u014d-sakata",
    "gn:population":0,
    "gn:timezone":"Asia/Tokyo",
    "iso:country":"JP",
    "name:jpn_x_preferred":[
        "\u897f\u5c71\u753a\u5742\u7530"
    ],
    "name:und_x_variant":[
        "Nishiyamach\u014d-sakata"
    ],
    "wof:name":"Nishiyamacho-sakata",
    "wof:placetype":"locality"
},
  "geometry": {"coordinates":[138.66566,37.44746],"type":"Point"}
}