{
  "type": "Feature",
  "properties": {
    "gn:admin1_code":"3.0",
    "gn:admin2_code":"2130225.0",
    "gn:asciiname":"Kanagicho-kanbara",
    "gn:country_code":"JP",
    "gn:dem":6,
    "gn:feature_class":"P",
    "gn:feature_code":"PPL",
    "gn:name":"Kanagich\u014d-kanbara",
    "gn:population":0,
    "gn:timezone":"Asia/Tokyo",
    "iso:country":"JP",
    "name:jpn_x_preferred":[
        "\u91d1\u6728\u753a\u795e\u539f"
    ],
    "name:jpn_x_variant":[
        "\u304b\u306a\u304e\u3061\u3087\u3046\u304b\u3093\u3070\u3089",
        "\u30ab\u30ca\u30ae\u30c1\u30e7\u30a6\u30ab\u30f3\u30d0\u30e9"
    ],
    "name:und_x_variant":[
        "Kanagich\u014d-kanbara"
    ],
    "wof:name":"Kanagicho-kanbara",
    "wof:placetype":"locality"
},
  "geometry": {"coordinates":[140.41911000000002,40.91348],"type":"Point"}
}