{
  "type": "Feature",
  "properties": {
    "gn:admin1_code":"21.0",
    "gn:admin2_code":"1865358.0",
    "gn:asciiname":"Bonotsuru",
    "gn:country_code":"JP",
    "gn:dem":40,
    "gn:feature_class":"P",
    "gn:feature_code":"PPLL",
    "gn:name":"B\u014dnotsuru",
    "gn:population":0,
    "gn:timezone":"Asia/Tokyo",
    "iso:country":"JP",
    "name:jpn_x_preferred":[
        "\u68d2\u306e\u9db4"
    ],
    "name:jpn_x_variant":[
        "\u307c\u3046\u306e\u3064\u308b",
        "\u30dc\u30a6\u30ce\u30c4\u30eb"
    ],
    "name:und_x_variant":[
        "B\u014dnotsuru"
    ],
    "wof:name":"Bonotsuru",
    "wof:placetype":"locality"
},
  "geometry": {"coordinates":[130.17161999999999,32.36863],"type":"Point"}
}