{
  "type": "Feature",
  "properties": {
    "iso:country":"JP",
    "name:eng_x_preferred":[
        "Ichikawa Misato"
    ],
    "name:eng_x_variant":[
        "Ichikawa Misato Town"
    ],
    "name:jpn_x_preferred":[
        "\u5e02\u5ddd\u4e09\u90f7\u753a"
    ],
    "qs:name":"\u5e02\u5ddd\u4e09\u90f7\u753a",
    "qs:name_adm0":"\u65e5\u672c",
    "qs:name_adm1":"\u5c71\u68a8\u770c",
    "qs:photos":99,
    "qs:photos_1k":20,
    "qs:photos_9k":1,
    "qs:photos_9r":3,
    "qs:photos_all":99,
    "qs:photos_sr":3,
    "qs:placetype":"Town",
    "qs:pop_sr":"0",
    "wof:name":"Ichikawa Misato",
    "wof:placetype":"locality"
},
  "geometry": {"coordinates":[138.517427,35.538639],"type":"Point"}
}