{
  "type": "Feature",
  "properties": {
    "gn:admin1_code":"2.0",
    "gn:admin2_code":"2113122.0",
    "gn:asciiname":"Tsukinoki",
    "gn:country_code":"JP",
    "gn:dem":16,
    "gn:feature_class":"P",
    "gn:feature_code":"PPL",
    "gn:name":"Tsukinoki",
    "gn:population":0,
    "gn:timezone":"Asia/Tokyo",
    "iso:country":"JP",
    "name:jpn_x_preferred":[
        "\u69fb\u30ce\u6728"
    ],
    "name:jpn_x_variant":[
        "\u3064\u3061\u306e\u304d",
        "\u30c4\u30c1\u30ce\u30ad"
    ],
    "wof:name":"Tsukinoki",
    "wof:placetype":"locality"
},
  "geometry": {"coordinates":[140.09788999999998,39.79393],"type":"Point"}
}