{
  "type": "Feature",
  "properties": {
    "gn:admin1_code":"4.0",
    "gn:admin2_code":"1857552.0",
    "gn:asciiname":"Kushizaki-minamicho",
    "gn:country_code":"JP",
    "gn:dem":26,
    "gn:feature_class":"P",
    "gn:feature_code":"PPL",
    "gn:name":"Kushizaki-minamich\u014d",
    "gn:population":0,
    "gn:timezone":"Asia/Tokyo",
    "iso:country":"JP",
    "name:jpn_x_preferred":[
        "\u4e32\u5d0e\u5357\u753a"
    ],
    "name:und_x_variant":[
        "Kushizaki-minamich\u014d"
    ],
    "wof:name":"Kushizaki-minamicho",
    "wof:placetype":"locality"
},
  "geometry": {"coordinates":[139.96142,35.77697],"type":"Point"}
}