{
  "type": "Feature",
  "properties": {
    "gn:admin1_code":"16.0",
    "gn:admin2_code":"2112223.0",
    "gn:asciiname":"Nakaosekigawa",
    "gn:country_code":"JP",
    "gn:dem":87,
    "gn:feature_class":"P",
    "gn:feature_code":"PPL",
    "gn:name":"Naka\u014dsekigawa",
    "gn:population":0,
    "gn:timezone":"Asia/Tokyo",
    "iso:country":"JP",
    "name:jpn_x_preferred":[
        "\u4e2d\u5927\u5830\u5ddd"
    ],
    "name:jpn_x_variant":[
        "\u306a\u304b\u304a\u304a\u305b\u304d\u304c\u308f",
        "\u30ca\u30ab\u30aa\u30aa\u30bb\u30ad\u30ac\u30ef"
    ],
    "name:und_x_variant":[
        "Naka\u014dsekigawa"
    ],
    "wof:name":"Nakaosekigawa",
    "wof:placetype":"locality"
},
  "geometry": {"coordinates":[141.1112,39.33438],"type":"Point"}
}