{
  "type": "Feature",
  "properties": {
    "gn:admin1_code":"21.0",
    "gn:admin2_code":"7412708.0",
    "gn:admin3_code":"43505.0",
    "gn:asciiname":"Hiratani",
    "gn:country_code":"JP",
    "gn:dem":519,
    "gn:feature_class":"P",
    "gn:feature_code":"PPLL",
    "gn:name":"Hiratani",
    "gn:population":0,
    "gn:timezone":"Asia/Tokyo",
    "iso:country":"JP",
    "name:jpn_x_preferred":[
        "\u5e73\u8c37"
    ],
    "name:jpn_x_variant":[
        "\u3072\u3089\u305f\u306b",
        "\u30d2\u30e9\u30bf\u30cb"
    ],
    "wof:name":"Hiratani",
    "wof:placetype":"locality"
},
  "geometry": {"coordinates":[131.01823000000002,32.20064],"type":"Point"}
}