{
  "type": "Feature",
  "properties": {
    "gn:admin1_code":"11.0",
    "gn:admin2_code":"7372275.0",
    "gn:asciiname":"Shimoshakuta",
    "gn:country_code":"JP",
    "gn:dem":703,
    "gn:feature_class":"P",
    "gn:feature_code":"PPL",
    "gn:name":"Shimoshakuta",
    "gn:population":0,
    "gn:timezone":"Asia/Tokyo",
    "iso:country":"JP",
    "name:jpn_x_preferred":[
        "\u4e0b\u5c3a\u7530"
    ],
    "wof:name":"Shimoshakuta",
    "wof:placetype":"locality"
},
  "geometry": {"coordinates":[133.08903999999998,35.01371],"type":"Point"}
}