{
  "type": "Feature",
  "properties": {
    "gn:admin1_code":"18",
    "gn:admin2_code":"1855201.0",
    "gn:asciiname":"Ban'yamine",
    "gn:country_code":"JP",
    "gn:dem":221,
    "gn:feature_class":"P",
    "gn:feature_code":"PPLL",
    "gn:name":"Ban\u2019yamine",
    "gn:population":0,
    "gn:timezone":"Asia/Tokyo",
    "iso:country":"JP",
    "name:jpn_x_preferred":[
        "\u756a\u5c4b\u5cef\u3000"
    ],
    "name:und_x_variant":[
        "Iwayamine",
        "Banyamine",
        "Banyagamine",
        "Ban\u2019yamine"
    ],
    "wof:name":"Ban'yamine",
    "wof:placetype":"locality"
},
  "geometry": {"coordinates":[130.98513,30.65991],"type":"Point"}
}