{
  "type": "Feature",
  "properties": {
    "gn:admin1_code":"16.0",
    "gn:admin2_code":"2112822.0",
    "gn:asciiname":"Towacho-sago",
    "gn:country_code":"JP",
    "gn:dem":175,
    "gn:feature_class":"P",
    "gn:feature_code":"PPL",
    "gn:name":"T\u014dwach\u014d-sago",
    "gn:population":0,
    "gn:timezone":"Asia/Tokyo",
    "iso:country":"JP",
    "name:jpn_x_preferred":[
        "\u6771\u548c\u753a\u7802\u5b50"
    ],
    "name:jpn_x_variant":[
        "\u3068\u3046\u308f\u3061\u3087\u3046\u3055\u3054",
        "\u30c8\u30a6\u30ef\u30c1\u30e7\u30a6\u30b5\u30b4"
    ],
    "name:und_x_variant":[
        "T\u014dwach\u014d-sago"
    ],
    "wof:name":"Towacho-sago",
    "wof:placetype":"locality"
},
  "geometry": {"coordinates":[141.25656000000001,39.34087],"type":"Point"}
}