{
  "type": "Feature",
  "properties": {
    "gn:admin1_code":"2.0",
    "gn:admin2_code":"2113122.0",
    "gn:asciiname":"Tosantai",
    "gn:country_code":"JP",
    "gn:dem":82,
    "gn:feature_class":"P",
    "gn:feature_code":"PPL",
    "gn:name":"Tosantai",
    "gn:population":0,
    "gn:timezone":"Asia/Tokyo",
    "iso:country":"JP",
    "name:jpn_x_preferred":[
        "\u5341\u4e09\u5cb1"
    ],
    "wof:name":"Tosantai",
    "wof:placetype":"locality"
},
  "geometry": {"coordinates":[140.27940000000001,39.72937],"type":"Point"}
}