{
  "type": "Feature",
  "properties": {
    "gn:admin1_code":"34.0",
    "gn:admin2_code":"7464124.0",
    "gn:asciiname":"Shobucho-obayashi",
    "gn:country_code":"JP",
    "gn:dem":12,
    "gn:feature_class":"P",
    "gn:feature_code":"PPL",
    "gn:name":"Sh\u014dbuch\u014d-obayashi",
    "gn:population":0,
    "gn:timezone":"Asia/Tokyo",
    "iso:country":"JP",
    "name:jpn_x_preferred":[
        "\u83d6\u84b2\u753a\u5c0f\u6797"
    ],
    "name:jpn_x_variant":[
        "\u3057\u3087\u3046\u3076\u3061\u3087\u3046\u304a\u3070\u3084\u3057",
        "\u30b7\u30e7\u30a6\u30d6\u30c1\u30e7\u30a6\u30aa\u30d0\u30e4\u30b7"
    ],
    "name:und_x_variant":[
        "Sh\u014dbuch\u014d-obayashi"
    ],
    "wof:name":"Shobucho-obayashi",
    "wof:placetype":"locality"
},
  "geometry": {"coordinates":[139.58108999999999,36.05676],"type":"Point"}
}