{
  "type": "Feature",
  "properties": {
    "gn:admin1_code":"09",
    "gn:asciiname":"Kurisu",
    "gn:cc2":"JP",
    "gn:country_code":"JP",
    "gn:dem":140,
    "gn:feature_class":"P",
    "gn:feature_code":"PPL",
    "gn:name":"Kurisu",
    "gn:population":0,
    "gn:timezone":"Asia/Tokyo",
    "iso:country":"JP",
    "name:und_x_variant":[
        "Kurusu",
        "Kurisu"
    ],
    "wof:name":"Kurisu",
    "wof:placetype":"locality"
},
  "geometry": {"coordinates":[136.96666999999999,35.41667],"type":"Point"}
}