{
  "type": "Feature",
  "properties": {
    "gn:admin1_code":"3.0",
    "gn:admin2_code":"2130654.0",
    "gn:asciiname":"Nakamachi",
    "gn:country_code":"JP",
    "gn:dem":28,
    "gn:feature_class":"P",
    "gn:feature_code":"PPL",
    "gn:name":"Nakamachi",
    "gn:population":0,
    "gn:timezone":"Asia/Tokyo",
    "iso:country":"JP",
    "name:jpn_x_preferred":[
        "\u4ef2\u753a"
    ],
    "name:jpn_x_variant":[
        "\u306a\u304b\u307e\u3061",
        "\u30ca\u30ab\u30de\u30c1"
    ],
    "wof:name":"Nakamachi",
    "wof:placetype":"locality"
},
  "geometry": {"coordinates":[140.59079,40.71226],"type":"Point"}
}