{
  "type": "Feature",
  "properties": {
    "gn:admin1_code":"29.0",
    "gn:admin2_code":"7468177.0",
    "gn:asciiname":"Imoji",
    "gn:country_code":"JP",
    "gn:dem":41,
    "gn:feature_class":"P",
    "gn:feature_code":"PPL",
    "gn:name":"Imoji",
    "gn:population":0,
    "gn:timezone":"Asia/Tokyo",
    "iso:country":"JP",
    "name:jpn_x_preferred":[
        "\u92f3\u7269\u5e2b"
    ],
    "wof:name":"Imoji",
    "wof:placetype":"locality"
},
  "geometry": {"coordinates":[139.52692999999999,38.20496],"type":"Point"}
}