{
  "type": "Feature",
  "properties": {
    "gn:admin1_code":"4.0",
    "gn:admin2_code":"7465524.0",
    "gn:asciiname":"Shiota",
    "gn:country_code":"JP",
    "gn:dem":3,
    "gn:feature_class":"P",
    "gn:feature_code":"PPLL",
    "gn:name":"Shiota",
    "gn:population":0,
    "gn:timezone":"Asia/Tokyo",
    "iso:country":"JP",
    "name:jpn_x_preferred":[
        "\u5869\u7530"
    ],
    "name:jpn_x_variant":[
        "\u3057\u304a\u305f",
        "\u30b7\u30aa\u30bf"
    ],
    "wof:name":"Shiota",
    "wof:placetype":"locality"
},
  "geometry": {"coordinates":[140.39664999999999,35.25583],"type":"Point"}
}