{
  "type": "Feature",
  "properties": {
    "gn:admin1_code":"6.0",
    "gn:admin2_code":"1849587.0",
    "gn:asciiname":"Shiraki",
    "gn:country_code":"JP",
    "gn:dem":6,
    "gn:feature_class":"P",
    "gn:feature_code":"PPL",
    "gn:name":"Shiraki",
    "gn:population":0,
    "gn:timezone":"Asia/Tokyo",
    "iso:country":"JP",
    "wof:name":"Shiraki",
    "wof:placetype":"locality"
},
  "geometry": {"coordinates":[135.97713999999999,35.73174],"type":"Point"}
}