{
  "type": "Feature",
  "properties": {
    "gn:admin1_code":"12.0",
    "gn:admin2_code":"2129370.0",
    "gn:asciiname":"Horikawacho",
    "gn:country_code":"JP",
    "gn:dem":2,
    "gn:feature_class":"P",
    "gn:feature_code":"PPL",
    "gn:name":"Horikawach\u014d",
    "gn:population":0,
    "gn:timezone":"Asia/Tokyo",
    "iso:country":"JP",
    "name:jpn_x_preferred":[
        "\u5800\u5ddd\u753a"
    ],
    "name:jpn_x_variant":[
        "\u307b\u308a\u304b\u308f\u3061\u3087\u3046",
        "\u30db\u30ea\u30ab\u30ef\u30c1\u30e7\u30a6"
    ],
    "name:und_x_variant":[
        "Horikawach\u014d"
    ],
    "wof:name":"Horikawacho",
    "wof:placetype":"locality"
},
  "geometry": {"coordinates":[144.39429999999999,42.99638],"type":"Point"}
}