{
  "type": "Feature",
  "properties": {
    "gn:admin1_code":"4.0",
    "gn:admin2_code":"1859468.0",
    "gn:asciiname":"Nishisakada",
    "gn:country_code":"JP",
    "gn:dem":9,
    "gn:feature_class":"P",
    "gn:feature_code":"PPL",
    "gn:name":"Nishisakada",
    "gn:population":0,
    "gn:timezone":"Asia/Tokyo",
    "iso:country":"JP",
    "name:jpn_x_preferred":[
        "\u897f\u5742\u7530"
    ],
    "name:jpn_x_variant":[
        "\u306b\u3057\u3055\u304b\u3060",
        "\u30cb\u30b7\u30b5\u30ab\u30c0"
    ],
    "wof:name":"Nishisakada",
    "wof:placetype":"locality"
},
  "geometry": {"coordinates":[139.88583,35.33857000000001],"type":"Point"}
}