{
  "type": "Feature",
  "properties": {
    "gn:admin1_code":"2.0",
    "gn:admin2_code":"9035660.0",
    "gn:asciiname":"Kakunodatemachi-shiraiwa",
    "gn:country_code":"JP",
    "gn:dem":97,
    "gn:feature_class":"P",
    "gn:feature_code":"PPL",
    "gn:name":"Kakunodatemachi-shiraiwa",
    "gn:population":0,
    "gn:timezone":"Asia/Tokyo",
    "iso:country":"JP",
    "name:jpn_x_preferred":[
        "\u89d2\u9928\u753a\u767d\u5ca9"
    ],
    "wof:name":"Kakunodatemachi-shiraiwa",
    "wof:placetype":"locality"
},
  "geometry": {"coordinates":[140.61439999999999,39.58872],"type":"Point"}
}