{
  "type": "Feature",
  "properties": {
    "gn:admin1_code":"16.0",
    "gn:admin2_code":"11497023.0",
    "gn:admin3_code":"3381.0",
    "gn:asciiname":"Futsukamachi",
    "gn:country_code":"JP",
    "gn:dem":125,
    "gn:feature_class":"P",
    "gn:feature_code":"PPL",
    "gn:name":"Futsukamachi",
    "gn:population":0,
    "gn:timezone":"Asia/Tokyo",
    "iso:country":"JP",
    "name:jpn_x_preferred":[
        "\u4e8c\u65e5\u753a"
    ],
    "wof:name":"Futsukamachi",
    "wof:placetype":"locality"
},
  "geometry": {"coordinates":[141.05359000000001,39.24052],"type":"Point"}
}