{
  "type": "Feature",
  "properties": {
    "gn:admin1_code":"7.0",
    "gn:admin2_code":"1856443.0",
    "gn:asciiname":"Kyodomari",
    "gn:country_code":"JP",
    "gn:dem":6,
    "gn:feature_class":"P",
    "gn:feature_code":"PPLL",
    "gn:name":"Ky\u014ddomari",
    "gn:population":0,
    "gn:timezone":"Asia/Tokyo",
    "iso:country":"JP",
    "name:jpn_x_preferred":[
        "\u4eac\u6cca"
    ],
    "name:und_x_variant":[
        "Ky\u014ddomari"
    ],
    "wof:name":"Kyodomari",
    "wof:placetype":"locality"
},
  "geometry": {"coordinates":[130.52930000000001,33.88648],"type":"Point"}
}