{
  "type": "Feature",
  "properties": {
    "iso:country":"JP",
    "name:jpn_x_preferred":[
        "\uff08\u4e01\u76ee\u306a\u3057\uff09"
    ],
    "qs:gn_adm0_cc":"JP",
    "qs:gn_local":1858729,
    "qs:gn_nam_loc":"\u8d8a\u8c37\u5e02, \u57fc\u7389\u770c, JP",
    "qs:gn_namadm1":"34",
    "qs:local_max":49,
    "qs:local_sum":168,
    "qs:localhoods":7,
    "qs:name":"\uff08\u4e01\u76ee\u306a\u3057\uff09",
    "qs:name_adm0":"\u65e5\u672c",
    "qs:name_adm1":"\u57fc\u7389\u770c",
    "qs:name_lau":"\u5927\u6ca2",
    "qs:name_local":"\u8d8a\u8c37\u5e02",
    "qs:photo_max":3,
    "qs:photo_sum":6,
    "qs:placetype":"Suburb",
    "qs:quad_count":3,
    "qs:woe_adm0":23424856,
    "qs:woe_adm1":2345883,
    "qs:woe_adm2":0,
    "qs:woe_lau":28409197,
    "qs:woe_local":1117577,
    "qs:woe_ver":"7.10.0",
    "wof:lang":[
        "jpn"
    ],
    "wof:name":"\uff08\u4e01\u76ee\u306a\u3057\uff09",
    "wof:placetype":"neighbourhood"
},
  "geometry": {"coordinates":[139.78729200000001,35.915007],"type":"Point"}
}