{
  "type": "Feature",
  "properties": {
    "gn:admin1_code":"21",
    "gn:admin2_code":"1865358.0",
    "gn:asciiname":"Itsuwamachi-oniike",
    "gn:country_code":"JP",
    "gn:dem":24,
    "gn:feature_class":"P",
    "gn:feature_code":"PPL",
    "gn:name":"Itsuwamachi-oniike",
    "gn:population":0,
    "gn:timezone":"Asia/Tokyo",
    "iso:country":"JP",
    "name:jpn_x_preferred":[
        "\u4e94\u548c\u753a\u9b3c\u6c60"
    ],
    "name:jpn_x_variant":[
        "\u3044\u3064\u308f\u307e\u3061\u304a\u306b\u3044\u3051",
        "\u30a4\u30c4\u30ef\u30de\u30c1\u30aa\u30cb\u30a4\u30b1"
    ],
    "name:und_x_variant":[
        "Oninoike",
        "Oniike",
        "Itsuwamachi-oniike"
    ],
    "wof:name":"Itsuwamachi-oniike",
    "wof:placetype":"locality"
},
  "geometry": {"coordinates":[130.1754,32.54503],"type":"Point"}
}