{
  "type": "Feature",
  "properties": {
    "iso:country":"JP",
    "name:eng_x_preferred":[
        "Akamine 2 Chome"
    ],
    "name:eng_x_variant":[
        "Akamine 2 Choume",
        "Akamine 2 Chome"
    ],
    "name:jpn_x_preferred":[
        "\uff12\u4e01\u76ee"
    ],
    "name:jpn_x_variant":[
        "\u3042\u304b\u307f\u306d \uff12\u3061\u3087\u3046\u3081",
        "\u8d64\u5dba \uff12\u4e01\u76ee",
        "\uff12\u3061\u3087\u3046\u3081"
    ],
    "qs:gn_adm0_cc":"JP",
    "qs:gn_local":1856035,
    "qs:gn_nam_loc":"\u90a3\u8987\u5e02, \u6c96\u7e04\u770c, JP",
    "qs:gn_namadm1":"47",
    "qs:local_max":23798,
    "qs:local_sum":33499,
    "qs:localhoods":35,
    "qs:name":"\uff12\u4e01\u76ee",
    "qs:name_adm0":"\u65e5\u672c",
    "qs:name_adm1":"\u6c96\u7e04\u770c",
    "qs:name_en":"Akamine 2 Chome",
    "qs:name_lau":"\u8d64\u5dba",
    "qs:name_local":"\u90a3\u8987\u5e02",
    "qs:photo_max":70,
    "qs:photo_sum":122,
    "qs:placetype":"Suburb",
    "qs:quad_count":5,
    "qs:woe_adm0":23424856,
    "qs:woe_adm1":2345896,
    "qs:woe_adm2":0,
    "qs:woe_lau":28493820,
    "qs:woe_local":1117818,
    "qs:woe_ver":"7.10.0",
    "wof:lang":[
        "jpn"
    ],
    "wof:name":"\uff12\u4e01\u76ee",
    "wof:placetype":"neighbourhood"
},
  "geometry": {"coordinates":[127.650617,26.196069],"type":"Point"}
}