{
  "type": "Feature",
  "properties": {
    "gn:admin1_code":"4.0",
    "gn:admin2_code":"8304237.0",
    "gn:asciiname":"Yuna",
    "gn:country_code":"JP",
    "gn:dem":40,
    "gn:feature_class":"P",
    "gn:feature_code":"PPLL",
    "gn:name":"Yuna",
    "gn:population":0,
    "gn:timezone":"Asia/Tokyo",
    "iso:country":"JP",
    "name:bre_x_preferred":[
        "Yuna"
    ],
    "name:ceb_x_preferred":[
        "Yuna"
    ],
    "name:chv_x_preferred":[
        "\u042e\u043d\u0430"
    ],
    "name:deu_x_preferred":[
        "Yuna"
    ],
    "name:fas_x_preferred":[
        "\u06cc\u0648\u0646\u0627"
    ],
    "name:fin_x_preferred":[
        "Yuna"
    ],
    "name:fra_x_preferred":[
        "Yuna"
    ],
    "name:jpn_x_preferred":[
        "\u6e6f\u540d"
    ],
    "name:jpn_x_variant":[
        "\u3086\u306a",
        "\u30e6\u30ca"
    ],
    "name:msa_x_preferred":[
        "Yuna"
    ],
    "name:nld_x_preferred":[
        "Yuna"
    ],
    "name:pol_x_preferred":[
        "Yuna"
    ],
    "name:rus_x_preferred":[
        "\u042e\u043d\u0430"
    ],
    "name:sqi_x_preferred":[
        "Yuna"
    ],
    "name:swe_x_preferred":[
        "Yuna"
    ],
    "wof:name":"Yuna",
    "wof:placetype":"locality"
},
  "geometry": {"coordinates":[140.05806999999999,35.35689],"type":"Point"}
}