{
  "type": "Feature",
  "properties": {
    "gn:admin1_code":"4.0",
    "gn:admin2_code":"8304237.0",
    "gn:asciiname":"Yuna",
    "gn:country_code":"JP",
    "gn:dem":40,
    "gn:feature_class":"P",
    "gn:feature_code":"PPLL",
    "gn:name":"Yuna",
    "gn:population":0,
    "gn:timezone":"Asia/Tokyo",
    "iso:country":"JP",
    "name:jpn_x_preferred":[
        "\u6e6f\u540d"
    ],
    "name:jpn_x_variant":[
        "\u3086\u306a",
        "\u30e6\u30ca"
    ],
    "wof:name":"Yuna",
    "wof:placetype":"locality"
},
  "geometry": {"coordinates":[140.05806999999999,35.35689],"type":"Point"}
}