{
  "type": "Feature",
  "properties": {
    "gn:admin1_code":"21.0",
    "gn:admin2_code":"1848441.0",
    "gn:asciiname":"Yonkumi",
    "gn:country_code":"JP",
    "gn:dem":-1,
    "gn:feature_class":"P",
    "gn:feature_code":"PPLL",
    "gn:name":"Yonkumi",
    "gn:population":0,
    "gn:timezone":"Asia/Tokyo",
    "iso:country":"JP",
    "name:jpn_x_preferred":[
        "\u56db\u7d44"
    ],
    "name:jpn_x_variant":[
        "\u3088\u3093\u304f\u307f",
        "\u30e8\u30f3\u30af\u30df"
    ],
    "wof:name":"Yonkumi",
    "wof:placetype":"locality"
},
  "geometry": {"coordinates":[130.61521000000002,32.57938],"type":"Point"}
}