{
  "type": "Feature",
  "properties": {
    "iso:country":"JP",
    "name:eng_x_preferred":[
        "Imai 1 Chome"
    ],
    "name:eng_x_variant":[
        "Imai 1 Choume",
        "Imai 1 Chome"
    ],
    "name:jpn_x_preferred":[
        "\uff11\u4e01\u76ee"
    ],
    "name:jpn_x_variant":[
        "\u3044\u307e\u3044 \uff11\u3061\u3087\u3046\u3081",
        "\u4eca\u4e95 \uff11\u4e01\u76ee",
        "\uff11\u3061\u3087\u3046\u3081"
    ],
    "qs:gn_local":0,
    "qs:local_max":542,
    "qs:local_sum":1419,
    "qs:localhoods":5,
    "qs:name":"\uff11\u4e01\u76ee",
    "qs:name_adm0":"\u65e5\u672c",
    "qs:name_adm1":"\u611b\u77e5\u770c",
    "qs:name_en":"Imai 1 Chome",
    "qs:name_lau":"\u4eca\u4e95",
    "qs:name_local":"\u72ac\u5c71\u5e02",
    "qs:photo_max":26,
    "qs:photo_sum":88,
    "qs:placetype":"Suburb",
    "qs:quad_count":7,
    "qs:woe_adm0":23424856,
    "qs:woe_adm1":2345851,
    "qs:woe_adm2":0,
    "qs:woe_lau":28443221,
    "qs:woe_local":15015456,
    "qs:woe_ver":"7.10.0",
    "wof:lang":[
        "jpn"
    ],
    "wof:name":"\uff11\u4e01\u76ee",
    "wof:placetype":"neighbourhood"
},
  "geometry": {"coordinates":[137.019364,35.374316],"type":"Point"}
}