{
  "type": "Feature",
  "properties": {
    "gn:admin1_code":"22.0",
    "gn:admin2_code":"1857906.0",
    "gn:admin3_code":"26109.0",
    "gn:asciiname":"Hazukashi",
    "gn:country_code":"JP",
    "gn:dem":12,
    "gn:feature_class":"P",
    "gn:feature_code":"PPL",
    "gn:name":"Hazukashi",
    "gn:population":0,
    "gn:timezone":"Asia/Tokyo",
    "iso:country":"JP",
    "name:jpn_x_preferred":[
        "\u7fbd\u675f\u5e2b"
    ],
    "wof:name":"Hazukashi",
    "wof:placetype":"locality"
},
  "geometry": {"coordinates":[135.72526000000002,34.92892],"type":"Point"}
}