{
  "type": "Feature",
  "properties": {
    "gn:admin1_code":"46.0",
    "gn:asciiname":"Kitagayato",
    "gn:country_code":"JP",
    "gn:dem":179,
    "gn:feature_class":"P",
    "gn:feature_code":"PPLL",
    "gn:name":"Kitagayato",
    "gn:population":0,
    "gn:timezone":"Asia/Tokyo",
    "iso:country":"JP",
    "name:jpn_x_preferred":[
        "\u5317\u30f6\u8c37\u6238"
    ],
    "wof:name":"Kitagayato",
    "wof:placetype":"locality"
},
  "geometry": {"coordinates":[138.53014999999999,35.2602],"type":"Point"}
}