{
  "type": "Feature",
  "properties": {
    "gn:admin1_code":"40.0",
    "gn:admin2_code":"1852582.0",
    "gn:asciiname":"Hachiyamacho",
    "gn:country_code":"JP",
    "gn:dem":39,
    "gn:feature_class":"P",
    "gn:feature_code":"PPL",
    "gn:name":"Hachiyamach\u014d",
    "gn:population":0,
    "gn:timezone":"Asia/Tokyo",
    "iso:country":"JP",
    "name:jpn_x_preferred":[
        "\u9262\u5c71\u753a"
    ],
    "name:und_x_variant":[
        "Hachiyamach\u014d"
    ],
    "wof:name":"Hachiyamacho",
    "wof:placetype":"locality"
},
  "geometry": {"coordinates":[139.69932,35.65139],"type":"Point"}
}