{
  "type": "Feature",
  "properties": {
    "gn:admin1_code":"40.0",
    "gn:admin2_code":"1852083.0",
    "gn:asciiname":"Arakicho",
    "gn:country_code":"JP",
    "gn:dem":34,
    "gn:feature_class":"P",
    "gn:feature_code":"PPL",
    "gn:name":"Arakich\u014d",
    "gn:population":0,
    "gn:timezone":"Asia/Tokyo",
    "iso:country":"JP",
    "name:jpn_x_preferred":[
        "\u8352\u6728\u753a"
    ],
    "name:und_x_variant":[
        "Arakich\u014d"
    ],
    "wof:name":"Arakicho",
    "wof:placetype":"locality"
},
  "geometry": {"coordinates":[139.72292999999999,35.69022000000001],"type":"Point"}
}