{
  "type": "Feature",
  "properties": {
    "gn:admin1_code":"18.0",
    "gn:admin2_code":"8300556.0",
    "gn:asciiname":"Shinchi",
    "gn:country_code":"JP",
    "gn:dem":25,
    "gn:feature_class":"P",
    "gn:feature_code":"PPLL",
    "gn:name":"Shinchi",
    "gn:population":0,
    "gn:timezone":"Asia/Tokyo",
    "iso:country":"JP",
    "name:jpn_x_preferred":[
        "\u65b0\u5730"
    ],
    "wof:name":"Shinchi",
    "wof:placetype":"locality"
},
  "geometry": {"coordinates":[130.89512999999999,31.32074],"type":"Point"}
}