{
  "type": "Feature",
  "properties": {
    "gn:admin1_code":"13.0",
    "gn:admin2_code":"1859161.0",
    "gn:admin3_code":"28109.0",
    "gn:asciiname":"Hiyodoridai",
    "gn:country_code":"JP",
    "gn:dem":265,
    "gn:feature_class":"P",
    "gn:feature_code":"PPL",
    "gn:name":"Hiyodoridai",
    "gn:population":0,
    "gn:timezone":"Asia/Tokyo",
    "iso:country":"JP",
    "name:jpn_x_preferred":[
        "\u3072\u3088\u3069\u308a\u53f0"
    ],
    "wof:name":"Hiyodoridai",
    "wof:placetype":"locality"
},
  "geometry": {"coordinates":[135.12103000000002,34.69964],"type":"Point"}
}