{
  "type": "Feature",
  "properties": {
    "gn:admin1_code":"13.0",
    "gn:admin2_code":"1861308.0",
    "gn:asciiname":"Higashiarioka",
    "gn:country_code":"JP",
    "gn:dem":8,
    "gn:feature_class":"P",
    "gn:feature_code":"PPL",
    "gn:name":"Higashiarioka",
    "gn:population":0,
    "gn:timezone":"Asia/Tokyo",
    "iso:country":"JP",
    "name:jpn_x_preferred":[
        "\u6771\u6709\u5ca1"
    ],
    "wof:name":"Higashiarioka",
    "wof:placetype":"locality"
},
  "geometry": {"coordinates":[135.42373000000001,34.77646],"type":"Point"}
}