{
  "type": "Feature",
  "properties": {
    "gn:admin1_code":"12.0",
    "gn:admin2_code":"2127732.0",
    "gn:asciiname":"Misawa",
    "gn:cc2":"JP",
    "gn:country_code":"JP",
    "gn:dem":15,
    "gn:feature_class":"P",
    "gn:feature_code":"PPL",
    "gn:name":"Misawa",
    "gn:population":0,
    "gn:timezone":"Asia/Tokyo",
    "iso:country":"JP",
    "name:jpn_x_preferred":[
        "\u7f8e\u6ca2"
    ],
    "name:und_x_variant":[
        "Bibi",
        "Misawa"
    ],
    "wof:name":"Misawa",
    "wof:placetype":"locality"
},
  "geometry": {"coordinates":[141.71666999999999,42.75],"type":"Point"}
}