{
  "type": "Feature",
  "properties": {
    "gn:admin1_code":"29.0",
    "gn:admin2_code":"7468177.0",
    "gn:asciiname":"Neya",
    "gn:country_code":"JP",
    "gn:dem":6,
    "gn:feature_class":"P",
    "gn:feature_code":"PPL",
    "gn:name":"Neya",
    "gn:population":0,
    "gn:timezone":"Asia/Tokyo",
    "iso:country":"JP",
    "name:ceb_x_preferred":[
        "Neya"
    ],
    "name:jpn_x_preferred":[
        "\u5bdd\u5c4b"
    ],
    "name:swe_x_preferred":[
        "Neya"
    ],
    "wof:name":"Neya",
    "wof:placetype":"locality"
},
  "geometry": {"coordinates":[139.51209,38.48499],"type":"Point"}
}