{
  "type": "Feature",
  "properties": {
    "iso:country":"JP",
    "name:eng_x_preferred":[
        "Kamiyacho 1 Chome"
    ],
    "name:eng_x_variant":[
        "Kamiyachou 1 Choume",
        "Kamiyacho 1 Chome"
    ],
    "name:jpn_x_preferred":[
        "\uff11\u4e01\u76ee"
    ],
    "name:jpn_x_variant":[
        "\u304b\u307f\u3084\u3061\u3087\u3046 \uff11\u3061\u3087\u3046\u3081",
        "\u7d19\u5c4b\u753a \uff11\u4e01\u76ee",
        "\uff11\u3061\u3087\u3046\u3081"
    ],
    "qs:gn_adm0_cc":"JP",
    "qs:gn_local":1862415,
    "qs:gn_nam_loc":"\u5e83\u5cf6\u5e02, \u5e83\u5cf6\u770c, JP",
    "qs:gn_namadm1":"11",
    "qs:local_max":2245,
    "qs:local_sum":19695,
    "qs:localhoods":32,
    "qs:name":"\uff11\u4e01\u76ee",
    "qs:name_adm0":"\u65e5\u672c",
    "qs:name_adm1":"\u5e83\u5cf6\u770c",
    "qs:name_adm2":"\u4e2d\u533a",
    "qs:name_en":"Kamiyacho 1 Chome",
    "qs:name_lau":"\u7d19\u5c4b\u753a",
    "qs:name_local":"\u5e83\u5cf6\u5e02",
    "qs:photo_max":274,
    "qs:photo_sum":1856,
    "qs:placetype":"Suburb",
    "qs:quad_count":38,
    "qs:woe_adm0":23424856,
    "qs:woe_adm1":2345861,
    "qs:woe_adm2":15015430,
    "qs:woe_lau":28473719,
    "qs:woe_local":1117227,
    "qs:woe_ver":"7.10.0",
    "wof:lang":[
        "jpn"
    ],
    "wof:name":"\uff11\u4e01\u76ee",
    "wof:placetype":"neighbourhood"
},
  "geometry": {"coordinates":[132.461286,34.394704],"type":"Point"}
}