{
  "type": "Feature",
  "properties": {
    "gn:admin1_code":"29",
    "gn:admin2_code":"1860992.0",
    "gn:asciiname":"Hyakkemmachi-shinden",
    "gn:cc2":"JP",
    "gn:country_code":"JP",
    "gn:dem":12,
    "gn:feature_class":"P",
    "gn:feature_code":"PPL",
    "gn:name":"Hyakkemmachi-shinden",
    "gn:population":0,
    "gn:timezone":"Asia/Tokyo",
    "iso:country":"JP",
    "name:und_x_variant":[
        "Kubiki",
        "Hyakkemmachi",
        "Hyakkemmachi-shinden"
    ],
    "wof:name":"Hyakkemmachi-shinden",
    "wof:placetype":"locality"
},
  "geometry": {"coordinates":[138.33333000000002,37.18333],"type":"Point"}
}