{
  "type": "Feature",
  "properties": {
    "gn:admin1_code":"18",
    "gn:admin2_code":"1853737.0",
    "gn:admin3_code":"46525.0",
    "gn:asciiname":"Kuji",
    "gn:cc2":"JP",
    "gn:country_code":"JP",
    "gn:dem":56,
    "gn:feature_class":"P",
    "gn:feature_code":"PPL",
    "gn:name":"Kuji",
    "gn:population":0,
    "gn:timezone":"Asia/Tokyo",
    "iso:country":"JP",
    "name:jpn_x_preferred":[
        "\u4e45\u6148"
    ],
    "name:und_x_variant":[
        "Kuzi",
        "Kuji"
    ],
    "wof:name":"Kuji",
    "wof:placetype":"locality"
},
  "geometry": {"coordinates":[129.25,28.23333],"type":"Point"}
}