{
  "type": "Feature",
  "properties": {
    "gn:admin1_code":"21.0",
    "gn:admin2_code":"7413151.0",
    "gn:asciiname":"Setaka",
    "gn:country_code":"JP",
    "gn:dem":20,
    "gn:feature_class":"P",
    "gn:feature_code":"PPLL",
    "gn:name":"Setaka",
    "gn:population":0,
    "gn:timezone":"Asia/Tokyo",
    "iso:country":"JP",
    "name:jpn_x_preferred":[
        "\u702c\u9ad8"
    ],
    "name:jpn_x_variant":[
        "\u305b\u305f\u304b",
        "\u30bb\u30bf\u30ab"
    ],
    "wof:name":"Setaka",
    "wof:placetype":"locality"
},
  "geometry": {"coordinates":[130.40939,32.55284],"type":"Point"}
}