{
  "type": "Feature",
  "properties": {
    "gn:admin1_code":"34.0",
    "gn:admin2_code":"7464123.0",
    "gn:asciiname":"Kakinokicho",
    "gn:country_code":"JP",
    "gn:dem":3,
    "gn:feature_class":"P",
    "gn:feature_code":"PPL",
    "gn:name":"Kakinokich\u014d",
    "gn:population":0,
    "gn:timezone":"Asia/Tokyo",
    "iso:country":"JP",
    "name:jpn_x_preferred":[
        "\u67ff\u6728\u753a"
    ],
    "name:und_x_variant":[
        "Kakinokich\u014d"
    ],
    "wof:name":"Kakinokicho",
    "wof:placetype":"locality"
},
  "geometry": {"coordinates":[139.83158,35.86342],"type":"Point"}
}