{
  "type": "Feature",
  "properties": {
    "gn:admin1_code":"28.0",
    "gn:admin2_code":"7412212.0",
    "gn:asciiname":"Haibara-sawa",
    "gn:country_code":"JP",
    "gn:dem":362,
    "gn:feature_class":"P",
    "gn:feature_code":"PPL",
    "gn:name":"Haibara-sawa",
    "gn:population":0,
    "gn:timezone":"Asia/Tokyo",
    "iso:country":"JP",
    "name:jpn_x_preferred":[
        "\u699b\u539f\u6fa4"
    ],
    "wof:name":"Haibara-sawa",
    "wof:placetype":"locality"
},
  "geometry": {"coordinates":[135.96974,34.49325],"type":"Point"}
}