{
  "type": "Feature",
  "properties": {
    "gn:admin1_code":"27",
    "gn:admin2_code":"1852895.0",
    "gn:asciiname":"Kawanotani",
    "gn:country_code":"JP",
    "gn:dem":11,
    "gn:feature_class":"P",
    "gn:feature_code":"PPLL",
    "gn:name":"Kawanotani",
    "gn:population":0,
    "gn:timezone":"Asia/Tokyo",
    "iso:country":"JP",
    "name:jpn_x_preferred":[
        "\u5ddd\u30ce\u8c37"
    ],
    "name:und_x_variant":[
        "Kawanoya",
        "Kawanotani"
    ],
    "wof:name":"Kawanotani",
    "wof:placetype":"locality"
},
  "geometry": {"coordinates":[129.69812999999999,33.14392],"type":"Point"}
}