{
  "type": "Feature",
  "properties": {
    "gn:admin1_code":"28.0",
    "gn:admin2_code":"1848164.0",
    "gn:admin3_code":"29452.0",
    "gn:asciiname":"Kuroishi",
    "gn:country_code":"JP",
    "gn:dem":441,
    "gn:feature_class":"P",
    "gn:feature_code":"PPL",
    "gn:name":"Kuroishi",
    "gn:population":0,
    "gn:timezone":"Asia/Tokyo",
    "iso:country":"JP",
    "name:jpn_x_preferred":[
        "\u9ed2\u77f3"
    ],
    "name:mlg_x_preferred":[
        "Kuroishi"
    ],
    "wof:name":"Kuroishi",
    "wof:placetype":"locality"
},
  "geometry": {"coordinates":[136.06223,34.24178],"type":"Point"}
}