{
  "type": "Feature",
  "properties": {
    "iso:country":"JP",
    "name:eng_x_preferred":[
        "Joto 6 Chome"
    ],
    "name:eng_x_variant":[
        "Joutou 6 Choume",
        "Joto 6 Chome"
    ],
    "name:jpn_x_preferred":[
        "\uff16\u4e01\u76ee"
    ],
    "name:jpn_x_variant":[
        "\u3058\u3087\u3046\u3068\u3046 \uff16\u3061\u3087\u3046\u3081",
        "\u57ce\u6771 \uff16\u4e01\u76ee",
        "\uff16\u3061\u3087\u3046\u3081"
    ],
    "qs:gn_local":0,
    "qs:local_max":82,
    "qs:local_sum":85,
    "qs:localhoods":2,
    "qs:name":"\uff16\u4e01\u76ee",
    "qs:name_adm0":"\u65e5\u672c",
    "qs:name_adm1":"\u6803\u6728\u770c",
    "qs:name_en":"Joto 6 Chome",
    "qs:name_lau":"\u57ce\u6771",
    "qs:name_local":"\u5c0f\u5c71\u5e02",
    "qs:photo_max":2,
    "qs:photo_sum":3,
    "qs:placetype":"Suburb",
    "qs:quad_count":2,
    "qs:woe_adm0":23424856,
    "qs:woe_adm1":2345887,
    "qs:woe_adm2":0,
    "qs:woe_lau":28405250,
    "qs:woe_local":1118039,
    "qs:woe_ver":"7.10.0",
    "wof:lang":[
        "jpn"
    ],
    "wof:name":"\uff16\u4e01\u76ee",
    "wof:placetype":"neighbourhood"
},
  "geometry": {"coordinates":[139.82208299999999,36.308487],"type":"Point"}
}