{
  "type": "Feature",
  "properties": {
    "gn:admin1_code":"2.0",
    "gn:admin2_code":"2113122.0",
    "gn:asciiname":"Araya-omotemachi",
    "gn:country_code":"JP",
    "gn:dem":8,
    "gn:feature_class":"P",
    "gn:feature_code":"PPL",
    "gn:name":"Araya-omotemachi",
    "gn:population":0,
    "gn:timezone":"Asia/Tokyo",
    "iso:country":"JP",
    "name:jpn_x_preferred":[
        "\u65b0\u5c4b\u8868\u753a"
    ],
    "name:jpn_x_variant":[
        "\u3042\u3089\u3084\u304a\u3082\u3066\u307e\u3061",
        "\u30a2\u30e9\u30e4\u30aa\u30e2\u30c6\u30de\u30c1"
    ],
    "wof:name":"Araya-omotemachi",
    "wof:placetype":"locality"
},
  "geometry": {"coordinates":[140.08428000000001,39.68106],"type":"Point"}
}