{
  "type": "Feature",
  "properties": {
    "gn:admin1_code":"27.0",
    "gn:admin2_code":"1857466.0",
    "gn:asciiname":"Mikuriyacho-kitabiramen",
    "gn:country_code":"JP",
    "gn:dem":14,
    "gn:feature_class":"P",
    "gn:feature_code":"PPL",
    "gn:name":"Mikuriyach\u014d-kitabiramen",
    "gn:population":0,
    "gn:timezone":"Asia/Tokyo",
    "iso:country":"JP",
    "name:jpn_x_preferred":[
        "\u5fa1\u53a8\u753a\u5317\u5e73\u514d"
    ],
    "name:und_x_variant":[
        "Mikuriyach\u014d-kitabiramen"
    ],
    "wof:name":"Mikuriyacho-kitabiramen",
    "wof:placetype":"locality"
},
  "geometry": {"coordinates":[129.6764,33.35448],"type":"Point"}
}