{
  "type": "Feature",
  "properties": {
    "gn:admin1_code":"21.0",
    "gn:admin2_code":"1850744.0",
    "gn:admin3_code":"43367.0",
    "gn:asciiname":"Kawarayashiki",
    "gn:country_code":"JP",
    "gn:dem":76,
    "gn:feature_class":"P",
    "gn:feature_code":"PPLL",
    "gn:name":"Kawarayashiki",
    "gn:population":0,
    "gn:timezone":"Asia/Tokyo",
    "iso:country":"JP",
    "name:jpn_x_preferred":[
        "\u74e6\u5c4b\u6577"
    ],
    "name:jpn_x_variant":[
        "\u304b\u308f\u3089\u3084\u3057\u304d",
        "\u30ab\u30ef\u30e9\u30e4\u30b7\u30ad"
    ],
    "wof:name":"Kawarayashiki",
    "wof:placetype":"locality"
},
  "geometry": {"coordinates":[130.55413999999999,33.06427],"type":"Point"}
}