{
  "type": "Feature",
  "properties": {
    "iso:country":"JP",
    "name:eng_x_preferred":[
        "Sakaemachi 3 Chome"
    ],
    "name:eng_x_variant":[
        "Sakaemachi 3 Choume",
        "Sakaemachi 3 Chome"
    ],
    "name:jpn_x_preferred":[
        "\uff13\u4e01\u76ee"
    ],
    "name:jpn_x_variant":[
        "\u3055\u304b\u3048\u307e\u3061 \uff13\u3061\u3087\u3046\u3081",
        "\u6804\u753a \uff13\u4e01\u76ee",
        "\uff13\u3061\u3087\u3046\u3081"
    ],
    "name:unk_x_variant":[
        "\uff13\u4e01\u76ee"
    ],
    "qs:gn_local":0,
    "qs:local_max":336,
    "qs:local_sum":443,
    "qs:localhoods":4,
    "qs:name":"\uff13\u4e01\u76ee",
    "qs:name_adm0":"\u65e5\u672c",
    "qs:name_adm1":"\u611b\u77e5\u770c",
    "qs:name_en":"Sakaemachi 3 Chome",
    "qs:name_lau":"\u6804\u753a",
    "qs:name_local":"\u78a7\u5357\u5e02",
    "qs:photo_max":8,
    "qs:photo_sum":12,
    "qs:placetype":"Suburb",
    "qs:quad_count":2,
    "qs:woe_adm0":23424856,
    "qs:woe_adm1":2345851,
    "qs:woe_adm2":0,
    "qs:woe_lau":28442201,
    "qs:woe_local":1108754,
    "qs:woe_ver":"7.10.0",
    "wof:lang":[
        "jpn"
    ],
    "wof:name":"\uff13\u4e01\u76ee",
    "wof:placetype":"neighbourhood"
},
  "geometry": {"coordinates":[136.99127200000001,34.886682],"type":"Point"}
}