{
  "type": "Feature",
  "properties": {
    "gn:admin1_code":"01",
    "gn:admin2_code":"1859272.0",
    "gn:admin3_code":"23561.0",
    "gn:asciiname":"Taguchi",
    "gn:country_code":"JP",
    "gn:dem":457,
    "gn:feature_class":"P",
    "gn:feature_code":"PPL",
    "gn:name":"Taguchi",
    "gn:population":0,
    "gn:timezone":"Asia/Tokyo",
    "iso:country":"JP",
    "wof:name":"Taguchi",
    "wof:placetype":"locality"
},
  "geometry": {"coordinates":[137.58333000000002,35.08333],"type":"Point"}
}