{
  "type": "Feature",
  "properties": {
    "gn:admin1_code":"7.0",
    "gn:admin2_code":"1861834.0",
    "gn:asciiname":"Mochida",
    "gn:country_code":"JP",
    "gn:dem":34,
    "gn:feature_class":"P",
    "gn:feature_code":"PPLL",
    "gn:name":"Mochida",
    "gn:population":0,
    "gn:timezone":"Asia/Tokyo",
    "iso:country":"JP",
    "name:fra_x_preferred":[
        "Mochida"
    ],
    "name:jpn_x_preferred":[
        "\u6301\u7530"
    ],
    "wof:name":"Mochida",
    "wof:placetype":"locality"
},
  "geometry": {"coordinates":[130.72158000000002,33.62906],"type":"Point"}
}