{
  "type": "Feature",
  "properties": {
    "gn:admin1_code":"12.0",
    "gn:admin2_code":"7428088.0",
    "gn:admin3_code":"1637.0",
    "gn:asciiname":"Nakafushiko",
    "gn:country_code":"JP",
    "gn:dem":116,
    "gn:feature_class":"P",
    "gn:feature_code":"PPL",
    "gn:name":"Nakafushiko",
    "gn:population":0,
    "gn:timezone":"Asia/Tokyo",
    "iso:country":"JP",
    "name:jpn_x_preferred":[
        "\u4e2d\u4f0f\u53e4"
    ],
    "name:und_x_variant":[
        "Naka-fushiko"
    ],
    "wof:name":"Nakafushiko",
    "wof:placetype":"locality"
},
  "geometry": {"coordinates":[143.06733,42.85887],"type":"Point"}
}