{
  "type": "Feature",
  "properties": {
    "gn:admin1_code":"3.0",
    "gn:admin2_code":"2130200.0",
    "gn:asciiname":"Torishimizu",
    "gn:country_code":"JP",
    "gn:dem":70,
    "gn:feature_class":"P",
    "gn:feature_code":"PPL",
    "gn:name":"T\u014drishimizu",
    "gn:population":0,
    "gn:timezone":"Asia/Tokyo",
    "iso:country":"JP",
    "name:jpn_x_preferred":[
        "\u901a\u6e05\u6c34"
    ],
    "name:jpn_x_variant":[
        "\u3068\u304a\u308a\u3057\u307f\u305a",
        "\u30c8\u30aa\u30ea\u30b7\u30df\u30ba"
    ],
    "name:und_x_variant":[
        "T\u014drishimizu"
    ],
    "wof:name":"Torishimizu",
    "wof:placetype":"locality"
},
  "geometry": {"coordinates":[141.42874,40.46887],"type":"Point"}
}