{
  "type": "Feature",
  "properties": {
    "gn:admin1_code":"12.0",
    "gn:admin2_code":"2130385.0",
    "gn:asciiname":"Enami",
    "gn:country_code":"JP",
    "gn:dem":37,
    "gn:feature_class":"P",
    "gn:feature_code":"PPL",
    "gn:name":"Enami",
    "gn:population":0,
    "gn:timezone":"Asia/Tokyo",
    "iso:country":"JP",
    "name:jpn_x_preferred":[
        "\u6075\u5357"
    ],
    "wof:name":"Enami",
    "wof:placetype":"locality"
},
  "geometry": {"coordinates":[141.59133,42.86272],"type":"Point"}
}