{
  "type": "Feature",
  "properties": {
    "gn:admin1_code":"34.0",
    "gn:admin2_code":"1851882.0",
    "gn:asciiname":"Ota'arai",
    "gn:country_code":"JP",
    "gn:dem":9,
    "gn:feature_class":"P",
    "gn:feature_code":"PPL",
    "gn:name":"\u014cta\u2019arai",
    "gn:population":0,
    "gn:timezone":"Asia/Tokyo",
    "iso:country":"JP",
    "name:jpn_x_preferred":[
        "\u592a\u7530\u65b0\u4e95"
    ],
    "name:jpn_x_variant":[
        "\u304a\u304a\u305f\u3042\u3089\u3044",
        "\u30aa\u30aa\u30bf\u30a2\u30e9\u30a4"
    ],
    "name:und_x_variant":[
        "\u014cta\u2019arai"
    ],
    "wof:name":"Ota'arai",
    "wof:placetype":"locality"
},
  "geometry": {"coordinates":[139.70567,36.0061],"type":"Point"}
}