{
  "type": "Feature",
  "properties": {
    "gn:admin1_code":"2.0",
    "gn:admin2_code":"2113122.0",
    "gn:asciiname":"Sekigami",
    "gn:country_code":"JP",
    "gn:dem":11,
    "gn:feature_class":"P",
    "gn:feature_code":"PPL",
    "gn:name":"Sekigami",
    "gn:population":0,
    "gn:timezone":"Asia/Tokyo",
    "iso:country":"JP",
    "name:jpn_x_preferred":[
        "\u95a2\u4e0a"
    ],
    "name:jpn_x_variant":[
        "\u305b\u304d\u304c\u307f",
        "\u30bb\u30ad\u30ac\u30df"
    ],
    "wof:name":"Sekigami",
    "wof:placetype":"locality"
},
  "geometry": {"coordinates":[140.15714,39.69798],"type":"Point"}
}