{
  "type": "Feature",
  "properties": {
    "gn:admin1_code":"3.0",
    "gn:asciiname":"Shikkari",
    "gn:cc2":"JP",
    "gn:country_code":"JP",
    "gn:dem":1,
    "gn:feature_class":"P",
    "gn:feature_code":"PPL",
    "gn:name":"Shikkari",
    "gn:population":0,
    "gn:timezone":"Asia/Tokyo",
    "iso:country":"JP",
    "name:und_x_variant":[
        "Shirikari",
        "Shikkari"
    ],
    "wof:name":"Shikkari",
    "wof:placetype":"locality"
},
  "geometry": {"coordinates":[141.44999999999999,41.36667],"type":"Point"}
}