{
  "type": "Feature",
  "properties": {
    "gn:admin1_code":"40.0",
    "gn:admin2_code":"1865750.0",
    "gn:asciiname":"Kitakaheicho",
    "gn:country_code":"JP",
    "gn:dem":5,
    "gn:feature_class":"P",
    "gn:feature_code":"PPL",
    "gn:name":"Kitakaheich\u014d",
    "gn:population":0,
    "gn:timezone":"Asia/Tokyo",
    "iso:country":"JP",
    "name:jpn_x_preferred":[
        "\u5317\u52a0\u5e73\u753a"
    ],
    "name:und_x_variant":[
        "Kitakaheich\u014d"
    ],
    "wof:name":"Kitakaheicho",
    "wof:placetype":"locality"
},
  "geometry": {"coordinates":[139.82875000000001,35.78426],"type":"Point"}
}