{
  "type": "Feature",
  "properties": {
    "gn:admin1_code":"19.0",
    "gn:admin2_code":"1848350.0",
    "gn:admin3_code":"14102.0",
    "gn:asciiname":"Irie",
    "gn:country_code":"JP",
    "gn:dem":6,
    "gn:feature_class":"P",
    "gn:feature_code":"PPL",
    "gn:name":"Irie",
    "gn:population":0,
    "gn:timezone":"Asia/Tokyo",
    "iso:country":"JP",
    "name:jpn_x_preferred":[
        "\u5165\u6c5f"
    ],
    "name:jpn_x_variant":[
        "\u3044\u308a\u3048",
        "\u30a4\u30ea\u30a8"
    ],
    "wof:name":"Irie",
    "wof:placetype":"locality"
},
  "geometry": {"coordinates":[139.64926,35.49019000000001],"type":"Point"}
}