{
  "type": "Feature",
  "properties": {
    "gn:admin1_code":"15.0",
    "gn:admin2_code":"1860845.0",
    "gn:asciiname":"Oshio-tsujimachi",
    "gn:country_code":"JP",
    "gn:dem":27,
    "gn:feature_class":"P",
    "gn:feature_code":"PPL",
    "gn:name":"Oshio-tsujimachi",
    "gn:population":0,
    "gn:timezone":"Asia/Tokyo",
    "iso:country":"JP",
    "name:jpn_x_preferred":[
        "\u5c0f\u5869\u8fbb\u753a"
    ],
    "wof:name":"Oshio-tsujimachi",
    "wof:placetype":"locality"
},
  "geometry": {"coordinates":[136.3296,36.33971],"type":"Point"}
}