{
  "type": "Feature",
  "properties": {
    "gn:admin1_code":"22",
    "gn:admin2_code":"1864008.0",
    "gn:asciiname":"Mimata",
    "gn:country_code":"JP",
    "gn:dem":91,
    "gn:feature_class":"P",
    "gn:feature_code":"PPL",
    "gn:name":"Mimata",
    "gn:population":0,
    "gn:timezone":"Asia/Tokyo",
    "iso:country":"JP",
    "wof:name":"Mimata",
    "wof:placetype":"locality"
},
  "geometry": {"coordinates":[135.19999999999999,35.25],"type":"Point"}
}