{
  "type": "Feature",
  "properties": {
    "gn:admin1_code":"7.0",
    "gn:admin2_code":"1859874.0",
    "gn:admin3_code":"40349.0",
    "gn:asciiname":"Yusu",
    "gn:country_code":"JP",
    "gn:dem":4,
    "gn:feature_class":"P",
    "gn:feature_code":"PPL",
    "gn:name":"Yusu",
    "gn:population":0,
    "gn:timezone":"Asia/Tokyo",
    "iso:country":"JP",
    "name:jpn_x_preferred":[
        "\u67da\u9808"
    ],
    "wof:name":"Yusu",
    "wof:placetype":"locality"
},
  "geometry": {"coordinates":[130.45151000000001,33.61416],"type":"Point"}
}