{
  "type": "Feature",
  "properties": {
    "gn:admin1_code":"21.0",
    "gn:admin2_code":"7412708.0",
    "gn:admin3_code":"43514.0",
    "gn:asciiname":"Seiganji",
    "gn:country_code":"JP",
    "gn:dem":254,
    "gn:feature_class":"P",
    "gn:feature_code":"PPLL",
    "gn:name":"Seiganji",
    "gn:population":0,
    "gn:timezone":"Asia/Tokyo",
    "iso:country":"JP",
    "name:jpn_x_preferred":[
        "\u6e05\u9858\u5bfa"
    ],
    "name:jpn_x_variant":[
        "\u305b\u3044\u304c\u3093\u3058",
        "\u30bb\u30a4\u30ac\u30f3\u30b8"
    ],
    "wof:name":"Seiganji",
    "wof:placetype":"locality"
},
  "geometry": {"coordinates":[130.93356,32.20383],"type":"Point"}
}