{
  "type": "Feature",
  "properties": {
    "gn:admin1_code":"34.0",
    "gn:admin2_code":"1859369.0",
    "gn:admin3_code":"11301.0",
    "gn:asciiname":"Oyamaue",
    "gn:country_code":"JP",
    "gn:dem":12,
    "gn:feature_class":"P",
    "gn:feature_code":"PPLL",
    "gn:name":"\u014cyamaue",
    "gn:population":0,
    "gn:timezone":"Asia/Tokyo",
    "iso:country":"JP",
    "name:jpn_x_preferred":[
        "\u5927\u5c71\u4e0a"
    ],
    "name:jpn_x_variant":[
        "\u304a\u304a\u3084\u307e\u3046\u3048",
        "\u30aa\u30aa\u30e4\u30de\u30a6\u30a8"
    ],
    "name:und_x_variant":[
        "\u014cyamaue"
    ],
    "wof:name":"Oyamaue",
    "wof:placetype":"locality"
},
  "geometry": {"coordinates":[139.61426,35.98755999999999],"type":"Point"}
}