{
  "type": "Feature",
  "properties": {
    "gn:admin1_code":"33.0",
    "gn:admin2_code":"7391355.0",
    "gn:asciiname":"Minamihatacho-kasaji",
    "gn:country_code":"JP",
    "gn:dem":58,
    "gn:feature_class":"P",
    "gn:feature_code":"PPL",
    "gn:name":"Minamihatach\u014d-kasaji",
    "gn:population":0,
    "gn:timezone":"Asia/Tokyo",
    "iso:country":"JP",
    "name:jpn_x_preferred":[
        "\u5357\u6ce2\u591a\u753a\u7b20\u690e"
    ],
    "name:und_x_variant":[
        "Minamihatach\u014d-kasaji"
    ],
    "wof:name":"Minamihatacho-kasaji",
    "wof:placetype":"locality"
},
  "geometry": {"coordinates":[129.93726999999998,33.29832],"type":"Point"}
}