{
  "type": "Feature",
  "properties": {
    "iso:country":"JP",
    "name:eng_x_preferred":[
        "Homigaoka 4 Chome"
    ],
    "name:eng_x_variant":[
        "Homigaoka 4 Choume",
        "Homigaoka 4 Chome"
    ],
    "name:jpn_x_preferred":[
        "\uff14\u4e01\u76ee"
    ],
    "name:jpn_x_variant":[
        "\u307b\u307f\u304c\u304a\u304b \uff14\u3061\u3087\u3046\u3081",
        "\u4fdd\u898b\u30b1\u4e18 \uff14\u4e01\u76ee",
        "\uff14\u3061\u3087\u3046\u3081"
    ],
    "qs:gn_local":0,
    "qs:local_max":500,
    "qs:local_sum":1065,
    "qs:localhoods":7,
    "qs:name":"\uff14\u4e01\u76ee",
    "qs:name_adm0":"\u65e5\u672c",
    "qs:name_adm1":"\u611b\u77e5\u770c",
    "qs:name_en":"Homigaoka 4 Chome",
    "qs:name_lau":"\u4fdd\u898b\u30b1\u4e18",
    "qs:name_local":"\u8c4a\u7530\u5e02",
    "qs:photo_max":79,
    "qs:photo_sum":500,
    "qs:placetype":"Suburb",
    "qs:quad_count":19,
    "qs:woe_adm0":23424856,
    "qs:woe_adm1":2345851,
    "qs:woe_adm2":0,
    "qs:woe_lau":28442500,
    "qs:woe_local":1118413,
    "qs:woe_ver":"7.10.0",
    "wof:lang":[
        "jpn"
    ],
    "wof:name":"\uff14\u4e01\u76ee",
    "wof:placetype":"neighbourhood"
},
  "geometry": {"coordinates":[137.144137,35.141884],"type":"Point"}
}