{
  "type": "Feature",
  "properties": {
    "gn:admin1_code":"3.0",
    "gn:admin2_code":"2127674.0",
    "gn:asciiname":"Okuse",
    "gn:country_code":"JP",
    "gn:dem":103,
    "gn:feature_class":"P",
    "gn:feature_code":"PPL",
    "gn:name":"Okuse",
    "gn:population":0,
    "gn:timezone":"Asia/Tokyo",
    "iso:country":"JP",
    "name:jpn_x_preferred":[
        "\u5965\u702c"
    ],
    "name:jpn_x_variant":[
        "\u304a\u304f\u305b",
        "\u30aa\u30af\u30bb"
    ],
    "wof:name":"Okuse",
    "wof:placetype":"locality"
},
  "geometry": {"coordinates":[141.10711000000001,40.58487],"type":"Point"}
}