{
  "type": "Feature",
  "properties": {
    "iso:country":"JP",
    "name:eng_x_preferred":[
        "Sakamoto 4 Chome"
    ],
    "name:eng_x_variant":[
        "Sakamoto 4 Choume",
        "Sakamoto 4 Chome"
    ],
    "name:jpn_x_preferred":[
        "\uff14\u4e01\u76ee"
    ],
    "name:jpn_x_variant":[
        "\u3055\u304b\u3082\u3068 \uff14\u3061\u3087\u3046\u3081",
        "\u5742\u672c \uff14\u4e01\u76ee",
        "\uff14\u3061\u3087\u3046\u3081"
    ],
    "qs:gn_local":0,
    "qs:local_max":966,
    "qs:local_sum":4101,
    "qs:localhoods":25,
    "qs:name":"\uff14\u4e01\u76ee",
    "qs:name_adm0":"\u65e5\u672c",
    "qs:name_adm1":"\u6ecb\u8cc0\u770c",
    "qs:name_en":"Sakamoto 4 Chome",
    "qs:name_lau":"\u5742\u672c",
    "qs:name_local":"\u5927\u6d25\u5e02",
    "qs:photo_max":107,
    "qs:photo_sum":456,
    "qs:placetype":"Suburb",
    "qs:quad_count":15,
    "qs:woe_adm0":23424856,
    "qs:woe_adm1":2345884,
    "qs:woe_adm2":0,
    "qs:woe_lau":1114035,
    "qs:woe_local":1118029,
    "qs:woe_ver":"7.10.0",
    "wof:lang":[
        "jpn"
    ],
    "wof:name":"\uff14\u4e01\u76ee",
    "wof:placetype":"neighbourhood"
},
  "geometry": {"coordinates":[135.862179,35.071018],"type":"Point"}
}