{
  "type": "Feature",
  "properties": {
    "gn:admin1_code":"3.0",
    "gn:admin2_code":"2130056.0",
    "gn:asciiname":"Nukatsubo",
    "gn:country_code":"JP",
    "gn:dem":18,
    "gn:feature_class":"P",
    "gn:feature_code":"PPL",
    "gn:name":"Nukatsubo",
    "gn:population":0,
    "gn:timezone":"Asia/Tokyo",
    "iso:country":"JP",
    "name:jpn_x_preferred":[
        "\u7ce0\u576a"
    ],
    "name:jpn_x_variant":[
        "\u306c\u304b\u3064\u307c",
        "\u30cc\u30ab\u30c4\u30dc"
    ],
    "wof:name":"Nukatsubo",
    "wof:placetype":"locality"
},
  "geometry": {"coordinates":[140.43259,40.6791],"type":"Point"}
}