{
  "type": "Feature",
  "properties": {
    "gn:admin1_code":"37.0",
    "gn:admin2_code":"1851376.0",
    "gn:asciiname":"Nakazato",
    "gn:country_code":"JP",
    "gn:dem":219,
    "gn:feature_class":"P",
    "gn:feature_code":"PPLL",
    "gn:name":"Nakazato",
    "gn:population":0,
    "gn:timezone":"Asia/Tokyo",
    "iso:country":"JP",
    "name:deu_x_preferred":[
        "Nakazato"
    ],
    "name:jpn_x_preferred":[
        "\u4e2d\u91cc"
    ],
    "wof:name":"Nakazato",
    "wof:placetype":"locality"
},
  "geometry": {"coordinates":[138.9006,35.20783],"type":"Point"}
}