{
  "type": "Feature",
  "properties": {
    "gn:admin1_code":"27",
    "gn:admin2_code":"1862734.0",
    "gn:admin3_code":"42322.0",
    "gn:asciiname":"Mitsugoego",
    "gn:country_code":"JP",
    "gn:dem":21,
    "gn:feature_class":"P",
    "gn:feature_code":"PPL",
    "gn:name":"Mitsugoeg\u014d",
    "gn:population":0,
    "gn:timezone":"Asia/Tokyo",
    "iso:country":"JP",
    "name:jpn_x_preferred":[
        "\u4e09\u8d8a\u90f7"
    ],
    "name:und_x_variant":[
        "Mitsukoshi",
        "Mitsukoe",
        "Mitsugoe",
        "Mitsugoeg\u014d"
    ],
    "wof:name":"Mitsugoego",
    "wof:placetype":"locality"
},
  "geometry": {"coordinates":[129.84523999999999,33.05456],"type":"Point"}
}