{
  "type": "Feature",
  "properties": {
    "gn:admin1_code":"2.0",
    "gn:admin2_code":"2113122.0",
    "gn:asciiname":"Tsuchizakiminato-chuo",
    "gn:country_code":"JP",
    "gn:dem":8,
    "gn:feature_class":"P",
    "gn:feature_code":"PPL",
    "gn:name":"Tsuchizakiminato-ch\u016b\u014d",
    "gn:population":0,
    "gn:timezone":"Asia/Tokyo",
    "iso:country":"JP",
    "name:jpn_x_preferred":[
        "\u571f\u5d0e\u6e2f\u4e2d\u592e"
    ],
    "name:jpn_x_variant":[
        "\u3064\u3061\u3056\u304d\u307f\u306a\u3068\u3061\u3085\u3046\u304a\u3046",
        "\u30c4\u30c1\u30b6\u30ad\u30df\u30ca\u30c8\u30c1\u30e5\u30a6\u30aa\u30a6"
    ],
    "name:und_x_variant":[
        "Tsuchizakiminato-ch\u016b\u014d"
    ],
    "wof:name":"Tsuchizakiminato-chuo",
    "wof:placetype":"locality"
},
  "geometry": {"coordinates":[140.06983,39.75676],"type":"Point"}
}