{
  "type": "Feature",
  "properties": {
    "gn:admin1_code":"10.0",
    "gn:admin2_code":"7453748.0",
    "gn:admin3_code":"10449.0",
    "gn:asciiname":"Akaya",
    "gn:country_code":"JP",
    "gn:dem":677,
    "gn:feature_class":"P",
    "gn:feature_code":"PPLL",
    "gn:name":"Akaya",
    "gn:population":0,
    "gn:timezone":"Asia/Tokyo",
    "iso:country":"JP",
    "name:jpn_x_preferred":[
        "\u8d64\u8c37"
    ],
    "wof:name":"Akaya",
    "wof:placetype":"locality"
},
  "geometry": {"coordinates":[138.89096000000001,36.75283],"type":"Point"}
}