{
  "type": "Feature",
  "properties": {
    "gn:admin1_code":"4.0",
    "gn:admin2_code":"1859468.0",
    "gn:asciiname":"Shimokoito",
    "gn:country_code":"JP",
    "gn:dem":33,
    "gn:feature_class":"P",
    "gn:feature_code":"PPLL",
    "gn:name":"Shimokoito",
    "gn:population":0,
    "gn:timezone":"Asia/Tokyo",
    "iso:country":"JP",
    "name:jpn_x_preferred":[
        "\u4e0b\u5c0f\u7cf8"
    ],
    "name:jpn_x_variant":[
        "\u3057\u3082\u3053\u3044\u3068",
        "\u30d2\u30e2\u30b3\u30a4\u30c8"
    ],
    "wof:name":"Shimokoito",
    "wof:placetype":"locality"
},
  "geometry": {"coordinates":[139.98372000000001,35.28374],"type":"Point"}
}