{
  "type": "Feature",
  "properties": {
    "iso:country":"JP",
    "qs:name":"\u821f\u6a4b\u6751",
    "qs:name_adm0":"\u65e5\u672c",
    "qs:name_adm1":"\u5bcc\u5c71\u770c",
    "qs:photos":188,
    "qs:photos_1k":38,
    "qs:photos_9k":1,
    "qs:photos_9r":4,
    "qs:photos_all":188,
    "qs:photos_sr":4,
    "qs:placetype":"Town",
    "qs:pop_sr":"0",
    "wof:name":"\u821f\u6a4b\u6751",
    "wof:placetype":"locality"
},
  "geometry": {"coordinates":[137.33493799999999,36.672893],"type":"Point"}
}