{
  "type": "Feature",
  "properties": {
    "gn:admin1_code":"21.0",
    "gn:admin2_code":"1850744.0",
    "gn:admin3_code":"43369.0",
    "gn:asciiname":"Urabe",
    "gn:country_code":"JP",
    "gn:dem":63,
    "gn:feature_class":"P",
    "gn:feature_code":"PPLL",
    "gn:name":"Urabe",
    "gn:population":0,
    "gn:timezone":"Asia/Tokyo",
    "iso:country":"JP",
    "name:jpn_x_preferred":[
        "\u6d66\u90e8"
    ],
    "name:jpn_x_variant":[
        "\u3046\u3089\u3079",
        "\u30a6\u30e9\u30d9"
    ],
    "wof:name":"Urabe",
    "wof:placetype":"locality"
},
  "geometry": {"coordinates":[130.60963000000001,33.0789],"type":"Point"}
}