{
  "type": "Feature",
  "properties": {
    "gn:admin1_code":"19.0",
    "gn:admin2_code":"1859635.0",
    "gn:admin3_code":"14133.0",
    "gn:asciiname":"Nishikase",
    "gn:country_code":"JP",
    "gn:dem":13,
    "gn:feature_class":"P",
    "gn:feature_code":"PPL",
    "gn:name":"Nishikase",
    "gn:population":0,
    "gn:timezone":"Asia/Tokyo",
    "iso:country":"JP",
    "name:jpn_x_preferred":[
        "\u897f\u52a0\u702c"
    ],
    "wof:name":"Nishikase",
    "wof:placetype":"locality"
},
  "geometry": {"coordinates":[139.66006999999999,35.55892],"type":"Point"}
}