{
  "type": "Feature",
  "properties": {
    "gn:admin1_code":"7.0",
    "gn:admin2_code":"1851269.0",
    "gn:admin3_code":"40602.0",
    "gn:asciiname":"Shinjo",
    "gn:country_code":"JP",
    "gn:dem":85,
    "gn:feature_class":"P",
    "gn:feature_code":"PPLL",
    "gn:name":"Shinj\u014d",
    "gn:population":0,
    "gn:timezone":"Asia/Tokyo",
    "iso:country":"JP",
    "name:jpn_x_preferred":[
        "\u65b0\u57ce"
    ],
    "name:und_x_variant":[
        "Shinj\u014d"
    ],
    "wof:name":"Shinjo",
    "wof:placetype":"locality"
},
  "geometry": {"coordinates":[130.84191000000001,33.57959],"type":"Point"}
}