{
  "type": "Feature",
  "properties": {
    "gn:admin1_code":"21.0",
    "gn:admin2_code":"1865358.0",
    "gn:asciiname":"Sarayama",
    "gn:country_code":"JP",
    "gn:dem":93,
    "gn:feature_class":"P",
    "gn:feature_code":"PPLL",
    "gn:name":"Sarayama",
    "gn:population":0,
    "gn:timezone":"Asia/Tokyo",
    "iso:country":"JP",
    "name:jpn_x_preferred":[
        "\u76bf\u5c71"
    ],
    "name:jpn_x_variant":[
        "\u3055\u3089\u3084\u307e",
        "\u30b5\u30e9\u30e4\u30de"
    ],
    "wof:name":"Sarayama",
    "wof:placetype":"locality"
},
  "geometry": {"coordinates":[130.03703000000002,32.38668],"type":"Point"}
}