{
  "type": "Feature",
  "properties": {
    "gn:admin1_code":"4.0",
    "gn:admin2_code":"2113012.0",
    "gn:admin3_code":"12101.0",
    "gn:asciiname":"Hamano",
    "gn:cc2":"JP",
    "gn:country_code":"JP",
    "gn:dem":0,
    "gn:feature_class":"P",
    "gn:feature_code":"PPL",
    "gn:name":"Hamano",
    "gn:population":0,
    "gn:timezone":"Asia/Tokyo",
    "iso:country":"JP",
    "name:und_x_variant":[
        "Hamanoch\u014d",
        "Hamano"
    ],
    "wof:name":"Hamano",
    "wof:placetype":"locality"
},
  "geometry": {"coordinates":[140.13333,35.55],"type":"Point"}
}