{
  "type": "Feature",
  "properties": {
    "gn:admin1_code":"21.0",
    "gn:admin2_code":"1865168.0",
    "gn:asciiname":"Karaike",
    "gn:country_code":"JP",
    "gn:dem":41,
    "gn:feature_class":"P",
    "gn:feature_code":"PPLL",
    "gn:name":"Karaike",
    "gn:population":0,
    "gn:timezone":"Asia/Tokyo",
    "iso:country":"JP",
    "name:jpn_x_preferred":[
        "\u5510\u6c60"
    ],
    "name:jpn_x_variant":[
        "\u304b\u3089\u3044\u3051",
        "\u30ab\u30e9\u30a4\u30b1"
    ],
    "wof:name":"Karaike",
    "wof:placetype":"locality"
},
  "geometry": {"coordinates":[130.48443,32.98586],"type":"Point"}
}