{
  "type": "Feature",
  "properties": {
    "gn:admin1_code":"26.0",
    "gn:admin2_code":"10629642.0",
    "gn:asciiname":"Ushio",
    "gn:country_code":"JP",
    "gn:dem":517,
    "gn:feature_class":"P",
    "gn:feature_code":"PPL",
    "gn:name":"Ushio",
    "gn:population":0,
    "gn:timezone":"Asia/Tokyo",
    "iso:country":"JP",
    "name:jpn_x_preferred":[
        "\u6f6e"
    ],
    "wof:name":"Ushio",
    "wof:placetype":"locality"
},
  "geometry": {"coordinates":[137.93022999999999,36.362],"type":"Point"}
}