{
  "type": "Feature",
  "properties": {
    "gn:admin1_code":"7.0",
    "gn:admin2_code":"1861834.0",
    "gn:asciiname":"Hiratsune-honmachi",
    "gn:country_code":"JP",
    "gn:dem":60,
    "gn:feature_class":"P",
    "gn:feature_code":"PPLL",
    "gn:name":"Hiratsune-honmachi",
    "gn:population":0,
    "gn:timezone":"Asia/Tokyo",
    "iso:country":"JP",
    "name:jpn_x_preferred":[
        "\u5e73\u6052\u672c\u753a"
    ],
    "wof:name":"Hiratsune-honmachi",
    "wof:placetype":"locality"
},
  "geometry": {"coordinates":[130.69333999999998,33.61062],"type":"Point"}
}