{
  "type": "Feature",
  "properties": {
    "gn:admin1_code":"21.0",
    "gn:admin2_code":"7412709.0",
    "gn:admin3_code":"43348.0",
    "gn:asciiname":"Uchizono",
    "gn:country_code":"JP",
    "gn:dem":212,
    "gn:feature_class":"P",
    "gn:feature_code":"PPLL",
    "gn:name":"Uchizono",
    "gn:population":0,
    "gn:timezone":"Asia/Tokyo",
    "iso:country":"JP",
    "name:jpn_x_preferred":[
        "\u5185\u5712"
    ],
    "name:jpn_x_variant":[
        "\u3046\u3061\u305e\u306e",
        "\u30a6\u30c1\u30be\u30ce"
    ],
    "wof:name":"Uchizono",
    "wof:placetype":"locality"
},
  "geometry": {"coordinates":[130.90326000000002,32.63596],"type":"Point"}
}