{
  "type": "Feature",
  "properties": {
    "iso:country":"JP",
    "name:eng_x_preferred":[
        "Zuiko 3 Chome"
    ],
    "name:eng_x_variant":[
        "Zuikou 3 Choume",
        "Zuiko 3 Chome"
    ],
    "name:jpn_x_preferred":[
        "\uff13\u4e01\u76ee"
    ],
    "name:jpn_x_variant":[
        "\u305a\u3044\u3053\u3046 \uff13\u3061\u3087\u3046\u3081",
        "\u745e\u5149 \uff13\u4e01\u76ee",
        "\uff13\u3061\u3087\u3046\u3081"
    ],
    "qs:gn_local":0,
    "qs:local_max":5466,
    "qs:local_sum":82256,
    "qs:localhoods":141,
    "qs:name":"\uff13\u4e01\u76ee",
    "qs:name_adm0":"\u65e5\u672c",
    "qs:name_adm1":"\u5927\u962a\u5e9c",
    "qs:name_adm2":"\u6771\u6dc0\u5ddd\u533a",
    "qs:name_en":"Zuiko 3 Chome",
    "qs:name_lau":"\u745e\u5149",
    "qs:name_local":"\u5927\u962a\u5e02",
    "qs:photo_max":5,
    "qs:photo_sum":6,
    "qs:placetype":"Suburb",
    "qs:quad_count":2,
    "qs:woe_adm0":23424856,
    "qs:woe_adm1":2345881,
    "qs:woe_adm2":15015390,
    "qs:woe_lau":28457285,
    "qs:woe_local":15015370,
    "qs:woe_ver":"7.10.0",
    "wof:lang":[
        "jpn"
    ],
    "wof:name":"\uff13\u4e01\u76ee",
    "wof:placetype":"neighbourhood"
},
  "geometry": {"coordinates":[135.54199199999999,34.749135],"type":"Point"}
}