{
  "type": "Feature",
  "properties": {
    "gn:admin1_code":"8.0",
    "gn:admin2_code":"2110976.0",
    "gn:admin3_code":"7561.0",
    "gn:asciiname":"Yachigoya",
    "gn:country_code":"JP",
    "gn:dem":23,
    "gn:feature_class":"P",
    "gn:feature_code":"PPL",
    "gn:name":"Yachigoya",
    "gn:population":0,
    "gn:timezone":"Asia/Tokyo",
    "iso:country":"JP",
    "name:jpn_x_preferred":[
        "\u8c37\u5730\u5c0f\u5c4b"
    ],
    "wof:name":"Yachigoya",
    "wof:placetype":"locality"
},
  "geometry": {"coordinates":[140.90528,37.87671],"type":"Point"}
}