{
  "type": "Feature",
  "properties": {
    "gn:admin1_code":"33.0",
    "gn:admin2_code":"7391363.0",
    "gn:asciiname":"Nishiyama",
    "gn:country_code":"JP",
    "gn:dem":12,
    "gn:feature_class":"P",
    "gn:feature_code":"PPLL",
    "gn:name":"Nishiyama",
    "gn:population":0,
    "gn:timezone":"Asia/Tokyo",
    "iso:country":"JP",
    "name:deu_x_preferred":[
        "Nishiyama"
    ],
    "name:fra_x_preferred":[
        "Nishiyama"
    ],
    "name:ita_x_preferred":[
        "Nishiyama"
    ],
    "name:jpn_x_preferred":[
        "\u897f\u5c71"
    ],
    "name:rus_x_preferred":[
        "\u041d\u0438\u0441\u0438\u044f\u043c\u0430"
    ],
    "wof:name":"Nishiyama",
    "wof:placetype":"locality"
},
  "geometry": {"coordinates":[130.06164999999999,33.15858],"type":"Point"}
}