{
  "type": "Feature",
  "properties": {
    "gn:admin1_code":"13",
    "gn:admin2_code":"1865406.0",
    "gn:asciiname":"Une-hara",
    "gn:country_code":"JP",
    "gn:dem":21,
    "gn:feature_class":"P",
    "gn:feature_code":"PPL",
    "gn:name":"Une-hara",
    "gn:population":0,
    "gn:timezone":"Asia/Tokyo",
    "iso:country":"JP",
    "name:jpn_x_preferred":[
        "\u6709\u5e74\u539f"
    ],
    "name:und_x_variant":[
        "Haramura",
        "Hara",
        "Unehara",
        "Une-hara"
    ],
    "wof:name":"Une-hara",
    "wof:placetype":"locality"
},
  "geometry": {"coordinates":[134.38718,34.83355],"type":"Point"}
}