{
  "type": "Feature",
  "properties": {
    "iso:country":"JP",
    "name:eng_x_preferred":[
        "Tomari"
    ],
    "name:jpn_x_preferred":[
        "\u6cca"
    ],
    "qs:name":"\u6cca",
    "qs:name_adm0":"\u65e5\u672c",
    "qs:name_adm1":"\u6c96\u7e04\u770c",
    "qs:photos":194,
    "qs:photos_1k":39,
    "qs:photos_9k":1,
    "qs:photos_9r":4,
    "qs:photos_all":273,
    "qs:photos_sr":4,
    "qs:placetype":"LocalAdmin",
    "qs:pop_sr":"0",
    "wof:name":"Tomari",
    "wof:placetype":"localadmin"
},
  "geometry": {"coordinates":[127.68568,26.22768],"type":"Point"}
}