{
  "type": "Feature",
  "properties": {
    "gn:admin1_code":"37.0",
    "gn:admin2_code":"1863526.0",
    "gn:asciiname":"Kamiai",
    "gn:country_code":"JP",
    "gn:dem":487,
    "gn:feature_class":"P",
    "gn:feature_code":"PPLL",
    "gn:name":"Kamiai",
    "gn:population":0,
    "gn:timezone":"Asia/Tokyo",
    "iso:country":"JP",
    "name:jpn_x_preferred":[
        "\u4e0a\u5408"
    ],
    "wof:name":"Kamiai",
    "wof:placetype":"locality"
},
  "geometry": {"coordinates":[138.92671999999999,35.31593],"type":"Point"}
}