{
  "type": "Feature",
  "properties": {
    "gn:admin1_code":"21.0",
    "gn:admin2_code":"1850744.0",
    "gn:admin3_code":"43369.0",
    "gn:asciiname":"Tateishi",
    "gn:country_code":"JP",
    "gn:dem":36,
    "gn:feature_class":"P",
    "gn:feature_code":"PPLL",
    "gn:name":"Tateishi",
    "gn:population":0,
    "gn:timezone":"Asia/Tokyo",
    "iso:country":"JP",
    "name:jpn_x_preferred":[
        "\u7acb\u77f3"
    ],
    "name:jpn_x_variant":[
        "\u305f\u3066\u3044\u3057",
        "\u30bf\u30c6\u30a4\u30b7"
    ],
    "wof:name":"Tateishi",
    "wof:placetype":"locality"
},
  "geometry": {"coordinates":[130.60900000000001,32.98229],"type":"Point"}
}