{
  "type": "Feature",
  "properties": {
    "gn:admin1_code":"2.0",
    "gn:admin2_code":"2128783.0",
    "gn:asciiname":"Futamata",
    "gn:country_code":"JP",
    "gn:dem":161,
    "gn:feature_class":"P",
    "gn:feature_code":"PPL",
    "gn:name":"Futamata",
    "gn:population":0,
    "gn:timezone":"Asia/Tokyo",
    "iso:country":"JP",
    "name:jpn_x_preferred":[
        "\u4e8c\u53c8"
    ],
    "name:jpn_x_variant":[
        "\u3075\u305f\u307e\u305f",
        "\u30d5\u30bf\u30de\u30bf"
    ],
    "wof:name":"Futamata",
    "wof:placetype":"locality"
},
  "geometry": {"coordinates":[140.63381000000001,40.19271],"type":"Point"}
}