{
  "type": "Feature",
  "properties": {
    "gn:admin1_code":"33.0",
    "gn:admin2_code":"1859936.0",
    "gn:asciiname":"Okuyama",
    "gn:country_code":"JP",
    "gn:dem":283,
    "gn:feature_class":"P",
    "gn:feature_code":"PPLL",
    "gn:name":"Okuyama",
    "gn:population":0,
    "gn:timezone":"Asia/Tokyo",
    "iso:country":"JP",
    "name:jpn_x_preferred":[
        "\u5965\u5c71"
    ],
    "wof:name":"Okuyama",
    "wof:placetype":"locality"
},
  "geometry": {"coordinates":[130.09663,33.02233],"type":"Point"}
}