{
  "type": "Feature",
  "properties": {
    "gn:admin1_code":"2.0",
    "gn:admin2_code":"2113122.0",
    "gn:asciiname":"Oomote",
    "gn:country_code":"JP",
    "gn:dem":7,
    "gn:feature_class":"P",
    "gn:feature_code":"PPL",
    "gn:name":"\u014comote",
    "gn:population":0,
    "gn:timezone":"Asia/Tokyo",
    "iso:country":"JP",
    "name:jpn_x_preferred":[
        "\u5927\u8868"
    ],
    "name:jpn_x_variant":[
        "\u304a\u304a\u304a\u3082\u3066",
        "\u30aa\u30aa\u30aa\u30e2\u30c6"
    ],
    "name:und_x_variant":[
        "\u014comote"
    ],
    "wof:name":"Oomote",
    "wof:placetype":"locality"
},
  "geometry": {"coordinates":[140.06653,39.84317],"type":"Point"}
}