{
  "type": "Feature",
  "properties": {
    "iso:country":"JP",
    "name:eng_x_preferred":[
        "Harumi 5 Chome"
    ],
    "name:eng_x_variant":[
        "Harumi 5 Choume",
        "Harumi 5 Chome"
    ],
    "name:jpn_x_preferred":[
        "\uff15\u4e01\u76ee"
    ],
    "name:jpn_x_variant":[
        "\u306f\u308b\u307f \uff15\u3061\u3087\u3046\u3081",
        "\u6674\u6d77 \uff15\u4e01\u76ee",
        "\uff15\u3061\u3087\u3046\u3081"
    ],
    "qs:gn_adm0_cc":"JP",
    "qs:gn_local":1850147,
    "qs:local_max":18112,
    "qs:local_sum":895907,
    "qs:localhoods":857,
    "qs:name":"\uff15\u4e01\u76ee",
    "qs:name_adm0":"\u65e5\u672c",
    "qs:name_adm1":"\u6771\u4eac\u90fd",
    "qs:name_adm2":"\u4e2d\u592e\u533a",
    "qs:name_en":"Harumi 5 Chome",
    "qs:name_lau":"\u6674\u6d77",
    "qs:name_local":"\u6771\u4eac",
    "qs:photo_max":894,
    "qs:photo_sum":1833,
    "qs:placetype":"Suburb",
    "qs:quad_count":22,
    "qs:woe_adm0":23424856,
    "qs:woe_adm1":2345889,
    "qs:woe_adm2":15015500,
    "qs:woe_lau":28413995,
    "qs:woe_local":1118370,
    "qs:woe_ver":"7.10.0",
    "wof:lang":[
        "jpn"
    ],
    "wof:name":"\uff15\u4e01\u76ee",
    "wof:placetype":"neighbourhood"
},
  "geometry": {"coordinates":[139.772773,35.647752],"type":"Point"}
}