{
  "type": "Feature",
  "properties": {
    "gn:admin1_code":"13.0",
    "gn:admin2_code":"1859755.0",
    "gn:admin3_code":"28301.0",
    "gn:asciiname":"Ibuchi",
    "gn:country_code":"JP",
    "gn:dem":112,
    "gn:feature_class":"P",
    "gn:feature_code":"PPL",
    "gn:name":"Ibuchi",
    "gn:population":0,
    "gn:timezone":"Asia/Tokyo",
    "iso:country":"JP",
    "name:jpn_x_preferred":[
        "\u732a\u6e15"
    ],
    "wof:name":"Ibuchi",
    "wof:placetype":"locality"
},
  "geometry": {"coordinates":[135.36077,34.89069],"type":"Point"}
}