{
  "type": "Feature",
  "properties": {
    "gn:admin1_code":"4.0",
    "gn:admin2_code":"8304237.0",
    "gn:asciiname":"Hatazawa-minami",
    "gn:country_code":"JP",
    "gn:dem":44,
    "gn:feature_class":"P",
    "gn:feature_code":"PPL",
    "gn:name":"Hatazawa-minami",
    "gn:population":0,
    "gn:timezone":"Asia/Tokyo",
    "iso:country":"JP",
    "name:jpn_x_preferred":[
        "\u7551\u6ca2\u5357"
    ],
    "name:jpn_x_variant":[
        "\u306f\u305f\u3056\u308f\u307f\u306a\u307f",
        "\u30cf\u30bf\u30b6\u30ef\u30df\u30ca\u30df"
    ],
    "wof:name":"Hatazawa-minami",
    "wof:placetype":"locality"
},
  "geometry": {"coordinates":[139.90388999999999,35.34074000000001],"type":"Point"}
}