{
  "type": "Feature",
  "properties": {
    "gn:admin1_code":"19.0",
    "gn:admin2_code":"1864091.0",
    "gn:asciiname":"Kajiyama",
    "gn:country_code":"JP",
    "gn:dem":15,
    "gn:feature_class":"P",
    "gn:feature_code":"PPLL",
    "gn:name":"Kajiyama",
    "gn:population":0,
    "gn:timezone":"Asia/Tokyo",
    "iso:country":"JP",
    "name:jpn_x_preferred":[
        "\u935b\u51b6\u5c71"
    ],
    "wof:name":"Kajiyama",
    "wof:placetype":"locality"
},
  "geometry": {"coordinates":[139.45552000000001,35.37449],"type":"Point"}
}