{
  "type": "Feature",
  "properties": {
    "gn:admin1_code":"12.0",
    "gn:admin2_code":"7428102.0",
    "gn:admin3_code":"1608.0",
    "gn:asciiname":"Hirau",
    "gn:country_code":"JP",
    "gn:dem":25,
    "gn:feature_class":"P",
    "gn:feature_code":"PPL",
    "gn:name":"Hirau",
    "gn:population":0,
    "gn:timezone":"Asia/Tokyo",
    "iso:country":"JP",
    "name:jpn_x_preferred":[
        "\u5e73\u5b87"
    ],
    "wof:name":"Hirau",
    "wof:placetype":"locality"
},
  "geometry": {"coordinates":[142.96147999999999,42.12209],"type":"Point"}
}