{
  "type": "Feature",
  "properties": {
    "iso:country":"JP",
    "name:eng_x_preferred":[
        "Dokichohigashi 5 Chome"
    ],
    "name:eng_x_variant":[
        "Dokichouhigashi 5 Choume",
        "Dokichohigashi 5 Chome"
    ],
    "name:jpn_x_preferred":[
        "\uff15\u4e01\u76ee"
    ],
    "name:jpn_x_variant":[
        "\u3069\u304d\u3061\u3087\u3046\u3072\u304c\u3057 \uff15\u3061\u3087\u3046\u3081",
        "\u571f\u5668\u753a\u6771 \uff15\u4e01\u76ee",
        "\uff15\u3061\u3087\u3046\u3081"
    ],
    "qs:gn_adm0_cc":"JP",
    "qs:gn_local":1857665,
    "qs:gn_nam_loc":"\u4e38\u4e80\u5e02, \u9999\u5ddd\u770c, JP",
    "qs:gn_namadm1":"17",
    "qs:local_max":196,
    "qs:local_sum":426,
    "qs:localhoods":5,
    "qs:name":"\uff15\u4e01\u76ee",
    "qs:name_adm0":"\u65e5\u672c",
    "qs:name_adm1":"\u9999\u5ddd\u770c",
    "qs:name_en":"Dokichohigashi 5 Chome",
    "qs:name_lau":"\u571f\u5668\u753a\u6771",
    "qs:name_local":"\u4e38\u4e80\u5e02",
    "qs:photo_max":30,
    "qs:photo_sum":58,
    "qs:placetype":"Suburb",
    "qs:quad_count":8,
    "qs:woe_adm0":23424856,
    "qs:woe_adm1":2345866,
    "qs:woe_adm2":0,
    "qs:woe_lau":28478612,
    "qs:woe_local":1111590,
    "qs:woe_ver":"7.10.0",
    "wof:lang":[
        "jpn"
    ],
    "wof:name":"\uff15\u4e01\u76ee",
    "wof:placetype":"neighbourhood"
},
  "geometry": {"coordinates":[133.82094000000001,34.30904],"type":"Point"}
}