{
  "type": "Feature",
  "properties": {
    "gn:admin1_code":"12.0",
    "gn:admin2_code":"2128971.0",
    "gn:asciiname":"Toyosato",
    "gn:country_code":"JP",
    "gn:dem":15,
    "gn:feature_class":"P",
    "gn:feature_code":"PPL",
    "gn:name":"Toyosato",
    "gn:population":0,
    "gn:timezone":"Asia/Tokyo",
    "iso:country":"JP",
    "name:jpn_x_preferred":[
        "\u8c4a\u91cc"
    ],
    "name:jpn_x_variant":[
        "\u3068\u3088\u3055\u3068",
        "\u30c8\u30e8\u30b5\u30c8"
    ],
    "wof:name":"Toyosato",
    "wof:placetype":"locality"
},
  "geometry": {"coordinates":[145.71796000000001,43.38158],"type":"Point"}
}