{
  "type": "Feature",
  "properties": {
    "gn:admin1_code":"36",
    "gn:admin2_code":"1857590.0",
    "gn:asciiname":"Kohama",
    "gn:cc2":"JP",
    "gn:country_code":"JP",
    "gn:dem":73,
    "gn:feature_class":"P",
    "gn:feature_code":"PPL",
    "gn:name":"Kohama",
    "gn:population":0,
    "gn:timezone":"Asia/Tokyo",
    "iso:country":"JP",
    "name:und_x_variant":[
        "Kobama",
        "Kohama"
    ],
    "wof:name":"Kohama",
    "wof:placetype":"locality"
},
  "geometry": {"coordinates":[131.73333,34.66667],"type":"Point"}
}