{
  "type": "Feature",
  "properties": {
    "gn:admin1_code":"21.0",
    "gn:admin2_code":"1848441.0",
    "gn:asciiname":"Nakao",
    "gn:country_code":"JP",
    "gn:dem":233,
    "gn:feature_class":"P",
    "gn:feature_code":"PPLL",
    "gn:name":"Nakao",
    "gn:population":0,
    "gn:timezone":"Asia/Tokyo",
    "iso:country":"JP",
    "name:fra_x_preferred":[
        "Nakao"
    ],
    "name:jpn_x_preferred":[
        "\u4e2d\u5c3e"
    ],
    "name:jpn_x_variant":[
        "\u306a\u304b\u304a",
        "\u30ca\u30ab\u30aa"
    ],
    "name:kor_x_preferred":[
        "\ub098\uce74\uc624"
    ],
    "wof:name":"Nakao",
    "wof:placetype":"locality"
},
  "geometry": {"coordinates":[130.79325,32.57193],"type":"Point"}
}