{
  "type": "Feature",
  "properties": {
    "gn:admin1_code":"21.0",
    "gn:admin2_code":"7412708.0",
    "gn:admin3_code":"43514.0",
    "gn:asciiname":"Kaminishibyu",
    "gn:country_code":"JP",
    "gn:dem":147,
    "gn:feature_class":"P",
    "gn:feature_code":"PPLL",
    "gn:name":"Kaminishiby\u016b",
    "gn:population":0,
    "gn:timezone":"Asia/Tokyo",
    "iso:country":"JP",
    "name:jpn_x_preferred":[
        "\u4e0a\u897f\u5225\u5e9c"
    ],
    "name:jpn_x_variant":[
        "\u304b\u307f\u306b\u3057\u3073\u3085\u3046",
        "\u30ab\u30df\u30cb\u30b7\u30d3\u30e5\u30a6"
    ],
    "name:und_x_variant":[
        "Kaminishiby\u016b"
    ],
    "wof:name":"Kaminishibyu",
    "wof:placetype":"locality"
},
  "geometry": {"coordinates":[130.88335000000001,32.22424],"type":"Point"}
}