{
  "type": "Feature",
  "properties": {
    "gn:admin1_code":"12.0",
    "gn:admin2_code":"2130704.0",
    "gn:asciiname":"Sumiyoshi",
    "gn:cc2":"JP",
    "gn:country_code":"JP",
    "gn:dem":158,
    "gn:feature_class":"P",
    "gn:feature_code":"PPL",
    "gn:name":"Sumiyoshi",
    "gn:population":0,
    "gn:timezone":"Asia/Tokyo",
    "iso:country":"JP",
    "name:und_x_variant":[
        "Kamiakabira",
        "Naka-akabira",
        "Sumiyoshi"
    ],
    "wof:name":"Sumiyoshi",
    "wof:placetype":"locality"
},
  "geometry": {"coordinates":[142.01667,43.55],"type":"Point"}
}