{
  "type": "Feature",
  "properties": {
    "gn:admin1_code":"21.0",
    "gn:admin2_code":"1850743.0",
    "gn:asciiname":"Kamihazama",
    "gn:country_code":"JP",
    "gn:dem":1,
    "gn:feature_class":"P",
    "gn:feature_code":"PPLL",
    "gn:name":"Kamihazama",
    "gn:population":0,
    "gn:timezone":"Asia/Tokyo",
    "iso:country":"JP",
    "name:jpn_x_preferred":[
        "\u4e0a\u8feb\u9593"
    ],
    "name:jpn_x_variant":[
        "\u304b\u307f\u306f\u3056\u307e",
        "\u30ab\u30df\u30cf\u30b6\u30de"
    ],
    "wof:name":"Kamihazama",
    "wof:placetype":"locality"
},
  "geometry": {"coordinates":[130.57886000000002,32.94172],"type":"Point"}
}