{
  "type": "Feature",
  "properties": {
    "gn:admin1_code":"21.0",
    "gn:admin2_code":"7413150.0",
    "gn:asciiname":"Suya",
    "gn:country_code":"JP",
    "gn:dem":255,
    "gn:feature_class":"P",
    "gn:feature_code":"PPLL",
    "gn:name":"Suya",
    "gn:population":0,
    "gn:timezone":"Asia/Tokyo",
    "iso:country":"JP",
    "name:ara_x_preferred":[
        "\u0633\u064a\u0631\u064a\u0647"
    ],
    "name:ben_x_preferred":[
        "\u09b8\u09c1\u09af\u09bc\u09be"
    ],
    "name:fra_x_preferred":[
        "Suya"
    ],
    "name:jpn_x_preferred":[
        "\u9808\u5c4b"
    ],
    "name:jpn_x_variant":[
        "\u3059\u3084",
        "\u30b9\u30e4"
    ],
    "name:por_x_preferred":[
        "Suya"
    ],
    "wof:name":"Suya",
    "wof:placetype":"locality"
},
  "geometry": {"coordinates":[130.74809999999999,33.12096],"type":"Point"}
}