{
  "type": "Feature",
  "properties": {
    "gn:admin1_code":"43.0",
    "gn:admin2_code":"7411114.0",
    "gn:asciiname":"Higashiyamada",
    "gn:country_code":"JP",
    "gn:dem":106,
    "gn:feature_class":"P",
    "gn:feature_code":"PPL",
    "gn:name":"Higashiyamada",
    "gn:population":0,
    "gn:timezone":"Asia/Tokyo",
    "iso:country":"JP",
    "name:jpn_x_preferred":[
        "\u6771\u5c71\u7530"
    ],
    "wof:name":"Higashiyamada",
    "wof:placetype":"locality"
},
  "geometry": {"coordinates":[135.36597,34.29066],"type":"Point"}
}