{
  "type": "Feature",
  "properties": {
    "gn:admin1_code":"3.0",
    "gn:admin2_code":"2130654.0",
    "gn:asciiname":"Oyasawa",
    "gn:country_code":"JP",
    "gn:dem":20,
    "gn:feature_class":"P",
    "gn:feature_code":"PPL",
    "gn:name":"\u014cyasawa",
    "gn:population":0,
    "gn:timezone":"Asia/Tokyo",
    "iso:country":"JP",
    "name:jpn_x_preferred":[
        "\u5927\u77e2\u6ca2"
    ],
    "name:jpn_x_variant":[
        "\u304a\u304a\u3084\u3055\u308f",
        "\u30aa\u30aa\u30e4\u30b5\u30ef"
    ],
    "name:und_x_variant":[
        "\u014cyasawa"
    ],
    "wof:name":"Oyasawa",
    "wof:placetype":"locality"
},
  "geometry": {"coordinates":[140.7748,40.78306],"type":"Point"}
}