{
  "type": "Feature",
  "properties": {
    "iso:country":"JP",
    "name:eng_x_preferred":[
        "Tsubetsu Town"
    ],
    "name:jpn_x_preferred":[
        "\u6d25\u5225\u753a"
    ],
    "qs:name":"\u6d25\u5225\u753a",
    "qs:name_adm0":"\u65e5\u672c",
    "qs:name_adm1":"\u5317\u6d77\u9053",
    "qs:photos":116,
    "qs:photos_1k":24,
    "qs:photos_9k":1,
    "qs:photos_9r":3,
    "qs:photos_all":116,
    "qs:photos_sr":3,
    "qs:placetype":"Town",
    "qs:pop_sr":"0",
    "wof:name":"Tsubetsu Town",
    "wof:placetype":"locality"
},
  "geometry": {"coordinates":[144.10119599999999,43.532091],"type":"Point"}
}