{
  "type": "Feature",
  "properties": {
    "gn:admin1_code":"3.0",
    "gn:admin2_code":"2128302.0",
    "gn:admin3_code":"2443.0",
    "gn:asciiname":"Ishigame",
    "gn:country_code":"JP",
    "gn:dem":170,
    "gn:feature_class":"P",
    "gn:feature_code":"PPL",
    "gn:name":"Ishigame",
    "gn:population":0,
    "gn:timezone":"Asia/Tokyo",
    "iso:country":"JP",
    "name:jpn_x_preferred":[
        "\u77f3\u4e80"
    ],
    "name:jpn_x_variant":[
        "\u3044\u3057\u304c\u3081",
        "\u30a4\u30b7\u30ac\u30e1"
    ],
    "wof:name":"Ishigame",
    "wof:placetype":"locality"
},
  "geometry": {"coordinates":[141.09868,40.30718],"type":"Point"}
}