{
  "type": "Feature",
  "properties": {
    "gn:admin1_code":"12.0",
    "gn:admin2_code":"2129373.0",
    "gn:admin3_code":"1661.0",
    "gn:asciiname":"Chippomanai",
    "gn:country_code":"JP",
    "gn:dem":66,
    "gn:feature_class":"P",
    "gn:feature_code":"PPLL",
    "gn:name":"Chippomanai",
    "gn:population":0,
    "gn:timezone":"Asia/Tokyo",
    "iso:country":"JP",
    "name:jpn_x_preferred":[
        "\u77e5\u65b9\u5b66"
    ],
    "name:jpn_x_variant":[
        "\u3061\u3063\u307d\u307e\u306a\u3044",
        "\u30c1\u30c3\u30dd\u30de\u30ca\u30a4"
    ],
    "wof:name":"Chippomanai",
    "wof:placetype":"locality"
},
  "geometry": {"coordinates":[144.73806999999999,42.93489],"type":"Point"}
}