{
  "type": "Feature",
  "properties": {
    "gn:admin1_code":"37.0",
    "gn:admin2_code":"1864104.0",
    "gn:asciiname":"Uehara",
    "gn:country_code":"JP",
    "gn:dem":441,
    "gn:feature_class":"P",
    "gn:feature_code":"PPLL",
    "gn:name":"Uehara",
    "gn:population":0,
    "gn:timezone":"Asia/Tokyo",
    "iso:country":"JP",
    "name:jpn_x_preferred":[
        "\u4e0a\u539f"
    ],
    "wof:name":"Uehara",
    "wof:placetype":"locality"
},
  "geometry": {"coordinates":[138.59974,35.29922],"type":"Point"}
}