{
  "type": "Feature",
  "properties": {
    "gn:admin1_code":"21.0",
    "gn:admin2_code":"1858418.0",
    "gn:admin3_code":"43105.0",
    "gn:asciiname":"Nanamoto",
    "gn:country_code":"JP",
    "gn:dem":89,
    "gn:feature_class":"P",
    "gn:feature_code":"PPLL",
    "gn:name":"Nanamoto",
    "gn:population":0,
    "gn:timezone":"Asia/Tokyo",
    "iso:country":"JP",
    "name:jpn_x_preferred":[
        "\u4e03\u672c"
    ],
    "name:jpn_x_variant":[
        "\u306a\u306a\u3082\u3068",
        "\u30ca\u30ca\u30e2\u30c8"
    ],
    "wof:name":"Nanamoto",
    "wof:placetype":"locality"
},
  "geometry": {"coordinates":[130.6619,32.90047],"type":"Point"}
}