{
  "type": "Feature",
  "properties": {
    "gn:admin1_code":"19.0",
    "gn:admin2_code":"1848350.0",
    "gn:admin3_code":"14106.0",
    "gn:asciiname":"Miyatacho",
    "gn:country_code":"JP",
    "gn:dem":8,
    "gn:feature_class":"P",
    "gn:feature_code":"PPL",
    "gn:name":"Miyatach\u014d",
    "gn:population":0,
    "gn:timezone":"Asia/Tokyo",
    "iso:country":"JP",
    "name:jpn_x_preferred":[
        "\u5bae\u7530\u753a"
    ],
    "name:jpn_x_variant":[
        "\u307f\u3084\u305f\u3061\u3087\u3046",
        "\u30df\u30e4\u30bf\u30c1\u30e7\u30a6"
    ],
    "name:und_x_variant":[
        "Miyatach\u014d"
    ],
    "wof:name":"Miyatacho",
    "wof:placetype":"locality"
},
  "geometry": {"coordinates":[139.60413,35.4591],"type":"Point"}
}