{
  "type": "Feature",
  "properties": {
    "gn:admin1_code":"33.0",
    "gn:admin2_code":"7391363.0",
    "gn:asciiname":"Gedo",
    "gn:country_code":"JP",
    "gn:dem":13,
    "gn:feature_class":"P",
    "gn:feature_code":"PPLL",
    "gn:name":"Ged\u014d",
    "gn:population":0,
    "gn:timezone":"Asia/Tokyo",
    "iso:country":"JP",
    "name:jpn_x_preferred":[
        "\u4e0b\u7ae5"
    ],
    "name:und_x_variant":[
        "Ged\u014d"
    ],
    "wof:name":"Gedo",
    "wof:placetype":"locality"
},
  "geometry": {"coordinates":[130.07699,33.10695],"type":"Point"}
}