{
  "type": "Feature",
  "properties": {
    "gn:admin1_code":"17.0",
    "gn:admin2_code":"1851654.0",
    "gn:admin3_code":"37324.0",
    "gn:asciiname":"Nyube",
    "gn:country_code":"JP",
    "gn:dem":4,
    "gn:feature_class":"P",
    "gn:feature_code":"PPLL",
    "gn:name":"Ny\u016bbe",
    "gn:population":0,
    "gn:timezone":"Asia/Tokyo",
    "iso:country":"JP",
    "name:jpn_x_preferred":[
        "\u5165\u90e8"
    ],
    "name:und_x_variant":[
        "Ny\u016bbe",
        "Nyube"
    ],
    "wof:name":"Nyube",
    "wof:placetype":"locality"
},
  "geometry": {"coordinates":[134.20345,34.48232],"type":"Point"}
}