{
  "type": "Feature",
  "properties": {
    "gn:admin1_code":"47",
    "gn:admin2_code":"1858371.0",
    "gn:admin3_code":"47301.0",
    "gn:asciiname":"Yona",
    "gn:country_code":"JP",
    "gn:dem":10,
    "gn:feature_class":"P",
    "gn:feature_code":"PPL",
    "gn:name":"Yona",
    "gn:population":0,
    "gn:timezone":"Asia/Tokyo",
    "iso:country":"JP",
    "name:cat_x_preferred":[
        "Yavana"
    ],
    "name:ell_x_preferred":[
        "\u0393\u03b9\u03cc\u03bd\u03b1"
    ],
    "name:ind_x_preferred":[
        "Yona"
    ],
    "name:jpn_x_preferred":[
        "\u4e0e\u90a3"
    ],
    "name:jpn_x_variant":[
        "\u3088\u306a"
    ],
    "name:kan_x_preferred":[
        "\u0caf\u0cb5\u0ca8"
    ],
    "name:nld_x_preferred":[
        "Yavana"
    ],
    "name:pol_x_preferred":[
        "Jawanowie"
    ],
    "name:rus_x_preferred":[
        "\u0419\u043e\u043d\u0430"
    ],
    "name:tam_x_preferred":[
        "\u0baf\u0bb5\u0ba9\u0bb0\u0bcd"
    ],
    "name:und_x_variant":[
        "Yuna",
        "Kana",
        "Yona"
    ],
    "wof:name":"Yona",
    "wof:placetype":"locality"
},
  "geometry": {"coordinates":[128.20463000000001,26.76476],"type":"Point"}
}