{
  "type": "Feature",
  "properties": {
    "gn:admin1_code":"47",
    "gn:admin2_code":"1858371.0",
    "gn:admin3_code":"47301.0",
    "gn:asciiname":"Yona",
    "gn:country_code":"JP",
    "gn:dem":10,
    "gn:feature_class":"P",
    "gn:feature_code":"PPL",
    "gn:name":"Yona",
    "gn:population":0,
    "gn:timezone":"Asia/Tokyo",
    "iso:country":"JP",
    "name:jpn_x_preferred":[
        "\u4e0e\u90a3"
    ],
    "name:jpn_x_variant":[
        "\u3088\u306a"
    ],
    "name:und_x_variant":[
        "Yuna",
        "Kana",
        "Yona"
    ],
    "wof:name":"Yona",
    "wof:placetype":"locality"
},
  "geometry": {"coordinates":[128.20463000000001,26.76476],"type":"Point"}
}