{
  "type": "Feature",
  "properties": {
    "gn:admin1_code":"37.0",
    "gn:admin2_code":"1860327.0",
    "gn:admin3_code":"22304.0",
    "gn:asciiname":"Kamigamo",
    "gn:country_code":"JP",
    "gn:dem":36,
    "gn:feature_class":"P",
    "gn:feature_code":"PPL",
    "gn:name":"Kamigamo",
    "gn:population":0,
    "gn:timezone":"Asia/Tokyo",
    "iso:country":"JP",
    "name:jpn_x_preferred":[
        "\u4e0a\u8cc0\u8302"
    ],
    "wof:name":"Kamigamo",
    "wof:placetype":"locality"
},
  "geometry": {"coordinates":[138.86358999999999,34.66188],"type":"Point"}
}