{
  "type": "Feature",
  "properties": {
    "gn:admin1_code":"24.0",
    "gn:admin2_code":"2112574.0",
    "gn:asciiname":"Sawada",
    "gn:country_code":"JP",
    "gn:dem":6,
    "gn:feature_class":"P",
    "gn:feature_code":"PPL",
    "gn:name":"Sawada",
    "gn:population":0,
    "gn:timezone":"Asia/Tokyo",
    "iso:country":"JP",
    "name:jpn_x_preferred":[
        "\u6ca2\u7530"
    ],
    "name:jpn_x_variant":[
        "\u3055\u308f\u3060",
        "\u30b5\u30ef\u30c0"
    ],
    "wof:name":"Sawada",
    "wof:placetype":"locality"
},
  "geometry": {"coordinates":[141.23926,38.47504],"type":"Point"}
}