{
  "type": "Feature",
  "properties": {
    "gn:admin1_code":"42",
    "gn:admin2_code":"1862610.0",
    "gn:asciiname":"Ozakai",
    "gn:country_code":"JP",
    "gn:dem":20,
    "gn:feature_class":"P",
    "gn:feature_code":"PPL",
    "gn:name":"\u014czakai",
    "gn:population":0,
    "gn:timezone":"Asia/Tokyo",
    "iso:country":"JP",
    "name:jpn_x_preferred":[
        "\u5927\u5883"
    ],
    "name:und_x_variant":[
        "Osakai",
        "\u014czakai"
    ],
    "wof:name":"Ozakai",
    "wof:placetype":"locality"
},
  "geometry": {"coordinates":[137.02705,36.92295],"type":"Point"}
}