{
  "type": "Feature",
  "properties": {
    "gn:admin1_code":"21",
    "gn:admin2_code":"1864973.0",
    "gn:asciiname":"Ichinomiyamachi-sakanashi",
    "gn:country_code":"JP",
    "gn:dem":538,
    "gn:feature_class":"P",
    "gn:feature_code":"PPL",
    "gn:name":"Ichinomiyamachi-sakanashi",
    "gn:population":0,
    "gn:timezone":"Asia/Tokyo",
    "iso:country":"JP",
    "name:jpn_x_preferred":[
        "\u4e00\u306e\u5bae\u753a\u5742\u68a8"
    ],
    "name:jpn_x_variant":[
        "\u3044\u3061\u306e\u307f\u3084\u307e\u3061\u3055\u304b\u306a\u3057",
        "\u30a4\u30c1\u30ce\u30df\u30e4\u30de\u30c1\u30b5\u30ab\u30ca\u30b7"
    ],
    "name:und_x_variant":[
        "Sakanashi"
    ],
    "wof:name":"Ichinomiyamachi-sakanashi",
    "wof:placetype":"locality"
},
  "geometry": {"coordinates":[131.14028000000002,32.93889],"type":"Point"}
}