{
  "type": "Feature",
  "properties": {
    "gn:admin1_code":"17.0",
    "gn:admin2_code":"1851095.0",
    "gn:asciiname":"Ikushimacho",
    "gn:country_code":"JP",
    "gn:dem":11,
    "gn:feature_class":"P",
    "gn:feature_code":"PPL",
    "gn:name":"Ikushimach\u014d",
    "gn:population":0,
    "gn:timezone":"Asia/Tokyo",
    "iso:country":"JP",
    "name:jpn_x_preferred":[
        "\u751f\u5cf6\u753a"
    ],
    "name:und_x_variant":[
        "Ikushimach\u014d",
        "Ikushima"
    ],
    "wof:name":"Ikushimacho",
    "wof:placetype":"locality"
},
  "geometry": {"coordinates":[133.96482,34.35977],"type":"Point"}
}