{
  "type": "Feature",
  "properties": {
    "gn:admin1_code":"32.0",
    "gn:admin2_code":"1850907.0",
    "gn:asciiname":"Niryo",
    "gn:country_code":"JP",
    "gn:dem":286,
    "gn:feature_class":"P",
    "gn:feature_code":"PPL",
    "gn:name":"Niry\u014d",
    "gn:population":0,
    "gn:timezone":"Asia/Tokyo",
    "iso:country":"JP",
    "name:jpn_x_preferred":[
        "\u4e8c\u6599"
    ],
    "name:und_x_variant":[
        "Niry\u014d"
    ],
    "wof:name":"Niryo",
    "wof:placetype":"locality"
},
  "geometry": {"coordinates":[135.57458,34.94385],"type":"Point"}
}