{
  "type": "Feature",
  "properties": {
    "gn:admin1_code":"24.0",
    "gn:admin2_code":"7446984.0",
    "gn:admin3_code":"4341.0",
    "gn:asciiname":"Kinumamachi",
    "gn:country_code":"JP",
    "gn:dem":17,
    "gn:feature_class":"P",
    "gn:feature_code":"PPL",
    "gn:name":"Kinumamachi",
    "gn:population":0,
    "gn:timezone":"Asia/Tokyo",
    "iso:country":"JP",
    "wof:name":"Kinumamachi",
    "wof:placetype":"locality"
},
  "geometry": {"coordinates":[140.78333000000001,37.93333],"type":"Point"}
}