{
  "type": "Feature",
  "properties": {
    "gn:admin1_code":"3.0",
    "gn:admin2_code":"2129393.0",
    "gn:asciiname":"Ishinazaka",
    "gn:country_code":"JP",
    "gn:dem":77,
    "gn:feature_class":"P",
    "gn:feature_code":"PPL",
    "gn:name":"Ishinazaka",
    "gn:population":0,
    "gn:timezone":"Asia/Tokyo",
    "iso:country":"JP",
    "name:jpn_x_preferred":[
        "\u77f3\u540d\u5742"
    ],
    "name:jpn_x_variant":[
        "\u3044\u3057\u306a\u3056\u304b",
        "\u30a4\u30b7\u30ca\u30b6\u30ab"
    ],
    "wof:name":"Ishinazaka",
    "wof:placetype":"locality"
},
  "geometry": {"coordinates":[140.63248999999999,40.62578],"type":"Point"}
}