{
  "type": "Feature",
  "properties": {
    "gn:admin1_code":"21.0",
    "gn:admin2_code":"1859488.0",
    "gn:asciiname":"Kamimura",
    "gn:country_code":"JP",
    "gn:dem":173,
    "gn:feature_class":"P",
    "gn:feature_code":"PPLL",
    "gn:name":"Kamimura",
    "gn:population":0,
    "gn:timezone":"Asia/Tokyo",
    "iso:country":"JP",
    "name:jpn_x_preferred":[
        "\u4e0a\u6751"
    ],
    "name:jpn_x_variant":[
        "\u304b\u307f\u3080\u3089",
        "\u30ab\u30df\u30e0\u30e9"
    ],
    "wof:name":"Kamimura",
    "wof:placetype":"locality"
},
  "geometry": {"coordinates":[130.84049999999999,33.01694000000001],"type":"Point"}
}