{
  "type": "Feature",
  "properties": {
    "gn:admin1_code":"4.0",
    "gn:admin2_code":"1864901.0",
    "gn:admin3_code":"12463.0",
    "gn:asciiname":"Ichibuse",
    "gn:country_code":"JP",
    "gn:dem":10,
    "gn:feature_class":"P",
    "gn:feature_code":"PPLL",
    "gn:name":"Ichibuse",
    "gn:population":0,
    "gn:timezone":"Asia/Tokyo",
    "iso:country":"JP",
    "name:jpn_x_preferred":[
        "\u5e02\u90e8\u702c"
    ],
    "name:jpn_x_variant":[
        "\u3044\u3061\u3076\u305b",
        "\u30a4\u30c1\u30d6\u30bb"
    ],
    "wof:name":"Ichibuse",
    "wof:placetype":"locality"
},
  "geometry": {"coordinates":[139.8415,35.10378],"type":"Point"}
}