{
  "type": "Feature",
  "properties": {
    "gn:admin1_code":"4.0",
    "gn:admin2_code":"8304237.0",
    "gn:asciiname":"Gogo",
    "gn:country_code":"JP",
    "gn:dem":50,
    "gn:feature_class":"P",
    "gn:feature_code":"PPLL",
    "gn:name":"Gog\u014d",
    "gn:population":0,
    "gn:timezone":"Asia/Tokyo",
    "iso:country":"JP",
    "name:jpn_x_preferred":[
        "\u4e94\u90f7"
    ],
    "name:jpn_x_variant":[
        "\u3054\u3054\u3046",
        "\u30b4\u30b4\u30a6"
    ],
    "name:und_x_variant":[
        "Gog\u014d"
    ],
    "wof:name":"Gogo",
    "wof:placetype":"locality"
},
  "geometry": {"coordinates":[140.09145000000001,35.3662],"type":"Point"}
}