{
  "type": "Feature",
  "properties": {
    "gn:admin1_code":"18.0",
    "gn:admin2_code":"8300556.0",
    "gn:asciiname":"Aritakecho",
    "gn:country_code":"JP",
    "gn:dem":273,
    "gn:feature_class":"P",
    "gn:feature_code":"PPL",
    "gn:name":"Aritakech\u014d",
    "gn:population":0,
    "gn:timezone":"Asia/Tokyo",
    "iso:country":"JP",
    "name:jpn_x_preferred":[
        "\u6709\u6b66\u753a"
    ],
    "name:und_x_variant":[
        "Aritakech\u014d"
    ],
    "wof:name":"Aritakecho",
    "wof:placetype":"locality"
},
  "geometry": {"coordinates":[130.79511000000002,31.42493],"type":"Point"}
}