{
  "type": "Feature",
  "properties": {
    "gn:admin1_code":"19.0",
    "gn:admin2_code":"1848308.0",
    "gn:asciiname":"Yoshikuracho",
    "gn:country_code":"JP",
    "gn:dem":30,
    "gn:feature_class":"P",
    "gn:feature_code":"PPL",
    "gn:name":"Yoshikurach\u014d",
    "gn:population":0,
    "gn:timezone":"Asia/Tokyo",
    "iso:country":"JP",
    "name:jpn_x_preferred":[
        "\u5409\u5009\u753a"
    ],
    "name:jpn_x_variant":[
        "\u3088\u3057\u304f\u3089\u3061\u3087\u3046",
        "\u30e8\u30b7\u30af\u30e9\u30c1\u30e7\u30a6"
    ],
    "name:und_x_variant":[
        "Yoshikurach\u014d"
    ],
    "wof:name":"Yoshikuracho",
    "wof:placetype":"locality"
},
  "geometry": {"coordinates":[139.64443,35.28566],"type":"Point"}
}