{
  "type": "Feature",
  "properties": {
    "gn:admin1_code":"2.0",
    "gn:admin2_code":"2128783.0",
    "gn:asciiname":"Sotokawara",
    "gn:country_code":"JP",
    "gn:dem":49,
    "gn:feature_class":"P",
    "gn:feature_code":"PPL",
    "gn:name":"Sotokawara",
    "gn:population":0,
    "gn:timezone":"Asia/Tokyo",
    "iso:country":"JP",
    "name:jpn_x_preferred":[
        "\u5916\u5ddd\u539f"
    ],
    "wof:name":"Sotokawara",
    "wof:placetype":"locality"
},
  "geometry": {"coordinates":[140.44802000000001,40.26506],"type":"Point"}
}