{
  "type": "Feature",
  "properties": {
    "gn:admin1_code":"21.0",
    "gn:admin2_code":"1858418.0",
    "gn:admin3_code":"43103.0",
    "gn:asciiname":"Yokote",
    "gn:country_code":"JP",
    "gn:dem":9,
    "gn:feature_class":"P",
    "gn:feature_code":"PPL",
    "gn:name":"Yokote",
    "gn:population":0,
    "gn:timezone":"Asia/Tokyo",
    "iso:country":"JP",
    "name:jpn_x_preferred":[
        "\u6a2a\u624b"
    ],
    "name:jpn_x_variant":[
        "\u3088\u3053\u3066",
        "\u30e8\u30b3\u30c6"
    ],
    "wof:name":"Yokote",
    "wof:placetype":"locality"
},
  "geometry": {"coordinates":[130.68847,32.80138],"type":"Point"}
}