{
  "type": "Feature",
  "properties": {
    "gn:admin1_code":"12.0",
    "gn:admin2_code":"2127415.0",
    "gn:asciiname":"Shimizusawanochi",
    "gn:country_code":"JP",
    "gn:dem":170,
    "gn:feature_class":"P",
    "gn:feature_code":"PPL",
    "gn:name":"Shimizusawan\u014dchi",
    "gn:population":0,
    "gn:timezone":"Asia/Tokyo",
    "iso:country":"JP",
    "wof:name":"Shimizusawanochi",
    "wof:placetype":"locality"
},
  "geometry": {"coordinates":[142.01667,42.96667],"type":"Point"}
}