{
  "type": "Feature",
  "properties": {
    "gn:admin1_code":"34.0",
    "gn:admin2_code":"1861470.0",
    "gn:admin3_code":"11324.0",
    "gn:asciiname":"Motomasu",
    "gn:country_code":"JP",
    "gn:dem":47,
    "gn:feature_class":"P",
    "gn:feature_code":"PPLL",
    "gn:name":"Motomasu",
    "gn:population":0,
    "gn:timezone":"Asia/Tokyo",
    "iso:country":"JP",
    "name:jpn_x_preferred":[
        "\u4e0b\u9952"
    ],
    "name:jpn_x_variant":[
        "\u3082\u3068\u307e\u3059"
    ],
    "wof:name":"Motomasu",
    "wof:placetype":"locality"
},
  "geometry": {"coordinates":[139.50728999999998,35.82402000000001],"type":"Point"}
}