{
  "type": "Feature",
  "properties": {
    "gn:admin1_code":"27.0",
    "gn:admin2_code":"1862734.0",
    "gn:admin3_code":"42323.0",
    "gn:asciiname":"Yumutago",
    "gn:country_code":"JP",
    "gn:dem":61,
    "gn:feature_class":"P",
    "gn:feature_code":"PPL",
    "gn:name":"Yumutag\u014d",
    "gn:population":0,
    "gn:timezone":"Asia/Tokyo",
    "iso:country":"JP",
    "name:jpn_x_preferred":[
        "\u6e6f\u7121\u7530\u90f7"
    ],
    "name:und_x_variant":[
        "Yumutag\u014d"
    ],
    "wof:name":"Yumutago",
    "wof:placetype":"locality"
},
  "geometry": {"coordinates":[129.91741999999999,33.14198],"type":"Point"}
}