{
  "type": "Feature",
  "properties": {
    "gn:admin1_code":"16.0",
    "gn:admin2_code":"2128940.0",
    "gn:asciiname":"Honda",
    "gn:country_code":"JP",
    "gn:dem":245,
    "gn:feature_class":"P",
    "gn:feature_code":"PPL",
    "gn:name":"Honda",
    "gn:population":0,
    "gn:timezone":"Asia/Tokyo",
    "iso:country":"JP",
    "name:jpn_x_preferred":[
        "\u672c\u7530"
    ],
    "name:jpn_x_variant":[
        "\u307b\u3093\u3060",
        "\u30db\u30f3\u30c0"
    ],
    "wof:name":"Honda",
    "wof:placetype":"locality"
},
  "geometry": {"coordinates":[141.17861000000005,40.26172],"type":"Point"}
}