{
  "type": "Feature",
  "properties": {
    "gn:admin1_code":"35.0",
    "gn:admin2_code":"1853552.0",
    "gn:asciiname":"Honmarucho",
    "gn:country_code":"JP",
    "gn:dem":89,
    "gn:feature_class":"P",
    "gn:feature_code":"PPL",
    "gn:name":"Honmaruch\u014d",
    "gn:population":0,
    "gn:timezone":"Asia/Tokyo",
    "iso:country":"JP",
    "name:jpn_x_preferred":[
        "\u672c\u4e38\u753a"
    ],
    "name:und_x_variant":[
        "Honmaruch\u014d"
    ],
    "wof:name":"Honmarucho",
    "wof:placetype":"locality"
},
  "geometry": {"coordinates":[135.89336,34.99276],"type":"Point"}
}