{
  "type": "Feature",
  "properties": {
    "gn:admin1_code":"4.0",
    "gn:admin2_code":"2111211.0",
    "gn:asciiname":"Shinmei",
    "gn:country_code":"JP",
    "gn:dem":2,
    "gn:feature_class":"P",
    "gn:feature_code":"PPLL",
    "gn:name":"Shinmei",
    "gn:population":0,
    "gn:timezone":"Asia/Tokyo",
    "iso:country":"JP",
    "name:jpn_x_preferred":[
        "\u795e\u660e"
    ],
    "name:jpn_x_variant":[
        "\u3057\u3093\u3081\u3044",
        "\u30b7\u30f3\u30e1\u30a4"
    ],
    "wof:name":"Shinmei",
    "wof:placetype":"locality"
},
  "geometry": {"coordinates":[140.39845,35.48670999999999],"type":"Point"}
}