{
  "type": "Feature",
  "properties": {
    "gn:admin1_code":"26",
    "gn:admin2_code":"1862841.0",
    "gn:admin3_code":"20448.0",
    "gn:asciiname":"Kamiikusaka",
    "gn:country_code":"JP",
    "gn:dem":555,
    "gn:feature_class":"P",
    "gn:feature_code":"PPL",
    "gn:name":"Kamiikusaka",
    "gn:population":0,
    "gn:timezone":"Asia/Tokyo",
    "iso:country":"JP",
    "name:jpn_x_preferred":[
        "\u4e0a\u751f\u5742"
    ],
    "name:und_x_variant":[
        "Kami-ikusaka",
        "Kamiikusaka"
    ],
    "wof:name":"Kamiikusaka",
    "wof:placetype":"locality"
},
  "geometry": {"coordinates":[137.93333000000001,36.41667],"type":"Point"}
}