{
  "type": "Feature",
  "properties": {
    "gn:admin1_code":"47",
    "gn:admin2_code":"1856061.0",
    "gn:asciiname":"Miyazato",
    "gn:country_code":"JP",
    "gn:dem":8,
    "gn:feature_class":"P",
    "gn:feature_code":"PPL",
    "gn:name":"Miyazato",
    "gn:population":0,
    "gn:timezone":"Asia/Tokyo",
    "iso:country":"JP",
    "name:jpn_x_preferred":[
        "\u5bae\u91cc"
    ],
    "name:und_x_variant":[
        "Miyasato",
        "Miy\u0101zatu",
        "Miyazato"
    ],
    "wof:name":"Miyazato",
    "wof:placetype":"locality"
},
  "geometry": {"coordinates":[127.96827,26.59534],"type":"Point"}
}