{
  "type": "Feature",
  "properties": {
    "gn:admin1_code":"3.0",
    "gn:admin2_code":"7439929.0",
    "gn:admin3_code":"2343.0",
    "gn:asciiname":"Kamitashiro",
    "gn:country_code":"JP",
    "gn:dem":127,
    "gn:feature_class":"P",
    "gn:feature_code":"PPL",
    "gn:name":"Kamitashiro",
    "gn:population":0,
    "gn:timezone":"Asia/Tokyo",
    "iso:country":"JP",
    "name:jpn_x_preferred":[
        "\u4e0a\u7530\u4ee3"
    ],
    "name:jpn_x_variant":[
        "\u304b\u307f\u305f\u3057\u308d",
        "\u30ab\u30df\u30bf\u30b7\u30ed"
    ],
    "wof:name":"Kamitashiro",
    "wof:placetype":"locality"
},
  "geometry": {"coordinates":[140.29599999999999,40.57577],"type":"Point"}
}