{
  "type": "Feature",
  "properties": {
    "gn:admin1_code":"15.0",
    "gn:admin2_code":"1860240.0",
    "gn:asciiname":"Higashimachi",
    "gn:country_code":"JP",
    "gn:dem":146,
    "gn:feature_class":"P",
    "gn:feature_code":"PPL",
    "gn:name":"Higashimachi",
    "gn:population":0,
    "gn:timezone":"Asia/Tokyo",
    "iso:country":"JP",
    "name:jpn_x_preferred":[
        "\u6771\u753a"
    ],
    "wof:name":"Higashimachi",
    "wof:placetype":"locality"
},
  "geometry": {"coordinates":[136.75703999999999,36.49347],"type":"Point"}
}