{
  "type": "Feature",
  "properties": {
    "gn:admin1_code":"2.0",
    "gn:admin2_code":"2113122.0",
    "gn:asciiname":"Kanaashi-oshimizu",
    "gn:country_code":"JP",
    "gn:dem":10,
    "gn:feature_class":"P",
    "gn:feature_code":"PPL",
    "gn:name":"Kanaashi-\u014dshimizu",
    "gn:population":0,
    "gn:timezone":"Asia/Tokyo",
    "iso:country":"JP",
    "name:jpn_x_preferred":[
        "\u91d1\u8db3\u5927\u6e05\u6c34"
    ],
    "name:jpn_x_variant":[
        "\u304b\u306a\u3042\u3057\u304a\u304a\u3057\u307f\u305a",
        "\u30ab\u30ca\u30a2\u30b7\u30aa\u30aa\u30b7\u30df\u30ba"
    ],
    "name:und_x_variant":[
        "Kanaashi-\u014dshimizu"
    ],
    "wof:name":"Kanaashi-oshimizu",
    "wof:placetype":"locality"
},
  "geometry": {"coordinates":[140.05213999999998,39.84252],"type":"Point"}
}