{
  "type": "Feature",
  "properties": {
    "gn:admin1_code":"7.0",
    "gn:admin2_code":"7406950.0",
    "gn:admin3_code":"40625.0",
    "gn:asciiname":"Nakahonjo",
    "gn:country_code":"JP",
    "gn:dem":24,
    "gn:feature_class":"P",
    "gn:feature_code":"PPLL",
    "gn:name":"Nakahonj\u014d",
    "gn:population":0,
    "gn:timezone":"Asia/Tokyo",
    "iso:country":"JP",
    "name:jpn_x_preferred":[
        "\u4e2d\u672c\u5e84"
    ],
    "name:und_x_variant":[
        "Nakahonj\u014d"
    ],
    "wof:name":"Nakahonjo",
    "wof:placetype":"locality"
},
  "geometry": {"coordinates":[130.94012000000001,33.65255],"type":"Point"}
}