{
  "type": "Feature",
  "properties": {
    "gn:admin1_code":"7.0",
    "gn:admin2_code":"1859888.0",
    "gn:asciiname":"Sugu-minami",
    "gn:country_code":"JP",
    "gn:dem":21,
    "gn:feature_class":"P",
    "gn:feature_code":"PPL",
    "gn:name":"Sugu-minami",
    "gn:population":0,
    "gn:timezone":"Asia/Tokyo",
    "iso:country":"JP",
    "name:jpn_x_preferred":[
        "\u9808\u7396\u5357"
    ],
    "wof:name":"Sugu-minami",
    "wof:placetype":"locality"
},
  "geometry": {"coordinates":[130.44607999999999,33.53905],"type":"Point"}
}