{
  "type": "Feature",
  "properties": {
    "gn:admin1_code":"15",
    "gn:admin2_code":"7467879.0",
    "gn:asciiname":"Ishizakimachi",
    "gn:country_code":"JP",
    "gn:dem":6,
    "gn:feature_class":"P",
    "gn:feature_code":"PPL",
    "gn:name":"Ishizakimachi",
    "gn:population":0,
    "gn:timezone":"Asia/Tokyo",
    "iso:country":"JP",
    "name:jpn_x_preferred":[
        "\u77f3\u5d0e\u753a"
    ],
    "name:und_x_variant":[
        "Isosaki",
        "Ishisaki",
        "Ishizaki",
        "Ishizakimachi"
    ],
    "wof:name":"Ishizakimachi",
    "wof:placetype":"locality"
},
  "geometry": {"coordinates":[136.93143999999998,37.0757],"type":"Point"}
}