{
  "type": "Feature",
  "properties": {
    "iso:country":"JP",
    "name:eng_x_preferred":[
        "Ichinowari 1 Chome"
    ],
    "name:eng_x_variant":[
        "Ichinowari 1 Choume",
        "Ichinowari 1 Chome"
    ],
    "name:jpn_x_preferred":[
        "\uff11\u4e01\u76ee"
    ],
    "name:jpn_x_variant":[
        "\u3044\u3061\u306e\u308f\u308a \uff11\u3061\u3087\u3046\u3081",
        "\u4e00\u30ce\u5272 \uff11\u4e01\u76ee",
        "\uff11\u3061\u3087\u3046\u3081"
    ],
    "qs:gn_adm0_cc":"JP",
    "qs:gn_local":1859884,
    "qs:gn_nam_loc":"\u6625\u65e5\u90e8\u5e02, \u57fc\u7389\u770c, JP",
    "qs:gn_namadm1":"34",
    "qs:local_max":144,
    "qs:local_sum":149,
    "qs:localhoods":2,
    "qs:name":"\uff11\u4e01\u76ee",
    "qs:name_adm0":"\u65e5\u672c",
    "qs:name_adm1":"\u57fc\u7389\u770c",
    "qs:name_en":"Ichinowari 1 Chome",
    "qs:name_lau":"\u4e00\u30ce\u5272",
    "qs:name_local":"\u6625\u65e5\u90e8\u5e02",
    "qs:photo_max":5,
    "qs:photo_sum":5,
    "qs:placetype":"Suburb",
    "qs:quad_count":1,
    "qs:woe_adm0":23424856,
    "qs:woe_adm1":2345883,
    "qs:woe_adm2":0,
    "qs:woe_lau":28408802,
    "qs:woe_local":1117473,
    "qs:woe_ver":"7.10.0",
    "qs_pg:name":"\uff11\u4e01\u76ee",
    "qs_pg:name_adm0":"\u65e5\u672c",
    "qs_pg:name_adm1":"\u57fc\u7389\u770c",
    "qs_pg:photos":5,
    "qs_pg:photos_1k":1,
    "qs_pg:photos_9k":1,
    "qs_pg:photos_9r":1,
    "qs_pg:photos_all":5,
    "qs_pg:photos_sr":1,
    "qs_pg:pop_sr":0,
    "qs_pg:qs_pg_placetype":"neighbourhood",
    "qs_pg:qs_pg_placetype_gp":"Suburb",
    "qs_pg:woe_adm0":23424856,
    "woe:adm0_id":23424856,
    "woe:name_adm0":"\u65e5\u672c",
    "woe:name_adm1":"\u57fc\u7389\u770c",
    "woe:placetype":"Suburb",
    "wof:lang":[
        "jpn"
    ],
    "wof:name":"\uff11\u4e01\u76ee",
    "wof:placetype":"neighbourhood"
},
  "geometry": {"coordinates":[139.76532,35.962444],"type":"Point"}
}