{
  "type": "Feature",
  "properties": {
    "gn:admin1_code":"6.0",
    "gn:admin2_code":"1863982.0",
    "gn:asciiname":"Kamimorida",
    "gn:country_code":"JP",
    "gn:dem":11,
    "gn:feature_class":"P",
    "gn:feature_code":"PPL",
    "gn:name":"Kamimorida",
    "gn:population":0,
    "gn:timezone":"Asia/Tokyo",
    "iso:country":"JP",
    "name:jpn_x_preferred":[
        "\u4e0a\u68ee\u7530"
    ],
    "wof:name":"Kamimorida",
    "wof:placetype":"locality"
},
  "geometry": {"coordinates":[136.23339999999999,36.11223],"type":"Point"}
}