{
  "type": "Feature",
  "properties": {
    "gn:admin1_code":"45.0",
    "gn:admin2_code":"1852222.0",
    "gn:asciiname":"Sakaemachi",
    "gn:country_code":"JP",
    "gn:dem":25,
    "gn:feature_class":"P",
    "gn:feature_code":"PPL",
    "gn:name":"Sakaemachi",
    "gn:population":0,
    "gn:timezone":"Asia/Tokyo",
    "iso:country":"JP",
    "name:jpn_x_preferred":[
        "\u6804\u753a"
    ],
    "wof:name":"Sakaemachi",
    "wof:placetype":"locality"
},
  "geometry": {"coordinates":[130.92868999999999,33.96498],"type":"Point"}
}