{
  "type": "Feature",
  "properties": {
    "gn:admin1_code":"3.0",
    "gn:admin2_code":"2130200.0",
    "gn:asciiname":"Nakai",
    "gn:country_code":"JP",
    "gn:dem":18,
    "gn:feature_class":"P",
    "gn:feature_code":"PPL",
    "gn:name":"Nakai",
    "gn:population":0,
    "gn:timezone":"Asia/Tokyo",
    "iso:country":"JP",
    "name:jpn_x_preferred":[
        "\u4e2d\u5c45"
    ],
    "name:jpn_x_variant":[
        "\u306a\u304b\u3044",
        "\u30ca\u30ab\u30a4"
    ],
    "wof:name":"Nakai",
    "wof:placetype":"locality"
},
  "geometry": {"coordinates":[141.49063999999996,40.47688],"type":"Point"}
}