{
  "type": "Feature",
  "properties": {
    "gn:admin1_code":"33.0",
    "gn:admin2_code":"1854650.0",
    "gn:asciiname":"Ogimachi-kurihara",
    "gn:country_code":"JP",
    "gn:dem":88,
    "gn:feature_class":"P",
    "gn:feature_code":"PPL",
    "gn:name":"Ogimachi-kurihara",
    "gn:population":0,
    "gn:timezone":"Asia/Tokyo",
    "iso:country":"JP",
    "name:jpn_x_preferred":[
        "\u5c0f\u57ce\u753a\u6817\u539f"
    ],
    "wof:name":"Ogimachi-kurihara",
    "wof:placetype":"locality"
},
  "geometry": {"coordinates":[130.17571999999998,33.28422],"type":"Point"}
}