{
  "type": "Feature",
  "properties": {
    "gn:admin1_code":"19.0",
    "gn:admin2_code":"1848350.0",
    "gn:admin3_code":"14101.0",
    "gn:asciiname":"Tsukunocho",
    "gn:country_code":"JP",
    "gn:dem":8,
    "gn:feature_class":"P",
    "gn:feature_code":"PPL",
    "gn:name":"Tsukunoch\u014d",
    "gn:population":0,
    "gn:timezone":"Asia/Tokyo",
    "iso:country":"JP",
    "name:jpn_x_preferred":[
        "\u4f43\u91ce\u753a"
    ],
    "name:und_x_variant":[
        "Tsukunoch\u014d"
    ],
    "wof:name":"Tsukunocho",
    "wof:placetype":"locality"
},
  "geometry": {"coordinates":[139.67346000000001,35.51529],"type":"Point"}
}