{
  "type": "Feature",
  "properties": {
    "gn:admin1_code":"7.0",
    "gn:admin2_code":"1863955.0",
    "gn:admin3_code":"40131.0",
    "gn:asciiname":"Katsuma",
    "gn:country_code":"JP",
    "gn:dem":15,
    "gn:feature_class":"P",
    "gn:feature_code":"PPL",
    "gn:name":"Katsuma",
    "gn:population":0,
    "gn:timezone":"Asia/Tokyo",
    "iso:country":"JP",
    "name:jpn_x_preferred":[
        "\u52dd\u99ac"
    ],
    "wof:name":"Katsuma",
    "wof:placetype":"locality"
},
  "geometry": {"coordinates":[130.29883999999998,33.68277],"type":"Point"}
}