{
  "type": "Feature",
  "properties": {
    "gn:admin1_code":"15.0",
    "gn:admin2_code":"7467882.0",
    "gn:asciiname":"Fukushimamachi",
    "gn:country_code":"JP",
    "gn:dem":6,
    "gn:feature_class":"P",
    "gn:feature_code":"PPL",
    "gn:name":"Fukushimamachi",
    "gn:population":0,
    "gn:timezone":"Asia/Tokyo",
    "iso:country":"JP",
    "name:jpn_x_preferred":[
        "\u798f\u5cf6\u753a"
    ],
    "wof:name":"Fukushimamachi",
    "wof:placetype":"locality"
},
  "geometry": {"coordinates":[136.46965,36.45962],"type":"Point"}
}