{
  "type": "Feature",
  "properties": {
    "gn:admin1_code":"3.0",
    "gn:admin2_code":"2130056.0",
    "gn:asciiname":"Kamiyayoi",
    "gn:country_code":"JP",
    "gn:dem":179,
    "gn:feature_class":"P",
    "gn:feature_code":"PPL",
    "gn:name":"Kamiyayoi",
    "gn:population":0,
    "gn:timezone":"Asia/Tokyo",
    "iso:country":"JP",
    "name:jpn_x_preferred":[
        "\u4e0a\u5f25\u751f"
    ],
    "name:jpn_x_variant":[
        "\u304b\u307f\u3084\u3088\u3044",
        "\u30ab\u30df\u30e4\u30e8\u30a4"
    ],
    "wof:name":"Kamiyayoi",
    "wof:placetype":"locality"
},
  "geometry": {"coordinates":[140.37037000000001,40.65629000000001],"type":"Point"}
}