{
  "type": "Feature",
  "properties": {
    "gn:admin1_code":"18.0",
    "gn:admin2_code":"7383993.0",
    "gn:asciiname":"Urashibahara",
    "gn:country_code":"JP",
    "gn:dem":93,
    "gn:feature_class":"P",
    "gn:feature_code":"PPLL",
    "gn:name":"Urashibahara",
    "gn:population":0,
    "gn:timezone":"Asia/Tokyo",
    "iso:country":"JP",
    "name:jpn_x_preferred":[
        "\u6d66\u829d\u539f"
    ],
    "wof:name":"Urashibahara",
    "wof:placetype":"locality"
},
  "geometry": {"coordinates":[130.51136,31.24342],"type":"Point"}
}