{
  "type": "Feature",
  "properties": {
    "gn:admin1_code":"21.0",
    "gn:admin2_code":"1858418.0",
    "gn:admin3_code":"43105.0",
    "gn:asciiname":"Uekimachi-tarumizu",
    "gn:country_code":"JP",
    "gn:dem":79,
    "gn:feature_class":"P",
    "gn:feature_code":"PPL",
    "gn:name":"Uekimachi-tarumizu",
    "gn:population":0,
    "gn:timezone":"Asia/Tokyo",
    "iso:country":"JP",
    "name:jpn_x_preferred":[
        "\u690d\u6728\u753a\u6ef4\u6c34"
    ],
    "name:jpn_x_variant":[
        "\u3046\u3048\u304d\u307e\u3061\u305f\u308b\u307f\u305a",
        "\u30a6\u30a8\u30ad\u30de\u30c1\u30bf\u30eb\u30df\u30ba"
    ],
    "wof:name":"Uekimachi-tarumizu",
    "wof:placetype":"locality"
},
  "geometry": {"coordinates":[130.68369999999999,32.89143],"type":"Point"}
}