{
  "type": "Feature",
  "properties": {
    "gn:admin1_code":"21.0",
    "gn:admin2_code":"7412708.0",
    "gn:admin3_code":"43507.0",
    "gn:asciiname":"Sengahira",
    "gn:country_code":"JP",
    "gn:dem":693,
    "gn:feature_class":"P",
    "gn:feature_code":"PPLL",
    "gn:name":"Sengahira",
    "gn:population":0,
    "gn:timezone":"Asia/Tokyo",
    "iso:country":"JP",
    "name:jpn_x_preferred":[
        "\u5343\u30f6\u5e73"
    ],
    "name:jpn_x_variant":[
        "\u305b\u3093\u304c\u3072\u3089",
        "\u30bb\u30f3\u30ac\u30d2\u30e9"
    ],
    "wof:name":"Sengahira",
    "wof:placetype":"locality"
},
  "geometry": {"coordinates":[131.02227999999999,32.39299],"type":"Point"}
}