{
  "type": "Feature",
  "properties": {
    "gn:admin1_code":"37.0",
    "gn:admin2_code":"1863526.0",
    "gn:asciiname":"Kyozukahara",
    "gn:country_code":"JP",
    "gn:dem":470,
    "gn:feature_class":"P",
    "gn:feature_code":"PPLL",
    "gn:name":"Ky\u014dzukahara",
    "gn:population":0,
    "gn:timezone":"Asia/Tokyo",
    "iso:country":"JP",
    "name:jpn_x_preferred":[
        "\u4eac\u585a\u539f"
    ],
    "name:und_x_variant":[
        "Ky\u014dzukahara"
    ],
    "wof:name":"Kyozukahara",
    "wof:placetype":"locality"
},
  "geometry": {"coordinates":[138.92908,35.30482999999999],"type":"Point"}
}