{
  "type": "Feature",
  "properties": {
    "gn:admin1_code":"37.0",
    "gn:admin2_code":"1863526.0",
    "gn:asciiname":"Motomura",
    "gn:country_code":"JP",
    "gn:dem":363,
    "gn:feature_class":"P",
    "gn:feature_code":"PPLL",
    "gn:name":"Motomura",
    "gn:population":0,
    "gn:timezone":"Asia/Tokyo",
    "iso:country":"JP",
    "name:jpn_x_preferred":[
        "\u672c\u6751"
    ],
    "wof:name":"Motomura",
    "wof:placetype":"locality"
},
  "geometry": {"coordinates":[138.91346999999999,35.25543],"type":"Point"}
}