{
  "type": "Feature",
  "properties": {
    "gn:admin1_code":"21.0",
    "gn:admin2_code":"1857206.0",
    "gn:asciiname":"Minamibukuro",
    "gn:country_code":"JP",
    "gn:dem":9,
    "gn:feature_class":"P",
    "gn:feature_code":"PPLL",
    "gn:name":"Minamibukuro",
    "gn:population":0,
    "gn:timezone":"Asia/Tokyo",
    "iso:country":"JP",
    "name:jpn_x_preferred":[
        "\u5357\u888b"
    ],
    "name:jpn_x_variant":[
        "\u307f\u306a\u307f\u3076\u304f\u308d",
        "\u30df\u30ca\u30df\u30d6\u30af\u30ed"
    ],
    "wof:name":"Minamibukuro",
    "wof:placetype":"locality"
},
  "geometry": {"coordinates":[130.37968999999998,32.17095],"type":"Point"}
}