{
  "type": "Feature",
  "properties": {
    "iso:country":"JP",
    "name:eng_x_preferred":[
        "Midorigaoka 3 Chome"
    ],
    "name:eng_x_variant":[
        "Midorigaoka 3 Choume",
        "Midorigaoka 3 Chome"
    ],
    "name:jpn_x_preferred":[
        "\uff13\u4e01\u76ee"
    ],
    "name:jpn_x_variant":[
        "\u307f\u3069\u308a\u304c\u304a\u304b \uff13\u3061\u3087\u3046\u3081",
        "\u7dd1\u30b1\u4e18 \uff13\u4e01\u76ee",
        "\uff13\u3061\u3087\u3046\u3081"
    ],
    "qs:gn_local":0,
    "qs:local_max":25,
    "qs:local_sum":35,
    "qs:localhoods":2,
    "qs:name":"\uff13\u4e01\u76ee",
    "qs:name_adm0":"\u65e5\u672c",
    "qs:name_adm1":"\u9ad8\u77e5\u770c",
    "qs:name_en":"Midorigaoka 3 Chome",
    "qs:name_lau":"\u7dd1\u30b1\u4e18",
    "qs:name_local":"\u5357\u56fd\u5e02",
    "qs:photo_max":10,
    "qs:photo_sum":10,
    "qs:placetype":"Suburb",
    "qs:quad_count":1,
    "qs:woe_adm0":23424856,
    "qs:woe_adm1":2345869,
    "qs:woe_adm2":0,
    "qs:woe_lau":28481134,
    "qs:woe_local":1117854,
    "qs:woe_ver":"7.10.0",
    "wof:lang":[
        "jpn"
    ],
    "wof:name":"\uff13\u4e01\u76ee",
    "wof:placetype":"neighbourhood"
},
  "geometry": {"coordinates":[133.612976,33.525368],"type":"Point"}
}