{
  "type": "Feature",
  "properties": {
    "gn:admin1_code":"19.0",
    "gn:admin2_code":"1854744.0",
    "gn:asciiname":"Tomeba",
    "gn:country_code":"JP",
    "gn:dem":56,
    "gn:feature_class":"P",
    "gn:feature_code":"PPLL",
    "gn:name":"Tomeba",
    "gn:population":0,
    "gn:timezone":"Asia/Tokyo",
    "iso:country":"JP",
    "name:jpn_x_preferred":[
        "\u7559\u5834"
    ],
    "wof:name":"Tomeba",
    "wof:placetype":"locality"
},
  "geometry": {"coordinates":[139.13083999999998,35.27164000000001],"type":"Point"}
}