{
  "type": "Feature",
  "properties": {
    "gn:admin1_code":"3.0",
    "gn:admin2_code":"7439944.0",
    "gn:asciiname":"Hosonuma",
    "gn:country_code":"JP",
    "gn:dem":0,
    "gn:feature_class":"P",
    "gn:feature_code":"PPL",
    "gn:name":"Hosonuma",
    "gn:population":0,
    "gn:timezone":"Asia/Tokyo",
    "iso:country":"JP",
    "name:jpn_x_preferred":[
        "\u7d30\u6cbc"
    ],
    "name:jpn_x_variant":[
        "\u307b\u305d\u306c\u307e",
        "\u30db\u30bd\u30cc\u30de"
    ],
    "wof:name":"Hosonuma",
    "wof:placetype":"locality"
},
  "geometry": {"coordinates":[140.40753000000001,40.89237],"type":"Point"}
}