{
  "type": "Feature",
  "properties": {
    "gn:admin1_code":"7.0",
    "gn:admin2_code":"1851269.0",
    "gn:admin3_code":"40601.0",
    "gn:asciiname":"Kegoya",
    "gn:country_code":"JP",
    "gn:dem":117,
    "gn:feature_class":"P",
    "gn:feature_code":"PPLL",
    "gn:name":"Kegoya",
    "gn:population":0,
    "gn:timezone":"Asia/Tokyo",
    "iso:country":"JP",
    "name:jpn_x_preferred":[
        "\u82b1\u53e4\u5c4b"
    ],
    "wof:name":"Kegoya",
    "wof:placetype":"locality"
},
  "geometry": {"coordinates":[130.85667000000001,33.72252],"type":"Point"}
}