{
  "type": "Feature",
  "properties": {
    "gn:admin1_code":"08",
    "gn:admin2_code":"2112535.0",
    "gn:asciiname":"Taira-minamishirado",
    "gn:country_code":"JP",
    "gn:dem":9,
    "gn:feature_class":"P",
    "gn:feature_code":"PPL",
    "gn:name":"Taira-minamishirado",
    "gn:population":0,
    "gn:timezone":"Asia/Tokyo",
    "iso:country":"JP",
    "name:jpn_x_preferred":[
        "\u5e73\u5357\u767d\u571f"
    ],
    "name:und_x_variant":[
        "Taira"
    ],
    "wof:name":"Taira-minamishirado",
    "wof:placetype":"locality"
},
  "geometry": {"coordinates":[140.91666999999995,37.05],"type":"Point"}
}