{
  "type": "Feature",
  "properties": {
    "gn:admin1_code":"30",
    "gn:admin2_code":"1854480.0",
    "gn:asciiname":"Nagahamamachi",
    "gn:country_code":"JP",
    "gn:dem":5,
    "gn:feature_class":"P",
    "gn:feature_code":"PPL",
    "gn:name":"Nagahamamachi",
    "gn:population":0,
    "gn:timezone":"Asia/Tokyo",
    "iso:country":"JP",
    "name:jpn_x_preferred":[
        "\u9577\u6d5c\u753a"
    ],
    "name:und_x_variant":[
        "Nagahama",
        "Nagahamach\u014d",
        "Nagahamamachi"
    ],
    "wof:name":"Nagahamamachi",
    "wof:placetype":"locality"
},
  "geometry": {"coordinates":[131.61858000000001,33.23725],"type":"Point"}
}