{
  "type": "Feature",
  "properties": {
    "gn:admin1_code":"4.0",
    "gn:admin2_code":"2112997.0",
    "gn:admin3_code":"12427.0",
    "gn:asciiname":"Yaita",
    "gn:country_code":"JP",
    "gn:dem":18,
    "gn:feature_class":"P",
    "gn:feature_code":"PPLL",
    "gn:name":"Yaita",
    "gn:population":0,
    "gn:timezone":"Asia/Tokyo",
    "iso:country":"JP",
    "name:jpn_x_preferred":[
        "\u516b\u677f"
    ],
    "name:jpn_x_variant":[
        "\u3084\u3044\u305f",
        "\u30e4\u30a4\u30bf"
    ],
    "wof:name":"Yaita",
    "wof:placetype":"locality"
},
  "geometry": {"coordinates":[140.27760000000001,35.37087000000001],"type":"Point"}
}