{
  "type": "Feature",
  "properties": {
    "gn:admin1_code":"16.0",
    "gn:admin2_code":"2112822.0",
    "gn:asciiname":"Nimaibashimachi-kita Itchome",
    "gn:country_code":"JP",
    "gn:dem":99,
    "gn:feature_class":"P",
    "gn:feature_code":"PPL",
    "gn:name":"Nimaibashimachi-kita Itch\u014dme",
    "gn:population":0,
    "gn:timezone":"Asia/Tokyo",
    "iso:country":"JP",
    "name:jpn_x_preferred":[
        "\u4e8c\u679a\u6a4b\u753a\u5317\u4e00\u4e01\u76ee"
    ],
    "name:jpn_x_variant":[
        "\u306b\u307e\u3044\u3070\u3057\u307e\u3061\u304d\u305f\u3044\u3063\u3061\u3087\u3046\u3081",
        "\u30cb\u30de\u30a4\u30d0\u30b7\u30de\u30c1\u30ad\u30bf\u30a4\u30c3\u30c1\u30e7\u30a6\u30e1"
    ],
    "name:und_x_variant":[
        "Nimaibashimachi-kita Itch\u014dme"
    ],
    "wof:name":"Nimaibashimachi-kita Itchome",
    "wof:placetype":"locality"
},
  "geometry": {"coordinates":[141.13167000000001,39.44409],"type":"Point"}
}