{
  "type": "Feature",
  "properties": {
    "gn:admin1_code":"7.0",
    "gn:admin2_code":"1861834.0",
    "gn:asciiname":"Shinmachi",
    "gn:country_code":"JP",
    "gn:dem":45,
    "gn:feature_class":"P",
    "gn:feature_code":"PPLL",
    "gn:name":"Shinmachi",
    "gn:population":0,
    "gn:timezone":"Asia/Tokyo",
    "iso:country":"JP",
    "name:fra_x_preferred":[
        "Shinmachi"
    ],
    "name:jpn_x_preferred":[
        "\u65b0\u753a"
    ],
    "name:jpn_x_variant":[
        "\u65b0\u753a\u904a\u5ed3"
    ],
    "wof:name":"Shinmachi",
    "wof:placetype":"locality"
},
  "geometry": {"coordinates":[130.73188000000002,33.61598],"type":"Point"}
}