{
  "type": "Feature",
  "properties": {
    "gn:admin1_code":"21.0",
    "gn:admin2_code":"1865358.0",
    "gn:asciiname":"Domeki",
    "gn:country_code":"JP",
    "gn:dem":168,
    "gn:feature_class":"P",
    "gn:feature_code":"PPLL",
    "gn:name":"D\u014dmeki",
    "gn:population":0,
    "gn:timezone":"Asia/Tokyo",
    "iso:country":"JP",
    "name:jpn_x_preferred":[
        "\u9053\u76ee\u6728"
    ],
    "name:jpn_x_variant":[
        "\u3069\u3046\u3081\u304d",
        "\u30c9\u30a6\u30e1\u30ad"
    ],
    "name:und_x_variant":[
        "D\u014dmeki"
    ],
    "wof:name":"Domeki",
    "wof:placetype":"locality"
},
  "geometry": {"coordinates":[130.13016000000002,32.43237],"type":"Point"}
}