{
  "type": "Feature",
  "properties": {
    "gn:admin1_code":"21.0",
    "gn:admin2_code":"1848443.0",
    "gn:admin3_code":"43468.0",
    "gn:asciiname":"Higashikamimiya",
    "gn:country_code":"JP",
    "gn:dem":29,
    "gn:feature_class":"P",
    "gn:feature_code":"PPLL",
    "gn:name":"Higashikamimiya",
    "gn:population":0,
    "gn:timezone":"Asia/Tokyo",
    "iso:country":"JP",
    "name:jpn_x_preferred":[
        "\u6771\u4e0a\u5bae"
    ],
    "name:jpn_x_variant":[
        "\u3072\u304c\u3057\u304b\u307f\u307f\u3084",
        "\u30d2\u30ac\u30b7\u30ab\u30df\u30df\u30e4"
    ],
    "wof:name":"Higashikamimiya",
    "wof:placetype":"locality"
},
  "geometry": {"coordinates":[130.68340000000001,32.55372],"type":"Point"}
}