{
  "type": "Feature",
  "properties": {
    "gn:admin1_code":"21",
    "gn:admin2_code":"7412709.0",
    "gn:admin3_code":"43348.0",
    "gn:asciiname":"Koshoji",
    "gn:country_code":"JP",
    "gn:dem":231,
    "gn:feature_class":"P",
    "gn:feature_code":"PPL",
    "gn:name":"K\u014dsh\u014dji",
    "gn:population":0,
    "gn:timezone":"Asia/Tokyo",
    "iso:country":"JP",
    "name:jpn_x_preferred":[
        "\u8208\u6b63\u5bfa"
    ],
    "name:jpn_x_variant":[
        "\u3053\u3046\u3057\u3087\u3046\u3058",
        "\u30b3\u30a6\u30b7\u30e7\u30a6\u30b8"
    ],
    "name:und_x_variant":[
        "Tono",
        "K\u014dsh\u014dji"
    ],
    "wof:name":"Koshoji",
    "wof:placetype":"locality"
},
  "geometry": {"coordinates":[130.93017,32.64438],"type":"Point"}
}