{
  "type": "Feature",
  "properties": {
    "gn:admin1_code":"21.0",
    "gn:admin2_code":"1865358.0",
    "gn:asciiname":"Sato",
    "gn:country_code":"JP",
    "gn:dem":14,
    "gn:feature_class":"P",
    "gn:feature_code":"PPLL",
    "gn:name":"Sato",
    "gn:population":0,
    "gn:timezone":"Asia/Tokyo",
    "iso:country":"JP",
    "name:jpn_x_preferred":[
        "\u91cc"
    ],
    "name:jpn_x_variant":[
        "\u3055\u3068",
        "\u30b5\u30c8"
    ],
    "wof:name":"Sato",
    "wof:placetype":"locality"
},
  "geometry": {"coordinates":[129.99522999999999,32.33626],"type":"Point"}
}