{
  "type": "Feature",
  "properties": {
    "gn:admin1_code":"18.0",
    "gn:admin2_code":"7383999.0",
    "gn:admin3_code":"46491.0",
    "gn:asciiname":"Nameigawa",
    "gn:country_code":"JP",
    "gn:dem":214,
    "gn:feature_class":"P",
    "gn:feature_code":"PPLL",
    "gn:name":"Nameigawa",
    "gn:population":0,
    "gn:timezone":"Asia/Tokyo",
    "iso:country":"JP",
    "name:jpn_x_preferred":[
        "\u6ed1\u5ddd"
    ],
    "wof:name":"Nameigawa",
    "wof:placetype":"locality"
},
  "geometry": {"coordinates":[130.8073,31.18482],"type":"Point"}
}