{
  "type": "Feature",
  "properties": {
    "gn:admin1_code":"25",
    "gn:admin2_code":"7413968.0",
    "gn:admin3_code":"45441.0",
    "gn:asciiname":"Toroku",
    "gn:country_code":"JP",
    "gn:dem":723,
    "gn:feature_class":"P",
    "gn:feature_code":"PPL",
    "gn:name":"Toroku",
    "gn:population":0,
    "gn:timezone":"Asia/Tokyo",
    "iso:country":"JP",
    "wof:name":"Toroku",
    "wof:placetype":"locality"
},
  "geometry": {"coordinates":[131.36667,32.76667],"type":"Point"}
}