{
  "type": "Feature",
  "properties": {
    "iso:country":"JP",
    "name:eng_x_preferred":[
        "Minatocho 2 Chome"
    ],
    "name:eng_x_variant":[
        "Minatochou 2 Choume",
        "Minatocho 2 Chome"
    ],
    "name:jpn_x_preferred":[
        "\uff12\u4e01\u76ee"
    ],
    "name:jpn_x_variant":[
        "\u307f\u306a\u3068\u3061\u3087\u3046 \uff12\u3061\u3087\u3046\u3081",
        "\u6e4a\u753a \uff12\u4e01\u76ee",
        "\uff12\u3061\u3087\u3046\u3081"
    ],
    "name:unk_x_variant":[
        "\uff12\u4e01\u76ee"
    ],
    "qs:gn_adm0_cc":"JP",
    "qs:gn_local":1863905,
    "qs:gn_nam_loc":"\u8239\u6a4b\u5e02, \u5343\u8449\u770c, JP",
    "qs:gn_namadm1":"04",
    "qs:local_max":634,
    "qs:local_sum":2057,
    "qs:localhoods":15,
    "qs:name":"\uff12\u4e01\u76ee",
    "qs:name_adm0":"\u65e5\u672c",
    "qs:name_adm1":"\u5343\u8449\u770c",
    "qs:name_en":"Minatocho 2 Chome",
    "qs:name_lau":"\u6e4a\u753a",
    "qs:name_local":"\u8239\u6a4b\u5e02",
    "qs:photo_max":4,
    "qs:photo_sum":7,
    "qs:placetype":"Suburb",
    "qs:quad_count":2,
    "qs:woe_adm0":23424856,
    "qs:woe_adm1":2345854,
    "qs:woe_adm2":0,
    "qs:woe_lau":28410973,
    "qs:woe_local":1117109,
    "qs:woe_ver":"7.10.0",
    "wof:lang":[
        "jpn"
    ],
    "wof:name":"\uff12\u4e01\u76ee",
    "wof:placetype":"neighbourhood"
},
  "geometry": {"coordinates":[139.97955300000001,35.693738],"type":"Point"}
}