{
  "type": "Feature",
  "properties": {
    "gn:admin1_code":"7.0",
    "gn:admin2_code":"7406950.0",
    "gn:admin3_code":"40625.0",
    "gn:asciiname":"Katsuyama-ueda",
    "gn:country_code":"JP",
    "gn:dem":16,
    "gn:feature_class":"P",
    "gn:feature_code":"PPL",
    "gn:name":"Katsuyama-ueda",
    "gn:population":0,
    "gn:timezone":"Asia/Tokyo",
    "iso:country":"JP",
    "name:jpn_x_preferred":[
        "\u52dd\u5c71\u4e0a\u7530"
    ],
    "wof:name":"Katsuyama-ueda",
    "wof:placetype":"locality"
},
  "geometry": {"coordinates":[130.92160000000001,33.69555],"type":"Point"}
}