{
  "type": "Feature",
  "properties": {
    "gn:admin1_code":"8.0",
    "gn:admin2_code":"7451503.0",
    "gn:admin3_code":"7344.0",
    "gn:asciiname":"Iitoyo",
    "gn:country_code":"JP",
    "gn:dem":277,
    "gn:feature_class":"P",
    "gn:feature_code":"PPL",
    "gn:name":"Iitoyo",
    "gn:population":0,
    "gn:timezone":"Asia/Tokyo",
    "iso:country":"JP",
    "name:jpn_x_preferred":[
        "\u98ef\u8c4a"
    ],
    "wof:name":"Iitoyo",
    "wof:placetype":"locality"
},
  "geometry": {"coordinates":[140.29061000000002,37.24351],"type":"Point"}
}