{
  "type": "Feature",
  "properties": {
    "iso:country":"JP",
    "name:eng_x_preferred":[
        "Sengawacho 1 Chome"
    ],
    "name:eng_x_variant":[
        "Sengawachou 1 Choume",
        "Sengawacho 1 Chome"
    ],
    "name:jpn_x_preferred":[
        "\uff11\u4e01\u76ee"
    ],
    "name:jpn_x_variant":[
        "\u305b\u3093\u304c\u308f\u3061\u3087\u3046 \uff11\u3061\u3087\u3046\u3081",
        "\u4ed9\u5ddd\u753a \uff11\u4e01\u76ee",
        "\uff11\u3061\u3087\u3046\u3081"
    ],
    "qs:gn_local":0,
    "qs:local_max":1845,
    "qs:local_sum":7669,
    "qs:localhoods":21,
    "qs:name":"\uff11\u4e01\u76ee",
    "qs:name_adm0":"\u65e5\u672c",
    "qs:name_adm1":"\u6771\u4eac\u90fd",
    "qs:name_en":"Sengawacho 1 Chome",
    "qs:name_lau":"\u4ed9\u5ddd\u753a",
    "qs:name_local":"\u8abf\u5e03\u5e02",
    "qs:photo_max":34,
    "qs:photo_sum":153,
    "qs:placetype":"Suburb",
    "qs:quad_count":10,
    "qs:woe_adm0":23424856,
    "qs:woe_adm1":2345889,
    "qs:woe_adm2":0,
    "qs:woe_lau":28415057,
    "qs:woe_local":1107816,
    "qs:woe_ver":"7.10.0",
    "wof:lang":[
        "jpn"
    ],
    "wof:name":"\uff11\u4e01\u76ee",
    "wof:placetype":"neighbourhood"
},
  "geometry": {"coordinates":[139.586018,35.660591],"type":"Point"}
}