{
  "type": "Feature",
  "properties": {
    "gn:admin1_code":"6.0",
    "gn:admin2_code":"1863982.0",
    "gn:asciiname":"Minamiyamacho",
    "gn:country_code":"JP",
    "gn:dem":23,
    "gn:feature_class":"P",
    "gn:feature_code":"PPL",
    "gn:name":"Minamiyamach\u014d",
    "gn:population":0,
    "gn:timezone":"Asia/Tokyo",
    "iso:country":"JP",
    "name:jpn_x_preferred":[
        "\u5357\u5c71\u753a"
    ],
    "name:und_x_variant":[
        "Minamiyamach\u014d"
    ],
    "wof:name":"Minamiyamacho",
    "wof:placetype":"locality"
},
  "geometry": {"coordinates":[136.2833,36.00978],"type":"Point"}
}