{
  "type": "Feature",
  "properties": {
    "iso:country":"JP",
    "name:eng_x_preferred":[
        "Roppongi 7 Chome"
    ],
    "name:eng_x_variant":[
        "Roppongi 7 Choume",
        "Roppongi 7 Chome"
    ],
    "name:jpn_x_preferred":[
        "\uff17\u4e01\u76ee"
    ],
    "name:jpn_x_variant":[
        "\u308d\u3063\u307d\u3093\u304e \uff17\u3061\u3087\u3046\u3081",
        "\u516d\u672c\u6728 \uff17\u4e01\u76ee",
        "\uff17\u3061\u3087\u3046\u3081"
    ],
    "qs:gn_adm0_cc":"JP",
    "qs:gn_local":1850147,
    "qs:local_max":18112,
    "qs:local_sum":895907,
    "qs:localhoods":857,
    "qs:name":"\uff17\u4e01\u76ee",
    "qs:name_adm0":"\u65e5\u672c",
    "qs:name_adm1":"\u6771\u4eac\u90fd",
    "qs:name_adm2":"\u6e2f\u533a",
    "qs:name_en":"Roppongi 7 Chome",
    "qs:name_lau":"\u516d\u672c\u6728",
    "qs:name_local":"\u6771\u4eac",
    "qs:photo_max":2153,
    "qs:photo_sum":8577,
    "qs:placetype":"Suburb",
    "qs:quad_count":31,
    "qs:woe_adm0":23424856,
    "qs:woe_adm1":2345889,
    "qs:woe_adm2":15015406,
    "qs:woe_lau":28494567,
    "qs:woe_local":1118370,
    "qs:woe_ver":"7.10.0",
    "wof:lang":[
        "jpn"
    ],
    "wof:name":"\uff17\u4e01\u76ee",
    "wof:placetype":"neighbourhood"
},
  "geometry": {"coordinates":[139.72878800000001,35.664506],"type":"Point"}
}