{
  "type": "Feature",
  "properties": {
    "gn:admin1_code":"12.0",
    "gn:admin2_code":"2128570.0",
    "gn:asciiname":"Hariusu",
    "gn:cc2":"JP",
    "gn:country_code":"JP",
    "gn:dem":143,
    "gn:feature_class":"P",
    "gn:feature_code":"PPL",
    "gn:name":"Hariusu",
    "gn:population":0,
    "gn:timezone":"Asia/Tokyo",
    "iso:country":"JP",
    "name:und_x_variant":[
        "Hariusumura",
        "Hariusuch\u014d",
        "Hariusu"
    ],
    "wof:name":"Hariusu",
    "wof:placetype":"locality"
},
  "geometry": {"coordinates":[141.11667,43.15],"type":"Point"}
}