{
  "type": "Feature",
  "properties": {
    "gn:admin1_code":"3.0",
    "gn:admin2_code":"7439944.0",
    "gn:asciiname":"Kizukuri-nagata",
    "gn:country_code":"JP",
    "gn:dem":6,
    "gn:feature_class":"P",
    "gn:feature_code":"PPL",
    "gn:name":"Kizukuri-nagata",
    "gn:population":0,
    "gn:timezone":"Asia/Tokyo",
    "iso:country":"JP",
    "name:jpn_x_preferred":[
        "\u6728\u9020\u6c38\u7530"
    ],
    "name:jpn_x_variant":[
        "\u304d\u3065\u304f\u308a\u306a\u304c\u305f",
        "\u30ad\u30c5\u30af\u30ea\u30ca\u30ac\u30bf"
    ],
    "wof:name":"Kizukuri-nagata",
    "wof:placetype":"locality"
},
  "geometry": {"coordinates":[140.36484999999999,40.83589],"type":"Point"}
}