{
  "type": "Feature",
  "properties": {
    "gn:admin1_code":"19.0",
    "gn:admin2_code":"1863429.0",
    "gn:asciiname":"Yanagicho",
    "gn:country_code":"JP",
    "gn:dem":175,
    "gn:feature_class":"P",
    "gn:feature_code":"PPL",
    "gn:name":"Yanagich\u014d",
    "gn:population":0,
    "gn:timezone":"Asia/Tokyo",
    "iso:country":"JP",
    "name:jpn_x_preferred":[
        "\u67f3\u753a"
    ],
    "name:und_x_variant":[
        "Yanagich\u014d"
    ],
    "wof:name":"Yanagicho",
    "wof:placetype":"locality"
},
  "geometry": {"coordinates":[139.18249,35.37519],"type":"Point"}
}