{
  "type": "Feature",
  "properties": {
    "gn:admin1_code":"21.0",
    "gn:admin2_code":"7413152.0",
    "gn:asciiname":"Matsubasemachi-ono",
    "gn:country_code":"JP",
    "gn:dem":10,
    "gn:feature_class":"P",
    "gn:feature_code":"PPL",
    "gn:name":"Matsubasemachi-\u014dno",
    "gn:population":0,
    "gn:timezone":"Asia/Tokyo",
    "iso:country":"JP",
    "name:jpn_x_preferred":[
        "\u677e\u6a4b\u753a\u5927\u91ce"
    ],
    "name:jpn_x_variant":[
        "\u307e\u3064\u3070\u305b\u307e\u3061\u304a\u304a\u306e",
        "\u30de\u30c4\u30d0\u30bb\u30de\u30c1\u30aa\u30aa\u30ce"
    ],
    "name:und_x_variant":[
        "Matsubasemachi-\u014dno"
    ],
    "wof:name":"Matsubasemachi-ono",
    "wof:placetype":"locality"
},
  "geometry": {"coordinates":[130.68138999999999,32.64821],"type":"Point"}
}