{
  "type": "Feature",
  "properties": {
    "gn:admin1_code":"24.0",
    "gn:admin2_code":"7446986.0",
    "gn:admin3_code":"4581.0",
    "gn:asciiname":"Oura",
    "gn:country_code":"JP",
    "gn:dem":9,
    "gn:feature_class":"P",
    "gn:feature_code":"PPL",
    "gn:name":"Oura",
    "gn:population":0,
    "gn:timezone":"Asia/Tokyo",
    "iso:country":"JP",
    "name:ceb_x_preferred":[
        "Oura"
    ],
    "name:fra_x_preferred":[
        "Oura"
    ],
    "name:jpn_x_preferred":[
        "\u5c3e\u6d66"
    ],
    "name:jpn_x_variant":[
        "\u304a\u3046\u3089",
        "\u30aa\u30a6\u30e9"
    ],
    "name:swe_x_preferred":[
        "Oura"
    ],
    "wof:name":"Oura",
    "wof:placetype":"locality"
},
  "geometry": {"coordinates":[141.49347,38.45477],"type":"Point"}
}