{
  "type": "Feature",
  "properties": {
    "gn:admin1_code":"11",
    "gn:admin2_code":"7372274.0",
    "gn:asciiname":"Ichi",
    "gn:country_code":"JP",
    "gn:dem":367,
    "gn:feature_class":"P",
    "gn:feature_code":"PPL",
    "gn:name":"Ichi",
    "gn:population":0,
    "gn:timezone":"Asia/Tokyo",
    "iso:country":"JP",
    "name:dan_x_preferred":[
        "Ichi"
    ],
    "name:fra_x_preferred":[
        "Ichi"
    ],
    "name:ita_x_preferred":[
        "Ichi"
    ],
    "wof:name":"Ichi",
    "wof:placetype":"locality"
},
  "geometry": {"coordinates":[132.61667,34.75],"type":"Point"}
}