{
  "type": "Feature",
  "properties": {
    "gn:admin1_code":"4.0",
    "gn:admin2_code":"1863903.0",
    "gn:asciiname":"Sakaecho",
    "gn:country_code":"JP",
    "gn:dem":6,
    "gn:feature_class":"P",
    "gn:feature_code":"PPL",
    "gn:name":"Sakaech\u014d",
    "gn:population":0,
    "gn:timezone":"Asia/Tokyo",
    "iso:country":"JP",
    "name:jpn_x_preferred":[
        "\u6804\u753a"
    ],
    "name:und_x_variant":[
        "Sakaech\u014d",
        "Sakae"
    ],
    "wof:name":"Sakaecho",
    "wof:placetype":"locality"
},
  "geometry": {"coordinates":[139.97307000000001,35.68829],"type":"Point"}
}