{
  "type": "Feature",
  "properties": {
    "gn:admin1_code":"37.0",
    "gn:admin2_code":"1864089.0",
    "gn:asciiname":"Fuji-matsuno",
    "gn:country_code":"JP",
    "gn:dem":51,
    "gn:feature_class":"P",
    "gn:feature_code":"PPLL",
    "gn:name":"Fuji-matsuno",
    "gn:population":0,
    "gn:timezone":"Asia/Tokyo",
    "iso:country":"JP",
    "name:jpn_x_preferred":[
        "\u5bcc\u58eb\u677e\u91ce"
    ],
    "wof:name":"Fuji-matsuno",
    "wof:placetype":"locality"
},
  "geometry": {"coordinates":[138.59673000000001,35.18738],"type":"Point"}
}