{
  "type": "Feature",
  "properties": {
    "gn:admin1_code":"4.0",
    "gn:admin2_code":"2112997.0",
    "gn:admin3_code":"12423.0",
    "gn:asciiname":"Iriyamazu",
    "gn:country_code":"JP",
    "gn:dem":4,
    "gn:feature_class":"P",
    "gn:feature_code":"PPL",
    "gn:name":"Iriyamazu",
    "gn:population":0,
    "gn:timezone":"Asia/Tokyo",
    "iso:country":"JP",
    "name:jpn_x_preferred":[
        "\u4e0d\u5165\u6597"
    ],
    "name:jpn_x_variant":[
        "\u3044\u308a\u3084\u307e\u305a",
        "\u30a4\u30ea\u30e4\u30de\u30ba"
    ],
    "wof:name":"Iriyamazu",
    "wof:placetype":"locality"
},
  "geometry": {"coordinates":[140.37781000000001,35.42048],"type":"Point"}
}