{
  "type": "Feature",
  "properties": {
    "iso:country":"JP",
    "name:eng_x_preferred":[
        "Higashitabata 1 Chome"
    ],
    "name:eng_x_variant":[
        "Higashitabata 1 Choume",
        "Higashitabata 1 Chome"
    ],
    "name:jpn_x_preferred":[
        "\uff11\u4e01\u76ee"
    ],
    "name:jpn_x_variant":[
        "\u3072\u304c\u3057\u305f\u3070\u305f \uff11\u3061\u3087\u3046\u3081",
        "\u6771\u7530\u7aef \uff11\u4e01\u76ee",
        "\uff11\u3061\u3087\u3046\u3081"
    ],
    "qs:gn_adm0_cc":"JP",
    "qs:gn_local":1850147,
    "qs:local_max":18112,
    "qs:local_sum":895907,
    "qs:localhoods":857,
    "qs:name":"\uff11\u4e01\u76ee",
    "qs:name_adm0":"\u65e5\u672c",
    "qs:name_adm1":"\u6771\u4eac\u90fd",
    "qs:name_adm2":"\u5317\u533a",
    "qs:name_en":"Higashitabata 1 Chome",
    "qs:name_lau":"\u6771\u7530\u7aef",
    "qs:name_local":"\u6771\u4eac",
    "qs:photo_max":56,
    "qs:photo_sum":99,
    "qs:photos":4,
    "qs:photos_1k":1,
    "qs:photos_9k":1,
    "qs:photos_9r":1,
    "qs:photos_all":4,
    "qs:photos_sr":1,
    "qs:placetype":"Suburb",
    "qs:pop_sr":"0",
    "qs:quad_count":6,
    "qs:woe_adm0":23424856,
    "qs:woe_adm1":2345889,
    "qs:woe_adm2":15015503,
    "qs:woe_lau":28414519,
    "qs:woe_local":1118370,
    "qs:woe_ver":"7.10.0",
    "wof:lang":[
        "jpn"
    ],
    "wof:name":"\uff11\u4e01\u76ee",
    "wof:placetype":"neighbourhood"
},
  "geometry": {"coordinates":[139.76600099999999,35.735561],"type":"Point"}
}