{
  "type": "Feature",
  "properties": {
    "gn:admin1_code":"21.0",
    "gn:admin2_code":"1865358.0",
    "gn:asciiname":"Hirakawachi",
    "gn:country_code":"JP",
    "gn:dem":55,
    "gn:feature_class":"P",
    "gn:feature_code":"PPLL",
    "gn:name":"Hirakawachi",
    "gn:population":0,
    "gn:timezone":"Asia/Tokyo",
    "iso:country":"JP",
    "name:jpn_x_preferred":[
        "\u5e73\u6cb3\u5185"
    ],
    "name:jpn_x_variant":[
        "\u3072\u3089\u304b\u308f\u3061",
        "\u30d2\u30e9\u30ab\u30ef\u30c1"
    ],
    "wof:name":"Hirakawachi",
    "wof:placetype":"locality"
},
  "geometry": {"coordinates":[130.1628,32.48806],"type":"Point"}
}