{
  "type": "Feature",
  "properties": {
    "gn:admin1_code":"19.0",
    "gn:admin2_code":"1859635.0",
    "gn:admin3_code":"14133.0",
    "gn:asciiname":"Kariyado",
    "gn:country_code":"JP",
    "gn:dem":10,
    "gn:feature_class":"P",
    "gn:feature_code":"PPL",
    "gn:name":"Kariyado",
    "gn:population":0,
    "gn:timezone":"Asia/Tokyo",
    "iso:country":"JP",
    "name:jpn_x_preferred":[
        "\u5208\u5bbf"
    ],
    "wof:name":"Kariyado",
    "wof:placetype":"locality"
},
  "geometry": {"coordinates":[139.66311999999999,35.5614],"type":"Point"}
}