{
  "type": "Feature",
  "properties": {
    "gn:admin1_code":"34.0",
    "gn:admin2_code":"1850180.0",
    "gn:asciiname":"Hibita",
    "gn:country_code":"JP",
    "gn:dem":52,
    "gn:feature_class":"P",
    "gn:feature_code":"PPL",
    "gn:name":"Hibita",
    "gn:population":0,
    "gn:timezone":"Asia/Tokyo",
    "iso:country":"JP",
    "name:jpn_x_preferred":[
        "\u65e5\u6bd4\u7530"
    ],
    "name:jpn_x_variant":[
        "\u3072\u3073\u305f",
        "\u30d2\u30d3\u30bf"
    ],
    "wof:name":"Hibita",
    "wof:placetype":"locality"
},
  "geometry": {"coordinates":[139.50635,35.80746],"type":"Point"}
}