{
  "type": "Feature",
  "properties": {
    "gn:admin1_code":"1.0",
    "gn:admin2_code":"7369798.0",
    "gn:asciiname":"Aisai",
    "gn:country_code":"JP",
    "gn:dem":-2,
    "gn:feature_class":"P",
    "gn:feature_code":"PPLA2",
    "gn:name":"Aisai",
    "gn:population":0,
    "gn:timezone":"Asia/Tokyo",
    "iso:country":"JP",
    "name:ara_x_preferred":[
        "\u0622\u064a\u0633\u0627\u064a"
    ],
    "name:fas_x_preferred":[
        "\u0622\u06cc\u0633\u0627\u06cc\u060c \u0622\u06cc\u0686\u06cc"
    ],
    "name:hun_x_preferred":[
        "Aiszai"
    ],
    "name:jpn_x_preferred":[
        "\u611b\u897f"
    ],
    "name:jpn_x_variant":[
        "\u611b\u897f\u5e02",
        "\u3042\u3044\u3055\u3044\u3057"
    ],
    "name:kat_x_preferred":[
        "\u10d0\u10d8\u10e1\u10d0\u10d8"
    ],
    "name:kaz_x_preferred":[
        "\u0410\u0439\u0441\u0430\u0439"
    ],
    "name:kor_x_preferred":[
        "\uc544\uc774\uc0ac\uc774 \uc2dc"
    ],
    "name:lit_x_preferred":[
        "Aisajus"
    ],
    "name:mzn_x_preferred":[
        "\u0622\u06cc\u0633\u0627\u06cc\u060c \u0622\u06cc\u0686\u06cc"
    ],
    "name:nan_x_preferred":[
        "Aisai-chh\u012b"
    ],
    "name:rus_x_preferred":[
        "\u0410\u0439\u0441\u0430\u0439"
    ],
    "name:tgk_x_preferred":[
        "\u0410\u0438\u0441\u0430\u0438"
    ],
    "name:tha_x_preferred":[
        "\u0e44\u0e2d\u0e44\u0e0b"
    ],
    "name:ukr_x_preferred":[
        "\u0410\u0439\u0441\u0430\u0439"
    ],
    "name:urd_x_preferred":[
        "\u0627\u06cc\u0633\u0627\u0626\u06cc\u060c \u0627\u06cc\u0686\u06cc"
    ],
    "name:zho_x_preferred":[
        "\u611b\u897f\u5e02"
    ],
    "wof:name":"Aisai",
    "wof:placetype":"locality"
},
  "geometry": {"coordinates":[136.73221999999998,35.16349],"type":"Point"}
}