{
  "type": "Feature",
  "properties": {
    "gn:admin1_code":"28.0",
    "gn:admin2_code":"7412212.0",
    "gn:asciiname":"Haibara-yasuda",
    "gn:country_code":"JP",
    "gn:dem":347,
    "gn:feature_class":"P",
    "gn:feature_code":"PPL",
    "gn:name":"Haibara-yasuda",
    "gn:population":0,
    "gn:timezone":"Asia/Tokyo",
    "iso:country":"JP",
    "name:jpn_x_preferred":[
        "\u699b\u539f\u5b89\u7530"
    ],
    "wof:name":"Haibara-yasuda",
    "wof:placetype":"locality"
},
  "geometry": {"coordinates":[135.93042,34.52146],"type":"Point"}
}