{
  "type": "Feature",
  "properties": {
    "gn:admin1_code":"4.0",
    "gn:admin2_code":"1859468.0",
    "gn:asciiname":"Tomiyoshi",
    "gn:country_code":"JP",
    "gn:dem":11,
    "gn:feature_class":"P",
    "gn:feature_code":"PPLL",
    "gn:name":"Tomiyoshi",
    "gn:population":0,
    "gn:timezone":"Asia/Tokyo",
    "iso:country":"JP",
    "name:jpn_x_preferred":[
        "\u5bcc\u5409"
    ],
    "name:jpn_x_variant":[
        "\u3068\u307f\u3088\u3057",
        "\u30c8\u30df\u30e8\u30b7"
    ],
    "wof:name":"Tomiyoshi",
    "wof:placetype":"locality"
},
  "geometry": {"coordinates":[139.90584999999999,35.32349],"type":"Point"}
}