{
  "type": "Feature",
  "properties": {
    "iso:country":"JP",
    "label:eng_x_preferred_longname":[
        "Mashiki Town"
    ],
    "label:eng_x_preferred_placetype":[
        "town"
    ],
    "name:eng_x_preferred":[
        "Mashiki"
    ],
    "name:eng_x_variant":[
        "Mashiki Town"
    ],
    "name:jpn_x_preferred":[
        "\u76ca\u57ce\u753a"
    ],
    "qs:name":"\u76ca\u57ce\u753a",
    "qs:name_adm0":"\u65e5\u672c",
    "qs:name_adm1":"\u718a\u672c\u770c",
    "qs:photos":31,
    "qs:photos_1k":6,
    "qs:photos_9k":1,
    "qs:photos_9r":2,
    "qs:photos_all":31,
    "qs:photos_sr":2,
    "qs:placetype":"Town",
    "qs:pop_sr":"0",
    "wof:name":"Mashiki",
    "wof:placetype":"locality"
},
  "geometry": {"coordinates":[130.851631,32.809167],"type":"Point"}
}