{
  "type": "Feature",
  "properties": {
    "gn:admin1_code":"7.0",
    "gn:admin2_code":"7407416.0",
    "gn:asciiname":"Tajiri",
    "gn:country_code":"JP",
    "gn:dem":177,
    "gn:feature_class":"P",
    "gn:feature_code":"PPLL",
    "gn:name":"Tajiri",
    "gn:population":0,
    "gn:timezone":"Asia/Tokyo",
    "iso:country":"JP",
    "name:deu_x_preferred":[
        "Tajiri"
    ],
    "name:epo_x_preferred":[
        "Ta\u011diri"
    ],
    "name:fra_x_preferred":[
        "Tajiri"
    ],
    "name:ita_x_preferred":[
        "Tajiri"
    ],
    "name:jpn_x_preferred":[
        "\u7530\u5c3b"
    ],
    "name:kor_x_preferred":[
        "\ub2e4\uc9c0\ub9ac"
    ],
    "name:nld_x_preferred":[
        "Tajiri"
    ],
    "name:rus_x_preferred":[
        "\u0422\u0430\u0434\u0437\u0438\u0440\u0438"
    ],
    "wof:name":"Tajiri",
    "wof:placetype":"locality"
},
  "geometry": {"coordinates":[130.60210000000001,33.65732],"type":"Point"}
}