{
  "type": "Feature",
  "properties": {
    "gn:admin1_code":"43.0",
    "gn:admin2_code":"7411114.0",
    "gn:asciiname":"Kishigawacho-inokuchi",
    "gn:country_code":"JP",
    "gn:dem":43,
    "gn:feature_class":"P",
    "gn:feature_code":"PPL",
    "gn:name":"Kishigawach\u014d-inokuchi",
    "gn:population":0,
    "gn:timezone":"Asia/Tokyo",
    "iso:country":"JP",
    "name:jpn_x_preferred":[
        "\u8cb4\u5fd7\u5ddd\u753a\u4e95\u30ce\u53e3"
    ],
    "name:und_x_variant":[
        "Kishigawach\u014d-inokuchi"
    ],
    "wof:name":"Kishigawacho-inokuchi",
    "wof:placetype":"locality"
},
  "geometry": {"coordinates":[135.31471999999999,34.20448],"type":"Point"}
}