{
  "type": "Feature",
  "properties": {
    "gn:admin1_code":"18",
    "gn:admin2_code":"1853737.0",
    "gn:admin3_code":"46524.0",
    "gn:asciiname":"Nagara",
    "gn:country_code":"JP",
    "gn:dem":23,
    "gn:feature_class":"P",
    "gn:feature_code":"PPL",
    "gn:name":"Nagara",
    "gn:population":0,
    "gn:timezone":"Asia/Tokyo",
    "iso:country":"JP",
    "name:jpn_x_preferred":[
        "\u540d\u67c4"
    ],
    "name:und_x_variant":[
        "Nakara"
    ],
    "wof:name":"Nagara",
    "wof:placetype":"locality"
},
  "geometry": {"coordinates":[129.25,28.25],"type":"Point"}
}