{
  "type": "Feature",
  "properties": {
    "gn:admin1_code":"19.0",
    "gn:admin2_code":"7470889.0",
    "gn:asciiname":"Kawaraguchi",
    "gn:country_code":"JP",
    "gn:dem":23,
    "gn:feature_class":"P",
    "gn:feature_code":"PPL",
    "gn:name":"Kawaraguchi",
    "gn:population":0,
    "gn:timezone":"Asia/Tokyo",
    "iso:country":"JP",
    "name:jpn_x_preferred":[
        "\u6cb3\u539f\u53e3"
    ],
    "wof:name":"Kawaraguchi",
    "wof:placetype":"locality"
},
  "geometry": {"coordinates":[139.37655000000001,35.4484],"type":"Point"}
}