{
  "type": "Feature",
  "properties": {
    "gn:admin1_code":"12.0",
    "gn:admin2_code":"2130304.0",
    "gn:asciiname":"Nunoppe",
    "gn:country_code":"JP",
    "gn:dem":261,
    "gn:feature_class":"P",
    "gn:feature_code":"PPL",
    "gn:name":"Nunoppe",
    "gn:population":0,
    "gn:timezone":"Asia/Tokyo",
    "iso:country":"JP",
    "wof:name":"Nunoppe",
    "wof:placetype":"locality"
},
  "geometry": {"coordinates":[142.40000000000001,43.28333],"type":"Point"}
}