{
  "type": "Feature",
  "properties": {
    "gn:admin1_code":"4.0",
    "gn:admin2_code":"1855071.0",
    "gn:asciiname":"Osakidai",
    "gn:country_code":"JP",
    "gn:dem":15,
    "gn:feature_class":"P",
    "gn:feature_code":"PPL",
    "gn:name":"Osakidai",
    "gn:population":0,
    "gn:timezone":"Asia/Tokyo",
    "iso:country":"JP",
    "name:jpn_x_preferred":[
        "\u5c3e\u5d0e\u53f0"
    ],
    "wof:name":"Osakidai",
    "wof:placetype":"locality"
},
  "geometry": {"coordinates":[139.83681999999999,35.98381],"type":"Point"}
}