{
  "type": "Feature",
  "properties": {
    "gn:admin1_code":"37.0",
    "gn:admin2_code":"7418320.0",
    "gn:asciiname":"Minazawa",
    "gn:country_code":"JP",
    "gn:dem":38,
    "gn:feature_class":"P",
    "gn:feature_code":"PPLL",
    "gn:name":"Minazawa",
    "gn:population":0,
    "gn:timezone":"Asia/Tokyo",
    "iso:country":"JP",
    "name:jpn_x_preferred":[
        "\u7686\u6ca2"
    ],
    "wof:name":"Minazawa",
    "wof:placetype":"locality"
},
  "geometry": {"coordinates":[138.95918,35.03256],"type":"Point"}
}