{
  "type": "Feature",
  "properties": {
    "gn:admin1_code":"36",
    "gn:admin2_code":"1857549.0",
    "gn:asciiname":"Kashimacho-mitsu",
    "gn:country_code":"JP",
    "gn:dem":98,
    "gn:feature_class":"P",
    "gn:feature_code":"PPL",
    "gn:name":"Kashimach\u014d-mitsu",
    "gn:population":0,
    "gn:timezone":"Asia/Tokyo",
    "iso:country":"JP",
    "name:jpn_x_preferred":[
        "\u9e7f\u5cf6\u753a\u5fa1\u6d25"
    ],
    "name:und_x_variant":[
        "Mizu",
        "Mitsu",
        "Kashimach\u014d-mitsu"
    ],
    "wof:name":"Kashimacho-mitsu",
    "wof:placetype":"locality"
},
  "geometry": {"coordinates":[133.02778000000001,35.53373],"type":"Point"}
}