{
  "type": "Feature",
  "properties": {
    "gn:admin1_code":"19.0",
    "gn:admin2_code":"1863429.0",
    "gn:asciiname":"Kotobukicho",
    "gn:country_code":"JP",
    "gn:dem":107,
    "gn:feature_class":"P",
    "gn:feature_code":"PPL",
    "gn:name":"Kotobukich\u014d",
    "gn:population":0,
    "gn:timezone":"Asia/Tokyo",
    "iso:country":"JP",
    "name:jpn_x_preferred":[
        "\u5bff\u753a"
    ],
    "name:und_x_variant":[
        "Kotobukich\u014d"
    ],
    "wof:name":"Kotobukicho",
    "wof:placetype":"locality"
},
  "geometry": {"coordinates":[139.22746000000001,35.37617],"type":"Point"}
}