{
  "type": "Feature",
  "properties": {
    "gn:admin1_code":"27",
    "gn:admin2_code":"1861758.0",
    "gn:asciiname":"Gonouracho-gonoura",
    "gn:country_code":"JP",
    "gn:dem":25,
    "gn:feature_class":"P",
    "gn:feature_code":"PPL",
    "gn:name":"G\u014dnourach\u014d-g\u014dnoura",
    "gn:population":0,
    "gn:timezone":"Asia/Tokyo",
    "iso:country":"JP",
    "name:jpn_x_preferred":[
        "\u90f7\u30ce\u6d66\u753a\u90f7\u30ce\u6d66"
    ],
    "name:und_x_variant":[
        "G\u014dnourach\u014d-g\u014dnoura",
        "G\u014dnoura"
    ],
    "wof:name":"Gonouracho-gonoura",
    "wof:placetype":"locality"
},
  "geometry": {"coordinates":[129.68621999999999,33.74603],"type":"Point"}
}