{
  "type": "Feature",
  "properties": {
    "gn:admin1_code":"28.0",
    "gn:admin2_code":"1848164.0",
    "gn:admin3_code":"29442.0",
    "gn:asciiname":"Hataya",
    "gn:country_code":"JP",
    "gn:dem":230,
    "gn:feature_class":"P",
    "gn:feature_code":"PPL",
    "gn:name":"Hataya",
    "gn:population":0,
    "gn:timezone":"Asia/Tokyo",
    "iso:country":"JP",
    "name:jpn_x_preferred":[
        "\u7551\u5c4b"
    ],
    "wof:name":"Hataya",
    "wof:placetype":"locality"
},
  "geometry": {"coordinates":[135.80484999999999,34.41146],"type":"Point"}
}