{
  "type": "Feature",
  "properties": {
    "gn:admin1_code":"21.0",
    "gn:admin2_code":"7412708.0",
    "gn:admin3_code":"43512.0",
    "gn:asciiname":"Shiiya",
    "gn:country_code":"JP",
    "gn:dem":220,
    "gn:feature_class":"P",
    "gn:feature_code":"PPLL",
    "gn:name":"Shiiya",
    "gn:population":0,
    "gn:timezone":"Asia/Tokyo",
    "iso:country":"JP",
    "name:jpn_x_preferred":[
        "\u690e\u5c4b"
    ],
    "wof:name":"Shiiya",
    "wof:placetype":"locality"
},
  "geometry": {"coordinates":[130.79098999999999,32.27291],"type":"Point"}
}