{
  "type": "Feature",
  "properties": {
    "gn:admin1_code":"34.0",
    "gn:admin2_code":"7464126.0",
    "gn:asciiname":"Matsuishi",
    "gn:country_code":"JP",
    "gn:dem":15,
    "gn:feature_class":"P",
    "gn:feature_code":"PPL",
    "gn:name":"Matsuishi",
    "gn:population":0,
    "gn:timezone":"Asia/Tokyo",
    "iso:country":"JP",
    "wof:name":"Matsuishi",
    "wof:placetype":"locality"
},
  "geometry": {"coordinates":[139.71188000000001,36.09973],"type":"Point"}
}