{
  "type": "Feature",
  "properties": {
    "iso:country":"JP",
    "name:eng_x_preferred":[
        "Nanyotori 5 Chome"
    ],
    "name:eng_x_variant":[
        "Nanyoutoori 5 Choume",
        "Nanyotori 5 Chome"
    ],
    "name:jpn_x_preferred":[
        "\uff15\u4e01\u76ee"
    ],
    "name:jpn_x_variant":[
        "\u306a\u3093\u3088\u3046\u3068\u304a\u308a \uff15\u3061\u3087\u3046\u3081",
        "\u5357\u967d\u901a \uff15\u4e01\u76ee",
        "\uff15\u3061\u3087\u3046\u3081"
    ],
    "name:unk_x_variant":[
        "\uff15\u4e01\u76ee"
    ],
    "qs:gn_local":0,
    "qs:local_max":3194,
    "qs:local_sum":30209,
    "qs:localhoods":92,
    "qs:name":"\uff15\u4e01\u76ee",
    "qs:name_adm0":"\u65e5\u672c",
    "qs:name_adm1":"\u611b\u77e5\u770c",
    "qs:name_adm2":"\u5357\u533a",
    "qs:name_en":"Nanyotori 5 Chome",
    "qs:name_lau":"\u5357\u967d\u901a",
    "qs:name_local":"\u540d\u53e4\u5c4b\u5e02",
    "qs:photo_max":97,
    "qs:photo_sum":97,
    "qs:placetype":"Suburb",
    "qs:quad_count":1,
    "qs:woe_adm0":23424856,
    "qs:woe_adm1":2345851,
    "qs:woe_adm2":15015405,
    "qs:woe_lau":28440031,
    "qs:woe_local":1117817,
    "qs:woe_ver":"7.10.0",
    "wof:lang":[
        "jpn"
    ],
    "wof:name":"\uff15\u4e01\u76ee",
    "wof:placetype":"neighbourhood"
},
  "geometry": {"coordinates":[136.899261,35.100811],"type":"Point"}
}