{
  "type": "Feature",
  "properties": {
    "gn:admin1_code":"21.0",
    "gn:admin2_code":"1865168.0",
    "gn:asciiname":"Sakurayamamachi",
    "gn:country_code":"JP",
    "gn:dem":21,
    "gn:feature_class":"P",
    "gn:feature_code":"PPL",
    "gn:name":"Sakurayamamachi",
    "gn:population":0,
    "gn:timezone":"Asia/Tokyo",
    "iso:country":"JP",
    "name:jpn_x_preferred":[
        "\u685c\u5c71\u753a"
    ],
    "name:jpn_x_variant":[
        "\u3055\u304f\u3089\u3084\u307e\u307e\u3061",
        "\u30b5\u30af\u30e9\u30e4\u30de\u30de\u30c1"
    ],
    "wof:name":"Sakurayamamachi",
    "wof:placetype":"locality"
},
  "geometry": {"coordinates":[130.45841999999999,32.9652],"type":"Point"}
}