{
  "type": "Feature",
  "properties": {
    "gn:admin1_code":"21.0",
    "gn:admin2_code":"1858418.0",
    "gn:admin3_code":"43105.0",
    "gn:asciiname":"Jogatsuji",
    "gn:country_code":"JP",
    "gn:dem":72,
    "gn:feature_class":"P",
    "gn:feature_code":"PPLL",
    "gn:name":"J\u014dgatsuji",
    "gn:population":0,
    "gn:timezone":"Asia/Tokyo",
    "iso:country":"JP",
    "name:jpn_x_preferred":[
        "\u57ce\u30f6\u8fbb"
    ],
    "name:jpn_x_variant":[
        "\u3058\u3087\u3046\u304c\u3064\u3058",
        "\u30b8\u30e7\u30a6\u30ac\u30c4\u30b8"
    ],
    "name:und_x_variant":[
        "J\u014dgatsuji"
    ],
    "wof:name":"Jogatsuji",
    "wof:placetype":"locality"
},
  "geometry": {"coordinates":[130.71451999999999,32.86904000000001],"type":"Point"}
}