{
  "type": "Feature",
  "properties": {
    "gn:admin1_code":"45",
    "gn:asciiname":"Hommura",
    "gn:cc2":"JP",
    "gn:country_code":"JP",
    "gn:dem":-9999,
    "gn:feature_class":"P",
    "gn:feature_code":"PPL",
    "gn:name":"Hommura",
    "gn:population":0,
    "gn:timezone":"Asia/Tokyo",
    "iso:country":"JP",
    "name:und_x_variant":[
        "Motomura",
        "Hommura"
    ],
    "wof:name":"Hommura",
    "wof:placetype":"locality"
},
  "geometry": {"coordinates":[131.40000000000001,34.48333],"type":"Point"}
}