{
  "type": "Feature",
  "properties": {
    "gn:admin1_code":"3.0",
    "gn:admin2_code":"2127674.0",
    "gn:asciiname":"Kobayashi",
    "gn:country_code":"JP",
    "gn:dem":52,
    "gn:feature_class":"P",
    "gn:feature_code":"PPL",
    "gn:name":"Kobayashi",
    "gn:population":0,
    "gn:timezone":"Asia/Tokyo",
    "iso:country":"JP",
    "name:jpn_x_preferred":[
        "\u5c0f\u6797"
    ],
    "name:jpn_x_variant":[
        "\u3053\u3070\u3084\u3057",
        "\u30b3\u30d0\u30e4\u30b7"
    ],
    "wof:name":"Kobayashi",
    "wof:placetype":"locality"
},
  "geometry": {"coordinates":[141.23488,40.5971],"type":"Point"}
}