{
  "type": "Feature",
  "properties": {
    "gn:admin1_code":"3.0",
    "gn:admin2_code":"2130056.0",
    "gn:asciiname":"Kawasaki",
    "gn:country_code":"JP",
    "gn:dem":43,
    "gn:feature_class":"P",
    "gn:feature_code":"PPL",
    "gn:name":"Kawasaki",
    "gn:population":0,
    "gn:timezone":"Asia/Tokyo",
    "iso:country":"JP",
    "name:jpn_x_preferred":[
        "\u5ddd\u5148"
    ],
    "name:jpn_x_variant":[
        "\u304b\u308f\u3055\u304d",
        "\u30ab\u30ef\u30b5\u30ad"
    ],
    "wof:name":"Kawasaki",
    "wof:placetype":"locality"
},
  "geometry": {"coordinates":[140.49128000000002,40.58964],"type":"Point"}
}