{
  "type": "Feature",
  "properties": {
    "gn:admin1_code":"42.0",
    "gn:admin2_code":"1849870.0",
    "gn:asciiname":"Makino",
    "gn:country_code":"JP",
    "gn:dem":113,
    "gn:feature_class":"P",
    "gn:feature_code":"PPL",
    "gn:name":"Makino",
    "gn:population":0,
    "gn:timezone":"Asia/Tokyo",
    "iso:country":"JP",
    "name:azb_x_preferred":[
        "\u0645\u0627\u06a9\u06cc\u0646\u0648"
    ],
    "name:fas_x_preferred":[
        "\u0645\u0627\u06a9\u06cc\u0646\u0648"
    ],
    "name:ind_x_preferred":[
        "Makino"
    ],
    "name:jpn_x_preferred":[
        "\u7267\u91ce"
    ],
    "name:jpn_x_variant":[
        "\u7267\u91ce\u30d5\u30e9\u30a4\u30b9\u88fd\u4f5c\u6240"
    ],
    "name:rus_x_preferred":[
        "Makino"
    ],
    "name:zho_x_preferred":[
        "\u7267\u91ce\u673a\u5e8a"
    ],
    "wof:name":"Makino",
    "wof:placetype":"locality"
},
  "geometry": {"coordinates":[137.26820000000001,36.59296],"type":"Point"}
}