{
  "type": "Feature",
  "properties": {
    "gn:admin1_code":"42.0",
    "gn:admin2_code":"1849870.0",
    "gn:asciiname":"Makino",
    "gn:country_code":"JP",
    "gn:dem":113,
    "gn:feature_class":"P",
    "gn:feature_code":"PPL",
    "gn:name":"Makino",
    "gn:population":0,
    "gn:timezone":"Asia/Tokyo",
    "iso:country":"JP",
    "name:jpn_x_preferred":[
        "\u7267\u91ce"
    ],
    "wof:name":"Makino",
    "wof:placetype":"locality"
},
  "geometry": {"coordinates":[137.26820000000001,36.59296],"type":"Point"}
}