{
  "type": "Feature",
  "properties": {
    "gn:admin1_code":"8.0",
    "gn:admin2_code":"1859317.0",
    "gn:asciiname":"Yamatomachi-wasetani",
    "gn:country_code":"JP",
    "gn:dem":317,
    "gn:feature_class":"P",
    "gn:feature_code":"PPL",
    "gn:name":"Yamatomachi-wasetani",
    "gn:population":0,
    "gn:timezone":"Asia/Tokyo",
    "iso:country":"JP",
    "name:jpn_x_preferred":[
        "\u5c71\u90fd\u753a\u65e9\u7a32\u8c37"
    ],
    "wof:name":"Yamatomachi-wasetani",
    "wof:placetype":"locality"
},
  "geometry": {"coordinates":[139.76621,37.69447],"type":"Point"}
}