{
  "type": "Feature",
  "properties": {
    "gn:admin1_code":"19.0",
    "gn:admin2_code":"1848350.0",
    "gn:admin3_code":"14116.0",
    "gn:asciiname":"Izumigaoka",
    "gn:country_code":"JP",
    "gn:dem":40,
    "gn:feature_class":"P",
    "gn:feature_code":"PPL",
    "gn:name":"Izumigaoka",
    "gn:population":0,
    "gn:timezone":"Asia/Tokyo",
    "iso:country":"JP",
    "name:jpn_x_preferred":[
        "\u548c\u6cc9\u304c\u4e18"
    ],
    "wof:name":"Izumigaoka",
    "wof:placetype":"locality"
},
  "geometry": {"coordinates":[139.49522999999999,35.40511],"type":"Point"}
}