{
  "type": "Feature",
  "properties": {
    "gn:admin1_code":"3.0",
    "gn:admin2_code":"2130088.0",
    "gn:admin3_code":"2301.0",
    "gn:asciiname":"Sotodoji",
    "gn:country_code":"JP",
    "gn:dem":79,
    "gn:feature_class":"P",
    "gn:feature_code":"PPL",
    "gn:name":"Sotod\u014dji",
    "gn:population":0,
    "gn:timezone":"Asia/Tokyo",
    "iso:country":"JP",
    "name:jpn_x_preferred":[
        "\u5916\u7ae5\u5b50"
    ],
    "name:jpn_x_variant":[
        "\u305d\u3068\u3069\u3046\u3058",
        "\u30bd\u30c8\u30c9\u30a6\u30b8"
    ],
    "name:und_x_variant":[
        "Sotod\u014dji"
    ],
    "wof:name":"Sotodoji",
    "wof:placetype":"locality"
},
  "geometry": {"coordinates":[140.98236,40.8862],"type":"Point"}
}