{
  "type": "Feature",
  "properties": {
    "iso:country":"JP",
    "label:eng_x_preferred_longname":[
        "Toga Village"
    ],
    "label:eng_x_preferred_placetype":[
        "village"
    ],
    "name:eng_x_preferred":[
        "Toga"
    ],
    "name:eng_x_variant":[
        "Toga Village"
    ],
    "name:jpn_x_preferred":[
        "\u5229\u8cc0\u6751"
    ],
    "qs:name":"\u5229\u8cc0\u6751",
    "qs:name_adm0":"\u65e5\u672c",
    "qs:name_adm1":"\u5bcc\u5c71\u770c",
    "qs:photos":29,
    "qs:photos_1k":6,
    "qs:photos_9k":1,
    "qs:photos_9r":2,
    "qs:photos_all":29,
    "qs:photos_sr":2,
    "qs:placetype":"LocalAdmin",
    "qs:pop_sr":"0",
    "wof:name":"Toga",
    "wof:placetype":"localadmin"
},
  "geometry": {"coordinates":[137.05478600000001,36.414099],"type":"Point"}
}