{
  "type": "Feature",
  "properties": {
    "gn:admin1_code":"37.0",
    "gn:admin2_code":"1864089.0",
    "gn:asciiname":"Hachioji-honcho",
    "gn:country_code":"JP",
    "gn:dem":364,
    "gn:feature_class":"P",
    "gn:feature_code":"PPLL",
    "gn:name":"Hachi\u014dji-honch\u014d",
    "gn:population":0,
    "gn:timezone":"Asia/Tokyo",
    "iso:country":"JP",
    "name:jpn_x_preferred":[
        "\u516b\u738b\u5bfa\u672c\u753a"
    ],
    "name:und_x_variant":[
        "Hachi\u014dji-honch\u014d"
    ],
    "wof:name":"Hachioji-honcho",
    "wof:placetype":"locality"
},
  "geometry": {"coordinates":[138.69203000000002,35.22709000000001],"type":"Point"}
}