{
  "type": "Feature",
  "properties": {
    "gn:admin1_code":"21.0",
    "gn:admin2_code":"1859490.0",
    "gn:admin3_code":"43404.0",
    "gn:asciiname":"Domyo",
    "gn:country_code":"JP",
    "gn:dem":105,
    "gn:feature_class":"P",
    "gn:feature_code":"PPLL",
    "gn:name":"D\u014dmy\u014d",
    "gn:population":0,
    "gn:timezone":"Asia/Tokyo",
    "iso:country":"JP",
    "name:jpn_x_preferred":[
        "\u9053\u660e"
    ],
    "name:jpn_x_variant":[
        "\u3069\u3046\u307f\u3087\u3046",
        "\u30c9\u30a6\u30df\u30e7\u30a6"
    ],
    "name:und_x_variant":[
        "D\u014dmy\u014d"
    ],
    "wof:name":"Domyo",
    "wof:placetype":"locality"
},
  "geometry": {"coordinates":[130.82762,32.83252],"type":"Point"}
}