{
  "type": "Feature",
  "properties": {
    "gn:admin1_code":"33.0",
    "gn:admin2_code":"1859936.0",
    "gn:asciiname":"Akaiwa",
    "gn:country_code":"JP",
    "gn:dem":217,
    "gn:feature_class":"P",
    "gn:feature_code":"PPLL",
    "gn:name":"Akaiwa",
    "gn:population":0,
    "gn:timezone":"Asia/Tokyo",
    "iso:country":"JP",
    "name:jpn_x_preferred":[
        "\u8d64\u5ca9"
    ],
    "wof:name":"Akaiwa",
    "wof:placetype":"locality"
},
  "geometry": {"coordinates":[130.10435000000001,33.03047],"type":"Point"}
}