{
  "type": "Feature",
  "properties": {
    "gn:admin1_code":"7.0",
    "gn:admin2_code":"1854055.0",
    "gn:admin3_code":"40384.0",
    "gn:asciiname":"Ogura",
    "gn:country_code":"JP",
    "gn:dem":22,
    "gn:feature_class":"P",
    "gn:feature_code":"PPLL",
    "gn:name":"Ogura",
    "gn:population":0,
    "gn:timezone":"Asia/Tokyo",
    "iso:country":"JP",
    "name:jpn_x_preferred":[
        "\u5c3e\u5009"
    ],
    "wof:name":"Ogura",
    "wof:placetype":"locality"
},
  "geometry": {"coordinates":[130.65791000000002,33.83007],"type":"Point"}
}