{
  "type": "Feature",
  "properties": {
    "gn:admin1_code":"08",
    "gn:admin2_code":"2112978.0",
    "gn:asciiname":"Ryozenmachi-shimo'oguni",
    "gn:country_code":"JP",
    "gn:dem":111,
    "gn:feature_class":"P",
    "gn:feature_code":"PPL",
    "gn:name":"Ry\u014dzenmachi-shimo\u2019oguni",
    "gn:population":0,
    "gn:timezone":"Asia/Tokyo",
    "iso:country":"JP",
    "name:jpn_x_preferred":[
        "\u970a\u5c71\u753a\u4e0b\u5c0f\u56fd"
    ],
    "name:und_x_variant":[
        "Shimo-okuni",
        "Shimo-oguni",
        "Ry\u014dzenmachi-shimo\u2019oguni"
    ],
    "wof:name":"Ryozenmachi-shimo'oguni",
    "wof:placetype":"locality"
},
  "geometry": {"coordinates":[140.58333000000002,37.76667],"type":"Point"}
}