{
  "type": "Feature",
  "properties": {
    "gn:admin1_code":"33",
    "gn:admin2_code":"1850832.0",
    "gn:asciiname":"Wakagimachi-kawago",
    "gn:country_code":"JP",
    "gn:dem":160,
    "gn:feature_class":"P",
    "gn:feature_code":"PPL",
    "gn:name":"Wakagimachi-kawago",
    "gn:population":0,
    "gn:timezone":"Asia/Tokyo",
    "iso:country":"JP",
    "name:jpn_x_preferred":[
        "\u82e5\u6728\u753a\u5ddd\u53e4"
    ],
    "name:und_x_variant":[
        "Wakaki-machi",
        "Wakagimachi",
        "Wakagimachi-kawago"
    ],
    "wof:name":"Wakagimachi-kawago",
    "wof:placetype":"locality"
},
  "geometry": {"coordinates":[130.01667,33.25],"type":"Point"}
}