{
  "type": "Feature",
  "properties": {
    "gn:admin1_code":"11",
    "gn:admin2_code":"1848699.0",
    "gn:admin3_code":"34369.0",
    "gn:asciiname":"Yae",
    "gn:country_code":"JP",
    "gn:dem":292,
    "gn:feature_class":"P",
    "gn:feature_code":"PPL",
    "gn:name":"Yae",
    "gn:population":0,
    "gn:timezone":"Asia/Tokyo",
    "iso:country":"JP",
    "wof:name":"Yae",
    "wof:placetype":"locality"
},
  "geometry": {"coordinates":[132.53333000000001,34.68333],"type":"Point"}
}