{
  "type": "Feature",
  "properties": {
    "gn:admin1_code":"38",
    "gn:admin2_code":"1849052.0",
    "gn:asciiname":"Koteyama",
    "gn:country_code":"JP",
    "gn:dem":107,
    "gn:feature_class":"P",
    "gn:feature_code":"PPL",
    "gn:name":"Koteyama",
    "gn:population":0,
    "gn:timezone":"Asia/Tokyo",
    "iso:country":"JP",
    "wof:name":"Koteyama",
    "wof:placetype":"locality"
},
  "geometry": {"coordinates":[139.96666999999999,36.53333],"type":"Point"}
}