{
  "type": "Feature",
  "properties": {
    "gn:admin1_code":"15",
    "gn:admin2_code":"1851337.0",
    "gn:asciiname":"Takojimamachi",
    "gn:country_code":"JP",
    "gn:dem":7,
    "gn:feature_class":"P",
    "gn:feature_code":"PPL",
    "gn:name":"Takojimamachi",
    "gn:population":0,
    "gn:timezone":"Asia/Tokyo",
    "iso:country":"JP",
    "name:jpn_x_preferred":[
        "\u86f8\u5cf6\u753a"
    ],
    "name:und_x_variant":[
        "Takajima",
        "Takoshima",
        "Takojimamachi",
        "Takojima"
    ],
    "wof:name":"Takojimamachi",
    "wof:placetype":"locality"
},
  "geometry": {"coordinates":[137.31218999999999,37.44135],"type":"Point"}
}