{
  "type": "Feature",
  "properties": {
    "gn:admin1_code":"8.0",
    "gn:admin2_code":"1859317.0",
    "gn:asciiname":"Hariu",
    "gn:country_code":"JP",
    "gn:dem":310,
    "gn:feature_class":"P",
    "gn:feature_code":"PPLL",
    "gn:name":"Hariu",
    "gn:population":0,
    "gn:timezone":"Asia/Tokyo",
    "iso:country":"JP",
    "name:jpn_x_preferred":[
        "\u91dd\u751f"
    ],
    "wof:name":"Hariu",
    "wof:placetype":"locality"
},
  "geometry": {"coordinates":[139.86331999999999,37.71929],"type":"Point"}
}