{
  "type": "Feature",
  "properties": {
    "gn:admin1_code":"04",
    "gn:admin2_code":"2111171.0",
    "gn:asciiname":"Yamakura",
    "gn:country_code":"JP",
    "gn:dem":42,
    "gn:feature_class":"P",
    "gn:feature_code":"PPL",
    "gn:name":"Yamakura",
    "gn:population":0,
    "gn:timezone":"Asia/Tokyo",
    "iso:country":"JP",
    "wof:name":"Yamakura",
    "wof:placetype":"locality"
},
  "geometry": {"coordinates":[140.53333000000001,35.78333],"type":"Point"}
}