{
  "type": "Feature",
  "properties": {
    "gn:admin1_code":"4.0",
    "gn:admin2_code":"1864901.0",
    "gn:admin3_code":"12463.0",
    "gn:asciiname":"Sunada",
    "gn:country_code":"JP",
    "gn:dem":9,
    "gn:feature_class":"P",
    "gn:feature_code":"PPLL",
    "gn:name":"Sunada",
    "gn:population":0,
    "gn:timezone":"Asia/Tokyo",
    "iso:country":"JP",
    "name:jpn_x_preferred":[
        "\u7802\u7530"
    ],
    "name:jpn_x_variant":[
        "\u3059\u306a\u3060",
        "\u30b9\u30ca\u30c0"
    ],
    "wof:name":"Sunada",
    "wof:placetype":"locality"
},
  "geometry": {"coordinates":[139.83295000000001,35.12123],"type":"Point"}
}