{
  "type": "Feature",
  "properties": {
    "gn:admin1_code":"4.0",
    "gn:admin2_code":"2112386.0",
    "gn:asciiname":"Minoguchi",
    "gn:country_code":"JP",
    "gn:dem":64,
    "gn:feature_class":"P",
    "gn:feature_code":"PPLL",
    "gn:name":"Minoguchi",
    "gn:population":0,
    "gn:timezone":"Asia/Tokyo",
    "iso:country":"JP",
    "name:jpn_x_preferred":[
        "\u30df\u30ce\u53e3"
    ],
    "name:jpn_x_variant":[
        "\u307f\u306e\u3050\u3061",
        "\u30df\u30ce\u30b0\u30c1"
    ],
    "wof:name":"Minoguchi",
    "wof:placetype":"locality"
},
  "geometry": {"coordinates":[140.07189,35.13765],"type":"Point"}
}