{
  "type": "Feature",
  "properties": {
    "gn:admin1_code":"21.0",
    "gn:admin2_code":"1865358.0",
    "gn:asciiname":"Sakiyama",
    "gn:country_code":"JP",
    "gn:dem":133,
    "gn:feature_class":"P",
    "gn:feature_code":"PPLL",
    "gn:name":"Sakiyama",
    "gn:population":0,
    "gn:timezone":"Asia/Tokyo",
    "iso:country":"JP",
    "name:jpn_x_preferred":[
        "\u54b2\u5c71"
    ],
    "name:jpn_x_variant":[
        "\u3055\u304d\u3084\u307e",
        "\u30b5\u30ad\u30e4\u30de"
    ],
    "wof:name":"Sakiyama",
    "wof:placetype":"locality"
},
  "geometry": {"coordinates":[129.97991000000002,32.36199999999999],"type":"Point"}
}