{
  "type": "Feature",
  "properties": {
    "iso:country":"JP",
    "name:eng_x_preferred":[
        "Hayashima"
    ],
    "name:eng_x_variant":[
        "Hayashima Town"
    ],
    "name:jpn_x_preferred":[
        "\u65e9\u5cf6\u753a"
    ],
    "qs:name":"\u65e9\u5cf6\u753a",
    "qs:name_adm0":"\u65e5\u672c",
    "qs:name_adm1":"\u5ca1\u5c71\u770c",
    "qs:photos":138,
    "qs:photos_1k":28,
    "qs:photos_9k":1,
    "qs:photos_9r":3,
    "qs:photos_all":138,
    "qs:photos_sr":3,
    "qs:placetype":"Town",
    "qs:pop_sr":"0",
    "wof:name":"Hayashima",
    "wof:placetype":"locality"
},
  "geometry": {"coordinates":[133.773651,34.610605],"type":"Point"}
}