{
  "type": "Feature",
  "properties": {
    "gn:admin1_code":"21.0",
    "gn:admin2_code":"7412705.0",
    "gn:admin3_code":"43482.0",
    "gn:asciiname":"Ominami",
    "gn:country_code":"JP",
    "gn:dem":50,
    "gn:feature_class":"P",
    "gn:feature_code":"PPLL",
    "gn:name":"\u014cminami",
    "gn:population":0,
    "gn:timezone":"Asia/Tokyo",
    "iso:country":"JP",
    "name:jpn_x_preferred":[
        "\u5927\u5357"
    ],
    "name:jpn_x_variant":[
        "\u304a\u304a\u307f\u306a\u307f",
        "\u30aa\u30aa\u30df\u30ca\u30df"
    ],
    "name:und_x_variant":[
        "\u014cminami"
    ],
    "wof:name":"Ominami",
    "wof:placetype":"locality"
},
  "geometry": {"coordinates":[130.51036999999999,32.24244],"type":"Point"}
}