{
  "type": "Feature",
  "properties": {
    "gn:admin1_code":"24.0",
    "gn:admin2_code":"7446988.0",
    "gn:admin3_code":"4362.0",
    "gn:asciiname":"Sakamoto",
    "gn:country_code":"JP",
    "gn:dem":25,
    "gn:feature_class":"P",
    "gn:feature_code":"PPL",
    "gn:name":"Sakamoto",
    "gn:population":0,
    "gn:timezone":"Asia/Tokyo",
    "iso:country":"JP",
    "name:jpn_x_preferred":[
        "\u5742\u5143"
    ],
    "wof:name":"Sakamoto",
    "wof:placetype":"locality"
},
  "geometry": {"coordinates":[140.90000000000001,37.91667],"type":"Point"}
}