{
  "type": "Feature",
  "properties": {
    "gn:admin1_code":"4.0",
    "gn:admin2_code":"1863903.0",
    "gn:asciiname":"Shiomicho",
    "gn:country_code":"JP",
    "gn:dem":4,
    "gn:feature_class":"P",
    "gn:feature_code":"PPL",
    "gn:name":"Shiomich\u014d",
    "gn:population":0,
    "gn:timezone":"Asia/Tokyo",
    "iso:country":"JP",
    "name:jpn_x_preferred":[
        "\u6f6e\u898b\u753a"
    ],
    "name:und_x_variant":[
        "Shiomich\u014d",
        "Shiomi"
    ],
    "wof:name":"Shiomicho",
    "wof:placetype":"locality"
},
  "geometry": {"coordinates":[139.96666999999999,35.675],"type":"Point"}
}