{
  "type": "Feature",
  "properties": {
    "gn:admin1_code":"26.0",
    "gn:admin2_code":"1857516.0",
    "gn:asciiname":"Shinakura",
    "gn:country_code":"JP",
    "gn:dem":856,
    "gn:feature_class":"P",
    "gn:feature_code":"PPL",
    "gn:name":"Shinakura",
    "gn:population":0,
    "gn:timezone":"Asia/Tokyo",
    "iso:country":"JP",
    "name:jpn_x_preferred":[
        "\u7a32\u5009"
    ],
    "wof:name":"Shinakura",
    "wof:placetype":"locality"
},
  "geometry": {"coordinates":[138.00148000000002,36.29297],"type":"Point"}
}