{
  "type": "Feature",
  "properties": {
    "gn:admin1_code":"32.0",
    "gn:admin2_code":"1864413.0",
    "gn:asciiname":"Tsunobecho",
    "gn:country_code":"JP",
    "gn:dem":4,
    "gn:feature_class":"P",
    "gn:feature_code":"PPL",
    "gn:name":"Tsunobech\u014d",
    "gn:population":0,
    "gn:timezone":"Asia/Tokyo",
    "iso:country":"JP",
    "name:jpn_x_preferred":[
        "\u6d25\u306e\u8fba\u753a"
    ],
    "name:und_x_variant":[
        "Tsunobech\u014d"
    ],
    "wof:name":"Tsunobecho",
    "wof:placetype":"locality"
},
  "geometry": {"coordinates":[135.63414,34.72490999999999],"type":"Point"}
}