{
  "type": "Feature",
  "properties": {
    "gn:admin1_code":"33.0",
    "gn:admin2_code":"7391363.0",
    "gn:asciiname":"Nanatsukawauchi",
    "gn:country_code":"JP",
    "gn:dem":80,
    "gn:feature_class":"P",
    "gn:feature_code":"PPLL",
    "gn:name":"Nanatsukawauchi",
    "gn:population":0,
    "gn:timezone":"Asia/Tokyo",
    "iso:country":"JP",
    "name:jpn_x_preferred":[
        "\u4e03\u30c4\u5ddd\u5185"
    ],
    "wof:name":"Nanatsukawauchi",
    "wof:placetype":"locality"
},
  "geometry": {"coordinates":[130.02420000000001,33.10409],"type":"Point"}
}