{
  "type": "Feature",
  "properties": {
    "gn:admin1_code":"4.0",
    "gn:admin2_code":"1861964.0",
    "gn:asciiname":"Koya-shinden",
    "gn:country_code":"JP",
    "gn:dem":5,
    "gn:feature_class":"P",
    "gn:feature_code":"PPL",
    "gn:name":"K\u014dya-shinden",
    "gn:population":0,
    "gn:timezone":"Asia/Tokyo",
    "iso:country":"JP",
    "name:jpn_x_preferred":[
        "\u9ad8\u8c37\u65b0\u7530"
    ],
    "name:und_x_variant":[
        "K\u014dya-shinden"
    ],
    "wof:name":"Koya-shinden",
    "wof:placetype":"locality"
},
  "geometry": {"coordinates":[139.95147,35.68024000000001],"type":"Point"}
}