{
  "type": "Feature",
  "properties": {
    "gn:admin1_code":"37.0",
    "gn:admin2_code":"1851714.0",
    "gn:admin3_code":"22103.0",
    "gn:asciiname":"Mukoyama",
    "gn:country_code":"JP",
    "gn:dem":114,
    "gn:feature_class":"P",
    "gn:feature_code":"PPLL",
    "gn:name":"Mukoyama",
    "gn:population":0,
    "gn:timezone":"Asia/Tokyo",
    "iso:country":"JP",
    "name:jpn_x_preferred":[
        "\u5411\u5c71"
    ],
    "wof:name":"Mukoyama",
    "wof:placetype":"locality"
},
  "geometry": {"coordinates":[138.55916000000002,35.13077],"type":"Point"}
}