{
  "type": "Feature",
  "properties": {
    "gn:admin1_code":"18.0",
    "gn:admin2_code":"7383991.0",
    "gn:asciiname":"Motai",
    "gn:country_code":"JP",
    "gn:dem":203,
    "gn:feature_class":"P",
    "gn:feature_code":"PPLL",
    "gn:name":"Motai",
    "gn:population":0,
    "gn:timezone":"Asia/Tokyo",
    "iso:country":"JP",
    "name:jpn_x_preferred":[
        "\u99ac\u6e21"
    ],
    "name:jpn_x_variant":[
        "\u3082\u305f\u3044",
        "\u30e2\u30bf\u30a4"
    ],
    "wof:name":"Motai",
    "wof:placetype":"locality"
},
  "geometry": {"coordinates":[130.54487,32.02178],"type":"Point"}
}