{
  "type": "Feature",
  "properties": {
    "gn:admin1_code":"47",
    "gn:admin2_code":"1850107.0",
    "gn:asciiname":"Kanera",
    "gn:country_code":"JP",
    "gn:dem":23,
    "gn:feature_class":"P",
    "gn:feature_code":"PPL",
    "gn:name":"Kanera",
    "gn:population":0,
    "gn:timezone":"Asia/Tokyo",
    "iso:country":"JP",
    "name:jpn_x_preferred":[
        "\u91d1\u826f"
    ],
    "name:und_x_variant":[
        "Karara",
        "Kanera"
    ],
    "wof:name":"Kanera",
    "wof:placetype":"locality"
},
  "geometry": {"coordinates":[127.70520999999999,26.18054],"type":"Point"}
}