{
  "type": "Feature",
  "properties": {
    "gn:admin1_code":"19.0",
    "gn:admin2_code":"1864091.0",
    "gn:asciiname":"Uchimodori",
    "gn:country_code":"JP",
    "gn:dem":41,
    "gn:feature_class":"P",
    "gn:feature_code":"PPL",
    "gn:name":"Uchimodori",
    "gn:population":0,
    "gn:timezone":"Asia/Tokyo",
    "iso:country":"JP",
    "name:jpn_x_preferred":[
        "\u6253\u623b"
    ],
    "wof:name":"Uchimodori",
    "wof:placetype":"locality"
},
  "geometry": {"coordinates":[139.42011000000002,35.39377],"type":"Point"}
}