{
  "type": "Feature",
  "properties": {
    "gn:admin1_code":"2.0",
    "gn:admin2_code":"2113122.0",
    "gn:asciiname":"Yabase-daidohigashi",
    "gn:country_code":"JP",
    "gn:dem":8,
    "gn:feature_class":"P",
    "gn:feature_code":"PPL",
    "gn:name":"Yabase-daid\u014dhigashi",
    "gn:population":0,
    "gn:timezone":"Asia/Tokyo",
    "iso:country":"JP",
    "name:jpn_x_preferred":[
        "\u516b\u6a4b\u5927\u9053\u6771"
    ],
    "name:jpn_x_variant":[
        "\u3084\u3070\u305b\u3060\u3044\u3069\u3046\u3072\u304c\u3057",
        "\u30e4\u30d0\u30bb\u30c0\u30a4\u30c9\u30a6\u30d2\u30ac\u30b7"
    ],
    "name:und_x_variant":[
        "Yabase-daid\u014dhigashi"
    ],
    "wof:name":"Yabase-daidohigashi",
    "wof:placetype":"locality"
},
  "geometry": {"coordinates":[140.09111999999999,39.72975],"type":"Point"}
}