{
  "type": "Feature",
  "properties": {
    "gn:admin1_code":"11",
    "gn:admin2_code":"1857327.0",
    "gn:asciiname":"Mukaita",
    "gn:country_code":"JP",
    "gn:dem":25,
    "gn:feature_class":"P",
    "gn:feature_code":"PPL",
    "gn:name":"Mukaita",
    "gn:population":0,
    "gn:timezone":"Asia/Tokyo",
    "iso:country":"JP",
    "name:und_x_variant":[
        "Muk\u014dtano",
        "Muk\u014dtanoura",
        "Mukaitanoura",
        "Mukaita"
    ],
    "wof:name":"Mukaita",
    "wof:placetype":"locality"
},
  "geometry": {"coordinates":[133.10499999999999,34.32944000000001],"type":"Point"}
}