{
  "type": "Feature",
  "properties": {
    "gn:admin1_code":"12.0",
    "gn:admin2_code":"7428102.0",
    "gn:admin3_code":"1608.0",
    "gn:asciiname":"Esamambetsu",
    "gn:country_code":"JP",
    "gn:dem":175,
    "gn:feature_class":"P",
    "gn:feature_code":"PPLL",
    "gn:name":"Esamambetsu",
    "gn:population":0,
    "gn:timezone":"Asia/Tokyo",
    "iso:country":"JP",
    "name:jpn_x_preferred":[
        "\u30a8\u30b5\u30de\u30f3\u30d9\u30c4"
    ],
    "name:jpn_x_variant":[
        "\u3048\u3055\u307e\u3093\u3079\u3064"
    ],
    "wof:name":"Esamambetsu",
    "wof:placetype":"locality"
},
  "geometry": {"coordinates":[143.00173000000001,42.19716],"type":"Point"}
}