{
  "type": "Feature",
  "properties": {
    "gn:admin1_code":"13",
    "gn:admin2_code":"1859161.0",
    "gn:admin3_code":"28111.0",
    "gn:asciiname":"Oshibedanicho-takawa",
    "gn:country_code":"JP",
    "gn:dem":73,
    "gn:feature_class":"P",
    "gn:feature_code":"PPL",
    "gn:name":"Oshibedanich\u014d-takawa",
    "gn:population":0,
    "gn:timezone":"Asia/Tokyo",
    "iso:country":"JP",
    "name:jpn_x_preferred":[
        "\u62bc\u90e8\u8c37\u753a\u9ad8\u548c"
    ],
    "name:und_x_variant":[
        "Oshibedanich\u014d-takawa",
        "Takawa"
    ],
    "wof:name":"Oshibedanicho-takawa",
    "wof:placetype":"locality"
},
  "geometry": {"coordinates":[135.01928999999998,34.74248],"type":"Point"}
}