{
  "type": "Feature",
  "properties": {
    "gn:admin1_code":"16.0",
    "gn:admin2_code":"2112822.0",
    "gn:asciiname":"Uchitakamatsu",
    "gn:country_code":"JP",
    "gn:dem":186,
    "gn:feature_class":"P",
    "gn:feature_code":"PPL",
    "gn:name":"Uchitakamatsu",
    "gn:population":0,
    "gn:timezone":"Asia/Tokyo",
    "iso:country":"JP",
    "name:jpn_x_preferred":[
        "\u5185\u9ad8\u677e"
    ],
    "name:jpn_x_variant":[
        "\u3046\u3061\u305f\u304b\u307e\u3064",
        "\u30a6\u30c1\u30bf\u30ab\u30de\u30c4"
    ],
    "wof:name":"Uchitakamatsu",
    "wof:placetype":"locality"
},
  "geometry": {"coordinates":[141.18323000000001,39.38374],"type":"Point"}
}