{
  "type": "Feature",
  "properties": {
    "gn:admin1_code":"21.0",
    "gn:admin2_code":"1865358.0",
    "gn:asciiname":"Imamura",
    "gn:country_code":"JP",
    "gn:dem":42,
    "gn:feature_class":"P",
    "gn:feature_code":"PPLL",
    "gn:name":"Imamura",
    "gn:population":0,
    "gn:timezone":"Asia/Tokyo",
    "iso:country":"JP",
    "name:jpn_x_preferred":[
        "\u4eca\u6751"
    ],
    "name:jpn_x_variant":[
        "\u3044\u307e\u3080\u3089",
        "\u30a4\u30de\u30e0\u30e9"
    ],
    "wof:name":"Imamura",
    "wof:placetype":"locality"
},
  "geometry": {"coordinates":[130.09028999999998,32.35798],"type":"Point"}
}