{
  "type": "Feature",
  "properties": {
    "gn:admin1_code":"15.0",
    "gn:admin2_code":"1860240.0",
    "gn:asciiname":"Yoshiwaramachi",
    "gn:country_code":"JP",
    "gn:dem":12,
    "gn:feature_class":"P",
    "gn:feature_code":"PPL",
    "gn:name":"Yoshiwaramachi",
    "gn:population":0,
    "gn:timezone":"Asia/Tokyo",
    "iso:country":"JP",
    "name:jpn_x_preferred":[
        "\u5409\u539f\u753a"
    ],
    "wof:name":"Yoshiwaramachi",
    "wof:placetype":"locality"
},
  "geometry": {"coordinates":[136.69130000000001,36.61101],"type":"Point"}
}