{
  "type": "Feature",
  "properties": {
    "gn:admin1_code":"05",
    "gn:admin2_code":"1857456.0",
    "gn:asciiname":"Obama",
    "gn:cc2":"JP",
    "gn:country_code":"JP",
    "gn:dem":47,
    "gn:feature_class":"P",
    "gn:feature_code":"PPL",
    "gn:name":"Obama",
    "gn:population":0,
    "gn:timezone":"Asia/Tokyo",
    "iso:country":"JP",
    "name:und_x_variant":[
        "Ohama",
        "Obama"
    ],
    "wof:name":"Obama",
    "wof:placetype":"locality"
},
  "geometry": {"coordinates":[132.63333,33.96667],"type":"Point"}
}