{
  "type": "Feature",
  "properties": {
    "gn:admin1_code":"27",
    "gn:admin2_code":"7418805.0",
    "gn:asciiname":"Oshimamura-konoura",
    "gn:country_code":"JP",
    "gn:dem":7,
    "gn:feature_class":"P",
    "gn:feature_code":"PPL",
    "gn:name":"\u014cshimamura-k\u014dnoura",
    "gn:population":0,
    "gn:timezone":"Asia/Tokyo",
    "iso:country":"JP",
    "name:jpn_x_preferred":[
        "\u5927\u5cf6\u6751\u795e\u6d66"
    ],
    "name:und_x_variant":[
        "\u014cshimamura-k\u014dnoura",
        "K\u014dnoura"
    ],
    "wof:name":"Oshimamura-konoura",
    "wof:placetype":"locality"
},
  "geometry": {"coordinates":[129.55848,33.47786],"type":"Point"}
}