{
  "type": "Feature",
  "properties": {
    "gn:admin1_code":"5.0",
    "gn:admin2_code":"1926135.0",
    "gn:asciiname":"Mizuba",
    "gn:country_code":"JP",
    "gn:dem":6,
    "gn:feature_class":"P",
    "gn:feature_code":"PPL",
    "gn:name":"Mizuba",
    "gn:population":0,
    "gn:timezone":"Asia/Tokyo",
    "iso:country":"JP",
    "wof:name":"Mizuba",
    "wof:placetype":"locality"
},
  "geometry": {"coordinates":[133.02167,34.12028],"type":"Point"}
}