{
  "type": "Feature",
  "properties": {
    "gn:admin1_code":"21.0",
    "gn:admin2_code":"7412706.0",
    "gn:admin3_code":"43447.0",
    "gn:asciiname":"Aoishi",
    "gn:country_code":"JP",
    "gn:dem":666,
    "gn:feature_class":"P",
    "gn:feature_code":"PPLL",
    "gn:name":"Aoishi",
    "gn:population":0,
    "gn:timezone":"Asia/Tokyo",
    "iso:country":"JP",
    "name:jpn_x_preferred":[
        "\u9752\u77f3"
    ],
    "name:jpn_x_variant":[
        "\u3042\u304a\u3044\u3057",
        "\u30a2\u30aa\u30a4\u30b7"
    ],
    "wof:name":"Aoishi",
    "wof:placetype":"locality"
},
  "geometry": {"coordinates":[130.98096000000001,32.62185],"type":"Point"}
}