{
  "type": "Feature",
  "properties": {
    "gn:admin1_code":"12.0",
    "gn:admin2_code":"7428090.0",
    "gn:admin3_code":"1664.0",
    "gn:asciiname":"Naka-chambetsu",
    "gn:country_code":"JP",
    "gn:dem":19,
    "gn:feature_class":"P",
    "gn:feature_code":"PPL",
    "gn:name":"Naka-chambetsu",
    "gn:population":0,
    "gn:timezone":"Asia/Tokyo",
    "iso:country":"JP",
    "wof:name":"Naka-chambetsu",
    "wof:placetype":"locality"
},
  "geometry": {"coordinates":[144.67611000000005,43.20806],"type":"Point"}
}