{
  "type": "Feature",
  "properties": {
    "gn:admin1_code":"33.0",
    "gn:admin2_code":"1853274.0",
    "gn:asciiname":"Tafuse",
    "gn:country_code":"JP",
    "gn:dem":4,
    "gn:feature_class":"P",
    "gn:feature_code":"PPL",
    "gn:name":"Tafuse",
    "gn:population":0,
    "gn:timezone":"Asia/Tokyo",
    "iso:country":"JP",
    "name:jpn_x_preferred":[
        "\u591a\u5e03\u65bd"
    ],
    "wof:name":"Tafuse",
    "wof:placetype":"locality"
},
  "geometry": {"coordinates":[130.28856000000002,33.2566],"type":"Point"}
}