{
  "type": "Feature",
  "properties": {
    "gn:admin1_code":"15.0",
    "gn:admin2_code":"1860845.0",
    "gn:asciiname":"Sakumimachi",
    "gn:country_code":"JP",
    "gn:dem":46,
    "gn:feature_class":"P",
    "gn:feature_code":"PPL",
    "gn:name":"Sakumimachi",
    "gn:population":0,
    "gn:timezone":"Asia/Tokyo",
    "iso:country":"JP",
    "name:jpn_x_preferred":[
        "\u4f5c\u898b\u753a"
    ],
    "wof:name":"Sakumimachi",
    "wof:placetype":"locality"
},
  "geometry": {"coordinates":[136.34962999999999,36.32607],"type":"Point"}
}