{
  "type": "Feature",
  "properties": {
    "gn:admin1_code":"12.0",
    "gn:admin2_code":"2130058.0",
    "gn:admin3_code":"1641.0",
    "gn:asciiname":"Kotobukidori",
    "gn:country_code":"JP",
    "gn:dem":68,
    "gn:feature_class":"P",
    "gn:feature_code":"PPL",
    "gn:name":"Kotobukid\u014dri",
    "gn:population":0,
    "gn:timezone":"Asia/Tokyo",
    "iso:country":"JP",
    "name:jpn_x_preferred":[
        "\u5bff\u901a"
    ],
    "name:jpn_x_variant":[
        "\u3053\u3068\u3076\u304d\u3069\u304a\u308a",
        "\u30b3\u30c8\u30d6\u30ad\u30c9\u30aa\u30ea"
    ],
    "name:und_x_variant":[
        "Kotobukid\u014dri"
    ],
    "wof:name":"Kotobukidori",
    "wof:placetype":"locality"
},
  "geometry": {"coordinates":[143.28013000000001,42.48553],"type":"Point"}
}