{
  "type": "Feature",
  "properties": {
    "gn:admin1_code":"8.0",
    "gn:admin2_code":"1857203.0",
    "gn:admin3_code":"7362.0",
    "gn:asciiname":"Ouchi",
    "gn:country_code":"JP",
    "gn:dem":670,
    "gn:feature_class":"P",
    "gn:feature_code":"PPL",
    "gn:name":"\u014cuchi",
    "gn:population":0,
    "gn:timezone":"Asia/Tokyo",
    "iso:country":"JP",
    "name:deu_x_preferred":[
        "Ouchi"
    ],
    "name:jpn_x_preferred":[
        "\u5927\u5185"
    ],
    "name:rus_x_preferred":[
        "\u041e\u0443\u0442\u0438"
    ],
    "name:und_x_variant":[
        "\u014cuchi"
    ],
    "wof:name":"Ouchi",
    "wof:placetype":"locality"
},
  "geometry": {"coordinates":[139.85996,37.33378],"type":"Point"}
}