{
  "type": "Feature",
  "properties": {
    "gn:admin1_code":"17",
    "gn:admin2_code":"1857664.0",
    "gn:asciiname":"Honjimacho-tomari",
    "gn:country_code":"JP",
    "gn:dem":4,
    "gn:feature_class":"P",
    "gn:feature_code":"PPL",
    "gn:name":"Honjimach\u014d-tomari",
    "gn:population":0,
    "gn:timezone":"Asia/Tokyo",
    "iso:country":"JP",
    "name:jpn_x_preferred":[
        "\u672c\u5cf6\u753a\u6cca"
    ],
    "name:und_x_variant":[
        "Motoshima",
        "Honjima",
        "Tomari",
        "Honjimach\u014d-tomari"
    ],
    "wof:name":"Honjimacho-tomari",
    "wof:placetype":"locality"
},
  "geometry": {"coordinates":[133.78166999999999,34.385],"type":"Point"}
}