{
  "type": "Feature",
  "properties": {
    "gn:admin1_code":"21.0",
    "gn:admin2_code":"7412708.0",
    "gn:admin3_code":"43512.0",
    "gn:asciiname":"Mizunashi",
    "gn:country_code":"JP",
    "gn:dem":453,
    "gn:feature_class":"P",
    "gn:feature_code":"PPLL",
    "gn:name":"Mizunashi",
    "gn:population":0,
    "gn:timezone":"Asia/Tokyo",
    "iso:country":"JP",
    "name:jpn_x_preferred":[
        "\u6c34\u7121"
    ],
    "name:jpn_x_variant":[
        "\u307f\u305a\u306a\u3057",
        "\u30df\u30ba\u30ca\u30b7"
    ],
    "wof:name":"Mizunashi",
    "wof:placetype":"locality"
},
  "geometry": {"coordinates":[130.71705,32.34326],"type":"Point"}
}