{
  "type": "Feature",
  "properties": {
    "gn:admin1_code":"33.0",
    "gn:admin2_code":"7391357.0",
    "gn:asciiname":"Kanzakimachi-jobaru",
    "gn:country_code":"JP",
    "gn:dem":23,
    "gn:feature_class":"P",
    "gn:feature_code":"PPL",
    "gn:name":"Kanzakimachi-j\u014dbaru",
    "gn:population":0,
    "gn:timezone":"Asia/Tokyo",
    "iso:country":"JP",
    "name:jpn_x_preferred":[
        "\u795e\u57fc\u753a\u57ce\u539f"
    ],
    "name:und_x_variant":[
        "Kanzakimachi-j\u014dbaru"
    ],
    "wof:name":"Kanzakimachi-jobaru",
    "wof:placetype":"locality"
},
  "geometry": {"coordinates":[130.35903000000002,33.33781],"type":"Point"}
}