{
  "type": "Feature",
  "properties": {
    "gn:admin1_code":"21.0",
    "gn:admin2_code":"7412706.0",
    "gn:admin3_code":"43447.0",
    "gn:asciiname":"Suge",
    "gn:country_code":"JP",
    "gn:dem":416,
    "gn:feature_class":"P",
    "gn:feature_code":"PPL",
    "gn:name":"Suge",
    "gn:population":0,
    "gn:timezone":"Asia/Tokyo",
    "iso:country":"JP",
    "name:jpn_x_preferred":[
        "\u83c5"
    ],
    "name:jpn_x_variant":[
        "\u3059\u3052",
        "\u30b9\u30b2"
    ],
    "wof:name":"Suge",
    "wof:placetype":"locality"
},
  "geometry": {"coordinates":[131.01671000000002,32.64799],"type":"Point"}
}