{
  "type": "Feature",
  "properties": {
    "gn:admin1_code":"42",
    "gn:admin2_code":"1858253.0",
    "gn:asciiname":"Aramata",
    "gn:country_code":"JP",
    "gn:dem":4,
    "gn:feature_class":"P",
    "gn:feature_code":"PPL",
    "gn:name":"Aramata",
    "gn:population":0,
    "gn:timezone":"Asia/Tokyo",
    "iso:country":"JP",
    "name:jpn_x_preferred":[
        "\u8352\u4fe3"
    ],
    "name:und_x_variant":[
        "Aramato",
        "Aramata"
    ],
    "wof:name":"Aramata",
    "wof:placetype":"locality"
},
  "geometry": {"coordinates":[137.42303999999999,36.91412],"type":"Point"}
}