{
  "type": "Feature",
  "properties": {
    "gn:admin1_code":"09",
    "gn:admin2_code":"7419031.0",
    "gn:asciiname":"Shimobora",
    "gn:cc2":"JP",
    "gn:country_code":"JP",
    "gn:dem":471,
    "gn:feature_class":"P",
    "gn:feature_code":"PPL",
    "gn:name":"Shimobora",
    "gn:population":0,
    "gn:timezone":"Asia/Tokyo",
    "iso:country":"JP",
    "name:und_x_variant":[
        "Shimohora",
        "Shimobora"
    ],
    "wof:name":"Shimobora",
    "wof:placetype":"locality"
},
  "geometry": {"coordinates":[137.08333000000002,35.75],"type":"Point"}
}