{
  "type": "Feature",
  "properties": {
    "gn:admin1_code":"47",
    "gn:admin2_code":"7415820.0",
    "gn:asciiname":"Oshiro",
    "gn:country_code":"JP",
    "gn:dem":70,
    "gn:feature_class":"P",
    "gn:feature_code":"PPL",
    "gn:name":"\u014cshiro",
    "gn:population":0,
    "gn:timezone":"Asia/Tokyo",
    "iso:country":"JP",
    "name:jpn_x_preferred":[
        "\u5927\u57ce"
    ],
    "name:jpn_x_variant":[
        "\u304a\u304a\u3057\u308d"
    ],
    "name:und_x_variant":[
        "Ufugusuku",
        "\u014cgusuku",
        "\u014cshiro"
    ],
    "wof:name":"Oshiro",
    "wof:placetype":"locality"
},
  "geometry": {"coordinates":[127.75635,26.16362],"type":"Point"}
}