{
  "type": "Feature",
  "properties": {
    "gn:admin1_code":"3.0",
    "gn:admin2_code":"2127674.0",
    "gn:asciiname":"Gokai",
    "gn:country_code":"JP",
    "gn:dem":90,
    "gn:feature_class":"P",
    "gn:feature_code":"PPL",
    "gn:name":"Gokai",
    "gn:population":0,
    "gn:timezone":"Asia/Tokyo",
    "iso:country":"JP",
    "name:jpn_x_preferred":[
        "\u4e94\u754c"
    ],
    "name:jpn_x_variant":[
        "\u3054\u304b\u3044",
        "\u30b4\u30ab\u30a4"
    ],
    "wof:name":"Gokai",
    "wof:placetype":"locality"
},
  "geometry": {"coordinates":[141.13688999999999,40.58649000000001],"type":"Point"}
}