{
  "type": "Feature",
  "properties": {
    "gn:admin1_code":"22",
    "gn:admin2_code":"1857764.0",
    "gn:asciiname":"Mihama",
    "gn:country_code":"JP",
    "gn:dem":9,
    "gn:feature_class":"P",
    "gn:feature_code":"PPL",
    "gn:name":"Mihama",
    "gn:population":0,
    "gn:timezone":"Asia/Tokyo",
    "iso:country":"JP",
    "name:und_x_variant":[
        "Minama",
        "Mihama"
    ],
    "wof:name":"Mihama",
    "wof:placetype":"locality"
},
  "geometry": {"coordinates":[135.39167,35.55667000000001],"type":"Point"}
}