{
  "type": "Feature",
  "properties": {
    "gn:admin1_code":"21.0",
    "gn:admin2_code":"7412706.0",
    "gn:admin3_code":"43443.0",
    "gn:asciiname":"Kuroishizaki",
    "gn:country_code":"JP",
    "gn:dem":85,
    "gn:feature_class":"P",
    "gn:feature_code":"PPLL",
    "gn:name":"Kuroishizaki",
    "gn:population":0,
    "gn:timezone":"Asia/Tokyo",
    "iso:country":"JP",
    "name:jpn_x_preferred":[
        "\u9ed2\u77f3\u5d0e"
    ],
    "name:jpn_x_variant":[
        "\u304f\u308d\u3044\u3057\u3056\u304d",
        "\u30af\u30ed\u30a4\u30b7\u30b6\u30ad"
    ],
    "wof:name":"Kuroishizaki",
    "wof:placetype":"locality"
},
  "geometry": {"coordinates":[130.82910000000001,32.8106],"type":"Point"}
}