{
  "type": "Feature",
  "properties": {
    "gn:admin1_code":"7.0",
    "gn:admin2_code":"7407416.0",
    "gn:asciiname":"Kamiinamitsu",
    "gn:country_code":"JP",
    "gn:dem":73,
    "gn:feature_class":"P",
    "gn:feature_code":"PPLL",
    "gn:name":"Kamiinamitsu",
    "gn:population":0,
    "gn:timezone":"Asia/Tokyo",
    "iso:country":"JP",
    "name:jpn_x_preferred":[
        "\u4e0a\u7a32\u5149"
    ],
    "wof:name":"Kamiinamitsu",
    "wof:placetype":"locality"
},
  "geometry": {"coordinates":[130.59832,33.72209],"type":"Point"}
}