{
  "type": "Feature",
  "properties": {
    "gn:admin1_code":"29",
    "gn:admin2_code":"7468177.0",
    "gn:asciiname":"Hayakawa",
    "gn:country_code":"JP",
    "gn:dem":6,
    "gn:feature_class":"P",
    "gn:feature_code":"PPL",
    "gn:name":"Hayakawa",
    "gn:population":0,
    "gn:timezone":"Asia/Tokyo",
    "iso:country":"JP",
    "name:jpn_x_preferred":[
        "\u65e9\u5ddd"
    ],
    "wof:name":"Hayakawa",
    "wof:placetype":"locality"
},
  "geometry": {"coordinates":[139.45203999999998,38.32556],"type":"Point"}
}