{
  "type": "Feature",
  "properties": {
    "gn:admin1_code":"12.0",
    "gn:admin2_code":"2130184.0",
    "gn:asciiname":"Masukawacho",
    "gn:country_code":"JP",
    "gn:dem":98,
    "gn:feature_class":"P",
    "gn:feature_code":"PPL",
    "gn:name":"Masukawach\u014d",
    "gn:population":0,
    "gn:timezone":"Asia/Tokyo",
    "iso:country":"JP",
    "name:jpn_x_preferred":[
        "\u9c52\u5ddd\u753a"
    ],
    "name:jpn_x_variant":[
        "\u307e\u3059\u304b\u308f\u3061\u3087\u3046",
        "\u30de\u30b9\u30ab\u30ef\u30c1\u30e7\u30a6"
    ],
    "name:und_x_variant":[
        "Masukawa",
        "Shimo-masukawa",
        "Masukawach\u014d",
        "Kami-masukawa"
    ],
    "wof:name":"Masukawacho",
    "wof:placetype":"locality"
},
  "geometry": {"coordinates":[140.85328999999999,41.8309],"type":"Point"}
}