{
  "type": "Feature",
  "properties": {
    "gn:admin1_code":"47",
    "gn:admin2_code":"1858371.0",
    "gn:admin3_code":"47301.0",
    "gn:asciiname":"Kaganji",
    "gn:country_code":"JP",
    "gn:dem":7,
    "gn:feature_class":"P",
    "gn:feature_code":"PPL",
    "gn:name":"Kaganji",
    "gn:population":0,
    "gn:timezone":"Asia/Tokyo",
    "iso:country":"JP",
    "name:jpn_x_preferred":[
        "\u93e1\u5730"
    ],
    "name:jpn_x_variant":[
        "\u304b\u304c\u3093\u3062"
    ],
    "name:und_x_variant":[
        "Kagasoji",
        "Kaganzu",
        "Kaganji"
    ],
    "wof:name":"Kaganji",
    "wof:placetype":"locality"
},
  "geometry": {"coordinates":[128.16246999999998,26.73203],"type":"Point"}
}