{
  "type": "Feature",
  "properties": {
    "gn:admin1_code":"40.0",
    "gn:admin2_code":"1852675.0",
    "gn:asciiname":"Kamiuma",
    "gn:country_code":"JP",
    "gn:dem":38,
    "gn:feature_class":"P",
    "gn:feature_code":"PPL",
    "gn:name":"Kamiuma",
    "gn:population":0,
    "gn:timezone":"Asia/Tokyo",
    "iso:country":"JP",
    "name:jpn_x_preferred":[
        "\u4e0a\u99ac"
    ],
    "wof:name":"Kamiuma",
    "wof:placetype":"locality"
},
  "geometry": {"coordinates":[139.65958000000001,35.63918],"type":"Point"}
}