{
  "type": "Feature",
  "properties": {
    "gn:admin1_code":"7.0",
    "gn:admin2_code":"1854055.0",
    "gn:admin3_code":"40384.0",
    "gn:asciiname":"Fujigamoto",
    "gn:country_code":"JP",
    "gn:dem":1,
    "gn:feature_class":"P",
    "gn:feature_code":"PPLL",
    "gn:name":"Fujigamoto",
    "gn:population":0,
    "gn:timezone":"Asia/Tokyo",
    "iso:country":"JP",
    "name:jpn_x_preferred":[
        "\u85e4\u30f6\u672c"
    ],
    "wof:name":"Fujigamoto",
    "wof:placetype":"locality"
},
  "geometry": {"coordinates":[130.66806,33.83581],"type":"Point"}
}