{
  "type": "Feature",
  "properties": {
    "gn:admin1_code":"7.0",
    "gn:admin2_code":"1861834.0",
    "gn:asciiname":"Wariishi",
    "gn:country_code":"JP",
    "gn:dem":171,
    "gn:feature_class":"P",
    "gn:feature_code":"PPLL",
    "gn:name":"Wariishi",
    "gn:population":0,
    "gn:timezone":"Asia/Tokyo",
    "iso:country":"JP",
    "name:jpn_x_preferred":[
        "\u5272\u77f3"
    ],
    "wof:name":"Wariishi",
    "wof:placetype":"locality"
},
  "geometry": {"coordinates":[130.6738,33.5515],"type":"Point"}
}