{
  "type": "Feature",
  "properties": {
    "gn:admin1_code":"3.0",
    "gn:admin2_code":"7439934.0",
    "gn:asciiname":"Sumotai",
    "gn:country_code":"JP",
    "gn:dem":43,
    "gn:feature_class":"P",
    "gn:feature_code":"PPL",
    "gn:name":"Sumotai",
    "gn:population":0,
    "gn:timezone":"Asia/Tokyo",
    "iso:country":"JP",
    "name:jpn_x_preferred":[
        "\u674e\u5e73"
    ],
    "name:jpn_x_variant":[
        "\u3059\u3082\u305f\u3044",
        "\u30b9\u30e2\u30bf\u30a4"
    ],
    "wof:name":"Sumotai",
    "wof:placetype":"locality"
},
  "geometry": {"coordinates":[140.59353000000002,40.61748],"type":"Point"}
}