{
  "type": "Feature",
  "properties": {
    "gn:admin1_code":"19.0",
    "gn:admin2_code":"1856849.0",
    "gn:asciiname":"Takenoshita",
    "gn:country_code":"JP",
    "gn:dem":29,
    "gn:feature_class":"P",
    "gn:feature_code":"PPLL",
    "gn:name":"Takenoshita",
    "gn:population":0,
    "gn:timezone":"Asia/Tokyo",
    "iso:country":"JP",
    "name:jpn_x_preferred":[
        "\u7af9\u30ce\u4e0b"
    ],
    "name:jpn_x_variant":[
        "\u305f\u3051\u306e\u3057\u305f",
        "\u30bf\u30b1\u30ce\u30b7\u30bf"
    ],
    "wof:name":"Takenoshita",
    "wof:placetype":"locality"
},
  "geometry": {"coordinates":[139.63226,35.19631],"type":"Point"}
}