{
  "type": "Feature",
  "properties": {
    "iso:country":"JP",
    "qs:name":"\u6749\u6238\u753a",
    "qs:name_adm0":"\u65e5\u672c",
    "qs:name_adm1":"\u57fc\u7389\u770c",
    "qs:photos":78,
    "qs:photos_1k":16,
    "qs:photos_9k":1,
    "qs:photos_9r":3,
    "qs:photos_all":105,
    "qs:photos_sr":3,
    "qs:placetype":"Town",
    "qs:pop_sr":"0",
    "wof:name":"\u6749\u6238\u753a",
    "wof:placetype":"locality"
},
  "geometry": {"coordinates":[139.733734,36.028277],"type":"Point"}
}