{
  "type": "Feature",
  "properties": {
    "iso:country":"JP",
    "name:eng_x_preferred":[
        "Takaokacho Tei"
    ],
    "name:eng_x_variant":[
        "Takaokachou Takaokacho Tei",
        "Takaokacho Tei"
    ],
    "name:jpn_x_preferred":[
        "\u4e01"
    ],
    "name:jpn_x_variant":[
        "\u305f\u304b\u304a\u304b\u3061\u3087\u3046 \u3066\u3044",
        "\u3066\u3044",
        "\u9ad8\u5ca1\u753a \u4e01"
    ],
    "qs:gn_local":0,
    "qs:local_max":54,
    "qs:local_sum":67,
    "qs:localhoods":2,
    "qs:name":"\u4e01",
    "qs:name_adm0":"\u65e5\u672c",
    "qs:name_adm1":"\u9ad8\u77e5\u770c",
    "qs:name_en":"Takaokacho Tei",
    "qs:name_lau":"\u9ad8\u5ca1\u753a",
    "qs:name_local":"\u571f\u4f50\u5e02",
    "qs:photo_max":13,
    "qs:photo_sum":13,
    "qs:placetype":"Suburb",
    "qs:quad_count":1,
    "qs:woe_adm0":23424856,
    "qs:woe_adm1":2345869,
    "qs:woe_adm2":0,
    "qs:woe_lau":28481155,
    "qs:woe_local":1118390,
    "qs:woe_ver":"7.10.0",
    "wof:lang":[
        "jpn"
    ],
    "wof:name":"\u4e01",
    "wof:placetype":"neighbourhood"
},
  "geometry": {"coordinates":[133.409729,33.511631],"type":"Point"}
}