{
  "type": "Feature",
  "properties": {
    "iso:country":"JP",
    "qs:name":"\u4e03\u98ef\u753a",
    "qs:name_adm0":"\u65e5\u672c",
    "qs:name_adm1":"\u5317\u6d77\u9053",
    "qs:photos":1509,
    "qs:photos_1k":306,
    "qs:photos_9k":7,
    "qs:photos_9r":8,
    "qs:photos_all":1531,
    "qs:photos_sr":13,
    "qs:placetype":"Town",
    "qs:pop_sr":"0",
    "wof:name":"\u4e03\u98ef\u753a",
    "wof:placetype":"locality"
},
  "geometry": {"coordinates":[140.67227700000001,41.986291],"type":"Point"}
}