{
  "type": "Feature",
  "properties": {
    "gn:admin1_code":"13",
    "gn:admin2_code":"1852830.0",
    "gn:admin3_code":"28501.0",
    "gn:asciiname":"Noino",
    "gn:country_code":"JP",
    "gn:dem":208,
    "gn:feature_class":"P",
    "gn:feature_code":"PPL",
    "gn:name":"Noino",
    "gn:population":0,
    "gn:timezone":"Asia/Tokyo",
    "iso:country":"JP",
    "name:jpn_x_preferred":[
        "\u4e43\u4e95\u91ce"
    ],
    "wof:name":"Noino",
    "wof:placetype":"locality"
},
  "geometry": {"coordinates":[134.43423999999999,34.99296],"type":"Point"}
}