{
  "type": "Feature",
  "properties": {
    "gn:admin1_code":"1.0",
    "gn:admin2_code":"1853518.0",
    "gn:asciiname":"Owariasahi",
    "gn:country_code":"JP",
    "gn:dem":48,
    "gn:feature_class":"P",
    "gn:feature_code":"PPL",
    "gn:name":"Owariasahi",
    "gn:population":0,
    "gn:timezone":"Asia/Tokyo",
    "iso:country":"JP",
    "name:jpn_x_preferred":[
        "\u5c3e\u5f35\u65ed"
    ],
    "wof:name":"Owariasahi",
    "wof:placetype":"locality"
},
  "geometry": {"coordinates":[137.03,35.208],"type":"Point"}
}