{
  "type": "Feature",
  "properties": {
    "gn:admin1_code":"2.0",
    "gn:admin2_code":"7443156.0",
    "gn:asciiname":"Arayashiki",
    "gn:country_code":"JP",
    "gn:dem":72,
    "gn:feature_class":"P",
    "gn:feature_code":"PPLL",
    "gn:name":"Arayashiki",
    "gn:population":0,
    "gn:timezone":"Asia/Tokyo",
    "iso:country":"JP",
    "name:jpn_x_preferred":[
        "\u65b0\u5c4b\u5e03"
    ],
    "wof:name":"Arayashiki",
    "wof:placetype":"locality"
},
  "geometry": {"coordinates":[140.42193999999998,40.0539],"type":"Point"}
}