{
  "type": "Feature",
  "properties": {
    "gn:admin1_code":"12.0",
    "gn:admin2_code":"7428115.0",
    "gn:admin3_code":"1552.0",
    "gn:asciiname":"Tochigi",
    "gn:country_code":"JP",
    "gn:dem":139,
    "gn:feature_class":"P",
    "gn:feature_code":"PPL",
    "gn:name":"Tochigi",
    "gn:population":0,
    "gn:timezone":"Asia/Tokyo",
    "iso:country":"JP",
    "name:ceb_x_preferred":[
        "Tochigi"
    ],
    "name:jpn_x_preferred":[
        "\u6803\u6728"
    ],
    "name:jpn_x_variant":[
        "\u3068\u3061\u304e",
        "\u30c8\u30c1\u30ae"
    ],
    "name:kor_x_preferred":[
        "\ub3c4\uce58\uae30"
    ],
    "name:mlg_x_preferred":[
        "Tochigi"
    ],
    "name:por_x_preferred":[
        "Tochigi"
    ],
    "name:ron_x_preferred":[
        "Tochigi"
    ],
    "name:rus_x_preferred":[
        "\u0422\u043e\u0442\u0438\u0433\u0438"
    ],
    "name:swa_x_preferred":[
        "Tochigi"
    ],
    "name:und_x_variant":[
        "Toshigi-dantai",
        "Tochigi-dantai",
        "Tochigi"
    ],
    "wof:name":"Tochigi",
    "wof:placetype":"locality"
},
  "geometry": {"coordinates":[143.71556000000001,43.93227],"type":"Point"}
}