{
  "type": "Feature",
  "properties": {
    "gn:admin1_code":"12.0",
    "gn:admin2_code":"2129370.0",
    "gn:asciiname":"Higashikawacho",
    "gn:country_code":"JP",
    "gn:dem":4,
    "gn:feature_class":"P",
    "gn:feature_code":"PPL",
    "gn:name":"Higashikawach\u014d",
    "gn:population":0,
    "gn:timezone":"Asia/Tokyo",
    "iso:country":"JP",
    "name:jpn_x_preferred":[
        "\u6771\u5ddd\u753a"
    ],
    "name:jpn_x_variant":[
        "\u3072\u304c\u3057\u304b\u308f\u3061\u3087\u3046",
        "\u30d2\u30ac\u30b7\u30ab\u30ef\u30c1\u30e7\u30a6"
    ],
    "name:und_x_variant":[
        "Higashikawach\u014d"
    ],
    "wof:name":"Higashikawacho",
    "wof:placetype":"locality"
},
  "geometry": {"coordinates":[144.37459999999999,43.01207],"type":"Point"}
}