{
  "type": "Feature",
  "properties": {
    "gn:admin1_code":"19.0",
    "gn:admin2_code":"1848350.0",
    "gn:admin3_code":"14117.0",
    "gn:asciiname":"Shimoya-honmachi",
    "gn:country_code":"JP",
    "gn:dem":18,
    "gn:feature_class":"P",
    "gn:feature_code":"PPL",
    "gn:name":"Shimoya-honmachi",
    "gn:population":0,
    "gn:timezone":"Asia/Tokyo",
    "iso:country":"JP",
    "name:jpn_x_preferred":[
        "\u4e0b\u8c37\u672c\u753a"
    ],
    "wof:name":"Shimoya-honmachi",
    "wof:placetype":"locality"
},
  "geometry": {"coordinates":[139.53697,35.54393],"type":"Point"}
}