{
  "type": "Feature",
  "properties": {
    "gn:admin1_code":"29",
    "gn:admin2_code":"1853313.0",
    "gn:asciiname":"Yokkamachi",
    "gn:country_code":"JP",
    "gn:dem":1,
    "gn:feature_class":"P",
    "gn:feature_code":"PPL",
    "gn:name":"Yokkamachi",
    "gn:population":0,
    "gn:timezone":"Asia/Tokyo",
    "iso:country":"JP",
    "name:jpn_x_preferred":[
        "\u56db\u65e5\u753a"
    ],
    "name:und_x_variant":[
        "Yotsukamachi",
        "Yokkamachi"
    ],
    "wof:name":"Yokkamachi",
    "wof:placetype":"locality"
},
  "geometry": {"coordinates":[138.34669,37.97901],"type":"Point"}
}