{
  "type": "Feature",
  "properties": {
    "gn:admin1_code":"18",
    "gn:admin2_code":"1853737.0",
    "gn:admin3_code":"46525.0",
    "gn:asciiname":"Osai",
    "gn:country_code":"JP",
    "gn:dem":39,
    "gn:feature_class":"P",
    "gn:feature_code":"PPL",
    "gn:name":"Osai",
    "gn:population":0,
    "gn:timezone":"Asia/Tokyo",
    "iso:country":"JP",
    "name:jpn_x_preferred":[
        "\u65bc\u6589"
    ],
    "name:new_x_preferred":[
        "\u0913\u091a\u0948"
    ],
    "name:tam_x_preferred":[
        "\u0b93\u0b9a\u0bc8"
    ],
    "wof:name":"Osai",
    "wof:placetype":"locality"
},
  "geometry": {"coordinates":[129.25283999999999,28.11308],"type":"Point"}
}