{
  "type": "Feature",
  "properties": {
    "gn:admin1_code":"3.0",
    "gn:admin2_code":"8534376.0",
    "gn:admin3_code":"2321.0",
    "gn:asciiname":"Kanasawa",
    "gn:country_code":"JP",
    "gn:dem":31,
    "gn:feature_class":"P",
    "gn:feature_code":"PPL",
    "gn:name":"Kanasawa",
    "gn:population":0,
    "gn:timezone":"Asia/Tokyo",
    "iso:country":"JP",
    "name:jpn_x_preferred":[
        "\u91d1\u6ca2"
    ],
    "name:jpn_x_variant":[
        "\u304b\u306a\u3055\u308f",
        "\u30ab\u30ca\u30b5\u30ef"
    ],
    "wof:name":"Kanasawa",
    "wof:placetype":"locality"
},
  "geometry": {"coordinates":[140.17891,40.7245],"type":"Point"}
}