{
  "type": "Feature",
  "properties": {
    "gn:admin1_code":"19.0",
    "gn:admin2_code":"1848350.0",
    "gn:admin3_code":"14114.0",
    "gn:asciiname":"Takemuracho",
    "gn:country_code":"JP",
    "gn:dem":64,
    "gn:feature_class":"P",
    "gn:feature_code":"PPL",
    "gn:name":"Takemurach\u014d",
    "gn:population":0,
    "gn:timezone":"Asia/Tokyo",
    "iso:country":"JP",
    "name:jpn_x_preferred":[
        "\u7af9\u6751\u753a"
    ],
    "name:und_x_variant":[
        "Takemurach\u014d"
    ],
    "wof:name":"Takemuracho",
    "wof:placetype":"locality"
},
  "geometry": {"coordinates":[139.47427999999999,35.48865],"type":"Point"}
}