{
  "type": "Feature",
  "properties": {
    "gn:admin1_code":"26.0",
    "gn:admin2_code":"1861837.0",
    "gn:asciiname":"Mizuho-toyo",
    "gn:country_code":"JP",
    "gn:dem":374,
    "gn:feature_class":"P",
    "gn:feature_code":"PPL",
    "gn:name":"Mizuho-toyo",
    "gn:population":0,
    "gn:timezone":"Asia/Tokyo",
    "iso:country":"JP",
    "name:jpn_x_preferred":[
        "\u745e\u7a42\u8c4a"
    ],
    "wof:name":"Mizuho-toyo",
    "wof:placetype":"locality"
},
  "geometry": {"coordinates":[138.40719999999999,36.91598],"type":"Point"}
}