{
  "type": "Feature",
  "properties": {
    "gn:admin1_code":"18",
    "gn:admin2_code":"1857710.0",
    "gn:asciiname":"Nakahai",
    "gn:cc2":"JP",
    "gn:country_code":"JP",
    "gn:dem":109,
    "gn:feature_class":"P",
    "gn:feature_code":"PPL",
    "gn:name":"Nakahai",
    "gn:population":0,
    "gn:timezone":"Asia/Tokyo",
    "iso:country":"JP",
    "name:und_x_variant":[
        "Nakabai",
        "Nakahai"
    ],
    "wof:name":"Nakahai",
    "wof:placetype":"locality"
},
  "geometry": {"coordinates":[130.34999999999999,31.28333],"type":"Point"}
}