{
  "type": "Feature",
  "properties": {
    "gn:admin1_code":"4.0",
    "gn:admin2_code":"2112330.0",
    "gn:asciiname":"Yobatsuka",
    "gn:country_code":"JP",
    "gn:dem":14,
    "gn:feature_class":"P",
    "gn:feature_code":"PPL",
    "gn:name":"Yobatsuka",
    "gn:population":0,
    "gn:timezone":"Asia/Tokyo",
    "iso:country":"JP",
    "name:jpn_x_preferred":[
        "\u547c\u585a"
    ],
    "wof:name":"Yobatsuka",
    "wof:placetype":"locality"
},
  "geometry": {"coordinates":[139.98093,35.87337],"type":"Point"}
}