{
  "type": "Feature",
  "properties": {
    "iso:country":"JP",
    "name:eng_x_preferred":[
        "Tojo"
    ],
    "name:eng_x_variant":[
        "Tojo Town"
    ],
    "name:jpn_x_preferred":[
        "\u6771\u5e84\u753a"
    ],
    "qs:name":"\u6771\u5e84\u753a",
    "qs:name_adm0":"\u65e5\u672c",
    "qs:name_adm1":"\u5343\u8449\u770c",
    "qs:photos":33,
    "qs:photos_1k":7,
    "qs:photos_9k":1,
    "qs:photos_9r":2,
    "qs:photos_all":33,
    "qs:photos_sr":2,
    "qs:placetype":"Town",
    "qs:pop_sr":"0",
    "wof:name":"Tojo",
    "wof:placetype":"locality"
},
  "geometry": {"coordinates":[140.66167899999999,35.844952],"type":"Point"}
}