{
  "type": "Feature",
  "properties": {
    "iso:country":"JP",
    "name:eng_x_preferred":[
        "Morinomiyachuo 1 Chome"
    ],
    "name:eng_x_variant":[
        "Morinomiyachuuou 1 Choume",
        "Morinomiyachuo 1 Chome"
    ],
    "name:jpn_x_preferred":[
        "\uff11\u4e01\u76ee"
    ],
    "name:jpn_x_variant":[
        "\u3082\u308a\u306e\u307f\u3084\u3061\u3085\u3046\u304a\u3046 \uff11\u3061\u3087\u3046\u3081",
        "\u68ee\u30ce\u5bae\u4e2d\u592e \uff11\u4e01\u76ee",
        "\uff11\u3061\u3087\u3046\u3081"
    ],
    "qs:gn_local":0,
    "qs:local_max":5466,
    "qs:local_sum":82256,
    "qs:localhoods":141,
    "qs:name":"\uff11\u4e01\u76ee",
    "qs:name_adm0":"\u65e5\u672c",
    "qs:name_adm1":"\u5927\u962a\u5e9c",
    "qs:name_adm2":"\u4e2d\u592e\u533a",
    "qs:name_en":"Morinomiyachuo 1 Chome",
    "qs:name_lau":"\u68ee\u30ce\u5bae\u4e2d\u592e",
    "qs:name_local":"\u5927\u962a\u5e02",
    "qs:photo_max":9,
    "qs:photo_sum":22,
    "qs:photos":6,
    "qs:photos_1k":1,
    "qs:photos_9k":1,
    "qs:photos_9r":1,
    "qs:photos_all":6,
    "qs:photos_sr":1,
    "qs:placetype":"Suburb",
    "qs:pop_sr":"0",
    "qs:quad_count":5,
    "qs:woe_adm0":23424856,
    "qs:woe_adm1":2345881,
    "qs:woe_adm2":1118622,
    "qs:woe_lau":28457659,
    "qs:woe_local":15015370,
    "qs:woe_ver":"7.10.0",
    "wof:lang":[
        "jpn"
    ],
    "wof:name":"\uff11\u4e01\u76ee",
    "wof:placetype":"neighbourhood"
},
  "geometry": {"coordinates":[135.53104300000001,34.676627],"type":"Point"}
}