{
  "type": "Feature",
  "properties": {
    "gn:admin1_code":"22.0",
    "gn:admin2_code":"1857906.0",
    "gn:admin3_code":"26109.0",
    "gn:asciiname":"Fukakusa",
    "gn:country_code":"JP",
    "gn:dem":34,
    "gn:feature_class":"P",
    "gn:feature_code":"PPL",
    "gn:name":"Fukakusa",
    "gn:population":0,
    "gn:timezone":"Asia/Tokyo",
    "iso:country":"JP",
    "name:jpn_x_preferred":[
        "\u6df1\u8349"
    ],
    "wof:name":"Fukakusa",
    "wof:placetype":"locality"
},
  "geometry": {"coordinates":[135.77261999999999,34.95872],"type":"Point"}
}