{
  "type": "Feature",
  "properties": {
    "gn:admin1_code":"7.0",
    "gn:admin2_code":"1859874.0",
    "gn:admin3_code":"40342.0",
    "gn:asciiname":"Hirabaru",
    "gn:country_code":"JP",
    "gn:dem":135,
    "gn:feature_class":"P",
    "gn:feature_code":"PPLL",
    "gn:name":"Hirabaru",
    "gn:population":0,
    "gn:timezone":"Asia/Tokyo",
    "iso:country":"JP",
    "name:jpn_x_preferred":[
        "\u5e73\u539f"
    ],
    "wof:name":"Hirabaru",
    "wof:placetype":"locality"
},
  "geometry": {"coordinates":[130.54861,33.61483],"type":"Point"}
}