{
  "type": "Feature",
  "properties": {
    "gn:admin1_code":"2.0",
    "gn:admin2_code":"2128783.0",
    "gn:asciiname":"Yutakacho",
    "gn:country_code":"JP",
    "gn:dem":56,
    "gn:feature_class":"P",
    "gn:feature_code":"PPL",
    "gn:name":"Yutakach\u014d",
    "gn:population":0,
    "gn:timezone":"Asia/Tokyo",
    "iso:country":"JP",
    "name:jpn_x_preferred":[
        "\u8c4a\u753a"
    ],
    "name:jpn_x_variant":[
        "\u3086\u305f\u304b\u3061\u3087\u3046",
        "\u30e6\u30bf\u30ab\u30c1\u30e7\u30a6"
    ],
    "name:und_x_variant":[
        "Yutakach\u014d"
    ],
    "wof:name":"Yutakacho",
    "wof:placetype":"locality"
},
  "geometry": {"coordinates":[140.55248,40.27391],"type":"Point"}
}