{
  "type": "Feature",
  "properties": {
    "gn:admin1_code":"12.0",
    "gn:admin2_code":"7428100.0",
    "gn:admin3_code":"1691.0",
    "gn:asciiname":"Nishishunbetsu-miyazonocho",
    "gn:country_code":"JP",
    "gn:dem":91,
    "gn:feature_class":"P",
    "gn:feature_code":"PPL",
    "gn:name":"Nishishunbetsu-miyazonoch\u014d",
    "gn:population":0,
    "gn:timezone":"Asia/Tokyo",
    "iso:country":"JP",
    "name:jpn_x_preferred":[
        "\u897f\u6625\u5225\u5bae\u5712\u753a"
    ],
    "name:jpn_x_variant":[
        "\u306b\u3057\u3057\u3085\u3093\u3079\u3064\u307f\u3084\u305e\u306e\u3061\u3087\u3046",
        "\u30cb\u30b7\u30b7\u30e5\u30f3\u30d9\u30c4\u30df\u30e4\u30be\u30ce\u30c1\u30e7\u30a6"
    ],
    "name:und_x_variant":[
        "Nishishunbetsu-miyazonoch\u014d"
    ],
    "wof:name":"Nishishunbetsu-miyazonocho",
    "wof:placetype":"locality"
},
  "geometry": {"coordinates":[144.8082,43.39474000000001],"type":"Point"}
}