{
  "type": "Feature",
  "properties": {
    "gn:admin1_code":"21.0",
    "gn:admin2_code":"7412706.0",
    "gn:admin3_code":"43442.0",
    "gn:asciiname":"Nishimura",
    "gn:country_code":"JP",
    "gn:dem":10,
    "gn:feature_class":"P",
    "gn:feature_code":"PPLL",
    "gn:name":"Nishimura",
    "gn:population":0,
    "gn:timezone":"Asia/Tokyo",
    "iso:country":"JP",
    "name:ces_x_preferred":[
        "Ni\u0161imura"
    ],
    "name:jpn_x_preferred":[
        "\u897f\u6751"
    ],
    "name:jpn_x_variant":[
        "\u306b\u3057\u3080\u3089",
        "\u30cb\u30b7\u30e0\u30e9"
    ],
    "wof:name":"Nishimura",
    "wof:placetype":"locality"
},
  "geometry": {"coordinates":[130.76438000000002,32.73751],"type":"Point"}
}