{
  "type": "Feature",
  "properties": {
    "gn:admin1_code":"3.0",
    "gn:admin2_code":"2129224.0",
    "gn:admin3_code":"2367.0",
    "gn:asciiname":"Takahi",
    "gn:country_code":"JP",
    "gn:dem":33,
    "gn:feature_class":"P",
    "gn:feature_code":"PPL",
    "gn:name":"Takahi",
    "gn:population":0,
    "gn:timezone":"Asia/Tokyo",
    "iso:country":"JP",
    "name:jpn_x_preferred":[
        "\u9ad8\u6a0b"
    ],
    "name:jpn_x_variant":[
        "\u305f\u304b\u3072",
        "\u30bf\u30ab\u30d2"
    ],
    "wof:name":"Takahi",
    "wof:placetype":"locality"
},
  "geometry": {"coordinates":[140.57551999999998,40.63642],"type":"Point"}
}