{
  "type": "Feature",
  "properties": {
    "gn:admin1_code":"3.0",
    "gn:admin2_code":"2130088.0",
    "gn:admin3_code":"2301.0",
    "gn:asciiname":"Maiyachi",
    "gn:country_code":"JP",
    "gn:dem":4,
    "gn:feature_class":"P",
    "gn:feature_code":"PPL",
    "gn:name":"Maiyachi",
    "gn:population":0,
    "gn:timezone":"Asia/Tokyo",
    "iso:country":"JP",
    "name:jpn_x_preferred":[
        "\u524d\u8422"
    ],
    "name:jpn_x_variant":[
        "\u307e\u3044\u3084\u3061",
        "\u30de\u30a4\u30e4\u30c1"
    ],
    "wof:name":"Maiyachi",
    "wof:placetype":"locality"
},
  "geometry": {"coordinates":[140.96482,40.93478],"type":"Point"}
}