{
  "type": "Feature",
  "properties": {
    "gn:admin1_code":"25.0",
    "gn:admin2_code":"1864313.0",
    "gn:asciiname":"Hikoyama",
    "gn:country_code":"JP",
    "gn:dem":298,
    "gn:feature_class":"P",
    "gn:feature_code":"PPLL",
    "gn:name":"Hikoyama",
    "gn:population":0,
    "gn:timezone":"Asia/Tokyo",
    "iso:country":"JP",
    "name:jpn_x_preferred":[
        "\u5f66\u5c71"
    ],
    "name:jpn_x_variant":[
        "\u3072\u3053\u3084\u307e",
        "\u30d2\u30b3\u30e4\u30de"
    ],
    "wof:name":"Hikoyama",
    "wof:placetype":"locality"
},
  "geometry": {"coordinates":[130.80369999999999,32.06954],"type":"Point"}
}