{
  "type": "Feature",
  "properties": {
    "gn:admin1_code":"21.0",
    "gn:admin2_code":"7412708.0",
    "gn:admin3_code":"43513.0",
    "gn:asciiname":"Miyazono",
    "gn:country_code":"JP",
    "gn:dem":117,
    "gn:feature_class":"P",
    "gn:feature_code":"PPLL",
    "gn:name":"Miyazono",
    "gn:population":0,
    "gn:timezone":"Asia/Tokyo",
    "iso:country":"JP",
    "name:jpn_x_preferred":[
        "\u5bae\u5712"
    ],
    "name:jpn_x_variant":[
        "\u307f\u3084\u305e\u306e",
        "\u30df\u30e4\u30be\u30ce"
    ],
    "wof:name":"Miyazono",
    "wof:placetype":"locality"
},
  "geometry": {"coordinates":[130.64819,32.2487],"type":"Point"}
}