{
  "type": "Feature",
  "properties": {
    "gn:admin1_code":"32.0",
    "gn:admin2_code":"1850907.0",
    "gn:asciiname":"Yanagawacho",
    "gn:country_code":"JP",
    "gn:dem":9,
    "gn:feature_class":"P",
    "gn:feature_code":"PPL",
    "gn:name":"Yanagawach\u014d",
    "gn:population":0,
    "gn:timezone":"Asia/Tokyo",
    "iso:country":"JP",
    "name:jpn_x_preferred":[
        "\u67f3\u5ddd\u753a"
    ],
    "name:und_x_variant":[
        "Yanagawach\u014d"
    ],
    "wof:name":"Yanagawacho",
    "wof:placetype":"locality"
},
  "geometry": {"coordinates":[135.59138999999999,34.82514],"type":"Point"}
}