{
  "type": "Feature",
  "properties": {
    "gn:admin1_code":"29",
    "gn:admin2_code":"7468159.0",
    "gn:admin3_code":"15504.0",
    "gn:asciiname":"Arahama",
    "gn:country_code":"JP",
    "gn:dem":13,
    "gn:feature_class":"P",
    "gn:feature_code":"PPL",
    "gn:name":"Arahama",
    "gn:population":0,
    "gn:timezone":"Asia/Tokyo",
    "iso:country":"JP",
    "wof:name":"Arahama",
    "wof:placetype":"locality"
},
  "geometry": {"coordinates":[138.60033999999999,37.4048],"type":"Point"}
}