{
  "type": "Feature",
  "properties": {
    "gn:admin1_code":"47",
    "gn:admin2_code":"1861279.0",
    "gn:asciiname":"Taketomi",
    "gn:country_code":"JP",
    "gn:dem":47,
    "gn:feature_class":"P",
    "gn:feature_code":"PPL",
    "gn:name":"Taketomi",
    "gn:population":0,
    "gn:timezone":"Asia/Tokyo",
    "iso:country":"JP",
    "name:jpn_x_preferred":[
        "\u6b66\u5bcc"
    ],
    "name:und_x_variant":[
        "Dakiton",
        "Dakitun",
        "Taketomi"
    ],
    "wof:name":"Taketomi",
    "wof:placetype":"locality"
},
  "geometry": {"coordinates":[127.69162,26.1546],"type":"Point"}
}