{
  "type": "Feature",
  "properties": {
    "gn:admin1_code":"16.0",
    "gn:admin2_code":"2112822.0",
    "gn:asciiname":"Doden",
    "gn:country_code":"JP",
    "gn:dem":105,
    "gn:feature_class":"P",
    "gn:feature_code":"PPL",
    "gn:name":"D\u014dden",
    "gn:population":0,
    "gn:timezone":"Asia/Tokyo",
    "iso:country":"JP",
    "name:jpn_x_preferred":[
        "\u9053\u7530"
    ],
    "name:jpn_x_variant":[
        "\u3069\u3046\u3067\u3093",
        "\u30c9\u30a6\u30c7\u30f3"
    ],
    "name:und_x_variant":[
        "D\u014dden"
    ],
    "wof:name":"Doden",
    "wof:placetype":"locality"
},
  "geometry": {"coordinates":[141.06179,39.36554],"type":"Point"}
}