{
  "type": "Feature",
  "properties": {
    "gn:admin1_code":"4.0",
    "gn:admin2_code":"2112330.0",
    "gn:asciiname":"Shinden",
    "gn:country_code":"JP",
    "gn:dem":23,
    "gn:feature_class":"P",
    "gn:feature_code":"PPLL",
    "gn:name":"Shinden",
    "gn:population":0,
    "gn:timezone":"Asia/Tokyo",
    "iso:country":"JP",
    "name:deu_x_preferred":[
        "Shinden"
    ],
    "name:jpn_x_preferred":[
        "\u65b0\u7530"
    ],
    "wof:name":"Shinden",
    "wof:placetype":"locality"
},
  "geometry": {"coordinates":[139.99468000000002,35.88869000000001],"type":"Point"}
}