{
  "type": "Feature",
  "properties": {
    "iso:country":"JP",
    "name:eng_x_preferred":[
        "Ichibancho 2 Chome"
    ],
    "name:eng_x_variant":[
        "Ichibanchou 2 Choume",
        "Ichibancho 2 Chome"
    ],
    "name:jpn_x_preferred":[
        "\uff12\u4e01\u76ee"
    ],
    "name:jpn_x_variant":[
        "\u3044\u3061\u3070\u3093\u3061\u3087\u3046 \uff12\u3061\u3087\u3046\u3081",
        "\u4e00\u756a\u753a \uff12\u4e01\u76ee",
        "\uff12\u3061\u3087\u3046\u3081"
    ],
    "qs:gn_adm0_cc":"JP",
    "qs:gn_local":1926099,
    "qs:gn_nam_loc":"\u677e\u5c71\u5e02, \u611b\u5a9b\u770c, JP",
    "qs:gn_namadm1":"05",
    "qs:local_max":845,
    "qs:local_sum":2298,
    "qs:localhoods":15,
    "qs:name":"\uff12\u4e01\u76ee",
    "qs:name_adm0":"\u65e5\u672c",
    "qs:name_adm1":"\u611b\u5a9b\u770c",
    "qs:name_en":"Ichibancho 2 Chome",
    "qs:name_lau":"\u4e00\u756a\u753a",
    "qs:name_local":"\u677e\u5c71\u5e02",
    "qs:photo_max":123,
    "qs:photo_sum":322,
    "qs:photos":12,
    "qs:photos_1k":2,
    "qs:photos_9k":1,
    "qs:photos_9r":1,
    "qs:photos_all":12,
    "qs:photos_sr":1,
    "qs:placetype":"Suburb",
    "qs:pop_sr":"0",
    "qs:quad_count":8,
    "qs:woe_adm0":23424856,
    "qs:woe_adm1":2345855,
    "qs:woe_adm2":0,
    "qs:woe_lau":28479033,
    "qs:woe_local":1117690,
    "qs:woe_ver":"7.10.0",
    "qs_pg:name":"\uff12\u4e01\u76ee",
    "qs_pg:name_adm0":"\u65e5\u672c",
    "qs_pg:name_adm1":"\u611b\u5a9b\u770c",
    "qs_pg:photos":93,
    "qs_pg:photos_1k":19,
    "qs_pg:photos_9k":1,
    "qs_pg:photos_9r":3,
    "qs_pg:photos_all":93,
    "qs_pg:photos_sr":3,
    "qs_pg:pop_sr":0,
    "qs_pg:qs_pg_placetype":"neighbourhood",
    "qs_pg:qs_pg_placetype_gp":"Suburb",
    "qs_pg:woe_adm0":23424856,
    "woe:adm0_id":23424856,
    "woe:name_adm0":"\u65e5\u672c",
    "woe:name_adm1":"\u611b\u5a9b\u770c",
    "woe:placetype":"Suburb",
    "wof:lang":[
        "jpn"
    ],
    "wof:name":"\uff12\u4e01\u76ee",
    "wof:placetype":"neighbourhood"
},
  "geometry": {"coordinates":[132.77098799999999,33.840764],"type":"Point"}
}