{
  "type": "Feature",
  "properties": {
    "gn:admin1_code":"4.0",
    "gn:admin2_code":"1859468.0",
    "gn:asciiname":"Ikaridai",
    "gn:country_code":"JP",
    "gn:dem":88,
    "gn:feature_class":"P",
    "gn:feature_code":"PPLL",
    "gn:name":"Ikaridai",
    "gn:population":0,
    "gn:timezone":"Asia/Tokyo",
    "iso:country":"JP",
    "name:jpn_x_preferred":[
        "\u7887\u53f0"
    ],
    "name:jpn_x_variant":[
        "\u3044\u304b\u308a\u3060\u3044",
        "\u30a4\u30ab\u30ea\u30c0\u30a4"
    ],
    "wof:name":"Ikaridai",
    "wof:placetype":"locality"
},
  "geometry": {"coordinates":[140.04381999999998,35.31017],"type":"Point"}
}