{
  "type": "Feature",
  "properties": {
    "gn:admin1_code":"21.0",
    "gn:admin2_code":"7413152.0",
    "gn:asciiname":"Omura",
    "gn:country_code":"JP",
    "gn:dem":56,
    "gn:feature_class":"P",
    "gn:feature_code":"PPLL",
    "gn:name":"Omura",
    "gn:population":0,
    "gn:timezone":"Asia/Tokyo",
    "iso:country":"JP",
    "name:deu_x_preferred":[
        "Omura"
    ],
    "name:jpn_x_preferred":[
        "\u5c3e\u6751"
    ],
    "name:jpn_x_variant":[
        "\u304a\u3080\u3089",
        "\u30aa\u30e0\u30e9"
    ],
    "name:nld_x_preferred":[
        "Omura"
    ],
    "name:rus_x_preferred":[
        "\u041e\u043c\u0443\u0440\u0430"
    ],
    "name:swe_x_preferred":[
        "Omura"
    ],
    "wof:name":"Omura",
    "wof:placetype":"locality"
},
  "geometry": {"coordinates":[130.76498000000001,32.65470999999999],"type":"Point"}
}