{
  "type": "Feature",
  "properties": {
    "gn:admin1_code":"7.0",
    "gn:admin2_code":"1859306.0",
    "gn:admin3_code":"40103.0",
    "gn:asciiname":"Sakuramachi",
    "gn:country_code":"JP",
    "gn:dem":0,
    "gn:feature_class":"P",
    "gn:feature_code":"PPL",
    "gn:name":"Sakuramachi",
    "gn:population":0,
    "gn:timezone":"Asia/Tokyo",
    "iso:country":"JP",
    "name:jpn_x_preferred":[
        "\u685c\u753a"
    ],
    "wof:name":"Sakuramachi",
    "wof:placetype":"locality"
},
  "geometry": {"coordinates":[130.80704,33.90969],"type":"Point"}
}