{
  "type": "Feature",
  "properties": {
    "gn:admin1_code":"37.0",
    "gn:admin2_code":"1851714.0",
    "gn:admin3_code":"22103.0",
    "gn:asciiname":"Rinkodaira",
    "gn:country_code":"JP",
    "gn:dem":52,
    "gn:feature_class":"P",
    "gn:feature_code":"PPLL",
    "gn:name":"Rink\u014ddaira",
    "gn:population":0,
    "gn:timezone":"Asia/Tokyo",
    "iso:country":"JP",
    "name:jpn_x_preferred":[
        "\u6797\u9999\u5e73"
    ],
    "name:jpn_x_variant":[
        "\u308a\u3093\u3053\u3046\u3060\u3044\u3089"
    ],
    "name:und_x_variant":[
        "Rink\u014ddaira"
    ],
    "wof:name":"Rinkodaira",
    "wof:placetype":"locality"
},
  "geometry": {"coordinates":[138.56256999999999,35.11513],"type":"Point"}
}