{
  "type": "Feature",
  "properties": {
    "gn:admin1_code":"27",
    "gn:admin2_code":"7418810.0",
    "gn:asciiname":"Mitsushimacho-imazato",
    "gn:country_code":"JP",
    "gn:dem":77,
    "gn:feature_class":"P",
    "gn:feature_code":"PPL",
    "gn:name":"Mitsushimach\u014d-imazato",
    "gn:population":0,
    "gn:timezone":"Asia/Tokyo",
    "iso:country":"JP",
    "name:jpn_x_preferred":[
        "\u7f8e\u6d25\u5cf6\u753a\u4eca\u91cc"
    ],
    "name:und_x_variant":[
        "Imasato",
        "Imazato",
        "Mitsushimach\u014d-imazato"
    ],
    "wof:name":"Mitsushimacho-imazato",
    "wof:placetype":"locality"
},
  "geometry": {"coordinates":[129.21707000000001,34.2893],"type":"Point"}
}