{
  "type": "Feature",
  "properties": {
    "iso:country":"JP",
    "name:eng_x_preferred":[
        "Hinode 4 Chome"
    ],
    "name:eng_x_variant":[
        "Hinode 4 Choume",
        "Hinode 4 Chome"
    ],
    "name:jpn_x_preferred":[
        "\uff14\u4e01\u76ee"
    ],
    "name:jpn_x_variant":[
        "\u3072\u306e\u3067 \uff14\u3061\u3087\u3046\u3081",
        "\u65e5\u306e\u51fa \uff14\u4e01\u76ee",
        "\uff14\u3061\u3087\u3046\u3081"
    ],
    "name:unk_x_variant":[
        "\uff14\u4e01\u76ee"
    ],
    "qs:gn_local":0,
    "qs:local_max":28643,
    "qs:local_sum":29847,
    "qs:localhoods":14,
    "qs:name":"\uff14\u4e01\u76ee",
    "qs:name_adm0":"\u65e5\u672c",
    "qs:name_adm1":"\u5343\u8449\u770c",
    "qs:name_en":"Hinode 4 Chome",
    "qs:name_lau":"\u65e5\u306e\u51fa",
    "qs:name_local":"\u6d66\u5b89\u5e02",
    "qs:photo_max":106,
    "qs:photo_sum":170,
    "qs:placetype":"Suburb",
    "qs:quad_count":8,
    "qs:woe_adm0":23424856,
    "qs:woe_adm1":2345854,
    "qs:woe_adm2":0,
    "qs:woe_lau":28412752,
    "qs:woe_local":1116236,
    "qs:woe_ver":"7.10.0",
    "wof:lang":[
        "jpn"
    ],
    "wof:name":"\uff14\u4e01\u76ee",
    "wof:placetype":"neighbourhood"
},
  "geometry": {"coordinates":[139.92675,35.643825],"type":"Point"}
}