{
  "type": "Feature",
  "properties": {
    "iso:country":"JP",
    "name:eng_x_preferred":[
        "Sakashitacho 1 Chome"
    ],
    "name:eng_x_variant":[
        "Sakashitachou 1 Choume",
        "Sakashitacho 1 Chome"
    ],
    "name:jpn_x_preferred":[
        "\uff11\u4e01\u76ee"
    ],
    "name:jpn_x_variant":[
        "\u3055\u304b\u3057\u305f\u3061\u3087\u3046 \uff11\u3061\u3087\u3046\u3081",
        "\u5742\u4e0b\u753a \uff11\u4e01\u76ee",
        "\uff11\u3061\u3087\u3046\u3081"
    ],
    "qs:gn_local":0,
    "qs:local_max":96,
    "qs:local_sum":268,
    "qs:localhoods":5,
    "qs:name":"\uff11\u4e01\u76ee",
    "qs:name_adm0":"\u65e5\u672c",
    "qs:name_adm1":"\u57fc\u7389\u770c",
    "qs:name_en":"Sakashitacho 1 Chome",
    "qs:name_lau":"\u5742\u4e0b\u753a",
    "qs:name_local":"\u9ce9\u30f6\u8c37\u5e02",
    "qs:photo_max":27,
    "qs:photo_sum":27,
    "qs:placetype":"Suburb",
    "qs:quad_count":1,
    "qs:woe_adm0":23424856,
    "qs:woe_adm1":2345883,
    "qs:woe_adm2":0,
    "qs:woe_lau":28409351,
    "qs:woe_local":1108712,
    "qs:woe_ver":"7.10.0",
    "wof:lang":[
        "jpn"
    ],
    "wof:name":"\uff11\u4e01\u76ee",
    "wof:placetype":"neighbourhood"
},
  "geometry": {"coordinates":[139.733734,35.830063],"type":"Point"}
}