{
  "type": "Feature",
  "properties": {
    "gn:admin1_code":"4.0",
    "gn:admin2_code":"7465521.0",
    "gn:asciiname":"Shimotakida",
    "gn:country_code":"JP",
    "gn:dem":46,
    "gn:feature_class":"P",
    "gn:feature_code":"PPL",
    "gn:name":"Shimotakida",
    "gn:population":0,
    "gn:timezone":"Asia/Tokyo",
    "iso:country":"JP",
    "name:jpn_x_preferred":[
        "\u4e0b\u6edd\u7530"
    ],
    "name:jpn_x_variant":[
        "\u3057\u3082\u305f\u304d\u3060",
        "\u30b7\u30e2\u30bf\u30ad\u30c0"
    ],
    "wof:name":"Shimotakida",
    "wof:placetype":"locality"
},
  "geometry": {"coordinates":[139.89456000000001,35.05505],"type":"Point"}
}