{
  "type": "Feature",
  "properties": {
    "gn:admin1_code":"32.0",
    "gn:admin2_code":"1861089.0",
    "gn:asciiname":"Shimonomiyacho",
    "gn:country_code":"JP",
    "gn:dem":117,
    "gn:feature_class":"P",
    "gn:feature_code":"PPL",
    "gn:name":"Shimonomiyach\u014d",
    "gn:population":0,
    "gn:timezone":"Asia/Tokyo",
    "iso:country":"JP",
    "name:jpn_x_preferred":[
        "\u4e0b\u5bae\u753a"
    ],
    "name:und_x_variant":[
        "Shimonomiyach\u014d"
    ],
    "wof:name":"Shimonomiyacho",
    "wof:placetype":"locality"
},
  "geometry": {"coordinates":[135.49212,34.43072],"type":"Point"}
}