{
  "type": "Feature",
  "properties": {
    "gn:admin1_code":"43.0",
    "gn:admin2_code":"7411113.0",
    "gn:asciiname":"Nakakuro",
    "gn:country_code":"JP",
    "gn:dem":19,
    "gn:feature_class":"P",
    "gn:feature_code":"PPL",
    "gn:name":"Nakakuro",
    "gn:population":0,
    "gn:timezone":"Asia/Tokyo",
    "iso:country":"JP",
    "name:jpn_x_preferred":[
        "\u4e2d\u9ed2"
    ],
    "wof:name":"Nakakuro",
    "wof:placetype":"locality"
},
  "geometry": {"coordinates":[135.2884,34.26981],"type":"Point"}
}