{
  "type": "Feature",
  "properties": {
    "gn:admin1_code":"7.0",
    "gn:admin2_code":"9035649.0",
    "gn:asciiname":"Nijo-nagaishi",
    "gn:country_code":"JP",
    "gn:dem":36,
    "gn:feature_class":"P",
    "gn:feature_code":"PPL",
    "gn:name":"Nij\u014d-nagaishi",
    "gn:population":0,
    "gn:timezone":"Asia/Tokyo",
    "iso:country":"JP",
    "name:jpn_x_preferred":[
        "\u4e8c\u4e08\u9577\u77f3"
    ],
    "name:und_x_variant":[
        "Nij\u014d-nagaishi"
    ],
    "wof:name":"Nijo-nagaishi",
    "wof:placetype":"locality"
},
  "geometry": {"coordinates":[130.16726,33.50942],"type":"Point"}
}