{
  "type": "Feature",
  "properties": {
    "gn:admin1_code":"28.0",
    "gn:admin2_code":"1848164.0",
    "gn:admin3_code":"29447.0",
    "gn:asciiname":"Nakatsukawa",
    "gn:country_code":"JP",
    "gn:dem":682,
    "gn:feature_class":"P",
    "gn:feature_code":"PPL",
    "gn:name":"Nakatsukawa",
    "gn:population":0,
    "gn:timezone":"Asia/Tokyo",
    "iso:country":"JP",
    "name:jpn_x_preferred":[
        "\u4e2d\u6d25\u5ddd"
    ],
    "wof:name":"Nakatsukawa",
    "wof:placetype":"locality"
},
  "geometry": {"coordinates":[135.70151999999999,34.15054],"type":"Point"}
}