{
  "type": "Feature",
  "properties": {
    "gn:admin1_code":"4.0",
    "gn:admin2_code":"2111211.0",
    "gn:asciiname":"Sanchu",
    "gn:country_code":"JP",
    "gn:dem":4,
    "gn:feature_class":"P",
    "gn:feature_code":"PPLL",
    "gn:name":"Sanch\u016b",
    "gn:population":0,
    "gn:timezone":"Asia/Tokyo",
    "iso:country":"JP",
    "name:jpn_x_preferred":[
        "\u4e09\u4e2d"
    ],
    "name:jpn_x_variant":[
        "\u3055\u3093\u3061\u3085\u3046",
        "\u30b5\u30f3\u30c1\u30e5\u30a6"
    ],
    "name:und_x_variant":[
        "Sanch\u016b"
    ],
    "wof:name":"Sanchu",
    "wof:placetype":"locality"
},
  "geometry": {"coordinates":[140.42051000000001,35.48817000000001],"type":"Point"}
}