{
  "type": "Feature",
  "properties": {
    "gn:admin1_code":"05",
    "gn:admin2_code":"1849041.0",
    "gn:asciiname":"Miyanoshita",
    "gn:country_code":"JP",
    "gn:dem":152,
    "gn:feature_class":"P",
    "gn:feature_code":"PPL",
    "gn:name":"Miyanoshita",
    "gn:population":0,
    "gn:timezone":"Asia/Tokyo",
    "iso:country":"JP",
    "wof:name":"Miyanoshita",
    "wof:placetype":"locality"
},
  "geometry": {"coordinates":[132.60768000000002,33.29111],"type":"Point"}
}