{
  "type": "Feature",
  "properties": {
    "iso:country":"JP",
    "name:eng_x_preferred":[
        "Takamatsu 2 Chome"
    ],
    "name:eng_x_variant":[
        "Takamatsu 2 Choume",
        "Takamatsu 2 Chome"
    ],
    "name:jpn_x_preferred":[
        "\uff12\u4e01\u76ee"
    ],
    "name:jpn_x_variant":[
        "\u305f\u304b\u307e\u3064 \uff12\u3061\u3087\u3046\u3081",
        "\u9ad8\u677e \uff12\u4e01\u76ee",
        "\uff12\u3061\u3087\u3046\u3081"
    ],
    "qs:gn_local":0,
    "qs:local_max":1889,
    "qs:local_sum":3996,
    "qs:localhoods":29,
    "qs:name":"\uff12\u4e01\u76ee",
    "qs:name_adm0":"\u65e5\u672c",
    "qs:name_adm1":"\u9759\u5ca1\u770c",
    "qs:name_adm2":"\u99ff\u6cb3\u533a",
    "qs:name_en":"Takamatsu 2 Chome",
    "qs:name_lau":"\u9ad8\u677e",
    "qs:name_local":"\u9759\u5ca1\u5e02",
    "qs:photo_max":3,
    "qs:photo_sum":13,
    "qs:placetype":"Suburb",
    "qs:quad_count":8,
    "qs:woe_adm0":23424856,
    "qs:woe_adm1":2345886,
    "qs:woe_adm2":28379225,
    "qs:woe_lau":28436468,
    "qs:woe_local":1118217,
    "qs:woe_ver":"7.10.0",
    "wof:lang":[
        "jpn"
    ],
    "wof:name":"\uff12\u4e01\u76ee",
    "wof:placetype":"neighbourhood"
},
  "geometry": {"coordinates":[138.43558200000001,34.950276],"type":"Point"}
}