{
  "type": "Feature",
  "properties": {
    "gn:admin1_code":"28.0",
    "gn:admin2_code":"1848164.0",
    "gn:admin3_code":"29449.0",
    "gn:asciiname":"Kawatsu",
    "gn:country_code":"JP",
    "gn:dem":447,
    "gn:feature_class":"P",
    "gn:feature_code":"PPL",
    "gn:name":"Kawatsu",
    "gn:population":0,
    "gn:timezone":"Asia/Tokyo",
    "iso:country":"JP",
    "name:jpn_x_preferred":[
        "\u5ddd\u6d25"
    ],
    "wof:name":"Kawatsu",
    "wof:placetype":"locality"
},
  "geometry": {"coordinates":[135.74927,34.06228],"type":"Point"}
}