{
  "type": "Feature",
  "properties": {
    "gn:admin1_code":"23.0",
    "gn:admin2_code":"1849544.0",
    "gn:asciiname":"Misugicho-kawakami",
    "gn:country_code":"JP",
    "gn:dem":331,
    "gn:feature_class":"P",
    "gn:feature_code":"PPL",
    "gn:name":"Misugich\u014d-kawakami",
    "gn:population":0,
    "gn:timezone":"Asia/Tokyo",
    "iso:country":"JP",
    "name:jpn_x_preferred":[
        "\u7f8e\u6749\u753a\u5ddd\u4e0a"
    ],
    "name:und_x_variant":[
        "Misugich\u014d-kawakami"
    ],
    "wof:name":"Misugicho-kawakami",
    "wof:placetype":"locality"
},
  "geometry": {"coordinates":[136.27000000000001,34.48672],"type":"Point"}
}