{
  "type": "Feature",
  "properties": {
    "gn:admin1_code":"39",
    "gn:admin2_code":"1850156.0",
    "gn:asciiname":"Kamihachimancho",
    "gn:country_code":"JP",
    "gn:dem":27,
    "gn:feature_class":"P",
    "gn:feature_code":"PPL",
    "gn:name":"Kamihachimanch\u014d",
    "gn:population":0,
    "gn:timezone":"Asia/Tokyo",
    "iso:country":"JP",
    "name:jpn_x_preferred":[
        "\u4e0a\u516b\u4e07\u753a"
    ],
    "name:und_x_variant":[
        "Kamihachimanch\u014d",
        "Kami-hachiman"
    ],
    "wof:name":"Kamihachimancho",
    "wof:placetype":"locality"
},
  "geometry": {"coordinates":[134.50671,34.032],"type":"Point"}
}