{
  "type": "Feature",
  "properties": {
    "gn:admin1_code":"46.0",
    "gn:admin2_code":"1857168.0",
    "gn:admin3_code":"19366.0",
    "gn:asciiname":"Koshido",
    "gn:country_code":"JP",
    "gn:dem":130,
    "gn:feature_class":"P",
    "gn:feature_code":"PPLL",
    "gn:name":"Koshido",
    "gn:population":0,
    "gn:timezone":"Asia/Tokyo",
    "iso:country":"JP",
    "name:jpn_x_preferred":[
        "\u8d8a\u6e21"
    ],
    "wof:name":"Koshido",
    "wof:placetype":"locality"
},
  "geometry": {"coordinates":[138.50790000000001,35.22806],"type":"Point"}
}