{
  "type": "Feature",
  "properties": {
    "gn:admin1_code":"45.0",
    "gn:admin2_code":"1852222.0",
    "gn:asciiname":"Chofu-samuraimachi",
    "gn:country_code":"JP",
    "gn:dem":20,
    "gn:feature_class":"P",
    "gn:feature_code":"PPL",
    "gn:name":"Ch\u014dfu-samuraimachi",
    "gn:population":0,
    "gn:timezone":"Asia/Tokyo",
    "iso:country":"JP",
    "name:jpn_x_preferred":[
        "\u9577\u5e9c\u4f8d\u753a"
    ],
    "name:und_x_variant":[
        "Ch\u014dfu-samuraimachi"
    ],
    "wof:name":"Chofu-samuraimachi",
    "wof:placetype":"locality"
},
  "geometry": {"coordinates":[130.98622,33.99518],"type":"Point"}
}