{
  "type": "Feature",
  "properties": {
    "gn:admin1_code":"3.0",
    "gn:admin2_code":"2130200.0",
    "gn:asciiname":"Kitsunekubo",
    "gn:country_code":"JP",
    "gn:dem":24,
    "gn:feature_class":"P",
    "gn:feature_code":"PPL",
    "gn:name":"Kitsunekubo",
    "gn:population":0,
    "gn:timezone":"Asia/Tokyo",
    "iso:country":"JP",
    "name:jpn_x_preferred":[
        "\u72d0\u7aaa"
    ],
    "name:jpn_x_variant":[
        "\u304d\u3064\u306d\u304f\u307c",
        "\u30ad\u30c4\u30cd\u30af\u30dc"
    ],
    "wof:name":"Kitsunekubo",
    "wof:placetype":"locality"
},
  "geometry": {"coordinates":[141.47166999999999,40.51054],"type":"Point"}
}