{
  "type": "Feature",
  "properties": {
    "gn:admin1_code":"18",
    "gn:asciiname":"Sekirubu",
    "gn:cc2":"JP",
    "gn:country_code":"JP",
    "gn:dem":-9999,
    "gn:feature_class":"P",
    "gn:feature_code":"PPL",
    "gn:name":"Sekirubu",
    "gn:population":0,
    "gn:timezone":"Asia/Tokyo",
    "iso:country":"JP",
    "name:und_x_variant":[
        "Sekerubu",
        "Sekerube",
        "Sekirubu"
    ],
    "wof:name":"Sekirubu",
    "wof:placetype":"locality"
},
  "geometry": {"coordinates":[129.59999999999999,28.41667],"type":"Point"}
}