{
  "type": "Feature",
  "properties": {
    "iso:country":"JP",
    "name:eng_x_preferred":[
        "Choda 5 Chome"
    ],
    "name:eng_x_variant":[
        "Chouda 5 Choume",
        "Choda 5 Chome"
    ],
    "name:jpn_x_preferred":[
        "\uff15\u4e01\u76ee"
    ],
    "name:jpn_x_variant":[
        "\u3061\u3087\u3046\u3060 \uff15\u3061\u3087\u3046\u3081",
        "\u753a\u7530 \uff15\u4e01\u76ee",
        "\uff15\u3061\u3087\u3046\u3081"
    ],
    "name:unk_x_variant":[
        "\uff15\u4e01\u76ee"
    ],
    "qs:gn_local":0,
    "qs:local_max":814,
    "qs:local_sum":1092,
    "qs:localhoods":4,
    "qs:name":"\uff15\u4e01\u76ee",
    "qs:name_adm0":"\u65e5\u672c",
    "qs:name_adm1":"\u4f50\u8cc0\u770c",
    "qs:name_en":"Choda 5 Chome",
    "qs:name_lau":"\u753a\u7530",
    "qs:name_local":"\u5510\u6d25\u5e02",
    "qs:photo_max":200,
    "qs:photo_sum":814,
    "qs:placetype":"Suburb",
    "qs:quad_count":16,
    "qs:woe_adm0":23424856,
    "qs:woe_adm1":2345882,
    "qs:woe_adm2":0,
    "qs:woe_lau":28485736,
    "qs:woe_local":1117451,
    "qs:woe_ver":"7.10.0",
    "wof:lang":[
        "jpn"
    ],
    "wof:name":"\uff15\u4e01\u76ee",
    "wof:placetype":"neighbourhood"
},
  "geometry": {"coordinates":[129.969154,33.450071],"type":"Point"}
}