{
  "type": "Feature",
  "properties": {
    "gn:admin1_code":"24.0",
    "gn:admin2_code":"2112574.0",
    "gn:asciiname":"Shimizudahama",
    "gn:country_code":"JP",
    "gn:dem":59,
    "gn:feature_class":"P",
    "gn:feature_code":"PPL",
    "gn:name":"Shimizudahama",
    "gn:population":0,
    "gn:timezone":"Asia/Tokyo",
    "iso:country":"JP",
    "name:jpn_x_preferred":[
        "\u6e05\u6c34\u7530\u6d5c"
    ],
    "name:jpn_x_variant":[
        "\u3057\u307f\u305a\u3060\u306f\u307e",
        "\u30b7\u30df\u30ba\u30c0\u30cf\u30de"
    ],
    "wof:name":"Shimizudahama",
    "wof:placetype":"locality"
},
  "geometry": {"coordinates":[141.4658,38.34626],"type":"Point"}
}