{
  "type": "Feature",
  "properties": {
    "gn:admin1_code":"21.0",
    "gn:admin2_code":"1864975.0",
    "gn:admin3_code":"43424.0",
    "gn:asciiname":"Yumita",
    "gn:country_code":"JP",
    "gn:dem":442,
    "gn:feature_class":"P",
    "gn:feature_code":"PPLL",
    "gn:name":"Yumita",
    "gn:population":0,
    "gn:timezone":"Asia/Tokyo",
    "iso:country":"JP",
    "name:jpn_x_preferred":[
        "\u5f13\u7530"
    ],
    "name:jpn_x_variant":[
        "\u3086\u307f\u305f",
        "\u30e6\u30df\u30bf"
    ],
    "wof:name":"Yumita",
    "wof:placetype":"locality"
},
  "geometry": {"coordinates":[131.05921999999998,33.15475],"type":"Point"}
}