{
  "type": "Feature",
  "properties": {
    "gn:admin1_code":"33.0",
    "gn:admin2_code":"1856784.0",
    "gn:admin3_code":"41346.0",
    "gn:asciiname":"Ichitake",
    "gn:country_code":"JP",
    "gn:dem":0,
    "gn:feature_class":"P",
    "gn:feature_code":"PPL",
    "gn:name":"Ichitake",
    "gn:population":0,
    "gn:timezone":"Asia/Tokyo",
    "iso:country":"JP",
    "name:jpn_x_preferred":[
        "\u5e02\u6b66"
    ],
    "wof:name":"Ichitake",
    "wof:placetype":"locality"
},
  "geometry": {"coordinates":[130.42616999999998,33.2941],"type":"Point"}
}