{
  "type": "Feature",
  "properties": {
    "gn:admin1_code":"21.0",
    "gn:admin2_code":"7413150.0",
    "gn:asciiname":"Kamotomachi-shimobunda",
    "gn:country_code":"JP",
    "gn:dem":23,
    "gn:feature_class":"P",
    "gn:feature_code":"PPL",
    "gn:name":"Kamotomachi-shimobunda",
    "gn:population":0,
    "gn:timezone":"Asia/Tokyo",
    "iso:country":"JP",
    "name:jpn_x_preferred":[
        "\u9e7f\u672c\u753a\u4e0b\u5206\u7530"
    ],
    "name:jpn_x_variant":[
        "\u304b\u3082\u3068\u307e\u3061\u3057\u3082\u3076\u3093\u3060",
        "\u30ab\u30e2\u30c8\u30de\u30c1\u30b7\u30e2\u30d6\u30f3\u30c0"
    ],
    "wof:name":"Kamotomachi-shimobunda",
    "wof:placetype":"locality"
},
  "geometry": {"coordinates":[130.71943000000002,32.98993],"type":"Point"}
}