{
  "type": "Feature",
  "properties": {
    "gn:admin1_code":"37.0",
    "gn:admin2_code":"1854900.0",
    "gn:asciiname":"Tsushimacho",
    "gn:country_code":"JP",
    "gn:dem":7,
    "gn:feature_class":"P",
    "gn:feature_code":"PPLL",
    "gn:name":"Tsushimach\u014d",
    "gn:population":0,
    "gn:timezone":"Asia/Tokyo",
    "iso:country":"JP",
    "name:jpn_x_preferred":[
        "\u6d25\u5cf6\u753a"
    ],
    "name:und_x_variant":[
        "Tsushimach\u014d"
    ],
    "wof:name":"Tsushimacho",
    "wof:placetype":"locality"
},
  "geometry": {"coordinates":[138.86049,35.07914],"type":"Point"}
}