{
  "type": "Feature",
  "properties": {
    "gn:admin1_code":"19.0",
    "gn:admin2_code":"1861448.0",
    "gn:asciiname":"Kasakubo",
    "gn:country_code":"JP",
    "gn:dem":33,
    "gn:feature_class":"P",
    "gn:feature_code":"PPL",
    "gn:name":"Kasakubo",
    "gn:population":0,
    "gn:timezone":"Asia/Tokyo",
    "iso:country":"JP",
    "name:jpn_x_preferred":[
        "\u7b20\u7aaa"
    ],
    "wof:name":"Kasakubo",
    "wof:placetype":"locality"
},
  "geometry": {"coordinates":[139.28128999999998,35.38805],"type":"Point"}
}