{
  "type": "Feature",
  "properties": {
    "gn:admin1_code":"21.0",
    "gn:admin2_code":"7413152.0",
    "gn:asciiname":"Shiranuhimachi-einoo",
    "gn:country_code":"JP",
    "gn:dem":117,
    "gn:feature_class":"P",
    "gn:feature_code":"PPL",
    "gn:name":"Shiranuhimachi-einoo",
    "gn:population":0,
    "gn:timezone":"Asia/Tokyo",
    "iso:country":"JP",
    "name:jpn_x_preferred":[
        "\u4e0d\u77e5\u706b\u753a\u6c38\u5c3e"
    ],
    "name:jpn_x_variant":[
        "\u3057\u3089\u306c\u3072\u307e\u3061\u3048\u3044\u306e\u304a",
        "\u30b7\u30e9\u30cc\u30d2\u30de\u30c1\u30a8\u30a4\u30ce\u30aa"
    ],
    "wof:name":"Shiranuhimachi-einoo",
    "wof:placetype":"locality"
},
  "geometry": {"coordinates":[130.62135000000001,32.6403],"type":"Point"}
}