{
  "type": "Feature",
  "properties": {
    "gn:admin1_code":"12.0",
    "gn:admin2_code":"7428078.0",
    "gn:admin3_code":"1663.0",
    "gn:asciiname":"Anebetsu-kisen",
    "gn:country_code":"JP",
    "gn:dem":15,
    "gn:feature_class":"P",
    "gn:feature_code":"PPL",
    "gn:name":"Anebetsu-kisen",
    "gn:population":0,
    "gn:timezone":"Asia/Tokyo",
    "iso:country":"JP",
    "name:jpn_x_preferred":[
        "\u59c9\u5225\u57fa\u7dda"
    ],
    "name:jpn_x_variant":[
        "\u3042\u306d\u3079\u3064\u304d\u305b\u3093",
        "\u30a2\u30cd\u30d9\u30c4\u30ad\u30bb\u30f3"
    ],
    "wof:name":"Anebetsu-kisen",
    "wof:placetype":"locality"
},
  "geometry": {"coordinates":[145.13419999999999,43.20954],"type":"Point"}
}