{
  "type": "Feature",
  "properties": {
    "gn:admin1_code":"21.0",
    "gn:admin2_code":"1864973.0",
    "gn:asciiname":"Shimotashiro",
    "gn:country_code":"JP",
    "gn:dem":473,
    "gn:feature_class":"P",
    "gn:feature_code":"PPLL",
    "gn:name":"Shimotashiro",
    "gn:population":0,
    "gn:timezone":"Asia/Tokyo",
    "iso:country":"JP",
    "name:jpn_x_preferred":[
        "\u4e0b\u7530\u4ee3"
    ],
    "name:jpn_x_variant":[
        "\u3057\u3082\u305f\u3057\u308d",
        "\u30b7\u30e2\u30bf\u30b7\u30ed"
    ],
    "wof:name":"Shimotashiro",
    "wof:placetype":"locality"
},
  "geometry": {"coordinates":[131.0172,32.94748],"type":"Point"}
}