{
  "type": "Feature",
  "properties": {
    "gn:country":"JP",
    "gn:fcode":"ADM3",
    "gn:population":0,
    "iso:country":"JP",
    "name:jpn_x_preferred":[
        "\u4e94\u971e\u753a"
    ],
    "name:jpn_x_variant":[
        "\u3054\u304b\u307e\u3061"
    ],
    "qs:name":"Goka-machi",
    "qs:photos_9r":0,
    "qs:photos_sr":0,
    "qs:pop_sr":"0",
    "wof:name":"Goka-machi",
    "wof:placetype":"localadmin",
    "wof:population":0
},
  "geometry": {"coordinates":[139.74859000000001,36.10802],"type":"Point"}
}