{
  "type": "Feature",
  "properties": {
    "gn:admin1_code":"8.0",
    "gn:admin2_code":"7451504.0",
    "gn:admin3_code":"7444.0",
    "gn:asciiname":"Kuwanohara",
    "gn:country_code":"JP",
    "gn:dem":261,
    "gn:feature_class":"P",
    "gn:feature_code":"PPL",
    "gn:name":"Kuwanohara",
    "gn:population":0,
    "gn:timezone":"Asia/Tokyo",
    "iso:country":"JP",
    "name:jpn_x_preferred":[
        "\u6851\u539f"
    ],
    "wof:name":"Kuwanohara",
    "wof:placetype":"locality"
},
  "geometry": {"coordinates":[139.63781,37.46733],"type":"Point"}
}