{
  "type": "Feature",
  "properties": {
    "gn:admin1_code":"21.0",
    "gn:admin2_code":"7413150.0",
    "gn:asciiname":"Yokoo",
    "gn:country_code":"JP",
    "gn:dem":285,
    "gn:feature_class":"P",
    "gn:feature_code":"PPLL",
    "gn:name":"Yokoo",
    "gn:population":0,
    "gn:timezone":"Asia/Tokyo",
    "iso:country":"JP",
    "name:jpn_x_preferred":[
        "\u6a2a\u5c3e"
    ],
    "name:jpn_x_variant":[
        "\u3088\u3053\u304a",
        "\u30e8\u30b3\u30aa"
    ],
    "wof:name":"Yokoo",
    "wof:placetype":"locality"
},
  "geometry": {"coordinates":[130.79911999999999,33.05139],"type":"Point"}
}