{
  "type": "Feature",
  "properties": {
    "gn:admin1_code":"46.0",
    "gn:admin2_code":"1864076.0",
    "gn:asciiname":"Midorigaoka",
    "gn:country_code":"JP",
    "gn:dem":785,
    "gn:feature_class":"P",
    "gn:feature_code":"PPL",
    "gn:name":"Midorigaoka",
    "gn:population":0,
    "gn:timezone":"Asia/Tokyo",
    "iso:country":"JP",
    "name:jpn_x_preferred":[
        "\u7dd1\u30f6\u4e18"
    ],
    "wof:name":"Midorigaoka",
    "wof:placetype":"locality"
},
  "geometry": {"coordinates":[138.79515000000001,35.49290999999999],"type":"Point"}
}