{
  "type": "Feature",
  "properties": {
    "gn:admin1_code":"3.0",
    "gn:admin2_code":"2130654.0",
    "gn:asciiname":"Magonai",
    "gn:country_code":"JP",
    "gn:dem":84,
    "gn:feature_class":"P",
    "gn:feature_code":"PPL",
    "gn:name":"Magonai",
    "gn:population":0,
    "gn:timezone":"Asia/Tokyo",
    "iso:country":"JP",
    "name:jpn_x_preferred":[
        "\u5b6b\u5185"
    ],
    "name:jpn_x_variant":[
        "\u307e\u3054\u306a\u3044",
        "\u30de\u30b4\u30ca\u30a4"
    ],
    "wof:name":"Magonai",
    "wof:placetype":"locality"
},
  "geometry": {"coordinates":[140.63485,40.75979],"type":"Point"}
}