{
  "type": "Feature",
  "properties": {
    "gn:admin1_code":"21.0",
    "gn:admin2_code":"1864975.0",
    "gn:admin3_code":"43423.0",
    "gn:asciiname":"Uriage",
    "gn:country_code":"JP",
    "gn:dem":488,
    "gn:feature_class":"P",
    "gn:feature_code":"PPLL",
    "gn:name":"Uriage",
    "gn:population":0,
    "gn:timezone":"Asia/Tokyo",
    "iso:country":"JP",
    "name:jpn_x_preferred":[
        "\u74dc\u4e0a"
    ],
    "name:jpn_x_variant":[
        "\u3046\u308a\u3042\u3052",
        "\u30a6\u30ea\u30a2\u30b2"
    ],
    "wof:name":"Uriage",
    "wof:placetype":"locality"
},
  "geometry": {"coordinates":[131.0496,33.08196],"type":"Point"}
}