{
  "type": "Feature",
  "properties": {
    "gn:admin1_code":"21.0",
    "gn:admin2_code":"7413152.0",
    "gn:asciiname":"Sunaizako",
    "gn:country_code":"JP",
    "gn:dem":103,
    "gn:feature_class":"P",
    "gn:feature_code":"PPLL",
    "gn:name":"Sunaizako",
    "gn:population":0,
    "gn:timezone":"Asia/Tokyo",
    "iso:country":"JP",
    "name:jpn_x_preferred":[
        "\u7802\u5c45\u8feb"
    ],
    "name:jpn_x_variant":[
        "\u3059\u306a\u3044\u3056\u3053",
        "\u30b9\u30ca\u30a4\u30b6\u30b3"
    ],
    "wof:name":"Sunaizako",
    "wof:placetype":"locality"
},
  "geometry": {"coordinates":[130.76325,32.58644],"type":"Point"}
}