{
  "type": "Feature",
  "properties": {
    "gn:admin1_code":"4.0",
    "gn:admin2_code":"7465524.0",
    "gn:asciiname":"Saikojimae",
    "gn:country_code":"JP",
    "gn:dem":10,
    "gn:feature_class":"P",
    "gn:feature_code":"PPLL",
    "gn:name":"Saik\u014djimae",
    "gn:population":0,
    "gn:timezone":"Asia/Tokyo",
    "iso:country":"JP",
    "name:jpn_x_preferred":[
        "\u897f\u5149\u5bfa\u524d"
    ],
    "name:jpn_x_variant":[
        "\u3055\u3044\u3053\u3046\u3058\u307e\u3048",
        "\u30b5\u30a4\u30b3\u30a6\u30b8\u30de\u30a8"
    ],
    "name:und_x_variant":[
        "Saik\u014djimae"
    ],
    "wof:name":"Saikojimae",
    "wof:placetype":"locality"
},
  "geometry": {"coordinates":[140.34819999999999,35.29528],"type":"Point"}
}