{
  "type": "Feature",
  "properties": {
    "gn:admin1_code":"4.0",
    "gn:admin2_code":"1863711.0",
    "gn:asciiname":"Iimorizuka",
    "gn:country_code":"JP",
    "gn:dem":36,
    "gn:feature_class":"P",
    "gn:feature_code":"PPLL",
    "gn:name":"Iimorizuka",
    "gn:population":0,
    "gn:timezone":"Asia/Tokyo",
    "iso:country":"JP",
    "name:jpn_x_preferred":[
        "\u98ef\u76db\u585a"
    ],
    "name:jpn_x_variant":[
        "\u3044\u3044\u3082\u308a\u3065\u304b",
        "\u30a4\u30a4\u30e2\u30ea\u30c5\u30ab"
    ],
    "wof:name":"Iimorizuka",
    "wof:placetype":"locality"
},
  "geometry": {"coordinates":[139.86913000000001,35.27071],"type":"Point"}
}