{
  "type": "Feature",
  "properties": {
    "gn:admin1_code":"2.0",
    "gn:admin2_code":"2128864.0",
    "gn:asciiname":"Futatsuimachi-kiriishi",
    "gn:country_code":"JP",
    "gn:dem":21,
    "gn:feature_class":"P",
    "gn:feature_code":"PPL",
    "gn:name":"Futatsuimachi-kiriishi",
    "gn:population":0,
    "gn:timezone":"Asia/Tokyo",
    "iso:country":"JP",
    "name:jpn_x_preferred":[
        "\u4e8c\u30c4\u4e95\u753a\u5207\u77f3"
    ],
    "name:und_x_variant":[
        "Kiriishi"
    ],
    "wof:name":"Futatsuimachi-kiriishi",
    "wof:placetype":"locality"
},
  "geometry": {"coordinates":[140.21238,40.2012],"type":"Point"}
}