{
  "type": "Feature",
  "properties": {
    "gn:admin1_code":"2.0",
    "gn:admin2_code":"2113122.0",
    "gn:asciiname":"Nigorikawa",
    "gn:country_code":"JP",
    "gn:dem":15,
    "gn:feature_class":"P",
    "gn:feature_code":"PPL",
    "gn:name":"Nigorikawa",
    "gn:population":0,
    "gn:timezone":"Asia/Tokyo",
    "iso:country":"JP",
    "name:jpn_x_preferred":[
        "\u6fc1\u5ddd"
    ],
    "name:jpn_x_variant":[
        "\u306b\u3054\u308a\u304b\u308f",
        "\u30cb\u30b4\u30ea\u30ab\u30ef"
    ],
    "wof:name":"Nigorikawa",
    "wof:placetype":"locality"
},
  "geometry": {"coordinates":[140.12751,39.74938],"type":"Point"}
}