{
  "type": "Feature",
  "properties": {
    "gn:admin1_code":"45",
    "gn:asciiname":"Tanoura",
    "gn:country_code":"JP",
    "gn:dem":24,
    "gn:feature_class":"P",
    "gn:feature_code":"PPL",
    "gn:name":"Tanoura",
    "gn:population":0,
    "gn:timezone":"Asia/Tokyo",
    "iso:country":"JP",
    "name:jpn_x_preferred":[
        "\u7530\u91ce\u6d66"
    ],
    "wof:name":"Tanoura",
    "wof:placetype":"locality"
},
  "geometry": {"coordinates":[130.99497,33.9563],"type":"Point"}
}