{
  "type": "Feature",
  "properties": {
    "gn:admin1_code":"33.0",
    "gn:admin2_code":"1850771.0",
    "gn:asciiname":"Mutabe",
    "gn:country_code":"JP",
    "gn:dem":17,
    "gn:feature_class":"P",
    "gn:feature_code":"PPLL",
    "gn:name":"Mutabe",
    "gn:population":0,
    "gn:timezone":"Asia/Tokyo",
    "iso:country":"JP",
    "name:jpn_x_preferred":[
        "\u725f\u7530\u8fba"
    ],
    "wof:name":"Mutabe",
    "wof:placetype":"locality"
},
  "geometry": {"coordinates":[130.13338000000002,33.26734],"type":"Point"}
}