{
  "type": "Feature",
  "properties": {
    "gn:admin1_code":"21.0",
    "gn:admin2_code":"7413151.0",
    "gn:asciiname":"Ryugatakemachi-takado",
    "gn:country_code":"JP",
    "gn:dem":121,
    "gn:feature_class":"P",
    "gn:feature_code":"PPL",
    "gn:name":"Ry\u016bgatakemachi-takado",
    "gn:population":0,
    "gn:timezone":"Asia/Tokyo",
    "iso:country":"JP",
    "name:jpn_x_preferred":[
        "\u9f8d\u30f6\u5cb3\u753a\u9ad8\u6238"
    ],
    "name:jpn_x_variant":[
        "\u308a\u3085\u3046\u304c\u305f\u3051\u307e\u3061\u305f\u304b\u3069",
        "\u30ea\u30e5\u30a6\u30ac\u30bf\u30b1\u30de\u30c1\u30bf\u30ab\u30c9"
    ],
    "name:und_x_variant":[
        "Ry\u016bgatakemachi-takado"
    ],
    "wof:name":"Ryugatakemachi-takado",
    "wof:placetype":"locality"
},
  "geometry": {"coordinates":[130.39388,32.39834],"type":"Point"}
}