{
  "type": "Feature",
  "properties": {
    "gn:admin1_code":"3.0",
    "gn:admin2_code":"2130056.0",
    "gn:asciiname":"Jonan",
    "gn:country_code":"JP",
    "gn:dem":63,
    "gn:feature_class":"P",
    "gn:feature_code":"PPL",
    "gn:name":"J\u014dnan",
    "gn:population":0,
    "gn:timezone":"Asia/Tokyo",
    "iso:country":"JP",
    "name:jpn_x_preferred":[
        "\u57ce\u5357"
    ],
    "name:jpn_x_variant":[
        "\u3058\u3087\u3046\u306a\u3093",
        "\u30b8\u30e7\u30a6\u30ca\u30f3"
    ],
    "name:und_x_variant":[
        "J\u014dnan"
    ],
    "wof:name":"Jonan",
    "wof:placetype":"locality"
},
  "geometry": {"coordinates":[140.46588,40.57898],"type":"Point"}
}