{
  "type": "Feature",
  "properties": {
    "gn:admin1_code":"8.0",
    "gn:admin2_code":"2112921.0",
    "gn:asciiname":"Machiniwasaka",
    "gn:country_code":"JP",
    "gn:dem":304,
    "gn:feature_class":"P",
    "gn:feature_code":"PPL",
    "gn:name":"Machiniwasaka",
    "gn:population":0,
    "gn:timezone":"Asia/Tokyo",
    "iso:country":"JP",
    "name:jpn_x_preferred":[
        "\u753a\u5ead\u5742"
    ],
    "name:und_x_variant":[
        "Machi-niwasaka"
    ],
    "wof:name":"Machiniwasaka",
    "wof:placetype":"locality"
},
  "geometry": {"coordinates":[140.36028000000002,37.77828],"type":"Point"}
}