{
  "type": "Feature",
  "properties": {
    "gn:admin1_code":"4.0",
    "gn:admin2_code":"2112557.0",
    "gn:admin3_code":"12441.0",
    "gn:asciiname":"Iwaihara",
    "gn:country_code":"JP",
    "gn:dem":132,
    "gn:feature_class":"P",
    "gn:feature_code":"PPLL",
    "gn:name":"Iwaihara",
    "gn:population":0,
    "gn:timezone":"Asia/Tokyo",
    "iso:country":"JP",
    "name:jpn_x_preferred":[
        "\u5ca9\u4e95\u539f"
    ],
    "name:jpn_x_variant":[
        "\u3044\u308f\u3044\u306f\u3089",
        "\u30a4\u30ef\u30a4\u30cf\u30e9"
    ],
    "wof:name":"Iwaihara",
    "wof:placetype":"locality"
},
  "geometry": {"coordinates":[140.17108000000002,35.23172],"type":"Point"}
}