{
  "type": "Feature",
  "properties": {
    "gn:admin1_code":"21.0",
    "gn:admin2_code":"1862350.0",
    "gn:asciiname":"Nishiotsukamachi",
    "gn:country_code":"JP",
    "gn:dem":526,
    "gn:feature_class":"P",
    "gn:feature_code":"PPL",
    "gn:name":"Nishi\u014dtsukamachi",
    "gn:population":0,
    "gn:timezone":"Asia/Tokyo",
    "iso:country":"JP",
    "name:jpn_x_preferred":[
        "\u897f\u5927\u585a\u753a"
    ],
    "name:jpn_x_variant":[
        "\u306b\u3057\u304a\u304a\u3064\u304b\u307e\u3061",
        "\u30cb\u30b7\u30aa\u30aa\u30c4\u30ab\u30de\u30c1"
    ],
    "name:und_x_variant":[
        "Nishi\u014dtsukamachi"
    ],
    "wof:name":"Nishiotsukamachi",
    "wof:placetype":"locality"
},
  "geometry": {"coordinates":[130.70063000000002,32.12507],"type":"Point"}
}