{
  "type": "Feature",
  "properties": {
    "gn:admin1_code":"14.0",
    "gn:admin2_code":"7452808.0",
    "gn:asciiname":"Suwa",
    "gn:country_code":"JP",
    "gn:dem":17,
    "gn:feature_class":"P",
    "gn:feature_code":"PPLL",
    "gn:name":"Suwa",
    "gn:population":0,
    "gn:timezone":"Asia/Tokyo",
    "iso:country":"JP",
    "name:jpn_x_preferred":[
        "\u8acf\u8a2a"
    ],
    "wof:name":"Suwa",
    "wof:placetype":"locality"
},
  "geometry": {"coordinates":[139.98603,35.97908],"type":"Point"}
}