{
  "type": "Feature",
  "properties": {
    "gn:admin1_code":"24.0",
    "gn:admin2_code":"2112574.0",
    "gn:asciiname":"Nakazone",
    "gn:country_code":"JP",
    "gn:dem":5,
    "gn:feature_class":"P",
    "gn:feature_code":"PPL",
    "gn:name":"Nakazone",
    "gn:population":0,
    "gn:timezone":"Asia/Tokyo",
    "iso:country":"JP",
    "name:jpn_x_preferred":[
        "\u4e2d\u57e3"
    ],
    "name:jpn_x_variant":[
        "\u306a\u304b\u305e\u306d",
        "\u30ca\u30ab\u30be\u30cd"
    ],
    "wof:name":"Nakazone",
    "wof:placetype":"locality"
},
  "geometry": {"coordinates":[141.24426,38.45068],"type":"Point"}
}