{
  "type": "Feature",
  "properties": {
    "gn:admin1_code":"10",
    "gn:admin2_code":"1853946.0",
    "gn:admin3_code":"10525.0",
    "gn:asciiname":"Nakano",
    "gn:country_code":"JP",
    "gn:dem":30,
    "gn:feature_class":"P",
    "gn:feature_code":"PPL",
    "gn:name":"Nakano",
    "gn:population":0,
    "gn:timezone":"Asia/Tokyo",
    "iso:country":"JP",
    "name:jpn_x_preferred":[
        "\u4e2d\u91ce"
    ],
    "wof:name":"Nakano",
    "wof:placetype":"locality"
},
  "geometry": {"coordinates":[139.46339,36.26321],"type":"Point"}
}