{
  "type": "Feature",
  "properties": {
    "gn:admin1_code":"10",
    "gn:admin2_code":"1853946.0",
    "gn:admin3_code":"10525.0",
    "gn:asciiname":"Nakano",
    "gn:country_code":"JP",
    "gn:dem":30,
    "gn:feature_class":"P",
    "gn:feature_code":"PPL",
    "gn:name":"Nakano",
    "gn:population":0,
    "gn:timezone":"Asia/Tokyo",
    "iso:country":"JP",
    "name:ceb_x_preferred":[
        "Nakano"
    ],
    "name:deu_x_preferred":[
        "Nakano"
    ],
    "name:epo_x_preferred":[
        "Nakano"
    ],
    "name:est_x_preferred":[
        "Nakano"
    ],
    "name:fas_x_preferred":[
        "\u0646\u0627\u06a9\u0627\u0646\u0648"
    ],
    "name:fin_x_preferred":[
        "Nakano"
    ],
    "name:ita_x_preferred":[
        "Nakano"
    ],
    "name:jpn_x_preferred":[
        "\u4e2d\u91ce"
    ],
    "name:kor_x_preferred":[
        "\ub098\uce74\ub178"
    ],
    "name:mlg_x_preferred":[
        "Nakano"
    ],
    "name:nld_x_preferred":[
        "Nakano"
    ],
    "name:por_x_preferred":[
        "Nakano"
    ],
    "name:ron_x_preferred":[
        "Nakano"
    ],
    "name:rus_x_preferred":[
        "\u041d\u0430\u043a\u0430\u043d\u043e"
    ],
    "name:swe_x_preferred":[
        "Nakano"
    ],
    "name:ukr_x_preferred":[
        "\u041d\u0430\u043a\u0430\u043d\u043e"
    ],
    "wof:name":"Nakano",
    "wof:placetype":"locality"
},
  "geometry": {"coordinates":[139.46339,36.26321],"type":"Point"}
}