{
  "type": "Feature",
  "properties": {
    "gn:admin1_code":"29",
    "gn:admin2_code":"7468177.0",
    "gn:asciiname":"Senami",
    "gn:country_code":"JP",
    "gn:dem":16,
    "gn:feature_class":"P",
    "gn:feature_code":"PPL",
    "gn:name":"Senami",
    "gn:population":0,
    "gn:timezone":"Asia/Tokyo",
    "iso:country":"JP",
    "wof:name":"Senami",
    "wof:placetype":"locality"
},
  "geometry": {"coordinates":[139.44999999999999,38.23333],"type":"Point"}
}