{
  "type": "Feature",
  "properties": {
    "gn:admin1_code":"4.0",
    "gn:admin2_code":"2112330.0",
    "gn:asciiname":"Eirakudai",
    "gn:country_code":"JP",
    "gn:dem":25,
    "gn:feature_class":"P",
    "gn:feature_code":"PPL",
    "gn:name":"Eirakudai",
    "gn:population":0,
    "gn:timezone":"Asia/Tokyo",
    "iso:country":"JP",
    "name:jpn_x_preferred":[
        "\u6c38\u697d\u53f0"
    ],
    "wof:name":"Eirakudai",
    "wof:placetype":"locality"
},
  "geometry": {"coordinates":[139.96985000000001,35.84492],"type":"Point"}
}