{
  "type": "Feature",
  "properties": {
    "iso:country":"JP",
    "qs:name":"\u5584\u901a\u5bfa\u5e02",
    "qs:name_adm0":"\u65e5\u672c",
    "qs:name_adm1":"\u9999\u5ddd\u770c",
    "qs:photos":185,
    "qs:photos_1k":37,
    "qs:photos_9k":3,
    "qs:photos_9r":5,
    "qs:photos_all":731,
    "qs:photos_sr":4,
    "qs:placetype":"Town",
    "qs:pop_sr":"0",
    "wof:name":"\u5584\u901a\u5bfa\u5e02",
    "wof:placetype":"locality"
},
  "geometry": {"coordinates":[133.78661099999999,34.22348],"type":"Point"}
}