{
  "type": "Feature",
  "properties": {
    "gn:admin1_code":"37.0",
    "gn:admin2_code":"1864104.0",
    "gn:asciiname":"Kamikawa",
    "gn:country_code":"JP",
    "gn:dem":364,
    "gn:feature_class":"P",
    "gn:feature_code":"PPLL",
    "gn:name":"Kamikawa",
    "gn:population":0,
    "gn:timezone":"Asia/Tokyo",
    "iso:country":"JP",
    "name:jpn_x_preferred":[
        "\u4e0a\u5ddd\u3000"
    ],
    "wof:name":"Kamikawa",
    "wof:placetype":"locality"
},
  "geometry": {"coordinates":[138.58768000000001,35.28742000000001],"type":"Point"}
}