{
  "type": "Feature",
  "properties": {
    "gn:admin1_code":"19.0",
    "gn:admin2_code":"1848350.0",
    "gn:admin3_code":"14105.0",
    "gn:asciiname":"Yoshinocho",
    "gn:country_code":"JP",
    "gn:dem":7,
    "gn:feature_class":"P",
    "gn:feature_code":"PPL",
    "gn:name":"Yoshinoch\u014d",
    "gn:population":0,
    "gn:timezone":"Asia/Tokyo",
    "iso:country":"JP",
    "name:jpn_x_preferred":[
        "\u5409\u91ce\u753a"
    ],
    "name:jpn_x_variant":[
        "\u3088\u3057\u306e\u3061\u3087\u3046",
        "\u30e8\u30b7\u30ce\u30c1\u30e7\u30a6"
    ],
    "name:und_x_variant":[
        "Yoshinoch\u014d"
    ],
    "wof:name":"Yoshinocho",
    "wof:placetype":"locality"
},
  "geometry": {"coordinates":[139.61941999999999,35.43612],"type":"Point"}
}