{
  "type": "Feature",
  "properties": {
    "gn:admin1_code":"19.0",
    "gn:admin2_code":"1848350.0",
    "gn:admin3_code":"14108.0",
    "gn:asciiname":"Teramae",
    "gn:country_code":"JP",
    "gn:dem":5,
    "gn:feature_class":"P",
    "gn:feature_code":"PPL",
    "gn:name":"Teramae",
    "gn:population":0,
    "gn:timezone":"Asia/Tokyo",
    "iso:country":"JP",
    "name:jpn_x_preferred":[
        "\u5bfa\u524d"
    ],
    "name:jpn_x_variant":[
        "\u3066\u3089\u307e\u3048",
        "\u30c6\u30e9\u30de\u30a8"
    ],
    "wof:name":"Teramae",
    "wof:placetype":"locality"
},
  "geometry": {"coordinates":[139.62876,35.33983],"type":"Point"}
}