{
  "type": "Feature",
  "properties": {
    "gn:admin1_code":"3.0",
    "gn:admin2_code":"2128302.0",
    "gn:admin3_code":"2441.0",
    "gn:asciiname":"Obasawa",
    "gn:country_code":"JP",
    "gn:dem":221,
    "gn:feature_class":"P",
    "gn:feature_code":"PPL",
    "gn:name":"\u014cbasawa",
    "gn:population":0,
    "gn:timezone":"Asia/Tokyo",
    "iso:country":"JP",
    "name:jpn_x_preferred":[
        "\u5927\u7fbd\u6ca2"
    ],
    "name:jpn_x_variant":[
        "\u304a\u304a\u3070\u3055\u308f",
        "\u30aa\u30aa\u30d0\u30b5\u30ef"
    ],
    "name:und_x_variant":[
        "\u014cbasawa"
    ],
    "wof:name":"Obasawa",
    "wof:placetype":"locality"
},
  "geometry": {"coordinates":[141.20613,40.31446],"type":"Point"}
}