{
  "type": "Feature",
  "properties": {
    "gn:admin1_code":"15.0",
    "gn:admin2_code":"1858904.0",
    "gn:asciiname":"Maruyamamachi",
    "gn:country_code":"JP",
    "gn:dem":401,
    "gn:feature_class":"P",
    "gn:feature_code":"PPL",
    "gn:name":"Maruyamamachi",
    "gn:population":0,
    "gn:timezone":"Asia/Tokyo",
    "iso:country":"JP",
    "name:jpn_x_preferred":[
        "\u4e38\u5c71\u753a"
    ],
    "wof:name":"Maruyamamachi",
    "wof:placetype":"locality"
},
  "geometry": {"coordinates":[136.53903,36.24922],"type":"Point"}
}