{
  "type": "Feature",
  "properties": {
    "gn:admin1_code":"21.0",
    "gn:admin2_code":"1848441.0",
    "gn:asciiname":"Yatsushiro",
    "gn:country_code":"JP",
    "gn:dem":0,
    "gn:feature_class":"P",
    "gn:feature_code":"PPLA2",
    "gn:name":"Yatsushiro",
    "gn:population":0,
    "gn:timezone":"Asia/Tokyo",
    "iso:country":"JP",
    "name:jpn_x_preferred":[
        "\u516b\u4ee3"
    ],
    "wof:name":"Yatsushiro",
    "wof:placetype":"locality"
},
  "geometry": {"coordinates":[130.65285,32.55723],"type":"Point"}
}