{
  "type": "Feature",
  "properties": {
    "gn:admin1_code":"37.0",
    "gn:admin2_code":"7418320.0",
    "gn:asciiname":"Okita",
    "gn:country_code":"JP",
    "gn:dem":13,
    "gn:feature_class":"P",
    "gn:feature_code":"PPLL",
    "gn:name":"\u014ckita",
    "gn:population":0,
    "gn:timezone":"Asia/Tokyo",
    "iso:country":"JP",
    "name:jpn_x_preferred":[
        "\u5927\u5317"
    ],
    "name:und_x_variant":[
        "\u014ckita"
    ],
    "wof:name":"Okita",
    "wof:placetype":"locality"
},
  "geometry": {"coordinates":[138.92866000000001,35.06092],"type":"Point"}
}