{
  "type": "Feature",
  "properties": {
    "gn:admin1_code":"4.0",
    "gn:admin2_code":"7465524.0",
    "gn:asciiname":"Nittayatsu",
    "gn:country_code":"JP",
    "gn:dem":33,
    "gn:feature_class":"P",
    "gn:feature_code":"PPLL",
    "gn:name":"Nittayatsu",
    "gn:population":0,
    "gn:timezone":"Asia/Tokyo",
    "iso:country":"JP",
    "name:jpn_x_preferred":[
        "\u65b0\u7530\u8c37"
    ],
    "name:jpn_x_variant":[
        "\u306b\u3063\u305f\u3084\u3064",
        "\u30cb\u30c3\u30bf\u30e4\u30c4"
    ],
    "wof:name":"Nittayatsu",
    "wof:placetype":"locality"
},
  "geometry": {"coordinates":[140.37528,35.25096],"type":"Point"}
}