{
  "type": "Feature",
  "properties": {
    "gn:admin1_code":"02",
    "gn:admin2_code":"2111935.0",
    "gn:admin3_code":"5361.0",
    "gn:asciiname":"Takadoyo",
    "gn:cc2":"JP",
    "gn:country_code":"JP",
    "gn:dem":60,
    "gn:feature_class":"P",
    "gn:feature_code":"PPL",
    "gn:name":"Takadoyo",
    "gn:population":0,
    "gn:timezone":"Asia/Tokyo",
    "iso:country":"JP",
    "name:und_x_variant":[
        "Takatoyo",
        "Takadoyo"
    ],
    "wof:name":"Takadoyo",
    "wof:placetype":"locality"
},
  "geometry": {"coordinates":[140.21666999999999,39.95],"type":"Point"}
}