{
  "type": "Feature",
  "properties": {
    "gn:admin1_code":"28.0",
    "gn:admin2_code":"1848164.0",
    "gn:admin3_code":"29452.0",
    "gn:asciiname":"Kitashiodani",
    "gn:country_code":"JP",
    "gn:dem":329,
    "gn:feature_class":"P",
    "gn:feature_code":"PPL",
    "gn:name":"Kitashiodani",
    "gn:population":0,
    "gn:timezone":"Asia/Tokyo",
    "iso:country":"JP",
    "name:jpn_x_preferred":[
        "\u5317\u5869\u8c37"
    ],
    "wof:name":"Kitashiodani",
    "wof:placetype":"locality"
},
  "geometry": {"coordinates":[135.95505,34.34565],"type":"Point"}
}