{
  "type": "Feature",
  "properties": {
    "gn:admin1_code":"17",
    "gn:admin2_code":"1851654.0",
    "gn:admin3_code":"37322.0",
    "gn:asciiname":"Odeshima",
    "gn:country_code":"JP",
    "gn:dem":22,
    "gn:feature_class":"P",
    "gn:feature_code":"PPLL",
    "gn:name":"Odeshima",
    "gn:population":0,
    "gn:timezone":"Asia/Tokyo",
    "iso:country":"JP",
    "name:jpn_x_preferred":[
        "\u5c0f\u8c4a\u5cf6"
    ],
    "name:und_x_variant":[
        "Tanoura",
        "Koteshima",
        "Odeshima"
    ],
    "wof:name":"Odeshima",
    "wof:placetype":"locality"
},
  "geometry": {"coordinates":[134.11330000000001,34.47691],"type":"Point"}
}