{
  "type": "Feature",
  "properties": {
    "gn:admin1_code":"4.0",
    "gn:admin2_code":"1857552.0",
    "gn:asciiname":"Rokkodai",
    "gn:country_code":"JP",
    "gn:dem":32,
    "gn:feature_class":"P",
    "gn:feature_code":"PPL",
    "gn:name":"Rokk\u014ddai",
    "gn:population":0,
    "gn:timezone":"Asia/Tokyo",
    "iso:country":"JP",
    "name:jpn_x_preferred":[
        "\u516d\u9ad8\u53f0"
    ],
    "name:und_x_variant":[
        "Rokk\u014ddai"
    ],
    "wof:name":"Rokkodai",
    "wof:placetype":"locality"
},
  "geometry": {"coordinates":[139.98901999999998,35.79862],"type":"Point"}
}