{
  "type": "Feature",
  "properties": {
    "gn:admin1_code":"21.0",
    "gn:admin2_code":"1858418.0",
    "gn:admin3_code":"43104.0",
    "gn:asciiname":"Shimada",
    "gn:country_code":"JP",
    "gn:dem":6,
    "gn:feature_class":"P",
    "gn:feature_code":"PPLL",
    "gn:name":"Shimada",
    "gn:population":0,
    "gn:timezone":"Asia/Tokyo",
    "iso:country":"JP",
    "name:jpn_x_preferred":[
        "\u5cf6\u7530"
    ],
    "name:jpn_x_variant":[
        "\u3057\u307e\u3060",
        "\u30b7\u30de\u30c0"
    ],
    "wof:name":"Shimada",
    "wof:placetype":"locality"
},
  "geometry": {"coordinates":[130.71513999999999,32.71561],"type":"Point"}
}