{
  "type": "Feature",
  "properties": {
    "gn:admin1_code":"07",
    "gn:admin2_code":"1859306.0",
    "gn:admin3_code":"40101.0",
    "gn:asciiname":"Komorie",
    "gn:country_code":"JP",
    "gn:dem":6,
    "gn:feature_class":"P",
    "gn:feature_code":"PPL",
    "gn:name":"Komorie",
    "gn:population":0,
    "gn:timezone":"Asia/Tokyo",
    "iso:country":"JP",
    "name:jpn_x_preferred":[
        "\u5c0f\u68ee\u6c5f"
    ],
    "wof:name":"Komorie",
    "wof:placetype":"locality"
},
  "geometry": {"coordinates":[130.94316000000001,33.92568],"type":"Point"}
}