{
  "type": "Feature",
  "properties": {
    "gn:admin1_code":"2.0",
    "gn:admin2_code":"2128783.0",
    "gn:asciiname":"Akaishi",
    "gn:country_code":"JP",
    "gn:dem":41,
    "gn:feature_class":"P",
    "gn:feature_code":"PPL",
    "gn:name":"Akaishi",
    "gn:population":0,
    "gn:timezone":"Asia/Tokyo",
    "iso:country":"JP",
    "name:jpn_x_preferred":[
        "\u8d64\u77f3"
    ],
    "name:jpn_x_variant":[
        "\u3042\u304b\u3044\u3057",
        "\u30a2\u30ab\u30a4\u30b7"
    ],
    "wof:name":"Akaishi",
    "wof:placetype":"locality"
},
  "geometry": {"coordinates":[140.50107,40.25659],"type":"Point"}
}