{
  "type": "Feature",
  "properties": {
    "iso:country":"JP",
    "name:eng_x_preferred":[
        "Kusunokimachi 3 Chome"
    ],
    "name:eng_x_variant":[
        "Kusunokimachi 3 Choume",
        "Kusunokimachi 3 Chome"
    ],
    "name:jpn_x_preferred":[
        "\uff13\u4e01\u76ee"
    ],
    "name:jpn_x_variant":[
        "\u304f\u3059\u306e\u304d\u307e\u3061 \uff13\u3061\u3087\u3046\u3081",
        "\u6960\u753a \uff13\u4e01\u76ee",
        "\uff13\u3061\u3087\u3046\u3081"
    ],
    "qs:gn_local":0,
    "qs:local_max":443,
    "qs:local_sum":1246,
    "qs:localhoods":8,
    "qs:name":"\uff13\u4e01\u76ee",
    "qs:name_adm0":"\u65e5\u672c",
    "qs:name_adm1":"\u5c71\u53e3\u770c",
    "qs:name_en":"Kusunokimachi 3 Chome",
    "qs:name_lau":"\u6960\u753a",
    "qs:name_local":"\u5ca9\u56fd\u5e02",
    "qs:photo_max":1,
    "qs:photo_sum":1,
    "qs:placetype":"Suburb",
    "qs:quad_count":1,
    "qs:woe_adm0":23424856,
    "qs:woe_adm1":2345894,
    "qs:woe_adm2":0,
    "qs:woe_lau":28476649,
    "qs:woe_local":1117342,
    "qs:woe_ver":"7.10.0",
    "wof:lang":[
        "jpn"
    ],
    "wof:name":"\uff13\u4e01\u76ee",
    "wof:placetype":"neighbourhood"
},
  "geometry": {"coordinates":[132.212219,34.154999],"type":"Point"}
}