{
  "type": "Feature",
  "properties": {
    "gn:admin1_code":"43.0",
    "gn:admin2_code":"1865123.0",
    "gn:admin3_code":"30362.0",
    "gn:asciiname":"Yamamoto",
    "gn:country_code":"JP",
    "gn:dem":16,
    "gn:feature_class":"P",
    "gn:feature_code":"PPL",
    "gn:name":"Yamamoto",
    "gn:population":0,
    "gn:timezone":"Asia/Tokyo",
    "iso:country":"JP",
    "name:jpn_x_preferred":[
        "\u5c71\u672c"
    ],
    "wof:name":"Yamamoto",
    "wof:placetype":"locality"
},
  "geometry": {"coordinates":[135.1703,34.01488],"type":"Point"}
}