{
  "type": "Feature",
  "properties": {
    "gn:admin1_code":"21.0",
    "gn:admin2_code":"1865358.0",
    "gn:asciiname":"Kusuura-shinden",
    "gn:country_code":"JP",
    "gn:dem":0,
    "gn:feature_class":"P",
    "gn:feature_code":"PPLL",
    "gn:name":"Kusuura-shinden",
    "gn:population":0,
    "gn:timezone":"Asia/Tokyo",
    "iso:country":"JP",
    "name:jpn_x_preferred":[
        "\u6960\u6d66\u65b0\u7530"
    ],
    "name:jpn_x_variant":[
        "\u304f\u3059\u3046\u3089\u3057\u3093\u3067\u3093",
        "\u30af\u30b9\u30a6\u30e9\u30b7\u30f3\u30c7\u30f3"
    ],
    "wof:name":"Kusuura-shinden",
    "wof:placetype":"locality"
},
  "geometry": {"coordinates":[130.20543000000001,32.43375],"type":"Point"}
}