{
  "type": "Feature",
  "properties": {
    "gn:admin1_code":"12.0",
    "gn:admin2_code":"7428121.0",
    "gn:admin3_code":"1581.0",
    "gn:asciiname":"Toyokawa",
    "gn:country_code":"JP",
    "gn:dem":12,
    "gn:feature_class":"P",
    "gn:feature_code":"PPL",
    "gn:name":"Toyokawa",
    "gn:population":0,
    "gn:timezone":"Asia/Tokyo",
    "iso:country":"JP",
    "name:jpn_x_preferred":[
        "\u8c4a\u5ddd"
    ],
    "wof:name":"Toyokawa",
    "wof:placetype":"locality"
},
  "geometry": {"coordinates":[141.83691000000005,42.6938],"type":"Point"}
}