{
  "type": "Feature",
  "properties": {
    "gn:admin1_code":"3.0",
    "gn:admin2_code":"2127674.0",
    "gn:asciiname":"Minamitai",
    "gn:country_code":"JP",
    "gn:dem":76,
    "gn:feature_class":"P",
    "gn:feature_code":"PPL",
    "gn:name":"Minamitai",
    "gn:population":0,
    "gn:timezone":"Asia/Tokyo",
    "iso:country":"JP",
    "name:jpn_x_preferred":[
        "\u5357\u5e73"
    ],
    "name:jpn_x_variant":[
        "\u307f\u306a\u307f\u305f\u3044",
        "\u30df\u30ca\u30df\u30bf\u30a4"
    ],
    "wof:name":"Minamitai",
    "wof:placetype":"locality"
},
  "geometry": {"coordinates":[141.18668,40.61848],"type":"Point"}
}