{
  "type": "Feature",
  "properties": {
    "gn:admin1_code":"7.0",
    "gn:admin2_code":"1848086.0",
    "gn:asciiname":"Minamionoi",
    "gn:country_code":"JP",
    "gn:dem":5,
    "gn:feature_class":"P",
    "gn:feature_code":"PPLL",
    "gn:name":"Minami\u014dnoi",
    "gn:population":0,
    "gn:timezone":"Asia/Tokyo",
    "iso:country":"JP",
    "name:jpn_x_preferred":[
        "\u5357\u5927\u91ce\u4e95"
    ],
    "name:und_x_variant":[
        "Minami\u014dnoi"
    ],
    "wof:name":"Minamionoi",
    "wof:placetype":"locality"
},
  "geometry": {"coordinates":[130.95654999999999,33.71335],"type":"Point"}
}