{
  "type": "Feature",
  "properties": {
    "gn:admin1_code":"43.0",
    "gn:admin2_code":"1861287.0",
    "gn:admin3_code":"30344.0",
    "gn:asciiname":"Samizu",
    "gn:country_code":"JP",
    "gn:dem":222,
    "gn:feature_class":"P",
    "gn:feature_code":"PPL",
    "gn:name":"Samizu",
    "gn:population":0,
    "gn:timezone":"Asia/Tokyo",
    "iso:country":"JP",
    "name:jpn_x_preferred":[
        "\u4f5c\u6c34"
    ],
    "wof:name":"Samizu",
    "wof:placetype":"locality"
},
  "geometry": {"coordinates":[135.57938999999999,34.26953],"type":"Point"}
}