{
  "type": "Feature",
  "properties": {
    "gn:admin1_code":"08",
    "gn:admin2_code":"7451502.0",
    "gn:admin3_code":"7505.0",
    "gn:asciiname":"Takanuki",
    "gn:country_code":"JP",
    "gn:dem":321,
    "gn:feature_class":"P",
    "gn:feature_code":"PPL",
    "gn:name":"Takanuki",
    "gn:population":0,
    "gn:timezone":"Asia/Tokyo",
    "iso:country":"JP",
    "name:jpn_x_preferred":[
        "\u7af9\u8cab"
    ],
    "wof:name":"Takanuki",
    "wof:placetype":"locality"
},
  "geometry": {"coordinates":[140.54419999999999,37.09815],"type":"Point"}
}