{
  "type": "Feature",
  "properties": {
    "gn:admin1_code":"33.0",
    "gn:admin2_code":"1850771.0",
    "gn:asciiname":"Higashitakumachi-noso",
    "gn:country_code":"JP",
    "gn:dem":39,
    "gn:feature_class":"P",
    "gn:feature_code":"PPL",
    "gn:name":"Higashitakumachi-n\u014dso",
    "gn:population":0,
    "gn:timezone":"Asia/Tokyo",
    "iso:country":"JP",
    "name:jpn_x_preferred":[
        "\u6771\u591a\u4e45\u753a\u7d0d\u6240"
    ],
    "name:und_x_variant":[
        "Higashitakumachi-n\u014dso"
    ],
    "wof:name":"Higashitakumachi-noso",
    "wof:placetype":"locality"
},
  "geometry": {"coordinates":[130.16867999999999,33.26012],"type":"Point"}
}