{
  "type": "Feature",
  "properties": {
    "gn:admin1_code":"29",
    "gn:admin2_code":"1852957.0",
    "gn:admin3_code":"15405.0",
    "gn:asciiname":"Amaze",
    "gn:country_code":"JP",
    "gn:dem":14,
    "gn:feature_class":"P",
    "gn:feature_code":"PPL",
    "gn:name":"Amaze",
    "gn:population":0,
    "gn:timezone":"Asia/Tokyo",
    "iso:country":"JP",
    "name:jpn_x_preferred":[
        "\u5c3c\u702c"
    ],
    "name:und_x_variant":[
        "Amase",
        "Amaze"
    ],
    "wof:name":"Amaze",
    "wof:placetype":"locality"
},
  "geometry": {"coordinates":[138.68034,37.53754],"type":"Point"}
}