{
  "type": "Feature",
  "properties": {
    "gn:admin1_code":"3.0",
    "gn:admin2_code":"2129754.0",
    "gn:admin3_code":"2405.0",
    "gn:asciiname":"Orimo-shinden",
    "gn:country_code":"JP",
    "gn:dem":27,
    "gn:feature_class":"P",
    "gn:feature_code":"PPL",
    "gn:name":"Orimo-shinden",
    "gn:population":0,
    "gn:timezone":"Asia/Tokyo",
    "iso:country":"JP",
    "name:jpn_x_preferred":[
        "\u6298\u8302\u65b0\u7530"
    ],
    "name:jpn_x_variant":[
        "\u304a\u308a\u3082\u3057\u3093\u3067\u3093",
        "\u30aa\u30ea\u30e2\u30b7\u30f3\u30c7\u30f3"
    ],
    "wof:name":"Orimo-shinden",
    "wof:placetype":"locality"
},
  "geometry": {"coordinates":[141.29488999999995,40.60766],"type":"Point"}
}