{
  "type": "Feature",
  "properties": {
    "gn:admin1_code":"40.0",
    "gn:admin2_code":"1865750.0",
    "gn:asciiname":"Higashihokima",
    "gn:country_code":"JP",
    "gn:dem":10,
    "gn:feature_class":"P",
    "gn:feature_code":"PPL",
    "gn:name":"Higashihokima",
    "gn:population":0,
    "gn:timezone":"Asia/Tokyo",
    "iso:country":"JP",
    "name:jpn_x_preferred":[
        "\u6771\u4fdd\u6728\u9593"
    ],
    "wof:name":"Higashihokima",
    "wof:placetype":"locality"
},
  "geometry": {"coordinates":[139.81332,35.79183],"type":"Point"}
}