{
  "type": "Feature",
  "properties": {
    "gn:admin1_code":"28.0",
    "gn:admin2_code":"1848592.0",
    "gn:asciiname":"Ikejiri",
    "gn:country_code":"JP",
    "gn:dem":51,
    "gn:feature_class":"P",
    "gn:feature_code":"PPL",
    "gn:name":"Ikejiri",
    "gn:population":0,
    "gn:timezone":"Asia/Tokyo",
    "iso:country":"JP",
    "name:jpn_x_preferred":[
        "\u6c60\u5c3b"
    ],
    "wof:name":"Ikejiri",
    "wof:placetype":"locality"
},
  "geometry": {"coordinates":[135.74742000000001,34.52761],"type":"Point"}
}