{
  "type": "Feature",
  "properties": {
    "iso:country":"JP",
    "name:eng_x_preferred":[
        "Watanabedori 2 Chome"
    ],
    "name:eng_x_variant":[
        "Watanabedoori 2 Choume",
        "Watanabedori 2 Chome"
    ],
    "name:jpn_x_preferred":[
        "\uff12\u4e01\u76ee"
    ],
    "name:jpn_x_variant":[
        "\u308f\u305f\u306a\u3079\u3069\u304a\u308a \uff12\u3061\u3087\u3046\u3081",
        "\u6e21\u8fba\u901a \uff12\u4e01\u76ee",
        "\uff12\u3061\u3087\u3046\u3081"
    ],
    "qs:gn_adm0_cc":"JP",
    "qs:gn_local":1863967,
    "qs:gn_nam_loc":"\u798f\u5ca1\u5e02, \u798f\u5ca1\u770c, JP",
    "qs:gn_namadm1":"07",
    "qs:local_max":4714,
    "qs:local_sum":31201,
    "qs:localhoods":64,
    "qs:name":"\uff12\u4e01\u76ee",
    "qs:name_adm0":"\u65e5\u672c",
    "qs:name_adm1":"\u798f\u5ca1\u770c",
    "qs:name_adm2":"\u4e2d\u592e\u533a",
    "qs:name_en":"Watanabedori 2 Chome",
    "qs:name_lau":"\u6e21\u8fba\u901a",
    "qs:name_local":"\u798f\u5ca1\u5e02",
    "qs:photo_max":2,
    "qs:photo_sum":2,
    "qs:placetype":"Suburb",
    "qs:quad_count":1,
    "qs:woe_adm0":23424856,
    "qs:woe_adm1":58646425,
    "qs:woe_adm2":15015414,
    "qs:woe_lau":28483220,
    "qs:woe_local":1117099,
    "qs:woe_ver":"7.10.0",
    "wof:lang":[
        "jpn"
    ],
    "wof:name":"\uff12\u4e01\u76ee",
    "wof:placetype":"neighbourhood"
},
  "geometry": {"coordinates":[130.402908,33.580875],"type":"Point"}
}