{
  "type": "Feature",
  "properties": {
    "iso:country":"JP",
    "name:eng_x_preferred":[
        "Yakumo 1 Chome"
    ],
    "name:eng_x_variant":[
        "Yakumo 1 Choume",
        "Yakumo 1 Chome"
    ],
    "name:jpn_x_preferred":[
        "\uff11\u4e01\u76ee"
    ],
    "name:jpn_x_variant":[
        "\u3084\u304f\u3082 \uff11\u3061\u3087\u3046\u3081",
        "\u516b\u96f2 \uff11\u4e01\u76ee",
        "\uff11\u3061\u3087\u3046\u3081"
    ],
    "qs:gn_local":0,
    "qs:local_max":4,
    "qs:local_sum":4,
    "qs:localhoods":1,
    "qs:name":"\uff11\u4e01\u76ee",
    "qs:name_adm0":"\u65e5\u672c",
    "qs:name_adm1":"\u8328\u57ce\u770c",
    "qs:name_en":"Yakumo 1 Chome",
    "qs:name_lau":"\u516b\u96f2",
    "qs:name_local":"\u7b20\u9593\u5e02",
    "qs:photo_max":2,
    "qs:photo_sum":4,
    "qs:placetype":"Suburb",
    "qs:quad_count":3,
    "qs:woe_adm0":23424856,
    "qs:woe_adm1":2345863,
    "qs:woe_adm2":0,
    "qs:woe_lau":28402679,
    "qs:woe_local":1117458,
    "qs:woe_ver":"7.10.0",
    "wof:lang":[
        "jpn"
    ],
    "wof:name":"\uff11\u4e01\u76ee",
    "wof:placetype":"neighbourhood"
},
  "geometry": {"coordinates":[140.30639600000001,36.351632],"type":"Point"}
}