{
  "type": "Feature",
  "properties": {
    "gn:admin1_code":"29.0",
    "gn:admin2_code":"1855427.0",
    "gn:admin3_code":"15103.0",
    "gn:asciiname":"Nagata",
    "gn:country_code":"JP",
    "gn:dem":-4,
    "gn:feature_class":"P",
    "gn:feature_code":"PPL",
    "gn:name":"Nagata",
    "gn:population":0,
    "gn:timezone":"Asia/Tokyo",
    "iso:country":"JP",
    "name:jpn_x_preferred":[
        "\u9577\u6f5f"
    ],
    "name:kor_x_preferred":[
        "\ub098\uac00\ud0c0"
    ],
    "wof:name":"Nagata",
    "wof:placetype":"locality"
},
  "geometry": {"coordinates":[139.06471000000002,37.88914000000001],"type":"Point"}
}