{
  "type": "Feature",
  "properties": {
    "gn:country":"JP",
    "gn:fcode":"ADMD",
    "gn:pop":0,
    "iso:country":"JP",
    "name:jpn_x_preferred":[
        "\u6771\u6d77\u6751"
    ],
    "name:jpn_x_variant":[
        "\u3068\u3046\u304b\u3044\u3080\u3089"
    ],
    "name:unk_x_variant":[
        "Ishigami-mura"
    ],
    "qs:name":"T\u014dkai-mura",
    "qs:photos_9r":0,
    "qs:photos_sr":0,
    "qs:pop_sr":"0",
    "wof:name":"T\u014dkai-mura",
    "wof:placetype":"localadmin",
    "wof:population":0
},
  "geometry": {"coordinates":[140.58332999999999,36.46667],"type":"Point"}
}