{
  "type": "Feature",
  "properties": {
    "gn:admin1_code":"27.0",
    "gn:admin2_code":"7418810.0",
    "gn:asciiname":"Iwashigaura",
    "gn:country_code":"JP",
    "gn:dem":13,
    "gn:feature_class":"P",
    "gn:feature_code":"PPL",
    "gn:name":"Iwashigaura",
    "gn:population":0,
    "gn:timezone":"Asia/Tokyo",
    "iso:country":"JP",
    "name:jpn_x_preferred":[
        "\u9c2f\u30f6\u6d66"
    ],
    "wof:name":"Iwashigaura",
    "wof:placetype":"locality"
},
  "geometry": {"coordinates":[129.43863999999999,34.51632],"type":"Point"}
}