{
  "type": "Feature",
  "properties": {
    "gn:admin1_code":"32.0",
    "gn:admin2_code":"1860764.0",
    "gn:asciiname":"Nishiki",
    "gn:country_code":"JP",
    "gn:dem":4,
    "gn:feature_class":"P",
    "gn:feature_code":"PPL",
    "gn:name":"Nishiki",
    "gn:population":0,
    "gn:timezone":"Asia/Tokyo",
    "iso:country":"JP",
    "name:deu_x_preferred":[
        "Nishiki"
    ],
    "name:jpn_x_preferred":[
        "\u4e8c\u8272"
    ],
    "name:kor_x_preferred":[
        "\ub2c8\uc2dc\ud0a4"
    ],
    "wof:name":"Nishiki",
    "wof:placetype":"locality"
},
  "geometry": {"coordinates":[135.34176000000002,34.44606],"type":"Point"}
}