{
  "type": "Feature",
  "properties": {
    "iso:country":"JP",
    "name:eng_x_preferred":[
        "Shinmachi 1 Chome"
    ],
    "name:eng_x_variant":[
        "Shinmachi 1 Choume",
        "Shinmachi 1 Chome"
    ],
    "name:jpn_x_preferred":[
        "\uff11\u4e01\u76ee"
    ],
    "name:jpn_x_variant":[
        "\u3057\u3093\u307e\u3061 \uff11\u3061\u3087\u3046\u3081",
        "\u65b0\u753a \uff11\u4e01\u76ee",
        "\uff11\u3061\u3087\u3046\u3081"
    ],
    "qs:gn_local":0,
    "qs:local_max":56,
    "qs:local_sum":68,
    "qs:localhoods":2,
    "qs:name":"\uff11\u4e01\u76ee",
    "qs:name_adm0":"\u65e5\u672c",
    "qs:name_adm1":"\u65b0\u6f5f\u770c",
    "qs:name_en":"Shinmachi 1 Chome",
    "qs:name_lau":"\u65b0\u753a",
    "qs:name_local":"\u52a0\u8302\u5e02",
    "qs:photo_max":28,
    "qs:photo_sum":56,
    "qs:placetype":"Suburb",
    "qs:quad_count":4,
    "qs:woe_adm0":23424856,
    "qs:woe_adm1":2345878,
    "qs:woe_adm2":0,
    "qs:woe_lau":28419878,
    "qs:woe_local":1117429,
    "qs:woe_ver":"7.10.0",
    "qs_pg:name":"\uff11\u4e01\u76ee",
    "qs_pg:name_adm0":"\u65e5\u672c",
    "qs_pg:name_adm1":"\u65b0\u6f5f\u770c",
    "qs_pg:photos":33,
    "qs_pg:photos_1k":7,
    "qs_pg:photos_9k":1,
    "qs_pg:photos_9r":2,
    "qs_pg:photos_all":33,
    "qs_pg:photos_sr":2,
    "qs_pg:pop_sr":0,
    "qs_pg:qs_pg_placetype":"neighbourhood",
    "qs_pg:qs_pg_placetype_gp":"Suburb",
    "qs_pg:woe_adm0":23424856,
    "woe:adm0_id":23424856,
    "woe:name_adm0":"\u65e5\u672c",
    "woe:name_adm1":"\u65b0\u6f5f\u770c",
    "woe:placetype":"Suburb",
    "wof:lang":[
        "jpn"
    ],
    "wof:name":"\uff11\u4e01\u76ee",
    "wof:placetype":"neighbourhood"
},
  "geometry": {"coordinates":[139.05448200000001,37.654961],"type":"Point"}
}