{
  "type": "Feature",
  "properties": {
    "gn:admin1_code":"7.0",
    "gn:admin2_code":"1848572.0",
    "gn:asciiname":"Mitsuhashimachi-isodori",
    "gn:country_code":"JP",
    "gn:dem":4,
    "gn:feature_class":"P",
    "gn:feature_code":"PPL",
    "gn:name":"Mitsuhashimachi-isodori",
    "gn:population":0,
    "gn:timezone":"Asia/Tokyo",
    "iso:country":"JP",
    "name:jpn_x_preferred":[
        "\u4e09\u6a4b\u753a\u78ef\u9ce5"
    ],
    "wof:name":"Mitsuhashimachi-isodori",
    "wof:placetype":"locality"
},
  "geometry": {"coordinates":[130.42809,33.17759],"type":"Point"}
}