{
  "type": "Feature",
  "properties": {
    "gn:admin1_code":"19.0",
    "gn:admin2_code":"1864091.0",
    "gn:asciiname":"Hijirigayato",
    "gn:country_code":"JP",
    "gn:dem":33,
    "gn:feature_class":"P",
    "gn:feature_code":"PPLL",
    "gn:name":"Hijirigayato",
    "gn:population":0,
    "gn:timezone":"Asia/Tokyo",
    "iso:country":"JP",
    "name:jpn_x_preferred":[
        "\u8056\u30f6\u8c37"
    ],
    "wof:name":"Hijirigayato",
    "wof:placetype":"locality"
},
  "geometry": {"coordinates":[139.45813999999999,35.36669000000001],"type":"Point"}
}