{
  "type": "Feature",
  "properties": {
    "gn:admin1_code":"24.0",
    "gn:admin2_code":"2111147.0",
    "gn:admin3_code":"4101.0",
    "gn:asciiname":"Hokkobara",
    "gn:country_code":"JP",
    "gn:dem":260,
    "gn:feature_class":"P",
    "gn:feature_code":"PPL",
    "gn:name":"Hokkobara",
    "gn:population":0,
    "gn:timezone":"Asia/Tokyo",
    "iso:country":"JP",
    "name:jpn_x_preferred":[
        "\u5317\u5b50\u539f"
    ],
    "name:und_x_variant":[
        "Hakkowara"
    ],
    "wof:name":"Hokkobara",
    "wof:placetype":"locality"
},
  "geometry": {"coordinates":[140.63361,38.31694],"type":"Point"}
}