{
  "type": "Feature",
  "properties": {
    "iso:country":"JP",
    "name:eng_x_preferred":[
        "Bancho 4 Chome"
    ],
    "name:eng_x_variant":[
        "Banchou 4 Choume",
        "Bancho 4 Chome"
    ],
    "name:jpn_x_preferred":[
        "\uff14\u4e01\u76ee"
    ],
    "name:jpn_x_variant":[
        "\u3070\u3093\u3061\u3087\u3046 \uff14\u3061\u3087\u3046\u3081",
        "\u756a\u753a \uff14\u4e01\u76ee",
        "\uff14\u3061\u3087\u3046\u3081"
    ],
    "qs:gn_adm0_cc":"JP",
    "qs:gn_local":1851100,
    "qs:local_max":1214,
    "qs:local_sum":2181,
    "qs:localhoods":8,
    "qs:name":"\uff14\u4e01\u76ee",
    "qs:name_adm0":"\u65e5\u672c",
    "qs:name_adm1":"\u9999\u5ddd\u770c",
    "qs:name_en":"Bancho 4 Chome",
    "qs:name_lau":"\u756a\u753a",
    "qs:name_local":"\u9ad8\u677e\u5e02",
    "qs:photo_max":38,
    "qs:photo_sum":58,
    "qs:placetype":"Suburb",
    "qs:quad_count":5,
    "qs:woe_adm0":23424856,
    "qs:woe_adm1":2345866,
    "qs:woe_adm2":0,
    "qs:woe_lau":28478463,
    "qs:woe_local":1118285,
    "qs:woe_ver":"7.10.0",
    "wof:lang":[
        "jpn"
    ],
    "wof:name":"\uff14\u4e01\u76ee",
    "wof:placetype":"neighbourhood"
},
  "geometry": {"coordinates":[134.04208199999999,34.339771],"type":"Point"}
}