{
  "type": "Feature",
  "properties": {
    "gn:admin1_code":"21.0",
    "gn:admin2_code":"7413150.0",
    "gn:asciiname":"Kikukamachi-kaminagano",
    "gn:country_code":"JP",
    "gn:dem":148,
    "gn:feature_class":"P",
    "gn:feature_code":"PPL",
    "gn:name":"Kikukamachi-kaminagano",
    "gn:population":0,
    "gn:timezone":"Asia/Tokyo",
    "iso:country":"JP",
    "name:jpn_x_preferred":[
        "\u83ca\u9e7f\u753a\u4e0a\u6c38\u91ce"
    ],
    "name:jpn_x_variant":[
        "\u304d\u304f\u304b\u307e\u3061\u304b\u307f\u306a\u304c\u306e",
        "\u30ad\u30af\u30ab\u30de\u30c1\u30ab\u30df\u30ca\u30ac\u30ce"
    ],
    "wof:name":"Kikukamachi-kaminagano",
    "wof:placetype":"locality"
},
  "geometry": {"coordinates":[130.78166000000002,33.04456],"type":"Point"}
}