{
  "type": "Feature",
  "properties": {
    "gn:admin1_code":"21.0",
    "gn:admin2_code":"1865168.0",
    "gn:asciiname":"Kunai",
    "gn:country_code":"JP",
    "gn:dem":11,
    "gn:feature_class":"P",
    "gn:feature_code":"PPL",
    "gn:name":"Kunai",
    "gn:population":0,
    "gn:timezone":"Asia/Tokyo",
    "iso:country":"JP",
    "name:cat_x_preferred":[
        "Kunai"
    ],
    "name:deu_x_preferred":[
        "Kunai"
    ],
    "name:epo_x_preferred":[
        "Kunajo"
    ],
    "name:eus_x_preferred":[
        "Kunai"
    ],
    "name:fas_x_preferred":[
        "\u06a9\u0648\u0646\u0627\u06cc"
    ],
    "name:fin_x_preferred":[
        "Kunai"
    ],
    "name:fra_x_preferred":[
        "Kuna\u00ef"
    ],
    "name:hun_x_preferred":[
        "Kunai"
    ],
    "name:ind_x_preferred":[
        "Kunai"
    ],
    "name:ita_x_preferred":[
        "Kunai"
    ],
    "name:jpn_x_preferred":[
        "\u5bae\u5185"
    ],
    "name:jpn_x_variant":[
        "\u304f\u306a\u3044",
        "\u30af\u30ca\u30a4"
    ],
    "name:kor_x_preferred":[
        "\uad6c\ub098\uc774"
    ],
    "name:lit_x_preferred":[
        "Kunai"
    ],
    "name:pol_x_preferred":[
        "Kunai"
    ],
    "name:por_x_preferred":[
        "Kunai"
    ],
    "name:rus_x_preferred":[
        "\u041a\u0443\u043d\u0430\u0439"
    ],
    "name:spa_x_preferred":[
        "Kunai"
    ],
    "name:swe_x_preferred":[
        "Kunai"
    ],
    "name:tha_x_preferred":[
        "\u0e04\u0e38\u0e19\u0e30\u0e2d\u0e34"
    ],
    "name:tur_x_preferred":[
        "Kunai"
    ],
    "name:ukr_x_preferred":[
        "\u041a\u0443\u043d\u0430\u0439"
    ],
    "name:vie_x_preferred":[
        "Kunai"
    ],
    "wof:name":"Kunai",
    "wof:placetype":"locality"
},
  "geometry": {"coordinates":[130.44293000000002,32.98701],"type":"Point"}
}