{
  "type": "Feature",
  "properties": {
    "gn:admin1_code":"7.0",
    "gn:admin2_code":"7406950.0",
    "gn:admin3_code":"40625.0",
    "gn:asciiname":"Sarubaru",
    "gn:country_code":"JP",
    "gn:dem":58,
    "gn:feature_class":"P",
    "gn:feature_code":"PPLL",
    "gn:name":"Sarubaru",
    "gn:population":0,
    "gn:timezone":"Asia/Tokyo",
    "iso:country":"JP",
    "name:jpn_x_preferred":[
        "\u733f\u6797"
    ],
    "name:jpn_x_variant":[
        "\u3055\u308b\u3070\u308b"
    ],
    "wof:name":"Sarubaru",
    "wof:placetype":"locality"
},
  "geometry": {"coordinates":[130.94941,33.62634],"type":"Point"}
}