{
  "type": "Feature",
  "properties": {
    "gn:admin1_code":"46.0",
    "gn:admin2_code":"1857168.0",
    "gn:admin3_code":"19365.0",
    "gn:asciiname":"Natsusaku",
    "gn:country_code":"JP",
    "gn:dem":450,
    "gn:feature_class":"P",
    "gn:feature_code":"PPLL",
    "gn:name":"Natsusaku",
    "gn:population":0,
    "gn:timezone":"Asia/Tokyo",
    "iso:country":"JP",
    "name:jpn_x_preferred":[
        "\u590f\u4f5c\u3000"
    ],
    "wof:name":"Natsusaku",
    "wof:placetype":"locality"
},
  "geometry": {"coordinates":[138.53913,35.49022],"type":"Point"}
}