{
  "type": "Feature",
  "properties": {
    "gn:admin1_code":"10",
    "gn:admin2_code":"1850994.0",
    "gn:asciiname":"Renjakucho",
    "gn:country_code":"JP",
    "gn:dem":100,
    "gn:feature_class":"P",
    "gn:feature_code":"PPL",
    "gn:name":"Renjakuch\u014d",
    "gn:population":0,
    "gn:timezone":"Asia/Tokyo",
    "iso:country":"JP",
    "name:jpn_x_preferred":[
        "\u9023\u96c0\u753a"
    ],
    "name:und_x_variant":[
        "Renjakuch\u014d"
    ],
    "wof:name":"Renjakucho",
    "wof:placetype":"locality"
},
  "geometry": {"coordinates":[139.00828999999999,36.3245],"type":"Point"}
}