{
  "type": "Feature",
  "properties": {
    "gn:admin1_code":"2.0",
    "gn:admin2_code":"2113122.0",
    "gn:asciiname":"Hata",
    "gn:country_code":"JP",
    "gn:dem":37,
    "gn:feature_class":"P",
    "gn:feature_code":"PPL",
    "gn:name":"Hata",
    "gn:population":0,
    "gn:timezone":"Asia/Tokyo",
    "iso:country":"JP",
    "name:ceb_x_preferred":[
        "Hata"
    ],
    "name:deu_x_preferred":[
        "Hata"
    ],
    "name:fra_x_preferred":[
        "Hata"
    ],
    "name:jpn_x_preferred":[
        "\u7551"
    ],
    "name:jpn_x_variant":[
        "\u306f\u305f",
        "\u30cf\u30bf"
    ],
    "name:rus_x_preferred":[
        "\u0425\u0430\u0442\u0430"
    ],
    "name:tur_x_preferred":[
        "Hata"
    ],
    "name:ukr_x_preferred":[
        "\u0425\u0430\u0442\u0430"
    ],
    "name:vie_x_preferred":[
        "Hata"
    ],
    "wof:name":"Hata",
    "wof:placetype":"locality"
},
  "geometry": {"coordinates":[140.22681,39.69279],"type":"Point"}
}