{
  "type": "Feature",
  "properties": {
    "gn:admin1_code":"19",
    "gn:admin2_code":"7470889.0",
    "gn:asciiname":"Miyanomae",
    "gn:country_code":"JP",
    "gn:dem":19,
    "gn:feature_class":"P",
    "gn:feature_code":"PPL",
    "gn:name":"Miyanomae",
    "gn:population":0,
    "gn:timezone":"Asia/Tokyo",
    "iso:country":"JP",
    "wof:name":"Miyanomae",
    "wof:placetype":"locality"
},
  "geometry": {"coordinates":[139.39278000000002,35.42278],"type":"Point"}
}