{
  "type": "Feature",
  "properties": {
    "gn:admin1_code":"19.0",
    "gn:admin2_code":"1864928.0",
    "gn:asciiname":"Kuboyashiki",
    "gn:country_code":"JP",
    "gn:dem":98,
    "gn:feature_class":"P",
    "gn:feature_code":"PPLL",
    "gn:name":"Kuboyashiki",
    "gn:population":0,
    "gn:timezone":"Asia/Tokyo",
    "iso:country":"JP",
    "name:jpn_x_preferred":[
        "\u4e45\u4fdd\u5c4b\u6577"
    ],
    "wof:name":"Kuboyashiki",
    "wof:placetype":"locality"
},
  "geometry": {"coordinates":[139.30091000000002,35.43688],"type":"Point"}
}