{
  "type": "Feature",
  "properties": {
    "gn:admin1_code":"37.0",
    "gn:admin2_code":"1864089.0",
    "gn:asciiname":"Ishii",
    "gn:country_code":"JP",
    "gn:dem":290,
    "gn:feature_class":"P",
    "gn:feature_code":"PPL",
    "gn:name":"Ishii",
    "gn:population":0,
    "gn:timezone":"Asia/Tokyo",
    "iso:country":"JP",
    "name:jpn_x_preferred":[
        "\u77f3\u4e95"
    ],
    "name:mlg_x_preferred":[
        "Ishii"
    ],
    "wof:name":"Ishii",
    "wof:placetype":"locality"
},
  "geometry": {"coordinates":[138.73641999999998,35.19754000000001],"type":"Point"}
}