{
  "type": "Feature",
  "properties": {
    "gn:admin1_code":"19.0",
    "gn:admin2_code":"1862461.0",
    "gn:asciiname":"Oshima",
    "gn:country_code":"JP",
    "gn:dem":9,
    "gn:feature_class":"P",
    "gn:feature_code":"PPL",
    "gn:name":"\u014cshima",
    "gn:population":0,
    "gn:timezone":"Asia/Tokyo",
    "iso:country":"JP",
    "name:jpn_x_preferred":[
        "\u5927\u5cf6"
    ],
    "name:und_x_variant":[
        "\u014cshima"
    ],
    "wof:name":"Oshima",
    "wof:placetype":"locality"
},
  "geometry": {"coordinates":[139.34596999999999,35.3816],"type":"Point"}
}