{
  "type": "Feature",
  "properties": {
    "gn:admin1_code":"21.0",
    "gn:admin2_code":"1864975.0",
    "gn:admin3_code":"43424.0",
    "gn:asciiname":"Otsuru",
    "gn:country_code":"JP",
    "gn:dem":585,
    "gn:feature_class":"P",
    "gn:feature_code":"PPLL",
    "gn:name":"\u014ctsuru",
    "gn:population":0,
    "gn:timezone":"Asia/Tokyo",
    "iso:country":"JP",
    "name:jpn_x_preferred":[
        "\u5927\u9db4"
    ],
    "name:jpn_x_variant":[
        "\u304a\u304a\u3064\u308b",
        "\u30aa\u30aa\u30c4\u30eb"
    ],
    "name:und_x_variant":[
        "\u014ctsuru"
    ],
    "wof:name":"Otsuru",
    "wof:placetype":"locality"
},
  "geometry": {"coordinates":[131.10742999999999,33.12410999999999],"type":"Point"}
}