{
  "type": "Feature",
  "properties": {
    "iso:country":"JP",
    "name:eng_x_preferred":[
        "Fujinogojo 7 Chome"
    ],
    "name:eng_x_variant":[
        "Fujinogojou 7 Choume",
        "Fujinogojo 7 Chome"
    ],
    "name:jpn_x_preferred":[
        "\uff17\u4e01\u76ee"
    ],
    "name:jpn_x_variant":[
        "\u3075\u3058\u306e\u3054\u3058\u3087\u3046 \uff17\u3061\u3087\u3046\u3081",
        "\u85e4\u91ce\u4e94\u6761 \uff17\u4e01\u76ee",
        "\uff17\u3061\u3087\u3046\u3081"
    ],
    "qs:gn_local":0,
    "qs:local_max":2554,
    "qs:local_sum":22076,
    "qs:localhoods":97,
    "qs:name":"\uff17\u4e01\u76ee",
    "qs:name_adm0":"\u65e5\u672c",
    "qs:name_adm1":"\u5317\u6d77\u9053",
    "qs:name_adm2":"\u5357\u533a",
    "qs:name_en":"Fujinogojo 7 Chome",
    "qs:name_lau":"\u85e4\u91ce\u4e94\u6761",
    "qs:name_local":"\u672d\u5e4c\u5e02",
    "qs:photo_max":52,
    "qs:photo_sum":55,
    "qs:placetype":"Suburb",
    "qs:quad_count":3,
    "qs:woe_adm0":23424856,
    "qs:woe_adm1":7153351,
    "qs:woe_adm2":1111800,
    "qs:woe_lau":28379937,
    "qs:woe_local":1118108,
    "qs:woe_ver":"7.10.0",
    "wof:lang":[
        "jpn"
    ],
    "wof:name":"\uff17\u4e01\u76ee",
    "wof:placetype":"neighbourhood"
},
  "geometry": {"coordinates":[141.29101800000001,42.955583],"type":"Point"}
}