{
  "type": "Feature",
  "properties": {
    "gn:admin1_code":"40.0",
    "gn:admin2_code":"1855502.0",
    "gn:asciiname":"Hayamiya",
    "gn:country_code":"JP",
    "gn:dem":39,
    "gn:feature_class":"P",
    "gn:feature_code":"PPL",
    "gn:name":"Hayamiya",
    "gn:population":0,
    "gn:timezone":"Asia/Tokyo",
    "iso:country":"JP",
    "name:jpn_x_preferred":[
        "\u65e9\u5bae"
    ],
    "wof:name":"Hayamiya",
    "wof:placetype":"locality"
},
  "geometry": {"coordinates":[139.654,35.75204],"type":"Point"}
}