{
  "type": "Feature",
  "properties": {
    "gn:admin1_code":"4.0",
    "gn:admin2_code":"1863711.0",
    "gn:asciiname":"Mukaino",
    "gn:country_code":"JP",
    "gn:dem":36,
    "gn:feature_class":"P",
    "gn:feature_code":"PPLL",
    "gn:name":"Mukaino",
    "gn:population":0,
    "gn:timezone":"Asia/Tokyo",
    "iso:country":"JP",
    "name:jpn_x_preferred":[
        "\u5411\u91ce"
    ],
    "name:jpn_x_variant":[
        "\u3080\u304b\u3044\u306e",
        "\u30e0\u30ab\u30a4\u30ce"
    ],
    "wof:name":"Mukaino",
    "wof:placetype":"locality"
},
  "geometry": {"coordinates":[139.87989999999999,35.19592],"type":"Point"}
}