{
  "type": "Feature",
  "properties": {
    "gn:admin1_code":"3.0",
    "gn:admin2_code":"2130654.0",
    "gn:asciiname":"Sugisawa",
    "gn:country_code":"JP",
    "gn:dem":28,
    "gn:feature_class":"P",
    "gn:feature_code":"PPL",
    "gn:name":"Sugisawa",
    "gn:population":0,
    "gn:timezone":"Asia/Tokyo",
    "iso:country":"JP",
    "name:jpn_x_preferred":[
        "\u6749\u6ca2"
    ],
    "name:jpn_x_variant":[
        "\u3059\u304e\u3055\u308f",
        "\u30b9\u30ae\u30b5\u30ef"
    ],
    "name:und_x_variant":[
        "Sugizawa",
        "Suginosawa",
        "Sugisawa"
    ],
    "wof:name":"Sugisawa",
    "wof:placetype":"locality"
},
  "geometry": {"coordinates":[140.58958999999999,40.72563],"type":"Point"}
}