{
  "type": "Feature",
  "properties": {
    "gn:admin1_code":"21.0",
    "gn:admin2_code":"7413150.0",
    "gn:asciiname":"Kogabaru",
    "gn:country_code":"JP",
    "gn:dem":92,
    "gn:feature_class":"P",
    "gn:feature_code":"PPLL",
    "gn:name":"Kogabaru",
    "gn:population":0,
    "gn:timezone":"Asia/Tokyo",
    "iso:country":"JP",
    "name:jpn_x_preferred":[
        "\u53e4\u9591\u539f"
    ],
    "name:jpn_x_variant":[
        "\u3053\u304c\u3070\u308b",
        "\u30b3\u30ac\u30d0\u30eb"
    ],
    "wof:name":"Kogabaru",
    "wof:placetype":"locality"
},
  "geometry": {"coordinates":[130.67448000000002,32.97006],"type":"Point"}
}