{
  "type": "Feature",
  "properties": {
    "gn:admin1_code":"12.0",
    "gn:admin2_code":"7428078.0",
    "gn:admin3_code":"1662.0",
    "gn:asciiname":"Ponnosawa",
    "gn:country_code":"JP",
    "gn:dem":21,
    "gn:feature_class":"P",
    "gn:feature_code":"PPL",
    "gn:name":"Ponnosawa",
    "gn:population":0,
    "gn:timezone":"Asia/Tokyo",
    "iso:country":"JP",
    "wof:name":"Ponnosawa",
    "wof:placetype":"locality"
},
  "geometry": {"coordinates":[144.66319999999999,42.98681],"type":"Point"}
}