{
  "type": "Feature",
  "properties": {
    "gn:admin1_code":"7.0",
    "gn:admin2_code":"1859306.0",
    "gn:admin3_code":"40108.0",
    "gn:asciiname":"Higashiyama",
    "gn:country_code":"JP",
    "gn:dem":54,
    "gn:feature_class":"P",
    "gn:feature_code":"PPL",
    "gn:name":"Higashiyama",
    "gn:population":0,
    "gn:timezone":"Asia/Tokyo",
    "iso:country":"JP",
    "name:jpn_x_preferred":[
        "\u6771\u5c71"
    ],
    "wof:name":"Higashiyama",
    "wof:placetype":"locality"
},
  "geometry": {"coordinates":[130.83008000000001,33.86389],"type":"Point"}
}