{
  "type": "Feature",
  "properties": {
    "gn:admin1_code":"4.0",
    "gn:admin2_code":"2112997.0",
    "gn:admin3_code":"12427.0",
    "gn:asciiname":"Jizomae",
    "gn:country_code":"JP",
    "gn:dem":46,
    "gn:feature_class":"P",
    "gn:feature_code":"PPLL",
    "gn:name":"Jiz\u014dmae",
    "gn:population":0,
    "gn:timezone":"Asia/Tokyo",
    "iso:country":"JP",
    "name:jpn_x_preferred":[
        "\u5730\u8535\u524d"
    ],
    "name:jpn_x_variant":[
        "\u3058\u305e\u3046\u307e\u3048",
        "\u30b8\u30be\u30a6\u30de\u30a8"
    ],
    "name:und_x_variant":[
        "Jiz\u014dmae"
    ],
    "wof:name":"Jizomae",
    "wof:placetype":"locality"
},
  "geometry": {"coordinates":[140.23666,35.3898],"type":"Point"}
}