{
  "type": "Feature",
  "properties": {
    "gn:admin1_code":"35",
    "gn:admin2_code":"1853552.0",
    "gn:asciiname":"Seta",
    "gn:country_code":"JP",
    "gn:dem":91,
    "gn:feature_class":"P",
    "gn:feature_code":"PPL",
    "gn:name":"Seta",
    "gn:population":0,
    "gn:timezone":"Asia/Tokyo",
    "iso:country":"JP",
    "name:deu_x_preferred":[
        "Seta"
    ],
    "name:epo_x_preferred":[
        "\u0124eto"
    ],
    "name:fra_x_preferred":[
        "Seta"
    ],
    "name:hun_x_preferred":[
        "Szeta"
    ],
    "name:ita_x_preferred":[
        "Setae"
    ],
    "name:jpn_x_preferred":[
        "\u702c\u7530"
    ],
    "name:nld_x_preferred":[
        "Seta"
    ],
    "name:pol_x_preferred":[
        "Szczecinka"
    ],
    "name:und_x_variant":[
        "Seta-ch\u014d"
    ],
    "wof:name":"Seta",
    "wof:placetype":"locality"
},
  "geometry": {"coordinates":[135.91001,34.97505],"type":"Point"}
}