{
  "type": "Feature",
  "properties": {
    "gn:admin1_code":"05",
    "gn:admin2_code":"1857121.0",
    "gn:admin3_code":"38506.0",
    "gn:asciiname":"Hisayoshi",
    "gn:country_code":"JP",
    "gn:dem":12,
    "gn:feature_class":"P",
    "gn:feature_code":"PPL",
    "gn:name":"Hisayoshi",
    "gn:population":0,
    "gn:timezone":"Asia/Tokyo",
    "iso:country":"JP",
    "name:jpn_x_preferred":[
        "\u4e45\u826f"
    ],
    "name:und_x_variant":[
        "Maura"
    ],
    "wof:name":"Hisayoshi",
    "wof:placetype":"locality"
},
  "geometry": {"coordinates":[132.55131,32.94775],"type":"Point"}
}