{
  "type": "Feature",
  "properties": {
    "gn:admin1_code":"29",
    "gn:admin2_code":"7468177.0",
    "gn:asciiname":"Kangawa",
    "gn:country_code":"JP",
    "gn:dem":10,
    "gn:feature_class":"P",
    "gn:feature_code":"PPL",
    "gn:name":"Kangawa",
    "gn:population":0,
    "gn:timezone":"Asia/Tokyo",
    "iso:country":"JP",
    "name:jpn_x_preferred":[
        "\u5bd2\u5ddd"
    ],
    "name:und_x_variant":[
        "Samukawa",
        "Kangawa"
    ],
    "wof:name":"Kangawa",
    "wof:placetype":"locality"
},
  "geometry": {"coordinates":[139.49489,38.45081],"type":"Point"}
}