{
  "type": "Feature",
  "properties": {
    "gn:admin1_code":"24.0",
    "gn:admin2_code":"2112074.0",
    "gn:admin3_code":"4422.0",
    "gn:asciiname":"Kawaramachi",
    "gn:country_code":"JP",
    "gn:dem":10,
    "gn:feature_class":"P",
    "gn:feature_code":"PPL",
    "gn:name":"Kawaramachi",
    "gn:population":0,
    "gn:timezone":"Asia/Tokyo",
    "iso:country":"JP",
    "name:jpn_x_preferred":[
        "\u5ddd\u539f\u753a"
    ],
    "name:jpn_x_variant":[
        "\u304b\u308f\u3089\u307e\u3061",
        "\u30ab\u30ef\u30e9\u30de\u30c1"
    ],
    "wof:name":"Kawaramachi",
    "wof:placetype":"locality"
},
  "geometry": {"coordinates":[141.01213999999999,38.47046],"type":"Point"}
}