{
  "type": "Feature",
  "properties": {
    "iso:country":"JP",
    "name:eng_x_preferred":[
        "Marifumachi 2 Chome"
    ],
    "name:eng_x_variant":[
        "Marifumachi 2 Choume",
        "Marifumachi 2 Chome"
    ],
    "name:jpn_x_preferred":[
        "\uff12\u4e01\u76ee"
    ],
    "name:jpn_x_variant":[
        "\u307e\u308a\u3075\u307e\u3061 \uff12\u3061\u3087\u3046\u3081",
        "\u9ebb\u91cc\u5e03\u753a \uff12\u4e01\u76ee",
        "\uff12\u3061\u3087\u3046\u3081"
    ],
    "qs:gn_local":0,
    "qs:local_max":443,
    "qs:local_sum":1246,
    "qs:localhoods":8,
    "qs:name":"\uff12\u4e01\u76ee",
    "qs:name_adm0":"\u65e5\u672c",
    "qs:name_adm1":"\u5c71\u53e3\u770c",
    "qs:name_en":"Marifumachi 2 Chome",
    "qs:name_lau":"\u9ebb\u91cc\u5e03\u753a",
    "qs:name_local":"\u5ca9\u56fd\u5e02",
    "qs:photo_max":19,
    "qs:photo_sum":30,
    "qs:placetype":"Suburb",
    "qs:quad_count":3,
    "qs:woe_adm0":23424856,
    "qs:woe_adm1":2345894,
    "qs:woe_adm2":0,
    "qs:woe_lau":1111588,
    "qs:woe_local":1117342,
    "qs:woe_ver":"7.10.0",
    "wof:lang":[
        "jpn"
    ],
    "wof:name":"\uff12\u4e01\u76ee",
    "wof:placetype":"neighbourhood"
},
  "geometry": {"coordinates":[132.223049,34.171881],"type":"Point"}
}