{
  "type": "Feature",
  "properties": {
    "gn:admin1_code":"47",
    "gn:admin2_code":"1855990.0",
    "gn:admin3_code":"47327.0",
    "gn:asciiname":"Toguchi",
    "gn:country_code":"JP",
    "gn:dem":12,
    "gn:feature_class":"P",
    "gn:feature_code":"PPL",
    "gn:name":"Toguchi",
    "gn:population":0,
    "gn:timezone":"Asia/Tokyo",
    "iso:country":"JP",
    "name:jpn_x_preferred":[
        "\u6e21\u53e3"
    ],
    "name:und_x_variant":[
        "Tokuchi",
        "Toguchi"
    ],
    "wof:name":"Toguchi",
    "wof:placetype":"locality"
},
  "geometry": {"coordinates":[127.80944,26.30384],"type":"Point"}
}