{
  "type": "Feature",
  "properties": {
    "gn:admin1_code":"43",
    "gn:admin2_code":"1862767.0",
    "gn:admin3_code":"30428.0",
    "gn:asciiname":"Tanami",
    "gn:country_code":"JP",
    "gn:dem":5,
    "gn:feature_class":"P",
    "gn:feature_code":"PPL",
    "gn:name":"Tanami",
    "gn:population":0,
    "gn:timezone":"Asia/Tokyo",
    "iso:country":"JP",
    "name:deu_x_preferred":[
        "Tanami"
    ],
    "name:und_x_variant":[
        "Tonami"
    ],
    "wof:name":"Tanami",
    "wof:placetype":"locality"
},
  "geometry": {"coordinates":[135.71605,33.48641],"type":"Point"}
}