{
  "type": "Feature",
  "properties": {
    "gn:admin1_code":"3.0",
    "gn:admin2_code":"2130200.0",
    "gn:asciiname":"Tsuchihashi",
    "gn:country_code":"JP",
    "gn:dem":168,
    "gn:feature_class":"P",
    "gn:feature_code":"PPL",
    "gn:name":"Tsuchihashi",
    "gn:population":0,
    "gn:timezone":"Asia/Tokyo",
    "iso:country":"JP",
    "name:jpn_x_preferred":[
        "\u571f\u6a4b"
    ],
    "name:jpn_x_variant":[
        "\u3064\u3061\u306f\u3057",
        "\u30c4\u30c1\u30cf\u30b7"
    ],
    "wof:name":"Tsuchihashi",
    "wof:placetype":"locality"
},
  "geometry": {"coordinates":[141.46428999999995,40.45171],"type":"Point"}
}