{
  "type": "Feature",
  "properties": {
    "gn:admin1_code":"3.0",
    "gn:admin2_code":"2130225.0",
    "gn:asciiname":"Yoshino",
    "gn:country_code":"JP",
    "gn:dem":26,
    "gn:feature_class":"P",
    "gn:feature_code":"PPL",
    "gn:name":"Yoshino",
    "gn:population":0,
    "gn:timezone":"Asia/Tokyo",
    "iso:country":"JP",
    "name:jpn_x_preferred":[
        "\u5409\u91ce"
    ],
    "name:jpn_x_variant":[
        "\u3088\u3057\u306e",
        "\u30e8\u30b7\u30ce"
    ],
    "wof:name":"Yoshino",
    "wof:placetype":"locality"
},
  "geometry": {"coordinates":[140.35024000000001,41.04882],"type":"Point"}
}