{
  "type": "Feature",
  "properties": {
    "gn:admin1_code":"21.0",
    "gn:admin2_code":"1865358.0",
    "gn:asciiname":"Kaminokura",
    "gn:country_code":"JP",
    "gn:dem":8,
    "gn:feature_class":"P",
    "gn:feature_code":"PPLL",
    "gn:name":"Kaminokura",
    "gn:population":0,
    "gn:timezone":"Asia/Tokyo",
    "iso:country":"JP",
    "name:jpn_x_preferred":[
        "\u4e0a\u30ce\u5009"
    ],
    "name:jpn_x_variant":[
        "\u304b\u307f\u306e\u304f\u3089",
        "\u30ab\u30df\u30ce\u30af\u30e9"
    ],
    "wof:name":"Kaminokura",
    "wof:placetype":"locality"
},
  "geometry": {"coordinates":[130.04477,32.16669],"type":"Point"}
}