{
  "type": "Feature",
  "properties": {
    "gn:admin1_code":"12.0",
    "gn:admin2_code":"2130058.0",
    "gn:admin3_code":"1642.0",
    "gn:asciiname":"Kashun",
    "gn:country_code":"JP",
    "gn:dem":102,
    "gn:feature_class":"P",
    "gn:feature_code":"PPLL",
    "gn:name":"Kashun",
    "gn:population":0,
    "gn:timezone":"Asia/Tokyo",
    "iso:country":"JP",
    "name:jpn_x_preferred":[
        "\u82b1\u6625"
    ],
    "name:jpn_x_variant":[
        "\u304b\u3057\u3085\u3093",
        "\u30ab\u30b7\u30e5\u30f3"
    ],
    "wof:name":"Kashun",
    "wof:placetype":"locality"
},
  "geometry": {"coordinates":[143.25125,42.39717],"type":"Point"}
}