{
  "type": "Feature",
  "properties": {
    "gn:admin1_code":"33.0",
    "gn:admin2_code":"7391363.0",
    "gn:asciiname":"Hirashige",
    "gn:country_code":"JP",
    "gn:dem":493,
    "gn:feature_class":"P",
    "gn:feature_code":"PPLL",
    "gn:name":"Hirashige",
    "gn:population":0,
    "gn:timezone":"Asia/Tokyo",
    "iso:country":"JP",
    "name:jpn_x_preferred":[
        "\u5e73\u91cd"
    ],
    "wof:name":"Hirashige",
    "wof:placetype":"locality"
},
  "geometry": {"coordinates":[130.01036000000002,33.02699],"type":"Point"}
}