{
  "type": "Feature",
  "properties": {
    "gn:admin1_code":"19.0",
    "gn:admin2_code":"1859635.0",
    "gn:admin3_code":"14134.0",
    "gn:asciiname":"Mukaigaoka",
    "gn:country_code":"JP",
    "gn:dem":46,
    "gn:feature_class":"P",
    "gn:feature_code":"PPL",
    "gn:name":"Mukaigaoka",
    "gn:population":0,
    "gn:timezone":"Asia/Tokyo",
    "iso:country":"JP",
    "name:jpn_x_preferred":[
        "\u5411\u30f6\u4e18"
    ],
    "wof:name":"Mukaigaoka",
    "wof:placetype":"locality"
},
  "geometry": {"coordinates":[139.59424000000001,35.59388],"type":"Point"}
}