{
  "type": "Feature",
  "properties": {
    "gn:admin1_code":"21.0",
    "gn:admin2_code":"1865358.0",
    "gn:asciiname":"Baba",
    "gn:country_code":"JP",
    "gn:dem":34,
    "gn:feature_class":"P",
    "gn:feature_code":"PPLL",
    "gn:name":"Baba",
    "gn:population":0,
    "gn:timezone":"Asia/Tokyo",
    "iso:country":"JP",
    "name:jpn_x_preferred":[
        "\u99ac\u5834"
    ],
    "name:jpn_x_variant":[
        "\u3070\u3070",
        "\u30d0\u30d0"
    ],
    "wof:name":"Baba",
    "wof:placetype":"locality"
},
  "geometry": {"coordinates":[130.18284,32.46116],"type":"Point"}
}