{
  "type": "Feature",
  "properties": {
    "gn:admin1_code":"19.0",
    "gn:admin2_code":"1865011.0",
    "gn:admin3_code":"14361.0",
    "gn:asciiname":"Matsumoto",
    "gn:country_code":"JP",
    "gn:dem":107,
    "gn:feature_class":"P",
    "gn:feature_code":"PPL",
    "gn:name":"Matsumoto",
    "gn:population":0,
    "gn:timezone":"Asia/Tokyo",
    "iso:country":"JP",
    "name:cat_x_preferred":[
        "Matsumoto"
    ],
    "name:ceb_x_preferred":[
        "Matsumoto"
    ],
    "name:deu_x_preferred":[
        "Matsumoto"
    ],
    "name:epo_x_preferred":[
        "Macumoto"
    ],
    "name:fin_x_preferred":[
        "Matsumoto"
    ],
    "name:fra_x_preferred":[
        "Matsumoto"
    ],
    "name:ind_x_preferred":[
        "Matsumoto"
    ],
    "name:ita_x_preferred":[
        "Matsumoto"
    ],
    "name:jpn_x_preferred":[
        "\u677e\u672c"
    ],
    "name:mlg_x_preferred":[
        "Matsumoto"
    ],
    "name:por_x_preferred":[
        "Matsumoto"
    ],
    "name:rus_x_preferred":[
        "\u041c\u0430\u0446\u0443\u043c\u043e\u0442\u043e"
    ],
    "name:spa_x_preferred":[
        "Matsumoto"
    ],
    "name:ukr_x_preferred":[
        "\u041c\u0430\u0446\u0443\u043c\u043e\u0442\u043e"
    ],
    "wof:name":"Matsumoto",
    "wof:placetype":"locality"
},
  "geometry": {"coordinates":[139.2054,35.33739],"type":"Point"}
}