{
  "type": "Feature",
  "properties": {
    "gn:admin1_code":"12.0",
    "gn:admin2_code":"7428079.0",
    "gn:admin3_code":"1647.0",
    "gn:asciiname":"Inaushi",
    "gn:country_code":"JP",
    "gn:dem":167,
    "gn:feature_class":"P",
    "gn:feature_code":"PPL",
    "gn:name":"Inaushi",
    "gn:population":0,
    "gn:timezone":"Asia/Tokyo",
    "iso:country":"JP",
    "name:jpn_x_preferred":[
        "\u7a32\u725b"
    ],
    "name:jpn_x_variant":[
        "\u3044\u306a\u3046\u3057",
        "\u30a4\u30ca\u30a6\u30b7"
    ],
    "wof:name":"Inaushi",
    "wof:placetype":"locality"
},
  "geometry": {"coordinates":[143.68593999999999,43.26353],"type":"Point"}
}