{
  "type": "Feature",
  "properties": {
    "gn:admin1_code":"21.0",
    "gn:admin2_code":"7413153.0",
    "gn:asciiname":"Kamisuya",
    "gn:country_code":"JP",
    "gn:dem":63,
    "gn:feature_class":"P",
    "gn:feature_code":"PPLL",
    "gn:name":"Kamisuya",
    "gn:population":0,
    "gn:timezone":"Asia/Tokyo",
    "iso:country":"JP",
    "name:jpn_x_preferred":[
        "\u4e0a\u9808\u5c4b"
    ],
    "name:jpn_x_variant":[
        "\u304b\u307f\u3059\u3084",
        "\u30ab\u30df\u30b9\u30e4"
    ],
    "wof:name":"Kamisuya",
    "wof:placetype":"locality"
},
  "geometry": {"coordinates":[130.73242999999999,32.86125999999999],"type":"Point"}
}