{
  "type": "Feature",
  "properties": {
    "gn:admin1_code":"18.0",
    "gn:admin2_code":"7383999.0",
    "gn:admin3_code":"46491.0",
    "gn:asciiname":"Uchizume",
    "gn:country_code":"JP",
    "gn:dem":30,
    "gn:feature_class":"P",
    "gn:feature_code":"PPLL",
    "gn:name":"Uchizume",
    "gn:population":0,
    "gn:timezone":"Asia/Tokyo",
    "iso:country":"JP",
    "name:jpn_x_preferred":[
        "\u6253\u8a70"
    ],
    "wof:name":"Uchizume",
    "wof:placetype":"locality"
},
  "geometry": {"coordinates":[130.86792,31.09791],"type":"Point"}
}