{
  "type": "Feature",
  "properties": {
    "gn:admin1_code":"21.0",
    "gn:admin2_code":"1859488.0",
    "gn:asciiname":"Tsuiji",
    "gn:country_code":"JP",
    "gn:dem":74,
    "gn:feature_class":"P",
    "gn:feature_code":"PPLL",
    "gn:name":"Tsuiji",
    "gn:population":0,
    "gn:timezone":"Asia/Tokyo",
    "iso:country":"JP",
    "name:jpn_x_preferred":[
        "\u7bc9\u5730"
    ],
    "name:jpn_x_variant":[
        "\u3064\u3044\u3058",
        "\u30c4\u30a4\u30b8"
    ],
    "wof:name":"Tsuiji",
    "wof:placetype":"locality"
},
  "geometry": {"coordinates":[130.82676000000001,32.9868],"type":"Point"}
}