{
  "type": "Feature",
  "properties": {
    "gn:admin1_code":"21.0",
    "gn:admin2_code":"1848441.0",
    "gn:asciiname":"Makayabata",
    "gn:country_code":"JP",
    "gn:dem":1112,
    "gn:feature_class":"P",
    "gn:feature_code":"PPLL",
    "gn:name":"Makayabata",
    "gn:population":0,
    "gn:timezone":"Asia/Tokyo",
    "iso:country":"JP",
    "name:jpn_x_preferred":[
        "\u771f\u8431\u7551"
    ],
    "name:jpn_x_variant":[
        "\u307e\u304b\u3084\u3070\u305f",
        "\u30de\u30ab\u30e4\u30d0\u30bf"
    ],
    "wof:name":"Makayabata",
    "wof:placetype":"locality"
},
  "geometry": {"coordinates":[130.98564999999999,32.48267],"type":"Point"}
}