{
  "type": "Feature",
  "properties": {
    "gn:admin1_code":"40.0",
    "gn:admin2_code":"1859211.0",
    "gn:asciiname":"Kamikiyoto",
    "gn:country_code":"JP",
    "gn:dem":52,
    "gn:feature_class":"P",
    "gn:feature_code":"PPL",
    "gn:name":"Kamikiyoto",
    "gn:population":0,
    "gn:timezone":"Asia/Tokyo",
    "iso:country":"JP",
    "name:jpn_x_preferred":[
        "\u4e0a\u6e05\u6238"
    ],
    "wof:name":"Kamikiyoto",
    "wof:placetype":"locality"
},
  "geometry": {"coordinates":[139.52241999999998,35.77721],"type":"Point"}
}