{
  "type": "Feature",
  "properties": {
    "gn:admin1_code":"29",
    "gn:admin2_code":"1853313.0",
    "gn:asciiname":"Sawasaki",
    "gn:country_code":"JP",
    "gn:dem":5,
    "gn:feature_class":"P",
    "gn:feature_code":"PPL",
    "gn:name":"Sawasaki",
    "gn:population":0,
    "gn:timezone":"Asia/Tokyo",
    "iso:country":"JP",
    "name:jpn_x_preferred":[
        "\u6ca2\u5d0e"
    ],
    "name:und_x_variant":[
        "Sawazaki"
    ],
    "wof:name":"Sawasaki",
    "wof:placetype":"locality"
},
  "geometry": {"coordinates":[138.20781000000002,37.82175],"type":"Point"}
}