{
  "type": "Feature",
  "properties": {
    "gn:admin1_code":"21.0",
    "gn:admin2_code":"7413151.0",
    "gn:asciiname":"Arakihama",
    "gn:country_code":"JP",
    "gn:dem":5,
    "gn:feature_class":"P",
    "gn:feature_code":"PPLL",
    "gn:name":"Arakihama",
    "gn:population":0,
    "gn:timezone":"Asia/Tokyo",
    "iso:country":"JP",
    "name:jpn_x_preferred":[
        "\u8352\u6728\u6d5c"
    ],
    "name:jpn_x_variant":[
        "\u3042\u3089\u304d\u306f\u307e",
        "\u30a2\u30e9\u30ad\u30cf\u30de"
    ],
    "wof:name":"Arakihama",
    "wof:placetype":"locality"
},
  "geometry": {"coordinates":[130.44266999999999,32.57439],"type":"Point"}
}