{
  "type": "Feature",
  "properties": {
    "gn:admin1_code":"3.0",
    "gn:admin2_code":"2127674.0",
    "gn:asciiname":"Minowa",
    "gn:country_code":"JP",
    "gn:dem":32,
    "gn:feature_class":"P",
    "gn:feature_code":"PPL",
    "gn:name":"Minowa",
    "gn:population":0,
    "gn:timezone":"Asia/Tokyo",
    "iso:country":"JP",
    "name:deu_x_preferred":[
        "Minowa"
    ],
    "name:jpn_x_preferred":[
        "\u7b95\u8f2a"
    ],
    "name:jpn_x_variant":[
        "\u307f\u306e\u308f",
        "\u30df\u30ce\u30ef"
    ],
    "name:kor_x_preferred":[
        "\ubbf8\ub178\uc640"
    ],
    "wof:name":"Minowa",
    "wof:placetype":"locality"
},
  "geometry": {"coordinates":[141.28181999999995,40.59756],"type":"Point"}
}