{
  "type": "Feature",
  "properties": {
    "gn:admin1_code":"42.0",
    "gn:admin2_code":"1850038.0",
    "gn:asciiname":"Noka",
    "gn:country_code":"JP",
    "gn:dem":58,
    "gn:feature_class":"P",
    "gn:feature_code":"PPL",
    "gn:name":"N\u014dka",
    "gn:population":0,
    "gn:timezone":"Asia/Tokyo",
    "iso:country":"JP",
    "name:jpn_x_preferred":[
        "\u82d7\u52a0"
    ],
    "name:und_x_variant":[
        "N\u014dka"
    ],
    "wof:name":"Noka",
    "wof:placetype":"locality"
},
  "geometry": {"coordinates":[136.93940000000001,36.61921],"type":"Point"}
}