{
  "type": "Feature",
  "properties": {
    "gn:admin1_code":"19.0",
    "gn:admin2_code":"1848308.0",
    "gn:asciiname":"Morisaki",
    "gn:country_code":"JP",
    "gn:dem":44,
    "gn:feature_class":"P",
    "gn:feature_code":"PPL",
    "gn:name":"Morisaki",
    "gn:population":0,
    "gn:timezone":"Asia/Tokyo",
    "iso:country":"JP",
    "name:jpn_x_preferred":[
        "\u68ee\u5d0e"
    ],
    "name:jpn_x_variant":[
        "\u3082\u308a\u3055\u304d",
        "\u30e2\u30ea\u30b5\u30ad"
    ],
    "wof:name":"Morisaki",
    "wof:placetype":"locality"
},
  "geometry": {"coordinates":[139.67753999999999,35.24714],"type":"Point"}
}