{
  "type": "Feature",
  "properties": {
    "gn:admin1_code":"4.0",
    "gn:admin2_code":"7465524.0",
    "gn:asciiname":"Minami-nakamura",
    "gn:country_code":"JP",
    "gn:dem":19,
    "gn:feature_class":"P",
    "gn:feature_code":"PPLL",
    "gn:name":"Minami-nakamura",
    "gn:population":0,
    "gn:timezone":"Asia/Tokyo",
    "iso:country":"JP",
    "name:jpn_x_preferred":[
        "\u5357\u4e2d\u6751"
    ],
    "name:jpn_x_variant":[
        "\u307f\u306a\u307f\u306a\u304b\u3080\u3089",
        "\u30df\u30ca\u30df\u30ca\u30ab\u30e0\u30e9"
    ],
    "wof:name":"Minami-nakamura",
    "wof:placetype":"locality"
},
  "geometry": {"coordinates":[140.32603,35.30829],"type":"Point"}
}