{
  "type": "Feature",
  "properties": {
    "gn:admin1_code":"37.0",
    "gn:admin2_code":"8301106.0",
    "gn:asciiname":"Nagabatake",
    "gn:country_code":"JP",
    "gn:dem":160,
    "gn:feature_class":"P",
    "gn:feature_code":"PPL",
    "gn:name":"Nagabatake",
    "gn:population":0,
    "gn:timezone":"Asia/Tokyo",
    "iso:country":"JP",
    "name:jpn_x_preferred":[
        "\u9577\u7551"
    ],
    "wof:name":"Nagabatake",
    "wof:placetype":"locality"
},
  "geometry": {"coordinates":[139.11704,34.93786],"type":"Point"}
}