{
  "type": "Feature",
  "properties": {
    "gn:admin1_code":"12.0",
    "gn:admin2_code":"7428095.0",
    "gn:admin3_code":"1559.0",
    "gn:asciiname":"Kamiyubetsu Tonden Shigaichi",
    "gn:country_code":"JP",
    "gn:dem":35,
    "gn:feature_class":"P",
    "gn:feature_code":"PPL",
    "gn:name":"Kamiy\u016bbetsu Tonden Shigaichi",
    "gn:population":0,
    "gn:timezone":"Asia/Tokyo",
    "iso:country":"JP",
    "name:jpn_x_preferred":[
        "\u4e0a\u6e67\u5225\u5c6f\u7530\u5e02\u8857\u5730"
    ],
    "name:jpn_x_variant":[
        "\u304b\u307f\u3086\u3046\u3079\u3064\u3068\u3093\u3067\u3093\u3057\u304c\u3044\u3061",
        "\u30ab\u30df\u30e6\u30a6\u30d9\u30c4\u30c8\u30f3\u30c7\u30f3\u30b7\u30ac\u30a4\u30c1"
    ],
    "name:und_x_variant":[
        "Tondenshigai",
        "Kami-y\u016bbetsu",
        "Kamiy\u016bbetsu Tonden Shigaichi"
    ],
    "wof:name":"Kamiyubetsu Tonden Shigaichi",
    "wof:placetype":"locality"
},
  "geometry": {"coordinates":[143.56721999999999,44.13556],"type":"Point"}
}