{
  "type": "Feature",
  "properties": {
    "gn:admin1_code":"27.0",
    "gn:admin2_code":"1852895.0",
    "gn:asciiname":"Shikamachicho-funenomura",
    "gn:country_code":"JP",
    "gn:dem":120,
    "gn:feature_class":"P",
    "gn:feature_code":"PPL",
    "gn:name":"Shikamachich\u014d-funenomura",
    "gn:population":0,
    "gn:timezone":"Asia/Tokyo",
    "iso:country":"JP",
    "name:jpn_x_preferred":[
        "\u9e7f\u753a\u753a\u8239\u30ce\u6751"
    ],
    "name:und_x_variant":[
        "Shikamachich\u014d-funenomura"
    ],
    "wof:name":"Shikamachicho-funenomura",
    "wof:placetype":"locality"
},
  "geometry": {"coordinates":[129.61255,33.27363],"type":"Point"}
}