{
  "type": "Feature",
  "properties": {
    "gn:admin1_code":"21.0",
    "gn:admin2_code":"1865168.0",
    "gn:asciiname":"Uchigoshi",
    "gn:country_code":"JP",
    "gn:dem":4,
    "gn:feature_class":"P",
    "gn:feature_code":"PPLL",
    "gn:name":"Uchigoshi",
    "gn:population":0,
    "gn:timezone":"Asia/Tokyo",
    "iso:country":"JP",
    "name:jpn_x_preferred":[
        "\u6253\u8d8a"
    ],
    "name:jpn_x_variant":[
        "\u3046\u3061\u3054\u3057",
        "\u30a6\u30c1\u30b4\u30b7"
    ],
    "wof:name":"Uchigoshi",
    "wof:placetype":"locality"
},
  "geometry": {"coordinates":[130.43503000000001,32.98273],"type":"Point"}
}