{
  "type": "Feature",
  "properties": {
    "gn:country":"JP",
    "iso:country":"JP",
    "qs:name":"\u7530\u5c3b\u753a",
    "qs:name_adm0":"\u65e5\u672c",
    "qs:name_adm1":"\u5927\u962a\u5e9c",
    "qs:photos":1359,
    "qs:photos_1k":275,
    "qs:photos_9k":6,
    "qs:photos_9r":7,
    "qs:photos_all":1359,
    "qs:photos_sr":12,
    "qs:placetype":"Town",
    "qs:pop_sr":"0",
    "wof:name":"\u7530\u5c3b\u753a",
    "wof:placetype":"locality"
},
  "geometry": {"coordinates":[135.244516,34.435188],"type":"Point"}
}