{
  "type": "Feature",
  "properties": {
    "gn:country":"JP",
    "gn:fcode":"ADMD",
    "gn:population":0,
    "iso:country":"JP",
    "name:jpn_x_preferred":[
        "\u65e5\u9ad8\u753a"
    ],
    "qs:name":"Hidaka-machi",
    "qs:photos_9r":0,
    "qs:photos_sr":0,
    "qs:pop_sr":"0",
    "wof:name":"Hidaka-machi",
    "wof:placetype":"localadmin",
    "wof:population":0
},
  "geometry": {"coordinates":[139.33906999999999,35.90773],"type":"Point"}
}