{
  "type": "Feature",
  "properties": {
    "gn:admin1_code":"28.0",
    "gn:admin2_code":"9036699.0",
    "gn:asciiname":"Tanakacho",
    "gn:country_code":"JP",
    "gn:dem":83,
    "gn:feature_class":"P",
    "gn:feature_code":"PPL",
    "gn:name":"Tanakach\u014d",
    "gn:population":0,
    "gn:timezone":"Asia/Tokyo",
    "iso:country":"JP",
    "name:jpn_x_preferred":[
        "\u7530\u4e2d\u753a"
    ],
    "name:und_x_variant":[
        "Tanakach\u014d"
    ],
    "wof:name":"Tanakacho",
    "wof:placetype":"locality"
},
  "geometry": {"coordinates":[135.80591000000001,34.4878],"type":"Point"}
}