{
  "type": "Feature",
  "properties": {
    "gn:admin1_code":"21.0",
    "gn:admin2_code":"7412706.0",
    "gn:admin3_code":"43447.0",
    "gn:asciiname":"Semine",
    "gn:country_code":"JP",
    "gn:dem":301,
    "gn:feature_class":"P",
    "gn:feature_code":"PPLL",
    "gn:name":"Semine",
    "gn:population":0,
    "gn:timezone":"Asia/Tokyo",
    "iso:country":"JP",
    "name:jpn_x_preferred":[
        "\u702c\u5cf0"
    ],
    "name:jpn_x_variant":[
        "\u305b\u307f\u306d",
        "\u30bb\u30df\u30cd"
    ],
    "wof:name":"Semine",
    "wof:placetype":"locality"
},
  "geometry": {"coordinates":[130.93826000000001,32.67695],"type":"Point"}
}