{
  "type": "Feature",
  "properties": {
    "gn:admin1_code":"21.0",
    "gn:admin2_code":"1859488.0",
    "gn:asciiname":"Shisuimachi-yoshidomi",
    "gn:country_code":"JP",
    "gn:dem":74,
    "gn:feature_class":"P",
    "gn:feature_code":"PPL",
    "gn:name":"Shisuimachi-yoshidomi",
    "gn:population":0,
    "gn:timezone":"Asia/Tokyo",
    "iso:country":"JP",
    "name:jpn_x_preferred":[
        "\u6cd7\u6c34\u753a\u5409\u5bcc"
    ],
    "name:jpn_x_variant":[
        "\u3057\u3059\u3044\u307e\u3057\u3088\u3057\u3069\u307f",
        "\u30b7\u30b9\u30a4\u30de\u30c1\u30e8\u30b7\u30c9\u30df"
    ],
    "wof:name":"Shisuimachi-yoshidomi",
    "wof:placetype":"locality"
},
  "geometry": {"coordinates":[130.78442999999999,32.93086],"type":"Point"}
}