{
  "type": "Feature",
  "properties": {
    "gn:admin1_code":"04",
    "gn:admin2_code":"7465521.0",
    "gn:asciiname":"Kohama",
    "gn:country_code":"JP",
    "gn:dem":44,
    "gn:feature_class":"P",
    "gn:feature_code":"PPLL",
    "gn:name":"Kohama",
    "gn:population":0,
    "gn:timezone":"Asia/Tokyo",
    "iso:country":"JP",
    "name:jpn_x_preferred":[
        "\u5c0f\u6d5c"
    ],
    "name:jpn_x_variant":[
        "\u3053\u306f\u307e",
        "\u30b3\u30cf\u30de"
    ],
    "name:kor_x_preferred":[
        "\uace0\ud558\ub9c8"
    ],
    "wof:name":"Kohama",
    "wof:placetype":"locality"
},
  "geometry": {"coordinates":[139.82303000000002,35.07060999999999],"type":"Point"}
}