{
  "type": "Feature",
  "properties": {
    "gn:admin1_code":"4.0",
    "gn:admin2_code":"1859468.0",
    "gn:asciiname":"Nigorizawa",
    "gn:country_code":"JP",
    "gn:dem":165,
    "gn:feature_class":"P",
    "gn:feature_code":"PPLL",
    "gn:name":"Nigorizawa",
    "gn:population":0,
    "gn:timezone":"Asia/Tokyo",
    "iso:country":"JP",
    "name:jpn_x_preferred":[
        "\u6fc1\u6ca2"
    ],
    "name:jpn_x_variant":[
        "\u306b\u3054\u308a\u3056\u308f",
        "\u30cb\u30b4\u30ea\u30b6\u30ef"
    ],
    "wof:name":"Nigorizawa",
    "wof:placetype":"locality"
},
  "geometry": {"coordinates":[140.02354,35.30401],"type":"Point"}
}