{
  "type": "Feature",
  "properties": {
    "iso:country":"JP",
    "name:eng_x_preferred":[
        "Nagai 4 Chome"
    ],
    "name:eng_x_variant":[
        "Nagai 4 Choume",
        "Nagai 4 Chome"
    ],
    "name:jpn_x_preferred":[
        "\uff14\u4e01\u76ee"
    ],
    "name:jpn_x_variant":[
        "\u306a\u304c\u3044 \uff14\u3061\u3087\u3046\u3081",
        "\u9577\u4e95 \uff14\u4e01\u76ee",
        "\uff14\u3061\u3087\u3046\u3081"
    ],
    "qs:gn_local":0,
    "qs:local_max":1046,
    "qs:local_sum":7358,
    "qs:localhoods":30,
    "qs:name":"\uff14\u4e01\u76ee",
    "qs:name_adm0":"\u65e5\u672c",
    "qs:name_adm1":"\u795e\u5948\u5ddd\u770c",
    "qs:name_en":"Nagai 4 Chome",
    "qs:name_lau":"\u9577\u4e95",
    "qs:name_local":"\u6a2a\u9808\u8cc0\u5e02",
    "qs:photo_max":171,
    "qs:photo_sum":539,
    "qs:placetype":"Suburb",
    "qs:quad_count":17,
    "qs:woe_adm0":23424856,
    "qs:woe_adm1":2345868,
    "qs:woe_adm2":0,
    "qs:woe_lau":1112318,
    "qs:woe_local":1118552,
    "qs:woe_ver":"7.10.0",
    "wof:lang":[
        "jpn"
    ],
    "wof:name":"\uff14\u4e01\u76ee",
    "wof:placetype":"neighbourhood"
},
  "geometry": {"coordinates":[139.61383499999999,35.194458],"type":"Point"}
}