{
  "type": "Feature",
  "properties": {
    "gn:admin1_code":"32.0",
    "gn:admin2_code":"1864413.0",
    "gn:asciiname":"Morofuku",
    "gn:country_code":"JP",
    "gn:dem":1,
    "gn:feature_class":"P",
    "gn:feature_code":"PPL",
    "gn:name":"Morofuku",
    "gn:population":0,
    "gn:timezone":"Asia/Tokyo",
    "iso:country":"JP",
    "name:jpn_x_preferred":[
        "\u8af8\u798f"
    ],
    "wof:name":"Morofuku",
    "wof:placetype":"locality"
},
  "geometry": {"coordinates":[135.60346999999999,34.7039],"type":"Point"}
}