{
  "type": "Feature",
  "properties": {
    "gn:admin1_code":"21.0",
    "gn:admin2_code":"7412708.0",
    "gn:admin3_code":"43501.0",
    "gn:asciiname":"Hirakawa",
    "gn:country_code":"JP",
    "gn:dem":155,
    "gn:feature_class":"P",
    "gn:feature_code":"PPLL",
    "gn:name":"Hirakawa",
    "gn:population":0,
    "gn:timezone":"Asia/Tokyo",
    "iso:country":"JP",
    "name:jpn_x_preferred":[
        "\u5e73\u5ddd"
    ],
    "name:jpn_x_variant":[
        "\u3072\u3089\u304b\u308f",
        "\u30d2\u30e9\u30ab\u30ef"
    ],
    "wof:name":"Hirakawa",
    "wof:placetype":"locality"
},
  "geometry": {"coordinates":[130.85536999999999,32.23967],"type":"Point"}
}