{
  "type": "Feature",
  "properties": {
    "iso:country":"JP",
    "qs:name":"\u672c\u57dc\u6751",
    "qs:name_adm0":"\u65e5\u672c",
    "qs:name_adm1":"\u5343\u8449\u770c",
    "qs:photos":29,
    "qs:photos_1k":6,
    "qs:photos_9k":1,
    "qs:photos_9r":2,
    "qs:photos_all":39,
    "qs:photos_sr":2,
    "qs:placetype":"Town",
    "qs:pop_sr":"0",
    "wof:name":"\u672c\u57dc\u6751",
    "wof:placetype":"locality"
},
  "geometry": {"coordinates":[140.18211299999999,35.807233],"type":"Point"}
}