{
  "type": "Feature",
  "properties": {
    "gn:admin1_code":"7.0",
    "gn:admin2_code":"7407416.0",
    "gn:asciiname":"Shibatani",
    "gn:country_code":"JP",
    "gn:dem":34,
    "gn:feature_class":"P",
    "gn:feature_code":"PPLL",
    "gn:name":"Shibatani",
    "gn:population":0,
    "gn:timezone":"Asia/Tokyo",
    "iso:country":"JP",
    "name:jpn_x_preferred":[
        "\u67f4\u8c37"
    ],
    "wof:name":"Shibatani",
    "wof:placetype":"locality"
},
  "geometry": {"coordinates":[130.67400000000001,33.73273],"type":"Point"}
}