{
  "type": "Feature",
  "properties": {
    "iso:country":"JP",
    "qs:name":"\u6e6f\u4e4b\u5cf6",
    "qs:name_adm0":"\u65e5\u672c",
    "qs:name_adm1":"\u5c90\u961c\u770c",
    "qs:photos":15,
    "qs:photos_1k":3,
    "qs:photos_9k":1,
    "qs:photos_9r":1,
    "qs:photos_all":15,
    "qs:photos_sr":1,
    "qs:placetype":"LocalAdmin",
    "qs:pop_sr":"0",
    "wof:name":"\u6e6f\u4e4b\u5cf6",
    "wof:placetype":"localadmin"
},
  "geometry": {"coordinates":[137.23561100000001,35.808055],"type":"Point"}
}