{
  "type": "Feature",
  "properties": {
    "gn:admin1_code":"21.0",
    "gn:admin2_code":"1864973.0",
    "gn:asciiname":"Namino-nakae",
    "gn:country_code":"JP",
    "gn:dem":661,
    "gn:feature_class":"P",
    "gn:feature_code":"PPL",
    "gn:name":"Namino-nakae",
    "gn:population":0,
    "gn:timezone":"Asia/Tokyo",
    "iso:country":"JP",
    "name:jpn_x_preferred":[
        "\u6d6a\u91ce\u4e2d\u6c5f"
    ],
    "name:jpn_x_variant":[
        "\u306a\u307f\u306e\u306a\u304b\u3048",
        "\u30ca\u30df\u30ce\u30ca\u30ab\u30a8"
    ],
    "wof:name":"Namino-nakae",
    "wof:placetype":"locality"
},
  "geometry": {"coordinates":[131.24561,32.9308],"type":"Point"}
}