{
  "type": "Feature",
  "properties": {
    "gn:admin1_code":"13",
    "gn:admin2_code":"1859161.0",
    "gn:admin3_code":"28105.0",
    "gn:asciiname":"Shimagamicho",
    "gn:country_code":"JP",
    "gn:dem":-1,
    "gn:feature_class":"P",
    "gn:feature_code":"PPL",
    "gn:name":"Shimagamich\u014d",
    "gn:population":0,
    "gn:timezone":"Asia/Tokyo",
    "iso:country":"JP",
    "name:jpn_x_preferred":[
        "\u5cf6\u4e0a\u753a"
    ],
    "name:und_x_variant":[
        "Shimakamich\u014d",
        "Shimagamich\u014d"
    ],
    "wof:name":"Shimagamicho",
    "wof:placetype":"locality"
},
  "geometry": {"coordinates":[135.17525000000001,34.66434],"type":"Point"}
}