{
  "type": "Feature",
  "properties": {
    "gn:admin1_code":"09",
    "gn:admin2_code":"1850890.0",
    "gn:asciiname":"Kanakido",
    "gn:country_code":"JP",
    "gn:dem":881,
    "gn:feature_class":"P",
    "gn:feature_code":"PPL",
    "gn:name":"Kanakido",
    "gn:population":0,
    "gn:timezone":"Asia/Tokyo",
    "iso:country":"JP",
    "wof:name":"Kanakido",
    "wof:placetype":"locality"
},
  "geometry": {"coordinates":[137.43333000000001,36.31667],"type":"Point"}
}