{
  "type": "Feature",
  "properties": {
    "gn:admin1_code":"2.0",
    "gn:admin2_code":"7443160.0",
    "gn:asciiname":"Yurihonjo",
    "gn:country_code":"JP",
    "gn:dem":4,
    "gn:feature_class":"P",
    "gn:feature_code":"PPLA2",
    "gn:name":"Yurihonj\u014d",
    "gn:population":0,
    "gn:timezone":"Asia/Tokyo",
    "iso:country":"JP",
    "name:ara_x_preferred":[
        "\u064a\u0648\u0631\u064a\u0647\u0648\u0646\u062c\u0648"
    ],
    "name:azb_x_preferred":[
        "\u06cc\u0648\u0631\u06cc\u0647\u0648\u0646\u062c\u0648"
    ],
    "name:ceb_x_preferred":[
        "Yurihonj\u014d"
    ],
    "name:deu_x_preferred":[
        "Yurihonj\u014d"
    ],
    "name:fas_x_preferred":[
        "\u06cc\u0648\u0631\u06cc\u0647\u0648\u0646\u062c\u0648\u060c \u0622\u06a9\u06cc\u062a\u0627"
    ],
    "name:fas_x_variant":[
        "\u06cc\u0648\u0631\u06cc\u0647\u0648\u0646\u062c\u0648"
    ],
    "name:fra_x_preferred":[
        "Yurihonj\u014d"
    ],
    "name:glg_x_preferred":[
        "Yurihonj\u014d"
    ],
    "name:hun_x_preferred":[
        "Jurihondzs\u00f3"
    ],
    "name:ita_x_preferred":[
        "Yurihonj\u014d"
    ],
    "name:jpn_x_preferred":[
        "\u7531\u5229\u672c\u8358"
    ],
    "name:jpn_x_variant":[
        "\u7531\u5229\u672c\u8358\u5e02"
    ],
    "name:kaz_x_preferred":[
        "\u042e\u0440\u0438\u0445\u043e\u043d\u0434\u0445\u0437\u0435 \u049b\u0430\u043b\u0430\u0441\u044b"
    ],
    "name:kor_x_preferred":[
        "\uc720\ub9ac\ud63c\uc870 \uc2dc"
    ],
    "name:kor_x_variant":[
        "\uc720\ub9ac\ud63c\uc870\uc2dc"
    ],
    "name:mzn_x_preferred":[
        "\u06cc\u0648\u0631\u06cc\u0647\u0648\u0646\u062c\u0648\u060c \u0622\u06a9\u06cc\u062a\u0627"
    ],
    "name:mzn_x_variant":[
        "\u06cc\u0648\u0631\u06cc\u0647\u0648\u0646\u062c\u0648"
    ],
    "name:nan_x_preferred":[
        "Yurihonzy\u00f4-chh\u012b"
    ],
    "name:nld_x_preferred":[
        "Yurihonjo"
    ],
    "name:pol_x_preferred":[
        "Yurihonj\u014d"
    ],
    "name:por_x_preferred":[
        "Yurihonjo"
    ],
    "name:ron_x_preferred":[
        "Yurihonjo"
    ],
    "name:ron_x_variant":[
        "Yurihonj\u014d"
    ],
    "name:rus_x_preferred":[
        "\u042e\u0440\u0438\u0445\u043e\u043d\u0434\u0437\u0451"
    ],
    "name:spa_x_preferred":[
        "Yurihonj\u014d"
    ],
    "name:swe_x_preferred":[
        "Yurihonjo"
    ],
    "name:tgk_x_preferred":[
        "\u042e\u0440\u0438\u04b3\u043e\u043d\u04b7\u043e"
    ],
    "name:tgl_x_preferred":[
        "Yurihondyo"
    ],
    "name:tgl_x_variant":[
        "Yurihonj\u014d"
    ],
    "name:tum_x_preferred":[
        "Yurihonj\u014d"
    ],
    "name:tur_x_preferred":[
        "Yurihonj\u014d"
    ],
    "name:ukr_x_preferred":[
        "\u042e\u0440\u0456-\u0425\u043e\u043d\u0434\u0437\u044c\u043e"
    ],
    "name:urd_x_preferred":[
        "\u06cc\u0648\u0631\u06cc\u06be\u0648\u0646\u062c\u0648\u060c \u0627\u06a9\u062a\u0627"
    ],
    "name:urd_x_variant":[
        "\u06cc\u0648\u0631\u06cc\u06c1\u0648\u0646\u062c\u0648"
    ],
    "name:vie_x_preferred":[
        "Yurihonj\u014d"
    ],
    "name:war_x_preferred":[
        "Yurihonj\u014d"
    ],
    "name:zho_x_preferred":[
        "\u7531\u5229\u672c\u838a\u5e02"
    ],
    "wof:name":"Yurihonjo",
    "wof:placetype":"locality"
},
  "geometry": {"coordinates":[140.05813000000001,39.3895],"type":"Point"}
}