{
  "type": "Feature",
  "properties": {
    "gn:admin1_code":"44",
    "gn:admin2_code":"7450462.0",
    "gn:admin3_code":"6461.0",
    "gn:asciiname":"Fukura",
    "gn:country_code":"JP",
    "gn:dem":4,
    "gn:feature_class":"P",
    "gn:feature_code":"PPL",
    "gn:name":"Fukura",
    "gn:population":0,
    "gn:timezone":"Asia/Tokyo",
    "iso:country":"JP",
    "name:jpn_x_preferred":[
        "\u5439\u6d66"
    ],
    "wof:name":"Fukura",
    "wof:placetype":"locality"
},
  "geometry": {"coordinates":[139.87853000000001,39.07303],"type":"Point"}
}