{
  "type": "Feature",
  "properties": {
    "gn:admin1_code":"40",
    "gn:admin2_code":"1857869.0",
    "gn:asciiname":"Nozuta",
    "gn:country_code":"JP",
    "gn:dem":60,
    "gn:feature_class":"P",
    "gn:feature_code":"PPL",
    "gn:name":"Nozuta",
    "gn:population":0,
    "gn:timezone":"Asia/Tokyo",
    "iso:country":"JP",
    "wof:name":"Nozuta",
    "wof:placetype":"locality"
},
  "geometry": {"coordinates":[139.43888999999999,35.58694000000001],"type":"Point"}
}