{
  "type": "Feature",
  "properties": {
    "gn:admin1_code":"29.0",
    "gn:admin2_code":"1855427.0",
    "gn:admin3_code":"15106.0",
    "gn:asciiname":"Odori",
    "gn:country_code":"JP",
    "gn:dem":0,
    "gn:feature_class":"P",
    "gn:feature_code":"PPL",
    "gn:name":"\u014cd\u014dri",
    "gn:population":0,
    "gn:timezone":"Asia/Tokyo",
    "iso:country":"JP",
    "name:ceb_x_preferred":[
        "Odori"
    ],
    "name:jpn_x_preferred":[
        "\u5927\u901a"
    ],
    "name:und_x_variant":[
        "\u014cd\u014dri"
    ],
    "wof:name":"Odori",
    "wof:placetype":"locality"
},
  "geometry": {"coordinates":[139.01908,37.84115],"type":"Point"}
}