{
  "type": "Feature",
  "properties": {
    "gn:admin1_code":"12.0",
    "gn:admin2_code":"7428081.0",
    "gn:admin3_code":"1403.0",
    "gn:asciiname":"Horikappu",
    "gn:cc2":"JP",
    "gn:country_code":"JP",
    "gn:dem":21,
    "gn:feature_class":"P",
    "gn:feature_code":"PPL",
    "gn:name":"Horikappu",
    "gn:population":0,
    "gn:timezone":"Asia/Tokyo",
    "iso:country":"JP",
    "name:und_x_variant":[
        "Horikabu",
        "Horikappu"
    ],
    "wof:name":"Horikappu",
    "wof:placetype":"locality"
},
  "geometry": {"coordinates":[140.53333000000001,43.03333],"type":"Point"}
}