{
  "type": "Feature",
  "properties": {
    "gn:admin1_code":"16.0",
    "gn:admin2_code":"2112822.0",
    "gn:asciiname":"Ushikado",
    "gn:country_code":"JP",
    "gn:dem":247,
    "gn:feature_class":"P",
    "gn:feature_code":"PPL",
    "gn:name":"Ushikado",
    "gn:population":0,
    "gn:timezone":"Asia/Tokyo",
    "iso:country":"JP",
    "name:jpn_x_preferred":[
        "\u725b\u89d2"
    ],
    "name:jpn_x_variant":[
        "\u3046\u3057\u304b\u3069",
        "\u30a6\u30b7\u30ab\u30c9"
    ],
    "wof:name":"Ushikado",
    "wof:placetype":"locality"
},
  "geometry": {"coordinates":[141.00624999999999,39.44177],"type":"Point"}
}