{
  "type": "Feature",
  "properties": {
    "gn:admin1_code":"29.0",
    "gn:admin2_code":"7468177.0",
    "gn:asciiname":"Iioka",
    "gn:country_code":"JP",
    "gn:dem":10,
    "gn:feature_class":"P",
    "gn:feature_code":"PPL",
    "gn:name":"Iioka",
    "gn:population":0,
    "gn:timezone":"Asia/Tokyo",
    "iso:country":"JP",
    "name:jpn_x_preferred":[
        "\u98ef\u5ca1"
    ],
    "wof:name":"Iioka",
    "wof:placetype":"locality"
},
  "geometry": {"coordinates":[139.4736,38.17011],"type":"Point"}
}