{
  "type": "Feature",
  "properties": {
    "iso:country":"JP",
    "name:eng_x_preferred":[
        "Hamacho 4 Chome"
    ],
    "name:eng_x_variant":[
        "Hamachou 4 Choume",
        "Hamacho 4 Chome"
    ],
    "name:jpn_x_preferred":[
        "\uff14\u4e01\u76ee"
    ],
    "name:jpn_x_variant":[
        "\u306f\u307e\u3061\u3087\u3046 \uff14\u3061\u3087\u3046\u3081",
        "\u6d5c\u753a \uff14\u4e01\u76ee",
        "\uff14\u3061\u3087\u3046\u3081"
    ],
    "qs:gn_adm0_cc":"JP",
    "qs:gn_local":1859642,
    "qs:local_max":4758,
    "qs:local_sum":25395,
    "qs:localhoods":83,
    "qs:name":"\uff14\u4e01\u76ee",
    "qs:name_adm0":"\u65e5\u672c",
    "qs:name_adm1":"\u795e\u5948\u5ddd\u770c",
    "qs:name_adm2":"\u5ddd\u5d0e\u533a",
    "qs:name_en":"Hamacho 4 Chome",
    "qs:name_lau":"\u6d5c\u753a",
    "qs:name_local":"\u5ddd\u5d0e\u5e02",
    "qs:photo_max":3,
    "qs:photo_sum":5,
    "qs:placetype":"Suburb",
    "qs:quad_count":2,
    "qs:woe_adm0":23424856,
    "qs:woe_adm1":2345868,
    "qs:woe_adm2":15015510,
    "qs:woe_lau":28416322,
    "qs:woe_local":1117502,
    "qs:woe_ver":"7.10.0",
    "wof:lang":[
        "jpn"
    ],
    "wof:name":"\uff14\u4e01\u76ee",
    "wof:placetype":"neighbourhood"
},
  "geometry": {"coordinates":[139.72357199999999,35.51658],"type":"Point"}
}