{
  "type": "Feature",
  "properties": {
    "gn:admin1_code":"12.0",
    "gn:admin2_code":"2130058.0",
    "gn:admin3_code":"1642.0",
    "gn:asciiname":"Rubeshibetsu",
    "gn:country_code":"JP",
    "gn:dem":43,
    "gn:feature_class":"P",
    "gn:feature_code":"PPL",
    "gn:name":"Rubeshibetsu",
    "gn:population":0,
    "gn:timezone":"Asia/Tokyo",
    "iso:country":"JP",
    "name:jpn_x_preferred":[
        "\u30eb\u30d9\u30b7\u30d9\u30c4"
    ],
    "name:jpn_x_variant":[
        "\u308b\u3079\u3057\u3079\u3064"
    ],
    "wof:name":"Rubeshibetsu",
    "wof:placetype":"locality"
},
  "geometry": {"coordinates":[143.33178999999996,42.20074],"type":"Point"}
}