{
  "type": "Feature",
  "properties": {
    "gn:admin1_code":"47.0",
    "gn:admin2_code":"1852456.0",
    "gn:admin3_code":"47358.0",
    "gn:asciiname":"Minato",
    "gn:country_code":"JP",
    "gn:dem":36,
    "gn:feature_class":"P",
    "gn:feature_code":"PPL",
    "gn:name":"Minato",
    "gn:population":0,
    "gn:timezone":"Asia/Tokyo",
    "iso:country":"JP",
    "name:deu_x_preferred":[
        "Minato"
    ],
    "name:fin_x_preferred":[
        "Minato"
    ],
    "name:fra_x_preferred":[
        "Minato"
    ],
    "name:ind_x_preferred":[
        "Minato"
    ],
    "name:ita_x_preferred":[
        "Minato"
    ],
    "name:jpn_x_preferred":[
        "\u6e2f"
    ],
    "name:jpn_x_variant":[
        "\u307f\u306a\u3068"
    ],
    "name:kor_x_preferred":[
        "\ubbf8\ub098\ud1a0"
    ],
    "name:mlg_x_preferred":[
        "Minato"
    ],
    "name:pol_x_preferred":[
        "Minato"
    ],
    "name:sco_x_preferred":[
        "Minato"
    ],
    "wof:name":"Minato",
    "wof:placetype":"locality"
},
  "geometry": {"coordinates":[131.28808000000001,25.95439],"type":"Point"}
}