{
  "type": "Feature",
  "properties": {
    "gn:admin1_code":"43",
    "gn:admin2_code":"1850706.0",
    "gn:asciiname":"Ono",
    "gn:country_code":"JP",
    "gn:dem":85,
    "gn:feature_class":"P",
    "gn:feature_code":"PPL",
    "gn:name":"Ono",
    "gn:population":0,
    "gn:timezone":"Asia/Tokyo",
    "iso:country":"JP",
    "wof:name":"Ono",
    "wof:placetype":"locality"
},
  "geometry": {"coordinates":[135.34999999999999,33.78333],"type":"Point"}
}