{
  "type": "Feature",
  "properties": {
    "gn:admin1_code":"43",
    "gn:admin2_code":"1850706.0",
    "gn:asciiname":"Ono",
    "gn:country_code":"JP",
    "gn:dem":85,
    "gn:feature_class":"P",
    "gn:feature_code":"PPL",
    "gn:name":"Ono",
    "gn:population":0,
    "gn:timezone":"Asia/Tokyo",
    "iso:country":"JP",
    "name:bul_x_preferred":[
        "\u041e\u043d\u043e"
    ],
    "name:cat_x_preferred":[
        "Ono"
    ],
    "name:ceb_x_preferred":[
        "Ono"
    ],
    "name:ces_x_preferred":[
        "Ono"
    ],
    "name:deu_x_preferred":[
        "Ono"
    ],
    "name:fra_x_preferred":[
        "Ono"
    ],
    "name:heb_x_preferred":[
        "\u05d0\u05d5\u05e0\u05d5"
    ],
    "name:nld_x_preferred":[
        "Ono"
    ],
    "name:pol_x_preferred":[
        "Ono"
    ],
    "name:por_x_preferred":[
        "Ono"
    ],
    "name:ron_x_preferred":[
        "Ono"
    ],
    "name:rus_x_preferred":[
        "\u041e\u043d\u043e"
    ],
    "name:swe_x_preferred":[
        "Ono"
    ],
    "name:ukr_x_preferred":[
        "\u041e\u043d\u043e"
    ],
    "name:vie_x_preferred":[
        "Ono"
    ],
    "wof:name":"Ono",
    "wof:placetype":"locality"
},
  "geometry": {"coordinates":[135.34999999999999,33.78333],"type":"Point"}
}