{
  "type": "Feature",
  "properties": {
    "gn:admin1_code":"4.0",
    "gn:admin2_code":"2112997.0",
    "gn:admin3_code":"12422.0",
    "gn:asciiname":"Myoka",
    "gn:country_code":"JP",
    "gn:dem":31,
    "gn:feature_class":"P",
    "gn:feature_code":"PPLL",
    "gn:name":"My\u014dka",
    "gn:population":0,
    "gn:timezone":"Asia/Tokyo",
    "iso:country":"JP",
    "name:jpn_x_preferred":[
        "\u5999\u4e0b"
    ],
    "name:jpn_x_variant":[
        "\u307f\u3087\u3046\u304b",
        "\u30df\u30e7\u30a6\u30ab"
    ],
    "name:und_x_variant":[
        "My\u014dka"
    ],
    "wof:name":"Myoka",
    "wof:placetype":"locality"
},
  "geometry": {"coordinates":[140.28030000000001,35.34067],"type":"Point"}
}