{
  "type": "Feature",
  "properties": {
    "gn:admin1_code":"22",
    "gn:admin2_code":"1857906.0",
    "gn:admin3_code":"26108.0",
    "gn:asciiname":"Shuzan",
    "gn:country_code":"JP",
    "gn:dem":244,
    "gn:feature_class":"P",
    "gn:feature_code":"PPL",
    "gn:name":"Sh\u016bzan",
    "gn:population":0,
    "gn:timezone":"Asia/Tokyo",
    "iso:country":"JP",
    "name:und_x_variant":[
        "Sh\u016bzan"
    ],
    "wof:name":"Shuzan",
    "wof:placetype":"locality"
},
  "geometry": {"coordinates":[135.63333,35.15],"type":"Point"}
}