{
  "type": "Feature",
  "properties": {
    "gn:admin1_code":"24.0",
    "gn:admin2_code":"2112574.0",
    "gn:asciiname":"Oyagawahama",
    "gn:country_code":"JP",
    "gn:dem":8,
    "gn:feature_class":"P",
    "gn:feature_code":"PPL",
    "gn:name":"\u014cyagawahama",
    "gn:population":0,
    "gn:timezone":"Asia/Tokyo",
    "iso:country":"JP",
    "name:jpn_x_preferred":[
        "\u5927\u8c37\u5ddd\u6d5c"
    ],
    "name:jpn_x_variant":[
        "\u304a\u304a\u3084\u304c\u308f\u306f\u307e",
        "\u30aa\u30aa\u30e4\u30ac\u30ef\u30cf\u30de"
    ],
    "name:und_x_variant":[
        "\u014cyagawahama"
    ],
    "wof:name":"Oyagawahama",
    "wof:placetype":"locality"
},
  "geometry": {"coordinates":[141.47959,38.37409],"type":"Point"}
}