{
  "type": "Feature",
  "properties": {
    "gn:admin1_code":"12.0",
    "gn:admin2_code":"7428089.0",
    "gn:admin3_code":"1631.0",
    "gn:asciiname":"Sumiyoshi",
    "gn:country_code":"JP",
    "gn:dem":71,
    "gn:feature_class":"P",
    "gn:feature_code":"PPL",
    "gn:name":"Sumiyoshi",
    "gn:population":0,
    "gn:timezone":"Asia/Tokyo",
    "iso:country":"JP",
    "name:jpn_x_preferred":[
        "\u4f4f\u5409"
    ],
    "wof:name":"Sumiyoshi",
    "wof:placetype":"locality"
},
  "geometry": {"coordinates":[143.18053,42.98525],"type":"Point"}
}