{
  "type": "Feature",
  "properties": {
    "gn:admin1_code":"08",
    "gn:admin2_code":"2110958.0",
    "gn:asciiname":"Tategaoka",
    "gn:country_code":"JP",
    "gn:dem":270,
    "gn:feature_class":"P",
    "gn:feature_code":"PPL",
    "gn:name":"Tategaoka",
    "gn:population":0,
    "gn:timezone":"Asia/Tokyo",
    "iso:country":"JP",
    "name:jpn_x_preferred":[
        "\u8218\u30f6\u5ca1"
    ],
    "name:und_x_variant":[
        "Tadegaoka",
        "Tategaoka"
    ],
    "wof:name":"Tategaoka",
    "wof:placetype":"locality"
},
  "geometry": {"coordinates":[140.29844,37.33007],"type":"Point"}
}