{
  "type": "Feature",
  "properties": {
    "gn:admin1_code":"16.0",
    "gn:admin2_code":"2111005.0",
    "gn:admin3_code":"3321.0",
    "gn:asciiname":"Kumabayashi",
    "gn:country_code":"JP",
    "gn:dem":129,
    "gn:feature_class":"P",
    "gn:feature_code":"PPL",
    "gn:name":"Kumabayashi",
    "gn:population":0,
    "gn:timezone":"Asia/Tokyo",
    "iso:country":"JP",
    "name:jpn_x_preferred":[
        "\u718a\u6797"
    ],
    "name:jpn_x_variant":[
        "\u304f\u307e\u3070\u3084\u3057",
        "\u30af\u30de\u30d0\u30e4\u30b7"
    ],
    "wof:name":"Kumabayashi",
    "wof:placetype":"locality"
},
  "geometry": {"coordinates":[141.11453,39.51231],"type":"Point"}
}