{
  "type": "Feature",
  "properties": {
    "gn:admin1_code":"13.0",
    "gn:admin2_code":"1859755.0",
    "gn:admin3_code":"28301.0",
    "gn:asciiname":"Tamida",
    "gn:country_code":"JP",
    "gn:dem":232,
    "gn:feature_class":"P",
    "gn:feature_code":"PPL",
    "gn:name":"Tamida",
    "gn:population":0,
    "gn:timezone":"Asia/Tokyo",
    "iso:country":"JP",
    "name:jpn_x_preferred":[
        "\u6c11\u7530"
    ],
    "wof:name":"Tamida",
    "wof:placetype":"locality"
},
  "geometry": {"coordinates":[135.39723000000001,34.93384],"type":"Point"}
}