{
  "type": "Feature",
  "properties": {
    "gn:admin1_code":"47",
    "gn:admin2_code":"7415821.0",
    "gn:asciiname":"Katsuren-hama",
    "gn:country_code":"JP",
    "gn:dem":7,
    "gn:feature_class":"P",
    "gn:feature_code":"PPL",
    "gn:name":"Katsuren-hama",
    "gn:population":0,
    "gn:timezone":"Asia/Tokyo",
    "iso:country":"JP",
    "name:jpn_x_preferred":[
        "\u52dd\u9023\u6d5c"
    ],
    "name:und_x_variant":[
        "Bama",
        "Hama",
        "Katsuren-hama"
    ],
    "wof:name":"Katsuren-hama",
    "wof:placetype":"locality"
},
  "geometry": {"coordinates":[127.95282,26.32583],"type":"Point"}
}