{
  "type": "Feature",
  "properties": {
    "gn:admin1_code":"2.0",
    "gn:admin2_code":"2128783.0",
    "gn:asciiname":"Tamachi",
    "gn:country_code":"JP",
    "gn:dem":61,
    "gn:feature_class":"P",
    "gn:feature_code":"PPL",
    "gn:name":"Tamachi",
    "gn:population":0,
    "gn:timezone":"Asia/Tokyo",
    "iso:country":"JP",
    "name:jpn_x_preferred":[
        "\u7530\u753a"
    ],
    "name:jpn_x_variant":[
        "\u305f\u307e\u3061",
        "\u30bf\u30de\u30c1"
    ],
    "wof:name":"Tamachi",
    "wof:placetype":"locality"
},
  "geometry": {"coordinates":[140.55858000000001,40.27371],"type":"Point"}
}