{
  "type": "Feature",
  "properties": {
    "gn:admin1_code":"05",
    "gn:admin2_code":"1926135.0",
    "gn:asciiname":"Hashihama",
    "gn:cc2":"JP",
    "gn:country_code":"JP",
    "gn:dem":5,
    "gn:feature_class":"P",
    "gn:feature_code":"PPL",
    "gn:name":"Hashihama",
    "gn:population":0,
    "gn:timezone":"Asia/Tokyo",
    "iso:country":"JP",
    "name:und_x_variant":[
        "Hatomahama",
        "Hatoba-hama"
    ],
    "wof:name":"Hashihama",
    "wof:placetype":"locality"
},
  "geometry": {"coordinates":[132.96796000000001,34.10861],"type":"Point"}
}