{
  "type": "Feature",
  "properties": {
    "gn:admin1_code":"21.0",
    "gn:admin2_code":"1865358.0",
    "gn:asciiname":"Kofurue",
    "gn:country_code":"JP",
    "gn:dem":15,
    "gn:feature_class":"P",
    "gn:feature_code":"PPLL",
    "gn:name":"Kofurue",
    "gn:population":0,
    "gn:timezone":"Asia/Tokyo",
    "iso:country":"JP",
    "name:jpn_x_preferred":[
        "\u5c0f\u53e4\u6c5f"
    ],
    "name:jpn_x_variant":[
        "\u3053\u3075\u308b\u3048",
        "\u30b3\u30d5\u30eb\u30a8"
    ],
    "wof:name":"Kofurue",
    "wof:placetype":"locality"
},
  "geometry": {"coordinates":[130.07249999999999,32.28399],"type":"Point"}
}