{
  "type": "Feature",
  "properties": {
    "gn:admin1_code":"21.0",
    "gn:admin2_code":"7412709.0",
    "gn:admin3_code":"43348.0",
    "gn:asciiname":"Tsubaki",
    "gn:country_code":"JP",
    "gn:dem":412,
    "gn:feature_class":"P",
    "gn:feature_code":"PPLL",
    "gn:name":"Tsubaki",
    "gn:population":0,
    "gn:timezone":"Asia/Tokyo",
    "iso:country":"JP",
    "name:deu_x_preferred":[
        "Tsubaki"
    ],
    "name:ita_x_preferred":[
        "Tsubaki"
    ],
    "name:jpn_x_preferred":[
        "\u693f"
    ],
    "name:jpn_x_variant":[
        "\u3064\u3070\u304d",
        "\u30c4\u30d0\u30ad"
    ],
    "name:rus_x_preferred":[
        "\u0426\u0443\u0431\u0430\u043a\u0438"
    ],
    "name:spa_x_preferred":[
        "Tsubaki"
    ],
    "wof:name":"Tsubaki",
    "wof:placetype":"locality"
},
  "geometry": {"coordinates":[130.88573,32.59779],"type":"Point"}
}