{
  "type": "Feature",
  "properties": {
    "iso:country":"JP",
    "qs:name":"\u5c0f\u6e05\u6c34\u753a",
    "qs:name_adm0":"\u65e5\u672c",
    "qs:name_adm1":"\u5317\u6d77\u9053",
    "qs:photos":270,
    "qs:photos_1k":55,
    "qs:photos_9k":1,
    "qs:photos_9r":4,
    "qs:photos_all":270,
    "qs:photos_sr":5,
    "qs:placetype":"Town",
    "qs:pop_sr":"0",
    "wof:name":"\u5c0f\u6e05\u6c34\u753a",
    "wof:placetype":"locality"
},
  "geometry": {"coordinates":[144.44755499999999,43.931033],"type":"Point"}
}