{
  "type": "Feature",
  "properties": {
    "gn:admin1_code":"19",
    "gn:admin2_code":"1859635.0",
    "gn:admin3_code":"14131.0",
    "gn:asciiname":"Ogimachi",
    "gn:country_code":"JP",
    "gn:dem":4,
    "gn:feature_class":"P",
    "gn:feature_code":"PPL",
    "gn:name":"\u014cgimachi",
    "gn:population":0,
    "gn:timezone":"Asia/Tokyo",
    "iso:country":"JP",
    "name:jpn_x_preferred":[
        "\u6247\u753a"
    ],
    "name:und_x_variant":[
        "Ogicho",
        "\u014cgimachi"
    ],
    "wof:name":"Ogimachi",
    "wof:placetype":"locality"
},
  "geometry": {"coordinates":[139.72621000000001,35.50519],"type":"Point"}
}