{
  "type": "Feature",
  "properties": {
    "gn:admin1_code":"26",
    "gn:admin2_code":"1856209.0",
    "gn:asciiname":"Yoshida",
    "gn:country_code":"JP",
    "gn:dem":374,
    "gn:feature_class":"P",
    "gn:feature_code":"PPL",
    "gn:name":"Yoshida",
    "gn:population":0,
    "gn:timezone":"Asia/Tokyo",
    "iso:country":"JP",
    "name:jpn_x_preferred":[
        "\u5409\u7530"
    ],
    "wof:name":"Yoshida",
    "wof:placetype":"locality"
},
  "geometry": {"coordinates":[138.21666999999999,36.66667],"type":"Point"}
}