{
  "type": "Feature",
  "properties": {
    "iso:country":"JP",
    "name:eng_x_preferred":[
        "Tokai 3 Chome"
    ],
    "name:eng_x_variant":[
        "Toukai 3 Choume",
        "Tokai 3 Chome"
    ],
    "name:jpn_x_preferred":[
        "\uff13\u4e01\u76ee"
    ],
    "name:jpn_x_variant":[
        "\u3068\u3046\u304b\u3044 \uff13\u3061\u3087\u3046\u3081",
        "\u6771\u6d77 \uff13\u4e01\u76ee",
        "\uff13\u3061\u3087\u3046\u3081"
    ],
    "qs:gn_adm0_cc":"JP",
    "qs:gn_local":1850147,
    "qs:local_max":18112,
    "qs:local_sum":895907,
    "qs:localhoods":857,
    "qs:name":"\uff13\u4e01\u76ee",
    "qs:name_adm0":"\u65e5\u672c",
    "qs:name_adm1":"\u6771\u4eac\u90fd",
    "qs:name_adm2":"\u5927\u7530\u533a",
    "qs:name_en":"Tokai 3 Chome",
    "qs:name_lau":"\u6771\u6d77",
    "qs:name_local":"\u6771\u4eac",
    "qs:photo_max":140,
    "qs:photo_sum":211,
    "qs:placetype":"Suburb",
    "qs:quad_count":10,
    "qs:woe_adm0":23424856,
    "qs:woe_adm1":2345889,
    "qs:woe_adm2":15015506,
    "qs:woe_lau":28414303,
    "qs:woe_local":1118370,
    "qs:woe_ver":"7.10.0",
    "wof:lang":[
        "jpn"
    ],
    "wof:name":"\uff13\u4e01\u76ee",
    "wof:placetype":"neighbourhood"
},
  "geometry": {"coordinates":[139.75984199999999,35.583923],"type":"Point"}
}