{
  "type": "Feature",
  "properties": {
    "gn:admin1_code":"13",
    "gn:admin2_code":"7370819.0",
    "gn:asciiname":"Ikuha",
    "gn:country_code":"JP",
    "gn:dem":23,
    "gn:feature_class":"P",
    "gn:feature_code":"PPL",
    "gn:name":"Ikuha",
    "gn:population":0,
    "gn:timezone":"Asia/Tokyo",
    "iso:country":"JP",
    "name:jpn_x_preferred":[
        "\u80b2\u6ce2"
    ],
    "name:und_x_variant":[
        "Ikuwa",
        "Ikuha"
    ],
    "wof:name":"Ikuha",
    "wof:placetype":"locality"
},
  "geometry": {"coordinates":[134.89153999999999,34.52608],"type":"Point"}
}