{
  "type": "Feature",
  "properties": {
    "gn:admin1_code":"19.0",
    "gn:admin2_code":"1848350.0",
    "gn:admin3_code":"14104.0",
    "gn:asciiname":"Wakabacho",
    "gn:country_code":"JP",
    "gn:dem":4,
    "gn:feature_class":"P",
    "gn:feature_code":"PPL",
    "gn:name":"Wakabach\u014d",
    "gn:population":0,
    "gn:timezone":"Asia/Tokyo",
    "iso:country":"JP",
    "name:jpn_x_preferred":[
        "\u82e5\u8449\u753a"
    ],
    "name:jpn_x_variant":[
        "\u308f\u304b\u3070\u3061\u3087\u3046",
        "\u30ef\u30ab\u30d0\u30c1\u30e7\u30a6"
    ],
    "name:und_x_variant":[
        "Wakabach\u014d"
    ],
    "wof:name":"Wakabacho",
    "wof:placetype":"locality"
},
  "geometry": {"coordinates":[139.62814,35.44226],"type":"Point"}
}