{
  "type": "Feature",
  "properties": {
    "gn:admin1_code":"28.0",
    "gn:admin2_code":"1848164.0",
    "gn:admin3_code":"29452.0",
    "gn:asciiname":"Hitoji",
    "gn:country_code":"JP",
    "gn:dem":384,
    "gn:feature_class":"P",
    "gn:feature_code":"PPL",
    "gn:name":"Hitoji",
    "gn:population":0,
    "gn:timezone":"Asia/Tokyo",
    "iso:country":"JP",
    "name:jpn_x_preferred":[
        "\u4eba\u77e5"
    ],
    "wof:name":"Hitoji",
    "wof:placetype":"locality"
},
  "geometry": {"coordinates":[135.96969000000001,34.32976],"type":"Point"}
}