{
  "type": "Feature",
  "properties": {
    "iso:country":"JP",
    "name:eng_x_preferred":[
        "Irabu Azaikemazoe"
    ],
    "name:eng_x_variant":[
        "Irabu Irabu Azaikemazoe",
        "Irabu Azaikemazoe"
    ],
    "name:jpn_x_preferred":[
        "\u5b57\u6c60\u9593\u6dfb"
    ],
    "name:jpn_x_variant":[
        "\u3042\u3056\u3044\u3051\u307e\u305e\u3048",
        "\u3044\u3089\u3076 \u3042\u3056\u3044\u3051\u307e\u305e\u3048",
        "\u4f0a\u826f\u90e8 \u5b57\u6c60\u9593\u6dfb"
    ],
    "qs:gn_local":0,
    "qs:local_max":975,
    "qs:local_sum":3712,
    "qs:localhoods":19,
    "qs:name":"\u5b57\u6c60\u9593\u6dfb",
    "qs:name_adm0":"\u65e5\u672c",
    "qs:name_adm1":"\u6c96\u7e04\u770c",
    "qs:name_en":"Irabu Azaikemazoe",
    "qs:name_lau":"\u4f0a\u826f\u90e8",
    "qs:name_local":"\u5bae\u53e4\u5cf6\u5e02",
    "qs:photo_max":88,
    "qs:photo_sum":112,
    "qs:placetype":"Suburb",
    "qs:quad_count":9,
    "qs:woe_adm0":23424856,
    "qs:woe_adm1":2345896,
    "qs:woe_adm2":0,
    "qs:woe_lau":1109533,
    "qs:woe_local":28379331,
    "qs:woe_ver":"7.10.0",
    "wof:lang":[
        "jpn"
    ],
    "wof:name":"\u5b57\u6c60\u9593\u6dfb",
    "wof:placetype":"neighbourhood"
},
  "geometry": {"coordinates":[125.21372100000001,24.837518],"type":"Point"}
}