{
  "type": "Feature",
  "properties": {
    "iso:country":"JP",
    "name:eng_x_preferred":[
        "Ichinomiya 4 Chome"
    ],
    "name:eng_x_variant":[
        "Ichinomiya 4 Choume",
        "Ichinomiya 4 Chome"
    ],
    "name:jpn_x_preferred":[
        "\uff14\u4e01\u76ee"
    ],
    "name:jpn_x_variant":[
        "\u3044\u3061\u306e\u307f\u3084 \uff14\u3061\u3087\u3046\u3081",
        "\u4e00\u4e4b\u5bae \uff14\u4e01\u76ee",
        "\uff14\u3061\u3087\u3046\u3081"
    ],
    "qs:gn_local":0,
    "qs:local_max":96,
    "qs:local_sum":161,
    "qs:localhoods":2,
    "qs:name":"\uff14\u4e01\u76ee",
    "qs:name_adm0":"\u65e5\u672c",
    "qs:name_adm1":"\u795e\u5948\u5ddd\u770c",
    "qs:name_adm2":"\u9ad8\u5ea7\u90e1",
    "qs:name_en":"Ichinomiya 4 Chome",
    "qs:name_lau":"\u4e00\u4e4b\u5bae",
    "qs:name_local":"\u5bd2\u5ddd\u753a",
    "qs:photo_max":81,
    "qs:photo_sum":96,
    "qs:placetype":"Suburb",
    "qs:quad_count":5,
    "qs:woe_adm0":23424856,
    "qs:woe_adm1":2345868,
    "qs:woe_adm2":24857808,
    "qs:woe_lau":28417402,
    "qs:woe_local":24722070,
    "qs:woe_ver":"7.10.0",
    "wof:lang":[
        "jpn"
    ],
    "wof:name":"\uff14\u4e01\u76ee",
    "wof:placetype":"neighbourhood"
},
  "geometry": {"coordinates":[139.38161600000001,35.372344],"type":"Point"}
}