{
  "type": "Feature",
  "properties": {
    "gn:admin1_code":"47",
    "gn:admin2_code":"7415819.0",
    "gn:asciiname":"Sawada",
    "gn:country_code":"JP",
    "gn:dem":8,
    "gn:feature_class":"P",
    "gn:feature_code":"PPL",
    "gn:name":"Sawada",
    "gn:population":0,
    "gn:timezone":"Asia/Tokyo",
    "iso:country":"JP",
    "name:jpn_x_preferred":[
        "\u4f50\u548c\u7530"
    ],
    "name:jpn_x_variant":[
        "\u3055\u308f\u3060"
    ],
    "name:und_x_variant":[
        "Saada",
        "Sawada"
    ],
    "wof:name":"Sawada",
    "wof:placetype":"locality"
},
  "geometry": {"coordinates":[125.16403,24.83754],"type":"Point"}
}