{
  "type": "Feature",
  "properties": {
    "gn:admin1_code":"2.0",
    "gn:admin2_code":"2128783.0",
    "gn:asciiname":"Koshigenai",
    "gn:country_code":"JP",
    "gn:dem":86,
    "gn:feature_class":"P",
    "gn:feature_code":"PPLL",
    "gn:name":"Koshigenai",
    "gn:population":0,
    "gn:timezone":"Asia/Tokyo",
    "iso:country":"JP",
    "name:jpn_x_preferred":[
        "\u5c0f\u8302\u5185"
    ],
    "name:jpn_x_variant":[
        "\u3053\u3057\u3052\u306a\u3044",
        "\u30b3\u30b7\u30b2\u30ca\u30a4"
    ],
    "wof:name":"Koshigenai",
    "wof:placetype":"locality"
},
  "geometry": {"coordinates":[140.60740000000001,40.28923],"type":"Point"}
}