{
  "type": "Feature",
  "properties": {
    "iso:country":"JP",
    "label:eng_x_preferred_longname":[
        "Yonabaru Town"
    ],
    "label:eng_x_preferred_placetype":[
        "town"
    ],
    "name:eng_x_preferred":[
        "Yonabaru"
    ],
    "name:eng_x_variant":[
        "Yonabaru Town"
    ],
    "name:jpn_x_preferred":[
        "\u4e0e\u90a3\u539f\u753a"
    ],
    "qs:name":"\u4e0e\u90a3\u539f\u753a",
    "qs:name_adm0":"\u65e5\u672c",
    "qs:name_adm1":"\u6c96\u7e04\u770c",
    "qs:photos":37,
    "qs:photos_1k":7,
    "qs:photos_9k":1,
    "qs:photos_9r":2,
    "qs:photos_all":37,
    "qs:photos_sr":2,
    "qs:placetype":"Town",
    "qs:pop_sr":"0",
    "wof:name":"Yonabaru",
    "wof:placetype":"locality"
},
  "geometry": {"coordinates":[127.75534,26.200519],"type":"Point"}
}