{
  "type": "Feature",
  "properties": {
    "gn:country":"JP",
    "gn:fcode":"PPL",
    "gn:population":29364,
    "iso:country":"JP",
    "name:ara_x_preferred":[
        "\u062a\u0648\u063a\u064a\u062a\u0633\u0648"
    ],
    "name:arz_x_preferred":[
        "\u062a\u0648\u062c\u064a\u062a\u0633\u0648"
    ],
    "name:ast_x_preferred":[
        "Togitsu"
    ],
    "name:cat_x_preferred":[
        "Togitsu"
    ],
    "name:ceb_x_preferred":[
        "Togitsu"
    ],
    "name:ces_x_preferred":[
        "Togicu"
    ],
    "name:deu_x_preferred":[
        "Togitsu"
    ],
    "name:eng_x_preferred":[
        "Togitsu"
    ],
    "name:fas_x_preferred":[
        "\u062a\u0648\u06af\u06cc\u062a\u0633\u0648"
    ],
    "name:fra_x_preferred":[
        "Togitsu"
    ],
    "name:gle_x_preferred":[
        "Togitsu"
    ],
    "name:ita_x_preferred":[
        "Togitsu"
    ],
    "name:jpn_x_preferred":[
        "\u6642\u6d25\u753a"
    ],
    "name:kor_x_preferred":[
        "\ub3c4\uae30\uc4f0 \uc815"
    ],
    "name:kor_x_variant":[
        "\ub3c4\uae30\uc4f0\uc815"
    ],
    "name:mlg_x_preferred":[
        "Togitsu"
    ],
    "name:msa_x_preferred":[
        "Togitsu"
    ],
    "name:mya_x_preferred":[
        "\u1010\u102d\u102f\u1002\u102d\u1006\u103d\u1010\u103a\u1019\u103c\u102d\u102f\u1037\u104a \u1014\u102c\u1002\u102b\u1006\u102c\u1000\u102e"
    ],
    "name:nld_x_preferred":[
        "Togitsu"
    ],
    "name:por_x_preferred":[
        "Togitsu"
    ],
    "name:rus_x_preferred":[
        "\u0422\u043e\u0433\u0438\u0446\u0443"
    ],
    "name:spa_x_preferred":[
        "Togitsu"
    ],
    "name:tgl_x_preferred":[
        "Togitsu"
    ],
    "name:tha_x_preferred":[
        "\u0e42\u0e17\u0e07\u0e34\u0e15\u0e2a\u0e36"
    ],
    "name:ukr_x_preferred":[
        "\u0422\u043e\u0491\u0456\u0446\u0443"
    ],
    "name:und_x_variant":[
        "Tokitsu"
    ],
    "name:zho_x_preferred":[
        "\u6642\u6d25\u753a"
    ],
    "qs:name":"Togitsu",
    "qs:photos_9r":0,
    "qs:photos_sr":0,
    "qs:pop_sr":"7",
    "wof:name":"Togitsu",
    "wof:placetype":"locality",
    "wof:population":29364
},
  "geometry": {"coordinates":[129.84999999999999,32.83333],"type":"Point"}
}