{
  "type": "Feature",
  "properties": {
    "gn:country":"JP",
    "gn:fcode":"PPL",
    "gn:pop":29364,
    "iso:country":"JP",
    "name:ara_x_preferred":[
        "\u062a\u0648\u063a\u064a\u062a\u0633\u0648"
    ],
    "name:chi_x_preferred":[
        "\u6642\u6d25\u753a"
    ],
    "name:dut_x_preferred":[
        "Togitsu"
    ],
    "name:eng_x_preferred":[
        "Togitsu"
    ],
    "name:fre_x_preferred":[
        "Togitsu"
    ],
    "name:ger_x_preferred":[
        "Togitsu"
    ],
    "name:ita_x_preferred":[
        "Togitsu"
    ],
    "name:jpn_x_preferred":[
        "\u6642\u6d25\u753a"
    ],
    "name:kor_x_preferred":[
        "\ub3c4\uae30\uc4f0 \uc815"
    ],
    "name:may_x_preferred":[
        "Togitsu"
    ],
    "name:por_x_preferred":[
        "Togitsu"
    ],
    "name:rus_x_preferred":[
        "\u0422\u043e\u0433\u0438\u0446\u0443"
    ],
    "name:spa_x_preferred":[
        "Togitsu"
    ],
    "name:tgl_x_preferred":[
        "Togitsu"
    ],
    "name:ukr_x_preferred":[
        "\u0422\u043e\u0491\u0456\u0446\u0443"
    ],
    "name:unk_x_variant":[
        "Tokitsu"
    ],
    "qs:name":"Togitsu",
    "qs:photos_9r":0,
    "qs:photos_sr":0,
    "qs:pop_sr":"7",
    "wof:name":"Togitsu",
    "wof:placetype":"locality",
    "wof:population":29364
},
  "geometry": {"coordinates":[129.84999999999999,32.83333],"type":"Point"}
}