{
  "type": "Feature",
  "properties": {
    "gn:admin1_code":"21",
    "gn:admin2_code":"1848443.0",
    "gn:admin3_code":"43468.0",
    "gn:asciiname":"Miyahara",
    "gn:country_code":"JP",
    "gn:dem":13,
    "gn:feature_class":"P",
    "gn:feature_code":"PPL",
    "gn:name":"Miyahara",
    "gn:population":0,
    "gn:timezone":"Asia/Tokyo",
    "iso:country":"JP",
    "name:jpn_x_preferred":[
        "\u5bae\u539f"
    ],
    "name:jpn_x_variant":[
        "\u307f\u3084\u306f\u3089",
        "\u30df\u30e4\u30cf\u30e9"
    ],
    "name:und_x_variant":[
        "Miyaharamura",
        "Miyanohara",
        "Miyanoharu",
        "Miyahara"
    ],
    "wof:name":"Miyahara",
    "wof:placetype":"locality"
},
  "geometry": {"coordinates":[130.67563000000001,32.55676],"type":"Point"}
}