{
  "type": "Feature",
  "properties": {
    "gn:admin1_code":"12.0",
    "gn:admin2_code":"2130449.0",
    "gn:asciiname":"Osatsu",
    "gn:country_code":"JP",
    "gn:dem":16,
    "gn:feature_class":"P",
    "gn:feature_code":"PPL",
    "gn:name":"Osatsu",
    "gn:population":0,
    "gn:timezone":"Asia/Tokyo",
    "iso:country":"JP",
    "name:jpn_x_preferred":[
        "\u9577\u90fd"
    ],
    "wof:name":"Osatsu",
    "wof:placetype":"locality"
},
  "geometry": {"coordinates":[141.63123000000004,42.8697],"type":"Point"}
}