{
  "type": "Feature",
  "properties": {
    "gn:admin1_code":"40.0",
    "gn:admin2_code":"1852140.0",
    "gn:asciiname":"Ebara",
    "gn:country_code":"JP",
    "gn:dem":28,
    "gn:feature_class":"P",
    "gn:feature_code":"PPL",
    "gn:name":"Ebara",
    "gn:population":0,
    "gn:timezone":"Asia/Tokyo",
    "iso:country":"JP",
    "name:jpn_x_preferred":[
        "\u834f\u539f"
    ],
    "wof:name":"Ebara",
    "wof:placetype":"locality"
},
  "geometry": {"coordinates":[139.70314999999999,35.61298],"type":"Point"}
}