{
  "type": "Feature",
  "properties": {
    "gn:admin1_code":"16.0",
    "gn:admin2_code":"2129400.0",
    "gn:admin3_code":"3507.0",
    "gn:asciiname":"Yagi",
    "gn:country_code":"JP",
    "gn:dem":18,
    "gn:feature_class":"P",
    "gn:feature_code":"PPL",
    "gn:name":"Yagi",
    "gn:population":0,
    "gn:timezone":"Asia/Tokyo",
    "iso:country":"JP",
    "name:deu_x_preferred":[
        "Yagi"
    ],
    "name:fra_x_preferred":[
        "Yagi"
    ],
    "name:ita_x_preferred":[
        "Yagi"
    ],
    "name:nld_x_preferred":[
        "Yagi"
    ],
    "name:nor_x_preferred":[
        "Yagi"
    ],
    "wof:name":"Yagi",
    "wof:placetype":"locality"
},
  "geometry": {"coordinates":[141.76107999999999,40.34946],"type":"Point"}
}