{
  "type": "Feature",
  "properties": {
    "iso:country":"JP",
    "name:eng_x_preferred":[
        "Kyowacho 2 Chome"
    ],
    "name:eng_x_variant":[
        "Kyouwachou 2 Choume",
        "Kyowacho 2 Chome"
    ],
    "name:jpn_x_preferred":[
        "\uff12\u4e01\u76ee"
    ],
    "name:jpn_x_variant":[
        "\u304d\u3087\u3046\u308f\u3061\u3087\u3046 \uff12\u3061\u3087\u3046\u3081",
        "\u5171\u548c\u753a \uff12\u4e01\u76ee",
        "\uff12\u3061\u3087\u3046\u3081"
    ],
    "qs:gn_local":0,
    "qs:local_max":65,
    "qs:local_sum":69,
    "qs:localhoods":2,
    "qs:name":"\uff12\u4e01\u76ee",
    "qs:name_adm0":"\u65e5\u672c",
    "qs:name_adm1":"\u611b\u77e5\u770c",
    "qs:name_en":"Kyowacho 2 Chome",
    "qs:name_lau":"\u5171\u548c\u753a\uff08\u3012474-0061\uff09",
    "qs:name_local":"\u5927\u5e9c\u5e02",
    "qs:photo_max":41,
    "qs:photo_sum":65,
    "qs:placetype":"Suburb",
    "qs:quad_count":4,
    "qs:woe_adm0":23424856,
    "qs:woe_adm1":2345851,
    "qs:woe_adm2":0,
    "qs:woe_lau":28444423,
    "qs:woe_local":1113195,
    "qs:woe_ver":"7.10.0",
    "wof:lang":[
        "jpn"
    ],
    "wof:name":"\uff12\u4e01\u76ee",
    "wof:placetype":"neighbourhood"
},
  "geometry": {"coordinates":[136.95311599999999,35.035635],"type":"Point"}
}