{
  "type": "Feature",
  "properties": {
    "gn:admin1_code":"43.0",
    "gn:admin2_code":"1865123.0",
    "gn:admin3_code":"30366.0",
    "gn:asciiname":"Kuromatsu",
    "gn:country_code":"JP",
    "gn:dem":376,
    "gn:feature_class":"P",
    "gn:feature_code":"PPL",
    "gn:name":"Kuromatsu",
    "gn:population":0,
    "gn:timezone":"Asia/Tokyo",
    "iso:country":"JP",
    "name:jpn_x_preferred":[
        "\u9ed2\u677e"
    ],
    "wof:name":"Kuromatsu",
    "wof:placetype":"locality"
},
  "geometry": {"coordinates":[135.26048,34.09395],"type":"Point"}
}