{
  "type": "Feature",
  "properties": {
    "gn:admin1_code":"34.0",
    "gn:admin2_code":"1859726.0",
    "gn:asciiname":"Koyajima",
    "gn:country_code":"JP",
    "gn:dem":10,
    "gn:feature_class":"P",
    "gn:feature_code":"PPLL",
    "gn:name":"Koyajima",
    "gn:population":0,
    "gn:timezone":"Asia/Tokyo",
    "iso:country":"JP",
    "name:jpn_x_preferred":[
        "\u5c0f\u8c37\u5cf6"
    ],
    "name:jpn_x_variant":[
        "\u3053\u3084\u3058\u307e",
        "\u30b3\u30e4\u30b8\u30de"
    ],
    "wof:name":"Koyajima",
    "wof:placetype":"locality"
},
  "geometry": {"coordinates":[139.70538999999999,35.84636],"type":"Point"}
}