{
  "type": "Feature",
  "properties": {
    "gn:admin1_code":"21.0",
    "gn:admin2_code":"1848441.0",
    "gn:asciiname":"Futami-suguchimachi",
    "gn:country_code":"JP",
    "gn:dem":86,
    "gn:feature_class":"P",
    "gn:feature_code":"PPL",
    "gn:name":"Futami-suguchimachi",
    "gn:population":0,
    "gn:timezone":"Asia/Tokyo",
    "iso:country":"JP",
    "name:jpn_x_preferred":[
        "\u4e8c\u898b\u6d32\u53e3\u753a"
    ],
    "wof:name":"Futami-suguchimachi",
    "wof:placetype":"locality"
},
  "geometry": {"coordinates":[130.55338999999998,32.41846],"type":"Point"}
}