{
  "type": "Feature",
  "properties": {
    "gn:admin1_code":"21.0",
    "gn:admin2_code":"1864975.0",
    "gn:admin3_code":"43433.0",
    "gn:asciiname":"Ideshita",
    "gn:country_code":"JP",
    "gn:dem":398,
    "gn:feature_class":"P",
    "gn:feature_code":"PPLL",
    "gn:name":"Ideshita",
    "gn:population":0,
    "gn:timezone":"Asia/Tokyo",
    "iso:country":"JP",
    "name:jpn_x_preferred":[
        "\u4e95\u624b\u4e0b"
    ],
    "name:jpn_x_variant":[
        "\u3044\u3067\u3057\u305f",
        "\u30a4\u30c7\u30b7\u30bf"
    ],
    "wof:name":"Ideshita",
    "wof:placetype":"locality"
},
  "geometry": {"coordinates":[131.03923999999998,32.82285],"type":"Point"}
}