{
  "type": "Feature",
  "properties": {
    "gn:admin1_code":"46.0",
    "gn:admin2_code":"1857168.0",
    "gn:admin3_code":"19366.0",
    "gn:asciiname":"Juku",
    "gn:country_code":"JP",
    "gn:dem":103,
    "gn:feature_class":"P",
    "gn:feature_code":"PPLL",
    "gn:name":"Juku",
    "gn:population":0,
    "gn:timezone":"Asia/Tokyo",
    "iso:country":"JP",
    "name:deu_x_preferred":[
        "Juku"
    ],
    "name:fra_x_preferred":[
        "Juku"
    ],
    "name:jpn_x_preferred":[
        "\u5bbf"
    ],
    "name:jpn_x_variant":[
        "\u5b66\u7fd2\u587e"
    ],
    "name:kor_x_preferred":[
        "\ud559\uc2b5\uc219"
    ],
    "wof:name":"Juku",
    "wof:placetype":"locality"
},
  "geometry": {"coordinates":[138.51605000000001,35.22013],"type":"Point"}
}