{
  "type": "Feature",
  "properties": {
    "gn:admin1_code":"3.0",
    "gn:admin2_code":"7439944.0",
    "gn:asciiname":"Kizukuri-shimofukuhara",
    "gn:country_code":"JP",
    "gn:dem":6,
    "gn:feature_class":"P",
    "gn:feature_code":"PPL",
    "gn:name":"Kizukuri-shimofukuhara",
    "gn:population":0,
    "gn:timezone":"Asia/Tokyo",
    "iso:country":"JP",
    "name:jpn_x_preferred":[
        "\u6728\u9020\u4e0b\u798f\u539f"
    ],
    "name:jpn_x_variant":[
        "\u304d\u3065\u304f\u308a\u3057\u3082\u3075\u304f\u306f\u3089",
        "\u30ad\u30c5\u30af\u30ea\u30b7\u30e2\u30d5\u30af\u30cf\u30e9"
    ],
    "wof:name":"Kizukuri-shimofukuhara",
    "wof:placetype":"locality"
},
  "geometry": {"coordinates":[140.32534999999999,40.79749],"type":"Point"}
}