{
  "type": "Feature",
  "properties": {
    "gn:admin1_code":"18.0",
    "gn:admin2_code":"1860823.0",
    "gn:asciiname":"Fumoto",
    "gn:country_code":"JP",
    "gn:dem":28,
    "gn:feature_class":"P",
    "gn:feature_code":"PPLL",
    "gn:name":"Fumoto",
    "gn:population":0,
    "gn:timezone":"Asia/Tokyo",
    "iso:country":"JP",
    "name:jpn_x_preferred":[
        "\u9e93"
    ],
    "wof:name":"Fumoto",
    "wof:placetype":"locality"
},
  "geometry": {"coordinates":[130.54013,31.37473],"type":"Point"}
}