{
  "type": "Feature",
  "properties": {
    "gn:admin1_code":"3.0",
    "gn:admin2_code":"2129393.0",
    "gn:asciiname":"Aonisawa",
    "gn:country_code":"JP",
    "gn:dem":444,
    "gn:feature_class":"P",
    "gn:feature_code":"PPL",
    "gn:name":"Aonisawa",
    "gn:population":0,
    "gn:timezone":"Asia/Tokyo",
    "iso:country":"JP",
    "name:jpn_x_preferred":[
        "\u9752\u8377\u6ca2"
    ],
    "name:jpn_x_variant":[
        "\u3042\u304a\u306b\u3055\u308f",
        "\u30a2\u30aa\u30cb\u30b5\u30ef"
    ],
    "wof:name":"Aonisawa",
    "wof:placetype":"locality"
},
  "geometry": {"coordinates":[140.72603000000001,40.55513],"type":"Point"}
}