{
  "type": "Feature",
  "properties": {
    "gn:admin1_code":"14.0",
    "gn:admin2_code":"9072668.0",
    "gn:admin3_code":"8564.0",
    "gn:asciiname":"Fukawa",
    "gn:country_code":"JP",
    "gn:dem":8,
    "gn:feature_class":"P",
    "gn:feature_code":"PPL",
    "gn:name":"Fukawa",
    "gn:population":0,
    "gn:timezone":"Asia/Tokyo",
    "iso:country":"JP",
    "wof:name":"Fukawa",
    "wof:placetype":"locality"
},
  "geometry": {"coordinates":[140.15000000000001,35.85],"type":"Point"}
}