{
  "type": "Feature",
  "properties": {
    "gn:admin1_code":"19",
    "gn:admin2_code":"1854744.0",
    "gn:asciiname":"Kamisoga",
    "gn:country_code":"JP",
    "gn:dem":45,
    "gn:feature_class":"P",
    "gn:feature_code":"PPL",
    "gn:name":"Kamisoga",
    "gn:population":0,
    "gn:timezone":"Asia/Tokyo",
    "iso:country":"JP",
    "name:jpn_x_preferred":[
        "\u4e0a\u66fd\u6211"
    ],
    "name:und_x_variant":[
        "Kami-soga"
    ],
    "wof:name":"Kamisoga",
    "wof:placetype":"locality"
},
  "geometry": {"coordinates":[139.17819,35.31197],"type":"Point"}
}