{
  "type": "Feature",
  "properties": {
    "gn:admin1_code":"24.0",
    "gn:admin2_code":"7447001.0",
    "gn:asciiname":"Kanpuzawa",
    "gn:country_code":"JP",
    "gn:dem":291,
    "gn:feature_class":"P",
    "gn:feature_code":"PPL",
    "gn:name":"Kanp\u016bzawa",
    "gn:population":0,
    "gn:timezone":"Asia/Tokyo",
    "iso:country":"JP",
    "name:jpn_x_preferred":[
        "\u5bd2\u98a8\u6ca2"
    ],
    "name:jpn_x_variant":[
        "\u304b\u3093\u3077\u3046\u3056\u308f",
        "\u30ab\u30f3\u30d7\u30a6\u30b6\u30ef"
    ],
    "name:und_x_variant":[
        "Kanp\u016bzawa"
    ],
    "wof:name":"Kanpuzawa",
    "wof:placetype":"locality"
},
  "geometry": {"coordinates":[140.68848,38.78441],"type":"Point"}
}