{
  "type": "Feature",
  "properties": {
    "gn:admin1_code":"12.0",
    "gn:admin2_code":"7428109.0",
    "gn:admin3_code":"1668.0",
    "gn:asciiname":"Shimowatenbetsu",
    "gn:country_code":"JP",
    "gn:dem":8,
    "gn:feature_class":"P",
    "gn:feature_code":"PPLL",
    "gn:name":"Shimowatenbetsu",
    "gn:population":0,
    "gn:timezone":"Asia/Tokyo",
    "iso:country":"JP",
    "name:jpn_x_preferred":[
        "\u4e0b\u548c\u5929\u5225"
    ],
    "name:jpn_x_variant":[
        "\u3057\u3082\u308f\u3066\u3093\u3079\u3064",
        "\u30b7\u30e2\u30ef\u30c6\u30f3\u30d9\u30c4"
    ],
    "wof:name":"Shimowatenbetsu",
    "wof:placetype":"locality"
},
  "geometry": {"coordinates":[144.02923999999999,42.9636],"type":"Point"}
}