{
  "type": "Feature",
  "properties": {
    "iso:country":"JP",
    "name:eng_x_preferred":[
        "Makomanaisaiwaimachi 3 Chome"
    ],
    "name:eng_x_variant":[
        "Makomanaisaiwaimachi 3 Choume",
        "Makomanaisaiwaimachi 3 Chome"
    ],
    "name:jpn_x_preferred":[
        "\uff13\u4e01\u76ee"
    ],
    "name:jpn_x_variant":[
        "\u307e\u3053\u307e\u306a\u3044\u3055\u3044\u308f\u3044\u307e\u3061 \uff13\u3061\u3087\u3046\u3081",
        "\u771f\u99d2\u5185\u5e78\u753a \uff13\u4e01\u76ee",
        "\uff13\u3061\u3087\u3046\u3081"
    ],
    "qs:gn_local":0,
    "qs:local_max":2554,
    "qs:local_sum":22076,
    "qs:localhoods":97,
    "qs:name":"\uff13\u4e01\u76ee",
    "qs:name_adm0":"\u65e5\u672c",
    "qs:name_adm1":"\u5317\u6d77\u9053",
    "qs:name_adm2":"\u5357\u533a",
    "qs:name_en":"Makomanaisaiwaimachi 3 Chome",
    "qs:name_lau":"\u771f\u99d2\u5185\u5e78\u753a",
    "qs:name_local":"\u672d\u5e4c\u5e02",
    "qs:photo_max":21,
    "qs:photo_sum":40,
    "qs:placetype":"Suburb",
    "qs:quad_count":3,
    "qs:woe_adm0":23424856,
    "qs:woe_adm1":7153351,
    "qs:woe_adm2":1111800,
    "qs:woe_lau":28379903,
    "qs:woe_local":1118108,
    "qs:woe_ver":"7.10.0",
    "wof:lang":[
        "jpn"
    ],
    "wof:name":"\uff13\u4e01\u76ee",
    "wof:placetype":"neighbourhood"
},
  "geometry": {"coordinates":[141.35819599999999,42.991537],"type":"Point"}
}