{
  "type": "Feature",
  "properties": {
    "gn:admin1_code":"7.0",
    "gn:admin2_code":"7407416.0",
    "gn:asciiname":"Kano",
    "gn:country_code":"JP",
    "gn:dem":43,
    "gn:feature_class":"P",
    "gn:feature_code":"PPL",
    "gn:name":"Kan\u014d",
    "gn:population":0,
    "gn:timezone":"Asia/Tokyo",
    "iso:country":"JP",
    "name:jpn_x_preferred":[
        "\u91d1\u751f"
    ],
    "name:und_x_variant":[
        "Kan\u014d"
    ],
    "wof:name":"Kano",
    "wof:placetype":"locality"
},
  "geometry": {"coordinates":[130.62416000000002,33.7172],"type":"Point"}
}