{
  "type": "Feature",
  "properties": {
    "gn:admin1_code":"21.0",
    "gn:admin2_code":"1858418.0",
    "gn:admin3_code":"43101.0",
    "gn:asciiname":"Obiyama",
    "gn:country_code":"JP",
    "gn:dem":35,
    "gn:feature_class":"P",
    "gn:feature_code":"PPL",
    "gn:name":"Obiyama",
    "gn:population":0,
    "gn:timezone":"Asia/Tokyo",
    "iso:country":"JP",
    "name:jpn_x_preferred":[
        "\u5e2f\u5c71"
    ],
    "name:jpn_x_variant":[
        "\u304a\u3073\u3084\u307e",
        "\u30aa\u30d3\u30e4\u30de"
    ],
    "wof:name":"Obiyama",
    "wof:placetype":"locality"
},
  "geometry": {"coordinates":[130.74780000000001,32.80164],"type":"Point"}
}