{
  "type": "Feature",
  "properties": {
    "gn:admin1_code":"4.0",
    "gn:admin2_code":"2112663.0",
    "gn:asciiname":"Kozaka",
    "gn:country_code":"JP",
    "gn:dem":49,
    "gn:feature_class":"P",
    "gn:feature_code":"PPL",
    "gn:name":"K\u014dzaka",
    "gn:population":0,
    "gn:timezone":"Asia/Tokyo",
    "iso:country":"JP",
    "name:jpn_x_preferred":[
        "\u9ad8\u5742"
    ],
    "name:jpn_x_variant":[
        "\u3053\u3046\u3056\u304b",
        "\u30b3\u30a6\u30b6\u30ab"
    ],
    "name:und_x_variant":[
        "K\u014dzaka"
    ],
    "wof:name":"Kozaka",
    "wof:placetype":"locality"
},
  "geometry": {"coordinates":[140.10959,35.45079000000001],"type":"Point"}
}