{
  "type": "Feature",
  "properties": {
    "gn:admin1_code":"21.0",
    "gn:admin2_code":"1848441.0",
    "gn:asciiname":"Kagamimachi-shimoarisa",
    "gn:country_code":"JP",
    "gn:dem":5,
    "gn:feature_class":"P",
    "gn:feature_code":"PPL",
    "gn:name":"Kagamimachi-shimoarisa",
    "gn:population":0,
    "gn:timezone":"Asia/Tokyo",
    "iso:country":"JP",
    "name:jpn_x_preferred":[
        "\u93e1\u753a\u4e0b\u6709\u4f50"
    ],
    "name:jpn_x_variant":[
        "\u304b\u304c\u307f\u307e\u3061\u3057\u3082\u3042\u308a\u3055",
        "\u30ab\u30ac\u30df\u30de\u30c1\u30b7\u30e2\u30a2\u30ea\u30b5"
    ],
    "wof:name":"Kagamimachi-shimoarisa",
    "wof:placetype":"locality"
},
  "geometry": {"coordinates":[130.66738000000001,32.56341],"type":"Point"}
}