{
  "type": "Feature",
  "properties": {
    "gn:admin1_code":"29.0",
    "gn:admin2_code":"7468177.0",
    "gn:asciiname":"Shimosukebuchi",
    "gn:country_code":"JP",
    "gn:dem":4,
    "gn:feature_class":"P",
    "gn:feature_code":"PPL",
    "gn:name":"Shimosukebuchi",
    "gn:population":0,
    "gn:timezone":"Asia/Tokyo",
    "iso:country":"JP",
    "name:jpn_x_preferred":[
        "\u4e0b\u52a9\u6e15"
    ],
    "wof:name":"Shimosukebuchi",
    "wof:placetype":"locality"
},
  "geometry": {"coordinates":[139.46815000000001,38.19781],"type":"Point"}
}