{
  "type": "Feature",
  "properties": {
    "iso:country":"JP",
    "name:eng_x_preferred":[
        "Tamako 4 Chome"
    ],
    "name:eng_x_variant":[
        "Tamako 4 Choume",
        "Tamako 4 Chome"
    ],
    "name:jpn_x_preferred":[
        "\uff14\u4e01\u76ee"
    ],
    "name:jpn_x_variant":[
        "\u305f\u307e\u3053 \uff14\u3061\u3087\u3046\u3081",
        "\u591a\u6469\u6e56 \uff14\u4e01\u76ee",
        "\uff14\u3061\u3087\u3046\u3081"
    ],
    "name:unk_x_variant":[
        "\uff14\u4e01\u76ee"
    ],
    "qs:gn_local":0,
    "qs:local_max":685,
    "qs:local_sum":818,
    "qs:localhoods":4,
    "qs:name":"\uff14\u4e01\u76ee",
    "qs:name_adm0":"\u65e5\u672c",
    "qs:name_adm1":"\u6771\u4eac\u90fd",
    "qs:name_en":"Tamako 4 Chome",
    "qs:name_lau":"\u591a\u6469\u6e56",
    "qs:name_local":"\u6771\u5927\u548c\u5e02",
    "qs:photo_max":7,
    "qs:photo_sum":11,
    "qs:placetype":"Suburb",
    "qs:quad_count":2,
    "qs:woe_adm0":23424856,
    "qs:woe_adm1":2345889,
    "qs:woe_adm2":0,
    "qs:woe_lau":28415259,
    "qs:woe_local":15015475,
    "qs:woe_ver":"7.10.0",
    "wof:lang":[
        "jpn"
    ],
    "wof:name":"\uff14\u4e01\u76ee",
    "wof:placetype":"neighbourhood"
},
  "geometry": {"coordinates":[139.442688,35.757655],"type":"Point"}
}