{
  "type": "Feature",
  "properties": {
    "gn:admin1_code":"19.0",
    "gn:admin2_code":"1848350.0",
    "gn:admin3_code":"14114.0",
    "gn:asciiname":"Miyazawa",
    "gn:country_code":"JP",
    "gn:dem":65,
    "gn:feature_class":"P",
    "gn:feature_code":"PPL",
    "gn:name":"Miyazawa",
    "gn:population":0,
    "gn:timezone":"Asia/Tokyo",
    "iso:country":"JP",
    "name:jpn_x_preferred":[
        "\u5bae\u6ca2"
    ],
    "wof:name":"Miyazawa",
    "wof:placetype":"locality"
},
  "geometry": {"coordinates":[139.49167,35.45522000000001],"type":"Point"}
}