{
  "type": "Feature",
  "properties": {
    "gn:country":"JP",
    "gn:fcode":"ADM3",
    "gn:population":0,
    "iso:country":"JP",
    "name:eng_x_preferred":[
        "Oirase"
    ],
    "name:eng_x_variant":[
        "Oirase Ch\u014d"
    ],
    "name:jpn_x_preferred":[
        "\u304a\u3044\u3089\u305b\u753a"
    ],
    "name:jpn_x_variant":[
        "\u304a\u3044\u3089\u305b\u3061\u3087\u3046",
        "\u30aa\u30a4\u30e9\u30bb\u30c1\u30e7\u30a6"
    ],
    "name:und_x_variant":[
        "Airase-ch\u014d"
    ],
    "qs:name":"Oirase Ch\u014d",
    "qs:photos_9r":0,
    "qs:photos_sr":0,
    "qs:pop_sr":"0",
    "wof:name":"Oirase",
    "wof:placetype":"localadmin",
    "wof:population":0
},
  "geometry": {"coordinates":[141.40196,40.6262],"type":"Point"}
}