{
  "type": "Feature",
  "properties": {
    "gn:admin1_code":"18",
    "gn:admin2_code":"7383991.0",
    "gn:asciiname":"Okuchi-yamano",
    "gn:country_code":"JP",
    "gn:dem":210,
    "gn:feature_class":"P",
    "gn:feature_code":"PPL",
    "gn:name":"\u014ckuchi-yamano",
    "gn:population":0,
    "gn:timezone":"Asia/Tokyo",
    "iso:country":"JP",
    "name:jpn_x_preferred":[
        "\u5927\u53e3\u5c71\u91ce"
    ],
    "name:jpn_x_variant":[
        "\u304a\u304a\u304f\u3061\u3084\u307e\u306e",
        "\u30aa\u30aa\u30af\u30c1\u30e4\u30de\u30ce"
    ],
    "name:und_x_variant":[
        "\u014ckuchi-yamano",
        "Yamano"
    ],
    "wof:name":"Okuchi-yamano",
    "wof:placetype":"locality"
},
  "geometry": {"coordinates":[130.57138,32.11091],"type":"Point"}
}