{
  "type": "Feature",
  "properties": {
    "gn:admin1_code":"7.0",
    "gn:admin2_code":"1854055.0",
    "gn:admin3_code":"40383.0",
    "gn:asciiname":"Togiri-yurino",
    "gn:country_code":"JP",
    "gn:dem":59,
    "gn:feature_class":"P",
    "gn:feature_code":"PPLL",
    "gn:name":"Togiri-yurino",
    "gn:population":0,
    "gn:timezone":"Asia/Tokyo",
    "iso:country":"JP",
    "name:jpn_x_preferred":[
        "\u6238\u5207\u767e\u5408\u91ce"
    ],
    "wof:name":"Togiri-yurino",
    "wof:placetype":"locality"
},
  "geometry": {"coordinates":[130.63817,33.82565],"type":"Point"}
}