{
  "type": "Feature",
  "properties": {
    "gn:admin1_code":"3.0",
    "gn:admin2_code":"2129525.0",
    "gn:admin3_code":"2387.0",
    "gn:asciiname":"Shitamae",
    "gn:country_code":"JP",
    "gn:dem":57,
    "gn:feature_class":"P",
    "gn:feature_code":"PPL",
    "gn:name":"Shitamae",
    "gn:population":0,
    "gn:timezone":"Asia/Tokyo",
    "iso:country":"JP",
    "name:jpn_x_preferred":[
        "\u4e0b\u524d"
    ],
    "name:jpn_x_variant":[
        "\u3057\u305f\u307e\u3048",
        "\u30b7\u30bf\u30de\u30a8"
    ],
    "name:und_x_variant":[
        "Shitamai",
        "Shitamae"
    ],
    "wof:name":"Shitamae",
    "wof:placetype":"locality"
},
  "geometry": {"coordinates":[140.27311,41.12464],"type":"Point"}
}