{
  "type": "Feature",
  "properties": {
    "gn:admin1_code":"43.0",
    "gn:admin2_code":"1860774.0",
    "gn:admin3_code":"30304.0",
    "gn:asciiname":"Kebarashimo",
    "gn:country_code":"JP",
    "gn:dem":300,
    "gn:feature_class":"P",
    "gn:feature_code":"PPL",
    "gn:name":"Kebarashimo",
    "gn:population":0,
    "gn:timezone":"Asia/Tokyo",
    "iso:country":"JP",
    "name:jpn_x_preferred":[
        "\u6bdb\u539f\u4e0b"
    ],
    "wof:name":"Kebarashimo",
    "wof:placetype":"locality"
},
  "geometry": {"coordinates":[135.43822,34.1406],"type":"Point"}
}