{
  "type": "Feature",
  "properties": {
    "gn:admin1_code":"34.0",
    "gn:admin2_code":"1861470.0",
    "gn:admin3_code":"11324.0",
    "gn:asciiname":"Miyamoto",
    "gn:country_code":"JP",
    "gn:dem":35,
    "gn:feature_class":"P",
    "gn:feature_code":"PPLL",
    "gn:name":"Miyamoto",
    "gn:population":0,
    "gn:timezone":"Asia/Tokyo",
    "iso:country":"JP",
    "name:jpn_x_preferred":[
        "\u5bae\u672c"
    ],
    "name:lav_x_preferred":[
        "Mijamoto"
    ],
    "wof:name":"Miyamoto",
    "wof:placetype":"locality"
},
  "geometry": {"coordinates":[139.51703000000001,35.84309000000001],"type":"Point"}
}