{
  "type": "Feature",
  "properties": {
    "gn:admin1_code":"21.0",
    "gn:admin2_code":"7412708.0",
    "gn:admin3_code":"43506.0",
    "gn:asciiname":"Kamisomeda",
    "gn:country_code":"JP",
    "gn:dem":191,
    "gn:feature_class":"P",
    "gn:feature_code":"PPL",
    "gn:name":"Kamisomeda",
    "gn:population":0,
    "gn:timezone":"Asia/Tokyo",
    "iso:country":"JP",
    "name:jpn_x_preferred":[
        "\u4e0a\u67d3\u7530"
    ],
    "name:jpn_x_variant":[
        "\u304b\u307f\u305d\u3081\u3060",
        "\u30ab\u30df\u30bd\u30e1\u30c0"
    ],
    "wof:name":"Kamisomeda",
    "wof:placetype":"locality"
},
  "geometry": {"coordinates":[130.98447999999999,32.2818],"type":"Point"}
}