{
  "type": "Feature",
  "properties": {
    "gn:admin1_code":"19.0",
    "gn:admin2_code":"1854744.0",
    "gn:asciiname":"Kayama",
    "gn:country_code":"JP",
    "gn:dem":29,
    "gn:feature_class":"P",
    "gn:feature_code":"PPL",
    "gn:name":"Kayama",
    "gn:population":0,
    "gn:timezone":"Asia/Tokyo",
    "iso:country":"JP",
    "name:jpn_x_preferred":[
        "\u6822\u5c71"
    ],
    "wof:name":"Kayama",
    "wof:placetype":"locality"
},
  "geometry": {"coordinates":[139.14072999999999,35.30551],"type":"Point"}
}