{
  "type": "Feature",
  "properties": {
    "gn:admin1_code":"21.0",
    "gn:admin2_code":"1858418.0",
    "gn:admin3_code":"43103.0",
    "gn:asciiname":"Yashima",
    "gn:country_code":"JP",
    "gn:dem":5,
    "gn:feature_class":"P",
    "gn:feature_code":"PPL",
    "gn:name":"Yashima",
    "gn:population":0,
    "gn:timezone":"Asia/Tokyo",
    "iso:country":"JP",
    "name:deu_x_preferred":[
        "Yashima"
    ],
    "name:ita_x_preferred":[
        "Yashima"
    ],
    "name:jpn_x_preferred":[
        "\u516b\u5cf6"
    ],
    "name:jpn_x_variant":[
        "\u3084\u3057\u307e",
        "\u30e4\u30b7\u30de"
    ],
    "name:rus_x_preferred":[
        "\u042f\u0441\u0438\u043c\u0430"
    ],
    "wof:name":"Yashima",
    "wof:placetype":"locality"
},
  "geometry": {"coordinates":[130.68203,32.77988],"type":"Point"}
}