{
  "type": "Feature",
  "properties": {
    "gn:admin1_code":"12.0",
    "gn:admin2_code":"7428121.0",
    "gn:admin3_code":"1581.0",
    "gn:asciiname":"Karumai",
    "gn:country_code":"JP",
    "gn:dem":24,
    "gn:feature_class":"P",
    "gn:feature_code":"PPL",
    "gn:name":"Karumai",
    "gn:population":0,
    "gn:timezone":"Asia/Tokyo",
    "iso:country":"JP",
    "name:jpn_x_preferred":[
        "\u8efd\u7c73"
    ],
    "wof:name":"Karumai",
    "wof:placetype":"locality"
},
  "geometry": {"coordinates":[141.90000000000001,42.66667],"type":"Point"}
}