{
  "type": "Feature",
  "properties": {
    "gn:admin1_code":"27",
    "gn:admin2_code":"7418810.0",
    "gn:asciiname":"Toyotamacho-kaiguchi",
    "gn:country_code":"JP",
    "gn:dem":39,
    "gn:feature_class":"P",
    "gn:feature_code":"PPL",
    "gn:name":"Toyotamach\u014d-kaiguchi",
    "gn:population":0,
    "gn:timezone":"Asia/Tokyo",
    "iso:country":"JP",
    "name:jpn_x_preferred":[
        "\u8c4a\u7389\u753a\u8c9d\u53e3"
    ],
    "name:und_x_variant":[
        "Kaiguti",
        "Kaiguchi",
        "Toyotamach\u014d-kaiguchi"
    ],
    "wof:name":"Toyotamacho-kaiguchi",
    "wof:placetype":"locality"
},
  "geometry": {"coordinates":[129.27866,34.36669000000001],"type":"Point"}
}