{
  "type": "Feature",
  "properties": {
    "gn:admin1_code":"21.0",
    "gn:admin2_code":"7412708.0",
    "gn:admin3_code":"43505.0",
    "gn:asciiname":"Yokobaba",
    "gn:country_code":"JP",
    "gn:dem":158,
    "gn:feature_class":"P",
    "gn:feature_code":"PPLL",
    "gn:name":"Yokobaba",
    "gn:population":0,
    "gn:timezone":"Asia/Tokyo",
    "iso:country":"JP",
    "name:jpn_x_preferred":[
        "\u6a2a\u99ac\u5834"
    ],
    "name:jpn_x_variant":[
        "\u3088\u3053\u3070\u3070",
        "\u30e8\u30b3\u30d0\u30d0"
    ],
    "wof:name":"Yokobaba",
    "wof:placetype":"locality"
},
  "geometry": {"coordinates":[130.93087,32.25778],"type":"Point"}
}