{
  "type": "Feature",
  "properties": {
    "gn:admin1_code":"27.0",
    "gn:admin2_code":"1857159.0",
    "gn:admin3_code":"42411.0",
    "gn:asciiname":"Nara",
    "gn:country_code":"JP",
    "gn:dem":57,
    "gn:feature_class":"P",
    "gn:feature_code":"PPL",
    "gn:name":"Nara",
    "gn:population":0,
    "gn:timezone":"Asia/Tokyo",
    "iso:country":"JP",
    "name:und_x_variant":[
        "Chara-dantai",
        "Nara-dantai",
        "Nara"
    ],
    "wof:name":"Nara",
    "wof:placetype":"locality"
},
  "geometry": {"coordinates":[129.05850000000001,32.84070999999999],"type":"Point"}
}