{
  "type": "Feature",
  "properties": {
    "gn:admin1_code":"15.0",
    "gn:admin2_code":"7467880.0",
    "gn:asciiname":"Uwadana",
    "gn:country_code":"JP",
    "gn:dem":18,
    "gn:feature_class":"P",
    "gn:feature_code":"PPL",
    "gn:name":"Uwadana",
    "gn:population":0,
    "gn:timezone":"Asia/Tokyo",
    "iso:country":"JP",
    "name:jpn_x_preferred":[
        "\u4e0a\u7530\u540d"
    ],
    "wof:name":"Uwadana",
    "wof:placetype":"locality"
},
  "geometry": {"coordinates":[136.73866000000001,36.74394],"type":"Point"}
}