{
  "type": "Feature",
  "properties": {
    "gn:admin1_code":"34.0",
    "gn:admin2_code":"1859726.0",
    "gn:asciiname":"Angyo-ryoke",
    "gn:country_code":"JP",
    "gn:dem":17,
    "gn:feature_class":"P",
    "gn:feature_code":"PPL",
    "gn:name":"Angy\u014d-ry\u014dke",
    "gn:population":0,
    "gn:timezone":"Asia/Tokyo",
    "iso:country":"JP",
    "name:jpn_x_preferred":[
        "\u5b89\u884c\u9818\u5bb6"
    ],
    "name:und_x_variant":[
        "Angy\u014d-ry\u014dke"
    ],
    "wof:name":"Angyo-ryoke",
    "wof:placetype":"locality"
},
  "geometry": {"coordinates":[139.75547,35.84722],"type":"Point"}
}