{
  "type": "Feature",
  "properties": {
    "gn:admin1_code":"4.0",
    "gn:admin2_code":"7465521.0",
    "gn:asciiname":"Kitahama",
    "gn:country_code":"JP",
    "gn:dem":10,
    "gn:feature_class":"P",
    "gn:feature_code":"PPLL",
    "gn:name":"Kitahama",
    "gn:population":0,
    "gn:timezone":"Asia/Tokyo",
    "iso:country":"JP",
    "name:jpn_x_preferred":[
        "\u5317\u6d5c"
    ],
    "name:jpn_x_variant":[
        "\u304d\u305f\u306f\u307e",
        "\u30ad\u30bf\u30cf\u30de"
    ],
    "wof:name":"Kitahama",
    "wof:placetype":"locality"
},
  "geometry": {"coordinates":[139.82761000000002,35.03629],"type":"Point"}
}