{
  "type": "Feature",
  "properties": {
    "gn:admin1_code":"7.0",
    "gn:admin2_code":"1864573.0",
    "gn:asciiname":"Byodoji",
    "gn:country_code":"JP",
    "gn:dem":271,
    "gn:feature_class":"P",
    "gn:feature_code":"PPL",
    "gn:name":"By\u014dd\u014dji",
    "gn:population":0,
    "gn:timezone":"Asia/Tokyo",
    "iso:country":"JP",
    "name:jpn_x_preferred":[
        "\u5e73\u7b49\u5bfa"
    ],
    "name:und_x_variant":[
        "By\u014dd\u014dji"
    ],
    "wof:name":"Byodoji",
    "wof:placetype":"locality"
},
  "geometry": {"coordinates":[130.47296,33.44285],"type":"Point"}
}