{
  "type": "Feature",
  "properties": {
    "gn:country":"JP",
    "gn:fcode":"PPL",
    "gn:pop":15825,
    "iso:country":"JP",
    "name:ara_x_preferred":[
        "\u0625\u062a\u0634\u064a\u0646\u0648\u0647"
    ],
    "name:chi_x_preferred":[
        "\u4e00\u6236\u753a"
    ],
    "name:dut_x_preferred":[
        "Ichinohe"
    ],
    "name:eng_x_preferred":[
        "Ichinohe"
    ],
    "name:fre_x_preferred":[
        "Ichinohe"
    ],
    "name:ger_x_preferred":[
        "Ichinohe"
    ],
    "name:ita_x_preferred":[
        "Ichinohe"
    ],
    "name:jpn_x_preferred":[
        "\u4e00\u6238"
    ],
    "name:jpn_x_variant":[
        "\u3044\u3061\u306e\u3078",
        "\u30a4\u30c1\u30ce\u30d8",
        "\u4e00\u6238\u753a"
    ],
    "name:kor_x_preferred":[
        "\uc774\uce58\ub178\ud5e4 \uc815"
    ],
    "name:may_x_preferred":[
        "Ichinohe"
    ],
    "name:por_x_preferred":[
        "Ichinohe"
    ],
    "name:rus_x_preferred":[
        "\u0418\u0442\u0438\u043d\u043e\u0445\u0435"
    ],
    "name:spa_x_preferred":[
        "Ichinohe"
    ],
    "name:tgl_x_preferred":[
        "Ichinohe"
    ],
    "name:ukr_x_preferred":[
        "\u0406\u0442\u0456\u043d\u043e\u0445\u0435"
    ],
    "name:unk_x_variant":[
        "Ehinohe"
    ],
    "qs:name":"Ichinohe",
    "qs:photos_9r":0,
    "qs:photos_sr":0,
    "qs:pop_sr":"6",
    "wd:wordcount":36,
    "wof:name":"Ichinohe",
    "wof:placetype":"locality",
    "wof:population":15825
},
  "geometry": {"coordinates":[141.30167,40.20694],"type":"Point"}
}