{
  "type": "Feature",
  "properties": {
    "gn:country":"JP",
    "gn:fcode":"PPL",
    "gn:population":15825,
    "iso:country":"JP",
    "name:ara_x_preferred":[
        "\u0625\u062a\u0634\u064a\u0646\u0648\u0647"
    ],
    "name:ast_x_preferred":[
        "Ichinohe"
    ],
    "name:ceb_x_preferred":[
        "Ichinohe-machi"
    ],
    "name:deu_x_preferred":[
        "Ichinohe"
    ],
    "name:eng_x_preferred":[
        "Ichinohe"
    ],
    "name:fas_x_preferred":[
        "\u0627\u06cc\u0686\u0646\u0648\u0647\u0647"
    ],
    "name:fra_x_preferred":[
        "Ichinohe"
    ],
    "name:ita_x_preferred":[
        "Ichinohe"
    ],
    "name:jpn_x_preferred":[
        "\u4e00\u6238"
    ],
    "name:jpn_x_variant":[
        "\u3044\u3061\u306e\u3078",
        "\u30a4\u30c1\u30ce\u30d8",
        "\u4e00\u6238\u753a"
    ],
    "name:kor_x_preferred":[
        "\uc774\uce58\ub178\ud5e4 \uc815"
    ],
    "name:kor_x_variant":[
        "\uc774\uce58\ub178\ud5e4\uc815"
    ],
    "name:msa_x_preferred":[
        "Ichinohe"
    ],
    "name:mya_x_preferred":[
        "\u1021\u102d\u1001\u103b\u102d\u1014\u102d\u102f\u101f\u1032\u1019\u103c\u102d\u102f\u1037\u104a \u1021\u102d\u101d\u1010\u1032"
    ],
    "name:nld_x_preferred":[
        "Ichinohe"
    ],
    "name:por_x_preferred":[
        "Ichinohe"
    ],
    "name:rus_x_preferred":[
        "\u0418\u0442\u0438\u043d\u043e\u0445\u0435"
    ],
    "name:spa_x_preferred":[
        "Ichinohe"
    ],
    "name:tgl_x_preferred":[
        "Ichinohe"
    ],
    "name:ukr_x_preferred":[
        "\u0406\u0442\u0456\u043d\u043e\u0445\u0435"
    ],
    "name:und_x_variant":[
        "Ehinohe"
    ],
    "name:zho_x_preferred":[
        "\u4e00\u6236\u753a"
    ],
    "qs:name":"Ichinohe",
    "qs:photos_9r":0,
    "qs:photos_sr":0,
    "qs:pop_sr":"6",
    "wd:wordcount":36,
    "wof:name":"Ichinohe",
    "wof:placetype":"locality",
    "wof:population":15825
},
  "geometry": {"coordinates":[141.30167,40.20694],"type":"Point"}
}