{
  "type": "Feature",
  "properties": {
    "gn:admin1_code":"4.0",
    "gn:admin2_code":"1855071.0",
    "gn:asciiname":"Yoshiharu",
    "gn:country_code":"JP",
    "gn:dem":10,
    "gn:feature_class":"P",
    "gn:feature_code":"PPL",
    "gn:name":"Yoshiharu",
    "gn:population":0,
    "gn:timezone":"Asia/Tokyo",
    "iso:country":"JP",
    "name:jpn_x_preferred":[
        "\u5409\u6625"
    ],
    "wof:name":"Yoshiharu",
    "wof:placetype":"locality"
},
  "geometry": {"coordinates":[139.86503000000002,35.96451],"type":"Point"}
}