{
  "type": "Feature",
  "properties": {
    "gn:admin1_code":"21.0",
    "gn:admin2_code":"1857206.0",
    "gn:asciiname":"Sakaemachi",
    "gn:country_code":"JP",
    "gn:dem":2,
    "gn:feature_class":"P",
    "gn:feature_code":"PPL",
    "gn:name":"Sakaemachi",
    "gn:population":0,
    "gn:timezone":"Asia/Tokyo",
    "iso:country":"JP",
    "name:jpn_x_preferred":[
        "\u6804\u753a"
    ],
    "name:jpn_x_variant":[
        "\u3055\u304b\u3048\u307e\u3061",
        "\u30b5\u30ab\u30a8\u30de\u30c1"
    ],
    "wof:name":"Sakaemachi",
    "wof:placetype":"locality"
},
  "geometry": {"coordinates":[130.39750000000001,32.21053],"type":"Point"}
}