{
  "type": "Feature",
  "properties": {
    "gn:admin1_code":"4.0",
    "gn:admin2_code":"2112386.0",
    "gn:asciiname":"Miyahigashi",
    "gn:country_code":"JP",
    "gn:dem":50,
    "gn:feature_class":"P",
    "gn:feature_code":"PPLL",
    "gn:name":"Miyahigashi",
    "gn:population":0,
    "gn:timezone":"Asia/Tokyo",
    "iso:country":"JP",
    "name:jpn_x_preferred":[
        "\u5bae\u6771"
    ],
    "name:jpn_x_variant":[
        "\u307f\u3084\u3072\u304c\u3057",
        "\u30df\u30e4\u30d2\u30ac\u30b7"
    ],
    "wof:name":"Miyahigashi",
    "wof:placetype":"locality"
},
  "geometry": {"coordinates":[140.02029999999999,35.1281],"type":"Point"}
}