{
  "type": "Feature",
  "properties": {
    "gn:admin1_code":"40.0",
    "gn:admin2_code":"1853655.0",
    "gn:asciiname":"Minamirokugo",
    "gn:country_code":"JP",
    "gn:dem":9,
    "gn:feature_class":"P",
    "gn:feature_code":"PPL",
    "gn:name":"Minamirokug\u014d",
    "gn:population":0,
    "gn:timezone":"Asia/Tokyo",
    "iso:country":"JP",
    "name:jpn_x_preferred":[
        "\u5357\u516d\u90f7"
    ],
    "name:und_x_variant":[
        "Minamirokug\u014d"
    ],
    "wof:name":"Minamirokugo",
    "wof:placetype":"locality"
},
  "geometry": {"coordinates":[139.72062,35.54675],"type":"Point"}
}