{
  "type": "Feature",
  "properties": {
    "gn:admin1_code":"3.0",
    "gn:admin2_code":"2128302.0",
    "gn:admin3_code":"2441.0",
    "gn:asciiname":"Nozuki",
    "gn:country_code":"JP",
    "gn:dem":96,
    "gn:feature_class":"P",
    "gn:feature_code":"PPL",
    "gn:name":"Nozuki",
    "gn:population":0,
    "gn:timezone":"Asia/Tokyo",
    "iso:country":"JP",
    "name:jpn_x_preferred":[
        "\u91ce\u6708"
    ],
    "name:jpn_x_variant":[
        "\u306e\u3065\u304d",
        "\u30ce\u30c5\u30ad"
    ],
    "wof:name":"Nozuki",
    "wof:placetype":"locality"
},
  "geometry": {"coordinates":[141.19255000000001,40.35048],"type":"Point"}
}