{
  "type": "Feature",
  "properties": {
    "gn:admin1_code":"34.0",
    "gn:admin2_code":"8304213.0",
    "gn:asciiname":"Yahara-shinden",
    "gn:country_code":"JP",
    "gn:dem":5,
    "gn:feature_class":"P",
    "gn:feature_code":"PPL",
    "gn:name":"Yahara-shinden",
    "gn:population":0,
    "gn:timezone":"Asia/Tokyo",
    "iso:country":"JP",
    "name:jpn_x_preferred":[
        "\u8c37\u539f\u65b0\u7530"
    ],
    "name:jpn_x_variant":[
        "\u3084\u306f\u3089\u3057\u3093\u3067\u3093",
        "\u30e4\u30cf\u30e9\u30b7\u30f3\u30c7\u30f3"
    ],
    "wof:name":"Yahara-shinden",
    "wof:placetype":"locality"
},
  "geometry": {"coordinates":[139.74420000000001,35.96283],"type":"Point"}
}