{
  "type": "Feature",
  "properties": {
    "gn:admin1_code":"4.0",
    "gn:admin2_code":"2112663.0",
    "gn:asciiname":"Saze",
    "gn:country_code":"JP",
    "gn:dem":22,
    "gn:feature_class":"P",
    "gn:feature_code":"PPL",
    "gn:name":"Saze",
    "gn:population":0,
    "gn:timezone":"Asia/Tokyo",
    "iso:country":"JP",
    "name:jpn_x_preferred":[
        "\u4f50\u662f"
    ],
    "name:jpn_x_variant":[
        "\u3055\u305c",
        "\u30b5\u30bc"
    ],
    "wof:name":"Saze",
    "wof:placetype":"locality"
},
  "geometry": {"coordinates":[140.13102000000001,35.40414000000001],"type":"Point"}
}