{
  "type": "Feature",
  "properties": {
    "gn:admin1_code":"3.0",
    "gn:admin2_code":"2128302.0",
    "gn:admin3_code":"2442.0",
    "gn:asciiname":"Kitamuki",
    "gn:country_code":"JP",
    "gn:dem":69,
    "gn:feature_class":"P",
    "gn:feature_code":"PPL",
    "gn:name":"Kitamuki",
    "gn:population":0,
    "gn:timezone":"Asia/Tokyo",
    "iso:country":"JP",
    "name:jpn_x_preferred":[
        "\u5317\u5411"
    ],
    "name:jpn_x_variant":[
        "\u304d\u305f\u3080\u304d",
        "\u30ad\u30bf\u30e0\u30ad"
    ],
    "wof:name":"Kitamuki",
    "wof:placetype":"locality"
},
  "geometry": {"coordinates":[141.29251000000005,40.4686],"type":"Point"}
}