{
  "type": "Feature",
  "properties": {
    "gn:admin1_code":"43.0",
    "gn:admin2_code":"1865123.0",
    "gn:admin3_code":"30362.0",
    "gn:asciiname":"Karo",
    "gn:country_code":"JP",
    "gn:dem":8,
    "gn:feature_class":"P",
    "gn:feature_code":"PPL",
    "gn:name":"Karo",
    "gn:population":0,
    "gn:timezone":"Asia/Tokyo",
    "iso:country":"JP",
    "name:jpn_x_preferred":[
        "\u5510\u5c3e"
    ],
    "wof:name":"Karo",
    "wof:placetype":"locality"
},
  "geometry": {"coordinates":[135.14977999999999,34.00476],"type":"Point"}
}