{
  "type": "Feature",
  "properties": {
    "gn:admin1_code":"4.0",
    "gn:admin2_code":"9062338.0",
    "gn:asciiname":"Shinkan",
    "gn:country_code":"JP",
    "gn:dem":40,
    "gn:feature_class":"P",
    "gn:feature_code":"PPL",
    "gn:name":"Shinkan",
    "gn:population":0,
    "gn:timezone":"Asia/Tokyo",
    "iso:country":"JP",
    "name:jpn_x_preferred":[
        "\u65b0\u5b98"
    ],
    "name:jpn_x_variant":[
        "\u3057\u3093\u304b\u3093",
        "\u30b7\u30f3\u30ab\u30f3"
    ],
    "wof:name":"Shinkan",
    "wof:placetype":"locality"
},
  "geometry": {"coordinates":[140.32206000000002,35.15401],"type":"Point"}
}