{
  "type": "Feature",
  "properties": {
    "gn:admin1_code":"21.0",
    "gn:admin2_code":"7412708.0",
    "gn:admin3_code":"43511.0",
    "gn:asciiname":"Tsutehira",
    "gn:country_code":"JP",
    "gn:dem":285,
    "gn:feature_class":"P",
    "gn:feature_code":"PPL",
    "gn:name":"Tsutehira",
    "gn:population":0,
    "gn:timezone":"Asia/Tokyo",
    "iso:country":"JP",
    "name:jpn_x_preferred":[
        "\u571f\u4f1a\u5e73"
    ],
    "name:jpn_x_variant":[
        "\u3064\u3066\u3072\u3089",
        "\u30c4\u30c6\u30d2\u30e9"
    ],
    "wof:name":"Tsutehira",
    "wof:placetype":"locality"
},
  "geometry": {"coordinates":[130.81,32.39897],"type":"Point"}
}