{
  "type": "Feature",
  "properties": {
    "gn:admin1_code":"12.0",
    "gn:admin2_code":"7428121.0",
    "gn:admin3_code":"1586.0",
    "gn:asciiname":"Kasuga",
    "gn:country_code":"JP",
    "gn:dem":20,
    "gn:feature_class":"P",
    "gn:feature_code":"PPL",
    "gn:name":"Kasuga",
    "gn:population":0,
    "gn:timezone":"Asia/Tokyo",
    "iso:country":"JP",
    "name:ces_x_preferred":[
        "Kasuga"
    ],
    "name:deu_x_preferred":[
        "Kasuga"
    ],
    "name:jpn_x_preferred":[
        "\u6625\u65e5"
    ],
    "name:pol_x_preferred":[
        "Kasuga"
    ],
    "name:ron_x_preferred":[
        "Kasuga"
    ],
    "name:rus_x_preferred":[
        "\u041a\u0430\u0441\u0443\u0433\u0430"
    ],
    "name:spa_x_preferred":[
        "Kasuga"
    ],
    "name:tha_x_preferred":[
        "\u0e04\u0e30\u0e0b\u0e38\u0e07\u0e30"
    ],
    "wof:name":"Kasuga",
    "wof:placetype":"locality"
},
  "geometry": {"coordinates":[141.99691999999999,42.58878],"type":"Point"}
}