{
  "type": "Feature",
  "properties": {
    "gn:admin1_code":"21.0",
    "gn:admin2_code":"1862350.0",
    "gn:asciiname":"Shimosatsumazemachi",
    "gn:country_code":"JP",
    "gn:dem":99,
    "gn:feature_class":"P",
    "gn:feature_code":"PPL",
    "gn:name":"Shimosatsumazemachi",
    "gn:population":0,
    "gn:timezone":"Asia/Tokyo",
    "iso:country":"JP",
    "name:jpn_x_preferred":[
        "\u4e0b\u85a9\u6469\u702c\u753a"
    ],
    "name:jpn_x_variant":[
        "\u3057\u3082\u3055\u3064\u307e\u305c\u307e\u3061",
        "\u30b7\u30e2\u30b5\u30c4\u30de\u30bc\u30de\u30c1"
    ],
    "wof:name":"Shimosatsumazemachi",
    "wof:placetype":"locality"
},
  "geometry": {"coordinates":[130.73491999999999,32.21231],"type":"Point"}
}