{
  "type": "Feature",
  "properties": {
    "gn:admin1_code":"3.0",
    "gn:admin2_code":"2129754.0",
    "gn:admin3_code":"2412.0",
    "gn:asciiname":"Hitokawame",
    "gn:country_code":"JP",
    "gn:dem":14,
    "gn:feature_class":"P",
    "gn:feature_code":"PPL",
    "gn:name":"Hitokawame",
    "gn:population":0,
    "gn:timezone":"Asia/Tokyo",
    "iso:country":"JP",
    "name:jpn_x_preferred":[
        "\u4e00\u5ddd\u76ee"
    ],
    "name:jpn_x_variant":[
        "\u3072\u3068\u304b\u308f\u3081",
        "\u30d2\u30c8\u30ab\u30ef\u30e1"
    ],
    "name:und_x_variant":[
        "Shitokawame",
        "Hitokawame"
    ],
    "wof:name":"Hitokawame",
    "wof:placetype":"locality"
},
  "geometry": {"coordinates":[141.44479999999999,40.63593],"type":"Point"}
}