{
  "type": "Feature",
  "properties": {
    "gn:admin1_code":"7.0",
    "gn:admin2_code":"1864588.0",
    "gn:admin3_code":"40647.0",
    "gn:asciiname":"Kamifukano",
    "gn:country_code":"JP",
    "gn:dem":67,
    "gn:feature_class":"P",
    "gn:feature_code":"PPL",
    "gn:name":"Kamifukano",
    "gn:population":0,
    "gn:timezone":"Asia/Tokyo",
    "iso:country":"JP",
    "name:jpn_x_preferred":[
        "\u4e0a\u6df1\u91ce"
    ],
    "wof:name":"Kamifukano",
    "wof:placetype":"locality"
},
  "geometry": {"coordinates":[130.99447000000001,33.63574000000001],"type":"Point"}
}