{
  "type": "Feature",
  "properties": {
    "gn:admin1_code":"23",
    "gn:admin2_code":"1848873.0",
    "gn:admin3_code":"24470.0",
    "gn:asciiname":"Onoki",
    "gn:country_code":"JP",
    "gn:dem":24,
    "gn:feature_class":"P",
    "gn:feature_code":"PPL",
    "gn:name":"\u014cnoki",
    "gn:population":0,
    "gn:timezone":"Asia/Tokyo",
    "iso:country":"JP",
    "name:und_x_variant":[
        "\u014cnoki"
    ],
    "wof:name":"Onoki",
    "wof:placetype":"locality"
},
  "geometry": {"coordinates":[136.63333,34.43333],"type":"Point"}
}