{
  "type": "Feature",
  "properties": {
    "gn:admin1_code":"21.0",
    "gn:admin2_code":"7412706.0",
    "gn:admin3_code":"43443.0",
    "gn:asciiname":"Nakatogawa",
    "gn:country_code":"JP",
    "gn:dem":9,
    "gn:feature_class":"P",
    "gn:feature_code":"PPLL",
    "gn:name":"Nakatogawa",
    "gn:population":0,
    "gn:timezone":"Asia/Tokyo",
    "iso:country":"JP",
    "name:jpn_x_preferred":[
        "\u4e2d\u7825\u5ddd"
    ],
    "name:jpn_x_variant":[
        "\u306a\u304b\u3068\u304c\u308f",
        "\u30ca\u30ab\u30c8\u30ac\u30ef"
    ],
    "wof:name":"Nakatogawa",
    "wof:placetype":"locality"
},
  "geometry": {"coordinates":[130.81296,32.76055],"type":"Point"}
}