{
  "type": "Feature",
  "properties": {
    "gn:admin1_code":"34",
    "gn:admin2_code":"1859584.0",
    "gn:asciiname":"Ochiai",
    "gn:country_code":"JP",
    "gn:dem":17,
    "gn:feature_class":"P",
    "gn:feature_code":"PPL",
    "gn:name":"Ochiai",
    "gn:population":0,
    "gn:timezone":"Asia/Tokyo",
    "iso:country":"JP",
    "wof:name":"Ochiai",
    "wof:placetype":"locality"
},
  "geometry": {"coordinates":[139.53333000000001,36.11667],"type":"Point"}
}