{
  "type": "Feature",
  "properties": {
    "gn:admin1_code":"3.0",
    "gn:admin2_code":"2129089.0",
    "gn:asciiname":"Kabayama",
    "gn:country_code":"JP",
    "gn:dem":35,
    "gn:feature_class":"P",
    "gn:feature_code":"PPL",
    "gn:name":"Kabayama",
    "gn:population":0,
    "gn:timezone":"Asia/Tokyo",
    "iso:country":"JP",
    "wof:name":"Kabayama",
    "wof:placetype":"locality"
},
  "geometry": {"coordinates":[141.21666999999999,41.31667],"type":"Point"}
}