{
  "type": "Feature",
  "properties": {
    "gn:admin1_code":"43.0",
    "gn:admin2_code":"1861287.0",
    "gn:admin3_code":"30341.0",
    "gn:asciiname":"Kaseda-higashi",
    "gn:country_code":"JP",
    "gn:dem":60,
    "gn:feature_class":"P",
    "gn:feature_code":"PPL",
    "gn:name":"Kaseda-higashi",
    "gn:population":0,
    "gn:timezone":"Asia/Tokyo",
    "iso:country":"JP",
    "name:jpn_x_preferred":[
        "\u7b20\u7530\u6771"
    ],
    "wof:name":"Kaseda-higashi",
    "wof:placetype":"locality"
},
  "geometry": {"coordinates":[135.4787,34.28946],"type":"Point"}
}