{
  "type": "Feature",
  "properties": {
    "gn:admin1_code":"45.0",
    "gn:admin2_code":"1852222.0",
    "gn:asciiname":"Nagasaki-shinmachi",
    "gn:country_code":"JP",
    "gn:dem":23,
    "gn:feature_class":"P",
    "gn:feature_code":"PPL",
    "gn:name":"Nagasaki-shinmachi",
    "gn:population":0,
    "gn:timezone":"Asia/Tokyo",
    "iso:country":"JP",
    "name:jpn_x_preferred":[
        "\u9577\u5d0e\u65b0\u753a"
    ],
    "wof:name":"Nagasaki-shinmachi",
    "wof:placetype":"locality"
},
  "geometry": {"coordinates":[130.92578999999998,33.9552],"type":"Point"}
}