{
  "type": "Feature",
  "properties": {
    "iso:country":"JP",
    "name:eng_x_preferred":[
        "Nakamuramachi 1 Chome"
    ],
    "name:eng_x_variant":[
        "Nakamuramachi 1 Choume",
        "Nakamuramachi 1 Chome"
    ],
    "name:jpn_x_preferred":[
        "\uff11\u4e01\u76ee"
    ],
    "name:jpn_x_variant":[
        "\u306a\u304b\u3080\u3089\u307e\u3061 \uff11\u3061\u3087\u3046\u3081",
        "\u4e2d\u6751\u753a \uff11\u4e01\u76ee",
        "\uff11\u3061\u3087\u3046\u3081"
    ],
    "qs:gn_local":0,
    "qs:local_max":709,
    "qs:local_sum":1370,
    "qs:localhoods":4,
    "qs:name":"\uff11\u4e01\u76ee",
    "qs:name_adm0":"\u65e5\u672c",
    "qs:name_adm1":"\u57fc\u7389\u770c",
    "qs:name_en":"Nakamuramachi 1 Chome",
    "qs:name_lau":"\u4e2d\u6751\u753a",
    "qs:name_local":"\u79e9\u7236\u5e02",
    "qs:photo_max":201,
    "qs:photo_sum":709,
    "qs:placetype":"Suburb",
    "qs:quad_count":17,
    "qs:woe_adm0":23424856,
    "qs:woe_adm1":2345883,
    "qs:woe_adm2":0,
    "qs:woe_lau":28408387,
    "qs:woe_local":1117035,
    "qs:woe_ver":"7.10.0",
    "wof:lang":[
        "jpn"
    ],
    "wof:name":"\uff11\u4e01\u76ee",
    "wof:placetype":"neighbourhood"
},
  "geometry": {"coordinates":[139.08534299999999,35.999087],"type":"Point"}
}