{
  "type": "Feature",
  "properties": {
    "gn:country":"JP",
    "gn:fcode":"PPL",
    "gn:pop":39693,
    "iso:country":"JP",
    "name:ara_x_preferred":[
        "\u0645\u0648\u0631\u0648\u064a\u0627\u0645\u0627"
    ],
    "name:deu_x_preferred":[
        "Moroyama"
    ],
    "name:eng_x_preferred":[
        "Moroyama"
    ],
    "name:fra_x_preferred":[
        "Moroyama"
    ],
    "name:heb_x_preferred":[
        "\u05de\u05d5\u05e8\u05d5\u05d9\u05d0\u05de\u05d4"
    ],
    "name:ita_x_preferred":[
        "Moroyama"
    ],
    "name:jpn_x_preferred":[
        "\u6bdb\u5442\u5c71\u753a"
    ],
    "name:kor_x_preferred":[
        "\ubaa8\ub85c\uc57c\ub9c8 \uc815"
    ],
    "name:msa_x_preferred":[
        "Moroyama"
    ],
    "name:nld_x_preferred":[
        "Moroyama"
    ],
    "name:por_x_preferred":[
        "Moroyama"
    ],
    "name:rus_x_preferred":[
        "\u041c\u043e\u0440\u043e\u044f\u043c\u0430"
    ],
    "name:spa_x_preferred":[
        "Moroyama"
    ],
    "name:tgl_x_preferred":[
        "Moroyama"
    ],
    "name:ukr_x_preferred":[
        "\u041c\u043e\u0440\u043e\u044f\u043c\u0430"
    ],
    "name:unk_x_variant":[
        "Moroyama"
    ],
    "name:zho_x_preferred":[
        "\u6bdb\u5442\u5c71\u753a"
    ],
    "qs:name":"Morohong\u014d",
    "qs:photos_9r":0,
    "qs:photos_sr":0,
    "qs:pop_sr":"7",
    "wof:name":"Morohong\u014d",
    "wof:placetype":"locality",
    "wof:population":39693
},
  "geometry": {"coordinates":[139.30444,35.93556],"type":"Point"}
}