{
  "type": "Feature",
  "properties": {
    "gn:admin1_code":"21.0",
    "gn:admin2_code":"1858418.0",
    "gn:admin3_code":"43104.0",
    "gn:asciiname":"Jonanmachi-sansan",
    "gn:country_code":"JP",
    "gn:dem":31,
    "gn:feature_class":"P",
    "gn:feature_code":"PPL",
    "gn:name":"J\u014dnanmachi-sansan",
    "gn:population":0,
    "gn:timezone":"Asia/Tokyo",
    "iso:country":"JP",
    "name:jpn_x_preferred":[
        "\u57ce\u5357\u753a\u3055\u3093\u3055\u3093"
    ],
    "name:jpn_x_variant":[
        "\u3058\u3087\u3046\u306a\u3093\u307e\u3061\u3055\u3093\u3055\u3093",
        "\u30b8\u30e7\u30a6\u30ca\u30f3\u30de\u30c1\u30b5\u30f3\u30b5\u30f3"
    ],
    "name:und_x_variant":[
        "J\u014dnanmachi-sansan"
    ],
    "wof:name":"Jonanmachi-sansan",
    "wof:placetype":"locality"
},
  "geometry": {"coordinates":[130.73651000000001,32.71128],"type":"Point"}
}