{
  "type": "Feature",
  "properties": {
    "gn:admin1_code":"19.0",
    "gn:admin2_code":"1865011.0",
    "gn:admin3_code":"14366.0",
    "gn:asciiname":"Nakanomyo",
    "gn:country_code":"JP",
    "gn:dem":50,
    "gn:feature_class":"P",
    "gn:feature_code":"PPL",
    "gn:name":"Nakanomy\u014d",
    "gn:population":0,
    "gn:timezone":"Asia/Tokyo",
    "iso:country":"JP",
    "name:jpn_x_preferred":[
        "\u4e2d\u4e4b\u540d"
    ],
    "name:und_x_variant":[
        "Nakanomy\u014d"
    ],
    "wof:name":"Nakanomyo",
    "wof:placetype":"locality"
},
  "geometry": {"coordinates":[139.11928999999998,35.33022000000001],"type":"Point"}
}