{
  "type": "Feature",
  "properties": {
    "gn:admin1_code":"28.0",
    "gn:admin2_code":"1848164.0",
    "gn:admin3_code":"29443.0",
    "gn:asciiname":"Tani",
    "gn:country_code":"JP",
    "gn:dem":344,
    "gn:feature_class":"P",
    "gn:feature_code":"PPL",
    "gn:name":"Tani",
    "gn:population":0,
    "gn:timezone":"Asia/Tokyo",
    "iso:country":"JP",
    "name:ceb_x_preferred":[
        "Tani"
    ],
    "name:deu_x_preferred":[
        "Tani"
    ],
    "name:fin_x_preferred":[
        "Tani"
    ],
    "name:fra_x_preferred":[
        "Tani"
    ],
    "name:ita_x_preferred":[
        "Tani"
    ],
    "name:jpn_x_preferred":[
        "\u8c37"
    ],
    "name:por_x_preferred":[
        "Tani"
    ],
    "name:swe_x_preferred":[
        "Tani"
    ],
    "wof:name":"Tani",
    "wof:placetype":"locality"
},
  "geometry": {"coordinates":[135.79365000000001,34.30982],"type":"Point"}
}