{
  "type": "Feature",
  "properties": {
    "gn:admin1_code":"24.0",
    "gn:admin2_code":"2112574.0",
    "gn:asciiname":"Kashiwagi",
    "gn:country_code":"JP",
    "gn:dem":2,
    "gn:feature_class":"P",
    "gn:feature_code":"PPL",
    "gn:name":"Kashiwagi",
    "gn:population":0,
    "gn:timezone":"Asia/Tokyo",
    "iso:country":"JP",
    "name:jpn_x_preferred":[
        "\u67cf\u6728"
    ],
    "name:jpn_x_variant":[
        "\u304b\u3057\u308f\u304e",
        "\u30ab\u30b7\u30ef\u30ae"
    ],
    "wof:name":"Kashiwagi",
    "wof:placetype":"locality"
},
  "geometry": {"coordinates":[141.22266999999999,38.47457],"type":"Point"}
}