{
  "type": "Feature",
  "properties": {
    "gn:admin1_code":"16.0",
    "gn:admin2_code":"7441806.0",
    "gn:admin3_code":"3483.0",
    "gn:asciiname":"Nagaimura",
    "gn:cc2":"JP",
    "gn:country_code":"JP",
    "gn:dem":557,
    "gn:feature_class":"P",
    "gn:feature_code":"PPL",
    "gn:name":"Nagaimura",
    "gn:population":0,
    "gn:timezone":"Asia/Tokyo",
    "iso:country":"JP",
    "name:und_x_variant":[
        "Nakaimura",
        "Nagaimura"
    ],
    "wof:name":"Nagaimura",
    "wof:placetype":"locality"
},
  "geometry": {"coordinates":[141.55000000000001,39.78333],"type":"Point"}
}