{
  "type": "Feature",
  "properties": {
    "gn:admin1_code":"37.0",
    "gn:admin2_code":"1851274.0",
    "gn:admin3_code":"22325.0",
    "gn:asciiname":"Binnosawa",
    "gn:country_code":"JP",
    "gn:dem":269,
    "gn:feature_class":"P",
    "gn:feature_code":"PPLL",
    "gn:name":"Binnosawa",
    "gn:population":0,
    "gn:timezone":"Asia/Tokyo",
    "iso:country":"JP",
    "name:jpn_x_preferred":[
        "\u9b22\u306e\u6ca2"
    ],
    "wof:name":"Binnosawa",
    "wof:placetype":"locality"
},
  "geometry": {"coordinates":[138.99535,35.10924],"type":"Point"}
}