{
  "type": "Feature",
  "properties": {
    "gn:admin1_code":"21.0",
    "gn:admin2_code":"7412709.0",
    "gn:admin3_code":"43348.0",
    "gn:asciiname":"Hayakusu",
    "gn:country_code":"JP",
    "gn:dem":466,
    "gn:feature_class":"P",
    "gn:feature_code":"PPL",
    "gn:name":"Hayakusu",
    "gn:population":0,
    "gn:timezone":"Asia/Tokyo",
    "iso:country":"JP",
    "name:jpn_x_preferred":[
        "\u65e9\u6960"
    ],
    "name:jpn_x_variant":[
        "\u306f\u3084\u304f\u3059",
        "\u30cf\u30e4\u30af\u30b9"
    ],
    "wof:name":"Hayakusu",
    "wof:placetype":"locality"
},
  "geometry": {"coordinates":[130.89061999999998,32.59555],"type":"Point"}
}