{
  "type": "Feature",
  "properties": {
    "iso:country":"JP",
    "name:eng_x_preferred":[
        "Kawabatacho 5 Chome"
    ],
    "name:eng_x_variant":[
        "Kawabatachou 5 Choume",
        "Kawabatacho 5 Chome"
    ],
    "name:jpn_x_preferred":[
        "\uff15\u4e01\u76ee"
    ],
    "name:jpn_x_variant":[
        "\u304b\u308f\u3070\u305f\u3061\u3087\u3046 \uff15\u3061\u3087\u3046\u3081",
        "\u5ddd\u7aef\u753a \uff15\u4e01\u76ee",
        "\uff15\u3061\u3087\u3046\u3081"
    ],
    "qs:gn_local":0,
    "qs:local_max":1296,
    "qs:local_sum":6373,
    "qs:localhoods":29,
    "qs:name":"\uff15\u4e01\u76ee",
    "qs:name_adm0":"\u65e5\u672c",
    "qs:name_adm1":"\u65b0\u6f5f\u770c",
    "qs:name_adm2":"\u4e2d\u592e\u533a",
    "qs:name_en":"Kawabatacho 5 Chome",
    "qs:name_lau":"\u5ddd\u7aef\u753a",
    "qs:name_local":"\u65b0\u6f5f\u5e02",
    "qs:photo_max":185,
    "qs:photo_sum":499,
    "qs:placetype":"Suburb",
    "qs:quad_count":11,
    "qs:woe_adm0":23424856,
    "qs:woe_adm1":2345878,
    "qs:woe_adm2":55805803,
    "qs:woe_lau":55807785,
    "qs:woe_local":1117881,
    "qs:woe_ver":"7.10.0",
    "wof:lang":[
        "jpn"
    ],
    "wof:name":"\uff15\u4e01\u76ee",
    "wof:placetype":"neighbourhood"
},
  "geometry": {"coordinates":[139.05401000000001,37.918795],"type":"Point"}
}