{
  "type": "Feature",
  "properties": {
    "gn:admin1_code":"29",
    "gn:admin2_code":"1853313.0",
    "gn:asciiname":"Sawane",
    "gn:country_code":"JP",
    "gn:dem":40,
    "gn:feature_class":"P",
    "gn:feature_code":"PPL",
    "gn:name":"Sawane",
    "gn:population":0,
    "gn:timezone":"Asia/Tokyo",
    "iso:country":"JP",
    "name:jpn_x_preferred":[
        "\u6ca2\u6839"
    ],
    "name:und_x_variant":[
        "Sawanemura"
    ],
    "wof:name":"Sawane",
    "wof:placetype":"locality"
},
  "geometry": {"coordinates":[138.26423,37.99828],"type":"Point"}
}