{
  "type": "Feature",
  "properties": {
    "gn:admin1_code":"21.0",
    "gn:admin2_code":"1850743.0",
    "gn:asciiname":"Nishitabata",
    "gn:country_code":"JP",
    "gn:dem":-1,
    "gn:feature_class":"P",
    "gn:feature_code":"PPLL",
    "gn:name":"Nishitabata",
    "gn:population":0,
    "gn:timezone":"Asia/Tokyo",
    "iso:country":"JP",
    "name:jpn_x_preferred":[
        "\u897f\u7530\u7aef"
    ],
    "name:jpn_x_variant":[
        "\u306b\u3057\u305f\u3070\u305f",
        "\u30cb\u30b7\u30bf\u30d0\u30bf"
    ],
    "wof:name":"Nishitabata",
    "wof:placetype":"locality"
},
  "geometry": {"coordinates":[130.56596999999999,32.90822],"type":"Point"}
}