{
  "type": "Feature",
  "properties": {
    "iso:country":"JP",
    "name:eng_x_preferred":[
        "Shitaya 1 Chome"
    ],
    "name:eng_x_variant":[
        "Shitaya 1 Choume",
        "Shitaya 1 Chome"
    ],
    "name:jpn_x_preferred":[
        "\uff11\u4e01\u76ee"
    ],
    "name:jpn_x_variant":[
        "\u3057\u305f\u3084 \uff11\u3061\u3087\u3046\u3081",
        "\u4e0b\u8c37 \uff11\u4e01\u76ee",
        "\uff11\u3061\u3087\u3046\u3081"
    ],
    "qs:gn_adm0_cc":"JP",
    "qs:gn_local":1850147,
    "qs:local_max":18112,
    "qs:local_sum":895907,
    "qs:localhoods":857,
    "qs:name":"\uff11\u4e01\u76ee",
    "qs:name_adm0":"\u65e5\u672c",
    "qs:name_adm1":"\u6771\u4eac\u90fd",
    "qs:name_adm2":"\u53f0\u6771\u533a",
    "qs:name_en":"Shitaya 1 Chome",
    "qs:name_lau":"\u4e0b\u8c37",
    "qs:name_local":"\u6771\u4eac",
    "qs:photo_max":134,
    "qs:photo_sum":522,
    "qs:placetype":"Suburb",
    "qs:quad_count":9,
    "qs:woe_adm0":23424856,
    "qs:woe_adm1":2345889,
    "qs:woe_adm2":15015401,
    "qs:woe_lau":28414139,
    "qs:woe_local":1118370,
    "qs:woe_ver":"7.10.0",
    "wof:lang":[
        "jpn"
    ],
    "wof:name":"\uff11\u4e01\u76ee",
    "wof:placetype":"neighbourhood"
},
  "geometry": {"coordinates":[139.78103400000001,35.718968],"type":"Point"}
}