{
  "type": "Feature",
  "properties": {
    "gn:admin1_code":"21.0",
    "gn:admin2_code":"1865358.0",
    "gn:asciiname":"Kitaharamachi",
    "gn:country_code":"JP",
    "gn:dem":3,
    "gn:feature_class":"P",
    "gn:feature_code":"PPL",
    "gn:name":"Kitaharamachi",
    "gn:population":0,
    "gn:timezone":"Asia/Tokyo",
    "iso:country":"JP",
    "name:jpn_x_preferred":[
        "\u5317\u6d5c\u753a"
    ],
    "name:jpn_x_variant":[
        "\u304d\u305f\u306f\u307e\u307e\u3061",
        "\u30ad\u30bf\u30cf\u30de\u30de\u30c1"
    ],
    "wof:name":"Kitaharamachi",
    "wof:placetype":"locality"
},
  "geometry": {"coordinates":[130.18666000000002,32.46572],"type":"Point"}
}