{
  "type": "Feature",
  "properties": {
    "gn:admin1_code":"47",
    "gn:admin2_code":"7415821.0",
    "gn:asciiname":"Katsuren-henna",
    "gn:country_code":"JP",
    "gn:dem":53,
    "gn:feature_class":"P",
    "gn:feature_code":"PPL",
    "gn:name":"Katsuren-henna",
    "gn:population":0,
    "gn:timezone":"Asia/Tokyo",
    "iso:country":"JP",
    "name:jpn_x_preferred":[
        "\u52dd\u9023\u5e73\u5b89\u540d"
    ],
    "name:und_x_variant":[
        "Katsuren",
        "Heanna",
        "Fuenna",
        "Heianna",
        "Henna",
        "Katsuren-henna"
    ],
    "wof:name":"Katsuren-henna",
    "wof:placetype":"locality"
},
  "geometry": {"coordinates":[127.89045,26.3213],"type":"Point"}
}