{
  "type": "Feature",
  "properties": {
    "gn:admin1_code":"23.0",
    "gn:admin2_code":"1849544.0",
    "gn:asciiname":"Ichishicho-onoki",
    "gn:country_code":"JP",
    "gn:dem":24,
    "gn:feature_class":"P",
    "gn:feature_code":"PPL",
    "gn:name":"Ichishich\u014d-\u014dnoki",
    "gn:population":0,
    "gn:timezone":"Asia/Tokyo",
    "iso:country":"JP",
    "name:jpn_x_preferred":[
        "\u4e00\u5fd7\u753a\u5927\u4ef0"
    ],
    "name:und_x_variant":[
        "Ichishich\u014d-\u014dnoki"
    ],
    "wof:name":"Ichishicho-onoki",
    "wof:placetype":"locality"
},
  "geometry": {"coordinates":[136.40450000000001,34.64552],"type":"Point"}
}