{
  "type": "Feature",
  "properties": {
    "gn:admin1_code":"34.0",
    "gn:admin2_code":"1849187.0",
    "gn:admin3_code":"11110.0",
    "gn:asciiname":"Mashinaga",
    "gn:country_code":"JP",
    "gn:dem":6,
    "gn:feature_class":"P",
    "gn:feature_code":"PPL",
    "gn:name":"Mashinaga",
    "gn:population":0,
    "gn:timezone":"Asia/Tokyo",
    "iso:country":"JP",
    "name:jpn_x_preferred":[
        "\u5897\u9577"
    ],
    "name:jpn_x_variant":[
        "\u307e\u3057\u306a\u304c",
        "\u30de\u30b7\u30ca\u30ac"
    ],
    "wof:name":"Mashinaga",
    "wof:placetype":"locality"
},
  "geometry": {"coordinates":[139.73936,35.94768],"type":"Point"}
}