{
  "type": "Feature",
  "properties": {
    "gn:admin1_code":"21.0",
    "gn:admin2_code":"1850743.0",
    "gn:asciiname":"Mukaida",
    "gn:country_code":"JP",
    "gn:dem":14,
    "gn:feature_class":"P",
    "gn:feature_code":"PPLL",
    "gn:name":"Mukaida",
    "gn:population":0,
    "gn:timezone":"Asia/Tokyo",
    "iso:country":"JP",
    "name:jpn_x_preferred":[
        "\u8fce\u7530"
    ],
    "name:jpn_x_variant":[
        "\u3080\u304b\u3044\u3060",
        "\u30e0\u30ab\u30a4\u30c0"
    ],
    "wof:name":"Mukaida",
    "wof:placetype":"locality"
},
  "geometry": {"coordinates":[130.5076,32.93851],"type":"Point"}
}