{
  "type": "Feature",
  "properties": {
    "gn:admin1_code":"40.0",
    "gn:admin2_code":"1852582.0",
    "gn:asciiname":"Oyamacho",
    "gn:country_code":"JP",
    "gn:dem":42,
    "gn:feature_class":"P",
    "gn:feature_code":"PPL",
    "gn:name":"\u014cyamach\u014d",
    "gn:population":0,
    "gn:timezone":"Asia/Tokyo",
    "iso:country":"JP",
    "name:jpn_x_preferred":[
        "\u5927\u5c71\u753a"
    ],
    "name:und_x_variant":[
        "\u014cyamach\u014d"
    ],
    "wof:name":"Oyamacho",
    "wof:placetype":"locality"
},
  "geometry": {"coordinates":[139.6755,35.66878],"type":"Point"}
}