{
  "type": "Feature",
  "properties": {
    "gn:admin1_code":"29.0",
    "gn:admin2_code":"1859907.0",
    "gn:asciiname":"Higashinagatori",
    "gn:country_code":"JP",
    "gn:dem":121,
    "gn:feature_class":"P",
    "gn:feature_code":"PPL",
    "gn:name":"Higashinagatori",
    "gn:population":0,
    "gn:timezone":"Asia/Tokyo",
    "iso:country":"JP",
    "name:jpn_x_preferred":[
        "\u6771\u9577\u9ce5"
    ],
    "wof:name":"Higashinagatori",
    "wof:placetype":"locality"
},
  "geometry": {"coordinates":[138.68676000000002,37.38026],"type":"Point"}
}