{
  "type": "Feature",
  "properties": {
    "gn:admin1_code":"29.0",
    "gn:admin2_code":"1855427.0",
    "gn:admin3_code":"15101.0",
    "gn:asciiname":"Washizu",
    "gn:country_code":"JP",
    "gn:dem":0,
    "gn:feature_class":"P",
    "gn:feature_code":"PPLL",
    "gn:name":"Washizu",
    "gn:population":0,
    "gn:timezone":"Asia/Tokyo",
    "iso:country":"JP",
    "name:jpn_x_preferred":[
        "\u9df2\u6d25"
    ],
    "wof:name":"Washizu",
    "wof:placetype":"locality"
},
  "geometry": {"coordinates":[139.21729999999999,37.87884],"type":"Point"}
}