{
  "type": "Feature",
  "properties": {
    "gn:admin1_code":"21.0",
    "gn:admin2_code":"7413152.0",
    "gn:asciiname":"Deharu",
    "gn:country_code":"JP",
    "gn:dem":37,
    "gn:feature_class":"P",
    "gn:feature_code":"PPLL",
    "gn:name":"Deharu",
    "gn:population":0,
    "gn:timezone":"Asia/Tokyo",
    "iso:country":"JP",
    "name:jpn_x_preferred":[
        "\u51fa\u6625"
    ],
    "name:jpn_x_variant":[
        "\u3067\u306f\u308b",
        "\u30c7\u30cf\u30eb"
    ],
    "wof:name":"Deharu",
    "wof:placetype":"locality"
},
  "geometry": {"coordinates":[130.74217999999999,32.57606],"type":"Point"}
}