{
  "type": "Feature",
  "properties": {
    "gn:admin1_code":"37.0",
    "gn:admin2_code":"1864104.0",
    "gn:asciiname":"Nonaka",
    "gn:country_code":"JP",
    "gn:dem":132,
    "gn:feature_class":"P",
    "gn:feature_code":"PPL",
    "gn:name":"Nonaka",
    "gn:population":0,
    "gn:timezone":"Asia/Tokyo",
    "iso:country":"JP",
    "name:jpn_x_preferred":[
        "\u91ce\u4e2d"
    ],
    "name:rus_x_preferred":[
        "\u041d\u043e\u043d\u0430\u043a\u0430"
    ],
    "wof:name":"Nonaka",
    "wof:placetype":"locality"
},
  "geometry": {"coordinates":[138.61008000000001,35.21239],"type":"Point"}
}