{
  "type": "Feature",
  "properties": {
    "gn:admin1_code":"33.0",
    "gn:admin2_code":"7391355.0",
    "gn:asciiname":"Okawacho-kawabaru",
    "gn:country_code":"JP",
    "gn:dem":36,
    "gn:feature_class":"P",
    "gn:feature_code":"PPL",
    "gn:name":"\u014ckawach\u014d-kawabaru",
    "gn:population":0,
    "gn:timezone":"Asia/Tokyo",
    "iso:country":"JP",
    "name:jpn_x_preferred":[
        "\u5927\u5ddd\u753a\u5ddd\u539f"
    ],
    "name:und_x_variant":[
        "\u014ckawach\u014d-kawabaru"
    ],
    "wof:name":"Okawacho-kawabaru",
    "wof:placetype":"locality"
},
  "geometry": {"coordinates":[129.97223,33.28339],"type":"Point"}
}