{
  "type": "Feature",
  "properties": {
    "gn:admin1_code":"8.0",
    "gn:admin2_code":"2112921.0",
    "gn:asciiname":"Obara",
    "gn:country_code":"JP",
    "gn:dem":74,
    "gn:feature_class":"P",
    "gn:feature_code":"PPLL",
    "gn:name":"Obara",
    "gn:population":0,
    "gn:timezone":"Asia/Tokyo",
    "iso:country":"JP",
    "name:jpn_x_preferred":[
        "\u5c0f\u539f"
    ],
    "name:por_x_preferred":[
        "Obara"
    ],
    "name:slv_x_preferred":[
        "Obara"
    ],
    "name:spa_x_preferred":[
        "Obara"
    ],
    "wof:name":"Obara",
    "wof:placetype":"locality"
},
  "geometry": {"coordinates":[140.47937999999999,37.71762],"type":"Point"}
}