{
  "type": "Feature",
  "properties": {
    "gn:admin1_code":"18.0",
    "gn:admin2_code":"7383999.0",
    "gn:admin3_code":"46492.0",
    "gn:asciiname":"Tsuji",
    "gn:country_code":"JP",
    "gn:dem":57,
    "gn:feature_class":"P",
    "gn:feature_code":"PPLL",
    "gn:name":"Tsuji",
    "gn:population":0,
    "gn:timezone":"Asia/Tokyo",
    "iso:country":"JP",
    "name:jpn_x_preferred":[
        "\u8fbb"
    ],
    "wof:name":"Tsuji",
    "wof:placetype":"locality"
},
  "geometry": {"coordinates":[130.90451999999999,31.38557],"type":"Point"}
}