{
  "type": "Feature",
  "properties": {
    "iso:country":"JP",
    "name:eng_x_preferred":[
        "Miyoshi 2 Chome"
    ],
    "name:eng_x_variant":[
        "Miyoshi 2 Choume",
        "Miyoshi 2 Chome"
    ],
    "name:jpn_x_preferred":[
        "\uff12\u4e01\u76ee"
    ],
    "name:jpn_x_variant":[
        "\u307f\u3088\u3057 \uff12\u3061\u3087\u3046\u3081",
        "\u4e09\u597d \uff12\u4e01\u76ee",
        "\uff12\u3061\u3087\u3046\u3081"
    ],
    "qs:gn_adm0_cc":"JP",
    "qs:gn_local":1850147,
    "qs:local_max":18112,
    "qs:local_sum":895907,
    "qs:localhoods":857,
    "qs:name":"\uff12\u4e01\u76ee",
    "qs:name_adm0":"\u65e5\u672c",
    "qs:name_adm1":"\u6771\u4eac\u90fd",
    "qs:name_adm2":"\u6c5f\u6771\u533a",
    "qs:name_en":"Miyoshi 2 Chome",
    "qs:name_lau":"\u4e09\u597d",
    "qs:name_local":"\u6771\u4eac",
    "qs:photo_max":281,
    "qs:photo_sum":754,
    "qs:placetype":"Suburb",
    "qs:quad_count":7,
    "qs:woe_adm0":23424856,
    "qs:woe_adm1":2345889,
    "qs:woe_adm2":15015377,
    "qs:woe_lau":28414216,
    "qs:woe_local":1118370,
    "qs:woe_ver":"7.10.0",
    "wof:lang":[
        "jpn"
    ],
    "wof:name":"\uff12\u4e01\u76ee",
    "wof:placetype":"neighbourhood"
},
  "geometry": {"coordinates":[139.80455000000001,35.680113],"type":"Point"}
}