{
  "type": "Feature",
  "properties": {
    "gn:admin1_code":"21.0",
    "gn:admin2_code":"1865358.0",
    "gn:asciiname":"Hondomachi-hontobaba",
    "gn:country_code":"JP",
    "gn:dem":38,
    "gn:feature_class":"P",
    "gn:feature_code":"PPL",
    "gn:name":"Hondomachi-hontobaba",
    "gn:population":0,
    "gn:timezone":"Asia/Tokyo",
    "iso:country":"JP",
    "name:jpn_x_preferred":[
        "\u672c\u6e21\u753a\u672c\u6238\u99ac\u5834"
    ],
    "name:jpn_x_variant":[
        "\u307b\u3093\u3069\u307e\u3061\u307b\u3093\u3068\u3070\u3070",
        "\u30db\u30f3\u30c9\u30de\u30c1\u30db\u30f3\u30c8\u30d0\u30d0"
    ],
    "wof:name":"Hondomachi-hontobaba",
    "wof:placetype":"locality"
},
  "geometry": {"coordinates":[130.17425,32.46953],"type":"Point"}
}