{
  "type": "Feature",
  "properties": {
    "iso:country":"JP",
    "name:eng_x_preferred":[
        "Hongo 1 Chome"
    ],
    "name:eng_x_variant":[
        "Hongou 1 Choume",
        "Hongo 1 Chome"
    ],
    "name:jpn_x_preferred":[
        "\uff11\u4e01\u76ee"
    ],
    "name:jpn_x_variant":[
        "\u307b\u3093\u3054\u3046 \uff11\u3061\u3087\u3046\u3081",
        "\u672c\u90f7 \uff11\u4e01\u76ee",
        "\uff11\u3061\u3087\u3046\u3081"
    ],
    "name:unk_x_variant":[
        "\uff11\u4e01\u76ee"
    ],
    "qs:gn_local":0,
    "qs:local_max":3194,
    "qs:local_sum":30209,
    "qs:localhoods":92,
    "qs:name":"\uff11\u4e01\u76ee",
    "qs:name_adm0":"\u65e5\u672c",
    "qs:name_adm1":"\u611b\u77e5\u770c",
    "qs:name_adm2":"\u540d\u6771\u533a",
    "qs:name_en":"Hongo 1 Chome",
    "qs:name_lau":"\u672c\u90f7",
    "qs:name_local":"\u540d\u53e4\u5c4b\u5e02",
    "qs:photo_max":28,
    "qs:photo_sum":51,
    "qs:placetype":"Suburb",
    "qs:quad_count":4,
    "qs:woe_adm0":23424856,
    "qs:woe_adm1":2345851,
    "qs:woe_adm2":15015554,
    "qs:woe_lau":28440291,
    "qs:woe_local":1117817,
    "qs:woe_ver":"7.10.0",
    "wof:lang":[
        "jpn"
    ],
    "wof:name":"\uff11\u4e01\u76ee",
    "wof:placetype":"neighbourhood"
},
  "geometry": {"coordinates":[137.02153200000001,35.18077],"type":"Point"}
}