{
  "type": "Feature",
  "properties": {
    "gn:admin1_code":"21.0",
    "gn:admin2_code":"7412706.0",
    "gn:admin3_code":"43441.0",
    "gn:asciiname":"Shoji",
    "gn:country_code":"JP",
    "gn:dem":28,
    "gn:feature_class":"P",
    "gn:feature_code":"PPLL",
    "gn:name":"Sh\u014dji",
    "gn:population":0,
    "gn:timezone":"Asia/Tokyo",
    "iso:country":"JP",
    "name:jpn_x_preferred":[
        "\u5c0f\u8def"
    ],
    "name:jpn_x_variant":[
        "\u3057\u3087\u3046\u3058",
        "\u30b7\u30e7\u30a6\u30b8"
    ],
    "name:und_x_variant":[
        "Sh\u014dji"
    ],
    "wof:name":"Shoji",
    "wof:placetype":"locality"
},
  "geometry": {"coordinates":[130.80983000000001,32.72635],"type":"Point"}
}