{
  "type": "Feature",
  "properties": {
    "gn:admin1_code":"21.0",
    "gn:admin2_code":"7412706.0",
    "gn:admin3_code":"43447.0",
    "gn:asciiname":"Tsubonouchi",
    "gn:country_code":"JP",
    "gn:dem":545,
    "gn:feature_class":"P",
    "gn:feature_code":"PPLL",
    "gn:name":"Tsubonouchi",
    "gn:population":0,
    "gn:timezone":"Asia/Tokyo",
    "iso:country":"JP",
    "name:jpn_x_preferred":[
        "\u576a\u306e\u5185"
    ],
    "name:jpn_x_variant":[
        "\u3064\u307c\u306e\u3046\u3061",
        "\u30c4\u30dc\u30ce\u30a6\u30c1"
    ],
    "wof:name":"Tsubonouchi",
    "wof:placetype":"locality"
},
  "geometry": {"coordinates":[131.00048000000001,32.72874],"type":"Point"}
}