{
  "type": "Feature",
  "properties": {
    "gn:admin1_code":"12.0",
    "gn:admin2_code":"2127513.0",
    "gn:asciiname":"Kiyohama",
    "gn:country_code":"JP",
    "gn:dem":15,
    "gn:feature_class":"P",
    "gn:feature_code":"PPLL",
    "gn:name":"Kiyohama",
    "gn:population":0,
    "gn:timezone":"Asia/Tokyo",
    "iso:country":"JP",
    "name:jpn_x_preferred":[
        "\u6e05\u6d5c"
    ],
    "name:jpn_x_variant":[
        "\u304d\u3088\u306f\u307e",
        "\u30ad\u30e8\u30cf\u30de"
    ],
    "wof:name":"Kiyohama",
    "wof:placetype":"locality"
},
  "geometry": {"coordinates":[141.89049,45.49867],"type":"Point"}
}