{
  "type": "Feature",
  "properties": {
    "gn:admin1_code":"13.0",
    "gn:admin2_code":"1851011.0",
    "gn:asciiname":"Kawamo",
    "gn:country_code":"JP",
    "gn:dem":40,
    "gn:feature_class":"P",
    "gn:feature_code":"PPL",
    "gn:name":"Kawamo",
    "gn:population":0,
    "gn:timezone":"Asia/Tokyo",
    "iso:country":"JP",
    "name:jpn_x_preferred":[
        "\u5ddd\u9762"
    ],
    "wof:name":"Kawamo",
    "wof:placetype":"locality"
},
  "geometry": {"coordinates":[135.3477,34.81108],"type":"Point"}
}