{
  "type": "Feature",
  "properties": {
    "gn:admin1_code":"27.0",
    "gn:admin2_code":"7418810.0",
    "gn:asciiname":"Nakamichidan",
    "gn:country_code":"JP",
    "gn:dem":25,
    "gn:feature_class":"P",
    "gn:feature_code":"PPL",
    "gn:name":"Nakamichidan",
    "gn:population":0,
    "gn:timezone":"Asia/Tokyo",
    "iso:country":"JP",
    "name:jpn_x_preferred":[
        "\u4e2d\u9053\u58c7"
    ],
    "wof:name":"Nakamichidan",
    "wof:placetype":"locality"
},
  "geometry": {"coordinates":[129.28666000000001,34.27539],"type":"Point"}
}