{
  "type": "Feature",
  "properties": {
    "gn:admin1_code":"21.0",
    "gn:admin2_code":"1859488.0",
    "gn:asciiname":"Hiraraishi",
    "gn:country_code":"JP",
    "gn:dem":222,
    "gn:feature_class":"P",
    "gn:feature_code":"PPLL",
    "gn:name":"Hiraraishi",
    "gn:population":0,
    "gn:timezone":"Asia/Tokyo",
    "iso:country":"JP",
    "name:jpn_x_preferred":[
        "\u5e73\u826f\u3005\u77f3"
    ],
    "name:jpn_x_variant":[
        "\u3072\u3089\u3089\u3044\u3057",
        "\u30d2\u30e9\u30e9\u30a4\u30b7"
    ],
    "wof:name":"Hiraraishi",
    "wof:placetype":"locality"
},
  "geometry": {"coordinates":[130.85135,32.99274],"type":"Point"}
}