{
  "type": "Feature",
  "properties": {
    "gn:admin1_code":"3.0",
    "gn:admin2_code":"2130654.0",
    "gn:asciiname":"Nandai",
    "gn:country_code":"JP",
    "gn:dem":61,
    "gn:feature_class":"P",
    "gn:feature_code":"PPL",
    "gn:name":"Nandai",
    "gn:population":0,
    "gn:timezone":"Asia/Tokyo",
    "iso:country":"JP",
    "name:jpn_x_preferred":[
        "\u5357\u5927"
    ],
    "name:jpn_x_variant":[
        "\u306a\u3093\u3060\u3044",
        "\u30ca\u30f3\u30c0\u30a4"
    ],
    "wof:name":"Nandai",
    "wof:placetype":"locality"
},
  "geometry": {"coordinates":[140.59209999999999,40.75358],"type":"Point"}
}