{
  "type": "Feature",
  "properties": {
    "gn:admin1_code":"4.0",
    "gn:admin2_code":"1863711.0",
    "gn:asciiname":"Kochayatsu",
    "gn:country_code":"JP",
    "gn:dem":16,
    "gn:feature_class":"P",
    "gn:feature_code":"PPLL",
    "gn:name":"Kochayatsu",
    "gn:population":0,
    "gn:timezone":"Asia/Tokyo",
    "iso:country":"JP",
    "name:jpn_x_preferred":[
        "\u6771\u98a8\u8c37"
    ],
    "name:jpn_x_variant":[
        "\u3053\u3061\u3083\u3084\u3064",
        "\u30b3\u30c1\u30e3\u30e4\u30c4"
    ],
    "wof:name":"Kochayatsu",
    "wof:placetype":"locality"
},
  "geometry": {"coordinates":[139.87736999999998,35.30089],"type":"Point"}
}