{
  "type": "Feature",
  "properties": {
    "gn:admin1_code":"4.0",
    "gn:admin2_code":"2112663.0",
    "gn:asciiname":"Hirano",
    "gn:country_code":"JP",
    "gn:dem":47,
    "gn:feature_class":"P",
    "gn:feature_code":"PPL",
    "gn:name":"Hirano",
    "gn:population":0,
    "gn:timezone":"Asia/Tokyo",
    "iso:country":"JP",
    "name:jpn_x_preferred":[
        "\u5e73\u91ce"
    ],
    "name:jpn_x_variant":[
        "\u3072\u3089\u306e",
        "\u30d2\u30e9\u30ce"
    ],
    "wof:name":"Hirano",
    "wof:placetype":"locality"
},
  "geometry": {"coordinates":[140.14698999999999,35.3358],"type":"Point"}
}