{
  "type": "Feature",
  "properties": {
    "gn:admin1_code":"33.0",
    "gn:admin2_code":"7391355.0",
    "gn:asciiname":"Ichiyama",
    "gn:country_code":"JP",
    "gn:dem":46,
    "gn:feature_class":"P",
    "gn:feature_code":"PPLL",
    "gn:name":"Ichiyama",
    "gn:population":0,
    "gn:timezone":"Asia/Tokyo",
    "iso:country":"JP",
    "name:jpn_x_preferred":[
        "\u5e02\u5c71"
    ],
    "wof:name":"Ichiyama",
    "wof:placetype":"locality"
},
  "geometry": {"coordinates":[129.90423000000001,33.25212],"type":"Point"}
}