{
  "type": "Feature",
  "properties": {
    "gn:admin1_code":"3.0",
    "gn:admin2_code":"2130056.0",
    "gn:asciiname":"Tonosaki",
    "gn:country_code":"JP",
    "gn:dem":35,
    "gn:feature_class":"P",
    "gn:feature_code":"PPL",
    "gn:name":"Tonosaki",
    "gn:population":0,
    "gn:timezone":"Asia/Tokyo",
    "iso:country":"JP",
    "name:jpn_x_preferred":[
        "\u5916\u5d0e"
    ],
    "name:jpn_x_variant":[
        "\u3068\u306e\u3055\u304d",
        "\u30c8\u30ce\u30b5\u30ad"
    ],
    "wof:name":"Tonosaki",
    "wof:placetype":"locality"
},
  "geometry": {"coordinates":[140.49428999999998,40.59639],"type":"Point"}
}