{
  "type": "Feature",
  "properties": {
    "gn:admin1_code":"24.0",
    "gn:admin2_code":"7447001.0",
    "gn:asciiname":"Hara",
    "gn:country_code":"JP",
    "gn:dem":308,
    "gn:feature_class":"P",
    "gn:feature_code":"PPL",
    "gn:name":"Hara",
    "gn:population":0,
    "gn:timezone":"Asia/Tokyo",
    "iso:country":"JP",
    "name:ceb_x_preferred":[
        "Hara"
    ],
    "name:deu_x_preferred":[
        "Hara"
    ],
    "name:est_x_preferred":[
        "Hara"
    ],
    "name:fin_x_preferred":[
        "Hara"
    ],
    "name:fra_x_preferred":[
        "Hara"
    ],
    "name:jpn_x_preferred":[
        "\u539f"
    ],
    "name:jpn_x_variant":[
        "\u306f\u3089",
        "\u30cf\u30e9"
    ],
    "name:nld_x_preferred":[
        "Hara"
    ],
    "name:pol_x_preferred":[
        "Hara"
    ],
    "name:por_x_preferred":[
        "Hara"
    ],
    "name:spa_x_preferred":[
        "Hara"
    ],
    "name:swe_x_preferred":[
        "Hara"
    ],
    "name:vol_x_preferred":[
        "Hara"
    ],
    "wof:name":"Hara",
    "wof:placetype":"locality"
},
  "geometry": {"coordinates":[140.65000000000001,38.8025],"type":"Point"}
}