{
  "type": "Feature",
  "properties": {
    "iso:country":"JP",
    "name:eng_x_preferred":[
        "Sumiyoshiminamimachi 2 Chome"
    ],
    "name:eng_x_variant":[
        "Sumiyoshiminamimachi 2 Choume",
        "Sumiyoshiminamimachi 2 Chome"
    ],
    "name:jpn_x_preferred":[
        "\uff12\u4e01\u76ee"
    ],
    "name:jpn_x_variant":[
        "\u3059\u307f\u3088\u3057\u307f\u306a\u307f\u307e\u3061 \uff12\u3061\u3087\u3046\u3081",
        "\u4f4f\u5409\u5357\u753a \uff12\u4e01\u76ee",
        "\uff12\u3061\u3087\u3046\u3081"
    ],
    "qs:gn_local":0,
    "qs:local_max":2400,
    "qs:local_sum":22318,
    "qs:localhoods":72,
    "qs:name":"\uff12\u4e01\u76ee",
    "qs:name_adm0":"\u65e5\u672c",
    "qs:name_adm1":"\u5175\u5eab\u770c",
    "qs:name_adm2":"\u6771\u7058\u533a",
    "qs:name_en":"Sumiyoshiminamimachi 2 Chome",
    "qs:name_lau":"\u4f4f\u5409\u5357\u753a",
    "qs:name_local":"\u795e\u6238\u5e02",
    "qs:photo_max":2,
    "qs:photo_sum":3,
    "qs:placetype":"Suburb",
    "qs:quad_count":2,
    "qs:woe_adm0":23424856,
    "qs:woe_adm1":2345862,
    "qs:woe_adm2":15015514,
    "qs:woe_lau":28460569,
    "qs:woe_local":1117545,
    "qs:woe_ver":"7.10.0",
    "wof:lang":[
        "jpn"
    ],
    "wof:name":"\uff12\u4e01\u76ee",
    "wof:placetype":"neighbourhood"
},
  "geometry": {"coordinates":[135.26458700000001,34.710761],"type":"Point"}
}