{
  "type": "Feature",
  "properties": {
    "gn:admin1_code":"40.0",
    "gn:admin2_code":"1865750.0",
    "gn:asciiname":"Senju-kawaracho",
    "gn:country_code":"JP",
    "gn:dem":4,
    "gn:feature_class":"P",
    "gn:feature_code":"PPL",
    "gn:name":"Senju-kawarach\u014d",
    "gn:population":0,
    "gn:timezone":"Asia/Tokyo",
    "iso:country":"JP",
    "name:jpn_x_preferred":[
        "\u5343\u4f4f\u6cb3\u539f\u753a"
    ],
    "name:und_x_variant":[
        "Senju-kawarach\u014d"
    ],
    "wof:name":"Senju-kawaracho",
    "wof:placetype":"locality"
},
  "geometry": {"coordinates":[139.79936999999998,35.74319000000001],"type":"Point"}
}