{
  "type": "Feature",
  "properties": {
    "gn:admin1_code":"3.0",
    "gn:admin2_code":"2130654.0",
    "gn:asciiname":"Kuwabara",
    "gn:country_code":"JP",
    "gn:dem":26,
    "gn:feature_class":"P",
    "gn:feature_code":"PPL",
    "gn:name":"Kuwabara",
    "gn:population":0,
    "gn:timezone":"Asia/Tokyo",
    "iso:country":"JP",
    "name:jpn_x_preferred":[
        "\u6851\u539f"
    ],
    "name:jpn_x_variant":[
        "\u304f\u308f\u3070\u3089",
        "\u30af\u30ef\u30d0\u30e9"
    ],
    "name:rus_x_preferred":[
        "\u041a\u0443\u0432\u0430\u0431\u0430\u0440\u0430"
    ],
    "wof:name":"Kuwabara",
    "wof:placetype":"locality"
},
  "geometry": {"coordinates":[140.81094999999999,40.8193],"type":"Point"}
}