{
  "type": "Feature",
  "properties": {
    "gn:admin1_code":"46.0",
    "gn:admin2_code":"1857168.0",
    "gn:admin3_code":"19365.0",
    "gn:asciiname":"Oiso-koiso",
    "gn:country_code":"JP",
    "gn:dem":510,
    "gn:feature_class":"P",
    "gn:feature_code":"PPL",
    "gn:name":"\u014ciso-koiso",
    "gn:population":0,
    "gn:timezone":"Asia/Tokyo",
    "iso:country":"JP",
    "name:jpn_x_preferred":[
        "\u5927\u78ef\u5c0f\u78ef"
    ],
    "name:und_x_variant":[
        "\u014ciso-koiso"
    ],
    "wof:name":"Oiso-koiso",
    "wof:placetype":"locality"
},
  "geometry": {"coordinates":[138.53276,35.497],"type":"Point"}
}