{
  "type": "Feature",
  "properties": {
    "gn:admin1_code":"18",
    "gn:admin2_code":"1855201.0",
    "gn:asciiname":"Genna",
    "gn:country_code":"JP",
    "gn:dem":58,
    "gn:feature_class":"P",
    "gn:feature_code":"PPL",
    "gn:name":"Genna",
    "gn:population":0,
    "gn:timezone":"Asia/Tokyo",
    "iso:country":"JP",
    "name:deu_x_preferred":[
        "Genna"
    ],
    "name:fas_x_preferred":[
        "\u06af\u0646\u0646\u0627"
    ],
    "name:fra_x_preferred":[
        "\u00c8re Genna"
    ],
    "name:ind_x_preferred":[
        "Genna"
    ],
    "name:ita_x_preferred":[
        "Genna"
    ],
    "name:jpn_x_preferred":[
        "\u73fe\u548c"
    ],
    "name:jpn_x_variant":[
        "\u5143\u548c"
    ],
    "name:rus_x_preferred":[
        "\u0413\u044d\u043d\u043d\u0430"
    ],
    "name:spa_x_preferred":[
        "Genna"
    ],
    "name:srp_x_preferred":[
        "\u0413\u0435\u043d\u0430"
    ],
    "name:swe_x_preferred":[
        "Genna"
    ],
    "name:und_x_variant":[
        "Kenna"
    ],
    "name:zho_x_preferred":[
        "\u5143\u548c"
    ],
    "wof:name":"Genna",
    "wof:placetype":"locality"
},
  "geometry": {"coordinates":[131.05409,30.70842],"type":"Point"}
}