{
  "type": "Feature",
  "properties": {
    "gn:admin1_code":"18",
    "gn:admin2_code":"1855201.0",
    "gn:asciiname":"Genna",
    "gn:country_code":"JP",
    "gn:dem":58,
    "gn:feature_class":"P",
    "gn:feature_code":"PPL",
    "gn:name":"Genna",
    "gn:population":0,
    "gn:timezone":"Asia/Tokyo",
    "iso:country":"JP",
    "name:jpn_x_preferred":[
        "\u73fe\u548c"
    ],
    "name:und_x_variant":[
        "Kenna",
        "Genna"
    ],
    "wof:name":"Genna",
    "wof:placetype":"locality"
},
  "geometry": {"coordinates":[131.05409,30.70842],"type":"Point"}
}