{
  "type": "Feature",
  "properties": {
    "gn:admin1_code":"21.0",
    "gn:admin2_code":"1848441.0",
    "gn:asciiname":"Taikan",
    "gn:country_code":"JP",
    "gn:dem":0,
    "gn:feature_class":"P",
    "gn:feature_code":"PPLL",
    "gn:name":"Taikan",
    "gn:population":0,
    "gn:timezone":"Asia/Tokyo",
    "iso:country":"JP",
    "name:jpn_x_preferred":[
        "\u5927\u9084"
    ],
    "name:jpn_x_variant":[
        "\u305f\u3044\u304b\u3093",
        "\u30bf\u30a4\u30ab\u30f3"
    ],
    "wof:name":"Taikan",
    "wof:placetype":"locality"
},
  "geometry": {"coordinates":[130.63459,32.58839],"type":"Point"}
}