{
  "type": "Feature",
  "properties": {
    "gn:admin1_code":"12.0",
    "gn:admin2_code":"2130058.0",
    "gn:admin3_code":"1642.0",
    "gn:asciiname":"Maruyamadori-minami",
    "gn:country_code":"JP",
    "gn:dem":47,
    "gn:feature_class":"P",
    "gn:feature_code":"PPL",
    "gn:name":"Maruyamad\u014dri-minami",
    "gn:population":0,
    "gn:timezone":"Asia/Tokyo",
    "iso:country":"JP",
    "name:jpn_x_preferred":[
        "\u4e38\u5c71\u901a\u5357"
    ],
    "name:jpn_x_variant":[
        "\u307e\u308b\u3084\u307e\u3069\u304a\u308a\u307f\u306a\u307f",
        "\u30de\u30eb\u30e4\u30de\u30c9\u30aa\u30ea\u30df\u30ca\u30df"
    ],
    "name:und_x_variant":[
        "Maruyamad\u014dri-minami"
    ],
    "wof:name":"Maruyamadori-minami",
    "wof:placetype":"locality"
},
  "geometry": {"coordinates":[143.30382,42.29418],"type":"Point"}
}