{
  "type": "Feature",
  "properties": {
    "gn:admin1_code":"21.0",
    "gn:admin2_code":"1857206.0",
    "gn:asciiname":"Ariki",
    "gn:country_code":"JP",
    "gn:dem":212,
    "gn:feature_class":"P",
    "gn:feature_code":"PPLL",
    "gn:name":"Ariki",
    "gn:population":0,
    "gn:timezone":"Asia/Tokyo",
    "iso:country":"JP",
    "name:fin_x_preferred":[
        "Ariki"
    ],
    "name:fra_x_preferred":[
        "Ariki"
    ],
    "name:glg_x_preferred":[
        "Ariki"
    ],
    "name:jpn_x_preferred":[
        "\u6709\u6728"
    ],
    "name:jpn_x_variant":[
        "\u3042\u308a\u304d",
        "\u30a2\u30ea\u30ad"
    ],
    "name:lit_x_preferred":[
        "Ariki"
    ],
    "name:pol_x_preferred":[
        "Ariki"
    ],
    "name:spa_x_preferred":[
        "Ariki"
    ],
    "wof:name":"Ariki",
    "wof:placetype":"locality"
},
  "geometry": {"coordinates":[130.53731999999999,32.16931],"type":"Point"}
}