{
  "type": "Feature",
  "properties": {
    "gn:admin1_code":"28.0",
    "gn:admin2_code":"1855604.0",
    "gn:asciiname":"Shijo-oji",
    "gn:country_code":"JP",
    "gn:dem":60,
    "gn:feature_class":"P",
    "gn:feature_code":"PPL",
    "gn:name":"Shij\u014d-\u014dji",
    "gn:population":0,
    "gn:timezone":"Asia/Tokyo",
    "iso:country":"JP",
    "name:jpn_x_preferred":[
        "\u56db\u6761\u5927\u8def"
    ],
    "name:und_x_variant":[
        "Shij\u014d-\u014dji"
    ],
    "wof:name":"Shijo-oji",
    "wof:placetype":"locality"
},
  "geometry": {"coordinates":[135.79709,34.67993],"type":"Point"}
}