{
  "type": "Feature",
  "properties": {
    "gn:admin1_code":"21.0",
    "gn:admin2_code":"7412706.0",
    "gn:admin3_code":"43443.0",
    "gn:asciiname":"Uchidera",
    "gn:country_code":"JP",
    "gn:dem":72,
    "gn:feature_class":"P",
    "gn:feature_code":"PPLL",
    "gn:name":"Uchidera",
    "gn:population":0,
    "gn:timezone":"Asia/Tokyo",
    "iso:country":"JP",
    "name:jpn_x_preferred":[
        "\u5185\u5bfa"
    ],
    "name:jpn_x_variant":[
        "\u3046\u3061\u3067\u3089",
        "\u30a6\u30c1\u30c7\u30e9"
    ],
    "wof:name":"Uchidera",
    "wof:placetype":"locality"
},
  "geometry": {"coordinates":[130.84343000000001,32.77741],"type":"Point"}
}