{
  "type": "Feature",
  "properties": {
    "gn:admin1_code":"3.0",
    "gn:admin2_code":"2129393.0",
    "gn:asciiname":"Ichinomachi",
    "gn:country_code":"JP",
    "gn:dem":55,
    "gn:feature_class":"P",
    "gn:feature_code":"PPL",
    "gn:name":"Ichinomachi",
    "gn:population":0,
    "gn:timezone":"Asia/Tokyo",
    "iso:country":"JP",
    "name:jpn_x_preferred":[
        "\u5e02\u30ce\u753a"
    ],
    "name:jpn_x_variant":[
        "\u3044\u3061\u306e\u307e\u3061",
        "\u30a4\u30c1\u30ce\u30de\u30c1"
    ],
    "wof:name":"Ichinomachi",
    "wof:placetype":"locality"
},
  "geometry": {"coordinates":[140.59569999999999,40.6436],"type":"Point"}
}