{
  "type": "Feature",
  "properties": {
    "gn:admin1_code":"47",
    "gn:admin2_code":"1858371.0",
    "gn:admin3_code":"47301.0",
    "gn:asciiname":"Ura",
    "gn:country_code":"JP",
    "gn:dem":9,
    "gn:feature_class":"P",
    "gn:feature_code":"PPL",
    "gn:name":"Ura",
    "gn:population":0,
    "gn:timezone":"Asia/Tokyo",
    "iso:country":"JP",
    "name:cat_x_preferred":[
        "Ur\u00e0"
    ],
    "name:ceb_x_preferred":[
        "Ura"
    ],
    "name:chv_x_preferred":[
        "\u0423\u0440\u0430"
    ],
    "name:fra_x_preferred":[
        "Ura"
    ],
    "name:jpn_x_preferred":[
        "\u5b87\u826f"
    ],
    "name:jpn_x_variant":[
        "\u3046\u3089"
    ],
    "name:nno_x_preferred":[
        "Ura"
    ],
    "name:que_x_preferred":[
        "Ura"
    ],
    "name:rus_x_preferred":[
        "\u0423\u0440\u0430"
    ],
    "name:slv_x_preferred":[
        "Ura"
    ],
    "name:swe_x_preferred":[
        "Ura"
    ],
    "name:ukr_x_preferred":[
        "\u0423\u0440\u0430"
    ],
    "name:und_x_variant":[
        "Una"
    ],
    "wof:name":"Ura",
    "wof:placetype":"locality"
},
  "geometry": {"coordinates":[128.19007999999999,26.75239],"type":"Point"}
}