{
  "type": "Feature",
  "properties": {
    "iso:country":"JP",
    "name:eng_x_preferred":[
        "Kumegawacho 5 Chome"
    ],
    "name:eng_x_variant":[
        "Kumegawachou 5 Choume",
        "Kumegawacho 5 Chome"
    ],
    "name:jpn_x_preferred":[
        "\uff15\u4e01\u76ee"
    ],
    "name:jpn_x_variant":[
        "\u304f\u3081\u304c\u308f\u3061\u3087\u3046 \uff15\u3061\u3087\u3046\u3081",
        "\u4e45\u7c73\u5ddd\u753a \uff15\u4e01\u76ee",
        "\uff15\u3061\u3087\u3046\u3081"
    ],
    "name:unk_x_variant":[
        "\uff15\u4e01\u76ee"
    ],
    "qs:gn_adm0_cc":"JP",
    "qs:gn_local":7279570,
    "qs:gn_nam_loc":"\u6771\u6751\u5c71\u5e02, \u6771\u4eac\u90fd, JP",
    "qs:gn_namadm1":"40",
    "qs:local_max":1147,
    "qs:local_sum":3178,
    "qs:localhoods":10,
    "qs:name":"\uff15\u4e01\u76ee",
    "qs:name_adm0":"\u65e5\u672c",
    "qs:name_adm1":"\u6771\u4eac\u90fd",
    "qs:name_en":"Kumegawacho 5 Chome",
    "qs:name_lau":"\u4e45\u7c73\u5ddd\u753a",
    "qs:name_local":"\u6771\u6751\u5c71\u5e02",
    "qs:photo_max":24,
    "qs:photo_sum":40,
    "qs:placetype":"Suburb",
    "qs:quad_count":4,
    "qs:woe_adm0":23424856,
    "qs:woe_adm1":2345889,
    "qs:woe_adm2":0,
    "qs:woe_lau":28415186,
    "qs:woe_local":1108816,
    "qs:woe_ver":"7.10.0",
    "wof:lang":[
        "jpn"
    ],
    "wof:name":"\uff15\u4e01\u76ee",
    "wof:placetype":"neighbourhood"
},
  "geometry": {"coordinates":[139.46662900000001,35.771141],"type":"Point"}
}