{
  "type": "Feature",
  "properties": {
    "gn:admin1_code":"37.0",
    "gn:admin2_code":"1851376.0",
    "gn:asciiname":"Endohara",
    "gn:country_code":"JP",
    "gn:dem":186,
    "gn:feature_class":"P",
    "gn:feature_code":"PPLL",
    "gn:name":"End\u014dhara",
    "gn:population":0,
    "gn:timezone":"Asia/Tokyo",
    "iso:country":"JP",
    "name:jpn_x_preferred":[
        "\u9060\u85e4\u539f"
    ],
    "name:und_x_variant":[
        "End\u014dhara"
    ],
    "wof:name":"Endohara",
    "wof:placetype":"locality"
},
  "geometry": {"coordinates":[138.91493,35.19783],"type":"Point"}
}