{
  "type": "Feature",
  "properties": {
    "iso:country":"JP",
    "name:eng_x_preferred":[
        "Jindaiji 3 Chome"
    ],
    "name:eng_x_variant":[
        "Jindaiji 3 Choume",
        "Jindaiji 3 Chome"
    ],
    "name:jpn_x_preferred":[
        "\uff13\u4e01\u76ee"
    ],
    "name:jpn_x_variant":[
        "\u3058\u3093\u3060\u3044\u3058 \uff13\u3061\u3087\u3046\u3081",
        "\u6df1\u5927\u5bfa \uff13\u4e01\u76ee",
        "\uff13\u3061\u3087\u3046\u3081"
    ],
    "qs:gn_adm0_cc":"JP",
    "qs:gn_local":1856942,
    "qs:gn_nam_loc":"\u4e09\u9df9\u5e02, \u6771\u4eac\u90fd, JP",
    "qs:gn_namadm1":"40",
    "qs:local_max":1442,
    "qs:local_sum":5491,
    "qs:localhoods":16,
    "qs:name":"\uff13\u4e01\u76ee",
    "qs:name_adm0":"\u65e5\u672c",
    "qs:name_adm1":"\u6771\u4eac\u90fd",
    "qs:name_en":"Jindaiji 3 Chome",
    "qs:name_lau":"\u6df1\u5927\u5bfa",
    "qs:name_local":"\u4e09\u9df9\u5e02",
    "qs:photo_max":19,
    "qs:photo_sum":37,
    "qs:placetype":"Suburb",
    "qs:quad_count":4,
    "qs:woe_adm0":23424856,
    "qs:woe_adm1":2345889,
    "qs:woe_adm2":0,
    "qs:woe_lau":28414944,
    "qs:woe_local":1110112,
    "qs:woe_ver":"7.10.0",
    "wof:lang":[
        "jpn"
    ],
    "wof:name":"\uff13\u4e01\u76ee",
    "wof:placetype":"neighbourhood"
},
  "geometry": {"coordinates":[139.53935999999999,35.689546],"type":"Point"}
}