{
  "type": "Feature",
  "properties": {
    "gn:admin1_code":"37.0",
    "gn:admin2_code":"1864089.0",
    "gn:asciiname":"Funayamacho",
    "gn:country_code":"JP",
    "gn:dem":62,
    "gn:feature_class":"P",
    "gn:feature_code":"PPLL",
    "gn:name":"Funayamach\u014d",
    "gn:population":0,
    "gn:timezone":"Asia/Tokyo",
    "iso:country":"JP",
    "name:jpn_x_preferred":[
        "\u821f\u5c71\u753a"
    ],
    "name:und_x_variant":[
        "Funayamach\u014d"
    ],
    "wof:name":"Funayamacho",
    "wof:placetype":"locality"
},
  "geometry": {"coordinates":[138.61621,35.15899],"type":"Point"}
}