{
  "type": "Feature",
  "properties": {
    "gn:admin1_code":"43",
    "gn:admin2_code":"1865123.0",
    "gn:admin3_code":"30366.0",
    "gn:asciiname":"Oshide",
    "gn:country_code":"JP",
    "gn:dem":390,
    "gn:feature_class":"P",
    "gn:feature_code":"PPL",
    "gn:name":"Oshide",
    "gn:population":0,
    "gn:timezone":"Asia/Tokyo",
    "iso:country":"JP",
    "name:jpn_x_preferred":[
        "\u62bc\u624b"
    ],
    "name:und_x_variant":[
        "Oshite"
    ],
    "wof:name":"Oshide",
    "wof:placetype":"locality"
},
  "geometry": {"coordinates":[135.50649999999999,34.13092],"type":"Point"}
}