{
  "type": "Feature",
  "properties": {
    "gn:admin1_code":"13.0",
    "gn:admin2_code":"1855132.0",
    "gn:asciiname":"Tsukaguchicho",
    "gn:country_code":"JP",
    "gn:dem":91,
    "gn:feature_class":"P",
    "gn:feature_code":"PPL",
    "gn:name":"Tsukaguchich\u014d",
    "gn:population":0,
    "gn:timezone":"Asia/Tokyo",
    "iso:country":"JP",
    "name:jpn_x_preferred":[
        "\u585a\u53e3\u753a"
    ],
    "name:und_x_variant":[
        "Tsukaguchich\u014d"
    ],
    "wof:name":"Tsukaguchicho",
    "wof:placetype":"locality"
},
  "geometry": {"coordinates":[135.01558,34.98728],"type":"Point"}
}