{
  "type": "Feature",
  "properties": {
    "gn:admin1_code":"23.0",
    "gn:admin2_code":"1861901.0",
    "gn:asciiname":"Kaminosho",
    "gn:country_code":"JP",
    "gn:dem":146,
    "gn:feature_class":"P",
    "gn:feature_code":"PPL",
    "gn:name":"Kaminosh\u014d",
    "gn:population":0,
    "gn:timezone":"Asia/Tokyo",
    "iso:country":"JP",
    "name:jpn_x_preferred":[
        "\u4e0a\u4e4b\u5e84"
    ],
    "name:und_x_variant":[
        "Kaminosh\u014d"
    ],
    "wof:name":"Kaminosho",
    "wof:placetype":"locality"
},
  "geometry": {"coordinates":[136.11941000000002,34.73506],"type":"Point"}
}