{
  "type": "Feature",
  "properties": {
    "gn:admin1_code":"21.0",
    "gn:admin2_code":"1857206.0",
    "gn:asciiname":"Yamatecho",
    "gn:country_code":"JP",
    "gn:dem":7,
    "gn:feature_class":"P",
    "gn:feature_code":"PPL",
    "gn:name":"Yamatech\u014d",
    "gn:population":0,
    "gn:timezone":"Asia/Tokyo",
    "iso:country":"JP",
    "name:jpn_x_preferred":[
        "\u5c71\u624b\u753a"
    ],
    "name:jpn_x_variant":[
        "\u3084\u307e\u3066\u3061\u3087\u3046",
        "\u30e4\u30de\u30c6\u30c1\u30e7\u30a6"
    ],
    "name:und_x_variant":[
        "Yamatech\u014d"
    ],
    "wof:name":"Yamatecho",
    "wof:placetype":"locality"
},
  "geometry": {"coordinates":[130.39869999999999,32.20421],"type":"Point"}
}