{
  "type": "Feature",
  "properties": {
    "gn:admin1_code":"23.0",
    "gn:admin2_code":"1857496.0",
    "gn:asciiname":"Onocho",
    "gn:country_code":"JP",
    "gn:dem":20,
    "gn:feature_class":"P",
    "gn:feature_code":"PPL",
    "gn:name":"Onoch\u014d",
    "gn:population":0,
    "gn:timezone":"Asia/Tokyo",
    "iso:country":"JP",
    "name:jpn_x_preferred":[
        "\u5c0f\u91ce\u753a"
    ],
    "name:und_x_variant":[
        "Onoch\u014d"
    ],
    "wof:name":"Onocho",
    "wof:placetype":"locality"
},
  "geometry": {"coordinates":[136.46716000000001,34.60957],"type":"Point"}
}