{
  "type": "Feature",
  "properties": {
    "gn:admin1_code":"25",
    "gn:admin2_code":"7413968.0",
    "gn:admin3_code":"45443.0",
    "gn:asciiname":"Sankasho",
    "gn:country_code":"JP",
    "gn:dem":542,
    "gn:feature_class":"P",
    "gn:feature_code":"PPL",
    "gn:name":"Sankasho",
    "gn:population":0,
    "gn:timezone":"Asia/Tokyo",
    "iso:country":"JP",
    "name:und_x_variant":[
        "Sangasho"
    ],
    "wof:name":"Sankasho",
    "wof:placetype":"locality"
},
  "geometry": {"coordinates":[131.20833000000002,32.68176],"type":"Point"}
}