{
  "type": "Feature",
  "properties": {
    "gn:country":"JP",
    "gn:fcode":"ADM3",
    "gn:population":0,
    "iso:country":"JP",
    "name:eng_x_preferred":[
        "Mibu"
    ],
    "name:eng_x_variant":[
        "Mibu-machi"
    ],
    "name:jpn_x_preferred":[
        "\u58ec\u751f\u753a"
    ],
    "name:jpn_x_variant":[
        "\u307f\u3076\u307e\u3061"
    ],
    "qs:name":"Mibu-machi",
    "qs:photos_9r":0,
    "qs:photos_sr":0,
    "qs:pop_sr":"0",
    "wof:name":"Mibu",
    "wof:placetype":"localadmin",
    "wof:population":0
},
  "geometry": {"coordinates":[139.80497,36.45753],"type":"Point"}
}