{
  "type": "Feature",
  "properties": {
    "iso:country":"JP",
    "name:eng_x_preferred":[
        "Fushimi 3 Chome"
    ],
    "name:eng_x_variant":[
        "Fushimi 3 Choume",
        "Fushimi 3 Chome"
    ],
    "name:jpn_x_preferred":[
        "\uff13\u4e01\u76ee"
    ],
    "name:jpn_x_variant":[
        "\u3075\u3057\u307f \uff13\u3061\u3087\u3046\u3081",
        "\u4f0f\u898b \uff13\u4e01\u76ee",
        "\uff13\u3061\u3087\u3046\u3081"
    ],
    "qs:gn_local":0,
    "qs:local_max":2554,
    "qs:local_sum":22076,
    "qs:localhoods":97,
    "qs:name":"\uff13\u4e01\u76ee",
    "qs:name_adm0":"\u65e5\u672c",
    "qs:name_adm1":"\u5317\u6d77\u9053",
    "qs:name_adm2":"\u4e2d\u592e\u533a",
    "qs:name_en":"Fushimi 3 Chome",
    "qs:name_lau":"\u4f0f\u898b",
    "qs:name_local":"\u672d\u5e4c\u5e02",
    "qs:photo_max":64,
    "qs:photo_sum":231,
    "qs:placetype":"Suburb",
    "qs:quad_count":19,
    "qs:woe_adm0":23424856,
    "qs:woe_adm1":7153351,
    "qs:woe_adm2":15015394,
    "qs:woe_lau":28379443,
    "qs:woe_local":1118108,
    "qs:woe_ver":"7.10.0",
    "wof:lang":[
        "jpn"
    ],
    "wof:name":"\uff13\u4e01\u76ee",
    "wof:placetype":"neighbourhood"
},
  "geometry": {"coordinates":[141.32539700000001,43.026624],"type":"Point"}
}