{
  "type": "Feature",
  "properties": {
    "gn:admin1_code":"4.0",
    "gn:admin2_code":"7465524.0",
    "gn:asciiname":"Kitayose",
    "gn:country_code":"JP",
    "gn:dem":23,
    "gn:feature_class":"P",
    "gn:feature_code":"PPLL",
    "gn:name":"Kitayose",
    "gn:population":0,
    "gn:timezone":"Asia/Tokyo",
    "iso:country":"JP",
    "name:jpn_x_preferred":[
        "\u5317\u5bc4\u702c"
    ],
    "name:jpn_x_variant":[
        "\u304d\u305f\u3088\u305b",
        "\u30ad\u30bf\u30e8\u30bb"
    ],
    "wof:name":"Kitayose",
    "wof:placetype":"locality"
},
  "geometry": {"coordinates":[140.38258000000002,35.24979000000001],"type":"Point"}
}