{
  "type": "Feature",
  "properties": {
    "gn:admin1_code":"21.0",
    "gn:admin2_code":"1858418.0",
    "gn:admin3_code":"43104.0",
    "gn:asciiname":"Tamukae",
    "gn:country_code":"JP",
    "gn:dem":8,
    "gn:feature_class":"P",
    "gn:feature_code":"PPL",
    "gn:name":"Tamukae",
    "gn:population":0,
    "gn:timezone":"Asia/Tokyo",
    "iso:country":"JP",
    "name:jpn_x_preferred":[
        "\u7530\u8fce"
    ],
    "name:jpn_x_variant":[
        "\u305f\u3080\u304b\u3048",
        "\u30bf\u30e0\u30ab\u30a8"
    ],
    "wof:name":"Tamukae",
    "wof:placetype":"locality"
},
  "geometry": {"coordinates":[130.71156000000002,32.77661],"type":"Point"}
}