{
  "type": "Feature",
  "properties": {
    "gn:admin1_code":"19.0",
    "gn:admin2_code":"1848350.0",
    "gn:admin3_code":"14104.0",
    "gn:asciiname":"Minamihonmoku",
    "gn:country_code":"JP",
    "gn:dem":-9999,
    "gn:feature_class":"P",
    "gn:feature_code":"PPL",
    "gn:name":"Minamihonmoku",
    "gn:population":0,
    "gn:timezone":"Asia/Tokyo",
    "iso:country":"JP",
    "name:jpn_x_preferred":[
        "\u5357\u672c\u7267"
    ],
    "name:jpn_x_variant":[
        "\u307f\u306a\u307f\u307b\u3093\u3082\u304f",
        "\u30df\u30ca\u30df\u30db\u30f3\u30e2\u30af"
    ],
    "wof:name":"Minamihonmoku",
    "wof:placetype":"locality"
},
  "geometry": {"coordinates":[139.68188999999998,35.40644],"type":"Point"}
}