{
  "type": "Feature",
  "properties": {
    "gn:admin1_code":"8.0",
    "gn:admin2_code":"2112535.0",
    "gn:asciiname":"Kamimisaka",
    "gn:country_code":"JP",
    "gn:dem":540,
    "gn:feature_class":"P",
    "gn:feature_code":"PPLL",
    "gn:name":"Kamimisaka",
    "gn:population":0,
    "gn:timezone":"Asia/Tokyo",
    "iso:country":"JP",
    "name:jpn_x_preferred":[
        "\u4e0a\u4e09\u5742"
    ],
    "name:und_x_variant":[
        "Kami-misaki",
        "Kami-misaka",
        "Kamimisaka"
    ],
    "wof:name":"Kamimisaka",
    "wof:placetype":"locality"
},
  "geometry": {"coordinates":[140.62441999999999,37.18233],"type":"Point"}
}