{
  "type": "Feature",
  "properties": {
    "gn:admin1_code":"12.0",
    "gn:admin2_code":"2128812.0",
    "gn:asciiname":"Beppucho",
    "gn:country_code":"JP",
    "gn:dem":80,
    "gn:feature_class":"P",
    "gn:feature_code":"PPL",
    "gn:name":"Beppuch\u014d",
    "gn:population":0,
    "gn:timezone":"Asia/Tokyo",
    "iso:country":"JP",
    "name:jpn_x_preferred":[
        "\u5225\u5e9c\u753a"
    ],
    "name:und_x_variant":[
        "Kami-obihiro",
        "Beppu",
        "Beppuch\u014d"
    ],
    "wof:name":"Beppucho",
    "wof:placetype":"locality"
},
  "geometry": {"coordinates":[143.15496000000005,42.86464],"type":"Point"}
}