{
  "type": "Feature",
  "properties": {
    "gn:admin1_code":"21.0",
    "gn:admin2_code":"7412709.0",
    "gn:admin3_code":"43348.0",
    "gn:asciiname":"Takishita",
    "gn:country_code":"JP",
    "gn:dem":156,
    "gn:feature_class":"P",
    "gn:feature_code":"PPLL",
    "gn:name":"Takishita",
    "gn:population":0,
    "gn:timezone":"Asia/Tokyo",
    "iso:country":"JP",
    "name:jpn_x_preferred":[
        "\u6edd\u4e0b"
    ],
    "name:jpn_x_variant":[
        "\u305f\u304d\u3057\u305f",
        "\u30bf\u30ad\u30b7\u30bf"
    ],
    "wof:name":"Takishita",
    "wof:placetype":"locality"
},
  "geometry": {"coordinates":[130.87028000000001,32.617],"type":"Point"}
}