{
  "type": "Feature",
  "properties": {
    "gn:admin1_code":"33.0",
    "gn:admin2_code":"8300623.0",
    "gn:asciiname":"Sakuramachi",
    "gn:country_code":"JP",
    "gn:dem":24,
    "gn:feature_class":"P",
    "gn:feature_code":"PPL",
    "gn:name":"Sakuramachi",
    "gn:population":0,
    "gn:timezone":"Asia/Tokyo",
    "iso:country":"JP",
    "name:jpn_x_preferred":[
        "\u685c\u753a"
    ],
    "wof:name":"Sakuramachi",
    "wof:placetype":"locality"
},
  "geometry": {"coordinates":[129.93998999999999,33.47205],"type":"Point"}
}