{
  "type": "Feature",
  "properties": {
    "gn:admin1_code":"19.0",
    "gn:admin2_code":"1865011.0",
    "gn:admin3_code":"14364.0",
    "gn:asciiname":"Hirayama",
    "gn:country_code":"JP",
    "gn:dem":141,
    "gn:feature_class":"P",
    "gn:feature_code":"PPL",
    "gn:name":"Hirayama",
    "gn:population":0,
    "gn:timezone":"Asia/Tokyo",
    "iso:country":"JP",
    "name:ces_x_preferred":[
        "Hirajama"
    ],
    "name:jpn_x_preferred":[
        "\u5e73\u5c71"
    ],
    "wof:name":"Hirayama",
    "wof:placetype":"locality"
},
  "geometry": {"coordinates":[139.06811999999999,35.35418],"type":"Point"}
}