{
  "type": "Feature",
  "properties": {
    "gn:admin1_code":"19.0",
    "gn:admin2_code":"1864091.0",
    "gn:asciiname":"Yamukai",
    "gn:country_code":"JP",
    "gn:dem":30,
    "gn:feature_class":"P",
    "gn:feature_code":"PPLL",
    "gn:name":"Yamukai",
    "gn:population":0,
    "gn:timezone":"Asia/Tokyo",
    "iso:country":"JP",
    "name:jpn_x_preferred":[
        "\u77e2\u5411"
    ],
    "wof:name":"Yamukai",
    "wof:placetype":"locality"
},
  "geometry": {"coordinates":[139.43648999999999,35.37399],"type":"Point"}
}