{
  "type": "Feature",
  "properties": {
    "gn:admin1_code":"33.0",
    "gn:admin2_code":"7391363.0",
    "gn:asciiname":"Kumano",
    "gn:country_code":"JP",
    "gn:dem":36,
    "gn:feature_class":"P",
    "gn:feature_code":"PPLL",
    "gn:name":"Kumano",
    "gn:population":0,
    "gn:timezone":"Asia/Tokyo",
    "iso:country":"JP",
    "name:deu_x_preferred":[
        "Kumano"
    ],
    "name:jpn_x_preferred":[
        "\u718a\u91ce"
    ],
    "name:nld_x_preferred":[
        "Kumano"
    ],
    "name:ron_x_preferred":[
        "Kumano"
    ],
    "name:spa_x_preferred":[
        "Kumano"
    ],
    "name:swe_x_preferred":[
        "Kumano"
    ],
    "name:zho_x_preferred":[
        "\u718a\u91ce"
    ],
    "wof:name":"Kumano",
    "wof:placetype":"locality"
},
  "geometry": {"coordinates":[130.02680000000001,33.13204],"type":"Point"}
}