{
  "type": "Feature",
  "properties": {
    "gn:admin1_code":"24.0",
    "gn:admin2_code":"7447001.0",
    "gn:asciiname":"Nashinoki",
    "gn:country_code":"JP",
    "gn:dem":319,
    "gn:feature_class":"P",
    "gn:feature_code":"PPL",
    "gn:name":"Nashinoki",
    "gn:population":0,
    "gn:timezone":"Asia/Tokyo",
    "iso:country":"JP",
    "name:jpn_x_preferred":[
        "\u68a8\u30ce\u6728"
    ],
    "name:jpn_x_variant":[
        "\u306a\u3057\u306e\u304d",
        "\u30ca\u30b7\u30ce\u30ad"
    ],
    "wof:name":"Nashinoki",
    "wof:placetype":"locality"
},
  "geometry": {"coordinates":[140.66114999999999,38.79104],"type":"Point"}
}