{
  "type": "Feature",
  "properties": {
    "gn:admin1_code":"32.0",
    "gn:admin2_code":"1853897.0",
    "gn:admin3_code":"27117.0",
    "gn:asciiname":"Shinmori",
    "gn:country_code":"JP",
    "gn:dem":5,
    "gn:feature_class":"P",
    "gn:feature_code":"PPL",
    "gn:name":"Shinmori",
    "gn:population":0,
    "gn:timezone":"Asia/Tokyo",
    "iso:country":"JP",
    "name:jpn_x_preferred":[
        "\u65b0\u68ee"
    ],
    "wof:name":"Shinmori",
    "wof:placetype":"locality"
},
  "geometry": {"coordinates":[135.56161,34.71916],"type":"Point"}
}