{
  "type": "Feature",
  "properties": {
    "gn:admin1_code":"37.0",
    "gn:admin2_code":"1864089.0",
    "gn:asciiname":"Yuzawadaira",
    "gn:country_code":"JP",
    "gn:dem":91,
    "gn:feature_class":"P",
    "gn:feature_code":"PPLL",
    "gn:name":"Yuzawadaira",
    "gn:population":0,
    "gn:timezone":"Asia/Tokyo",
    "iso:country":"JP",
    "name:jpn_x_preferred":[
        "\u6e6f\u6ca2\u5e73"
    ],
    "wof:name":"Yuzawadaira",
    "wof:placetype":"locality"
},
  "geometry": {"coordinates":[138.63701,35.18412],"type":"Point"}
}