{
  "type": "Feature",
  "properties": {
    "gn:admin1_code":"12.0",
    "gn:admin2_code":"2129373.0",
    "gn:admin3_code":"1661.0",
    "gn:asciiname":"Kamibeppo",
    "gn:country_code":"JP",
    "gn:dem":20,
    "gn:feature_class":"P",
    "gn:feature_code":"PPL",
    "gn:name":"Kamibeppo",
    "gn:population":0,
    "gn:timezone":"Asia/Tokyo",
    "iso:country":"JP",
    "name:jpn_x_preferred":[
        "\u4e0a\u5225\u4fdd"
    ],
    "name:jpn_x_variant":[
        "\u304b\u307f\u3079\u3063\u307d",
        "\u30ab\u30df\u30d9\u30c3\u30dd"
    ],
    "wof:name":"Kamibeppo",
    "wof:placetype":"locality"
},
  "geometry": {"coordinates":[144.51631,43.01445],"type":"Point"}
}