{
  "type": "Feature",
  "properties": {
    "gn:admin1_code":"08",
    "gn:admin2_code":"7451504.0",
    "gn:admin3_code":"7445.0",
    "gn:asciiname":"Kosugawa",
    "gn:country_code":"JP",
    "gn:dem":323,
    "gn:feature_class":"P",
    "gn:feature_code":"PPL",
    "gn:name":"Kosugawa",
    "gn:population":0,
    "gn:timezone":"Asia/Tokyo",
    "iso:country":"JP",
    "name:jpn_x_preferred":[
        "\u8d8a\u5ddd"
    ],
    "name:und_x_variant":[
        "Kosukawa",
        "Kosugawa"
    ],
    "wof:name":"Kosugawa",
    "wof:placetype":"locality"
},
  "geometry": {"coordinates":[139.47041000000002,37.39971],"type":"Point"}
}