{
  "type": "Feature",
  "properties": {
    "gn:admin1_code":"19.0",
    "gn:admin2_code":"1856849.0",
    "gn:asciiname":"Shirasu",
    "gn:country_code":"JP",
    "gn:dem":26,
    "gn:feature_class":"P",
    "gn:feature_code":"PPLL",
    "gn:name":"Shirasu",
    "gn:population":0,
    "gn:timezone":"Asia/Tokyo",
    "iso:country":"JP",
    "name:jpn_x_preferred":[
        "\u767d\u9808"
    ],
    "name:jpn_x_variant":[
        "\u3057\u3089\u3059",
        "\u30b7\u30e9\u30b9"
    ],
    "wof:name":"Shirasu",
    "wof:placetype":"locality"
},
  "geometry": {"coordinates":[139.61906000000002,35.15297],"type":"Point"}
}