{
  "type": "Feature",
  "properties": {
    "gn:admin1_code":"27",
    "gn:admin2_code":"1857159.0",
    "gn:admin3_code":"42411.0",
    "gn:asciiname":"Tsuwazakigo",
    "gn:country_code":"JP",
    "gn:dem":151,
    "gn:feature_class":"P",
    "gn:feature_code":"PPL",
    "gn:name":"Tsuwazakig\u014d",
    "gn:population":0,
    "gn:timezone":"Asia/Tokyo",
    "iso:country":"JP",
    "name:jpn_x_preferred":[
        "\u6d25\u548c\u5d0e\u90f7"
    ],
    "name:und_x_variant":[
        "Tsuwasaki",
        "Tsuwazaki",
        "Tsuwazakig\u014d"
    ],
    "wof:name":"Tsuwazakigo",
    "wof:placetype":"locality"
},
  "geometry": {"coordinates":[129.10806000000002,33.14194000000001],"type":"Point"}
}