{
  "type": "Feature",
  "properties": {
    "gn:admin1_code":"37.0",
    "gn:admin2_code":"1851401.0",
    "gn:admin3_code":"22341.0",
    "gn:asciiname":"Yahata",
    "gn:country_code":"JP",
    "gn:dem":22,
    "gn:feature_class":"P",
    "gn:feature_code":"PPL",
    "gn:name":"Yahata",
    "gn:population":0,
    "gn:timezone":"Asia/Tokyo",
    "iso:country":"JP",
    "name:jpn_x_preferred":[
        "\u516b\u5e61"
    ],
    "wof:name":"Yahata",
    "wof:placetype":"locality"
},
  "geometry": {"coordinates":[138.89347000000001,35.10836],"type":"Point"}
}