{
  "type": "Feature",
  "properties": {
    "gn:admin1_code":"16.0",
    "gn:admin2_code":"2129400.0",
    "gn:admin3_code":"3501.0",
    "gn:asciiname":"Numa",
    "gn:country_code":"JP",
    "gn:dem":255,
    "gn:feature_class":"P",
    "gn:feature_code":"PPL",
    "gn:name":"Numa",
    "gn:population":0,
    "gn:timezone":"Asia/Tokyo",
    "iso:country":"JP",
    "name:ceb_x_preferred":[
        "Numa"
    ],
    "name:deu_x_preferred":[
        "Numa"
    ],
    "name:fra_x_preferred":[
        "Numa"
    ],
    "name:ita_x_preferred":[
        "Numa"
    ],
    "name:jpn_x_preferred":[
        "\u6cbc"
    ],
    "name:jpn_x_variant":[
        "\u306c\u307e",
        "\u30cc\u30de"
    ],
    "name:por_x_preferred":[
        "Numa"
    ],
    "name:swe_x_preferred":[
        "Numa"
    ],
    "wof:name":"Numa",
    "wof:placetype":"locality"
},
  "geometry": {"coordinates":[141.38731000000001,40.32606],"type":"Point"}
}