{
  "type": "Feature",
  "properties": {
    "gn:admin1_code":"34.0",
    "gn:admin2_code":"8304213.0",
    "gn:asciiname":"Horinouchi-higashi",
    "gn:country_code":"JP",
    "gn:dem":2,
    "gn:feature_class":"P",
    "gn:feature_code":"PPLL",
    "gn:name":"Horinouchi-higashi",
    "gn:population":0,
    "gn:timezone":"Asia/Tokyo",
    "iso:country":"JP",
    "name:jpn_x_preferred":[
        "\u5800\u4e4b\u5185\u6771"
    ],
    "wof:name":"Horinouchi-higashi",
    "wof:placetype":"locality"
},
  "geometry": {"coordinates":[139.79182,35.9958],"type":"Point"}
}