{
  "type": "Feature",
  "properties": {
    "gn:admin1_code":"19",
    "gn:admin2_code":"1865011.0",
    "gn:admin3_code":"14364.0",
    "gn:asciiname":"Kaminawa",
    "gn:country_code":"JP",
    "gn:dem":266,
    "gn:feature_class":"P",
    "gn:feature_code":"PPL",
    "gn:name":"Kaminawa",
    "gn:population":0,
    "gn:timezone":"Asia/Tokyo",
    "iso:country":"JP",
    "name:jpn_x_preferred":[
        "\u795e\u7e04"
    ],
    "wof:name":"Kaminawa",
    "wof:placetype":"locality"
},
  "geometry": {"coordinates":[139.04726000000002,35.40195999999999],"type":"Point"}
}