{
  "type": "Feature",
  "properties": {
    "gn:admin1_code":"28.0",
    "gn:admin2_code":"1855604.0",
    "gn:asciiname":"Rokuyaoncho",
    "gn:country_code":"JP",
    "gn:dem":130,
    "gn:feature_class":"P",
    "gn:feature_code":"PPL",
    "gn:name":"Rokuyaonch\u014d",
    "gn:population":0,
    "gn:timezone":"Asia/Tokyo",
    "iso:country":"JP",
    "name:jpn_x_preferred":[
        "\u9e7f\u91ce\u5712\u753a"
    ],
    "name:und_x_variant":[
        "Rokuyaonch\u014d"
    ],
    "wof:name":"Rokuyaoncho",
    "wof:placetype":"locality"
},
  "geometry": {"coordinates":[135.84836999999999,34.66236],"type":"Point"}
}