{
  "type": "Feature",
  "properties": {
    "gn:admin1_code":"23",
    "gn:admin2_code":"1848370.0",
    "gn:asciiname":"Suizawa-honmachi",
    "gn:country_code":"JP",
    "gn:dem":156,
    "gn:feature_class":"P",
    "gn:feature_code":"PPL",
    "gn:name":"Suizawa-honmachi",
    "gn:population":0,
    "gn:timezone":"Asia/Tokyo",
    "iso:country":"JP",
    "name:jpn_x_preferred":[
        "\u6c34\u6ca2\u672c\u753a"
    ],
    "name:und_x_variant":[
        "Suisawa",
        "Suizawa",
        "Suizawa-honmachi"
    ],
    "wof:name":"Suizawa-honmachi",
    "wof:placetype":"locality"
},
  "geometry": {"coordinates":[136.48254,34.97264000000001],"type":"Point"}
}