{
  "type": "Feature",
  "properties": {
    "gn:admin1_code":"37.0",
    "gn:admin2_code":"1854900.0",
    "gn:asciiname":"Wakabacho",
    "gn:country_code":"JP",
    "gn:dem":13,
    "gn:feature_class":"P",
    "gn:feature_code":"PPL",
    "gn:name":"Wakabach\u014d",
    "gn:population":0,
    "gn:timezone":"Asia/Tokyo",
    "iso:country":"JP",
    "name:jpn_x_preferred":[
        "\u82e5\u8449\u753a"
    ],
    "name:und_x_variant":[
        "Wakabach\u014d"
    ],
    "wof:name":"Wakabacho",
    "wof:placetype":"locality"
},
  "geometry": {"coordinates":[138.85611,35.11904000000001],"type":"Point"}
}