{
  "type": "Feature",
  "properties": {
    "gn:admin1_code":"4.0",
    "gn:admin2_code":"1863711.0",
    "gn:asciiname":"Ushifusayatsu",
    "gn:country_code":"JP",
    "gn:dem":44,
    "gn:feature_class":"P",
    "gn:feature_code":"PPLL",
    "gn:name":"Ushifusayatsu",
    "gn:population":0,
    "gn:timezone":"Asia/Tokyo",
    "iso:country":"JP",
    "name:jpn_x_preferred":[
        "\u5348\u623f\u8c37"
    ],
    "name:jpn_x_variant":[
        "\u3046\u3057\u3075\u3055\u3084\u3064",
        "\u30a6\u30b7\u30d5\u30b5\u30e4\u30c4"
    ],
    "wof:name":"Ushifusayatsu",
    "wof:placetype":"locality"
},
  "geometry": {"coordinates":[139.89996000000002,35.26615],"type":"Point"}
}