{
  "type": "Feature",
  "properties": {
    "gn:admin1_code":"21.0",
    "gn:admin2_code":"1858418.0",
    "gn:admin3_code":"43105.0",
    "gn:asciiname":"Arahira",
    "gn:country_code":"JP",
    "gn:dem":152,
    "gn:feature_class":"P",
    "gn:feature_code":"PPLL",
    "gn:name":"Arahira",
    "gn:population":0,
    "gn:timezone":"Asia/Tokyo",
    "iso:country":"JP",
    "name:jpn_x_preferred":[
        "\u8352\u5e73"
    ],
    "name:jpn_x_variant":[
        "\u3042\u3089\u3072\u3089",
        "\u30a2\u30e9\u30d2\u30e9"
    ],
    "wof:name":"Arahira",
    "wof:placetype":"locality"
},
  "geometry": {"coordinates":[130.65259,32.87283],"type":"Point"}
}