{
  "type": "Feature",
  "properties": {
    "gn:admin1_code":"3.0",
    "gn:admin2_code":"7439937.0",
    "gn:asciiname":"Tomisaki",
    "gn:country_code":"JP",
    "gn:dem":18,
    "gn:feature_class":"P",
    "gn:feature_code":"PPL",
    "gn:name":"Tomisaki",
    "gn:population":0,
    "gn:timezone":"Asia/Tokyo",
    "iso:country":"JP",
    "name:jpn_x_preferred":[
        "\u5bcc\u5d0e"
    ],
    "name:jpn_x_variant":[
        "\u3068\u307f\u3055\u304d",
        "\u30c8\u30df\u30b5\u30ad"
    ],
    "wof:name":"Tomisaki",
    "wof:placetype":"locality"
},
  "geometry": {"coordinates":[141.36501000000001,40.79942],"type":"Point"}
}