{
  "type": "Feature",
  "properties": {
    "gn:admin1_code":"34.0",
    "gn:admin2_code":"1849187.0",
    "gn:admin3_code":"11109.0",
    "gn:asciiname":"Daiyama",
    "gn:country_code":"JP",
    "gn:dem":16,
    "gn:feature_class":"P",
    "gn:feature_code":"PPL",
    "gn:name":"Daiyama",
    "gn:population":0,
    "gn:timezone":"Asia/Tokyo",
    "iso:country":"JP",
    "name:jpn_x_preferred":[
        "\u4ee3\u5c71"
    ],
    "name:jpn_x_variant":[
        "\u3060\u3044\u3084\u307e",
        "\u30c0\u30a4\u30e4\u30de"
    ],
    "wof:name":"Daiyama",
    "wof:placetype":"locality"
},
  "geometry": {"coordinates":[139.70776999999998,35.90193],"type":"Point"}
}