{
  "type": "Feature",
  "properties": {
    "gn:admin1_code":"4.0",
    "gn:admin2_code":"1863711.0",
    "gn:asciiname":"Obata",
    "gn:country_code":"JP",
    "gn:dem":49,
    "gn:feature_class":"P",
    "gn:feature_code":"PPLL",
    "gn:name":"Obata",
    "gn:population":0,
    "gn:timezone":"Asia/Tokyo",
    "iso:country":"JP",
    "name:jpn_x_preferred":[
        "\u5c0f\u7551"
    ],
    "name:jpn_x_variant":[
        "\u304a\u3070\u305f",
        "\u30aa\u30d0\u30bf"
    ],
    "wof:name":"Obata",
    "wof:placetype":"locality"
},
  "geometry": {"coordinates":[139.94582,35.19999],"type":"Point"}
}