{
  "type": "Feature",
  "properties": {
    "gn:admin1_code":"45",
    "gn:admin2_code":"1863413.0",
    "gn:asciiname":"Tamagawa",
    "gn:country_code":"JP",
    "gn:dem":3,
    "gn:feature_class":"P",
    "gn:feature_code":"PPL",
    "gn:name":"Tamagawa",
    "gn:population":0,
    "gn:timezone":"Asia/Tokyo",
    "iso:country":"JP",
    "wof:name":"Tamagawa",
    "wof:placetype":"locality"
},
  "geometry": {"coordinates":[131.66661999999999,34.65007],"type":"Point"}
}