{
  "type": "Feature",
  "properties": {
    "iso:country":"JP",
    "name:eng_x_preferred":[
        "Takayama Village"
    ],
    "name:jpn_x_preferred":[
        "\u9ad8\u5c71\u6751"
    ],
    "qs:name":"\u9ad8\u5c71\u6751",
    "qs:name_adm0":"\u65e5\u672c",
    "qs:name_adm1":"\u9577\u91ce\u770c",
    "qs:photos":647,
    "qs:photos_1k":131,
    "qs:photos_9k":3,
    "qs:photos_9r":5,
    "qs:photos_all":647,
    "qs:photos_sr":8,
    "qs:placetype":"Town",
    "qs:pop_sr":"0",
    "wof:name":"Takayama Village",
    "wof:placetype":"locality"
},
  "geometry": {"coordinates":[138.49158600000001,36.671575],"type":"Point"}
}