{
  "type": "Feature",
  "properties": {
    "gn:admin1_code":"16.0",
    "gn:admin2_code":"7441817.0",
    "gn:asciiname":"Shioya",
    "gn:country_code":"JP",
    "gn:dem":10,
    "gn:feature_class":"P",
    "gn:feature_code":"PPL",
    "gn:name":"Shioya",
    "gn:population":0,
    "gn:timezone":"Asia/Tokyo",
    "iso:country":"JP",
    "name:jpn_x_preferred":[
        "\u5869\u8c37"
    ],
    "name:jpn_x_variant":[
        "\u3057\u304a\u3084",
        "\u30b7\u30aa\u30e4"
    ],
    "name:kor_x_preferred":[
        "\uc2dc\uc624\uc57c"
    ],
    "wof:name":"Shioya",
    "wof:placetype":"locality"
},
  "geometry": {"coordinates":[141.68313000000001,38.99231],"type":"Point"}
}