{
  "type": "Feature",
  "properties": {
    "gn:admin1_code":"11.0",
    "gn:admin2_code":"1853990.0",
    "gn:asciiname":"Kojin",
    "gn:country_code":"JP",
    "gn:dem":4,
    "gn:feature_class":"P",
    "gn:feature_code":"PPL",
    "gn:name":"K\u014djin",
    "gn:population":0,
    "gn:timezone":"Asia/Tokyo",
    "iso:country":"JP",
    "name:und_x_variant":[
        "K\u014djin"
    ],
    "wof:name":"Kojin",
    "wof:placetype":"locality"
},
  "geometry": {"coordinates":[133.18000000000001,34.28222],"type":"Point"}
}