{
  "type": "Feature",
  "properties": {
    "gn:admin1_code":"31",
    "gn:admin2_code":"7405223.0",
    "gn:asciiname":"Biseicho-utodani",
    "gn:country_code":"JP",
    "gn:dem":248,
    "gn:feature_class":"P",
    "gn:feature_code":"PPL",
    "gn:name":"Biseich\u014d-utodani",
    "gn:population":0,
    "gn:timezone":"Asia/Tokyo",
    "iso:country":"JP",
    "name:jpn_x_preferred":[
        "\u7f8e\u661f\u753a\u5b87\u6238\u8c37"
    ],
    "name:und_x_variant":[
        "Biseich\u014d-utodani",
        "Utodani"
    ],
    "wof:name":"Biseicho-utodani",
    "wof:placetype":"locality"
},
  "geometry": {"coordinates":[133.57221000000001,34.71163],"type":"Point"}
}