{
  "type": "Feature",
  "properties": {
    "gn:admin1_code":"34.0",
    "gn:admin2_code":"1854369.0",
    "gn:asciiname":"Hara",
    "gn:country_code":"JP",
    "gn:dem":21,
    "gn:feature_class":"P",
    "gn:feature_code":"PPLL",
    "gn:name":"Hara",
    "gn:population":0,
    "gn:timezone":"Asia/Tokyo",
    "iso:country":"JP",
    "name:ceb_x_preferred":[
        "Hara"
    ],
    "name:deu_x_preferred":[
        "Hara"
    ],
    "name:est_x_preferred":[
        "Hara"
    ],
    "name:fin_x_preferred":[
        "Hara"
    ],
    "name:fra_x_preferred":[
        "Hara"
    ],
    "name:jpn_x_preferred":[
        "\u539f"
    ],
    "name:nld_x_preferred":[
        "Hara"
    ],
    "name:pol_x_preferred":[
        "Hara"
    ],
    "name:por_x_preferred":[
        "Hara"
    ],
    "name:spa_x_preferred":[
        "Hara"
    ],
    "name:swe_x_preferred":[
        "Hara"
    ],
    "name:vol_x_preferred":[
        "Hara"
    ],
    "wof:name":"Hara",
    "wof:placetype":"locality"
},
  "geometry": {"coordinates":[139.51289,35.99744000000001],"type":"Point"}
}