{
  "type": "Feature",
  "properties": {
    "gn:admin1_code":"16.0",
    "gn:admin2_code":"2111528.0",
    "gn:asciiname":"Hosoura",
    "gn:country_code":"JP",
    "gn:dem":82,
    "gn:feature_class":"P",
    "gn:feature_code":"PPL",
    "gn:name":"Hosoura",
    "gn:population":0,
    "gn:timezone":"Asia/Tokyo",
    "iso:country":"JP",
    "wof:name":"Hosoura",
    "wof:placetype":"locality"
},
  "geometry": {"coordinates":[141.73333,39.005],"type":"Point"}
}