{
  "type": "Feature",
  "properties": {
    "gn:admin1_code":"18.0",
    "gn:admin2_code":"7383999.0",
    "gn:admin3_code":"46491.0",
    "gn:asciiname":"Nejime-kawakita",
    "gn:country_code":"JP",
    "gn:dem":59,
    "gn:feature_class":"P",
    "gn:feature_code":"PPL",
    "gn:name":"Nejime-kawakita",
    "gn:population":0,
    "gn:timezone":"Asia/Tokyo",
    "iso:country":"JP",
    "name:jpn_x_preferred":[
        "\u6839\u5360\u5ddd\u5317"
    ],
    "wof:name":"Nejime-kawakita",
    "wof:placetype":"locality"
},
  "geometry": {"coordinates":[130.79714999999999,31.2228],"type":"Point"}
}