{
  "type": "Feature",
  "properties": {
    "gn:admin1_code":"7.0",
    "gn:admin2_code":"7407413.0",
    "gn:asciiname":"Mukoshimomasu",
    "gn:country_code":"JP",
    "gn:dem":59,
    "gn:feature_class":"P",
    "gn:feature_code":"PPLL",
    "gn:name":"Muk\u014dshimomasu",
    "gn:population":0,
    "gn:timezone":"Asia/Tokyo",
    "iso:country":"JP",
    "name:jpn_x_preferred":[
        "\u5411\u4e0b\u76ca"
    ],
    "name:und_x_variant":[
        "Muk\u014dshimomasu"
    ],
    "wof:name":"Mukoshimomasu",
    "wof:placetype":"locality"
},
  "geometry": {"coordinates":[130.73777999999999,33.54132],"type":"Point"}
}