{
  "type": "Feature",
  "properties": {
    "gn:admin1_code":"23.0",
    "gn:admin2_code":"1849544.0",
    "gn:asciiname":"Misugicho-nyunomata",
    "gn:country_code":"JP",
    "gn:dem":441,
    "gn:feature_class":"P",
    "gn:feature_code":"PPL",
    "gn:name":"Misugich\u014d-ny\u016bnomata",
    "gn:population":0,
    "gn:timezone":"Asia/Tokyo",
    "iso:country":"JP",
    "name:jpn_x_preferred":[
        "\u7f8e\u6749\u753a\u4e39\u751f\u4fe3"
    ],
    "name:und_x_variant":[
        "Misugich\u014d-ny\u016bnomata"
    ],
    "wof:name":"Misugicho-nyunomata",
    "wof:placetype":"locality"
},
  "geometry": {"coordinates":[136.30351999999999,34.48195],"type":"Point"}
}