{
  "type": "Feature",
  "properties": {
    "gn:admin1_code":"23.0",
    "gn:admin2_code":"7417704.0",
    "gn:admin3_code":"24441.0",
    "gn:asciiname":"Shimoizue",
    "gn:country_code":"JP",
    "gn:dem":63,
    "gn:feature_class":"P",
    "gn:feature_code":"PPL",
    "gn:name":"Shimoizue",
    "gn:population":0,
    "gn:timezone":"Asia/Tokyo",
    "iso:country":"JP",
    "name:jpn_x_preferred":[
        "\u4e0b\u51fa\u6c5f"
    ],
    "wof:name":"Shimoizue",
    "wof:placetype":"locality"
},
  "geometry": {"coordinates":[136.46938,34.46769],"type":"Point"}
}