{
  "type": "Feature",
  "properties": {
    "gn:admin1_code":"21.0",
    "gn:admin2_code":"1849062.0",
    "gn:asciiname":"Higashi",
    "gn:country_code":"JP",
    "gn:dem":47,
    "gn:feature_class":"P",
    "gn:feature_code":"PPLL",
    "gn:name":"Higashi",
    "gn:population":0,
    "gn:timezone":"Asia/Tokyo",
    "iso:country":"JP",
    "name:jpn_x_preferred":[
        "\u6771"
    ],
    "name:jpn_x_variant":[
        "\u3072\u304c\u3057",
        "\u30d2\u30ac\u30b7"
    ],
    "wof:name":"Higashi",
    "wof:placetype":"locality"
},
  "geometry": {"coordinates":[130.56455,32.66772],"type":"Point"}
}