{
  "type": "Feature",
  "properties": {
    "gn:country":"JP",
    "gn:fcode":"PPL",
    "gn:pop":39728,
    "iso:country":"JP",
    "name:ara_x_preferred":[
        "\u0645\u064a\u0628\u0648"
    ],
    "name:deu_x_preferred":[
        "Mibu"
    ],
    "name:eng_x_preferred":[
        "Mibu"
    ],
    "name:fra_x_preferred":[
        "Mibu"
    ],
    "name:ita_x_preferred":[
        "Mibu"
    ],
    "name:jpn_x_preferred":[
        "\u58ec\u751f\u753a"
    ],
    "name:kor_x_preferred":[
        "\ubbf8\ubd80 \uc815"
    ],
    "name:msa_x_preferred":[
        "Mibu"
    ],
    "name:nld_x_preferred":[
        "Mibu"
    ],
    "name:por_x_preferred":[
        "Mibu"
    ],
    "name:rus_x_preferred":[
        "\u041c\u0438\u0431\u0443"
    ],
    "name:spa_x_preferred":[
        "Mibu"
    ],
    "name:tgl_x_preferred":[
        "Mibu"
    ],
    "name:ukr_x_preferred":[
        "\u041c\u0456\u0431\u0443"
    ],
    "name:zho_x_preferred":[
        "\u58ec\u751f\u753a"
    ],
    "qs:name":"Mibu",
    "qs:photos_9r":0,
    "qs:photos_sr":0,
    "qs:pop_sr":"7",
    "wof:name":"Mibu",
    "wof:placetype":"locality",
    "wof:population":39728
},
  "geometry": {"coordinates":[139.80000000000001,36.41667],"type":"Point"}
}