{
  "type": "Feature",
  "properties": {
    "gn:admin1_code":"23.0",
    "gn:admin2_code":"1857496.0",
    "gn:asciiname":"Ureshino-kurodacho",
    "gn:country_code":"JP",
    "gn:dem":8,
    "gn:feature_class":"P",
    "gn:feature_code":"PPL",
    "gn:name":"Ureshino-kurodach\u014d",
    "gn:population":0,
    "gn:timezone":"Asia/Tokyo",
    "iso:country":"JP",
    "name:jpn_x_preferred":[
        "\u5b09\u91ce\u9ed2\u7530\u753a"
    ],
    "name:und_x_variant":[
        "Ureshino-kurodach\u014d"
    ],
    "wof:name":"Ureshino-kurodacho",
    "wof:placetype":"locality"
},
  "geometry": {"coordinates":[136.48036999999999,34.63955],"type":"Point"}
}