{
  "type": "Feature",
  "properties": {
    "iso:country":"JP",
    "name:eng_x_preferred":[
        "Tsukiji 5 Chome"
    ],
    "name:eng_x_variant":[
        "Tsukiji 5 Choume",
        "Tsukiji 5 Chome"
    ],
    "name:jpn_x_preferred":[
        "\uff15\u4e01\u76ee"
    ],
    "name:jpn_x_variant":[
        "\u3064\u304d\u3058 \uff15\u3061\u3087\u3046\u3081",
        "\u7bc9\u5730 \uff15\u4e01\u76ee",
        "\uff15\u3061\u3087\u3046\u3081"
    ],
    "qs:gn_adm0_cc":"JP",
    "qs:gn_local":1850147,
    "qs:local_max":18112,
    "qs:local_sum":895907,
    "qs:localhoods":857,
    "qs:name":"\uff15\u4e01\u76ee",
    "qs:name_adm0":"\u65e5\u672c",
    "qs:name_adm1":"\u6771\u4eac\u90fd",
    "qs:name_adm2":"\u4e2d\u592e\u533a",
    "qs:name_en":"Tsukiji 5 Chome",
    "qs:name_lau":"\u7bc9\u5730",
    "qs:name_local":"\u6771\u4eac",
    "qs:photo_max":4301,
    "qs:photo_sum":7339,
    "qs:placetype":"Suburb",
    "qs:quad_count":24,
    "qs:woe_adm0":23424856,
    "qs:woe_adm1":2345889,
    "qs:woe_adm2":15015500,
    "qs:woe_lau":28413971,
    "qs:woe_local":1118370,
    "qs:woe_ver":"7.10.0",
    "qs_pg:name":"\uff15\u4e01\u76ee",
    "qs_pg:name_adm0":"\u65e5\u672c",
    "qs_pg:name_adm1":"\u6771\u4eac\u90fd",
    "qs_pg:photos":6460,
    "qs_pg:photos_1k":1000,
    "qs_pg:photos_9k":29,
    "qs_pg:photos_9r":14,
    "qs_pg:photos_all":6460,
    "qs_pg:photos_sr":24,
    "qs_pg:pop_sr":0,
    "qs_pg:qs_pg_placetype":"neighbourhood",
    "qs_pg:qs_pg_placetype_gp":"Suburb",
    "qs_pg:woe_adm0":23424856,
    "woe:adm0_id":23424856,
    "woe:name_adm0":"\u65e5\u672c",
    "woe:name_adm1":"\u6771\u4eac\u90fd",
    "woe:placetype":"Suburb",
    "wof:lang":[
        "jpn"
    ],
    "wof:name":"\uff15\u4e01\u76ee",
    "wof:placetype":"neighbourhood"
},
  "geometry": {"coordinates":[139.76898299999999,35.662484],"type":"Point"}
}