{
  "type": "Feature",
  "properties": {
    "gn:admin1_code":"21.0",
    "gn:admin2_code":"1859488.0",
    "gn:asciiname":"Shichijomachi-kiyomizu",
    "gn:country_code":"JP",
    "gn:dem":31,
    "gn:feature_class":"P",
    "gn:feature_code":"PPL",
    "gn:name":"Shichij\u014dmachi-kiyomizu",
    "gn:population":0,
    "gn:timezone":"Asia/Tokyo",
    "iso:country":"JP",
    "name:jpn_x_preferred":[
        "\u4e03\u57ce\u753a\u6e05\u6c34"
    ],
    "name:jpn_x_variant":[
        "\u3057\u3061\u3058\u3087\u3046\u307e\u3061\u304d\u3088\u307f\u305a",
        "\u30b7\u30c1\u30b8\u30e7\u30a6\u30de\u30c1\u30ad\u30e8\u30df\u30ba"
    ],
    "name:und_x_variant":[
        "Shichij\u014dmachi-kiyomizu"
    ],
    "wof:name":"Shichijomachi-kiyomizu",
    "wof:placetype":"locality"
},
  "geometry": {"coordinates":[130.77188000000001,32.95868],"type":"Point"}
}