{
  "type": "Feature",
  "properties": {
    "gn:admin1_code":"3.0",
    "gn:admin2_code":"2127674.0",
    "gn:asciiname":"Doteyama",
    "gn:country_code":"JP",
    "gn:dem":73,
    "gn:feature_class":"P",
    "gn:feature_code":"PPL",
    "gn:name":"Doteyama",
    "gn:population":0,
    "gn:timezone":"Asia/Tokyo",
    "iso:country":"JP",
    "name:jpn_x_preferred":[
        "\u571f\u624b\u5c71"
    ],
    "name:jpn_x_variant":[
        "\u3069\u3066\u3084\u307e",
        "\u30c9\u30c6\u30e4\u30de"
    ],
    "wof:name":"Doteyama",
    "wof:placetype":"locality"
},
  "geometry": {"coordinates":[141.20591999999999,40.63277],"type":"Point"}
}