{
  "type": "Feature",
  "properties": {
    "iso:country":"JP",
    "name:eng_x_preferred":[
        "Koya 2 Chome"
    ],
    "name:eng_x_variant":[
        "Kouya 2 Choume",
        "Koya 2 Chome"
    ],
    "name:jpn_x_preferred":[
        "\uff12\u4e01\u76ee"
    ],
    "name:jpn_x_variant":[
        "\u3053\u3046\u3084 \uff12\u3061\u3087\u3046\u3081",
        "\u8208\u91ce \uff12\u4e01\u76ee",
        "\uff12\u3061\u3087\u3046\u3081"
    ],
    "name:unk_x_variant":[
        "\uff12\u4e01\u76ee"
    ],
    "qs:gn_local":0,
    "qs:local_max":813,
    "qs:local_sum":1387,
    "qs:localhoods":7,
    "qs:name":"\uff12\u4e01\u76ee",
    "qs:name_adm0":"\u65e5\u672c",
    "qs:name_adm1":"\u65b0\u6f5f\u770c",
    "qs:name_en":"Koya 2 Chome",
    "qs:name_lau":"\u8208\u91ce",
    "qs:name_local":"\u4e09\u6761\u5e02",
    "qs:photo_max":24,
    "qs:photo_sum":41,
    "qs:placetype":"Suburb",
    "qs:quad_count":4,
    "qs:woe_adm0":23424856,
    "qs:woe_adm1":2345878,
    "qs:woe_adm2":0,
    "qs:woe_lau":28419227,
    "qs:woe_local":1118103,
    "qs:woe_ver":"7.10.0",
    "wof:lang":[
        "jpn"
    ],
    "wof:name":"\uff12\u4e01\u76ee",
    "wof:placetype":"neighbourhood"
},
  "geometry": {"coordinates":[138.97218100000001,37.628768],"type":"Point"}
}