{
  "type": "Feature",
  "properties": {
    "gn:admin1_code":"16.0",
    "gn:admin2_code":"2112822.0",
    "gn:asciiname":"Uchimuro",
    "gn:country_code":"JP",
    "gn:dem":130,
    "gn:feature_class":"P",
    "gn:feature_code":"PPL",
    "gn:name":"Uchimuro",
    "gn:population":0,
    "gn:timezone":"Asia/Tokyo",
    "iso:country":"JP",
    "name:jpn_x_preferred":[
        "\u5185\u5ba4"
    ],
    "name:jpn_x_variant":[
        "\u3046\u3061\u3080\u308d",
        "\u30a6\u30c1\u30e0\u30ed"
    ],
    "wof:name":"Uchimuro",
    "wof:placetype":"locality"
},
  "geometry": {"coordinates":[141.03135,39.36065],"type":"Point"}
}