{
  "type": "Feature",
  "properties": {
    "gn:admin1_code":"10.0",
    "gn:admin2_code":"1860108.0",
    "gn:admin3_code":"10382.0",
    "gn:asciiname":"Kuriyama",
    "gn:country_code":"JP",
    "gn:dem":521,
    "gn:feature_class":"P",
    "gn:feature_code":"PPL",
    "gn:name":"Kuriyama",
    "gn:population":0,
    "gn:timezone":"Asia/Tokyo",
    "iso:country":"JP",
    "name:deu_x_preferred":[
        "Kuriyama"
    ],
    "name:jpn_x_preferred":[
        "\u6817\u5c71"
    ],
    "wof:name":"Kuriyama",
    "wof:placetype":"locality"
},
  "geometry": {"coordinates":[138.79498999999998,36.19093],"type":"Point"}
}