{
  "type": "Feature",
  "properties": {
    "gn:admin1_code":"21.0",
    "gn:admin2_code":"7413150.0",
    "gn:asciiname":"Meno",
    "gn:country_code":"JP",
    "gn:dem":97,
    "gn:feature_class":"P",
    "gn:feature_code":"PPLL",
    "gn:name":"Meno",
    "gn:population":0,
    "gn:timezone":"Asia/Tokyo",
    "iso:country":"JP",
    "name:ara_x_preferred":[
        "\u0645\u064a\u0646\u0648"
    ],
    "name:bul_x_preferred":[
        "\u041c\u0435\u043d\u043e\u043d"
    ],
    "name:cat_x_preferred":[
        "Men\u00f3"
    ],
    "name:dan_x_preferred":[
        "Menon"
    ],
    "name:deu_x_preferred":[
        "Menon"
    ],
    "name:ell_x_preferred":[
        "\u039c\u03ad\u03bd\u03c9\u03bd"
    ],
    "name:est_x_preferred":[
        "Menon"
    ],
    "name:fas_x_preferred":[
        "\u0645\u0646\u0648\u0646"
    ],
    "name:fin_x_preferred":[
        "Menon"
    ],
    "name:fra_x_preferred":[
        "M\u00e9non"
    ],
    "name:heb_x_preferred":[
        "\u05de\u05e0\u05d5\u05df"
    ],
    "name:hun_x_preferred":[
        "Men\u00f3n"
    ],
    "name:ind_x_preferred":[
        "Menon"
    ],
    "name:isl_x_preferred":[
        "Menon"
    ],
    "name:ita_x_preferred":[
        "Menone"
    ],
    "name:jpn_x_preferred":[
        "\u7c73\u91ce"
    ],
    "name:jpn_x_variant":[
        "\u3081\u306e",
        "\u30e1\u30ce",
        "\u30e1\u30ce\u30f3"
    ],
    "name:kat_x_preferred":[
        "\u10db\u10d4\u10dc\u10dd\u10dc\u10d8"
    ],
    "name:nld_x_preferred":[
        "Meno"
    ],
    "name:nor_x_preferred":[
        "Menon"
    ],
    "name:pol_x_preferred":[
        "Menon"
    ],
    "name:por_x_preferred":[
        "M\u00eanon"
    ],
    "name:ron_x_preferred":[
        "Menon"
    ],
    "name:rus_x_preferred":[
        "\u041c\u0435\u043d\u043e\u043d"
    ],
    "name:spa_x_preferred":[
        "Men\u00f3n"
    ],
    "name:ukr_x_preferred":[
        "\u041c\u0435\u043d\u043e\u043d"
    ],
    "name:zho_x_preferred":[
        "\u7f8e\u8bfa\u7bc7"
    ],
    "wof:name":"Meno",
    "wof:placetype":"locality"
},
  "geometry": {"coordinates":[130.66233,32.96739],"type":"Point"}
}