{
  "type": "Feature",
  "properties": {
    "gn:admin1_code":"3.0",
    "gn:admin2_code":"8534376.0",
    "gn:admin3_code":"2321.0",
    "gn:asciiname":"Minamiukitamachi",
    "gn:country_code":"JP",
    "gn:dem":27,
    "gn:feature_class":"P",
    "gn:feature_code":"PPL",
    "gn:name":"Minamiukitamachi",
    "gn:population":0,
    "gn:timezone":"Asia/Tokyo",
    "iso:country":"JP",
    "name:jpn_x_preferred":[
        "\u5357\u6d6e\u7530\u753a"
    ],
    "name:jpn_x_variant":[
        "\u307f\u306a\u307f\u3046\u304d\u305f\u307e\u3061",
        "\u30df\u30ca\u30df\u30a6\u30ad\u30bf\u30de\u30c1"
    ],
    "wof:name":"Minamiukitamachi",
    "wof:placetype":"locality"
},
  "geometry": {"coordinates":[140.24504999999999,40.78016],"type":"Point"}
}