{
  "type": "Feature",
  "properties": {
    "gn:admin1_code":"36.0",
    "gn:admin2_code":"1854361.0",
    "gn:admin3_code":"32528.0",
    "gn:asciiname":"Takugi",
    "gn:country_code":"JP",
    "gn:dem":7,
    "gn:feature_class":"P",
    "gn:feature_code":"PPL",
    "gn:name":"Takugi",
    "gn:population":0,
    "gn:timezone":"Asia/Tokyo",
    "iso:country":"JP",
    "name:jpn_x_preferred":[
        "\u86f8\u6728"
    ],
    "wof:name":"Takugi",
    "wof:placetype":"locality"
},
  "geometry": {"coordinates":[133.25013999999999,36.16291],"type":"Point"}
}