{
  "type": "Feature",
  "properties": {
    "iso:country":"JP",
    "qs:name":"\uff14\u4e01\u76ee",
    "qs:name_adm0":"\u65e5\u672c",
    "qs:name_adm1":"\u795e\u5948\u5ddd\u770c",
    "qs:photos":75,
    "qs:photos_1k":15,
    "qs:photos_9k":1,
    "qs:photos_9r":2,
    "qs:photos_all":75,
    "qs:photos_sr":2,
    "qs:placetype":"Suburb",
    "qs:pop_sr":"0",
    "wof:name":"\uff14\u4e01\u76ee",
    "wof:placetype":"neighbourhood"
},
  "geometry": {"coordinates":[139.64150900000001,35.581104],"type":"Point"}
}