{
  "type": "Feature",
  "properties": {
    "iso:country":"JP",
    "name:eng_x_preferred":[
        "Namidatemaeda 3 Chome"
    ],
    "name:eng_x_variant":[
        "Namidatemaeda 3 Choume",
        "Namidatemaeda 3 Chome"
    ],
    "name:jpn_x_preferred":[
        "\uff13\u4e01\u76ee"
    ],
    "name:jpn_x_variant":[
        "\u306a\u307f\u3060\u3066\u307e\u3048\u3060 \uff13\u3061\u3087\u3046\u3081",
        "\u6d6a\u9928\u524d\u7530 \uff13\u4e01\u76ee",
        "\uff13\u3061\u3087\u3046\u3081"
    ],
    "qs:gn_local":0,
    "qs:local_max":933,
    "qs:local_sum":1431,
    "qs:localhoods":7,
    "qs:name":"\uff13\u4e01\u76ee",
    "qs:name_adm0":"\u65e5\u672c",
    "qs:name_adm1":"\u9752\u68ee\u770c",
    "qs:name_en":"Namidatemaeda 3 Chome",
    "qs:name_lau":"\u6d6a\u9928\u524d\u7530",
    "qs:name_local":"\u9752\u68ee\u5e02",
    "qs:photo_max":44,
    "qs:photo_sum":97,
    "qs:placetype":"Suburb",
    "qs:quad_count":10,
    "qs:woe_adm0":23424856,
    "qs:woe_adm1":2345853,
    "qs:woe_adm2":0,
    "qs:woe_lau":28387275,
    "qs:woe_local":1116973,
    "qs:woe_ver":"7.10.0",
    "wof:lang":[
        "jpn"
    ],
    "wof:name":"\uff13\u4e01\u76ee",
    "wof:placetype":"neighbourhood"
},
  "geometry": {"coordinates":[140.70199099999999,40.806714],"type":"Point"}
}