{
  "type": "Feature",
  "properties": {
    "gn:admin1_code":"21.0",
    "gn:admin2_code":"1850743.0",
    "gn:asciiname":"Kamenoko",
    "gn:country_code":"JP",
    "gn:dem":17,
    "gn:feature_class":"P",
    "gn:feature_code":"PPL",
    "gn:name":"Kamenok\u014d",
    "gn:population":0,
    "gn:timezone":"Asia/Tokyo",
    "iso:country":"JP",
    "name:jpn_x_preferred":[
        "\u4e80\u7532"
    ],
    "name:jpn_x_variant":[
        "\u304b\u3081\u306e\u3053\u3046",
        "\u30ab\u30e1\u30ce\u30b3\u30a6"
    ],
    "name:und_x_variant":[
        "Kamenok\u014d"
    ],
    "wof:name":"Kamenoko",
    "wof:placetype":"locality"
},
  "geometry": {"coordinates":[130.55233999999999,32.92918],"type":"Point"}
}