{
  "type": "Feature",
  "properties": {
    "gn:admin1_code":"36",
    "gn:admin2_code":"1857549.0",
    "gn:asciiname":"Mihonosekicho-chikumi",
    "gn:country_code":"JP",
    "gn:dem":56,
    "gn:feature_class":"P",
    "gn:feature_code":"PPL",
    "gn:name":"Mihonosekich\u014d-chikumi",
    "gn:population":0,
    "gn:timezone":"Asia/Tokyo",
    "iso:country":"JP",
    "name:jpn_x_preferred":[
        "\u7f8e\u4fdd\u95a2\u753a\u5343\u914c"
    ],
    "name:und_x_variant":[
        "Chikume",
        "Chikumi",
        "Mihonosekich\u014d-chikumi"
    ],
    "wof:name":"Mihonosekicho-chikumi",
    "wof:placetype":"locality"
},
  "geometry": {"coordinates":[133.13762,35.56542],"type":"Point"}
}