{
  "type": "Feature",
  "properties": {
    "iso:country":"JP",
    "name:eng_x_preferred":[
        "Okura"
    ],
    "name:eng_x_variant":[
        "Okura Village"
    ],
    "name:jpn_x_preferred":[
        "\u5927\u8535\u6751"
    ],
    "qs:name":"\u5927\u8535\u6751",
    "qs:name_adm0":"\u65e5\u672c",
    "qs:name_adm1":"\u5c71\u5f62\u770c",
    "qs:photos":46,
    "qs:photos_1k":9,
    "qs:photos_9k":1,
    "qs:photos_9r":2,
    "qs:photos_all":46,
    "qs:photos_sr":2,
    "qs:placetype":"Town",
    "qs:pop_sr":"0",
    "wof:name":"Okura",
    "wof:placetype":"locality"
},
  "geometry": {"coordinates":[140.16662099999999,38.60852],"type":"Point"}
}