{
  "type": "Feature",
  "properties": {
    "gn:admin1_code":"43.0",
    "gn:admin2_code":"1863079.0",
    "gn:asciiname":"Sugo",
    "gn:country_code":"JP",
    "gn:dem":270,
    "gn:feature_class":"P",
    "gn:feature_code":"PPL",
    "gn:name":"Sug\u014d",
    "gn:population":0,
    "gn:timezone":"Asia/Tokyo",
    "iso:country":"JP",
    "name:jpn_x_preferred":[
        "\u9808\u6cb3"
    ],
    "name:und_x_variant":[
        "Sug\u014d"
    ],
    "wof:name":"Sugo",
    "wof:placetype":"locality"
},
  "geometry": {"coordinates":[135.65836999999999,34.30027],"type":"Point"}
}