{
  "type": "Feature",
  "properties": {
    "iso:country":"JP",
    "name:eng_x_preferred":[
        "Monomiyama 3 Chome"
    ],
    "name:eng_x_variant":[
        "Monomiyama 3 Choume",
        "Monomiyama 3 Chome"
    ],
    "name:jpn_x_preferred":[
        "\uff13\u4e01\u76ee"
    ],
    "name:jpn_x_variant":[
        "\u3082\u306e\u307f\u3084\u307e \uff13\u3061\u3087\u3046\u3081",
        "\u7269\u898b\u5c71 \uff13\u4e01\u76ee",
        "\uff13\u3061\u3087\u3046\u3081"
    ],
    "qs:gn_local":0,
    "qs:local_max":1296,
    "qs:local_sum":6373,
    "qs:localhoods":29,
    "qs:name":"\uff13\u4e01\u76ee",
    "qs:name_adm0":"\u65e5\u672c",
    "qs:name_adm1":"\u65b0\u6f5f\u770c",
    "qs:name_adm2":"\u6771\u533a",
    "qs:name_en":"Monomiyama 3 Chome",
    "qs:name_lau":"\u7269\u898b\u5c71",
    "qs:name_local":"\u65b0\u6f5f\u5e02",
    "qs:photo_max":196,
    "qs:photo_sum":238,
    "qs:placetype":"Suburb",
    "qs:quad_count":3,
    "qs:woe_adm0":23424856,
    "qs:woe_adm1":2345878,
    "qs:woe_adm2":55805802,
    "qs:woe_lau":55807717,
    "qs:woe_local":1117881,
    "qs:woe_ver":"7.10.0",
    "wof:lang":[
        "jpn"
    ],
    "wof:name":"\uff13\u4e01\u76ee",
    "wof:placetype":"neighbourhood"
},
  "geometry": {"coordinates":[139.09699900000001,37.945664],"type":"Point"}
}