{
  "type": "Feature",
  "properties": {
    "iso:country":"JP",
    "name:eng_x_preferred":[
        "Honchodori 1 Chome"
    ],
    "name:eng_x_variant":[
        "Honchoudoori 1 Choume",
        "Honchodori 1 Chome"
    ],
    "name:jpn_x_preferred":[
        "\uff11\u4e01\u76ee"
    ],
    "name:jpn_x_variant":[
        "\u307b\u3093\u3061\u3087\u3046\u3069\u304a\u308a \uff11\u3061\u3087\u3046\u3081",
        "\u672c\u753a\u901a \uff11\u4e01\u76ee",
        "\uff11\u3061\u3087\u3046\u3081"
    ],
    "qs:gn_adm0_cc":"JP",
    "qs:gn_local":2111834,
    "qs:gn_nam_loc":"\u76db\u5ca1\u5e02, \u5ca9\u624b\u770c, JP",
    "qs:gn_namadm1":"16",
    "qs:local_max":736,
    "qs:local_sum":1250,
    "qs:localhoods":8,
    "qs:name":"\uff11\u4e01\u76ee",
    "qs:name_adm0":"\u65e5\u672c",
    "qs:name_adm1":"\u5ca9\u624b\u770c",
    "qs:name_en":"Honchodori 1 Chome",
    "qs:name_lau":"\u672c\u753a\u901a",
    "qs:name_local":"\u76db\u5ca1\u5e02",
    "qs:photo_max":25,
    "qs:photo_sum":69,
    "qs:placetype":"Suburb",
    "qs:quad_count":9,
    "qs:woe_adm0":23424856,
    "qs:woe_adm1":2345865,
    "qs:woe_adm2":0,
    "qs:woe_lau":28389499,
    "qs:woe_local":1117776,
    "qs:woe_ver":"7.10.0",
    "qs_pg:name":"\uff11\u4e01\u76ee",
    "qs_pg:name_adm0":"\u65e5\u672c",
    "qs_pg:name_adm1":"\u5ca9\u624b\u770c",
    "qs_pg:photos":38,
    "qs_pg:photos_1k":8,
    "qs_pg:photos_9k":1,
    "qs_pg:photos_9r":2,
    "qs_pg:photos_all":38,
    "qs_pg:photos_sr":2,
    "qs_pg:pop_sr":0,
    "qs_pg:qs_pg_placetype":"neighbourhood",
    "qs_pg:qs_pg_placetype_gp":"Suburb",
    "qs_pg:woe_adm0":23424856,
    "woe:adm0_id":23424856,
    "woe:name_adm0":"\u65e5\u672c",
    "woe:name_adm1":"\u5ca9\u624b\u770c",
    "woe:placetype":"Suburb",
    "wof:lang":[
        "jpn"
    ],
    "wof:name":"\uff11\u4e01\u76ee",
    "wof:placetype":"neighbourhood"
},
  "geometry": {"coordinates":[141.15628000000001,39.703989],"type":"Point"}
}