{
  "type": "Feature",
  "properties": {
    "gn:admin1_code":"25",
    "gn:admin2_code":"1858599.0",
    "gn:admin3_code":"45403.0",
    "gn:asciiname":"Makinokuchi",
    "gn:cc2":"JP",
    "gn:country_code":"JP",
    "gn:dem":683,
    "gn:feature_class":"P",
    "gn:feature_code":"PPL",
    "gn:name":"Makinokuchi",
    "gn:population":0,
    "gn:timezone":"Asia/Tokyo",
    "iso:country":"JP",
    "name:und_x_variant":[
        "Makinouchi",
        "Makinoguchi",
        "Makinokuchi"
    ],
    "wof:name":"Makinokuchi",
    "wof:placetype":"locality"
},
  "geometry": {"coordinates":[131.11667,32.28333],"type":"Point"}
}