{
  "type": "Feature",
  "properties": {
    "gn:admin1_code":"10.0",
    "gn:admin2_code":"7453747.0",
    "gn:admin3_code":"10424.0",
    "gn:asciiname":"Goshodaira",
    "gn:country_code":"JP",
    "gn:dem":1006,
    "gn:feature_class":"P",
    "gn:feature_code":"PPLL",
    "gn:name":"Goshodaira",
    "gn:population":0,
    "gn:timezone":"Asia/Tokyo",
    "iso:country":"JP",
    "name:jpn_x_preferred":[
        "\u5fa1\u6240\u5e73"
    ],
    "wof:name":"Goshodaira",
    "wof:placetype":"locality"
},
  "geometry": {"coordinates":[138.58748,36.48882],"type":"Point"}
}