{
  "type": "Feature",
  "properties": {
    "gn:admin1_code":"18.0",
    "gn:admin2_code":"7383999.0",
    "gn:admin3_code":"46491.0",
    "gn:asciiname":"Kaminohara",
    "gn:country_code":"JP",
    "gn:dem":87,
    "gn:feature_class":"P",
    "gn:feature_code":"PPLL",
    "gn:name":"Kaminohara",
    "gn:population":0,
    "gn:timezone":"Asia/Tokyo",
    "iso:country":"JP",
    "name:jpn_x_preferred":[
        "\u4e0a\u4e4b\u539f"
    ],
    "wof:name":"Kaminohara",
    "wof:placetype":"locality"
},
  "geometry": {"coordinates":[130.82058000000001,31.10265],"type":"Point"}
}