{
  "type": "Feature",
  "properties": {
    "gn:admin1_code":"01",
    "gn:admin2_code":"7369802.0",
    "gn:asciiname":"Maeshiba",
    "gn:country_code":"JP",
    "gn:dem":-1,
    "gn:feature_class":"P",
    "gn:feature_code":"PPL",
    "gn:name":"Maeshiba",
    "gn:population":0,
    "gn:timezone":"Asia/Tokyo",
    "iso:country":"JP",
    "wof:name":"Maeshiba",
    "wof:placetype":"locality"
},
  "geometry": {"coordinates":[137.33333000000002,34.78333],"type":"Point"}
}