{
  "type": "Feature",
  "properties": {
    "iso:country":"JP",
    "name:eng_x_preferred":[
        "Akashi"
    ],
    "name:eng_x_variant":[
        "Akashi City"
    ],
    "name:jpn_x_preferred":[
        "\u660e\u77f3\u5e02"
    ],
    "qs:name":"\u660e\u77f3\u5e02",
    "qs:name_adm0":"\u65e5\u672c",
    "qs:name_adm1":"\u5175\u5eab\u770c",
    "qs:photos":248,
    "qs:photos_1k":50,
    "qs:photos_9k":13,
    "qs:photos_9r":11,
    "qs:photos_all":2957,
    "qs:photos_sr":4,
    "qs:placetype":"Town",
    "qs:pop_sr":"0",
    "wof:name":"Akashi",
    "wof:placetype":"locality"
},
  "geometry": {"coordinates":[134.97528,34.65538],"type":"Point"}
}