{
  "type": "Feature",
  "properties": {
    "gn:admin1_code":"40.0",
    "gn:admin2_code":"1864529.0",
    "gn:asciiname":"Kioicho",
    "gn:country_code":"JP",
    "gn:dem":33,
    "gn:feature_class":"P",
    "gn:feature_code":"PPL",
    "gn:name":"Kioich\u014d",
    "gn:population":0,
    "gn:timezone":"Asia/Tokyo",
    "iso:country":"JP",
    "name:jpn_x_preferred":[
        "\u7d00\u5c3e\u4e95\u753a"
    ],
    "name:und_x_variant":[
        "Kioich\u014d"
    ],
    "wof:name":"Kioicho",
    "wof:placetype":"locality"
},
  "geometry": {"coordinates":[139.73676,35.68124],"type":"Point"}
}