{
  "type": "Feature",
  "properties": {
    "gn:admin1_code":"09",
    "gn:admin2_code":"1850890.0",
    "gn:asciiname":"Kiyomicho-natsumaya",
    "gn:country_code":"JP",
    "gn:dem":889,
    "gn:feature_class":"P",
    "gn:feature_code":"PPL",
    "gn:name":"Kiyomich\u014d-natsumaya",
    "gn:population":0,
    "gn:timezone":"Asia/Tokyo",
    "iso:country":"JP",
    "name:jpn_x_preferred":[
        "\u6e05\u898b\u753a\u590f\u53a9"
    ],
    "name:und_x_variant":[
        "Natsumai",
        "Natsumaya",
        "Kiyomich\u014d-natsumaya"
    ],
    "wof:name":"Kiyomicho-natsumaya",
    "wof:placetype":"locality"
},
  "geometry": {"coordinates":[137.07936000000001,36.14247],"type":"Point"}
}