{
  "type": "Feature",
  "properties": {
    "gn:admin1_code":"21.0",
    "gn:admin2_code":"1850744.0",
    "gn:admin3_code":"43367.0",
    "gn:asciiname":"Nagose",
    "gn:country_code":"JP",
    "gn:dem":63,
    "gn:feature_class":"P",
    "gn:feature_code":"PPLL",
    "gn:name":"Nagose",
    "gn:population":0,
    "gn:timezone":"Asia/Tokyo",
    "iso:country":"JP",
    "name:jpn_x_preferred":[
        "\u540d\u53e4\u702c"
    ],
    "name:jpn_x_variant":[
        "\u306a\u3054\u305b",
        "\u30ca\u30b4\u30bb"
    ],
    "wof:name":"Nagose",
    "wof:placetype":"locality"
},
  "geometry": {"coordinates":[130.52590000000001,33.04754000000001],"type":"Point"}
}