{
  "type": "Feature",
  "properties": {
    "gn:admin1_code":"34.0",
    "gn:admin2_code":"7464123.0",
    "gn:asciiname":"Seimon",
    "gn:country_code":"JP",
    "gn:dem":5,
    "gn:feature_class":"P",
    "gn:feature_code":"PPL",
    "gn:name":"Seimon",
    "gn:population":0,
    "gn:timezone":"Asia/Tokyo",
    "iso:country":"JP",
    "name:jpn_x_preferred":[
        "\u6e05\u9580"
    ],
    "wof:name":"Seimon",
    "wof:placetype":"locality"
},
  "geometry": {"coordinates":[139.78253000000001,35.85295],"type":"Point"}
}