{
  "type": "Feature",
  "properties": {
    "gn:admin1_code":"29.0",
    "gn:admin2_code":"7468158.0",
    "gn:admin3_code":"15482.0",
    "gn:asciiname":"Yokone",
    "gn:country_code":"JP",
    "gn:dem":709,
    "gn:feature_class":"P",
    "gn:feature_code":"PPLL",
    "gn:name":"Yokone",
    "gn:population":0,
    "gn:timezone":"Asia/Tokyo",
    "iso:country":"JP",
    "name:jpn_x_preferred":[
        "\u6a2a\u6839"
    ],
    "wof:name":"Yokone",
    "wof:placetype":"locality"
},
  "geometry": {"coordinates":[138.62880000000001,36.94907],"type":"Point"}
}