{
  "type": "Feature",
  "properties": {
    "gn:admin1_code":"21.0",
    "gn:admin2_code":"1862350.0",
    "gn:asciiname":"Kobutsuchomachi",
    "gn:country_code":"JP",
    "gn:dem":175,
    "gn:feature_class":"P",
    "gn:feature_code":"PPL",
    "gn:name":"Kobutsuch\u014dmachi",
    "gn:population":0,
    "gn:timezone":"Asia/Tokyo",
    "iso:country":"JP",
    "name:jpn_x_preferred":[
        "\u53e4\u4ecf\u9802\u753a"
    ],
    "name:jpn_x_variant":[
        "\u3053\u3076\u3064\u3061\u3087\u3046\u307e\u3061",
        "\u30b3\u30d6\u30c4\u30c1\u30e7\u30a6\u30de\u30c1"
    ],
    "name:und_x_variant":[
        "Kobutsuch\u014dmachi"
    ],
    "wof:name":"Kobutsuchomachi",
    "wof:placetype":"locality"
},
  "geometry": {"coordinates":[130.76238999999998,32.16739],"type":"Point"}
}