{
  "type": "Feature",
  "properties": {
    "gn:admin1_code":"05",
    "gn:admin2_code":"1926135.0",
    "gn:asciiname":"Miyakubo",
    "gn:country_code":"JP",
    "gn:dem":5,
    "gn:feature_class":"P",
    "gn:feature_code":"PPL",
    "gn:name":"Miyakubo",
    "gn:population":0,
    "gn:timezone":"Asia/Tokyo",
    "iso:country":"JP",
    "name:jpn_x_preferred":[
        "\u5bae\u7aaa\u753a"
    ],
    "name:spa_x_preferred":[
        "Miyakubo"
    ],
    "name:und_x_variant":[
        "Miyanokubo",
        "Miyakubo"
    ],
    "wof:name":"Miyakubo",
    "wof:placetype":"locality"
},
  "geometry": {"coordinates":[133.07499999999999,34.17610999999999],"type":"Point"}
}