{
  "type": "Feature",
  "properties": {
    "gn:admin1_code":"21.0",
    "gn:admin2_code":"7412706.0",
    "gn:admin3_code":"43443.0",
    "gn:asciiname":"Shimoharu",
    "gn:country_code":"JP",
    "gn:dem":8,
    "gn:feature_class":"P",
    "gn:feature_code":"PPLL",
    "gn:name":"Shimoharu",
    "gn:population":0,
    "gn:timezone":"Asia/Tokyo",
    "iso:country":"JP",
    "name:jpn_x_preferred":[
        "\u4e0b\u539f"
    ],
    "name:jpn_x_variant":[
        "\u3057\u3082\u306f\u308b",
        "\u30b7\u30e2\u30cf\u30eb"
    ],
    "wof:name":"Shimoharu",
    "wof:placetype":"locality"
},
  "geometry": {"coordinates":[130.79613999999998,32.76236],"type":"Point"}
}