{
  "type": "Feature",
  "properties": {
    "gn:admin1_code":"21.0",
    "gn:admin2_code":"7412708.0",
    "gn:admin3_code":"43501.0",
    "gn:asciiname":"Shimo'ozuru",
    "gn:country_code":"JP",
    "gn:dem":156,
    "gn:feature_class":"P",
    "gn:feature_code":"PPLL",
    "gn:name":"Shimo\u2019\u014dzuru",
    "gn:population":0,
    "gn:timezone":"Asia/Tokyo",
    "iso:country":"JP",
    "name:jpn_x_preferred":[
        "\u4e0b\u5927\u9db4"
    ],
    "name:jpn_x_variant":[
        "\u3057\u3082\u304a\u304a\u3065\u308b",
        "\u30b7\u30e2\u30aa\u30aa\u30c5\u30eb"
    ],
    "name:und_x_variant":[
        "Shimo\u2019\u014dzuru"
    ],
    "wof:name":"Shimo'ozuru",
    "wof:placetype":"locality"
},
  "geometry": {"coordinates":[130.82936000000001,32.19119],"type":"Point"}
}