{
  "type": "Feature",
  "properties": {
    "gn:admin1_code":"28.0",
    "gn:admin2_code":"7411376.0",
    "gn:admin3_code":"29402.0",
    "gn:asciiname":"Nyudani",
    "gn:country_code":"JP",
    "gn:dem":402,
    "gn:feature_class":"P",
    "gn:feature_code":"PPL",
    "gn:name":"Ny\u016bdani",
    "gn:population":0,
    "gn:timezone":"Asia/Tokyo",
    "iso:country":"JP",
    "name:jpn_x_preferred":[
        "\u5165\u8c37"
    ],
    "name:und_x_variant":[
        "Ny\u016bdani"
    ],
    "wof:name":"Nyudani",
    "wof:placetype":"locality"
},
  "geometry": {"coordinates":[135.84222,34.44272],"type":"Point"}
}