{
  "type": "Feature",
  "properties": {
    "gn:admin1_code":"7.0",
    "gn:admin2_code":"7406950.0",
    "gn:admin3_code":"40625.0",
    "gn:asciiname":"Ochozu",
    "gn:country_code":"JP",
    "gn:dem":91,
    "gn:feature_class":"P",
    "gn:feature_code":"PPL",
    "gn:name":"Och\u014dzu",
    "gn:population":0,
    "gn:timezone":"Asia/Tokyo",
    "iso:country":"JP",
    "name:jpn_x_preferred":[
        "\u5fa1\u624b\u6c34"
    ],
    "name:und_x_variant":[
        "Och\u014dzu"
    ],
    "wof:name":"Ochozu",
    "wof:placetype":"locality"
},
  "geometry": {"coordinates":[130.90126000000001,33.67437],"type":"Point"}
}