{
  "type": "Feature",
  "properties": {
    "gn:admin1_code":"14",
    "gn:admin2_code":"1852162.0",
    "gn:asciiname":"Takasai",
    "gn:country_code":"JP",
    "gn:dem":26,
    "gn:feature_class":"P",
    "gn:feature_code":"PPL",
    "gn:name":"Takasai",
    "gn:population":0,
    "gn:timezone":"Asia/Tokyo",
    "iso:country":"JP",
    "wof:name":"Takasai",
    "wof:placetype":"locality"
},
  "geometry": {"coordinates":[140.01667,36.18333],"type":"Point"}
}