{
  "type": "Feature",
  "properties": {
    "gn:admin1_code":"37.0",
    "gn:admin2_code":"1854900.0",
    "gn:asciiname":"Uchiura-shigedera",
    "gn:country_code":"JP",
    "gn:dem":24,
    "gn:feature_class":"P",
    "gn:feature_code":"PPL",
    "gn:name":"Uchiura-shigedera",
    "gn:population":0,
    "gn:timezone":"Asia/Tokyo",
    "iso:country":"JP",
    "name:jpn_x_preferred":[
        "\u5185\u6d66\u91cd\u5bfa"
    ],
    "wof:name":"Uchiura-shigedera",
    "wof:placetype":"locality"
},
  "geometry": {"coordinates":[138.89578999999998,35.03334],"type":"Point"}
}