{
  "type": "Feature",
  "properties": {
    "iso:country":"JP",
    "name:eng_x_preferred":[
        "Nijoojiminami 3 Chome"
    ],
    "name:eng_x_variant":[
        "Nijouoojiminami 3 Choume",
        "Nijoojiminami 3 Chome"
    ],
    "name:jpn_x_preferred":[
        "\uff13\u4e01\u76ee"
    ],
    "name:jpn_x_variant":[
        "\u306b\u3058\u3087\u3046\u304a\u304a\u3058\u307f\u306a\u307f \uff13\u3061\u3087\u3046\u3081",
        "\u4e8c\u6761\u5927\u8def\u5357 \uff13\u4e01\u76ee",
        "\uff13\u3061\u3087\u3046\u3081"
    ],
    "name:unk_x_variant":[
        "\uff13\u4e01\u76ee"
    ],
    "qs:gn_local":0,
    "qs:local_max":12821,
    "qs:local_sum":32218,
    "qs:localhoods":19,
    "qs:name":"\uff13\u4e01\u76ee",
    "qs:name_adm0":"\u65e5\u672c",
    "qs:name_adm1":"\u5948\u826f\u770c",
    "qs:name_en":"Nijoojiminami 3 Chome",
    "qs:name_lau":"\u4e8c\u6761\u5927\u8def\u5357",
    "qs:name_local":"\u5948\u826f\u5e02",
    "qs:photo_max":110,
    "qs:photo_sum":447,
    "qs:placetype":"Suburb",
    "qs:quad_count":16,
    "qs:woe_adm0":23424856,
    "qs:woe_adm1":2345877,
    "qs:woe_adm2":0,
    "qs:woe_lau":28465901,
    "qs:woe_local":1117858,
    "qs:woe_ver":"7.10.0",
    "wof:lang":[
        "jpn"
    ],
    "wof:name":"\uff13\u4e01\u76ee",
    "wof:placetype":"neighbourhood"
},
  "geometry": {"coordinates":[135.79597699999999,34.690439],"type":"Point"}
}