{
  "type": "Feature",
  "properties": {
    "iso:country":"JP",
    "name:eng_x_preferred":[
        "Aramachi 2 Chome"
    ],
    "name:eng_x_variant":[
        "Aramachi 2 Choume",
        "Aramachi 2 Chome"
    ],
    "name:jpn_x_preferred":[
        "\uff12\u4e01\u76ee"
    ],
    "name:jpn_x_variant":[
        "\u3042\u3089\u307e\u3061 \uff12\u3061\u3087\u3046\u3081",
        "\u8352\u753a \uff12\u4e01\u76ee",
        "\uff12\u3061\u3087\u3046\u3081"
    ],
    "qs:gn_local":0,
    "qs:local_max":38,
    "qs:local_sum":39,
    "qs:localhoods":2,
    "qs:name":"\uff12\u4e01\u76ee",
    "qs:name_adm0":"\u65e5\u672c",
    "qs:name_adm1":"\u6803\u6728\u770c",
    "qs:name_en":"Aramachi 2 Chome",
    "qs:name_lau":"\u8352\u753a",
    "qs:name_local":"\u771f\u5ca1\u5e02",
    "qs:photo_max":1,
    "qs:photo_sum":1,
    "qs:placetype":"Suburb",
    "qs:quad_count":1,
    "qs:woe_adm0":23424856,
    "qs:woe_adm1":2345887,
    "qs:woe_adm2":0,
    "qs:woe_lau":28405315,
    "qs:woe_local":1112126,
    "qs:woe_ver":"7.10.0",
    "wof:lang":[
        "jpn"
    ],
    "wof:name":"\uff12\u4e01\u76ee",
    "wof:placetype":"neighbourhood"
},
  "geometry": {"coordinates":[140.01800499999999,36.445591],"type":"Point"}
}