{
  "type": "Feature",
  "properties": {
    "gn:admin1_code":"2.0",
    "gn:admin2_code":"7443160.0",
    "gn:asciiname":"Chokaimachi-nakahitane",
    "gn:country_code":"JP",
    "gn:dem":290,
    "gn:feature_class":"P",
    "gn:feature_code":"PPL",
    "gn:name":"Ch\u014dkaimachi-nakahitane",
    "gn:population":0,
    "gn:timezone":"Asia/Tokyo",
    "iso:country":"JP",
    "name:jpn_x_preferred":[
        "\u9ce5\u6d77\u753a\u4ef2\u76f4\u6839"
    ],
    "name:und_x_variant":[
        "Ch\u014dkaimachi-nakahitane"
    ],
    "wof:name":"Chokaimachi-nakahitane",
    "wof:placetype":"locality"
},
  "geometry": {"coordinates":[140.17376000000002,39.14496],"type":"Point"}
}