{
  "type": "Feature",
  "properties": {
    "gn:admin1_code":"40.0",
    "gn:admin2_code":"1857420.0",
    "gn:asciiname":"Himon'ya",
    "gn:country_code":"JP",
    "gn:dem":34,
    "gn:feature_class":"P",
    "gn:feature_code":"PPL",
    "gn:name":"Himon\u2019ya",
    "gn:population":0,
    "gn:timezone":"Asia/Tokyo",
    "iso:country":"JP",
    "name:jpn_x_preferred":[
        "\u7891\u6587\u8c37"
    ],
    "name:und_x_variant":[
        "Himon\u2019ya"
    ],
    "wof:name":"Himon'ya",
    "wof:placetype":"locality"
},
  "geometry": {"coordinates":[139.68713,35.62],"type":"Point"}
}