{
  "type": "Feature",
  "properties": {
    "gn:admin1_code":"21.0",
    "gn:admin2_code":"7412706.0",
    "gn:admin3_code":"43447.0",
    "gn:asciiname":"Tachibana",
    "gn:country_code":"JP",
    "gn:dem":521,
    "gn:feature_class":"P",
    "gn:feature_code":"PPLL",
    "gn:name":"Tachibana",
    "gn:population":0,
    "gn:timezone":"Asia/Tokyo",
    "iso:country":"JP",
    "name:deu_x_preferred":[
        "Tachibana"
    ],
    "name:fin_x_preferred":[
        "Tachibana"
    ],
    "name:jpn_x_preferred":[
        "\u6a58"
    ],
    "name:jpn_x_variant":[
        "\u305f\u3061\u3070\u306a",
        "\u30bf\u30c1\u30d0\u30ca"
    ],
    "name:kor_x_preferred":[
        "\ub2e4\uce58\ubc14\ub098"
    ],
    "name:rus_x_preferred":[
        "\u0422\u0430\u0442\u0438\u0431\u0430\u043d\u0430"
    ],
    "wof:name":"Tachibana",
    "wof:placetype":"locality"
},
  "geometry": {"coordinates":[131.20408999999998,32.74789000000001],"type":"Point"}
}