{
  "type": "Feature",
  "properties": {
    "gn:admin1_code":"3.0",
    "gn:admin2_code":"2130088.0",
    "gn:admin3_code":"2301.0",
    "gn:asciiname":"Asadokoro",
    "gn:country_code":"JP",
    "gn:dem":74,
    "gn:feature_class":"P",
    "gn:feature_code":"PPL",
    "gn:name":"Asadokoro",
    "gn:population":0,
    "gn:timezone":"Asia/Tokyo",
    "iso:country":"JP",
    "name:jpn_x_preferred":[
        "\u6d45\u6240"
    ],
    "name:jpn_x_variant":[
        "\u3042\u3055\u3069\u3053\u308d",
        "\u30a2\u30b5\u30c9\u30b3\u30ed"
    ],
    "wof:name":"Asadokoro",
    "wof:placetype":"locality"
},
  "geometry": {"coordinates":[140.97403,40.94559],"type":"Point"}
}