{
  "type": "Feature",
  "properties": {
    "iso:country":"JP",
    "qs:name":"\u3044\u308f\u304d\u5e02",
    "qs:name_adm0":"\u65e5\u672c",
    "qs:name_adm1":"\u798f\u5cf6\u770c",
    "qs:photos":800,
    "qs:photos_1k":162,
    "qs:photos_9k":17,
    "qs:photos_9r":12,
    "qs:photos_all":3864,
    "qs:photos_sr":9,
    "qs:placetype":"Town",
    "qs:pop_sr":"0",
    "wof:name":"\u3044\u308f\u304d\u5e02",
    "wof:placetype":"locality"
},
  "geometry": {"coordinates":[140.92094399999999,36.997666],"type":"Point"}
}