{
  "type": "Feature",
  "properties": {
    "gn:admin1_code":"7.0",
    "gn:admin2_code":"1859090.0",
    "gn:asciiname":"Netabi",
    "gn:country_code":"JP",
    "gn:dem":56,
    "gn:feature_class":"P",
    "gn:feature_code":"PPL",
    "gn:name":"Netabi",
    "gn:population":0,
    "gn:timezone":"Asia/Tokyo",
    "iso:country":"JP",
    "name:jpn_x_preferred":[
        "\u7c73\u591a\u6bd4"
    ],
    "wof:name":"Netabi",
    "wof:placetype":"locality"
},
  "geometry": {"coordinates":[130.51511000000002,33.72926],"type":"Point"}
}