{
  "type": "Feature",
  "properties": {
    "gn:admin1_code":"24.0",
    "gn:admin2_code":"2110755.0",
    "gn:asciiname":"Minamikatamachi-oinogake",
    "gn:country_code":"JP",
    "gn:dem":19,
    "gn:feature_class":"P",
    "gn:feature_code":"PPL",
    "gn:name":"Minamikatamachi-oinogake",
    "gn:population":0,
    "gn:timezone":"Asia/Tokyo",
    "iso:country":"JP",
    "name:jpn_x_preferred":[
        "\u5357\u65b9\u753a\u72fc\u639b"
    ],
    "name:und_x_variant":[
        "\u014ckamitsugi",
        "Oinukake",
        "Minamikatamachi-oinogake"
    ],
    "wof:name":"Minamikatamachi-oinogake",
    "wof:placetype":"locality"
},
  "geometry": {"coordinates":[141.12006,38.65844],"type":"Point"}
}