{
  "type": "Feature",
  "properties": {
    "gn:country":"JP",
    "gn:fcode":"ADM3",
    "gn:pop":0,
    "iso:country":"JP",
    "name:jpn_x_preferred":[
        "\u5927\u6cc9\u753a"
    ],
    "name:jpn_x_variant":[
        "\u304a\u304a\u3044\u305a\u307f\u307e\u3061"
    ],
    "qs:name":"\u014cizumi-machi",
    "qs:photos_9r":0,
    "qs:photos_sr":0,
    "qs:pop_sr":"0",
    "wof:name":"\u014cizumi-machi",
    "wof:placetype":"localadmin",
    "wof:population":0
},
  "geometry": {"coordinates":[139.40702999999999,36.24972],"type":"Point"}
}