{
  "type": "Feature",
  "properties": {
    "gn:admin1_code":"28",
    "gn:admin2_code":"1853062.0",
    "gn:asciiname":"Hase",
    "gn:country_code":"JP",
    "gn:dem":165,
    "gn:feature_class":"P",
    "gn:feature_code":"PPL",
    "gn:name":"Hase",
    "gn:population":0,
    "gn:timezone":"Asia/Tokyo",
    "iso:country":"JP",
    "name:ceb_x_preferred":[
        "Hase"
    ],
    "name:chv_x_preferred":[
        "\u0425\u0430\u0437\u0435"
    ],
    "name:dan_x_preferred":[
        "Hase"
    ],
    "name:deu_x_preferred":[
        "Hase"
    ],
    "name:epo_x_preferred":[
        "Hase"
    ],
    "name:est_x_preferred":[
        "Hase j\u00f5gi"
    ],
    "name:fas_x_preferred":[
        "\u0647\u0627\u0632\u0647"
    ],
    "name:fra_x_preferred":[
        "Hase"
    ],
    "name:fry_x_preferred":[
        "Hase"
    ],
    "name:ita_x_preferred":[
        "Hase"
    ],
    "name:jpn_x_preferred":[
        "\u521d\u702c"
    ],
    "name:nld_x_preferred":[
        "Hase"
    ],
    "name:nno_x_preferred":[
        "Elva Hase"
    ],
    "name:nor_x_preferred":[
        "Hase"
    ],
    "name:pol_x_preferred":[
        "Hase"
    ],
    "name:rus_x_preferred":[
        "\u0425\u0430\u0437\u0435"
    ],
    "name:spa_x_preferred":[
        "R\u00edo Hase"
    ],
    "name:swe_x_preferred":[
        "Hase"
    ],
    "name:und_x_variant":[
        "Hasse"
    ],
    "name:zho_x_preferred":[
        "\u54c8\u745f\u6cb3"
    ],
    "wof:name":"Hase",
    "wof:placetype":"locality"
},
  "geometry": {"coordinates":[135.90563,34.53198],"type":"Point"}
}