{
  "type": "Feature",
  "properties": {
    "gn:admin1_code":"28",
    "gn:admin2_code":"1853062.0",
    "gn:asciiname":"Hase",
    "gn:country_code":"JP",
    "gn:dem":165,
    "gn:feature_class":"P",
    "gn:feature_code":"PPL",
    "gn:name":"Hase",
    "gn:population":0,
    "gn:timezone":"Asia/Tokyo",
    "iso:country":"JP",
    "name:jpn_x_preferred":[
        "\u521d\u702c"
    ],
    "name:und_x_variant":[
        "Hasse",
        "Hase"
    ],
    "wof:name":"Hase",
    "wof:placetype":"locality"
},
  "geometry": {"coordinates":[135.90563,34.53198],"type":"Point"}
}