{
  "type": "Feature",
  "properties": {
    "gn:admin1_code":"7.0",
    "gn:admin2_code":"7406950.0",
    "gn:admin3_code":"40625.0",
    "gn:asciiname":"Anbi",
    "gn:country_code":"JP",
    "gn:dem":42,
    "gn:feature_class":"P",
    "gn:feature_code":"PPLL",
    "gn:name":"Anbi",
    "gn:population":0,
    "gn:timezone":"Asia/Tokyo",
    "iso:country":"JP",
    "name:jpn_x_preferred":[
        "\u5b89\u5e73"
    ],
    "name:jpn_x_variant":[
        "\u3042\u3093\u3073"
    ],
    "wof:name":"Anbi",
    "wof:placetype":"locality"
},
  "geometry": {"coordinates":[130.93626,33.64151],"type":"Point"}
}