{
  "type": "Feature",
  "properties": {
    "gn:admin1_code":"8.0",
    "gn:admin2_code":"2112535.0",
    "gn:asciiname":"Miwamachi-nakadera",
    "gn:country_code":"JP",
    "gn:dem":407,
    "gn:feature_class":"P",
    "gn:feature_code":"PPL",
    "gn:name":"Miwamachi-nakadera",
    "gn:population":0,
    "gn:timezone":"Asia/Tokyo",
    "iso:country":"JP",
    "name:jpn_x_preferred":[
        "\u4e09\u548c\u753a\u4e2d\u5bfa"
    ],
    "wof:name":"Miwamachi-nakadera",
    "wof:placetype":"locality"
},
  "geometry": {"coordinates":[140.71046999999999,37.1318],"type":"Point"}
}