{
  "type": "Feature",
  "properties": {
    "gn:admin1_code":"6.0",
    "gn:admin2_code":"7467387.0",
    "gn:asciiname":"Mikunicho-kaji",
    "gn:country_code":"JP",
    "gn:dem":19,
    "gn:feature_class":"P",
    "gn:feature_code":"PPL",
    "gn:name":"Mikunich\u014d-kaji",
    "gn:population":0,
    "gn:timezone":"Asia/Tokyo",
    "iso:country":"JP",
    "name:jpn_x_preferred":[
        "\u4e09\u56fd\u753a\u68b6"
    ],
    "name:und_x_variant":[
        "Mikunich\u014d-kaji"
    ],
    "wof:name":"Mikunicho-kaji",
    "wof:placetype":"locality"
},
  "geometry": {"coordinates":[136.14803999999998,36.25219],"type":"Point"}
}