{
  "type": "Feature",
  "properties": {
    "gn:admin1_code":"23.0",
    "gn:admin2_code":"1861901.0",
    "gn:asciiname":"Shindo",
    "gn:country_code":"JP",
    "gn:dem":191,
    "gn:feature_class":"P",
    "gn:feature_code":"PPL",
    "gn:name":"Shind\u014d",
    "gn:population":0,
    "gn:timezone":"Asia/Tokyo",
    "iso:country":"JP",
    "name:deu_x_preferred":[
        "Shindo"
    ],
    "name:fra_x_preferred":[
        "Shindo"
    ],
    "name:jpn_x_preferred":[
        "\u65b0\u5802"
    ],
    "name:und_x_variant":[
        "Shind\u014d"
    ],
    "wof:name":"Shindo",
    "wof:placetype":"locality"
},
  "geometry": {"coordinates":[136.20219,34.82287],"type":"Point"}
}