{
  "type": "Feature",
  "properties": {
    "gn:admin1_code":"4.0",
    "gn:admin2_code":"1859468.0",
    "gn:asciiname":"Imokubo",
    "gn:country_code":"JP",
    "gn:dem":84,
    "gn:feature_class":"P",
    "gn:feature_code":"PPL",
    "gn:name":"Imokubo",
    "gn:population":0,
    "gn:timezone":"Asia/Tokyo",
    "iso:country":"JP",
    "name:jpn_x_preferred":[
        "\u828b\u7aaa"
    ],
    "name:jpn_x_variant":[
        "\u3044\u3082\u304f\u307c",
        "\u30a4\u30e2\u30af\u30dc"
    ],
    "wof:name":"Imokubo",
    "wof:placetype":"locality"
},
  "geometry": {"coordinates":[140.0583,35.28022],"type":"Point"}
}