{
  "type": "Feature",
  "properties": {
    "gn:admin1_code":"27",
    "gn:admin2_code":"1852895.0",
    "gn:asciiname":"Yunokicho",
    "gn:country_code":"JP",
    "gn:dem":130,
    "gn:feature_class":"P",
    "gn:feature_code":"PPL",
    "gn:name":"Yunokich\u014d",
    "gn:population":0,
    "gn:timezone":"Asia/Tokyo",
    "iso:country":"JP",
    "name:jpn_x_preferred":[
        "\u67da\u6728\u753a"
    ],
    "name:und_x_variant":[
        "Yunokich\u014d",
        "Yunoki"
    ],
    "wof:name":"Yunokicho",
    "wof:placetype":"locality"
},
  "geometry": {"coordinates":[129.76428000000001,33.20795],"type":"Point"}
}