{
  "type": "Feature",
  "properties": {
    "gn:admin1_code":"19.0",
    "gn:admin2_code":"1848350.0",
    "gn:admin3_code":"14115.0",
    "gn:asciiname":"Katsuradai-nishi",
    "gn:country_code":"JP",
    "gn:dem":62,
    "gn:feature_class":"P",
    "gn:feature_code":"PPL",
    "gn:name":"Katsuradai-nishi",
    "gn:population":0,
    "gn:timezone":"Asia/Tokyo",
    "iso:country":"JP",
    "name:jpn_x_preferred":[
        "\u6842\u53f0\u897f"
    ],
    "name:jpn_x_variant":[
        "\u304b\u3064\u3089\u3060\u3044\u306b\u3057",
        "\u30ab\u30c4\u30e9\u30c0\u30a4\u30cb\u30b7"
    ],
    "wof:name":"Katsuradai-nishi",
    "wof:placetype":"locality"
},
  "geometry": {"coordinates":[139.56148999999999,35.35561],"type":"Point"}
}