{
  "type": "Feature",
  "properties": {
    "gn:admin1_code":"21.0",
    "gn:admin2_code":"1857206.0",
    "gn:asciiname":"Makinouchi",
    "gn:country_code":"JP",
    "gn:dem":16,
    "gn:feature_class":"P",
    "gn:feature_code":"PPL",
    "gn:name":"Makinouchi",
    "gn:population":0,
    "gn:timezone":"Asia/Tokyo",
    "iso:country":"JP",
    "name:jpn_x_preferred":[
        "\u7267\u30ce\u5185"
    ],
    "name:jpn_x_variant":[
        "\u307e\u304d\u306e\u3046\u3061",
        "\u30de\u30ad\u30ce\u30a6\u30c1"
    ],
    "wof:name":"Makinouchi",
    "wof:placetype":"locality"
},
  "geometry": {"coordinates":[130.41085000000001,32.21732],"type":"Point"}
}