{
  "type": "Feature",
  "properties": {
    "gn:admin1_code":"18.0",
    "gn:admin2_code":"1855201.0",
    "gn:asciiname":"Chikamasa",
    "gn:country_code":"JP",
    "gn:dem":43,
    "gn:feature_class":"P",
    "gn:feature_code":"PPLL",
    "gn:name":"Chikamasa",
    "gn:population":0,
    "gn:timezone":"Asia/Tokyo",
    "iso:country":"JP",
    "name:jpn_x_preferred":[
        "\u8fd1\u653f"
    ],
    "wof:name":"Chikamasa",
    "wof:placetype":"locality"
},
  "geometry": {"coordinates":[131.04168999999999,30.71849000000001],"type":"Point"}
}