{
  "type": "Feature",
  "properties": {
    "iso:country":"JP",
    "name:eng_x_preferred":[
        "Mama 4 Chome"
    ],
    "name:eng_x_variant":[
        "Mama 4 Choume",
        "Mama 4 Chome"
    ],
    "name:jpn_x_preferred":[
        "\uff14\u4e01\u76ee"
    ],
    "name:jpn_x_variant":[
        "\u307e\u307e \uff14\u3061\u3087\u3046\u3081",
        "\u771f\u9593 \uff14\u4e01\u76ee",
        "\uff14\u3061\u3087\u3046\u3081"
    ],
    "qs:gn_adm0_cc":"JP",
    "qs:gn_local":1861968,
    "qs:gn_nam_loc":"\u5e02\u5ddd\u5e02, \u5343\u8449\u770c, JP",
    "qs:gn_namadm1":"04",
    "qs:local_max":248,
    "qs:local_sum":1717,
    "qs:localhoods":18,
    "qs:name":"\uff14\u4e01\u76ee",
    "qs:name_adm0":"\u65e5\u672c",
    "qs:name_adm1":"\u5343\u8449\u770c",
    "qs:name_en":"Mama 4 Chome",
    "qs:name_lau":"\u771f\u9593",
    "qs:name_local":"\u5e02\u5ddd\u5e02",
    "qs:photo_max":39,
    "qs:photo_sum":84,
    "qs:placetype":"Suburb",
    "qs:quad_count":4,
    "qs:woe_adm0":23424856,
    "qs:woe_adm1":2345854,
    "qs:woe_adm2":0,
    "qs:woe_lau":28410890,
    "qs:woe_local":1117273,
    "qs:woe_ver":"7.10.0",
    "wof:lang":[
        "jpn"
    ],
    "wof:name":"\uff14\u4e01\u76ee",
    "wof:placetype":"neighbourhood"
},
  "geometry": {"coordinates":[139.909637,35.73916],"type":"Point"}
}