{
  "type": "Feature",
  "properties": {
    "gn:admin1_code":"33.0",
    "gn:admin2_code":"7391358.0",
    "gn:admin3_code":"41425.0",
    "gn:asciiname":"Hideshinmura",
    "gn:country_code":"JP",
    "gn:dem":-5,
    "gn:feature_class":"P",
    "gn:feature_code":"PPLL",
    "gn:name":"Hideshinmura",
    "gn:population":0,
    "gn:timezone":"Asia/Tokyo",
    "iso:country":"JP",
    "name:jpn_x_preferred":[
        "\u79c0\u65b0\u6751"
    ],
    "wof:name":"Hideshinmura",
    "wof:placetype":"locality"
},
  "geometry": {"coordinates":[130.15056999999999,33.18123],"type":"Point"}
}