{
  "type": "Feature",
  "properties": {
    "gn:admin1_code":"43.0",
    "gn:admin2_code":"1863079.0",
    "gn:asciiname":"Sudacho-shimokusa",
    "gn:country_code":"JP",
    "gn:dem":146,
    "gn:feature_class":"P",
    "gn:feature_code":"PPL",
    "gn:name":"Sudach\u014d-shimokusa",
    "gn:population":0,
    "gn:timezone":"Asia/Tokyo",
    "iso:country":"JP",
    "name:jpn_x_preferred":[
        "\u9685\u7530\u753a\u971c\u8349"
    ],
    "name:und_x_variant":[
        "Sudach\u014d-shimokusa"
    ],
    "wof:name":"Sudacho-shimokusa",
    "wof:placetype":"locality"
},
  "geometry": {"coordinates":[135.6352,34.34655],"type":"Point"}
}