{
  "type": "Feature",
  "properties": {
    "gn:admin1_code":"4.0",
    "gn:admin2_code":"7465521.0",
    "gn:asciiname":"Hamasuga",
    "gn:country_code":"JP",
    "gn:dem":11,
    "gn:feature_class":"P",
    "gn:feature_code":"PPLL",
    "gn:name":"Hamasuga",
    "gn:population":0,
    "gn:timezone":"Asia/Tokyo",
    "iso:country":"JP",
    "name:jpn_x_preferred":[
        "\u6d5c\u9808\u8cc0"
    ],
    "name:jpn_x_variant":[
        "\u306f\u307e\u3059\u304c",
        "\u30cf\u30de\u30b9\u30ac"
    ],
    "wof:name":"Hamasuga",
    "wof:placetype":"locality"
},
  "geometry": {"coordinates":[139.82572999999999,35.06209],"type":"Point"}
}