{
  "type": "Feature",
  "properties": {
    "gn:admin1_code":"12.0",
    "gn:admin2_code":"2129370.0",
    "gn:asciiname":"Saiyanai",
    "gn:country_code":"JP",
    "gn:dem":234,
    "gn:feature_class":"P",
    "gn:feature_code":"PPL",
    "gn:name":"Saiyanai",
    "gn:population":0,
    "gn:timezone":"Asia/Tokyo",
    "iso:country":"JP",
    "wof:name":"Saiyanai",
    "wof:placetype":"locality"
},
  "geometry": {"coordinates":[144.09999999999999,43.31667],"type":"Point"}
}