{
  "type": "Feature",
  "properties": {
    "gn:admin1_code":"7.0",
    "gn:admin2_code":"1858305.0",
    "gn:admin3_code":"40402.0",
    "gn:asciiname":"Higashiku",
    "gn:country_code":"JP",
    "gn:dem":9,
    "gn:feature_class":"P",
    "gn:feature_code":"PPLL",
    "gn:name":"Higashiku",
    "gn:population":0,
    "gn:timezone":"Asia/Tokyo",
    "iso:country":"JP",
    "name:jpn_x_preferred":[
        "\u6771\u533a"
    ],
    "wof:name":"Higashiku",
    "wof:placetype":"locality"
},
  "geometry": {"coordinates":[130.67646999999999,33.79475],"type":"Point"}
}