{
  "type": "Feature",
  "properties": {
    "iso:country":"JP",
    "label:eng_x_preferred_longname":[
        "Ogaki City"
    ],
    "label:eng_x_preferred_placetype":[
        "city"
    ],
    "name:eng_x_preferred":[
        "Ogaki"
    ],
    "name:eng_x_variant":[
        "Ogaki City"
    ],
    "name:jpn_x_preferred":[
        "\u5927\u57a3\u5e02"
    ],
    "qs:name":"\u5927\u57a3\u5e02",
    "qs:name_adm0":"\u65e5\u672c",
    "qs:name_adm1":"\u5c90\u961c\u770c",
    "qs:photos":214,
    "qs:photos_1k":43,
    "qs:photos_9k":6,
    "qs:photos_9r":7,
    "qs:photos_all":1300,
    "qs:photos_sr":4,
    "qs:placetype":"Town",
    "qs:pop_sr":"0",
    "wof:name":"Ogaki",
    "wof:placetype":"locality"
},
  "geometry": {"coordinates":[136.6089815,35.3631975],"type":"Point"}
}