{
  "type": "Feature",
  "properties": {
    "gn:admin1_code":"4.0",
    "gn:admin2_code":"2112663.0",
    "gn:asciiname":"Nishikuniyoshi",
    "gn:country_code":"JP",
    "gn:dem":31,
    "gn:feature_class":"P",
    "gn:feature_code":"PPL",
    "gn:name":"Nishikuniyoshi",
    "gn:population":0,
    "gn:timezone":"Asia/Tokyo",
    "iso:country":"JP",
    "name:jpn_x_preferred":[
        "\u897f\u56fd\u5409"
    ],
    "name:jpn_x_variant":[
        "\u306b\u3057\u304f\u306b\u3088\u3057",
        "\u30cb\u30b7\u30af\u30cb\u30e8\u30b7"
    ],
    "wof:name":"Nishikuniyoshi",
    "wof:placetype":"locality"
},
  "geometry": {"coordinates":[140.11841000000001,35.40338],"type":"Point"}
}