{
  "type": "Feature",
  "properties": {
    "gn:admin1_code":"19.0",
    "gn:admin2_code":"1864622.0",
    "gn:asciiname":"Higashikaigan-kita",
    "gn:country_code":"JP",
    "gn:dem":11,
    "gn:feature_class":"P",
    "gn:feature_code":"PPL",
    "gn:name":"Higashikaigan-kita",
    "gn:population":0,
    "gn:timezone":"Asia/Tokyo",
    "iso:country":"JP",
    "name:jpn_x_preferred":[
        "\u6771\u6d77\u5cb8\u5317"
    ],
    "wof:name":"Higashikaigan-kita",
    "wof:placetype":"locality"
},
  "geometry": {"coordinates":[139.41423,35.32759],"type":"Point"}
}