{
  "type": "Feature",
  "properties": {
    "iso:country":"JP",
    "name:eng_x_preferred":[
        "Higashikaiganminami 2 Chome"
    ],
    "name:eng_x_variant":[
        "Higashikaiganminami 2 Choume",
        "Higashikaiganminami 2 Chome"
    ],
    "name:jpn_x_preferred":[
        "\uff12\u4e01\u76ee"
    ],
    "name:jpn_x_variant":[
        "\u3072\u304c\u3057\u304b\u3044\u304c\u3093\u307f\u306a\u307f \uff12\u3061\u3087\u3046\u3081",
        "\u6771\u6d77\u5cb8\u5357 \uff12\u4e01\u76ee",
        "\uff12\u3061\u3087\u3046\u3081"
    ],
    "qs:gn_local":0,
    "qs:local_max":690,
    "qs:local_sum":1970,
    "qs:localhoods":8,
    "qs:name":"\uff12\u4e01\u76ee",
    "qs:name_adm0":"\u65e5\u672c",
    "qs:name_adm1":"\u795e\u5948\u5ddd\u770c",
    "qs:name_en":"Higashikaiganminami 2 Chome",
    "qs:name_lau":"\u6771\u6d77\u5cb8\u5357",
    "qs:name_local":"\u8305\u30f6\u5d0e\u5e02",
    "qs:photo_max":24,
    "qs:photo_sum":59,
    "qs:placetype":"Suburb",
    "qs:quad_count":6,
    "qs:woe_adm0":23424856,
    "qs:woe_adm1":2345868,
    "qs:woe_adm2":0,
    "qs:woe_lau":28416951,
    "qs:woe_local":1107765,
    "qs:woe_ver":"7.10.0",
    "wof:lang":[
        "jpn"
    ],
    "wof:name":"\uff12\u4e01\u76ee",
    "wof:placetype":"neighbourhood"
},
  "geometry": {"coordinates":[139.41126499999999,35.324069],"type":"Point"}
}