{
  "type": "Feature",
  "properties": {
    "iso:country":"JP",
    "name:eng_x_preferred":[
        "Yamamotodori 1 Chome"
    ],
    "name:eng_x_variant":[
        "Yamamotodoori 1 Choume",
        "Yamamotodori 1 Chome"
    ],
    "name:jpn_x_preferred":[
        "\uff11\u4e01\u76ee"
    ],
    "name:jpn_x_variant":[
        "\u3084\u307e\u3082\u3068\u3069\u304a\u308a \uff11\u3061\u3087\u3046\u3081",
        "\u5c71\u672c\u901a \uff11\u4e01\u76ee",
        "\uff11\u3061\u3087\u3046\u3081"
    ],
    "qs:gn_local":0,
    "qs:local_max":2400,
    "qs:local_sum":22318,
    "qs:localhoods":72,
    "qs:name":"\uff11\u4e01\u76ee",
    "qs:name_adm0":"\u65e5\u672c",
    "qs:name_adm1":"\u5175\u5eab\u770c",
    "qs:name_adm2":"\u4e2d\u592e\u533a",
    "qs:name_en":"Yamamotodori 1 Chome",
    "qs:name_lau":"\u5c71\u672c\u901a",
    "qs:name_local":"\u795e\u6238\u5e02",
    "qs:photo_max":44,
    "qs:photo_sum":87,
    "qs:placetype":"Suburb",
    "qs:quad_count":6,
    "qs:woe_adm0":23424856,
    "qs:woe_adm1":2345862,
    "qs:woe_adm2":15015438,
    "qs:woe_lau":28461230,
    "qs:woe_local":1117545,
    "qs:woe_ver":"7.10.0",
    "qs_pg:name":"\uff11\u4e01\u76ee",
    "qs_pg:name_adm0":"\u65e5\u672c",
    "qs_pg:name_adm1":"\u5175\u5eab\u770c",
    "qs_pg:photos":93,
    "qs_pg:photos_1k":19,
    "qs_pg:photos_9k":1,
    "qs_pg:photos_9r":3,
    "qs_pg:photos_all":93,
    "qs_pg:photos_sr":3,
    "qs_pg:pop_sr":0,
    "qs_pg:qs_pg_placetype":"neighbourhood",
    "qs_pg:qs_pg_placetype_gp":"Suburb",
    "qs_pg:woe_adm0":23424856,
    "woe:adm0_id":23424856,
    "woe:name_adm0":"\u65e5\u672c",
    "woe:name_adm1":"\u5175\u5eab\u770c",
    "woe:placetype":"Suburb",
    "wof:lang":[
        "jpn"
    ],
    "wof:name":"\uff11\u4e01\u76ee",
    "wof:placetype":"neighbourhood"
},
  "geometry": {"coordinates":[135.19059300000001,34.69952],"type":"Point"}
}