{
  "type": "Feature",
  "properties": {
    "gn:admin1_code":"6.0",
    "gn:admin2_code":"1863982.0",
    "gn:asciiname":"Yasutakecho",
    "gn:country_code":"JP",
    "gn:dem":8,
    "gn:feature_class":"P",
    "gn:feature_code":"PPL",
    "gn:name":"Yasutakech\u014d",
    "gn:population":0,
    "gn:timezone":"Asia/Tokyo",
    "iso:country":"JP",
    "name:jpn_x_preferred":[
        "\u5b89\u7af9\u753a"
    ],
    "name:und_x_variant":[
        "Yasutakech\u014d"
    ],
    "wof:name":"Yasutakecho",
    "wof:placetype":"locality"
},
  "geometry": {"coordinates":[136.19163999999998,36.09741],"type":"Point"}
}