{
  "type": "Feature",
  "properties": {
    "gn:admin1_code":"3.0",
    "gn:admin2_code":"2129393.0",
    "gn:asciiname":"Kitatanaka",
    "gn:country_code":"JP",
    "gn:dem":33,
    "gn:feature_class":"P",
    "gn:feature_code":"PPL",
    "gn:name":"Kitatanaka",
    "gn:population":0,
    "gn:timezone":"Asia/Tokyo",
    "iso:country":"JP",
    "name:jpn_x_preferred":[
        "\u5317\u7530\u4e2d"
    ],
    "name:jpn_x_variant":[
        "\u304d\u305f\u305f\u306a\u304b",
        "\u30ad\u30bf\u30bf\u30ca\u30ab"
    ],
    "wof:name":"Kitatanaka",
    "wof:placetype":"locality"
},
  "geometry": {"coordinates":[140.59346000000002,40.66482],"type":"Point"}
}