{
  "type": "Feature",
  "properties": {
    "iso:country":"JP",
    "name:eng_x_preferred":[
        "Shimoarata 1 Chome"
    ],
    "name:eng_x_variant":[
        "Shimoarata 1 Choume",
        "Shimoarata 1 Chome"
    ],
    "name:jpn_x_preferred":[
        "\uff11\u4e01\u76ee"
    ],
    "name:jpn_x_variant":[
        "\u3057\u3082\u3042\u3089\u305f \uff11\u3061\u3087\u3046\u3081",
        "\u4e0b\u8352\u7530 \uff11\u4e01\u76ee",
        "\uff11\u3061\u3087\u3046\u3081"
    ],
    "qs:gn_local":0,
    "qs:local_max":1952,
    "qs:local_sum":6256,
    "qs:localhoods":14,
    "qs:name":"\uff11\u4e01\u76ee",
    "qs:name_adm0":"\u65e5\u672c",
    "qs:name_adm1":"\u9e7f\u5150\u5cf6\u770c",
    "qs:name_en":"Shimoarata 1 Chome",
    "qs:name_lau":"\u4e0b\u8352\u7530",
    "qs:name_local":"\u9e7f\u5150\u5cf6\u5e02",
    "qs:photo_max":112,
    "qs:photo_sum":812,
    "qs:placetype":"Suburb",
    "qs:quad_count":37,
    "qs:woe_adm0":23424856,
    "qs:woe_adm1":2345867,
    "qs:woe_adm2":0,
    "qs:woe_lau":28492477,
    "qs:woe_local":1117378,
    "qs:woe_ver":"7.10.0",
    "wof:lang":[
        "jpn"
    ],
    "wof:name":"\uff11\u4e01\u76ee",
    "wof:placetype":"neighbourhood"
},
  "geometry": {"coordinates":[130.55999399999999,31.588577],"type":"Point"}
}