{
  "type": "Feature",
  "properties": {
    "gn:admin1_code":"34.0",
    "gn:admin2_code":"1864112.0",
    "gn:asciiname":"Midorino-minami",
    "gn:country_code":"JP",
    "gn:dem":7,
    "gn:feature_class":"P",
    "gn:feature_code":"PPL",
    "gn:name":"Midorino-minami",
    "gn:population":0,
    "gn:timezone":"Asia/Tokyo",
    "iso:country":"JP",
    "name:jpn_x_preferred":[
        "\u307f\u3069\u308a\u91ce\u5357"
    ],
    "wof:name":"Midorino-minami",
    "wof:placetype":"locality"
},
  "geometry": {"coordinates":[139.56496999999999,35.86549],"type":"Point"}
}