{
  "type": "Feature",
  "properties": {
    "gn:admin1_code":"45",
    "gn:admin2_code":"1853738.0",
    "gn:admin3_code":"35305.0",
    "gn:asciiname":"Ihota",
    "gn:cc2":"JP",
    "gn:country_code":"JP",
    "gn:dem":22,
    "gn:feature_class":"P",
    "gn:feature_code":"PPL",
    "gn:name":"Ihota",
    "gn:population":0,
    "gn:timezone":"Asia/Tokyo",
    "iso:country":"JP",
    "name:und_x_variant":[
        "Iyota",
        "Iota",
        "Iyoda",
        "Ihota"
    ],
    "wof:name":"Ihota",
    "wof:placetype":"locality"
},
  "geometry": {"coordinates":[132.43333000000001,33.93333],"type":"Point"}
}