{
  "type": "Feature",
  "properties": {
    "gn:admin1_code":"19.0",
    "gn:admin2_code":"1865009.0",
    "gn:admin3_code":"14384.0",
    "gn:asciiname":"Shirohori",
    "gn:country_code":"JP",
    "gn:dem":60,
    "gn:feature_class":"P",
    "gn:feature_code":"PPL",
    "gn:name":"Shirohori",
    "gn:population":0,
    "gn:timezone":"Asia/Tokyo",
    "iso:country":"JP",
    "name:jpn_x_preferred":[
        "\u57ce\u5800"
    ],
    "wof:name":"Shirohori",
    "wof:placetype":"locality"
},
  "geometry": {"coordinates":[139.10393999999999,35.14825],"type":"Point"}
}