{
  "type": "Feature",
  "properties": {
    "gn:admin1_code":"6.0",
    "gn:admin2_code":"7467384.0",
    "gn:asciiname":"Minamirokuroshi",
    "gn:country_code":"JP",
    "gn:dem":466,
    "gn:feature_class":"P",
    "gn:feature_code":"PPL",
    "gn:name":"Minamirokuroshi",
    "gn:population":0,
    "gn:timezone":"Asia/Tokyo",
    "iso:country":"JP",
    "name:jpn_x_preferred":[
        "\u5357\u516d\u5442\u5e2b"
    ],
    "wof:name":"Minamirokuroshi",
    "wof:placetype":"locality"
},
  "geometry": {"coordinates":[136.57898,36.01462],"type":"Point"}
}