{
  "type": "Feature",
  "properties": {
    "gn:admin1_code":"10.0",
    "gn:admin2_code":"1853626.0",
    "gn:asciiname":"Yabuzukacho",
    "gn:country_code":"JP",
    "gn:dem":92,
    "gn:feature_class":"P",
    "gn:feature_code":"PPL",
    "gn:name":"Yabuzukach\u014d",
    "gn:population":0,
    "gn:timezone":"Asia/Tokyo",
    "iso:country":"JP",
    "name:jpn_x_preferred":[
        "\u85ea\u585a\u753a"
    ],
    "name:und_x_variant":[
        "Yabuzukach\u014d"
    ],
    "wof:name":"Yabuzukacho",
    "wof:placetype":"locality"
},
  "geometry": {"coordinates":[139.31108,36.36006],"type":"Point"}
}