{
  "type": "Feature",
  "properties": {
    "gn:admin1_code":"18.0",
    "gn:admin2_code":"7383999.0",
    "gn:admin3_code":"46490.0",
    "gn:asciiname":"Gonohai",
    "gn:country_code":"JP",
    "gn:dem":204,
    "gn:feature_class":"P",
    "gn:feature_code":"PPLL",
    "gn:name":"G\u014dnohai",
    "gn:population":0,
    "gn:timezone":"Asia/Tokyo",
    "iso:country":"JP",
    "name:jpn_x_preferred":[
        "\u90f7\u30ce\u539f"
    ],
    "name:und_x_variant":[
        "G\u014dnohai"
    ],
    "wof:name":"Gonohai",
    "wof:placetype":"locality"
},
  "geometry": {"coordinates":[130.82482999999999,31.18671],"type":"Point"}
}