{
  "type": "Feature",
  "properties": {
    "gn:admin1_code":"05",
    "gn:admin2_code":"10861187.0",
    "gn:asciiname":"Tsuburi",
    "gn:country_code":"JP",
    "gn:dem":8,
    "gn:feature_class":"P",
    "gn:feature_code":"PPL",
    "gn:name":"Tsuburi",
    "gn:population":0,
    "gn:timezone":"Asia/Tokyo",
    "iso:country":"JP",
    "wof:name":"Tsuburi",
    "wof:placetype":"locality"
},
  "geometry": {"coordinates":[132.42781000000002,33.37498],"type":"Point"}
}