{
  "type": "Feature",
  "properties": {
    "gn:admin1_code":"4.0",
    "gn:admin2_code":"1859468.0",
    "gn:asciiname":"Yokodai",
    "gn:country_code":"JP",
    "gn:dem":32,
    "gn:feature_class":"P",
    "gn:feature_code":"PPL",
    "gn:name":"Y\u014dk\u014ddai",
    "gn:population":0,
    "gn:timezone":"Asia/Tokyo",
    "iso:country":"JP",
    "name:jpn_x_preferred":[
        "\u967d\u5149\u53f0"
    ],
    "name:jpn_x_variant":[
        "\u3088\u3046\u3053\u3046\u3060\u3044",
        "\u30e8\u30a6\u30b3\u30a6\u30c0\u30a4"
    ],
    "name:und_x_variant":[
        "Y\u014dk\u014ddai"
    ],
    "wof:name":"Yokodai",
    "wof:placetype":"locality"
},
  "geometry": {"coordinates":[139.90488999999999,35.33453],"type":"Point"}
}