{
  "type": "Feature",
  "properties": {
    "gn:country":"JP",
    "gn:fcode":"PPL",
    "gn:pop":11737,
    "iso:country":"JP",
    "name:unk_x_variant":[
        "Shiita"
    ],
    "qs:name":"Shiida",
    "qs:photos_9r":0,
    "qs:photos_sr":0,
    "qs:pop_sr":"6",
    "wd:wordcount":55,
    "wof:name":"Shiida",
    "wof:placetype":"locality",
    "wof:population":11737
},
  "geometry": {"coordinates":[131.05797000000001,33.65341],"type":"Point"}
}