{
  "type": "Feature",
  "properties": {
    "iso:country":"JP",
    "name:eng_x_preferred":[
        "Sunabacho 2 Chome"
    ],
    "name:eng_x_variant":[
        "Sunabachou 2 Choume",
        "Sunabacho 2 Chome"
    ],
    "name:jpn_x_preferred":[
        "\uff12\u4e01\u76ee"
    ],
    "name:jpn_x_variant":[
        "\u3059\u306a\u3070\u3061\u3087\u3046 \uff12\u3061\u3087\u3046\u3081",
        "\u7802\u5834\u753a \uff12\u4e01\u76ee",
        "\uff12\u3061\u3087\u3046\u3081"
    ],
    "qs:gn_local":0,
    "qs:local_max":145,
    "qs:local_sum":292,
    "qs:localhoods":4,
    "qs:name":"\uff12\u4e01\u76ee",
    "qs:name_adm0":"\u65e5\u672c",
    "qs:name_adm1":"\u611b\u5a9b\u770c",
    "qs:name_en":"Sunabacho 2 Chome",
    "qs:name_lau":"\u7802\u5834\u753a",
    "qs:name_local":"\u4eca\u6cbb\u5e02",
    "qs:photo_max":21,
    "qs:photo_sum":145,
    "qs:placetype":"Suburb",
    "qs:quad_count":18,
    "qs:woe_adm0":23424856,
    "qs:woe_adm1":2345855,
    "qs:woe_adm2":0,
    "qs:woe_lau":28479477,
    "qs:woe_local":1109423,
    "qs:woe_ver":"7.10.0",
    "wof:lang":[
        "jpn"
    ],
    "wof:name":"\uff12\u4e01\u76ee",
    "wof:placetype":"neighbourhood"
},
  "geometry": {"coordinates":[132.98241899999999,34.114557],"type":"Point"}
}