{
  "type": "Feature",
  "properties": {
    "gn:admin1_code":"8.0",
    "gn:admin2_code":"1859317.0",
    "gn:asciiname":"Yamatomachi-aikawa",
    "gn:country_code":"JP",
    "gn:dem":354,
    "gn:feature_class":"P",
    "gn:feature_code":"PPL",
    "gn:name":"Yamatomachi-aikawa",
    "gn:population":0,
    "gn:timezone":"Asia/Tokyo",
    "iso:country":"JP",
    "name:jpn_x_preferred":[
        "\u5c71\u90fd\u753a\u76f8\u5ddd"
    ],
    "wof:name":"Yamatomachi-aikawa",
    "wof:placetype":"locality"
},
  "geometry": {"coordinates":[139.79378,37.68503],"type":"Point"}
}