{
  "type": "Feature",
  "properties": {
    "gn:admin1_code":"24.0",
    "gn:admin2_code":"7447001.0",
    "gn:asciiname":"Hannohara",
    "gn:country_code":"JP",
    "gn:dem":26,
    "gn:feature_class":"P",
    "gn:feature_code":"PPL",
    "gn:name":"Hannohara",
    "gn:population":0,
    "gn:timezone":"Asia/Tokyo",
    "iso:country":"JP",
    "name:jpn_x_preferred":[
        "\u534a\u91ce\u539f"
    ],
    "name:jpn_x_variant":[
        "\u306f\u3093\u306e\u306f\u3089",
        "\u30cf\u30f3\u30ce\u30cf\u30e9"
    ],
    "wof:name":"Hannohara",
    "wof:placetype":"locality"
},
  "geometry": {"coordinates":[141.07136,38.47672],"type":"Point"}
}