{
  "type": "Feature",
  "properties": {
    "gn:admin1_code":"2.0",
    "gn:admin2_code":"2113122.0",
    "gn:asciiname":"Izumi-baba",
    "gn:country_code":"JP",
    "gn:dem":11,
    "gn:feature_class":"P",
    "gn:feature_code":"PPL",
    "gn:name":"Izumi-baba",
    "gn:population":0,
    "gn:timezone":"Asia/Tokyo",
    "iso:country":"JP",
    "name:jpn_x_preferred":[
        "\u6cc9\u99ac\u5834"
    ],
    "name:jpn_x_variant":[
        "\u3044\u305a\u307f\u3070\u3070",
        "\u30a4\u30ba\u30df\u30d0\u30d0"
    ],
    "wof:name":"Izumi-baba",
    "wof:placetype":"locality"
},
  "geometry": {"coordinates":[140.12450999999999,39.7329],"type":"Point"}
}