{
  "type": "Feature",
  "properties": {
    "iso:country":"JP",
    "name:eng_x_preferred":[
        "Midorigaoka 1 Chome"
    ],
    "name:eng_x_variant":[
        "Midorigaoka 1 Choume",
        "Midorigaoka 1 Chome"
    ],
    "name:jpn_x_preferred":[
        "\uff11\u4e01\u76ee"
    ],
    "name:jpn_x_variant":[
        "\u307f\u3069\u308a\u304c\u304a\u304b \uff11\u3061\u3087\u3046\u3081",
        "\u7dd1\u304c\u4e18 \uff11\u4e01\u76ee",
        "\uff11\u3061\u3087\u3046\u3081"
    ],
    "qs:gn_adm0_cc":"JP",
    "qs:gn_local":1859100,
    "qs:gn_nam_loc":"\u7532\u5e9c\u5e02, \u5c71\u68a8\u770c, JP",
    "qs:gn_namadm1":"46",
    "qs:local_max":393,
    "qs:local_sum":885,
    "qs:localhoods":11,
    "qs:name":"\uff11\u4e01\u76ee",
    "qs:name_adm0":"\u65e5\u672c",
    "qs:name_adm1":"\u5c71\u68a8\u770c",
    "qs:name_en":"Midorigaoka 1 Chome",
    "qs:name_lau":"\u7dd1\u304c\u4e18",
    "qs:name_local":"\u7532\u5e9c\u5e02",
    "qs:photo_max":7,
    "qs:photo_sum":11,
    "qs:placetype":"Suburb",
    "qs:quad_count":2,
    "qs:woe_adm0":23424856,
    "qs:woe_adm1":2345895,
    "qs:woe_adm2":0,
    "qs:woe_lau":28430506,
    "qs:woe_local":1117554,
    "qs:woe_ver":"7.10.0",
    "wof:lang":[
        "jpn"
    ],
    "wof:name":"\uff11\u4e01\u76ee",
    "wof:placetype":"neighbourhood"
},
  "geometry": {"coordinates":[138.558819,35.67738],"type":"Point"}
}