{
  "type": "Feature",
  "properties": {
    "gn:admin1_code":"2.0",
    "gn:admin2_code":"7443149.0",
    "gn:asciiname":"Okita",
    "gn:country_code":"JP",
    "gn:dem":24,
    "gn:feature_class":"P",
    "gn:feature_code":"PPL",
    "gn:name":"Okita",
    "gn:population":0,
    "gn:timezone":"Asia/Tokyo",
    "iso:country":"JP",
    "name:jpn_x_preferred":[
        "\u6c96\u7530"
    ],
    "wof:name":"Okita",
    "wof:placetype":"locality"
},
  "geometry": {"coordinates":[140.3869,39.48287],"type":"Point"}
}