{
  "type": "Feature",
  "properties": {
    "gn:admin1_code":"8.0",
    "gn:admin2_code":"7451517.0",
    "gn:asciiname":"Kozawa",
    "gn:cc2":"JP",
    "gn:country_code":"JP",
    "gn:dem":1,
    "gn:feature_class":"P",
    "gn:feature_code":"PPL",
    "gn:name":"Kozawa",
    "gn:population":0,
    "gn:timezone":"Asia/Tokyo",
    "iso:country":"JP",
    "name:und_x_variant":[
        "\u014czawa",
        "Kozawa"
    ],
    "wof:name":"Kozawa",
    "wof:placetype":"locality"
},
  "geometry": {"coordinates":[141.01667,37.56667],"type":"Point"}
}