{
  "type": "Feature",
  "properties": {
    "gn:admin1_code":"21.0",
    "gn:admin2_code":"1848443.0",
    "gn:admin3_code":"43468.0",
    "gn:asciiname":"Takatsuka",
    "gn:country_code":"JP",
    "gn:dem":28,
    "gn:feature_class":"P",
    "gn:feature_code":"PPL",
    "gn:name":"Takatsuka",
    "gn:population":0,
    "gn:timezone":"Asia/Tokyo",
    "iso:country":"JP",
    "name:jpn_x_preferred":[
        "\u9ad8\u585a"
    ],
    "name:jpn_x_variant":[
        "\u305f\u304b\u3064\u304b",
        "\u30bf\u30ab\u30c4\u30ab"
    ],
    "wof:name":"Takatsuka",
    "wof:placetype":"locality"
},
  "geometry": {"coordinates":[130.70223999999999,32.5798],"type":"Point"}
}