{
  "type": "Feature",
  "properties": {
    "gn:admin1_code":"39",
    "gn:admin2_code":"7406325.0",
    "gn:asciiname":"Fujinoike",
    "gn:country_code":"JP",
    "gn:dem":1222,
    "gn:feature_class":"P",
    "gn:feature_code":"PPL",
    "gn:name":"Fujinoike",
    "gn:population":0,
    "gn:timezone":"Asia/Tokyo",
    "iso:country":"JP",
    "wof:name":"Fujinoike",
    "wof:placetype":"locality"
},
  "geometry": {"coordinates":[134.11667,33.86667],"type":"Point"}
}