{
  "type": "Feature",
  "properties": {
    "gn:admin1_code":"21.0",
    "gn:admin2_code":"7412706.0",
    "gn:admin3_code":"43447.0",
    "gn:asciiname":"Ohoshi",
    "gn:country_code":"JP",
    "gn:dem":393,
    "gn:feature_class":"P",
    "gn:feature_code":"PPLL",
    "gn:name":"\u014choshi",
    "gn:population":0,
    "gn:timezone":"Asia/Tokyo",
    "iso:country":"JP",
    "name:jpn_x_preferred":[
        "\u5927\u661f"
    ],
    "name:jpn_x_variant":[
        "\u304a\u304a\u307b\u3057",
        "\u30aa\u30aa\u30db\u30b7"
    ],
    "name:und_x_variant":[
        "\u014choshi"
    ],
    "wof:name":"Ohoshi",
    "wof:placetype":"locality"
},
  "geometry": {"coordinates":[130.90517,32.73666],"type":"Point"}
}