{
  "type": "Feature",
  "properties": {
    "gn:admin1_code":"18",
    "gn:admin2_code":"1853737.0",
    "gn:admin3_code":"46535.0",
    "gn:asciiname":"Gusuku",
    "gn:country_code":"JP",
    "gn:dem":55,
    "gn:feature_class":"P",
    "gn:feature_code":"PPL",
    "gn:name":"Gusuku",
    "gn:population":0,
    "gn:timezone":"Asia/Tokyo",
    "iso:country":"JP",
    "name:jpn_x_preferred":[
        "\u57ce"
    ],
    "wof:name":"Gusuku",
    "wof:placetype":"locality"
},
  "geometry": {"coordinates":[128.43606,27.02668],"type":"Point"}
}