{
  "type": "Feature",
  "properties": {
    "gn:admin1_code":"18",
    "gn:admin2_code":"1853737.0",
    "gn:admin3_code":"46535.0",
    "gn:asciiname":"Gusuku",
    "gn:country_code":"JP",
    "gn:dem":55,
    "gn:feature_class":"P",
    "gn:feature_code":"PPL",
    "gn:name":"Gusuku",
    "gn:population":0,
    "gn:timezone":"Asia/Tokyo",
    "iso:country":"JP",
    "name:ara_x_preferred":[
        "\u063a\u0648\u0633\u0648\u0643\u0648"
    ],
    "name:bel_x_preferred":[
        "\u0413\u0443\u0441\u0443\u043a\u0443"
    ],
    "name:cat_x_preferred":[
        "Gusuku"
    ],
    "name:ces_x_preferred":[
        "Gusuku"
    ],
    "name:fin_x_preferred":[
        "Gusuku"
    ],
    "name:fra_x_preferred":[
        "Gusuku"
    ],
    "name:heb_x_preferred":[
        "\u05d2\u05d5\u05e1\u05d5\u05e7\u05d5"
    ],
    "name:hrv_x_preferred":[
        "Gusuku"
    ],
    "name:ind_x_preferred":[
        "Gusuku"
    ],
    "name:ita_x_preferred":[
        "Gusuku"
    ],
    "name:jpn_x_preferred":[
        "\u57ce"
    ],
    "name:jpn_x_variant":[
        "\u30b0\u30b9\u30af"
    ],
    "name:kor_x_preferred":[
        "\uad6c\uc2a4\ucfe0"
    ],
    "name:nld_x_preferred":[
        "Gusuku"
    ],
    "name:nor_x_preferred":[
        "Gusuku"
    ],
    "name:por_x_preferred":[
        "Gusuku"
    ],
    "name:rus_x_preferred":[
        "\u0413\u0443\u0441\u0443\u043a\u0443"
    ],
    "name:slk_x_preferred":[
        "Gusuku"
    ],
    "name:swe_x_preferred":[
        "Gusuku"
    ],
    "name:tur_x_preferred":[
        "Gusuku"
    ],
    "name:vie_x_preferred":[
        "Gusuku"
    ],
    "wof:name":"Gusuku",
    "wof:placetype":"locality"
},
  "geometry": {"coordinates":[128.43606,27.02668],"type":"Point"}
}