{
  "type": "Feature",
  "properties": {
    "gn:admin1_code":"21.0",
    "gn:admin2_code":"1849062.0",
    "gn:asciiname":"Gata",
    "gn:country_code":"JP",
    "gn:dem":-1,
    "gn:feature_class":"P",
    "gn:feature_code":"PPLL",
    "gn:name":"Gata",
    "gn:population":0,
    "gn:timezone":"Asia/Tokyo",
    "iso:country":"JP",
    "name:bos_x_preferred":[
        "Gata"
    ],
    "name:cat_x_preferred":[
        "Gata"
    ],
    "name:ceb_x_preferred":[
        "Gata"
    ],
    "name:deu_x_preferred":[
        "Perreo#Wortherkunft"
    ],
    "name:fra_x_preferred":[
        "Gata"
    ],
    "name:glg_x_preferred":[
        "Gata"
    ],
    "name:jpn_x_preferred":[
        "\u6f5f"
    ],
    "name:jpn_x_variant":[
        "\u304c\u305f",
        "\u30ac\u30bf"
    ],
    "name:nld_x_preferred":[
        "Gata"
    ],
    "name:por_x_preferred":[
        "Gata"
    ],
    "name:slv_x_preferred":[
        "Gata"
    ],
    "name:spa_x_preferred":[
        "Gata"
    ],
    "name:srp_x_preferred":[
        "\u0413\u0430\u0442\u0430"
    ],
    "name:swe_x_preferred":[
        "Gata"
    ],
    "name:tur_x_preferred":[
        "Gata"
    ],
    "wof:name":"Gata",
    "wof:placetype":"locality"
},
  "geometry": {"coordinates":[130.60448,32.69647],"type":"Point"}
}