{
  "type": "Feature",
  "properties": {
    "iso:country":"JP",
    "name:eng_x_preferred":[
        "Minowacho 3 Chome"
    ],
    "name:eng_x_variant":[
        "Minowachou 3 Choume",
        "Minowacho 3 Chome"
    ],
    "name:jpn_x_preferred":[
        "\uff13\u4e01\u76ee"
    ],
    "name:jpn_x_variant":[
        "\u307f\u306e\u308f\u3061\u3087\u3046 \uff13\u3061\u3087\u3046\u3081",
        "\u7b95\u8f2a\u753a \uff13\u4e01\u76ee",
        "\uff13\u3061\u3087\u3046\u3081"
    ],
    "qs:gn_local":0,
    "qs:local_max":6208,
    "qs:local_sum":82309,
    "qs:localhoods":190,
    "qs:name":"\uff13\u4e01\u76ee",
    "qs:name_adm0":"\u65e5\u672c",
    "qs:name_adm1":"\u795e\u5948\u5ddd\u770c",
    "qs:name_adm2":"\u6e2f\u5317\u533a",
    "qs:name_en":"Minowacho 3 Chome",
    "qs:name_lau":"\u7b95\u8f2a\u753a",
    "qs:name_local":"\u6a2a\u6d5c\u5e02",
    "qs:photo_max":445,
    "qs:photo_sum":533,
    "qs:placetype":"Suburb",
    "qs:quad_count":11,
    "qs:woe_adm0":23424856,
    "qs:woe_adm1":2345868,
    "qs:woe_adm2":15015537,
    "qs:woe_lau":28415990,
    "qs:woe_local":1118550,
    "qs:woe_ver":"7.10.0",
    "wof:lang":[
        "jpn"
    ],
    "wof:name":"\uff13\u4e01\u76ee",
    "wof:placetype":"neighbourhood"
},
  "geometry": {"coordinates":[139.644757,35.540758],"type":"Point"}
}