{
  "type": "Feature",
  "properties": {
    "gn:admin1_code":"20",
    "gn:admin2_code":"1851029.0",
    "gn:admin3_code":"39412.0",
    "gn:asciiname":"Yotsuura",
    "gn:country_code":"JP",
    "gn:dem":8,
    "gn:feature_class":"P",
    "gn:feature_code":"PPL",
    "gn:name":"Yotsuura",
    "gn:population":0,
    "gn:timezone":"Asia/Tokyo",
    "iso:country":"JP",
    "name:und_x_variant":[
        "Yotsu-no-ura",
        "Yotsunoura",
        "Yotsuura"
    ],
    "wof:name":"Yotsuura",
    "wof:placetype":"locality"
},
  "geometry": {"coordinates":[133.21418,33.16637],"type":"Point"}
}