{
  "type": "Feature",
  "properties": {
    "gn:admin1_code":"12.0",
    "gn:admin2_code":"2129373.0",
    "gn:admin3_code":"1661.0",
    "gn:asciiname":"Takadai",
    "gn:country_code":"JP",
    "gn:dem":53,
    "gn:feature_class":"P",
    "gn:feature_code":"PPLL",
    "gn:name":"Takadai",
    "gn:population":0,
    "gn:timezone":"Asia/Tokyo",
    "iso:country":"JP",
    "name:jpn_x_preferred":[
        "\u9ad8\u53f0"
    ],
    "name:jpn_x_variant":[
        "\u305f\u304b\u3060\u3044",
        "\u30bf\u30ab\u30c0\u30a4"
    ],
    "wof:name":"Takadai",
    "wof:placetype":"locality"
},
  "geometry": {"coordinates":[144.49112,43.03933],"type":"Point"}
}