{
  "type": "Feature",
  "properties": {
    "gn:admin1_code":"12.0",
    "gn:admin2_code":"7428090.0",
    "gn:admin3_code":"1665.0",
    "gn:asciiname":"Sattomonai",
    "gn:country_code":"JP",
    "gn:dem":131,
    "gn:feature_class":"P",
    "gn:feature_code":"PPL",
    "gn:name":"Sattomonai",
    "gn:population":0,
    "gn:timezone":"Asia/Tokyo",
    "iso:country":"JP",
    "name:jpn_x_preferred":[
        "\u672d\u53cb\u5185"
    ],
    "name:jpn_x_variant":[
        "\u3055\u3063\u3068\u3082\u306a\u3044",
        "\u30b5\u30c3\u30c8\u30e2\u30ca\u30a4"
    ],
    "name:und_x_variant":[
        "Satsutomonai",
        "Sattomonai"
    ],
    "wof:name":"Sattomonai",
    "wof:placetype":"locality"
},
  "geometry": {"coordinates":[144.40773000000004,43.52284],"type":"Point"}
}