{
  "type": "Feature",
  "properties": {
    "gn:admin1_code":"3.0",
    "gn:admin2_code":"2130225.0",
    "gn:asciiname":"Suehiro",
    "gn:country_code":"JP",
    "gn:dem":5,
    "gn:feature_class":"P",
    "gn:feature_code":"PPL",
    "gn:name":"Suehiro",
    "gn:population":0,
    "gn:timezone":"Asia/Tokyo",
    "iso:country":"JP",
    "name:jpn_x_preferred":[
        "\u672b\u5e83"
    ],
    "name:jpn_x_variant":[
        "\u3059\u3048\u3072\u308d",
        "\u30b9\u30a8\u30d2\u30ed"
    ],
    "wof:name":"Suehiro",
    "wof:placetype":"locality"
},
  "geometry": {"coordinates":[140.47342,40.79986],"type":"Point"}
}