{
  "type": "Feature",
  "properties": {
    "gn:admin1_code":"25",
    "gn:admin2_code":"1856706.0",
    "gn:asciiname":"Shimo-kuranaga",
    "gn:country_code":"JP",
    "gn:dem":14,
    "gn:feature_class":"P",
    "gn:feature_code":"PPL",
    "gn:name":"Shimo-kuranaga",
    "gn:population":0,
    "gn:timezone":"Asia/Tokyo",
    "iso:country":"JP",
    "wof:name":"Shimo-kuranaga",
    "wof:placetype":"locality"
},
  "geometry": {"coordinates":[131.34999999999999,31.93333],"type":"Point"}
}