{
  "type": "Feature",
  "properties": {
    "gn:admin1_code":"37.0",
    "gn:admin2_code":"1864104.0",
    "gn:asciiname":"Araya",
    "gn:country_code":"JP",
    "gn:dem":242,
    "gn:feature_class":"P",
    "gn:feature_code":"PPLL",
    "gn:name":"Araya",
    "gn:population":0,
    "gn:timezone":"Asia/Tokyo",
    "iso:country":"JP",
    "name:ceb_x_preferred":[
        "Araya"
    ],
    "name:deu_x_preferred":[
        "Araya"
    ],
    "name:fra_x_preferred":[
        "Araya"
    ],
    "name:ita_x_preferred":[
        "Araya"
    ],
    "name:jpn_x_preferred":[
        "\u65b0\u5c4b"
    ],
    "name:rus_x_preferred":[
        "\u0410\u0440\u0430\u044f"
    ],
    "name:spa_x_preferred":[
        "Araya"
    ],
    "name:swe_x_preferred":[
        "Araya"
    ],
    "wof:name":"Araya",
    "wof:placetype":"locality"
},
  "geometry": {"coordinates":[138.59119999999999,35.26819000000001],"type":"Point"}
}