{
  "type": "Feature",
  "properties": {
    "gn:admin1_code":"3.0",
    "gn:admin2_code":"2130056.0",
    "gn:asciiname":"Katada",
    "gn:country_code":"JP",
    "gn:dem":26,
    "gn:feature_class":"P",
    "gn:feature_code":"PPL",
    "gn:name":"Katada",
    "gn:population":0,
    "gn:timezone":"Asia/Tokyo",
    "iso:country":"JP",
    "name:jpn_x_preferred":[
        "\u5805\u7530"
    ],
    "name:jpn_x_variant":[
        "\u304b\u305f\u3060",
        "\u30ab\u30bf\u30c0"
    ],
    "wof:name":"Katada",
    "wof:placetype":"locality"
},
  "geometry": {"coordinates":[140.49021999999999,40.61262],"type":"Point"}
}