{
  "type": "Feature",
  "properties": {
    "gn:admin1_code":"4.0",
    "gn:admin2_code":"1863711.0",
    "gn:asciiname":"Jodo",
    "gn:country_code":"JP",
    "gn:dem":9,
    "gn:feature_class":"P",
    "gn:feature_code":"PPL",
    "gn:name":"J\u014dd\u014d",
    "gn:population":0,
    "gn:timezone":"Asia/Tokyo",
    "iso:country":"JP",
    "name:jpn_x_preferred":[
        "\u4e0a\u9053"
    ],
    "name:jpn_x_variant":[
        "\u3058\u3087\u3046\u3069\u3046",
        "\u30b8\u30e7\u30a6\u30c9\u30a6"
    ],
    "name:und_x_variant":[
        "J\u014dd\u014d"
    ],
    "wof:name":"Jodo",
    "wof:placetype":"locality"
},
  "geometry": {"coordinates":[139.86938999999998,35.29620999999999],"type":"Point"}
}