{
  "type": "Feature",
  "properties": {
    "gn:admin1_code":"37.0",
    "gn:admin2_code":"1864089.0",
    "gn:asciiname":"Negata",
    "gn:country_code":"JP",
    "gn:dem":58,
    "gn:feature_class":"P",
    "gn:feature_code":"PPLL",
    "gn:name":"Negata",
    "gn:population":0,
    "gn:timezone":"Asia/Tokyo",
    "iso:country":"JP",
    "name:jpn_x_preferred":[
        "\u6839\u65b9"
    ],
    "wof:name":"Negata",
    "wof:placetype":"locality"
},
  "geometry": {"coordinates":[138.60605000000001,35.17784],"type":"Point"}
}