{
  "type": "Feature",
  "properties": {
    "gn:admin1_code":"18",
    "gn:admin2_code":"1861090.0",
    "gn:asciiname":"Shibahiki",
    "gn:cc2":"JP",
    "gn:country_code":"JP",
    "gn:dem":87,
    "gn:feature_class":"P",
    "gn:feature_code":"PPL",
    "gn:name":"Shibahiki",
    "gn:population":0,
    "gn:timezone":"Asia/Tokyo",
    "iso:country":"JP",
    "name:und_x_variant":[
        "Shibabiki",
        "Shibahiki"
    ],
    "wof:name":"Shibahiki",
    "wof:placetype":"locality"
},
  "geometry": {"coordinates":[130.30000000000001,32.05],"type":"Point"}
}