{
  "type": "Feature",
  "properties": {
    "gn:admin1_code":"16.0",
    "gn:admin2_code":"2112655.0",
    "gn:asciiname":"Tsukinokidaira",
    "gn:country_code":"JP",
    "gn:dem":306,
    "gn:feature_class":"P",
    "gn:feature_code":"PPL",
    "gn:name":"Tsukinokidaira",
    "gn:population":0,
    "gn:timezone":"Asia/Tokyo",
    "iso:country":"JP",
    "name:jpn_x_preferred":[
        "\u69fb\u30ce\u6728\u5e73"
    ],
    "wof:name":"Tsukinokidaira",
    "wof:placetype":"locality"
},
  "geometry": {"coordinates":[140.88638,39.01326],"type":"Point"}
}