{
  "type": "Feature",
  "properties": {
    "gn:admin1_code":"19.0",
    "gn:admin2_code":"1847999.0",
    "gn:asciiname":"Shindenjuku",
    "gn:country_code":"JP",
    "gn:dem":28,
    "gn:feature_class":"P",
    "gn:feature_code":"PPL",
    "gn:name":"Shindenjuku",
    "gn:population":0,
    "gn:timezone":"Asia/Tokyo",
    "iso:country":"JP",
    "name:jpn_x_preferred":[
        "\u65b0\u7530\u5bbf"
    ],
    "wof:name":"Shindenjuku",
    "wof:placetype":"locality"
},
  "geometry": {"coordinates":[139.38093000000001,35.4822],"type":"Point"}
}