{
  "type": "Feature",
  "properties": {
    "gn:admin1_code":"27.0",
    "gn:admin2_code":"1852895.0",
    "gn:asciiname":"Shikamachicho-shikamachi",
    "gn:country_code":"JP",
    "gn:dem":10,
    "gn:feature_class":"P",
    "gn:feature_code":"PPL",
    "gn:name":"Shikamachich\u014d-shikamachi",
    "gn:population":0,
    "gn:timezone":"Asia/Tokyo",
    "iso:country":"JP",
    "name:jpn_x_preferred":[
        "\u9e7f\u753a\u753a\u9e7f\u753a"
    ],
    "name:und_x_variant":[
        "Shikamachich\u014d-shikamachi"
    ],
    "wof:name":"Shikamachicho-shikamachi",
    "wof:placetype":"locality"
},
  "geometry": {"coordinates":[129.6129,33.29586],"type":"Point"}
}