{
  "type": "Feature",
  "properties": {
    "gn:admin1_code":"7.0",
    "gn:admin2_code":"1863955.0",
    "gn:admin3_code":"40137.0",
    "gn:asciiname":"Arae",
    "gn:country_code":"JP",
    "gn:dem":2,
    "gn:feature_class":"P",
    "gn:feature_code":"PPL",
    "gn:name":"Arae",
    "gn:population":0,
    "gn:timezone":"Asia/Tokyo",
    "iso:country":"JP",
    "name:deu_x_preferred":[
        "Ara"
    ],
    "name:jpn_x_preferred":[
        "\u8352\u6c5f"
    ],
    "name:por_x_preferred":[
        "Aras"
    ],
    "name:spa_x_preferred":[
        "Arae"
    ],
    "wof:name":"Arae",
    "wof:placetype":"locality"
},
  "geometry": {"coordinates":[130.35193999999998,33.57207],"type":"Point"}
}