{
  "type": "Feature",
  "properties": {
    "gn:admin1_code":"2.0",
    "gn:admin2_code":"2113122.0",
    "gn:asciiname":"Terauchi-yakeyama",
    "gn:country_code":"JP",
    "gn:dem":40,
    "gn:feature_class":"P",
    "gn:feature_code":"PPL",
    "gn:name":"Terauchi-yakeyama",
    "gn:population":0,
    "gn:timezone":"Asia/Tokyo",
    "iso:country":"JP",
    "name:jpn_x_preferred":[
        "\u5bfa\u5185\u713c\u5c71"
    ],
    "name:jpn_x_variant":[
        "\u3066\u3089\u3046\u3061\u3084\u3051\u3084\u307e",
        "\u30c6\u30e9\u30a6\u30c1\u30e4\u30b1\u30e4\u30de"
    ],
    "wof:name":"Terauchi-yakeyama",
    "wof:placetype":"locality"
},
  "geometry": {"coordinates":[140.07591000000002,39.74127],"type":"Point"}
}