{
  "type": "Feature",
  "properties": {
    "gn:admin1_code":"2.0",
    "gn:admin2_code":"2111935.0",
    "gn:admin3_code":"5363.0",
    "gn:asciiname":"Masaka",
    "gn:country_code":"JP",
    "gn:dem":19,
    "gn:feature_class":"P",
    "gn:feature_code":"PPL",
    "gn:name":"Masaka",
    "gn:population":0,
    "gn:timezone":"Asia/Tokyo",
    "iso:country":"JP",
    "name:ceb_x_preferred":[
        "Masaka"
    ],
    "name:dan_x_preferred":[
        "Masaka"
    ],
    "name:deu_x_preferred":[
        "Masaka"
    ],
    "name:fra_x_preferred":[
        "Masaka"
    ],
    "name:hrv_x_preferred":[
        "Masaka"
    ],
    "name:hun_x_preferred":[
        "Masaka"
    ],
    "name:ita_x_preferred":[
        "Masaka"
    ],
    "name:jpn_x_preferred":[
        "\u771f\u5742"
    ],
    "name:jpn_x_variant":[
        "\u30de\u30b5\u30ab"
    ],
    "name:lit_x_preferred":[
        "Masaka"
    ],
    "name:lug_x_preferred":[
        "Masaka"
    ],
    "name:nld_x_preferred":[
        "Masaka"
    ],
    "name:pol_x_preferred":[
        "Masaka"
    ],
    "name:ron_x_preferred":[
        "Masaka"
    ],
    "name:rus_x_preferred":[
        "\u041c\u0430\u0441\u0430\u043a\u0430"
    ],
    "name:spa_x_preferred":[
        "Masaka"
    ],
    "name:swa_x_preferred":[
        "Masaka"
    ],
    "name:swe_x_preferred":[
        "Masaka"
    ],
    "wof:name":"Masaka",
    "wof:placetype":"locality"
},
  "geometry": {"coordinates":[140.08333000000002,39.96667],"type":"Point"}
}