{
  "type": "Feature",
  "properties": {
    "gn:admin1_code":"11",
    "gn:admin2_code":"1853990.0",
    "gn:asciiname":"Mitera",
    "gn:country_code":"JP",
    "gn:dem":13,
    "gn:feature_class":"P",
    "gn:feature_code":"PPL",
    "gn:name":"Mitera",
    "gn:population":0,
    "gn:timezone":"Asia/Tokyo",
    "iso:country":"JP",
    "wof:name":"Mitera",
    "wof:placetype":"locality"
},
  "geometry": {"coordinates":[133.11667,34.27806],"type":"Point"}
}