{
  "type": "Feature",
  "properties": {
    "gn:admin1_code":"4.0",
    "gn:admin2_code":"2112386.0",
    "gn:asciiname":"Yairo",
    "gn:country_code":"JP",
    "gn:dem":20,
    "gn:feature_class":"P",
    "gn:feature_code":"PPL",
    "gn:name":"Yairo",
    "gn:population":0,
    "gn:timezone":"Asia/Tokyo",
    "iso:country":"JP",
    "name:jpn_x_preferred":[
        "\u516b\u8272"
    ],
    "name:jpn_x_variant":[
        "\u3084\u3044\u308d",
        "\u30e4\u30a4\u30ed"
    ],
    "wof:name":"Yairo",
    "wof:placetype":"locality"
},
  "geometry": {"coordinates":[140.09163000000001,35.1188],"type":"Point"}
}