{
  "type": "Feature",
  "properties": {
    "gn:admin1_code":"7.0",
    "gn:admin2_code":"7407416.0",
    "gn:asciiname":"Kokoroyoshi",
    "gn:country_code":"JP",
    "gn:dem":21,
    "gn:feature_class":"P",
    "gn:feature_code":"PPLL",
    "gn:name":"Kokoroyoshi",
    "gn:population":0,
    "gn:timezone":"Asia/Tokyo",
    "iso:country":"JP",
    "name:jpn_x_preferred":[
        "\u5fc3\u5409"
    ],
    "wof:name":"Kokoroyoshi",
    "wof:placetype":"locality"
},
  "geometry": {"coordinates":[130.69811999999999,33.73009],"type":"Point"}
}