{
  "type": "Feature",
  "properties": {
    "iso:country":"JP",
    "name:eng_x_preferred":[
        "Nakahira 4 Chome"
    ],
    "name:eng_x_variant":[
        "Nakahira 4 Choume",
        "Nakahira 4 Chome"
    ],
    "name:jpn_x_preferred":[
        "\uff14\u4e01\u76ee"
    ],
    "name:jpn_x_variant":[
        "\u306a\u304b\u3072\u3089 \uff14\u3061\u3087\u3046\u3081",
        "\u4e2d\u5e73 \uff14\u4e01\u76ee",
        "\uff14\u3061\u3087\u3046\u3081"
    ],
    "name:unk_x_variant":[
        "\uff14\u4e01\u76ee"
    ],
    "qs:gn_local":0,
    "qs:local_max":3194,
    "qs:local_sum":30209,
    "qs:localhoods":92,
    "qs:name":"\uff14\u4e01\u76ee",
    "qs:name_adm0":"\u65e5\u672c",
    "qs:name_adm1":"\u611b\u77e5\u770c",
    "qs:name_adm2":"\u5929\u767d\u533a",
    "qs:name_en":"Nakahira 4 Chome",
    "qs:name_lau":"\u4e2d\u5e73",
    "qs:name_local":"\u540d\u53e4\u5c4b\u5e02",
    "qs:photo_max":14,
    "qs:photo_sum":14,
    "qs:placetype":"Suburb",
    "qs:quad_count":1,
    "qs:woe_adm0":23424856,
    "qs:woe_adm1":2345851,
    "qs:woe_adm2":1115595,
    "qs:woe_lau":28440369,
    "qs:woe_local":1117817,
    "qs:woe_ver":"7.10.0",
    "wof:lang":[
        "jpn"
    ],
    "wof:name":"\uff14\u4e01\u76ee",
    "wof:placetype":"neighbourhood"
},
  "geometry": {"coordinates":[137.00225800000001,35.113167],"type":"Point"}
}