{
  "type": "Feature",
  "properties": {
    "gn:admin1_code":"43",
    "gn:admin2_code":"1861287.0",
    "gn:admin3_code":"30341.0",
    "gn:asciiname":"Nishishibuta",
    "gn:country_code":"JP",
    "gn:dem":52,
    "gn:feature_class":"P",
    "gn:feature_code":"PPL",
    "gn:name":"Nishishibuta",
    "gn:population":0,
    "gn:timezone":"Asia/Tokyo",
    "iso:country":"JP",
    "name:jpn_x_preferred":[
        "\u897f\u6e0b\u7530"
    ],
    "name:und_x_variant":[
        "Nishi-shibuta"
    ],
    "wof:name":"Nishishibuta",
    "wof:placetype":"locality"
},
  "geometry": {"coordinates":[135.46725000000001,34.27611],"type":"Point"}
}