{
  "type": "Feature",
  "properties": {
    "gn:admin1_code":"24.0",
    "gn:admin2_code":"2112261.0",
    "gn:asciiname":"Akaiwa-kamihada",
    "gn:country_code":"JP",
    "gn:dem":210,
    "gn:feature_class":"P",
    "gn:feature_code":"PPL",
    "gn:name":"Akaiwa-kamihada",
    "gn:population":0,
    "gn:timezone":"Asia/Tokyo",
    "iso:country":"JP",
    "name:jpn_x_preferred":[
        "\u8d64\u5ca9\u4e0a\u7fbd\u7530"
    ],
    "name:jpn_x_variant":[
        "\u3042\u304b\u3044\u308f\u304b\u307f\u306f\u3060",
        "\u30a2\u30ab\u30a4\u30ef\u30ab\u30df\u30cf\u30c0",
        "\u4e0a\u7fbd\u7530"
    ],
    "name:und_x_variant":[
        "Kamihada"
    ],
    "wof:name":"Akaiwa-kamihada",
    "wof:placetype":"locality"
},
  "geometry": {"coordinates":[141.50498000000005,38.85876],"type":"Point"}
}