{
  "type": "Feature",
  "properties": {
    "gn:admin1_code":"18.0",
    "gn:admin2_code":"1862007.0",
    "gn:asciiname":"Mizusako",
    "gn:country_code":"JP",
    "gn:dem":135,
    "gn:feature_class":"P",
    "gn:feature_code":"PPLL",
    "gn:name":"Mizusako",
    "gn:population":0,
    "gn:timezone":"Asia/Tokyo",
    "iso:country":"JP",
    "name:jpn_x_preferred":[
        "\u6c34\u8feb"
    ],
    "wof:name":"Mizusako",
    "wof:placetype":"locality"
},
  "geometry": {"coordinates":[130.59474,31.26203],"type":"Point"}
}