{
  "type": "Feature",
  "properties": {
    "gn:admin1_code":"40.0",
    "gn:admin2_code":"1859115.0",
    "gn:asciiname":"Miyukicho",
    "gn:country_code":"JP",
    "gn:dem":75,
    "gn:feature_class":"P",
    "gn:feature_code":"PPL",
    "gn:name":"Miyukich\u014d",
    "gn:population":0,
    "gn:timezone":"Asia/Tokyo",
    "iso:country":"JP",
    "name:jpn_x_preferred":[
        "\u5fa1\u5e78\u753a"
    ],
    "name:und_x_variant":[
        "Miyukich\u014d"
    ],
    "wof:name":"Miyukicho",
    "wof:placetype":"locality"
},
  "geometry": {"coordinates":[139.50323999999998,35.7141],"type":"Point"}
}