{
  "type": "Feature",
  "properties": {
    "gn:admin1_code":"7.0",
    "gn:admin2_code":"7407416.0",
    "gn:asciiname":"Kirino",
    "gn:country_code":"JP",
    "gn:dem":14,
    "gn:feature_class":"P",
    "gn:feature_code":"PPLL",
    "gn:name":"Kirino",
    "gn:population":0,
    "gn:timezone":"Asia/Tokyo",
    "iso:country":"JP",
    "name:jpn_x_preferred":[
        "\u6850\u91ce\u3000"
    ],
    "wof:name":"Kirino",
    "wof:placetype":"locality"
},
  "geometry": {"coordinates":[130.66269,33.71981],"type":"Point"}
}