{
  "type": "Feature",
  "properties": {
    "gn:admin1_code":"34.0",
    "gn:admin2_code":"7464123.0",
    "gn:asciiname":"Sezaki",
    "gn:country_code":"JP",
    "gn:dem":5,
    "gn:feature_class":"P",
    "gn:feature_code":"PPL",
    "gn:name":"Sezaki",
    "gn:population":0,
    "gn:timezone":"Asia/Tokyo",
    "iso:country":"JP",
    "name:jpn_x_preferred":[
        "\u702c\u5d0e"
    ],
    "wof:name":"Sezaki",
    "wof:placetype":"locality"
},
  "geometry": {"coordinates":[139.81008,35.81252],"type":"Point"}
}