{
  "type": "Feature",
  "properties": {
    "gn:admin1_code":"33.0",
    "gn:admin2_code":"8300623.0",
    "gn:asciiname":"Honmon",
    "gn:country_code":"JP",
    "gn:dem":453,
    "gn:feature_class":"P",
    "gn:feature_code":"PPLL",
    "gn:name":"Honmon",
    "gn:population":0,
    "gn:timezone":"Asia/Tokyo",
    "iso:country":"JP",
    "name:jpn_x_preferred":[
        "\u672c\u9580"
    ],
    "wof:name":"Honmon",
    "wof:placetype":"locality"
},
  "geometry": {"coordinates":[130.08516,33.35037],"type":"Point"}
}