{
  "type": "Feature",
  "properties": {
    "gn:admin1_code":"2.0",
    "gn:admin2_code":"7443149.0",
    "gn:asciiname":"Nagano",
    "gn:country_code":"JP",
    "gn:dem":40,
    "gn:feature_class":"P",
    "gn:feature_code":"PPL",
    "gn:name":"Nagano",
    "gn:population":0,
    "gn:timezone":"Asia/Tokyo",
    "iso:country":"JP",
    "name:ceb_x_preferred":[
        "Nagano"
    ],
    "name:ces_x_preferred":[
        "Nagano"
    ],
    "name:deu_x_preferred":[
        "Nagano"
    ],
    "name:epo_x_preferred":[
        "Nagano"
    ],
    "name:fra_x_preferred":[
        "Nagano"
    ],
    "name:fry_x_preferred":[
        "Nagano"
    ],
    "name:jpn_x_preferred":[
        "\u9577\u91ce"
    ],
    "name:kor_x_preferred":[
        "\ub098\uac00\ub178"
    ],
    "name:mlg_x_preferred":[
        "Nagano"
    ],
    "name:nld_x_preferred":[
        "Nagano"
    ],
    "name:ron_x_preferred":[
        "Nagano"
    ],
    "name:rus_x_preferred":[
        "\u041d\u0430\u0433\u0430\u043d\u043e"
    ],
    "name:tha_x_preferred":[
        "\u0e19\u0e30\u0e07\u0e30\u0e42\u0e19\u0e30"
    ],
    "name:ukr_x_preferred":[
        "\u041d\u0430\u0491\u0430\u043d\u043e"
    ],
    "wof:name":"Nagano",
    "wof:placetype":"locality"
},
  "geometry": {"coordinates":[140.53333000000001,39.53333],"type":"Point"}
}