{
  "type": "Feature",
  "properties": {
    "gn:admin1_code":"2.0",
    "gn:admin2_code":"7443149.0",
    "gn:asciiname":"Nagano",
    "gn:country_code":"JP",
    "gn:dem":40,
    "gn:feature_class":"P",
    "gn:feature_code":"PPL",
    "gn:name":"Nagano",
    "gn:population":0,
    "gn:timezone":"Asia/Tokyo",
    "iso:country":"JP",
    "name:jpn_x_preferred":[
        "\u9577\u91ce"
    ],
    "wof:name":"Nagano",
    "wof:placetype":"locality"
},
  "geometry": {"coordinates":[140.53333000000001,39.53333],"type":"Point"}
}