{
  "type": "Feature",
  "properties": {
    "gn:admin1_code":"06",
    "gn:admin2_code":"7465771.0",
    "gn:admin3_code":"18404.0",
    "gn:asciiname":"Yunoo",
    "gn:cc2":"JP",
    "gn:country_code":"JP",
    "gn:dem":103,
    "gn:feature_class":"P",
    "gn:feature_code":"PPL",
    "gn:name":"Yunoo",
    "gn:population":0,
    "gn:timezone":"Asia/Tokyo",
    "iso:country":"JP",
    "name:jpn_x_preferred":[
        "\u6e6f\u5c3e"
    ],
    "name:und_x_variant":[
        "Yun\u014d-mura",
        "Yuno"
    ],
    "wof:name":"Yunoo",
    "wof:placetype":"locality"
},
  "geometry": {"coordinates":[136.19614000000001,35.79324000000001],"type":"Point"}
}