{
  "type": "Feature",
  "properties": {
    "gn:admin1_code":"3.0",
    "gn:asciiname":"Jogasawa",
    "gn:country_code":"JP",
    "gn:dem":1,
    "gn:feature_class":"P",
    "gn:feature_code":"PPL",
    "gn:name":"J\u014dgasawa",
    "gn:population":0,
    "gn:timezone":"Asia/Tokyo",
    "iso:country":"JP",
    "name:und_x_variant":[
        "J\u014dgasawa"
    ],
    "wof:name":"Jogasawa",
    "wof:placetype":"locality"
},
  "geometry": {"coordinates":[141.13333,41.21667],"type":"Point"}
}