{
  "type": "Feature",
  "properties": {
    "gn:admin1_code":"40.0",
    "gn:admin2_code":"1852083.0",
    "gn:asciiname":"Yokoteramachi",
    "gn:country_code":"JP",
    "gn:dem":29,
    "gn:feature_class":"P",
    "gn:feature_code":"PPL",
    "gn:name":"Yokoteramachi",
    "gn:population":0,
    "gn:timezone":"Asia/Tokyo",
    "iso:country":"JP",
    "name:jpn_x_preferred":[
        "\u6a2a\u5bfa\u753a"
    ],
    "wof:name":"Yokoteramachi",
    "wof:placetype":"locality"
},
  "geometry": {"coordinates":[139.73531,35.70159],"type":"Point"}
}