{
  "type": "Feature",
  "properties": {
    "gn:admin1_code":"10",
    "gn:admin2_code":"7453747.0",
    "gn:admin3_code":"10421.0",
    "gn:asciiname":"Shimosawatari",
    "gn:country_code":"JP",
    "gn:dem":509,
    "gn:feature_class":"P",
    "gn:feature_code":"PPL",
    "gn:name":"Shimosawatari",
    "gn:population":0,
    "gn:timezone":"Asia/Tokyo",
    "iso:country":"JP",
    "name:jpn_x_preferred":[
        "\u4e0b\u6ca2\u6e21"
    ],
    "name:und_x_variant":[
        "Shimo-sawatari"
    ],
    "wof:name":"Shimosawatari",
    "wof:placetype":"locality"
},
  "geometry": {"coordinates":[138.78887,36.61423],"type":"Point"}
}