{
  "type": "Feature",
  "properties": {
    "gn:admin1_code":"25.0",
    "gn:admin2_code":"1864313.0",
    "gn:asciiname":"Oda",
    "gn:country_code":"JP",
    "gn:dem":227,
    "gn:feature_class":"P",
    "gn:feature_code":"PPL",
    "gn:name":"Oda",
    "gn:population":0,
    "gn:timezone":"Asia/Tokyo",
    "iso:country":"JP",
    "name:jpn_x_preferred":[
        "\u5c0f\u7530"
    ],
    "name:jpn_x_variant":[
        "\u304a\u3060",
        "\u30aa\u30c0"
    ],
    "wof:name":"Oda",
    "wof:placetype":"locality"
},
  "geometry": {"coordinates":[130.81892999999999,32.05055],"type":"Point"}
}