{
  "type": "Feature",
  "properties": {
    "gn:admin1_code":"11",
    "gn:admin2_code":"1858288.0",
    "gn:asciiname":"Ondocho-fujinowaki",
    "gn:country_code":"JP",
    "gn:dem":33,
    "gn:feature_class":"P",
    "gn:feature_code":"PPL",
    "gn:name":"Ondoch\u014d-fujinowaki",
    "gn:population":0,
    "gn:timezone":"Asia/Tokyo",
    "iso:country":"JP",
    "name:jpn_x_preferred":[
        "\u97f3\u6238\u753a\u85e4\u8107"
    ],
    "name:und_x_variant":[
        "Ondoch\u014d-fujinowaki",
        "Fujinowaki"
    ],
    "wof:name":"Ondocho-fujinowaki",
    "wof:placetype":"locality"
},
  "geometry": {"coordinates":[132.50098,34.14838],"type":"Point"}
}