{
  "type": "Feature",
  "properties": {
    "gn:admin1_code":"19.0",
    "gn:admin2_code":"1848350.0",
    "gn:admin3_code":"14114.0",
    "gn:asciiname":"Azumanodai",
    "gn:country_code":"JP",
    "gn:dem":75,
    "gn:feature_class":"P",
    "gn:feature_code":"PPL",
    "gn:name":"Azumanodai",
    "gn:population":0,
    "gn:timezone":"Asia/Tokyo",
    "iso:country":"JP",
    "name:jpn_x_preferred":[
        "\u6771\u91ce\u53f0"
    ],
    "wof:name":"Azumanodai",
    "wof:placetype":"locality"
},
  "geometry": {"coordinates":[139.49943999999999,35.4757],"type":"Point"}
}