{
  "type": "Feature",
  "properties": {
    "gn:admin1_code":"34.0",
    "gn:admin2_code":"1849187.0",
    "gn:admin3_code":"11103.0",
    "gn:asciiname":"Shimocho",
    "gn:country_code":"JP",
    "gn:dem":16,
    "gn:feature_class":"P",
    "gn:feature_code":"PPL",
    "gn:name":"Shimoch\u014d",
    "gn:population":0,
    "gn:timezone":"Asia/Tokyo",
    "iso:country":"JP",
    "name:jpn_x_preferred":[
        "\u4e0b\u753a"
    ],
    "name:und_x_variant":[
        "Shimoch\u014d"
    ],
    "wof:name":"Shimocho",
    "wof:placetype":"locality"
},
  "geometry": {"coordinates":[139.62988000000001,35.90384],"type":"Point"}
}