{
  "type": "Feature",
  "properties": {
    "gn:admin1_code":"21.0",
    "gn:admin2_code":"7413152.0",
    "gn:asciiname":"Utowari",
    "gn:country_code":"JP",
    "gn:dem":-2,
    "gn:feature_class":"P",
    "gn:feature_code":"PPLL",
    "gn:name":"Utowari",
    "gn:population":0,
    "gn:timezone":"Asia/Tokyo",
    "iso:country":"JP",
    "name:jpn_x_preferred":[
        "\u5b87\u571f\u5272"
    ],
    "name:jpn_x_variant":[
        "\u3046\u3068\u308f\u308a",
        "\u30a6\u30c8\u30ef\u30ea"
    ],
    "wof:name":"Utowari",
    "wof:placetype":"locality"
},
  "geometry": {"coordinates":[130.69067999999999,32.60885],"type":"Point"}
}