{
  "type": "Feature",
  "properties": {
    "gn:admin1_code":"21.0",
    "gn:admin2_code":"1859488.0",
    "gn:asciiname":"Takanaga",
    "gn:country_code":"JP",
    "gn:dem":93,
    "gn:feature_class":"P",
    "gn:feature_code":"PPLL",
    "gn:name":"Takanaga",
    "gn:population":0,
    "gn:timezone":"Asia/Tokyo",
    "iso:country":"JP",
    "name:jpn_x_preferred":[
        "\u9ad8\u6c38"
    ],
    "name:jpn_x_variant":[
        "\u305f\u304b\u306a\u304c",
        "\u30bf\u30ab\u30ca\u30ac"
    ],
    "wof:name":"Takanaga",
    "wof:placetype":"locality"
},
  "geometry": {"coordinates":[130.83908,32.94168],"type":"Point"}
}