{
  "type": "Feature",
  "properties": {
    "gn:admin1_code":"2.0",
    "gn:admin2_code":"2129594.0",
    "gn:admin3_code":"5303.0",
    "gn:asciiname":"Iwazawa",
    "gn:country_code":"JP",
    "gn:dem":154,
    "gn:feature_class":"P",
    "gn:feature_code":"PPLL",
    "gn:name":"Iwazawa",
    "gn:population":0,
    "gn:timezone":"Asia/Tokyo",
    "iso:country":"JP",
    "name:jpn_x_preferred":[
        "\u5ca9\u6ca2"
    ],
    "name:jpn_x_variant":[
        "\u3044\u308f\u3056\u308f",
        "\u30a4\u30ef\u30b6\u30ef"
    ],
    "wof:name":"Iwazawa",
    "wof:placetype":"locality"
},
  "geometry": {"coordinates":[140.74156000000005,40.31444000000001],"type":"Point"}
}