{
  "type": "Feature",
  "properties": {
    "iso:country":"JP",
    "name:eng_x_preferred":[
        "Ishigakinishi 1 Chome"
    ],
    "name:eng_x_variant":[
        "Ishigakinishi 1 Choume",
        "Ishigakinishi 1 Chome"
    ],
    "name:jpn_x_preferred":[
        "\uff11\u4e01\u76ee"
    ],
    "name:jpn_x_variant":[
        "\u3044\u3057\u304c\u304d\u306b\u3057 \uff11\u3061\u3087\u3046\u3081",
        "\u77f3\u57a3\u897f \uff11\u4e01\u76ee",
        "\uff11\u3061\u3087\u3046\u3081"
    ],
    "qs:gn_local":0,
    "qs:local_max":1013,
    "qs:local_sum":1496,
    "qs:localhoods":6,
    "qs:name":"\uff11\u4e01\u76ee",
    "qs:name_adm0":"\u65e5\u672c",
    "qs:name_adm1":"\u5927\u5206\u770c",
    "qs:name_en":"Ishigakinishi 1 Chome",
    "qs:name_lau":"\u77f3\u57a3\u897f",
    "qs:name_local":"\u5225\u5e9c\u5e02",
    "qs:photo_max":128,
    "qs:photo_sum":232,
    "qs:placetype":"Suburb",
    "qs:quad_count":10,
    "qs:woe_adm0":23424856,
    "qs:woe_adm1":2345879,
    "qs:woe_adm2":0,
    "qs:woe_lau":28490417,
    "qs:woe_local":1117022,
    "qs:woe_ver":"7.10.0",
    "qs_pg:name":"\uff11\u4e01\u76ee",
    "qs_pg:name_adm0":"\u65e5\u672c",
    "qs_pg:name_adm1":"\u5927\u5206\u770c",
    "qs_pg:photos":249,
    "qs_pg:photos_1k":50,
    "qs_pg:photos_9k":1,
    "qs_pg:photos_9r":4,
    "qs_pg:photos_all":249,
    "qs_pg:photos_sr":4,
    "qs_pg:pop_sr":0,
    "qs_pg:qs_pg_placetype":"neighbourhood",
    "qs_pg:qs_pg_placetype_gp":"Suburb",
    "qs_pg:woe_adm0":23424856,
    "woe:adm0_id":23424856,
    "woe:name_adm0":"\u65e5\u672c",
    "woe:name_adm1":"\u5927\u5206\u770c",
    "woe:placetype":"Suburb",
    "wof:lang":[
        "jpn"
    ],
    "wof:name":"\uff11\u4e01\u76ee",
    "wof:placetype":"neighbourhood"
},
  "geometry": {"coordinates":[131.490263,33.283632],"type":"Point"}
}