{
  "type": "Feature",
  "properties": {
    "gn:admin1_code":"21.0",
    "gn:admin2_code":"1859488.0",
    "gn:asciiname":"Shisuimachi-naga",
    "gn:country_code":"JP",
    "gn:dem":75,
    "gn:feature_class":"P",
    "gn:feature_code":"PPL",
    "gn:name":"Shisuimachi-naga",
    "gn:population":0,
    "gn:timezone":"Asia/Tokyo",
    "iso:country":"JP",
    "name:jpn_x_preferred":[
        "\u6cd7\u6c34\u753a\u6c38"
    ],
    "name:jpn_x_variant":[
        "\u3057\u3059\u3044\u307e\u3061\u306a\u304c",
        "\u30b7\u30b9\u30a4\u30de\u30c1\u30ca\u30ac"
    ],
    "wof:name":"Shisuimachi-naga",
    "wof:placetype":"locality"
},
  "geometry": {"coordinates":[130.80418999999998,32.92162],"type":"Point"}
}