{
  "type": "Feature",
  "properties": {
    "gn:admin1_code":"7.0",
    "gn:admin2_code":"1860814.0",
    "gn:admin3_code":"40421.0",
    "gn:asciiname":"Futatsuka",
    "gn:country_code":"JP",
    "gn:dem":31,
    "gn:feature_class":"P",
    "gn:feature_code":"PPLL",
    "gn:name":"Futatsuka",
    "gn:population":0,
    "gn:timezone":"Asia/Tokyo",
    "iso:country":"JP",
    "name:jpn_x_preferred":[
        "\u4e8c\u585a"
    ],
    "wof:name":"Futatsuka",
    "wof:placetype":"locality"
},
  "geometry": {"coordinates":[130.69385,33.58159000000001],"type":"Point"}
}