{
  "type": "Feature",
  "properties": {
    "gn:admin1_code":"29.0",
    "gn:admin2_code":"7468177.0",
    "gn:asciiname":"Minamiodaira",
    "gn:country_code":"JP",
    "gn:dem":94,
    "gn:feature_class":"P",
    "gn:feature_code":"PPL",
    "gn:name":"Minami\u014ddaira",
    "gn:population":0,
    "gn:timezone":"Asia/Tokyo",
    "iso:country":"JP",
    "name:jpn_x_preferred":[
        "\u5357\u5927\u5e73"
    ],
    "name:und_x_variant":[
        "Minami\u014ddaira"
    ],
    "wof:name":"Minamiodaira",
    "wof:placetype":"locality"
},
  "geometry": {"coordinates":[139.52437,38.17935],"type":"Point"}
}