{
  "type": "Feature",
  "properties": {
    "gn:admin1_code":"43.0",
    "gn:admin2_code":"1848936.0",
    "gn:asciiname":"Nozaki",
    "gn:country_code":"JP",
    "gn:dem":1,
    "gn:feature_class":"P",
    "gn:feature_code":"PPL",
    "gn:name":"Nozaki",
    "gn:population":0,
    "gn:timezone":"Asia/Tokyo",
    "iso:country":"JP",
    "name:jpn_x_preferred":[
        "\u91ce\u5d0e"
    ],
    "name:kor_x_preferred":[
        "\ub178\uc790\ud0a4"
    ],
    "wof:name":"Nozaki",
    "wof:placetype":"locality"
},
  "geometry": {"coordinates":[135.15674000000001,34.24513],"type":"Point"}
}