{
  "type": "Feature",
  "properties": {
    "gn:admin1_code":"3.0",
    "gn:admin2_code":"2130056.0",
    "gn:asciiname":"Itchoda",
    "gn:country_code":"JP",
    "gn:dem":42,
    "gn:feature_class":"P",
    "gn:feature_code":"PPL",
    "gn:name":"Itch\u014dda",
    "gn:population":0,
    "gn:timezone":"Asia/Tokyo",
    "iso:country":"JP",
    "name:jpn_x_preferred":[
        "\u4e00\u753a\u7530"
    ],
    "name:jpn_x_variant":[
        "\u3044\u3063\u3061\u3087\u3046\u3060",
        "\u30a4\u30c3\u30c1\u30e7\u30a6\u30c0"
    ],
    "name:und_x_variant":[
        "Itch\u014dda"
    ],
    "wof:name":"Itchoda",
    "wof:placetype":"locality"
},
  "geometry": {"coordinates":[140.42236,40.61081],"type":"Point"}
}