{
  "type": "Feature",
  "properties": {
    "gn:admin1_code":"7.0",
    "gn:admin2_code":"1859306.0",
    "gn:admin3_code":"40105.0",
    "gn:asciiname":"Sawami",
    "gn:country_code":"JP",
    "gn:dem":14,
    "gn:feature_class":"P",
    "gn:feature_code":"PPL",
    "gn:name":"Sawami",
    "gn:population":0,
    "gn:timezone":"Asia/Tokyo",
    "iso:country":"JP",
    "name:jpn_x_preferred":[
        "\u6ca2\u898b"
    ],
    "wof:name":"Sawami",
    "wof:placetype":"locality"
},
  "geometry": {"coordinates":[130.83741000000001,33.89281],"type":"Point"}
}