{
  "type": "Feature",
  "properties": {
    "gn:admin1_code":"23",
    "gn:admin2_code":"1848370.0",
    "gn:asciiname":"Nishi-hino",
    "gn:cc2":"JP",
    "gn:country_code":"JP",
    "gn:dem":24,
    "gn:feature_class":"P",
    "gn:feature_code":"PPL",
    "gn:name":"Nishi-hino",
    "gn:population":0,
    "gn:timezone":"Asia/Tokyo",
    "iso:country":"JP",
    "name:und_x_variant":[
        "Nishi-hinomachi",
        "Nishi-hino"
    ],
    "wof:name":"Nishi-hino",
    "wof:placetype":"locality"
},
  "geometry": {"coordinates":[136.58333000000002,34.95],"type":"Point"}
}