{
  "type": "Feature",
  "properties": {
    "gn:admin1_code":"09",
    "gn:admin2_code":"1850890.0",
    "gn:asciiname":"Kamitakaracho-zaike",
    "gn:country_code":"JP",
    "gn:dem":638,
    "gn:feature_class":"P",
    "gn:feature_code":"PPL",
    "gn:name":"Kamitakarach\u014d-zaike",
    "gn:population":0,
    "gn:timezone":"Asia/Tokyo",
    "iso:country":"JP",
    "name:jpn_x_preferred":[
        "\u4e0a\u5b9d\u753a\u5728\u5bb6"
    ],
    "name:und_x_variant":[
        "Kamitakarach\u014d-zaike",
        "Zaike"
    ],
    "wof:name":"Kamitakaracho-zaike",
    "wof:placetype":"locality"
},
  "geometry": {"coordinates":[137.36667,36.28333],"type":"Point"}
}