{
  "type": "Feature",
  "properties": {
    "gn:admin1_code":"19.0",
    "gn:admin2_code":"1854744.0",
    "gn:asciiname":"Higashicho",
    "gn:country_code":"JP",
    "gn:dem":8,
    "gn:feature_class":"P",
    "gn:feature_code":"PPL",
    "gn:name":"Higashich\u014d",
    "gn:population":0,
    "gn:timezone":"Asia/Tokyo",
    "iso:country":"JP",
    "name:jpn_x_preferred":[
        "\u6771\u753a"
    ],
    "name:und_x_variant":[
        "Higashich\u014d"
    ],
    "wof:name":"Higashicho",
    "wof:placetype":"locality"
},
  "geometry": {"coordinates":[139.17553000000001,35.25992],"type":"Point"}
}