{
  "type": "Feature",
  "properties": {
    "gn:admin1_code":"3.0",
    "gn:admin2_code":"7439944.0",
    "gn:asciiname":"Komada",
    "gn:country_code":"JP",
    "gn:dem":11,
    "gn:feature_class":"P",
    "gn:feature_code":"PPL",
    "gn:name":"Komada",
    "gn:population":0,
    "gn:timezone":"Asia/Tokyo",
    "iso:country":"JP",
    "name:jpn_x_preferred":[
        "\u99d2\u7530"
    ],
    "name:jpn_x_variant":[
        "\u3053\u307e\u3060",
        "\u30b3\u30de\u30c0"
    ],
    "wof:name":"Komada",
    "wof:placetype":"locality"
},
  "geometry": {"coordinates":[140.30525,40.81254000000001],"type":"Point"}
}