{
  "type": "Feature",
  "properties": {
    "gn:admin1_code":"34.0",
    "gn:admin2_code":"1849187.0",
    "gn:admin3_code":"11108.0",
    "gn:asciiname":"Minamiurawa",
    "gn:country_code":"JP",
    "gn:dem":14,
    "gn:feature_class":"P",
    "gn:feature_code":"PPL",
    "gn:name":"Minamiurawa",
    "gn:population":0,
    "gn:timezone":"Asia/Tokyo",
    "iso:country":"JP",
    "name:jpn_x_preferred":[
        "\u5357\u6d66\u548c"
    ],
    "name:jpn_x_variant":[
        "\u307f\u306a\u307f\u3046\u3089\u308f",
        "\u30df\u30ca\u30df\u30a6\u30e9\u30ef"
    ],
    "wof:name":"Minamiurawa",
    "wof:placetype":"locality"
},
  "geometry": {"coordinates":[139.67096999999998,35.8497],"type":"Point"}
}