{
  "type": "Feature",
  "properties": {
    "gn:admin1_code":"16.0",
    "gn:admin2_code":"2112822.0",
    "gn:asciiname":"Shimokitamanchome",
    "gn:country_code":"JP",
    "gn:dem":98,
    "gn:feature_class":"P",
    "gn:feature_code":"PPL",
    "gn:name":"Shimokitamanch\u014dme",
    "gn:population":0,
    "gn:timezone":"Asia/Tokyo",
    "iso:country":"JP",
    "name:jpn_x_preferred":[
        "\u4e0b\u5317\u4e07\u4e01\u76ee"
    ],
    "name:jpn_x_variant":[
        "\u3057\u3082\u304d\u305f\u307e\u3093\u3061\u3087\u3046\u3081",
        "\u30b7\u30e2\u30ad\u30bf\u30de\u30f3\u30c1\u30e7\u30a6\u30e1"
    ],
    "name:und_x_variant":[
        "Shimokitamanch\u014dme"
    ],
    "wof:name":"Shimokitamanchome",
    "wof:placetype":"locality"
},
  "geometry": {"coordinates":[141.09768,39.39459],"type":"Point"}
}