{
  "type": "Feature",
  "properties": {
    "gn:admin1_code":"16.0",
    "gn:admin2_code":"2129400.0",
    "gn:admin3_code":"3506.0",
    "gn:asciiname":"Kozawa",
    "gn:country_code":"JP",
    "gn:dem":320,
    "gn:feature_class":"P",
    "gn:feature_code":"PPL",
    "gn:name":"Kozawa",
    "gn:population":0,
    "gn:timezone":"Asia/Tokyo",
    "iso:country":"JP",
    "name:jpn_x_preferred":[
        "\u5c0f\u6ca2"
    ],
    "name:jpn_x_variant":[
        "\u3053\u3056\u308f",
        "\u30b3\u30b6\u30ef"
    ],
    "wof:name":"Kozawa",
    "wof:placetype":"locality"
},
  "geometry": {"coordinates":[141.42126999999999,40.19018],"type":"Point"}
}