{
  "type": "Feature",
  "properties": {
    "gn:admin1_code":"36",
    "gn:admin2_code":"1863519.0",
    "gn:asciiname":"Tsunozucho",
    "gn:country_code":"JP",
    "gn:dem":8,
    "gn:feature_class":"P",
    "gn:feature_code":"PPL",
    "gn:name":"Tsunozuch\u014d",
    "gn:population":0,
    "gn:timezone":"Asia/Tokyo",
    "iso:country":"JP",
    "name:jpn_x_preferred":[
        "\u90fd\u91ce\u6d25\u753a"
    ],
    "name:und_x_variant":[
        "Tonozu",
        "Tsunozu",
        "Tsunozuch\u014d"
    ],
    "wof:name":"Tsunozucho",
    "wof:placetype":"locality"
},
  "geometry": {"coordinates":[132.19248000000002,34.986],"type":"Point"}
}