{
  "type": "Feature",
  "properties": {
    "gn:admin1_code":"22.0",
    "gn:admin2_code":"1859202.0",
    "gn:asciiname":"Saganaka",
    "gn:country_code":"JP",
    "gn:dem":35,
    "gn:feature_class":"P",
    "gn:feature_code":"PPL",
    "gn:name":"Saganaka",
    "gn:population":0,
    "gn:timezone":"Asia/Tokyo",
    "iso:country":"JP",
    "name:jpn_x_preferred":[
        "\u76f8\u697d"
    ],
    "wof:name":"Saganaka",
    "wof:placetype":"locality"
},
  "geometry": {"coordinates":[135.80056999999999,34.73343],"type":"Point"}
}