{
  "type": "Feature",
  "properties": {
    "gn:admin1_code":"3.0",
    "gn:admin2_code":"7439944.0",
    "gn:asciiname":"Kowamaki",
    "gn:country_code":"JP",
    "gn:dem":12,
    "gn:feature_class":"P",
    "gn:feature_code":"PPL",
    "gn:name":"Kowamaki",
    "gn:population":0,
    "gn:timezone":"Asia/Tokyo",
    "iso:country":"JP",
    "name:jpn_x_preferred":[
        "\u5c0f\u548c\u5dfb"
    ],
    "name:jpn_x_variant":[
        "\u3053\u308f\u307e\u304d",
        "\u30b3\u30ef\u30de\u30ad"
    ],
    "wof:name":"Kowamaki",
    "wof:placetype":"locality"
},
  "geometry": {"coordinates":[140.41568000000001,40.76901],"type":"Point"}
}