{
  "type": "Feature",
  "properties": {
    "gn:admin1_code":"21.0",
    "gn:admin2_code":"1859488.0",
    "gn:asciiname":"Kawashimo",
    "gn:country_code":"JP",
    "gn:dem":96,
    "gn:feature_class":"P",
    "gn:feature_code":"PPLL",
    "gn:name":"Kawashimo",
    "gn:population":0,
    "gn:timezone":"Asia/Tokyo",
    "iso:country":"JP",
    "name:jpn_x_preferred":[
        "\u5ddd\u4e0b"
    ],
    "name:jpn_x_variant":[
        "\u304b\u308f\u3057\u3082",
        "\u30ab\u30ef\u30b7\u30e2"
    ],
    "wof:name":"Kawashimo",
    "wof:placetype":"locality"
},
  "geometry": {"coordinates":[130.83396999999999,32.92857],"type":"Point"}
}