{
  "type": "Feature",
  "properties": {
    "gn:admin1_code":"3.0",
    "gn:admin2_code":"7439934.0",
    "gn:asciiname":"Surige",
    "gn:country_code":"JP",
    "gn:dem":355,
    "gn:feature_class":"P",
    "gn:feature_code":"PPL",
    "gn:name":"Surige",
    "gn:population":0,
    "gn:timezone":"Asia/Tokyo",
    "iso:country":"JP",
    "name:jpn_x_preferred":[
        "\u647a\u6bdb"
    ],
    "name:jpn_x_variant":[
        "\u3059\u308a\u3052",
        "\u30b9\u30ea\u30b2"
    ],
    "wof:name":"Surige",
    "wof:placetype":"locality"
},
  "geometry": {"coordinates":[140.74262999999999,40.51971],"type":"Point"}
}