{
  "type": "Feature",
  "properties": {
    "gn:admin1_code":"21.0",
    "gn:admin2_code":"1850744.0",
    "gn:admin3_code":"43367.0",
    "gn:asciiname":"Hakkakume",
    "gn:country_code":"JP",
    "gn:dem":115,
    "gn:feature_class":"P",
    "gn:feature_code":"PPLL",
    "gn:name":"Hakkakume",
    "gn:population":0,
    "gn:timezone":"Asia/Tokyo",
    "iso:country":"JP",
    "name:jpn_x_preferred":[
        "\u516b\u89d2\u76ee"
    ],
    "name:jpn_x_variant":[
        "\u306f\u3063\u304b\u304f\u3081",
        "\u30cf\u30c3\u30ab\u30af\u30e1"
    ],
    "wof:name":"Hakkakume",
    "wof:placetype":"locality"
},
  "geometry": {"coordinates":[130.50038999999998,33.04808],"type":"Point"}
}