{
  "type": "Feature",
  "properties": {
    "gn:admin1_code":"8.0",
    "gn:admin2_code":"2112139.0",
    "gn:asciiname":"Tamuramachi-moriyama",
    "gn:country_code":"JP",
    "gn:dem":241,
    "gn:feature_class":"P",
    "gn:feature_code":"PPL",
    "gn:name":"Tamuramachi-moriyama",
    "gn:population":0,
    "gn:timezone":"Asia/Tokyo",
    "iso:country":"JP",
    "name:jpn_x_preferred":[
        "\u7530\u6751\u753a\u5b88\u5c71"
    ],
    "name:und_x_variant":[
        "Moriyama"
    ],
    "wof:name":"Tamuramachi-moriyama",
    "wof:placetype":"locality"
},
  "geometry": {"coordinates":[140.40880000000001,37.33093],"type":"Point"}
}