{
  "type": "Feature",
  "properties": {
    "gn:admin1_code":"6.0",
    "gn:admin2_code":"1863982.0",
    "gn:asciiname":"Yaemaki-nakacho",
    "gn:country_code":"JP",
    "gn:dem":9,
    "gn:feature_class":"P",
    "gn:feature_code":"PPL",
    "gn:name":"Yaemaki-nakach\u014d",
    "gn:population":0,
    "gn:timezone":"Asia/Tokyo",
    "iso:country":"JP",
    "name:jpn_x_preferred":[
        "\u516b\u91cd\u5dfb\u4e2d\u753a"
    ],
    "name:und_x_variant":[
        "Yaemaki-nakach\u014d"
    ],
    "wof:name":"Yaemaki-nakacho",
    "wof:placetype":"locality"
},
  "geometry": {"coordinates":[136.22219999999999,36.10498],"type":"Point"}
}