{
  "type": "Feature",
  "properties": {
    "gn:admin1_code":"19.0",
    "gn:admin2_code":"1864928.0",
    "gn:asciiname":"Okatsukoku",
    "gn:country_code":"JP",
    "gn:dem":94,
    "gn:feature_class":"P",
    "gn:feature_code":"PPL",
    "gn:name":"Okatsukoku",
    "gn:population":0,
    "gn:timezone":"Asia/Tokyo",
    "iso:country":"JP",
    "name:jpn_x_preferred":[
        "\u5ca1\u6d25\u53e4\u4e45"
    ],
    "wof:name":"Okatsukoku",
    "wof:placetype":"locality"
},
  "geometry": {"coordinates":[139.31108,35.4274],"type":"Point"}
}