{
  "type": "Feature",
  "properties": {
    "iso:country":"JP",
    "name:jpn_x_preferred":[
        "\uff08\u4e01\u76ee\u306a\u3057\uff09"
    ],
    "qs:gn_local":0,
    "qs:local_max":227,
    "qs:local_sum":405,
    "qs:localhoods":5,
    "qs:name":"\uff08\u4e01\u76ee\u306a\u3057\uff09",
    "qs:name_adm0":"\u65e5\u672c",
    "qs:name_adm1":"\u9577\u91ce\u770c",
    "qs:name_lau":"\u5e38\u5165",
    "qs:name_local":"\u4e0a\u7530\u5e02",
    "qs:photo_max":2,
    "qs:photo_sum":2,
    "qs:placetype":"Suburb",
    "qs:quad_count":1,
    "qs:woe_adm0":23424856,
    "qs:woe_adm1":2345875,
    "qs:woe_adm2":0,
    "qs:woe_lau":28431675,
    "qs:woe_local":1118456,
    "qs:woe_ver":"7.10.0",
    "wof:lang":[
        "jpn"
    ],
    "wof:name":"\uff08\u4e01\u76ee\u306a\u3057\uff09",
    "wof:placetype":"neighbourhood"
},
  "geometry": {"coordinates":[138.24371300000001,36.383701],"type":"Point"}
}