{
  "type": "Feature",
  "properties": {
    "gn:admin1_code":"16.0",
    "gn:admin2_code":"2129400.0",
    "gn:admin3_code":"3501.0",
    "gn:asciiname":"Higashi",
    "gn:country_code":"JP",
    "gn:dem":327,
    "gn:feature_class":"P",
    "gn:feature_code":"PPL",
    "gn:name":"Higashi",
    "gn:population":0,
    "gn:timezone":"Asia/Tokyo",
    "iso:country":"JP",
    "name:ceb_x_preferred":[
        "Higashi"
    ],
    "name:deu_x_preferred":[
        "Higashi"
    ],
    "name:jpn_x_preferred":[
        "\u6771"
    ],
    "name:jpn_x_variant":[
        "\u3072\u304c\u3057",
        "\u30d2\u30ac\u30b7"
    ],
    "name:pol_x_preferred":[
        "Higashi"
    ],
    "name:spa_x_preferred":[
        "Higashi"
    ],
    "name:ukr_x_preferred":[
        "\u0425\u0456\u0491\u0430\u0441\u0456"
    ],
    "wof:name":"Higashi",
    "wof:placetype":"locality"
},
  "geometry": {"coordinates":[141.42026000000001,40.30362],"type":"Point"}
}