{
  "type": "Feature",
  "properties": {
    "gn:admin1_code":"4.0",
    "gn:admin2_code":"7465521.0",
    "gn:asciiname":"Shuku",
    "gn:country_code":"JP",
    "gn:dem":16,
    "gn:feature_class":"P",
    "gn:feature_code":"PPLL",
    "gn:name":"Shuku",
    "gn:population":0,
    "gn:timezone":"Asia/Tokyo",
    "iso:country":"JP",
    "name:jpn_x_preferred":[
        "\u5bbf"
    ],
    "name:jpn_x_variant":[
        "\u3057\u3085\u304f",
        "\u30b7\u30e5\u30af"
    ],
    "wof:name":"Shuku",
    "wof:placetype":"locality"
},
  "geometry": {"coordinates":[139.88851,35.01524000000001],"type":"Point"}
}