{
  "type": "Feature",
  "properties": {
    "gn:admin1_code":"21.0",
    "gn:admin2_code":"7413152.0",
    "gn:asciiname":"Uchikoshi",
    "gn:country_code":"JP",
    "gn:dem":24,
    "gn:feature_class":"P",
    "gn:feature_code":"PPLL",
    "gn:name":"Uchikoshi",
    "gn:population":0,
    "gn:timezone":"Asia/Tokyo",
    "iso:country":"JP",
    "name:jpn_x_preferred":[
        "\u6253\u8d8a"
    ],
    "name:jpn_x_variant":[
        "\u3046\u3061\u3053\u3057",
        "\u30a6\u30c1\u30b3\u30b7"
    ],
    "wof:name":"Uchikoshi",
    "wof:placetype":"locality"
},
  "geometry": {"coordinates":[130.53246999999999,32.62566],"type":"Point"}
}