{
  "type": "Feature",
  "properties": {
    "gn:admin1_code":"27.0",
    "gn:admin2_code":"1859301.0",
    "gn:admin3_code":"42391.0",
    "gn:asciiname":"Kodamen",
    "gn:country_code":"JP",
    "gn:dem":18,
    "gn:feature_class":"P",
    "gn:feature_code":"PPL",
    "gn:name":"K\u014ddamen",
    "gn:population":0,
    "gn:timezone":"Asia/Tokyo",
    "iso:country":"JP",
    "name:jpn_x_preferred":[
        "\u795e\u7530\u514d"
    ],
    "name:und_x_variant":[
        "K\u014ddamen"
    ],
    "wof:name":"Kodamen",
    "wof:placetype":"locality"
},
  "geometry": {"coordinates":[129.66783000000001,33.25963],"type":"Point"}
}