{
  "type": "Feature",
  "properties": {
    "gn:admin1_code":"19.0",
    "gn:admin2_code":"1865011.0",
    "gn:admin3_code":"14362.0",
    "gn:asciiname":"Yoshiwara",
    "gn:country_code":"JP",
    "gn:dem":43,
    "gn:feature_class":"P",
    "gn:feature_code":"PPLL",
    "gn:name":"Yoshiwara",
    "gn:population":0,
    "gn:timezone":"Asia/Tokyo",
    "iso:country":"JP",
    "name:jpn_x_preferred":[
        "\u5409\u539f\u3000"
    ],
    "wof:name":"Yoshiwara",
    "wof:placetype":"locality"
},
  "geometry": {"coordinates":[139.15145999999999,35.32876],"type":"Point"}
}