{
  "type": "Feature",
  "properties": {
    "gn:admin1_code":"19.0",
    "gn:admin2_code":"1865011.0",
    "gn:admin3_code":"14362.0",
    "gn:asciiname":"Yoshiwara",
    "gn:country_code":"JP",
    "gn:dem":43,
    "gn:feature_class":"P",
    "gn:feature_code":"PPLL",
    "gn:name":"Yoshiwara",
    "gn:population":0,
    "gn:timezone":"Asia/Tokyo",
    "iso:country":"JP",
    "name:cat_x_preferred":[
        "Yoshiwara"
    ],
    "name:ces_x_preferred":[
        "Jo\u0161iwara"
    ],
    "name:cym_x_preferred":[
        "Yoshiwara"
    ],
    "name:deu_x_preferred":[
        "Yoshiwara"
    ],
    "name:fas_x_preferred":[
        "\u06cc\u0648\u0634\u06cc\u0648\u0627\u0631\u0627"
    ],
    "name:fra_x_preferred":[
        "Yoshiwara"
    ],
    "name:hun_x_preferred":[
        "Josivara"
    ],
    "name:jpn_x_preferred":[
        "\u5409\u539f\u3000"
    ],
    "name:jpn_x_variant":[
        "\u5409\u539f"
    ],
    "name:kor_x_preferred":[
        "\uc694\uc2dc\uc640\ub77c"
    ],
    "name:msa_x_preferred":[
        "Yoshiwara"
    ],
    "name:nld_x_preferred":[
        "Yoshiwara"
    ],
    "name:rus_x_preferred":[
        "\u0401\u0441\u0438\u0432\u0430\u0440\u0430"
    ],
    "name:spa_x_preferred":[
        "Yoshiwara"
    ],
    "name:ukr_x_preferred":[
        "\u0419\u043e\u0448\u0456\u0432\u0430\u0440\u0430"
    ],
    "wof:name":"Yoshiwara",
    "wof:placetype":"locality"
},
  "geometry": {"coordinates":[139.15145999999999,35.32876],"type":"Point"}
}