{
  "type": "Feature",
  "properties": {
    "gn:admin1_code":"7.0",
    "gn:admin2_code":"1859306.0",
    "gn:admin3_code":"40109.0",
    "gn:asciiname":"Funakoshi",
    "gn:country_code":"JP",
    "gn:dem":37,
    "gn:feature_class":"P",
    "gn:feature_code":"PPL",
    "gn:name":"Funakoshi",
    "gn:population":0,
    "gn:timezone":"Asia/Tokyo",
    "iso:country":"JP",
    "name:jpn_x_preferred":[
        "\u8239\u8d8a"
    ],
    "wof:name":"Funakoshi",
    "wof:placetype":"locality"
},
  "geometry": {"coordinates":[130.74178999999998,33.81467],"type":"Point"}
}