{
  "type": "Feature",
  "properties": {
    "gn:admin1_code":"22.0",
    "gn:admin2_code":"1851574.0",
    "gn:admin3_code":"26367.0",
    "gn:asciiname":"Imayama",
    "gn:country_code":"JP",
    "gn:dem":119,
    "gn:feature_class":"P",
    "gn:feature_code":"PPLL",
    "gn:name":"Imayama",
    "gn:population":0,
    "gn:timezone":"Asia/Tokyo",
    "iso:country":"JP",
    "name:jpn_x_preferred":[
        "\u4eca\u5c71"
    ],
    "wof:name":"Imayama",
    "wof:placetype":"locality"
},
  "geometry": {"coordinates":[136.02619000000001,34.76062],"type":"Point"}
}