{
  "type": "Feature",
  "properties": {
    "gn:admin1_code":"21.0",
    "gn:admin2_code":"1865360.0",
    "gn:admin3_code":"43531.0",
    "gn:asciiname":"Kawamukai",
    "gn:country_code":"JP",
    "gn:dem":27,
    "gn:feature_class":"P",
    "gn:feature_code":"PPLL",
    "gn:name":"Kawamukai",
    "gn:population":0,
    "gn:timezone":"Asia/Tokyo",
    "iso:country":"JP",
    "name:jpn_x_preferred":[
        "\u5ddd\u5411"
    ],
    "name:jpn_x_variant":[
        "\u304b\u308f\u3080\u304b\u3044",
        "\u30ab\u30ef\u30e0\u30ab\u30a4"
    ],
    "wof:name":"Kawamukai",
    "wof:placetype":"locality"
},
  "geometry": {"coordinates":[130.08799999999999,32.5252],"type":"Point"}
}