{
  "type": "Feature",
  "properties": {
    "iso:country":"JP",
    "name:eng_x_preferred":[
        "Onna"
    ],
    "name:eng_x_variant":[
        "Onna Village"
    ],
    "name:jpn_x_preferred":[
        "\u6069\u7d0d\u6751"
    ],
    "qs:name":"\u6069\u7d0d\u6751",
    "qs:name_adm0":"\u65e5\u672c",
    "qs:name_adm1":"\u6c96\u7e04\u770c",
    "qs:photos":5000,
    "qs:photos_1k":1000,
    "qs:photos_9k":22,
    "qs:photos_9r":14,
    "qs:photos_all":5000,
    "qs:photos_sr":24,
    "qs:placetype":"Town",
    "qs:pop_sr":"0",
    "wof:name":"Onna",
    "wof:placetype":"locality"
},
  "geometry": {"coordinates":[127.84034699999999,26.470986],"type":"Point"}
}