{
  "type": "Feature",
  "properties": {
    "iso:country":"JP",
    "name:eng_x_preferred":[
        "Chuo 4 Chome"
    ],
    "name:eng_x_variant":[
        "Chuuou 4 Choume",
        "Chuo 4 Chome"
    ],
    "name:jpn_x_preferred":[
        "\uff14\u4e01\u76ee"
    ],
    "name:jpn_x_variant":[
        "\u3061\u3085\u3046\u304a\u3046 \uff14\u3061\u3087\u3046\u3081",
        "\u4e2d\u592e \uff14\u4e01\u76ee",
        "\uff14\u3061\u3087\u3046\u3081"
    ],
    "qs:gn_local":0,
    "qs:local_max":247,
    "qs:local_sum":633,
    "qs:localhoods":7,
    "qs:name":"\uff14\u4e01\u76ee",
    "qs:name_adm0":"\u65e5\u672c",
    "qs:name_adm1":"\u5c71\u5f62\u770c",
    "qs:name_en":"Chuo 4 Chome",
    "qs:name_lau":"\u4e2d\u592e",
    "qs:name_local":"\u7c73\u6ca2\u5e02",
    "qs:photo_max":17,
    "qs:photo_sum":57,
    "qs:placetype":"Suburb",
    "qs:quad_count":6,
    "qs:woe_adm0":23424856,
    "qs:woe_adm1":2345893,
    "qs:woe_adm2":0,
    "qs:woe_lau":28396483,
    "qs:woe_local":1118558,
    "qs:woe_ver":"7.10.0",
    "qs_pg:name":"\uff14\u4e01\u76ee",
    "qs_pg:name_adm0":"\u65e5\u672c",
    "qs_pg:name_adm1":"\u5c71\u5f62\u770c",
    "qs_pg:photos":5,
    "qs_pg:photos_1k":1,
    "qs_pg:photos_9k":1,
    "qs_pg:photos_9r":1,
    "qs_pg:photos_all":5,
    "qs_pg:photos_sr":1,
    "qs_pg:pop_sr":0,
    "qs_pg:qs_pg_placetype":"neighbourhood",
    "qs_pg:qs_pg_placetype_gp":"Suburb",
    "qs_pg:woe_adm0":23424856,
    "woe:adm0_id":23424856,
    "woe:name_adm0":"\u65e5\u672c",
    "woe:name_adm1":"\u5c71\u5f62\u770c",
    "woe:placetype":"Suburb",
    "wof:lang":[
        "jpn"
    ],
    "wof:name":"\uff14\u4e01\u76ee",
    "wof:placetype":"neighbourhood"
},
  "geometry": {"coordinates":[140.107551,37.917889],"type":"Point"}
}