{
  "type": "Feature",
  "properties": {
    "gn:admin1_code":"2.0",
    "gn:admin2_code":"2113122.0",
    "gn:asciiname":"Iijima-naganohoncho",
    "gn:country_code":"JP",
    "gn:dem":13,
    "gn:feature_class":"P",
    "gn:feature_code":"PPL",
    "gn:name":"Iijima-naganohonch\u014d",
    "gn:population":0,
    "gn:timezone":"Asia/Tokyo",
    "iso:country":"JP",
    "name:jpn_x_preferred":[
        "\u98ef\u5cf6\u9577\u91ce\u672c\u753a"
    ],
    "name:jpn_x_variant":[
        "\u3044\u3044\u3058\u307e\u306a\u304c\u306e\u307b\u3093\u3061\u3087\u3046",
        "\u30a4\u30a4\u30b8\u30de\u30ca\u30ac\u30ce\u30db\u30f3\u30c1\u30e7\u30a6"
    ],
    "name:und_x_variant":[
        "Iijima-naganohonch\u014d"
    ],
    "wof:name":"Iijima-naganohoncho",
    "wof:placetype":"locality"
},
  "geometry": {"coordinates":[140.08157,39.7735],"type":"Point"}
}