{
  "type": "Feature",
  "properties": {
    "iso:country":"JP",
    "name:eng_x_preferred":[
        "Soja City"
    ],
    "name:jpn_x_preferred":[
        "\u7dcf\u793e\u5e02"
    ],
    "qs:name":"\u7dcf\u793e\u5e02",
    "qs:name_adm0":"\u65e5\u672c",
    "qs:name_adm1":"\u5ca1\u5c71\u770c",
    "qs:photos":372,
    "qs:photos_1k":75,
    "qs:photos_9k":3,
    "qs:photos_9r":5,
    "qs:photos_all":618,
    "qs:photos_sr":6,
    "qs:placetype":"Town",
    "qs:pop_sr":"0",
    "wof:name":"Soja City",
    "wof:placetype":"locality"
},
  "geometry": {"coordinates":[133.74013400000001,34.680722],"type":"Point"}
}