{
  "type": "Feature",
  "properties": {
    "gn:admin1_code":"18.0",
    "gn:admin2_code":"7383999.0",
    "gn:admin3_code":"46482.0",
    "gn:asciiname":"Otsukahara",
    "gn:country_code":"JP",
    "gn:dem":9,
    "gn:feature_class":"P",
    "gn:feature_code":"PPLL",
    "gn:name":"\u014ctsukahara",
    "gn:population":0,
    "gn:timezone":"Asia/Tokyo",
    "iso:country":"JP",
    "name:jpn_x_preferred":[
        "\u5927\u585a\u539f"
    ],
    "name:und_x_variant":[
        "\u014ctsukahara"
    ],
    "wof:name":"Otsukahara",
    "wof:placetype":"locality"
},
  "geometry": {"coordinates":[130.98537999999999,31.36487],"type":"Point"}
}