{
  "type": "Feature",
  "properties": {
    "gn:admin1_code":"38.0",
    "gn:admin2_code":"2111674.0",
    "gn:admin3_code":"9411.0",
    "gn:asciiname":"Ogawa",
    "gn:cc2":"JP",
    "gn:country_code":"JP",
    "gn:dem":113,
    "gn:feature_class":"P",
    "gn:feature_code":"PPL",
    "gn:name":"Ogawa",
    "gn:population":0,
    "gn:timezone":"Asia/Tokyo",
    "iso:country":"JP",
    "name:jpn_x_preferred":[
        "\u5c0f\u5ddd\u753a"
    ],
    "name:und_x_variant":[
        "Okawa",
        "Ogawa"
    ],
    "wof:name":"Ogawa",
    "wof:placetype":"locality"
},
  "geometry": {"coordinates":[140.13333,36.75],"type":"Point"}
}