{
  "type": "Feature",
  "properties": {
    "gn:admin1_code":"46.0",
    "gn:admin2_code":"7415908.0",
    "gn:admin3_code":"19429.0",
    "gn:asciiname":"Odawa",
    "gn:country_code":"JP",
    "gn:dem":917,
    "gn:feature_class":"P",
    "gn:feature_code":"PPL",
    "gn:name":"\u014cdawa",
    "gn:population":0,
    "gn:timezone":"Asia/Tokyo",
    "iso:country":"JP",
    "name:jpn_x_preferred":[
        "\u5927\u7530\u548c"
    ],
    "name:und_x_variant":[
        "\u014cdawa"
    ],
    "wof:name":"Odawa",
    "wof:placetype":"locality"
},
  "geometry": {"coordinates":[138.72196,35.488],"type":"Point"}
}