{
  "type": "Feature",
  "properties": {
    "gn:admin1_code":"46.0",
    "gn:admin2_code":"7415908.0",
    "gn:admin3_code":"19429.0",
    "gn:asciiname":"Odawa",
    "gn:country_code":"JP",
    "gn:dem":917,
    "gn:feature_class":"P",
    "gn:feature_code":"PPL",
    "gn:name":"\u014cdawa",
    "gn:population":0,
    "gn:timezone":"Asia/Tokyo",
    "iso:country":"JP",
    "name:ara_x_preferred":[
        "\u0623\u0648\u062a\u0627\u0648\u0627"
    ],
    "name:aze_x_preferred":[
        "Ottavalar"
    ],
    "name:bel_x_preferred":[
        "\u0410\u0442\u0430\u0432\u0430"
    ],
    "name:bul_x_preferred":[
        "\u041e\u0442\u0430\u0432\u0430"
    ],
    "name:cat_x_preferred":[
        "Ottawes"
    ],
    "name:ceb_x_preferred":[
        "Odawa"
    ],
    "name:dan_x_preferred":[
        "Odawa"
    ],
    "name:deu_x_preferred":[
        "Odawa"
    ],
    "name:epo_x_preferred":[
        "Otavoj"
    ],
    "name:fin_x_preferred":[
        "Ottawat"
    ],
    "name:fra_x_preferred":[
        "Outaouais"
    ],
    "name:glg_x_preferred":[
        "Pobo ottawa"
    ],
    "name:hrv_x_preferred":[
        "Ottawa"
    ],
    "name:hun_x_preferred":[
        "Otav\u00e1k"
    ],
    "name:ita_x_preferred":[
        "Odawa"
    ],
    "name:jpn_x_preferred":[
        "\u5927\u7530\u548c"
    ],
    "name:jpn_x_variant":[
        "\u30aa\u30bf\u30ef\u65cf"
    ],
    "name:kor_x_preferred":[
        "\uc624\ud0c0\uc640\uc871"
    ],
    "name:nld_x_preferred":[
        "Odaawaag"
    ],
    "name:nor_x_preferred":[
        "Ottawa"
    ],
    "name:pol_x_preferred":[
        "Ottawowie"
    ],
    "name:por_x_preferred":[
        "Odawa"
    ],
    "name:rus_x_preferred":[
        "\u041e\u0442\u0442\u0430\u0432\u0430"
    ],
    "name:spa_x_preferred":[
        "Ottawa"
    ],
    "name:srp_x_preferred":[
        "\u041e\u0442\u0430\u0432\u0430"
    ],
    "name:swe_x_preferred":[
        "Ottawa"
    ],
    "name:tur_x_preferred":[
        "Odavalar"
    ],
    "name:ukr_x_preferred":[
        "\u041e\u0442\u0442\u0430\u0432\u0430"
    ],
    "name:und_x_variant":[
        "\u014cdawa"
    ],
    "wof:name":"Odawa",
    "wof:placetype":"locality"
},
  "geometry": {"coordinates":[138.72196,35.488],"type":"Point"}
}