{
  "type": "Feature",
  "properties": {
    "gn:admin1_code":"21.0",
    "gn:admin2_code":"7413152.0",
    "gn:asciiname":"Matsubasemachi-toyozaki",
    "gn:country_code":"JP",
    "gn:dem":0,
    "gn:feature_class":"P",
    "gn:feature_code":"PPL",
    "gn:name":"Matsubasemachi-toyozaki",
    "gn:population":0,
    "gn:timezone":"Asia/Tokyo",
    "iso:country":"JP",
    "name:jpn_x_preferred":[
        "\u677e\u6a4b\u753a\u8c4a\u5d0e"
    ],
    "name:jpn_x_variant":[
        "\u307e\u3064\u3070\u305b\u307e\u3061\u3068\u3088\u3056\u304d",
        "\u30de\u30c4\u30d0\u30bb\u30de\u30c1\u30c8\u30e8\u30b6\u30ad"
    ],
    "wof:name":"Matsubasemachi-toyozaki",
    "wof:placetype":"locality"
},
  "geometry": {"coordinates":[130.67278000000002,32.63274000000001],"type":"Point"}
}