{
  "type": "Feature",
  "properties": {
    "gn:admin1_code":"33.0",
    "gn:admin2_code":"1850832.0",
    "gn:asciiname":"Motobe-yamanaka",
    "gn:country_code":"JP",
    "gn:dem":73,
    "gn:feature_class":"P",
    "gn:feature_code":"PPLL",
    "gn:name":"Motobe-yamanaka",
    "gn:population":0,
    "gn:timezone":"Asia/Tokyo",
    "iso:country":"JP",
    "name:jpn_x_preferred":[
        "\u672c\u90e8\u5c71\u4e2d"
    ],
    "wof:name":"Motobe-yamanaka",
    "wof:placetype":"locality"
},
  "geometry": {"coordinates":[129.97943999999998,33.24578],"type":"Point"}
}