{
  "type": "Feature",
  "properties": {
    "gn:admin1_code":"32.0",
    "gn:admin2_code":"1853897.0",
    "gn:admin3_code":"27109.0",
    "gn:asciiname":"Shinpoincho",
    "gn:country_code":"JP",
    "gn:dem":16,
    "gn:feature_class":"P",
    "gn:feature_code":"PPL",
    "gn:name":"Shinp\u014dinch\u014d",
    "gn:population":0,
    "gn:timezone":"Asia/Tokyo",
    "iso:country":"JP",
    "name:jpn_x_preferred":[
        "\u771f\u6cd5\u9662\u753a"
    ],
    "name:und_x_variant":[
        "Shinp\u014dinch\u014d"
    ],
    "wof:name":"Shinpoincho",
    "wof:placetype":"locality"
},
  "geometry": {"coordinates":[135.52116000000001,34.65704],"type":"Point"}
}