{
  "type": "Feature",
  "properties": {
    "gn:admin1_code":"2.0",
    "gn:admin2_code":"2128783.0",
    "gn:asciiname":"Tsurida",
    "gn:country_code":"JP",
    "gn:dem":65,
    "gn:feature_class":"P",
    "gn:feature_code":"PPLL",
    "gn:name":"Tsurida",
    "gn:population":0,
    "gn:timezone":"Asia/Tokyo",
    "iso:country":"JP",
    "name:jpn_x_preferred":[
        "\u91e3\u7530"
    ],
    "name:jpn_x_variant":[
        "\u3064\u308a\u3060",
        "\u30c4\u30ea\u30c0"
    ],
    "wof:name":"Tsurida",
    "wof:placetype":"locality"
},
  "geometry": {"coordinates":[140.57228000000001,40.21936],"type":"Point"}
}