{
  "type": "Feature",
  "properties": {
    "gn:admin1_code":"04",
    "gn:admin2_code":"7465521.0",
    "gn:asciiname":"Tomiuracho-haraoka",
    "gn:country_code":"JP",
    "gn:dem":8,
    "gn:feature_class":"P",
    "gn:feature_code":"PPL",
    "gn:name":"Tomiurach\u014d-haraoka",
    "gn:population":0,
    "gn:timezone":"Asia/Tokyo",
    "iso:country":"JP",
    "name:jpn_x_preferred":[
        "\u5bcc\u6d66\u753a\u539f\u5ca1"
    ],
    "name:jpn_x_variant":[
        "\u3068\u307f\u3046\u3089\u3061\u3087\u3046\u306f\u3089\u304a\u304b",
        "\u30c8\u30df\u30a6\u30e9\u30c1\u30e7\u30a6\u30cf\u30e9\u30aa\u30ab"
    ],
    "name:und_x_variant":[
        "Okamoto",
        "Haraoka",
        "Tomiurach\u014d-haraoka"
    ],
    "wof:name":"Tomiuracho-haraoka",
    "wof:placetype":"locality"
},
  "geometry": {"coordinates":[139.83611000000002,35.04468],"type":"Point"}
}