{
  "type": "Feature",
  "properties": {
    "gn:admin1_code":"34.0",
    "gn:admin2_code":"7464127.0",
    "gn:asciiname":"Suka",
    "gn:country_code":"JP",
    "gn:dem":5,
    "gn:feature_class":"P",
    "gn:feature_code":"PPL",
    "gn:name":"Suka",
    "gn:population":0,
    "gn:timezone":"Asia/Tokyo",
    "iso:country":"JP",
    "name:jpn_x_preferred":[
        "\u9808\u8cc0"
    ],
    "wof:name":"Suka",
    "wof:placetype":"locality"
},
  "geometry": {"coordinates":[139.83446000000001,35.89732],"type":"Point"}
}