{
  "type": "Feature",
  "properties": {
    "gn:admin1_code":"40.0",
    "gn:admin2_code":"1859087.0",
    "gn:asciiname":"Maeharacho",
    "gn:country_code":"JP",
    "gn:dem":54,
    "gn:feature_class":"P",
    "gn:feature_code":"PPL",
    "gn:name":"Maeharach\u014d",
    "gn:population":0,
    "gn:timezone":"Asia/Tokyo",
    "iso:country":"JP",
    "name:jpn_x_preferred":[
        "\u524d\u539f\u753a"
    ],
    "name:jpn_x_variant":[
        "\u307e\u3048\u306f\u3089\u3061\u3087\u3046",
        "\u30de\u30a8\u30cf\u30e9\u30c1\u30e7\u30a6"
    ],
    "name:und_x_variant":[
        "Maeharach\u014d"
    ],
    "wof:name":"Maeharacho",
    "wof:placetype":"locality"
},
  "geometry": {"coordinates":[139.50401000000002,35.69367000000001],"type":"Point"}
}