{
  "type": "Feature",
  "properties": {
    "gn:admin1_code":"7.0",
    "gn:admin2_code":"7407415.0",
    "gn:asciiname":"Takatamachi-shimokusuda",
    "gn:country_code":"JP",
    "gn:dem":6,
    "gn:feature_class":"P",
    "gn:feature_code":"PPL",
    "gn:name":"Takatamachi-shimokusuda",
    "gn:population":0,
    "gn:timezone":"Asia/Tokyo",
    "iso:country":"JP",
    "name:jpn_x_preferred":[
        "\u9ad8\u7530\u753a\u4e0b\u6960\u7530"
    ],
    "wof:name":"Takatamachi-shimokusuda",
    "wof:placetype":"locality"
},
  "geometry": {"coordinates":[130.46677,33.09433],"type":"Point"}
}