{
  "type": "Feature",
  "properties": {
    "iso:country":"JP",
    "label:eng_x_preferred_longname":[
        "Imizu City"
    ],
    "label:eng_x_preferred_placetype":[
        "city"
    ],
    "name:eng_x_preferred":[
        "Imizu"
    ],
    "name:eng_x_variant":[
        "Imizu City"
    ],
    "name:jpn_x_preferred":[
        "\u5c04\u6c34\u5e02"
    ],
    "qs:name":"\u5c04\u6c34\u5e02",
    "qs:name_adm0":"\u65e5\u672c",
    "qs:name_adm1":"\u5bcc\u5c71\u770c",
    "qs:photos":88,
    "qs:photos_1k":18,
    "qs:photos_9k":1,
    "qs:photos_9r":4,
    "qs:photos_all":206,
    "qs:photos_sr":3,
    "qs:placetype":"Town",
    "qs:pop_sr":"0",
    "wof:name":"Imizu",
    "wof:placetype":"locality"
},
  "geometry": {"coordinates":[137.09530599999999,36.733236],"type":"Point"}
}