{
  "type": "Feature",
  "properties": {
    "gn:admin1_code":"21.0",
    "gn:admin2_code":"7413151.0",
    "gn:asciiname":"Yamanonaka",
    "gn:country_code":"JP",
    "gn:dem":33,
    "gn:feature_class":"P",
    "gn:feature_code":"PPLL",
    "gn:name":"Yamanonaka",
    "gn:population":0,
    "gn:timezone":"Asia/Tokyo",
    "iso:country":"JP",
    "name:jpn_x_preferred":[
        "\u5c71\u306e\u4e2d"
    ],
    "name:jpn_x_variant":[
        "\u3084\u307e\u306e\u306a\u304b",
        "\u30e4\u30de\u30ce\u30ca\u30ab"
    ],
    "wof:name":"Yamanonaka",
    "wof:placetype":"locality"
},
  "geometry": {"coordinates":[130.44441,32.50935],"type":"Point"}
}