{
  "type": "Feature",
  "properties": {
    "gn:admin1_code":"3.0",
    "gn:admin2_code":"2127674.0",
    "gn:asciiname":"Senritai",
    "gn:country_code":"JP",
    "gn:dem":78,
    "gn:feature_class":"P",
    "gn:feature_code":"PPL",
    "gn:name":"Senritai",
    "gn:population":0,
    "gn:timezone":"Asia/Tokyo",
    "iso:country":"JP",
    "name:jpn_x_preferred":[
        "\u5343\u91cc\u5e73"
    ],
    "name:jpn_x_variant":[
        "\u305b\u3093\u308a\u305f\u3044",
        "\u30bb\u30f3\u30ea\u30bf\u30a4"
    ],
    "wof:name":"Senritai",
    "wof:placetype":"locality"
},
  "geometry": {"coordinates":[141.23439999999999,40.64852],"type":"Point"}
}