{
  "type": "Feature",
  "properties": {
    "gn:admin1_code":"3.0",
    "gn:admin2_code":"2128302.0",
    "gn:admin3_code":"2445.0",
    "gn:asciiname":"Furumaki",
    "gn:country_code":"JP",
    "gn:dem":166,
    "gn:feature_class":"P",
    "gn:feature_code":"PPL",
    "gn:name":"Furumaki",
    "gn:population":0,
    "gn:timezone":"Asia/Tokyo",
    "iso:country":"JP",
    "name:jpn_x_preferred":[
        "\u53e4\u7267"
    ],
    "name:jpn_x_variant":[
        "\u3075\u308b\u307e\u304d",
        "\u30d5\u30eb\u30de\u30ad"
    ],
    "wof:name":"Furumaki",
    "wof:placetype":"locality"
},
  "geometry": {"coordinates":[141.23713999999995,40.41386],"type":"Point"}
}