{
  "type": "Feature",
  "properties": {
    "gn:admin1_code":"37.0",
    "gn:admin2_code":"1851401.0",
    "gn:admin3_code":"22344.0",
    "gn:asciiname":"Mukokuwagi",
    "gn:country_code":"JP",
    "gn:dem":386,
    "gn:feature_class":"P",
    "gn:feature_code":"PPLL",
    "gn:name":"Muk\u014dkuwagi",
    "gn:population":0,
    "gn:timezone":"Asia/Tokyo",
    "iso:country":"JP",
    "name:jpn_x_preferred":[
        "\u5411\u6851\u6728"
    ],
    "name:und_x_variant":[
        "Muk\u014dkuwagi"
    ],
    "wof:name":"Mukokuwagi",
    "wof:placetype":"locality"
},
  "geometry": {"coordinates":[138.97866999999999,35.31609],"type":"Point"}
}