{
  "type": "Feature",
  "properties": {
    "gn:admin1_code":"21.0",
    "gn:admin2_code":"7412705.0",
    "gn:admin3_code":"43484.0",
    "gn:asciiname":"Nagahama",
    "gn:country_code":"JP",
    "gn:dem":6,
    "gn:feature_class":"P",
    "gn:feature_code":"PPLL",
    "gn:name":"Nagahama",
    "gn:population":0,
    "gn:timezone":"Asia/Tokyo",
    "iso:country":"JP",
    "name:ceb_x_preferred":[
        "Nagahama"
    ],
    "name:ces_x_preferred":[
        "Nagahama"
    ],
    "name:deu_x_preferred":[
        "Nagahama"
    ],
    "name:jpn_x_preferred":[
        "\u9577\u6d5c"
    ],
    "name:jpn_x_variant":[
        "\u306a\u304c\u306f\u307e",
        "\u30ca\u30ac\u30cf\u30de"
    ],
    "name:mlg_x_preferred":[
        "Nagahama"
    ],
    "wof:name":"Nagahama",
    "wof:placetype":"locality"
},
  "geometry": {"coordinates":[130.45538999999999,32.28913],"type":"Point"}
}