{
  "type": "Feature",
  "properties": {
    "gn:admin1_code":"19.0",
    "gn:admin2_code":"1859635.0",
    "gn:admin3_code":"14137.0",
    "gn:asciiname":"Shimoasao",
    "gn:country_code":"JP",
    "gn:dem":39,
    "gn:feature_class":"P",
    "gn:feature_code":"PPL",
    "gn:name":"Shimoasao",
    "gn:population":0,
    "gn:timezone":"Asia/Tokyo",
    "iso:country":"JP",
    "name:jpn_x_preferred":[
        "\u4e0b\u9ebb\u751f"
    ],
    "wof:name":"Shimoasao",
    "wof:placetype":"locality"
},
  "geometry": {"coordinates":[139.50675000000001,35.58076],"type":"Point"}
}