{
  "type": "Feature",
  "properties": {
    "gn:admin1_code":"07",
    "gn:admin2_code":"1863955.0",
    "gn:admin3_code":"40137.0",
    "gn:asciiname":"Magaribuchi",
    "gn:country_code":"JP",
    "gn:dem":277,
    "gn:feature_class":"P",
    "gn:feature_code":"PPL",
    "gn:name":"Magaribuchi",
    "gn:population":0,
    "gn:timezone":"Asia/Tokyo",
    "iso:country":"JP",
    "name:jpn_x_preferred":[
        "\u66f2\u6e15"
    ],
    "name:und_x_variant":[
        "Magaributchi",
        "Magarifuchi"
    ],
    "wof:name":"Magaribuchi",
    "wof:placetype":"locality"
},
  "geometry": {"coordinates":[130.30168999999998,33.49301],"type":"Point"}
}