{
  "type": "Feature",
  "properties": {
    "gn:admin1_code":"4.0",
    "gn:admin2_code":"2112386.0",
    "gn:asciiname":"Kominato",
    "gn:country_code":"JP",
    "gn:dem":75,
    "gn:feature_class":"P",
    "gn:feature_code":"PPL",
    "gn:name":"Kominato",
    "gn:population":0,
    "gn:timezone":"Asia/Tokyo",
    "iso:country":"JP",
    "name:jpn_x_preferred":[
        "\u5c0f\u6e4a"
    ],
    "name:jpn_x_variant":[
        "\u3053\u307f\u306a\u3068",
        "\u30b3\u30df\u30ca\u30c8"
    ],
    "wof:name":"Kominato",
    "wof:placetype":"locality"
},
  "geometry": {"coordinates":[140.20203999999998,35.12439000000001],"type":"Point"}
}