{
  "type": "Feature",
  "properties": {
    "gn:admin1_code":"3.0",
    "gn:admin2_code":"2127674.0",
    "gn:asciiname":"Shichigo",
    "gn:country_code":"JP",
    "gn:dem":71,
    "gn:feature_class":"P",
    "gn:feature_code":"PPL",
    "gn:name":"Shichig\u014d",
    "gn:population":0,
    "gn:timezone":"Asia/Tokyo",
    "iso:country":"JP",
    "name:jpn_x_preferred":[
        "\u4e03\u90f7"
    ],
    "name:jpn_x_variant":[
        "\u3057\u3061\u3054\u3046",
        "\u30b7\u30c1\u30b4\u30a6"
    ],
    "name:und_x_variant":[
        "Shichig\u014d"
    ],
    "wof:name":"Shichigo",
    "wof:placetype":"locality"
},
  "geometry": {"coordinates":[141.19128000000001,40.63171],"type":"Point"}
}