{
  "type": "Feature",
  "properties": {
    "gn:admin1_code":"7.0",
    "gn:admin2_code":"1860814.0",
    "gn:admin3_code":"40421.0",
    "gn:asciiname":"Haji-ni",
    "gn:country_code":"JP",
    "gn:dem":36,
    "gn:feature_class":"P",
    "gn:feature_code":"PPLL",
    "gn:name":"Haji-ni",
    "gn:population":0,
    "gn:timezone":"Asia/Tokyo",
    "iso:country":"JP",
    "name:jpn_x_preferred":[
        "\u571f\u5e2b\u4e8c"
    ],
    "wof:name":"Haji-ni",
    "wof:placetype":"locality"
},
  "geometry": {"coordinates":[130.67965000000001,33.57726],"type":"Point"}
}