{
  "type": "Feature",
  "properties": {
    "gn:admin1_code":"21.0",
    "gn:admin2_code":"7412708.0",
    "gn:admin3_code":"43511.0",
    "gn:asciiname":"Azami",
    "gn:country_code":"JP",
    "gn:dem":653,
    "gn:feature_class":"P",
    "gn:feature_code":"PPLL",
    "gn:name":"Azami",
    "gn:population":0,
    "gn:timezone":"Asia/Tokyo",
    "iso:country":"JP",
    "name:jpn_x_preferred":[
        "\u6d45\u898b"
    ],
    "name:jpn_x_variant":[
        "\u3042\u3056\u307f",
        "\u30a2\u30b6\u30df"
    ],
    "wof:name":"Azami",
    "wof:placetype":"locality"
},
  "geometry": {"coordinates":[130.75382999999999,32.43584],"type":"Point"}
}