{
  "type": "Feature",
  "properties": {
    "gn:admin1_code":"16.0",
    "gn:admin2_code":"2112822.0",
    "gn:asciiname":"Yonekura",
    "gn:country_code":"JP",
    "gn:dem":96,
    "gn:feature_class":"P",
    "gn:feature_code":"PPL",
    "gn:name":"Yonekura",
    "gn:population":0,
    "gn:timezone":"Asia/Tokyo",
    "iso:country":"JP",
    "name:jpn_x_preferred":[
        "\u7c73\u5009"
    ],
    "name:jpn_x_variant":[
        "\u3088\u306d\u304f\u3089",
        "\u30e8\u30cd\u30af\u30e9"
    ],
    "wof:name":"Yonekura",
    "wof:placetype":"locality"
},
  "geometry": {"coordinates":[141.084,39.3819],"type":"Point"}
}