{
  "type": "Feature",
  "properties": {
    "iso:country":"JP",
    "name:eng_x_preferred":[
        "Yukawa 1 Chome"
    ],
    "name:eng_x_variant":[
        "Yukawa 1 Choume",
        "Yukawa 1 Chome"
    ],
    "name:jpn_x_preferred":[
        "\uff11\u4e01\u76ee"
    ],
    "name:jpn_x_variant":[
        "\u3086\u304b\u308f \uff11\u3061\u3087\u3046\u3081",
        "\u6e6f\u5ddd \uff11\u4e01\u76ee",
        "\uff11\u3061\u3087\u3046\u3081"
    ],
    "qs:gn_local":0,
    "qs:local_max":488,
    "qs:local_sum":1345,
    "qs:localhoods":6,
    "qs:name":"\uff11\u4e01\u76ee",
    "qs:name_adm0":"\u65e5\u672c",
    "qs:name_adm1":"\u9759\u5ca1\u770c",
    "qs:name_en":"Yukawa 1 Chome",
    "qs:name_lau":"\u6e6f\u5ddd",
    "qs:name_local":"\u4f0a\u6771\u5e02",
    "qs:photo_max":45,
    "qs:photo_sum":63,
    "qs:placetype":"Suburb",
    "qs:quad_count":3,
    "qs:woe_adm0":23424856,
    "qs:woe_adm1":2345886,
    "qs:woe_adm2":0,
    "qs:woe_lau":28437543,
    "qs:woe_local":1117332,
    "qs:woe_ver":"7.10.0",
    "wof:lang":[
        "jpn"
    ],
    "wof:name":"\uff11\u4e01\u76ee",
    "wof:placetype":"neighbourhood"
},
  "geometry": {"coordinates":[139.09181599999999,34.975111],"type":"Point"}
}