{
  "type": "Feature",
  "properties": {
    "gn:admin1_code":"15.0",
    "gn:admin2_code":"7467839.0",
    "gn:admin3_code":"17463.0",
    "gn:asciiname":"Kurogawa",
    "gn:country_code":"JP",
    "gn:dem":127,
    "gn:feature_class":"P",
    "gn:feature_code":"PPL",
    "gn:name":"Kurogawa",
    "gn:population":0,
    "gn:timezone":"Asia/Tokyo",
    "iso:country":"JP",
    "name:jpn_x_preferred":[
        "\u9ed2\u5ddd"
    ],
    "wof:name":"Kurogawa",
    "wof:placetype":"locality"
},
  "geometry": {"coordinates":[137.04003,37.36371],"type":"Point"}
}