{
  "type": "Feature",
  "properties": {
    "gn:admin1_code":"7.0",
    "gn:admin2_code":"1854385.0",
    "gn:asciiname":"Onoshima",
    "gn:country_code":"JP",
    "gn:dem":1,
    "gn:feature_class":"P",
    "gn:feature_code":"PPL",
    "gn:name":"\u014cnoshima",
    "gn:population":0,
    "gn:timezone":"Asia/Tokyo",
    "iso:country":"JP",
    "name:jpn_x_preferred":[
        "\u5927\u91ce\u5cf6"
    ],
    "name:und_x_variant":[
        "\u014cnoshima"
    ],
    "wof:name":"Onoshima",
    "wof:placetype":"locality"
},
  "geometry": {"coordinates":[130.34904,33.19823],"type":"Point"}
}