{
  "type": "Feature",
  "properties": {
    "gn:admin1_code":"2.0",
    "gn:admin2_code":"2129594.0",
    "gn:admin3_code":"5303.0",
    "gn:asciiname":"Kamikosaka",
    "gn:country_code":"JP",
    "gn:dem":166,
    "gn:feature_class":"P",
    "gn:feature_code":"PPLL",
    "gn:name":"Kamikosaka",
    "gn:population":0,
    "gn:timezone":"Asia/Tokyo",
    "iso:country":"JP",
    "name:jpn_x_preferred":[
        "\u4e0a\u5c0f\u5742"
    ],
    "name:jpn_x_variant":[
        "\u304b\u307f\u3053\u3055\u304b",
        "\u30ab\u30df\u30b3\u30b5\u30ab"
    ],
    "wof:name":"Kamikosaka",
    "wof:placetype":"locality"
},
  "geometry": {"coordinates":[140.73925,40.32688],"type":"Point"}
}