{
  "type": "Feature",
  "properties": {
    "gn:admin1_code":"12.0",
    "gn:admin2_code":"2129373.0",
    "gn:admin3_code":"1661.0",
    "gn:asciiname":"Takkobu",
    "gn:country_code":"JP",
    "gn:dem":19,
    "gn:feature_class":"P",
    "gn:feature_code":"PPL",
    "gn:name":"Takkobu",
    "gn:population":0,
    "gn:timezone":"Asia/Tokyo",
    "iso:country":"JP",
    "name:jpn_x_preferred":[
        "\u9054\u53e4\u6b66"
    ],
    "name:jpn_x_variant":[
        "\u305f\u3063\u3053\u3076",
        "\u30bf\u30c3\u30b3\u30d6"
    ],
    "name:und_x_variant":[
        "Enkomu",
        "Tatsukobu",
        "Tatsukomu",
        "Takkomu",
        "Takkobu"
    ],
    "wof:name":"Takkobu",
    "wof:placetype":"locality"
},
  "geometry": {"coordinates":[144.50393,43.09263],"type":"Point"}
}