{
  "type": "Feature",
  "properties": {
    "gn:admin1_code":"8.0",
    "gn:admin2_code":"2112139.0",
    "gn:asciiname":"Nakahama",
    "gn:country_code":"JP",
    "gn:dem":517,
    "gn:feature_class":"P",
    "gn:feature_code":"PPLL",
    "gn:name":"Nakahama",
    "gn:population":0,
    "gn:timezone":"Asia/Tokyo",
    "iso:country":"JP",
    "name:jpn_x_preferred":[
        "\u4e2d\u6d5c"
    ],
    "wof:name":"Nakahama",
    "wof:placetype":"locality"
},
  "geometry": {"coordinates":[140.08484000000001,37.41892],"type":"Point"}
}