{
  "type": "Feature",
  "properties": {
    "gn:admin1_code":"8.0",
    "gn:admin2_code":"7451504.0",
    "gn:admin3_code":"7447.0",
    "gn:asciiname":"Fukunaga",
    "gn:country_code":"JP",
    "gn:dem":245,
    "gn:feature_class":"P",
    "gn:feature_code":"PPLL",
    "gn:name":"Fukunaga",
    "gn:population":0,
    "gn:timezone":"Asia/Tokyo",
    "iso:country":"JP",
    "name:jpn_x_preferred":[
        "\u798f\u6c38"
    ],
    "name:rus_x_preferred":[
        "\u0424\u0443\u043a\u0443\u043d\u0430\u0433\u0430"
    ],
    "wof:name":"Fukunaga",
    "wof:placetype":"locality"
},
  "geometry": {"coordinates":[139.8828,37.42811],"type":"Point"}
}