{
  "type": "Feature",
  "properties": {
    "gn:admin1_code":"21.0",
    "gn:admin2_code":"1848443.0",
    "gn:admin3_code":"43468.0",
    "gn:asciiname":"Tategami",
    "gn:country_code":"JP",
    "gn:dem":57,
    "gn:feature_class":"P",
    "gn:feature_code":"PPL",
    "gn:name":"Tategami",
    "gn:population":0,
    "gn:timezone":"Asia/Tokyo",
    "iso:country":"JP",
    "name:jpn_x_preferred":[
        "\u7acb\u795e"
    ],
    "name:jpn_x_variant":[
        "\u305f\u3066\u304c\u307f",
        "\u30bf\u30c6\u30ac\u30df"
    ],
    "wof:name":"Tategami",
    "wof:placetype":"locality"
},
  "geometry": {"coordinates":[130.69967,32.55155],"type":"Point"}
}