{
  "type": "Feature",
  "properties": {
    "gn:admin1_code":"21.0",
    "gn:admin2_code":"7412709.0",
    "gn:admin3_code":"43348.0",
    "gn:asciiname":"Shidonbaru",
    "gn:country_code":"JP",
    "gn:dem":186,
    "gn:feature_class":"P",
    "gn:feature_code":"PPLL",
    "gn:name":"Shidonbaru",
    "gn:population":0,
    "gn:timezone":"Asia/Tokyo",
    "iso:country":"JP",
    "name:jpn_x_preferred":[
        "\u5fd7\u9053\u539f"
    ],
    "name:jpn_x_variant":[
        "\u3057\u3069\u3093\u3070\u308b",
        "\u30b7\u30c9\u30f3\u30d0\u30eb"
    ],
    "wof:name":"Shidonbaru",
    "wof:placetype":"locality"
},
  "geometry": {"coordinates":[130.88826,32.62116],"type":"Point"}
}