{
  "type": "Feature",
  "properties": {
    "gn:admin1_code":"17",
    "gn:admin2_code":"1855768.0",
    "gn:admin3_code":"37406.0",
    "gn:asciiname":"Yamawaki",
    "gn:country_code":"JP",
    "gn:dem":136,
    "gn:feature_class":"P",
    "gn:feature_code":"PPL",
    "gn:name":"Yamawaki",
    "gn:population":0,
    "gn:timezone":"Asia/Tokyo",
    "iso:country":"JP",
    "name:jpn_x_preferred":[
        "\u5c71\u8107"
    ],
    "wof:name":"Yamawaki",
    "wof:placetype":"locality"
},
  "geometry": {"coordinates":[133.81882999999999,34.12195999999999],"type":"Point"}
}