{
  "type": "Feature",
  "properties": {
    "gn:admin1_code":"40.0",
    "gn:admin2_code":"1858665.0",
    "gn:asciiname":"Fuyuki",
    "gn:country_code":"JP",
    "gn:dem":5,
    "gn:feature_class":"P",
    "gn:feature_code":"PPL",
    "gn:name":"Fuyuki",
    "gn:population":0,
    "gn:timezone":"Asia/Tokyo",
    "iso:country":"JP",
    "name:jpn_x_preferred":[
        "\u51ac\u6728"
    ],
    "name:kor_x_preferred":[
        "\ub098\uc4f0\ubbf8"
    ],
    "wof:name":"Fuyuki",
    "wof:placetype":"locality"
},
  "geometry": {"coordinates":[139.80133999999998,35.67423],"type":"Point"}
}