{
  "type": "Feature",
  "properties": {
    "gn:admin1_code":"29.0",
    "gn:admin2_code":"1853313.0",
    "gn:asciiname":"Mitate",
    "gn:country_code":"JP",
    "gn:dem":46,
    "gn:feature_class":"P",
    "gn:feature_code":"PPL",
    "gn:name":"Mitate",
    "gn:population":0,
    "gn:timezone":"Asia/Tokyo",
    "iso:country":"JP",
    "name:jpn_x_preferred":[
        "\u898b\u7acb"
    ],
    "wof:name":"Mitate",
    "wof:placetype":"locality"
},
  "geometry": {"coordinates":[138.50766999999999,38.29034],"type":"Point"}
}