{
  "type": "Feature",
  "properties": {
    "gn:admin1_code":"27.0",
    "gn:admin2_code":"1862734.0",
    "gn:admin3_code":"42323.0",
    "gn:asciiname":"Murakigo",
    "gn:country_code":"JP",
    "gn:dem":42,
    "gn:feature_class":"P",
    "gn:feature_code":"PPL",
    "gn:name":"Murakig\u014d",
    "gn:population":0,
    "gn:timezone":"Asia/Tokyo",
    "iso:country":"JP",
    "name:jpn_x_preferred":[
        "\u6751\u6728\u90f7"
    ],
    "name:und_x_variant":[
        "Murakig\u014d"
    ],
    "wof:name":"Murakigo",
    "wof:placetype":"locality"
},
  "geometry": {"coordinates":[129.87738000000002,33.14543],"type":"Point"}
}