{
  "type": "Feature",
  "properties": {
    "iso:country":"JP",
    "name:eng_x_preferred":[
        "Shinkoiwa 1 Chome"
    ],
    "name:eng_x_variant":[
        "Shinkoiwa 1 Choume",
        "Shinkoiwa 1 Chome"
    ],
    "name:jpn_x_preferred":[
        "\uff11\u4e01\u76ee"
    ],
    "name:jpn_x_variant":[
        "\u3057\u3093\u3053\u3044\u308f \uff11\u3061\u3087\u3046\u3081",
        "\u65b0\u5c0f\u5ca9 \uff11\u4e01\u76ee",
        "\uff11\u3061\u3087\u3046\u3081"
    ],
    "qs:gn_adm0_cc":"JP",
    "qs:gn_local":1850147,
    "qs:local_max":18112,
    "qs:local_sum":895907,
    "qs:localhoods":857,
    "qs:name":"\uff11\u4e01\u76ee",
    "qs:name_adm0":"\u65e5\u672c",
    "qs:name_adm1":"\u6771\u4eac\u90fd",
    "qs:name_adm2":"\u845b\u98fe\u533a",
    "qs:name_en":"Shinkoiwa 1 Chome",
    "qs:name_lau":"\u65b0\u5c0f\u5ca9",
    "qs:name_local":"\u6771\u4eac",
    "qs:photo_max":43,
    "qs:photo_sum":106,
    "qs:placetype":"Suburb",
    "qs:quad_count":5,
    "qs:woe_adm0":23424856,
    "qs:woe_adm1":2345889,
    "qs:woe_adm2":15015375,
    "qs:woe_lau":28414722,
    "qs:woe_local":1118370,
    "qs:woe_ver":"7.10.0",
    "wof:lang":[
        "jpn"
    ],
    "wof:name":"\uff11\u4e01\u76ee",
    "wof:placetype":"neighbourhood"
},
  "geometry": {"coordinates":[139.85929999999999,35.715699],"type":"Point"}
}