{
  "type": "Feature",
  "properties": {
    "gn:admin1_code":"7.0",
    "gn:admin2_code":"7407412.0",
    "gn:asciiname":"Hanaminosato",
    "gn:country_code":"JP",
    "gn:dem":10,
    "gn:feature_class":"P",
    "gn:feature_code":"PPL",
    "gn:name":"Hanaminosato",
    "gn:population":0,
    "gn:timezone":"Asia/Tokyo",
    "iso:country":"JP",
    "name:jpn_x_preferred":[
        "\u82b1\u898b\u306e\u91cc"
    ],
    "wof:name":"Hanaminosato",
    "wof:placetype":"locality"
},
  "geometry": {"coordinates":[130.47242,33.75421],"type":"Point"}
}