{
  "type": "Feature",
  "properties": {
    "gn:admin1_code":"34.0",
    "gn:admin2_code":"8304214.0",
    "gn:asciiname":"Azeyoshi",
    "gn:country_code":"JP",
    "gn:dem":18,
    "gn:feature_class":"P",
    "gn:feature_code":"PPL",
    "gn:name":"Azeyoshi",
    "gn:population":0,
    "gn:timezone":"Asia/Tokyo",
    "iso:country":"JP",
    "name:jpn_x_preferred":[
        "\u7554\u5409"
    ],
    "name:jpn_x_variant":[
        "\u3042\u305c\u3088\u3057",
        "\u30a2\u30bc\u30e8\u30b7"
    ],
    "wof:name":"Azeyoshi",
    "wof:placetype":"locality"
},
  "geometry": {"coordinates":[139.54587000000001,35.96378],"type":"Point"}
}