{
  "type": "Feature",
  "properties": {
    "gn:admin1_code":"21.0",
    "gn:admin2_code":"1850744.0",
    "gn:admin3_code":"43369.0",
    "gn:asciiname":"Kobaru",
    "gn:country_code":"JP",
    "gn:dem":42,
    "gn:feature_class":"P",
    "gn:feature_code":"PPLL",
    "gn:name":"Kobaru",
    "gn:population":0,
    "gn:timezone":"Asia/Tokyo",
    "iso:country":"JP",
    "name:jpn_x_preferred":[
        "\u5c0f\u539f"
    ],
    "name:jpn_x_variant":[
        "\u3053\u3070\u308b",
        "\u30b3\u30d0\u30eb"
    ],
    "wof:name":"Kobaru",
    "wof:placetype":"locality"
},
  "geometry": {"coordinates":[130.61868999999999,33.06153],"type":"Point"}
}