{
  "type": "Feature",
  "properties": {
    "gn:admin1_code":"16.0",
    "gn:admin2_code":"2128940.0",
    "gn:asciiname":"Yotsuyaku",
    "gn:country_code":"JP",
    "gn:dem":255,
    "gn:feature_class":"P",
    "gn:feature_code":"PPL",
    "gn:name":"Yotsuyaku",
    "gn:population":0,
    "gn:timezone":"Asia/Tokyo",
    "iso:country":"JP",
    "name:jpn_x_preferred":[
        "\u56db\u30c3\u5f79"
    ],
    "name:jpn_x_variant":[
        "\u3088\u3064\u3084\u304f",
        "\u30e8\u30c4\u30e4\u30af"
    ],
    "wof:name":"Yotsuyaku",
    "wof:placetype":"locality"
},
  "geometry": {"coordinates":[141.33799999999999,40.24641],"type":"Point"}
}