{
  "type": "Feature",
  "properties": {
    "gn:admin1_code":"34.0",
    "gn:admin2_code":"1859739.0",
    "gn:asciiname":"Terai",
    "gn:country_code":"JP",
    "gn:dem":10,
    "gn:feature_class":"P",
    "gn:feature_code":"PPL",
    "gn:name":"Terai",
    "gn:population":0,
    "gn:timezone":"Asia/Tokyo",
    "iso:country":"JP",
    "name:jpn_x_preferred":[
        "\u5bfa\u4e95"
    ],
    "wof:name":"Terai",
    "wof:placetype":"locality"
},
  "geometry": {"coordinates":[139.50688,35.93429000000001],"type":"Point"}
}