{
  "type": "Feature",
  "properties": {
    "iso:country":"JP",
    "qs:name":"\u4e03\u5b97\u753a",
    "qs:name_adm0":"\u65e5\u672c",
    "qs:name_adm1":"\u5c90\u961c\u770c",
    "qs:photos":29,
    "qs:photos_1k":6,
    "qs:photos_9k":1,
    "qs:photos_9r":2,
    "qs:photos_all":29,
    "qs:photos_sr":2,
    "qs:placetype":"Town",
    "qs:pop_sr":"0",
    "wof:name":"\u4e03\u5b97\u753a",
    "wof:placetype":"locality"
},
  "geometry": {"coordinates":[137.125382,35.541359],"type":"Point"}
}