{
  "type": "Feature",
  "properties": {
    "gn:admin1_code":"12.0",
    "gn:admin2_code":"7428084.0",
    "gn:admin3_code":"1609.0",
    "gn:asciiname":"Kamichikaura",
    "gn:country_code":"JP",
    "gn:dem":6,
    "gn:feature_class":"P",
    "gn:feature_code":"PPLL",
    "gn:name":"Kamichikaura",
    "gn:population":0,
    "gn:timezone":"Asia/Tokyo",
    "iso:country":"JP",
    "name:jpn_x_preferred":[
        "\u4e0a\u8fd1\u6d66"
    ],
    "name:jpn_x_variant":[
        "\u304b\u307f\u3061\u304b\u3046\u3089",
        "\u30ab\u30df\u30c1\u30ab\u30a6\u30e9"
    ],
    "wof:name":"Kamichikaura",
    "wof:placetype":"locality"
},
  "geometry": {"coordinates":[143.07220000000001,42.06062],"type":"Point"}
}