{
  "type": "Feature",
  "properties": {
    "gn:admin1_code":"4.0",
    "gn:admin2_code":"2112997.0",
    "gn:admin3_code":"12426.0",
    "gn:asciiname":"Inatsuka",
    "gn:country_code":"JP",
    "gn:dem":45,
    "gn:feature_class":"P",
    "gn:feature_code":"PPL",
    "gn:name":"Inatsuka",
    "gn:population":0,
    "gn:timezone":"Asia/Tokyo",
    "iso:country":"JP",
    "name:jpn_x_preferred":[
        "\u7a32\u585a"
    ],
    "name:jpn_x_variant":[
        "\u3044\u306a\u3064\u304b",
        "\u30a4\u30ca\u30c4\u30ab"
    ],
    "wof:name":"Inatsuka",
    "wof:placetype":"locality"
},
  "geometry": {"coordinates":[140.19297,35.43202],"type":"Point"}
}