{
  "type": "Feature",
  "properties": {
    "gn:admin1_code":"21.0",
    "gn:admin2_code":"7413152.0",
    "gn:asciiname":"Ogawamachi-gonoe",
    "gn:country_code":"JP",
    "gn:dem":1,
    "gn:feature_class":"P",
    "gn:feature_code":"PPL",
    "gn:name":"Ogawamachi-g\u014dnoe",
    "gn:population":0,
    "gn:timezone":"Asia/Tokyo",
    "iso:country":"JP",
    "name:jpn_x_preferred":[
        "\u5c0f\u5ddd\u753a\u6cb3\u6c5f"
    ],
    "name:jpn_x_variant":[
        "\u304a\u304c\u308f\u307e\u3061\u3054\u3046\u306e\u3048",
        "\u30aa\u30ac\u30ef\u30de\u30c1\u30b4\u30a6\u30ce\u30a8"
    ],
    "name:und_x_variant":[
        "Ogawamachi-g\u014dnoe"
    ],
    "wof:name":"Ogawamachi-gonoe",
    "wof:placetype":"locality"
},
  "geometry": {"coordinates":[130.70824999999999,32.60484],"type":"Point"}
}