{
  "type": "Feature",
  "properties": {
    "gn:admin1_code":"19",
    "gn:admin2_code":"1853293.0",
    "gn:admin3_code":"14151.0",
    "gn:asciiname":"Nemoro",
    "gn:country_code":"JP",
    "gn:dem":202,
    "gn:feature_class":"P",
    "gn:feature_code":"PPL",
    "gn:name":"Nemoro",
    "gn:population":0,
    "gn:timezone":"Asia/Tokyo",
    "iso:country":"JP",
    "wof:name":"Nemoro",
    "wof:placetype":"locality"
},
  "geometry": {"coordinates":[139.27083000000002,35.57417],"type":"Point"}
}