{
  "type": "Feature",
  "properties": {
    "gn:admin1_code":"21.0",
    "gn:admin2_code":"1865358.0",
    "gn:asciiname":"Nakadake",
    "gn:country_code":"JP",
    "gn:dem":152,
    "gn:feature_class":"P",
    "gn:feature_code":"PPLL",
    "gn:name":"Nakadake",
    "gn:population":0,
    "gn:timezone":"Asia/Tokyo",
    "iso:country":"JP",
    "name:jpn_x_preferred":[
        "\u4e2d\u5cb3"
    ],
    "name:jpn_x_variant":[
        "\u306a\u304b\u3060\u3051",
        "\u30ca\u30ab\u30c0\u30b1"
    ],
    "wof:name":"Nakadake",
    "wof:placetype":"locality"
},
  "geometry": {"coordinates":[130.12967,32.36704],"type":"Point"}
}