{
  "type": "Feature",
  "properties": {
    "gn:admin1_code":"26",
    "gn:admin2_code":"1852309.0",
    "gn:admin3_code":"20407.0",
    "gn:asciiname":"Kami-seinaiji",
    "gn:country_code":"JP",
    "gn:dem":882,
    "gn:feature_class":"P",
    "gn:feature_code":"PPL",
    "gn:name":"Kami-seinaiji",
    "gn:population":0,
    "gn:timezone":"Asia/Tokyo",
    "iso:country":"JP",
    "wof:name":"Kami-seinaiji",
    "wof:placetype":"locality"
},
  "geometry": {"coordinates":[137.68152000000001,35.50428],"type":"Point"}
}