{
  "type": "Feature",
  "properties": {
    "gn:admin1_code":"16.0",
    "gn:admin2_code":"2111528.0",
    "gn:asciiname":"Nagasaki",
    "gn:country_code":"JP",
    "gn:dem":27,
    "gn:feature_class":"P",
    "gn:feature_code":"PPL",
    "gn:name":"Nagasaki",
    "gn:population":0,
    "gn:timezone":"Asia/Tokyo",
    "iso:country":"JP",
    "wof:name":"Nagasaki",
    "wof:placetype":"locality"
},
  "geometry": {"coordinates":[141.7509,39.02166],"type":"Point"}
}