{
  "type": "Feature",
  "properties": {
    "gn:admin1_code":"12.0",
    "gn:asciiname":"Ofukeshi",
    "gn:cc2":"JP",
    "gn:country_code":"JP",
    "gn:dem":1,
    "gn:feature_class":"P",
    "gn:feature_code":"PPL",
    "gn:name":"Ofukeshi",
    "gn:population":0,
    "gn:timezone":"Asia/Tokyo",
    "iso:country":"JP",
    "name:und_x_variant":[
        "\u014cgishi",
        "Ohukesi",
        "Ofukeshi"
    ],
    "wof:name":"Ofukeshi",
    "wof:placetype":"locality"
},
  "geometry": {"coordinates":[140.63333,42.58333],"type":"Point"}
}