{
  "type": "Feature",
  "properties": {
    "gn:admin1_code":"28.0",
    "gn:admin2_code":"1848592.0",
    "gn:asciiname":"Onaka",
    "gn:country_code":"JP",
    "gn:dem":61,
    "gn:feature_class":"P",
    "gn:feature_code":"PPL",
    "gn:name":"\u014cnaka",
    "gn:population":0,
    "gn:timezone":"Asia/Tokyo",
    "iso:country":"JP",
    "name:jpn_x_preferred":[
        "\u5927\u4e2d"
    ],
    "name:swe_x_preferred":[
        "Onaka"
    ],
    "name:und_x_variant":[
        "\u014cnaka"
    ],
    "wof:name":"Onaka",
    "wof:placetype":"locality"
},
  "geometry": {"coordinates":[135.73626999999999,34.51351],"type":"Point"}
}