{
  "type": "Feature",
  "properties": {
    "iso:country":"JP",
    "name:eng_x_preferred":[
        "Kannonmachi 3 Chome"
    ],
    "name:eng_x_variant":[
        "Kannonmachi 3 Choume",
        "Kannonmachi 3 Chome"
    ],
    "name:jpn_x_preferred":[
        "\uff13\u4e01\u76ee"
    ],
    "name:jpn_x_variant":[
        "\u304b\u3093\u306e\u3093\u307e\u3061 \uff13\u3061\u3087\u3046\u3081",
        "\u89b3\u97f3\u753a \uff13\u4e01\u76ee",
        "\uff13\u3061\u3087\u3046\u3081"
    ],
    "qs:gn_adm0_cc":"JP",
    "qs:gn_local":1860243,
    "qs:gn_nam_loc":"\u91d1\u6ca2\u5e02, \u77f3\u5ddd\u770c, JP",
    "qs:gn_namadm1":"15",
    "qs:local_max":2809,
    "qs:local_sum":12445,
    "qs:localhoods":25,
    "qs:name":"\uff13\u4e01\u76ee",
    "qs:name_adm0":"\u65e5\u672c",
    "qs:name_adm1":"\u77f3\u5ddd\u770c",
    "qs:name_en":"Kannonmachi 3 Chome",
    "qs:name_lau":"\u89b3\u97f3\u753a",
    "qs:name_local":"\u91d1\u6ca2\u5e02",
    "qs:photo_max":3,
    "qs:photo_sum":6,
    "qs:placetype":"Suburb",
    "qs:quad_count":3,
    "qs:woe_adm0":23424856,
    "qs:woe_adm1":2345864,
    "qs:woe_adm2":0,
    "qs:woe_lau":28425932,
    "qs:woe_local":1117438,
    "qs:woe_ver":"7.10.0",
    "wof:lang":[
        "jpn"
    ],
    "wof:name":"\uff13\u4e01\u76ee",
    "wof:placetype":"neighbourhood"
},
  "geometry": {"coordinates":[136.677246,36.571425],"type":"Point"}
}