{
  "type": "Feature",
  "properties": {
    "gn:admin1_code":"6.0",
    "gn:admin2_code":"7467385.0",
    "gn:asciiname":"Nunome",
    "gn:country_code":"JP",
    "gn:dem":5,
    "gn:feature_class":"P",
    "gn:feature_code":"PPL",
    "gn:name":"Nunome",
    "gn:population":0,
    "gn:timezone":"Asia/Tokyo",
    "iso:country":"JP",
    "name:jpn_x_preferred":[
        "\u5e03\u76ee"
    ],
    "wof:name":"Nunome",
    "wof:placetype":"locality"
},
  "geometry": {"coordinates":[136.18159,36.21745],"type":"Point"}
}