{
  "type": "Feature",
  "properties": {
    "gn:admin1_code":"15",
    "gn:admin2_code":"1860811.0",
    "gn:admin3_code":"17365.0",
    "gn:asciiname":"Mukai-awagasaki",
    "gn:country_code":"JP",
    "gn:dem":9,
    "gn:feature_class":"P",
    "gn:feature_code":"PPL",
    "gn:name":"Mukai-awagasaki",
    "gn:population":0,
    "gn:timezone":"Asia/Tokyo",
    "iso:country":"JP",
    "name:jpn_x_preferred":[
        "\u5411\u7c9f\u5d0e"
    ],
    "wof:name":"Mukai-awagasaki",
    "wof:placetype":"locality"
},
  "geometry": {"coordinates":[136.63726,36.63246],"type":"Point"}
}