{
  "type": "Feature",
  "properties": {
    "gn:admin1_code":"21.0",
    "gn:admin2_code":"1848441.0",
    "gn:asciiname":"Jusanbanwari",
    "gn:country_code":"JP",
    "gn:dem":2,
    "gn:feature_class":"P",
    "gn:feature_code":"PPLL",
    "gn:name":"J\u016bsanbanwari",
    "gn:population":0,
    "gn:timezone":"Asia/Tokyo",
    "iso:country":"JP",
    "name:jpn_x_preferred":[
        "\u5341\u4e09\u756a\u5272"
    ],
    "name:jpn_x_variant":[
        "\u3058\u3085\u3046\u3055\u3093\u3070\u3093\u308f\u308a",
        "\u30b8\u30e5\u30a6\u30b5\u30f3\u30d0\u30f3\u30ef\u30ea"
    ],
    "name:und_x_variant":[
        "J\u016bsanbanwari"
    ],
    "wof:name":"Jusanbanwari",
    "wof:placetype":"locality"
},
  "geometry": {"coordinates":[130.61494999999999,32.56716],"type":"Point"}
}