{
  "type": "Feature",
  "properties": {
    "gn:admin1_code":"37",
    "gn:admin2_code":"1860327.0",
    "gn:admin3_code":"22302.0",
    "gn:asciiname":"Yatsu",
    "gn:country_code":"JP",
    "gn:dem":27,
    "gn:feature_class":"P",
    "gn:feature_code":"PPL",
    "gn:name":"Yatsu",
    "gn:population":0,
    "gn:timezone":"Asia/Tokyo",
    "iso:country":"JP",
    "name:jpn_x_preferred":[
        "\u8c37\u6d25"
    ],
    "wof:name":"Yatsu",
    "wof:placetype":"locality"
},
  "geometry": {"coordinates":[138.99275,34.7446],"type":"Point"}
}