{
  "type": "Feature",
  "properties": {
    "gn:admin1_code":"21.0",
    "gn:admin2_code":"1850743.0",
    "gn:asciiname":"Nakasakamonta",
    "gn:country_code":"JP",
    "gn:dem":27,
    "gn:feature_class":"P",
    "gn:feature_code":"PPL",
    "gn:name":"Nakasakamonta",
    "gn:population":0,
    "gn:timezone":"Asia/Tokyo",
    "iso:country":"JP",
    "name:jpn_x_preferred":[
        "\u4e2d\u5742\u9580\u7530"
    ],
    "name:jpn_x_variant":[
        "\u306a\u304b\u3055\u304b\u3082\u3093\u305f",
        "\u30ca\u30ab\u30b5\u30ab\u30e2\u30f3\u30bf"
    ],
    "wof:name":"Nakasakamonta",
    "wof:placetype":"locality"
},
  "geometry": {"coordinates":[130.61162999999999,32.91139],"type":"Point"}
}