{
  "type": "Feature",
  "properties": {
    "gn:admin1_code":"21.0",
    "gn:admin2_code":"1848441.0",
    "gn:asciiname":"Sakamotomachi-sakamoto",
    "gn:country_code":"JP",
    "gn:dem":175,
    "gn:feature_class":"P",
    "gn:feature_code":"PPL",
    "gn:name":"Sakamotomachi-sakamoto",
    "gn:population":0,
    "gn:timezone":"Asia/Tokyo",
    "iso:country":"JP",
    "name:jpn_x_preferred":[
        "\u5742\u672c\u753a\u5742\u672c"
    ],
    "wof:name":"Sakamotomachi-sakamoto",
    "wof:placetype":"locality"
},
  "geometry": {"coordinates":[130.66345000000001,32.43476],"type":"Point"}
}