{
  "type": "Feature",
  "properties": {
    "gn:admin1_code":"36",
    "gn:admin2_code":"1854750.0",
    "gn:asciiname":"Kawaicho-yoshinaga",
    "gn:country_code":"JP",
    "gn:dem":96,
    "gn:feature_class":"P",
    "gn:feature_code":"PPL",
    "gn:name":"Kawaich\u014d-yoshinaga",
    "gn:population":0,
    "gn:timezone":"Asia/Tokyo",
    "iso:country":"JP",
    "name:jpn_x_preferred":[
        "\u5ddd\u5408\u753a\u5409\u6c38"
    ],
    "name:und_x_variant":[
        "Kawaich\u014d-yoshinaga",
        "Kawai"
    ],
    "wof:name":"Kawaicho-yoshinaga",
    "wof:placetype":"locality"
},
  "geometry": {"coordinates":[132.51667,35.15],"type":"Point"}
}