{
  "type": "Feature",
  "properties": {
    "iso:country":"JP",
    "name:eng_x_preferred":[
        "Dotonbori 1 Chome"
    ],
    "name:eng_x_variant":[
        "Doutonbori 1 Choume",
        "Dotonbori 1 Chome"
    ],
    "name:jpn_x_preferred":[
        "\uff11\u4e01\u76ee"
    ],
    "name:jpn_x_variant":[
        "\u3069\u3046\u3068\u3093\u307c\u308a \uff11\u3061\u3087\u3046\u3081",
        "\u9053\u9813\u5800 \uff11\u4e01\u76ee",
        "\uff11\u3061\u3087\u3046\u3081"
    ],
    "qs:gn_local":0,
    "qs:local_max":5466,
    "qs:local_sum":82256,
    "qs:localhoods":141,
    "qs:name":"\uff11\u4e01\u76ee",
    "qs:name_adm0":"\u65e5\u672c",
    "qs:name_adm1":"\u5927\u962a\u5e9c",
    "qs:name_adm2":"\u4e2d\u592e\u533a",
    "qs:name_en":"Dotonbori 1 Chome",
    "qs:name_lau":"\u9053\u9813\u5800",
    "qs:name_local":"\u5927\u962a\u5e02",
    "qs:photo_max":68,
    "qs:photo_sum":278,
    "qs:placetype":"Suburb",
    "qs:quad_count":12,
    "qs:woe_adm0":23424856,
    "qs:woe_adm1":2345881,
    "qs:woe_adm2":1118622,
    "qs:woe_lau":28457671,
    "qs:woe_local":15015370,
    "qs:woe_ver":"7.10.0",
    "wof:lang":[
        "jpn"
    ],
    "wof:name":"\uff11\u4e01\u76ee",
    "wof:placetype":"neighbourhood"
},
  "geometry": {"coordinates":[135.506596,34.670268],"type":"Point"}
}