{
  "type": "Feature",
  "properties": {
    "gn:admin1_code":"24.0",
    "gn:admin2_code":"7447001.0",
    "gn:asciiname":"Odateyama",
    "gn:country_code":"JP",
    "gn:dem":24,
    "gn:feature_class":"P",
    "gn:feature_code":"PPL",
    "gn:name":"\u014cdateyama",
    "gn:population":0,
    "gn:timezone":"Asia/Tokyo",
    "iso:country":"JP",
    "name:jpn_x_preferred":[
        "\u5927\u9928\u5c71"
    ],
    "name:jpn_x_variant":[
        "\u304a\u304a\u3060\u3066\u3084\u307e",
        "\u30aa\u30aa\u30c0\u30c6\u30e4\u30de"
    ],
    "name:und_x_variant":[
        "\u014cdateyama"
    ],
    "wof:name":"Odateyama",
    "wof:placetype":"locality"
},
  "geometry": {"coordinates":[141.08892,38.4713],"type":"Point"}
}