{
  "type": "Feature",
  "properties": {
    "iso:country":"JP",
    "name:eng_x_preferred":[
        "Makuharicho 1 Chome"
    ],
    "name:eng_x_variant":[
        "Makuharichou 1 Choume",
        "Makuharicho 1 Chome"
    ],
    "name:jpn_x_preferred":[
        "\uff11\u4e01\u76ee"
    ],
    "name:jpn_x_variant":[
        "\u307e\u304f\u306f\u308a\u3061\u3087\u3046 \uff11\u3061\u3087\u3046\u3081",
        "\u5e55\u5f35\u753a \uff11\u4e01\u76ee",
        "\uff11\u3061\u3087\u3046\u3081"
    ],
    "qs:gn_adm0_cc":"JP",
    "qs:gn_local":2113015,
    "qs:gn_nam_loc":"\u5343\u8449\u5e02, \u5343\u8449\u770c, JP",
    "qs:gn_namadm1":"04",
    "qs:local_max":7724,
    "qs:local_sum":19805,
    "qs:localhoods":49,
    "qs:name":"\uff11\u4e01\u76ee",
    "qs:name_adm0":"\u65e5\u672c",
    "qs:name_adm1":"\u5343\u8449\u770c",
    "qs:name_adm2":"\u82b1\u898b\u5ddd\u533a",
    "qs:name_en":"Makuharicho 1 Chome",
    "qs:name_lau":"\u5e55\u5f35\u753a",
    "qs:name_local":"\u5343\u8449\u5e02",
    "qs:photo_max":9,
    "qs:photo_sum":9,
    "qs:placetype":"Suburb",
    "qs:quad_count":1,
    "qs:woe_adm0":23424856,
    "qs:woe_adm1":2345854,
    "qs:woe_adm2":24707532,
    "qs:woe_lau":28410576,
    "qs:woe_local":1117034,
    "qs:woe_ver":"7.10.0",
    "wof:lang":[
        "jpn"
    ],
    "wof:name":"\uff11\u4e01\u76ee",
    "wof:placetype":"neighbourhood"
},
  "geometry": {"coordinates":[140.04547099999999,35.66399],"type":"Point"}
}