{
  "type": "Feature",
  "properties": {
    "gn:admin1_code":"3.0",
    "gn:admin2_code":"2130654.0",
    "gn:asciiname":"Chayamachi",
    "gn:country_code":"JP",
    "gn:dem":3,
    "gn:feature_class":"P",
    "gn:feature_code":"PPL",
    "gn:name":"Chayamachi",
    "gn:population":0,
    "gn:timezone":"Asia/Tokyo",
    "iso:country":"JP",
    "name:jpn_x_preferred":[
        "\u8336\u5c4b\u753a"
    ],
    "name:jpn_x_variant":[
        "\u3061\u3083\u3084\u307e\u3061",
        "\u30c1\u30e3\u30e4\u30de\u30c1"
    ],
    "wof:name":"Chayamachi",
    "wof:placetype":"locality"
},
  "geometry": {"coordinates":[140.76386000000005,40.82675],"type":"Point"}
}