{
  "type": "Feature",
  "properties": {
    "gn:admin1_code":"6.0",
    "gn:admin2_code":"1863982.0",
    "gn:asciiname":"Okubocho",
    "gn:country_code":"JP",
    "gn:dem":11,
    "gn:feature_class":"P",
    "gn:feature_code":"PPL",
    "gn:name":"\u014ckuboch\u014d",
    "gn:population":0,
    "gn:timezone":"Asia/Tokyo",
    "iso:country":"JP",
    "name:jpn_x_preferred":[
        "\u5927\u7aaa\u753a"
    ],
    "name:und_x_variant":[
        "\u014ckuboch\u014d"
    ],
    "wof:name":"Okubocho",
    "wof:placetype":"locality"
},
  "geometry": {"coordinates":[136.08166,36.13852],"type":"Point"}
}