{
  "type": "Feature",
  "properties": {
    "gn:admin1_code":"37.0",
    "gn:admin2_code":"1856971.0",
    "gn:asciiname":"Kawaharagaya",
    "gn:country_code":"JP",
    "gn:dem":27,
    "gn:feature_class":"P",
    "gn:feature_code":"PPL",
    "gn:name":"Kawaharagaya",
    "gn:population":0,
    "gn:timezone":"Asia/Tokyo",
    "iso:country":"JP",
    "name:jpn_x_preferred":[
        "\u5ddd\u539f\u30f6\u8c37"
    ],
    "wof:name":"Kawaharagaya",
    "wof:placetype":"locality"
},
  "geometry": {"coordinates":[138.92841999999999,35.12303],"type":"Point"}
}