{
  "type": "Feature",
  "properties": {
    "gn:admin1_code":"40.0",
    "gn:admin2_code":"8304376.0",
    "gn:asciiname":"Sumiyoshicho",
    "gn:country_code":"JP",
    "gn:dem":59,
    "gn:feature_class":"P",
    "gn:feature_code":"PPL",
    "gn:name":"Sumiyoshich\u014d",
    "gn:population":0,
    "gn:timezone":"Asia/Tokyo",
    "iso:country":"JP",
    "name:jpn_x_preferred":[
        "\u4f4f\u5409\u753a"
    ],
    "name:und_x_variant":[
        "Sumiyoshich\u014d"
    ],
    "wof:name":"Sumiyoshicho",
    "wof:placetype":"locality"
},
  "geometry": {"coordinates":[139.55053000000001,35.74524],"type":"Point"}
}