{
  "type": "Feature",
  "properties": {
    "gn:admin1_code":"33.0",
    "gn:admin2_code":"1855238.0",
    "gn:admin3_code":"41401.0",
    "gn:asciiname":"Kuromuta",
    "gn:country_code":"JP",
    "gn:dem":61,
    "gn:feature_class":"P",
    "gn:feature_code":"PPL",
    "gn:name":"Kuromuta",
    "gn:population":0,
    "gn:timezone":"Asia/Tokyo",
    "iso:country":"JP",
    "name:jpn_x_preferred":[
        "\u9ed2\u725f\u7530"
    ],
    "wof:name":"Kuromuta",
    "wof:placetype":"locality"
},
  "geometry": {"coordinates":[129.87147999999999,33.19803],"type":"Point"}
}