{
  "type": "Feature",
  "properties": {
    "iso:country":"JP",
    "name:eng_x_preferred":[
        "Ebisuminami 1 Chome"
    ],
    "name:eng_x_variant":[
        "Ebisuminami 1 Choume",
        "Ebisuminami 1 Chome"
    ],
    "name:jpn_x_preferred":[
        "\uff11\u4e01\u76ee"
    ],
    "name:jpn_x_variant":[
        "\u3048\u3073\u3059\u307f\u306a\u307f \uff11\u3061\u3087\u3046\u3081",
        "\u6075\u6bd4\u5bff\u5357 \uff11\u4e01\u76ee",
        "\uff11\u3061\u3087\u3046\u3081"
    ],
    "qs:gn_adm0_cc":"JP",
    "qs:gn_local":1850147,
    "qs:local_max":18112,
    "qs:local_sum":895907,
    "qs:localhoods":857,
    "qs:name":"\uff11\u4e01\u76ee",
    "qs:name_adm0":"\u65e5\u672c",
    "qs:name_adm1":"\u6771\u4eac\u90fd",
    "qs:name_adm2":"\u6e0b\u8c37\u533a",
    "qs:name_en":"Ebisuminami 1 Chome",
    "qs:name_lau":"\u6075\u6bd4\u5bff\u5357",
    "qs:name_local":"\u6771\u4eac",
    "qs:photo_max":359,
    "qs:photo_sum":751,
    "qs:placetype":"Suburb",
    "qs:quad_count":6,
    "qs:woe_adm0":23424856,
    "qs:woe_adm1":2345889,
    "qs:woe_adm2":15015387,
    "qs:woe_lau":28414398,
    "qs:woe_local":1118370,
    "qs:woe_ver":"7.10.0",
    "wof:lang":[
        "jpn"
    ],
    "wof:name":"\uff11\u4e01\u76ee",
    "wof:placetype":"neighbourhood"
},
  "geometry": {"coordinates":[139.709352,35.646045],"type":"Point"}
}