{
  "type": "Feature",
  "properties": {
    "gn:admin1_code":"08",
    "gn:admin2_code":"1857203.0",
    "gn:admin3_code":"7368.0",
    "gn:asciiname":"Hamano",
    "gn:country_code":"JP",
    "gn:dem":594,
    "gn:feature_class":"P",
    "gn:feature_code":"PPL",
    "gn:name":"Hamano",
    "gn:population":0,
    "gn:timezone":"Asia/Tokyo",
    "iso:country":"JP",
    "name:jpn_x_preferred":[
        "\u6d5c\u91ce"
    ],
    "wof:name":"Hamano",
    "wof:placetype":"locality"
},
  "geometry": {"coordinates":[139.50826000000001,37.15415],"type":"Point"}
}