{
  "type": "Feature",
  "properties": {
    "gn:admin1_code":"21.0",
    "gn:admin2_code":"1848441.0",
    "gn:asciiname":"Daido",
    "gn:country_code":"JP",
    "gn:dem":129,
    "gn:feature_class":"P",
    "gn:feature_code":"PPLL",
    "gn:name":"Daid\u014d",
    "gn:population":0,
    "gn:timezone":"Asia/Tokyo",
    "iso:country":"JP",
    "name:jpn_x_preferred":[
        "\u5927\u9053"
    ],
    "name:jpn_x_variant":[
        "\u3060\u3044\u3069\u3046",
        "\u30c0\u30a4\u30c9\u30a6"
    ],
    "name:und_x_variant":[
        "Daid\u014d"
    ],
    "wof:name":"Daido",
    "wof:placetype":"locality"
},
  "geometry": {"coordinates":[130.75707,32.55631],"type":"Point"}
}