{
  "type": "Feature",
  "properties": {
    "gn:admin1_code":"16.0",
    "gn:admin2_code":"2111005.0",
    "gn:admin3_code":"3321.0",
    "gn:asciiname":"Uchikuromori",
    "gn:country_code":"JP",
    "gn:dem":142,
    "gn:feature_class":"P",
    "gn:feature_code":"PPL",
    "gn:name":"Uchikuromori",
    "gn:population":0,
    "gn:timezone":"Asia/Tokyo",
    "iso:country":"JP",
    "name:jpn_x_preferred":[
        "\u5185\u9ed2\u68ee"
    ],
    "name:jpn_x_variant":[
        "\u3046\u3061\u304f\u308d\u3082\u308a",
        "\u30a6\u30c1\u30af\u30ed\u30e2\u30ea"
    ],
    "wof:name":"Uchikuromori",
    "wof:placetype":"locality"
},
  "geometry": {"coordinates":[141.21833000000001,39.50498],"type":"Point"}
}