{
  "type": "Feature",
  "properties": {
    "gn:admin1_code":"23",
    "gn:admin2_code":"1849544.0",
    "gn:asciiname":"Geinocho-mukumoto",
    "gn:country_code":"JP",
    "gn:dem":70,
    "gn:feature_class":"P",
    "gn:feature_code":"PPL",
    "gn:name":"Gein\u014dch\u014d-mukumoto",
    "gn:population":0,
    "gn:timezone":"Asia/Tokyo",
    "iso:country":"JP",
    "name:jpn_x_preferred":[
        "\u82b8\u6fc3\u753a\u690b\u672c"
    ],
    "name:und_x_variant":[
        "Gein\u014dch\u014d-mukumoto",
        "Mukumoto"
    ],
    "wof:name":"Geinocho-mukumoto",
    "wof:placetype":"locality"
},
  "geometry": {"coordinates":[136.42372,34.81325],"type":"Point"}
}