{
  "type": "Feature",
  "properties": {
    "gn:admin1_code":"33.0",
    "gn:admin2_code":"7391355.0",
    "gn:asciiname":"Kurogawacho-yokono",
    "gn:country_code":"JP",
    "gn:dem":315,
    "gn:feature_class":"P",
    "gn:feature_code":"PPL",
    "gn:name":"Kurogawach\u014d-yokono",
    "gn:population":0,
    "gn:timezone":"Asia/Tokyo",
    "iso:country":"JP",
    "name:jpn_x_preferred":[
        "\u9ed2\u5ddd\u753a\u6a2a\u91ce"
    ],
    "name:und_x_variant":[
        "Kurogawach\u014d-yokono"
    ],
    "wof:name":"Kurogawacho-yokono",
    "wof:placetype":"locality"
},
  "geometry": {"coordinates":[129.88647,33.3149],"type":"Point"}
}