{
  "type": "Feature",
  "properties": {
    "gn:admin1_code":"16.0",
    "gn:admin2_code":"7441817.0",
    "gn:asciiname":"Kogakuchi",
    "gn:country_code":"JP",
    "gn:dem":21,
    "gn:feature_class":"P",
    "gn:feature_code":"PPL",
    "gn:name":"Kogakuchi",
    "gn:population":0,
    "gn:timezone":"Asia/Tokyo",
    "iso:country":"JP",
    "name:jpn_x_preferred":[
        "\u5c0f\u30f6\u53e3"
    ],
    "name:jpn_x_variant":[
        "\u3053\u304c\u304f\u3061",
        "\u30b3\u30ac\u30af\u30c1"
    ],
    "wof:name":"Kogakuchi",
    "wof:placetype":"locality"
},
  "geometry": {"coordinates":[141.70335,38.98488],"type":"Point"}
}