{
  "type": "Feature",
  "properties": {
    "gn:admin1_code":"34.0",
    "gn:admin2_code":"1856987.0",
    "gn:asciiname":"Togasaki",
    "gn:country_code":"JP",
    "gn:dem":3,
    "gn:feature_class":"P",
    "gn:feature_code":"PPL",
    "gn:name":"Togasaki",
    "gn:population":0,
    "gn:timezone":"Asia/Tokyo",
    "iso:country":"JP",
    "name:jpn_x_preferred":[
        "\u6238\u30f6\u5d0e"
    ],
    "wof:name":"Togasaki",
    "wof:placetype":"locality"
},
  "geometry": {"coordinates":[139.86531000000002,35.80274],"type":"Point"}
}