{
  "type": "Feature",
  "properties": {
    "gn:admin1_code":"37.0",
    "gn:admin2_code":"1854900.0",
    "gn:asciiname":"Masado",
    "gn:country_code":"JP",
    "gn:dem":14,
    "gn:feature_class":"P",
    "gn:feature_code":"PPLL",
    "gn:name":"Masado",
    "gn:population":0,
    "gn:timezone":"Asia/Tokyo",
    "iso:country":"JP",
    "name:jpn_x_preferred":[
        "\u653f\u6238"
    ],
    "wof:name":"Masado",
    "wof:placetype":"locality"
},
  "geometry": {"coordinates":[138.91946000000002,35.07254],"type":"Point"}
}