{
  "type": "Feature",
  "properties": {
    "gn:admin1_code":"7.0",
    "gn:admin2_code":"7406950.0",
    "gn:admin3_code":"40625.0",
    "gn:asciiname":"Osaka",
    "gn:country_code":"JP",
    "gn:dem":74,
    "gn:feature_class":"P",
    "gn:feature_code":"PPLL",
    "gn:name":"\u014csaka",
    "gn:population":0,
    "gn:timezone":"Asia/Tokyo",
    "iso:country":"JP",
    "name:jpn_x_preferred":[
        "\u5927\u5742"
    ],
    "name:und_x_variant":[
        "\u014csaka"
    ],
    "wof:name":"Osaka",
    "wof:placetype":"locality"
},
  "geometry": {"coordinates":[130.90192999999999,33.65308],"type":"Point"}
}