{
  "type": "Feature",
  "properties": {
    "gn:admin1_code":"42.0",
    "gn:admin2_code":"1853505.0",
    "gn:asciiname":"Horakuji",
    "gn:country_code":"JP",
    "gn:dem":37,
    "gn:feature_class":"P",
    "gn:feature_code":"PPL",
    "gn:name":"H\u014drakuji",
    "gn:population":0,
    "gn:timezone":"Asia/Tokyo",
    "iso:country":"JP",
    "name:jpn_x_preferred":[
        "\u6cd5\u697d\u5bfa"
    ],
    "name:und_x_variant":[
        "H\u014drakuji"
    ],
    "wof:name":"Horakuji",
    "wof:placetype":"locality"
},
  "geometry": {"coordinates":[136.87024,36.69523],"type":"Point"}
}