{
  "type": "Feature",
  "properties": {
    "gn:admin1_code":"21.0",
    "gn:admin2_code":"7412709.0",
    "gn:admin3_code":"43348.0",
    "gn:asciiname":"Mitsuwa",
    "gn:country_code":"JP",
    "gn:dem":208,
    "gn:feature_class":"P",
    "gn:feature_code":"PPL",
    "gn:name":"Mitsuwa",
    "gn:population":0,
    "gn:timezone":"Asia/Tokyo",
    "iso:country":"JP",
    "name:jpn_x_preferred":[
        "\u4e09\u548c"
    ],
    "name:jpn_x_variant":[
        "\u307f\u3064\u308f",
        "\u30df\u30c4\u30ef"
    ],
    "wof:name":"Mitsuwa",
    "wof:placetype":"locality"
},
  "geometry": {"coordinates":[130.86899,32.6268],"type":"Point"}
}