{
  "type": "Feature",
  "properties": {
    "iso:country":"JP",
    "qs:name":"\uff13\u4e01\u76ee",
    "qs:name_adm0":"\u65e5\u672c",
    "qs:name_adm1":"\u611b\u77e5\u770c",
    "qs:photos":459,
    "qs:photos_1k":93,
    "qs:photos_9k":2,
    "qs:photos_9r":5,
    "qs:photos_all":459,
    "qs:photos_sr":7,
    "qs:placetype":"Suburb",
    "qs:pop_sr":"0",
    "wof:name":"\uff13\u4e01\u76ee",
    "wof:placetype":"neighbourhood"
},
  "geometry": {"coordinates":[136.88632200000001,35.173835],"type":"Point"}
}