{
  "type": "Feature",
  "properties": {
    "gn:admin1_code":"21.0",
    "gn:admin2_code":"7412706.0",
    "gn:admin3_code":"43441.0",
    "gn:asciiname":"Shiinoo",
    "gn:country_code":"JP",
    "gn:dem":306,
    "gn:feature_class":"P",
    "gn:feature_code":"PPLL",
    "gn:name":"Shiinoo",
    "gn:population":0,
    "gn:timezone":"Asia/Tokyo",
    "iso:country":"JP",
    "name:jpn_x_preferred":[
        "\u690e\u30ce\u5c3e"
    ],
    "name:jpn_x_variant":[
        "\u3057\u3044\u306e\u304a",
        "\u30b7\u30a4\u30ce\u30aa"
    ],
    "wof:name":"Shiinoo",
    "wof:placetype":"locality"
},
  "geometry": {"coordinates":[130.87538000000001,32.73305],"type":"Point"}
}