{
  "type": "Feature",
  "properties": {
    "gn:admin1_code":"24.0",
    "gn:admin2_code":"7447001.0",
    "gn:asciiname":"Kyuden",
    "gn:country_code":"JP",
    "gn:dem":125,
    "gn:feature_class":"P",
    "gn:feature_code":"PPL",
    "gn:name":"Ky\u016bden",
    "gn:population":0,
    "gn:timezone":"Asia/Tokyo",
    "iso:country":"JP",
    "name:jpn_x_preferred":[
        "\u4e45\u7530"
    ],
    "name:jpn_x_variant":[
        "\u304d\u3085\u3046\u3067\u3093",
        "\u30ad\u30e5\u30a6\u30c7\u30f3"
    ],
    "name:und_x_variant":[
        "Ky\u016bden"
    ],
    "wof:name":"Kyuden",
    "wof:placetype":"locality"
},
  "geometry": {"coordinates":[140.74423000000004,38.74264],"type":"Point"}
}