{
  "type": "Feature",
  "properties": {
    "gn:admin1_code":"34.0",
    "gn:admin2_code":"7464127.0",
    "gn:asciiname":"Doniwa",
    "gn:country_code":"JP",
    "gn:dem":3,
    "gn:feature_class":"P",
    "gn:feature_code":"PPL",
    "gn:name":"D\u014dniwa",
    "gn:population":0,
    "gn:timezone":"Asia/Tokyo",
    "iso:country":"JP",
    "name:jpn_x_preferred":[
        "\u9053\u5ead"
    ],
    "name:und_x_variant":[
        "D\u014dniwa"
    ],
    "wof:name":"Doniwa",
    "wof:placetype":"locality"
},
  "geometry": {"coordinates":[139.84338,35.86127000000001],"type":"Point"}
}