{
  "type": "Feature",
  "properties": {
    "gn:admin1_code":"16.0",
    "gn:admin2_code":"7441817.0",
    "gn:asciiname":"Furuya",
    "gn:country_code":"JP",
    "gn:dem":27,
    "gn:feature_class":"P",
    "gn:feature_code":"PPL",
    "gn:name":"Furuya",
    "gn:population":0,
    "gn:timezone":"Asia/Tokyo",
    "iso:country":"JP",
    "name:jpn_x_preferred":[
        "\u53e4\u8c37"
    ],
    "name:jpn_x_variant":[
        "\u3075\u308b\u3084",
        "\u30d5\u30eb\u30e4"
    ],
    "wof:name":"Furuya",
    "wof:placetype":"locality"
},
  "geometry": {"coordinates":[141.62294,38.98895],"type":"Point"}
}