{
  "type": "Feature",
  "properties": {
    "iso:country":"JP",
    "name:eng_x_preferred":[
        "Nishioi 6 Chome"
    ],
    "name:eng_x_variant":[
        "Nishiooi 6 Choume",
        "Nishioi 6 Chome"
    ],
    "name:jpn_x_preferred":[
        "\uff16\u4e01\u76ee"
    ],
    "name:jpn_x_variant":[
        "\u306b\u3057\u304a\u304a\u3044 \uff16\u3061\u3087\u3046\u3081",
        "\u897f\u5927\u4e95 \uff16\u4e01\u76ee",
        "\uff16\u3061\u3087\u3046\u3081"
    ],
    "qs:gn_adm0_cc":"JP",
    "qs:gn_local":1850147,
    "qs:local_max":18112,
    "qs:local_sum":895907,
    "qs:localhoods":857,
    "qs:name":"\uff16\u4e01\u76ee",
    "qs:name_adm0":"\u65e5\u672c",
    "qs:name_adm1":"\u6771\u4eac\u90fd",
    "qs:name_adm2":"\u54c1\u5ddd\u533a",
    "qs:name_en":"Nishioi 6 Chome",
    "qs:name_lau":"\u897f\u5927\u4e95",
    "qs:name_local":"\u6771\u4eac",
    "qs:photo_max":67,
    "qs:photo_sum":132,
    "qs:placetype":"Suburb",
    "qs:quad_count":6,
    "qs:woe_adm0":23424856,
    "qs:woe_adm1":2345889,
    "qs:woe_adm2":15015507,
    "qs:woe_lau":28414234,
    "qs:woe_local":1118370,
    "qs:woe_ver":"7.10.0",
    "wof:lang":[
        "jpn"
    ],
    "wof:name":"\uff16\u4e01\u76ee",
    "wof:placetype":"neighbourhood"
},
  "geometry": {"coordinates":[139.72280000000001,35.603111],"type":"Point"}
}