{
  "type": "Feature",
  "properties": {
    "iso:country":"JP",
    "name:eng_x_preferred":[
        "Maruyamadai 1 Chome"
    ],
    "name:eng_x_variant":[
        "Maruyamadai 1 Choume",
        "Maruyamadai 1 Chome"
    ],
    "name:jpn_x_preferred":[
        "\uff11\u4e01\u76ee"
    ],
    "name:jpn_x_variant":[
        "\u307e\u308b\u3084\u307e\u3060\u3044 \uff11\u3061\u3087\u3046\u3081",
        "\u4e38\u5c71\u53f0 \uff11\u4e01\u76ee",
        "\uff11\u3061\u3087\u3046\u3081"
    ],
    "qs:gn_local":0,
    "qs:local_max":195,
    "qs:local_sum":383,
    "qs:localhoods":4,
    "qs:name":"\uff11\u4e01\u76ee",
    "qs:name_adm0":"\u65e5\u672c",
    "qs:name_adm1":"\u57fc\u7389\u770c",
    "qs:name_en":"Maruyamadai 1 Chome",
    "qs:name_lau":"\u4e38\u5c71\u53f0",
    "qs:name_local":"\u548c\u5149\u5e02",
    "qs:photo_max":24,
    "qs:photo_sum":39,
    "qs:placetype":"Suburb",
    "qs:quad_count":8,
    "qs:woe_adm0":23424856,
    "qs:woe_adm1":2345883,
    "qs:woe_adm2":0,
    "qs:woe_lau":28409409,
    "qs:woe_local":15015490,
    "qs:woe_ver":"7.10.0",
    "wof:lang":[
        "jpn"
    ],
    "wof:name":"\uff11\u4e01\u76ee",
    "wof:placetype":"neighbourhood"
},
  "geometry": {"coordinates":[139.61273199999999,35.78733],"type":"Point"}
}