{
  "type": "Feature",
  "properties": {
    "gn:admin1_code":"7.0",
    "gn:admin2_code":"7407413.0",
    "gn:asciiname":"Hirahigashi",
    "gn:country_code":"JP",
    "gn:dem":52,
    "gn:feature_class":"P",
    "gn:feature_code":"PPLL",
    "gn:name":"Hirahigashi",
    "gn:population":0,
    "gn:timezone":"Asia/Tokyo",
    "iso:country":"JP",
    "name:jpn_x_preferred":[
        "\u5e73\u6771"
    ],
    "wof:name":"Hirahigashi",
    "wof:placetype":"locality"
},
  "geometry": {"coordinates":[130.74340000000001,33.59321],"type":"Point"}
}