{
  "type": "Feature",
  "properties": {
    "gn:admin1_code":"08",
    "gn:admin2_code":"2112535.0",
    "gn:asciiname":"Miwamachi-watado",
    "gn:country_code":"JP",
    "gn:dem":451,
    "gn:feature_class":"P",
    "gn:feature_code":"PPL",
    "gn:name":"Miwamachi-watado",
    "gn:population":0,
    "gn:timezone":"Asia/Tokyo",
    "iso:country":"JP",
    "name:jpn_x_preferred":[
        "\u4e09\u548c\u753a\u6e21\u6238"
    ],
    "name:und_x_variant":[
        "Watato",
        "Watado",
        "Miwamachi-watado"
    ],
    "wof:name":"Miwamachi-watado",
    "wof:placetype":"locality"
},
  "geometry": {"coordinates":[140.73333,37.11667],"type":"Point"}
}