{
  "type": "Feature",
  "properties": {
    "iso:country":"JP",
    "name:eng_x_preferred":[
        "Intapaku 5chome"
    ],
    "name:eng_x_variant":[
        "Intaapaaku 5choume",
        "Intapaku 5chome"
    ],
    "name:jpn_x_preferred":[
        "\uff15\u4e01\u76ee"
    ],
    "name:jpn_x_variant":[
        "\u3044\u3093\u305f\u30fc\u3071\u30fc\u304f \uff15\u3061\u3087\u3046\u3081",
        "\u30a4\u30f3\u30bf\u30fc\u30d1\u30fc\u30af \uff15\u4e01\u76ee",
        "\uff15\u3061\u3087\u3046\u3081"
    ],
    "qs:gn_local":0,
    "qs:local_max":271,
    "qs:local_sum":1195,
    "qs:localhoods":16,
    "qs:name":"\uff15\u4e01\u76ee",
    "qs:name_adm0":"\u65e5\u672c",
    "qs:name_adm1":"\u6803\u6728\u770c",
    "qs:name_en":"Intapaku 5chome",
    "qs:name_lau":"\u30a4\u30f3\u30bf\u30fc\u30d1\u30fc\u30af",
    "qs:name_local":"\u5b87\u90fd\u5bae\u5e02",
    "qs:photo_max":5,
    "qs:photo_sum":5,
    "qs:placetype":"Suburb",
    "qs:quad_count":1,
    "qs:woe_adm0":23424856,
    "qs:woe_adm1":2345887,
    "qs:woe_adm2":0,
    "qs:woe_lau":90013160,
    "qs:woe_local":1118483,
    "qs:woe_ver":"7.10.0",
    "wof:lang":[
        "jpn"
    ],
    "wof:name":"\uff15\u4e01\u76ee",
    "wof:placetype":"neighbourhood"
},
  "geometry": {"coordinates":[139.908142,36.489765],"type":"Point"}
}