{
  "type": "Feature",
  "properties": {
    "gn:admin1_code":"40.0",
    "gn:admin2_code":"8304376.0",
    "gn:asciiname":"Nishiharacho",
    "gn:country_code":"JP",
    "gn:dem":66,
    "gn:feature_class":"P",
    "gn:feature_code":"PPL",
    "gn:name":"Nishiharach\u014d",
    "gn:population":0,
    "gn:timezone":"Asia/Tokyo",
    "iso:country":"JP",
    "name:jpn_x_preferred":[
        "\u897f\u539f\u753a"
    ],
    "name:und_x_variant":[
        "Nishiharach\u014d"
    ],
    "wof:name":"Nishiharacho",
    "wof:placetype":"locality"
},
  "geometry": {"coordinates":[139.53219999999999,35.73629000000001],"type":"Point"}
}