{
  "type": "Feature",
  "properties": {
    "gn:admin1_code":"4.0",
    "gn:admin2_code":"1857552.0",
    "gn:asciiname":"Ohashi",
    "gn:country_code":"JP",
    "gn:dem":26,
    "gn:feature_class":"P",
    "gn:feature_code":"PPL",
    "gn:name":"\u014chashi",
    "gn:population":0,
    "gn:timezone":"Asia/Tokyo",
    "iso:country":"JP",
    "name:jpn_x_preferred":[
        "\u5927\u6a4b"
    ],
    "name:und_x_variant":[
        "\u014chashi"
    ],
    "wof:name":"Ohashi",
    "wof:placetype":"locality"
},
  "geometry": {"coordinates":[139.91463000000002,35.76815],"type":"Point"}
}