{
  "type": "Feature",
  "properties": {
    "gn:admin1_code":"21.0",
    "gn:admin2_code":"1848441.0",
    "gn:asciiname":"Mugishima-higashimachi",
    "gn:country_code":"JP",
    "gn:dem":9,
    "gn:feature_class":"P",
    "gn:feature_code":"PPL",
    "gn:name":"Mugishima-higashimachi",
    "gn:population":0,
    "gn:timezone":"Asia/Tokyo",
    "iso:country":"JP",
    "name:jpn_x_preferred":[
        "\u9ea6\u5cf6\u6771\u753a"
    ],
    "wof:name":"Mugishima-higashimachi",
    "wof:placetype":"locality"
},
  "geometry": {"coordinates":[130.61281,32.49773],"type":"Point"}
}