{
  "type": "Feature",
  "properties": {
    "gn:admin1_code":"24",
    "gn:admin2_code":"2111817.0",
    "gn:admin3_code":"4606.0",
    "gn:asciiname":"Takihama",
    "gn:country_code":"JP",
    "gn:dem":9,
    "gn:feature_class":"P",
    "gn:feature_code":"PPL",
    "gn:name":"Takihama",
    "gn:population":0,
    "gn:timezone":"Asia/Tokyo",
    "iso:country":"JP",
    "name:jpn_x_preferred":[
        "\u6edd\u6d5c"
    ],
    "name:und_x_variant":[
        "Takinohama",
        "Takihama"
    ],
    "wof:name":"Takihama",
    "wof:placetype":"locality"
},
  "geometry": {"coordinates":[141.49164999999999,38.64035],"type":"Point"}
}