{
  "type": "Feature",
  "properties": {
    "gn:admin1_code":"27",
    "gn:admin2_code":"7418807.0",
    "gn:asciiname":"Ichinogo",
    "gn:cc2":"JP",
    "gn:country_code":"JP",
    "gn:dem":-5,
    "gn:feature_class":"P",
    "gn:feature_code":"PPL",
    "gn:name":"Ichinog\u014d",
    "gn:population":0,
    "gn:timezone":"Asia/Tokyo",
    "iso:country":"JP",
    "name:und_x_variant":[
        "Matsubara",
        "Matubara",
        "Ichinog\u014d"
    ],
    "wof:name":"Ichinogo",
    "wof:placetype":"locality"
},
  "geometry": {"coordinates":[129.93333000000001,32.96667],"type":"Point"}
}