{
  "type": "Feature",
  "properties": {
    "gn:admin1_code":"4.0",
    "gn:admin2_code":"1859468.0",
    "gn:asciiname":"Oyashiki",
    "gn:country_code":"JP",
    "gn:dem":43,
    "gn:feature_class":"P",
    "gn:feature_code":"PPLL",
    "gn:name":"Oyashiki",
    "gn:population":0,
    "gn:timezone":"Asia/Tokyo",
    "iso:country":"JP",
    "name:jpn_x_preferred":[
        "\u5fa1\u5c4b\u6577"
    ],
    "name:jpn_x_variant":[
        "\u304a\u3084\u3057\u304d",
        "\u30aa\u30e4\u30b7\u30ad"
    ],
    "wof:name":"Oyashiki",
    "wof:placetype":"locality"
},
  "geometry": {"coordinates":[140.08306999999999,35.28733],"type":"Point"}
}