{
  "type": "Feature",
  "properties": {
    "gn:admin1_code":"26.0",
    "gn:admin2_code":"1849427.0",
    "gn:asciiname":"Kongoji",
    "gn:country_code":"JP",
    "gn:dem":591,
    "gn:feature_class":"P",
    "gn:feature_code":"PPLL",
    "gn:name":"Kong\u014dji",
    "gn:population":0,
    "gn:timezone":"Asia/Tokyo",
    "iso:country":"JP",
    "name:jpn_x_preferred":[
        "\u91d1\u525b\u5bfa"
    ],
    "name:und_x_variant":[
        "Kong\u014dji"
    ],
    "wof:name":"Kongoji",
    "wof:placetype":"locality"
},
  "geometry": {"coordinates":[138.28555,36.42126],"type":"Point"}
}