{
  "type": "Feature",
  "properties": {
    "gn:admin1_code":"21.0",
    "gn:admin2_code":"7412705.0",
    "gn:admin3_code":"43484.0",
    "gn:asciiname":"Hirakunikami",
    "gn:country_code":"JP",
    "gn:dem":32,
    "gn:feature_class":"P",
    "gn:feature_code":"PPLL",
    "gn:name":"Hirakunikami",
    "gn:population":0,
    "gn:timezone":"Asia/Tokyo",
    "iso:country":"JP",
    "name:jpn_x_preferred":[
        "\u5e73\u56fd\u4e0a"
    ],
    "name:jpn_x_variant":[
        "\u3072\u3089\u304f\u306b\u304b\u307f",
        "\u30d2\u30e9\u30af\u30cb\u30ab\u30df"
    ],
    "wof:name":"Hirakunikami",
    "wof:placetype":"locality"
},
  "geometry": {"coordinates":[130.45531,32.2699],"type":"Point"}
}