{
  "type": "Feature",
  "properties": {
    "gn:admin1_code":"45",
    "gn:admin2_code":"1857072.0",
    "gn:asciiname":"Edo",
    "gn:country_code":"JP",
    "gn:dem":173,
    "gn:feature_class":"P",
    "gn:feature_code":"PPL",
    "gn:name":"Ed\u014d",
    "gn:population":0,
    "gn:timezone":"Asia/Tokyo",
    "iso:country":"JP",
    "wof:name":"Edo",
    "wof:placetype":"locality"
},
  "geometry": {"coordinates":[131.34999999999999,34.26667],"type":"Point"}
}