{
  "type": "Feature",
  "properties": {
    "gn:admin1_code":"7.0",
    "gn:admin2_code":"7407416.0",
    "gn:asciiname":"Shimokano",
    "gn:country_code":"JP",
    "gn:dem":36,
    "gn:feature_class":"P",
    "gn:feature_code":"PPLL",
    "gn:name":"Shimokan\u014d",
    "gn:population":0,
    "gn:timezone":"Asia/Tokyo",
    "iso:country":"JP",
    "name:jpn_x_preferred":[
        "\u4e0b\u91d1\u751f"
    ],
    "name:und_x_variant":[
        "Shimokan\u014d"
    ],
    "wof:name":"Shimokano",
    "wof:placetype":"locality"
},
  "geometry": {"coordinates":[130.62531999999999,33.72084],"type":"Point"}
}