{
  "type": "Feature",
  "properties": {
    "gn:admin1_code":"28.0",
    "gn:admin2_code":"1848164.0",
    "gn:admin3_code":"29441.0",
    "gn:asciiname":"Tachino",
    "gn:country_code":"JP",
    "gn:dem":180,
    "gn:feature_class":"P",
    "gn:feature_code":"PPL",
    "gn:name":"Tachino",
    "gn:population":0,
    "gn:timezone":"Asia/Tokyo",
    "iso:country":"JP",
    "name:jpn_x_preferred":[
        "\u7acb\u91ce"
    ],
    "wof:name":"Tachino",
    "wof:placetype":"locality"
},
  "geometry": {"coordinates":[135.86486000000002,34.39663],"type":"Point"}
}