{
  "type": "Feature",
  "properties": {
    "gn:admin1_code":"37.0",
    "gn:admin2_code":"1864089.0",
    "gn:asciiname":"Takaoka-honcho",
    "gn:country_code":"JP",
    "gn:dem":31,
    "gn:feature_class":"P",
    "gn:feature_code":"PPL",
    "gn:name":"Takaoka-honch\u014d",
    "gn:population":0,
    "gn:timezone":"Asia/Tokyo",
    "iso:country":"JP",
    "name:jpn_x_preferred":[
        "\u9df9\u5ca1\u672c\u753a"
    ],
    "name:und_x_variant":[
        "Takaoka-honch\u014d"
    ],
    "wof:name":"Takaoka-honcho",
    "wof:placetype":"locality"
},
  "geometry": {"coordinates":[138.64926,35.18179],"type":"Point"}
}