{
  "type": "Feature",
  "properties": {
    "gn:admin1_code":"3.0",
    "gn:admin2_code":"2129754.0",
    "gn:admin3_code":"2405.0",
    "gn:asciiname":"Kamiyoshida",
    "gn:country_code":"JP",
    "gn:dem":18,
    "gn:feature_class":"P",
    "gn:feature_code":"PPL",
    "gn:name":"Kamiyoshida",
    "gn:population":0,
    "gn:timezone":"Asia/Tokyo",
    "iso:country":"JP",
    "name:jpn_x_preferred":[
        "\u4e0a\u5409\u7530"
    ],
    "name:jpn_x_variant":[
        "\u304b\u307f\u3088\u3057\u3060",
        "\u30ab\u30df\u30e8\u30b7\u30c0"
    ],
    "wof:name":"Kamiyoshida",
    "wof:placetype":"locality"
},
  "geometry": {"coordinates":[141.32818,40.59392],"type":"Point"}
}