{
  "type": "Feature",
  "properties": {
    "gn:admin1_code":"21.0",
    "gn:admin2_code":"1848441.0",
    "gn:asciiname":"Yoshimutamachi",
    "gn:country_code":"JP",
    "gn:dem":1,
    "gn:feature_class":"P",
    "gn:feature_code":"PPL",
    "gn:name":"Yoshimutamachi",
    "gn:population":0,
    "gn:timezone":"Asia/Tokyo",
    "iso:country":"JP",
    "name:jpn_x_preferred":[
        "\u846d\u725f\u7530\u753a"
    ],
    "wof:name":"Yoshimutamachi",
    "wof:placetype":"locality"
},
  "geometry": {"coordinates":[130.58165,32.49038],"type":"Point"}
}