{
  "type": "Feature",
  "properties": {
    "gn:admin1_code":"16.0",
    "gn:admin2_code":"2112822.0",
    "gn:asciiname":"Koharada",
    "gn:country_code":"JP",
    "gn:dem":151,
    "gn:feature_class":"P",
    "gn:feature_code":"PPL",
    "gn:name":"Koharada",
    "gn:population":0,
    "gn:timezone":"Asia/Tokyo",
    "iso:country":"JP",
    "name:jpn_x_preferred":[
        "\u5c0f\u539f\u7530"
    ],
    "name:jpn_x_variant":[
        "\u3053\u306f\u3089\u3060",
        "\u30b3\u30cf\u30e9\u30c0"
    ],
    "wof:name":"Koharada",
    "wof:placetype":"locality"
},
  "geometry": {"coordinates":[141.23623999999995,39.47906],"type":"Point"}
}