{
  "type": "Feature",
  "properties": {
    "gn:admin1_code":"21.0",
    "gn:admin2_code":"1848441.0",
    "gn:asciiname":"Ochiai",
    "gn:country_code":"JP",
    "gn:dem":223,
    "gn:feature_class":"P",
    "gn:feature_code":"PPLL",
    "gn:name":"Ochiai",
    "gn:population":0,
    "gn:timezone":"Asia/Tokyo",
    "iso:country":"JP",
    "name:jpn_x_preferred":[
        "\u843d\u5408"
    ],
    "name:jpn_x_variant":[
        "\u304a\u3061\u3042\u3044",
        "\u30aa\u30c1\u30a2\u30a4"
    ],
    "wof:name":"Ochiai",
    "wof:placetype":"locality"
},
  "geometry": {"coordinates":[130.80784,32.54524],"type":"Point"}
}