{
  "type": "Feature",
  "properties": {
    "gn:admin1_code":"32.0",
    "gn:admin2_code":"1862538.0",
    "gn:asciiname":"Makino-honmachi",
    "gn:country_code":"JP",
    "gn:dem":25,
    "gn:feature_class":"P",
    "gn:feature_code":"PPL",
    "gn:name":"Makino-honmachi",
    "gn:population":0,
    "gn:timezone":"Asia/Tokyo",
    "iso:country":"JP",
    "name:jpn_x_preferred":[
        "\u7267\u91ce\u672c\u753a"
    ],
    "name:jpn_x_variant":[
        "\u4e09\u6817"
    ],
    "wof:name":"Makino-honmachi",
    "wof:placetype":"locality"
},
  "geometry": {"coordinates":[135.67311999999998,34.84059],"type":"Point"}
}