{
  "type": "Feature",
  "properties": {
    "gn:admin1_code":"3.0",
    "gn:admin2_code":"2130056.0",
    "gn:asciiname":"Kitayokocho",
    "gn:country_code":"JP",
    "gn:dem":28,
    "gn:feature_class":"P",
    "gn:feature_code":"PPL",
    "gn:name":"Kitayokoch\u014d",
    "gn:population":0,
    "gn:timezone":"Asia/Tokyo",
    "iso:country":"JP",
    "name:jpn_x_preferred":[
        "\u5317\u6a2a\u753a"
    ],
    "name:jpn_x_variant":[
        "\u304d\u305f\u3088\u3053\u3061\u3087\u3046",
        "\u30ad\u30bf\u30e8\u30b3\u30c1\u30e7\u30a6"
    ],
    "name:und_x_variant":[
        "Kitayokoch\u014d"
    ],
    "wof:name":"Kitayokocho",
    "wof:placetype":"locality"
},
  "geometry": {"coordinates":[140.47897,40.60845],"type":"Point"}
}