{
  "type": "Feature",
  "properties": {
    "gn:admin1_code":"4.0",
    "gn:admin2_code":"1855071.0",
    "gn:asciiname":"Imagamishimo",
    "gn:country_code":"JP",
    "gn:dem":1,
    "gn:feature_class":"P",
    "gn:feature_code":"PPLL",
    "gn:name":"Imagamishimo",
    "gn:population":0,
    "gn:timezone":"Asia/Tokyo",
    "iso:country":"JP",
    "name:jpn_x_preferred":[
        "\u4eca\u4e0a\u4e0b"
    ],
    "wof:name":"Imagamishimo",
    "wof:placetype":"locality"
},
  "geometry": {"coordinates":[139.87479999999999,35.91842000000001],"type":"Point"}
}