{
  "type": "Feature",
  "properties": {
    "gn:admin1_code":"34.0",
    "gn:admin2_code":"1858728.0",
    "gn:asciiname":"Gamo-honcho",
    "gn:country_code":"JP",
    "gn:dem":4,
    "gn:feature_class":"P",
    "gn:feature_code":"PPL",
    "gn:name":"Gam\u014d-honch\u014d",
    "gn:population":0,
    "gn:timezone":"Asia/Tokyo",
    "iso:country":"JP",
    "name:jpn_x_preferred":[
        "\u84b2\u751f\u672c\u753a"
    ],
    "name:und_x_variant":[
        "Gam\u014d-honch\u014d"
    ],
    "wof:name":"Gamo-honcho",
    "wof:placetype":"locality"
},
  "geometry": {"coordinates":[139.79791,35.86462],"type":"Point"}
}