{
  "type": "Feature",
  "properties": {
    "gn:admin1_code":"10.0",
    "gn:admin2_code":"1852593.0",
    "gn:asciiname":"Teraushiro",
    "gn:country_code":"JP",
    "gn:dem":452,
    "gn:feature_class":"P",
    "gn:feature_code":"PPLL",
    "gn:name":"Teraushiro",
    "gn:population":0,
    "gn:timezone":"Asia/Tokyo",
    "iso:country":"JP",
    "name:jpn_x_preferred":[
        "\u5bfa\u5f8c"
    ],
    "wof:name":"Teraushiro",
    "wof:placetype":"locality"
},
  "geometry": {"coordinates":[139.07473999999999,36.56265],"type":"Point"}
}