{
  "type": "Feature",
  "properties": {
    "gn:admin1_code":"7.0",
    "gn:admin2_code":"1851269.0",
    "gn:admin3_code":"40605.0",
    "gn:asciiname":"Shikibu",
    "gn:country_code":"JP",
    "gn:dem":57,
    "gn:feature_class":"P",
    "gn:feature_code":"PPLL",
    "gn:name":"Shikibu",
    "gn:population":0,
    "gn:timezone":"Asia/Tokyo",
    "iso:country":"JP",
    "name:jpn_x_preferred":[
        "\u5f0f\u90e8"
    ],
    "wof:name":"Shikibu",
    "wof:placetype":"locality"
},
  "geometry": {"coordinates":[130.80616000000001,33.61998],"type":"Point"}
}