{
  "type": "Feature",
  "properties": {
    "gn:admin1_code":"6.0",
    "gn:admin2_code":"7465770.0",
    "gn:admin3_code":"18322.0",
    "gn:asciiname":"Nakajima",
    "gn:country_code":"JP",
    "gn:dem":73,
    "gn:feature_class":"P",
    "gn:feature_code":"PPL",
    "gn:name":"Nakajima",
    "gn:population":0,
    "gn:timezone":"Asia/Tokyo",
    "iso:country":"JP",
    "name:jpn_x_preferred":[
        "\u4e2d\u5cf6"
    ],
    "wof:name":"Nakajima",
    "wof:placetype":"locality"
},
  "geometry": {"coordinates":[136.41076000000001,36.07656],"type":"Point"}
}