{
  "type": "Feature",
  "properties": {
    "gn:admin1_code":"15.0",
    "gn:admin2_code":"7467839.0",
    "gn:admin3_code":"17463.0",
    "gn:asciiname":"Kitakawachi",
    "gn:country_code":"JP",
    "gn:dem":224,
    "gn:feature_class":"P",
    "gn:feature_code":"PPL",
    "gn:name":"Kitakawachi",
    "gn:population":0,
    "gn:timezone":"Asia/Tokyo",
    "iso:country":"JP",
    "name:jpn_x_preferred":[
        "\u5317\u6cb3\u5185"
    ],
    "wof:name":"Kitakawachi",
    "wof:placetype":"locality"
},
  "geometry": {"coordinates":[137.01203000000001,37.38484],"type":"Point"}
}