{
  "type": "Feature",
  "properties": {
    "gn:admin1_code":"24.0",
    "gn:admin2_code":"2112261.0",
    "gn:asciiname":"Akaiwa-oimatsu",
    "gn:country_code":"JP",
    "gn:dem":23,
    "gn:feature_class":"P",
    "gn:feature_code":"PPL",
    "gn:name":"Akaiwa-oimatsu",
    "gn:population":0,
    "gn:timezone":"Asia/Tokyo",
    "iso:country":"JP",
    "name:jpn_x_preferred":[
        "\u8d64\u5ca9\u8001\u677e"
    ],
    "name:jpn_x_variant":[
        "\u3042\u304b\u3044\u308f\u304a\u3044\u307e\u3064",
        "\u30a2\u30ab\u30a4\u30ef\u30aa\u30a4\u30de\u30c4"
    ],
    "wof:name":"Akaiwa-oimatsu",
    "wof:placetype":"locality"
},
  "geometry": {"coordinates":[141.57437999999999,38.88469],"type":"Point"}
}