{
  "type": "Feature",
  "properties": {
    "gn:admin1_code":"2.0",
    "gn:admin2_code":"2128783.0",
    "gn:asciiname":"Aizomecho",
    "gn:country_code":"JP",
    "gn:dem":72,
    "gn:feature_class":"P",
    "gn:feature_code":"PPL",
    "gn:name":"Aizomech\u014d",
    "gn:population":0,
    "gn:timezone":"Asia/Tokyo",
    "iso:country":"JP",
    "name:jpn_x_preferred":[
        "\u76f8\u67d3\u753a"
    ],
    "name:jpn_x_variant":[
        "\u3042\u3044\u305e\u3081\u3061\u3087\u3046",
        "\u30a2\u30a4\u30be\u30e1\u30c1\u30e7\u30a6"
    ],
    "name:und_x_variant":[
        "Aizomech\u014d"
    ],
    "wof:name":"Aizomecho",
    "wof:placetype":"locality"
},
  "geometry": {"coordinates":[140.56888000000001,40.2659],"type":"Point"}
}