{
  "type": "Feature",
  "properties": {
    "gn:admin1_code":"30",
    "gn:admin2_code":"7414051.0",
    "gn:asciiname":"Nukumi",
    "gn:country_code":"JP",
    "gn:dem":599,
    "gn:feature_class":"P",
    "gn:feature_code":"PPLL",
    "gn:name":"Nukumi",
    "gn:population":0,
    "gn:timezone":"Asia/Tokyo",
    "iso:country":"JP",
    "name:jpn_x_preferred":[
        "\u6e29\u898b"
    ],
    "wof:name":"Nukumi",
    "wof:placetype":"locality"
},
  "geometry": {"coordinates":[131.43333000000001,33.06667],"type":"Point"}
}