{
  "type": "Feature",
  "properties": {
    "gn:admin1_code":"28.0",
    "gn:admin2_code":"1848164.0",
    "gn:admin3_code":"29444.0",
    "gn:asciiname":"Katsurahara",
    "gn:country_code":"JP",
    "gn:dem":399,
    "gn:feature_class":"P",
    "gn:feature_code":"PPL",
    "gn:name":"Katsurahara",
    "gn:population":0,
    "gn:timezone":"Asia/Tokyo",
    "iso:country":"JP",
    "name:jpn_x_preferred":[
        "\u6842\u539f"
    ],
    "wof:name":"Katsurahara",
    "wof:placetype":"locality"
},
  "geometry": {"coordinates":[135.82688000000002,34.29789],"type":"Point"}
}