{
  "type": "Feature",
  "properties": {
    "gn:admin1_code":"09",
    "gn:admin2_code":"7418819.0",
    "gn:admin3_code":"21401.0",
    "gn:asciiname":"Tsuka",
    "gn:country_code":"JP",
    "gn:dem":357,
    "gn:feature_class":"P",
    "gn:feature_code":"PPL",
    "gn:name":"Tsuka",
    "gn:population":0,
    "gn:timezone":"Asia/Tokyo",
    "iso:country":"JP",
    "wof:name":"Tsuka",
    "wof:placetype":"locality"
},
  "geometry": {"coordinates":[136.43045000000001,35.73509],"type":"Point"}
}