{
  "type": "Feature",
  "properties": {
    "gn:admin1_code":"44.0",
    "gn:admin2_code":"2111850.0",
    "gn:admin3_code":"6362.0",
    "gn:asciiname":"Genzahara",
    "gn:country_code":"JP",
    "gn:dem":248,
    "gn:feature_class":"P",
    "gn:feature_code":"PPL",
    "gn:name":"Genzahara",
    "gn:population":0,
    "gn:timezone":"Asia/Tokyo",
    "iso:country":"JP",
    "name:jpn_x_preferred":[
        "\u6e90\u4f50\u539f"
    ],
    "name:jpn_x_variant":[
        "\u3052\u3093\u3056\u306f\u3089",
        "\u30b2\u30f3\u30b6\u30cf\u30e9"
    ],
    "wof:name":"Genzahara",
    "wof:placetype":"locality"
},
  "geometry": {"coordinates":[140.52889999999999,38.77247],"type":"Point"}
}