{
  "type": "Feature",
  "properties": {
    "gn:admin1_code":"3.0",
    "gn:admin2_code":"2130056.0",
    "gn:asciiname":"Aramachi",
    "gn:country_code":"JP",
    "gn:dem":34,
    "gn:feature_class":"P",
    "gn:feature_code":"PPL",
    "gn:name":"Aramachi",
    "gn:population":0,
    "gn:timezone":"Asia/Tokyo",
    "iso:country":"JP",
    "name:jpn_x_preferred":[
        "\u65b0\u753a"
    ],
    "name:jpn_x_variant":[
        "\u3042\u3089\u307e\u3061",
        "\u30a2\u30e9\u30de\u30c1"
    ],
    "wof:name":"Aramachi",
    "wof:placetype":"locality"
},
  "geometry": {"coordinates":[140.45757,40.60692],"type":"Point"}
}