{
  "type": "Feature",
  "properties": {
    "gn:admin1_code":"24.0",
    "gn:admin2_code":"2111147.0",
    "gn:admin3_code":"4105.0",
    "gn:asciiname":"Kubo",
    "gn:country_code":"JP",
    "gn:dem":54,
    "gn:feature_class":"P",
    "gn:feature_code":"PPLL",
    "gn:name":"Kubo",
    "gn:population":0,
    "gn:timezone":"Asia/Tokyo",
    "iso:country":"JP",
    "name:ceb_x_preferred":[
        "Kubo"
    ],
    "name:deu_x_preferred":[
        "Kubo"
    ],
    "name:epo_x_preferred":[
        "Kubo"
    ],
    "name:fra_x_preferred":[
        "Kubo"
    ],
    "name:ita_x_preferred":[
        "Kubo"
    ],
    "name:jpn_x_preferred":[
        "\u7aaa"
    ],
    "name:kor_x_preferred":[
        "\uad6c\ubcf4"
    ],
    "name:rus_x_preferred":[
        "\u041a\u0443\u0431\u043e"
    ],
    "name:slk_x_preferred":[
        "Kubo"
    ],
    "name:tgl_x_preferred":[
        "Kubo"
    ],
    "wof:name":"Kubo",
    "wof:placetype":"locality"
},
  "geometry": {"coordinates":[140.80591000000001,38.32959],"type":"Point"}
}