{
  "type": "Feature",
  "properties": {
    "gn:admin1_code":"24.0",
    "gn:admin2_code":"2111147.0",
    "gn:admin3_code":"4105.0",
    "gn:asciiname":"Kubo",
    "gn:country_code":"JP",
    "gn:dem":54,
    "gn:feature_class":"P",
    "gn:feature_code":"PPLL",
    "gn:name":"Kubo",
    "gn:population":0,
    "gn:timezone":"Asia/Tokyo",
    "iso:country":"JP",
    "name:jpn_x_preferred":[
        "\u7aaa"
    ],
    "wof:name":"Kubo",
    "wof:placetype":"locality"
},
  "geometry": {"coordinates":[140.80591000000001,38.32959],"type":"Point"}
}