{
  "type": "Feature",
  "properties": {
    "gn:admin1_code":"18",
    "gn:admin2_code":"7383991.0",
    "gn:asciiname":"Yunoo",
    "gn:country_code":"JP",
    "gn:dem":190,
    "gn:feature_class":"P",
    "gn:feature_code":"PPL",
    "gn:name":"Yunoo",
    "gn:population":0,
    "gn:timezone":"Asia/Tokyo",
    "iso:country":"JP",
    "wof:name":"Yunoo",
    "wof:placetype":"locality"
},
  "geometry": {"coordinates":[130.66666999999998,31.98333],"type":"Point"}
}