{
  "type": "Feature",
  "properties": {
    "gn:admin1_code":"2.0",
    "gn:admin2_code":"7443149.0",
    "gn:asciiname":"Fukubera",
    "gn:country_code":"JP",
    "gn:dem":25,
    "gn:feature_class":"P",
    "gn:feature_code":"PPL",
    "gn:name":"Fukubera",
    "gn:population":0,
    "gn:timezone":"Asia/Tokyo",
    "iso:country":"JP",
    "name:jpn_x_preferred":[
        "\u798f\u90e8\u7f85"
    ],
    "wof:name":"Fukubera",
    "wof:placetype":"locality"
},
  "geometry": {"coordinates":[140.27267000000001,39.5276],"type":"Point"}
}