{
  "type": "Feature",
  "properties": {
    "gn:admin1_code":"37.0",
    "gn:admin2_code":"1864104.0",
    "gn:asciiname":"Kikiriyama",
    "gn:country_code":"JP",
    "gn:dem":291,
    "gn:feature_class":"P",
    "gn:feature_code":"PPLL",
    "gn:name":"Kikiriyama",
    "gn:population":0,
    "gn:timezone":"Asia/Tokyo",
    "iso:country":"JP",
    "name:jpn_x_preferred":[
        "\u6728\u4f10\u5c71"
    ],
    "wof:name":"Kikiriyama",
    "wof:placetype":"locality"
},
  "geometry": {"coordinates":[138.64783,35.24247000000001],"type":"Point"}
}