{
  "type": "Feature",
  "properties": {
    "gn:admin1_code":"37.0",
    "gn:admin2_code":"1864104.0",
    "gn:asciiname":"Horinouchi",
    "gn:country_code":"JP",
    "gn:dem":349,
    "gn:feature_class":"P",
    "gn:feature_code":"PPLL",
    "gn:name":"Horinouchi",
    "gn:population":0,
    "gn:timezone":"Asia/Tokyo",
    "iso:country":"JP",
    "name:jpn_x_preferred":[
        "\u5800\u4e4b\u5185"
    ],
    "wof:name":"Horinouchi",
    "wof:placetype":"locality"
},
  "geometry": {"coordinates":[138.61404999999999,35.27847],"type":"Point"}
}