{
  "type": "Feature",
  "properties": {
    "gn:admin1_code":"3.0",
    "gn:admin2_code":"2129754.0",
    "gn:admin3_code":"2412.0",
    "gn:asciiname":"Mukaiyama",
    "gn:country_code":"JP",
    "gn:dem":49,
    "gn:feature_class":"P",
    "gn:feature_code":"PPL",
    "gn:name":"Mukaiyama",
    "gn:population":0,
    "gn:timezone":"Asia/Tokyo",
    "iso:country":"JP",
    "name:jpn_x_preferred":[
        "\u5411\u5c71"
    ],
    "name:jpn_x_variant":[
        "\u3080\u304b\u3044\u3084\u307e",
        "\u30e0\u30ab\u30a4\u30e4\u30de"
    ],
    "wof:name":"Mukaiyama",
    "wof:placetype":"locality"
},
  "geometry": {"coordinates":[141.36858000000001,40.6284],"type":"Point"}
}