{
  "type": "Feature",
  "properties": {
    "iso:country":"JP",
    "name:eng_x_preferred":[
        "Motomachi 1 Chome"
    ],
    "name:eng_x_variant":[
        "Motomachi 1 Choume",
        "Motomachi 1 Chome"
    ],
    "name:jpn_x_preferred":[
        "\uff11\u4e01\u76ee"
    ],
    "name:jpn_x_variant":[
        "\u3082\u3068\u307e\u3061 \uff11\u3061\u3087\u3046\u3081",
        "\u672c\u753a \uff11\u4e01\u76ee",
        "\uff11\u3061\u3087\u3046\u3081"
    ],
    "name:unk_x_variant":[
        "\uff11\u4e01\u76ee"
    ],
    "qs:gn_local":0,
    "qs:local_max":311,
    "qs:local_sum":1154,
    "qs:localhoods":8,
    "qs:name":"\uff11\u4e01\u76ee",
    "qs:name_adm0":"\u65e5\u672c",
    "qs:name_adm1":"\u5317\u6d77\u9053",
    "qs:photos":29,
    "qs:photos_1k":6,
    "qs:photos_9k":1,
    "qs:photos_9r":2,
    "qs:photos_all":29,
    "qs:photos_sr":2,
    "qs:placetype":"Suburb",
    "qs:pop_sr":"0",
    "qs:quad_count":3,
    "qs:woe_adm0":23424856,
    "qs:woe_adm1":7153351,
    "qs:woe_adm2":24853906,
    "qs:woe_lau":28384346,
    "qs:woe_local":1117024,
    "qs:woe_ver":"7.10.0",
    "wof:lang":[
        "jpn"
    ],
    "wof:name":"\uff11\u4e01\u76ee",
    "wof:placetype":"neighbourhood"
},
  "geometry": {"coordinates":[142.46149800000001,43.591302],"type":"Point"}
}