{
  "type": "Feature",
  "properties": {
    "gn:admin1_code":"3.0",
    "gn:admin2_code":"2128134.0",
    "gn:admin3_code":"2423.0",
    "gn:asciiname":"Zaimoku",
    "gn:country_code":"JP",
    "gn:dem":7,
    "gn:feature_class":"P",
    "gn:feature_code":"PPL",
    "gn:name":"Zaimoku",
    "gn:population":0,
    "gn:timezone":"Asia/Tokyo",
    "iso:country":"JP",
    "name:jpn_x_preferred":[
        "\u6750\u6728"
    ],
    "name:jpn_x_variant":[
        "\u3056\u3044\u3082\u304f",
        "\u30b6\u30a4\u30e2\u30af"
    ],
    "wof:name":"Zaimoku",
    "wof:placetype":"locality"
},
  "geometry": {"coordinates":[140.89146000000005,41.47063],"type":"Point"}
}