{
  "type": "Feature",
  "properties": {
    "gn:admin1_code":"19.0",
    "gn:admin2_code":"1854744.0",
    "gn:asciiname":"Dogashima",
    "gn:country_code":"JP",
    "gn:dem":357,
    "gn:feature_class":"P",
    "gn:feature_code":"PPLL",
    "gn:name":"D\u014dgashima",
    "gn:population":0,
    "gn:timezone":"Asia/Tokyo",
    "iso:country":"JP",
    "name:jpn_x_preferred":[
        "\u5802\u30f6\u5cf6"
    ],
    "name:und_x_variant":[
        "D\u014dgashima"
    ],
    "wof:name":"Dogashima",
    "wof:placetype":"locality"
},
  "geometry": {"coordinates":[139.06301999999999,35.24576],"type":"Point"}
}