{
  "type": "Feature",
  "properties": {
    "gn:admin1_code":"21.0",
    "gn:admin2_code":"7412706.0",
    "gn:admin3_code":"43447.0",
    "gn:asciiname":"Shimogawaino",
    "gn:country_code":"JP",
    "gn:dem":408,
    "gn:feature_class":"P",
    "gn:feature_code":"PPL",
    "gn:name":"Shimogawaino",
    "gn:population":0,
    "gn:timezone":"Asia/Tokyo",
    "iso:country":"JP",
    "name:jpn_x_preferred":[
        "\u4e0b\u5ddd\u4e95\u91ce"
    ],
    "name:jpn_x_variant":[
        "\u3057\u3082\u304c\u308f\u3044\u306e",
        "\u30b7\u30e2\u30ac\u30ef\u30a4\u30ce"
    ],
    "wof:name":"Shimogawaino",
    "wof:placetype":"locality"
},
  "geometry": {"coordinates":[131.01483999999999,32.67043],"type":"Point"}
}