{
  "type": "Feature",
  "properties": {
    "gn:admin1_code":"24.0",
    "gn:admin2_code":"2112574.0",
    "gn:asciiname":"Kanomata",
    "gn:cc2":"JP",
    "gn:country_code":"JP",
    "gn:dem":2,
    "gn:feature_class":"P",
    "gn:feature_code":"PPL",
    "gn:name":"Kanomata",
    "gn:population":0,
    "gn:timezone":"Asia/Tokyo",
    "iso:country":"JP",
    "name:jpn_x_preferred":[
        "\u9e7f\u53c8"
    ],
    "name:jpn_x_variant":[
        "\u304b\u306e\u307e\u305f",
        "\u30ab\u30ce\u30de\u30bf"
    ],
    "name:und_x_variant":[
        "Kamata",
        "Kanomata"
    ],
    "wof:name":"Kanomata",
    "wof:placetype":"locality"
},
  "geometry": {"coordinates":[141.28333000000001,38.48333],"type":"Point"}
}