{
  "type": "Feature",
  "properties": {
    "gn:admin1_code":"34.0",
    "gn:admin2_code":"1858728.0",
    "gn:asciiname":"Oppori",
    "gn:country_code":"JP",
    "gn:dem":7,
    "gn:feature_class":"P",
    "gn:feature_code":"PPLL",
    "gn:name":"Oppori",
    "gn:population":0,
    "gn:timezone":"Asia/Tokyo",
    "iso:country":"JP",
    "name:jpn_x_preferred":[
        "\u8ffd\u5800"
    ],
    "name:jpn_x_variant":[
        "\u304a\u3063\u307d\u308a"
    ],
    "wof:name":"Oppori",
    "wof:placetype":"locality"
},
  "geometry": {"coordinates":[139.77091999999999,35.9309],"type":"Point"}
}