{
  "type": "Feature",
  "properties": {
    "gn:admin1_code":"16.0",
    "gn:admin2_code":"7441804.0",
    "gn:admin3_code":"3301.0",
    "gn:asciiname":"Kaminishine",
    "gn:country_code":"JP",
    "gn:dem":263,
    "gn:feature_class":"P",
    "gn:feature_code":"PPL",
    "gn:name":"Kaminishine",
    "gn:population":0,
    "gn:timezone":"Asia/Tokyo",
    "iso:country":"JP",
    "name:jpn_x_preferred":[
        "\u4e0a\u897f\u6839"
    ],
    "wof:name":"Kaminishine",
    "wof:placetype":"locality"
},
  "geometry": {"coordinates":[140.94212999999999,39.74693],"type":"Point"}
}