{
  "type": "Feature",
  "properties": {
    "gn:admin1_code":"31",
    "gn:admin2_code":"7405228.0",
    "gn:asciiname":"Akuchi",
    "gn:cc2":"JP",
    "gn:country_code":"JP",
    "gn:dem":523,
    "gn:feature_class":"P",
    "gn:feature_code":"PPL",
    "gn:name":"Akuchi",
    "gn:population":0,
    "gn:timezone":"Asia/Tokyo",
    "iso:country":"JP",
    "name:und_x_variant":[
        "Aguchi",
        "Akuchi"
    ],
    "wof:name":"Akuchi",
    "wof:placetype":"locality"
},
  "geometry": {"coordinates":[133.63333,35.01667],"type":"Point"}
}