{
  "type": "Feature",
  "properties": {
    "iso:country":"JP",
    "name:eng_x_preferred":[
        "Toyonari 1chome"
    ],
    "name:eng_x_variant":[
        "Toyonari 1choume",
        "Toyonari 1chome"
    ],
    "name:jpn_x_preferred":[
        "\uff11\u4e01\u76ee",
        "\u4f0a\u52e2\u4f50\u6728\u753a"
    ],
    "name:jpn_x_variant":[
        "\u3068\u3088\u306a\u308a \uff11\u3061\u3087\u3046\u3081",
        "\u8c4a\u6210 \uff11\u4e01\u76ee",
        "\uff11\u3061\u3087\u3046\u3081"
    ],
    "name:unk_x_variant":[
        "\uff11\u4e01\u76ee"
    ],
    "qs:gn_local":0,
    "qs:local_max":1269,
    "qs:local_sum":3018,
    "qs:localhoods":10,
    "qs:name":"\uff11\u4e01\u76ee",
    "qs:name_adm0":"\u65e5\u672c",
    "qs:name_adm1":"\u5ca1\u5c71\u770c",
    "qs:name_adm2":"\u5357\u533a",
    "qs:name_en":"Toyonari 1chome",
    "qs:name_lau":"\u8c4a\u6210",
    "qs:name_local":"\u5ca1\u5c71\u5e02",
    "qs:photo_max":1024,
    "qs:photo_sum":1269,
    "qs:placetype":"Suburb",
    "qs:quad_count":6,
    "qs:woe_adm0":23424856,
    "qs:woe_adm1":2345880,
    "qs:woe_adm2":90035257,
    "qs:woe_lau":90035956,
    "qs:woe_local":90036018,
    "qs:woe_ver":"7.10.0",
    "wof:lang":[
        "jpn"
    ],
    "wof:name":"\uff11\u4e01\u76ee",
    "wof:placetype":"neighbourhood"
},
  "geometry": {"coordinates":[133.930643,34.634325],"type":"Point"}
}