{
  "type": "Feature",
  "properties": {
    "gn:admin1_code":"21.0",
    "gn:admin2_code":"1864975.0",
    "gn:admin3_code":"43423.0",
    "gn:asciiname":"Takenokuma",
    "gn:country_code":"JP",
    "gn:dem":461,
    "gn:feature_class":"P",
    "gn:feature_code":"PPLL",
    "gn:name":"Takenokuma",
    "gn:population":0,
    "gn:timezone":"Asia/Tokyo",
    "iso:country":"JP",
    "name:jpn_x_preferred":[
        "\u7af9\u306e\u718a"
    ],
    "name:jpn_x_variant":[
        "\u305f\u3051\u306e\u304f\u307e",
        "\u30bf\u30b1\u30ce\u30af\u30de"
    ],
    "wof:name":"Takenokuma",
    "wof:placetype":"locality"
},
  "geometry": {"coordinates":[131.07658999999998,33.09041],"type":"Point"}
}