{
  "type": "Feature",
  "properties": {
    "gn:admin1_code":"18",
    "gn:admin2_code":"7383993.0",
    "gn:asciiname":"Eicho-beppu",
    "gn:country_code":"JP",
    "gn:dem":50,
    "gn:feature_class":"P",
    "gn:feature_code":"PPL",
    "gn:name":"Eich\u014d-beppu",
    "gn:population":0,
    "gn:timezone":"Asia/Tokyo",
    "iso:country":"JP",
    "name:jpn_x_preferred":[
        "\u9834\u5a03\u753a\u5225\u5e9c"
    ],
    "name:und_x_variant":[
        "By\u016b",
        "Beppu",
        "Eich\u014d-beppu"
    ],
    "wof:name":"Eicho-beppu",
    "wof:placetype":"locality"
},
  "geometry": {"coordinates":[130.41666999999998,31.26667],"type":"Point"}
}