{
  "type": "Feature",
  "properties": {
    "gn:admin1_code":"21.0",
    "gn:admin2_code":"7413152.0",
    "gn:asciiname":"Kanaketa",
    "gn:country_code":"JP",
    "gn:dem":2,
    "gn:feature_class":"P",
    "gn:feature_code":"PPLL",
    "gn:name":"Kanaketa",
    "gn:population":0,
    "gn:timezone":"Asia/Tokyo",
    "iso:country":"JP",
    "name:jpn_x_preferred":[
        "\u91d1\u6841"
    ],
    "name:jpn_x_variant":[
        "\u304b\u306a\u3051\u305f",
        "\u30ab\u30ca\u30b1\u30bf"
    ],
    "wof:name":"Kanaketa",
    "wof:placetype":"locality"
},
  "geometry": {"coordinates":[130.50385,32.61865],"type":"Point"}
}