{
  "type": "Feature",
  "properties": {
    "gn:admin1_code":"25",
    "gn:admin2_code":"7413968.0",
    "gn:admin3_code":"45442.0",
    "gn:asciiname":"Kamikawa",
    "gn:country_code":"JP",
    "gn:dem":608,
    "gn:feature_class":"P",
    "gn:feature_code":"PPL",
    "gn:name":"Kamikawa",
    "gn:population":0,
    "gn:timezone":"Asia/Tokyo",
    "iso:country":"JP",
    "name:ceb_x_preferred":[
        "Kamikawa"
    ],
    "name:deu_x_preferred":[
        "Kamikawa"
    ],
    "name:fra_x_preferred":[
        "Kamikawa"
    ],
    "name:mlg_x_preferred":[
        "Kamikawa"
    ],
    "name:rus_x_preferred":[
        "\u041a\u0430\u043c\u0438\u043a\u0430\u0432\u0430"
    ],
    "wof:name":"Kamikawa",
    "wof:placetype":"locality"
},
  "geometry": {"coordinates":[131.44999999999999,32.78333],"type":"Point"}
}