{
  "type": "Feature",
  "properties": {
    "gn:admin1_code":"19",
    "gn:admin2_code":"1848308.0",
    "gn:asciiname":"Kubiri",
    "gn:country_code":"JP",
    "gn:dem":23,
    "gn:feature_class":"P",
    "gn:feature_code":"PPL",
    "gn:name":"Kubiri",
    "gn:population":0,
    "gn:timezone":"Asia/Tokyo",
    "iso:country":"JP",
    "name:jpn_x_preferred":[
        "\u4e45\u6bd4\u91cc"
    ],
    "name:jpn_x_variant":[
        "\u304f\u3073\u308a",
        "\u30af\u30d3\u30ea"
    ],
    "wof:name":"Kubiri",
    "wof:placetype":"locality"
},
  "geometry": {"coordinates":[139.70597000000001,35.23407],"type":"Point"}
}