{
  "type": "Feature",
  "properties": {
    "gn:admin1_code":"21.0",
    "gn:admin2_code":"7413152.0",
    "gn:asciiname":"Heta",
    "gn:country_code":"JP",
    "gn:dem":42,
    "gn:feature_class":"P",
    "gn:feature_code":"PPLL",
    "gn:name":"Heta",
    "gn:population":0,
    "gn:timezone":"Asia/Tokyo",
    "iso:country":"JP",
    "name:jpn_x_preferred":[
        "\u90e8\u7530"
    ],
    "name:jpn_x_variant":[
        "\u3078\u305f",
        "\u30d8\u30bf"
    ],
    "wof:name":"Heta",
    "wof:placetype":"locality"
},
  "geometry": {"coordinates":[130.75142,32.64127],"type":"Point"}
}