{
  "type": "Feature",
  "properties": {
    "gn:admin1_code":"23.0",
    "gn:admin2_code":"1861901.0",
    "gn:asciiname":"Okubano",
    "gn:country_code":"JP",
    "gn:dem":311,
    "gn:feature_class":"P",
    "gn:feature_code":"PPL",
    "gn:name":"Okubano",
    "gn:population":0,
    "gn:timezone":"Asia/Tokyo",
    "iso:country":"JP",
    "name:jpn_x_preferred":[
        "\u5965\u99ac\u91ce"
    ],
    "wof:name":"Okubano",
    "wof:placetype":"locality"
},
  "geometry": {"coordinates":[136.25917999999999,34.73273],"type":"Point"}
}