{
  "type": "Feature",
  "properties": {
    "gn:admin1_code":"28.0",
    "gn:admin2_code":"1863538.0",
    "gn:asciiname":"Asamachi",
    "gn:country_code":"JP",
    "gn:dem":177,
    "gn:feature_class":"P",
    "gn:feature_code":"PPL",
    "gn:name":"Asamachi",
    "gn:population":0,
    "gn:timezone":"Asia/Tokyo",
    "iso:country":"JP",
    "name:jpn_x_preferred":[
        "\u671d\u753a"
    ],
    "wof:name":"Asamachi",
    "wof:placetype":"locality"
},
  "geometry": {"coordinates":[135.73718,34.42266],"type":"Point"}
}