{
  "type": "Feature",
  "properties": {
    "gn:admin1_code":"18",
    "gn:admin2_code":"7383995.0",
    "gn:asciiname":"Gumizakicho",
    "gn:country_code":"JP",
    "gn:dem":71,
    "gn:feature_class":"P",
    "gn:feature_code":"PPL",
    "gn:name":"Gumizakich\u014d",
    "gn:population":0,
    "gn:timezone":"Asia/Tokyo",
    "iso:country":"JP",
    "name:jpn_x_preferred":[
        "\u4e45\u898b\u5d0e\u753a"
    ],
    "name:und_x_variant":[
        "Kumisaki",
        "Gumizaki",
        "Gumizakich\u014d"
    ],
    "wof:name":"Gumizakicho",
    "wof:placetype":"locality"
},
  "geometry": {"coordinates":[130.19999999999999,31.83333],"type":"Point"}
}