{
  "type": "Feature",
  "properties": {
    "gn:admin1_code":"16.0",
    "gn:admin2_code":"2110604.0",
    "gn:admin3_code":"3366.0",
    "gn:asciiname":"Nonoshuku",
    "gn:country_code":"JP",
    "gn:dem":300,
    "gn:feature_class":"P",
    "gn:feature_code":"PPL",
    "gn:name":"Nonoshuku",
    "gn:population":0,
    "gn:timezone":"Asia/Tokyo",
    "iso:country":"JP",
    "name:jpn_x_preferred":[
        "\u91ce\u3005\u5bbf"
    ],
    "wof:name":"Nonoshuku",
    "wof:placetype":"locality"
},
  "geometry": {"coordinates":[140.72828999999999,39.28502],"type":"Point"}
}