{
  "type": "Feature",
  "properties": {
    "gn:admin1_code":"37.0",
    "gn:admin2_code":"1864104.0",
    "gn:asciiname":"Kibunecho",
    "gn:country_code":"JP",
    "gn:dem":130,
    "gn:feature_class":"P",
    "gn:feature_code":"PPL",
    "gn:name":"Kibunech\u014d",
    "gn:population":0,
    "gn:timezone":"Asia/Tokyo",
    "iso:country":"JP",
    "name:jpn_x_preferred":[
        "\u8cb4\u8239\u753a"
    ],
    "name:und_x_variant":[
        "Kibunech\u014d"
    ],
    "wof:name":"Kibunecho",
    "wof:placetype":"locality"
},
  "geometry": {"coordinates":[138.60213999999999,35.22736],"type":"Point"}
}