{
  "type": "Feature",
  "properties": {
    "gn:admin1_code":"26.0",
    "gn:admin2_code":"7416554.0",
    "gn:admin3_code":"20423.0",
    "gn:asciiname":"Tsumago",
    "gn:country_code":"JP",
    "gn:dem":425,
    "gn:elevation":"423.0",
    "gn:feature_class":"P",
    "gn:feature_code":"PPL",
    "gn:name":"Tsumago",
    "gn:population":200,
    "gn:timezone":"Asia/Tokyo",
    "iso:country":"JP",
    "name:rus_x_preferred":[
        "\u0426\u0443\u043c\u0430\u0433\u043e"
    ],
    "wof:name":"Tsumago",
    "wof:placetype":"locality",
    "wof:population":200
},
  "geometry": {"coordinates":[137.59535,35.57699],"type":"Point"}
}