{
  "type": "Feature",
  "properties": {
    "gn:admin1_code":"47",
    "gn:admin2_code":"1858371.0",
    "gn:admin3_code":"47306.0",
    "gn:asciiname":"Nakasone",
    "gn:country_code":"JP",
    "gn:dem":7,
    "gn:feature_class":"P",
    "gn:feature_code":"PPL",
    "gn:name":"Nakasone",
    "gn:population":0,
    "gn:timezone":"Asia/Tokyo",
    "iso:country":"JP",
    "name:jpn_x_preferred":[
        "\u4ef2\u5b97\u6839"
    ],
    "name:und_x_variant":[
        "Nakasoni",
        "Nakazone",
        "Nakazuni",
        "Nakasone"
    ],
    "wof:name":"Nakasone",
    "wof:placetype":"locality"
},
  "geometry": {"coordinates":[127.97811000000002,26.68234],"type":"Point"}
}