{
  "type": "Feature",
  "properties": {
    "gn:admin1_code":"3.0",
    "gn:admin2_code":"8534376.0",
    "gn:admin3_code":"2323.0",
    "gn:asciiname":"Hamano",
    "gn:country_code":"JP",
    "gn:dem":14,
    "gn:feature_class":"P",
    "gn:feature_code":"PPLL",
    "gn:name":"Hamano",
    "gn:population":0,
    "gn:timezone":"Asia/Tokyo",
    "iso:country":"JP",
    "name:jpn_x_preferred":[
        "\u6d5c\u91ce"
    ],
    "name:jpn_x_variant":[
        "\u306f\u307e\u306e",
        "\u30cf\u30de\u30ce"
    ],
    "wof:name":"Hamano",
    "wof:placetype":"locality"
},
  "geometry": {"coordinates":[139.90807000000001,40.58686],"type":"Point"}
}