{
  "type": "Feature",
  "properties": {
    "gn:admin1_code":"7.0",
    "gn:admin2_code":"1864573.0",
    "gn:asciiname":"Ashiki",
    "gn:country_code":"JP",
    "gn:dem":49,
    "gn:feature_class":"P",
    "gn:feature_code":"PPL",
    "gn:name":"Ashiki",
    "gn:population":0,
    "gn:timezone":"Asia/Tokyo",
    "iso:country":"JP",
    "name:jpn_x_preferred":[
        "\u963f\u5fd7\u5c90"
    ],
    "wof:name":"Ashiki",
    "wof:placetype":"locality"
},
  "geometry": {"coordinates":[130.55228,33.50179],"type":"Point"}
}