{
  "type": "Feature",
  "properties": {
    "gn:admin1_code":"26",
    "gn:admin2_code":"1852309.0",
    "gn:admin3_code":"20413.0",
    "gn:asciiname":"Mitsushima",
    "gn:cc2":"JP",
    "gn:country_code":"JP",
    "gn:dem":530,
    "gn:feature_class":"P",
    "gn:feature_code":"PPL",
    "gn:name":"Mitsushima",
    "gn:population":0,
    "gn:timezone":"Asia/Tokyo",
    "iso:country":"JP",
    "name:und_x_variant":[
        "Hiraoka",
        "Mitsushima"
    ],
    "wof:name":"Mitsushima",
    "wof:placetype":"locality"
},
  "geometry": {"coordinates":[137.84999999999999,35.26667],"type":"Point"}
}