{
  "type": "Feature",
  "properties": {
    "gn:admin1_code":"43.0",
    "gn:admin2_code":"7411114.0",
    "gn:asciiname":"Momoyamacho-notahara",
    "gn:country_code":"JP",
    "gn:dem":146,
    "gn:feature_class":"P",
    "gn:feature_code":"PPL",
    "gn:name":"Momoyamach\u014d-notahara",
    "gn:population":0,
    "gn:timezone":"Asia/Tokyo",
    "iso:country":"JP",
    "name:jpn_x_preferred":[
        "\u6843\u5c71\u753a\u91ce\u7530\u539f"
    ],
    "name:und_x_variant":[
        "Momoyamach\u014d-notahara"
    ],
    "wof:name":"Momoyamacho-notahara",
    "wof:placetype":"locality"
},
  "geometry": {"coordinates":[135.37568000000002,34.19173],"type":"Point"}
}