{
  "type": "Feature",
  "properties": {
    "gn:admin1_code":"21.0",
    "gn:admin2_code":"7412708.0",
    "gn:admin3_code":"43514.0",
    "gn:asciiname":"Sagisu",
    "gn:country_code":"JP",
    "gn:dem":179,
    "gn:feature_class":"P",
    "gn:feature_code":"PPLL",
    "gn:name":"Sagisu",
    "gn:population":0,
    "gn:timezone":"Asia/Tokyo",
    "iso:country":"JP",
    "name:jpn_x_preferred":[
        "\u9dfa\u5de3"
    ],
    "name:jpn_x_variant":[
        "\u3055\u304e\u3059",
        "\u30b5\u30ae\u30b9"
    ],
    "name:slv_x_preferred":[
        "Sagisu"
    ],
    "wof:name":"Sagisu",
    "wof:placetype":"locality"
},
  "geometry": {"coordinates":[130.86198999999999,32.26474],"type":"Point"}
}