{
  "type": "Feature",
  "properties": {
    "gn:admin1_code":"8.0",
    "gn:admin2_code":"7451502.0",
    "gn:admin3_code":"7501.0",
    "gn:asciiname":"Itabashi",
    "gn:country_code":"JP",
    "gn:dem":479,
    "gn:feature_class":"P",
    "gn:feature_code":"PPL",
    "gn:name":"Itabashi",
    "gn:population":0,
    "gn:timezone":"Asia/Tokyo",
    "iso:country":"JP",
    "name:ace_x_preferred":[
        "Itabashi"
    ],
    "name:ara_x_preferred":[
        "\u0625\u064a\u062a\u0627\u0628\u0627\u0634\u064a"
    ],
    "name:aze_x_preferred":[
        "\u0130taba\u015fi"
    ],
    "name:cat_x_preferred":[
        "Itabashi"
    ],
    "name:ceb_x_preferred":[
        "Itabashi-ku"
    ],
    "name:dan_x_preferred":[
        "Itabashi"
    ],
    "name:deu_x_preferred":[
        "Itabashi"
    ],
    "name:epo_x_preferred":[
        "Kvartalo Itaba\u015di"
    ],
    "name:est_x_preferred":[
        "Itabashi"
    ],
    "name:eus_x_preferred":[
        "Itabashi"
    ],
    "name:fas_x_preferred":[
        "\u0627\u06cc\u062a\u0627\u0628\u0627\u0634\u06cc-\u06a9\u0648"
    ],
    "name:fin_x_preferred":[
        "Itabashi"
    ],
    "name:fra_x_preferred":[
        "Itabashi"
    ],
    "name:gan_x_preferred":[
        "\u677f\u6a4b\u5340"
    ],
    "name:glg_x_preferred":[
        "Itabashi"
    ],
    "name:hat_x_preferred":[
        "Itabashi"
    ],
    "name:hye_x_preferred":[
        "\u053b\u0569\u0561\u057d\u0561\u0562\u056b"
    ],
    "name:ind_x_preferred":[
        "Itabashi"
    ],
    "name:ita_x_preferred":[
        "Itabashi"
    ],
    "name:jpn_x_preferred":[
        "\u677f\u6a4b"
    ],
    "name:jpn_x_variant":[
        "\u677f\u6a4b\u533a"
    ],
    "name:kat_x_preferred":[
        "\u10d8\u10e2\u10d0\u10d1\u10d0\u10e8\u10d8"
    ],
    "name:kor_x_preferred":[
        "\uc774\ud0c0\ubc14\uc2dc\uad6c"
    ],
    "name:lit_x_preferred":[
        "Itaba\u0161is"
    ],
    "name:msa_x_preferred":[
        "Itabashi"
    ],
    "name:nld_x_preferred":[
        "Itabashi"
    ],
    "name:nor_x_preferred":[
        "Itabashi"
    ],
    "name:pol_x_preferred":[
        "Itabashi"
    ],
    "name:por_x_preferred":[
        "Itabashi"
    ],
    "name:ron_x_preferred":[
        "Itabashi"
    ],
    "name:rus_x_preferred":[
        "\u0418\u0442\u0430\u0431\u0430\u0441\u0438"
    ],
    "name:spa_x_preferred":[
        "Itabashi"
    ],
    "name:swe_x_preferred":[
        "Itabashi"
    ],
    "name:tgl_x_preferred":[
        "Itabashi"
    ],
    "name:tha_x_preferred":[
        "\u0e41\u0e02\u0e27\u0e07\u0e2d\u0e34\u0e15\u0e32\u0e1a\u0e32\u0e0a\u0e34"
    ],
    "name:tum_x_preferred":[
        "Itabashi"
    ],
    "name:tur_x_preferred":[
        "Itabashi"
    ],
    "name:ukr_x_preferred":[
        "\u0420\u0430\u0439\u043e\u043d \u0406\u0442\u0430\u0431\u0430\u0441\u0456"
    ],
    "name:urd_x_preferred":[
        "\u0627\u062a\u0627\u0628\u0627\u0634\u06cc"
    ],
    "name:vie_x_preferred":[
        "Itabashi"
    ],
    "name:war_x_preferred":[
        "Itabashi"
    ],
    "name:zho_x_preferred":[
        "\u677f\u6a4b\u5340"
    ],
    "wof:name":"Itabashi",
    "wof:placetype":"locality"
},
  "geometry": {"coordinates":[140.47928999999999,37.09826],"type":"Point"}
}