{
  "type": "Feature",
  "properties": {
    "gn:admin1_code":"8.0",
    "gn:admin2_code":"7451502.0",
    "gn:admin3_code":"7501.0",
    "gn:asciiname":"Itabashi",
    "gn:country_code":"JP",
    "gn:dem":479,
    "gn:feature_class":"P",
    "gn:feature_code":"PPL",
    "gn:name":"Itabashi",
    "gn:population":0,
    "gn:timezone":"Asia/Tokyo",
    "iso:country":"JP",
    "name:jpn_x_preferred":[
        "\u677f\u6a4b"
    ],
    "wof:name":"Itabashi",
    "wof:placetype":"locality"
},
  "geometry": {"coordinates":[140.47928999999999,37.09826],"type":"Point"}
}