{
  "type": "Feature",
  "properties": {
    "gn:admin1_code":"29.0",
    "gn:admin2_code":"1865200.0",
    "gn:asciiname":"Miyauchi",
    "gn:country_code":"JP",
    "gn:dem":45,
    "gn:feature_class":"P",
    "gn:feature_code":"PPL",
    "gn:name":"Miyauchi",
    "gn:population":0,
    "gn:timezone":"Asia/Tokyo",
    "iso:country":"JP",
    "name:deu_x_preferred":[
        "Miyauchi"
    ],
    "name:jpn_x_preferred":[
        "\u5bae\u5185"
    ],
    "wof:name":"Miyauchi",
    "wof:placetype":"locality"
},
  "geometry": {"coordinates":[138.23863,37.05055],"type":"Point"}
}