{
  "type": "Feature",
  "properties": {
    "gn:admin1_code":"15.0",
    "gn:admin2_code":"1860240.0",
    "gn:asciiname":"Imamachi",
    "gn:country_code":"JP",
    "gn:dem":6,
    "gn:feature_class":"P",
    "gn:feature_code":"PPL",
    "gn:name":"Imamachi",
    "gn:population":0,
    "gn:timezone":"Asia/Tokyo",
    "iso:country":"JP",
    "name:jpn_x_preferred":[
        "\u4eca\u753a"
    ],
    "wof:name":"Imamachi",
    "wof:placetype":"locality"
},
  "geometry": {"coordinates":[136.70578999999998,36.63182000000001],"type":"Point"}
}