{
  "type": "Feature",
  "properties": {
    "iso:country":"JP",
    "qs:name":"\u5b57\u938c\u7814",
    "qs:name_adm0":"\u65e5\u672c",
    "qs:name_adm1":"\u611b\u77e5\u770c",
    "qs:photos":6,
    "qs:photos_1k":1,
    "qs:photos_9k":1,
    "qs:photos_9r":1,
    "qs:photos_all":6,
    "qs:photos_sr":1,
    "qs:placetype":"Suburb",
    "qs:pop_sr":"0",
    "wof:name":"\u5b57\u938c\u7814",
    "wof:placetype":"neighbourhood"
},
  "geometry": {"coordinates":[136.96741499999999,35.0688845],"type":"Point"}
}