{
  "type": "Feature",
  "properties": {
    "gn:admin1_code":"12.0",
    "gn:admin2_code":"7428078.0",
    "gn:admin3_code":"1663.0",
    "gn:asciiname":"Hamanaka-kisen",
    "gn:country_code":"JP",
    "gn:dem":56,
    "gn:feature_class":"P",
    "gn:feature_code":"PPL",
    "gn:name":"Hamanaka-kisen",
    "gn:population":0,
    "gn:timezone":"Asia/Tokyo",
    "iso:country":"JP",
    "name:jpn_x_preferred":[
        "\u6d5c\u4e2d\u57fa\u7dda"
    ],
    "name:jpn_x_variant":[
        "\u306f\u307e\u306a\u304b\u304d\u305b\u3093",
        "\u30cf\u30de\u30ca\u30ab\u30ad\u30bb\u30f3"
    ],
    "wof:name":"Hamanaka-kisen",
    "wof:placetype":"locality"
},
  "geometry": {"coordinates":[145.07335,43.16933],"type":"Point"}
}