{
  "type": "Feature",
  "properties": {
    "gn:admin1_code":"18.0",
    "gn:admin2_code":"8300556.0",
    "gn:asciiname":"Takakuma-chuo",
    "gn:country_code":"JP",
    "gn:dem":96,
    "gn:feature_class":"P",
    "gn:feature_code":"PPLL",
    "gn:name":"Takakuma-ch\u016b\u014d",
    "gn:population":0,
    "gn:timezone":"Asia/Tokyo",
    "iso:country":"JP",
    "name:jpn_x_preferred":[
        "\u9ad8\u9688\u4e2d\u592e"
    ],
    "name:und_x_variant":[
        "Takakuma-ch\u016b\u014d"
    ],
    "wof:name":"Takakuma-chuo",
    "wof:placetype":"locality"
},
  "geometry": {"coordinates":[130.87209999999999,31.49141],"type":"Point"}
}