{
  "type": "Feature",
  "properties": {
    "gn:admin1_code":"3.0",
    "gn:admin2_code":"2130200.0",
    "gn:asciiname":"Futanaike",
    "gn:country_code":"JP",
    "gn:dem":23,
    "gn:feature_class":"P",
    "gn:feature_code":"PPL",
    "gn:name":"Futanaike",
    "gn:population":0,
    "gn:timezone":"Asia/Tokyo",
    "iso:country":"JP",
    "name:jpn_x_preferred":[
        "\u84cb\u540d\u6c60"
    ],
    "name:jpn_x_variant":[
        "\u3075\u305f\u306a\u3044\u3051",
        "\u30d5\u30bf\u30ca\u30a4\u30b1"
    ],
    "wof:name":"Futanaike",
    "wof:placetype":"locality"
},
  "geometry": {"coordinates":[141.50137000000001,40.49108],"type":"Point"}
}