{
  "type": "Feature",
  "properties": {
    "gn:admin1_code":"21.0",
    "gn:admin2_code":"1858418.0",
    "gn:admin3_code":"43105.0",
    "gn:asciiname":"Mukozaka",
    "gn:country_code":"JP",
    "gn:dem":83,
    "gn:feature_class":"P",
    "gn:feature_code":"PPLL",
    "gn:name":"Muk\u014dzaka",
    "gn:population":0,
    "gn:timezone":"Asia/Tokyo",
    "iso:country":"JP",
    "name:jpn_x_preferred":[
        "\u5411\u5742"
    ],
    "name:jpn_x_variant":[
        "\u3080\u3053\u3046\u3056\u304b",
        "\u30e0\u30b3\u30a6\u30b6\u30ab"
    ],
    "name:und_x_variant":[
        "Muk\u014dzaka"
    ],
    "wof:name":"Mukozaka",
    "wof:placetype":"locality"
},
  "geometry": {"coordinates":[130.69351,32.8792],"type":"Point"}
}