{
  "type": "Feature",
  "properties": {
    "gn:admin1_code":"46",
    "gn:admin2_code":"1857168.0",
    "gn:admin3_code":"19366.0",
    "gn:asciiname":"Nambu",
    "gn:country_code":"JP",
    "gn:dem":145,
    "gn:feature_class":"P",
    "gn:feature_code":"PPL",
    "gn:name":"Nambu",
    "gn:population":0,
    "gn:timezone":"Asia/Tokyo",
    "iso:country":"JP",
    "wof:name":"Nambu",
    "wof:placetype":"locality"
},
  "geometry": {"coordinates":[138.44999999999999,35.28333],"type":"Point"}
}