{
  "type": "Feature",
  "properties": {
    "gn:admin1_code":"46",
    "gn:admin2_code":"1857168.0",
    "gn:admin3_code":"19366.0",
    "gn:asciiname":"Nambu",
    "gn:country_code":"JP",
    "gn:dem":145,
    "gn:feature_class":"P",
    "gn:feature_code":"PPL",
    "gn:name":"Nambu",
    "gn:population":0,
    "gn:timezone":"Asia/Tokyo",
    "iso:country":"JP",
    "name:fas_x_preferred":[
        "\u0646\u0627\u0646\u0628\u0648"
    ],
    "name:fra_x_preferred":[
        "Nanbu"
    ],
    "name:hye_x_preferred":[
        "\u0546\u0561\u0574\u0562\u0578\u0582"
    ],
    "name:ita_x_preferred":[
        "Nanbu"
    ],
    "name:jpn_x_preferred":[
        "\u5357\u90e8\u753a"
    ],
    "name:kor_x_preferred":[
        "\ub09c\ubd80\uc815"
    ],
    "name:msa_x_preferred":[
        "Nanbu"
    ],
    "name:mya_x_preferred":[
        "\u1014\u1014\u103a\u1018\u102f\u1019\u103c\u102d\u102f\u1037\u104a \u101a\u102c\u1019\u1014\u102c\u101b\u103e\u102d"
    ],
    "name:rus_x_preferred":[
        "\u041d\u0430\u043c\u0431\u0443"
    ],
    "name:tgl_x_preferred":[
        "Nambu"
    ],
    "name:ukr_x_preferred":[
        "\u041d\u0430\u043c\u0431\u0443"
    ],
    "name:zho_x_preferred":[
        "\u5357\u90e8\u753a"
    ],
    "wof:name":"Nambu",
    "wof:placetype":"locality"
},
  "geometry": {"coordinates":[138.44999999999999,35.28333],"type":"Point"}
}