{
  "type": "Feature",
  "properties": {
    "gn:admin1_code":"34.0",
    "gn:admin2_code":"8304213.0",
    "gn:asciiname":"Yomoya",
    "gn:country_code":"JP",
    "gn:dem":10,
    "gn:feature_class":"P",
    "gn:feature_code":"PPLL",
    "gn:name":"Yomoya",
    "gn:population":0,
    "gn:timezone":"Asia/Tokyo",
    "iso:country":"JP",
    "name:jpn_x_preferred":[
        "\u56db\u65b9\u8c37"
    ],
    "name:jpn_x_variant":[
        "\u3088\u3082\u3084",
        "\u30e8\u30e2\u30e4"
    ],
    "wof:name":"Yomoya",
    "wof:placetype":"locality"
},
  "geometry": {"coordinates":[139.73223000000002,35.99544],"type":"Point"}
}