{
  "type": "Feature",
  "properties": {
    "gn:admin1_code":"29",
    "gn:admin2_code":"7468177.0",
    "gn:asciiname":"Miyanoshita",
    "gn:country_code":"JP",
    "gn:dem":6,
    "gn:feature_class":"P",
    "gn:feature_code":"PPL",
    "gn:name":"Miyanoshita",
    "gn:population":0,
    "gn:timezone":"Asia/Tokyo",
    "iso:country":"JP",
    "name:jpn_x_preferred":[
        "\u5bae\u30ce\u4e0b"
    ],
    "name:und_x_variant":[
        "Miyashita",
        "Miyanoshita"
    ],
    "wof:name":"Miyanoshita",
    "wof:placetype":"locality"
},
  "geometry": {"coordinates":[139.48903000000001,38.24823],"type":"Point"}
}