{
  "type": "Feature",
  "properties": {
    "gn:admin1_code":"19.0",
    "gn:admin2_code":"1864622.0",
    "gn:asciiname":"Tsujihigashi",
    "gn:country_code":"JP",
    "gn:dem":7,
    "gn:feature_class":"P",
    "gn:feature_code":"PPLL",
    "gn:name":"Tsujihigashi",
    "gn:population":0,
    "gn:timezone":"Asia/Tokyo",
    "iso:country":"JP",
    "name:jpn_x_preferred":[
        "\u8fbb\u6771"
    ],
    "wof:name":"Tsujihigashi",
    "wof:placetype":"locality"
},
  "geometry": {"coordinates":[139.38385,35.33955],"type":"Point"}
}