{
  "type": "Feature",
  "properties": {
    "gn:admin1_code":"3.0",
    "gn:admin2_code":"2130654.0",
    "gn:asciiname":"Gohonmatsu",
    "gn:country_code":"JP",
    "gn:dem":58,
    "gn:feature_class":"P",
    "gn:feature_code":"PPL",
    "gn:name":"Gohonmatsu",
    "gn:population":0,
    "gn:timezone":"Asia/Tokyo",
    "iso:country":"JP",
    "name:jpn_x_preferred":[
        "\u4e94\u672c\u677e"
    ],
    "name:jpn_x_variant":[
        "\u3054\u307b\u3093\u307e\u3064",
        "\u30b4\u30db\u30f3\u30de\u30c4"
    ],
    "wof:name":"Gohonmatsu",
    "wof:placetype":"locality"
},
  "geometry": {"coordinates":[140.61854,40.72456],"type":"Point"}
}