{
  "type": "Feature",
  "properties": {
    "gn:admin1_code":"8.0",
    "gn:admin2_code":"2112921.0",
    "gn:asciiname":"Honokizawa",
    "gn:cc2":"JP",
    "gn:country_code":"JP",
    "gn:dem":452,
    "gn:feature_class":"P",
    "gn:feature_code":"PPL",
    "gn:name":"H\u014dnokizawa",
    "gn:population":0,
    "gn:timezone":"Asia/Tokyo",
    "iso:country":"JP",
    "name:und_x_variant":[
        "Hosawa",
        "H\u014dnokizawa"
    ],
    "wof:name":"Honokizawa",
    "wof:placetype":"locality"
},
  "geometry": {"coordinates":[140.34999999999999,37.83333],"type":"Point"}
}