{
  "type": "Feature",
  "properties": {
    "gn:admin1_code":"7.0",
    "gn:admin2_code":"7407417.0",
    "gn:asciiname":"Maruyamamachi",
    "gn:country_code":"JP",
    "gn:dem":6,
    "gn:feature_class":"P",
    "gn:feature_code":"PPL",
    "gn:name":"Maruyamamachi",
    "gn:population":0,
    "gn:timezone":"Asia/Tokyo",
    "iso:country":"JP",
    "name:jpn_x_preferred":[
        "\u4e38\u5c71\u753a"
    ],
    "wof:name":"Maruyamamachi",
    "wof:placetype":"locality"
},
  "geometry": {"coordinates":[130.72387000000001,33.73448],"type":"Point"}
}