{
  "type": "Feature",
  "properties": {
    "iso:country":"JP",
    "name:eng_x_preferred":[
        "Honson 3 Chome"
    ],
    "name:eng_x_variant":[
        "Honson 3 Choume",
        "Honson 3 Chome"
    ],
    "name:jpn_x_preferred":[
        "\uff13\u4e01\u76ee"
    ],
    "name:jpn_x_variant":[
        "\u307b\u3093\u305d\u3093 \uff13\u3061\u3087\u3046\u3081",
        "\u672c\u6751 \uff13\u4e01\u76ee",
        "\uff13\u3061\u3087\u3046\u3081"
    ],
    "qs:gn_local":0,
    "qs:local_max":189,
    "qs:local_sum":552,
    "qs:localhoods":4,
    "qs:name":"\uff13\u4e01\u76ee",
    "qs:name_adm0":"\u65e5\u672c",
    "qs:name_adm1":"\u6771\u4eac\u90fd",
    "qs:name_en":"Honson 3 Chome",
    "qs:name_lau":"\u672c\u6751",
    "qs:name_local":"\u65b0\u5cf6\u6751",
    "qs:photo_max":20,
    "qs:photo_sum":115,
    "qs:placetype":"Suburb",
    "qs:quad_count":9,
    "qs:woe_adm0":23424856,
    "qs:woe_adm1":2345889,
    "qs:woe_adm2":0,
    "qs:woe_lau":28415476,
    "qs:woe_local":15015576,
    "qs:woe_ver":"7.10.0",
    "wof:lang":[
        "jpn"
    ],
    "wof:name":"\uff13\u4e01\u76ee",
    "wof:placetype":"neighbourhood"
},
  "geometry": {"coordinates":[139.27246400000001,34.372598],"type":"Point"}
}