{
  "type": "Feature",
  "properties": {
    "gn:admin1_code":"4.0",
    "gn:admin2_code":"2112997.0",
    "gn:admin3_code":"12426.0",
    "gn:asciiname":"Nagarayama",
    "gn:country_code":"JP",
    "gn:dem":85,
    "gn:feature_class":"P",
    "gn:feature_code":"PPL",
    "gn:name":"Nagarayama",
    "gn:population":0,
    "gn:timezone":"Asia/Tokyo",
    "iso:country":"JP",
    "name:jpn_x_preferred":[
        "\u9577\u67c4\u5c71"
    ],
    "name:jpn_x_variant":[
        "\u306a\u304c\u3089\u3084\u307e",
        "\u30ca\u30ac\u30e9\u30e4\u30de"
    ],
    "wof:name":"Nagarayama",
    "wof:placetype":"locality"
},
  "geometry": {"coordinates":[140.19648999999998,35.45373],"type":"Point"}
}