{
  "type": "Feature",
  "properties": {
    "gn:admin1_code":"33.0",
    "gn:admin2_code":"1853274.0",
    "gn:asciiname":"Haji",
    "gn:country_code":"JP",
    "gn:dem":450,
    "gn:feature_class":"P",
    "gn:feature_code":"PPLL",
    "gn:name":"Haji",
    "gn:population":0,
    "gn:timezone":"Asia/Tokyo",
    "iso:country":"JP",
    "name:jpn_x_preferred":[
        "\u571f\u5e2b"
    ],
    "wof:name":"Haji",
    "wof:placetype":"locality"
},
  "geometry": {"coordinates":[130.28942000000001,33.43732],"type":"Point"}
}