{
  "type": "Feature",
  "properties": {
    "gn:admin1_code":"06",
    "gn:admin2_code":"1854843.0",
    "gn:asciiname":"Nakai",
    "gn:country_code":"JP",
    "gn:dem":27,
    "gn:feature_class":"P",
    "gn:feature_code":"PPL",
    "gn:name":"Nakai",
    "gn:population":0,
    "gn:timezone":"Asia/Tokyo",
    "iso:country":"JP",
    "name:cat_x_preferred":[
        "Nakai"
    ],
    "name:deu_x_preferred":[
        "Nakai"
    ],
    "name:fra_x_preferred":[
        "Nakai"
    ],
    "name:rus_x_preferred":[
        "\u041d\u0430\u043a\u0430\u0438"
    ],
    "name:spa_x_preferred":[
        "Nakai"
    ],
    "name:ukr_x_preferred":[
        "\u041d\u0430\u043a\u0430\u0457"
    ],
    "wof:name":"Nakai",
    "wof:placetype":"locality"
},
  "geometry": {"coordinates":[135.71068,35.4534],"type":"Point"}
}