{
  "type": "Feature",
  "properties": {
    "gn:admin1_code":"36",
    "gn:admin2_code":"7392557.0",
    "gn:asciiname":"Mitoyacho-mitoya",
    "gn:country_code":"JP",
    "gn:dem":44,
    "gn:feature_class":"P",
    "gn:feature_code":"PPL",
    "gn:name":"Mitoyach\u014d-mitoya",
    "gn:population":0,
    "gn:timezone":"Asia/Tokyo",
    "iso:country":"JP",
    "name:jpn_x_preferred":[
        "\u4e09\u5200\u5c4b\u753a\u4e09\u5200\u5c4b"
    ],
    "name:und_x_variant":[
        "Mitoyach\u014d-mitoya",
        "Mitoya"
    ],
    "wof:name":"Mitoyacho-mitoya",
    "wof:placetype":"locality"
},
  "geometry": {"coordinates":[132.86667,35.28333],"type":"Point"}
}