{
  "type": "Feature",
  "properties": {
    "gn:admin1_code":"12.0",
    "gn:admin2_code":"7428116.0",
    "gn:admin3_code":"1607.0",
    "gn:asciiname":"Shoheicho-nishidori",
    "gn:country_code":"JP",
    "gn:dem":36,
    "gn:feature_class":"P",
    "gn:feature_code":"PPL",
    "gn:name":"Sh\u014dheich\u014d-nishid\u014dri",
    "gn:population":0,
    "gn:timezone":"Asia/Tokyo",
    "iso:country":"JP",
    "name:jpn_x_preferred":[
        "\u660c\u5e73\u753a\u897f\u901a"
    ],
    "name:jpn_x_variant":[
        "\u3057\u3087\u3046\u3078\u3044\u3061\u3087\u3046\u306b\u3057\u3069\u304a\u308a",
        "\u30b7\u30e7\u30a6\u30d8\u30a4\u30c1\u30e7\u30a6\u30cb\u30b7\u30c9\u30aa\u30ea"
    ],
    "name:und_x_variant":[
        "Sh\u014dheich\u014d-nishid\u014dri"
    ],
    "wof:name":"Shoheicho-nishidori",
    "wof:placetype":"locality"
},
  "geometry": {"coordinates":[142.77438999999995,42.16832],"type":"Point"}
}