{
  "type": "Feature",
  "properties": {
    "gn:admin1_code":"16.0",
    "gn:admin2_code":"2128940.0",
    "gn:asciiname":"Kaijo",
    "gn:country_code":"JP",
    "gn:dem":217,
    "gn:feature_class":"P",
    "gn:feature_code":"PPL",
    "gn:name":"Kaij\u014d",
    "gn:population":0,
    "gn:timezone":"Asia/Tokyo",
    "iso:country":"JP",
    "name:jpn_x_preferred":[
        "\u6d77\u4e0a"
    ],
    "name:jpn_x_variant":[
        "\u304b\u3044\u3058\u3087\u3046",
        "\u30ab\u30a4\u30b8\u30e7\u30a6"
    ],
    "name:und_x_variant":[
        "Kaij\u014d"
    ],
    "wof:name":"Kaijo",
    "wof:placetype":"locality"
},
  "geometry": {"coordinates":[141.13516999999999,40.16689],"type":"Point"}
}