{
  "type": "Feature",
  "properties": {
    "gn:admin1_code":"20",
    "gn:admin2_code":"1855637.0",
    "gn:asciiname":"Gomenmachi",
    "gn:country_code":"JP",
    "gn:dem":11,
    "gn:feature_class":"P",
    "gn:feature_code":"PPL",
    "gn:name":"Gomenmachi",
    "gn:population":0,
    "gn:timezone":"Asia/Tokyo",
    "iso:country":"JP",
    "name:jpn_x_preferred":[
        "\u5fa1\u514d\u753a"
    ],
    "name:und_x_variant":[
        "Gomen"
    ],
    "wof:name":"Gomenmachi",
    "wof:placetype":"locality"
},
  "geometry": {"coordinates":[133.64046000000002,33.57435],"type":"Point"}
}