{
  "type": "Feature",
  "properties": {
    "gn:admin1_code":"11",
    "gn:admin2_code":"1862821.0",
    "gn:asciiname":"Takayacho-shiraichi",
    "gn:country_code":"JP",
    "gn:dem":248,
    "gn:feature_class":"P",
    "gn:feature_code":"PPL",
    "gn:name":"Takayach\u014d-shiraichi",
    "gn:population":0,
    "gn:timezone":"Asia/Tokyo",
    "iso:country":"JP",
    "name:jpn_x_preferred":[
        "\u9ad8\u5c4b\u753a\u767d\u5e02"
    ],
    "name:und_x_variant":[
        "Takayach\u014d-shiraichi",
        "Shiraichi"
    ],
    "wof:name":"Takayacho-shiraichi",
    "wof:placetype":"locality"
},
  "geometry": {"coordinates":[132.81941,34.45845],"type":"Point"}
}