{
  "type": "Feature",
  "properties": {
    "iso:country":"JP",
    "name:eng_x_preferred":[
        "Showachuo 4 Chome"
    ],
    "name:eng_x_variant":[
        "Shouwachuuou 4 Choume",
        "Showachuo 4 Chome"
    ],
    "name:jpn_x_preferred":[
        "\uff14\u4e01\u76ee"
    ],
    "name:jpn_x_variant":[
        "\u3057\u3087\u3046\u308f\u3061\u3085\u3046\u304a\u3046 \uff14\u3061\u3087\u3046\u3081",
        "\u662d\u548c\u4e2d\u592e \uff14\u4e01\u76ee",
        "\uff14\u3061\u3087\u3046\u3081"
    ],
    "name:unk_x_variant":[
        "\uff14\u4e01\u76ee"
    ],
    "qs:gn_local":0,
    "qs:local_max":400,
    "qs:local_sum":812,
    "qs:localhoods":16,
    "qs:name":"\uff14\u4e01\u76ee",
    "qs:name_adm0":"\u65e5\u672c",
    "qs:name_adm1":"\u5317\u6d77\u9053",
    "qs:name_en":"Showachuo 4 Chome",
    "qs:name_lau":"\u662d\u548c\u4e2d\u592e",
    "qs:name_local":"\u91e7\u8def\u5e02",
    "qs:photo_max":6,
    "qs:photo_sum":11,
    "qs:placetype":"Suburb",
    "qs:quad_count":3,
    "qs:woe_adm0":23424856,
    "qs:woe_adm1":7153351,
    "qs:woe_adm2":0,
    "qs:woe_lau":28380898,
    "qs:woe_local":1117640,
    "qs:woe_ver":"7.10.0",
    "wof:lang":[
        "jpn"
    ],
    "wof:name":"\uff14\u4e01\u76ee",
    "wof:placetype":"neighbourhood"
},
  "geometry": {"coordinates":[144.35910000000001,43.024546],"type":"Point"}
}