{
  "type": "Feature",
  "properties": {
    "iso:country":"JP",
    "name:eng_x_preferred":[
        "Uetakecho 2 Chome"
    ],
    "name:eng_x_variant":[
        "Uetakechou 2 Choume",
        "Uetakecho 2 Chome"
    ],
    "name:jpn_x_preferred":[
        "\uff12\u4e01\u76ee"
    ],
    "name:jpn_x_variant":[
        "\u3046\u3048\u305f\u3051\u3061\u3087\u3046 \uff12\u3061\u3087\u3046\u3081",
        "\u690d\u7af9\u753a \uff12\u4e01\u76ee",
        "\uff12\u3061\u3087\u3046\u3081"
    ],
    "qs:gn_local":0,
    "qs:local_max":581,
    "qs:local_sum":6772,
    "qs:localhoods":52,
    "qs:name":"\uff12\u4e01\u76ee",
    "qs:name_adm0":"\u65e5\u672c",
    "qs:name_adm1":"\u57fc\u7389\u770c",
    "qs:name_adm2":"\u5317\u533a",
    "qs:name_en":"Uetakecho 2 Chome",
    "qs:name_lau":"\u690d\u7af9\u753a",
    "qs:name_local":"\u3055\u3044\u305f\u307e\u5e02",
    "qs:photo_max":17,
    "qs:photo_sum":33,
    "qs:placetype":"Suburb",
    "qs:quad_count":3,
    "qs:woe_adm0":23424856,
    "qs:woe_adm1":2345883,
    "qs:woe_adm2":24851614,
    "qs:woe_lau":28407643,
    "qs:woe_local":1116753,
    "qs:woe_ver":"7.10.0",
    "wof:lang":[
        "jpn"
    ],
    "wof:name":"\uff12\u4e01\u76ee",
    "wof:placetype":"neighbourhood"
},
  "geometry": {"coordinates":[139.62260599999999,35.93212],"type":"Point"}
}