{
  "type": "Feature",
  "properties": {
    "gn:admin1_code":"19.0",
    "gn:admin2_code":"1865011.0",
    "gn:admin3_code":"14364.0",
    "gn:asciiname":"Yosawa",
    "gn:country_code":"JP",
    "gn:dem":191,
    "gn:feature_class":"P",
    "gn:feature_code":"PPLL",
    "gn:name":"Y\u014dsawa",
    "gn:population":0,
    "gn:timezone":"Asia/Tokyo",
    "iso:country":"JP",
    "name:jpn_x_preferred":[
        "\u7528\u6ca2\u3000"
    ],
    "name:und_x_variant":[
        "Y\u014dsawa"
    ],
    "wof:name":"Yosawa",
    "wof:placetype":"locality"
},
  "geometry": {"coordinates":[139.03516000000002,35.38366],"type":"Point"}
}