{
  "type": "Feature",
  "properties": {
    "gn:admin1_code":"4.0",
    "gn:admin2_code":"2112663.0",
    "gn:asciiname":"Asai-komukai",
    "gn:country_code":"JP",
    "gn:dem":11,
    "gn:feature_class":"P",
    "gn:feature_code":"PPL",
    "gn:name":"Asai-komukai",
    "gn:population":0,
    "gn:timezone":"Asia/Tokyo",
    "iso:country":"JP",
    "name:jpn_x_preferred":[
        "\u6d45\u4e95\u5c0f\u5411"
    ],
    "name:jpn_x_variant":[
        "\u3042\u3055\u3044\u3053\u3080\u304b\u3044",
        "\u30a2\u30b5\u30a4\u30b3\u30e0\u30ab\u30a4"
    ],
    "wof:name":"Asai-komukai",
    "wof:placetype":"locality"
},
  "geometry": {"coordinates":[140.11426,35.46827000000001],"type":"Point"}
}