{
  "type": "Feature",
  "properties": {
    "gn:admin1_code":"29.0",
    "gn:admin2_code":"7468179.0",
    "gn:asciiname":"Horikoshi",
    "gn:country_code":"JP",
    "gn:dem":12,
    "gn:feature_class":"P",
    "gn:feature_code":"PPL",
    "gn:name":"Horikoshi",
    "gn:population":0,
    "gn:timezone":"Asia/Tokyo",
    "iso:country":"JP",
    "name:jpn_x_preferred":[
        "\u5800\u8d8a"
    ],
    "wof:name":"Horikoshi",
    "wof:placetype":"locality"
},
  "geometry": {"coordinates":[139.22971999999999,37.80635],"type":"Point"}
}