{
  "type": "Feature",
  "properties": {
    "gn:admin1_code":"24.0",
    "gn:admin2_code":"2111130.0",
    "gn:admin3_code":"4322.0",
    "gn:asciiname":"Hosokura",
    "gn:country_code":"JP",
    "gn:dem":194,
    "gn:feature_class":"P",
    "gn:feature_code":"PPLL",
    "gn:name":"Hosokura",
    "gn:population":0,
    "gn:timezone":"Asia/Tokyo",
    "iso:country":"JP",
    "name:jpn_x_preferred":[
        "\u7d30\u5009"
    ],
    "wof:name":"Hosokura",
    "wof:placetype":"locality"
},
  "geometry": {"coordinates":[140.76667,38.15],"type":"Point"}
}