{
  "type": "Feature",
  "properties": {
    "gn:admin1_code":"19.0",
    "gn:admin2_code":"1848350.0",
    "gn:admin3_code":"14102.0",
    "gn:asciiname":"Takashimacho",
    "gn:country_code":"JP",
    "gn:dem":37,
    "gn:feature_class":"P",
    "gn:feature_code":"PPL",
    "gn:name":"Takashimach\u014d",
    "gn:population":0,
    "gn:timezone":"Asia/Tokyo",
    "iso:country":"JP",
    "name:jpn_x_preferred":[
        "\u9ad8\u5cf6\u753a"
    ],
    "name:jpn_x_variant":[
        "\u305f\u304b\u3057\u307e\u3061\u3087\u3046",
        "\u30bf\u30ab\u30b7\u30de\u30c1\u30e7\u30a6"
    ],
    "name:und_x_variant":[
        "Takashimach\u014d"
    ],
    "wof:name":"Takashimacho",
    "wof:placetype":"locality"
},
  "geometry": {"coordinates":[139.62233000000001,35.47206],"type":"Point"}
}