{
  "type": "Feature",
  "properties": {
    "gn:admin1_code":"13",
    "gn:admin2_code":"1859161.0",
    "gn:admin3_code":"28110.0",
    "gn:asciiname":"Tsutsuicho",
    "gn:country_code":"JP",
    "gn:dem":15,
    "gn:feature_class":"P",
    "gn:feature_code":"PPL",
    "gn:name":"Tsutsuich\u014d",
    "gn:population":0,
    "gn:timezone":"Asia/Tokyo",
    "iso:country":"JP",
    "name:jpn_x_preferred":[
        "\u7b52\u4e95\u753a"
    ],
    "name:und_x_variant":[
        "Tsutsiu-cho",
        "Tsutsuich\u014d"
    ],
    "wof:name":"Tsutsuicho",
    "wof:placetype":"locality"
},
  "geometry": {"coordinates":[135.20876999999999,34.70324],"type":"Point"}
}