{
  "type": "Feature",
  "properties": {
    "gn:admin1_code":"36.0",
    "gn:admin2_code":"1854750.0",
    "gn:asciiname":"Yuminato",
    "gn:country_code":"JP",
    "gn:dem":25,
    "gn:feature_class":"P",
    "gn:feature_code":"PPL",
    "gn:name":"Yuminato",
    "gn:population":0,
    "gn:timezone":"Asia/Tokyo",
    "iso:country":"JP",
    "name:jpn_x_preferred":[
        "\u6e6f\u6e4a"
    ],
    "wof:name":"Yuminato",
    "wof:placetype":"locality"
},
  "geometry": {"coordinates":[132.36245,35.11046],"type":"Point"}
}