{
  "type": "Feature",
  "properties": {
    "gn:admin1_code":"3.0",
    "gn:admin2_code":"2130200.0",
    "gn:asciiname":"Kanegasawa",
    "gn:country_code":"JP",
    "gn:dem":48,
    "gn:feature_class":"P",
    "gn:feature_code":"PPL",
    "gn:name":"Kanegasawa",
    "gn:population":0,
    "gn:timezone":"Asia/Tokyo",
    "iso:country":"JP",
    "name:jpn_x_preferred":[
        "\u91d1\u30f6\u6ca2"
    ],
    "name:jpn_x_variant":[
        "\u304b\u306d\u304c\u3055\u308f",
        "\u30ab\u30cd\u30ac\u30b5\u30ef"
    ],
    "wof:name":"Kanegasawa",
    "wof:placetype":"locality"
},
  "geometry": {"coordinates":[141.38038,40.51288],"type":"Point"}
}