{
  "type": "Feature",
  "properties": {
    "gn:admin1_code":"47",
    "gn:admin2_code":"1863626.0",
    "gn:asciiname":"Futenma",
    "gn:country_code":"JP",
    "gn:dem":75,
    "gn:feature_class":"P",
    "gn:feature_code":"PPL",
    "gn:name":"Futenma",
    "gn:population":0,
    "gn:timezone":"Asia/Tokyo",
    "iso:country":"JP",
    "name:jpn_x_preferred":[
        "\u666e\u5929\u9593"
    ],
    "name:und_x_variant":[
        "Zentemma",
        "Futenma",
        "Futima",
        "Camp Futema",
        "Futema",
        "Futemma"
    ],
    "wof:name":"Futenma",
    "wof:placetype":"locality"
},
  "geometry": {"coordinates":[127.77306000000002,26.28722],"type":"Point"}
}