{
  "type": "Feature",
  "properties": {
    "gn:admin1_code":"2.0",
    "gn:admin2_code":"2129593.0",
    "gn:asciiname":"Towada-oyu",
    "gn:country_code":"JP",
    "gn:dem":468,
    "gn:feature_class":"P",
    "gn:feature_code":"PPL",
    "gn:name":"Towada-oyu",
    "gn:population":0,
    "gn:timezone":"Asia/Tokyo",
    "iso:country":"JP",
    "name:jpn_x_preferred":[
        "\u5341\u548c\u7530\u5927\u6e6f"
    ],
    "name:jpn_x_variant":[
        "\u3068\u308f\u3060\u304a\u3086",
        "\u30c8\u30ef\u30c0\u30aa\u30e6"
    ],
    "wof:name":"Towada-oyu",
    "wof:placetype":"locality"
},
  "geometry": {"coordinates":[140.87638000000001,40.38218],"type":"Point"}
}