{
  "type": "Feature",
  "properties": {
    "gn:admin1_code":"37.0",
    "gn:admin2_code":"7418320.0",
    "gn:asciiname":"Mikado",
    "gn:country_code":"JP",
    "gn:dem":21,
    "gn:feature_class":"P",
    "gn:feature_code":"PPL",
    "gn:name":"Mikado",
    "gn:population":0,
    "gn:timezone":"Asia/Tokyo",
    "iso:country":"JP",
    "name:jpn_x_preferred":[
        "\u5fa1\u9580"
    ],
    "wof:name":"Mikado",
    "wof:placetype":"locality"
},
  "geometry": {"coordinates":[138.94460000000001,35.01996],"type":"Point"}
}