{
  "type": "Feature",
  "properties": {
    "gn:admin1_code":"3.0",
    "gn:admin2_code":"2130056.0",
    "gn:asciiname":"Otomo",
    "gn:country_code":"JP",
    "gn:dem":19,
    "gn:feature_class":"P",
    "gn:feature_code":"PPL",
    "gn:name":"Otomo",
    "gn:population":0,
    "gn:timezone":"Asia/Tokyo",
    "iso:country":"JP",
    "name:jpn_x_preferred":[
        "\u5c0f\u53cb"
    ],
    "name:jpn_x_variant":[
        "\u304a\u3068\u3082",
        "\u30aa\u30c8\u30e2"
    ],
    "wof:name":"Otomo",
    "wof:placetype":"locality"
},
  "geometry": {"coordinates":[140.40932000000001,40.71082],"type":"Point"}
}