{
  "type": "Feature",
  "properties": {
    "gn:admin1_code":"21.0",
    "gn:admin2_code":"7412705.0",
    "gn:admin3_code":"43482.0",
    "gn:asciiname":"Iwaigawachi",
    "gn:country_code":"JP",
    "gn:dem":181,
    "gn:feature_class":"P",
    "gn:feature_code":"PPLL",
    "gn:name":"Iwaigawachi",
    "gn:population":0,
    "gn:timezone":"Asia/Tokyo",
    "iso:country":"JP",
    "name:jpn_x_preferred":[
        "\u5ca9\u5c4b\u5ddd\u5185"
    ],
    "name:jpn_x_variant":[
        "\u3044\u308f\u3044\u304c\u308f\u3061",
        "\u30a4\u30ef\u30a4\u30ac\u30ef\u30c1"
    ],
    "wof:name":"Iwaigawachi",
    "wof:placetype":"locality"
},
  "geometry": {"coordinates":[130.58688999999998,32.35305],"type":"Point"}
}