{
  "type": "Feature",
  "properties": {
    "gn:admin1_code":"3.0",
    "gn:admin2_code":"2129754.0",
    "gn:admin3_code":"2405.0",
    "gn:asciiname":"Tsubokezawa",
    "gn:country_code":"JP",
    "gn:dem":65,
    "gn:feature_class":"P",
    "gn:feature_code":"PPL",
    "gn:name":"Tsubokezawa",
    "gn:population":0,
    "gn:timezone":"Asia/Tokyo",
    "iso:country":"JP",
    "name:jpn_x_preferred":[
        "\u576a\u6bdb\u6ca2"
    ],
    "name:jpn_x_variant":[
        "\u3064\u307c\u3051\u3056\u308f",
        "\u30c4\u30dc\u30b1\u30b6\u30ef"
    ],
    "wof:name":"Tsubokezawa",
    "wof:placetype":"locality"
},
  "geometry": {"coordinates":[141.33022,40.63505],"type":"Point"}
}