{
  "type": "Feature",
  "properties": {
    "gn:admin1_code":"2.0",
    "gn:admin2_code":"7443149.0",
    "gn:asciiname":"Ota",
    "gn:country_code":"JP",
    "gn:dem":93,
    "gn:feature_class":"P",
    "gn:feature_code":"PPL",
    "gn:name":"\u014cta",
    "gn:population":0,
    "gn:timezone":"Asia/Tokyo",
    "iso:country":"JP",
    "name:jpn_x_preferred":[
        "\u592a\u7530"
    ],
    "name:und_x_variant":[
        "\u014cta"
    ],
    "wof:name":"Ota",
    "wof:placetype":"locality"
},
  "geometry": {"coordinates":[140.6216,39.51694000000001],"type":"Point"}
}