{
  "type": "Feature",
  "properties": {
    "gn:admin1_code":"30",
    "gn:admin2_code":"7279571.0",
    "gn:asciiname":"Furuichi",
    "gn:country_code":"JP",
    "gn:dem":44,
    "gn:feature_class":"P",
    "gn:feature_code":"PPL",
    "gn:name":"Furuichi",
    "gn:population":0,
    "gn:timezone":"Asia/Tokyo",
    "iso:country":"JP",
    "wof:name":"Furuichi",
    "wof:placetype":"locality"
},
  "geometry": {"coordinates":[131.71666999999999,33.48333],"type":"Point"}
}