{
  "type": "Feature",
  "properties": {
    "gn:admin1_code":"23.0",
    "gn:admin2_code":"7417704.0",
    "gn:admin3_code":"24443.0",
    "gn:asciiname":"Kuzu",
    "gn:country_code":"JP",
    "gn:dem":315,
    "gn:feature_class":"P",
    "gn:feature_code":"PPL",
    "gn:name":"Kuzu",
    "gn:population":0,
    "gn:timezone":"Asia/Tokyo",
    "iso:country":"JP",
    "name:jpn_x_preferred":[
        "\u4e45\u8c46"
    ],
    "wof:name":"Kuzu",
    "wof:placetype":"locality"
},
  "geometry": {"coordinates":[136.21271000000002,34.28248],"type":"Point"}
}