{
  "type": "Feature",
  "properties": {
    "gn:admin1_code":"16.0",
    "gn:admin2_code":"2128940.0",
    "gn:asciiname":"Kamimachi",
    "gn:country_code":"JP",
    "gn:dem":108,
    "gn:feature_class":"P",
    "gn:feature_code":"PPL",
    "gn:name":"Kamimachi",
    "gn:population":0,
    "gn:timezone":"Asia/Tokyo",
    "iso:country":"JP",
    "name:jpn_x_preferred":[
        "\u4e0a\u753a"
    ],
    "name:jpn_x_variant":[
        "\u304b\u307f\u307e\u3061",
        "\u30ab\u30df\u30de\u30c1"
    ],
    "wof:name":"Kamimachi",
    "wof:placetype":"locality"
},
  "geometry": {"coordinates":[141.29809,40.30584],"type":"Point"}
}