{
  "type": "Feature",
  "properties": {
    "gn:admin1_code":"34.0",
    "gn:admin2_code":"1849187.0",
    "gn:admin3_code":"11107.0",
    "gn:asciiname":"Kizaki",
    "gn:country_code":"JP",
    "gn:dem":17,
    "gn:feature_class":"P",
    "gn:feature_code":"PPL",
    "gn:name":"Kizaki",
    "gn:population":0,
    "gn:timezone":"Asia/Tokyo",
    "iso:country":"JP",
    "name:jpn_x_preferred":[
        "\u6728\u5d0e"
    ],
    "name:jpn_x_variant":[
        "\u304d\u3056\u304d",
        "\u30ad\u30b6\u30ad"
    ],
    "wof:name":"Kizaki",
    "wof:placetype":"locality"
},
  "geometry": {"coordinates":[139.66101,35.88719000000001],"type":"Point"}
}