{
  "type": "Feature",
  "properties": {
    "gn:admin1_code":"21.0",
    "gn:admin2_code":"1848441.0",
    "gn:asciiname":"Otogawa",
    "gn:country_code":"JP",
    "gn:dem":277,
    "gn:feature_class":"P",
    "gn:feature_code":"PPLL",
    "gn:name":"Otogawa",
    "gn:population":0,
    "gn:timezone":"Asia/Tokyo",
    "iso:country":"JP",
    "name:jpn_x_preferred":[
        "\u4e59\u5ddd"
    ],
    "name:jpn_x_variant":[
        "\u304a\u3068\u304c\u308f",
        "\u30aa\u30c8\u30ac\u30ef"
    ],
    "wof:name":"Otogawa",
    "wof:placetype":"locality"
},
  "geometry": {"coordinates":[130.80462,32.54187],"type":"Point"}
}