{
  "type": "Feature",
  "properties": {
    "gn:admin1_code":"3.0",
    "gn:admin2_code":"2128302.0",
    "gn:admin3_code":"2443.0",
    "gn:asciiname":"Tsuchibashi-michinoue",
    "gn:country_code":"JP",
    "gn:dem":122,
    "gn:feature_class":"P",
    "gn:feature_code":"PPL",
    "gn:name":"Tsuchibashi-michinoue",
    "gn:population":0,
    "gn:timezone":"Asia/Tokyo",
    "iso:country":"JP",
    "name:jpn_x_preferred":[
        "\u571f\u6a4b\u9053\u30ce\u4e0a"
    ],
    "name:jpn_x_variant":[
        "\u3064\u3061\u3070\u3057\u307f\u3061\u306e\u3046\u3048",
        "\u30c4\u30c1\u30d0\u30b7\u30df\u30c1\u30ce\u30a6\u30a8"
    ],
    "wof:name":"Tsuchibashi-michinoue",
    "wof:placetype":"locality"
},
  "geometry": {"coordinates":[141.15583999999996,40.34404],"type":"Point"}
}