{
  "type": "Feature",
  "properties": {
    "gn:admin1_code":"31",
    "gn:admin2_code":"7405225.0",
    "gn:asciiname":"Shoden",
    "gn:country_code":"JP",
    "gn:dem":174,
    "gn:feature_class":"P",
    "gn:feature_code":"PPL",
    "gn:name":"Sh\u014dden",
    "gn:population":0,
    "gn:timezone":"Asia/Tokyo",
    "iso:country":"JP",
    "name:und_x_variant":[
        "Sh\u014dden"
    ],
    "wof:name":"Shoden",
    "wof:placetype":"locality"
},
  "geometry": {"coordinates":[133.46666999999999,34.96667],"type":"Point"}
}