{
  "type": "Feature",
  "properties": {
    "gn:admin1_code":"21.0",
    "gn:admin2_code":"7412705.0",
    "gn:admin3_code":"43482.0",
    "gn:asciiname":"Akasaka",
    "gn:country_code":"JP",
    "gn:dem":160,
    "gn:feature_class":"P",
    "gn:feature_code":"PPLL",
    "gn:name":"Akasaka",
    "gn:population":0,
    "gn:timezone":"Asia/Tokyo",
    "iso:country":"JP",
    "name:deu_x_preferred":[
        "Akasaka"
    ],
    "name:fra_x_preferred":[
        "Akasaka"
    ],
    "name:ita_x_preferred":[
        "Akasaka"
    ],
    "name:jpn_x_preferred":[
        "\u8d64\u5742"
    ],
    "name:jpn_x_variant":[
        "\u3042\u304b\u3055\u304b",
        "\u30a2\u30ab\u30b5\u30ab"
    ],
    "name:kor_x_preferred":[
        "\uc544\uce74\uc0ac\uce74"
    ],
    "name:rus_x_preferred":[
        "\u0410\u043a\u0430\u0441\u0430\u043a\u0430"
    ],
    "name:ukr_x_preferred":[
        "\u0410\u043a\u0430\u0441\u0430\u043a\u0430"
    ],
    "wof:name":"Akasaka",
    "wof:placetype":"locality"
},
  "geometry": {"coordinates":[130.54397,32.31225],"type":"Point"}
}