{
  "type": "Feature",
  "properties": {
    "gn:admin1_code":"24.0",
    "gn:admin2_code":"2112092.0",
    "gn:asciiname":"Okawaguchi-konse",
    "gn:country_code":"JP",
    "gn:dem":146,
    "gn:feature_class":"P",
    "gn:feature_code":"PPLL",
    "gn:name":"\u014ckawaguchi-konse",
    "gn:population":0,
    "gn:timezone":"Asia/Tokyo",
    "iso:country":"JP",
    "name:jpn_x_preferred":[
        "\u5927\u5ddd\u53e3\u5c0f\u53e4"
    ],
    "name:und_x_variant":[
        "\u014ckawaguchi-konse",
        "\u014ckawaguchi"
    ],
    "wof:name":"Okawaguchi-konse",
    "wof:placetype":"locality"
},
  "geometry": {"coordinates":[140.89250000000001,38.735],"type":"Point"}
}