{
  "type": "Feature",
  "properties": {
    "gn:country":"JP",
    "gn:fcode":"ADM3",
    "gn:population":0,
    "iso:country":"JP",
    "name:jpn_x_preferred":[
        "\u5f53\u5225\u753a"
    ],
    "name:jpn_x_variant":[
        "\u3068\u3046\u3079\u3064\u3061\u3087\u3046"
    ],
    "qs:name":"Toubetsu-ch\u014d",
    "qs:photos_9r":0,
    "qs:photos_sr":0,
    "qs:pop_sr":"0",
    "wof:name":"Toubetsu-ch\u014d",
    "wof:placetype":"localadmin",
    "wof:population":0
},
  "geometry": {"coordinates":[141.56273999999999,43.36359],"type":"Point"}
}