{
  "type": "Feature",
  "properties": {
    "gn:admin1_code":"6.0",
    "gn:admin2_code":"1863982.0",
    "gn:asciiname":"Otoshicho",
    "gn:country_code":"JP",
    "gn:dem":17,
    "gn:feature_class":"P",
    "gn:feature_code":"PPL",
    "gn:name":"\u014ctoshich\u014d",
    "gn:population":0,
    "gn:timezone":"Asia/Tokyo",
    "iso:country":"JP",
    "name:jpn_x_preferred":[
        "\u5927\u5e74\u753a"
    ],
    "name:und_x_variant":[
        "\u014ctoshich\u014d"
    ],
    "wof:name":"Otoshicho",
    "wof:placetype":"locality"
},
  "geometry": {"coordinates":[136.14143000000001,36.1119],"type":"Point"}
}