{
  "type": "Feature",
  "properties": {
    "gn:admin1_code":"34.0",
    "gn:admin2_code":"7464124.0",
    "gn:asciiname":"Kuzume",
    "gn:country_code":"JP",
    "gn:dem":11,
    "gn:feature_class":"P",
    "gn:feature_code":"PPL",
    "gn:name":"Kuzume",
    "gn:population":0,
    "gn:timezone":"Asia/Tokyo",
    "iso:country":"JP",
    "name:jpn_x_preferred":[
        "\u845b\u6885"
    ],
    "name:jpn_x_variant":[
        "\u304f\u305a\u3081",
        "\u30af\u30ba\u30e1"
    ],
    "wof:name":"Kuzume",
    "wof:placetype":"locality"
},
  "geometry": {"coordinates":[139.65482,36.094],"type":"Point"}
}