{
  "type": "Feature",
  "properties": {
    "gn:admin1_code":"7.0",
    "gn:admin2_code":"7406950.0",
    "gn:admin3_code":"40625.0",
    "gn:asciiname":"Higashiko",
    "gn:country_code":"JP",
    "gn:dem":194,
    "gn:feature_class":"P",
    "gn:feature_code":"PPLL",
    "gn:name":"Higashik\u014d",
    "gn:population":0,
    "gn:timezone":"Asia/Tokyo",
    "iso:country":"JP",
    "name:jpn_x_preferred":[
        "\u6771\u8b1b"
    ],
    "name:und_x_variant":[
        "Higashik\u014d"
    ],
    "wof:name":"Higashiko",
    "wof:placetype":"locality"
},
  "geometry": {"coordinates":[130.95182,33.5744],"type":"Point"}
}