{
  "type": "Feature",
  "properties": {
    "iso:country":"JP",
    "name:eng_x_preferred":[
        "Shichikuyama 6 Chome"
    ],
    "name:eng_x_variant":[
        "Shichikuyama 6 Choume",
        "Shichikuyama 6 Chome"
    ],
    "name:jpn_x_preferred":[
        "\uff16\u4e01\u76ee"
    ],
    "name:jpn_x_variant":[
        "\u3057\u3061\u304f\u3084\u307e \uff16\u3061\u3087\u3046\u3081",
        "\u7d2b\u7af9\u5c71 \uff16\u4e01\u76ee",
        "\uff16\u3061\u3087\u3046\u3081"
    ],
    "qs:gn_local":0,
    "qs:local_max":1296,
    "qs:local_sum":6373,
    "qs:localhoods":29,
    "qs:name":"\uff16\u4e01\u76ee",
    "qs:name_adm0":"\u65e5\u672c",
    "qs:name_adm1":"\u65b0\u6f5f\u770c",
    "qs:name_adm2":"\u4e2d\u592e\u533a",
    "qs:name_en":"Shichikuyama 6 Chome",
    "qs:name_lau":"\u7d2b\u7af9\u5c71",
    "qs:name_local":"\u65b0\u6f5f\u5e02",
    "qs:photo_max":5,
    "qs:photo_sum":5,
    "qs:placetype":"Suburb",
    "qs:quad_count":1,
    "qs:woe_adm0":23424856,
    "qs:woe_adm1":2345878,
    "qs:woe_adm2":55805803,
    "qs:woe_lau":55807814,
    "qs:woe_local":1117881,
    "qs:woe_ver":"7.10.0",
    "wof:lang":[
        "jpn"
    ],
    "wof:name":"\uff16\u4e01\u76ee",
    "wof:placetype":"neighbourhood"
},
  "geometry": {"coordinates":[139.067688,37.898697],"type":"Point"}
}