{
  "type": "Feature",
  "properties": {
    "gn:admin1_code":"37",
    "gn:admin2_code":"1852349.0",
    "gn:asciiname":"Shirahama",
    "gn:country_code":"JP",
    "gn:dem":88,
    "gn:feature_class":"P",
    "gn:feature_code":"PPL",
    "gn:name":"Shirahama",
    "gn:population":0,
    "gn:timezone":"Asia/Tokyo",
    "iso:country":"JP",
    "name:jpn_x_preferred":[
        "\u767d\u6d5c"
    ],
    "name:und_x_variant":[
        "Sinohama",
        "Shirahama"
    ],
    "wof:name":"Shirahama",
    "wof:placetype":"locality"
},
  "geometry": {"coordinates":[138.96876,34.70275],"type":"Point"}
}