{
  "type": "Feature",
  "properties": {
    "gn:admin1_code":"7.0",
    "gn:admin2_code":"1856443.0",
    "gn:asciiname":"Miyata",
    "gn:country_code":"JP",
    "gn:dem":20,
    "gn:feature_class":"P",
    "gn:feature_code":"PPL",
    "gn:name":"Miyata",
    "gn:population":0,
    "gn:timezone":"Asia/Tokyo",
    "iso:country":"JP",
    "name:deu_x_preferred":[
        "Miyata K\u014dgy\u014d"
    ],
    "name:jpn_x_preferred":[
        "\u5bae\u7530"
    ],
    "name:jpn_x_variant":[
        "\u30e2\u30ea\u30bf\u5bae\u7530\u5de5\u696d"
    ],
    "name:mlg_x_preferred":[
        "Miyata"
    ],
    "name:nld_x_preferred":[
        "Miyata"
    ],
    "wof:name":"Miyata",
    "wof:placetype":"locality"
},
  "geometry": {"coordinates":[130.56638999999998,33.79447],"type":"Point"}
}