{
  "type": "Feature",
  "properties": {
    "gn:admin1_code":"19",
    "gn:admin2_code":"1863429.0",
    "gn:asciiname":"Mikurube",
    "gn:country_code":"JP",
    "gn:dem":249,
    "gn:feature_class":"P",
    "gn:feature_code":"PPL",
    "gn:name":"Mikurube",
    "gn:population":0,
    "gn:timezone":"Asia/Tokyo",
    "iso:country":"JP",
    "name:jpn_x_preferred":[
        "\u4e09\u5efb\u90e8"
    ],
    "name:und_x_variant":[
        "Mikuruba"
    ],
    "wof:name":"Mikurube",
    "wof:placetype":"locality"
},
  "geometry": {"coordinates":[139.16459,35.40011],"type":"Point"}
}