{
  "type": "Feature",
  "properties": {
    "gn:admin1_code":"40.0",
    "gn:admin2_code":"1851510.0",
    "gn:asciiname":"Takaido-higashi",
    "gn:country_code":"JP",
    "gn:dem":48,
    "gn:feature_class":"P",
    "gn:feature_code":"PPL",
    "gn:name":"Takaido-higashi",
    "gn:population":0,
    "gn:timezone":"Asia/Tokyo",
    "iso:country":"JP",
    "name:jpn_x_preferred":[
        "\u9ad8\u4e95\u6238\u6771"
    ],
    "wof:name":"Takaido-higashi",
    "wof:placetype":"locality"
},
  "geometry": {"coordinates":[139.61999,35.68616],"type":"Point"}
}