{
  "type": "Feature",
  "properties": {
    "gn:admin1_code":"3.0",
    "gn:admin2_code":"8534376.0",
    "gn:admin3_code":"2321.0",
    "gn:asciiname":"Ryoshimachi",
    "gn:country_code":"JP",
    "gn:dem":9,
    "gn:feature_class":"P",
    "gn:feature_code":"PPL",
    "gn:name":"Ry\u014dshimachi",
    "gn:population":0,
    "gn:timezone":"Asia/Tokyo",
    "iso:country":"JP",
    "name:jpn_x_preferred":[
        "\u6f01\u5e2b\u753a"
    ],
    "name:jpn_x_variant":[
        "\u308a\u3087\u3046\u3057\u307e\u3061",
        "\u30ea\u30e7\u30a6\u30b7\u30de\u30c1"
    ],
    "name:und_x_variant":[
        "Ry\u014dshimachi"
    ],
    "wof:name":"Ryoshimachi",
    "wof:placetype":"locality"
},
  "geometry": {"coordinates":[140.19990000000001,40.78275],"type":"Point"}
}