{
  "type": "Feature",
  "properties": {
    "gn:admin1_code":"29.0",
    "gn:admin2_code":"1855427.0",
    "gn:admin3_code":"15108.0",
    "gn:asciiname":"Ishize",
    "gn:country_code":"JP",
    "gn:dem":24,
    "gn:feature_class":"P",
    "gn:feature_code":"PPL",
    "gn:name":"Ishize",
    "gn:population":0,
    "gn:timezone":"Asia/Tokyo",
    "iso:country":"JP",
    "name:jpn_x_preferred":[
        "\u77f3\u702c"
    ],
    "wof:name":"Ishize",
    "wof:placetype":"locality"
},
  "geometry": {"coordinates":[138.83763000000002,37.72295],"type":"Point"}
}