{
  "type": "Feature",
  "properties": {
    "gn:admin1_code":"26",
    "gn:admin2_code":"1852309.0",
    "gn:admin3_code":"20413.0",
    "gn:asciiname":"Hiraoka",
    "gn:country_code":"JP",
    "gn:dem":663,
    "gn:feature_class":"P",
    "gn:feature_code":"PPL",
    "gn:name":"Hiraoka",
    "gn:population":0,
    "gn:timezone":"Asia/Tokyo",
    "iso:country":"JP",
    "wof:name":"Hiraoka",
    "wof:placetype":"locality"
},
  "geometry": {"coordinates":[137.86667,35.26667],"type":"Point"}
}