{
  "type": "Feature",
  "properties": {
    "gn:admin1_code":"19",
    "gn:admin2_code":"1848350.0",
    "gn:admin3_code":"14108.0",
    "gn:asciiname":"Susakicho",
    "gn:country_code":"JP",
    "gn:dem":1,
    "gn:feature_class":"P",
    "gn:feature_code":"PPL",
    "gn:name":"Susakich\u014d",
    "gn:population":0,
    "gn:timezone":"Asia/Tokyo",
    "iso:country":"JP",
    "name:jpn_x_preferred":[
        "\u6d32\u5d0e\u753a"
    ],
    "name:jpn_x_variant":[
        "\u3059\u3055\u304d\u3061\u3087\u3046",
        "\u30b9\u30b5\u30ad\u30c1\u30e7\u30a6"
    ],
    "name:und_x_variant":[
        "Suzakich\u014d",
        "Susakich\u014d",
        "Susaki"
    ],
    "wof:name":"Susakicho",
    "wof:placetype":"locality"
},
  "geometry": {"coordinates":[139.62739999999999,35.33259],"type":"Point"}
}