{
  "type": "Feature",
  "properties": {
    "gn:admin1_code":"32.0",
    "gn:admin2_code":"1857170.0",
    "gn:admin3_code":"27382.0",
    "gn:asciiname":"Hiraishi",
    "gn:country_code":"JP",
    "gn:dem":169,
    "gn:feature_class":"P",
    "gn:feature_code":"PPL",
    "gn:name":"Hiraishi",
    "gn:population":0,
    "gn:timezone":"Asia/Tokyo",
    "iso:country":"JP",
    "name:jpn_x_preferred":[
        "\u5e73\u77f3"
    ],
    "wof:name":"Hiraishi",
    "wof:placetype":"locality"
},
  "geometry": {"coordinates":[135.65861000000001,34.49532],"type":"Point"}
}