{
  "type": "Feature",
  "properties": {
    "gn:admin1_code":"19.0",
    "gn:admin2_code":"1848350.0",
    "gn:admin3_code":"14115.0",
    "gn:asciiname":"Kasama",
    "gn:country_code":"JP",
    "gn:dem":13,
    "gn:feature_class":"P",
    "gn:feature_code":"PPL",
    "gn:name":"Kasama",
    "gn:population":0,
    "gn:timezone":"Asia/Tokyo",
    "iso:country":"JP",
    "name:ceb_x_preferred":[
        "Kasama"
    ],
    "name:deu_x_preferred":[
        "Kasama"
    ],
    "name:fas_x_preferred":[
        "\u06a9\u0627\u0632\u0627\u0645\u0627"
    ],
    "name:hun_x_preferred":[
        "Kasama"
    ],
    "name:ita_x_preferred":[
        "Kasama"
    ],
    "name:jpn_x_preferred":[
        "\u7b20\u9593"
    ],
    "name:jpn_x_variant":[
        "\u304b\u3055\u307e",
        "\u30ab\u30b5\u30de"
    ],
    "name:mlg_x_preferred":[
        "Kasama"
    ],
    "name:nld_x_preferred":[
        "Kasama"
    ],
    "name:pol_x_preferred":[
        "Kasama"
    ],
    "name:ron_x_preferred":[
        "Kasama"
    ],
    "name:rus_x_preferred":[
        "\u041a\u0430\u0441\u0430\u043c\u0430"
    ],
    "name:spa_x_preferred":[
        "Kasama"
    ],
    "name:swe_x_preferred":[
        "Kasama"
    ],
    "name:tgl_x_preferred":[
        "Kasama"
    ],
    "name:ukr_x_preferred":[
        "\u041a\u0430\u0441\u0430\u043c\u0430"
    ],
    "wof:name":"Kasama",
    "wof:placetype":"locality"
},
  "geometry": {"coordinates":[139.53613000000001,35.36083],"type":"Point"}
}