{
  "type": "Feature",
  "properties": {
    "iso:country":"JP",
    "name:eng_x_preferred":[
        "Aobacho 4 Chome"
    ],
    "name:eng_x_variant":[
        "Aobachou 4 Choume",
        "Aobacho 4 Chome"
    ],
    "name:jpn_x_preferred":[
        "\uff14\u4e01\u76ee"
    ],
    "name:jpn_x_variant":[
        "\u3042\u304a\u3070\u3061\u3087\u3046 \uff14\u3061\u3087\u3046\u3081",
        "\u9752\u8449\u753a \uff14\u4e01\u76ee",
        "\uff14\u3061\u3087\u3046\u3081"
    ],
    "qs:gn_adm0_cc":"JP",
    "qs:gn_local":7279570,
    "qs:gn_nam_loc":"\u6771\u6751\u5c71\u5e02, \u6771\u4eac\u90fd, JP",
    "qs:gn_namadm1":"40",
    "qs:local_max":1147,
    "qs:local_sum":3178,
    "qs:localhoods":10,
    "qs:name":"\uff14\u4e01\u76ee",
    "qs:name_adm0":"\u65e5\u672c",
    "qs:name_adm1":"\u6771\u4eac\u90fd",
    "qs:name_en":"Aobacho 4 Chome",
    "qs:name_lau":"\u9752\u8449\u753a",
    "qs:name_local":"\u6771\u6751\u5c71\u5e02",
    "qs:photo_max":12,
    "qs:photo_sum":12,
    "qs:placetype":"Suburb",
    "qs:quad_count":1,
    "qs:woe_adm0":23424856,
    "qs:woe_adm1":2345889,
    "qs:woe_adm2":0,
    "qs:woe_lau":28415183,
    "qs:woe_local":1108816,
    "qs:woe_ver":"7.10.0",
    "wof:lang":[
        "jpn"
    ],
    "wof:name":"\uff14\u4e01\u76ee",
    "wof:placetype":"neighbourhood"
},
  "geometry": {"coordinates":[139.50027499999999,35.765457],"type":"Point"}
}