{
  "type": "Feature",
  "properties": {
    "gn:admin1_code":"13",
    "gn:admin2_code":"1859161.0",
    "gn:admin3_code":"28109.0",
    "gn:asciiname":"Dojocho-shiota",
    "gn:country_code":"JP",
    "gn:dem":152,
    "gn:feature_class":"P",
    "gn:feature_code":"PPL",
    "gn:name":"D\u014dj\u014dch\u014d-shiota",
    "gn:population":0,
    "gn:timezone":"Asia/Tokyo",
    "iso:country":"JP",
    "name:jpn_x_preferred":[
        "\u9053\u5834\u753a\u5869\u7530"
    ],
    "name:und_x_variant":[
        "Dojokawahara",
        "D\u014dj\u014d",
        "D\u014dj\u014dch\u014d-shiota"
    ],
    "wof:name":"Dojocho-shiota",
    "wof:placetype":"locality"
},
  "geometry": {"coordinates":[135.23648,34.86949],"type":"Point"}
}