{
  "type": "Feature",
  "properties": {
    "gn:admin1_code":"21.0",
    "gn:admin2_code":"1857206.0",
    "gn:asciiname":"Gioncho",
    "gn:country_code":"JP",
    "gn:dem":29,
    "gn:feature_class":"P",
    "gn:feature_code":"PPL",
    "gn:name":"Gionch\u014d",
    "gn:population":0,
    "gn:timezone":"Asia/Tokyo",
    "iso:country":"JP",
    "name:jpn_x_preferred":[
        "\u7947\u5712\u753a"
    ],
    "name:jpn_x_variant":[
        "\u304e\u304a\u3093\u3061\u3087\u3046",
        "\u30ae\u30aa\u30f3\u30c1\u30e7\u30a6"
    ],
    "name:und_x_variant":[
        "Gionch\u014d"
    ],
    "wof:name":"Gioncho",
    "wof:placetype":"locality"
},
  "geometry": {"coordinates":[130.38453999999999,32.21187],"type":"Point"}
}