{
  "type": "Feature",
  "properties": {
    "gn:admin1_code":"36",
    "gn:admin2_code":"7392557.0",
    "gn:asciiname":"Kisukicho-yumura",
    "gn:country_code":"JP",
    "gn:dem":302,
    "gn:feature_class":"P",
    "gn:feature_code":"PPL",
    "gn:name":"Kisukich\u014d-yumura",
    "gn:population":0,
    "gn:timezone":"Asia/Tokyo",
    "iso:country":"JP",
    "name:und_x_variant":[
        "Shin-yumura",
        "Kisukich\u014d-yumura"
    ],
    "wof:name":"Kisukicho-yumura",
    "wof:placetype":"locality"
},
  "geometry": {"coordinates":[132.91666999999998,35.21667],"type":"Point"}
}