{
  "type": "Feature",
  "properties": {
    "gn:admin1_code":"20",
    "gn:admin2_code":"7405899.0",
    "gn:asciiname":"Noichicho-higashisako",
    "gn:country_code":"JP",
    "gn:dem":42,
    "gn:feature_class":"P",
    "gn:feature_code":"PPL",
    "gn:name":"Noichich\u014d-higashisako",
    "gn:population":0,
    "gn:timezone":"Asia/Tokyo",
    "iso:country":"JP",
    "name:jpn_x_preferred":[
        "\u91ce\u5e02\u753a\u6771\u4f50\u53e4"
    ],
    "name:und_x_variant":[
        "Noichich\u014d-higashisako",
        "Higashi-sako"
    ],
    "wof:name":"Noichicho-higashisako",
    "wof:placetype":"locality"
},
  "geometry": {"coordinates":[133.71046999999999,33.58723],"type":"Point"}
}