{
  "type": "Feature",
  "properties": {
    "gn:admin1_code":"22.0",
    "gn:admin2_code":"1857764.0",
    "gn:asciiname":"Sezaki",
    "gn:country_code":"JP",
    "gn:dem":21,
    "gn:feature_class":"P",
    "gn:feature_code":"PPL",
    "gn:name":"Sezaki",
    "gn:population":0,
    "gn:timezone":"Asia/Tokyo",
    "iso:country":"JP",
    "wof:name":"Sezaki",
    "wof:placetype":"locality"
},
  "geometry": {"coordinates":[135.34999999999999,35.5425],"type":"Point"}
}