{
  "type": "Feature",
  "properties": {
    "gn:admin1_code":"21.0",
    "gn:admin2_code":"1859488.0",
    "gn:asciiname":"Minamisumiyoshi",
    "gn:country_code":"JP",
    "gn:dem":72,
    "gn:feature_class":"P",
    "gn:feature_code":"PPLL",
    "gn:name":"Minamisumiyoshi",
    "gn:population":0,
    "gn:timezone":"Asia/Tokyo",
    "iso:country":"JP",
    "name:jpn_x_preferred":[
        "\u5357\u4f4f\u5409"
    ],
    "name:jpn_x_variant":[
        "\u307f\u306a\u307f\u3059\u307f\u3088\u3057",
        "\u30df\u30ca\u30df\u30b9\u30df\u30e8\u30b7"
    ],
    "wof:name":"Minamisumiyoshi",
    "wof:placetype":"locality"
},
  "geometry": {"coordinates":[130.81156999999999,32.93415],"type":"Point"}
}