{
  "type": "Feature",
  "properties": {
    "gn:admin1_code":"4.0",
    "gn:admin2_code":"8304237.0",
    "gn:asciiname":"Rokutanda",
    "gn:country_code":"JP",
    "gn:dem":24,
    "gn:feature_class":"P",
    "gn:feature_code":"PPLL",
    "gn:name":"Rokutanda",
    "gn:population":0,
    "gn:timezone":"Asia/Tokyo",
    "iso:country":"JP",
    "name:jpn_x_preferred":[
        "\u516d\u53cd\u7530"
    ],
    "name:jpn_x_variant":[
        "\u308d\u304f\u305f\u3093\u3060",
        "\u30ed\u30af\u30bf\u30f3\u30c0"
    ],
    "wof:name":"Rokutanda",
    "wof:placetype":"locality"
},
  "geometry": {"coordinates":[140.03888000000001,35.34695],"type":"Point"}
}