{
  "type": "Feature",
  "properties": {
    "gn:admin1_code":"4.0",
    "gn:admin2_code":"1855071.0",
    "gn:asciiname":"Shimosangao",
    "gn:country_code":"JP",
    "gn:dem":16,
    "gn:feature_class":"P",
    "gn:feature_code":"PPL",
    "gn:name":"Shimosangao",
    "gn:population":0,
    "gn:timezone":"Asia/Tokyo",
    "iso:country":"JP",
    "name:jpn_x_preferred":[
        "\u4e0b\u4e09\u30f6\u5c3e"
    ],
    "wof:name":"Shimosangao",
    "wof:placetype":"locality"
},
  "geometry": {"coordinates":[139.92157,35.92044],"type":"Point"}
}