{
  "type": "Feature",
  "properties": {
    "gn:admin1_code":"4.0",
    "gn:admin2_code":"2110982.0",
    "gn:asciiname":"Owada",
    "gn:country_code":"JP",
    "gn:dem":18,
    "gn:feature_class":"P",
    "gn:feature_code":"PPLL",
    "gn:name":"\u014cwada",
    "gn:population":0,
    "gn:timezone":"Asia/Tokyo",
    "iso:country":"JP",
    "name:jpn_x_preferred":[
        "\u5927\u548c\u7530"
    ],
    "name:jpn_x_variant":[
        "\u304a\u304a\u308f\u3060",
        "\u30aa\u30aa\u30ef\u30c0"
    ],
    "name:und_x_variant":[
        "\u014cwada"
    ],
    "wof:name":"Owada",
    "wof:placetype":"locality"
},
  "geometry": {"coordinates":[140.03824,35.40414000000001],"type":"Point"}
}