{
  "type": "Feature",
  "properties": {
    "gn:admin1_code":"21.0",
    "gn:admin2_code":"1850744.0",
    "gn:admin3_code":"43368.0",
    "gn:asciiname":"Tatehama",
    "gn:country_code":"JP",
    "gn:dem":6,
    "gn:feature_class":"P",
    "gn:feature_code":"PPLL",
    "gn:name":"Tatehama",
    "gn:population":0,
    "gn:timezone":"Asia/Tokyo",
    "iso:country":"JP",
    "name:jpn_x_preferred":[
        "\u5efa\u6d5c"
    ],
    "name:jpn_x_variant":[
        "\u305f\u3066\u306f\u307e",
        "\u30bf\u30c6\u30cf\u30de"
    ],
    "wof:name":"Tatehama",
    "wof:placetype":"locality"
},
  "geometry": {"coordinates":[130.45838000000001,32.93527],"type":"Point"}
}