{
  "type": "Feature",
  "properties": {
    "iso:country":"JP",
    "qs:name":"\uff11\u4e01\u76ee",
    "qs:name_adm0":"\u65e5\u672c",
    "qs:name_adm1":"\u65b0\u6f5f\u770c",
    "qs:photos":144,
    "qs:photos_1k":29,
    "qs:photos_9k":1,
    "qs:photos_9r":3,
    "qs:photos_all":144,
    "qs:photos_sr":3,
    "qs:placetype":"Suburb",
    "qs:pop_sr":"0",
    "wof:name":"\uff11\u4e01\u76ee",
    "wof:placetype":"neighbourhood"
},
  "geometry": {"coordinates":[139.04589799999999,37.925655],"type":"Point"}
}