{
  "type": "Feature",
  "properties": {
    "gn:admin1_code":"3.0",
    "gn:admin2_code":"2130654.0",
    "gn:asciiname":"Fukazawa",
    "gn:country_code":"JP",
    "gn:dem":183,
    "gn:feature_class":"P",
    "gn:feature_code":"PPL",
    "gn:name":"Fukazawa",
    "gn:population":0,
    "gn:timezone":"Asia/Tokyo",
    "iso:country":"JP",
    "name:jpn_x_preferred":[
        "\u6df1\u6ca2"
    ],
    "name:jpn_x_variant":[
        "\u3075\u304b\u3056\u308f",
        "\u30d5\u30ab\u30b6\u30ef"
    ],
    "wof:name":"Fukazawa",
    "wof:placetype":"locality"
},
  "geometry": {"coordinates":[140.81252000000001,40.76623],"type":"Point"}
}