{
  "type": "Feature",
  "properties": {
    "gn:admin1_code":"21.0",
    "gn:admin2_code":"1858418.0",
    "gn:admin3_code":"43104.0",
    "gn:asciiname":"Jonanmachi-ikari",
    "gn:country_code":"JP",
    "gn:dem":3,
    "gn:feature_class":"P",
    "gn:feature_code":"PPL",
    "gn:name":"J\u014dnanmachi-ikari",
    "gn:population":0,
    "gn:timezone":"Asia/Tokyo",
    "iso:country":"JP",
    "name:jpn_x_preferred":[
        "\u57ce\u5357\u753a\u7887"
    ],
    "name:jpn_x_variant":[
        "\u3058\u3087\u3046\u306a\u3093\u307e\u3061\u3044\u304b\u308a",
        "\u30b8\u30e7\u30a6\u30ca\u30f3\u30de\u30c1\u30a4\u30ab\u30ea"
    ],
    "name:und_x_variant":[
        "J\u014dnanmachi-ikari"
    ],
    "wof:name":"Jonanmachi-ikari",
    "wof:placetype":"locality"
},
  "geometry": {"coordinates":[130.72141000000002,32.7207],"type":"Point"}
}