{
  "type": "Feature",
  "properties": {
    "gn:admin1_code":"21.0",
    "gn:admin2_code":"7412708.0",
    "gn:admin3_code":"43513.0",
    "gn:asciiname":"Baba",
    "gn:country_code":"JP",
    "gn:dem":124,
    "gn:feature_class":"P",
    "gn:feature_code":"PPLL",
    "gn:name":"Baba",
    "gn:population":0,
    "gn:timezone":"Asia/Tokyo",
    "iso:country":"JP",
    "name:jpn_x_preferred":[
        "\u99ac\u5834"
    ],
    "name:jpn_x_variant":[
        "\u3070\u3070",
        "\u30d0\u30d0"
    ],
    "wof:name":"Baba",
    "wof:placetype":"locality"
},
  "geometry": {"coordinates":[130.65978000000001,32.24359],"type":"Point"}
}