{
  "type": "Feature",
  "properties": {
    "gn:admin1_code":"22",
    "gn:admin2_code":"7412200.0",
    "gn:asciiname":"Kumihamacho-kazurano",
    "gn:country_code":"JP",
    "gn:dem":1,
    "gn:feature_class":"P",
    "gn:feature_code":"PPL",
    "gn:name":"Kumihamach\u014d-kazurano",
    "gn:population":0,
    "gn:timezone":"Asia/Tokyo",
    "iso:country":"JP",
    "name:und_x_variant":[
        "Kuzuno",
        "Kumihamach\u014d-kazurano"
    ],
    "wof:name":"Kumihamacho-kazurano",
    "wof:placetype":"locality"
},
  "geometry": {"coordinates":[134.92662000000001,35.63838],"type":"Point"}
}