{
  "type": "Feature",
  "properties": {
    "gn:country":"JP",
    "gn:fcode":"PPL",
    "gn:pop":31412,
    "iso:country":"JP",
    "name:ara_x_preferred":[
        "\u0646\u064a\u0646\u0648\u0645\u064a\u0627"
    ],
    "name:chi_x_preferred":[
        "\u4e8c\u5bae\u753a"
    ],
    "name:dut_x_preferred":[
        "Ninomiya"
    ],
    "name:eng_x_preferred":[
        "Ninomiya"
    ],
    "name:fre_x_preferred":[
        "Ninomiya"
    ],
    "name:ger_x_preferred":[
        "Ninomiya"
    ],
    "name:ita_x_preferred":[
        "Ninomiya"
    ],
    "name:jpn_x_preferred":[
        "\u4e8c\u5bae"
    ],
    "name:kor_x_preferred":[
        "\ub2c8\ub178\ubbf8\uc57c \uc815"
    ],
    "name:may_x_preferred":[
        "Ninomiya"
    ],
    "name:por_x_preferred":[
        "Ninomiya"
    ],
    "name:rus_x_preferred":[
        "\u041d\u0438\u043d\u043e\u043c\u0438\u044f"
    ],
    "name:spa_x_preferred":[
        "Ninomiya"
    ],
    "name:tgl_x_preferred":[
        "Ninomiya"
    ],
    "name:ukr_x_preferred":[
        "\u041d\u0456\u043d\u043e\u043c\u0456\u044f"
    ],
    "qs:name":"Ninomiya",
    "qs:photos_9r":0,
    "qs:photos_sr":0,
    "qs:pop_sr":"7",
    "wd:wordcount":58,
    "wof:name":"Ninomiya",
    "wof:placetype":"locality",
    "wof:population":31412
},
  "geometry": {"coordinates":[139.25333000000001,35.30333],"type":"Point"}
}