{
  "type": "Feature",
  "properties": {
    "gn:admin1_code":"37.0",
    "gn:admin2_code":"1851401.0",
    "gn:admin3_code":"22342.0",
    "gn:asciiname":"Sakashita",
    "gn:country_code":"JP",
    "gn:dem":90,
    "gn:feature_class":"P",
    "gn:feature_code":"PPLL",
    "gn:name":"Sakashita",
    "gn:population":0,
    "gn:timezone":"Asia/Tokyo",
    "iso:country":"JP",
    "name:jpn_x_preferred":[
        "\u5742\u4e0b"
    ],
    "wof:name":"Sakashita",
    "wof:placetype":"locality"
},
  "geometry": {"coordinates":[138.89282,35.15297],"type":"Point"}
}