{
  "type": "Feature",
  "properties": {
    "gn:admin1_code":"15.0",
    "gn:admin2_code":"1858904.0",
    "gn:asciiname":"Nishiaratanimachi",
    "gn:country_code":"JP",
    "gn:dem":34,
    "gn:feature_class":"P",
    "gn:feature_code":"PPL",
    "gn:name":"Nishiaratanimachi",
    "gn:population":0,
    "gn:timezone":"Asia/Tokyo",
    "iso:country":"JP",
    "name:jpn_x_preferred":[
        "\u897f\u8352\u8c37\u753a"
    ],
    "wof:name":"Nishiaratanimachi",
    "wof:placetype":"locality"
},
  "geometry": {"coordinates":[136.45820000000001,36.32055],"type":"Point"}
}