{
  "type": "Feature",
  "properties": {
    "gn:admin1_code":"40.0",
    "gn:admin2_code":"1861322.0",
    "gn:asciiname":"Hikawacho",
    "gn:country_code":"JP",
    "gn:dem":28,
    "gn:feature_class":"P",
    "gn:feature_code":"PPL",
    "gn:name":"Hikawach\u014d",
    "gn:population":0,
    "gn:timezone":"Asia/Tokyo",
    "iso:country":"JP",
    "name:jpn_x_preferred":[
        "\u6c37\u5ddd\u753a"
    ],
    "name:und_x_variant":[
        "Hikawach\u014d"
    ],
    "wof:name":"Hikawacho",
    "wof:placetype":"locality"
},
  "geometry": {"coordinates":[139.70623999999998,35.75362],"type":"Point"}
}