{
  "type": "Feature",
  "properties": {
    "gn:admin1_code":"32",
    "gn:admin2_code":"1853167.0",
    "gn:admin3_code":"27141.0",
    "gn:asciiname":"Shichido-nishimachi",
    "gn:country_code":"JP",
    "gn:dem":7,
    "gn:feature_class":"P",
    "gn:feature_code":"PPL",
    "gn:name":"Shichid\u014d-nishimachi",
    "gn:population":0,
    "gn:timezone":"Asia/Tokyo",
    "iso:country":"JP",
    "name:jpn_x_preferred":[
        "\u4e03\u9053\u897f\u753a"
    ],
    "name:und_x_variant":[
        "Hichid\u014d-nishich\u014d",
        "Shichido Nishimachi",
        "Shichid\u014d-nishich\u014d",
        "Shichid\u014d-nishimachi"
    ],
    "wof:name":"Shichido-nishimachi",
    "wof:placetype":"locality"
},
  "geometry": {"coordinates":[135.48369,34.59443],"type":"Point"}
}