{
  "type": "Feature",
  "properties": {
    "gn:admin1_code":"4.0",
    "gn:admin2_code":"1863711.0",
    "gn:asciiname":"Chikusa-shinden",
    "gn:country_code":"JP",
    "gn:dem":11,
    "gn:feature_class":"P",
    "gn:feature_code":"PPL",
    "gn:name":"Chikusa-shinden",
    "gn:population":0,
    "gn:timezone":"Asia/Tokyo",
    "iso:country":"JP",
    "name:jpn_x_preferred":[
        "\u5343\u7a2e\u65b0\u7530"
    ],
    "name:jpn_x_variant":[
        "\u3061\u304f\u3055\u3057\u3093\u3067\u3093",
        "\u30c1\u30af\u30b5\u30b7\u30f3\u30c7\u30f3"
    ],
    "wof:name":"Chikusa-shinden",
    "wof:placetype":"locality"
},
  "geometry": {"coordinates":[139.85557,35.29618],"type":"Point"}
}