{
  "type": "Feature",
  "properties": {
    "gn:admin1_code":"19.0",
    "gn:admin2_code":"1856849.0",
    "gn:asciiname":"Ikeda",
    "gn:country_code":"JP",
    "gn:dem":35,
    "gn:feature_class":"P",
    "gn:feature_code":"PPLL",
    "gn:name":"Ikeda",
    "gn:population":0,
    "gn:timezone":"Asia/Tokyo",
    "iso:country":"JP",
    "name:ceb_x_preferred":[
        "Ikeda"
    ],
    "name:deu_x_preferred":[
        "Ikeda"
    ],
    "name:fra_x_preferred":[
        "Ikeda"
    ],
    "name:ita_x_preferred":[
        "Ikeda"
    ],
    "name:jpn_x_preferred":[
        "\u6c60\u7530"
    ],
    "name:jpn_x_variant":[
        "\u3044\u3051\u3060",
        "\u30a4\u30b1\u30c0"
    ],
    "name:kor_x_preferred":[
        "\uc774\ucf00\ub2e4"
    ],
    "name:mlg_x_preferred":[
        "Ikeda"
    ],
    "name:ron_x_preferred":[
        "Ikeda"
    ],
    "name:rus_x_preferred":[
        "\u0418\u043a\u0435\u0434\u0430"
    ],
    "name:swe_x_preferred":[
        "Ikeda"
    ],
    "name:ukr_x_preferred":[
        "\u0406\u043a\u0435\u0434\u0430"
    ],
    "wof:name":"Ikeda",
    "wof:placetype":"locality"
},
  "geometry": {"coordinates":[139.67018000000002,35.1502],"type":"Point"}
}