{
  "type": "Feature",
  "properties": {
    "iso:country":"JP",
    "name:eng_x_preferred":[
        "Zoshiki 2 Chome"
    ],
    "name:eng_x_variant":[
        "Zoushiki 2 Choume",
        "Zoshiki 2 Chome"
    ],
    "name:jpn_x_preferred":[
        "\uff12\u4e01\u76ee"
    ],
    "name:jpn_x_variant":[
        "\u305e\u3046\u3057\u304d \uff12\u3061\u3087\u3046\u3081",
        "\u8535\u6577 \uff12\u4e01\u76ee",
        "\uff12\u3061\u3087\u3046\u3081"
    ],
    "qs:gn_local":0,
    "qs:local_max":685,
    "qs:local_sum":818,
    "qs:localhoods":4,
    "qs:name":"\uff12\u4e01\u76ee",
    "qs:name_adm0":"\u65e5\u672c",
    "qs:name_adm1":"\u6771\u4eac\u90fd",
    "qs:name_en":"Zoshiki 2 Chome",
    "qs:name_lau":"\u8535\u6577",
    "qs:name_local":"\u6771\u5927\u548c\u5e02",
    "qs:photo_max":9,
    "qs:photo_sum":9,
    "qs:placetype":"Suburb",
    "qs:quad_count":1,
    "qs:woe_adm0":23424856,
    "qs:woe_adm1":2345889,
    "qs:woe_adm2":0,
    "qs:woe_lau":28415256,
    "qs:woe_local":15015475,
    "qs:woe_ver":"7.10.0",
    "wof:lang":[
        "jpn"
    ],
    "wof:name":"\uff12\u4e01\u76ee",
    "wof:placetype":"neighbourhood"
},
  "geometry": {"coordinates":[139.41925000000001,35.753201],"type":"Point"}
}