{
  "type": "Feature",
  "properties": {
    "gn:admin1_code":"37.0",
    "gn:admin2_code":"1864104.0",
    "gn:asciiname":"Hashikami",
    "gn:country_code":"JP",
    "gn:dem":77,
    "gn:feature_class":"P",
    "gn:feature_code":"PPLL",
    "gn:name":"Hashikami",
    "gn:population":0,
    "gn:timezone":"Asia/Tokyo",
    "iso:country":"JP",
    "name:jpn_x_preferred":[
        "\u6a4b\u4e0a"
    ],
    "wof:name":"Hashikami",
    "wof:placetype":"locality"
},
  "geometry": {"coordinates":[138.53790000000001,35.22157],"type":"Point"}
}