{
  "type": "Feature",
  "properties": {
    "gn:admin1_code":"17",
    "gn:admin2_code":"1856906.0",
    "gn:asciiname":"Shimo",
    "gn:cc2":"JP",
    "gn:country_code":"JP",
    "gn:dem":37,
    "gn:feature_class":"P",
    "gn:feature_code":"PPL",
    "gn:name":"Shimo",
    "gn:population":0,
    "gn:timezone":"Asia/Tokyo",
    "iso:country":"JP",
    "name:und_x_variant":[
        "Saita-nishi",
        "Shimo"
    ],
    "wof:name":"Shimo",
    "wof:placetype":"locality"
},
  "geometry": {"coordinates":[133.73333,34.11667],"type":"Point"}
}