{
  "type": "Feature",
  "properties": {
    "gn:admin1_code":"47",
    "gn:admin2_code":"1855990.0",
    "gn:admin3_code":"47329.0",
    "gn:asciiname":"Yonagusuku",
    "gn:country_code":"JP",
    "gn:dem":9,
    "gn:feature_class":"P",
    "gn:feature_code":"PPL",
    "gn:name":"Yonagusuku",
    "gn:population":0,
    "gn:timezone":"Asia/Tokyo",
    "iso:country":"JP",
    "name:jpn_x_preferred":[
        "\u4e0e\u90a3\u57ce"
    ],
    "name:und_x_variant":[
        "Gaja",
        "Yunagusuku",
        "Yonakusuku",
        "Yonagusuku"
    ],
    "wof:name":"Yonagusuku",
    "wof:placetype":"locality"
},
  "geometry": {"coordinates":[127.76206000000001,26.21948],"type":"Point"}
}