{
  "type": "Feature",
  "properties": {
    "gn:admin1_code":"44.0",
    "gn:admin2_code":"2111850.0",
    "gn:admin3_code":"6362.0",
    "gn:asciiname":"Ohori",
    "gn:country_code":"JP",
    "gn:dem":215,
    "gn:feature_class":"P",
    "gn:feature_code":"PPL",
    "gn:name":"\u014chori",
    "gn:population":0,
    "gn:timezone":"Asia/Tokyo",
    "iso:country":"JP",
    "name:jpn_x_preferred":[
        "\u5927\u5800"
    ],
    "name:und_x_variant":[
        "\u014chori"
    ],
    "wof:name":"Ohori",
    "wof:placetype":"locality"
},
  "geometry": {"coordinates":[140.46666999999999,38.76667],"type":"Point"}
}