{
  "type": "Feature",
  "properties": {
    "gn:admin1_code":"16.0",
    "gn:admin2_code":"2112822.0",
    "gn:asciiname":"Suehirocho",
    "gn:country_code":"JP",
    "gn:dem":91,
    "gn:feature_class":"P",
    "gn:feature_code":"PPL",
    "gn:name":"Suehiroch\u014d",
    "gn:population":0,
    "gn:timezone":"Asia/Tokyo",
    "iso:country":"JP",
    "name:jpn_x_preferred":[
        "\u672b\u5e83\u753a"
    ],
    "name:jpn_x_variant":[
        "\u3059\u3048\u3072\u308d\u3061\u3087\u3046",
        "\u30b9\u30a8\u30d2\u30ed\u30c1\u30e7\u30a6"
    ],
    "name:und_x_variant":[
        "Suehiroch\u014d"
    ],
    "wof:name":"Suehirocho",
    "wof:placetype":"locality"
},
  "geometry": {"coordinates":[141.11306000000005,39.38737],"type":"Point"}
}