{
  "type": "Feature",
  "properties": {
    "gn:admin1_code":"8.0",
    "gn:admin2_code":"1859317.0",
    "gn:asciiname":"Kogamine",
    "gn:country_code":"JP",
    "gn:dem":161,
    "gn:feature_class":"P",
    "gn:feature_code":"PPLL",
    "gn:name":"Kogamine",
    "gn:population":0,
    "gn:timezone":"Asia/Tokyo",
    "iso:country":"JP",
    "name:jpn_x_preferred":[
        "\u5c0f\u30f6\u5cef"
    ],
    "wof:name":"Kogamine",
    "wof:placetype":"locality"
},
  "geometry": {"coordinates":[139.68350000000001,37.60848],"type":"Point"}
}