{
  "type": "Feature",
  "properties": {
    "gn:admin1_code":"25.0",
    "gn:admin2_code":"1864313.0",
    "gn:asciiname":"Hiramatsu",
    "gn:country_code":"JP",
    "gn:dem":229,
    "gn:feature_class":"P",
    "gn:feature_code":"PPLL",
    "gn:name":"Hiramatsu",
    "gn:population":0,
    "gn:timezone":"Asia/Tokyo",
    "iso:country":"JP",
    "name:jpn_x_preferred":[
        "\u5e73\u677e"
    ],
    "name:jpn_x_variant":[
        "\u3072\u3089\u307e\u3064",
        "\u30d2\u30e9\u30de\u30c4"
    ],
    "wof:name":"Hiramatsu",
    "wof:placetype":"locality"
},
  "geometry": {"coordinates":[130.77975000000001,32.04962],"type":"Point"}
}