{
  "type": "Feature",
  "properties": {
    "iso:country":"JP",
    "name:eng_x_preferred":[
        "Omotecho 2 Chome"
    ],
    "name:eng_x_variant":[
        "Omotechou 2 Choume",
        "Omotecho 2 Chome"
    ],
    "name:jpn_x_preferred":[
        "\uff12\u4e01\u76ee"
    ],
    "name:jpn_x_variant":[
        "\u304a\u3082\u3066\u3061\u3087\u3046 \uff12\u3061\u3087\u3046\u3081",
        "\u8868\u753a \uff12\u4e01\u76ee",
        "\uff12\u3061\u3087\u3046\u3081"
    ],
    "qs:gn_adm0_cc":"JP",
    "qs:gn_local":1857843,
    "qs:local_max":1025,
    "qs:local_sum":1267,
    "qs:localhoods":11,
    "qs:name":"\uff12\u4e01\u76ee",
    "qs:name_adm0":"\u65e5\u672c",
    "qs:name_adm1":"\u7fa4\u99ac\u770c",
    "qs:name_en":"Omotecho 2 Chome",
    "qs:name_lau":"\u8868\u753a",
    "qs:name_local":"\u524d\u6a4b\u5e02",
    "qs:photo_max":1,
    "qs:photo_sum":1,
    "qs:placetype":"Suburb",
    "qs:quad_count":1,
    "qs:woe_adm0":23424856,
    "qs:woe_adm1":2345860,
    "qs:woe_adm2":0,
    "qs:woe_lau":1113591,
    "qs:woe_local":1117656,
    "qs:woe_ver":"7.10.0",
    "wof:lang":[
        "jpn"
    ],
    "wof:name":"\uff12\u4e01\u76ee",
    "wof:placetype":"neighbourhood"
},
  "geometry": {"coordinates":[139.07867400000001,36.37928],"type":"Point"}
}