{
  "type": "Feature",
  "properties": {
    "gn:admin1_code":"4.0",
    "gn:admin2_code":"2111211.0",
    "gn:asciiname":"Kitayoshida",
    "gn:country_code":"JP",
    "gn:dem":7,
    "gn:feature_class":"P",
    "gn:feature_code":"PPL",
    "gn:name":"Kitayoshida",
    "gn:population":0,
    "gn:timezone":"Asia/Tokyo",
    "iso:country":"JP",
    "name:jpn_x_preferred":[
        "\u5317\u5409\u7530"
    ],
    "name:jpn_x_variant":[
        "\u304d\u305f\u3088\u3057\u3060",
        "\u30ad\u30bf\u30e8\u30b7\u30c0"
    ],
    "wof:name":"Kitayoshida",
    "wof:placetype":"locality"
},
  "geometry": {"coordinates":[140.36098000000001,35.49681],"type":"Point"}
}