{
  "type": "Feature",
  "properties": {
    "gn:admin1_code":"4.0",
    "gn:admin2_code":"9062338.0",
    "gn:asciiname":"Ueno",
    "gn:country_code":"JP",
    "gn:dem":93,
    "gn:feature_class":"P",
    "gn:feature_code":"PPL",
    "gn:name":"Ueno",
    "gn:population":0,
    "gn:timezone":"Asia/Tokyo",
    "iso:country":"JP",
    "name:jpn_x_preferred":[
        "\u690d\u91ce"
    ],
    "name:jpn_x_variant":[
        "\u3046\u3048\u306e",
        "\u30a6\u30a8\u30ce"
    ],
    "wof:name":"Ueno",
    "wof:placetype":"locality"
},
  "geometry": {"coordinates":[140.25232,35.15625],"type":"Point"}
}