{
  "type": "Feature",
  "properties": {
    "gn:admin1_code":"21.0",
    "gn:admin2_code":"1857206.0",
    "gn:asciiname":"Nakazuru",
    "gn:country_code":"JP",
    "gn:dem":36,
    "gn:feature_class":"P",
    "gn:feature_code":"PPLL",
    "gn:name":"Nakazuru",
    "gn:population":0,
    "gn:timezone":"Asia/Tokyo",
    "iso:country":"JP",
    "name:jpn_x_preferred":[
        "\u4e2d\u9db4"
    ],
    "name:jpn_x_variant":[
        "\u306a\u304b\u3065\u308b",
        "\u30ca\u30ab\u30c5\u30eb"
    ],
    "wof:name":"Nakazuru",
    "wof:placetype":"locality"
},
  "geometry": {"coordinates":[130.43029000000001,32.19644],"type":"Point"}
}