{
  "type": "Feature",
  "properties": {
    "gn:admin1_code":"12.0",
    "gn:admin2_code":"2127513.0",
    "gn:asciiname":"Midori",
    "gn:country_code":"JP",
    "gn:dem":16,
    "gn:feature_class":"P",
    "gn:feature_code":"PPL",
    "gn:name":"Midori",
    "gn:population":0,
    "gn:timezone":"Asia/Tokyo",
    "iso:country":"JP",
    "name:dan_x_preferred":[
        "Midori"
    ],
    "name:deu_x_preferred":[
        "Midori"
    ],
    "name:fas_x_preferred":[
        "\u0645\u06cc\u062f\u0648\u0631\u06cc"
    ],
    "name:fin_x_preferred":[
        "Midori"
    ],
    "name:ita_x_preferred":[
        "Midori"
    ],
    "name:jpn_x_preferred":[
        "\u7dd1"
    ],
    "name:jpn_x_variant":[
        "\u307f\u3069\u308a",
        "\u30df\u30c9\u30ea",
        "Midori"
    ],
    "name:nld_x_preferred":[
        "Midori"
    ],
    "name:pol_x_preferred":[
        "Midori"
    ],
    "name:por_x_preferred":[
        "Midori"
    ],
    "name:rus_x_preferred":[
        "Midori"
    ],
    "name:spa_x_preferred":[
        "Midori"
    ],
    "name:swe_x_preferred":[
        "Midori"
    ],
    "name:ukr_x_preferred":[
        "\u041c\u0456\u0434\u043e\u0440\u0456"
    ],
    "name:und_x_variant":[
        "Kusanru"
    ],
    "wof:name":"Midori",
    "wof:placetype":"locality"
},
  "geometry": {"coordinates":[141.67864,45.38873],"type":"Point"}
}