{
  "type": "Feature",
  "properties": {
    "gn:admin1_code":"12.0",
    "gn:admin2_code":"7428076.0",
    "gn:admin3_code":"1544.0",
    "gn:asciiname":"Nunokawa",
    "gn:country_code":"JP",
    "gn:dem":229,
    "gn:feature_class":"P",
    "gn:feature_code":"PPL",
    "gn:name":"Nunokawa",
    "gn:population":0,
    "gn:timezone":"Asia/Tokyo",
    "iso:country":"JP",
    "name:jpn_x_preferred":[
        "\u5e03\u5ddd"
    ],
    "name:jpn_x_variant":[
        "\u306c\u306e\u304b\u308f",
        "\u30cc\u30ce\u30ab\u30ef"
    ],
    "name:und_x_variant":[
        "Aioi",
        "Nunokawa"
    ],
    "wof:name":"Nunokawa",
    "wof:placetype":"locality"
},
  "geometry": {"coordinates":[143.97524999999999,43.58731],"type":"Point"}
}