{
  "type": "Feature",
  "properties": {
    "gn:admin1_code":"21.0",
    "gn:admin2_code":"7412709.0",
    "gn:admin3_code":"43348.0",
    "gn:asciiname":"Maku",
    "gn:country_code":"JP",
    "gn:dem":200,
    "gn:feature_class":"P",
    "gn:feature_code":"PPLL",
    "gn:name":"Maku",
    "gn:population":0,
    "gn:timezone":"Asia/Tokyo",
    "iso:country":"JP",
    "name:jpn_x_preferred":[
        "\u5e55"
    ],
    "name:jpn_x_variant":[
        "\u307e\u304f",
        "\u30de\u30af"
    ],
    "wof:name":"Maku",
    "wof:placetype":"locality"
},
  "geometry": {"coordinates":[130.84313,32.60318],"type":"Point"}
}