{
  "type": "Feature",
  "properties": {
    "gn:admin1_code":"34.0",
    "gn:admin2_code":"1858728.0",
    "gn:asciiname":"Sagamicho",
    "gn:country_code":"JP",
    "gn:dem":5,
    "gn:feature_class":"P",
    "gn:feature_code":"PPL",
    "gn:name":"Sagamich\u014d",
    "gn:population":0,
    "gn:timezone":"Asia/Tokyo",
    "iso:country":"JP",
    "name:jpn_x_preferred":[
        "\u76f8\u6a21\u753a"
    ],
    "name:und_x_variant":[
        "Sagamich\u014d"
    ],
    "wof:name":"Sagamicho",
    "wof:placetype":"locality"
},
  "geometry": {"coordinates":[139.80876999999998,35.88655],"type":"Point"}
}