{
  "type": "Feature",
  "properties": {
    "gn:admin1_code":"26.0",
    "gn:admin2_code":"1855829.0",
    "gn:asciiname":"Sakurasawa",
    "gn:country_code":"JP",
    "gn:dem":351,
    "gn:feature_class":"P",
    "gn:feature_code":"PPL",
    "gn:name":"Sakurasawa",
    "gn:population":0,
    "gn:timezone":"Asia/Tokyo",
    "iso:country":"JP",
    "name:jpn_x_preferred":[
        "\u685c\u6ca2"
    ],
    "wof:name":"Sakurasawa",
    "wof:placetype":"locality"
},
  "geometry": {"coordinates":[138.34815,36.70826],"type":"Point"}
}