{
  "type": "Feature",
  "properties": {
    "gn:admin1_code":"33.0",
    "gn:admin2_code":"1853274.0",
    "gn:asciiname":"Kawasoemachi-kanoe",
    "gn:country_code":"JP",
    "gn:dem":1,
    "gn:feature_class":"P",
    "gn:feature_code":"PPL",
    "gn:name":"Kawasoemachi-kanoe",
    "gn:population":0,
    "gn:timezone":"Asia/Tokyo",
    "iso:country":"JP",
    "name:jpn_x_preferred":[
        "\u5ddd\u526f\u753a\u9e7f\u6c5f"
    ],
    "wof:name":"Kawasoemachi-kanoe",
    "wof:placetype":"locality"
},
  "geometry": {"coordinates":[130.31994,33.1953],"type":"Point"}
}