{
  "type": "Feature",
  "properties": {
    "iso:country":"JP",
    "name:eng_x_preferred":[
        "Chatan 1 Chome"
    ],
    "name:eng_x_variant":[
        "Chatan 1 Choume",
        "Chatan 1 Chome"
    ],
    "name:jpn_x_preferred":[
        "\uff11\u4e01\u76ee"
    ],
    "name:jpn_x_variant":[
        "\u3061\u3083\u305f\u3093 \uff11\u3061\u3087\u3046\u3081",
        "\u5317\u8c37 \uff11\u4e01\u76ee",
        "\uff11\u3061\u3087\u3046\u3081"
    ],
    "qs:gn_local":0,
    "qs:local_max":50518,
    "qs:local_sum":54632,
    "qs:localhoods":4,
    "qs:name":"\uff11\u4e01\u76ee",
    "qs:name_adm0":"\u65e5\u672c",
    "qs:name_adm1":"\u6c96\u7e04\u770c",
    "qs:name_adm2":"\u4e2d\u982d\u90e1",
    "qs:name_en":"Chatan 1 Chome",
    "qs:name_lau":"\u5317\u8c37",
    "qs:name_local":"\u5317\u8c37\u753a",
    "qs:photo_max":49976,
    "qs:photo_sum":50518,
    "qs:placetype":"Suburb",
    "qs:quad_count":31,
    "qs:woe_adm0":23424856,
    "qs:woe_adm1":2345896,
    "qs:woe_adm2":24857536,
    "qs:woe_lau":28494311,
    "qs:woe_local":1107752,
    "qs:woe_ver":"7.10.0",
    "wof:lang":[
        "jpn"
    ],
    "wof:name":"\uff11\u4e01\u76ee",
    "wof:placetype":"neighbourhood"
},
  "geometry": {"coordinates":[127.758696,26.311824],"type":"Point"}
}