{
  "type": "Feature",
  "properties": {
    "gn:admin1_code":"19.0",
    "gn:admin2_code":"1864091.0",
    "gn:asciiname":"Kugenuma-fujigaya",
    "gn:country_code":"JP",
    "gn:dem":10,
    "gn:feature_class":"P",
    "gn:feature_code":"PPL",
    "gn:name":"Kugenuma-fujigaya",
    "gn:population":0,
    "gn:timezone":"Asia/Tokyo",
    "iso:country":"JP",
    "name:jpn_x_preferred":[
        "\u9d60\u6cbc\u85e4\u304c\u8c37"
    ],
    "wof:name":"Kugenuma-fujigaya",
    "wof:placetype":"locality"
},
  "geometry": {"coordinates":[139.48206000000002,35.32479],"type":"Point"}
}