{
  "type": "Feature",
  "properties": {
    "gn:admin1_code":"06",
    "gn:admin2_code":"1849587.0",
    "gn:asciiname":"Jogo",
    "gn:country_code":"JP",
    "gn:dem":17,
    "gn:feature_class":"P",
    "gn:feature_code":"PPL",
    "gn:name":"Jogo",
    "gn:population":0,
    "gn:timezone":"Asia/Tokyo",
    "iso:country":"JP",
    "name:und_x_variant":[
        "J\u014dg\u016b"
    ],
    "wof:name":"Jogo",
    "wof:placetype":"locality"
},
  "geometry": {"coordinates":[136.02943999999999,35.69222],"type":"Point"}
}