{
  "type": "Feature",
  "properties": {
    "gn:admin1_code":"21.0",
    "gn:admin2_code":"1859488.0",
    "gn:asciiname":"Nagano",
    "gn:country_code":"JP",
    "gn:dem":175,
    "gn:feature_class":"P",
    "gn:feature_code":"PPLL",
    "gn:name":"Nagano",
    "gn:population":0,
    "gn:timezone":"Asia/Tokyo",
    "iso:country":"JP",
    "name:jpn_x_preferred":[
        "\u9577\u91ce"
    ],
    "name:jpn_x_variant":[
        "\u306a\u304c\u306e",
        "\u30ca\u30ac\u30ce"
    ],
    "wof:name":"Nagano",
    "wof:placetype":"locality"
},
  "geometry": {"coordinates":[130.84376,33.02673],"type":"Point"}
}