{
  "type": "Feature",
  "properties": {
    "gn:admin1_code":"23.0",
    "gn:admin2_code":"1856290.0",
    "gn:asciiname":"Kikyogaoka",
    "gn:country_code":"JP",
    "gn:dem":225,
    "gn:feature_class":"P",
    "gn:feature_code":"PPL",
    "gn:name":"Kiky\u014dgaoka",
    "gn:population":0,
    "gn:timezone":"Asia/Tokyo",
    "iso:country":"JP",
    "name:jpn_x_preferred":[
        "\u6854\u6897\u304c\u4e18"
    ],
    "name:und_x_variant":[
        "Kiky\u014dgaoka"
    ],
    "wof:name":"Kikyogaoka",
    "wof:placetype":"locality"
},
  "geometry": {"coordinates":[136.12006,34.64356],"type":"Point"}
}