{
  "type": "Feature",
  "properties": {
    "gn:admin1_code":"36",
    "gn:admin2_code":"1857590.0",
    "gn:asciiname":"Kambara",
    "gn:cc2":"JP",
    "gn:country_code":"JP",
    "gn:dem":321,
    "gn:feature_class":"P",
    "gn:feature_code":"PPL",
    "gn:name":"Kambara",
    "gn:population":0,
    "gn:timezone":"Asia/Tokyo",
    "iso:country":"JP",
    "name:nld_x_preferred":[
        "Kambara"
    ],
    "name:spa_x_preferred":[
        "Kambara"
    ],
    "name:und_x_variant":[
        "Hikimi"
    ],
    "name:zho_x_preferred":[
        "\u582a\u82ad\u62c9\u9cc4\u5c5e"
    ],
    "wof:name":"Kambara",
    "wof:placetype":"locality"
},
  "geometry": {"coordinates":[132.01667,34.56667],"type":"Point"}
}