{
  "type": "Feature",
  "properties": {
    "gn:admin1_code":"27.0",
    "gn:admin2_code":"1852895.0",
    "gn:asciiname":"Sakibemachi",
    "gn:country_code":"JP",
    "gn:dem":3,
    "gn:feature_class":"P",
    "gn:feature_code":"PPL",
    "gn:name":"Sakibemachi",
    "gn:population":0,
    "gn:timezone":"Asia/Tokyo",
    "iso:country":"JP",
    "name:jpn_x_preferred":[
        "\u5d0e\u8fba\u753a"
    ],
    "wof:name":"Sakibemachi",
    "wof:placetype":"locality"
},
  "geometry": {"coordinates":[129.72871999999998,33.1339],"type":"Point"}
}