{
  "type": "Feature",
  "properties": {
    "gn:admin1_code":"21.0",
    "gn:admin2_code":"7412706.0",
    "gn:admin3_code":"43447.0",
    "gn:asciiname":"Nanatsuzako",
    "gn:country_code":"JP",
    "gn:dem":592,
    "gn:feature_class":"P",
    "gn:feature_code":"PPLL",
    "gn:name":"Nanatsuzako",
    "gn:population":0,
    "gn:timezone":"Asia/Tokyo",
    "iso:country":"JP",
    "name:jpn_x_preferred":[
        "\u4e03\u30c4\u8feb"
    ],
    "name:jpn_x_variant":[
        "\u306a\u306a\u3064\u3056\u3053",
        "\u30ca\u30ca\u30c4\u30b6\u30b3"
    ],
    "wof:name":"Nanatsuzako",
    "wof:placetype":"locality"
},
  "geometry": {"coordinates":[131.13891000000001,32.67791],"type":"Point"}
}