{
  "type": "Feature",
  "properties": {
    "gn:admin1_code":"35.0",
    "gn:admin2_code":"1858984.0",
    "gn:asciiname":"Shigarakicho-kinose",
    "gn:country_code":"JP",
    "gn:dem":276,
    "gn:feature_class":"P",
    "gn:feature_code":"PPL",
    "gn:name":"Shigarakich\u014d-kinose",
    "gn:population":0,
    "gn:timezone":"Asia/Tokyo",
    "iso:country":"JP",
    "name:jpn_x_preferred":[
        "\u4fe1\u697d\u753a\u9ec4\u702c"
    ],
    "name:und_x_variant":[
        "Shigarakich\u014d-kinose"
    ],
    "wof:name":"Shigarakicho-kinose",
    "wof:placetype":"locality"
},
  "geometry": {"coordinates":[136.07910999999999,34.92004],"type":"Point"}
}