{
  "type": "Feature",
  "properties": {
    "gn:admin1_code":"12.0",
    "gn:asciiname":"Minami-shukutsu",
    "gn:cc2":"JP",
    "gn:country_code":"JP",
    "gn:dem":-9999,
    "gn:feature_class":"P",
    "gn:feature_code":"PPL",
    "gn:name":"Minami-shukutsu",
    "gn:population":0,
    "gn:timezone":"Asia/Tokyo",
    "iso:country":"JP",
    "name:und_x_variant":[
        "Shikutsushi",
        "Minami-shikuzushich\u014d",
        "Shikuzu",
        "Minami-shukutsumachi",
        "Shukutsu",
        "Minami-shukutsu"
    ],
    "wof:name":"Minami-shukutsu",
    "wof:placetype":"locality"
},
  "geometry": {"coordinates":[141.01667,43.23333],"type":"Point"}
}