{
  "type": "Feature",
  "properties": {
    "gn:admin1_code":"34.0",
    "gn:admin2_code":"1858728.0",
    "gn:asciiname":"Noboritocho",
    "gn:country_code":"JP",
    "gn:dem":5,
    "gn:feature_class":"P",
    "gn:feature_code":"PPL",
    "gn:name":"Noboritoch\u014d",
    "gn:population":0,
    "gn:timezone":"Asia/Tokyo",
    "iso:country":"JP",
    "name:jpn_x_preferred":[
        "\u767b\u6238\u753a"
    ],
    "name:und_x_variant":[
        "Noboritoch\u014d"
    ],
    "wof:name":"Noboritocho",
    "wof:placetype":"locality"
},
  "geometry": {"coordinates":[139.79821000000001,35.87279],"type":"Point"}
}