{
  "type": "Feature",
  "properties": {
    "gn:admin1_code":"40",
    "gn:admin2_code":"1859115.0",
    "gn:asciiname":"Ogawa-shinden",
    "gn:country_code":"JP",
    "gn:dem":77,
    "gn:feature_class":"P",
    "gn:feature_code":"PPL",
    "gn:name":"Ogawa-shinden",
    "gn:population":0,
    "gn:timezone":"Asia/Tokyo",
    "iso:country":"JP",
    "wof:name":"Ogawa-shinden",
    "wof:placetype":"locality"
},
  "geometry": {"coordinates":[139.48333,35.73333],"type":"Point"}
}