{
  "type": "Feature",
  "properties": {
    "gn:admin1_code":"4.0",
    "gn:admin2_code":"1859468.0",
    "gn:asciiname":"Honkaefuchi",
    "gn:country_code":"JP",
    "gn:dem":30,
    "gn:feature_class":"P",
    "gn:feature_code":"PPLL",
    "gn:name":"Honkaefuchi",
    "gn:population":0,
    "gn:timezone":"Asia/Tokyo",
    "iso:country":"JP",
    "name:jpn_x_preferred":[
        "\u672c\u8cc0\u6075\u6df5"
    ],
    "name:jpn_x_variant":[
        "\u307b\u3093\u304b\u3048\u3075\u3061",
        "\u30db\u30f3\u30ab\u30a8\u30d5\u30c1"
    ],
    "wof:name":"Honkaefuchi",
    "wof:placetype":"locality"
},
  "geometry": {"coordinates":[140.05098999999998,35.33335],"type":"Point"}
}