{
  "type": "Feature",
  "properties": {
    "gn:admin1_code":"19.0",
    "gn:admin2_code":"1856849.0",
    "gn:asciiname":"Wadanosato",
    "gn:country_code":"JP",
    "gn:dem":9,
    "gn:feature_class":"P",
    "gn:feature_code":"PPLL",
    "gn:name":"Wadanosato",
    "gn:population":0,
    "gn:timezone":"Asia/Tokyo",
    "iso:country":"JP",
    "name:jpn_x_preferred":[
        "\u548c\u7530\u30ce\u91cc"
    ],
    "name:jpn_x_variant":[
        "\u308f\u3060\u306e\u3055\u3068",
        "\u30ef\u30c0\u30ce\u30b5\u30c8"
    ],
    "wof:name":"Wadanosato",
    "wof:placetype":"locality"
},
  "geometry": {"coordinates":[139.62788,35.19325999999999],"type":"Point"}
}