{
  "type": "Feature",
  "properties": {
    "gn:admin1_code":"26",
    "gn:admin2_code":"1856209.0",
    "gn:asciiname":"Chusha",
    "gn:country_code":"JP",
    "gn:dem":1187,
    "gn:feature_class":"P",
    "gn:feature_code":"PPLL",
    "gn:name":"Ch\u016bsha",
    "gn:population":0,
    "gn:timezone":"Asia/Tokyo",
    "iso:country":"JP",
    "name:jpn_x_preferred":[
        "\u4e2d\u793e"
    ],
    "name:und_x_variant":[
        "Ch\u016bsha"
    ],
    "wof:name":"Chusha",
    "wof:placetype":"locality"
},
  "geometry": {"coordinates":[138.08616000000001,36.73972],"type":"Point"}
}