{
  "type": "Feature",
  "properties": {
    "iso:country":"JP",
    "label:eng_x_preferred_longname":[
        "Myoko City"
    ],
    "label:eng_x_preferred_placetype":[
        "city"
    ],
    "name:eng_x_preferred":[
        "Myoko"
    ],
    "name:eng_x_variant":[
        "Myoko City"
    ],
    "name:jpn_x_preferred":[
        "\u5999\u9ad8\u5e02"
    ],
    "qs:name":"\u5999\u9ad8\u5e02",
    "qs:name_adm0":"\u65e5\u672c",
    "qs:name_adm1":"\u65b0\u6f5f\u770c",
    "qs:photos":687,
    "qs:photos_1k":139,
    "qs:photos_9k":3,
    "qs:photos_9r":5,
    "qs:photos_all":733,
    "qs:photos_sr":8,
    "qs:placetype":"Town",
    "qs:pop_sr":"0",
    "wof:name":"Myoko",
    "wof:placetype":"locality"
},
  "geometry": {"coordinates":[138.19288599999999,36.870282],"type":"Point"}
}