{
  "type": "Feature",
  "properties": {
    "gn:admin1_code":"7.0",
    "gn:admin2_code":"1856443.0",
    "gn:asciiname":"Hirai",
    "gn:country_code":"JP",
    "gn:dem":27,
    "gn:feature_class":"P",
    "gn:feature_code":"PPL",
    "gn:name":"Hirai",
    "gn:population":0,
    "gn:timezone":"Asia/Tokyo",
    "iso:country":"JP",
    "name:deu_x_preferred":[
        "Hirai"
    ],
    "name:fra_x_preferred":[
        "Hirai"
    ],
    "name:jpn_x_preferred":[
        "\u5e73\u4e95"
    ],
    "name:kor_x_preferred":[
        "\ud788\ub77c\uc774"
    ],
    "name:pol_x_preferred":[
        "Hirai"
    ],
    "name:por_x_preferred":[
        "Hirai"
    ],
    "name:rus_x_preferred":[
        "\u0425\u0438\u0440\u0430\u0438"
    ],
    "wof:name":"Hirai",
    "wof:placetype":"locality"
},
  "geometry": {"coordinates":[130.52489,33.79514],"type":"Point"}
}