{
  "type": "Feature",
  "properties": {
    "gn:admin1_code":"7.0",
    "gn:admin2_code":"1851269.0",
    "gn:admin3_code":"40608.0",
    "gn:asciiname":"Shimoibaru",
    "gn:country_code":"JP",
    "gn:dem":76,
    "gn:feature_class":"P",
    "gn:feature_code":"PPLL",
    "gn:name":"Shimoibaru",
    "gn:population":0,
    "gn:timezone":"Asia/Tokyo",
    "iso:country":"JP",
    "name:jpn_x_preferred":[
        "\u4e0b\u4f0a\u539f"
    ],
    "wof:name":"Shimoibaru",
    "wof:placetype":"locality"
},
  "geometry": {"coordinates":[130.86006,33.58288],"type":"Point"}
}