{
  "type": "Feature",
  "properties": {
    "gn:admin1_code":"24.0",
    "gn:admin2_code":"2111889.0",
    "gn:admin3_code":"4401.0",
    "gn:asciiname":"Nakasai",
    "gn:country_code":"JP",
    "gn:dem":16,
    "gn:feature_class":"P",
    "gn:feature_code":"PPL",
    "gn:name":"Nakasai",
    "gn:population":0,
    "gn:timezone":"Asia/Tokyo",
    "iso:country":"JP",
    "name:jpn_x_preferred":[
        "\u4e2d\u624d"
    ],
    "name:jpn_x_variant":[
        "\u306a\u304b\u3055\u3044",
        "\u30ca\u30ab\u30b5\u30a4"
    ],
    "wof:name":"Nakasai",
    "wof:placetype":"locality"
},
  "geometry": {"coordinates":[141.11635999999999,38.42934],"type":"Point"}
}