{
  "type": "Feature",
  "properties": {
    "gn:admin1_code":"18.0",
    "gn:admin2_code":"7383999.0",
    "gn:admin3_code":"46490.0",
    "gn:asciiname":"Hiraishi",
    "gn:country_code":"JP",
    "gn:dem":157,
    "gn:feature_class":"P",
    "gn:feature_code":"PPLL",
    "gn:name":"Hiraishi",
    "gn:population":0,
    "gn:timezone":"Asia/Tokyo",
    "iso:country":"JP",
    "name:jpn_x_preferred":[
        "\u5e73\u77f3"
    ],
    "wof:name":"Hiraishi",
    "wof:placetype":"locality"
},
  "geometry": {"coordinates":[130.84118000000001,31.19351],"type":"Point"}
}