{
  "type": "Feature",
  "properties": {
    "gn:admin1_code":"4.0",
    "gn:admin2_code":"7465521.0",
    "gn:asciiname":"Mozawa",
    "gn:country_code":"JP",
    "gn:dem":166,
    "gn:feature_class":"P",
    "gn:feature_code":"PPLL",
    "gn:name":"Mozawa",
    "gn:population":0,
    "gn:timezone":"Asia/Tokyo",
    "iso:country":"JP",
    "name:jpn_x_preferred":[
        "\u8302\u6ca2"
    ],
    "name:jpn_x_variant":[
        "\u3082\u3056\u308f",
        "\u30e2\u30b6\u30ef"
    ],
    "wof:name":"Mozawa",
    "wof:placetype":"locality"
},
  "geometry": {"coordinates":[139.98152999999999,35.09876],"type":"Point"}
}