{
  "type": "Feature",
  "properties": {
    "gn:admin1_code":"3.0",
    "gn:admin2_code":"2128302.0",
    "gn:admin3_code":"2443.0",
    "gn:asciiname":"Shishinai",
    "gn:country_code":"JP",
    "gn:dem":141,
    "gn:feature_class":"P",
    "gn:feature_code":"PPL",
    "gn:name":"Shishinai",
    "gn:population":0,
    "gn:timezone":"Asia/Tokyo",
    "iso:country":"JP",
    "name:jpn_x_preferred":[
        "\u7345\u5b50\u5185"
    ],
    "name:jpn_x_variant":[
        "\u3057\u3057\u306a\u3044",
        "\u30b7\u30b7\u30ca\u30a4"
    ],
    "wof:name":"Shishinai",
    "wof:placetype":"locality"
},
  "geometry": {"coordinates":[141.13923,40.33475],"type":"Point"}
}