{
  "type": "Feature",
  "properties": {
    "gn:admin1_code":"24.0",
    "gn:admin2_code":"2112574.0",
    "gn:asciiname":"Mano",
    "gn:country_code":"JP",
    "gn:dem":32,
    "gn:feature_class":"P",
    "gn:feature_code":"PPL",
    "gn:name":"Mano",
    "gn:population":0,
    "gn:timezone":"Asia/Tokyo",
    "iso:country":"JP",
    "name:ceb_x_preferred":[
        "Mano"
    ],
    "name:deu_x_preferred":[
        "Mano"
    ],
    "name:fra_x_preferred":[
        "Mano"
    ],
    "name:ita_x_preferred":[
        "Mano"
    ],
    "name:jpn_x_preferred":[
        "\u771f\u91ce"
    ],
    "name:jpn_x_variant":[
        "\u307e\u306e",
        "\u30de\u30ce"
    ],
    "name:nld_x_preferred":[
        "Mano"
    ],
    "name:pol_x_preferred":[
        "Mano"
    ],
    "name:rus_x_preferred":[
        "\u041c\u0430\u043d\u043e"
    ],
    "name:spa_x_preferred":[
        "Mano"
    ],
    "name:swe_x_preferred":[
        "Mano"
    ],
    "name:tur_x_preferred":[
        "Mano"
    ],
    "wof:name":"Mano",
    "wof:placetype":"locality"
},
  "geometry": {"coordinates":[141.37260000000001,38.4644],"type":"Point"}
}