{
  "type": "Feature",
  "properties": {
    "gn:admin1_code":"4.0",
    "gn:admin2_code":"2112997.0",
    "gn:admin3_code":"12424.0",
    "gn:asciiname":"Ushigome-shinden",
    "gn:country_code":"JP",
    "gn:dem":3,
    "gn:feature_class":"P",
    "gn:feature_code":"PPLL",
    "gn:name":"Ushigome-shinden",
    "gn:population":0,
    "gn:timezone":"Asia/Tokyo",
    "iso:country":"JP",
    "name:jpn_x_preferred":[
        "\u725b\u8fbc\u65b0\u7530"
    ],
    "name:jpn_x_variant":[
        "\u3046\u3057\u3054\u3081\u3057\u3093\u3067\u3093",
        "\u30a6\u30b7\u30b4\u30e1\u30b7\u30f3\u30c7\u30f3"
    ],
    "wof:name":"Ushigome-shinden",
    "wof:placetype":"locality"
},
  "geometry": {"coordinates":[140.38085000000001,35.4707],"type":"Point"}
}