{
  "type": "Feature",
  "properties": {
    "gn:admin1_code":"19.0",
    "gn:admin2_code":"1864622.0",
    "gn:asciiname":"Nango",
    "gn:country_code":"JP",
    "gn:dem":5,
    "gn:feature_class":"P",
    "gn:feature_code":"PPL",
    "gn:name":"Nango",
    "gn:population":0,
    "gn:timezone":"Asia/Tokyo",
    "iso:country":"JP",
    "name:cat_x_preferred":[
        "Nango"
    ],
    "name:ceb_x_preferred":[
        "Nango"
    ],
    "name:deu_x_preferred":[
        "Nango"
    ],
    "name:fra_x_preferred":[
        "Nang\u014d"
    ],
    "name:jpn_x_preferred":[
        "\u5357\u6e56"
    ],
    "name:swe_x_preferred":[
        "Nango"
    ],
    "wof:name":"Nango",
    "wof:placetype":"locality"
},
  "geometry": {"coordinates":[139.39276999999998,35.32349],"type":"Point"}
}