{
  "type": "Feature",
  "properties": {
    "gn:admin1_code":"21.0",
    "gn:admin2_code":"1857206.0",
    "gn:asciiname":"Yanagihira",
    "gn:country_code":"JP",
    "gn:dem":358,
    "gn:feature_class":"P",
    "gn:feature_code":"PPLL",
    "gn:name":"Yanagihira",
    "gn:population":0,
    "gn:timezone":"Asia/Tokyo",
    "iso:country":"JP",
    "name:jpn_x_preferred":[
        "\u67f3\u5e73"
    ],
    "name:jpn_x_variant":[
        "\u3084\u306a\u304e\u3072\u3089",
        "\u30e4\u30ca\u30ae\u30d2\u30e9"
    ],
    "wof:name":"Yanagihira",
    "wof:placetype":"locality"
},
  "geometry": {"coordinates":[130.56931,32.17685],"type":"Point"}
}