{
  "type": "Feature",
  "properties": {
    "gn:admin1_code":"43.0",
    "gn:admin2_code":"7411114.0",
    "gn:asciiname":"Hatano",
    "gn:country_code":"JP",
    "gn:dem":420,
    "gn:feature_class":"P",
    "gn:feature_code":"PPL",
    "gn:name":"Hatano",
    "gn:population":0,
    "gn:timezone":"Asia/Tokyo",
    "iso:country":"JP",
    "name:jpn_x_preferred":[
        "\u7551\u91ce"
    ],
    "wof:name":"Hatano",
    "wof:placetype":"locality"
},
  "geometry": {"coordinates":[135.42588999999998,34.22475],"type":"Point"}
}