{
  "type": "Feature",
  "properties": {
    "gn:admin1_code":"3.0",
    "gn:admin2_code":"2130200.0",
    "gn:asciiname":"Shoboji",
    "gn:country_code":"JP",
    "gn:dem":32,
    "gn:feature_class":"P",
    "gn:feature_code":"PPL",
    "gn:name":"Sh\u014db\u014dji",
    "gn:population":0,
    "gn:timezone":"Asia/Tokyo",
    "iso:country":"JP",
    "name:jpn_x_preferred":[
        "\u6b63\u6cd5\u5bfa"
    ],
    "name:jpn_x_variant":[
        "\u3057\u3087\u3046\u307c\u3046\u3058",
        "\u30b7\u30e7\u30a6\u30dc\u30a6\u30b8"
    ],
    "name:und_x_variant":[
        "Sh\u014db\u014dji"
    ],
    "wof:name":"Shoboji",
    "wof:placetype":"locality"
},
  "geometry": {"coordinates":[141.40743999999995,40.51815],"type":"Point"}
}