{
  "type": "Feature",
  "properties": {
    "gn:admin1_code":"19.0",
    "gn:admin2_code":"1848350.0",
    "gn:admin3_code":"14107.0",
    "gn:asciiname":"Takigashira",
    "gn:country_code":"JP",
    "gn:dem":16,
    "gn:feature_class":"P",
    "gn:feature_code":"PPL",
    "gn:name":"Takigashira",
    "gn:population":0,
    "gn:timezone":"Asia/Tokyo",
    "iso:country":"JP",
    "name:jpn_x_preferred":[
        "\u6edd\u982d"
    ],
    "name:jpn_x_variant":[
        "\u305f\u304d\u304c\u3057\u3089",
        "\u30bf\u30ad\u30ac\u30b7\u30e9"
    ],
    "wof:name":"Takigashira",
    "wof:placetype":"locality"
},
  "geometry": {"coordinates":[139.61858999999998,35.4209],"type":"Point"}
}