{
  "type": "Feature",
  "properties": {
    "gn:admin1_code":"37.0",
    "gn:admin2_code":"1851376.0",
    "gn:asciiname":"Imazato",
    "gn:country_code":"JP",
    "gn:dem":304,
    "gn:feature_class":"P",
    "gn:feature_code":"PPL",
    "gn:name":"Imazato",
    "gn:population":0,
    "gn:timezone":"Asia/Tokyo",
    "iso:country":"JP",
    "name:jpn_x_preferred":[
        "\u4eca\u91cc"
    ],
    "wof:name":"Imazato",
    "wof:placetype":"locality"
},
  "geometry": {"coordinates":[138.88682,35.21999],"type":"Point"}
}