{
  "type": "Feature",
  "properties": {
    "gn:admin1_code":"21.0",
    "gn:admin2_code":"1859490.0",
    "gn:admin3_code":"43403.0",
    "gn:asciiname":"Hokamaki",
    "gn:country_code":"JP",
    "gn:dem":134,
    "gn:feature_class":"P",
    "gn:feature_code":"PPL",
    "gn:name":"Hokamaki",
    "gn:population":0,
    "gn:timezone":"Asia/Tokyo",
    "iso:country":"JP",
    "name:jpn_x_preferred":[
        "\u5916\u7267"
    ],
    "name:jpn_x_variant":[
        "\u307b\u304b\u307e\u304d",
        "\u30db\u30ab\u30de\u30ad"
    ],
    "wof:name":"Hokamaki",
    "wof:placetype":"locality"
},
  "geometry": {"coordinates":[130.92705000000001,32.86731],"type":"Point"}
}