{
  "type": "Feature",
  "properties": {
    "gn:admin1_code":"25.0",
    "gn:admin2_code":"1864313.0",
    "gn:asciiname":"Wakimura",
    "gn:country_code":"JP",
    "gn:dem":239,
    "gn:feature_class":"P",
    "gn:feature_code":"PPLL",
    "gn:name":"Wakimura",
    "gn:population":0,
    "gn:timezone":"Asia/Tokyo",
    "iso:country":"JP",
    "name:jpn_x_preferred":[
        "\u8107\u6751"
    ],
    "name:jpn_x_variant":[
        "\u308f\u304d\u3080\u3089",
        "\u30ef\u30ad\u30e0\u30e9"
    ],
    "wof:name":"Wakimura",
    "wof:placetype":"locality"
},
  "geometry": {"coordinates":[130.83309,32.05041],"type":"Point"}
}