{
  "type": "Feature",
  "properties": {
    "gn:admin1_code":"28.0",
    "gn:admin2_code":"1850395.0",
    "gn:asciiname":"Kabatacho",
    "gn:country_code":"JP",
    "gn:dem":45,
    "gn:feature_class":"P",
    "gn:feature_code":"PPL",
    "gn:name":"Kabatach\u014d",
    "gn:population":0,
    "gn:timezone":"Asia/Tokyo",
    "iso:country":"JP",
    "name:jpn_x_preferred":[
        "\u5609\u5e61\u753a"
    ],
    "name:und_x_variant":[
        "Kabatach\u014d"
    ],
    "wof:name":"Kabatacho",
    "wof:placetype":"locality"
},
  "geometry": {"coordinates":[135.79828999999998,34.58658],"type":"Point"}
}