{
  "type": "Feature",
  "properties": {
    "gn:admin1_code":"3.0",
    "gn:admin2_code":"2130654.0",
    "gn:asciiname":"Namidate-maeda",
    "gn:country_code":"JP",
    "gn:dem":8,
    "gn:feature_class":"P",
    "gn:feature_code":"PPL",
    "gn:name":"Namidate-maeda",
    "gn:population":0,
    "gn:timezone":"Asia/Tokyo",
    "iso:country":"JP",
    "name:jpn_x_preferred":[
        "\u6d6a\u9928\u524d\u7530"
    ],
    "name:jpn_x_variant":[
        "\u306a\u307f\u3060\u3066\u307e\u3048\u3060",
        "\u30ca\u30df\u30c0\u30c6\u30de\u30a8\u30c0"
    ],
    "name:und_x_variant":[
        "Namidate"
    ],
    "wof:name":"Namidate-maeda",
    "wof:placetype":"locality"
},
  "geometry": {"coordinates":[140.72148000000001,40.8162],"type":"Point"}
}