{
  "type": "Feature",
  "properties": {
    "iso:country":"JP",
    "name:eng_x_preferred":[
        "Maruyamanishimachi 8 Chome"
    ],
    "name:eng_x_variant":[
        "Maruyamanishimachi 8 Choume",
        "Maruyamanishimachi 8 Chome"
    ],
    "name:jpn_x_preferred":[
        "\uff18\u4e01\u76ee"
    ],
    "name:jpn_x_variant":[
        "\u307e\u308b\u3084\u307e\u306b\u3057\u307e\u3061 \uff18\u3061\u3087\u3046\u3081",
        "\u5186\u5c71\u897f\u753a \uff18\u4e01\u76ee",
        "\uff18\u3061\u3087\u3046\u3081"
    ],
    "qs:gn_local":0,
    "qs:local_max":2554,
    "qs:local_sum":22076,
    "qs:localhoods":97,
    "qs:name":"\uff18\u4e01\u76ee",
    "qs:name_adm0":"\u65e5\u672c",
    "qs:name_adm1":"\u5317\u6d77\u9053",
    "qs:name_adm2":"\u4e2d\u592e\u533a",
    "qs:name_en":"Maruyamanishimachi 8 Chome",
    "qs:name_lau":"\u5186\u5c71\u897f\u753a",
    "qs:name_local":"\u672d\u5e4c\u5e02",
    "qs:photo_max":1,
    "qs:photo_sum":1,
    "qs:placetype":"Suburb",
    "qs:quad_count":1,
    "qs:woe_adm0":23424856,
    "qs:woe_adm1":7153351,
    "qs:woe_adm2":15015394,
    "qs:woe_lau":28379446,
    "qs:woe_local":1118108,
    "qs:woe_ver":"7.10.0",
    "wof:lang":[
        "jpn"
    ],
    "wof:name":"\uff18\u4e01\u76ee",
    "wof:placetype":"neighbourhood"
},
  "geometry": {"coordinates":[141.303406,43.042797],"type":"Point"}
}