{
  "type": "Feature",
  "properties": {
    "gn:admin1_code":"21.0",
    "gn:admin2_code":"1865168.0",
    "gn:asciiname":"Kabashimo",
    "gn:country_code":"JP",
    "gn:dem":24,
    "gn:feature_class":"P",
    "gn:feature_code":"PPLL",
    "gn:name":"Kabashimo",
    "gn:population":0,
    "gn:timezone":"Asia/Tokyo",
    "iso:country":"JP",
    "name:jpn_x_preferred":[
        "\u6a3a\u4e0b"
    ],
    "name:jpn_x_variant":[
        "\u304b\u3070\u3057\u3082",
        "\u30ab\u30d0\u30b7\u30e2"
    ],
    "wof:name":"Kabashimo",
    "wof:placetype":"locality"
},
  "geometry": {"coordinates":[130.49395000000001,32.96754],"type":"Point"}
}