{
  "type": "Feature",
  "properties": {
    "gn:admin1_code":"21.0",
    "gn:admin2_code":"1848441.0",
    "gn:asciiname":"Hagiwara",
    "gn:country_code":"JP",
    "gn:dem":5,
    "gn:feature_class":"P",
    "gn:feature_code":"PPLL",
    "gn:name":"Hagiwara",
    "gn:population":0,
    "gn:timezone":"Asia/Tokyo",
    "iso:country":"JP",
    "name:jpn_x_preferred":[
        "\u8429\u539f"
    ],
    "name:jpn_x_variant":[
        "\u306f\u304e\u308f\u3089",
        "\u30cf\u30ae\u30ef\u30e9"
    ],
    "wof:name":"Hagiwara",
    "wof:placetype":"locality"
},
  "geometry": {"coordinates":[130.61776,32.50471],"type":"Point"}
}