{
  "type": "Feature",
  "properties": {
    "gn:admin1_code":"27.0",
    "gn:admin2_code":"7418810.0",
    "gn:asciiname":"Kamitsushimacho-omasu",
    "gn:country_code":"JP",
    "gn:dem":4,
    "gn:feature_class":"P",
    "gn:feature_code":"PPL",
    "gn:name":"Kamitsushimach\u014d-\u014dmasu",
    "gn:population":0,
    "gn:timezone":"Asia/Tokyo",
    "iso:country":"JP",
    "name:jpn_x_preferred":[
        "\u4e0a\u5bfe\u99ac\u753a\u5927\u5897"
    ],
    "name:und_x_variant":[
        "Kamitsushimach\u014d-\u014dmasu"
    ],
    "wof:name":"Kamitsushimacho-omasu",
    "wof:placetype":"locality"
},
  "geometry": {"coordinates":[129.43553,34.62455],"type":"Point"}
}