{
  "type": "Feature",
  "properties": {
    "iso:country":"JP",
    "label:eng_x_preferred_longname":[
        "Koryo Town"
    ],
    "label:eng_x_preferred_placetype":[
        "town"
    ],
    "name:eng_x_preferred":[
        "Koryo"
    ],
    "name:eng_x_variant":[
        "Koryo Town"
    ],
    "name:jpn_x_preferred":[
        "\u5e83\u9675\u753a"
    ],
    "qs:name":"\u5e83\u9675\u753a",
    "qs:name_adm0":"\u65e5\u672c",
    "qs:name_adm1":"\u5948\u826f\u770c",
    "qs:photos":17,
    "qs:photos_1k":3,
    "qs:photos_9k":1,
    "qs:photos_9r":2,
    "qs:photos_all":67,
    "qs:photos_sr":1,
    "qs:placetype":"Town",
    "qs:pop_sr":"0",
    "wof:name":"Koryo",
    "wof:placetype":"locality"
},
  "geometry": {"coordinates":[135.757541,34.560016],"type":"Point"}
}