{
  "type": "Feature",
  "properties": {
    "gn:admin1_code":"21.0",
    "gn:admin2_code":"1848441.0",
    "gn:asciiname":"Okamachi-naka",
    "gn:country_code":"JP",
    "gn:dem":14,
    "gn:feature_class":"P",
    "gn:feature_code":"PPL",
    "gn:name":"Okamachi-naka",
    "gn:population":0,
    "gn:timezone":"Asia/Tokyo",
    "iso:country":"JP",
    "name:jpn_x_preferred":[
        "\u5ca1\u753a\u4e2d"
    ],
    "name:jpn_x_variant":[
        "\u304a\u304b\u307e\u3061\u306a\u304b",
        "\u30aa\u30ab\u30de\u30c1\u30ca\u30ab"
    ],
    "wof:name":"Okamachi-naka",
    "wof:placetype":"locality"
},
  "geometry": {"coordinates":[130.67085,32.53547],"type":"Point"}
}