{
  "type": "Feature",
  "properties": {
    "gn:admin1_code":"21.0",
    "gn:admin2_code":"1864975.0",
    "gn:admin3_code":"43424.0",
    "gn:asciiname":"Murobaru",
    "gn:country_code":"JP",
    "gn:dem":388,
    "gn:feature_class":"P",
    "gn:feature_code":"PPLL",
    "gn:name":"Murobaru",
    "gn:population":0,
    "gn:timezone":"Asia/Tokyo",
    "iso:country":"JP",
    "name:jpn_x_preferred":[
        "\u5ba4\u539f"
    ],
    "name:jpn_x_variant":[
        "\u3080\u308d\u3070\u308b",
        "\u30e0\u30ed\u30d0\u30eb"
    ],
    "wof:name":"Murobaru",
    "wof:placetype":"locality"
},
  "geometry": {"coordinates":[130.98582999999999,33.13947],"type":"Point"}
}