{
  "type": "Feature",
  "properties": {
    "gn:admin1_code":"26.0",
    "gn:admin2_code":"1856209.0",
    "gn:asciiname":"Toyonomachi-ishi",
    "gn:country_code":"JP",
    "gn:dem":336,
    "gn:feature_class":"P",
    "gn:feature_code":"PPL",
    "gn:name":"Toyonomachi-ishi",
    "gn:population":0,
    "gn:timezone":"Asia/Tokyo",
    "iso:country":"JP",
    "name:jpn_x_preferred":[
        "\u8c4a\u91ce\u753a\u77f3"
    ],
    "wof:name":"Toyonomachi-ishi",
    "wof:placetype":"locality"
},
  "geometry": {"coordinates":[138.26123000000001,36.70469],"type":"Point"}
}