{
  "type": "Feature",
  "properties": {
    "gn:admin1_code":"21.0",
    "gn:admin2_code":"7412706.0",
    "gn:admin3_code":"43447.0",
    "gn:asciiname":"Umenokizuru",
    "gn:country_code":"JP",
    "gn:dem":585,
    "gn:feature_class":"P",
    "gn:feature_code":"PPLL",
    "gn:name":"Umenokizuru",
    "gn:population":0,
    "gn:timezone":"Asia/Tokyo",
    "iso:country":"JP",
    "name:jpn_x_preferred":[
        "\u6885\u30ce\u6728\u9db4"
    ],
    "name:jpn_x_variant":[
        "\u3046\u3081\u306e\u304d\u3065\u308b",
        "\u30a6\u30e1\u30ce\u30ad\u30c5\u30eb"
    ],
    "wof:name":"Umenokizuru",
    "wof:placetype":"locality"
},
  "geometry": {"coordinates":[131.07395,32.64976],"type":"Point"}
}