{
  "type": "Feature",
  "properties": {
    "gn:admin1_code":"12.0",
    "gn:admin2_code":"2130058.0",
    "gn:admin3_code":"1641.0",
    "gn:asciiname":"Tateyama",
    "gn:cc2":"JP",
    "gn:country_code":"JP",
    "gn:dem":118,
    "gn:feature_class":"P",
    "gn:feature_code":"PPL",
    "gn:name":"Tateyama",
    "gn:population":0,
    "gn:timezone":"Asia/Tokyo",
    "iso:country":"JP",
    "name:ceb_x_preferred":[
        "Tateyama"
    ],
    "name:deu_x_preferred":[
        "Tateyama"
    ],
    "name:fra_x_preferred":[
        "Tateyama"
    ],
    "name:jpn_x_preferred":[
        "\u7acb\u5c71"
    ],
    "name:mlg_x_preferred":[
        "Tateyama"
    ],
    "name:nld_x_preferred":[
        "Tateyama"
    ],
    "name:ron_x_preferred":[
        "Tateyama"
    ],
    "name:rus_x_preferred":[
        "\u0422\u0430\u0442\u0435\u044f\u043c\u0430"
    ],
    "name:ukr_x_preferred":[
        "\u0422\u0430\u0442\u0435\u044f\u043c\u0430"
    ],
    "name:und_x_variant":[
        "Endatara"
    ],
    "wof:name":"Tateyama",
    "wof:placetype":"locality"
},
  "geometry": {"coordinates":[143.21666999999999,42.45],"type":"Point"}
}