{
  "type": "Feature",
  "properties": {
    "gn:admin1_code":"4.0",
    "gn:admin2_code":"2112997.0",
    "gn:admin3_code":"12427.0",
    "gn:asciiname":"Hiramatsu",
    "gn:country_code":"JP",
    "gn:dem":64,
    "gn:feature_class":"P",
    "gn:feature_code":"PPLL",
    "gn:name":"Hiramatsu",
    "gn:population":0,
    "gn:timezone":"Asia/Tokyo",
    "iso:country":"JP",
    "name:jpn_x_preferred":[
        "\u5e73\u677e"
    ],
    "name:jpn_x_variant":[
        "\u3072\u3089\u307e\u3064",
        "\u30d2\u30e9\u30de\u30c4"
    ],
    "wof:name":"Hiramatsu",
    "wof:placetype":"locality"
},
  "geometry": {"coordinates":[140.22057000000001,35.36594],"type":"Point"}
}