{
  "type": "Feature",
  "properties": {
    "gn:admin1_code":"34.0",
    "gn:admin2_code":"1858728.0",
    "gn:asciiname":"Onomacho",
    "gn:country_code":"JP",
    "gn:dem":7,
    "gn:feature_class":"P",
    "gn:feature_code":"PPL",
    "gn:name":"\u014cnomach\u014d",
    "gn:population":0,
    "gn:timezone":"Asia/Tokyo",
    "iso:country":"JP",
    "name:jpn_x_preferred":[
        "\u5927\u91ce\u9593\u753a"
    ],
    "name:und_x_variant":[
        "\u014cnomach\u014d"
    ],
    "wof:name":"Onomacho",
    "wof:placetype":"locality"
},
  "geometry": {"coordinates":[139.77842999999999,35.8642],"type":"Point"}
}