{
  "type": "Feature",
  "properties": {
    "gn:admin1_code":"4.0",
    "gn:admin2_code":"8304237.0",
    "gn:asciiname":"Mine",
    "gn:country_code":"JP",
    "gn:dem":34,
    "gn:feature_class":"P",
    "gn:feature_code":"PPLL",
    "gn:name":"Mine",
    "gn:population":0,
    "gn:timezone":"Asia/Tokyo",
    "iso:country":"JP",
    "name:ceb_x_preferred":[
        "Mine"
    ],
    "name:ces_x_preferred":[
        "Mine"
    ],
    "name:dan_x_preferred":[
        "Mine"
    ],
    "name:deu_x_preferred":[
        "Mine"
    ],
    "name:epo_x_preferred":[
        "Mino"
    ],
    "name:fra_x_preferred":[
        "Mine"
    ],
    "name:hin_x_preferred":[
        "\u0916\u093e\u0928"
    ],
    "name:hun_x_preferred":[
        "Mine"
    ],
    "name:ita_x_preferred":[
        "Mine"
    ],
    "name:jpn_x_preferred":[
        "\u5cf0"
    ],
    "name:jpn_x_variant":[
        "\u307f\u306d",
        "\u30df\u30cd"
    ],
    "name:nld_x_preferred":[
        "Mine"
    ],
    "name:nno_x_preferred":[
        "Mine"
    ],
    "name:por_x_preferred":[
        "Mine"
    ],
    "name:rus_x_preferred":[
        "Mine"
    ],
    "name:swe_x_preferred":[
        "Mine"
    ],
    "name:tgl_x_preferred":[
        "Mine"
    ],
    "name:tha_x_preferred":[
        "\u0e44\u0e21\u0e19\u0e4c"
    ],
    "name:tur_x_preferred":[
        "Mine"
    ],
    "name:vie_x_preferred":[
        "Mine"
    ],
    "wof:name":"Mine",
    "wof:placetype":"locality"
},
  "geometry": {"coordinates":[139.92543999999998,35.36436],"type":"Point"}
}