{
  "type": "Feature",
  "properties": {
    "gn:admin1_code":"4.0",
    "gn:admin2_code":"8304237.0",
    "gn:asciiname":"Mine",
    "gn:country_code":"JP",
    "gn:dem":34,
    "gn:feature_class":"P",
    "gn:feature_code":"PPLL",
    "gn:name":"Mine",
    "gn:population":0,
    "gn:timezone":"Asia/Tokyo",
    "iso:country":"JP",
    "name:jpn_x_preferred":[
        "\u5cf0"
    ],
    "name:jpn_x_variant":[
        "\u307f\u306d",
        "\u30df\u30cd"
    ],
    "wof:name":"Mine",
    "wof:placetype":"locality"
},
  "geometry": {"coordinates":[139.92543999999998,35.36436],"type":"Point"}
}