{
  "type": "Feature",
  "properties": {
    "gn:admin1_code":"23.0",
    "gn:admin2_code":"7417711.0",
    "gn:asciiname":"Futaocho",
    "gn:country_code":"JP",
    "gn:dem":83,
    "gn:feature_class":"P",
    "gn:feature_code":"PPL",
    "gn:name":"Futaoch\u014d",
    "gn:population":0,
    "gn:timezone":"Asia/Tokyo",
    "iso:country":"JP",
    "name:jpn_x_preferred":[
        "\u4e21\u5c3e\u753a"
    ],
    "name:und_x_variant":[
        "Futaoch\u014d"
    ],
    "wof:name":"Futaocho",
    "wof:placetype":"locality"
},
  "geometry": {"coordinates":[136.42676,34.90305],"type":"Point"}
}