{
  "type": "Feature",
  "properties": {
    "gn:admin1_code":"21.0",
    "gn:admin2_code":"1848441.0",
    "gn:asciiname":"Amagaemachi",
    "gn:country_code":"JP",
    "gn:dem":-1,
    "gn:feature_class":"P",
    "gn:feature_code":"PPL",
    "gn:name":"Amagaemachi",
    "gn:population":0,
    "gn:timezone":"Asia/Tokyo",
    "iso:country":"JP",
    "name:jpn_x_preferred":[
        "\u6d77\u58eb\u6c5f\u753a"
    ],
    "name:jpn_x_variant":[
        "\u3042\u307e\u304c\u3048\u307e\u3061",
        "\u30a2\u30de\u30ac\u30a8\u30de\u30c1"
    ],
    "wof:name":"Amagaemachi",
    "wof:placetype":"locality"
},
  "geometry": {"coordinates":[130.62197,32.52892],"type":"Point"}
}