{
  "type": "Feature",
  "properties": {
    "iso:country":"JP",
    "name:eng_x_preferred":[
        "Reihoku"
    ],
    "name:eng_x_variant":[
        "Reihoku Town"
    ],
    "name:jpn_x_preferred":[
        "\u82d3\u5317\u753a"
    ],
    "qs:name":"\u82d3\u5317\u753a",
    "qs:name_adm0":"\u65e5\u672c",
    "qs:name_adm1":"\u718a\u672c\u770c",
    "qs:photos":39,
    "qs:photos_1k":8,
    "qs:photos_9k":1,
    "qs:photos_9r":2,
    "qs:photos_all":39,
    "qs:photos_sr":2,
    "qs:placetype":"Town",
    "qs:pop_sr":"0",
    "wof:name":"Reihoku",
    "wof:placetype":"locality"
},
  "geometry": {"coordinates":[130.03049999999999,32.529316],"type":"Point"}
}