{
  "type": "Feature",
  "properties": {
    "gn:admin1_code":"21.0",
    "gn:admin2_code":"1859490.0",
    "gn:admin3_code":"43403.0",
    "gn:asciiname":"Iwasaka",
    "gn:country_code":"JP",
    "gn:dem":94,
    "gn:feature_class":"P",
    "gn:feature_code":"PPL",
    "gn:name":"Iwasaka",
    "gn:population":0,
    "gn:timezone":"Asia/Tokyo",
    "iso:country":"JP",
    "name:jpn_x_preferred":[
        "\u5ca9\u5742"
    ],
    "name:jpn_x_variant":[
        "\u3044\u308f\u3055\u304b",
        "\u30a4\u30ef\u30b5\u30ab"
    ],
    "wof:name":"Iwasaka",
    "wof:placetype":"locality"
},
  "geometry": {"coordinates":[130.88713999999999,32.85895],"type":"Point"}
}