{
  "type": "Feature",
  "properties": {
    "gn:admin1_code":"3.0",
    "gn:admin2_code":"2129393.0",
    "gn:asciiname":"Sakunoki",
    "gn:country_code":"JP",
    "gn:dem":70,
    "gn:feature_class":"P",
    "gn:feature_code":"PPL",
    "gn:name":"Sakunoki",
    "gn:population":0,
    "gn:timezone":"Asia/Tokyo",
    "iso:country":"JP",
    "name:jpn_x_preferred":[
        "\u67f5\u30ce\u6728"
    ],
    "name:jpn_x_variant":[
        "\u3055\u304f\u306e\u304d",
        "\u30b5\u30af\u30ce\u30ad"
    ],
    "wof:name":"Sakunoki",
    "wof:placetype":"locality"
},
  "geometry": {"coordinates":[140.61057,40.63807],"type":"Point"}
}