{
  "type": "Feature",
  "properties": {
    "gn:admin1_code":"24.0",
    "gn:admin2_code":"2111889.0",
    "gn:admin3_code":"4401.0",
    "gn:asciiname":"Kyozan",
    "gn:country_code":"JP",
    "gn:dem":26,
    "gn:feature_class":"P",
    "gn:feature_code":"PPL",
    "gn:name":"Kyozan",
    "gn:population":0,
    "gn:timezone":"Asia/Tokyo",
    "iso:country":"JP",
    "name:jpn_x_preferred":[
        "\u5c45\u5c71"
    ],
    "name:jpn_x_variant":[
        "\u304d\u3087\u3056\u3093",
        "\u30ad\u30e7\u30b6\u30f3"
    ],
    "wof:name":"Kyozan",
    "wof:placetype":"locality"
},
  "geometry": {"coordinates":[141.0633,38.39761],"type":"Point"}
}