{
  "type": "Feature",
  "properties": {
    "gn:admin1_code":"21.0",
    "gn:admin2_code":"1848441.0",
    "gn:asciiname":"Sendanmachi",
    "gn:country_code":"JP",
    "gn:dem":6,
    "gn:feature_class":"P",
    "gn:feature_code":"PPL",
    "gn:name":"Sendanmachi",
    "gn:population":0,
    "gn:timezone":"Asia/Tokyo",
    "iso:country":"JP",
    "name:jpn_x_preferred":[
        "\u6834\u6a80\u753a"
    ],
    "wof:name":"Sendanmachi",
    "wof:placetype":"locality"
},
  "geometry": {"coordinates":[130.59718999999998,32.49501],"type":"Point"}
}