{
  "type": "Feature",
  "properties": {
    "gn:admin1_code":"28.0",
    "gn:admin2_code":"1853062.0",
    "gn:asciiname":"Shiba",
    "gn:country_code":"JP",
    "gn:dem":71,
    "gn:feature_class":"P",
    "gn:feature_code":"PPL",
    "gn:name":"Shiba",
    "gn:population":0,
    "gn:timezone":"Asia/Tokyo",
    "iso:country":"JP",
    "name:ceb_x_preferred":[
        "Shiba"
    ],
    "name:deu_x_preferred":[
        "Shiba"
    ],
    "name:fas_x_preferred":[
        "\u0634\u06cc\u0628\u0627"
    ],
    "name:fra_x_preferred":[
        "Shiba"
    ],
    "name:ita_x_preferred":[
        "Shiba"
    ],
    "name:jpn_x_preferred":[
        "\u829d"
    ],
    "name:pol_x_preferred":[
        "Shiba"
    ],
    "name:rus_x_preferred":[
        "\u0421\u0438\u0431\u0430"
    ],
    "wof:name":"Shiba",
    "wof:placetype":"locality"
},
  "geometry": {"coordinates":[135.84156999999999,34.53472],"type":"Point"}
}