{
  "type": "Feature",
  "properties": {
    "gn:admin1_code":"28.0",
    "gn:admin2_code":"1853062.0",
    "gn:asciiname":"Shiba",
    "gn:country_code":"JP",
    "gn:dem":71,
    "gn:feature_class":"P",
    "gn:feature_code":"PPL",
    "gn:name":"Shiba",
    "gn:population":0,
    "gn:timezone":"Asia/Tokyo",
    "iso:country":"JP",
    "name:jpn_x_preferred":[
        "\u829d"
    ],
    "wof:name":"Shiba",
    "wof:placetype":"locality"
},
  "geometry": {"coordinates":[135.84156999999999,34.53472],"type":"Point"}
}