{
  "type": "Feature",
  "properties": {
    "gn:admin1_code":"4.0",
    "gn:admin2_code":"2112330.0",
    "gn:asciiname":"Masuodai",
    "gn:country_code":"JP",
    "gn:dem":27,
    "gn:feature_class":"P",
    "gn:feature_code":"PPL",
    "gn:name":"Masuodai",
    "gn:population":0,
    "gn:timezone":"Asia/Tokyo",
    "iso:country":"JP",
    "name:jpn_x_preferred":[
        "\u5897\u5c3e\u53f0"
    ],
    "wof:name":"Masuodai",
    "wof:placetype":"locality"
},
  "geometry": {"coordinates":[139.97388999999998,35.82445999999999],"type":"Point"}
}