{
  "type": "Feature",
  "properties": {
    "gn:admin1_code":"2.0",
    "gn:admin2_code":"2113122.0",
    "gn:asciiname":"Shimokitate-takarakawa",
    "gn:country_code":"JP",
    "gn:dem":53,
    "gn:feature_class":"P",
    "gn:feature_code":"PPL",
    "gn:name":"Shimokitate-takarakawa",
    "gn:population":0,
    "gn:timezone":"Asia/Tokyo",
    "iso:country":"JP",
    "name:jpn_x_preferred":[
        "\u4e0b\u5317\u624b\u5b9d\u5ddd"
    ],
    "name:jpn_x_variant":[
        "\u3057\u3082\u304d\u305f\u3066\u305f\u304b\u3089\u304b\u308f",
        "\u30b7\u30e2\u30ad\u30bf\u30c6\u30bf\u30ab\u30e9\u30ab\u30ef",
        "\u5b9d\u5ddd"
    ],
    "name:und_x_variant":[
        "Takarakawa"
    ],
    "wof:name":"Shimokitate-takarakawa",
    "wof:placetype":"locality"
},
  "geometry": {"coordinates":[140.1979,39.71183],"type":"Point"}
}