{
  "type": "Feature",
  "properties": {
    "gn:admin1_code":"21.0",
    "gn:admin2_code":"1858418.0",
    "gn:admin3_code":"43104.0",
    "gn:asciiname":"Aidomimachi",
    "gn:country_code":"JP",
    "gn:dem":2,
    "gn:feature_class":"P",
    "gn:feature_code":"PPL",
    "gn:name":"Aidomimachi",
    "gn:population":0,
    "gn:timezone":"Asia/Tokyo",
    "iso:country":"JP",
    "name:jpn_x_preferred":[
        "\u4f1a\u5bcc\u753a"
    ],
    "name:jpn_x_variant":[
        "\u3042\u3044\u3069\u307f\u307e\u3061",
        "\u30a2\u30a4\u30c9\u30df\u30de\u30c1"
    ],
    "wof:name":"Aidomimachi",
    "wof:placetype":"locality"
},
  "geometry": {"coordinates":[130.65468999999999,32.75337],"type":"Point"}
}