{
  "type": "Feature",
  "properties": {
    "gn:admin1_code":"11",
    "gn:admin2_code":"1858288.0",
    "gn:asciiname":"Ondocho-tonoko",
    "gn:country_code":"JP",
    "gn:dem":16,
    "gn:feature_class":"P",
    "gn:feature_code":"PPL",
    "gn:name":"Ondoch\u014d-tonoko",
    "gn:population":0,
    "gn:timezone":"Asia/Tokyo",
    "iso:country":"JP",
    "name:jpn_x_preferred":[
        "\u97f3\u6238\u753a\u6e21\u5b50"
    ],
    "name:und_x_variant":[
        "Ondoch\u014d-tonoko",
        "Tonoko"
    ],
    "wof:name":"Ondocho-tonoko",
    "wof:placetype":"locality"
},
  "geometry": {"coordinates":[132.51388,34.18837],"type":"Point"}
}