{
  "type": "Feature",
  "properties": {
    "gn:admin1_code":"40",
    "gn:admin2_code":"1858665.0",
    "gn:asciiname":"Fukuzumi",
    "gn:country_code":"JP",
    "gn:dem":8,
    "gn:feature_class":"P",
    "gn:feature_code":"PPL",
    "gn:name":"Fukuzumi",
    "gn:population":0,
    "gn:timezone":"Asia/Tokyo",
    "iso:country":"JP",
    "name:jpn_x_preferred":[
        "\u798f\u4f4f"
    ],
    "name:und_x_variant":[
        "Fukuzumich\u014d",
        "Fukagawa-Fukuzumich\u014d",
        "Fukuzumi"
    ],
    "wof:name":"Fukuzumi",
    "wof:placetype":"locality"
},
  "geometry": {"coordinates":[139.79241999999999,35.67625],"type":"Point"}
}