{
  "type": "Feature",
  "properties": {
    "gn:admin1_code":"19.0",
    "gn:admin2_code":"1848350.0",
    "gn:admin3_code":"14107.0",
    "gn:asciiname":"Morigaoka",
    "gn:country_code":"JP",
    "gn:dem":51,
    "gn:feature_class":"P",
    "gn:feature_code":"PPL",
    "gn:name":"Morigaoka",
    "gn:population":0,
    "gn:timezone":"Asia/Tokyo",
    "iso:country":"JP",
    "name:jpn_x_preferred":[
        "\u68ee\u304c\u4e18"
    ],
    "name:jpn_x_variant":[
        "\u3082\u308a\u304c\u304a\u304b",
        "\u30e2\u30ea\u30ac\u30aa\u30ab"
    ],
    "wof:name":"Morigaoka",
    "wof:placetype":"locality"
},
  "geometry": {"coordinates":[139.60216,35.40117],"type":"Point"}
}