{
  "type": "Feature",
  "properties": {
    "gn:admin1_code":"13.0",
    "gn:admin2_code":"1859671.0",
    "gn:asciiname":"Yuyamadai",
    "gn:country_code":"JP",
    "gn:dem":95,
    "gn:feature_class":"P",
    "gn:feature_code":"PPL",
    "gn:name":"Yuyamadai",
    "gn:population":0,
    "gn:timezone":"Asia/Tokyo",
    "iso:country":"JP",
    "name:jpn_x_preferred":[
        "\u6e6f\u5c71\u53f0"
    ],
    "wof:name":"Yuyamadai",
    "wof:placetype":"locality"
},
  "geometry": {"coordinates":[135.40121000000002,34.84954],"type":"Point"}
}