{
  "type": "Feature",
  "properties": {
    "gn:admin1_code":"3.0",
    "gn:admin2_code":"2129754.0",
    "gn:admin3_code":"2408.0",
    "gn:asciiname":"Hamadai",
    "gn:country_code":"JP",
    "gn:dem":7,
    "gn:feature_class":"P",
    "gn:feature_code":"PPL",
    "gn:name":"Hamadai",
    "gn:population":0,
    "gn:timezone":"Asia/Tokyo",
    "iso:country":"JP",
    "name:jpn_x_preferred":[
        "\u6d5c\u53f0"
    ],
    "name:jpn_x_variant":[
        "\u306f\u307e\u3060\u3044",
        "\u30cf\u30de\u30c0\u30a4"
    ],
    "wof:name":"Hamadai",
    "wof:placetype":"locality"
},
  "geometry": {"coordinates":[141.29587000000001,40.81297],"type":"Point"}
}