{
  "type": "Feature",
  "properties": {
    "gn:admin1_code":"19.0",
    "gn:admin2_code":"1848350.0",
    "gn:admin3_code":"14109.0",
    "gn:asciiname":"Toriyamacho",
    "gn:country_code":"JP",
    "gn:dem":5,
    "gn:feature_class":"P",
    "gn:feature_code":"PPL",
    "gn:name":"Toriyamach\u014d",
    "gn:population":0,
    "gn:timezone":"Asia/Tokyo",
    "iso:country":"JP",
    "name:jpn_x_preferred":[
        "\u9ce5\u5c71\u753a"
    ],
    "name:jpn_x_variant":[
        "\u3068\u308a\u3084\u307e\u3061\u3087\u3046",
        "\u30c8\u30ea\u30e4\u30de\u30c1\u30e7\u30a6"
    ],
    "name:und_x_variant":[
        "Toriyamach\u014d"
    ],
    "wof:name":"Toriyamacho",
    "wof:placetype":"locality"
},
  "geometry": {"coordinates":[139.60401999999999,35.50358],"type":"Point"}
}