{
  "type": "Feature",
  "properties": {
    "gn:admin1_code":"6.0",
    "gn:admin2_code":"7467385.0",
    "gn:asciiname":"Minamihikida",
    "gn:country_code":"JP",
    "gn:dem":8,
    "gn:feature_class":"P",
    "gn:feature_code":"PPL",
    "gn:name":"Minamihikida",
    "gn:population":0,
    "gn:timezone":"Asia/Tokyo",
    "iso:country":"JP",
    "name:jpn_x_preferred":[
        "\u5357\u758b\u7530"
    ],
    "wof:name":"Minamihikida",
    "wof:placetype":"locality"
},
  "geometry": {"coordinates":[136.26464999999999,36.18213],"type":"Point"}
}