{
  "type": "Feature",
  "properties": {
    "gn:admin1_code":"18.0",
    "gn:admin2_code":"7383991.0",
    "gn:asciiname":"Ishigochi",
    "gn:country_code":"JP",
    "gn:dem":260,
    "gn:feature_class":"P",
    "gn:feature_code":"PPLL",
    "gn:name":"Ishigochi",
    "gn:population":0,
    "gn:timezone":"Asia/Tokyo",
    "iso:country":"JP",
    "name:jpn_x_preferred":[
        "\u77f3\u4e95\u5ddd\u5185"
    ],
    "name:jpn_x_variant":[
        "\u3044\u3057\u3054\u3061",
        "\u30a4\u30b7\u30b4\u30c1"
    ],
    "wof:name":"Ishigochi",
    "wof:placetype":"locality"
},
  "geometry": {"coordinates":[130.56942000000001,32.12073],"type":"Point"}
}