{
  "type": "Feature",
  "properties": {
    "gn:admin1_code":"36",
    "gn:admin2_code":"1857549.0",
    "gn:asciiname":"Kashimacho-etomo",
    "gn:country_code":"JP",
    "gn:dem":58,
    "gn:feature_class":"P",
    "gn:feature_code":"PPL",
    "gn:name":"Kashimach\u014d-etomo",
    "gn:population":0,
    "gn:timezone":"Asia/Tokyo",
    "iso:country":"JP",
    "name:jpn_x_preferred":[
        "\u9e7f\u5cf6\u753a\u6075\u66c7"
    ],
    "name:und_x_variant":[
        "Etomo",
        "Etomomachi",
        "Kashimach\u014d-etomo"
    ],
    "wof:name":"Kashimacho-etomo",
    "wof:placetype":"locality"
},
  "geometry": {"coordinates":[132.97763,35.53095],"type":"Point"}
}