{
  "type": "Feature",
  "properties": {
    "gn:admin1_code":"18",
    "gn:admin2_code":"7383987.0",
    "gn:asciiname":"Sumiyocho-gusuku",
    "gn:country_code":"JP",
    "gn:dem":69,
    "gn:feature_class":"P",
    "gn:feature_code":"PPL",
    "gn:name":"Sumiy\u014dch\u014d-gusuku",
    "gn:population":0,
    "gn:timezone":"Asia/Tokyo",
    "iso:country":"JP",
    "name:jpn_x_preferred":[
        "\u4f4f\u7528\u753a\u57ce"
    ],
    "name:und_x_variant":[
        "Shiro",
        "Kuj\u014d",
        "Gusuku",
        "Sumiy\u014dch\u014d-gusuku"
    ],
    "wof:name":"Sumiyocho-gusuku",
    "wof:placetype":"locality"
},
  "geometry": {"coordinates":[129.46251999999998,28.30009],"type":"Point"}
}