{
  "type": "Feature",
  "properties": {
    "gn:admin1_code":"22",
    "gn:admin2_code":"7412201.0",
    "gn:asciiname":"Habu",
    "gn:country_code":"JP",
    "gn:dem":443,
    "gn:feature_class":"P",
    "gn:feature_code":"PPL",
    "gn:name":"Habu",
    "gn:population":0,
    "gn:timezone":"Asia/Tokyo",
    "iso:country":"JP",
    "name:fra_x_preferred":[
        "Habu"
    ],
    "name:jpn_x_preferred":[
        "\u30cf\u30d6"
    ],
    "name:por_x_preferred":[
        "Habu"
    ],
    "wof:name":"Habu",
    "wof:placetype":"locality"
},
  "geometry": {"coordinates":[135.44999999999999,35.05],"type":"Point"}
}