{
  "type": "Feature",
  "properties": {
    "gn:admin1_code":"37.0",
    "gn:admin2_code":"1864089.0",
    "gn:asciiname":"Atsuharanaka",
    "gn:country_code":"JP",
    "gn:dem":60,
    "gn:feature_class":"P",
    "gn:feature_code":"PPLL",
    "gn:name":"Atsuharanaka",
    "gn:population":0,
    "gn:timezone":"Asia/Tokyo",
    "iso:country":"JP",
    "name:jpn_x_preferred":[
        "\u539a\u539f\u4e2d"
    ],
    "wof:name":"Atsuharanaka",
    "wof:placetype":"locality"
},
  "geometry": {"coordinates":[138.65960999999999,35.1846],"type":"Point"}
}