{
  "type": "Feature",
  "properties": {
    "iso:country":"JP",
    "name:eng_x_preferred":[
        "Miyanosawaichijo 2 Chome"
    ],
    "name:eng_x_variant":[
        "Miyanosawaichijou 2 Choume",
        "Miyanosawaichijo 2 Chome"
    ],
    "name:jpn_x_preferred":[
        "\uff12\u4e01\u76ee"
    ],
    "name:jpn_x_variant":[
        "\u307f\u3084\u306e\u3055\u308f\u3044\u3061\u3058\u3087\u3046 \uff12\u3061\u3087\u3046\u3081",
        "\u5bae\u306e\u6ca2\u4e00\u6761 \uff12\u4e01\u76ee",
        "\uff12\u3061\u3087\u3046\u3081"
    ],
    "name:unk_x_variant":[
        "\uff12\u4e01\u76ee"
    ],
    "qs:gn_local":0,
    "qs:local_max":2554,
    "qs:local_sum":22076,
    "qs:localhoods":97,
    "qs:name":"\uff12\u4e01\u76ee",
    "qs:name_adm0":"\u65e5\u672c",
    "qs:name_adm1":"\u5317\u6d77\u9053",
    "qs:name_adm2":"\u897f\u533a",
    "qs:name_en":"Miyanosawaichijo 2 Chome",
    "qs:name_lau":"\u5bae\u306e\u6ca2\u4e00\u6761",
    "qs:name_local":"\u672d\u5e4c\u5e02",
    "qs:photo_max":259,
    "qs:photo_sum":393,
    "qs:placetype":"Suburb",
    "qs:quad_count":10,
    "qs:woe_adm0":23424856,
    "qs:woe_adm1":7153351,
    "qs:woe_adm2":15015545,
    "qs:woe_lau":28380030,
    "qs:woe_local":1118108,
    "qs:woe_ver":"7.10.0",
    "wof:lang":[
        "jpn"
    ],
    "wof:name":"\uff12\u4e01\u76ee",
    "wof:placetype":"neighbourhood"
},
  "geometry": {"coordinates":[141.27167299999999,43.089432],"type":"Point"}
}