{
  "type": "Feature",
  "properties": {
    "iso:country":"JP",
    "qs:name":"\u5bae\u7530\u6751",
    "qs:name_adm0":"\u65e5\u672c",
    "qs:name_adm1":"\u9577\u91ce\u770c",
    "qs:photos":771,
    "qs:photos_1k":156,
    "qs:photos_9k":3,
    "qs:photos_9r":6,
    "qs:photos_all":771,
    "qs:photos_sr":9,
    "qs:placetype":"Town",
    "qs:pop_sr":"0",
    "wof:name":"\u5bae\u7530\u6751",
    "wof:placetype":"locality"
},
  "geometry": {"coordinates":[137.80883299999999,35.7825],"type":"Point"}
}