{
  "type": "Feature",
  "properties": {
    "gn:admin1_code":"36",
    "gn:admin2_code":"1863308.0",
    "gn:asciiname":"Asaicho",
    "gn:country_code":"JP",
    "gn:dem":48,
    "gn:feature_class":"P",
    "gn:feature_code":"PPL",
    "gn:name":"Asaich\u014d",
    "gn:population":0,
    "gn:timezone":"Asia/Tokyo",
    "iso:country":"JP",
    "name:jpn_x_preferred":[
        "\u6d45\u4e95\u753a"
    ],
    "name:und_x_variant":[
        "Asaich\u014d",
        "Asai"
    ],
    "wof:name":"Asaicho",
    "wof:placetype":"locality"
},
  "geometry": {"coordinates":[132.08393000000001,34.90731],"type":"Point"}
}