{
  "type": "Feature",
  "properties": {
    "iso:country":"JP",
    "name:eng_x_preferred":[
        "Kazahaya 1 Chome"
    ],
    "name:eng_x_variant":[
        "Kazahaya 1 Choume",
        "Kazahaya 1 Chome"
    ],
    "name:jpn_x_preferred":[
        "\uff11\u4e01\u76ee"
    ],
    "name:jpn_x_variant":[
        "\u304b\u3056\u306f\u3084 \uff11\u3061\u3087\u3046\u3081",
        "\u98a8\u65e9 \uff11\u4e01\u76ee",
        "\uff11\u3061\u3087\u3046\u3081"
    ],
    "qs:gn_adm0_cc":"JP",
    "qs:gn_local":1859924,
    "qs:gn_nam_loc":"\u67cf\u5e02, \u5343\u8449\u770c, JP",
    "qs:gn_namadm1":"04",
    "qs:local_max":531,
    "qs:local_sum":2701,
    "qs:localhoods":19,
    "qs:name":"\uff11\u4e01\u76ee",
    "qs:name_adm0":"\u65e5\u672c",
    "qs:name_adm1":"\u5343\u8449\u770c",
    "qs:name_en":"Kazahaya 1 Chome",
    "qs:name_lau":"\u98a8\u65e9",
    "qs:name_local":"\u67cf\u5e02",
    "qs:photo_max":6,
    "qs:photo_sum":6,
    "qs:placetype":"Suburb",
    "qs:quad_count":1,
    "qs:woe_adm0":23424856,
    "qs:woe_adm1":2345854,
    "qs:woe_adm2":0,
    "qs:woe_lau":28411969,
    "qs:woe_local":1117469,
    "qs:woe_ver":"7.10.0",
    "wof:lang":[
        "jpn"
    ],
    "wof:name":"\uff11\u4e01\u76ee",
    "wof:placetype":"neighbourhood"
},
  "geometry": {"coordinates":[140.01251199999999,35.828949],"type":"Point"}
}