{
  "type": "Feature",
  "properties": {
    "gn:admin1_code":"45.0",
    "gn:admin2_code":"1852222.0",
    "gn:asciiname":"Hatabu-miyanoshitacho",
    "gn:country_code":"JP",
    "gn:dem":7,
    "gn:feature_class":"P",
    "gn:feature_code":"PPL",
    "gn:name":"Hatabu-miyanoshitach\u014d",
    "gn:population":0,
    "gn:timezone":"Asia/Tokyo",
    "iso:country":"JP",
    "name:jpn_x_preferred":[
        "\u5e61\u751f\u5bae\u306e\u4e0b\u753a"
    ],
    "name:und_x_variant":[
        "Hatabu-miyanoshitach\u014d"
    ],
    "wof:name":"Hatabu-miyanoshitacho",
    "wof:placetype":"locality"
},
  "geometry": {"coordinates":[130.93111999999999,33.98178],"type":"Point"}
}