{
  "type": "Feature",
  "properties": {
    "gn:admin1_code":"3.0",
    "gn:admin2_code":"7439934.0",
    "gn:asciiname":"Kojo",
    "gn:country_code":"JP",
    "gn:dem":37,
    "gn:feature_class":"P",
    "gn:feature_code":"PPL",
    "gn:name":"K\u014dj\u014d",
    "gn:population":0,
    "gn:timezone":"Asia/Tokyo",
    "iso:country":"JP",
    "name:deu_x_preferred":[
        "Kojo"
    ],
    "name:fin_x_preferred":[
        "Kojo"
    ],
    "name:jpn_x_preferred":[
        "K\u014dj\u014d"
    ],
    "name:jpn_x_variant":[
        "\u5149\u57ce",
        "\u3053\u3046\u3058\u3087\u3046",
        "\u30b3\u30a6\u30b8\u30e7\u30a6"
    ],
    "name:rus_x_preferred":[
        "\u041a\u043e\u0439\u043e"
    ],
    "wof:name":"Kojo",
    "wof:placetype":"locality"
},
  "geometry": {"coordinates":[140.55861999999999,40.59101],"type":"Point"}
}