{
  "type": "Feature",
  "properties": {
    "gn:admin1_code":"25.0",
    "gn:admin2_code":"7413970.0",
    "gn:asciiname":"Nagakutsu",
    "gn:country_code":"JP",
    "gn:dem":241,
    "gn:feature_class":"P",
    "gn:feature_code":"PPLL",
    "gn:name":"Nagakutsu",
    "gn:population":0,
    "gn:timezone":"Asia/Tokyo",
    "iso:country":"JP",
    "name:jpn_x_preferred":[
        "\u6c38\u4e45\u6d25"
    ],
    "name:jpn_x_variant":[
        "\u306a\u304c\u304f\u3064",
        "\u30ca\u30ac\u30af\u30c4"
    ],
    "wof:name":"Nagakutsu",
    "wof:placetype":"locality"
},
  "geometry": {"coordinates":[130.96652,32.02178],"type":"Point"}
}