{
  "type": "Feature",
  "properties": {
    "gn:admin1_code":"13.0",
    "gn:admin2_code":"7370821.0",
    "gn:asciiname":"Eifuku",
    "gn:country_code":"JP",
    "gn:dem":139,
    "gn:feature_class":"P",
    "gn:feature_code":"PPL",
    "gn:name":"Eifuku",
    "gn:population":0,
    "gn:timezone":"Asia/Tokyo",
    "iso:country":"JP",
    "name:jpn_x_preferred":[
        "\u6c38\u798f"
    ],
    "wof:name":"Eifuku",
    "wof:placetype":"locality"
},
  "geometry": {"coordinates":[135.09386999999998,34.91225],"type":"Point"}
}