{
  "type": "Feature",
  "properties": {
    "gn:admin1_code":"33.0",
    "gn:admin2_code":"8300623.0",
    "gn:asciiname":"Choda",
    "gn:country_code":"JP",
    "gn:dem":4,
    "gn:feature_class":"P",
    "gn:feature_code":"PPL",
    "gn:name":"Ch\u014dda",
    "gn:population":0,
    "gn:timezone":"Asia/Tokyo",
    "iso:country":"JP",
    "name:jpn_x_preferred":[
        "\u753a\u7530"
    ],
    "name:und_x_variant":[
        "Ch\u014dda"
    ],
    "wof:name":"Choda",
    "wof:placetype":"locality"
},
  "geometry": {"coordinates":[129.96769,33.43979],"type":"Point"}
}