{
  "type": "Feature",
  "properties": {
    "gn:admin1_code":"21.0",
    "gn:admin2_code":"1848441.0",
    "gn:asciiname":"Kesado",
    "gn:country_code":"JP",
    "gn:dem":86,
    "gn:feature_class":"P",
    "gn:feature_code":"PPLL",
    "gn:name":"Kesad\u014d",
    "gn:population":0,
    "gn:timezone":"Asia/Tokyo",
    "iso:country":"JP",
    "name:jpn_x_preferred":[
        "\u8888\u88df\u5802"
    ],
    "name:und_x_variant":[
        "Kesad\u014d"
    ],
    "wof:name":"Kesado",
    "wof:placetype":"locality"
},
  "geometry": {"coordinates":[130.65697,32.47137],"type":"Point"}
}