{
  "type": "Feature",
  "properties": {
    "gn:admin1_code":"21.0",
    "gn:admin2_code":"1848441.0",
    "gn:asciiname":"Nishimuta-shimogumi",
    "gn:country_code":"JP",
    "gn:dem":0,
    "gn:feature_class":"P",
    "gn:feature_code":"PPLL",
    "gn:name":"Nishimuta-shimogumi",
    "gn:population":0,
    "gn:timezone":"Asia/Tokyo",
    "iso:country":"JP",
    "name:jpn_x_preferred":[
        "\u897f\u725f\u7530\u4e0b\u7d44"
    ],
    "name:jpn_x_variant":[
        "\u306b\u3057\u3080\u305f\u3057\u3082\u3050\u307f",
        "\u30cb\u30b7\u30e0\u30bf\u30b7\u30e2\u30b0\u30df"
    ],
    "wof:name":"Nishimuta-shimogumi",
    "wof:placetype":"locality"
},
  "geometry": {"coordinates":[130.61433,32.53927],"type":"Point"}
}