{
  "type": "Feature",
  "properties": {
    "gn:admin1_code":"34.0",
    "gn:admin2_code":"1858728.0",
    "gn:asciiname":"Higashiosawa",
    "gn:country_code":"JP",
    "gn:dem":6,
    "gn:feature_class":"P",
    "gn:feature_code":"PPL",
    "gn:name":"Higashi\u014dsawa",
    "gn:population":0,
    "gn:timezone":"Asia/Tokyo",
    "iso:country":"JP",
    "name:jpn_x_preferred":[
        "\u6771\u5927\u6ca2"
    ],
    "name:und_x_variant":[
        "Higashi\u014dsawa"
    ],
    "wof:name":"Higashiosawa",
    "wof:placetype":"locality"
},
  "geometry": {"coordinates":[139.78954999999999,35.90963],"type":"Point"}
}