{
  "type": "Feature",
  "properties": {
    "iso:country":"JP",
    "name:eng_x_preferred":[
        "Hamasaki 4 Chome"
    ],
    "name:eng_x_variant":[
        "Hamasaki 4 Choume",
        "Hamasaki 4 Chome"
    ],
    "name:jpn_x_preferred":[
        "\uff14\u4e01\u76ee"
    ],
    "name:jpn_x_variant":[
        "\u306f\u307e\u3055\u304d \uff14\u3061\u3087\u3046\u3081",
        "\u6d5c\u5d0e \uff14\u4e01\u76ee",
        "\uff14\u3061\u3087\u3046\u3081"
    ],
    "qs:gn_adm0_cc":"JP",
    "qs:gn_local":1907299,
    "qs:gn_nam_loc":"\u671d\u971e\u5e02, \u57fc\u7389\u770c, JP",
    "qs:gn_namadm1":"34",
    "qs:local_max":167,
    "qs:local_sum":318,
    "qs:localhoods":4,
    "qs:name":"\uff14\u4e01\u76ee",
    "qs:name_adm0":"\u65e5\u672c",
    "qs:name_adm1":"\u57fc\u7389\u770c",
    "qs:name_en":"Hamasaki 4 Chome",
    "qs:name_lau":"\u6d5c\u5d0e",
    "qs:name_local":"\u671d\u971e\u5e02",
    "qs:photo_max":25,
    "qs:photo_sum":45,
    "qs:placetype":"Suburb",
    "qs:quad_count":6,
    "qs:woe_adm0":23424856,
    "qs:woe_adm1":2345883,
    "qs:woe_adm2":0,
    "qs:woe_lau":28409376,
    "qs:woe_local":15015443,
    "qs:woe_ver":"7.10.0",
    "wof:lang":[
        "jpn"
    ],
    "wof:name":"\uff14\u4e01\u76ee",
    "wof:placetype":"neighbourhood"
},
  "geometry": {"coordinates":[139.60429199999999,35.812354],"type":"Point"}
}