{
  "type": "Feature",
  "properties": {
    "gn:admin1_code":"35.0",
    "gn:admin2_code":"1858984.0",
    "gn:asciiname":"Konancho-sugitani",
    "gn:country_code":"JP",
    "gn:dem":210,
    "gn:feature_class":"P",
    "gn:feature_code":"PPL",
    "gn:name":"K\u014dnanch\u014d-sugitani",
    "gn:population":0,
    "gn:timezone":"Asia/Tokyo",
    "iso:country":"JP",
    "name:jpn_x_preferred":[
        "\u7532\u5357\u753a\u6749\u8c37"
    ],
    "name:und_x_variant":[
        "K\u014dnanch\u014d-sugitani"
    ],
    "wof:name":"Konancho-sugitani",
    "wof:placetype":"locality"
},
  "geometry": {"coordinates":[136.14583000000002,34.9189],"type":"Point"}
}