{
  "type": "Feature",
  "properties": {
    "gn:admin1_code":"2.0",
    "gn:admin2_code":"2113122.0",
    "gn:asciiname":"Araya-tajirizawanishimachi",
    "gn:country_code":"JP",
    "gn:dem":9,
    "gn:feature_class":"P",
    "gn:feature_code":"PPL",
    "gn:name":"Araya-tajirizawanishimachi",
    "gn:population":0,
    "gn:timezone":"Asia/Tokyo",
    "iso:country":"JP",
    "name:jpn_x_preferred":[
        "\u65b0\u5c4b\u7530\u5c3b\u6ca2\u897f\u753a"
    ],
    "name:jpn_x_variant":[
        "\u3042\u3089\u3084\u305f\u3058\u308a\u3056\u308f\u306b\u3057\u307e\u3061",
        "\u30a2\u30e9\u30e4\u30bf\u30b8\u30ea\u30b6\u30ef\u30cb\u30b7\u30de\u30c1"
    ],
    "wof:name":"Araya-tajirizawanishimachi",
    "wof:placetype":"locality"
},
  "geometry": {"coordinates":[140.09046999999998,39.66903],"type":"Point"}
}