{
  "type": "Feature",
  "properties": {
    "gn:admin1_code":"3.0",
    "gn:admin2_code":"2130088.0",
    "gn:admin3_code":"2307.0",
    "gn:asciiname":"Minmaya-shimaibashi",
    "gn:country_code":"JP",
    "gn:dem":29,
    "gn:feature_class":"P",
    "gn:feature_code":"PPL",
    "gn:name":"Minmaya-shimaibashi",
    "gn:population":0,
    "gn:timezone":"Asia/Tokyo",
    "iso:country":"JP",
    "name:jpn_x_preferred":[
        "\u4e09\u53a9\u56db\u679a\u6a4b"
    ],
    "name:jpn_x_variant":[
        "\u307f\u3093\u307e\u3084\u3057\u307e\u3044\u3070\u3057",
        "\u30df\u30f3\u30de\u30e4\u30b7\u30de\u30a4\u30d0\u30b7"
    ],
    "wof:name":"Minmaya-shimaibashi",
    "wof:placetype":"locality"
},
  "geometry": {"coordinates":[140.40508,41.21883],"type":"Point"}
}