{
  "type": "Feature",
  "properties": {
    "gn:admin1_code":"37.0",
    "gn:admin2_code":"9036693.0",
    "gn:asciiname":"Okubo",
    "gn:country_code":"JP",
    "gn:dem":44,
    "gn:feature_class":"P",
    "gn:feature_code":"PPL",
    "gn:name":"\u014ckubo",
    "gn:population":0,
    "gn:timezone":"Asia/Tokyo",
    "iso:country":"JP",
    "name:jpn_x_preferred":[
        "\u5927\u4e45\u4fdd"
    ],
    "name:und_x_variant":[
        "\u014ckubo"
    ],
    "wof:name":"Okubo",
    "wof:placetype":"locality"
},
  "geometry": {"coordinates":[138.76376000000002,34.8894],"type":"Point"}
}