{
  "type": "Feature",
  "properties": {
    "gn:country":"JP",
    "gn:fcode":"ADM3",
    "gn:pop":0,
    "iso:country":"JP",
    "name:jpn_x_preferred":[
        "\u862d\u8d8a\u753a"
    ],
    "name:jpn_x_variant":[
        "\u3089\u3093\u3053\u3057\u3061\u3087\u3046"
    ],
    "qs:name":"Rankoshi-ch\u014d",
    "qs:photos_9r":0,
    "qs:photos_sr":0,
    "qs:pop_sr":"0",
    "wof:name":"Rankoshi-ch\u014d",
    "wof:placetype":"localadmin",
    "wof:population":0
},
  "geometry": {"coordinates":[140.49125000000001,42.80031],"type":"Point"}
}