{
  "type": "Feature",
  "properties": {
    "gn:admin1_code":"21.0",
    "gn:admin2_code":"7412705.0",
    "gn:admin3_code":"43484.0",
    "gn:asciiname":"Ote",
    "gn:country_code":"JP",
    "gn:dem":27,
    "gn:feature_class":"P",
    "gn:feature_code":"PPLL",
    "gn:name":"\u014cte",
    "gn:population":0,
    "gn:timezone":"Asia/Tokyo",
    "iso:country":"JP",
    "name:jpn_x_preferred":[
        "\u5927\u624b"
    ],
    "name:jpn_x_variant":[
        "\u304a\u304a\u3066",
        "\u30aa\u30aa\u30c6"
    ],
    "name:und_x_variant":[
        "\u014cte"
    ],
    "wof:name":"Ote",
    "wof:placetype":"locality"
},
  "geometry": {"coordinates":[130.46286000000001,32.23348],"type":"Point"}
}