{
  "type": "Feature",
  "properties": {
    "gn:admin1_code":"21.0",
    "gn:admin2_code":"7413152.0",
    "gn:asciiname":"Ogawamachi-shindende",
    "gn:country_code":"JP",
    "gn:dem":1,
    "gn:feature_class":"P",
    "gn:feature_code":"PPL",
    "gn:name":"Ogawamachi-shindende",
    "gn:population":0,
    "gn:timezone":"Asia/Tokyo",
    "iso:country":"JP",
    "name:jpn_x_preferred":[
        "\u5c0f\u5ddd\u753a\u65b0\u7530\u51fa"
    ],
    "name:jpn_x_variant":[
        "\u304a\u304c\u308f\u307e\u3061\u3057\u3093\u3067\u3093\u3067",
        "\u30aa\u30ac\u30ef\u30de\u30c1\u30b7\u30f3\u30c7\u30f3\u30c7"
    ],
    "wof:name":"Ogawamachi-shindende",
    "wof:placetype":"locality"
},
  "geometry": {"coordinates":[130.68046000000001,32.6133],"type":"Point"}
}