{
  "type": "Feature",
  "properties": {
    "gn:admin1_code":"42.0",
    "gn:admin2_code":"1849870.0",
    "gn:asciiname":"Fuchumachi-fukuro",
    "gn:country_code":"JP",
    "gn:dem":17,
    "gn:feature_class":"P",
    "gn:feature_code":"PPL",
    "gn:name":"Fuch\u016bmachi-fukuro",
    "gn:population":0,
    "gn:timezone":"Asia/Tokyo",
    "iso:country":"JP",
    "name:jpn_x_preferred":[
        "\u5a66\u4e2d\u753a\u888b"
    ],
    "name:und_x_variant":[
        "Fuch\u016bmachi-fukuro"
    ],
    "wof:name":"Fuchumachi-fukuro",
    "wof:placetype":"locality"
},
  "geometry": {"coordinates":[137.15426000000002,36.65172000000001],"type":"Point"}
}