{
  "type": "Feature",
  "properties": {
    "gn:admin1_code":"3.0",
    "gn:admin2_code":"7439937.0",
    "gn:asciiname":"Minamimachi",
    "gn:country_code":"JP",
    "gn:dem":50,
    "gn:feature_class":"P",
    "gn:feature_code":"PPL",
    "gn:name":"Minamimachi",
    "gn:population":0,
    "gn:timezone":"Asia/Tokyo",
    "iso:country":"JP",
    "name:jpn_x_preferred":[
        "\u5357\u753a"
    ],
    "name:jpn_x_variant":[
        "\u307f\u306a\u307f\u307e\u3061",
        "\u30df\u30ca\u30df\u30de\u30c1"
    ],
    "wof:name":"Minamimachi",
    "wof:placetype":"locality"
},
  "geometry": {"coordinates":[141.36944,40.67321],"type":"Point"}
}