{
  "type": "Feature",
  "properties": {
    "gn:admin1_code":"47",
    "gn:admin2_code":"7415820.0",
    "gn:asciiname":"Tamagusuku",
    "gn:country_code":"JP",
    "gn:dem":9,
    "gn:feature_class":"P",
    "gn:feature_code":"PPL",
    "gn:name":"Tamagusuku",
    "gn:population":0,
    "gn:timezone":"Asia/Tokyo",
    "iso:country":"JP",
    "name:fra_x_preferred":[
        "Tamagusuku"
    ],
    "name:jpn_x_preferred":[
        "\u7389\u57ce"
    ],
    "name:vie_x_preferred":[
        "Tamagusuku"
    ],
    "wof:name":"Tamagusuku",
    "wof:placetype":"locality"
},
  "geometry": {"coordinates":[127.77639000000001,26.13583],"type":"Point"}
}