{
  "type": "Feature",
  "properties": {
    "gn:admin1_code":"3.0",
    "gn:admin2_code":"8534376.0",
    "gn:admin3_code":"2321.0",
    "gn:asciiname":"Yokoyama",
    "gn:country_code":"JP",
    "gn:dem":98,
    "gn:feature_class":"P",
    "gn:feature_code":"PPL",
    "gn:name":"Yokoyama",
    "gn:population":0,
    "gn:timezone":"Asia/Tokyo",
    "iso:country":"JP",
    "name:jpn_x_preferred":[
        "\u6a2a\u5c71"
    ],
    "name:jpn_x_variant":[
        "\u3088\u3053\u3084\u307e",
        "\u30e8\u30b3\u30e4\u30de"
    ],
    "wof:name":"Yokoyama",
    "wof:placetype":"locality"
},
  "geometry": {"coordinates":[140.22746000000001,40.73109],"type":"Point"}
}