{
  "type": "Feature",
  "properties": {
    "gn:admin1_code":"12.0",
    "gn:admin2_code":"2129370.0",
    "gn:asciiname":"Oinosawa",
    "gn:country_code":"JP",
    "gn:dem":138,
    "gn:feature_class":"P",
    "gn:feature_code":"PPL",
    "gn:name":"\u014cinosawa",
    "gn:population":0,
    "gn:timezone":"Asia/Tokyo",
    "iso:country":"JP",
    "name:und_x_variant":[
        "\u014cinosawa"
    ],
    "wof:name":"Oinosawa",
    "wof:placetype":"locality"
},
  "geometry": {"coordinates":[143.90000000000001,42.95],"type":"Point"}
}