{
  "type": "Feature",
  "properties": {
    "gn:admin1_code":"09",
    "gn:admin2_code":"1860326.0",
    "gn:admin3_code":"21506.0",
    "gn:asciiname":"Naka-shinden",
    "gn:country_code":"JP",
    "gn:dem":662,
    "gn:feature_class":"P",
    "gn:feature_code":"PPL",
    "gn:name":"Naka-shinden",
    "gn:population":0,
    "gn:timezone":"Asia/Tokyo",
    "iso:country":"JP",
    "wof:name":"Naka-shinden",
    "wof:placetype":"locality"
},
  "geometry": {"coordinates":[137.36667,35.58333],"type":"Point"}
}