{
  "type": "Feature",
  "properties": {
    "gn:admin1_code":"21.0",
    "gn:admin2_code":"1864975.0",
    "gn:admin3_code":"43432.0",
    "gn:asciiname":"Kawahara",
    "gn:country_code":"JP",
    "gn:dem":286,
    "gn:feature_class":"P",
    "gn:feature_code":"PPL",
    "gn:name":"Kawahara",
    "gn:population":0,
    "gn:timezone":"Asia/Tokyo",
    "iso:country":"JP",
    "name:jpn_x_preferred":[
        "\u6cb3\u539f"
    ],
    "name:jpn_x_variant":[
        "\u304b\u308f\u306f\u3089",
        "\u30ab\u30ef\u30cf\u30e9"
    ],
    "wof:name":"Kawahara",
    "wof:placetype":"locality"
},
  "geometry": {"coordinates":[130.89747,32.80667],"type":"Point"}
}