{
  "type": "Feature",
  "properties": {
    "gn:admin1_code":"7.0",
    "gn:admin2_code":"7406950.0",
    "gn:admin3_code":"40625.0",
    "gn:asciiname":"Hirazuru",
    "gn:country_code":"JP",
    "gn:dem":448,
    "gn:feature_class":"P",
    "gn:feature_code":"PPLL",
    "gn:name":"Hirazuru",
    "gn:population":0,
    "gn:timezone":"Asia/Tokyo",
    "iso:country":"JP",
    "name:jpn_x_preferred":[
        "\u5e73\u9db4"
    ],
    "wof:name":"Hirazuru",
    "wof:placetype":"locality"
},
  "geometry": {"coordinates":[130.94803999999999,33.52959],"type":"Point"}
}