{
  "type": "Feature",
  "properties": {
    "gn:admin1_code":"34.0",
    "gn:admin2_code":"1849187.0",
    "gn:admin3_code":"11104.0",
    "gn:asciiname":"Miyagato",
    "gn:country_code":"JP",
    "gn:dem":12,
    "gn:feature_class":"P",
    "gn:feature_code":"PPL",
    "gn:name":"Miyagat\u014d",
    "gn:population":0,
    "gn:timezone":"Asia/Tokyo",
    "iso:country":"JP",
    "name:jpn_x_preferred":[
        "\u5bae\u30f6\u8c37\u5854"
    ],
    "name:jpn_x_variant":[
        "\u307f\u3084\u304c\u3068\u3046",
        "\u30df\u30e4\u30ac\u30c8\u30a6"
    ],
    "name:und_x_variant":[
        "Miyagat\u014d"
    ],
    "wof:name":"Miyagato",
    "wof:placetype":"locality"
},
  "geometry": {"coordinates":[139.67583999999999,35.94260999999999],"type":"Point"}
}