{
  "type": "Feature",
  "properties": {
    "gn:admin1_code":"3.0",
    "gn:admin2_code":"2130225.0",
    "gn:asciiname":"Fukuoka",
    "gn:country_code":"JP",
    "gn:dem":19,
    "gn:feature_class":"P",
    "gn:feature_code":"PPL",
    "gn:name":"Fukuoka",
    "gn:population":0,
    "gn:timezone":"Asia/Tokyo",
    "iso:country":"JP",
    "name:jpn_x_preferred":[
        "\u798f\u5ca1"
    ],
    "name:jpn_x_variant":[
        "\u3075\u304f\u304a\u304b",
        "\u30d5\u30af\u30aa\u30ab"
    ],
    "wof:name":"Fukuoka",
    "wof:placetype":"locality"
},
  "geometry": {"coordinates":[140.49498,40.797],"type":"Point"}
}