{
  "type": "Feature",
  "properties": {
    "gn:admin1_code":"3.0",
    "gn:admin2_code":"2128302.0",
    "gn:admin3_code":"2441.0",
    "gn:asciiname":"Konakajima",
    "gn:country_code":"JP",
    "gn:dem":63,
    "gn:feature_class":"P",
    "gn:feature_code":"PPL",
    "gn:name":"Konakajima",
    "gn:population":0,
    "gn:timezone":"Asia/Tokyo",
    "iso:country":"JP",
    "name:jpn_x_preferred":[
        "\u5c0f\u4e2d\u5cf6"
    ],
    "name:jpn_x_variant":[
        "\u3053\u306a\u304b\u3058\u307e",
        "\u30b3\u30ca\u30ab\u30b8\u30de"
    ],
    "wof:name":"Konakajima",
    "wof:placetype":"locality"
},
  "geometry": {"coordinates":[141.28957,40.36572],"type":"Point"}
}