{
  "type": "Feature",
  "properties": {
    "gn:admin1_code":"2.0",
    "gn:admin2_code":"2128864.0",
    "gn:asciiname":"Ushikubito",
    "gn:country_code":"JP",
    "gn:dem":28,
    "gn:feature_class":"P",
    "gn:feature_code":"PPLL",
    "gn:name":"Ushikubit\u014d",
    "gn:population":0,
    "gn:timezone":"Asia/Tokyo",
    "iso:country":"JP",
    "name:jpn_x_preferred":[
        "\u4e11\u9996\u982d"
    ],
    "name:und_x_variant":[
        "Ushikubit\u014d"
    ],
    "wof:name":"Ushikubito",
    "wof:placetype":"locality"
},
  "geometry": {"coordinates":[140.08445,40.23972],"type":"Point"}
}