{
  "type": "Feature",
  "properties": {
    "gn:admin1_code":"11",
    "gn:admin2_code":"8740425.0",
    "gn:asciiname":"Ogakicho-okimi",
    "gn:country_code":"JP",
    "gn:dem":40,
    "gn:feature_class":"P",
    "gn:feature_code":"PPL",
    "gn:name":"\u014cgakich\u014d-\u014dkimi",
    "gn:population":0,
    "gn:timezone":"Asia/Tokyo",
    "iso:country":"JP",
    "name:jpn_x_preferred":[
        "\u5927\u67ff\u753a\u5927\u541b"
    ],
    "name:und_x_variant":[
        "Ogimi",
        "\u014ckimi",
        "\u014cgakich\u014d-\u014dkimi"
    ],
    "wof:name":"Ogakicho-okimi",
    "wof:placetype":"locality"
},
  "geometry": {"coordinates":[132.47796,34.16669],"type":"Point"}
}