{
  "type": "Feature",
  "properties": {
    "gn:admin1_code":"29.0",
    "gn:admin2_code":"1853313.0",
    "gn:asciiname":"Etsutsumi",
    "gn:country_code":"JP",
    "gn:dem":43,
    "gn:feature_class":"P",
    "gn:feature_code":"PPL",
    "gn:name":"Etsutsumi",
    "gn:population":0,
    "gn:timezone":"Asia/Tokyo",
    "iso:country":"JP",
    "name:jpn_x_preferred":[
        "\u6c5f\u7a4d"
    ],
    "wof:name":"Etsutsumi",
    "wof:placetype":"locality"
},
  "geometry": {"coordinates":[138.22324,37.83439],"type":"Point"}
}