{
  "type": "Feature",
  "properties": {
    "gn:admin1_code":"13.0",
    "gn:admin2_code":"7370821.0",
    "gn:asciiname":"Kurodani",
    "gn:country_code":"JP",
    "gn:dem":93,
    "gn:feature_class":"P",
    "gn:feature_code":"PPL",
    "gn:name":"Kurodani",
    "gn:population":0,
    "gn:timezone":"Asia/Tokyo",
    "iso:country":"JP",
    "name:jpn_x_preferred":[
        "\u9ed2\u8c37"
    ],
    "wof:name":"Kurodani",
    "wof:placetype":"locality"
},
  "geometry": {"coordinates":[135.07284999999999,34.91867],"type":"Point"}
}