{
  "type": "Feature",
  "properties": {
    "gn:admin1_code":"21.0",
    "gn:admin2_code":"7412706.0",
    "gn:admin3_code":"43444.0",
    "gn:asciiname":"Gotan",
    "gn:country_code":"JP",
    "gn:dem":13,
    "gn:feature_class":"P",
    "gn:feature_code":"PPLL",
    "gn:name":"Gotan",
    "gn:population":0,
    "gn:timezone":"Asia/Tokyo",
    "iso:country":"JP",
    "name:jpn_x_preferred":[
        "\u4e94\u53cd"
    ],
    "name:jpn_x_variant":[
        "\u3054\u305f\u3093",
        "\u30b4\u30bf\u30f3"
    ],
    "wof:name":"Gotan",
    "wof:placetype":"locality"
},
  "geometry": {"coordinates":[130.77227999999999,32.71588],"type":"Point"}
}