{
  "type": "Feature",
  "properties": {
    "gn:admin1_code":"4.0",
    "gn:admin2_code":"1849185.0",
    "gn:asciiname":"Nekozane",
    "gn:country_code":"JP",
    "gn:dem":4,
    "gn:feature_class":"P",
    "gn:feature_code":"PPL",
    "gn:name":"Nekozane",
    "gn:population":0,
    "gn:timezone":"Asia/Tokyo",
    "iso:country":"JP",
    "name:jpn_x_preferred":[
        "\u732b\u5b9f"
    ],
    "wof:name":"Nekozane",
    "wof:placetype":"locality"
},
  "geometry": {"coordinates":[139.89919,35.66035],"type":"Point"}
}