{
  "type": "Feature",
  "properties": {
    "gn:admin1_code":"7.0",
    "gn:admin2_code":"7407413.0",
    "gn:asciiname":"Tadewara",
    "gn:country_code":"JP",
    "gn:dem":128,
    "gn:feature_class":"P",
    "gn:feature_code":"PPLL",
    "gn:name":"Tadewara",
    "gn:population":0,
    "gn:timezone":"Asia/Tokyo",
    "iso:country":"JP",
    "name:jpn_x_preferred":[
        "\u7530\u51fa\u539f"
    ],
    "wof:name":"Tadewara",
    "wof:placetype":"locality"
},
  "geometry": {"coordinates":[130.78253999999998,33.51206],"type":"Point"}
}