{
  "type": "Feature",
  "properties": {
    "gn:admin1_code":"16.0",
    "gn:admin2_code":"2112822.0",
    "gn:asciiname":"Gasho",
    "gn:country_code":"JP",
    "gn:dem":77,
    "gn:feature_class":"P",
    "gn:feature_code":"PPL",
    "gn:name":"Gash\u014d",
    "gn:population":0,
    "gn:timezone":"Asia/Tokyo",
    "iso:country":"JP",
    "name:jpn_x_preferred":[
        "\u6211\u751f"
    ],
    "name:jpn_x_variant":[
        "\u304c\u3057\u3087\u3046",
        "\u30ac\u30b7\u30e7\u30a6"
    ],
    "name:und_x_variant":[
        "Gash\u014d"
    ],
    "wof:name":"Gasho",
    "wof:placetype":"locality"
},
  "geometry": {"coordinates":[141.14851999999999,39.41296],"type":"Point"}
}