{
  "type": "Feature",
  "properties": {
    "gn:admin1_code":"19.0",
    "gn:admin2_code":"1847999.0",
    "gn:asciiname":"Myo'o",
    "gn:country_code":"JP",
    "gn:dem":62,
    "gn:feature_class":"P",
    "gn:feature_code":"PPL",
    "gn:name":"My\u014d\u2019\u014d",
    "gn:population":0,
    "gn:timezone":"Asia/Tokyo",
    "iso:country":"JP",
    "name:jpn_x_preferred":[
        "\u660e\u738b"
    ],
    "name:und_x_variant":[
        "My\u014d\u2019\u014d"
    ],
    "wof:name":"Myo'o",
    "wof:placetype":"locality"
},
  "geometry": {"coordinates":[139.40170000000001,35.49024],"type":"Point"}
}