{
  "type": "Feature",
  "properties": {
    "gn:admin1_code":"25.0",
    "gn:admin2_code":"1864313.0",
    "gn:asciiname":"Kakinokibaru",
    "gn:country_code":"JP",
    "gn:dem":353,
    "gn:feature_class":"P",
    "gn:feature_code":"PPLL",
    "gn:name":"Kakinokibaru",
    "gn:population":0,
    "gn:timezone":"Asia/Tokyo",
    "iso:country":"JP",
    "name:jpn_x_preferred":[
        "\u67ff\u6728\u539f"
    ],
    "name:jpn_x_variant":[
        "\u304b\u304d\u306e\u304d\u3070\u308b",
        "\u30ab\u30ad\u30ce\u30ad\u30d0\u30eb"
    ],
    "wof:name":"Kakinokibaru",
    "wof:placetype":"locality"
},
  "geometry": {"coordinates":[130.90017,32.06219],"type":"Point"}
}