{
  "type": "Feature",
  "properties": {
    "gn:admin1_code":"3.0",
    "gn:admin2_code":"7439929.0",
    "gn:admin3_code":"2343.0",
    "gn:asciiname":"Tashiro",
    "gn:country_code":"JP",
    "gn:dem":144,
    "gn:feature_class":"P",
    "gn:feature_code":"PPL",
    "gn:name":"Tashiro",
    "gn:population":0,
    "gn:timezone":"Asia/Tokyo",
    "iso:country":"JP",
    "name:deu_x_preferred":[
        "Tashiro"
    ],
    "name:ita_x_preferred":[
        "Tashiro"
    ],
    "name:jpn_x_preferred":[
        "\u7530\u4ee3"
    ],
    "name:jpn_x_variant":[
        "\u305f\u3057\u308d",
        "\u30bf\u30b7\u30ed"
    ],
    "name:kor_x_preferred":[
        "\ub2e4\uc2dc\ub85c"
    ],
    "name:rus_x_preferred":[
        "\u0422\u0430\u0441\u0438\u0440\u043e"
    ],
    "wof:name":"Tashiro",
    "wof:placetype":"locality"
},
  "geometry": {"coordinates":[140.29856999999998,40.57147],"type":"Point"}
}