{
  "type": "Feature",
  "properties": {
    "gn:admin1_code":"25.0",
    "gn:admin2_code":"1864313.0",
    "gn:asciiname":"Okamoto",
    "gn:country_code":"JP",
    "gn:dem":277,
    "gn:feature_class":"P",
    "gn:feature_code":"PPLL",
    "gn:name":"Okamoto",
    "gn:population":0,
    "gn:timezone":"Asia/Tokyo",
    "iso:country":"JP",
    "name:jpn_x_preferred":[
        "\u5ca1\u5143"
    ],
    "name:jpn_x_variant":[
        "\u304a\u304b\u3082\u3068",
        "\u30aa\u30ab\u30e2\u30c8"
    ],
    "wof:name":"Okamoto",
    "wof:placetype":"locality"
},
  "geometry": {"coordinates":[130.78876,32.01746],"type":"Point"}
}