{
  "type": "Feature",
  "properties": {
    "gn:admin1_code":"29.0",
    "gn:admin2_code":"1862804.0",
    "gn:admin3_code":"15385.0",
    "gn:asciiname":"Kuroiwa",
    "gn:country_code":"JP",
    "gn:dem":64,
    "gn:feature_class":"P",
    "gn:feature_code":"PPL",
    "gn:name":"Kuroiwa",
    "gn:population":0,
    "gn:timezone":"Asia/Tokyo",
    "iso:country":"JP",
    "name:jpn_x_preferred":[
        "\u9ed2\u5ca9"
    ],
    "wof:name":"Kuroiwa",
    "wof:placetype":"locality"
},
  "geometry": {"coordinates":[139.38130000000001,37.69391],"type":"Point"}
}