{
  "type": "Feature",
  "properties": {
    "gn:admin1_code":"3.0",
    "gn:admin2_code":"2127674.0",
    "gn:asciiname":"Ofudo",
    "gn:country_code":"JP",
    "gn:dem":94,
    "gn:feature_class":"P",
    "gn:feature_code":"PPL",
    "gn:name":"\u014cfud\u014d",
    "gn:population":0,
    "gn:timezone":"Asia/Tokyo",
    "iso:country":"JP",
    "name:jpn_x_preferred":[
        "\u5927\u4e0d\u52d5"
    ],
    "name:jpn_x_variant":[
        "\u304a\u304a\u3075\u3069\u3046",
        "\u30aa\u30aa\u30d5\u30c9\u30a6"
    ],
    "name:und_x_variant":[
        "\u014cfud\u014d"
    ],
    "wof:name":"Ofudo",
    "wof:placetype":"locality"
},
  "geometry": {"coordinates":[141.19496000000001,40.54911],"type":"Point"}
}