{
  "type": "Feature",
  "properties": {
    "gn:admin1_code":"21.0",
    "gn:admin2_code":"7413150.0",
    "gn:asciiname":"Tsubai",
    "gn:country_code":"JP",
    "gn:dem":38,
    "gn:feature_class":"P",
    "gn:feature_code":"PPL",
    "gn:name":"Tsubai",
    "gn:population":0,
    "gn:timezone":"Asia/Tokyo",
    "iso:country":"JP",
    "name:jpn_x_preferred":[
        "\u693f\u4e95"
    ],
    "name:jpn_x_variant":[
        "\u3064\u3070\u3044",
        "\u30c4\u30d0\u30a4"
    ],
    "wof:name":"Tsubai",
    "wof:placetype":"locality"
},
  "geometry": {"coordinates":[130.63845000000001,33.01584],"type":"Point"}
}