{
  "type": "Feature",
  "properties": {
    "gn:admin1_code":"27.0",
    "gn:admin2_code":"1862734.0",
    "gn:admin3_code":"42323.0",
    "gn:asciiname":"Nigorifuchi",
    "gn:country_code":"JP",
    "gn:dem":57,
    "gn:feature_class":"P",
    "gn:feature_code":"PPL",
    "gn:name":"Nigorifuchi",
    "gn:population":0,
    "gn:timezone":"Asia/Tokyo",
    "iso:country":"JP",
    "name:jpn_x_preferred":[
        "\u6fc1\u6df5"
    ],
    "wof:name":"Nigorifuchi",
    "wof:placetype":"locality"
},
  "geometry": {"coordinates":[129.88241000000002,33.13706],"type":"Point"}
}