{
  "type": "Feature",
  "properties": {
    "gn:admin1_code":"4.0",
    "gn:admin2_code":"2112330.0",
    "gn:asciiname":"Dainoyama",
    "gn:country_code":"JP",
    "gn:dem":22,
    "gn:feature_class":"P",
    "gn:feature_code":"PPLL",
    "gn:name":"Dainoyama",
    "gn:population":0,
    "gn:timezone":"Asia/Tokyo",
    "iso:country":"JP",
    "name:jpn_x_preferred":[
        "\u53f0\u30ce\u5c71"
    ],
    "wof:name":"Dainoyama",
    "wof:placetype":"locality"
},
  "geometry": {"coordinates":[139.97819999999999,35.89891],"type":"Point"}
}