{
  "type": "Feature",
  "properties": {
    "gn:admin1_code":"12.0",
    "gn:admin2_code":"7428088.0",
    "gn:admin3_code":"1637.0",
    "gn:asciiname":"Hotoku",
    "gn:country_code":"JP",
    "gn:dem":145,
    "gn:feature_class":"P",
    "gn:feature_code":"PPLL",
    "gn:name":"H\u014dtoku",
    "gn:population":0,
    "gn:timezone":"Asia/Tokyo",
    "iso:country":"JP",
    "name:jpn_x_preferred":[
        "\u5831\u5fb3"
    ],
    "name:und_x_variant":[
        "H\u014dtoku"
    ],
    "wof:name":"Hotoku",
    "wof:placetype":"locality"
},
  "geometry": {"coordinates":[142.97686999999999,42.90245],"type":"Point"}
}