{
  "type": "Feature",
  "properties": {
    "gn:admin1_code":"4.0",
    "gn:admin2_code":"1859468.0",
    "gn:asciiname":"Isobe",
    "gn:country_code":"JP",
    "gn:dem":39,
    "gn:feature_class":"P",
    "gn:feature_code":"PPLL",
    "gn:name":"Isobe",
    "gn:population":0,
    "gn:timezone":"Asia/Tokyo",
    "iso:country":"JP",
    "name:jpn_x_preferred":[
        "\u78ef\u8fba"
    ],
    "name:jpn_x_variant":[
        "\u3044\u305d\u3079",
        "\u30a4\u30bd\u30d9"
    ],
    "wof:name":"Isobe",
    "wof:placetype":"locality"
},
  "geometry": {"coordinates":[140.03843999999998,35.33252],"type":"Point"}
}