{
  "type": "Feature",
  "properties": {
    "gn:admin1_code":"21.0",
    "gn:admin2_code":"1858418.0",
    "gn:admin3_code":"43103.0",
    "gn:asciiname":"Rendaiji",
    "gn:country_code":"JP",
    "gn:dem":6,
    "gn:feature_class":"P",
    "gn:feature_code":"PPL",
    "gn:name":"Rendaiji",
    "gn:population":0,
    "gn:timezone":"Asia/Tokyo",
    "iso:country":"JP",
    "name:jpn_x_preferred":[
        "\u84ee\u53f0\u5bfa"
    ],
    "name:jpn_x_variant":[
        "\u308c\u3093\u3060\u3044\u3058",
        "\u30ec\u30f3\u30c0\u30a4\u30b8"
    ],
    "wof:name":"Rendaiji",
    "wof:placetype":"locality"
},
  "geometry": {"coordinates":[130.68722,32.77443],"type":"Point"}
}