{
  "type": "Feature",
  "properties": {
    "gn:admin1_code":"34.0",
    "gn:admin2_code":"1859316.0",
    "gn:admin3_code":"11465.0",
    "gn:asciiname":"Michiue",
    "gn:country_code":"JP",
    "gn:dem":6,
    "gn:feature_class":"P",
    "gn:feature_code":"PPLL",
    "gn:name":"Michiue",
    "gn:population":0,
    "gn:timezone":"Asia/Tokyo",
    "iso:country":"JP",
    "name:jpn_x_preferred":[
        "\u9053\u4e0a"
    ],
    "wof:name":"Michiue",
    "wof:placetype":"locality"
},
  "geometry": {"coordinates":[139.81948,35.95282],"type":"Point"}
}