{
  "type": "Feature",
  "properties": {
    "gn:country":"JP",
    "gn:fcode":"ADMD",
    "gn:population":0,
    "iso:country":"JP",
    "name:eng_x_preferred":[
        "Heguri"
    ],
    "name:eng_x_variant":[
        "Heguri-ch\u014d"
    ],
    "name:jpn_x_preferred":[
        "\u5e73\u7fa4\u753a"
    ],
    "name:und_x_variant":[
        "Heguri"
    ],
    "qs:name":"Heguri-ch\u014d",
    "qs:photos_9r":0,
    "qs:photos_sr":0,
    "qs:pop_sr":"0",
    "wof:name":"Heguri",
    "wof:placetype":"localadmin",
    "wof:population":0
},
  "geometry": {"coordinates":[135.70088999999999,34.62869],"type":"Point"}
}