{
  "type": "Feature",
  "properties": {
    "gn:admin1_code":"39",
    "gn:admin2_code":"1860803.0",
    "gn:admin3_code":"36388.0",
    "gn:asciiname":"Kono",
    "gn:cc2":"JP",
    "gn:country_code":"JP",
    "gn:dem":39,
    "gn:feature_class":"P",
    "gn:feature_code":"PPL",
    "gn:name":"K\u014dno",
    "gn:population":0,
    "gn:timezone":"Asia/Tokyo",
    "iso:country":"JP",
    "name:ceb_x_preferred":[
        "Kono"
    ],
    "name:deu_x_preferred":[
        "Kono"
    ],
    "name:eus_x_preferred":[
        "Kono"
    ],
    "name:fra_x_preferred":[
        "Kono"
    ],
    "name:ido_x_preferred":[
        "Kono"
    ],
    "name:rus_x_preferred":[
        "\u041a\u043e\u043d\u043e"
    ],
    "name:swe_x_preferred":[
        "Kono"
    ],
    "name:ukr_x_preferred":[
        "\u041a\u043e\u043d\u043e"
    ],
    "name:und_x_variant":[
        "Kamino",
        "K\u014dno"
    ],
    "wof:name":"Kono",
    "wof:placetype":"locality"
},
  "geometry": {"coordinates":[134.31666999999999,33.65],"type":"Point"}
}