{
  "type": "Feature",
  "properties": {
    "gn:admin1_code":"23.0",
    "gn:admin2_code":"1861901.0",
    "gn:asciiname":"Kawakami",
    "gn:country_code":"JP",
    "gn:dem":235,
    "gn:feature_class":"P",
    "gn:feature_code":"PPLL",
    "gn:name":"Kawakami",
    "gn:population":0,
    "gn:timezone":"Asia/Tokyo",
    "iso:country":"JP",
    "name:jpn_x_preferred":[
        "\u5ddd\u4e0a"
    ],
    "wof:name":"Kawakami",
    "wof:placetype":"locality"
},
  "geometry": {"coordinates":[136.18292,34.64791],"type":"Point"}
}