{
  "type": "Feature",
  "properties": {
    "gn:admin1_code":"7.0",
    "gn:admin2_code":"7407416.0",
    "gn:asciiname":"Honjo",
    "gn:country_code":"JP",
    "gn:dem":8,
    "gn:feature_class":"P",
    "gn:feature_code":"PPL",
    "gn:name":"Honj\u014d",
    "gn:population":0,
    "gn:timezone":"Asia/Tokyo",
    "iso:country":"JP",
    "name:ceb_x_preferred":[
        "Honjo"
    ],
    "name:deu_x_preferred":[
        "Honjo"
    ],
    "name:jpn_x_preferred":[
        "\u672c\u57ce"
    ],
    "name:por_x_preferred":[
        "Honjo"
    ],
    "name:rus_x_preferred":[
        "\u0425\u043e\u043d\u0434\u0437\u0451"
    ],
    "name:swe_x_preferred":[
        "Honjo"
    ],
    "name:und_x_variant":[
        "Honj\u014d"
    ],
    "wof:name":"Honjo",
    "wof:placetype":"locality"
},
  "geometry": {"coordinates":[130.67585,33.72873],"type":"Point"}
}