{
  "type": "Feature",
  "properties": {
    "gn:admin1_code":"37.0",
    "gn:admin2_code":"1851401.0",
    "gn:admin3_code":"22342.0",
    "gn:asciiname":"Motonagakubo",
    "gn:country_code":"JP",
    "gn:dem":208,
    "gn:feature_class":"P",
    "gn:feature_code":"PPL",
    "gn:name":"Motonagakubo",
    "gn:population":0,
    "gn:timezone":"Asia/Tokyo",
    "iso:country":"JP",
    "name:jpn_x_preferred":[
        "\u5143\u9577\u7aaa"
    ],
    "wof:name":"Motonagakubo",
    "wof:placetype":"locality"
},
  "geometry": {"coordinates":[138.86318,35.16616],"type":"Point"}
}