{
  "type": "Feature",
  "properties": {
    "gn:admin1_code":"4.0",
    "gn:admin2_code":"2112330.0",
    "gn:asciiname":"Shukunogo",
    "gn:country_code":"JP",
    "gn:dem":18,
    "gn:feature_class":"P",
    "gn:feature_code":"PPLL",
    "gn:name":"Shukunogo",
    "gn:population":0,
    "gn:timezone":"Asia/Tokyo",
    "iso:country":"JP",
    "name:jpn_x_preferred":[
        "\u5bbf\u30ce\u5f8c"
    ],
    "wof:name":"Shukunogo",
    "wof:placetype":"locality"
},
  "geometry": {"coordinates":[139.98544999999999,35.8924],"type":"Point"}
}