{
  "type": "Feature",
  "properties": {
    "gn:country":"JP",
    "gn:fcode":"PPL",
    "gn:population":19535,
    "iso:country":"JP",
    "name:ceb_x_preferred":[
        "Fukumitsu"
    ],
    "name:deu_x_preferred":[
        "Fukumitsu"
    ],
    "name:eng_x_preferred":[
        "Fukumitsu"
    ],
    "name:fra_x_preferred":[
        "Fukumitsu"
    ],
    "name:gle_x_preferred":[
        "Fukumitsu"
    ],
    "name:jpn_x_preferred":[
        "\u798f\u5149"
    ],
    "name:jpn_x_variant":[
        "\u798f\u5149\u753a"
    ],
    "name:kor_x_preferred":[
        "\ud6c4\ucfe0\ubbf8\uc4f0\uc815"
    ],
    "name:mlg_x_preferred":[
        "Fukumitsu"
    ],
    "name:nld_x_preferred":[
        "Fukumitsu"
    ],
    "name:und_x_variant":[
        "Fukumitsumachi"
    ],
    "qs:name":"Fukumitsu",
    "qs:photos_9r":0,
    "qs:photos_sr":0,
    "qs:pop_sr":"6",
    "wd:wordcount":26,
    "wof:name":"Fukumitsu",
    "wof:placetype":"locality",
    "wof:population":19535
},
  "geometry": {"coordinates":[136.86667,36.55],"type":"Point"}
}