{
  "type": "Feature",
  "properties": {
    "gn:country":"JP",
    "gn:fcode":"PPL",
    "gn:pop":19535,
    "iso:country":"JP",
    "name:dut_x_preferred":[
        "Fukumitsu"
    ],
    "name:eng_x_preferred":[
        "Fukumitsu"
    ],
    "name:fre_x_preferred":[
        "Fukumitsu"
    ],
    "name:ger_x_preferred":[
        "Fukumitsu"
    ],
    "name:jpn_x_preferred":[
        "\u798f\u5149"
    ],
    "name:unk_x_variant":[
        "Fukumitsumachi"
    ],
    "qs:name":"Fukumitsu",
    "qs:photos_9r":0,
    "qs:photos_sr":0,
    "qs:pop_sr":"6",
    "wd:wordcount":26,
    "wof:name":"Fukumitsu",
    "wof:placetype":"locality",
    "wof:population":19535
},
  "geometry": {"coordinates":[136.86667,36.55],"type":"Point"}
}