{
  "type": "Feature",
  "properties": {
    "gn:admin1_code":"4.0",
    "gn:admin2_code":"7465521.0",
    "gn:asciiname":"Ogami",
    "gn:country_code":"JP",
    "gn:dem":75,
    "gn:feature_class":"P",
    "gn:feature_code":"PPLL",
    "gn:name":"\u014cgami",
    "gn:population":0,
    "gn:timezone":"Asia/Tokyo",
    "iso:country":"JP",
    "name:jpn_x_preferred":[
        "\u5927\u4e0a"
    ],
    "name:jpn_x_variant":[
        "\u304a\u304a\u304c\u307f",
        "\u30aa\u30aa\u30ac\u30df"
    ],
    "name:und_x_variant":[
        "\u014cgami"
    ],
    "wof:name":"Ogami",
    "wof:placetype":"locality"
},
  "geometry": {"coordinates":[139.86723999999998,35.04351],"type":"Point"}
}