{
  "type": "Feature",
  "properties": {
    "iso:country":"JP",
    "name:eng_x_preferred":[
        "Shirakabe 1 Chome"
    ],
    "name:eng_x_variant":[
        "Shirakabe 1 Choume",
        "Shirakabe 1 Chome"
    ],
    "name:jpn_x_preferred":[
        "\uff11\u4e01\u76ee"
    ],
    "name:jpn_x_variant":[
        "\u3057\u3089\u304b\u3079 \uff11\u3061\u3087\u3046\u3081",
        "\u767d\u58c1 \uff11\u4e01\u76ee",
        "\uff11\u3061\u3087\u3046\u3081"
    ],
    "qs:gn_local":0,
    "qs:local_max":3194,
    "qs:local_sum":30209,
    "qs:localhoods":92,
    "qs:name":"\uff11\u4e01\u76ee",
    "qs:name_adm0":"\u65e5\u672c",
    "qs:name_adm1":"\u611b\u77e5\u770c",
    "qs:name_adm2":"\u6771\u533a",
    "qs:name_en":"Shirakabe 1 Chome",
    "qs:name_lau":"\u767d\u58c1",
    "qs:name_local":"\u540d\u53e4\u5c4b\u5e02",
    "qs:photo_max":36,
    "qs:photo_sum":59,
    "qs:placetype":"Suburb",
    "qs:quad_count":5,
    "qs:woe_adm0":23424856,
    "qs:woe_adm1":2345851,
    "qs:woe_adm2":15015552,
    "qs:woe_lau":28439030,
    "qs:woe_local":1117817,
    "qs:woe_ver":"7.10.0",
    "wof:lang":[
        "jpn"
    ],
    "wof:name":"\uff11\u4e01\u76ee",
    "wof:placetype":"neighbourhood"
},
  "geometry": {"coordinates":[136.91235800000001,35.182428],"type":"Point"}
}