{
  "type": "Feature",
  "properties": {
    "gn:admin1_code":"24.0",
    "gn:admin2_code":"2112261.0",
    "gn:asciiname":"Kunoki",
    "gn:country_code":"JP",
    "gn:dem":128,
    "gn:feature_class":"P",
    "gn:feature_code":"PPL",
    "gn:name":"Kunoki",
    "gn:population":0,
    "gn:timezone":"Asia/Tokyo",
    "iso:country":"JP",
    "name:jpn_x_preferred":[
        "\u4e5d\u6728"
    ],
    "name:jpn_x_variant":[
        "\u304f\u306e\u304d",
        "\u30af\u30ce\u30ad"
    ],
    "wof:name":"Kunoki",
    "wof:placetype":"locality"
},
  "geometry": {"coordinates":[141.51264,38.92008],"type":"Point"}
}