{
  "type": "Feature",
  "properties": {
    "gn:admin1_code":"21.0",
    "gn:admin2_code":"7412705.0",
    "gn:admin3_code":"43484.0",
    "gn:asciiname":"Nagata",
    "gn:country_code":"JP",
    "gn:dem":27,
    "gn:feature_class":"P",
    "gn:feature_code":"PPLL",
    "gn:name":"Nagata",
    "gn:population":0,
    "gn:timezone":"Asia/Tokyo",
    "iso:country":"JP",
    "name:jpn_x_preferred":[
        "\u9577\u7530"
    ],
    "name:jpn_x_variant":[
        "\u306a\u304c\u305f",
        "\u30ca\u30ac\u30bf"
    ],
    "name:kor_x_preferred":[
        "\ub098\uac00\ud0c0"
    ],
    "wof:name":"Nagata",
    "wof:placetype":"locality"
},
  "geometry": {"coordinates":[130.44801000000001,32.26903],"type":"Point"}
}