{
  "type": "Feature",
  "properties": {
    "gn:admin1_code":"31",
    "gn:admin2_code":"1858309.0",
    "gn:asciiname":"Kojima-ajino",
    "gn:country_code":"JP",
    "gn:dem":5,
    "gn:feature_class":"P",
    "gn:feature_code":"PPL",
    "gn:name":"Kojima-ajino",
    "gn:population":0,
    "gn:timezone":"Asia/Tokyo",
    "iso:country":"JP",
    "name:jpn_x_preferred":[
        "\u5150\u5cf6\u5473\u91ce"
    ],
    "name:und_x_variant":[
        "Azino",
        "Adino",
        "Kojima-Ajino",
        "Ajino",
        "Kojima-ajino"
    ],
    "wof:name":"Kojima-ajino",
    "wof:placetype":"locality"
},
  "geometry": {"coordinates":[133.80000000000001,34.46667],"type":"Point"}
}