{
  "type": "Feature",
  "properties": {
    "gn:admin1_code":"34.0",
    "gn:admin2_code":"1854369.0",
    "gn:asciiname":"Kashiwabara",
    "gn:country_code":"JP",
    "gn:dem":22,
    "gn:feature_class":"P",
    "gn:feature_code":"PPLL",
    "gn:name":"Kashiwabara",
    "gn:population":0,
    "gn:timezone":"Asia/Tokyo",
    "iso:country":"JP",
    "name:jpn_x_preferred":[
        "\u67cf\u539f"
    ],
    "wof:name":"Kashiwabara",
    "wof:placetype":"locality"
},
  "geometry": {"coordinates":[139.52281000000002,35.98611],"type":"Point"}
}