{
  "type": "Feature",
  "properties": {
    "gn:admin1_code":"2.0",
    "gn:admin2_code":"2113122.0",
    "gn:asciiname":"Iijima-matsune-higashicho",
    "gn:country_code":"JP",
    "gn:dem":12,
    "gn:feature_class":"P",
    "gn:feature_code":"PPL",
    "gn:name":"Iijima-matsune-higashich\u014d",
    "gn:population":0,
    "gn:timezone":"Asia/Tokyo",
    "iso:country":"JP",
    "name:jpn_x_preferred":[
        "\u98ef\u5cf6\u677e\u6839\u6771\u753a"
    ],
    "name:jpn_x_variant":[
        "\u3044\u3044\u3058\u307e\u307e\u3064\u306d\u3072\u304c\u3057\u3061\u3087\u3046",
        "\u30a4\u30a4\u30b8\u30de\u30de\u30c4\u30cd\u30d2\u30ac\u30b7\u30c1\u30e7\u30a6"
    ],
    "name:und_x_variant":[
        "Iijima-matsune-higashich\u014d"
    ],
    "wof:name":"Iijima-matsune-higashicho",
    "wof:placetype":"locality"
},
  "geometry": {"coordinates":[140.07308,39.77226],"type":"Point"}
}