{
  "type": "Feature",
  "properties": {
    "gn:admin1_code":"43.0",
    "gn:admin2_code":"1865121.0",
    "gn:asciiname":"Tsujido",
    "gn:country_code":"JP",
    "gn:dem":5,
    "gn:feature_class":"P",
    "gn:feature_code":"PPL",
    "gn:name":"Tsujid\u014d",
    "gn:population":0,
    "gn:timezone":"Asia/Tokyo",
    "iso:country":"JP",
    "name:jpn_x_preferred":[
        "\u8fbb\u5802"
    ],
    "name:und_x_variant":[
        "Tsujid\u014d"
    ],
    "wof:name":"Tsujido",
    "wof:placetype":"locality"
},
  "geometry": {"coordinates":[135.14574999999999,34.07576],"type":"Point"}
}