{
  "type": "Feature",
  "properties": {
    "gn:admin1_code":"35.0",
    "gn:admin2_code":"6822197.0",
    "gn:asciiname":"Higashiomi",
    "gn:country_code":"JP",
    "gn:dem":172,
    "gn:feature_class":"P",
    "gn:feature_code":"PPLA2",
    "gn:name":"Higashi\u014dmi",
    "gn:population":0,
    "gn:timezone":"Asia/Tokyo",
    "iso:country":"JP",
    "name:jpn_x_preferred":[
        "\u6771\u8fd1\u6c5f"
    ],
    "wof:name":"Higashiomi",
    "wof:placetype":"locality"
},
  "geometry": {"coordinates":[136.26273999999998,35.1039],"type":"Point"}
}