{
  "type": "Feature",
  "properties": {
    "gn:admin1_code":"27",
    "gn:admin2_code":"7418808.0",
    "gn:asciiname":"Motogoe",
    "gn:cc2":"JP",
    "gn:country_code":"JP",
    "gn:dem":103,
    "gn:feature_class":"P",
    "gn:feature_code":"PPL",
    "gn:name":"Motogoe",
    "gn:population":0,
    "gn:timezone":"Asia/Tokyo",
    "iso:country":"JP",
    "name:und_x_variant":[
        "Motokoshi",
        "Motogoe"
    ],
    "wof:name":"Motogoe",
    "wof:placetype":"locality"
},
  "geometry": {"coordinates":[129.80000000000001,32.96667],"type":"Point"}
}