{
  "type": "Feature",
  "properties": {
    "iso:country":"JP",
    "name:eng_x_preferred":[
        "Mimomi 2 Chome"
    ],
    "name:eng_x_variant":[
        "Mimomi 2 Choume",
        "Mimomi 2 Chome"
    ],
    "name:jpn_x_preferred":[
        "\uff12\u4e01\u76ee"
    ],
    "name:jpn_x_variant":[
        "\u307f\u3082\u307f \uff12\u3061\u3087\u3046\u3081",
        "\u5b9f\u7c7e \uff12\u4e01\u76ee",
        "\uff12\u3061\u3087\u3046\u3081"
    ],
    "name:unk_x_variant":[
        "\uff12\u4e01\u76ee"
    ],
    "qs:gn_adm0_cc":"JP",
    "qs:gn_local":2111687,
    "qs:gn_nam_loc":"\u7fd2\u5fd7\u91ce\u5e02, \u5343\u8449\u770c, JP",
    "qs:gn_namadm1":"04",
    "qs:local_max":408,
    "qs:local_sum":996,
    "qs:localhoods":8,
    "qs:name":"\uff12\u4e01\u76ee",
    "qs:name_adm0":"\u65e5\u672c",
    "qs:name_adm1":"\u5343\u8449\u770c",
    "qs:name_en":"Mimomi 2 Chome",
    "qs:name_lau":"\u5b9f\u7c7e",
    "qs:name_local":"\u7fd2\u5fd7\u91ce\u5e02",
    "qs:photo_max":9,
    "qs:photo_sum":12,
    "qs:placetype":"Suburb",
    "qs:quad_count":2,
    "qs:woe_adm0":23424856,
    "qs:woe_adm1":2345854,
    "qs:woe_adm2":0,
    "qs:woe_lau":28411852,
    "qs:woe_local":1112678,
    "qs:woe_ver":"7.10.0",
    "wof:lang":[
        "jpn"
    ],
    "wof:name":"\uff12\u4e01\u76ee",
    "wof:placetype":"neighbourhood"
},
  "geometry": {"coordinates":[140.06744399999999,35.682955],"type":"Point"}
}