{
  "type": "Feature",
  "properties": {
    "gn:admin1_code":"16.0",
    "gn:admin2_code":"2111005.0",
    "gn:admin3_code":"3321.0",
    "gn:asciiname":"Nozoe",
    "gn:country_code":"JP",
    "gn:dem":140,
    "gn:feature_class":"P",
    "gn:feature_code":"PPL",
    "gn:name":"Nozoe",
    "gn:population":0,
    "gn:timezone":"Asia/Tokyo",
    "iso:country":"JP",
    "name:jpn_x_preferred":[
        "\u91ce\u6dfb"
    ],
    "name:jpn_x_variant":[
        "\u306e\u305e\u3048",
        "\u30ce\u30be\u30a8"
    ],
    "wof:name":"Nozoe",
    "wof:placetype":"locality"
},
  "geometry": {"coordinates":[141.10924,39.51014],"type":"Point"}
}