{
  "type": "Feature",
  "properties": {
    "gn:admin1_code":"16.0",
    "gn:admin2_code":"2112822.0",
    "gn:asciiname":"Kitamura",
    "gn:country_code":"JP",
    "gn:dem":119,
    "gn:feature_class":"P",
    "gn:feature_code":"PPL",
    "gn:name":"Kitamura",
    "gn:population":0,
    "gn:timezone":"Asia/Tokyo",
    "iso:country":"JP",
    "name:jpn_x_preferred":[
        "\u5317\u6751"
    ],
    "name:jpn_x_variant":[
        "\u304d\u305f\u3080\u3089",
        "\u30ad\u30bf\u30e0\u30e9"
    ],
    "name:rus_x_preferred":[
        "\u041a\u0438\u0442\u0430\u043c\u0443\u0440\u0430"
    ],
    "wof:name":"Kitamura",
    "wof:placetype":"locality"
},
  "geometry": {"coordinates":[141.07831999999999,39.41435],"type":"Point"}
}