{
  "type": "Feature",
  "properties": {
    "gn:admin1_code":"16.0",
    "gn:admin2_code":"2128940.0",
    "gn:asciiname":"Yuda",
    "gn:country_code":"JP",
    "gn:dem":108,
    "gn:feature_class":"P",
    "gn:feature_code":"PPL",
    "gn:name":"Yuda",
    "gn:population":0,
    "gn:timezone":"Asia/Tokyo",
    "iso:country":"JP",
    "name:jpn_x_preferred":[
        "\u6e6f\u7530"
    ],
    "name:jpn_x_variant":[
        "\u3086\u3060",
        "\u30e6\u30c0"
    ],
    "wof:name":"Yuda",
    "wof:placetype":"locality"
},
  "geometry": {"coordinates":[141.32279,40.32301],"type":"Point"}
}