{
  "type": "Feature",
  "properties": {
    "gn:admin1_code":"21.0",
    "gn:admin2_code":"1850743.0",
    "gn:asciiname":"Kawasaki",
    "gn:country_code":"JP",
    "gn:dem":6,
    "gn:feature_class":"P",
    "gn:feature_code":"PPLL",
    "gn:name":"Kawasaki",
    "gn:population":0,
    "gn:timezone":"Asia/Tokyo",
    "iso:country":"JP",
    "name:jpn_x_preferred":[
        "\u6cb3\u5d0e"
    ],
    "name:jpn_x_variant":[
        "\u304b\u308f\u3055\u304d",
        "\u30ab\u30ef\u30b5\u30ad"
    ],
    "wof:name":"Kawasaki",
    "wof:placetype":"locality"
},
  "geometry": {"coordinates":[130.57053999999999,32.93451],"type":"Point"}
}