{
  "type": "Feature",
  "properties": {
    "gn:admin1_code":"21.0",
    "gn:admin2_code":"7412705.0",
    "gn:admin3_code":"43482.0",
    "gn:asciiname":"Kojo",
    "gn:country_code":"JP",
    "gn:dem":7,
    "gn:feature_class":"P",
    "gn:feature_code":"PPLL",
    "gn:name":"Koj\u014d",
    "gn:population":0,
    "gn:timezone":"Asia/Tokyo",
    "iso:country":"JP",
    "name:jpn_x_preferred":[
        "\u53e4\u57ce"
    ],
    "name:und_x_variant":[
        "Koj\u014d"
    ],
    "wof:name":"Kojo",
    "wof:placetype":"locality"
},
  "geometry": {"coordinates":[130.51612,32.3628],"type":"Point"}
}