{
  "type": "Feature",
  "properties": {
    "gn:admin1_code":"22.0",
    "gn:admin2_code":"7412199.0",
    "gn:asciiname":"Kawaguchi-horinouchi",
    "gn:country_code":"JP",
    "gn:dem":15,
    "gn:feature_class":"P",
    "gn:feature_code":"PPL",
    "gn:name":"Kawaguchi-horinouchi",
    "gn:population":0,
    "gn:timezone":"Asia/Tokyo",
    "iso:country":"JP",
    "name:jpn_x_preferred":[
        "\u5ddd\u53e3\u5800\u30ce\u5185"
    ],
    "wof:name":"Kawaguchi-horinouchi",
    "wof:placetype":"locality"
},
  "geometry": {"coordinates":[135.72194999999999,34.8778],"type":"Point"}
}