{
  "type": "Feature",
  "properties": {
    "gn:admin1_code":"7.0",
    "gn:admin2_code":"1859306.0",
    "gn:admin3_code":"40108.0",
    "gn:asciiname":"Hanaomachi",
    "gn:country_code":"JP",
    "gn:dem":131,
    "gn:feature_class":"P",
    "gn:feature_code":"PPL",
    "gn:name":"Hanaomachi",
    "gn:population":0,
    "gn:timezone":"Asia/Tokyo",
    "iso:country":"JP",
    "name:jpn_x_preferred":[
        "\u82b1\u5c3e\u753a"
    ],
    "wof:name":"Hanaomachi",
    "wof:placetype":"locality"
},
  "geometry": {"coordinates":[130.78946999999999,33.85359],"type":"Point"}
}