{
  "type": "Feature",
  "properties": {
    "gn:admin1_code":"25",
    "gn:admin2_code":"1858035.0",
    "gn:asciiname":"Sakida",
    "gn:cc2":"JP",
    "gn:country_code":"JP",
    "gn:dem":26,
    "gn:feature_class":"P",
    "gn:feature_code":"PPL",
    "gn:name":"Sakida",
    "gn:population":0,
    "gn:timezone":"Asia/Tokyo",
    "iso:country":"JP",
    "name:jpn_x_preferred":[
        "\u5d0e\u7530"
    ],
    "name:und_x_variant":[
        "Sakita",
        "Sakida"
    ],
    "wof:name":"Sakida",
    "wof:placetype":"locality"
},
  "geometry": {"coordinates":[131.24167,31.40833],"type":"Point"}
}