{
  "type": "Feature",
  "properties": {
    "gn:admin1_code":"4.0",
    "gn:admin2_code":"1861964.0",
    "gn:asciiname":"Nakakokubun",
    "gn:country_code":"JP",
    "gn:dem":27,
    "gn:feature_class":"P",
    "gn:feature_code":"PPL",
    "gn:name":"Nakakokubun",
    "gn:population":0,
    "gn:timezone":"Asia/Tokyo",
    "iso:country":"JP",
    "name:jpn_x_preferred":[
        "\u4e2d\u56fd\u5206"
    ],
    "wof:name":"Nakakokubun",
    "wof:placetype":"locality"
},
  "geometry": {"coordinates":[139.91261,35.75304000000001],"type":"Point"}
}