{
  "type": "Feature",
  "properties": {
    "gn:admin1_code":"16.0",
    "gn:admin2_code":"2129400.0",
    "gn:admin3_code":"3506.0",
    "gn:asciiname":"Sodekawa",
    "gn:country_code":"JP",
    "gn:dem":328,
    "gn:feature_class":"P",
    "gn:feature_code":"PPL",
    "gn:name":"Sodekawa",
    "gn:population":0,
    "gn:timezone":"Asia/Tokyo",
    "iso:country":"JP",
    "name:jpn_x_preferred":[
        "\u8896\u5ddd"
    ],
    "name:jpn_x_variant":[
        "\u305d\u3067\u304b\u308f",
        "\u30bd\u30c7\u30ab\u30ef"
    ],
    "wof:name":"Sodekawa",
    "wof:placetype":"locality"
},
  "geometry": {"coordinates":[141.40385000000001,40.22538],"type":"Point"}
}