{
  "type": "Feature",
  "properties": {
    "gn:admin1_code":"4.0",
    "gn:admin2_code":"2112663.0",
    "gn:asciiname":"Shiizu",
    "gn:country_code":"JP",
    "gn:dem":20,
    "gn:feature_class":"P",
    "gn:feature_code":"PPL",
    "gn:name":"Shiizu",
    "gn:population":0,
    "gn:timezone":"Asia/Tokyo",
    "iso:country":"JP",
    "name:jpn_x_preferred":[
        "\u690e\u6d25"
    ],
    "name:jpn_x_variant":[
        "\u3057\u3044\u3065",
        "\u30b7\u30a4\u30c5"
    ],
    "wof:name":"Shiizu",
    "wof:placetype":"locality"
},
  "geometry": {"coordinates":[140.03446,35.4692],"type":"Point"}
}