{
  "type": "Feature",
  "properties": {
    "gn:admin1_code":"18",
    "gn:admin2_code":"7383995.0",
    "gn:asciiname":"Sunatake",
    "gn:country_code":"JP",
    "gn:dem":71,
    "gn:feature_class":"P",
    "gn:feature_code":"PPL",
    "gn:name":"Sunatake",
    "gn:population":0,
    "gn:timezone":"Asia/Tokyo",
    "iso:country":"JP",
    "wof:name":"Sunatake",
    "wof:placetype":"locality"
},
  "geometry": {"coordinates":[130.19999999999999,31.83333],"type":"Point"}
}