{
  "type": "Feature",
  "properties": {
    "gn:admin1_code":"19.0",
    "gn:admin2_code":"1860670.0",
    "gn:asciiname":"Tsu",
    "gn:country_code":"JP",
    "gn:dem":10,
    "gn:feature_class":"P",
    "gn:feature_code":"PPL",
    "gn:name":"Tsu",
    "gn:population":0,
    "gn:timezone":"Asia/Tokyo",
    "iso:country":"JP",
    "name:ceb_x_preferred":[
        "Tsu"
    ],
    "name:hun_x_preferred":[
        "Tsu"
    ],
    "name:jpn_x_preferred":[
        "\u6d25"
    ],
    "name:jpn_x_variant":[
        "\u3064",
        "\u30c4"
    ],
    "name:mlg_x_preferred":[
        "Tsu"
    ],
    "name:nld_x_preferred":[
        "Tsu"
    ],
    "name:por_x_preferred":[
        "Tsu"
    ],
    "name:rus_x_preferred":[
        "\u0426\u0443"
    ],
    "name:spa_x_preferred":[
        "Tsu"
    ],
    "name:ukr_x_preferred":[
        "\u0426\u0443"
    ],
    "wof:name":"Tsu",
    "wof:placetype":"locality"
},
  "geometry": {"coordinates":[139.5027,35.31483],"type":"Point"}
}