{
  "type": "Feature",
  "properties": {
    "gn:admin1_code":"22.0",
    "gn:admin2_code":"1859202.0",
    "gn:asciiname":"Umedani",
    "gn:country_code":"JP",
    "gn:dem":81,
    "gn:feature_class":"P",
    "gn:feature_code":"PPL",
    "gn:name":"Umedani",
    "gn:population":0,
    "gn:timezone":"Asia/Tokyo",
    "iso:country":"JP",
    "name:jpn_x_preferred":[
        "\u6885\u8c37"
    ],
    "wof:name":"Umedani",
    "wof:placetype":"locality"
},
  "geometry": {"coordinates":[135.84483999999998,34.72320999999999],"type":"Point"}
}