{
  "type": "Feature",
  "properties": {
    "gn:admin1_code":"13",
    "gn:admin2_code":"1859161.0",
    "gn:admin3_code":"28110.0",
    "gn:asciiname":"Shimo-yamatedori",
    "gn:country_code":"JP",
    "gn:dem":23,
    "gn:feature_class":"P",
    "gn:feature_code":"PPL",
    "gn:name":"Shimo-yamated\u014dri",
    "gn:population":0,
    "gn:timezone":"Asia/Tokyo",
    "iso:country":"JP",
    "name:jpn_x_preferred":[
        "\u4e0b\u5c71\u624b\u901a"
    ],
    "name:und_x_variant":[
        "Shimo-yamated\u014dri"
    ],
    "wof:name":"Shimo-yamatedori",
    "wof:placetype":"locality"
},
  "geometry": {"coordinates":[135.18887000000001,34.6928],"type":"Point"}
}