{
  "type": "Feature",
  "properties": {
    "gn:admin1_code":"7.0",
    "gn:admin2_code":"1861834.0",
    "gn:asciiname":"Amagi",
    "gn:country_code":"JP",
    "gn:dem":27,
    "gn:feature_class":"P",
    "gn:feature_code":"PPLL",
    "gn:name":"Amagi",
    "gn:population":0,
    "gn:timezone":"Asia/Tokyo",
    "iso:country":"JP",
    "name:ces_x_preferred":[
        "Amagi"
    ],
    "name:deu_x_preferred":[
        "Amagi"
    ],
    "name:fra_x_preferred":[
        "Amagi"
    ],
    "name:ita_x_preferred":[
        "Amagi"
    ],
    "name:jpn_x_preferred":[
        "\u7518\u6728"
    ],
    "name:kor_x_preferred":[
        "\uc544\ub9c8\uae30"
    ],
    "name:mlg_x_preferred":[
        "Amagi"
    ],
    "name:pol_x_preferred":[
        "Amagi"
    ],
    "name:rus_x_preferred":[
        "\u0410\u043c\u0430\u0433\u0438"
    ],
    "name:spa_x_preferred":[
        "Amagi"
    ],
    "name:ukr_x_preferred":[
        "\u0410\u043c\u0430\u0491\u0456"
    ],
    "wof:name":"Amagi",
    "wof:placetype":"locality"
},
  "geometry": {"coordinates":[130.69089,33.65414000000001],"type":"Point"}
}