{
  "type": "Feature",
  "properties": {
    "gn:admin1_code":"7.0",
    "gn:admin2_code":"1861834.0",
    "gn:asciiname":"Amagi",
    "gn:country_code":"JP",
    "gn:dem":27,
    "gn:feature_class":"P",
    "gn:feature_code":"PPLL",
    "gn:name":"Amagi",
    "gn:population":0,
    "gn:timezone":"Asia/Tokyo",
    "iso:country":"JP",
    "name:jpn_x_preferred":[
        "\u7518\u6728"
    ],
    "wof:name":"Amagi",
    "wof:placetype":"locality"
},
  "geometry": {"coordinates":[130.69089,33.65414000000001],"type":"Point"}
}