{
  "type": "Feature",
  "properties": {
    "gn:admin1_code":"37.0",
    "gn:admin2_code":"1863526.0",
    "gn:asciiname":"Nakayasuba",
    "gn:country_code":"JP",
    "gn:dem":447,
    "gn:feature_class":"P",
    "gn:feature_code":"PPLL",
    "gn:name":"Nakayasuba",
    "gn:population":0,
    "gn:timezone":"Asia/Tokyo",
    "iso:country":"JP",
    "name:jpn_x_preferred":[
        "\u4e2d\u4f11\u5834"
    ],
    "wof:name":"Nakayasuba",
    "wof:placetype":"locality"
},
  "geometry": {"coordinates":[138.95858000000001,35.29881],"type":"Point"}
}