{
  "type": "Feature",
  "properties": {
    "gn:admin1_code":"21.0",
    "gn:admin2_code":"1850744.0",
    "gn:admin3_code":"43367.0",
    "gn:asciiname":"Tara",
    "gn:country_code":"JP",
    "gn:dem":85,
    "gn:feature_class":"P",
    "gn:feature_code":"PPLL",
    "gn:name":"Tara",
    "gn:population":0,
    "gn:timezone":"Asia/Tokyo",
    "iso:country":"JP",
    "name:jpn_x_preferred":[
        "\u7530\u826f"
    ],
    "name:jpn_x_variant":[
        "\u305f\u3089",
        "\u30bf\u30e9"
    ],
    "wof:name":"Tara",
    "wof:placetype":"locality"
},
  "geometry": {"coordinates":[130.53611999999998,33.00609],"type":"Point"}
}