{
  "type": "Feature",
  "properties": {
    "gn:admin1_code":"40.0",
    "gn:admin2_code":"1864529.0",
    "gn:asciiname":"Nishikanda",
    "gn:country_code":"JP",
    "gn:dem":16,
    "gn:feature_class":"P",
    "gn:feature_code":"PPL",
    "gn:name":"Nishikanda",
    "gn:population":0,
    "gn:timezone":"Asia/Tokyo",
    "iso:country":"JP",
    "name:jpn_x_preferred":[
        "\u897f\u795e\u7530"
    ],
    "wof:name":"Nishikanda",
    "wof:placetype":"locality"
},
  "geometry": {"coordinates":[139.75462999999999,35.69914],"type":"Point"}
}