{
  "type": "Feature",
  "properties": {
    "gn:admin1_code":"16.0",
    "gn:admin2_code":"2112223.0",
    "gn:asciiname":"Otake",
    "gn:country_code":"JP",
    "gn:dem":128,
    "gn:feature_class":"P",
    "gn:feature_code":"PPL",
    "gn:name":"\u014ctake",
    "gn:population":0,
    "gn:timezone":"Asia/Tokyo",
    "iso:country":"JP",
    "name:deu_x_preferred":[
        "\u014ctake"
    ],
    "name:fra_x_preferred":[
        "Otake"
    ],
    "name:jpn_x_preferred":[
        "\u5927\u7af9"
    ],
    "name:jpn_x_variant":[
        "\u304a\u304a\u305f\u3051",
        "\u30aa\u30aa\u30bf\u30b1"
    ],
    "name:und_x_variant":[
        "\u014ctake"
    ],
    "wof:name":"Otake",
    "wof:placetype":"locality"
},
  "geometry": {"coordinates":[141.1617,39.34726],"type":"Point"}
}