{
  "type": "Feature",
  "properties": {
    "iso:country":"JP",
    "label:eng_x_preferred_longname":[
        "Akune City"
    ],
    "label:eng_x_preferred_placetype":[
        "city"
    ],
    "name:eng_x_preferred":[
        "Akune"
    ],
    "name:eng_x_variant":[
        "Akune City"
    ],
    "name:jpn_x_preferred":[
        "\u963f\u4e45\u6839\u5e02"
    ],
    "qs:name":"\u963f\u4e45\u6839\u5e02",
    "qs:name_adm0":"\u65e5\u672c",
    "qs:name_adm1":"\u9e7f\u5150\u5cf6\u770c",
    "qs:photos":60,
    "qs:photos_1k":12,
    "qs:photos_9k":1,
    "qs:photos_9r":2,
    "qs:photos_all":67,
    "qs:photos_sr":2,
    "qs:placetype":"Town",
    "qs:pop_sr":"0",
    "wof:name":"Akune",
    "wof:placetype":"locality"
},
  "geometry": {"coordinates":[130.19070450000001,32.084052],"type":"Point"}
}