{
  "type": "Feature",
  "properties": {
    "gn:admin1_code":"7.0",
    "gn:admin2_code":"1851269.0",
    "gn:admin3_code":"40610.0",
    "gn:asciiname":"Kuzuhara",
    "gn:country_code":"JP",
    "gn:dem":74,
    "gn:feature_class":"P",
    "gn:feature_code":"PPLL",
    "gn:name":"Kuzuhara",
    "gn:population":0,
    "gn:timezone":"Asia/Tokyo",
    "iso:country":"JP",
    "name:jpn_x_preferred":[
        "\u845b\u539f"
    ],
    "wof:name":"Kuzuhara",
    "wof:placetype":"locality"
},
  "geometry": {"coordinates":[130.79714999999999,33.70153],"type":"Point"}
}