{
  "type": "Feature",
  "properties": {
    "gn:admin1_code":"19.0",
    "gn:admin2_code":"1863429.0",
    "gn:asciiname":"Yayoicho",
    "gn:country_code":"JP",
    "gn:dem":185,
    "gn:feature_class":"P",
    "gn:feature_code":"PPL",
    "gn:name":"Yayoich\u014d",
    "gn:population":0,
    "gn:timezone":"Asia/Tokyo",
    "iso:country":"JP",
    "name:jpn_x_preferred":[
        "\u5f25\u751f\u753a"
    ],
    "name:und_x_variant":[
        "Yayoich\u014d"
    ],
    "wof:name":"Yayoicho",
    "wof:placetype":"locality"
},
  "geometry": {"coordinates":[139.18098000000001,35.38225999999999],"type":"Point"}
}