{
  "type": "Feature",
  "properties": {
    "gn:admin1_code":"6.0",
    "gn:admin2_code":"1859762.0",
    "gn:asciiname":"Shikadanicho-nishiosowaguchi",
    "gn:country_code":"JP",
    "gn:dem":125,
    "gn:feature_class":"P",
    "gn:feature_code":"PPL",
    "gn:name":"Shikadanich\u014d-nishiosowaguchi",
    "gn:population":0,
    "gn:timezone":"Asia/Tokyo",
    "iso:country":"JP",
    "name:jpn_x_preferred":[
        "\u9e7f\u8c37\u753a\u897f\u9045\u7fbd\u53e3"
    ],
    "name:und_x_variant":[
        "Shikadanich\u014d-nishiosowaguchi"
    ],
    "wof:name":"Shikadanicho-nishiosowaguchi",
    "wof:placetype":"locality"
},
  "geometry": {"coordinates":[136.46746999999999,36.04813],"type":"Point"}
}