{
  "type": "Feature",
  "properties": {
    "gn:admin1_code":"21.0",
    "gn:admin2_code":"1865358.0",
    "gn:asciiname":"Kami-kashinomitsuru",
    "gn:country_code":"JP",
    "gn:dem":218,
    "gn:feature_class":"P",
    "gn:feature_code":"PPLL",
    "gn:name":"Kami-kashinomitsuru",
    "gn:population":0,
    "gn:timezone":"Asia/Tokyo",
    "iso:country":"JP",
    "name:jpn_x_preferred":[
        "\u4e0a\u6a2b\u306e\u5b9f\u9db4"
    ],
    "name:jpn_x_variant":[
        "\u304b\u307f\u304b\u3057\u306e\u307f\u3064\u308b",
        "\u30ab\u30df\u30ab\u30b7\u30ce\u30df\u30c4\u30eb"
    ],
    "wof:name":"Kami-kashinomitsuru",
    "wof:placetype":"locality"
},
  "geometry": {"coordinates":[130.11338999999998,32.41084],"type":"Point"}
}