{
  "type": "Feature",
  "properties": {
    "gn:admin1_code":"3.0",
    "gn:admin2_code":"2130654.0",
    "gn:asciiname":"Yaeda",
    "gn:country_code":"JP",
    "gn:dem":6,
    "gn:feature_class":"P",
    "gn:feature_code":"PPL",
    "gn:name":"Yaeda",
    "gn:population":0,
    "gn:timezone":"Asia/Tokyo",
    "iso:country":"JP",
    "name:jpn_x_preferred":[
        "\u516b\u91cd\u7530"
    ],
    "name:jpn_x_variant":[
        "\u3084\u3048\u3060",
        "\u30e4\u30a8\u30c0"
    ],
    "wof:name":"Yaeda",
    "wof:placetype":"locality"
},
  "geometry": {"coordinates":[140.79865000000001,40.83187],"type":"Point"}
}