{
  "type": "Feature",
  "properties": {
    "gn:admin1_code":"21.0",
    "gn:admin2_code":"1865358.0",
    "gn:asciiname":"Shidanohara",
    "gn:country_code":"JP",
    "gn:dem":22,
    "gn:feature_class":"P",
    "gn:feature_code":"PPLL",
    "gn:name":"Shidanohara",
    "gn:population":0,
    "gn:timezone":"Asia/Tokyo",
    "iso:country":"JP",
    "name:jpn_x_preferred":[
        "\u5fd7\u7530\u30ce\u539f"
    ],
    "name:jpn_x_variant":[
        "\u3057\u3060\u306e\u306f\u3089",
        "\u30b7\u30c0\u30ce\u30cf\u30e9"
    ],
    "wof:name":"Shidanohara",
    "wof:placetype":"locality"
},
  "geometry": {"coordinates":[130.1516,32.51159000000001],"type":"Point"}
}