{
  "type": "Feature",
  "properties": {
    "gn:admin1_code":"21.0",
    "gn:admin2_code":"1862350.0",
    "gn:asciiname":"Ohara",
    "gn:country_code":"JP",
    "gn:dem":148,
    "gn:feature_class":"P",
    "gn:feature_code":"PPLL",
    "gn:name":"\u014chara",
    "gn:population":0,
    "gn:timezone":"Asia/Tokyo",
    "iso:country":"JP",
    "name:deu_x_preferred":[
        "Ohara"
    ],
    "name:ita_x_preferred":[
        "Ohara"
    ],
    "name:jpn_x_preferred":[
        "\u5927\u539f"
    ],
    "name:jpn_x_variant":[
        "\u304a\u304a\u306f\u3089",
        "\u30aa\u30aa\u30cf\u30e9"
    ],
    "name:kor_x_preferred":[
        "\uc624\ud558\ub77c"
    ],
    "name:und_x_variant":[
        "\u014chara"
    ],
    "wof:name":"Ohara",
    "wof:placetype":"locality"
},
  "geometry": {"coordinates":[130.72977,32.19808],"type":"Point"}
}