{
  "type": "Feature",
  "properties": {
    "gn:admin1_code":"34.0",
    "gn:admin2_code":"1859726.0",
    "gn:asciiname":"Higashikawaguchi",
    "gn:country_code":"JP",
    "gn:dem":8,
    "gn:feature_class":"P",
    "gn:feature_code":"PPL",
    "gn:name":"Higashikawaguchi",
    "gn:population":0,
    "gn:timezone":"Asia/Tokyo",
    "iso:country":"JP",
    "name:jpn_x_preferred":[
        "\u6771\u5ddd\u53e3"
    ],
    "name:jpn_x_variant":[
        "\u3072\u304c\u3057\u304b\u308f\u3050\u3061",
        "\u30d2\u30ac\u30b7\u30ab\u30ef\u30b0\u30c1"
    ],
    "wof:name":"Higashikawaguchi",
    "wof:placetype":"locality"
},
  "geometry": {"coordinates":[139.74631000000002,35.87942],"type":"Point"}
}