{
  "type": "Feature",
  "properties": {
    "gn:admin1_code":"16.0",
    "gn:admin2_code":"2111528.0",
    "gn:asciiname":"Masutate",
    "gn:country_code":"JP",
    "gn:dem":373,
    "gn:feature_class":"P",
    "gn:feature_code":"PPL",
    "gn:name":"Masutate",
    "gn:population":0,
    "gn:timezone":"Asia/Tokyo",
    "iso:country":"JP",
    "wof:name":"Masutate",
    "wof:placetype":"locality"
},
  "geometry": {"coordinates":[141.85499999999999,39.12167],"type":"Point"}
}