{
  "type": "Feature",
  "properties": {
    "gn:admin1_code":"19.0",
    "gn:admin2_code":"1848350.0",
    "gn:admin3_code":"14114.0",
    "gn:asciiname":"Akuwaminami",
    "gn:country_code":"JP",
    "gn:dem":65,
    "gn:feature_class":"P",
    "gn:feature_code":"PPL",
    "gn:name":"Akuwaminami",
    "gn:population":0,
    "gn:timezone":"Asia/Tokyo",
    "iso:country":"JP",
    "name:jpn_x_preferred":[
        "\u963f\u4e45\u548c\u5357"
    ],
    "name:jpn_x_variant":[
        "\u3042\u304f\u308f\u307f\u306a\u307f",
        "\u30a2\u30af\u30ef\u30df\u30ca\u30df"
    ],
    "wof:name":"Akuwaminami",
    "wof:placetype":"locality"
},
  "geometry": {"coordinates":[139.50412,35.44114000000001],"type":"Point"}
}