{
  "type": "Feature",
  "properties": {
    "gn:admin1_code":"16",
    "gn:admin2_code":"2110604.0",
    "gn:admin3_code":"3366.0",
    "gn:asciiname":"Tsuchihata",
    "gn:country_code":"JP",
    "gn:dem":294,
    "gn:feature_class":"P",
    "gn:feature_code":"PPL",
    "gn:name":"Tsuchihata",
    "gn:population":0,
    "gn:timezone":"Asia/Tokyo",
    "iso:country":"JP",
    "name:jpn_x_preferred":[
        "\u571f\u7551"
    ],
    "name:und_x_variant":[
        "Tsuchibatak\u014dzan",
        "Tsuchihata",
        "Tsuchihatak\u014dzan"
    ],
    "wof:name":"Tsuchihata",
    "wof:placetype":"locality"
},
  "geometry": {"coordinates":[140.77098000000001,39.28797],"type":"Point"}
}