{
  "type": "Feature",
  "properties": {
    "iso:country":"JP",
    "name:eng_x_preferred":[
        "Miyazaki 1 Chome"
    ],
    "name:eng_x_variant":[
        "Miyazaki 1 Choume",
        "Miyazaki 1 Chome"
    ],
    "name:jpn_x_preferred":[
        "\uff11\u4e01\u76ee"
    ],
    "name:jpn_x_variant":[
        "\u307f\u3084\u3056\u304d \uff11\u3061\u3087\u3046\u3081",
        "\u5bae\u5d0e \uff11\u4e01\u76ee",
        "\uff11\u3061\u3087\u3046\u3081"
    ],
    "name:unk_x_variant":[
        "\uff11\u4e01\u76ee"
    ],
    "qs:gn_adm0_cc":"JP",
    "qs:gn_local":1859642,
    "qs:local_max":4758,
    "qs:local_sum":25395,
    "qs:localhoods":83,
    "qs:name":"\uff11\u4e01\u76ee",
    "qs:name_adm0":"\u65e5\u672c",
    "qs:name_adm1":"\u795e\u5948\u5ddd\u770c",
    "qs:name_adm2":"\u5bae\u524d\u533a",
    "qs:name_en":"Miyazaki 1 Chome",
    "qs:name_lau":"\u5bae\u5d0e",
    "qs:name_local":"\u5ddd\u5d0e\u5e02",
    "qs:photo_max":21,
    "qs:photo_sum":67,
    "qs:placetype":"Suburb",
    "qs:quad_count":9,
    "qs:woe_adm0":23424856,
    "qs:woe_adm1":2345868,
    "qs:woe_adm2":15015511,
    "qs:woe_lau":28416471,
    "qs:woe_local":1117502,
    "qs:woe_ver":"7.10.0",
    "wof:lang":[
        "jpn"
    ],
    "wof:name":"\uff11\u4e01\u76ee",
    "wof:placetype":"neighbourhood"
},
  "geometry": {"coordinates":[139.59692799999999,35.58134],"type":"Point"}
}