{
  "type": "Feature",
  "properties": {
    "gn:admin1_code":"32",
    "gn:admin2_code":"1853897.0",
    "gn:admin3_code":"27102.0",
    "gn:asciiname":"Gamo",
    "gn:country_code":"JP",
    "gn:dem":11,
    "gn:feature_class":"P",
    "gn:feature_code":"PPL",
    "gn:name":"Gam\u014d",
    "gn:population":0,
    "gn:timezone":"Asia/Tokyo",
    "iso:country":"JP",
    "name:deu_x_preferred":[
        "Gamo"
    ],
    "name:fra_x_preferred":[
        "Gamo"
    ],
    "name:jpn_x_preferred":[
        "\u4eac\u6a4b"
    ],
    "name:jpn_x_variant":[
        "\u84b2\u751f"
    ],
    "name:por_x_preferred":[
        "Gamo"
    ],
    "name:und_x_variant":[
        "Ky\u014dbashi",
        "Gam\u014d"
    ],
    "wof:name":"Gamo",
    "wof:placetype":"locality"
},
  "geometry": {"coordinates":[135.53002000000001,34.69639],"type":"Point"}
}