{
  "type": "Feature",
  "properties": {
    "gn:admin1_code":"3.0",
    "gn:admin2_code":"2130056.0",
    "gn:asciiname":"Horikoshi",
    "gn:country_code":"JP",
    "gn:dem":41,
    "gn:feature_class":"P",
    "gn:feature_code":"PPL",
    "gn:name":"Horikoshi",
    "gn:population":0,
    "gn:timezone":"Asia/Tokyo",
    "iso:country":"JP",
    "name:jpn_x_preferred":[
        "\u5800\u8d8a"
    ],
    "name:jpn_x_variant":[
        "\u307b\u308a\u3053\u3057",
        "\u30db\u30ea\u30b3\u30b7"
    ],
    "wof:name":"Horikoshi",
    "wof:placetype":"locality"
},
  "geometry": {"coordinates":[140.51728,40.57257],"type":"Point"}
}