{
  "type": "Feature",
  "properties": {
    "gn:admin1_code":"4.0",
    "gn:admin2_code":"2110982.0",
    "gn:asciiname":"Nagawari",
    "gn:country_code":"JP",
    "gn:dem":72,
    "gn:feature_class":"P",
    "gn:feature_code":"PPLL",
    "gn:name":"Nagawari",
    "gn:population":0,
    "gn:timezone":"Asia/Tokyo",
    "iso:country":"JP",
    "name:jpn_x_preferred":[
        "\u9577\u5272"
    ],
    "name:jpn_x_variant":[
        "\u306a\u304c\u308f\u308a",
        "\u30ca\u30ac\u30ef\u30ea"
    ],
    "wof:name":"Nagawari",
    "wof:placetype":"locality"
},
  "geometry": {"coordinates":[140.05889999999999,35.41887],"type":"Point"}
}