{
  "type": "Feature",
  "properties": {
    "gn:admin1_code":"21.0",
    "gn:admin2_code":"1865358.0",
    "gn:asciiname":"Gotsu",
    "gn:country_code":"JP",
    "gn:dem":11,
    "gn:feature_class":"P",
    "gn:feature_code":"PPLL",
    "gn:name":"Gots\u016b",
    "gn:population":0,
    "gn:timezone":"Asia/Tokyo",
    "iso:country":"JP",
    "name:jpn_x_preferred":[
        "\u4e94\u901a"
    ],
    "name:jpn_x_variant":[
        "\u3054\u3064\u3046",
        "\u30b4\u30c4\u30a6"
    ],
    "name:und_x_variant":[
        "Gots\u016b"
    ],
    "wof:name":"Gotsu",
    "wof:placetype":"locality"
},
  "geometry": {"coordinates":[130.03573,32.2878],"type":"Point"}
}