{
  "type": "Feature",
  "properties": {
    "gn:admin1_code":"23.0",
    "gn:admin2_code":"1856290.0",
    "gn:asciiname":"Uyama",
    "gn:country_code":"JP",
    "gn:dem":262,
    "gn:feature_class":"P",
    "gn:feature_code":"PPL",
    "gn:name":"Uyama",
    "gn:population":0,
    "gn:timezone":"Asia/Tokyo",
    "iso:country":"JP",
    "name:jpn_x_preferred":[
        "\u9d8f\u5c71"
    ],
    "wof:name":"Uyama",
    "wof:placetype":"locality"
},
  "geometry": {"coordinates":[136.08893,34.66899],"type":"Point"}
}