{
  "type": "Feature",
  "properties": {
    "gn:admin1_code":"08",
    "gn:admin2_code":"1859662.0",
    "gn:admin3_code":"7421.0",
    "gn:asciiname":"Todera",
    "gn:country_code":"JP",
    "gn:dem":252,
    "gn:feature_class":"P",
    "gn:feature_code":"PPL",
    "gn:name":"T\u014ddera",
    "gn:population":0,
    "gn:timezone":"Asia/Tokyo",
    "iso:country":"JP",
    "name:jpn_x_preferred":[
        "\u5854\u5bfa"
    ],
    "name:und_x_variant":[
        "T\u014ddera"
    ],
    "wof:name":"Todera",
    "wof:placetype":"locality"
},
  "geometry": {"coordinates":[139.79496,37.57573],"type":"Point"}
}