{
  "type": "Feature",
  "properties": {
    "gn:admin1_code":"21.0",
    "gn:admin2_code":"7412706.0",
    "gn:admin3_code":"43447.0",
    "gn:asciiname":"Midorikawa",
    "gn:country_code":"JP",
    "gn:dem":698,
    "gn:feature_class":"P",
    "gn:feature_code":"PPL",
    "gn:name":"Midorikawa",
    "gn:population":0,
    "gn:timezone":"Asia/Tokyo",
    "iso:country":"JP",
    "name:jpn_x_preferred":[
        "\u7dd1\u5ddd"
    ],
    "name:jpn_x_variant":[
        "\u307f\u3069\u308a\u304b\u308f",
        "\u30df\u30c9\u30ea\u30ab\u30ef"
    ],
    "wof:name":"Midorikawa",
    "wof:placetype":"locality"
},
  "geometry": {"coordinates":[131.09756000000002,32.62765],"type":"Point"}
}