{
  "type": "Feature",
  "properties": {
    "gn:admin1_code":"33.0",
    "gn:admin2_code":"7391355.0",
    "gn:asciiname":"Minamihatacho-fumaneki",
    "gn:country_code":"JP",
    "gn:dem":44,
    "gn:feature_class":"P",
    "gn:feature_code":"PPL",
    "gn:name":"Minamihatach\u014d-fumaneki",
    "gn:population":0,
    "gn:timezone":"Asia/Tokyo",
    "iso:country":"JP",
    "name:jpn_x_preferred":[
        "\u5357\u6ce2\u591a\u753a\u5e9c\u62db"
    ],
    "name:und_x_variant":[
        "Minamihatach\u014d-fumaneki"
    ],
    "wof:name":"Minamihatacho-fumaneki",
    "wof:placetype":"locality"
},
  "geometry": {"coordinates":[129.91801999999998,33.29843],"type":"Point"}
}