{
  "type": "Feature",
  "properties": {
    "gn:admin1_code":"21.0",
    "gn:admin2_code":"1865358.0",
    "gn:asciiname":"Myose",
    "gn:country_code":"JP",
    "gn:dem":8,
    "gn:feature_class":"P",
    "gn:feature_code":"PPLL",
    "gn:name":"My\u014dse",
    "gn:population":0,
    "gn:timezone":"Asia/Tokyo",
    "iso:country":"JP",
    "name:jpn_x_preferred":[
        "\u660e\u702c"
    ],
    "name:jpn_x_variant":[
        "\u307f\u3087\u3046\u305b",
        "\u30df\u30e7\u30a6\u30bb"
    ],
    "name:und_x_variant":[
        "My\u014dse"
    ],
    "wof:name":"Myose",
    "wof:placetype":"locality"
},
  "geometry": {"coordinates":[130.20321999999999,32.47999],"type":"Point"}
}