{
  "type": "Feature",
  "properties": {
    "gn:admin1_code":"18.0",
    "gn:admin2_code":"7383987.0",
    "gn:asciiname":"Naze-hiratacho",
    "gn:country_code":"JP",
    "gn:dem":101,
    "gn:feature_class":"P",
    "gn:feature_code":"PPL",
    "gn:name":"Naze-hiratach\u014d",
    "gn:population":0,
    "gn:timezone":"Asia/Tokyo",
    "iso:country":"JP",
    "name:jpn_x_preferred":[
        "\u540d\u702c\u5e73\u7530\u753a"
    ],
    "name:und_x_variant":[
        "Naze-hiratach\u014d"
    ],
    "wof:name":"Naze-hiratacho",
    "wof:placetype":"locality"
},
  "geometry": {"coordinates":[129.5027,28.36021],"type":"Point"}
}