{
  "type": "Feature",
  "properties": {
    "gn:admin1_code":"4.0",
    "gn:admin2_code":"1864901.0",
    "gn:admin3_code":"12463.0",
    "gn:asciiname":"Yoshihama",
    "gn:country_code":"JP",
    "gn:dem":25,
    "gn:feature_class":"P",
    "gn:feature_code":"PPL",
    "gn:name":"Yoshihama",
    "gn:population":0,
    "gn:timezone":"Asia/Tokyo",
    "iso:country":"JP",
    "name:jpn_x_preferred":[
        "\u5409\u6d5c"
    ],
    "name:jpn_x_variant":[
        "\u3088\u3057\u306f\u307e",
        "\u30e8\u30b7\u30cf\u30de"
    ],
    "wof:name":"Yoshihama",
    "wof:placetype":"locality"
},
  "geometry": {"coordinates":[139.84063999999998,35.13042],"type":"Point"}
}