{
  "type": "Feature",
  "properties": {
    "gn:admin1_code":"7.0",
    "gn:admin2_code":"1859306.0",
    "gn:admin3_code":"40106.0",
    "gn:asciiname":"Myokencho",
    "gn:country_code":"JP",
    "gn:dem":47,
    "gn:feature_class":"P",
    "gn:feature_code":"PPL",
    "gn:name":"My\u014dkench\u014d",
    "gn:population":0,
    "gn:timezone":"Asia/Tokyo",
    "iso:country":"JP",
    "name:jpn_x_preferred":[
        "\u5999\u898b\u753a"
    ],
    "name:und_x_variant":[
        "My\u014dkench\u014d"
    ],
    "wof:name":"Myokencho",
    "wof:placetype":"locality"
},
  "geometry": {"coordinates":[130.90456,33.86543],"type":"Point"}
}