{
  "type": "Feature",
  "properties": {
    "iso:country":"JP",
    "qs:name":"\u5948\u4e95\u6c5f\u753a",
    "qs:name_adm0":"\u65e5\u672c",
    "qs:name_adm1":"\u5317\u6d77\u9053",
    "qs:photos":41,
    "qs:photos_1k":8,
    "qs:photos_9k":1,
    "qs:photos_9r":2,
    "qs:photos_all":41,
    "qs:photos_sr":2,
    "qs:placetype":"Town",
    "qs:pop_sr":"0",
    "wof:name":"\u5948\u4e95\u6c5f\u753a",
    "wof:placetype":"locality"
},
  "geometry": {"coordinates":[141.888766,43.425877],"type":"Point"}
}