{
  "type": "Feature",
  "properties": {
    "gn:admin1_code":"08",
    "gn:admin2_code":"1848677.0",
    "gn:admin3_code":"7408.0",
    "gn:asciiname":"Shimodate",
    "gn:country_code":"JP",
    "gn:dem":531,
    "gn:feature_class":"P",
    "gn:feature_code":"PPL",
    "gn:name":"Shimodate",
    "gn:population":0,
    "gn:timezone":"Asia/Tokyo",
    "iso:country":"JP",
    "name:jpn_x_preferred":[
        "\u4e0b\u9928"
    ],
    "wof:name":"Shimodate",
    "wof:placetype":"locality"
},
  "geometry": {"coordinates":[140.13202999999999,37.56757],"type":"Point"}
}