{
  "type": "Feature",
  "properties": {
    "gn:admin1_code":"13",
    "gn:admin2_code":"7370817.0",
    "gn:asciiname":"Nada-shirosaki",
    "gn:country_code":"JP",
    "gn:dem":69,
    "gn:feature_class":"P",
    "gn:feature_code":"PPL",
    "gn:name":"Nada-shirosaki",
    "gn:population":0,
    "gn:timezone":"Asia/Tokyo",
    "iso:country":"JP",
    "name:jpn_x_preferred":[
        "\u7058\u767d\u5d0e"
    ],
    "name:und_x_variant":[
        "Uno",
        "Shirasaki",
        "Shirosaki",
        "Nada-shirosaki"
    ],
    "wof:name":"Nada-shirosaki",
    "wof:placetype":"locality"
},
  "geometry": {"coordinates":[134.84999999999999,34.23333],"type":"Point"}
}