{
  "type": "Feature",
  "properties": {
    "gn:admin1_code":"24.0",
    "gn:admin2_code":"7446990.0",
    "gn:asciiname":"Ohinata",
    "gn:country_code":"JP",
    "gn:dem":24,
    "gn:feature_class":"P",
    "gn:feature_code":"PPL",
    "gn:name":"\u014chinata",
    "gn:population":0,
    "gn:timezone":"Asia/Tokyo",
    "iso:country":"JP",
    "name:jpn_x_preferred":[
        "\u5927\u65e5\u5411"
    ],
    "name:jpn_x_variant":[
        "\u304a\u304a\u3072\u306a\u305f",
        "\u30aa\u30aa\u30d2\u30ca\u30bf"
    ],
    "name:und_x_variant":[
        "\u014chinata"
    ],
    "wof:name":"Ohinata",
    "wof:placetype":"locality"
},
  "geometry": {"coordinates":[141.12996999999999,38.43587],"type":"Point"}
}