{
  "type": "Feature",
  "properties": {
    "gn:admin1_code":"21.0",
    "gn:admin2_code":"1858418.0",
    "gn:admin3_code":"43102.0",
    "gn:asciiname":"Yamanokami",
    "gn:country_code":"JP",
    "gn:dem":46,
    "gn:feature_class":"P",
    "gn:feature_code":"PPLL",
    "gn:name":"Yamanokami",
    "gn:population":0,
    "gn:timezone":"Asia/Tokyo",
    "iso:country":"JP",
    "name:jpn_x_preferred":[
        "\u5c71\u30ce\u795e"
    ],
    "name:jpn_x_variant":[
        "\u3084\u307e\u306e\u304b\u307f",
        "\u30e4\u30de\u30ce\u30ab\u30df"
    ],
    "wof:name":"Yamanokami",
    "wof:placetype":"locality"
},
  "geometry": {"coordinates":[130.77476999999999,32.79653],"type":"Point"}
}