{
  "type": "Feature",
  "properties": {
    "gn:admin1_code":"2.0",
    "gn:admin2_code":"2128783.0",
    "gn:asciiname":"Sakuracho-minami",
    "gn:country_code":"JP",
    "gn:dem":68,
    "gn:feature_class":"P",
    "gn:feature_code":"PPL",
    "gn:name":"Sakurach\u014d-minami",
    "gn:population":0,
    "gn:timezone":"Asia/Tokyo",
    "iso:country":"JP",
    "name:jpn_x_preferred":[
        "\u685c\u753a\u5357"
    ],
    "name:jpn_x_variant":[
        "\u3055\u304f\u3089\u3061\u3087\u3046\u307f\u306a\u307f",
        "\u30b5\u30af\u30e9\u30c1\u30e7\u30a6\u30df\u30ca\u30df"
    ],
    "name:und_x_variant":[
        "Sakurach\u014d-minami"
    ],
    "wof:name":"Sakuracho-minami",
    "wof:placetype":"locality"
},
  "geometry": {"coordinates":[140.5669,40.26773],"type":"Point"}
}