{
  "type": "Feature",
  "properties": {
    "gn:admin1_code":"12.0",
    "gn:admin2_code":"7428078.0",
    "gn:admin3_code":"1662.0",
    "gn:asciiname":"Oboro",
    "gn:country_code":"JP",
    "gn:dem":11,
    "gn:feature_class":"P",
    "gn:feature_code":"PPL",
    "gn:name":"Oboro",
    "gn:population":0,
    "gn:timezone":"Asia/Tokyo",
    "iso:country":"JP",
    "name:fra_x_preferred":[
        "Oboro"
    ],
    "name:jpn_x_preferred":[
        "\u5c3e\u5e4c"
    ],
    "name:jpn_x_variant":[
        "\u304a\u307c\u308d",
        "\u30aa\u30dc\u30ed"
    ],
    "name:spa_x_preferred":[
        "Oboro"
    ],
    "name:und_x_variant":[
        "Opporo"
    ],
    "wof:name":"Oboro",
    "wof:placetype":"locality"
},
  "geometry": {"coordinates":[144.70096000000001,43.01239],"type":"Point"}
}