{
  "type": "Feature",
  "properties": {
    "gn:admin1_code":"19.0",
    "gn:admin2_code":"1856851.0",
    "gn:admin3_code":"14301.0",
    "gn:asciiname":"Nagae",
    "gn:country_code":"JP",
    "gn:dem":47,
    "gn:feature_class":"P",
    "gn:feature_code":"PPL",
    "gn:name":"Nagae",
    "gn:population":0,
    "gn:timezone":"Asia/Tokyo",
    "iso:country":"JP",
    "name:jpn_x_preferred":[
        "\u9577\u67c4"
    ],
    "name:jpn_x_variant":[
        "\u306a\u304c\u3048",
        "\u30ca\u30ac\u30a8"
    ],
    "wof:name":"Nagae",
    "wof:placetype":"locality"
},
  "geometry": {"coordinates":[139.58686,35.28518],"type":"Point"}
}