{
  "type": "Feature",
  "properties": {
    "gn:admin1_code":"37.0",
    "gn:admin2_code":"7418322.0",
    "gn:asciiname":"Futamata",
    "gn:country_code":"JP",
    "gn:dem":239,
    "gn:feature_class":"P",
    "gn:feature_code":"PPL",
    "gn:name":"Futamata",
    "gn:population":0,
    "gn:timezone":"Asia/Tokyo",
    "iso:country":"JP",
    "name:jpn_x_preferred":[
        "\u4e8c\u4fe3"
    ],
    "wof:name":"Futamata",
    "wof:placetype":"locality"
},
  "geometry": {"coordinates":[138.15135000000001,34.94993],"type":"Point"}
}