{
  "type": "Feature",
  "properties": {
    "gn:admin1_code":"21.0",
    "gn:admin2_code":"7413151.0",
    "gn:asciiname":"Karajiro",
    "gn:country_code":"JP",
    "gn:dem":16,
    "gn:feature_class":"P",
    "gn:feature_code":"PPLL",
    "gn:name":"Karajiro",
    "gn:population":0,
    "gn:timezone":"Asia/Tokyo",
    "iso:country":"JP",
    "name:jpn_x_preferred":[
        "\u5510\u7db2\u4ee3"
    ],
    "name:jpn_x_variant":[
        "\u304b\u3089\u3058\u308d",
        "\u30ab\u30e9\u30b8\u30ed"
    ],
    "wof:name":"Karajiro",
    "wof:placetype":"locality"
},
  "geometry": {"coordinates":[130.35476,32.37878],"type":"Point"}
}