{
  "type": "Feature",
  "properties": {
    "gn:admin1_code":"9.0",
    "gn:admin2_code":"7419032.0",
    "gn:asciiname":"Kawaicho-inagoe",
    "gn:country_code":"JP",
    "gn:dem":849,
    "gn:feature_class":"P",
    "gn:feature_code":"PPL",
    "gn:name":"Kawaich\u014d-inagoe",
    "gn:population":0,
    "gn:timezone":"Asia/Tokyo",
    "iso:country":"JP",
    "name:jpn_x_preferred":[
        "\u6cb3\u5408\u753a\u7a32\u8d8a"
    ],
    "name:und_x_variant":[
        "Kawaich\u014d-inagoe"
    ],
    "wof:name":"Kawaicho-inagoe",
    "wof:placetype":"locality"
},
  "geometry": {"coordinates":[137.07766999999998,36.24486],"type":"Point"}
}