{
  "type": "Feature",
  "properties": {
    "gn:admin1_code":"01",
    "gn:admin2_code":"1859272.0",
    "gn:admin3_code":"23563.0",
    "gn:asciiname":"Kamikurogawa",
    "gn:country_code":"JP",
    "gn:dem":568,
    "gn:feature_class":"P",
    "gn:feature_code":"PPL",
    "gn:name":"Kamikurogawa",
    "gn:population":0,
    "gn:timezone":"Asia/Tokyo",
    "iso:country":"JP",
    "wof:name":"Kamikurogawa",
    "wof:placetype":"locality"
},
  "geometry": {"coordinates":[137.69072,35.14879000000001],"type":"Point"}
}