{
  "type": "Feature",
  "properties": {
    "gn:admin1_code":"15",
    "gn:admin2_code":"7467839.0",
    "gn:admin3_code":"17463.0",
    "gn:asciiname":"Kuri-kawashiri",
    "gn:country_code":"JP",
    "gn:dem":32,
    "gn:feature_class":"P",
    "gn:feature_code":"PPL",
    "gn:name":"Kuri-kawashiri",
    "gn:population":0,
    "gn:timezone":"Asia/Tokyo",
    "iso:country":"JP",
    "name:jpn_x_preferred":[
        "\u4e5d\u91cc\u5ddd\u5c3b"
    ],
    "name:und_x_variant":[
        "Kawajiri"
    ],
    "wof:name":"Kuri-kawashiri",
    "wof:placetype":"locality"
},
  "geometry": {"coordinates":[137.25,37.33333],"type":"Point"}
}