{
  "type": "Feature",
  "properties": {
    "gn:admin1_code":"40.0",
    "gn:admin2_code":"1853655.0",
    "gn:asciiname":"Omori-honcho",
    "gn:country_code":"JP",
    "gn:dem":9,
    "gn:feature_class":"P",
    "gn:feature_code":"PPL",
    "gn:name":"\u014cmori-honch\u014d",
    "gn:population":0,
    "gn:timezone":"Asia/Tokyo",
    "iso:country":"JP",
    "name:jpn_x_preferred":[
        "\u5927\u68ee\u672c\u753a"
    ],
    "name:und_x_variant":[
        "\u014cmori-honch\u014d"
    ],
    "wof:name":"Omori-honcho",
    "wof:placetype":"locality"
},
  "geometry": {"coordinates":[139.73788000000002,35.58041],"type":"Point"}
}