{
  "type": "Feature",
  "properties": {
    "gn:admin1_code":"32.0",
    "gn:admin2_code":"1861089.0",
    "gn:asciiname":"Fuchucho",
    "gn:country_code":"JP",
    "gn:dem":20,
    "gn:feature_class":"P",
    "gn:feature_code":"PPL",
    "gn:name":"Fuch\u016bch\u014d",
    "gn:population":0,
    "gn:timezone":"Asia/Tokyo",
    "iso:country":"JP",
    "name:jpn_x_preferred":[
        "\u5e9c\u4e2d\u753a"
    ],
    "name:und_x_variant":[
        "Fuch\u016bch\u014d"
    ],
    "wof:name":"Fuchucho",
    "wof:placetype":"locality"
},
  "geometry": {"coordinates":[135.42614,34.48609],"type":"Point"}
}