{
  "type": "Feature",
  "properties": {
    "gn:admin1_code":"21.0",
    "gn:admin2_code":"1857206.0",
    "gn:asciiname":"Konogochi",
    "gn:country_code":"JP",
    "gn:dem":89,
    "gn:feature_class":"P",
    "gn:feature_code":"PPLL",
    "gn:name":"Konogochi",
    "gn:population":0,
    "gn:timezone":"Asia/Tokyo",
    "iso:country":"JP",
    "name:jpn_x_preferred":[
        "\u5c0f\u91ce\u5ddd\u5185"
    ],
    "name:jpn_x_variant":[
        "\u3053\u306e\u3054\u3061",
        "\u30b3\u30ce\u30b4\u30c1"
    ],
    "wof:name":"Konogochi",
    "wof:placetype":"locality"
},
  "geometry": {"coordinates":[130.44732999999999,32.21169],"type":"Point"}
}