{
  "type": "Feature",
  "properties": {
    "gn:admin1_code":"21.0",
    "gn:admin2_code":"7413152.0",
    "gn:asciiname":"Hashirayama",
    "gn:country_code":"JP",
    "gn:dem":105,
    "gn:feature_class":"P",
    "gn:feature_code":"PPLL",
    "gn:name":"Hashirayama",
    "gn:population":0,
    "gn:timezone":"Asia/Tokyo",
    "iso:country":"JP",
    "name:jpn_x_preferred":[
        "\u67f1\u5c71"
    ],
    "name:jpn_x_variant":[
        "\u306f\u3057\u3089\u3084\u307e",
        "\u30cf\u30b7\u30e9\u30e4\u30de"
    ],
    "wof:name":"Hashirayama",
    "wof:placetype":"locality"
},
  "geometry": {"coordinates":[130.74521999999999,32.57193],"type":"Point"}
}