{
  "type": "Feature",
  "properties": {
    "gn:admin1_code":"21.0",
    "gn:admin2_code":"7413150.0",
    "gn:asciiname":"Yamashita",
    "gn:country_code":"JP",
    "gn:dem":188,
    "gn:feature_class":"P",
    "gn:feature_code":"PPLL",
    "gn:name":"Yamashita",
    "gn:population":0,
    "gn:timezone":"Asia/Tokyo",
    "iso:country":"JP",
    "name:jpn_x_preferred":[
        "\u5c71\u4e0b"
    ],
    "name:jpn_x_variant":[
        "\u3084\u307e\u3057\u305f",
        "\u30e4\u30de\u30b7\u30bf"
    ],
    "name:nor_x_preferred":[
        "Yamashita"
    ],
    "wof:name":"Yamashita",
    "wof:placetype":"locality"
},
  "geometry": {"coordinates":[130.77951000000002,33.07232],"type":"Point"}
}