{
  "type": "Feature",
  "properties": {
    "gn:admin1_code":"21.0",
    "gn:admin2_code":"1865358.0",
    "gn:asciiname":"Fukamimachi",
    "gn:country_code":"JP",
    "gn:dem":23,
    "gn:feature_class":"P",
    "gn:feature_code":"PPL",
    "gn:name":"Fukamimachi",
    "gn:population":0,
    "gn:timezone":"Asia/Tokyo",
    "iso:country":"JP",
    "name:jpn_x_preferred":[
        "\u6df1\u6d77\u753a"
    ],
    "name:jpn_x_variant":[
        "\u3075\u304b\u307f\u307e\u3061",
        "\u30d5\u30ab\u30df\u30de\u30c1"
    ],
    "wof:name":"Fukamimachi",
    "wof:placetype":"locality"
},
  "geometry": {"coordinates":[130.08838,32.25232],"type":"Point"}
}