{
  "type": "Feature",
  "properties": {
    "gn:admin1_code":"7.0",
    "gn:admin2_code":"1863955.0",
    "gn:admin3_code":"40135.0",
    "gn:asciiname":"Kuwabara",
    "gn:country_code":"JP",
    "gn:dem":18,
    "gn:feature_class":"P",
    "gn:feature_code":"PPL",
    "gn:name":"Kuwabara",
    "gn:population":0,
    "gn:timezone":"Asia/Tokyo",
    "iso:country":"JP",
    "name:jpn_x_preferred":[
        "\u6851\u539f"
    ],
    "wof:name":"Kuwabara",
    "wof:placetype":"locality"
},
  "geometry": {"coordinates":[130.22418999999999,33.60461],"type":"Point"}
}