{
  "type": "Feature",
  "properties": {
    "gn:admin1_code":"28.0",
    "gn:admin2_code":"1848592.0",
    "gn:asciiname":"Imazatocho",
    "gn:country_code":"JP",
    "gn:dem":58,
    "gn:feature_class":"P",
    "gn:feature_code":"PPL",
    "gn:name":"Imazatoch\u014d",
    "gn:population":0,
    "gn:timezone":"Asia/Tokyo",
    "iso:country":"JP",
    "name:jpn_x_preferred":[
        "\u4eca\u91cc\u753a"
    ],
    "name:und_x_variant":[
        "Imazatoch\u014d"
    ],
    "wof:name":"Imazatocho",
    "wof:placetype":"locality"
},
  "geometry": {"coordinates":[135.75319999999999,34.51011],"type":"Point"}
}