{
  "type": "Feature",
  "properties": {
    "iso:country":"JP",
    "label:eng_x_preferred_longname":[
        "Yoro Town"
    ],
    "label:eng_x_preferred_placetype":[
        "town"
    ],
    "name:eng_x_preferred":[
        "Yoro"
    ],
    "name:eng_x_variant":[
        "Yoro Town"
    ],
    "name:jpn_x_preferred":[
        "\u990a\u8001\u753a"
    ],
    "qs:name":"\u990a\u8001\u753a",
    "qs:name_adm0":"\u65e5\u672c",
    "qs:name_adm1":"\u5c90\u961c\u770c",
    "qs:photos":296,
    "qs:photos_1k":60,
    "qs:photos_9k":1,
    "qs:photos_9r":5,
    "qs:photos_all":309,
    "qs:photos_sr":5,
    "qs:placetype":"Town",
    "qs:pop_sr":"0",
    "wof:name":"Yoro",
    "wof:placetype":"locality"
},
  "geometry": {"coordinates":[136.55226049999999,35.2871515],"type":"Point"}
}