{
  "type": "Feature",
  "properties": {
    "gn:admin1_code":"41",
    "gn:admin2_code":"1853248.0",
    "gn:admin3_code":"31389.0",
    "gn:asciiname":"Kanayama",
    "gn:country_code":"JP",
    "gn:dem":201,
    "gn:feature_class":"P",
    "gn:feature_code":"PPL",
    "gn:name":"Kanayama",
    "gn:population":0,
    "gn:timezone":"Asia/Tokyo",
    "iso:country":"JP",
    "name:jpn_x_preferred":[
        "\u91d1\u5c71"
    ],
    "name:und_x_variant":[
        "T\u014dj\u014d",
        "Kaneyama",
        "Kanayama"
    ],
    "wof:name":"Kanayama",
    "wof:placetype":"locality"
},
  "geometry": {"coordinates":[133.36913999999999,35.29190999999999],"type":"Point"}
}