{
  "type": "Feature",
  "properties": {
    "gn:admin1_code":"4.0",
    "gn:admin2_code":"2112997.0",
    "gn:admin3_code":"12424.0",
    "gn:asciiname":"Nakakawagishi",
    "gn:country_code":"JP",
    "gn:dem":3,
    "gn:feature_class":"P",
    "gn:feature_code":"PPLL",
    "gn:name":"Nakakawagishi",
    "gn:population":0,
    "gn:timezone":"Asia/Tokyo",
    "iso:country":"JP",
    "name:jpn_x_preferred":[
        "\u4e2d\u5ddd\u5cb8"
    ],
    "name:jpn_x_variant":[
        "\u306a\u304b\u304b\u308f\u304e\u3057",
        "\u30ca\u30ab\u30ab\u30ef\u30ae\u30b7"
    ],
    "wof:name":"Nakakawagishi",
    "wof:placetype":"locality"
},
  "geometry": {"coordinates":[140.39883999999998,35.4451],"type":"Point"}
}