{
  "type": "Feature",
  "properties": {
    "gn:admin1_code":"16.0",
    "gn:admin2_code":"2112822.0",
    "gn:asciiname":"Nishinaka",
    "gn:country_code":"JP",
    "gn:dem":83,
    "gn:feature_class":"P",
    "gn:feature_code":"PPL",
    "gn:name":"Nishinaka",
    "gn:population":0,
    "gn:timezone":"Asia/Tokyo",
    "iso:country":"JP",
    "name:jpn_x_preferred":[
        "\u897f\u4e2d"
    ],
    "name:jpn_x_variant":[
        "\u306b\u3057\u306a\u304b",
        "\u30cb\u30b7\u30ca\u30ab"
    ],
    "wof:name":"Nishinaka",
    "wof:placetype":"locality"
},
  "geometry": {"coordinates":[141.12197,39.42022],"type":"Point"}
}