{
  "type": "Feature",
  "properties": {
    "gn:admin1_code":"7.0",
    "gn:admin2_code":"7407413.0",
    "gn:asciiname":"Tani",
    "gn:country_code":"JP",
    "gn:dem":119,
    "gn:feature_class":"P",
    "gn:feature_code":"PPLL",
    "gn:name":"Tani",
    "gn:population":0,
    "gn:timezone":"Asia/Tokyo",
    "iso:country":"JP",
    "name:jpn_x_preferred":[
        "\u8c37"
    ],
    "wof:name":"Tani",
    "wof:placetype":"locality"
},
  "geometry": {"coordinates":[130.74639999999999,33.52029],"type":"Point"}
}