{
  "type": "Feature",
  "properties": {
    "gn:admin1_code":"21.0",
    "gn:admin2_code":"1858418.0",
    "gn:admin3_code":"43105.0",
    "gn:asciiname":"Tani",
    "gn:country_code":"JP",
    "gn:dem":44,
    "gn:feature_class":"P",
    "gn:feature_code":"PPLL",
    "gn:name":"Tani",
    "gn:population":0,
    "gn:timezone":"Asia/Tokyo",
    "iso:country":"JP",
    "name:ceb_x_preferred":[
        "Tani"
    ],
    "name:deu_x_preferred":[
        "Tani"
    ],
    "name:fin_x_preferred":[
        "Tani"
    ],
    "name:fra_x_preferred":[
        "Tani"
    ],
    "name:ita_x_preferred":[
        "Tani"
    ],
    "name:jpn_x_preferred":[
        "\u8c37"
    ],
    "name:jpn_x_variant":[
        "\u305f\u306b",
        "\u30bf\u30cb"
    ],
    "name:por_x_preferred":[
        "Tani"
    ],
    "name:swe_x_preferred":[
        "Tani"
    ],
    "wof:name":"Tani",
    "wof:placetype":"locality"
},
  "geometry": {"coordinates":[130.64753000000002,32.91899],"type":"Point"}
}