{
  "type": "Feature",
  "properties": {
    "iso:country":"JP",
    "name:eng_x_preferred":[
        "Higashikideracho 2 Chome"
    ],
    "name:eng_x_variant":[
        "Higashikiderachou 2 Choume",
        "Higashikideracho 2 Chome"
    ],
    "name:jpn_x_preferred":[
        "\uff12\u4e01\u76ee"
    ],
    "name:jpn_x_variant":[
        "\u3072\u304c\u3057\u304d\u3067\u3089\u3061\u3087\u3046 \uff12\u3061\u3087\u3046\u3081",
        "\u6771\u7d00\u5bfa\u753a \uff12\u4e01\u76ee",
        "\uff12\u3061\u3087\u3046\u3081"
    ],
    "name:unk_x_variant":[
        "\uff12\u4e01\u76ee"
    ],
    "qs:gn_local":0,
    "qs:local_max":12821,
    "qs:local_sum":32218,
    "qs:localhoods":19,
    "qs:name":"\uff12\u4e01\u76ee",
    "qs:name_adm0":"\u65e5\u672c",
    "qs:name_adm1":"\u5948\u826f\u770c",
    "qs:name_en":"Higashikideracho 2 Chome",
    "qs:name_lau":"\u6771\u7d00\u5bfa\u753a",
    "qs:name_local":"\u5948\u826f\u5e02",
    "qs:photo_max":1977,
    "qs:photo_sum":12821,
    "qs:placetype":"Suburb",
    "qs:quad_count":74,
    "qs:woe_adm0":23424856,
    "qs:woe_adm1":2345877,
    "qs:woe_adm2":0,
    "qs:woe_lau":28465923,
    "qs:woe_local":1117858,
    "qs:woe_ver":"7.10.0",
    "wof:lang":[
        "jpn"
    ],
    "wof:name":"\uff12\u4e01\u76ee",
    "wof:placetype":"neighbourhood"
},
  "geometry": {"coordinates":[135.842207,34.684073],"type":"Point"}
}