{
  "type": "Feature",
  "properties": {
    "gn:admin1_code":"7.0",
    "gn:admin2_code":"1856443.0",
    "gn:asciiname":"Oiminami",
    "gn:country_code":"JP",
    "gn:dem":20,
    "gn:feature_class":"P",
    "gn:feature_code":"PPL",
    "gn:name":"\u014ciminami",
    "gn:population":0,
    "gn:timezone":"Asia/Tokyo",
    "iso:country":"JP",
    "name:jpn_x_preferred":[
        "\u5927\u4e95\u5357"
    ],
    "name:und_x_variant":[
        "\u014ciminami"
    ],
    "wof:name":"Oiminami",
    "wof:placetype":"locality"
},
  "geometry": {"coordinates":[130.52803,33.80538],"type":"Point"}
}