{
  "type": "Feature",
  "properties": {
    "gn:admin1_code":"16",
    "gn:admin2_code":"7441808.0",
    "gn:asciiname":"Tanaka",
    "gn:country_code":"JP",
    "gn:dem":275,
    "gn:feature_class":"P",
    "gn:feature_code":"PPL",
    "gn:name":"Tanaka",
    "gn:population":0,
    "gn:timezone":"Asia/Tokyo",
    "iso:country":"JP",
    "name:epo_x_preferred":[
        "Tanaka"
    ],
    "name:spa_x_preferred":[
        "Tanaka"
    ],
    "name:ukr_x_preferred":[
        "\u0422\u0430\u043d\u0430\u043a\u0430"
    ],
    "wof:name":"Tanaka",
    "wof:placetype":"locality"
},
  "geometry": {"coordinates":[141.06666999999999,39.95],"type":"Point"}
}