{
  "type": "Feature",
  "properties": {
    "gn:admin1_code":"21.0",
    "gn:admin2_code":"1865358.0",
    "gn:asciiname":"Kashinoura",
    "gn:country_code":"JP",
    "gn:dem":20,
    "gn:feature_class":"P",
    "gn:feature_code":"PPLL",
    "gn:name":"Kashinoura",
    "gn:population":0,
    "gn:timezone":"Asia/Tokyo",
    "iso:country":"JP",
    "name:jpn_x_preferred":[
        "\u6a2b\u306e\u6d66"
    ],
    "name:jpn_x_variant":[
        "\u304b\u3057\u306e\u3046\u3089",
        "\u30ab\u30b7\u30ce\u30a6\u30e9"
    ],
    "wof:name":"Kashinoura",
    "wof:placetype":"locality"
},
  "geometry": {"coordinates":[130.20861000000002,32.39288],"type":"Point"}
}