{
  "type": "Feature",
  "properties": {
    "gn:admin1_code":"28.0",
    "gn:admin2_code":"1848164.0",
    "gn:admin3_code":"29453.0",
    "gn:asciiname":"Tanjiri",
    "gn:country_code":"JP",
    "gn:dem":559,
    "gn:feature_class":"P",
    "gn:feature_code":"PPL",
    "gn:name":"Tanjiri",
    "gn:population":0,
    "gn:timezone":"Asia/Tokyo",
    "iso:country":"JP",
    "name:jpn_x_preferred":[
        "\u8c37\u5c3b"
    ],
    "wof:name":"Tanjiri",
    "wof:placetype":"locality"
},
  "geometry": {"coordinates":[136.03453999999999,34.45105],"type":"Point"}
}