{
  "type": "Feature",
  "properties": {
    "gn:admin1_code":"19.0",
    "gn:admin2_code":"1854744.0",
    "gn:asciiname":"Nishinaruda",
    "gn:country_code":"JP",
    "gn:dem":21,
    "gn:feature_class":"P",
    "gn:feature_code":"PPLL",
    "gn:name":"Nishinaruda",
    "gn:population":0,
    "gn:timezone":"Asia/Tokyo",
    "iso:country":"JP",
    "name:jpn_x_preferred":[
        "\u897f\u6210\u7530"
    ],
    "wof:name":"Nishinaruda",
    "wof:placetype":"locality"
},
  "geometry": {"coordinates":[139.16296,35.2935],"type":"Point"}
}