{
  "type": "Feature",
  "properties": {
    "gn:admin1_code":"3.0",
    "gn:admin2_code":"2127674.0",
    "gn:asciiname":"Ushidomari",
    "gn:country_code":"JP",
    "gn:dem":59,
    "gn:feature_class":"P",
    "gn:feature_code":"PPL",
    "gn:name":"Ushidomari",
    "gn:population":0,
    "gn:timezone":"Asia/Tokyo",
    "iso:country":"JP",
    "name:jpn_x_preferred":[
        "\u725b\u6cca"
    ],
    "name:jpn_x_variant":[
        "\u3046\u3057\u3069\u307e\u308a",
        "\u30a6\u30b7\u30c9\u30de\u30ea"
    ],
    "wof:name":"Ushidomari",
    "wof:placetype":"locality"
},
  "geometry": {"coordinates":[141.23310000000001,40.61815],"type":"Point"}
}