{
  "type": "Feature",
  "properties": {
    "gn:admin1_code":"29",
    "gn:admin2_code":"1853313.0",
    "gn:asciiname":"Sawanemachi",
    "gn:country_code":"JP",
    "gn:dem":18,
    "gn:feature_class":"P",
    "gn:feature_code":"PPL",
    "gn:name":"Sawanemachi",
    "gn:population":0,
    "gn:timezone":"Asia/Tokyo",
    "iso:country":"JP",
    "name:jpn_x_preferred":[
        "\u6ca2\u6839\u753a"
    ],
    "name:und_x_variant":[
        "Sawane",
        "Sawanemachi",
        "Sawane Sawanemachi"
    ],
    "wof:name":"Sawanemachi",
    "wof:placetype":"locality"
},
  "geometry": {"coordinates":[138.27413999999999,38.00384],"type":"Point"}
}