{
  "type": "Feature",
  "properties": {
    "gn:admin1_code":"12.0",
    "gn:admin2_code":"2128971.0",
    "gn:asciiname":"Kaigancho",
    "gn:country_code":"JP",
    "gn:dem":5,
    "gn:feature_class":"P",
    "gn:feature_code":"PPL",
    "gn:name":"Kaiganch\u014d",
    "gn:population":0,
    "gn:timezone":"Asia/Tokyo",
    "iso:country":"JP",
    "name:jpn_x_preferred":[
        "\u6d77\u5cb8\u753a"
    ],
    "name:jpn_x_variant":[
        "\u304b\u3044\u304c\u3093\u3061\u3087\u3046",
        "\u30ab\u30a4\u30ac\u30f3\u30c1\u30e7\u30a6"
    ],
    "name:und_x_variant":[
        "Kaiganch\u014d"
    ],
    "wof:name":"Kaigancho",
    "wof:placetype":"locality"
},
  "geometry": {"coordinates":[145.58760000000001,43.34124],"type":"Point"}
}