{
  "type": "Feature",
  "properties": {
    "gn:admin1_code":"21.0",
    "gn:admin2_code":"7413150.0",
    "gn:asciiname":"Obaru",
    "gn:country_code":"JP",
    "gn:dem":19,
    "gn:feature_class":"P",
    "gn:feature_code":"PPL",
    "gn:name":"Obaru",
    "gn:population":0,
    "gn:timezone":"Asia/Tokyo",
    "iso:country":"JP",
    "name:jpn_x_preferred":[
        "\u5c0f\u539f"
    ],
    "name:jpn_x_variant":[
        "\u304a\u3070\u308b",
        "\u30aa\u30d0\u30eb"
    ],
    "wof:name":"Obaru",
    "wof:placetype":"locality"
},
  "geometry": {"coordinates":[130.6601,33.00807],"type":"Point"}
}