{
  "type": "Feature",
  "properties": {
    "gn:admin1_code":"34.0",
    "gn:admin2_code":"1849187.0",
    "gn:admin3_code":"11101.0",
    "gn:asciiname":"Sajikawa",
    "gn:country_code":"JP",
    "gn:dem":12,
    "gn:feature_class":"P",
    "gn:feature_code":"PPL",
    "gn:name":"Sajikawa",
    "gn:population":0,
    "gn:timezone":"Asia/Tokyo",
    "iso:country":"JP",
    "name:jpn_x_preferred":[
        "\u4f50\u77e5\u5ddd"
    ],
    "wof:name":"Sajikawa",
    "wof:placetype":"locality"
},
  "geometry": {"coordinates":[139.58251999999999,35.90266],"type":"Point"}
}