{
  "type": "Feature",
  "properties": {
    "gn:admin1_code":"21.0",
    "gn:admin2_code":"1850743.0",
    "gn:asciiname":"Tensuimachi-takezaki",
    "gn:country_code":"JP",
    "gn:dem":-1,
    "gn:feature_class":"P",
    "gn:feature_code":"PPL",
    "gn:name":"Tensuimachi-takezaki",
    "gn:population":0,
    "gn:timezone":"Asia/Tokyo",
    "iso:country":"JP",
    "name:jpn_x_preferred":[
        "\u5929\u6c34\u753a\u7af9\u5d0e"
    ],
    "name:jpn_x_variant":[
        "\u3066\u3093\u3059\u3044\u307e\u3061\u305f\u3051\u3056\u304d",
        "\u30c6\u30f3\u30b9\u30a4\u30de\u30c1\u30bf\u30b1\u30b6\u30ad"
    ],
    "wof:name":"Tensuimachi-takezaki",
    "wof:placetype":"locality"
},
  "geometry": {"coordinates":[130.57643999999999,32.89027],"type":"Point"}
}