{
  "type": "Feature",
  "properties": {
    "gn:admin1_code":"8.0",
    "gn:admin2_code":"2110958.0",
    "gn:asciiname":"Kitayashiki",
    "gn:country_code":"JP",
    "gn:dem":275,
    "gn:feature_class":"P",
    "gn:feature_code":"PPLL",
    "gn:name":"Kitayashiki",
    "gn:population":0,
    "gn:timezone":"Asia/Tokyo",
    "iso:country":"JP",
    "name:jpn_x_preferred":[
        "\u5317\u5c4b\u6577"
    ],
    "wof:name":"Kitayashiki",
    "wof:placetype":"locality"
},
  "geometry": {"coordinates":[140.31001000000001,37.25451],"type":"Point"}
}