{
  "type": "Feature",
  "properties": {
    "gn:admin1_code":"47",
    "gn:admin2_code":"7415820.0",
    "gn:asciiname":"Sashiki",
    "gn:country_code":"JP",
    "gn:dem":13,
    "gn:feature_class":"P",
    "gn:feature_code":"PPL",
    "gn:name":"Sashiki",
    "gn:population":0,
    "gn:timezone":"Asia/Tokyo",
    "iso:country":"JP",
    "name:jpn_x_preferred":[
        "\u4f50\u6577"
    ],
    "name:jpn_x_variant":[
        "\u4f50\u6577\u753a"
    ],
    "wof:name":"Sashiki",
    "wof:placetype":"locality"
},
  "geometry": {"coordinates":[127.7893,26.1678],"type":"Point"}
}