{
  "type": "Feature",
  "properties": {
    "gn:admin1_code":"28.0",
    "gn:admin2_code":"1863590.0",
    "gn:asciiname":"Kurunocho",
    "gn:country_code":"JP",
    "gn:dem":268,
    "gn:feature_class":"P",
    "gn:feature_code":"PPL",
    "gn:name":"Kurunoch\u014d",
    "gn:population":0,
    "gn:timezone":"Asia/Tokyo",
    "iso:country":"JP",
    "name:jpn_x_preferred":[
        "\u4e45\u7559\u91ce\u753a"
    ],
    "name:und_x_variant":[
        "Kurunoch\u014d"
    ],
    "wof:name":"Kurunocho",
    "wof:placetype":"locality"
},
  "geometry": {"coordinates":[135.69515000000001,34.38438],"type":"Point"}
}