{
  "type": "Feature",
  "properties": {
    "gn:admin1_code":"40.0",
    "gn:admin2_code":"1861322.0",
    "gn:asciiname":"Daimon",
    "gn:country_code":"JP",
    "gn:dem":31,
    "gn:feature_class":"P",
    "gn:feature_code":"PPL",
    "gn:name":"Daimon",
    "gn:population":0,
    "gn:timezone":"Asia/Tokyo",
    "iso:country":"JP",
    "name:jpn_x_preferred":[
        "\u5927\u9580"
    ],
    "wof:name":"Daimon",
    "wof:placetype":"locality"
},
  "geometry": {"coordinates":[139.64932999999999,35.78395],"type":"Point"}
}