{
  "type": "Feature",
  "properties": {
    "iso:country":"JP",
    "name:eng_x_preferred":[
        "Gose City"
    ],
    "name:jpn_x_preferred":[
        "\u5fa1\u6240\u5e02"
    ],
    "qs:name":"\u5fa1\u6240\u5e02",
    "qs:name_adm0":"\u65e5\u672c",
    "qs:name_adm1":"\u5948\u826f\u770c",
    "qs:photos":212,
    "qs:photos_1k":43,
    "qs:photos_9k":1,
    "qs:photos_9r":4,
    "qs:photos_all":223,
    "qs:photos_sr":4,
    "qs:placetype":"Town",
    "qs:pop_sr":"0",
    "wof:name":"Gose City",
    "wof:placetype":"locality"
},
  "geometry": {"coordinates":[135.722824,34.4406965],"type":"Point"}
}