{
  "type": "Feature",
  "properties": {
    "gn:admin1_code":"8.0",
    "gn:admin2_code":"1857203.0",
    "gn:admin3_code":"7368.0",
    "gn:asciiname":"Kanaizawa",
    "gn:country_code":"JP",
    "gn:dem":656,
    "gn:feature_class":"P",
    "gn:feature_code":"PPL",
    "gn:name":"Kanaizawa",
    "gn:population":0,
    "gn:timezone":"Asia/Tokyo",
    "iso:country":"JP",
    "name:jpn_x_preferred":[
        "\u91d1\u4e95\u6ca2"
    ],
    "wof:name":"Kanaizawa",
    "wof:placetype":"locality"
},
  "geometry": {"coordinates":[139.71226999999999,37.20387],"type":"Point"}
}