{
  "type": "Feature",
  "properties": {
    "gn:admin1_code":"3.0",
    "gn:admin2_code":"2130088.0",
    "gn:admin3_code":"2307.0",
    "gn:asciiname":"Kamanosawa",
    "gn:country_code":"JP",
    "gn:dem":14,
    "gn:feature_class":"P",
    "gn:feature_code":"PPL",
    "gn:name":"Kamanosawa",
    "gn:population":0,
    "gn:timezone":"Asia/Tokyo",
    "iso:country":"JP",
    "name:jpn_x_preferred":[
        "\u91dc\u91ce\u6ca2"
    ],
    "name:jpn_x_variant":[
        "\u304b\u307e\u306e\u3055\u308f",
        "\u30ab\u30de\u30ce\u30b5\u30ef"
    ],
    "wof:name":"Kamanosawa",
    "wof:placetype":"locality"
},
  "geometry": {"coordinates":[140.40132,41.22305],"type":"Point"}
}