{
  "type": "Feature",
  "properties": {
    "gn:admin1_code":"4.0",
    "gn:admin2_code":"7465524.0",
    "gn:asciiname":"Misakicho-kamone",
    "gn:country_code":"JP",
    "gn:dem":40,
    "gn:feature_class":"P",
    "gn:feature_code":"PPL",
    "gn:name":"Misakich\u014d-kamone",
    "gn:population":0,
    "gn:timezone":"Asia/Tokyo",
    "iso:country":"JP",
    "name:jpn_x_preferred":[
        "\u5cac\u753a\u9d28\u6839"
    ],
    "name:jpn_x_variant":[
        "\u307f\u3055\u304d\u3061\u3087\u3046\u304b\u3082\u306d",
        "\u30df\u30b5\u30ad\u30c1\u30e7\u30a6\u30ab\u30e2\u30cd"
    ],
    "name:und_x_variant":[
        "Misakich\u014d-kamone"
    ],
    "wof:name":"Misakicho-kamone",
    "wof:placetype":"locality"
},
  "geometry": {"coordinates":[140.35856000000001,35.28648],"type":"Point"}
}