{
  "type": "Feature",
  "properties": {
    "gn:admin1_code":"8.0",
    "gn:admin2_code":"7451503.0",
    "gn:admin3_code":"7344.0",
    "gn:asciiname":"Kuwanayashiki",
    "gn:country_code":"JP",
    "gn:dem":284,
    "gn:feature_class":"P",
    "gn:feature_code":"PPLL",
    "gn:name":"Kuwanayashiki",
    "gn:population":0,
    "gn:timezone":"Asia/Tokyo",
    "iso:country":"JP",
    "name:jpn_x_preferred":[
        "\u6851\u540d\u90b8"
    ],
    "wof:name":"Kuwanayashiki",
    "wof:placetype":"locality"
},
  "geometry": {"coordinates":[140.26283999999998,37.23226],"type":"Point"}
}