{
  "type": "Feature",
  "properties": {
    "gn:admin1_code":"35.0",
    "gn:admin2_code":"1858984.0",
    "gn:asciiname":"Konancho-ichihara",
    "gn:country_code":"JP",
    "gn:dem":169,
    "gn:feature_class":"P",
    "gn:feature_code":"PPL",
    "gn:name":"K\u014dnanch\u014d-ichihara",
    "gn:population":0,
    "gn:timezone":"Asia/Tokyo",
    "iso:country":"JP",
    "name:jpn_x_preferred":[
        "\u7532\u5357\u753a\u5e02\u539f"
    ],
    "name:und_x_variant":[
        "K\u014dnanch\u014d-ichihara"
    ],
    "wof:name":"Konancho-ichihara",
    "wof:placetype":"locality"
},
  "geometry": {"coordinates":[136.15663000000001,34.93455],"type":"Point"}
}