{
  "type": "Feature",
  "properties": {
    "gn:admin1_code":"3.0",
    "gn:admin2_code":"2128302.0",
    "gn:admin3_code":"2441.0",
    "gn:asciiname":"Janumaodai",
    "gn:country_code":"JP",
    "gn:dem":189,
    "gn:feature_class":"P",
    "gn:feature_code":"PPL",
    "gn:name":"Januma\u014ddai",
    "gn:population":0,
    "gn:timezone":"Asia/Tokyo",
    "iso:country":"JP",
    "name:jpn_x_preferred":[
        "\u86c7\u6cbc\u5927\u5e73"
    ],
    "name:jpn_x_variant":[
        "\u3058\u3083\u306c\u307e\u304a\u304a\u3060\u3044",
        "\u30b8\u30e3\u30cc\u30de\u30aa\u30aa\u30c0\u30a4"
    ],
    "name:und_x_variant":[
        "Januma\u014ddai"
    ],
    "wof:name":"Janumaodai",
    "wof:placetype":"locality"
},
  "geometry": {"coordinates":[141.19432,40.4146],"type":"Point"}
}