{
  "type": "Feature",
  "properties": {
    "gn:admin1_code":"37",
    "gn:admin2_code":"1854900.0",
    "gn:asciiname":"Shishihama",
    "gn:cc2":"JP",
    "gn:country_code":"JP",
    "gn:dem":4,
    "gn:feature_class":"P",
    "gn:feature_code":"PPL",
    "gn:name":"Shishihama",
    "gn:population":0,
    "gn:timezone":"Asia/Tokyo",
    "iso:country":"JP",
    "name:und_x_variant":[
        "E-no-ura",
        "Shishihama"
    ],
    "wof:name":"Shishihama",
    "wof:placetype":"locality"
},
  "geometry": {"coordinates":[138.88423999999998,35.05427],"type":"Point"}
}