{
  "type": "Feature",
  "properties": {
    "gn:admin1_code":"40.0",
    "gn:admin2_code":"1864514.0",
    "gn:asciiname":"Somechi",
    "gn:country_code":"JP",
    "gn:dem":34,
    "gn:feature_class":"P",
    "gn:feature_code":"PPL",
    "gn:name":"Somechi",
    "gn:population":0,
    "gn:timezone":"Asia/Tokyo",
    "iso:country":"JP",
    "name:jpn_x_preferred":[
        "\u67d3\u5730"
    ],
    "wof:name":"Somechi",
    "wof:placetype":"locality"
},
  "geometry": {"coordinates":[139.55226999999999,35.64103],"type":"Point"}
}