{
  "type": "Feature",
  "properties": {
    "gn:admin1_code":"46.0",
    "gn:admin2_code":"1864076.0",
    "gn:asciiname":"Shiroyama-higashi",
    "gn:country_code":"JP",
    "gn:dem":850,
    "gn:feature_class":"P",
    "gn:feature_code":"PPLL",
    "gn:name":"Shiroyama-higashi",
    "gn:population":0,
    "gn:timezone":"Asia/Tokyo",
    "iso:country":"JP",
    "name:jpn_x_preferred":[
        "\u57ce\u5c71\u6771"
    ],
    "wof:name":"Shiroyama-higashi",
    "wof:placetype":"locality"
},
  "geometry": {"coordinates":[138.80374,35.46637],"type":"Point"}
}