{
  "type": "Feature",
  "properties": {
    "gn:admin1_code":"34",
    "gn:admin2_code":"1849187.0",
    "gn:admin3_code":"11107.0",
    "gn:asciiname":"Tokiwa",
    "gn:country_code":"JP",
    "gn:dem":17,
    "gn:feature_class":"P",
    "gn:feature_code":"PPL",
    "gn:name":"Tokiwa",
    "gn:population":0,
    "gn:timezone":"Asia/Tokyo",
    "iso:country":"JP",
    "name:jpn_x_preferred":[
        "\u5e38\u76e4"
    ],
    "name:jpn_x_variant":[
        "\u3068\u304d\u308f",
        "\u30c8\u30ad\u30ef"
    ],
    "name:spa_x_preferred":[
        "Tokiwa"
    ],
    "name:und_x_variant":[
        "Tokiwach\u014d"
    ],
    "wof:name":"Tokiwa",
    "wof:placetype":"locality"
},
  "geometry": {"coordinates":[139.64642000000001,35.86758],"type":"Point"}
}