{
  "type": "Feature",
  "properties": {
    "gn:admin1_code":"19.0",
    "gn:admin2_code":"1848308.0",
    "gn:asciiname":"Yamanakacho",
    "gn:country_code":"JP",
    "gn:dem":96,
    "gn:feature_class":"P",
    "gn:feature_code":"PPL",
    "gn:name":"Yamanakach\u014d",
    "gn:population":0,
    "gn:timezone":"Asia/Tokyo",
    "iso:country":"JP",
    "name:jpn_x_preferred":[
        "\u5c71\u4e2d\u753a"
    ],
    "name:jpn_x_variant":[
        "\u3084\u307e\u306a\u304b\u3061\u3087\u3046",
        "\u30e4\u30de\u30ca\u30ab\u30c1\u30e7\u30a6"
    ],
    "name:und_x_variant":[
        "Yamanakach\u014d"
    ],
    "wof:name":"Yamanakacho",
    "wof:placetype":"locality"
},
  "geometry": {"coordinates":[139.63630000000001,35.27724],"type":"Point"}
}