{
  "type": "Feature",
  "properties": {
    "gn:admin1_code":"37.0",
    "gn:admin2_code":"1864089.0",
    "gn:asciiname":"Atsuharahigashi",
    "gn:country_code":"JP",
    "gn:dem":58,
    "gn:feature_class":"P",
    "gn:feature_code":"PPLL",
    "gn:name":"Atsuharahigashi",
    "gn:population":0,
    "gn:timezone":"Asia/Tokyo",
    "iso:country":"JP",
    "name:jpn_x_preferred":[
        "\u539a\u539f\u6771"
    ],
    "wof:name":"Atsuharahigashi",
    "wof:placetype":"locality"
},
  "geometry": {"coordinates":[138.66557,35.18172],"type":"Point"}
}