{
  "type": "Feature",
  "properties": {
    "gn:admin1_code":"4.0",
    "gn:admin2_code":"7465524.0",
    "gn:asciiname":"Higashiyatsu",
    "gn:country_code":"JP",
    "gn:dem":20,
    "gn:feature_class":"P",
    "gn:feature_code":"PPLL",
    "gn:name":"Higashiyatsu",
    "gn:population":0,
    "gn:timezone":"Asia/Tokyo",
    "iso:country":"JP",
    "name:jpn_x_preferred":[
        "\u6771\u8c37"
    ],
    "name:jpn_x_variant":[
        "\u3072\u304c\u3057\u3084\u3064",
        "\u30d2\u30ac\u30b7\u30e4\u30c4"
    ],
    "wof:name":"Higashiyatsu",
    "wof:placetype":"locality"
},
  "geometry": {"coordinates":[140.29251000000002,35.30255],"type":"Point"}
}