{
  "type": "Feature",
  "properties": {
    "gn:admin1_code":"09",
    "gn:admin2_code":"1863645.0",
    "gn:asciiname":"Wada",
    "gn:cc2":"JP",
    "gn:country_code":"JP",
    "gn:dem":372,
    "gn:feature_class":"P",
    "gn:feature_code":"PPL",
    "gn:name":"Wada",
    "gn:population":0,
    "gn:timezone":"Asia/Tokyo",
    "iso:country":"JP",
    "name:ceb_x_preferred":[
        "Wada"
    ],
    "name:deu_x_preferred":[
        "Wada"
    ],
    "name:fra_x_preferred":[
        "Wada"
    ],
    "name:mar_x_preferred":[
        "\u0935\u093e\u0921\u093e"
    ],
    "name:pol_x_preferred":[
        "Wada"
    ],
    "name:rus_x_preferred":[
        "\u0412\u0430\u0434\u0430"
    ],
    "name:swe_x_preferred":[
        "Wada"
    ],
    "name:und_x_variant":[
        "Kirihora"
    ],
    "wof:name":"Wada",
    "wof:placetype":"locality"
},
  "geometry": {"coordinates":[137.11667,35.65],"type":"Point"}
}