{
  "type": "Feature",
  "properties": {
    "gn:admin1_code":"12.0",
    "gn:admin2_code":"7428079.0",
    "gn:admin3_code":"1647.0",
    "gn:asciiname":"Rawan",
    "gn:country_code":"JP",
    "gn:dem":168,
    "gn:feature_class":"P",
    "gn:feature_code":"PPL",
    "gn:name":"Rawan",
    "gn:population":0,
    "gn:timezone":"Asia/Tokyo",
    "iso:country":"JP",
    "name:jpn_x_preferred":[
        "\u87ba\u6e7e"
    ],
    "name:jpn_x_variant":[
        "\u3089\u308f\u3093",
        "\u30e9\u30ef\u30f3"
    ],
    "wof:name":"Rawan",
    "wof:placetype":"locality"
},
  "geometry": {"coordinates":[143.70616999999999,43.31414],"type":"Point"}
}