{
  "type": "Feature",
  "properties": {
    "gn:admin1_code":"05",
    "gn:asciiname":"Iwagi",
    "gn:cc2":"JP",
    "gn:country_code":"JP",
    "gn:dem":-9999,
    "gn:feature_class":"P",
    "gn:feature_code":"PPL",
    "gn:name":"Iwagi",
    "gn:population":0,
    "gn:timezone":"Asia/Tokyo",
    "iso:country":"JP",
    "name:jpn_x_preferred":[
        "\u5ca9\u57ce\u6751"
    ],
    "name:spa_x_preferred":[
        "Iwagi"
    ],
    "name:und_x_variant":[
        "Iwaki",
        "Iwagi"
    ],
    "wof:name":"Iwagi",
    "wof:placetype":"locality"
},
  "geometry": {"coordinates":[133.15000000000001,34.23639],"type":"Point"}
}