{
  "type": "Feature",
  "properties": {
    "gn:admin1_code":"37.0",
    "gn:admin2_code":"1864089.0",
    "gn:asciiname":"Murono",
    "gn:country_code":"JP",
    "gn:dem":223,
    "gn:feature_class":"P",
    "gn:feature_code":"PPLL",
    "gn:name":"Murono",
    "gn:population":0,
    "gn:timezone":"Asia/Tokyo",
    "iso:country":"JP",
    "name:jpn_x_preferred":[
        "\u5ba4\u91ce"
    ],
    "wof:name":"Murono",
    "wof:placetype":"locality"
},
  "geometry": {"coordinates":[138.60792000000001,35.16625],"type":"Point"}
}