{
  "type": "Feature",
  "properties": {
    "gn:admin1_code":"30",
    "gn:admin2_code":"1853234.0",
    "gn:asciiname":"Inokushiura",
    "gn:country_code":"JP",
    "gn:dem":21,
    "gn:feature_class":"P",
    "gn:feature_code":"PPL",
    "gn:name":"Inokushiura",
    "gn:population":0,
    "gn:timezone":"Asia/Tokyo",
    "iso:country":"JP",
    "name:jpn_x_preferred":[
        "\u732a\u4e32\u6d66"
    ],
    "name:und_x_variant":[
        "Ikushi",
        "Inokushi",
        "Inokushiura"
    ],
    "wof:name":"Inokushiura",
    "wof:placetype":"locality"
},
  "geometry": {"coordinates":[131.90164999999999,32.80096],"type":"Point"}
}