{
  "type": "Feature",
  "properties": {
    "gn:admin1_code":"4.0",
    "gn:admin2_code":"7465524.0",
    "gn:asciiname":"Kobako",
    "gn:country_code":"JP",
    "gn:dem":18,
    "gn:feature_class":"P",
    "gn:feature_code":"PPLL",
    "gn:name":"Kobako",
    "gn:population":0,
    "gn:timezone":"Asia/Tokyo",
    "iso:country":"JP",
    "name:jpn_x_preferred":[
        "\u5c0f\u7bb1"
    ],
    "name:jpn_x_variant":[
        "\u3053\u3070\u3053",
        "\u30b3\u30d0\u30b3"
    ],
    "wof:name":"Kobako",
    "wof:placetype":"locality"
},
  "geometry": {"coordinates":[140.34519,35.27598],"type":"Point"}
}