{
  "type": "Feature",
  "properties": {
    "gn:admin1_code":"3.0",
    "gn:admin2_code":"2130200.0",
    "gn:asciiname":"Ichikawa",
    "gn:country_code":"JP",
    "gn:dem":5,
    "gn:feature_class":"P",
    "gn:feature_code":"PPL",
    "gn:name":"Ichikawa",
    "gn:population":0,
    "gn:timezone":"Asia/Tokyo",
    "iso:country":"JP",
    "name:jpn_x_preferred":[
        "\u5e02\u5ddd"
    ],
    "name:jpn_x_variant":[
        "\u3044\u3061\u304b\u308f",
        "\u30a4\u30c1\u30ab\u30ef"
    ],
    "wof:name":"Ichikawa",
    "wof:placetype":"locality"
},
  "geometry": {"coordinates":[141.44999999999999,40.58333],"type":"Point"}
}