{
  "type": "Feature",
  "properties": {
    "gn:admin1_code":"33.0",
    "gn:admin2_code":"7391358.0",
    "gn:admin3_code":"41424.0",
    "gn:asciiname":"Yamaguchi",
    "gn:country_code":"JP",
    "gn:dem":41,
    "gn:feature_class":"P",
    "gn:feature_code":"PPL",
    "gn:name":"Yamaguchi",
    "gn:population":0,
    "gn:timezone":"Asia/Tokyo",
    "iso:country":"JP",
    "name:jpn_x_preferred":[
        "\u5c71\u53e3"
    ],
    "wof:name":"Yamaguchi",
    "wof:placetype":"locality"
},
  "geometry": {"coordinates":[130.14721,33.23474],"type":"Point"}
}