{
  "type": "Feature",
  "properties": {
    "gn:admin1_code":"44.0",
    "gn:admin2_code":"2111850.0",
    "gn:admin3_code":"6364.0",
    "gn:asciiname":"Uchimachi",
    "gn:country_code":"JP",
    "gn:dem":75,
    "gn:feature_class":"P",
    "gn:feature_code":"PPL",
    "gn:name":"Uchimachi",
    "gn:population":0,
    "gn:timezone":"Asia/Tokyo",
    "iso:country":"JP",
    "name:jpn_x_preferred":[
        "\u5185\u753a"
    ],
    "wof:name":"Uchimachi",
    "wof:placetype":"locality"
},
  "geometry": {"coordinates":[140.24278000000001,38.85028],"type":"Point"}
}