{
  "type": "Feature",
  "properties": {
    "gn:admin1_code":"40.0",
    "gn:admin2_code":"1852582.0",
    "gn:asciiname":"Sakuragaokacho",
    "gn:country_code":"JP",
    "gn:dem":46,
    "gn:feature_class":"P",
    "gn:feature_code":"PPL",
    "gn:name":"Sakuragaokach\u014d",
    "gn:population":0,
    "gn:timezone":"Asia/Tokyo",
    "iso:country":"JP",
    "name:jpn_x_preferred":[
        "\u685c\u4e18\u753a"
    ],
    "name:und_x_variant":[
        "Sakuragaokach\u014d"
    ],
    "wof:name":"Sakuragaokacho",
    "wof:placetype":"locality"
},
  "geometry": {"coordinates":[139.70129,35.65578],"type":"Point"}
}