{
  "type": "Feature",
  "properties": {
    "gn:admin1_code":"4.0",
    "gn:admin2_code":"1864901.0",
    "gn:admin3_code":"12463.0",
    "gn:asciiname":"Ezukikami",
    "gn:country_code":"JP",
    "gn:dem":111,
    "gn:feature_class":"P",
    "gn:feature_code":"PPLL",
    "gn:name":"Ezukikami",
    "gn:population":0,
    "gn:timezone":"Asia/Tokyo",
    "iso:country":"JP",
    "name:jpn_x_preferred":[
        "\u6c5f\u6708\u4e0a"
    ],
    "name:jpn_x_variant":[
        "\u3048\u3065\u304d\u304b\u307f",
        "\u30a8\u30c5\u30ad\u30ab\u30df"
    ],
    "wof:name":"Ezukikami",
    "wof:placetype":"locality"
},
  "geometry": {"coordinates":[139.86600000000001,35.13147],"type":"Point"}
}