{
  "type": "Feature",
  "properties": {
    "gn:admin1_code":"27.0",
    "gn:admin2_code":"1862734.0",
    "gn:admin3_code":"42321.0",
    "gn:asciiname":"Kaburago",
    "gn:country_code":"JP",
    "gn:dem":343,
    "gn:feature_class":"P",
    "gn:feature_code":"PPL",
    "gn:name":"Kaburag\u014d",
    "gn:population":0,
    "gn:timezone":"Asia/Tokyo",
    "iso:country":"JP",
    "name:jpn_x_preferred":[
        "\u856a\u90f7"
    ],
    "name:und_x_variant":[
        "Kaburag\u014d"
    ],
    "wof:name":"Kaburago",
    "wof:placetype":"locality"
},
  "geometry": {"coordinates":[129.97909000000001,33.00496],"type":"Point"}
}