{
  "type": "Feature",
  "properties": {
    "gn:admin1_code":"21.0",
    "gn:admin2_code":"7412709.0",
    "gn:admin3_code":"43348.0",
    "gn:asciiname":"Zei",
    "gn:country_code":"JP",
    "gn:dem":297,
    "gn:feature_class":"P",
    "gn:feature_code":"PPLL",
    "gn:name":"Zei",
    "gn:population":0,
    "gn:timezone":"Asia/Tokyo",
    "iso:country":"JP",
    "name:jpn_x_preferred":[
        "\u52e2\u4e95"
    ],
    "name:jpn_x_variant":[
        "\u305c\u3044",
        "\u30bc\u30a4"
    ],
    "wof:name":"Zei",
    "wof:placetype":"locality"
},
  "geometry": {"coordinates":[130.93943999999999,32.64445],"type":"Point"}
}