{
  "type": "Feature",
  "properties": {
    "gn:admin1_code":"06",
    "gn:admin2_code":"1854517.0",
    "gn:admin3_code":"18483.0",
    "gn:asciiname":"Hongo",
    "gn:country_code":"JP",
    "gn:dem":2,
    "gn:feature_class":"P",
    "gn:feature_code":"PPL",
    "gn:name":"Hong\u014d",
    "gn:population":0,
    "gn:timezone":"Asia/Tokyo",
    "iso:country":"JP",
    "wof:name":"Hongo",
    "wof:placetype":"locality"
},
  "geometry": {"coordinates":[135.61935,35.48206],"type":"Point"}
}