{
  "type": "Feature",
  "properties": {
    "gn:admin1_code":"7.0",
    "gn:admin2_code":"1851269.0",
    "gn:admin3_code":"40608.0",
    "gn:asciiname":"Shimomotomatsu",
    "gn:country_code":"JP",
    "gn:dem":49,
    "gn:feature_class":"P",
    "gn:feature_code":"PPLL",
    "gn:name":"Shimomotomatsu",
    "gn:population":0,
    "gn:timezone":"Asia/Tokyo",
    "iso:country":"JP",
    "name:jpn_x_preferred":[
        "\u4e0b\u5143\u677e"
    ],
    "wof:name":"Shimomotomatsu",
    "wof:placetype":"locality"
},
  "geometry": {"coordinates":[130.85221000000001,33.59299],"type":"Point"}
}