{
  "type": "Feature",
  "properties": {
    "gn:admin1_code":"11",
    "gn:admin2_code":"1850858.0",
    "gn:asciiname":"Takasaki",
    "gn:country_code":"JP",
    "gn:dem":30,
    "gn:feature_class":"P",
    "gn:feature_code":"PPL",
    "gn:name":"Takasaki",
    "gn:population":0,
    "gn:timezone":"Asia/Tokyo",
    "iso:country":"JP",
    "name:ara_x_preferred":[
        "\u062a\u0627\u0643\u0627\u0633\u0627\u0643\u064a"
    ],
    "name:azb_x_preferred":[
        "\u062a\u0627\u06a9\u0627\u0633\u0627\u06a9\u06cc"
    ],
    "name:aze_x_preferred":[
        "Takasaki"
    ],
    "name:bak_x_preferred":[
        "\u0422\u0430\u043a\u0430\u0441\u0430\u043a\u0438"
    ],
    "name:bul_x_preferred":[
        "\u0422\u0430\u043a\u0430\u0441\u0430\u043a\u0438"
    ],
    "name:ces_x_preferred":[
        "Takasaki"
    ],
    "name:dan_x_preferred":[
        "Takasaki"
    ],
    "name:deu_x_preferred":[
        "Takasaki"
    ],
    "name:eus_x_preferred":[
        "Takasaki"
    ],
    "name:fas_x_preferred":[
        "\u062a\u0627\u06a9\u0627\u0633\u0627\u06a9\u06cc"
    ],
    "name:fin_x_preferred":[
        "Takasaki"
    ],
    "name:fra_x_preferred":[
        "Takasaki"
    ],
    "name:gle_x_preferred":[
        "Takasaki"
    ],
    "name:glg_x_preferred":[
        "Takasaki"
    ],
    "name:hye_x_preferred":[
        "\u054f\u0561\u056f\u0561\u057d\u0561\u056f\u056b"
    ],
    "name:ind_x_preferred":[
        "Takasaki"
    ],
    "name:ita_x_preferred":[
        "Takasaki"
    ],
    "name:jpn_x_preferred":[
        "\u9ad8\u5d0e\u5e02"
    ],
    "name:kat_x_preferred":[
        "\u10e2\u10d0\u10d9\u10d0\u10e1\u10d0\u10d9\u10d8"
    ],
    "name:kor_x_preferred":[
        "\ub2e4\uce74\uc0ac\ud0a4\uc2dc"
    ],
    "name:mlg_x_preferred":[
        "Takasaki"
    ],
    "name:msa_x_preferred":[
        "Takasaki"
    ],
    "name:mzn_x_preferred":[
        "\u062a\u0627\u06a9\u0627\u0633\u0627\u06a9\u06cc"
    ],
    "name:nld_x_preferred":[
        "Takasaki"
    ],
    "name:nor_x_preferred":[
        "Takasaki"
    ],
    "name:pol_x_preferred":[
        "Takasaki"
    ],
    "name:por_x_preferred":[
        "Takasaki"
    ],
    "name:ron_x_preferred":[
        "Takasaki"
    ],
    "name:rus_x_preferred":[
        "\u0422\u0430\u043a\u0430\u0441\u0430\u043a\u0438"
    ],
    "name:sco_x_preferred":[
        "Takasaki"
    ],
    "name:spa_x_preferred":[
        "Takasaki"
    ],
    "name:srp_x_preferred":[
        "\u0422\u0430\u043a\u0430\u0441\u0430\u043a\u0438"
    ],
    "name:swe_x_preferred":[
        "Takasaki"
    ],
    "name:tgk_x_preferred":[
        "\u0422\u0430\u043a\u0430\u0441\u0430\u043a\u0438"
    ],
    "name:tgl_x_preferred":[
        "Takasaki"
    ],
    "name:tha_x_preferred":[
        "\u0e17\u0e32\u0e01\u0e32\u0e0b\u0e32\u0e01\u0e34"
    ],
    "name:tum_x_preferred":[
        "Takasaki"
    ],
    "name:tur_x_preferred":[
        "Takasaki"
    ],
    "name:ukr_x_preferred":[
        "\u0422\u0430\u043a\u0430\u0441\u0430\u043a\u0456"
    ],
    "name:urd_x_preferred":[
        "\u062a\u0627\u06a9\u0627\u0633\u0627\u06a9\u06cc"
    ],
    "name:vie_x_preferred":[
        "Takasaki"
    ],
    "name:war_x_preferred":[
        "Takasaki"
    ],
    "name:zho_x_preferred":[
        "\u9ad8\u5d0e\u5e02"
    ],
    "wof:name":"Takasaki",
    "wof:placetype":"locality"
},
  "geometry": {"coordinates":[132.93333000000001,34.33333],"type":"Point"}
}