{
  "type": "Feature",
  "properties": {
    "gn:admin1_code":"44.0",
    "gn:admin2_code":"1849562.0",
    "gn:asciiname":"Koiwagawa",
    "gn:country_code":"JP",
    "gn:dem":8,
    "gn:feature_class":"P",
    "gn:feature_code":"PPL",
    "gn:name":"Koiwagawa",
    "gn:population":0,
    "gn:timezone":"Asia/Tokyo",
    "iso:country":"JP",
    "name:jpn_x_preferred":[
        "\u5c0f\u5ca9\u5ddd"
    ],
    "wof:name":"Koiwagawa",
    "wof:placetype":"locality"
},
  "geometry": {"coordinates":[139.56572,38.59124],"type":"Point"}
}