{
  "type": "Feature",
  "properties": {
    "gn:admin1_code":"34.0",
    "gn:admin2_code":"1863058.0",
    "gn:asciiname":"Nokubo",
    "gn:country_code":"JP",
    "gn:dem":12,
    "gn:feature_class":"P",
    "gn:feature_code":"PPLL",
    "gn:name":"Nokubo",
    "gn:population":0,
    "gn:timezone":"Asia/Tokyo",
    "iso:country":"JP",
    "name:jpn_x_preferred":[
        "\u91ce\u4e45\u4fdd"
    ],
    "name:jpn_x_variant":[
        "\u306e\u304f\u307c",
        "\u30ce\u30af\u30dc"
    ],
    "wof:name":"Nokubo",
    "wof:placetype":"locality"
},
  "geometry": {"coordinates":[139.64829,35.99269],"type":"Point"}
}