{
  "type": "Feature",
  "properties": {
    "gn:admin1_code":"2.0",
    "gn:admin2_code":"2113122.0",
    "gn:asciiname":"Shimokitate-torisawa",
    "gn:country_code":"JP",
    "gn:dem":19,
    "gn:feature_class":"P",
    "gn:feature_code":"PPL",
    "gn:name":"Shimokitate-t\u014drisawa",
    "gn:population":0,
    "gn:timezone":"Asia/Tokyo",
    "iso:country":"JP",
    "name:jpn_x_preferred":[
        "\u4e0b\u5317\u624b\u901a\u6ca2"
    ],
    "name:jpn_x_variant":[
        "\u3057\u3082\u304d\u305f\u3066\u3068\u304a\u308a\u3055\u308f",
        "\u30b7\u30e2\u30ad\u30bf\u30c6\u30c8\u30aa\u30ea\u30b5\u30ef",
        "\u901a\u6ca2"
    ],
    "name:und_x_variant":[
        "Shimokitate-t\u014drisawa",
        "T\u014drisawa"
    ],
    "wof:name":"Shimokitate-torisawa",
    "wof:placetype":"locality"
},
  "geometry": {"coordinates":[140.18571,39.71159],"type":"Point"}
}