{
  "type": "Feature",
  "properties": {
    "gn:admin1_code":"21.0",
    "gn:admin2_code":"1864975.0",
    "gn:admin3_code":"43424.0",
    "gn:asciiname":"Handa",
    "gn:country_code":"JP",
    "gn:dem":412,
    "gn:feature_class":"P",
    "gn:feature_code":"PPLL",
    "gn:name":"Handa",
    "gn:population":0,
    "gn:timezone":"Asia/Tokyo",
    "iso:country":"JP",
    "name:jpn_x_preferred":[
        "\u571f\u7530"
    ],
    "name:jpn_x_variant":[
        "\u306f\u3093\u3060",
        "\u30cf\u30f3\u30c0"
    ],
    "wof:name":"Handa",
    "wof:placetype":"locality"
},
  "geometry": {"coordinates":[131.06122999999999,33.13365],"type":"Point"}
}