{
  "type": "Feature",
  "properties": {
    "gn:admin1_code":"21.0",
    "gn:admin2_code":"1850744.0",
    "gn:admin3_code":"43368.0",
    "gn:asciiname":"Akada",
    "gn:country_code":"JP",
    "gn:dem":23,
    "gn:feature_class":"P",
    "gn:feature_code":"PPLL",
    "gn:name":"Akada",
    "gn:population":0,
    "gn:timezone":"Asia/Tokyo",
    "iso:country":"JP",
    "name:jpn_x_preferred":[
        "\u8d64\u7530"
    ],
    "name:jpn_x_variant":[
        "\u3042\u304b\u3060",
        "\u30a2\u30ab\u30c0"
    ],
    "wof:name":"Akada",
    "wof:placetype":"locality"
},
  "geometry": {"coordinates":[130.48031,32.94813],"type":"Point"}
}