{
  "type": "Feature",
  "properties": {
    "gn:admin1_code":"23",
    "gn:admin2_code":"1848873.0",
    "gn:admin3_code":"24461.0",
    "gn:asciiname":"Shimo-uni",
    "gn:country_code":"JP",
    "gn:dem":34,
    "gn:feature_class":"P",
    "gn:feature_code":"PPL",
    "gn:name":"Shimo-uni",
    "gn:population":0,
    "gn:timezone":"Asia/Tokyo",
    "iso:country":"JP",
    "wof:name":"Shimo-uni",
    "wof:placetype":"locality"
},
  "geometry": {"coordinates":[136.65000000000001,34.51667],"type":"Point"}
}