{
  "type": "Feature",
  "properties": {
    "gn:admin1_code":"21.0",
    "gn:admin2_code":"1865358.0",
    "gn:asciiname":"Sazuki",
    "gn:country_code":"JP",
    "gn:dem":10,
    "gn:feature_class":"P",
    "gn:feature_code":"PPLL",
    "gn:name":"Sazuki",
    "gn:population":0,
    "gn:timezone":"Asia/Tokyo",
    "iso:country":"JP",
    "name:jpn_x_preferred":[
        "\u7802\u6708"
    ],
    "name:jpn_x_variant":[
        "\u3055\u3065\u304d",
        "\u30b5\u30c5\u30ad"
    ],
    "wof:name":"Sazuki",
    "wof:placetype":"locality"
},
  "geometry": {"coordinates":[130.02966000000001,32.17604],"type":"Point"}
}