{
  "type": "Feature",
  "properties": {
    "gn:admin1_code":"29.0",
    "gn:admin2_code":"1856195.0",
    "gn:asciiname":"Onuma-shinden",
    "gn:country_code":"JP",
    "gn:dem":10,
    "gn:feature_class":"P",
    "gn:feature_code":"PPL",
    "gn:name":"\u014cnuma-shinden",
    "gn:population":0,
    "gn:timezone":"Asia/Tokyo",
    "iso:country":"JP",
    "name:jpn_x_preferred":[
        "\u5927\u6cbc\u65b0\u7530"
    ],
    "name:und_x_variant":[
        "\u014cnuma-shinden"
    ],
    "wof:name":"Onuma-shinden",
    "wof:placetype":"locality"
},
  "geometry": {"coordinates":[138.87814,37.60535],"type":"Point"}
}