{
  "type": "Feature",
  "properties": {
    "gn:admin1_code":"19.0",
    "gn:admin2_code":"1848595.0",
    "gn:asciiname":"Shimosoyagi",
    "gn:country_code":"JP",
    "gn:dem":58,
    "gn:feature_class":"P",
    "gn:feature_code":"PPL",
    "gn:name":"Shimos\u014dyagi",
    "gn:population":0,
    "gn:timezone":"Asia/Tokyo",
    "iso:country":"JP",
    "name:jpn_x_preferred":[
        "\u4e0b\u8349\u67f3"
    ],
    "name:und_x_variant":[
        "Shimos\u014dyagi"
    ],
    "wof:name":"Shimosoyagi",
    "wof:placetype":"locality"
},
  "geometry": {"coordinates":[139.45063999999999,35.47089000000001],"type":"Point"}
}