{
  "type": "Feature",
  "properties": {
    "gn:admin1_code":"32.0",
    "gn:admin2_code":"1861089.0",
    "gn:asciiname":"Butsunamicho",
    "gn:country_code":"JP",
    "gn:dem":157,
    "gn:feature_class":"P",
    "gn:feature_code":"PPL",
    "gn:name":"Butsunamich\u014d",
    "gn:population":0,
    "gn:timezone":"Asia/Tokyo",
    "iso:country":"JP",
    "name:jpn_x_preferred":[
        "\u4ecf\u4e26\u753a"
    ],
    "name:und_x_variant":[
        "Butsunamich\u014d"
    ],
    "wof:name":"Butsunamicho",
    "wof:placetype":"locality"
},
  "geometry": {"coordinates":[135.48560000000001,34.42157],"type":"Point"}
}