{
  "type": "Feature",
  "properties": {
    "gn:admin1_code":"24.0",
    "gn:admin2_code":"7447001.0",
    "gn:asciiname":"Tajiri-kitakogota",
    "gn:country_code":"JP",
    "gn:dem":10,
    "gn:feature_class":"P",
    "gn:feature_code":"PPL",
    "gn:name":"Tajiri-kitakogota",
    "gn:population":0,
    "gn:timezone":"Asia/Tokyo",
    "iso:country":"JP",
    "name:jpn_x_preferred":[
        "\u7530\u5c3b\u5317\u5c0f\u725b\u7530"
    ],
    "wof:name":"Tajiri-kitakogota",
    "wof:placetype":"locality"
},
  "geometry": {"coordinates":[141.07968,38.56597],"type":"Point"}
}