{
  "type": "Feature",
  "properties": {
    "gn:admin1_code":"47",
    "gn:admin2_code":"1855990.0",
    "gn:admin3_code":"47329.0",
    "gn:asciiname":"Onaha",
    "gn:country_code":"JP",
    "gn:dem":8,
    "gn:feature_class":"P",
    "gn:feature_code":"PPL",
    "gn:name":"Onaha",
    "gn:population":0,
    "gn:timezone":"Asia/Tokyo",
    "iso:country":"JP",
    "name:jpn_x_preferred":[
        "\u5c0f\u90a3\u8987"
    ],
    "name:und_x_variant":[
        "Komaha",
        "Unafuwa",
        "Konaha",
        "Unaha",
        "Onaha"
    ],
    "wof:name":"Onaha",
    "wof:placetype":"locality"
},
  "geometry": {"coordinates":[127.76936000000001,26.22221],"type":"Point"}
}