{
  "type": "Feature",
  "properties": {
    "gn:admin1_code":"21.0",
    "gn:admin2_code":"1865358.0",
    "gn:asciiname":"Nakayama",
    "gn:country_code":"JP",
    "gn:dem":113,
    "gn:feature_class":"P",
    "gn:feature_code":"PPLL",
    "gn:name":"Nakayama",
    "gn:population":0,
    "gn:timezone":"Asia/Tokyo",
    "iso:country":"JP",
    "name:jpn_x_preferred":[
        "\u4e2d\u5c71"
    ],
    "name:jpn_x_variant":[
        "\u306a\u304b\u3084\u307e",
        "\u30ca\u30ab\u30e4\u30de"
    ],
    "wof:name":"Nakayama",
    "wof:placetype":"locality"
},
  "geometry": {"coordinates":[130.15899999999999,32.38509000000001],"type":"Point"}
}