{
  "type": "Feature",
  "properties": {
    "gn:admin1_code":"13.0",
    "gn:admin2_code":"7370811.0",
    "gn:asciiname":"Hosokawacho-nakazato",
    "gn:country_code":"JP",
    "gn:dem":112,
    "gn:feature_class":"P",
    "gn:feature_code":"PPL",
    "gn:name":"Hosokawach\u014d-nakazato",
    "gn:population":0,
    "gn:timezone":"Asia/Tokyo",
    "iso:country":"JP",
    "name:jpn_x_preferred":[
        "\u7d30\u5ddd\u753a\u4e2d\u91cc"
    ],
    "name:und_x_variant":[
        "Hosokawach\u014d-nakazato"
    ],
    "wof:name":"Hosokawacho-nakazato",
    "wof:placetype":"locality"
},
  "geometry": {"coordinates":[135.06604999999999,34.8355],"type":"Point"}
}