{
  "type": "Feature",
  "properties": {
    "gn:country":"JP",
    "gn:fcode":"ADM3",
    "gn:population":0,
    "iso:country":"JP",
    "name:eng_x_preferred":[
        "Nozawaonsen"
    ],
    "name:eng_x_variant":[
        "Nozawaonsen-mura"
    ],
    "name:jpn_x_preferred":[
        "\u91ce\u6ca2\u6e29\u6cc9\u6751"
    ],
    "name:jpn_x_variant":[
        "\u306e\u3056\u308f\u304a\u3093\u305b\u3093\u3080\u3089"
    ],
    "name:und_x_variant":[
        "Nozawa-onsen Mura"
    ],
    "qs:name":"Nozawaonsen-mura",
    "qs:photos_9r":0,
    "qs:photos_sr":0,
    "qs:pop_sr":"0",
    "wof:name":"Nozawaonsen",
    "wof:placetype":"localadmin",
    "wof:population":0
},
  "geometry": {"coordinates":[138.46706,36.93151],"type":"Point"}
}