{
  "type": "Feature",
  "properties": {
    "gn:admin1_code":"35.0",
    "gn:admin2_code":"1858984.0",
    "gn:asciiname":"Kokacho-ohara-ueda",
    "gn:country_code":"JP",
    "gn:dem":254,
    "gn:feature_class":"P",
    "gn:feature_code":"PPL",
    "gn:name":"K\u014dkach\u014d-\u014dhara-ueda",
    "gn:population":0,
    "gn:timezone":"Asia/Tokyo",
    "iso:country":"JP",
    "name:jpn_x_preferred":[
        "\u7532\u8cc0\u753a\u5927\u539f\u4e0a\u7530"
    ],
    "name:und_x_variant":[
        "K\u014dkach\u014d-\u014dhara-ueda"
    ],
    "wof:name":"Kokacho-ohara-ueda",
    "wof:placetype":"locality"
},
  "geometry": {"coordinates":[136.24534,34.91370999999999],"type":"Point"}
}