{
  "type": "Feature",
  "properties": {
    "gn:admin1_code":"21.0",
    "gn:admin2_code":"7412708.0",
    "gn:admin3_code":"43505.0",
    "gn:asciiname":"Edagochi",
    "gn:country_code":"JP",
    "gn:dem":237,
    "gn:feature_class":"P",
    "gn:feature_code":"PPLL",
    "gn:name":"Edag\u014dchi",
    "gn:population":0,
    "gn:timezone":"Asia/Tokyo",
    "iso:country":"JP",
    "name:jpn_x_preferred":[
        "\u679d\u5ddd\u5185"
    ],
    "name:jpn_x_variant":[
        "\u3048\u3069\u3054\u3046\u3061",
        "\u30a8\u30c9\u30b4\u30a6\u30c1"
    ],
    "name:und_x_variant":[
        "Edag\u014dchi"
    ],
    "wof:name":"Edagochi",
    "wof:placetype":"locality"
},
  "geometry": {"coordinates":[130.97091,32.24449],"type":"Point"}
}