{
  "type": "Feature",
  "properties": {
    "gn:admin1_code":"14.0",
    "gn:admin2_code":"7452680.0",
    "gn:asciiname":"Nagakura",
    "gn:country_code":"JP",
    "gn:dem":34,
    "gn:feature_class":"P",
    "gn:feature_code":"PPL",
    "gn:name":"Nagakura",
    "gn:population":0,
    "gn:timezone":"Asia/Tokyo",
    "iso:country":"JP",
    "name:deu_x_preferred":[
        "Nagakura"
    ],
    "wof:name":"Nagakura",
    "wof:placetype":"locality"
},
  "geometry": {"coordinates":[140.28333000000001,36.56667],"type":"Point"}
}