{
  "type": "Feature",
  "properties": {
    "gn:admin1_code":"21.0",
    "gn:admin2_code":"1864975.0",
    "gn:admin3_code":"43423.0",
    "gn:asciiname":"Jono",
    "gn:country_code":"JP",
    "gn:dem":468,
    "gn:feature_class":"P",
    "gn:feature_code":"PPLL",
    "gn:name":"J\u014dn\u014d",
    "gn:population":0,
    "gn:timezone":"Asia/Tokyo",
    "iso:country":"JP",
    "name:jpn_x_preferred":[
        "\u57ce\u306e\u5c3e"
    ],
    "name:jpn_x_variant":[
        "\u3058\u3087\u3046\u306e\u3046",
        "\u30b8\u30e7\u30a6\u30ce\u30a6"
    ],
    "name:und_x_variant":[
        "J\u014dn\u014d"
    ],
    "wof:name":"Jono",
    "wof:placetype":"locality"
},
  "geometry": {"coordinates":[131.04986,33.10299000000001],"type":"Point"}
}