{
  "type": "Feature",
  "properties": {
    "gn:admin1_code":"3.0",
    "gn:admin2_code":"7439944.0",
    "gn:asciiname":"Nekobuchi",
    "gn:country_code":"JP",
    "gn:dem":6,
    "gn:feature_class":"P",
    "gn:feature_code":"PPL",
    "gn:name":"Nekobuchi",
    "gn:population":0,
    "gn:timezone":"Asia/Tokyo",
    "iso:country":"JP",
    "name:jpn_x_preferred":[
        "\u732b\u6df5"
    ],
    "name:jpn_x_variant":[
        "\u306d\u3053\u3076\u3061",
        "\u30cd\u30b3\u30d6\u30c1"
    ],
    "wof:name":"Nekobuchi",
    "wof:placetype":"locality"
},
  "geometry": {"coordinates":[140.36420000000001,40.77758],"type":"Point"}
}