{
  "type": "Feature",
  "properties": {
    "gn:admin1_code":"37.0",
    "gn:admin2_code":"1851714.0",
    "gn:admin3_code":"22102.0",
    "gn:asciiname":"Osaka",
    "gn:country_code":"JP",
    "gn:dem":23,
    "gn:feature_class":"P",
    "gn:feature_code":"PPL",
    "gn:name":"Osaka",
    "gn:population":0,
    "gn:timezone":"Asia/Tokyo",
    "iso:country":"JP",
    "name:jpn_x_preferred":[
        "\u5c0f\u5742"
    ],
    "wof:name":"Osaka",
    "wof:placetype":"locality"
},
  "geometry": {"coordinates":[138.34598,34.92165],"type":"Point"}
}