{
  "type": "Feature",
  "properties": {
    "iso:country":"JP",
    "qs:name":"\uff11\u4e01\u76ee",
    "qs:name_adm0":"\u65e5\u672c",
    "qs:name_adm1":"\u9577\u5d0e\u770c",
    "qs:photos":226,
    "qs:photos_1k":46,
    "qs:photos_9k":1,
    "qs:photos_9r":4,
    "qs:photos_all":226,
    "qs:photos_sr":4,
    "qs:placetype":"Suburb",
    "qs:pop_sr":"0",
    "wof:name":"\uff11\u4e01\u76ee",
    "wof:placetype":"neighbourhood"
},
  "geometry": {"coordinates":[129.88327050000001,32.7424],"type":"Point"}
}