{
  "type": "Feature",
  "properties": {
    "gn:admin1_code":"39",
    "gn:admin2_code":"1859771.0",
    "gn:admin3_code":"36302.0",
    "gn:asciiname":"Asahi",
    "gn:country_code":"JP",
    "gn:dem":637,
    "gn:feature_class":"P",
    "gn:feature_code":"PPL",
    "gn:name":"Asahi",
    "gn:population":0,
    "gn:timezone":"Asia/Tokyo",
    "iso:country":"JP",
    "wof:name":"Asahi",
    "wof:placetype":"locality"
},
  "geometry": {"coordinates":[134.36667,33.86667],"type":"Point"}
}