{
  "type": "Feature",
  "properties": {
    "gn:admin1_code":"21.0",
    "gn:admin2_code":"1858418.0",
    "gn:admin3_code":"43102.0",
    "gn:asciiname":"Kyozuka-honmachi",
    "gn:country_code":"JP",
    "gn:dem":26,
    "gn:feature_class":"P",
    "gn:feature_code":"PPL",
    "gn:name":"Ky\u014dzuka-honmachi",
    "gn:population":0,
    "gn:timezone":"Asia/Tokyo",
    "iso:country":"JP",
    "name:jpn_x_preferred":[
        "\u4eac\u585a\u672c\u753a"
    ],
    "name:jpn_x_variant":[
        "\u304d\u3087\u3046\u3065\u304b\u307b\u3093\u307e\u3061",
        "\u30ad\u30e7\u30a6\u30c5\u30ab\u30db\u30f3\u30de\u30c1"
    ],
    "name:und_x_variant":[
        "Ky\u014dzuka-honmachi"
    ],
    "wof:name":"Kyozuka-honmachi",
    "wof:placetype":"locality"
},
  "geometry": {"coordinates":[130.74931999999998,32.79505],"type":"Point"}
}