{
  "type": "Feature",
  "properties": {
    "iso:country":"JP",
    "name:eng_x_preferred":[
        "Ekimae 1 Chome"
    ],
    "name:eng_x_variant":[
        "Ekimae 1 Choume",
        "Ekimae 1 Chome"
    ],
    "name:jpn_x_preferred":[
        "\uff11\u4e01\u76ee"
    ],
    "name:jpn_x_variant":[
        "\u3048\u304d\u307e\u3048 \uff11\u3061\u3087\u3046\u3081",
        "\u99c5\u524d \uff11\u4e01\u76ee",
        "\uff11\u3061\u3087\u3046\u3081"
    ],
    "qs:gn_local":0,
    "qs:local_max":247,
    "qs:local_sum":633,
    "qs:localhoods":7,
    "qs:name":"\uff11\u4e01\u76ee",
    "qs:name_adm0":"\u65e5\u672c",
    "qs:name_adm1":"\u5c71\u5f62\u770c",
    "qs:name_en":"Ekimae 1 Chome",
    "qs:name_lau":"\u99c5\u524d",
    "qs:name_local":"\u7c73\u6ca2\u5e02",
    "qs:photo_max":39,
    "qs:photo_sum":160,
    "qs:placetype":"Suburb",
    "qs:quad_count":8,
    "qs:woe_adm0":23424856,
    "qs:woe_adm1":2345893,
    "qs:woe_adm2":0,
    "qs:woe_lau":28396434,
    "qs:woe_local":1118558,
    "qs:woe_ver":"7.10.0",
    "wof:lang":[
        "jpn"
    ],
    "wof:name":"\uff11\u4e01\u76ee",
    "wof:placetype":"neighbourhood"
},
  "geometry": {"coordinates":[140.12877399999999,37.909262],"type":"Point"}
}