{
  "type": "Feature",
  "properties": {
    "iso:country":"JP",
    "qs:name":"\u7f8e\u6d5c\u753a",
    "qs:name_adm0":"\u65e5\u672c",
    "qs:name_adm1":"\u798f\u4e95\u770c",
    "qs:photos":195,
    "qs:photos_1k":40,
    "qs:photos_9k":1,
    "qs:photos_9r":4,
    "qs:photos_all":195,
    "qs:photos_sr":4,
    "qs:placetype":"Town",
    "qs:pop_sr":"0",
    "wof:name":"\u7f8e\u6d5c\u753a",
    "wof:placetype":"locality"
},
  "geometry": {"coordinates":[135.980186,35.691321],"type":"Point"}
}