{
  "type": "Feature",
  "properties": {
    "gn:admin1_code":"43.0",
    "gn:admin2_code":"1865123.0",
    "gn:admin3_code":"30366.0",
    "gn:asciiname":"Numa",
    "gn:country_code":"JP",
    "gn:dem":424,
    "gn:feature_class":"P",
    "gn:feature_code":"PPL",
    "gn:name":"Numa",
    "gn:population":0,
    "gn:timezone":"Asia/Tokyo",
    "iso:country":"JP",
    "name:ceb_x_preferred":[
        "Numa"
    ],
    "name:deu_x_preferred":[
        "Numa"
    ],
    "name:fra_x_preferred":[
        "Numa"
    ],
    "name:ita_x_preferred":[
        "Numa"
    ],
    "name:jpn_x_preferred":[
        "\u6cbc"
    ],
    "name:por_x_preferred":[
        "Numa"
    ],
    "name:swe_x_preferred":[
        "Numa"
    ],
    "wof:name":"Numa",
    "wof:placetype":"locality"
},
  "geometry": {"coordinates":[135.38023000000001,34.09987],"type":"Point"}
}