{
  "type": "Feature",
  "properties": {
    "gn:admin1_code":"33.0",
    "gn:admin2_code":"1850771.0",
    "gn:asciiname":"Minamitakumachi-shimotaku",
    "gn:country_code":"JP",
    "gn:dem":11,
    "gn:feature_class":"P",
    "gn:feature_code":"PPL",
    "gn:name":"Minamitakumachi-shimotaku",
    "gn:population":0,
    "gn:timezone":"Asia/Tokyo",
    "iso:country":"JP",
    "name:jpn_x_preferred":[
        "\u5357\u591a\u4e45\u753a\u4e0b\u591a\u4e45"
    ],
    "wof:name":"Minamitakumachi-shimotaku",
    "wof:placetype":"locality"
},
  "geometry": {"coordinates":[130.12975,33.27127],"type":"Point"}
}