{
  "type": "Feature",
  "properties": {
    "gn:admin1_code":"24.0",
    "gn:admin2_code":"2112574.0",
    "gn:asciiname":"Asahi",
    "gn:country_code":"JP",
    "gn:dem":10,
    "gn:feature_class":"P",
    "gn:feature_code":"PPL",
    "gn:name":"Asahi",
    "gn:population":0,
    "gn:timezone":"Asia/Tokyo",
    "iso:country":"JP",
    "name:cat_x_preferred":[
        "Asahi"
    ],
    "name:ceb_x_preferred":[
        "Asahi"
    ],
    "name:deu_x_preferred":[
        "Asahi"
    ],
    "name:fas_x_preferred":[
        "\u0622\u0633\u0627\u0647\u06cc"
    ],
    "name:fin_x_preferred":[
        "Asahi"
    ],
    "name:fra_x_preferred":[
        "Asahi"
    ],
    "name:ita_x_preferred":[
        "Asahi"
    ],
    "name:jpn_x_preferred":[
        "\u671d\u65e5"
    ],
    "name:jpn_x_variant":[
        "\u3042\u3055\u3072",
        "\u30a2\u30b5\u30d2"
    ],
    "name:kor_x_preferred":[
        "\uc544\uc0ac\ud788"
    ],
    "name:lit_x_preferred":[
        "Asahi"
    ],
    "name:mlg_x_preferred":[
        "Asahi"
    ],
    "name:nld_x_preferred":[
        "Asahi"
    ],
    "name:pol_x_preferred":[
        "Asahi"
    ],
    "name:por_x_preferred":[
        "Asahi"
    ],
    "name:ron_x_preferred":[
        "Asahi"
    ],
    "name:rus_x_preferred":[
        "\u0410\u0441\u0430\u0445\u0438"
    ],
    "name:spa_x_preferred":[
        "Asahi"
    ],
    "name:swe_x_preferred":[
        "Asahi"
    ],
    "name:tgl_x_preferred":[
        "Asahi"
    ],
    "name:ukr_x_preferred":[
        "\u0410\u0441\u0430\u0445\u0456"
    ],
    "wof:name":"Asahi",
    "wof:placetype":"locality"
},
  "geometry": {"coordinates":[141.17181000000005,38.48669],"type":"Point"}
}