{
  "type": "Feature",
  "properties": {
    "gn:admin1_code":"21.0",
    "gn:admin2_code":"7412706.0",
    "gn:admin3_code":"43447.0",
    "gn:asciiname":"Ichibaru",
    "gn:country_code":"JP",
    "gn:dem":495,
    "gn:feature_class":"P",
    "gn:feature_code":"PPL",
    "gn:name":"Ichibaru",
    "gn:population":0,
    "gn:timezone":"Asia/Tokyo",
    "iso:country":"JP",
    "name:jpn_x_preferred":[
        "\u5e02\u539f"
    ],
    "name:jpn_x_variant":[
        "\u3044\u3061\u3070\u308b",
        "\u30a4\u30c1\u30d0\u30eb"
    ],
    "wof:name":"Ichibaru",
    "wof:placetype":"locality"
},
  "geometry": {"coordinates":[130.95731000000001,32.69194],"type":"Point"}
}