{
  "type": "Feature",
  "properties": {
    "gn:admin1_code":"4.0",
    "gn:admin2_code":"1859468.0",
    "gn:asciiname":"Senbuchidai",
    "gn:country_code":"JP",
    "gn:dem":68,
    "gn:feature_class":"P",
    "gn:feature_code":"PPLL",
    "gn:name":"Senbuchidai",
    "gn:population":0,
    "gn:timezone":"Asia/Tokyo",
    "iso:country":"JP",
    "name:jpn_x_preferred":[
        "\u5343\u6df5\u53f0"
    ],
    "name:jpn_x_variant":[
        "\u305b\u3093\u3076\u3061\u3060\u3044",
        "\u30bb\u30f3\u30d6\u30c1\u30c0\u30a4"
    ],
    "wof:name":"Senbuchidai",
    "wof:placetype":"locality"
},
  "geometry": {"coordinates":[140.03986,35.3128],"type":"Point"}
}