{
  "type": "Feature",
  "properties": {
    "gn:admin1_code":"3.0",
    "gn:admin2_code":"2130088.0",
    "gn:admin3_code":"2307.0",
    "gn:asciiname":"Hyoro",
    "gn:country_code":"JP",
    "gn:dem":33,
    "gn:feature_class":"P",
    "gn:feature_code":"PPL",
    "gn:name":"Hy\u014dr\u014d",
    "gn:population":0,
    "gn:timezone":"Asia/Tokyo",
    "iso:country":"JP",
    "name:jpn_x_preferred":[
        "Hy\u014dr\u014d"
    ],
    "name:jpn_x_variant":[
        "\u68b9\u6994",
        "\u3072\u3087\u3046\u308d\u3046",
        "\u30d2\u30e7\u30a6\u30ed\u30a6"
    ],
    "wof:name":"Hyoro",
    "wof:placetype":"locality"
},
  "geometry": {"coordinates":[140.35990000000001,41.24995],"type":"Point"}
}