{
  "type": "Feature",
  "properties": {
    "gn:admin1_code":"39.0",
    "gn:admin2_code":"10172903.0",
    "gn:asciiname":"Otsucho-kizuno",
    "gn:country_code":"JP",
    "gn:dem":1,
    "gn:feature_class":"P",
    "gn:feature_code":"PPL",
    "gn:name":"\u014ctsuch\u014d-kizuno",
    "gn:population":0,
    "gn:timezone":"Asia/Tokyo",
    "iso:country":"JP",
    "name:jpn_x_preferred":[
        "\u5927\u6d25\u753a\u6728\u6d25\u91ce"
    ],
    "name:und_x_variant":[
        "\u014ctsuch\u014d-kizuno"
    ],
    "wof:name":"Otsucho-kizuno",
    "wof:placetype":"locality"
},
  "geometry": {"coordinates":[134.5874,34.16445],"type":"Point"}
}