{
  "type": "Feature",
  "properties": {
    "gn:admin1_code":"6.0",
    "gn:admin2_code":"7465771.0",
    "gn:admin3_code":"18404.0",
    "gn:asciiname":"Kaburaki",
    "gn:country_code":"JP",
    "gn:dem":2,
    "gn:feature_class":"P",
    "gn:feature_code":"PPLL",
    "gn:name":"Kaburaki",
    "gn:population":0,
    "gn:timezone":"Asia/Tokyo",
    "iso:country":"JP",
    "wof:name":"Kaburaki",
    "wof:placetype":"locality"
},
  "geometry": {"coordinates":[136.03888999999998,35.85073],"type":"Point"}
}