{
  "type": "Feature",
  "properties": {
    "gn:admin1_code":"29",
    "gn:admin2_code":"1861238.0",
    "gn:admin3_code":"15581.0",
    "gn:asciiname":"Kajikatani",
    "gn:country_code":"JP",
    "gn:dem":91,
    "gn:feature_class":"P",
    "gn:feature_code":"PPL",
    "gn:name":"Kajikatani",
    "gn:population":0,
    "gn:timezone":"Asia/Tokyo",
    "iso:country":"JP",
    "name:jpn_x_preferred":[
        "\u9b96\u8c37"
    ],
    "wof:name":"Kajikatani",
    "wof:placetype":"locality"
},
  "geometry": {"coordinates":[139.56528,38.05278],"type":"Point"}
}