{
  "type": "Feature",
  "properties": {
    "gn:admin1_code":"06",
    "gn:admin2_code":"1854843.0",
    "gn:asciiname":"Nishizu",
    "gn:cc2":"JP",
    "gn:country_code":"JP",
    "gn:dem":4,
    "gn:feature_class":"P",
    "gn:feature_code":"PPL",
    "gn:name":"Nishizu",
    "gn:population":0,
    "gn:timezone":"Asia/Tokyo",
    "iso:country":"JP",
    "name:und_x_variant":[
        "Nisizu"
    ],
    "wof:name":"Nishizu",
    "wof:placetype":"locality"
},
  "geometry": {"coordinates":[135.75231000000002,35.51647],"type":"Point"}
}