{
  "type": "Feature",
  "properties": {
    "gn:admin1_code":"14.0",
    "gn:admin2_code":"8304035.0",
    "gn:asciiname":"Sakuragawa",
    "gn:country_code":"JP",
    "gn:dem":211,
    "gn:feature_class":"P",
    "gn:feature_code":"PPLA2",
    "gn:name":"Sakuragawa",
    "gn:population":0,
    "gn:timezone":"Asia/Tokyo",
    "iso:country":"JP",
    "name:ara_x_preferred":[
        "\u0633\u0627\u0643\u0648\u0631\u0627\u063a\u0627\u0648\u0627"
    ],
    "name:fas_x_preferred":[
        "\u0633\u0627\u06a9\u0648\u0631\u0627\u06af\u0627\u0648\u0627\u060c \u0627\u06cc\u0628\u0627\u0631\u0627\u06a9\u06cc"
    ],
    "name:jpn_x_preferred":[
        "\u685c\u5ddd"
    ],
    "name:jpn_x_variant":[
        "\u685c\u5ddd\u5e02"
    ],
    "name:kor_x_preferred":[
        "\uc0ac\ucfe0\ub77c\uac00\uc640 \uc2dc"
    ],
    "name:mzn_x_preferred":[
        "\u0633\u0627\u06a9\u0648\u0631\u0627\u06af\u0627\u0648\u0627\u060c \u0627\u06cc\u0628\u0627\u0631\u0627\u06a9\u06cc"
    ],
    "name:nan_x_preferred":[
        "Sakuragawa-chh\u012b"
    ],
    "name:rus_x_preferred":[
        "\u0421\u0430\u043a\u0443\u0440\u0430\u0433\u0430\u0432\u0430"
    ],
    "name:ukr_x_preferred":[
        "\u0421\u0430\u043a\u0443\u0440\u0430\u0491\u0430\u0432\u0430"
    ],
    "name:zho_x_preferred":[
        "\u6afb\u5ddd\u5e02"
    ],
    "wof:name":"Sakuragawa",
    "wof:placetype":"locality"
},
  "geometry": {"coordinates":[140.11564999999999,36.25052],"type":"Point"}
}