{
  "type": "Feature",
  "properties": {
    "gn:admin1_code":"12.0",
    "gn:admin2_code":"7428094.0",
    "gn:admin3_code":"1694.0",
    "gn:asciiname":"Mappu",
    "gn:country_code":"JP",
    "gn:dem":6,
    "gn:feature_class":"P",
    "gn:feature_code":"PPL",
    "gn:name":"Mappu",
    "gn:population":0,
    "gn:timezone":"Asia/Tokyo",
    "iso:country":"JP",
    "wof:name":"Mappu",
    "wof:placetype":"locality"
},
  "geometry": {"coordinates":[145.13848999999999,43.96317],"type":"Point"}
}