{
  "type": "Feature",
  "properties": {
    "gn:admin1_code":"21.0",
    "gn:admin2_code":"1859488.0",
    "gn:asciiname":"Hongashiwa",
    "gn:country_code":"JP",
    "gn:dem":447,
    "gn:feature_class":"P",
    "gn:feature_code":"PPLL",
    "gn:name":"Hongashiwa",
    "gn:population":0,
    "gn:timezone":"Asia/Tokyo",
    "iso:country":"JP",
    "name:jpn_x_preferred":[
        "\u672c\u67cf"
    ],
    "name:jpn_x_variant":[
        "\u307b\u3093\u304c\u3057\u308f",
        "\u30db\u30f3\u30ac\u30b7\u30ef"
    ],
    "wof:name":"Hongashiwa",
    "wof:placetype":"locality"
},
  "geometry": {"coordinates":[130.89757,33.0273],"type":"Point"}
}