{
  "type": "Feature",
  "properties": {
    "iso:country":"JP",
    "name:eng_x_preferred":[
        "Isogo 1 Chome"
    ],
    "name:eng_x_variant":[
        "Isogo 1 Choume",
        "Isogo 1 Chome"
    ],
    "name:jpn_x_preferred":[
        "\uff11\u4e01\u76ee"
    ],
    "name:jpn_x_variant":[
        "\u3044\u305d\u3054 \uff11\u3061\u3087\u3046\u3081",
        "\u78ef\u5b50 \uff11\u4e01\u76ee",
        "\uff11\u3061\u3087\u3046\u3081"
    ],
    "qs:gn_local":0,
    "qs:local_max":6208,
    "qs:local_sum":82309,
    "qs:localhoods":190,
    "qs:name":"\uff11\u4e01\u76ee",
    "qs:name_adm0":"\u65e5\u672c",
    "qs:name_adm1":"\u795e\u5948\u5ddd\u770c",
    "qs:name_adm2":"\u78ef\u5b50\u533a",
    "qs:name_en":"Isogo 1 Chome",
    "qs:name_lau":"\u78ef\u5b50",
    "qs:name_local":"\u6a2a\u6d5c\u5e02",
    "qs:photo_max":24,
    "qs:photo_sum":65,
    "qs:placetype":"Suburb",
    "qs:quad_count":4,
    "qs:woe_adm0":23424856,
    "qs:woe_adm1":2345868,
    "qs:woe_adm2":15015535,
    "qs:woe_lau":28415888,
    "qs:woe_local":1118550,
    "qs:woe_ver":"7.10.0",
    "wof:lang":[
        "jpn"
    ],
    "wof:name":"\uff11\u4e01\u76ee",
    "wof:placetype":"neighbourhood"
},
  "geometry": {"coordinates":[139.63542799999999,35.406032],"type":"Point"}
}