{
  "type": "Feature",
  "properties": {
    "iso:country":"JP",
    "name:eng_x_preferred":[
        "Mihama 3 Chome"
    ],
    "name:eng_x_variant":[
        "Mihama 3 Choume",
        "Mihama 3 Chome"
    ],
    "name:jpn_x_preferred":[
        "\uff13\u4e01\u76ee"
    ],
    "name:jpn_x_variant":[
        "\u307f\u306f\u307e \uff13\u3061\u3087\u3046\u3081",
        "\u7f8e\u6d5c \uff13\u4e01\u76ee",
        "\uff13\u3061\u3087\u3046\u3081"
    ],
    "name:unk_x_variant":[
        "\uff13\u4e01\u76ee"
    ],
    "qs:gn_local":0,
    "qs:local_max":50518,
    "qs:local_sum":54632,
    "qs:localhoods":4,
    "qs:name":"\uff13\u4e01\u76ee",
    "qs:name_adm0":"\u65e5\u672c",
    "qs:name_adm1":"\u6c96\u7e04\u770c",
    "qs:name_adm2":"\u4e2d\u982d\u90e1",
    "qs:name_en":"Mihama 3 Chome",
    "qs:name_lau":"\u7f8e\u6d5c",
    "qs:name_local":"\u5317\u8c37\u753a",
    "qs:photo_max":59,
    "qs:photo_sum":646,
    "qs:placetype":"Suburb",
    "qs:quad_count":51,
    "qs:woe_adm0":23424856,
    "qs:woe_adm1":2345896,
    "qs:woe_adm2":24857536,
    "qs:woe_lau":28494312,
    "qs:woe_local":1107752,
    "qs:woe_ver":"7.10.0",
    "wof:lang":[
        "jpn"
    ],
    "wof:name":"\uff13\u4e01\u76ee",
    "wof:placetype":"neighbourhood"
},
  "geometry": {"coordinates":[127.75299200000001,26.329192],"type":"Point"}
}