{
  "type": "Feature",
  "properties": {
    "gn:admin1_code":"21.0",
    "gn:admin2_code":"1858418.0",
    "gn:admin3_code":"43104.0",
    "gn:asciiname":"Shimogondo",
    "gn:country_code":"JP",
    "gn:dem":2,
    "gn:feature_class":"P",
    "gn:feature_code":"PPLL",
    "gn:name":"Shimogond\u014d",
    "gn:population":0,
    "gn:timezone":"Asia/Tokyo",
    "iso:country":"JP",
    "name:jpn_x_preferred":[
        "\u4e0b\u8b77\u85e4"
    ],
    "name:jpn_x_variant":[
        "\u3057\u3082\u3054\u3093\u3069\u3046",
        "\u30b7\u30e2\u30b4\u30f3\u30c9\u30a6"
    ],
    "name:und_x_variant":[
        "Shimogond\u014d"
    ],
    "wof:name":"Shimogondo",
    "wof:placetype":"locality"
},
  "geometry": {"coordinates":[130.66576000000001,32.74655],"type":"Point"}
}