{
  "type": "Feature",
  "properties": {
    "gn:admin1_code":"21.0",
    "gn:admin2_code":"7412706.0",
    "gn:admin3_code":"43447.0",
    "gn:asciiname":"Umegi",
    "gn:country_code":"JP",
    "gn:dem":534,
    "gn:feature_class":"P",
    "gn:feature_code":"PPLL",
    "gn:name":"Umegi",
    "gn:population":0,
    "gn:timezone":"Asia/Tokyo",
    "iso:country":"JP",
    "name:jpn_x_preferred":[
        "\u6885\u6728"
    ],
    "name:jpn_x_variant":[
        "\u3046\u3081\u304e",
        "\u30a6\u30e1\u30ae"
    ],
    "wof:name":"Umegi",
    "wof:placetype":"locality"
},
  "geometry": {"coordinates":[130.98911000000001,32.71715],"type":"Point"}
}