{
  "type": "Feature",
  "properties": {
    "gn:admin1_code":"13",
    "gn:admin2_code":"7370819.0",
    "gn:asciiname":"Ei",
    "gn:country_code":"JP",
    "gn:dem":19,
    "gn:feature_class":"P",
    "gn:feature_code":"PPL",
    "gn:name":"Ei",
    "gn:population":0,
    "gn:timezone":"Asia/Tokyo",
    "iso:country":"JP",
    "name:jpn_x_preferred":[
        "\u6c5f\u4e95"
    ],
    "name:und_x_variant":[
        "Tarui"
    ],
    "wof:name":"Ei",
    "wof:placetype":"locality"
},
  "geometry": {"coordinates":[134.82506000000001,34.46158],"type":"Point"}
}