{
  "type": "Feature",
  "properties": {
    "gn:admin1_code":"21.0",
    "gn:admin2_code":"7412708.0",
    "gn:admin3_code":"43511.0",
    "gn:asciiname":"Hae",
    "gn:country_code":"JP",
    "gn:dem":344,
    "gn:feature_class":"P",
    "gn:feature_code":"PPL",
    "gn:name":"Hae",
    "gn:population":0,
    "gn:timezone":"Asia/Tokyo",
    "iso:country":"JP",
    "name:jpn_x_preferred":[
        "\u516b\u91cd"
    ],
    "name:jpn_x_variant":[
        "\u306f\u3048",
        "\u30cf\u30a8"
    ],
    "wof:name":"Hae",
    "wof:placetype":"locality"
},
  "geometry": {"coordinates":[130.86008000000001,32.45707],"type":"Point"}
}