{
  "type": "Feature",
  "properties": {
    "gn:admin1_code":"34.0",
    "gn:admin2_code":"1859726.0",
    "gn:asciiname":"Koshimizu",
    "gn:country_code":"JP",
    "gn:dem":12,
    "gn:feature_class":"P",
    "gn:feature_code":"PPLL",
    "gn:name":"Koshimizu",
    "gn:population":0,
    "gn:timezone":"Asia/Tokyo",
    "iso:country":"JP",
    "name:jpn_x_preferred":[
        "\u5c0f\u6e05\u6c34"
    ],
    "wof:name":"Koshimizu",
    "wof:placetype":"locality"
},
  "geometry": {"coordinates":[139.75781000000001,35.83798],"type":"Point"}
}