{
  "type": "Feature",
  "properties": {
    "gn:admin1_code":"4.0",
    "gn:admin2_code":"9062338.0",
    "gn:asciiname":"Matsube-yamada",
    "gn:country_code":"JP",
    "gn:dem":112,
    "gn:feature_class":"P",
    "gn:feature_code":"PPLL",
    "gn:name":"Matsube-yamada",
    "gn:population":0,
    "gn:timezone":"Asia/Tokyo",
    "iso:country":"JP",
    "name:jpn_x_preferred":[
        "\u677e\u90e8\u5c71\u7530"
    ],
    "name:jpn_x_variant":[
        "\u307e\u3064\u3079\u3084\u307e\u3060",
        "\u30de\u30c4\u30d9\u30e4\u30de\u30c0"
    ],
    "wof:name":"Matsube-yamada",
    "wof:placetype":"locality"
},
  "geometry": {"coordinates":[140.28586000000001,35.15988],"type":"Point"}
}