{
  "type": "Feature",
  "properties": {
    "gn:admin1_code":"34.0",
    "gn:admin2_code":"7464121.0",
    "gn:asciiname":"Sakurai",
    "gn:country_code":"JP",
    "gn:dem":200,
    "gn:feature_class":"P",
    "gn:feature_code":"PPLL",
    "gn:name":"Sakurai",
    "gn:population":0,
    "gn:timezone":"Asia/Tokyo",
    "iso:country":"JP",
    "name:deu_x_preferred":[
        "Sakurai"
    ],
    "name:jpn_x_preferred":[
        "\u685c\u4e95"
    ],
    "name:pol_x_preferred":[
        "Sakurai"
    ],
    "name:rus_x_preferred":[
        "\u0421\u0430\u043a\u0443\u0440\u0430\u0438"
    ],
    "name:spa_x_preferred":[
        "Sakurai"
    ],
    "name:ukr_x_preferred":[
        "\u0421\u0430\u043a\u0443\u0440\u0430\u0439"
    ],
    "wof:name":"Sakurai",
    "wof:placetype":"locality"
},
  "geometry": {"coordinates":[139.04402999999999,36.03403],"type":"Point"}
}