{
  "type": "Feature",
  "properties": {
    "gn:admin1_code":"21.0",
    "gn:admin2_code":"1858418.0",
    "gn:admin3_code":"43105.0",
    "gn:asciiname":"Futata",
    "gn:country_code":"JP",
    "gn:dem":33,
    "gn:feature_class":"P",
    "gn:feature_code":"PPLL",
    "gn:name":"Futata",
    "gn:population":0,
    "gn:timezone":"Asia/Tokyo",
    "iso:country":"JP",
    "name:jpn_x_preferred":[
        "\u4e8c\u7530"
    ],
    "name:jpn_x_variant":[
        "\u3075\u305f\u305f",
        "\u30d5\u30bf\u30bf"
    ],
    "wof:name":"Futata",
    "wof:placetype":"locality"
},
  "geometry": {"coordinates":[130.71756000000002,32.96545],"type":"Point"}
}