{
  "type": "Feature",
  "properties": {
    "gn:admin1_code":"12.0",
    "gn:admin2_code":"7428088.0",
    "gn:admin3_code":"1637.0",
    "gn:asciiname":"Kamibisei",
    "gn:country_code":"JP",
    "gn:dem":216,
    "gn:feature_class":"P",
    "gn:feature_code":"PPL",
    "gn:name":"Kamibisei",
    "gn:population":0,
    "gn:timezone":"Asia/Tokyo",
    "iso:country":"JP",
    "name:jpn_x_preferred":[
        "\u4e0a\u7f8e\u751f"
    ],
    "name:und_x_variant":[
        "Kami bibai",
        "Kami-bisei",
        "Kamibisei"
    ],
    "wof:name":"Kamibisei",
    "wof:placetype":"locality"
},
  "geometry": {"coordinates":[142.95529999999999,42.80936],"type":"Point"}
}