{
  "type": "Feature",
  "properties": {
    "iso:country":"JP",
    "qs:name":"\uff13\u4e01\u76ee",
    "qs:name_adm0":"\u65e5\u672c",
    "qs:name_adm1":"\u5c90\u961c\u770c",
    "qs:photos":422,
    "qs:photos_1k":86,
    "qs:photos_9k":2,
    "qs:photos_9r":5,
    "qs:photos_all":422,
    "qs:photos_sr":6,
    "qs:placetype":"Suburb",
    "qs:pop_sr":"0",
    "wof:name":"\uff13\u4e01\u76ee",
    "wof:placetype":"neighbourhood"
},
  "geometry": {"coordinates":[137.260265,36.149934],"type":"Point"}
}