{
  "type": "Feature",
  "properties": {
    "gn:admin1_code":"18.0",
    "gn:admin2_code":"8300556.0",
    "gn:asciiname":"Oairacho",
    "gn:country_code":"JP",
    "gn:dem":56,
    "gn:feature_class":"P",
    "gn:feature_code":"PPL",
    "gn:name":"\u014cairach\u014d",
    "gn:population":0,
    "gn:timezone":"Asia/Tokyo",
    "iso:country":"JP",
    "name:jpn_x_preferred":[
        "\u5927\u59f6\u826f\u753a"
    ],
    "name:und_x_variant":[
        "\u014cairach\u014d"
    ],
    "wof:name":"Oairacho",
    "wof:placetype":"locality"
},
  "geometry": {"coordinates":[130.82501999999999,31.32959],"type":"Point"}
}