{
  "type": "Feature",
  "properties": {
    "gn:admin1_code":"10.0",
    "gn:admin2_code":"1852593.0",
    "gn:asciiname":"Akagimachi-shikishima",
    "gn:country_code":"JP",
    "gn:dem":259,
    "gn:feature_class":"P",
    "gn:feature_code":"PPL",
    "gn:name":"Akagimachi-shikishima",
    "gn:population":0,
    "gn:timezone":"Asia/Tokyo",
    "iso:country":"JP",
    "name:jpn_x_preferred":[
        "\u8d64\u57ce\u753a\u6577\u5cf6"
    ],
    "wof:name":"Akagimachi-shikishima",
    "wof:placetype":"locality"
},
  "geometry": {"coordinates":[139.03913,36.53689],"type":"Point"}
}