{
  "type": "Feature",
  "properties": {
    "gn:admin1_code":"8.0",
    "gn:admin2_code":"2112979.0",
    "gn:admin3_code":"7303.0",
    "gn:asciiname":"Fujita",
    "gn:country_code":"JP",
    "gn:dem":68,
    "gn:feature_class":"P",
    "gn:feature_code":"PPL",
    "gn:name":"Fujita",
    "gn:population":0,
    "gn:timezone":"Asia/Tokyo",
    "iso:country":"JP",
    "name:jpn_x_preferred":[
        "\u85e4\u7530"
    ],
    "wof:name":"Fujita",
    "wof:placetype":"locality"
},
  "geometry": {"coordinates":[140.55332000000001,37.8781],"type":"Point"}
}