{
  "type": "Feature",
  "properties": {
    "gn:admin1_code":"07",
    "gn:admin2_code":"9035649.0",
    "gn:asciiname":"Fukunaga",
    "gn:country_code":"JP",
    "gn:dem":4,
    "gn:feature_class":"P",
    "gn:feature_code":"PPL",
    "gn:name":"Fukunaga",
    "gn:population":0,
    "gn:timezone":"Asia/Tokyo",
    "iso:country":"JP",
    "name:jpn_x_preferred":[
        "\u798f\u6c38"
    ],
    "name:rus_x_preferred":[
        "\u0424\u0443\u043a\u0443\u043d\u0430\u0433\u0430"
    ],
    "wof:name":"Fukunaga",
    "wof:placetype":"locality"
},
  "geometry": {"coordinates":[130.15433000000002,33.5211],"type":"Point"}
}