{
  "type": "Feature",
  "properties": {
    "gn:admin1_code":"33.0",
    "gn:admin2_code":"7391355.0",
    "gn:asciiname":"Nonoto",
    "gn:country_code":"JP",
    "gn:dem":165,
    "gn:feature_class":"P",
    "gn:feature_code":"PPLL",
    "gn:name":"Nonot\u014d",
    "gn:population":0,
    "gn:timezone":"Asia/Tokyo",
    "iso:country":"JP",
    "name:jpn_x_preferred":[
        "\u91ce\u3005\u982d"
    ],
    "name:und_x_variant":[
        "Nonot\u014d"
    ],
    "wof:name":"Nonoto",
    "wof:placetype":"locality"
},
  "geometry": {"coordinates":[129.77995000000001,33.31191],"type":"Point"}
}