{
  "type": "Feature",
  "properties": {
    "gn:admin1_code":"21.0",
    "gn:admin2_code":"1862350.0",
    "gn:asciiname":"Akaike-okumizunashi",
    "gn:country_code":"JP",
    "gn:dem":211,
    "gn:feature_class":"P",
    "gn:feature_code":"PPLL",
    "gn:name":"Akaike-okumizunashi",
    "gn:population":0,
    "gn:timezone":"Asia/Tokyo",
    "iso:country":"JP",
    "name:jpn_x_preferred":[
        "\u8d64\u6c60\u5965\u6c34\u7121"
    ],
    "name:jpn_x_variant":[
        "\u3042\u304b\u3044\u3051\u304a\u304f\u307f\u305a\u306a\u3057",
        "\u30a2\u30ab\u30a4\u30b1\u30aa\u30af\u30df\u30ba\u30ca\u30b7"
    ],
    "wof:name":"Akaike-okumizunashi",
    "wof:placetype":"locality"
},
  "geometry": {"coordinates":[130.77247,32.17512],"type":"Point"}
}