{
  "type": "Feature",
  "properties": {
    "gn:admin1_code":"34",
    "gn:admin2_code":"8304214.0",
    "gn:asciiname":"Hirakata",
    "gn:country_code":"JP",
    "gn:dem":17,
    "gn:feature_class":"P",
    "gn:feature_code":"PPL",
    "gn:name":"Hirakata",
    "gn:population":0,
    "gn:timezone":"Asia/Tokyo",
    "iso:country":"JP",
    "name:ara_x_preferred":[
        "\u0647\u064a\u0631\u0627\u0643\u0627\u062a\u0627"
    ],
    "name:aze_x_preferred":[
        "Hirakata"
    ],
    "name:bul_x_preferred":[
        "\u0425\u0438\u0440\u0430\u043a\u0430\u0442\u0430"
    ],
    "name:cat_x_preferred":[
        "Hirakata"
    ],
    "name:ceb_x_preferred":[
        "Hirakata Shi"
    ],
    "name:deu_x_preferred":[
        "Hirakata"
    ],
    "name:epo_x_preferred":[
        "Hirakata"
    ],
    "name:eus_x_preferred":[
        "Hirakata"
    ],
    "name:fas_x_preferred":[
        "\u0647\u06cc\u0631\u0627\u06a9\u0627\u062a\u0627"
    ],
    "name:fin_x_preferred":[
        "Hirakata"
    ],
    "name:fra_x_preferred":[
        "Hirakata"
    ],
    "name:gle_x_preferred":[
        "Hirakata"
    ],
    "name:glg_x_preferred":[
        "Hirakata"
    ],
    "name:ita_x_preferred":[
        "Hirakata"
    ],
    "name:jpn_x_preferred":[
        "\u5e73\u65b9"
    ],
    "name:jpn_x_variant":[
        "\u3072\u3089\u304b\u305f",
        "\u30d2\u30e9\u30ab\u30bf",
        "\u679a\u65b9\u5e02"
    ],
    "name:kor_x_preferred":[
        "\ud788\ub77c\uce74\ud0c0\uc2dc"
    ],
    "name:lit_x_preferred":[
        "Hirakata"
    ],
    "name:mlg_x_preferred":[
        "Hirakata"
    ],
    "name:msa_x_preferred":[
        "Hirakata"
    ],
    "name:mzn_x_preferred":[
        "\u0647\u06cc\u0631\u0627\u06a9\u0627\u062a\u0627"
    ],
    "name:nld_x_preferred":[
        "Hirakata"
    ],
    "name:pol_x_preferred":[
        "Hirakata"
    ],
    "name:por_x_preferred":[
        "Hirakata"
    ],
    "name:ron_x_preferred":[
        "Hirakata"
    ],
    "name:rus_x_preferred":[
        "\u0425\u0438\u0440\u0430\u043a\u0430\u0442\u0430"
    ],
    "name:sco_x_preferred":[
        "Hirakata"
    ],
    "name:spa_x_preferred":[
        "Hirakata"
    ],
    "name:srp_x_preferred":[
        "\u0425\u0438\u0440\u0430\u043a\u0430\u0442\u0430"
    ],
    "name:swe_x_preferred":[
        "Hirakata"
    ],
    "name:tgk_x_preferred":[
        "\u04b2\u0438\u0440\u0430\u043a\u0430\u0442\u0430"
    ],
    "name:tgl_x_preferred":[
        "Hirakata"
    ],
    "name:tha_x_preferred":[
        "\u0e2e\u0e34\u0e23\u0e32\u0e01\u0e32\u0e15\u0e30"
    ],
    "name:tur_x_preferred":[
        "Hirakata"
    ],
    "name:ukr_x_preferred":[
        "\u0425\u0456\u0440\u0430\u043a\u0430\u0442\u0430"
    ],
    "name:urd_x_preferred":[
        "\u06c1\u06cc\u0631\u0627\u06a9\u0627\u062a\u0627"
    ],
    "name:vie_x_preferred":[
        "Hirakata"
    ],
    "name:war_x_preferred":[
        "Hirakata"
    ],
    "name:zho_x_preferred":[
        "\u679a\u65b9\u5e02"
    ],
    "wof:name":"Hirakata",
    "wof:placetype":"locality"
},
  "geometry": {"coordinates":[139.55222000000001,35.95062],"type":"Point"}
}