{
  "type": "Feature",
  "properties": {
    "gn:admin1_code":"12.0",
    "gn:admin2_code":"7428102.0",
    "gn:admin3_code":"1608.0",
    "gn:asciiname":"Honcho",
    "gn:country_code":"JP",
    "gn:dem":4,
    "gn:feature_class":"P",
    "gn:feature_code":"PPL",
    "gn:name":"Honch\u014d",
    "gn:population":0,
    "gn:timezone":"Asia/Tokyo",
    "iso:country":"JP",
    "name:ceb_x_preferred":[
        "Samani Ch\u014d"
    ],
    "name:fas_x_preferred":[
        "\u0633\u0645\u0646\u06cc"
    ],
    "name:fra_x_preferred":[
        "Samani"
    ],
    "name:ido_x_preferred":[
        "Samani"
    ],
    "name:ita_x_preferred":[
        "Samani"
    ],
    "name:jpn_x_preferred":[
        "\u672c\u753a"
    ],
    "name:jpn_x_variant":[
        "\u307b\u3093\u3061\u3087\u3046",
        "\u30db\u30f3\u30c1\u30e7\u30a6",
        "\u69d8\u4f3c\u753a"
    ],
    "name:kor_x_preferred":[
        "\uc0ac\ub9c8\ub2c8\uc815"
    ],
    "name:msa_x_preferred":[
        "Samani"
    ],
    "name:mya_x_preferred":[
        "\u1006\u1019\u1014\u102d\u1019\u103c\u102d\u102f\u1037\u104a \u101f\u1031\u102c\u1037\u1000\u102d\u102f\u1004\u103a\u1038\u1012\u102d\u102f\u1038"
    ],
    "name:rus_x_preferred":[
        "\u0421\u0430\u043c\u0430\u043d\u0438"
    ],
    "name:ukr_x_preferred":[
        "\u0421\u0430\u043c\u0430\u043d\u0456"
    ],
    "name:und_x_variant":[
        "Utoma",
        "Samanai",
        "Shamani",
        "Syamani",
        "Honch\u014d"
    ],
    "name:zho_x_preferred":[
        "\u6a23\u4f3c\u753a"
    ],
    "wof:name":"Honcho",
    "wof:placetype":"locality"
},
  "geometry": {"coordinates":[142.91784999999999,42.12841],"type":"Point"}
}