{
  "type": "Feature",
  "properties": {
    "gn:admin1_code":"12.0",
    "gn:admin2_code":"7428102.0",
    "gn:admin3_code":"1608.0",
    "gn:asciiname":"Honcho",
    "gn:country_code":"JP",
    "gn:dem":4,
    "gn:feature_class":"P",
    "gn:feature_code":"PPL",
    "gn:name":"Honch\u014d",
    "gn:population":0,
    "gn:timezone":"Asia/Tokyo",
    "iso:country":"JP",
    "name:jpn_x_preferred":[
        "\u672c\u753a"
    ],
    "name:jpn_x_variant":[
        "\u307b\u3093\u3061\u3087\u3046",
        "\u30db\u30f3\u30c1\u30e7\u30a6"
    ],
    "name:und_x_variant":[
        "Utoma",
        "Samanai",
        "Shamani",
        "Syamani",
        "Samani",
        "Honch\u014d"
    ],
    "wof:name":"Honcho",
    "wof:placetype":"locality"
},
  "geometry": {"coordinates":[142.91784999999999,42.12841],"type":"Point"}
}