{
  "type": "Feature",
  "properties": {
    "gn:admin1_code":"34.0",
    "gn:admin2_code":"1849187.0",
    "gn:admin3_code":"11110.0",
    "gn:asciiname":"Honjuku",
    "gn:country_code":"JP",
    "gn:dem":14,
    "gn:feature_class":"P",
    "gn:feature_code":"PPL",
    "gn:name":"Honjuku",
    "gn:population":0,
    "gn:timezone":"Asia/Tokyo",
    "iso:country":"JP",
    "name:jpn_x_preferred":[
        "\u672c\u5bbf"
    ],
    "name:jpn_x_variant":[
        "\u307b\u3093\u3058\u3085\u304f",
        "\u30db\u30f3\u30b8\u30e5\u30af"
    ],
    "wof:name":"Honjuku",
    "wof:placetype":"locality"
},
  "geometry": {"coordinates":[139.68973,35.96652],"type":"Point"}
}