{
  "type": "Feature",
  "properties": {
    "gn:admin1_code":"34.0",
    "gn:admin2_code":"1858728.0",
    "gn:asciiname":"Minamiogishima",
    "gn:country_code":"JP",
    "gn:dem":4,
    "gn:feature_class":"P",
    "gn:feature_code":"PPL",
    "gn:name":"Minamiogishima",
    "gn:population":0,
    "gn:timezone":"Asia/Tokyo",
    "iso:country":"JP",
    "name:jpn_x_preferred":[
        "\u5357\u837b\u5cf6"
    ],
    "wof:name":"Minamiogishima",
    "wof:placetype":"locality"
},
  "geometry": {"coordinates":[139.76646000000002,35.91139000000001],"type":"Point"}
}