{
  "type": "Feature",
  "properties": {
    "gn:admin1_code":"21.0",
    "gn:admin2_code":"1864975.0",
    "gn:admin3_code":"43432.0",
    "gn:asciiname":"Hoshigaoka",
    "gn:country_code":"JP",
    "gn:dem":180,
    "gn:feature_class":"P",
    "gn:feature_code":"PPLL",
    "gn:name":"Hoshigaoka",
    "gn:population":0,
    "gn:timezone":"Asia/Tokyo",
    "iso:country":"JP",
    "name:jpn_x_preferred":[
        "\u661f\u30f6\u4e18"
    ],
    "name:jpn_x_variant":[
        "\u307b\u3057\u304c\u304a\u304b",
        "\u30db\u30b7\u30ac\u30aa\u30ab"
    ],
    "wof:name":"Hoshigaoka",
    "wof:placetype":"locality"
},
  "geometry": {"coordinates":[130.88862,32.83959],"type":"Point"}
}