{
  "type": "Feature",
  "properties": {
    "gn:admin1_code":"21.0",
    "gn:admin2_code":"1850744.0",
    "gn:admin3_code":"43368.0",
    "gn:asciiname":"Tateno",
    "gn:country_code":"JP",
    "gn:dem":9,
    "gn:feature_class":"P",
    "gn:feature_code":"PPLL",
    "gn:name":"Tateno",
    "gn:population":0,
    "gn:timezone":"Asia/Tokyo",
    "iso:country":"JP",
    "name:jpn_x_preferred":[
        "\u7acb\u91ce"
    ],
    "name:jpn_x_variant":[
        "\u305f\u3066\u306e",
        "\u30bf\u30c6\u30ce"
    ],
    "wof:name":"Tateno",
    "wof:placetype":"locality"
},
  "geometry": {"coordinates":[130.47871999999998,32.93671],"type":"Point"}
}