{
  "type": "Feature",
  "properties": {
    "iso:country":"JP",
    "name:eng_x_preferred":[
        "Nagayamajunijo 4 Chome"
    ],
    "name:eng_x_variant":[
        "Nagayamajuunijou 4 Choume",
        "Nagayamajunijo 4 Chome"
    ],
    "name:jpn_x_preferred":[
        "\uff14\u4e01\u76ee"
    ],
    "name:jpn_x_variant":[
        "\u306a\u304c\u3084\u307e\u3058\u3085\u3046\u306b\u3058\u3087\u3046 \uff14\u3061\u3087\u3046\u3081",
        "\u6c38\u5c71\u5341\u4e8c\u6761 \uff14\u4e01\u76ee",
        "\uff14\u3061\u3087\u3046\u3081"
    ],
    "name:unk_x_variant":[
        "\uff14\u4e01\u76ee"
    ],
    "qs:gn_local":0,
    "qs:local_max":1584,
    "qs:local_sum":2444,
    "qs:localhoods":13,
    "qs:name":"\uff14\u4e01\u76ee",
    "qs:name_adm0":"\u65e5\u672c",
    "qs:name_adm1":"\u5317\u6d77\u9053",
    "qs:name_en":"Nagayamajunijo 4 Chome",
    "qs:name_lau":"\u6c38\u5c71\u5341\u4e8c\u6761",
    "qs:name_local":"\u65ed\u5ddd\u5e02",
    "qs:photo_max":25,
    "qs:photo_sum":33,
    "qs:placetype":"Suburb",
    "qs:quad_count":3,
    "qs:woe_adm0":23424856,
    "qs:woe_adm1":7153351,
    "qs:woe_adm2":0,
    "qs:woe_lau":28380698,
    "qs:woe_local":1116988,
    "qs:woe_ver":"7.10.0",
    "wof:lang":[
        "jpn"
    ],
    "wof:name":"\uff14\u4e01\u76ee",
    "wof:placetype":"neighbourhood"
},
  "geometry": {"coordinates":[142.41505599999999,43.781797],"type":"Point"}
}