{
  "type": "Feature",
  "properties": {
    "gn:admin1_code":"21.0",
    "gn:admin2_code":"1850743.0",
    "gn:asciiname":"Hachiban",
    "gn:country_code":"JP",
    "gn:dem":0,
    "gn:feature_class":"P",
    "gn:feature_code":"PPLL",
    "gn:name":"Hachiban",
    "gn:population":0,
    "gn:timezone":"Asia/Tokyo",
    "iso:country":"JP",
    "name:jpn_x_preferred":[
        "\u516b\u756a"
    ],
    "name:jpn_x_variant":[
        "\u306f\u3061\u3070\u3093",
        "\u30cf\u30c1\u30d0\u30f3"
    ],
    "wof:name":"Hachiban",
    "wof:placetype":"locality"
},
  "geometry": {"coordinates":[130.55571,32.86987],"type":"Point"}
}