{
  "type": "Feature",
  "properties": {
    "iso:country":"JP",
    "name:ara_x_preferred":[
        "\u0623\u0648\u0633\u0627"
    ],
    "name:ben_x_preferred":[
        "\u0987\u0989\u09b8\u09be"
    ],
    "name:ell_x_preferred":[
        "\u039f\u03cd\u03b6\u03b1"
    ],
    "name:eng_x_preferred":[
        "Usa"
    ],
    "name:eng_x_variant":[
        "Usa City"
    ],
    "name:heb_x_preferred":[
        "\u05d0\u05d5\u05bc\u05e1\u05d4"
    ],
    "name:hin_x_preferred":[
        "\u0909\u0938\u093e "
    ],
    "name:ind_x_preferred":[
        "Usa"
    ],
    "name:jpn_x_preferred":[
        "\u5b87\u4f50\u5e02"
    ],
    "name:kor_x_preferred":[
        "\uc6b0\uc0ac"
    ],
    "name:por_x_preferred":[
        "Usa"
    ],
    "name:swe_x_preferred":[
        "Usa"
    ],
    "name:urd_x_preferred":[
        "\u0627\u0648\u0633\u0627"
    ],
    "name:vie_x_preferred":[
        "S\u00f4ng Usa"
    ],
    "qs:name":"\u5b87\u4f50\u5e02",
    "qs:name_adm0":"\u65e5\u672c",
    "qs:name_adm1":"\u5927\u5206\u770c",
    "qs:photos":363,
    "qs:photos_1k":74,
    "qs:photos_9k":2,
    "qs:photos_9r":5,
    "qs:photos_all":367,
    "qs:photos_sr":6,
    "qs:placetype":"Town",
    "qs:pop_sr":"0",
    "wof:name":"Usa",
    "wof:placetype":"locality"
},
  "geometry": {"coordinates":[131.37452200000001,33.524944],"type":"Point"}
}