{
  "type": "Feature",
  "properties": {
    "iso:country":"JP",
    "name:eng_x_preferred":[
        "Usa City"
    ],
    "name:jpn_x_preferred":[
        "\u5b87\u4f50\u5e02"
    ],
    "qs:name":"\u5b87\u4f50\u5e02",
    "qs:name_adm0":"\u65e5\u672c",
    "qs:name_adm1":"\u5927\u5206\u770c",
    "qs:photos":363,
    "qs:photos_1k":74,
    "qs:photos_9k":2,
    "qs:photos_9r":5,
    "qs:photos_all":367,
    "qs:photos_sr":6,
    "qs:placetype":"Town",
    "qs:pop_sr":"0",
    "wof:name":"Usa City",
    "wof:placetype":"locality"
},
  "geometry": {"coordinates":[131.37452200000001,33.524944],"type":"Point"}
}