{
  "type": "Feature",
  "properties": {
    "gn:admin1_code":"21.0",
    "gn:admin2_code":"7413153.0",
    "gn:asciiname":"Nonoshima",
    "gn:country_code":"JP",
    "gn:dem":84,
    "gn:feature_class":"P",
    "gn:feature_code":"PPL",
    "gn:name":"Nonoshima",
    "gn:population":0,
    "gn:timezone":"Asia/Tokyo",
    "iso:country":"JP",
    "name:jpn_x_preferred":[
        "\u91ce\u3005\u5cf6"
    ],
    "name:jpn_x_variant":[
        "\u306e\u306e\u3057\u307e",
        "\u30ce\u30ce\u30b7\u30de"
    ],
    "wof:name":"Nonoshima",
    "wof:placetype":"locality"
},
  "geometry": {"coordinates":[130.73497,32.89409000000001],"type":"Point"}
}