{
  "type": "Feature",
  "properties": {
    "gn:admin1_code":"26",
    "gn:admin2_code":"1853055.0",
    "gn:asciiname":"Komagome",
    "gn:country_code":"JP",
    "gn:dem":864,
    "gn:feature_class":"P",
    "gn:feature_code":"PPLL",
    "gn:name":"Komagome",
    "gn:population":0,
    "gn:timezone":"Asia/Tokyo",
    "iso:country":"JP",
    "name:jpn_x_preferred":[
        "\u99d2\u8fbc"
    ],
    "wof:name":"Komagome",
    "wof:placetype":"locality"
},
  "geometry": {"coordinates":[138.5581,36.23757],"type":"Point"}
}