{
  "type": "Feature",
  "properties": {
    "gn:admin1_code":"47",
    "gn:admin2_code":"1849184.0",
    "gn:asciiname":"Maeda",
    "gn:country_code":"JP",
    "gn:dem":123,
    "gn:feature_class":"P",
    "gn:feature_code":"PPL",
    "gn:name":"Maeda",
    "gn:population":0,
    "gn:timezone":"Asia/Tokyo",
    "iso:country":"JP",
    "name:deu_x_preferred":[
        "Maeda"
    ],
    "name:fra_x_preferred":[
        "Maeda"
    ],
    "name:jpn_x_preferred":[
        "\u524d\u7530"
    ],
    "name:kor_x_preferred":[
        "\ub9c8\uc5d0\ub2e4"
    ],
    "name:rus_x_preferred":[
        "\u041c\u0430\u044d\u0434\u0430"
    ],
    "name:ukr_x_preferred":[
        "\u041c\u0430\u0435\u0434\u0430"
    ],
    "name:und_x_variant":[
        "Meida",
        "Meda"
    ],
    "wof:name":"Maeda",
    "wof:placetype":"locality"
},
  "geometry": {"coordinates":[127.73560999999999,26.23997],"type":"Point"}
}