{
  "type": "Feature",
  "properties": {
    "iso:country":"JP",
    "name:eng_x_preferred":[
        "Kichijojihoncho 2 Chome"
    ],
    "name:eng_x_variant":[
        "Kichijoujihonchou 2 Choume",
        "Kichijojihoncho 2 Chome"
    ],
    "name:jpn_x_preferred":[
        "\uff12\u4e01\u76ee"
    ],
    "name:jpn_x_variant":[
        "\u304d\u3061\u3058\u3087\u3046\u3058\u307b\u3093\u3061\u3087\u3046 \uff12\u3061\u3087\u3046\u3081",
        "\u5409\u7965\u5bfa\u672c\u753a \uff12\u4e01\u76ee",
        "\uff12\u3061\u3087\u3046\u3081"
    ],
    "qs:gn_adm0_cc":"JP",
    "qs:gn_local":1856367,
    "qs:gn_nam_loc":"\u6b66\u8535\u91ce\u5e02, \u6771\u4eac\u90fd, JP",
    "qs:gn_namadm1":"40",
    "qs:local_max":4951,
    "qs:local_sum":14684,
    "qs:localhoods":12,
    "qs:name":"\uff12\u4e01\u76ee",
    "qs:name_adm0":"\u65e5\u672c",
    "qs:name_adm1":"\u6771\u4eac\u90fd",
    "qs:name_en":"Kichijojihoncho 2 Chome",
    "qs:name_lau":"\u5409\u7965\u5bfa\u672c\u753a",
    "qs:name_local":"\u6b66\u8535\u91ce\u5e02",
    "qs:photo_max":2221,
    "qs:photo_sum":4430,
    "qs:placetype":"Suburb",
    "qs:quad_count":20,
    "qs:woe_adm0":23424856,
    "qs:woe_adm1":2345889,
    "qs:woe_adm2":0,
    "qs:woe_lau":28414926,
    "qs:woe_local":1112268,
    "qs:woe_ver":"7.10.0",
    "qs_pg:name":"\uff12\u4e01\u76ee",
    "qs_pg:name_adm0":"\u65e5\u672c",
    "qs_pg:name_adm1":"\u6771\u4eac\u90fd",
    "qs_pg:photos":3389,
    "qs_pg:photos_1k":687,
    "qs_pg:photos_9k":15,
    "qs_pg:photos_9r":11,
    "qs_pg:photos_all":3389,
    "qs_pg:photos_sr":20,
    "qs_pg:pop_sr":0,
    "qs_pg:qs_pg_placetype":"neighbourhood",
    "qs_pg:qs_pg_placetype_gp":"Suburb",
    "qs_pg:woe_adm0":23424856,
    "woe:adm0_id":23424856,
    "woe:name_adm0":"\u65e5\u672c",
    "woe:name_adm1":"\u6771\u4eac\u90fd",
    "woe:placetype":"Suburb",
    "wof:lang":[
        "jpn"
    ],
    "wof:name":"\uff12\u4e01\u76ee",
    "wof:placetype":"neighbourhood"
},
  "geometry": {"coordinates":[139.57818900000001,35.704285],"type":"Point"}
}