{
  "type": "Feature",
  "properties": {
    "gn:admin1_code":"45.0",
    "gn:admin2_code":"1857072.0",
    "gn:asciiname":"Ominecho-nishibun",
    "gn:country_code":"JP",
    "gn:dem":127,
    "gn:feature_class":"P",
    "gn:feature_code":"PPL",
    "gn:name":"\u014cminech\u014d-nishibun",
    "gn:population":0,
    "gn:timezone":"Asia/Tokyo",
    "iso:country":"JP",
    "name:jpn_x_preferred":[
        "\u5927\u5dba\u753a\u897f\u5206"
    ],
    "name:und_x_variant":[
        "\u014cminech\u014d-nishibun"
    ],
    "wof:name":"Ominecho-nishibun",
    "wof:placetype":"locality"
},
  "geometry": {"coordinates":[131.16876000000002,34.15251],"type":"Point"}
}