{
  "type": "Feature",
  "properties": {
    "gn:admin1_code":"3.0",
    "gn:admin2_code":"2127674.0",
    "gn:asciiname":"Minamihiguchi",
    "gn:country_code":"JP",
    "gn:dem":67,
    "gn:feature_class":"P",
    "gn:feature_code":"PPL",
    "gn:name":"Minamihiguchi",
    "gn:population":0,
    "gn:timezone":"Asia/Tokyo",
    "iso:country":"JP",
    "name:jpn_x_preferred":[
        "\u5357\u6a0b\u53e3"
    ],
    "name:jpn_x_variant":[
        "\u307f\u306a\u307f\u3072\u3050\u3061",
        "\u30df\u30ca\u30df\u30d2\u30b0\u30c1"
    ],
    "wof:name":"Minamihiguchi",
    "wof:placetype":"locality"
},
  "geometry": {"coordinates":[141.21702999999999,40.64176],"type":"Point"}
}