{
  "type": "Feature",
  "properties": {
    "gn:admin1_code":"3.0",
    "gn:admin2_code":"2128302.0",
    "gn:admin3_code":"2441.0",
    "gn:asciiname":"Arata",
    "gn:country_code":"JP",
    "gn:dem":160,
    "gn:feature_class":"P",
    "gn:feature_code":"PPL",
    "gn:name":"Arata",
    "gn:population":0,
    "gn:timezone":"Asia/Tokyo",
    "iso:country":"JP",
    "name:ceb_x_preferred":[
        "Arata"
    ],
    "name:deu_x_preferred":[
        "Arata"
    ],
    "name:fra_x_preferred":[
        "Arata"
    ],
    "name:ind_x_preferred":[
        "Arata"
    ],
    "name:ita_x_preferred":[
        "Arata"
    ],
    "name:jpn_x_preferred":[
        "\u8352\u7530"
    ],
    "name:jpn_x_variant":[
        "\u3042\u3089\u305f",
        "\u30a2\u30e9\u30bf"
    ],
    "name:slv_x_preferred":[
        "Arata"
    ],
    "name:swe_x_preferred":[
        "Arata"
    ],
    "wof:name":"Arata",
    "wof:placetype":"locality"
},
  "geometry": {"coordinates":[141.17143000000004,40.40115],"type":"Point"}
}