{
  "type": "Feature",
  "properties": {
    "gn:admin1_code":"16.0",
    "gn:admin2_code":"7441817.0",
    "gn:asciiname":"Nagahora",
    "gn:country_code":"JP",
    "gn:dem":10,
    "gn:feature_class":"P",
    "gn:feature_code":"PPL",
    "gn:name":"Nagahora",
    "gn:population":0,
    "gn:timezone":"Asia/Tokyo",
    "iso:country":"JP",
    "name:jpn_x_preferred":[
        "\u9577\u6d1e"
    ],
    "name:jpn_x_variant":[
        "\u306a\u304c\u307b\u3089",
        "\u30ca\u30ac\u30db\u30e9"
    ],
    "name:und_x_variant":[
        "Ch\u014dd\u014d",
        "Nagahora"
    ],
    "wof:name":"Nagahora",
    "wof:placetype":"locality"
},
  "geometry": {"coordinates":[141.70706999999999,38.9819],"type":"Point"}
}