{
  "type": "Feature",
  "properties": {
    "gn:admin1_code":"2.0",
    "gn:admin2_code":"2113122.0",
    "gn:asciiname":"Shimokitate-kurokawa",
    "gn:country_code":"JP",
    "gn:dem":34,
    "gn:feature_class":"P",
    "gn:feature_code":"PPL",
    "gn:name":"Shimokitate-kurokawa",
    "gn:population":0,
    "gn:timezone":"Asia/Tokyo",
    "iso:country":"JP",
    "name:jpn_x_preferred":[
        "\u4e0b\u5317\u624b\u9ed2\u5ddd"
    ],
    "name:jpn_x_variant":[
        "\u3057\u3082\u304d\u305f\u3066\u304f\u308d\u304b\u308f",
        "\u30b7\u30e2\u30ad\u30bf\u30c6\u30af\u30ed\u30ab\u30ef",
        "\u9ed2\u5ddd"
    ],
    "name:und_x_variant":[
        "Kurokawa"
    ],
    "wof:name":"Shimokitate-kurokawa",
    "wof:placetype":"locality"
},
  "geometry": {"coordinates":[140.17633999999998,39.70487],"type":"Point"}
}