{
  "type": "Feature",
  "properties": {
    "gn:admin1_code":"18.0",
    "gn:admin2_code":"8714932.0",
    "gn:admin3_code":"46501.0",
    "gn:asciiname":"Haranosato",
    "gn:country_code":"JP",
    "gn:dem":31,
    "gn:feature_class":"P",
    "gn:feature_code":"PPLL",
    "gn:name":"Haranosato",
    "gn:population":0,
    "gn:timezone":"Asia/Tokyo",
    "iso:country":"JP",
    "name:jpn_x_preferred":[
        "\u539f\u4e4b\u91cc"
    ],
    "wof:name":"Haranosato",
    "wof:placetype":"locality"
},
  "geometry": {"coordinates":[130.94658000000001,30.55806],"type":"Point"}
}