{
  "type": "Feature",
  "properties": {
    "gn:admin1_code":"29.0",
    "gn:admin2_code":"1852604.0",
    "gn:asciiname":"Goto",
    "gn:country_code":"JP",
    "gn:dem":17,
    "gn:feature_class":"P",
    "gn:feature_code":"PPLL",
    "gn:name":"Got\u014d",
    "gn:population":0,
    "gn:timezone":"Asia/Tokyo",
    "iso:country":"JP",
    "name:deu_x_preferred":[
        "Sprunganweisung"
    ],
    "name:epo_x_preferred":[
        "Salta ordono"
    ],
    "name:fas_x_preferred":[
        "Goto"
    ],
    "name:fra_x_preferred":[
        "Goto"
    ],
    "name:heb_x_preferred":[
        "\u05e4\u05e7\u05d5\u05d3\u05ea goto"
    ],
    "name:hrv_x_preferred":[
        "Goto"
    ],
    "name:jpn_x_preferred":[
        "\u4e94\u6597"
    ],
    "name:jpn_x_variant":[
        "Goto\u6587"
    ],
    "name:kor_x_preferred":[
        "Goto \ubb38"
    ],
    "name:nld_x_preferred":[
        "Spronginstructie"
    ],
    "name:pol_x_preferred":[
        "Instrukcja skoku"
    ],
    "name:por_x_preferred":[
        "Goto"
    ],
    "name:rus_x_preferred":[
        "Goto"
    ],
    "name:srp_x_preferred":[
        "Goto naredba"
    ],
    "name:swe_x_preferred":[
        "Goto"
    ],
    "name:ukr_x_preferred":[
        "\u0411\u0435\u0437\u0443\u043c\u043e\u0432\u043d\u0438\u0439 \u043f\u0435\u0440\u0435\u0445\u0456\u0434"
    ],
    "name:und_x_variant":[
        "Got\u014d"
    ],
    "name:zho_x_preferred":[
        "Goto"
    ],
    "wof:name":"Goto",
    "wof:placetype":"locality"
},
  "geometry": {"coordinates":[139.39435,37.95002],"type":"Point"}
}