{
  "type": "Feature",
  "properties": {
    "gn:admin1_code":"29.0",
    "gn:admin2_code":"1852604.0",
    "gn:asciiname":"Goto",
    "gn:country_code":"JP",
    "gn:dem":17,
    "gn:feature_class":"P",
    "gn:feature_code":"PPLL",
    "gn:name":"Got\u014d",
    "gn:population":0,
    "gn:timezone":"Asia/Tokyo",
    "iso:country":"JP",
    "name:jpn_x_preferred":[
        "\u4e94\u6597"
    ],
    "name:und_x_variant":[
        "Got\u014d"
    ],
    "wof:name":"Goto",
    "wof:placetype":"locality"
},
  "geometry": {"coordinates":[139.39435,37.95002],"type":"Point"}
}