{
  "type": "Feature",
  "properties": {
    "gn:country":"JP",
    "gn:fcode":"PPLX",
    "gn:pop":16361,
    "iso:country":"JP",
    "name:unk_x_variant":[
        "Takeda"
    ],
    "qs:name":"Takedamachi",
    "qs:photos_9r":0,
    "qs:photos_sr":0,
    "qs:pop_sr":"6",
    "wof:name":"Takedamachi",
    "wof:placetype":"neighbourhood",
    "wof:population":16361
},
  "geometry": {"coordinates":[131.40000000000001,32.96667],"type":"Point"}
}