{
  "type": "Feature",
  "properties": {
    "gn:admin1_code":"4.0",
    "gn:admin2_code":"2111854.0",
    "gn:asciiname":"Wadamae",
    "gn:country_code":"JP",
    "gn:dem":15,
    "gn:feature_class":"P",
    "gn:feature_code":"PPLL",
    "gn:name":"Wadamae",
    "gn:population":0,
    "gn:timezone":"Asia/Tokyo",
    "iso:country":"JP",
    "name:jpn_x_preferred":[
        "\u548c\u7530\u524d"
    ],
    "name:jpn_x_variant":[
        "\u308f\u3060\u307e\u3048",
        "\u30ef\u30c0\u30de\u30a8"
    ],
    "wof:name":"Wadamae",
    "wof:placetype":"locality"
},
  "geometry": {"coordinates":[140.26858999999999,35.44531],"type":"Point"}
}