{
  "type": "Feature",
  "properties": {
    "iso:country":"JP",
    "name:eng_x_preferred":[
        "Bifuka Town"
    ],
    "name:jpn_x_preferred":[
        "\u7f8e\u6df1\u753a"
    ],
    "qs:name":"\u7f8e\u6df1\u753a",
    "qs:name_adm0":"\u65e5\u672c",
    "qs:name_adm1":"\u5317\u6d77\u9053",
    "qs:photos":42,
    "qs:photos_1k":9,
    "qs:photos_9k":1,
    "qs:photos_9r":2,
    "qs:photos_all":61,
    "qs:photos_sr":2,
    "qs:placetype":"Town",
    "qs:pop_sr":"0",
    "wof:name":"Bifuka Town",
    "wof:placetype":"locality"
},
  "geometry": {"coordinates":[142.32530600000001,44.558552],"type":"Point"}
}