{
  "type": "Feature",
  "properties": {
    "gn:admin1_code":"11",
    "gn:admin2_code":"1857327.0",
    "gn:asciiname":"Yahatacho-kaichi",
    "gn:country_code":"JP",
    "gn:dem":227,
    "gn:feature_class":"P",
    "gn:feature_code":"PPL",
    "gn:name":"Yahatach\u014d-kaichi",
    "gn:population":0,
    "gn:timezone":"Asia/Tokyo",
    "iso:country":"JP",
    "name:jpn_x_preferred":[
        "\u516b\u5e61\u753a\u57a3\u5185"
    ],
    "name:und_x_variant":[
        "Yahatach\u014d-kaichi",
        "Kaichi"
    ],
    "wof:name":"Yahatacho-kaichi",
    "wof:placetype":"locality"
},
  "geometry": {"coordinates":[133.06523000000001,34.47115],"type":"Point"}
}