{
  "type": "Feature",
  "properties": {
    "iso:country":"JP",
    "name:eng_x_preferred":[
        "Tomioka 2 Chome"
    ],
    "name:eng_x_variant":[
        "Tomioka 2 Choume",
        "Tomioka 2 Chome"
    ],
    "name:jpn_x_preferred":[
        "\uff12\u4e01\u76ee"
    ],
    "name:jpn_x_variant":[
        "\u3068\u307f\u304a\u304b \uff12\u3061\u3087\u3046\u3081",
        "\u5bcc\u5ca1 \uff12\u4e01\u76ee",
        "\uff12\u3061\u3087\u3046\u3081"
    ],
    "qs:gn_adm0_cc":"JP",
    "qs:gn_local":1850147,
    "qs:local_max":18112,
    "qs:local_sum":895907,
    "qs:localhoods":857,
    "qs:name":"\uff12\u4e01\u76ee",
    "qs:name_adm0":"\u65e5\u672c",
    "qs:name_adm1":"\u6771\u4eac\u90fd",
    "qs:name_adm2":"\u6c5f\u6771\u533a",
    "qs:name_en":"Tomioka 2 Chome",
    "qs:name_lau":"\u5bcc\u5ca1",
    "qs:name_local":"\u6771\u4eac",
    "qs:photo_max":23,
    "qs:photo_sum":58,
    "qs:placetype":"Suburb",
    "qs:quad_count":4,
    "qs:woe_adm0":23424856,
    "qs:woe_adm1":2345889,
    "qs:woe_adm2":15015377,
    "qs:woe_lau":28414207,
    "qs:woe_local":1118370,
    "qs:woe_ver":"7.10.0",
    "wof:lang":[
        "jpn"
    ],
    "wof:name":"\uff12\u4e01\u76ee",
    "wof:placetype":"neighbourhood"
},
  "geometry": {"coordinates":[139.80080699999999,35.6703],"type":"Point"}
}