{
  "type": "Feature",
  "properties": {
    "gn:admin1_code":"19.0",
    "gn:admin2_code":"1848308.0",
    "gn:asciiname":"Sakuragaoka",
    "gn:country_code":"JP",
    "gn:dem":56,
    "gn:feature_class":"P",
    "gn:feature_code":"PPL",
    "gn:name":"Sakuragaoka",
    "gn:population":0,
    "gn:timezone":"Asia/Tokyo",
    "iso:country":"JP",
    "name:jpn_x_preferred":[
        "\u685c\u304c\u4e18"
    ],
    "name:jpn_x_variant":[
        "\u3055\u304f\u3089\u304c\u304a\u304b",
        "\u30b5\u30af\u30e9\u30ac\u30aa\u30ab"
    ],
    "wof:name":"Sakuragaoka",
    "wof:placetype":"locality"
},
  "geometry": {"coordinates":[139.70052999999999,35.25477],"type":"Point"}
}