{
  "type": "Feature",
  "properties": {
    "gn:admin1_code":"37.0",
    "gn:admin2_code":"1863526.0",
    "gn:asciiname":"Tsukamoto",
    "gn:country_code":"JP",
    "gn:dem":458,
    "gn:feature_class":"P",
    "gn:feature_code":"PPLL",
    "gn:name":"Tsukamoto",
    "gn:population":0,
    "gn:timezone":"Asia/Tokyo",
    "iso:country":"JP",
    "name:jpn_x_preferred":[
        "\u585a\u672c"
    ],
    "wof:name":"Tsukamoto",
    "wof:placetype":"locality"
},
  "geometry": {"coordinates":[138.93615,35.30154],"type":"Point"}
}