{
  "type": "Feature",
  "properties": {
    "gn:admin1_code":"4.0",
    "gn:admin2_code":"2112997.0",
    "gn:admin3_code":"12423.0",
    "gn:asciiname":"Hitotsumatsu-cho",
    "gn:country_code":"JP",
    "gn:dem":2,
    "gn:feature_class":"P",
    "gn:feature_code":"PPLL",
    "gn:name":"Hitotsumatsu-ch\u014d",
    "gn:population":0,
    "gn:timezone":"Asia/Tokyo",
    "iso:country":"JP",
    "name:jpn_x_preferred":[
        "\u4e00\u677e\u4e01"
    ],
    "name:jpn_x_variant":[
        "\u3072\u3068\u3064\u307e\u3064\u3061\u3087\u3046",
        "\u30d2\u30c8\u30c4\u30de\u30c4\u30c1\u30e7\u30a6"
    ],
    "name:und_x_variant":[
        "Hitotsumatsu-ch\u014d"
    ],
    "wof:name":"Hitotsumatsu-cho",
    "wof:placetype":"locality"
},
  "geometry": {"coordinates":[140.38,35.4082],"type":"Point"}
}