{
  "type": "Feature",
  "properties": {
    "gn:admin1_code":"19",
    "gn:admin2_code":"1853293.0",
    "gn:admin3_code":"14151.0",
    "gn:asciiname":"Dojo",
    "gn:country_code":"JP",
    "gn:dem":332,
    "gn:feature_class":"P",
    "gn:feature_code":"PPL",
    "gn:name":"D\u014dj\u014d",
    "gn:population":0,
    "gn:timezone":"Asia/Tokyo",
    "iso:country":"JP",
    "name:jpn_x_preferred":[
        "D\u014dj\u014d"
    ],
    "wof:name":"Dojo",
    "wof:placetype":"locality"
},
  "geometry": {"coordinates":[139.20889,35.53889],"type":"Point"}
}