{
  "type": "Feature",
  "properties": {
    "gn:admin1_code":"19",
    "gn:admin2_code":"1853293.0",
    "gn:admin3_code":"14151.0",
    "gn:asciiname":"Dojo",
    "gn:country_code":"JP",
    "gn:dem":332,
    "gn:feature_class":"P",
    "gn:feature_code":"PPL",
    "gn:name":"D\u014dj\u014d",
    "gn:population":0,
    "gn:timezone":"Asia/Tokyo",
    "iso:country":"JP",
    "name:ara_x_preferred":[
        "\u062f\u0648\u062c\u0648"
    ],
    "name:ast_x_preferred":[
        "Dojo"
    ],
    "name:ben_x_preferred":[
        "\u09a6\u09cb\u099c\u09cb"
    ],
    "name:bul_x_preferred":[
        "\u0414\u043e\u0434\u0436\u043e"
    ],
    "name:cat_x_preferred":[
        "Dojo"
    ],
    "name:ces_x_preferred":[
        "D\u00f3d\u017e\u00f3"
    ],
    "name:dan_x_preferred":[
        "Dojo"
    ],
    "name:deu_x_preferred":[
        "D\u014dj\u014d"
    ],
    "name:ell_x_preferred":[
        "\u039d\u03c4\u03cc\u03c4\u03b6\u03bf"
    ],
    "name:epo_x_preferred":[
        "Do\u0135o"
    ],
    "name:est_x_preferred":[
        "D\u014dj\u014d"
    ],
    "name:fin_x_preferred":[
        "D\u014dj\u014d"
    ],
    "name:fra_x_preferred":[
        "Dojo"
    ],
    "name:fry_x_preferred":[
        "Dojo"
    ],
    "name:glg_x_preferred":[
        "Dojo"
    ],
    "name:heb_x_preferred":[
        "\u05d3\u05d5\u05d2'\u05d5"
    ],
    "name:hun_x_preferred":[
        "D\u00f3dzs\u00f3"
    ],
    "name:ind_x_preferred":[
        "Dojo"
    ],
    "name:ita_x_preferred":[
        "Dojo"
    ],
    "name:jpn_x_preferred":[
        "D\u014dj\u014d"
    ],
    "name:kor_x_preferred":[
        "\ub3c4\uc7a5"
    ],
    "name:lit_x_preferred":[
        "Dod\u017eo"
    ],
    "name:msa_x_preferred":[
        "Dojo"
    ],
    "name:nld_x_preferred":[
        "Dojo"
    ],
    "name:nno_x_preferred":[
        "Dojo"
    ],
    "name:nor_x_preferred":[
        "Dojo"
    ],
    "name:pol_x_preferred":[
        "Dojo"
    ],
    "name:por_x_preferred":[
        "Dojo"
    ],
    "name:ron_x_preferred":[
        "Dojo"
    ],
    "name:rus_x_preferred":[
        "\u0414\u043e\u0434\u0437\u0451"
    ],
    "name:slk_x_preferred":[
        "D\u00f3d\u017e\u00f3"
    ],
    "name:slv_x_preferred":[
        "Dod\u017eo"
    ],
    "name:spa_x_preferred":[
        "D\u014dj\u014d"
    ],
    "name:srp_x_preferred":[
        "\u0414\u043e\u045f\u043e"
    ],
    "name:swe_x_preferred":[
        "Dojo"
    ],
    "name:tur_x_preferred":[
        "Dojo"
    ],
    "name:ukr_x_preferred":[
        "\u0414\u043e\u0434\u0437\u044c\u043e"
    ],
    "name:vie_x_preferred":[
        "Dojo"
    ],
    "wof:name":"Dojo",
    "wof:placetype":"locality"
},
  "geometry": {"coordinates":[139.20889,35.53889],"type":"Point"}
}