{
  "type": "Feature",
  "properties": {
    "gn:admin1_code":"3.0",
    "gn:admin2_code":"2127674.0",
    "gn:asciiname":"Nakasato Gawa",
    "gn:country_code":"JP",
    "gn:dem":95,
    "gn:feature_class":"P",
    "gn:feature_code":"PPL",
    "gn:name":"Nakasato Gawa",
    "gn:population":0,
    "gn:timezone":"Asia/Tokyo",
    "iso:country":"JP",
    "name:jpn_x_preferred":[
        "\u4e2d\u91cc\u5ddd"
    ],
    "name:jpn_x_variant":[
        "\u306a\u304b\u3055\u3068\u304c\u308f",
        "\u30ca\u30ab\u30b5\u30c8\u30ac\u30ef"
    ],
    "wof:name":"Nakasato Gawa",
    "wof:placetype":"locality"
},
  "geometry": {"coordinates":[141.10002,40.59428],"type":"Point"}
}