{
  "type": "Feature",
  "properties": {
    "gn:admin1_code":"7.0",
    "gn:admin2_code":"1864588.0",
    "gn:admin3_code":"40647.0",
    "gn:asciiname":"Sawada",
    "gn:country_code":"JP",
    "gn:dem":237,
    "gn:feature_class":"P",
    "gn:feature_code":"PPL",
    "gn:name":"Sawada",
    "gn:population":0,
    "gn:timezone":"Asia/Tokyo",
    "iso:country":"JP",
    "name:jpn_x_preferred":[
        "\u5bd2\u7530"
    ],
    "wof:name":"Sawada",
    "wof:placetype":"locality"
},
  "geometry": {"coordinates":[130.99177,33.55499],"type":"Point"}
}