{
  "type": "Feature",
  "properties": {
    "gn:admin1_code":"10.0",
    "gn:admin2_code":"7453836.0",
    "gn:asciiname":"Higashihirai",
    "gn:country_code":"JP",
    "gn:dem":127,
    "gn:feature_class":"P",
    "gn:feature_code":"PPL",
    "gn:name":"Higashihirai",
    "gn:population":0,
    "gn:timezone":"Asia/Tokyo",
    "iso:country":"JP",
    "name:jpn_x_preferred":[
        "\u6771\u5e73\u4e95"
    ],
    "wof:name":"Higashihirai",
    "wof:placetype":"locality"
},
  "geometry": {"coordinates":[139.04471999999998,36.22641],"type":"Point"}
}