{
  "type": "Feature",
  "properties": {
    "gn:admin1_code":"4.0",
    "gn:admin2_code":"2112997.0",
    "gn:admin3_code":"12427.0",
    "gn:asciiname":"Kutsuta",
    "gn:country_code":"JP",
    "gn:dem":22,
    "gn:feature_class":"P",
    "gn:feature_code":"PPLL",
    "gn:name":"Kutsuta",
    "gn:population":0,
    "gn:timezone":"Asia/Tokyo",
    "iso:country":"JP",
    "name:jpn_x_preferred":[
        "\u845b\u7530"
    ],
    "name:jpn_x_variant":[
        "\u304f\u3064\u305f",
        "\u30af\u30c4\u30bf"
    ],
    "wof:name":"Kutsuta",
    "wof:placetype":"locality"
},
  "geometry": {"coordinates":[140.26596999999998,35.38081],"type":"Point"}
}