{
  "type": "Feature",
  "properties": {
    "gn:admin1_code":"26",
    "gn:admin2_code":"1859278.0",
    "gn:admin3_code":"20321.0",
    "gn:asciiname":"Kyukaruizawa",
    "gn:country_code":"JP",
    "gn:dem":960,
    "gn:feature_class":"P",
    "gn:feature_code":"PPLL",
    "gn:name":"Ky\u016bkaruizawa",
    "gn:population":0,
    "gn:timezone":"Asia/Tokyo",
    "iso:country":"JP",
    "name:jpn_x_preferred":[
        "\u65e7\u8efd\u4e95\u6ca2"
    ],
    "name:und_x_variant":[
        "Ky\u016b-karuizawa",
        "Ky\u016b-karuisawa",
        "Ky\u016bkaruizawa"
    ],
    "wof:name":"Kyukaruizawa",
    "wof:placetype":"locality"
},
  "geometry": {"coordinates":[138.63517999999999,36.35776],"type":"Point"}
}