{
  "type": "Feature",
  "properties": {
    "gn:admin1_code":"12.0",
    "gn:admin2_code":"7428116.0",
    "gn:admin3_code":"1607.0",
    "gn:asciiname":"Higashicho-chinomi",
    "gn:country_code":"JP",
    "gn:dem":9,
    "gn:feature_class":"P",
    "gn:feature_code":"PPL",
    "gn:name":"Higashich\u014d-chinomi",
    "gn:population":0,
    "gn:timezone":"Asia/Tokyo",
    "iso:country":"JP",
    "name:jpn_x_preferred":[
        "\u6771\u753a\u3061\u306e\u307f"
    ],
    "name:jpn_x_variant":[
        "\u3072\u304c\u3057\u3061\u3087\u3046\u3061\u306e\u307f",
        "\u30d2\u30ac\u30b7\u30c1\u30e7\u30a6\u30c1\u30ce\u30df"
    ],
    "name:und_x_variant":[
        "Higashich\u014d-chinomi"
    ],
    "wof:name":"Higashicho-chinomi",
    "wof:placetype":"locality"
},
  "geometry": {"coordinates":[142.79134999999999,42.16412],"type":"Point"}
}