{
  "type": "Feature",
  "properties": {
    "gn:admin1_code":"21.0",
    "gn:admin2_code":"1865360.0",
    "gn:admin3_code":"43531.0",
    "gn:asciiname":"Shikiyama-minamibira",
    "gn:country_code":"JP",
    "gn:dem":270,
    "gn:feature_class":"P",
    "gn:feature_code":"PPLL",
    "gn:name":"Shikiyama-minamibira",
    "gn:population":0,
    "gn:timezone":"Asia/Tokyo",
    "iso:country":"JP",
    "name:jpn_x_preferred":[
        "\u5fd7\u5c90\u5c71\u5357\u5e73"
    ],
    "name:jpn_x_variant":[
        "\u3057\u304d\u3084\u307e\u307f\u306a\u307f\u3073\u3089",
        "\u30b7\u30ad\u30e4\u30de\u30df\u30ca\u30df\u30d3\u30e9"
    ],
    "wof:name":"Shikiyama-minamibira",
    "wof:placetype":"locality"
},
  "geometry": {"coordinates":[130.08523,32.48775999999999],"type":"Point"}
}