{
  "type": "Feature",
  "properties": {
    "iso:country":"JP",
    "qs:name":"\u5b89\u516b\u753a",
    "qs:name_adm0":"\u65e5\u672c",
    "qs:name_adm1":"\u5c90\u961c\u770c",
    "qs:photos":39,
    "qs:photos_1k":8,
    "qs:photos_9k":1,
    "qs:photos_9r":2,
    "qs:photos_all":66,
    "qs:photos_sr":2,
    "qs:placetype":"Town",
    "qs:pop_sr":"0",
    "wof:name":"\u5b89\u516b\u753a",
    "wof:placetype":"locality"
},
  "geometry": {"coordinates":[136.666831,35.332072],"type":"Point"}
}