{
  "type": "Feature",
  "properties": {
    "gn:admin1_code":"30",
    "gn:admin2_code":"1858008.0",
    "gn:admin3_code":"44461.0",
    "gn:asciiname":"Nakamura",
    "gn:country_code":"JP",
    "gn:dem":439,
    "gn:feature_class":"P",
    "gn:feature_code":"PPLL",
    "gn:name":"Nakamura",
    "gn:population":0,
    "gn:timezone":"Asia/Tokyo",
    "iso:country":"JP",
    "name:jpn_x_preferred":[
        "\u4e2d\u6751"
    ],
    "wof:name":"Nakamura",
    "wof:placetype":"locality"
},
  "geometry": {"coordinates":[131.20703999999998,33.22681],"type":"Point"}
}