{
  "type": "Feature",
  "properties": {
    "gn:admin1_code":"28.0",
    "gn:admin2_code":"1848164.0",
    "gn:admin3_code":"29442.0",
    "gn:asciiname":"Ashihara",
    "gn:country_code":"JP",
    "gn:dem":238,
    "gn:feature_class":"P",
    "gn:feature_code":"PPL",
    "gn:name":"Ashihara",
    "gn:population":0,
    "gn:timezone":"Asia/Tokyo",
    "iso:country":"JP",
    "name:deu_x_preferred":[
        "Ashihara"
    ],
    "name:jpn_x_preferred":[
        "\u82a6\u539f"
    ],
    "wof:name":"Ashihara",
    "wof:placetype":"locality"
},
  "geometry": {"coordinates":[135.79503,34.41562],"type":"Point"}
}