{
  "type": "Feature",
  "properties": {
    "gn:admin1_code":"27.0",
    "gn:admin2_code":"1862734.0",
    "gn:admin3_code":"42321.0",
    "gn:asciiname":"Onegotogo",
    "gn:country_code":"JP",
    "gn:dem":12,
    "gn:feature_class":"P",
    "gn:feature_code":"PPL",
    "gn:name":"\u014cnegotog\u014d",
    "gn:population":0,
    "gn:timezone":"Asia/Tokyo",
    "iso:country":"JP",
    "name:jpn_x_preferred":[
        "\u5927\u97f3\u7434\u90f7"
    ],
    "name:und_x_variant":[
        "\u014cnegotog\u014d"
    ],
    "wof:name":"Onegotogo",
    "wof:placetype":"locality"
},
  "geometry": {"coordinates":[129.89191,33.05925999999999],"type":"Point"}
}