{
  "type": "Feature",
  "properties": {
    "gn:admin1_code":"12.0",
    "gn:admin2_code":"7428090.0",
    "gn:admin3_code":"1664.0",
    "gn:asciiname":"Kumaushi-gen'ya",
    "gn:country_code":"JP",
    "gn:dem":124,
    "gn:feature_class":"P",
    "gn:feature_code":"PPL",
    "gn:name":"Kumaushi-gen\u2019ya",
    "gn:population":0,
    "gn:timezone":"Asia/Tokyo",
    "iso:country":"JP",
    "name:jpn_x_preferred":[
        "\u718a\u725b\u539f\u91ce"
    ],
    "name:jpn_x_variant":[
        "\u304f\u307e\u3046\u3057\u3052\u3093\u3084",
        "\u30af\u30de\u30a6\u30b7\u30b2\u30f3\u30e4"
    ],
    "name:und_x_variant":[
        "Kumaushi-gen\u2019ya"
    ],
    "wof:name":"Kumaushi-gen'ya",
    "wof:placetype":"locality"
},
  "geometry": {"coordinates":[144.57727,43.40603],"type":"Point"}
}