{
  "type": "Feature",
  "properties": {
    "gn:admin1_code":"34.0",
    "gn:admin2_code":"7464123.0",
    "gn:asciiname":"Aoyagi",
    "gn:country_code":"JP",
    "gn:dem":6,
    "gn:feature_class":"P",
    "gn:feature_code":"PPL",
    "gn:name":"Aoyagi",
    "gn:population":0,
    "gn:timezone":"Asia/Tokyo",
    "iso:country":"JP",
    "name:jpn_x_preferred":[
        "\u9752\u67f3"
    ],
    "wof:name":"Aoyagi",
    "wof:placetype":"locality"
},
  "geometry": {"coordinates":[139.82158000000001,35.85111],"type":"Point"}
}