{
  "type": "Feature",
  "properties": {
    "gn:admin1_code":"15",
    "gn:admin2_code":"1848973.0",
    "gn:asciiname":"Soryomachi",
    "gn:country_code":"JP",
    "gn:dem":93,
    "gn:feature_class":"P",
    "gn:feature_code":"PPL",
    "gn:name":"S\u014dry\u014dmachi",
    "gn:population":0,
    "gn:timezone":"Asia/Tokyo",
    "iso:country":"JP",
    "name:jpn_x_preferred":[
        "\u60e3\u9818\u753a"
    ],
    "name:jpn_x_variant":[
        "S\u014dry\u014d"
    ],
    "name:und_x_variant":[
        "S\u014dry\u014dmachi"
    ],
    "wof:name":"Soryomachi",
    "wof:placetype":"locality"
},
  "geometry": {"coordinates":[136.95711,37.40457],"type":"Point"}
}