{
  "type": "Feature",
  "properties": {
    "gn:admin1_code":"18.0",
    "gn:admin2_code":"1862007.0",
    "gn:asciiname":"Usuyama",
    "gn:country_code":"JP",
    "gn:dem":104,
    "gn:feature_class":"P",
    "gn:feature_code":"PPLL",
    "gn:name":"Usuyama",
    "gn:population":0,
    "gn:timezone":"Asia/Tokyo",
    "iso:country":"JP",
    "name:jpn_x_preferred":[
        "\u81fc\u5c71"
    ],
    "wof:name":"Usuyama",
    "wof:placetype":"locality"
},
  "geometry": {"coordinates":[130.59692999999999,31.26636],"type":"Point"}
}