{
  "type": "Feature",
  "properties": {
    "gn:admin1_code":"3.0",
    "gn:admin2_code":"2127674.0",
    "gn:asciiname":"Akabushi",
    "gn:country_code":"JP",
    "gn:dem":190,
    "gn:feature_class":"P",
    "gn:feature_code":"PPL",
    "gn:name":"Akabushi",
    "gn:population":0,
    "gn:timezone":"Asia/Tokyo",
    "iso:country":"JP",
    "name:jpn_x_preferred":[
        "\u8d64\u4f0f"
    ],
    "name:jpn_x_variant":[
        "\u3042\u304b\u3076\u3057",
        "\u30a2\u30ab\u30d6\u30b7"
    ],
    "wof:name":"Akabushi",
    "wof:placetype":"locality"
},
  "geometry": {"coordinates":[141.18361000000004,40.49965],"type":"Point"}
}