{
  "type": "Feature",
  "properties": {
    "gn:admin1_code":"37.0",
    "gn:admin2_code":"1851401.0",
    "gn:admin3_code":"22342.0",
    "gn:asciiname":"Yoji",
    "gn:country_code":"JP",
    "gn:dem":100,
    "gn:feature_class":"P",
    "gn:feature_code":"PPLL",
    "gn:name":"Y\u014dji",
    "gn:population":0,
    "gn:timezone":"Asia/Tokyo",
    "iso:country":"JP",
    "name:jpn_x_preferred":[
        "\u7528\u5730"
    ],
    "name:jpn_x_variant":[
        "\u3088\u3046\u3062"
    ],
    "name:und_x_variant":[
        "Y\u014dji"
    ],
    "wof:name":"Yoji",
    "wof:placetype":"locality"
},
  "geometry": {"coordinates":[138.89466000000002,35.15750999999999],"type":"Point"}
}