{
  "type": "Feature",
  "properties": {
    "gn:admin1_code":"12.0",
    "gn:admin2_code":"7428097.0",
    "gn:admin3_code":"1643.0",
    "gn:asciiname":"Satsunai-mizuhomachi",
    "gn:country_code":"JP",
    "gn:dem":33,
    "gn:feature_class":"P",
    "gn:feature_code":"PPL",
    "gn:name":"Satsunai-mizuhomachi",
    "gn:population":0,
    "gn:timezone":"Asia/Tokyo",
    "iso:country":"JP",
    "name:jpn_x_preferred":[
        "\u672d\u5185\u307f\u305a\u307b\u753a"
    ],
    "name:jpn_x_variant":[
        "\u3055\u3064\u306a\u3044\u307f\u305a\u307b\u307e\u3061",
        "\u30b5\u30c4\u30ca\u30a4\u30df\u30ba\u30db\u30de\u30c1"
    ],
    "wof:name":"Satsunai-mizuhomachi",
    "wof:placetype":"locality"
},
  "geometry": {"coordinates":[143.24836999999999,42.9017],"type":"Point"}
}