{
  "type": "Feature",
  "properties": {
    "gn:admin1_code":"12.0",
    "gn:admin2_code":"7428090.0",
    "gn:admin3_code":"1664.0",
    "gn:asciiname":"Jumonji",
    "gn:country_code":"JP",
    "gn:dem":36,
    "gn:feature_class":"P",
    "gn:feature_code":"PPLL",
    "gn:name":"J\u016bmonji",
    "gn:population":0,
    "gn:timezone":"Asia/Tokyo",
    "iso:country":"JP",
    "name:jpn_x_preferred":[
        "\u5341\u6587\u5b57"
    ],
    "name:jpn_x_variant":[
        "\u3058\u3085\u3046\u3082\u3093\u3058",
        "\u30b8\u30e5\u30a6\u30e2\u30f3\u30b8"
    ],
    "name:und_x_variant":[
        "Jumombira",
        "J\u016bmonhira",
        "J\u016bmombera",
        "J\u016bmonji"
    ],
    "wof:name":"Jumonji",
    "wof:placetype":"locality"
},
  "geometry": {"coordinates":[144.57419999999999,43.3585],"type":"Point"}
}