{
  "type": "Feature",
  "properties": {
    "gn:admin1_code":"33.0",
    "gn:admin2_code":"7391354.0",
    "gn:admin3_code":"41441.0",
    "gn:asciiname":"Jinnouchi",
    "gn:country_code":"JP",
    "gn:dem":12,
    "gn:feature_class":"P",
    "gn:feature_code":"PPLL",
    "gn:name":"Jinnouchi",
    "gn:population":0,
    "gn:timezone":"Asia/Tokyo",
    "iso:country":"JP",
    "name:jpn_x_preferred":[
        "\u9663\u30ce\u5185"
    ],
    "wof:name":"Jinnouchi",
    "wof:placetype":"locality"
},
  "geometry": {"coordinates":[130.18213,33.01065999999999],"type":"Point"}
}