{
  "type": "Feature",
  "properties": {
    "gn:admin1_code":"41.0",
    "gn:admin2_code":"1848276.0",
    "gn:asciiname":"Kaike-onsen",
    "gn:country_code":"JP",
    "gn:dem":5,
    "gn:feature_class":"P",
    "gn:feature_code":"PPL",
    "gn:name":"Kaike-onsen",
    "gn:population":0,
    "gn:timezone":"Asia/Tokyo",
    "iso:country":"JP",
    "name:jpn_x_preferred":[
        "\u7686\u751f\u6e29\u6cc9"
    ],
    "wof:name":"Kaike-onsen",
    "wof:placetype":"locality"
},
  "geometry": {"coordinates":[133.36359999999999,35.4536],"type":"Point"}
}