{
  "type": "Feature",
  "properties": {
    "gn:admin1_code":"37.0",
    "gn:admin2_code":"1854900.0",
    "gn:asciiname":"Higashisawada",
    "gn:country_code":"JP",
    "gn:dem":36,
    "gn:feature_class":"P",
    "gn:feature_code":"PPL",
    "gn:name":"Higashisawada",
    "gn:population":0,
    "gn:timezone":"Asia/Tokyo",
    "iso:country":"JP",
    "name:jpn_x_preferred":[
        "\u6771\u6ca2\u7530"
    ],
    "wof:name":"Higashisawada",
    "wof:placetype":"locality"
},
  "geometry": {"coordinates":[138.85651999999999,35.12672],"type":"Point"}
}