{
  "type": "Feature",
  "properties": {
    "gn:admin1_code":"42.0",
    "gn:admin2_code":"1861653.0",
    "gn:asciiname":"Mitoda",
    "gn:country_code":"JP",
    "gn:dem":15,
    "gn:feature_class":"P",
    "gn:feature_code":"PPL",
    "gn:name":"Mitoda",
    "gn:population":0,
    "gn:timezone":"Asia/Tokyo",
    "iso:country":"JP",
    "name:jpn_x_preferred":[
        "\u6c34\u6238\u7530"
    ],
    "name:jpn_x_variant":[
        "\u307f\u3068\u3060"
    ],
    "wof:name":"Mitoda",
    "wof:placetype":"locality"
},
  "geometry": {"coordinates":[137.07043000000002,36.70542],"type":"Point"}
}