{
  "type": "Feature",
  "properties": {
    "gn:admin1_code":"21.0",
    "gn:admin2_code":"7412706.0",
    "gn:admin3_code":"43447.0",
    "gn:asciiname":"Subaru",
    "gn:country_code":"JP",
    "gn:dem":502,
    "gn:feature_class":"P",
    "gn:feature_code":"PPL",
    "gn:name":"Subaru",
    "gn:population":0,
    "gn:timezone":"Asia/Tokyo",
    "iso:country":"JP",
    "name:jpn_x_preferred":[
        "\u9808\u539f"
    ],
    "name:jpn_x_variant":[
        "\u3059\u3070\u308b",
        "\u30b9\u30d0\u30eb"
    ],
    "wof:name":"Subaru",
    "wof:placetype":"locality"
},
  "geometry": {"coordinates":[131.07623000000001,32.68441],"type":"Point"}
}