{
  "type": "Feature",
  "properties": {
    "gn:admin1_code":"2.0",
    "gn:admin2_code":"2128783.0",
    "gn:asciiname":"Itakoishi",
    "gn:country_code":"JP",
    "gn:dem":55,
    "gn:feature_class":"P",
    "gn:feature_code":"PPL",
    "gn:name":"Itakoishi",
    "gn:population":0,
    "gn:timezone":"Asia/Tokyo",
    "iso:country":"JP",
    "name:jpn_x_preferred":[
        "\u677f\u5b50\u77f3"
    ],
    "name:jpn_x_variant":[
        "\u3044\u305f\u3053\u3044\u3057",
        "\u30a4\u30bf\u30b3\u30a4\u30b7"
    ],
    "wof:name":"Itakoishi",
    "wof:placetype":"locality"
},
  "geometry": {"coordinates":[140.55453,40.29452],"type":"Point"}
}