{
  "type": "Feature",
  "properties": {
    "gn:admin1_code":"22",
    "gn:admin2_code":"1849362.0",
    "gn:asciiname":"Shizukawa",
    "gn:country_code":"JP",
    "gn:dem":48,
    "gn:feature_class":"P",
    "gn:feature_code":"PPL",
    "gn:name":"Shizukawa",
    "gn:population":0,
    "gn:timezone":"Asia/Tokyo",
    "iso:country":"JP",
    "name:jpn_x_preferred":[
        "\u5fd7\u6d25\u5ddd"
    ],
    "name:und_x_variant":[
        "Shizu Gawa",
        "Shitsugawa",
        "Shitsukawa",
        "Shizukawa"
    ],
    "wof:name":"Shizukawa",
    "wof:placetype":"locality"
},
  "geometry": {"coordinates":[135.82606000000001,34.88927],"type":"Point"}
}