{
  "type": "Feature",
  "properties": {
    "iso:country":"JP",
    "qs:name":"\uff11\u4e01\u76ee",
    "qs:name_adm0":"\u65e5\u672c",
    "qs:name_adm1":"\u548c\u6b4c\u5c71\u770c",
    "qs:photos":23,
    "qs:photos_1k":5,
    "qs:photos_9k":1,
    "qs:photos_9r":1,
    "qs:photos_all":23,
    "qs:photos_sr":1,
    "qs:placetype":"Suburb",
    "qs:pop_sr":"0",
    "wof:name":"\uff11\u4e01\u76ee",
    "wof:placetype":"neighbourhood"
},
  "geometry": {"coordinates":[135.94461100000001,33.627866],"type":"Point"}
}