{
  "type": "Feature",
  "properties": {
    "gn:admin1_code":"28.0",
    "gn:admin2_code":"1855604.0",
    "gn:asciiname":"Obocho",
    "gn:country_code":"JP",
    "gn:dem":371,
    "gn:feature_class":"P",
    "gn:feature_code":"PPL",
    "gn:name":"\u014cboch\u014d",
    "gn:population":0,
    "gn:timezone":"Asia/Tokyo",
    "iso:country":"JP",
    "name:jpn_x_preferred":[
        "\u5927\u4fdd\u753a"
    ],
    "name:und_x_variant":[
        "\u014cboch\u014d"
    ],
    "wof:name":"Obocho",
    "wof:placetype":"locality"
},
  "geometry": {"coordinates":[135.95301000000001,34.69326],"type":"Point"}
}