{
  "type": "Feature",
  "properties": {
    "gn:admin1_code":"7.0",
    "gn:admin2_code":"1859306.0",
    "gn:admin3_code":"40103.0",
    "gn:asciiname":"Odake",
    "gn:country_code":"JP",
    "gn:dem":9,
    "gn:feature_class":"P",
    "gn:feature_code":"PPL",
    "gn:name":"Odake",
    "gn:population":0,
    "gn:timezone":"Asia/Tokyo",
    "iso:country":"JP",
    "name:jpn_x_preferred":[
        "\u5c0f\u7af9"
    ],
    "wof:name":"Odake",
    "wof:placetype":"locality"
},
  "geometry": {"coordinates":[130.75148999999999,33.9171],"type":"Point"}
}