{
  "type": "Feature",
  "properties": {
    "gn:admin1_code":"21.0",
    "gn:admin2_code":"1865358.0",
    "gn:asciiname":"Magarisako",
    "gn:country_code":"JP",
    "gn:dem":20,
    "gn:feature_class":"P",
    "gn:feature_code":"PPLL",
    "gn:name":"Magarisako",
    "gn:population":0,
    "gn:timezone":"Asia/Tokyo",
    "iso:country":"JP",
    "name:jpn_x_preferred":[
        "\u66f2\u8feb"
    ],
    "name:jpn_x_variant":[
        "\u307e\u304c\u308a\u3055\u3053",
        "\u30de\u30ac\u30ea\u30b5\u30b3"
    ],
    "wof:name":"Magarisako",
    "wof:placetype":"locality"
},
  "geometry": {"coordinates":[130.36293000000001,32.43223],"type":"Point"}
}