{
  "type": "Feature",
  "properties": {
    "gn:admin1_code":"18",
    "gn:admin2_code":"8714932.0",
    "gn:admin3_code":"46501.0",
    "gn:asciiname":"Hamatsuwaki",
    "gn:country_code":"JP",
    "gn:dem":9,
    "gn:feature_class":"P",
    "gn:feature_code":"PPLL",
    "gn:name":"Hamatsuwaki",
    "gn:population":0,
    "gn:timezone":"Asia/Tokyo",
    "iso:country":"JP",
    "name:jpn_x_preferred":[
        "\u6d5c\u6d25\u8107"
    ],
    "name:und_x_variant":[
        "Hamatsubaki"
    ],
    "wof:name":"Hamatsuwaki",
    "wof:placetype":"locality"
},
  "geometry": {"coordinates":[130.95047,30.60309],"type":"Point"}
}