{
  "type": "Feature",
  "properties": {
    "gn:admin1_code":"13.0",
    "gn:admin2_code":"1859755.0",
    "gn:admin3_code":"28301.0",
    "gn:asciiname":"Yuda",
    "gn:country_code":"JP",
    "gn:dem":101,
    "gn:feature_class":"P",
    "gn:feature_code":"PPL",
    "gn:name":"Y\u016bda",
    "gn:population":0,
    "gn:timezone":"Asia/Tokyo",
    "iso:country":"JP",
    "name:jpn_x_preferred":[
        "\u7d2b\u5408"
    ],
    "name:und_x_variant":[
        "Y\u016bda"
    ],
    "wof:name":"Yuda",
    "wof:placetype":"locality"
},
  "geometry": {"coordinates":[135.37832,34.91062],"type":"Point"}
}