{
  "type": "Feature",
  "properties": {
    "gn:admin1_code":"40",
    "gn:admin2_code":"1858665.0",
    "gn:asciiname":"Susaki",
    "gn:country_code":"JP",
    "gn:dem":15,
    "gn:feature_class":"P",
    "gn:feature_code":"PPL",
    "gn:name":"Susaki",
    "gn:population":0,
    "gn:timezone":"Asia/Tokyo",
    "iso:country":"JP",
    "name:jpn_x_preferred":[
        "\u6771\u967d"
    ],
    "name:und_x_variant":[
        "T\u014dy\u014dch\u014d",
        "Fukagawa-T\u014dy\u014dch\u014d",
        "T\u014dy\u014d",
        "Susakibentench\u014d",
        "Susaki",
        "Fukagawa-Susakibentench\u014d",
        "Fukagawa-Shiozakich\u014d",
        "Hiraich\u014d",
        "Fukagawa-Hiraich\u014d"
    ],
    "wof:name":"Susaki",
    "wof:placetype":"locality"
},
  "geometry": {"coordinates":[139.81456,35.6698],"type":"Point"}
}