{
  "type": "Feature",
  "properties": {
    "iso:country":"JP",
    "qs:name":"\uff11\u4e01\u76ee",
    "qs:name_adm0":"\u65e5\u672c",
    "qs:name_adm1":"\u795e\u5948\u5ddd\u770c",
    "qs:photos":10,
    "qs:photos_1k":2,
    "qs:photos_9k":1,
    "qs:photos_9r":1,
    "qs:photos_all":10,
    "qs:photos_sr":1,
    "qs:placetype":"Suburb",
    "qs:pop_sr":"0",
    "wof:name":"\uff11\u4e01\u76ee",
    "wof:placetype":"neighbourhood"
},
  "geometry": {"coordinates":[139.66416749999999,35.4937385],"type":"Point"}
}