{
  "type": "Feature",
  "properties": {
    "gn:admin1_code":"36",
    "gn:admin2_code":"1863308.0",
    "gn:asciiname":"Haza",
    "gn:country_code":"JP",
    "gn:dem":393,
    "gn:feature_class":"P",
    "gn:feature_code":"PPL",
    "gn:name":"Haza",
    "gn:population":0,
    "gn:timezone":"Asia/Tokyo",
    "iso:country":"JP",
    "name:ceb_x_preferred":[
        "Haza"
    ],
    "name:deu_x_preferred":[
        "Haza"
    ],
    "name:eus_x_preferred":[
        "Haza"
    ],
    "name:fra_x_preferred":[
        "Haza"
    ],
    "name:spa_x_preferred":[
        "Haza"
    ],
    "name:swe_x_preferred":[
        "Haza"
    ],
    "wof:name":"Haza",
    "wof:placetype":"locality"
},
  "geometry": {"coordinates":[132.19999999999999,34.78333],"type":"Point"}
}