{
  "type": "Feature",
  "properties": {
    "gn:admin1_code":"21.0",
    "gn:admin2_code":"7413153.0",
    "gn:asciiname":"Aioi",
    "gn:country_code":"JP",
    "gn:dem":42,
    "gn:feature_class":"P",
    "gn:feature_code":"PPL",
    "gn:name":"Aioi",
    "gn:population":0,
    "gn:timezone":"Asia/Tokyo",
    "iso:country":"JP",
    "name:jpn_x_preferred":[
        "\u5408\u751f"
    ],
    "name:jpn_x_variant":[
        "\u3042\u3044\u304a\u3044",
        "\u30a2\u30a4\u30aa\u30a4"
    ],
    "name:kor_x_preferred":[
        "\uc544\uc774\uc624\uc774"
    ],
    "wof:name":"Aioi",
    "wof:placetype":"locality"
},
  "geometry": {"coordinates":[130.75342000000001,32.91985],"type":"Point"}
}