{
  "type": "Feature",
  "properties": {
    "gn:admin1_code":"3.0",
    "gn:admin2_code":"2130056.0",
    "gn:asciiname":"Kumajima",
    "gn:country_code":"JP",
    "gn:dem":36,
    "gn:feature_class":"P",
    "gn:feature_code":"PPL",
    "gn:name":"Kumajima",
    "gn:population":0,
    "gn:timezone":"Asia/Tokyo",
    "iso:country":"JP",
    "name:jpn_x_preferred":[
        "\u718a\u5d8b"
    ],
    "name:jpn_x_variant":[
        "\u304f\u307e\u3058\u307e",
        "\u30af\u30de\u30b8\u30de"
    ],
    "wof:name":"Kumajima",
    "wof:placetype":"locality"
},
  "geometry": {"coordinates":[140.43951000000001,40.61476],"type":"Point"}
}