{
  "type": "Feature",
  "properties": {
    "gn:admin1_code":"34.0",
    "gn:admin2_code":"1849187.0",
    "gn:admin3_code":"11107.0",
    "gn:asciiname":"Higashi-takasagocho",
    "gn:country_code":"JP",
    "gn:dem":15,
    "gn:feature_class":"P",
    "gn:feature_code":"PPL",
    "gn:name":"Higashi-takasagoch\u014d",
    "gn:population":0,
    "gn:timezone":"Asia/Tokyo",
    "iso:country":"JP",
    "name:jpn_x_preferred":[
        "\u6771\u9ad8\u7802\u753a"
    ],
    "name:jpn_x_variant":[
        "\u3072\u304c\u3057\u305f\u304b\u3055\u3054\u3061\u3087\u3046",
        "\u30d2\u30ac\u30b7\u30bf\u30ab\u30b5\u30b4\u30c1\u30e7\u30a6"
    ],
    "name:und_x_variant":[
        "Higashi-takasagoch\u014d"
    ],
    "wof:name":"Higashi-takasagocho",
    "wof:placetype":"locality"
},
  "geometry": {"coordinates":[139.66003000000001,35.85675999999999],"type":"Point"}
}