{
  "type": "Feature",
  "properties": {
    "gn:admin1_code":"27",
    "gn:admin2_code":"1852895.0",
    "gn:asciiname":"Ionouracho",
    "gn:country_code":"JP",
    "gn:dem":9,
    "gn:feature_class":"P",
    "gn:feature_code":"PPL",
    "gn:name":"Ionourach\u014d",
    "gn:population":0,
    "gn:timezone":"Asia/Tokyo",
    "iso:country":"JP",
    "name:jpn_x_preferred":[
        "\u5eb5\u6d66\u753a"
    ],
    "name:und_x_variant":[
        "Iorinouramachi",
        "Ionourach\u014d",
        "Ionouramen",
        "Ionda",
        "Ionoura"
    ],
    "wof:name":"Ionouracho",
    "wof:placetype":"locality"
},
  "geometry": {"coordinates":[129.70353,33.12621],"type":"Point"}
}