{
  "type": "Feature",
  "properties": {
    "gn:admin1_code":"21.0",
    "gn:admin2_code":"1859490.0",
    "gn:admin3_code":"43404.0",
    "gn:asciiname":"Shinmachi",
    "gn:country_code":"JP",
    "gn:dem":83,
    "gn:feature_class":"P",
    "gn:feature_code":"PPLL",
    "gn:name":"Shinmachi",
    "gn:population":0,
    "gn:timezone":"Asia/Tokyo",
    "iso:country":"JP",
    "name:fra_x_preferred":[
        "Shinmachi"
    ],
    "name:jpn_x_preferred":[
        "\u65b0\u753a"
    ],
    "name:jpn_x_variant":[
        "\u3057\u3093\u307e\u3061",
        "\u30b7\u30f3\u30de\u30c1",
        "\u65b0\u753a\u904a\u5ed3"
    ],
    "wof:name":"Shinmachi",
    "wof:placetype":"locality"
},
  "geometry": {"coordinates":[130.82359,32.86785],"type":"Point"}
}