{
  "type": "Feature",
  "properties": {
    "gn:admin1_code":"28.0",
    "gn:admin2_code":"7411377.0",
    "gn:admin3_code":"29322.0",
    "gn:asciiname":"Hirose",
    "gn:country_code":"JP",
    "gn:dem":169,
    "gn:feature_class":"P",
    "gn:feature_code":"PPL",
    "gn:name":"Hirose",
    "gn:population":0,
    "gn:timezone":"Asia/Tokyo",
    "iso:country":"JP",
    "name:deu_x_preferred":[
        "Hirose"
    ],
    "name:ita_x_preferred":[
        "Hirose"
    ],
    "name:jpn_x_preferred":[
        "\u5e83\u702c"
    ],
    "name:kor_x_preferred":[
        "\ud788\ub85c\uc138"
    ],
    "name:rus_x_preferred":[
        "\u0425\u0438\u0440\u043e\u0441\u044d"
    ],
    "wof:name":"Hirose",
    "wof:placetype":"locality"
},
  "geometry": {"coordinates":[136.07813999999999,34.67698],"type":"Point"}
}