{
  "type": "Feature",
  "properties": {
    "gn:admin1_code":"3.0",
    "gn:admin2_code":"2130225.0",
    "gn:asciiname":"Komagari",
    "gn:country_code":"JP",
    "gn:dem":7,
    "gn:feature_class":"P",
    "gn:feature_code":"PPL",
    "gn:name":"Komagari",
    "gn:population":0,
    "gn:timezone":"Asia/Tokyo",
    "iso:country":"JP",
    "name:jpn_x_preferred":[
        "\u5c0f\u66f2"
    ],
    "name:jpn_x_variant":[
        "\u3053\u307e\u304c\u308a",
        "\u30b3\u30de\u30ac\u30ea"
    ],
    "wof:name":"Komagari",
    "wof:placetype":"locality"
},
  "geometry": {"coordinates":[140.42466000000002,40.81361],"type":"Point"}
}