{
  "type": "Feature",
  "properties": {
    "gn:admin1_code":"40",
    "gn:admin2_code":"7475134.0",
    "gn:asciiname":"Minowa",
    "gn:country_code":"JP",
    "gn:dem":9,
    "gn:feature_class":"P",
    "gn:feature_code":"PPL",
    "gn:name":"Minowa",
    "gn:population":0,
    "gn:timezone":"Asia/Tokyo",
    "iso:country":"JP",
    "name:deu_x_preferred":[
        "Minowa"
    ],
    "name:jpn_x_preferred":[
        "\u4e09\u30ce\u8f2a"
    ],
    "name:kor_x_preferred":[
        "\ubbf8\ub178\uc640"
    ],
    "wof:name":"Minowa",
    "wof:placetype":"locality"
},
  "geometry": {"coordinates":[139.79223000000002,35.72811],"type":"Point"}
}