{
  "type": "Feature",
  "properties": {
    "gn:admin1_code":"29",
    "gn:admin2_code":"1856195.0",
    "gn:asciiname":"Teradomari-koshimizu",
    "gn:country_code":"JP",
    "gn:dem":78,
    "gn:feature_class":"P",
    "gn:feature_code":"PPL",
    "gn:name":"Teradomari-k\u014dshimizu",
    "gn:population":0,
    "gn:timezone":"Asia/Tokyo",
    "iso:country":"JP",
    "name:jpn_x_preferred":[
        "\u5bfa\u6cca\u9999\u6e05\u6c34"
    ],
    "name:und_x_variant":[
        "Teradomari-k\u014dshimizu",
        "Teradomari"
    ],
    "wof:name":"Teradomari-koshimizu",
    "wof:placetype":"locality"
},
  "geometry": {"coordinates":[138.76685000000001,37.63312],"type":"Point"}
}