{
  "type": "Feature",
  "properties": {
    "gn:admin1_code":"19",
    "gn:admin2_code":"1859635.0",
    "gn:admin3_code":"14131.0",
    "gn:asciiname":"Watarida-higashicho",
    "gn:country_code":"JP",
    "gn:dem":2,
    "gn:feature_class":"P",
    "gn:feature_code":"PPL",
    "gn:name":"Watarida-higashich\u014d",
    "gn:population":0,
    "gn:timezone":"Asia/Tokyo",
    "iso:country":"JP",
    "name:jpn_x_preferred":[
        "\u6e21\u7530\u6771\u753a"
    ],
    "name:und_x_variant":[
        "Watarida-higashich\u014d",
        "Higashi-watarida"
    ],
    "wof:name":"Watarida-higashicho",
    "wof:placetype":"locality"
},
  "geometry": {"coordinates":[139.7079,35.51839000000001],"type":"Point"}
}