{
  "type": "Feature",
  "properties": {
    "gn:admin1_code":"45.0",
    "gn:admin2_code":"1852222.0",
    "gn:asciiname":"Akamacho",
    "gn:country_code":"JP",
    "gn:dem":6,
    "gn:feature_class":"P",
    "gn:feature_code":"PPL",
    "gn:name":"Akamach\u014d",
    "gn:population":0,
    "gn:timezone":"Asia/Tokyo",
    "iso:country":"JP",
    "name:jpn_x_preferred":[
        "\u8d64\u9593\u753a"
    ],
    "name:und_x_variant":[
        "Akamach\u014d"
    ],
    "wof:name":"Akamacho",
    "wof:placetype":"locality"
},
  "geometry": {"coordinates":[130.94436000000002,33.95933],"type":"Point"}
}