{
  "type": "Feature",
  "properties": {
    "gn:admin1_code":"37.0",
    "gn:admin2_code":"1854900.0",
    "gn:asciiname":"Togaya",
    "gn:country_code":"JP",
    "gn:dem":15,
    "gn:feature_class":"P",
    "gn:feature_code":"PPLL",
    "gn:name":"Togaya",
    "gn:population":0,
    "gn:timezone":"Asia/Tokyo",
    "iso:country":"JP",
    "name:jpn_x_preferred":[
        "\u6238\u30f6\u8c37"
    ],
    "wof:name":"Togaya",
    "wof:placetype":"locality"
},
  "geometry": {"coordinates":[138.90361999999999,35.06748],"type":"Point"}
}