{
  "type": "Feature",
  "properties": {
    "gn:admin1_code":"12.0",
    "gn:admin2_code":"7428114.0",
    "gn:admin3_code":"1649.0",
    "gn:asciiname":"Kawakami",
    "gn:country_code":"JP",
    "gn:dem":244,
    "gn:feature_class":"P",
    "gn:feature_code":"PPL",
    "gn:name":"Kawakami",
    "gn:population":0,
    "gn:timezone":"Asia/Tokyo",
    "iso:country":"JP",
    "name:ceb_x_preferred":[
        "Kawakami"
    ],
    "name:deu_x_preferred":[
        "Kawakami"
    ],
    "name:fra_x_preferred":[
        "Kawakami"
    ],
    "name:ita_x_preferred":[
        "Kawakami"
    ],
    "name:jpn_x_preferred":[
        "\u5ddd\u4e0a"
    ],
    "name:jpn_x_variant":[
        "\u304b\u308f\u304b\u307f",
        "\u30ab\u30ef\u30ab\u30df",
        "\u5ddd\u4e0a\u6751"
    ],
    "name:kor_x_preferred":[
        "\uac00\uc640\uce74\ubbf8\ucd0c"
    ],
    "name:rus_x_preferred":[
        "\u041a\u0430\u0432\u0430\u043a\u0430\u043c\u0438"
    ],
    "name:ukr_x_preferred":[
        "\u041a\u0430\u0432\u0430\u043a\u0430\u043c\u0456"
    ],
    "name:und_x_variant":[
        "Kamikawa",
        "Kami-kawakami"
    ],
    "wof:name":"Kawakami",
    "wof:placetype":"locality"
},
  "geometry": {"coordinates":[143.69574,43.14131],"type":"Point"}
}