{
  "type": "Feature",
  "properties": {
    "gn:admin1_code":"12.0",
    "gn:admin2_code":"7428114.0",
    "gn:admin3_code":"1649.0",
    "gn:asciiname":"Kawakami",
    "gn:country_code":"JP",
    "gn:dem":244,
    "gn:feature_class":"P",
    "gn:feature_code":"PPL",
    "gn:name":"Kawakami",
    "gn:population":0,
    "gn:timezone":"Asia/Tokyo",
    "iso:country":"JP",
    "name:jpn_x_preferred":[
        "\u5ddd\u4e0a"
    ],
    "name:jpn_x_variant":[
        "\u304b\u308f\u304b\u307f",
        "\u30ab\u30ef\u30ab\u30df"
    ],
    "name:und_x_variant":[
        "Kamikawa",
        "Kami-kawakami"
    ],
    "wof:name":"Kawakami",
    "wof:placetype":"locality"
},
  "geometry": {"coordinates":[143.69574,43.14131],"type":"Point"}
}