{
  "type": "Feature",
  "properties": {
    "gn:admin1_code":"34.0",
    "gn:admin2_code":"1859726.0",
    "gn:asciiname":"Godo",
    "gn:country_code":"JP",
    "gn:dem":19,
    "gn:feature_class":"P",
    "gn:feature_code":"PPL",
    "gn:name":"G\u014ddo",
    "gn:population":0,
    "gn:timezone":"Asia/Tokyo",
    "iso:country":"JP",
    "name:ceb_x_preferred":[
        "Godo"
    ],
    "name:deu_x_preferred":[
        "Godo"
    ],
    "name:fra_x_preferred":[
        "Godo"
    ],
    "name:jpn_x_preferred":[
        "\u795e\u6238"
    ],
    "name:jpn_x_variant":[
        "\u3054\u3046\u3069",
        "\u30b4\u30a6\u30c9"
    ],
    "name:spa_x_preferred":[
        "Godo"
    ],
    "name:swe_x_preferred":[
        "Godo"
    ],
    "name:ukr_x_preferred":[
        "\u0490\u043e\u0434\u043e"
    ],
    "name:und_x_variant":[
        "G\u014ddo"
    ],
    "wof:name":"Godo",
    "wof:placetype":"locality"
},
  "geometry": {"coordinates":[139.72574,35.85293],"type":"Point"}
}