{
  "type": "Feature",
  "properties": {
    "gn:admin1_code":"21.0",
    "gn:admin2_code":"1865168.0",
    "gn:asciiname":"Hachimandai",
    "gn:country_code":"JP",
    "gn:dem":21,
    "gn:feature_class":"P",
    "gn:feature_code":"PPL",
    "gn:name":"Hachimandai",
    "gn:population":0,
    "gn:timezone":"Asia/Tokyo",
    "iso:country":"JP",
    "name:jpn_x_preferred":[
        "\u516b\u5e61\u53f0"
    ],
    "name:jpn_x_variant":[
        "\u306f\u3061\u307e\u3093\u3060\u3044",
        "\u30cf\u30c1\u30de\u30f3\u30c0\u30a4"
    ],
    "wof:name":"Hachimandai",
    "wof:placetype":"locality"
},
  "geometry": {"coordinates":[130.48287999999999,32.96567],"type":"Point"}
}