{
  "type": "Feature",
  "properties": {
    "gn:admin1_code":"9.0",
    "gn:admin2_code":"1850890.0",
    "gn:asciiname":"Shokawacho-nakahata",
    "gn:country_code":"JP",
    "gn:dem":788,
    "gn:feature_class":"P",
    "gn:feature_code":"PPL",
    "gn:name":"Sh\u014dkawach\u014d-nakahata",
    "gn:population":0,
    "gn:timezone":"Asia/Tokyo",
    "iso:country":"JP",
    "name:jpn_x_preferred":[
        "\u8358\u5ddd\u753a\u4e2d\u7551"
    ],
    "name:und_x_variant":[
        "Sh\u014dkawach\u014d-nakahata"
    ],
    "wof:name":"Shokawacho-nakahata",
    "wof:placetype":"locality"
},
  "geometry": {"coordinates":[136.95171000000002,36.04231],"type":"Point"}
}