{
  "type": "Feature",
  "properties": {
    "gn:admin1_code":"4.0",
    "gn:admin2_code":"2112557.0",
    "gn:admin3_code":"12441.0",
    "gn:asciiname":"Odoro",
    "gn:country_code":"JP",
    "gn:dem":31,
    "gn:feature_class":"P",
    "gn:feature_code":"PPLL",
    "gn:name":"Odoro",
    "gn:population":0,
    "gn:timezone":"Asia/Tokyo",
    "iso:country":"JP",
    "name:jpn_x_preferred":[
        "\u5c0f\u571f\u5442"
    ],
    "name:jpn_x_variant":[
        "\u304a\u3069\u308d",
        "\u30aa\u30c9\u30ed"
    ],
    "wof:name":"Odoro",
    "wof:placetype":"locality"
},
  "geometry": {"coordinates":[140.24582000000001,35.30984],"type":"Point"}
}