{
  "type": "Feature",
  "properties": {
    "gn:admin1_code":"24.0",
    "gn:admin2_code":"2112574.0",
    "gn:asciiname":"Sakaeda",
    "gn:country_code":"JP",
    "gn:dem":3,
    "gn:feature_class":"P",
    "gn:feature_code":"PPL",
    "gn:name":"Sakaeda",
    "gn:population":0,
    "gn:timezone":"Asia/Tokyo",
    "iso:country":"JP",
    "name:jpn_x_preferred":[
        "\u6804\u7530"
    ],
    "name:jpn_x_variant":[
        "\u3055\u304b\u3048\u3060",
        "\u30b5\u30ab\u30a8\u30c0"
    ],
    "wof:name":"Sakaeda",
    "wof:placetype":"locality"
},
  "geometry": {"coordinates":[141.35048999999995,38.42195],"type":"Point"}
}