{
  "type": "Feature",
  "properties": {
    "gn:admin1_code":"4.0",
    "gn:admin2_code":"7465521.0",
    "gn:asciiname":"Moto'ori",
    "gn:country_code":"JP",
    "gn:dem":18,
    "gn:feature_class":"P",
    "gn:feature_code":"PPL",
    "gn:name":"Moto\u2019ori",
    "gn:population":0,
    "gn:timezone":"Asia/Tokyo",
    "iso:country":"JP",
    "name:jpn_x_preferred":[
        "\u672c\u7e54"
    ],
    "name:jpn_x_variant":[
        "\u3082\u3068\u304a\u308a",
        "\u30e2\u30c8\u30aa\u30ea"
    ],
    "name:und_x_variant":[
        "Moto\u2019ori"
    ],
    "wof:name":"Moto'ori",
    "wof:placetype":"locality"
},
  "geometry": {"coordinates":[139.89666,35.01689],"type":"Point"}
}