{
  "type": "Feature",
  "properties": {
    "iso:country":"JP",
    "name:eng_x_preferred":[
        "Takanabe"
    ],
    "name:eng_x_variant":[
        "Takanabe Town"
    ],
    "name:jpn_x_preferred":[
        "\u9ad8\u934b\u753a"
    ],
    "qs:name":"\u9ad8\u934b\u753a",
    "qs:name_adm0":"\u65e5\u672c",
    "qs:name_adm1":"\u5bae\u5d0e\u770c",
    "qs:photos":36,
    "qs:photos_1k":7,
    "qs:photos_9k":1,
    "qs:photos_9r":2,
    "qs:photos_all":36,
    "qs:photos_sr":2,
    "qs:placetype":"Town",
    "qs:pop_sr":"0",
    "wof:name":"Takanabe",
    "wof:placetype":"locality"
},
  "geometry": {"coordinates":[131.53398100000001,32.122871],"type":"Point"}
}