{
  "type": "Feature",
  "properties": {
    "gn:admin1_code":"18",
    "gn:admin2_code":"8300556.0",
    "gn:asciiname":"Kihokucho-kamimobiki",
    "gn:country_code":"JP",
    "gn:dem":263,
    "gn:feature_class":"P",
    "gn:feature_code":"PPL",
    "gn:name":"Kihokuch\u014d-kamimobiki",
    "gn:population":0,
    "gn:timezone":"Asia/Tokyo",
    "iso:country":"JP",
    "name:jpn_x_preferred":[
        "\u8f1d\u5317\u753a\u4e0a\u767e\u5f15"
    ],
    "name:und_x_variant":[
        "Fumoto",
        "Mobiki",
        "Kihokuch\u014d-kamimobiki"
    ],
    "wof:name":"Kihokucho-kamimobiki",
    "wof:placetype":"locality"
},
  "geometry": {"coordinates":[130.86667,31.55],"type":"Point"}
}