{
  "type": "Feature",
  "properties": {
    "gn:admin1_code":"21.0",
    "gn:admin2_code":"1864973.0",
    "gn:asciiname":"Namino-namino",
    "gn:country_code":"JP",
    "gn:dem":808,
    "gn:feature_class":"P",
    "gn:feature_code":"PPL",
    "gn:name":"Namino-namino",
    "gn:population":0,
    "gn:timezone":"Asia/Tokyo",
    "iso:country":"JP",
    "name:jpn_x_preferred":[
        "\u6ce2\u91ce\u6ce2\u91ce"
    ],
    "name:jpn_x_variant":[
        "\u306a\u307f\u306e\u306a\u307f\u306e",
        "\u30ca\u30df\u30ce\u30ca\u30df\u30ce"
    ],
    "wof:name":"Namino-namino",
    "wof:placetype":"locality"
},
  "geometry": {"coordinates":[131.18006,32.90732],"type":"Point"}
}