{
  "type": "Feature",
  "properties": {
    "gn:admin1_code":"45.0",
    "gn:admin2_code":"1852222.0",
    "gn:asciiname":"Shinchicho",
    "gn:country_code":"JP",
    "gn:dem":5,
    "gn:feature_class":"P",
    "gn:feature_code":"PPL",
    "gn:name":"Shinchich\u014d",
    "gn:population":0,
    "gn:timezone":"Asia/Tokyo",
    "iso:country":"JP",
    "name:jpn_x_preferred":[
        "\u65b0\u5730\u753a"
    ],
    "name:und_x_variant":[
        "Shinchich\u014d"
    ],
    "wof:name":"Shinchicho",
    "wof:placetype":"locality"
},
  "geometry": {"coordinates":[130.92171000000002,33.95591],"type":"Point"}
}