{
  "type": "Feature",
  "properties": {
    "gn:admin1_code":"7.0",
    "gn:admin2_code":"1859306.0",
    "gn:admin3_code":"40103.0",
    "gn:asciiname":"An'ya",
    "gn:country_code":"JP",
    "gn:dem":18,
    "gn:feature_class":"P",
    "gn:feature_code":"PPL",
    "gn:name":"An\u2019ya",
    "gn:population":0,
    "gn:timezone":"Asia/Tokyo",
    "iso:country":"JP",
    "name:jpn_x_preferred":[
        "\u5b89\u5c4b"
    ],
    "name:und_x_variant":[
        "An\u2019ya"
    ],
    "wof:name":"An'ya",
    "wof:placetype":"locality"
},
  "geometry": {"coordinates":[130.71531000000002,33.92944],"type":"Point"}
}