{
  "type": "Feature",
  "properties": {
    "gn:admin1_code":"12.0",
    "gn:asciiname":"Pommai",
    "gn:cc2":"JP",
    "gn:country_code":"JP",
    "gn:dem":-9999,
    "gn:feature_class":"P",
    "gn:feature_code":"PPL",
    "gn:name":"Pommai",
    "gn:population":0,
    "gn:timezone":"Asia/Tokyo",
    "iso:country":"JP",
    "name:und_x_variant":[
        "Pommae",
        "Pommai"
    ],
    "wof:name":"Pommai",
    "wof:placetype":"locality"
},
  "geometry": {"coordinates":[140.91666999999995,43.21667],"type":"Point"}
}