{
  "type": "Feature",
  "properties": {
    "gn:admin1_code":"21.0",
    "gn:admin2_code":"1850743.0",
    "gn:asciiname":"Mitsukawa",
    "gn:country_code":"JP",
    "gn:dem":101,
    "gn:feature_class":"P",
    "gn:feature_code":"PPL",
    "gn:name":"Mitsukawa",
    "gn:population":0,
    "gn:timezone":"Asia/Tokyo",
    "iso:country":"JP",
    "name:jpn_x_preferred":[
        "\u4e09\u30c3\u5ddd"
    ],
    "name:jpn_x_variant":[
        "\u307f\u3064\u304b\u308f",
        "\u30df\u30c4\u30ab\u30ef"
    ],
    "wof:name":"Mitsukawa",
    "wof:placetype":"locality"
},
  "geometry": {"coordinates":[130.55749,32.98629],"type":"Point"}
}