{
  "type": "Feature",
  "properties": {
    "gn:admin1_code":"14.0",
    "gn:admin2_code":"7452802.0",
    "gn:asciiname":"Onami",
    "gn:country_code":"JP",
    "gn:dem":24,
    "gn:feature_class":"P",
    "gn:feature_code":"PPLL",
    "gn:name":"\u014cnami",
    "gn:population":0,
    "gn:timezone":"Asia/Tokyo",
    "iso:country":"JP",
    "name:jpn_x_preferred":[
        "\u5927\u4e26"
    ],
    "name:und_x_variant":[
        "\u014cnami"
    ],
    "wof:name":"Onami",
    "wof:placetype":"locality"
},
  "geometry": {"coordinates":[139.93743000000001,35.99091],"type":"Point"}
}