{
  "type": "Feature",
  "properties": {
    "gn:admin1_code":"27",
    "gn:admin2_code":"7418804.0",
    "gn:asciiname":"Narumachi-ura",
    "gn:country_code":"JP",
    "gn:dem":28,
    "gn:feature_class":"P",
    "gn:feature_code":"PPL",
    "gn:name":"Narumachi-ura",
    "gn:population":0,
    "gn:timezone":"Asia/Tokyo",
    "iso:country":"JP",
    "name:jpn_x_preferred":[
        "\u5948\u7559\u753a\u6d66"
    ],
    "name:und_x_variant":[
        "Naru"
    ],
    "wof:name":"Narumachi-ura",
    "wof:placetype":"locality"
},
  "geometry": {"coordinates":[128.93180000000001,32.83209],"type":"Point"}
}