{
  "type": "Feature",
  "properties": {
    "gn:admin1_code":"3.0",
    "gn:admin2_code":"2130654.0",
    "gn:asciiname":"Komagome",
    "gn:country_code":"JP",
    "gn:dem":616,
    "gn:feature_class":"P",
    "gn:feature_code":"PPL",
    "gn:name":"Komagome",
    "gn:population":0,
    "gn:timezone":"Asia/Tokyo",
    "iso:country":"JP",
    "name:jpn_x_preferred":[
        "\u99d2\u8fbc"
    ],
    "name:jpn_x_variant":[
        "\u3053\u307e\u3054\u3081",
        "\u30b3\u30de\u30b4\u30e1"
    ],
    "wof:name":"Komagome",
    "wof:placetype":"locality"
},
  "geometry": {"coordinates":[140.92644999999999,40.6889],"type":"Point"}
}