{
  "type": "Feature",
  "properties": {
    "gn:admin1_code":"4.0",
    "gn:admin2_code":"7465524.0",
    "gn:asciiname":"Nishifukira",
    "gn:country_code":"JP",
    "gn:dem":12,
    "gn:feature_class":"P",
    "gn:feature_code":"PPLL",
    "gn:name":"Nishifukira",
    "gn:population":0,
    "gn:timezone":"Asia/Tokyo",
    "iso:country":"JP",
    "name:jpn_x_preferred":[
        "\u897f\u5439\u826f"
    ],
    "name:jpn_x_variant":[
        "\u306b\u3057\u3075\u304d\u3089",
        "\u30cb\u30b7\u30d5\u30ad\u30e9"
    ],
    "wof:name":"Nishifukira",
    "wof:placetype":"locality"
},
  "geometry": {"coordinates":[140.33061000000001,35.30515],"type":"Point"}
}