{
  "type": "Feature",
  "properties": {
    "gn:admin1_code":"16.0",
    "gn:admin2_code":"2112822.0",
    "gn:asciiname":"Kuzusaka",
    "gn:country_code":"JP",
    "gn:dem":151,
    "gn:feature_class":"P",
    "gn:feature_code":"PPL",
    "gn:name":"Kuzusaka",
    "gn:population":0,
    "gn:timezone":"Asia/Tokyo",
    "iso:country":"JP",
    "name:jpn_x_preferred":[
        "\u845b\u5742"
    ],
    "name:jpn_x_variant":[
        "\u304f\u305a\u3055\u304b",
        "\u30af\u30ba\u30b5\u30ab"
    ],
    "wof:name":"Kuzusaka",
    "wof:placetype":"locality"
},
  "geometry": {"coordinates":[141.20490000000001,39.47284000000001],"type":"Point"}
}