{
  "type": "Feature",
  "properties": {
    "gn:admin1_code":"33",
    "gn:admin2_code":"8300623.0",
    "gn:asciiname":"Higashioshimamachi",
    "gn:country_code":"JP",
    "gn:dem":5,
    "gn:feature_class":"P",
    "gn:feature_code":"PPL",
    "gn:name":"Higashi\u014dshimamachi",
    "gn:population":0,
    "gn:timezone":"Asia/Tokyo",
    "iso:country":"JP",
    "name:jpn_x_preferred":[
        "\u6771\u5927\u5cf6\u753a"
    ],
    "name:und_x_variant":[
        "Higashi\u014dshimamachi",
        "\u014cshima",
        "Higashi\u014dshima"
    ],
    "wof:name":"Higashioshimamachi",
    "wof:placetype":"locality"
},
  "geometry": {"coordinates":[129.96402,33.47282],"type":"Point"}
}