{
  "type": "Feature",
  "properties": {
    "gn:admin1_code":"25.0",
    "gn:admin2_code":"1864313.0",
    "gn:asciiname":"Ekimae",
    "gn:country_code":"JP",
    "gn:dem":278,
    "gn:feature_class":"P",
    "gn:feature_code":"PPLL",
    "gn:name":"Ekimae",
    "gn:population":0,
    "gn:timezone":"Asia/Tokyo",
    "iso:country":"JP",
    "name:jpn_x_preferred":[
        "\u99c5\u524d"
    ],
    "name:jpn_x_variant":[
        "\u3048\u304d\u307e\u3048",
        "\u30a8\u30ad\u30de\u30a8"
    ],
    "wof:name":"Ekimae",
    "wof:placetype":"locality"
},
  "geometry": {"coordinates":[130.87171999999998,32.03351],"type":"Point"}
}