{
  "type": "Feature",
  "properties": {
    "gn:admin1_code":"19.0",
    "gn:admin2_code":"1864928.0",
    "gn:asciiname":"Shimomaegawara",
    "gn:country_code":"JP",
    "gn:dem":31,
    "gn:feature_class":"P",
    "gn:feature_code":"PPLL",
    "gn:name":"Shimomaegawara",
    "gn:population":0,
    "gn:timezone":"Asia/Tokyo",
    "iso:country":"JP",
    "name:jpn_x_preferred":[
        "\u4e0b\u524d\u6cb3\u539f"
    ],
    "wof:name":"Shimomaegawara",
    "wof:placetype":"locality"
},
  "geometry": {"coordinates":[139.357,35.47533],"type":"Point"}
}