{
  "type": "Feature",
  "properties": {
    "gn:admin1_code":"18.0",
    "gn:admin2_code":"1862007.0",
    "gn:asciiname":"Yamagawa-shiomicho",
    "gn:country_code":"JP",
    "gn:dem":7,
    "gn:feature_class":"P",
    "gn:feature_code":"PPL",
    "gn:name":"Yamagawa-shiomich\u014d",
    "gn:population":0,
    "gn:timezone":"Asia/Tokyo",
    "iso:country":"JP",
    "name:jpn_x_preferred":[
        "\u5c71\u5ddd\u6f6e\u898b\u753a"
    ],
    "name:und_x_variant":[
        "Yamagawa-shiomich\u014d"
    ],
    "wof:name":"Yamagawa-shiomicho",
    "wof:placetype":"locality"
},
  "geometry": {"coordinates":[130.64070000000001,31.20428],"type":"Point"}
}