{
  "type": "Feature",
  "properties": {
    "gn:admin1_code":"29",
    "gn:admin2_code":"7468182.0",
    "gn:asciiname":"Kurokawa",
    "gn:country_code":"JP",
    "gn:dem":46,
    "gn:feature_class":"P",
    "gn:feature_code":"PPL",
    "gn:name":"Kurokawa",
    "gn:population":0,
    "gn:timezone":"Asia/Tokyo",
    "iso:country":"JP",
    "name:jpn_x_preferred":[
        "\u9ed2\u5ddd"
    ],
    "wof:name":"Kurokawa",
    "wof:placetype":"locality"
},
  "geometry": {"coordinates":[139.43896999999998,38.07864],"type":"Point"}
}