{
  "type": "Feature",
  "properties": {
    "gn:admin1_code":"21.0",
    "gn:admin2_code":"7412706.0",
    "gn:admin3_code":"43447.0",
    "gn:asciiname":"Toshio",
    "gn:country_code":"JP",
    "gn:dem":583,
    "gn:feature_class":"P",
    "gn:feature_code":"PPLL",
    "gn:name":"Toshio",
    "gn:population":0,
    "gn:timezone":"Asia/Tokyo",
    "iso:country":"JP",
    "name:jpn_x_preferred":[
        "\u6597\u5869"
    ],
    "name:jpn_x_variant":[
        "\u3068\u3057\u304a",
        "\u30c8\u30b7\u30aa"
    ],
    "wof:name":"Toshio",
    "wof:placetype":"locality"
},
  "geometry": {"coordinates":[131.12918999999999,32.71074],"type":"Point"}
}