{
  "type": "Feature",
  "properties": {
    "gn:admin1_code":"4.0",
    "gn:admin2_code":"2112386.0",
    "gn:asciiname":"Kozuka",
    "gn:country_code":"JP",
    "gn:dem":216,
    "gn:feature_class":"P",
    "gn:feature_code":"PPL",
    "gn:name":"Kozuka",
    "gn:population":0,
    "gn:timezone":"Asia/Tokyo",
    "iso:country":"JP",
    "name:jpn_x_preferred":[
        "\u91d1\u675f"
    ],
    "name:jpn_x_variant":[
        "\u3053\u3065\u304b",
        "\u30b3\u30c5\u30ab"
    ],
    "wof:name":"Kozuka",
    "wof:placetype":"locality"
},
  "geometry": {"coordinates":[139.95079999999999,35.14604],"type":"Point"}
}