{
  "type": "Feature",
  "properties": {
    "gn:admin1_code":"24.0",
    "gn:admin2_code":"2111130.0",
    "gn:admin3_code":"4324.0",
    "gn:asciiname":"Aone-onsen",
    "gn:country_code":"JP",
    "gn:dem":620,
    "gn:feature_class":"P",
    "gn:feature_code":"PPL",
    "gn:name":"Aone-onsen",
    "gn:population":0,
    "gn:timezone":"Asia/Tokyo",
    "iso:country":"JP",
    "name:jpn_x_preferred":[
        "\u9752\u6839\u6e29\u6cc9"
    ],
    "name:und_x_variant":[
        "Aone"
    ],
    "wof:name":"Aone-onsen",
    "wof:placetype":"locality"
},
  "geometry": {"coordinates":[140.53361000000001,38.14194000000001],"type":"Point"}
}