{
  "type": "Feature",
  "properties": {
    "gn:admin1_code":"9.0",
    "gn:admin2_code":"1850890.0",
    "gn:asciiname":"Kugunocho-yanajima",
    "gn:country_code":"JP",
    "gn:dem":687,
    "gn:feature_class":"P",
    "gn:feature_code":"PPL",
    "gn:name":"Kugunoch\u014d-yanajima",
    "gn:population":0,
    "gn:timezone":"Asia/Tokyo",
    "iso:country":"JP",
    "name:jpn_x_preferred":[
        "\u4e45\u3005\u91ce\u753a\u67f3\u5cf6"
    ],
    "name:und_x_variant":[
        "Kugunoch\u014d-yanajima"
    ],
    "wof:name":"Kugunocho-yanajima",
    "wof:placetype":"locality"
},
  "geometry": {"coordinates":[137.29541,36.07604],"type":"Point"}
}