{
  "type": "Feature",
  "properties": {
    "iso:country":"JP",
    "qs:name":"\u4e94\u5cf6\u5e02",
    "qs:name_adm0":"\u65e5\u672c",
    "qs:name_adm1":"\u9577\u5d0e\u770c",
    "qs:photos":494,
    "qs:photos_1k":100,
    "qs:photos_9k":2,
    "qs:photos_9r":5,
    "qs:photos_all":529,
    "qs:photos_sr":7,
    "qs:placetype":"Town",
    "qs:pop_sr":"0",
    "wof:name":"\u4e94\u5cf6\u5e02",
    "wof:placetype":"locality"
},
  "geometry": {"coordinates":[128.79272399999999,32.689087],"type":"Point"}
}