{
  "type": "Feature",
  "properties": {
    "gn:admin1_code":"27.0",
    "gn:admin2_code":"1852895.0",
    "gn:asciiname":"Kashimaecho",
    "gn:country_code":"JP",
    "gn:dem":15,
    "gn:feature_class":"P",
    "gn:feature_code":"PPL",
    "gn:name":"Kashimaech\u014d",
    "gn:population":0,
    "gn:timezone":"Asia/Tokyo",
    "iso:country":"JP",
    "name:jpn_x_preferred":[
        "\u9e7f\u5b50\u524d\u753a"
    ],
    "name:und_x_variant":[
        "Kashimaech\u014d"
    ],
    "wof:name":"Kashimaecho",
    "wof:placetype":"locality"
},
  "geometry": {"coordinates":[129.68462,33.16254],"type":"Point"}
}