{
  "type": "Feature",
  "properties": {
    "gn:admin1_code":"28.0",
    "gn:admin2_code":"1849448.0",
    "gn:admin3_code":"29385.0",
    "gn:asciiname":"Kazura",
    "gn:country_code":"JP",
    "gn:dem":452,
    "gn:feature_class":"P",
    "gn:feature_code":"PPL",
    "gn:name":"Kazura",
    "gn:population":0,
    "gn:timezone":"Asia/Tokyo",
    "iso:country":"JP",
    "name:jpn_x_preferred":[
        "\u845b"
    ],
    "wof:name":"Kazura",
    "wof:placetype":"locality"
},
  "geometry": {"coordinates":[136.13183000000001,34.52242],"type":"Point"}
}