{
  "type": "Feature",
  "properties": {
    "gn:admin1_code":"27.0",
    "gn:admin2_code":"7418805.0",
    "gn:asciiname":"Ikemuke",
    "gn:country_code":"JP",
    "gn:dem":109,
    "gn:feature_class":"P",
    "gn:feature_code":"PPLL",
    "gn:name":"Ikemuke",
    "gn:population":0,
    "gn:timezone":"Asia/Tokyo",
    "iso:country":"JP",
    "name:jpn_x_preferred":[
        "\u751f\u5411"
    ],
    "wof:name":"Ikemuke",
    "wof:placetype":"locality"
},
  "geometry": {"coordinates":[129.57813000000002,33.33533],"type":"Point"}
}