{
  "type": "Feature",
  "properties": {
    "gn:admin1_code":"19.0",
    "gn:admin2_code":"1865011.0",
    "gn:admin3_code":"14364.0",
    "gn:asciiname":"Hisari",
    "gn:country_code":"JP",
    "gn:dem":105,
    "gn:feature_class":"P",
    "gn:feature_code":"PPLL",
    "gn:name":"Hisari",
    "gn:population":0,
    "gn:timezone":"Asia/Tokyo",
    "iso:country":"JP",
    "name:jpn_x_preferred":[
        "\u5c3a\u91cc"
    ],
    "wof:name":"Hisari",
    "wof:placetype":"locality"
},
  "geometry": {"coordinates":[139.09756000000002,35.36566],"type":"Point"}
}