{
  "type": "Feature",
  "properties": {
    "gn:admin1_code":"32.0",
    "gn:admin2_code":"1861089.0",
    "gn:asciiname":"Matsuojicho",
    "gn:country_code":"JP",
    "gn:dem":75,
    "gn:feature_class":"P",
    "gn:feature_code":"PPL",
    "gn:name":"Matsuojich\u014d",
    "gn:population":0,
    "gn:timezone":"Asia/Tokyo",
    "iso:country":"JP",
    "name:jpn_x_preferred":[
        "\u677e\u5c3e\u5bfa\u753a"
    ],
    "name:und_x_variant":[
        "Matsuojich\u014d"
    ],
    "wof:name":"Matsuojicho",
    "wof:placetype":"locality"
},
  "geometry": {"coordinates":[135.46037999999999,34.43543],"type":"Point"}
}