{
  "type": "Feature",
  "properties": {
    "gn:admin1_code":"47",
    "gn:admin2_code":"1856030.0",
    "gn:asciiname":"Matsugawa",
    "gn:country_code":"JP",
    "gn:dem":19,
    "gn:feature_class":"P",
    "gn:feature_code":"PPL",
    "gn:name":"Matsugawa",
    "gn:population":0,
    "gn:timezone":"Asia/Tokyo",
    "iso:country":"JP",
    "name:jpn_x_preferred":[
        "\u677e\u5ddd"
    ],
    "name:und_x_variant":[
        "Machigawa",
        "Matsugawa"
    ],
    "wof:name":"Matsugawa",
    "wof:placetype":"locality"
},
  "geometry": {"coordinates":[127.70198000000001,26.21502000000001],"type":"Point"}
}