{
  "type": "Feature",
  "properties": {
    "gn:admin1_code":"29.0",
    "gn:admin2_code":"1856195.0",
    "gn:asciiname":"Nishitakayama-shinden",
    "gn:country_code":"JP",
    "gn:dem":14,
    "gn:feature_class":"P",
    "gn:feature_code":"PPL",
    "gn:name":"Nishitakayama-shinden",
    "gn:population":0,
    "gn:timezone":"Asia/Tokyo",
    "iso:country":"JP",
    "name:jpn_x_preferred":[
        "\u897f\u9ad8\u5c71\u65b0\u7530"
    ],
    "wof:name":"Nishitakayama-shinden",
    "wof:placetype":"locality"
},
  "geometry": {"coordinates":[138.87312,37.57427],"type":"Point"}
}