{
  "type": "Feature",
  "properties": {
    "gn:admin1_code":"21.0",
    "gn:admin2_code":"1859490.0",
    "gn:admin3_code":"43404.0",
    "gn:asciiname":"Iguchi",
    "gn:country_code":"JP",
    "gn:dem":65,
    "gn:feature_class":"P",
    "gn:feature_code":"PPLL",
    "gn:name":"Iguchi",
    "gn:population":0,
    "gn:timezone":"Asia/Tokyo",
    "iso:country":"JP",
    "name:jpn_x_preferred":[
        "\u4e95\u53e3"
    ],
    "name:jpn_x_variant":[
        "\u3044\u3050\u3061",
        "\u30a4\u30b0\u30c1"
    ],
    "wof:name":"Iguchi",
    "wof:placetype":"locality"
},
  "geometry": {"coordinates":[130.81127000000001,32.85189],"type":"Point"}
}