{
  "type": "Feature",
  "properties": {
    "gn:admin1_code":"12.0",
    "gn:admin2_code":"2130058.0",
    "gn:admin3_code":"1642.0",
    "gn:asciiname":"Namikidori-higashi",
    "gn:country_code":"JP",
    "gn:dem":32,
    "gn:feature_class":"P",
    "gn:feature_code":"PPL",
    "gn:name":"Namikid\u014dri-higashi",
    "gn:population":0,
    "gn:timezone":"Asia/Tokyo",
    "iso:country":"JP",
    "name:jpn_x_preferred":[
        "\u4e26\u6728\u901a\u6771"
    ],
    "name:jpn_x_variant":[
        "\u306a\u307f\u304d\u3069\u304a\u308a\u3072\u304c\u3057",
        "\u30ca\u30df\u30ad\u30c9\u30aa\u30ea\u30d2\u30ac\u30b7"
    ],
    "name:und_x_variant":[
        "Namikid\u014dri-higashi"
    ],
    "wof:name":"Namikidori-higashi",
    "wof:placetype":"locality"
},
  "geometry": {"coordinates":[143.31768,42.30053],"type":"Point"}
}