{
  "type": "Feature",
  "properties": {
    "gn:admin1_code":"3.0",
    "gn:admin2_code":"2130088.0",
    "gn:admin3_code":"2307.0",
    "gn:asciiname":"Motouta",
    "gn:country_code":"JP",
    "gn:dem":127,
    "gn:feature_class":"P",
    "gn:feature_code":"PPL",
    "gn:name":"Motouta",
    "gn:population":0,
    "gn:timezone":"Asia/Tokyo",
    "iso:country":"JP",
    "name:jpn_x_preferred":[
        "\u5143\u5b87\u7530"
    ],
    "name:jpn_x_variant":[
        "\u3082\u3068\u3046\u305f",
        "\u30e2\u30c8\u30a6\u30bf"
    ],
    "wof:name":"Motouta",
    "wof:placetype":"locality"
},
  "geometry": {"coordinates":[140.61118999999999,41.2001],"type":"Point"}
}