{
  "type": "Feature",
  "properties": {
    "gn:admin1_code":"34.0",
    "gn:admin2_code":"1858728.0",
    "gn:asciiname":"Omichi",
    "gn:country_code":"JP",
    "gn:dem":7,
    "gn:feature_class":"P",
    "gn:feature_code":"PPL",
    "gn:name":"\u014cmichi",
    "gn:population":0,
    "gn:timezone":"Asia/Tokyo",
    "iso:country":"JP",
    "name:jpn_x_preferred":[
        "\u5927\u9053"
    ],
    "name:und_x_variant":[
        "\u014cmichi"
    ],
    "wof:name":"Omichi",
    "wof:placetype":"locality"
},
  "geometry": {"coordinates":[139.76049,35.92140999999999],"type":"Point"}
}