{
  "type": "Feature",
  "properties": {
    "gn:admin1_code":"4.0",
    "gn:admin2_code":"1857552.0",
    "gn:asciiname":"Kushizaki-shinden",
    "gn:country_code":"JP",
    "gn:dem":26,
    "gn:feature_class":"P",
    "gn:feature_code":"PPL",
    "gn:name":"Kushizaki-shinden",
    "gn:population":0,
    "gn:timezone":"Asia/Tokyo",
    "iso:country":"JP",
    "name:jpn_x_preferred":[
        "\u4e32\u5d0e\u65b0\u7530"
    ],
    "wof:name":"Kushizaki-shinden",
    "wof:placetype":"locality"
},
  "geometry": {"coordinates":[139.97743,35.77714],"type":"Point"}
}