{
  "type": "Feature",
  "properties": {
    "gn:admin1_code":"21.0",
    "gn:admin2_code":"1865358.0",
    "gn:asciiname":"Muranaka",
    "gn:country_code":"JP",
    "gn:dem":137,
    "gn:feature_class":"P",
    "gn:feature_code":"PPLL",
    "gn:name":"Muranaka",
    "gn:population":0,
    "gn:timezone":"Asia/Tokyo",
    "iso:country":"JP",
    "name:jpn_x_preferred":[
        "\u6751\u4e2d"
    ],
    "name:jpn_x_variant":[
        "\u3080\u3089\u306a\u304b",
        "\u30e0\u30e9\u30ca\u30ab"
    ],
    "wof:name":"Muranaka",
    "wof:placetype":"locality"
},
  "geometry": {"coordinates":[130.07299999999998,32.41857],"type":"Point"}
}