{
  "type": "Feature",
  "properties": {
    "gn:admin1_code":"28.0",
    "gn:admin2_code":"7412212.0",
    "gn:asciiname":"Murou-ono",
    "gn:country_code":"JP",
    "gn:dem":296,
    "gn:feature_class":"P",
    "gn:feature_code":"PPL",
    "gn:name":"Murou-\u014dno",
    "gn:population":0,
    "gn:timezone":"Asia/Tokyo",
    "iso:country":"JP",
    "name:jpn_x_preferred":[
        "\u5ba4\u751f\u5927\u91ce"
    ],
    "name:und_x_variant":[
        "Murou-\u014dno"
    ],
    "wof:name":"Murou-ono",
    "wof:placetype":"locality"
},
  "geometry": {"coordinates":[136.01498000000001,34.56972],"type":"Point"}
}