{
  "type": "Feature",
  "properties": {
    "gn:admin1_code":"16.0",
    "gn:admin2_code":"2129400.0",
    "gn:admin3_code":"3501.0",
    "gn:asciiname":"Takakubo",
    "gn:country_code":"JP",
    "gn:dem":212,
    "gn:feature_class":"P",
    "gn:feature_code":"PPL",
    "gn:name":"Takakubo",
    "gn:population":0,
    "gn:timezone":"Asia/Tokyo",
    "iso:country":"JP",
    "name:jpn_x_preferred":[
        "\u9ad8\u4e45\u4fdd"
    ],
    "name:jpn_x_variant":[
        "\u305f\u304b\u304f\u307c",
        "\u30bf\u30ab\u30af\u30dc"
    ],
    "wof:name":"Takakubo",
    "wof:placetype":"locality"
},
  "geometry": {"coordinates":[141.45713999999995,40.37098],"type":"Point"}
}