{
  "type": "Feature",
  "properties": {
    "gn:admin1_code":"43",
    "gn:admin2_code":"7411114.0",
    "gn:asciiname":"Kokawa",
    "gn:country_code":"JP",
    "gn:dem":42,
    "gn:feature_class":"P",
    "gn:feature_code":"PPL",
    "gn:name":"Kokawa",
    "gn:population":0,
    "gn:timezone":"Asia/Tokyo",
    "iso:country":"JP",
    "name:jpn_x_preferred":[
        "\u7c89\u5ddd"
    ],
    "name:und_x_variant":[
        "Kokawach\u014d",
        "Kokawa"
    ],
    "wof:name":"Kokawa",
    "wof:placetype":"locality"
},
  "geometry": {"coordinates":[135.40648999999999,34.2734],"type":"Point"}
}