{
  "type": "Feature",
  "properties": {
    "gn:admin1_code":"3.0",
    "gn:admin2_code":"2128302.0",
    "gn:admin3_code":"2445.0",
    "gn:asciiname":"Shimotoga",
    "gn:country_code":"JP",
    "gn:dem":49,
    "gn:feature_class":"P",
    "gn:feature_code":"PPL",
    "gn:name":"Shimotoga",
    "gn:population":0,
    "gn:timezone":"Asia/Tokyo",
    "iso:country":"JP",
    "name:jpn_x_preferred":[
        "\u4e0b\u6597\u8cc0"
    ],
    "name:jpn_x_variant":[
        "\u3057\u3082\u3068\u304c",
        "\u30b7\u30e2\u30c8\u30ac"
    ],
    "wof:name":"Shimotoga",
    "wof:placetype":"locality"
},
  "geometry": {"coordinates":[141.34691999999995,40.4598],"type":"Point"}
}