{
  "type": "Feature",
  "properties": {
    "gn:admin1_code":"18.0",
    "gn:admin2_code":"7383991.0",
    "gn:asciiname":"Koji",
    "gn:country_code":"JP",
    "gn:dem":218,
    "gn:feature_class":"P",
    "gn:feature_code":"PPLL",
    "gn:name":"K\u014dji",
    "gn:population":0,
    "gn:timezone":"Asia/Tokyo",
    "iso:country":"JP",
    "name:ceb_x_preferred":[
        "Koji"
    ],
    "name:ita_x_preferred":[
        "Koji"
    ],
    "name:jpn_x_preferred":[
        "\u5c0f\u8def"
    ],
    "name:jpn_x_variant":[
        "\u3053\u3046\u3058",
        "\u30b3\u30a6\u30b8"
    ],
    "name:swe_x_preferred":[
        "Koji"
    ],
    "name:und_x_variant":[
        "K\u014dji"
    ],
    "wof:name":"Koji",
    "wof:placetype":"locality"
},
  "geometry": {"coordinates":[130.66418000000002,32.01835999999999],"type":"Point"}
}