{
  "type": "Feature",
  "properties": {
    "gn:admin1_code":"4.0",
    "gn:admin2_code":"1859468.0",
    "gn:asciiname":"Ogisaku",
    "gn:country_code":"JP",
    "gn:dem":80,
    "gn:feature_class":"P",
    "gn:feature_code":"PPL",
    "gn:name":"Ogisaku",
    "gn:population":0,
    "gn:timezone":"Asia/Tokyo",
    "iso:country":"JP",
    "name:jpn_x_preferred":[
        "\u837b\u4f5c"
    ],
    "name:jpn_x_variant":[
        "\u304a\u304e\u3055\u304f",
        "\u30aa\u30ae\u30b5\u30af"
    ],
    "wof:name":"Ogisaku",
    "wof:placetype":"locality"
},
  "geometry": {"coordinates":[139.96627000000001,35.28577999999999],"type":"Point"}
}