{
  "type": "Feature",
  "properties": {
    "gn:admin1_code":"32",
    "gn:admin2_code":"1852716.0",
    "gn:admin3_code":"27362.0",
    "gn:asciiname":"Yoshimi",
    "gn:country_code":"JP",
    "gn:dem":5,
    "gn:feature_class":"P",
    "gn:feature_code":"PPL",
    "gn:name":"Yoshimi",
    "gn:population":0,
    "gn:timezone":"Asia/Tokyo",
    "iso:country":"JP",
    "name:jpn_x_preferred":[
        "\u5409\u898b"
    ],
    "name:kor_x_preferred":[
        "\uc694\uc2dc\ubbf8"
    ],
    "wof:name":"Yoshimi",
    "wof:placetype":"locality"
},
  "geometry": {"coordinates":[135.28671,34.39194000000001],"type":"Point"}
}