{
  "type": "Feature",
  "properties": {
    "gn:admin1_code":"4.0",
    "gn:admin2_code":"1863711.0",
    "gn:asciiname":"Utogi",
    "gn:country_code":"JP",
    "gn:dem":117,
    "gn:feature_class":"P",
    "gn:feature_code":"PPLL",
    "gn:name":"Ut\u014dgi",
    "gn:population":0,
    "gn:timezone":"Asia/Tokyo",
    "iso:country":"JP",
    "name:jpn_x_preferred":[
        "\u5b87\u85e4\u6728"
    ],
    "name:jpn_x_variant":[
        "\u3046\u3068\u3046\u304e",
        "\u30a6\u30c8\u30a6\u30ae"
    ],
    "name:und_x_variant":[
        "Ut\u014dgi"
    ],
    "wof:name":"Utogi",
    "wof:placetype":"locality"
},
  "geometry": {"coordinates":[139.97179,35.17361],"type":"Point"}
}