{
  "type": "Feature",
  "properties": {
    "gn:admin1_code":"32.0",
    "gn:admin2_code":"1850907.0",
    "gn:asciiname":"Shodokorocho",
    "gn:country_code":"JP",
    "gn:dem":7,
    "gn:feature_class":"P",
    "gn:feature_code":"PPL",
    "gn:name":"Sh\u014ddokoroch\u014d",
    "gn:population":0,
    "gn:timezone":"Asia/Tokyo",
    "iso:country":"JP",
    "name:jpn_x_preferred":[
        "\u5e84\u6240\u753a"
    ],
    "name:und_x_variant":[
        "Sh\u014ddokoroch\u014d"
    ],
    "wof:name":"Shodokorocho",
    "wof:placetype":"locality"
},
  "geometry": {"coordinates":[135.6146,34.83785],"type":"Point"}
}