{
  "type": "Feature",
  "properties": {
    "gn:admin1_code":"44.0",
    "gn:admin2_code":"2112756.0",
    "gn:admin3_code":"6382.0",
    "gn:asciiname":"Wago",
    "gn:country_code":"JP",
    "gn:dem":391,
    "gn:feature_class":"P",
    "gn:feature_code":"PPLL",
    "gn:name":"Wag\u014d",
    "gn:population":0,
    "gn:timezone":"Asia/Tokyo",
    "iso:country":"JP",
    "name:cat_x_preferred":[
        "Yamato kotoba"
    ],
    "name:jpn_x_preferred":[
        "\u548c\u5408"
    ],
    "name:jpn_x_variant":[
        "\u5927\u548c\u8a00\u8449"
    ],
    "name:kor_x_preferred":[
        "\uc57c\ub9c8\ud1a0 \uace0\ud1a0\ubc14"
    ],
    "name:und_x_variant":[
        "Wag\u014d"
    ],
    "wof:name":"Wago",
    "wof:placetype":"locality"
},
  "geometry": {"coordinates":[139.97486999999998,37.91042],"type":"Point"}
}