{
  "type": "Feature",
  "properties": {
    "gn:admin1_code":"26.0",
    "gn:admin2_code":"1849427.0",
    "gn:asciiname":"Kamimuroga",
    "gn:country_code":"JP",
    "gn:dem":591,
    "gn:feature_class":"P",
    "gn:feature_code":"PPL",
    "gn:name":"Kamimuroga",
    "gn:population":0,
    "gn:timezone":"Asia/Tokyo",
    "iso:country":"JP",
    "name:jpn_x_preferred":[
        "\u4e0a\u5ba4\u8cc0"
    ],
    "wof:name":"Kamimuroga",
    "wof:placetype":"locality"
},
  "geometry": {"coordinates":[138.14341999999999,36.41331],"type":"Point"}
}