{
  "type": "Feature",
  "properties": {
    "iso:country":"JP",
    "qs:name":"\u5929\u795e",
    "qs:name_adm0":"\u65e5\u672c",
    "qs:name_adm1":"\u798f\u5ca1\u770c",
    "qs:photos":2,
    "qs:photos_1k":1,
    "qs:photos_9k":13,
    "qs:photos_9r":11,
    "qs:photos_all":2821,
    "qs:photos_sr":1,
    "qs:placetype":"LocalAdmin",
    "qs:pop_sr":"0",
    "wof:name":"\u5929\u795e",
    "wof:placetype":"localadmin"
},
  "geometry": {"coordinates":[130.40015,33.591367],"type":"Point"}
}