{
  "type": "Feature",
  "properties": {
    "gn:admin1_code":"12.0",
    "gn:admin2_code":"2129370.0",
    "gn:asciiname":"Otanoshike-kita",
    "gn:country_code":"JP",
    "gn:dem":6,
    "gn:feature_class":"P",
    "gn:feature_code":"PPL",
    "gn:name":"Otanoshike-kita",
    "gn:population":0,
    "gn:timezone":"Asia/Tokyo",
    "iso:country":"JP",
    "name:jpn_x_preferred":[
        "\u5927\u697d\u6bdb\u5317"
    ],
    "name:jpn_x_variant":[
        "\u304a\u305f\u306e\u3057\u3051\u304d\u305f",
        "\u30aa\u30bf\u30ce\u30b7\u30b1\u30ad\u30bf"
    ],
    "wof:name":"Otanoshike-kita",
    "wof:placetype":"locality"
},
  "geometry": {"coordinates":[144.29435000000001,43.01555],"type":"Point"}
}