{
  "type": "Feature",
  "properties": {
    "gn:admin1_code":"7.0",
    "gn:admin2_code":"1848086.0",
    "gn:asciiname":"Shimokenji",
    "gn:country_code":"JP",
    "gn:dem":4,
    "gn:feature_class":"P",
    "gn:feature_code":"PPL",
    "gn:name":"Shimokenji",
    "gn:population":0,
    "gn:timezone":"Asia/Tokyo",
    "iso:country":"JP",
    "name:jpn_x_preferred":[
        "\u4e0b\u691c\u5730"
    ],
    "wof:name":"Shimokenji",
    "wof:placetype":"locality"
},
  "geometry": {"coordinates":[130.95248999999998,33.72194],"type":"Point"}
}