{
  "type": "Feature",
  "properties": {
    "iso:country":"JP",
    "name:eng_x_preferred":[
        "Toyako"
    ],
    "name:eng_x_variant":[
        "Toyako Town"
    ],
    "name:jpn_x_preferred":[
        "\u6d1e\u723a\u6e56\u753a"
    ],
    "qs:name":"\u6d1e\u723a\u6e56\u753a",
    "qs:name_adm0":"\u65e5\u672c",
    "qs:name_adm1":"\u5317\u6d77\u9053",
    "qs:photos":1379,
    "qs:photos_1k":279,
    "qs:photos_9k":6,
    "qs:photos_9r":7,
    "qs:photos_all":1379,
    "qs:photos_sr":12,
    "qs:placetype":"Town",
    "qs:pop_sr":"0",
    "wof:name":"Toyako",
    "wof:placetype":"locality"
},
  "geometry": {"coordinates":[140.816574,42.577354],"type":"Point"}
}