{
  "type": "Feature",
  "properties": {
    "gn:admin1_code":"21.0",
    "gn:admin2_code":"1858418.0",
    "gn:admin3_code":"43105.0",
    "gn:asciiname":"Uekimachi-imafuji",
    "gn:country_code":"JP",
    "gn:dem":77,
    "gn:feature_class":"P",
    "gn:feature_code":"PPL",
    "gn:name":"Uekimachi-imafuji",
    "gn:population":0,
    "gn:timezone":"Asia/Tokyo",
    "iso:country":"JP",
    "name:jpn_x_preferred":[
        "\u690d\u6728\u753a\u4eca\u85e4"
    ],
    "name:jpn_x_variant":[
        "\u3046\u3048\u304d\u307e\u3061\u3044\u307e\u3075\u3058",
        "\u30a6\u30a8\u30ad\u30de\u30c1\u30a4\u30de\u30d5\u30b8"
    ],
    "wof:name":"Uekimachi-imafuji",
    "wof:placetype":"locality"
},
  "geometry": {"coordinates":[130.69756000000001,32.93696],"type":"Point"}
}