{
  "type": "Feature",
  "properties": {
    "gn:admin1_code":"21.0",
    "gn:admin2_code":"1865358.0",
    "gn:asciiname":"Omatsudo",
    "gn:country_code":"JP",
    "gn:dem":10,
    "gn:feature_class":"P",
    "gn:feature_code":"PPLL",
    "gn:name":"\u014cmatsudo",
    "gn:population":0,
    "gn:timezone":"Asia/Tokyo",
    "iso:country":"JP",
    "name:jpn_x_preferred":[
        "\u5927\u677e\u6238"
    ],
    "name:jpn_x_variant":[
        "\u304a\u304a\u307e\u3064\u3069",
        "\u30aa\u30aa\u30de\u30c4\u30c9"
    ],
    "name:und_x_variant":[
        "\u014cmatsudo"
    ],
    "wof:name":"Omatsudo",
    "wof:placetype":"locality"
},
  "geometry": {"coordinates":[130.22341,32.45656],"type":"Point"}
}