{
  "type": "Feature",
  "properties": {
    "gn:admin1_code":"7.0",
    "gn:admin2_code":"1861834.0",
    "gn:asciiname":"Oki",
    "gn:country_code":"JP",
    "gn:dem":47,
    "gn:feature_class":"P",
    "gn:feature_code":"PPLL",
    "gn:name":"\u014cki",
    "gn:population":0,
    "gn:timezone":"Asia/Tokyo",
    "iso:country":"JP",
    "name:ceb_x_preferred":[
        "Oki"
    ],
    "name:deu_x_preferred":[
        "Oki"
    ],
    "name:fra_x_preferred":[
        "Oki"
    ],
    "name:jpn_x_preferred":[
        "\u5927\u6728"
    ],
    "name:nld_x_preferred":[
        "Oki"
    ],
    "name:nor_x_preferred":[
        "Oki"
    ],
    "name:pol_x_preferred":[
        "Oki"
    ],
    "name:por_x_preferred":[
        "Oki"
    ],
    "name:rus_x_preferred":[
        "\u041e\u043a\u0438"
    ],
    "name:swe_x_preferred":[
        "Oki"
    ],
    "name:und_x_variant":[
        "\u014cki"
    ],
    "wof:name":"Oki",
    "wof:placetype":"locality"
},
  "geometry": {"coordinates":[130.65124,33.57987],"type":"Point"}
}