{
  "type": "Feature",
  "properties": {
    "gn:admin1_code":"24",
    "gn:admin2_code":"2112092.0",
    "gn:asciiname":"Tomeoka",
    "gn:country_code":"JP",
    "gn:dem":81,
    "gn:feature_class":"P",
    "gn:feature_code":"PPLL",
    "gn:name":"Tomeoka",
    "gn:population":0,
    "gn:timezone":"Asia/Tokyo",
    "iso:country":"JP",
    "name:jpn_x_preferred":[
        "\u7559\u5ca1"
    ],
    "name:und_x_variant":[
        "Ry\u016boka",
        "Tomeoka"
    ],
    "wof:name":"Tomeoka",
    "wof:placetype":"locality"
},
  "geometry": {"coordinates":[140.95249999999999,38.87472],"type":"Point"}
}