{
  "type": "Feature",
  "properties": {
    "iso:country":"JP",
    "name:eng_x_preferred":[
        "Miwa"
    ],
    "name:jpn_x_preferred":[
        "\u4e09\u8f2a"
    ],
    "qs:name":"\u4e09\u8f2a",
    "qs:name_adm0":"\u65e5\u672c",
    "qs:name_adm1":"\u9577\u91ce\u770c",
    "qs:photos":2,
    "qs:photos_1k":1,
    "qs:photos_9k":4,
    "qs:photos_9r":7,
    "qs:photos_all":1012,
    "qs:photos_sr":1,
    "qs:placetype":"LocalAdmin",
    "qs:pop_sr":"0",
    "wof:name":"Miwa",
    "wof:placetype":"localadmin"
},
  "geometry": {"coordinates":[138.18766500000001,36.659642],"type":"Point"}
}