{
  "type": "Feature",
  "properties": {
    "gn:admin1_code":"16.0",
    "gn:admin2_code":"2128940.0",
    "gn:asciiname":"Ushimagi",
    "gn:country_code":"JP",
    "gn:dem":174,
    "gn:feature_class":"P",
    "gn:feature_code":"PPL",
    "gn:name":"Ushimagi",
    "gn:population":0,
    "gn:timezone":"Asia/Tokyo",
    "iso:country":"JP",
    "name:jpn_x_preferred":[
        "\u725b\u9593\u6728"
    ],
    "name:jpn_x_variant":[
        "\u3046\u3057\u307e\u304e",
        "\u30a6\u30b7\u30de\u30ae"
    ],
    "wof:name":"Ushimagi",
    "wof:placetype":"locality"
},
  "geometry": {"coordinates":[141.20925,40.30042],"type":"Point"}
}