{
  "type": "Feature",
  "properties": {
    "gn:admin1_code":"16.0",
    "gn:admin2_code":"2128941.0",
    "gn:admin3_code":"3524.0",
    "gn:asciiname":"Suwano",
    "gn:country_code":"JP",
    "gn:dem":141,
    "gn:feature_class":"P",
    "gn:feature_code":"PPL",
    "gn:name":"Suwano",
    "gn:population":0,
    "gn:timezone":"Asia/Tokyo",
    "iso:country":"JP",
    "name:jpn_x_preferred":[
        "\u8acf\u8a2a\u91ce"
    ],
    "name:jpn_x_variant":[
        "\u3059\u308f\u306e",
        "\u30b9\u30ef\u30ce"
    ],
    "wof:name":"Suwano",
    "wof:placetype":"locality"
},
  "geometry": {"coordinates":[141.30021000000005,40.20841],"type":"Point"}
}