{
  "type": "Feature",
  "properties": {
    "gn:admin1_code":"34",
    "gn:admin2_code":"8304214.0",
    "gn:asciiname":"Haraichi",
    "gn:country_code":"JP",
    "gn:dem":14,
    "gn:feature_class":"P",
    "gn:feature_code":"PPL",
    "gn:name":"Haraichi",
    "gn:population":0,
    "gn:timezone":"Asia/Tokyo",
    "iso:country":"JP",
    "name:jpn_x_preferred":[
        "\u539f\u5e02"
    ],
    "name:jpn_x_variant":[
        "\u306f\u3089\u3044\u3061",
        "\u30cf\u30e9\u30a4\u30c1"
    ],
    "wof:name":"Haraichi",
    "wof:placetype":"locality"
},
  "geometry": {"coordinates":[139.62792999999999,35.96326],"type":"Point"}
}