{
  "type": "Feature",
  "properties": {
    "gn:admin1_code":"32.0",
    "gn:admin2_code":"1850907.0",
    "gn:asciiname":"Shimotanabecho",
    "gn:country_code":"JP",
    "gn:dem":9,
    "gn:feature_class":"P",
    "gn:feature_code":"PPL",
    "gn:name":"Shimotanabech\u014d",
    "gn:population":0,
    "gn:timezone":"Asia/Tokyo",
    "iso:country":"JP",
    "name:jpn_x_preferred":[
        "\u4e0b\u7530\u90e8\u753a"
    ],
    "name:und_x_variant":[
        "Shimotanabech\u014d"
    ],
    "wof:name":"Shimotanabecho",
    "wof:placetype":"locality"
},
  "geometry": {"coordinates":[135.61896999999999,34.83488],"type":"Point"}
}