{
  "type": "Feature",
  "properties": {
    "iso:country":"JP",
    "name:eng_x_preferred":[
        "Washimiya 6 Chome"
    ],
    "name:eng_x_variant":[
        "Washimiya 6 Choume",
        "Washimiya 6 Chome"
    ],
    "name:jpn_x_preferred":[
        "\uff16\u4e01\u76ee"
    ],
    "name:jpn_x_variant":[
        "\u308f\u3057\u307f\u3084 \uff16\u3061\u3087\u3046\u3081",
        "\u9df2\u5bae \uff16\u4e01\u76ee",
        "\uff16\u3061\u3087\u3046\u3081"
    ],
    "name:unk_x_variant":[
        "\uff16\u4e01\u76ee"
    ],
    "qs:gn_local":0,
    "qs:local_max":173,
    "qs:local_sum":217,
    "qs:localhoods":3,
    "qs:name":"\uff16\u4e01\u76ee",
    "qs:name_adm0":"\u65e5\u672c",
    "qs:name_adm1":"\u57fc\u7389\u770c",
    "qs:name_adm2":"\u5317\u845b\u98fe\u90e1",
    "qs:name_en":"Washimiya 6 Chome",
    "qs:name_lau":"\u9df2\u5bae",
    "qs:name_local":"\u9df2\u5bae\u753a",
    "qs:photo_max":2,
    "qs:photo_sum":2,
    "qs:placetype":"Suburb",
    "qs:quad_count":1,
    "qs:woe_adm0":23424856,
    "qs:woe_adm1":2345883,
    "qs:woe_adm2":24857571,
    "qs:woe_lau":28410436,
    "qs:woe_local":24727957,
    "qs:woe_ver":"7.10.0",
    "wof:lang":[
        "jpn"
    ],
    "wof:name":"\uff16\u4e01\u76ee",
    "wof:placetype":"neighbourhood"
},
  "geometry": {"coordinates":[139.67193599999999,36.095718],"type":"Point"}
}