{
  "type": "Feature",
  "properties": {
    "gn:admin1_code":"3.0",
    "gn:admin2_code":"2130654.0",
    "gn:asciiname":"Wakamiya",
    "gn:country_code":"JP",
    "gn:dem":10,
    "gn:feature_class":"P",
    "gn:feature_code":"PPL",
    "gn:name":"Wakamiya",
    "gn:population":0,
    "gn:timezone":"Asia/Tokyo",
    "iso:country":"JP",
    "name:jpn_x_preferred":[
        "\u308f\u304b\u307f\u3084"
    ],
    "name:jpn_x_variant":[
        "\u82e5\u5bae",
        "\u30ef\u30ab\u30df\u30e4"
    ],
    "wof:name":"Wakamiya",
    "wof:placetype":"locality"
},
  "geometry": {"coordinates":[140.73695000000001,40.80441],"type":"Point"}
}