{
  "type": "Feature",
  "properties": {
    "gn:admin1_code":"3.0",
    "gn:admin2_code":"2130654.0",
    "gn:asciiname":"Kawaharamachi",
    "gn:country_code":"JP",
    "gn:dem":27,
    "gn:feature_class":"P",
    "gn:feature_code":"PPL",
    "gn:name":"Kawaharamachi",
    "gn:population":0,
    "gn:timezone":"Asia/Tokyo",
    "iso:country":"JP",
    "name:jpn_x_preferred":[
        "\u5ddd\u539f\u753a"
    ],
    "name:jpn_x_variant":[
        "\u304b\u308f\u306f\u3089\u307e\u3061",
        "\u30ab\u30ef\u30cf\u30e9\u30de\u30c1"
    ],
    "wof:name":"Kawaharamachi",
    "wof:placetype":"locality"
},
  "geometry": {"coordinates":[140.59884,40.71277],"type":"Point"}
}