{
  "type": "Feature",
  "properties": {
    "gn:admin1_code":"22",
    "gn:admin2_code":"1857906.0",
    "gn:admin3_code":"26109.0",
    "gn:asciiname":"Yodo",
    "gn:country_code":"JP",
    "gn:dem":16,
    "gn:feature_class":"P",
    "gn:feature_code":"PPL",
    "gn:name":"Yodo",
    "gn:population":0,
    "gn:timezone":"Asia/Tokyo",
    "iso:country":"JP",
    "wof:name":"Yodo",
    "wof:placetype":"locality"
},
  "geometry": {"coordinates":[135.71926000000002,34.90269],"type":"Point"}
}