{
  "type": "Feature",
  "properties": {
    "gn:admin1_code":"7.0",
    "gn:admin2_code":"1851269.0",
    "gn:admin3_code":"40605.0",
    "gn:asciiname":"Nakatabara",
    "gn:country_code":"JP",
    "gn:dem":55,
    "gn:feature_class":"P",
    "gn:feature_code":"PPLL",
    "gn:name":"Nakatabara",
    "gn:population":0,
    "gn:timezone":"Asia/Tokyo",
    "iso:country":"JP",
    "name:jpn_x_preferred":[
        "\u4e2d\u7530\u539f"
    ],
    "wof:name":"Nakatabara",
    "wof:placetype":"locality"
},
  "geometry": {"coordinates":[130.81020000000001,33.6024],"type":"Point"}
}