{
  "type": "Feature",
  "properties": {
    "gn:admin1_code":"25",
    "gn:admin2_code":"1858599.0",
    "gn:admin3_code":"45404.0",
    "gn:asciiname":"Takajo",
    "gn:country_code":"JP",
    "gn:dem":15,
    "gn:feature_class":"P",
    "gn:feature_code":"PPL",
    "gn:name":"Takaj\u014d",
    "gn:population":0,
    "gn:timezone":"Asia/Tokyo",
    "iso:country":"JP",
    "name:und_x_variant":[
        "Takaj\u014d"
    ],
    "wof:name":"Takajo",
    "wof:placetype":"locality"
},
  "geometry": {"coordinates":[131.48333,32.16667],"type":"Point"}
}