{
  "type": "Feature",
  "properties": {
    "gn:admin1_code":"40",
    "gn:admin2_code":"1856942.0",
    "gn:asciiname":"Shuku",
    "gn:cc2":"JP",
    "gn:country_code":"JP",
    "gn:dem":53,
    "gn:feature_class":"P",
    "gn:feature_code":"PPL",
    "gn:name":"Shuku",
    "gn:population":0,
    "gn:timezone":"Asia/Tokyo",
    "iso:country":"JP",
    "name:und_x_variant":[
        "Shiku-machi",
        "Shukumachi",
        "Shuku"
    ],
    "wof:name":"Shuku",
    "wof:placetype":"locality"
},
  "geometry": {"coordinates":[139.58333000000002,35.68333],"type":"Point"}
}