{
  "type": "Feature",
  "properties": {
    "gn:admin1_code":"19.0",
    "gn:admin2_code":"1848350.0",
    "gn:admin3_code":"14103.0",
    "gn:asciiname":"Nishitobecho",
    "gn:country_code":"JP",
    "gn:dem":31,
    "gn:feature_class":"P",
    "gn:feature_code":"PPL",
    "gn:name":"Nishitobech\u014d",
    "gn:population":0,
    "gn:timezone":"Asia/Tokyo",
    "iso:country":"JP",
    "name:jpn_x_preferred":[
        "\u897f\u6238\u90e8\u753a"
    ],
    "name:jpn_x_variant":[
        "\u306b\u3057\u3068\u3079\u3061\u3087\u3046",
        "\u30cb\u30b7\u30c8\u30d9\u30c1\u30e7\u30a6"
    ],
    "name:und_x_variant":[
        "Nishitobech\u014d"
    ],
    "wof:name":"Nishitobecho",
    "wof:placetype":"locality"
},
  "geometry": {"coordinates":[139.61940000000001,35.44928],"type":"Point"}
}