{
  "type": "Feature",
  "properties": {
    "gn:admin1_code":"32.0",
    "gn:admin2_code":"1859747.0",
    "gn:asciiname":"Iwaze",
    "gn:country_code":"JP",
    "gn:dem":201,
    "gn:feature_class":"P",
    "gn:feature_code":"PPL",
    "gn:name":"Iwaze",
    "gn:population":0,
    "gn:timezone":"Asia/Tokyo",
    "iso:country":"JP",
    "name:jbn_x_preferred":[
        "Iwaze"
    ],
    "name:jpn_x_preferred":[
        "\u5ca9\u702c"
    ],
    "wof:name":"Iwaze",
    "wof:placetype":"locality"
},
  "geometry": {"coordinates":[135.59153999999998,34.41293],"type":"Point"}
}