{
  "type": "Feature",
  "properties": {
    "gn:admin1_code":"44.0",
    "gn:admin2_code":"2111850.0",
    "gn:admin3_code":"6362.0",
    "gn:asciiname":"Hatsugasawa",
    "gn:country_code":"JP",
    "gn:dem":255,
    "gn:feature_class":"P",
    "gn:feature_code":"PPL",
    "gn:name":"Hatsugasawa",
    "gn:population":0,
    "gn:timezone":"Asia/Tokyo",
    "iso:country":"JP",
    "name:jpn_x_preferred":[
        "\u521d\u30f6\u6ca2"
    ],
    "name:jpn_x_variant":[
        "\u306f\u3064\u304c\u3055\u308f",
        "\u30cf\u30c4\u30ac\u30b5\u30ef"
    ],
    "wof:name":"Hatsugasawa",
    "wof:placetype":"locality"
},
  "geometry": {"coordinates":[140.50393,38.78341],"type":"Point"}
}