{
  "type": "Feature",
  "properties": {
    "gn:admin1_code":"45",
    "gn:asciiname":"Nowara",
    "gn:cc2":"JP",
    "gn:country_code":"JP",
    "gn:dem":0,
    "gn:feature_class":"P",
    "gn:feature_code":"PPL",
    "gn:name":"Nowara",
    "gn:population":0,
    "gn:timezone":"Asia/Tokyo",
    "iso:country":"JP",
    "name:und_x_variant":[
        "Nohara",
        "Nowara"
    ],
    "wof:name":"Nowara",
    "wof:placetype":"locality"
},
  "geometry": {"coordinates":[131.94999999999999,33.95],"type":"Point"}
}