{
  "type": "Feature",
  "properties": {
    "gn:admin1_code":"43.0",
    "gn:admin2_code":"1865123.0",
    "gn:admin3_code":"30366.0",
    "gn:asciiname":"Ozo",
    "gn:country_code":"JP",
    "gn:dem":455,
    "gn:feature_class":"P",
    "gn:feature_code":"PPL",
    "gn:name":"\u014cz\u014d",
    "gn:population":0,
    "gn:timezone":"Asia/Tokyo",
    "iso:country":"JP",
    "name:jpn_x_preferred":[
        "\u014cz\u014d"
    ],
    "name:jpn_x_variant":[
        "\u5927\u8535"
    ],
    "wof:name":"Ozo",
    "wof:placetype":"locality"
},
  "geometry": {"coordinates":[135.44683999999998,34.11573],"type":"Point"}
}