{
  "type": "Feature",
  "properties": {
    "gn:admin1_code":"3.0",
    "gn:admin2_code":"2130056.0",
    "gn:asciiname":"Tatsunokuchi",
    "gn:country_code":"JP",
    "gn:dem":45,
    "gn:feature_class":"P",
    "gn:feature_code":"PPL",
    "gn:name":"Tatsunokuchi",
    "gn:population":0,
    "gn:timezone":"Asia/Tokyo",
    "iso:country":"JP",
    "name:jpn_x_preferred":[
        "\u9f8d\u30ce\u53e3"
    ],
    "name:jpn_x_variant":[
        "\u305f\u3064\u306e\u304f\u3061",
        "\u30bf\u30c4\u30ce\u30af\u30c1"
    ],
    "wof:name":"Tatsunokuchi",
    "wof:placetype":"locality"
},
  "geometry": {"coordinates":[140.42023,40.59583],"type":"Point"}
}