{
  "type": "Feature",
  "properties": {
    "gn:admin1_code":"37.0",
    "gn:admin2_code":"1863526.0",
    "gn:asciiname":"Mukaimura",
    "gn:country_code":"JP",
    "gn:dem":429,
    "gn:feature_class":"P",
    "gn:feature_code":"PPLL",
    "gn:name":"Mukaimura",
    "gn:population":0,
    "gn:timezone":"Asia/Tokyo",
    "iso:country":"JP",
    "name:jpn_x_preferred":[
        "\u5411\u6751"
    ],
    "wof:name":"Mukaimura",
    "wof:placetype":"locality"
},
  "geometry": {"coordinates":[138.95577,35.31061],"type":"Point"}
}