{
  "type": "Feature",
  "properties": {
    "gn:admin1_code":"21.0",
    "gn:admin2_code":"1850744.0",
    "gn:admin3_code":"43364.0",
    "gn:asciiname":"Sugenotani",
    "gn:country_code":"JP",
    "gn:dem":118,
    "gn:feature_class":"P",
    "gn:feature_code":"PPLL",
    "gn:name":"Sugenotani",
    "gn:population":0,
    "gn:timezone":"Asia/Tokyo",
    "iso:country":"JP",
    "name:jpn_x_preferred":[
        "\u83c5\u30ce\u8c37"
    ],
    "name:jpn_x_variant":[
        "\u3059\u3052\u306e\u305f\u306b",
        "\u30b9\u30b2\u30ce\u30bf\u30cb"
    ],
    "wof:name":"Sugenotani",
    "wof:placetype":"locality"
},
  "geometry": {"coordinates":[130.61931000000001,32.88245],"type":"Point"}
}