{
  "type": "Feature",
  "properties": {
    "gn:admin1_code":"3.0",
    "gn:admin2_code":"2130225.0",
    "gn:asciiname":"Koya",
    "gn:country_code":"JP",
    "gn:dem":21,
    "gn:feature_class":"P",
    "gn:feature_code":"PPL",
    "gn:name":"K\u014dya",
    "gn:population":0,
    "gn:timezone":"Asia/Tokyo",
    "iso:country":"JP",
    "name:jpn_x_preferred":[
        "\u9ad8\u91ce"
    ],
    "name:jpn_x_variant":[
        "\u3053\u3046\u3084",
        "\u30b3\u30a6\u30e4"
    ],
    "name:und_x_variant":[
        "K\u014dya"
    ],
    "wof:name":"Koya",
    "wof:placetype":"locality"
},
  "geometry": {"coordinates":[140.52638999999999,40.73999],"type":"Point"}
}