{
  "type": "Feature",
  "properties": {
    "gn:admin1_code":"21.0",
    "gn:admin2_code":"1865358.0",
    "gn:asciiname":"Ikariishi-shimo",
    "gn:country_code":"JP",
    "gn:dem":100,
    "gn:feature_class":"P",
    "gn:feature_code":"PPLL",
    "gn:name":"Ikariishi-shimo",
    "gn:population":0,
    "gn:timezone":"Asia/Tokyo",
    "iso:country":"JP",
    "name:jpn_x_preferred":[
        "\u7887\u77f3\u4e0b"
    ],
    "name:jpn_x_variant":[
        "\u3044\u304b\u308a\u3044\u3057\u3057\u3082",
        "\u30a4\u30ab\u30ea\u30a4\u30b7\u30b7\u30e2"
    ],
    "wof:name":"Ikariishi-shimo",
    "wof:placetype":"locality"
},
  "geometry": {"coordinates":[130.14852999999999,32.3686],"type":"Point"}
}