{
  "type": "Feature",
  "properties": {
    "gn:admin1_code":"32.0",
    "gn:admin2_code":"1857170.0",
    "gn:admin3_code":"27383.0",
    "gn:asciiname":"Azumazaka",
    "gn:country_code":"JP",
    "gn:dem":234,
    "gn:feature_class":"P",
    "gn:feature_code":"PPL",
    "gn:name":"Azumazaka",
    "gn:population":0,
    "gn:timezone":"Asia/Tokyo",
    "iso:country":"JP",
    "name:jpn_x_preferred":[
        "\u6771\u962a"
    ],
    "wof:name":"Azumazaka",
    "wof:placetype":"locality"
},
  "geometry": {"coordinates":[135.62549000000001,34.44371],"type":"Point"}
}