{
  "type": "Feature",
  "properties": {
    "gn:admin1_code":"21.0",
    "gn:admin2_code":"1859488.0",
    "gn:asciiname":"Kyokushi-fumoto",
    "gn:country_code":"JP",
    "gn:dem":178,
    "gn:feature_class":"P",
    "gn:feature_code":"PPL",
    "gn:name":"Kyokushi-fumoto",
    "gn:population":0,
    "gn:timezone":"Asia/Tokyo",
    "iso:country":"JP",
    "name:jpn_x_preferred":[
        "\u65ed\u5fd7\u9e93"
    ],
    "name:jpn_x_variant":[
        "\u304d\u3087\u304f\u3057\u3075\u3082\u3068",
        "\u30ad\u30e7\u30af\u30b7\u30d5\u30e2\u30c8"
    ],
    "wof:name":"Kyokushi-fumoto",
    "wof:placetype":"locality"
},
  "geometry": {"coordinates":[130.87701999999999,32.94430999999999],"type":"Point"}
}