{
  "type": "Feature",
  "properties": {
    "gn:admin1_code":"6.0",
    "gn:admin2_code":"1863982.0",
    "gn:asciiname":"Shimaderacho",
    "gn:country_code":"JP",
    "gn:dem":15,
    "gn:feature_class":"P",
    "gn:feature_code":"PPL",
    "gn:name":"Shimaderach\u014d",
    "gn:population":0,
    "gn:timezone":"Asia/Tokyo",
    "iso:country":"JP",
    "name:jpn_x_preferred":[
        "\u5cf6\u5bfa\u753a"
    ],
    "name:und_x_variant":[
        "Shimaderach\u014d"
    ],
    "wof:name":"Shimaderacho",
    "wof:placetype":"locality"
},
  "geometry": {"coordinates":[136.14443,36.02491],"type":"Point"}
}