{
  "type": "Feature",
  "properties": {
    "gn:admin1_code":"43",
    "gn:admin2_code":"1863079.0",
    "gn:asciiname":"Shimizu",
    "gn:country_code":"JP",
    "gn:dem":76,
    "gn:feature_class":"P",
    "gn:feature_code":"PPL",
    "gn:name":"Shimizu",
    "gn:population":0,
    "gn:timezone":"Asia/Tokyo",
    "iso:country":"JP",
    "name:jpn_x_preferred":[
        "\u6e05\u6c34"
    ],
    "wof:name":"Shimizu",
    "wof:placetype":"locality"
},
  "geometry": {"coordinates":[135.60040000000001,34.30752],"type":"Point"}
}