{
  "type": "Feature",
  "properties": {
    "gn:admin1_code":"16.0",
    "gn:admin2_code":"7441806.0",
    "gn:admin3_code":"3483.0",
    "gn:asciiname":"Kado",
    "gn:country_code":"JP",
    "gn:dem":458,
    "gn:feature_class":"P",
    "gn:feature_code":"PPL",
    "gn:name":"Kado",
    "gn:population":0,
    "gn:timezone":"Asia/Tokyo",
    "iso:country":"JP",
    "name:ceb_x_preferred":[
        "Kado"
    ],
    "name:deu_x_preferred":[
        "Kado"
    ],
    "name:epo_x_preferred":[
        "Kado"
    ],
    "name:fra_x_preferred":[
        "Kado"
    ],
    "name:rus_x_preferred":[
        "\u041a\u0430\u0434\u043e"
    ],
    "name:srp_x_preferred":[
        "\u041a\u0430\u0434\u043e"
    ],
    "name:swe_x_preferred":[
        "Kado"
    ],
    "wof:name":"Kado",
    "wof:placetype":"locality"
},
  "geometry": {"coordinates":[141.65000000000001,39.86667],"type":"Point"}
}