{
  "type": "Feature",
  "properties": {
    "gn:admin1_code":"24.0",
    "gn:admin2_code":"2112574.0",
    "gn:asciiname":"Kosaki",
    "gn:country_code":"JP",
    "gn:dem":44,
    "gn:feature_class":"P",
    "gn:feature_code":"PPL",
    "gn:name":"Kosaki",
    "gn:population":0,
    "gn:timezone":"Asia/Tokyo",
    "iso:country":"JP",
    "name:ceb_x_preferred":[
        "Kosaki"
    ],
    "name:jpn_x_preferred":[
        "\u5c0f\u5d0e"
    ],
    "name:jpn_x_variant":[
        "\u3053\u3055\u304d",
        "\u30b3\u30b5\u30ad"
    ],
    "name:lit_x_preferred":[
        "Kosakai"
    ],
    "name:pol_x_preferred":[
        "Kosaki"
    ],
    "name:ukr_x_preferred":[
        "\u041a\u043e\u0441\u0430\u043a\u0456"
    ],
    "wof:name":"Kosaki",
    "wof:placetype":"locality"
},
  "geometry": {"coordinates":[141.19998000000001,38.4997],"type":"Point"}
}