{
  "type": "Feature",
  "properties": {
    "gn:admin1_code":"07",
    "gn:admin2_code":"1859306.0",
    "gn:admin3_code":"40103.0",
    "gn:asciiname":"Sutara",
    "gn:country_code":"JP",
    "gn:dem":47,
    "gn:feature_class":"P",
    "gn:feature_code":"PPL",
    "gn:name":"Sutara",
    "gn:population":0,
    "gn:timezone":"Asia/Tokyo",
    "iso:country":"JP",
    "name:jpn_x_preferred":[
        "\u4fee\u591a\u7f85"
    ],
    "name:und_x_variant":[
        "Shutara",
        "Sutara"
    ],
    "wof:name":"Sutara",
    "wof:placetype":"locality"
},
  "geometry": {"coordinates":[130.80002999999999,33.89971],"type":"Point"}
}