{
  "type": "Feature",
  "properties": {
    "gn:admin1_code":"27",
    "gn:admin2_code":"1857159.0",
    "gn:admin3_code":"42411.0",
    "gn:asciiname":"Arakawa",
    "gn:country_code":"JP",
    "gn:dem":126,
    "gn:feature_class":"P",
    "gn:feature_code":"PPL",
    "gn:name":"Arakawa",
    "gn:population":0,
    "gn:timezone":"Asia/Tokyo",
    "iso:country":"JP",
    "name:deu_x_preferred":[
        "Arakawa"
    ],
    "name:epo_x_preferred":[
        "Araka\u016da"
    ],
    "name:fas_x_preferred":[
        "\u0622\u0631\u0627\u06a9\u0627\u0648\u0627"
    ],
    "name:fra_x_preferred":[
        "Arakawa"
    ],
    "name:ind_x_preferred":[
        "Arakawa"
    ],
    "name:ita_x_preferred":[
        "Arakawa"
    ],
    "name:kor_x_preferred":[
        "\uc544\ub77c\uce74\uc640"
    ],
    "name:nld_x_preferred":[
        "Arakawa"
    ],
    "name:pol_x_preferred":[
        "Arakawa"
    ],
    "name:ron_x_preferred":[
        "Arakawa"
    ],
    "name:rus_x_preferred":[
        "\u0410\u0440\u0430\u043a\u0430\u0432\u0430"
    ],
    "name:spa_x_preferred":[
        "Arakawa"
    ],
    "name:swe_x_preferred":[
        "Arakawa"
    ],
    "name:tha_x_preferred":[
        "\u0e2d\u0e30\u0e23\u0e30\u0e01\u0e30\u0e27\u0e30"
    ],
    "name:ukr_x_preferred":[
        "\u0420\u0456\u0447\u043a\u0430 \u0410\u0440\u0430"
    ],
    "wof:name":"Arakawa",
    "wof:placetype":"locality"
},
  "geometry": {"coordinates":[129.05500000000001,32.91667],"type":"Point"}
}