{
  "type": "Feature",
  "properties": {
    "gn:admin1_code":"4.0",
    "gn:admin2_code":"1861964.0",
    "gn:asciiname":"Chidoricho",
    "gn:country_code":"JP",
    "gn:dem":4,
    "gn:feature_class":"P",
    "gn:feature_code":"PPL",
    "gn:name":"Chidorich\u014d",
    "gn:population":0,
    "gn:timezone":"Asia/Tokyo",
    "iso:country":"JP",
    "name:jpn_x_preferred":[
        "\u5343\u9ce5\u753a"
    ],
    "name:und_x_variant":[
        "Chidorich\u014d"
    ],
    "wof:name":"Chidoricho",
    "wof:placetype":"locality"
},
  "geometry": {"coordinates":[139.93044,35.67312000000001],"type":"Point"}
}