{
  "type": "Feature",
  "properties": {
    "gn:admin1_code":"4.0",
    "gn:admin2_code":"2112997.0",
    "gn:admin3_code":"12426.0",
    "gn:asciiname":"Hattame",
    "gn:country_code":"JP",
    "gn:dem":74,
    "gn:feature_class":"P",
    "gn:feature_code":"PPLL",
    "gn:name":"Hattame",
    "gn:population":0,
    "gn:timezone":"Asia/Tokyo",
    "iso:country":"JP",
    "name:jpn_x_preferred":[
        "\u516b\u53cd\u76ee"
    ],
    "name:jpn_x_variant":[
        "\u306f\u3063\u305f\u3081",
        "\u30cf\u30c3\u30bf\u30e1"
    ],
    "wof:name":"Hattame",
    "wof:placetype":"locality"
},
  "geometry": {"coordinates":[140.24035000000001,35.47019],"type":"Point"}
}