{
  "type": "Feature",
  "properties": {
    "gn:admin1_code":"4.0",
    "gn:admin2_code":"2110982.0",
    "gn:asciiname":"Yamanaka",
    "gn:country_code":"JP",
    "gn:dem":14,
    "gn:feature_class":"P",
    "gn:feature_code":"PPLL",
    "gn:name":"Yamanaka",
    "gn:population":0,
    "gn:timezone":"Asia/Tokyo",
    "iso:country":"JP",
    "name:jpn_x_preferred":[
        "\u5c71\u4e2d"
    ],
    "name:jpn_x_variant":[
        "\u3084\u307e\u306a\u304b",
        "\u30e4\u30de\u30ca\u30ab"
    ],
    "wof:name":"Yamanaka",
    "wof:placetype":"locality"
},
  "geometry": {"coordinates":[140.00951000000001,35.38574000000001],"type":"Point"}
}