{
  "type": "Feature",
  "properties": {
    "iso:country":"JP",
    "qs:name":"\u5e83\u91ce\u753a",
    "qs:name_adm0":"\u65e5\u672c",
    "qs:name_adm1":"\u798f\u5cf6\u770c",
    "qs:photos":37,
    "qs:photos_1k":7,
    "qs:photos_9k":1,
    "qs:photos_9r":2,
    "qs:photos_all":63,
    "qs:photos_sr":2,
    "qs:placetype":"Town",
    "qs:pop_sr":"0",
    "wof:name":"\u5e83\u91ce\u753a",
    "wof:placetype":"locality"
},
  "geometry": {"coordinates":[140.93835799999999,37.223847],"type":"Point"}
}