{
  "type": "Feature",
  "properties": {
    "gn:admin1_code":"37.0",
    "gn:admin2_code":"1864089.0",
    "gn:asciiname":"Asahicho",
    "gn:country_code":"JP",
    "gn:dem":36,
    "gn:feature_class":"P",
    "gn:feature_code":"PPLL",
    "gn:name":"Asahich\u014d",
    "gn:population":0,
    "gn:timezone":"Asia/Tokyo",
    "iso:country":"JP",
    "name:jpn_x_preferred":[
        "\u65ed\u753a"
    ],
    "name:und_x_variant":[
        "Asahich\u014d"
    ],
    "wof:name":"Asahicho",
    "wof:placetype":"locality"
},
  "geometry": {"coordinates":[138.63534000000001,35.17581],"type":"Point"}
}