{
  "type": "Feature",
  "properties": {
    "gn:admin1_code":"30",
    "gn:admin2_code":"1855742.0",
    "gn:asciiname":"Yamakunimachi-morizane",
    "gn:country_code":"JP",
    "gn:dem":369,
    "gn:feature_class":"P",
    "gn:feature_code":"PPL",
    "gn:name":"Yamakunimachi-morizane",
    "gn:population":0,
    "gn:timezone":"Asia/Tokyo",
    "iso:country":"JP",
    "name:jpn_x_preferred":[
        "\u5c71\u56fd\u753a\u5b88\u5b9f"
    ],
    "name:und_x_variant":[
        "Morisane",
        "Morimi",
        "Morizane",
        "Yamakunimachi-morizane"
    ],
    "wof:name":"Yamakunimachi-morizane",
    "wof:placetype":"locality"
},
  "geometry": {"coordinates":[131.02751999999998,33.39607],"type":"Point"}
}