{
  "type": "Feature",
  "properties": {
    "gn:admin1_code":"43.0",
    "gn:admin2_code":"1860774.0",
    "gn:admin3_code":"30304.0",
    "gn:asciiname":"Takahata",
    "gn:country_code":"JP",
    "gn:dem":170,
    "gn:feature_class":"P",
    "gn:feature_code":"PPL",
    "gn:name":"Takahata",
    "gn:population":0,
    "gn:timezone":"Asia/Tokyo",
    "iso:country":"JP",
    "name:jpn_x_preferred":[
        "\u9ad8\u7551"
    ],
    "wof:name":"Takahata",
    "wof:placetype":"locality"
},
  "geometry": {"coordinates":[135.39722,34.13659000000001],"type":"Point"}
}