{
  "type": "Feature",
  "properties": {
    "gn:admin1_code":"12.0",
    "gn:admin2_code":"2129370.0",
    "gn:asciiname":"Showaminami",
    "gn:country_code":"JP",
    "gn:dem":7,
    "gn:feature_class":"P",
    "gn:feature_code":"PPL",
    "gn:name":"Sh\u014dwaminami",
    "gn:population":0,
    "gn:timezone":"Asia/Tokyo",
    "iso:country":"JP",
    "name:jpn_x_preferred":[
        "\u662d\u548c\u5357"
    ],
    "name:jpn_x_variant":[
        "\u3057\u3087\u3046\u308f\u307f\u306a\u307f",
        "\u30b7\u30e7\u30a6\u30ef\u30df\u30ca\u30df"
    ],
    "name:und_x_variant":[
        "Sh\u014dwaminami"
    ],
    "wof:name":"Showaminami",
    "wof:placetype":"locality"
},
  "geometry": {"coordinates":[144.35292999999999,43.02145],"type":"Point"}
}