{
  "type": "Feature",
  "properties": {
    "gn:admin1_code":"13.0",
    "gn:admin2_code":"1855204.0",
    "gn:asciiname":"Jurinjicho",
    "gn:country_code":"JP",
    "gn:dem":248,
    "gn:feature_class":"P",
    "gn:feature_code":"PPL",
    "gn:name":"J\u016brinjich\u014d",
    "gn:population":0,
    "gn:timezone":"Asia/Tokyo",
    "iso:country":"JP",
    "name:jpn_x_preferred":[
        "\u9df2\u6797\u5bfa\u753a"
    ],
    "name:und_x_variant":[
        "J\u016brinjich\u014d"
    ],
    "wof:name":"Jurinjicho",
    "wof:placetype":"locality"
},
  "geometry": {"coordinates":[135.3133,34.77338],"type":"Point"}
}