{
  "type": "Feature",
  "properties": {
    "gn:admin1_code":"21.0",
    "gn:admin2_code":"1848441.0",
    "gn:asciiname":"Izumimachi-kureko",
    "gn:country_code":"JP",
    "gn:dem":781,
    "gn:feature_class":"P",
    "gn:feature_code":"PPL",
    "gn:name":"Izumimachi-kureko",
    "gn:population":0,
    "gn:timezone":"Asia/Tokyo",
    "iso:country":"JP",
    "name:jpn_x_preferred":[
        "\u548c\u6cc9\u753a\u4e45\u9023\u5b50"
    ],
    "name:jpn_x_variant":[
        "\u3044\u305a\u307f\u307e\u3061\u304f\u308c\u3053",
        "\u30a4\u30ba\u30df\u30de\u30c1\u30af\u30ec\u30b3"
    ],
    "wof:name":"Izumimachi-kureko",
    "wof:placetype":"locality"
},
  "geometry": {"coordinates":[130.91879,32.46145],"type":"Point"}
}