{
  "type": "Feature",
  "properties": {
    "iso:country":"JP",
    "name:eng_x_preferred":[
        "Jozankeionsennishi 2 Chome"
    ],
    "name:eng_x_variant":[
        "Jouzankeionsennishi 2 Choume",
        "Jozankeionsennishi 2 Chome"
    ],
    "name:jpn_x_preferred":[
        "\uff12\u4e01\u76ee"
    ],
    "name:jpn_x_variant":[
        "\u3058\u3087\u3046\u3056\u3093\u3051\u3044\u304a\u3093\u305b\u3093\u306b\u3057 \uff12\u3061\u3087\u3046\u3081",
        "\u5b9a\u5c71\u6e13\u6e29\u6cc9\u897f \uff12\u4e01\u76ee",
        "\uff12\u3061\u3087\u3046\u3081"
    ],
    "name:unk_x_variant":[
        "\uff12\u4e01\u76ee"
    ],
    "qs:gn_local":0,
    "qs:local_max":2554,
    "qs:local_sum":22076,
    "qs:localhoods":97,
    "qs:name":"\uff12\u4e01\u76ee",
    "qs:name_adm0":"\u65e5\u672c",
    "qs:name_adm1":"\u5317\u6d77\u9053",
    "qs:name_adm2":"\u5357\u533a",
    "qs:name_en":"Jozankeionsennishi 2 Chome",
    "qs:name_lau":"\u5b9a\u5c71\u6e13\u6e29\u6cc9\u897f",
    "qs:name_local":"\u672d\u5e4c\u5e02",
    "qs:photo_max":22,
    "qs:photo_sum":41,
    "qs:placetype":"Suburb",
    "qs:quad_count":6,
    "qs:woe_adm0":23424856,
    "qs:woe_adm1":7153351,
    "qs:woe_adm2":1111800,
    "qs:woe_lau":28379882,
    "qs:woe_local":1118108,
    "qs:woe_ver":"7.10.0",
    "wof:lang":[
        "jpn"
    ],
    "wof:name":"\uff12\u4e01\u76ee",
    "wof:placetype":"neighbourhood"
},
  "geometry": {"coordinates":[141.166078,42.969216],"type":"Point"}
}