{
  "type": "Feature",
  "properties": {
    "gn:admin1_code":"19.0",
    "gn:admin2_code":"1865011.0",
    "gn:admin3_code":"14364.0",
    "gn:asciiname":"Maekochi",
    "gn:country_code":"JP",
    "gn:dem":77,
    "gn:feature_class":"P",
    "gn:feature_code":"PPLL",
    "gn:name":"Maek\u014dchi",
    "gn:population":0,
    "gn:timezone":"Asia/Tokyo",
    "iso:country":"JP",
    "name:jpn_x_preferred":[
        "\u524d\u8015\u5730"
    ],
    "name:und_x_variant":[
        "Maek\u014dchi"
    ],
    "wof:name":"Maekochi",
    "wof:placetype":"locality"
},
  "geometry": {"coordinates":[139.10347999999999,35.35504],"type":"Point"}
}