{
  "type": "Feature",
  "properties": {
    "gn:admin1_code":"21.0",
    "gn:admin2_code":"7412708.0",
    "gn:admin3_code":"43510.0",
    "gn:asciiname":"Matsubaba",
    "gn:country_code":"JP",
    "gn:dem":138,
    "gn:feature_class":"P",
    "gn:feature_code":"PPLL",
    "gn:name":"Matsubaba",
    "gn:population":0,
    "gn:timezone":"Asia/Tokyo",
    "iso:country":"JP",
    "name:jpn_x_preferred":[
        "\u677e\u99ac\u5834"
    ],
    "wof:name":"Matsubaba",
    "wof:placetype":"locality"
},
  "geometry": {"coordinates":[130.81933999999998,32.26061],"type":"Point"}
}