{
  "type": "Feature",
  "properties": {
    "gn:admin1_code":"4.0",
    "gn:admin2_code":"7465524.0",
    "gn:asciiname":"Misakicho-yagami",
    "gn:country_code":"JP",
    "gn:dem":37,
    "gn:feature_class":"P",
    "gn:feature_code":"PPL",
    "gn:name":"Misakich\u014d-yagami",
    "gn:population":0,
    "gn:timezone":"Asia/Tokyo",
    "iso:country":"JP",
    "name:jpn_x_preferred":[
        "\u5cac\u753a\u8c37\u4e0a"
    ],
    "name:jpn_x_variant":[
        "\u307f\u3055\u304d\u3061\u3087\u3046\u3084\u304c\u307f",
        "\u30df\u30b5\u30ad\u30c1\u30e7\u30a6\u30e4\u30ac\u30df"
    ],
    "name:und_x_variant":[
        "Misakich\u014d-yagami"
    ],
    "wof:name":"Misakicho-yagami",
    "wof:placetype":"locality"
},
  "geometry": {"coordinates":[140.36250000000001,35.33538],"type":"Point"}
}