{
  "type": "Feature",
  "properties": {
    "gn:admin1_code":"3.0",
    "gn:admin2_code":"2128302.0",
    "gn:admin3_code":"2441.0",
    "gn:asciiname":"Naradate",
    "gn:country_code":"JP",
    "gn:dem":111,
    "gn:feature_class":"P",
    "gn:feature_code":"PPL",
    "gn:name":"Naradate",
    "gn:population":0,
    "gn:timezone":"Asia/Tokyo",
    "iso:country":"JP",
    "name:jpn_x_preferred":[
        "\u6962\u9928"
    ],
    "name:jpn_x_variant":[
        "\u306a\u3089\u3060\u3066",
        "\u30ca\u30e9\u30c0\u30c6"
    ],
    "wof:name":"Naradate",
    "wof:placetype":"locality"
},
  "geometry": {"coordinates":[141.23326,40.35565],"type":"Point"}
}