{
  "type": "Feature",
  "properties": {
    "gn:admin1_code":"12.0",
    "gn:admin2_code":"2130419.0",
    "gn:asciiname":"Osaru",
    "gn:country_code":"JP",
    "gn:dem":6,
    "gn:feature_class":"P",
    "gn:feature_code":"PPL",
    "gn:name":"Osaru",
    "gn:population":0,
    "gn:timezone":"Asia/Tokyo",
    "iso:country":"JP",
    "wof:name":"Osaru",
    "wof:placetype":"locality"
},
  "geometry": {"coordinates":[140.83803999999995,42.49215],"type":"Point"}
}