{
  "type": "Feature",
  "properties": {
    "gn:admin1_code":"3.0",
    "gn:admin2_code":"2128302.0",
    "gn:admin3_code":"2450.0",
    "gn:asciiname":"Okakedai",
    "gn:country_code":"JP",
    "gn:dem":233,
    "gn:feature_class":"P",
    "gn:feature_code":"PPL",
    "gn:name":"\u014ckakedai",
    "gn:population":0,
    "gn:timezone":"Asia/Tokyo",
    "iso:country":"JP",
    "name:jpn_x_preferred":[
        "\u5927\u6b20\u5e73"
    ],
    "name:jpn_x_variant":[
        "\u304a\u304a\u304b\u3051\u3060\u3044",
        "\u30aa\u30aa\u30ab\u30b1\u30c0\u30a4"
    ],
    "name:und_x_variant":[
        "\u014ckakedai"
    ],
    "wof:name":"Okakedai",
    "wof:placetype":"locality"
},
  "geometry": {"coordinates":[141.14543999999995,40.49306],"type":"Point"}
}