{
  "type": "Feature",
  "properties": {
    "gn:admin1_code":"21.0",
    "gn:admin2_code":"7413152.0",
    "gn:asciiname":"Tainoura",
    "gn:country_code":"JP",
    "gn:dem":26,
    "gn:feature_class":"P",
    "gn:feature_code":"PPLL",
    "gn:name":"Tainoura",
    "gn:population":0,
    "gn:timezone":"Asia/Tokyo",
    "iso:country":"JP",
    "name:jpn_x_preferred":[
        "\u7530\u4e95\u4e4b\u6d66"
    ],
    "name:jpn_x_variant":[
        "\u305f\u3044\u306e\u3046\u3089",
        "\u30bf\u30a4\u30ce\u30a6\u30e9"
    ],
    "wof:name":"Tainoura",
    "wof:placetype":"locality"
},
  "geometry": {"coordinates":[130.48758000000001,32.6061],"type":"Point"}
}