{
  "type": "Feature",
  "properties": {
    "gn:admin1_code":"19.0",
    "gn:admin2_code":"1848308.0",
    "gn:asciiname":"Shiomidai",
    "gn:country_code":"JP",
    "gn:dem":61,
    "gn:feature_class":"P",
    "gn:feature_code":"PPL",
    "gn:name":"Shiomidai",
    "gn:population":0,
    "gn:timezone":"Asia/Tokyo",
    "iso:country":"JP",
    "name:jpn_x_preferred":[
        "\u6c50\u898b\u53f0"
    ],
    "name:jpn_x_variant":[
        "\u3057\u304a\u307f\u3060\u3044",
        "\u30b7\u30aa\u30df\u30c0\u30a4"
    ],
    "wof:name":"Shiomidai",
    "wof:placetype":"locality"
},
  "geometry": {"coordinates":[139.65992,35.26375],"type":"Point"}
}