{
  "type": "Feature",
  "properties": {
    "gn:admin1_code":"33.0",
    "gn:admin2_code":"7391355.0",
    "gn:asciiname":"Okawacho-higashitashiro",
    "gn:country_code":"JP",
    "gn:dem":168,
    "gn:feature_class":"P",
    "gn:feature_code":"PPL",
    "gn:name":"\u014ckawach\u014d-higashitashiro",
    "gn:population":0,
    "gn:timezone":"Asia/Tokyo",
    "iso:country":"JP",
    "name:jpn_x_preferred":[
        "\u5927\u5ddd\u753a\u6771\u7530\u4ee3"
    ],
    "name:und_x_variant":[
        "\u014ckawach\u014d-higashitashiro"
    ],
    "wof:name":"Okawacho-higashitashiro",
    "wof:placetype":"locality"
},
  "geometry": {"coordinates":[129.99976000000001,33.28942],"type":"Point"}
}