{
  "type": "Feature",
  "properties": {
    "gn:admin1_code":"2.0",
    "gn:admin2_code":"2113122.0",
    "gn:asciiname":"Hodono-kanasamachi",
    "gn:country_code":"JP",
    "gn:dem":12,
    "gn:feature_class":"P",
    "gn:feature_code":"PPL",
    "gn:name":"Hodono-kanasamachi",
    "gn:population":0,
    "gn:timezone":"Asia/Tokyo",
    "iso:country":"JP",
    "name:jpn_x_preferred":[
        "\u4fdd\u6238\u91ce\u91d1\u7802\u753a"
    ],
    "name:jpn_x_variant":[
        "\u307b\u3069\u306e\u304b\u306a\u3055\u307e\u3061",
        "\u30db\u30c9\u30ce\u30ab\u30ca\u30b5\u30de\u30c1"
    ],
    "wof:name":"Hodono-kanasamachi",
    "wof:placetype":"locality"
},
  "geometry": {"coordinates":[140.12235999999999,39.73079],"type":"Point"}
}