{
  "type": "Feature",
  "properties": {
    "gn:admin1_code":"26.0",
    "gn:admin2_code":"1860552.0",
    "gn:admin3_code":"20382.0",
    "gn:asciiname":"Shinden",
    "gn:country_code":"JP",
    "gn:dem":808,
    "gn:feature_class":"P",
    "gn:feature_code":"PPL",
    "gn:name":"Shinden",
    "gn:population":0,
    "gn:timezone":"Asia/Tokyo",
    "iso:country":"JP",
    "name:deu_x_preferred":[
        "Shinden"
    ],
    "name:jpn_x_preferred":[
        "\u65b0\u7530"
    ],
    "wof:name":"Shinden",
    "wof:placetype":"locality"
},
  "geometry": {"coordinates":[137.97233,36.02759000000001],"type":"Point"}
}