{
  "type": "Feature",
  "properties": {
    "gn:admin1_code":"43.0",
    "gn:admin2_code":"1865123.0",
    "gn:admin3_code":"30362.0",
    "gn:asciiname":"Higashinaka",
    "gn:country_code":"JP",
    "gn:dem":11,
    "gn:feature_class":"P",
    "gn:feature_code":"PPL",
    "gn:name":"Higashinaka",
    "gn:population":0,
    "gn:timezone":"Asia/Tokyo",
    "iso:country":"JP",
    "name:jpn_x_preferred":[
        "\u6771\u4e2d"
    ],
    "wof:name":"Higashinaka",
    "wof:placetype":"locality"
},
  "geometry": {"coordinates":[135.18453,34.01942],"type":"Point"}
}