{
  "type": "Feature",
  "properties": {
    "gn:admin1_code":"6.0",
    "gn:admin2_code":"7465772.0",
    "gn:admin3_code":"18442.0",
    "gn:asciiname":"Okunoura",
    "gn:country_code":"JP",
    "gn:dem":8,
    "gn:feature_class":"P",
    "gn:feature_code":"PPL",
    "gn:name":"Okunoura",
    "gn:population":0,
    "gn:timezone":"Asia/Tokyo",
    "iso:country":"JP",
    "wof:name":"Okunoura",
    "wof:placetype":"locality"
},
  "geometry": {"coordinates":[135.96666999999999,35.71167],"type":"Point"}
}