{
  "type": "Feature",
  "properties": {
    "gn:admin1_code":"42.0",
    "gn:admin2_code":"1850038.0",
    "gn:asciiname":"Shogawamachi-mitani",
    "gn:country_code":"JP",
    "gn:dem":86,
    "gn:feature_class":"P",
    "gn:feature_code":"PPL",
    "gn:name":"Sh\u014dgawamachi-mitani",
    "gn:population":0,
    "gn:timezone":"Asia/Tokyo",
    "iso:country":"JP",
    "name:jpn_x_preferred":[
        "\u5e84\u5ddd\u753a\u4e09\u8c37"
    ],
    "name:und_x_variant":[
        "Sh\u014dgawamachi-mitani"
    ],
    "wof:name":"Shogawamachi-mitani",
    "wof:placetype":"locality"
},
  "geometry": {"coordinates":[137.00540000000001,36.61086],"type":"Point"}
}