{
  "type": "Feature",
  "properties": {
    "gn:admin1_code":"30",
    "gn:asciiname":"Katsura",
    "gn:cc2":"JP",
    "gn:country_code":"JP",
    "gn:dem":-9999,
    "gn:feature_class":"P",
    "gn:feature_code":"PPL",
    "gn:name":"Katsura",
    "gn:population":0,
    "gn:timezone":"Asia/Tokyo",
    "iso:country":"JP",
    "name:deu_x_preferred":[
        "Katsura"
    ],
    "name:fas_x_preferred":[
        "\u06a9\u0627\u062a\u0633\u0648\u0631\u0627"
    ],
    "name:jpn_x_preferred":[
        "\u304b\u3064\u3089"
    ],
    "name:nld_x_preferred":[
        "Katsura"
    ],
    "name:rus_x_preferred":[
        "\u041a\u0430\u0446\u0443\u0440\u0430"
    ],
    "name:spa_x_preferred":[
        "Katsura"
    ],
    "name:swe_x_preferred":[
        "Katsura"
    ],
    "name:tha_x_preferred":[
        "\u0e04\u0e30\u0e2a\u0e36\u0e23\u0e30"
    ],
    "name:ukr_x_preferred":[
        "\u041a\u0430\u0446\u0443\u0440\u0430"
    ],
    "name:und_x_variant":[
        "Kazura",
        "Katura"
    ],
    "wof:name":"Katsura",
    "wof:placetype":"locality"
},
  "geometry": {"coordinates":[131.90000000000001,32.98333],"type":"Point"}
}