{
  "type": "Feature",
  "properties": {
    "gn:admin1_code":"30",
    "gn:asciiname":"Katsura",
    "gn:cc2":"JP",
    "gn:country_code":"JP",
    "gn:dem":-9999,
    "gn:feature_class":"P",
    "gn:feature_code":"PPL",
    "gn:name":"Katsura",
    "gn:population":0,
    "gn:timezone":"Asia/Tokyo",
    "iso:country":"JP",
    "name:und_x_variant":[
        "Kazura",
        "Katura",
        "Katsura"
    ],
    "wof:name":"Katsura",
    "wof:placetype":"locality"
},
  "geometry": {"coordinates":[131.90000000000001,32.98333],"type":"Point"}
}