{
  "type": "Feature",
  "properties": {
    "gn:admin1_code":"27",
    "gn:asciiname":"Tainoura",
    "gn:cc2":"JP",
    "gn:country_code":"JP",
    "gn:dem":1,
    "gn:feature_class":"P",
    "gn:feature_code":"PPL",
    "gn:name":"Tainoura",
    "gn:population":0,
    "gn:timezone":"Asia/Tokyo",
    "iso:country":"JP",
    "name:und_x_variant":[
        "Higashi",
        "Tainoura"
    ],
    "wof:name":"Tainoura",
    "wof:placetype":"locality"
},
  "geometry": {"coordinates":[129.10138999999998,32.95167],"type":"Point"}
}