{
  "type": "Feature",
  "properties": {
    "gn:admin1_code":"36.0",
    "gn:admin2_code":"1854361.0",
    "gn:admin3_code":"32527.0",
    "gn:asciiname":"Oe",
    "gn:country_code":"JP",
    "gn:dem":8,
    "gn:feature_class":"P",
    "gn:feature_code":"PPL",
    "gn:name":"\u014ce",
    "gn:population":0,
    "gn:timezone":"Asia/Tokyo",
    "iso:country":"JP",
    "name:jpn_x_preferred":[
        "\u5927\u6c5f"
    ],
    "name:und_x_variant":[
        "\u014ce"
    ],
    "wof:name":"Oe",
    "wof:placetype":"locality"
},
  "geometry": {"coordinates":[133.03991000000002,36.01143],"type":"Point"}
}