{
  "type": "Feature",
  "properties": {
    "gn:admin1_code":"24.0",
    "gn:admin2_code":"2112074.0",
    "gn:admin3_code":"4424.0",
    "gn:asciiname":"Warabizaki",
    "gn:country_code":"JP",
    "gn:dem":43,
    "gn:feature_class":"P",
    "gn:feature_code":"PPL",
    "gn:name":"Warabizaki",
    "gn:population":0,
    "gn:timezone":"Asia/Tokyo",
    "iso:country":"JP",
    "name:jpn_x_preferred":[
        "\u8568\u5d0e"
    ],
    "wof:name":"Warabizaki",
    "wof:placetype":"locality"
},
  "geometry": {"coordinates":[140.88749999999999,38.50389000000001],"type":"Point"}
}