{
  "type": "Feature",
  "properties": {
    "gn:admin1_code":"21.0",
    "gn:admin2_code":"1858418.0",
    "gn:admin3_code":"43104.0",
    "gn:asciiname":"Nicho",
    "gn:country_code":"JP",
    "gn:dem":-1,
    "gn:feature_class":"P",
    "gn:feature_code":"PPLL",
    "gn:name":"Nich\u014d",
    "gn:population":0,
    "gn:timezone":"Asia/Tokyo",
    "iso:country":"JP",
    "name:jpn_x_preferred":[
        "\u5f10\u753a"
    ],
    "name:jpn_x_variant":[
        "\u306b\u3061\u3087\u3046",
        "\u30cb\u30c1\u30e7\u30a6"
    ],
    "name:und_x_variant":[
        "Nich\u014d"
    ],
    "wof:name":"Nicho",
    "wof:placetype":"locality"
},
  "geometry": {"coordinates":[130.62358,32.71587],"type":"Point"}
}