{
  "type": "Feature",
  "properties": {
    "gn:admin1_code":"4.0",
    "gn:admin2_code":"1863711.0",
    "gn:asciiname":"Osawa",
    "gn:country_code":"JP",
    "gn:dem":86,
    "gn:feature_class":"P",
    "gn:feature_code":"PPLL",
    "gn:name":"\u014csawa",
    "gn:population":0,
    "gn:timezone":"Asia/Tokyo",
    "iso:country":"JP",
    "name:jpn_x_preferred":[
        "\u5927\u6ca2"
    ],
    "name:jpn_x_variant":[
        "\u304a\u304a\u3055\u308f",
        "\u30aa\u30aa\u30b5\u30ef"
    ],
    "name:und_x_variant":[
        "\u014csawa"
    ],
    "wof:name":"Osawa",
    "wof:placetype":"locality"
},
  "geometry": {"coordinates":[139.84776000000002,35.18382],"type":"Point"}
}