{
  "type": "Feature",
  "properties": {
    "gn:admin1_code":"21",
    "gn:admin2_code":"7412706.0",
    "gn:admin3_code":"43441.0",
    "gn:asciiname":"Tabata",
    "gn:country_code":"JP",
    "gn:dem":371,
    "gn:feature_class":"P",
    "gn:feature_code":"PPL",
    "gn:name":"Tabata",
    "gn:population":0,
    "gn:timezone":"Asia/Tokyo",
    "iso:country":"JP",
    "name:deu_x_preferred":[
        "Tabata"
    ],
    "name:fra_x_preferred":[
        "Tabata"
    ],
    "name:ita_x_preferred":[
        "Tabata"
    ],
    "name:jpn_x_preferred":[
        "\u7530\u7551"
    ],
    "name:jpn_x_variant":[
        "\u305f\u3070\u305f",
        "\u30bf\u30d0\u30bf"
    ],
    "name:rus_x_preferred":[
        "\u0422\u0430\u0431\u0430\u0442\u0430"
    ],
    "name:swe_x_preferred":[
        "Tabata"
    ],
    "wof:name":"Tabata",
    "wof:placetype":"locality"
},
  "geometry": {"coordinates":[130.8674,32.68513],"type":"Point"}
}