{
  "type": "Feature",
  "properties": {
    "gn:admin1_code":"11",
    "gn:admin2_code":"1863017.0",
    "gn:asciiname":"Toge",
    "gn:country_code":"JP",
    "gn:dem":298,
    "gn:feature_class":"P",
    "gn:feature_code":"PPL",
    "gn:name":"T\u014dge",
    "gn:population":0,
    "gn:timezone":"Asia/Tokyo",
    "iso:country":"JP",
    "name:jpn_x_preferred":[
        "\u5ce0"
    ],
    "name:und_x_variant":[
        "T\u014dge"
    ],
    "wof:name":"Toge",
    "wof:placetype":"locality"
},
  "geometry": {"coordinates":[132.23658999999998,34.36054],"type":"Point"}
}