{
  "type": "Feature",
  "properties": {
    "gn:admin1_code":"19.0",
    "gn:admin2_code":"1856849.0",
    "gn:asciiname":"Godo",
    "gn:country_code":"JP",
    "gn:dem":32,
    "gn:feature_class":"P",
    "gn:feature_code":"PPLL",
    "gn:name":"G\u014ddo",
    "gn:population":0,
    "gn:timezone":"Asia/Tokyo",
    "iso:country":"JP",
    "name:jpn_x_preferred":[
        "\u90f7\u6238"
    ],
    "name:jpn_x_variant":[
        "\u3054\u3046\u3069",
        "\u30b4\u30a6\u30c9"
    ],
    "name:und_x_variant":[
        "G\u014ddo"
    ],
    "wof:name":"Godo",
    "wof:placetype":"locality"
},
  "geometry": {"coordinates":[139.62764999999999,35.15388],"type":"Point"}
}