{
  "type": "Feature",
  "properties": {
    "gn:admin1_code":"4.0",
    "gn:admin2_code":"7465524.0",
    "gn:asciiname":"Kogariya",
    "gn:country_code":"JP",
    "gn:dem":16,
    "gn:feature_class":"P",
    "gn:feature_code":"PPLL",
    "gn:name":"Kogariya",
    "gn:population":0,
    "gn:timezone":"Asia/Tokyo",
    "iso:country":"JP",
    "name:jpn_x_preferred":[
        "\u5c0f\u5208\u8c37"
    ],
    "name:jpn_x_variant":[
        "\u3053\u304c\u308a\u3084",
        "\u30b3\u30ac\u30ea\u30e4"
    ],
    "wof:name":"Kogariya",
    "wof:placetype":"locality"
},
  "geometry": {"coordinates":[140.30389,35.28325],"type":"Point"}
}