{
  "type": "Feature",
  "properties": {
    "gn:admin1_code":"24.0",
    "gn:admin2_code":"2111889.0",
    "gn:admin3_code":"4406.0",
    "gn:asciiname":"Ogai",
    "gn:country_code":"JP",
    "gn:dem":92,
    "gn:feature_class":"P",
    "gn:feature_code":"PPL",
    "gn:name":"\u014cgai",
    "gn:population":0,
    "gn:timezone":"Asia/Tokyo",
    "iso:country":"JP",
    "name:jpn_x_preferred":[
        "\u5927\u8c9d"
    ],
    "name:jpn_x_variant":[
        "\u304a\u304a\u304c\u3044",
        "\u30aa\u30aa\u30ac\u30a4"
    ],
    "name:und_x_variant":[
        "\u014cgai"
    ],
    "wof:name":"Ogai",
    "wof:placetype":"locality"
},
  "geometry": {"coordinates":[141.02331999999996,38.36505],"type":"Point"}
}