{
  "type": "Feature",
  "properties": {
    "gn:admin1_code":"33.0",
    "gn:admin2_code":"1859936.0",
    "gn:asciiname":"Otsue",
    "gn:country_code":"JP",
    "gn:dem":193,
    "gn:feature_class":"P",
    "gn:feature_code":"PPLL",
    "gn:name":"\u014ctsue",
    "gn:population":0,
    "gn:timezone":"Asia/Tokyo",
    "iso:country":"JP",
    "name:jpn_x_preferred":[
        "\u5927\u6d25\u6c5f"
    ],
    "name:und_x_variant":[
        "\u014ctsue"
    ],
    "wof:name":"Otsue",
    "wof:placetype":"locality"
},
  "geometry": {"coordinates":[130.12976,33.04343],"type":"Point"}
}