{
  "type": "Feature",
  "properties": {
    "gn:admin1_code":"12.0",
    "gn:admin2_code":"7428116.0",
    "gn:admin3_code":"1607.0",
    "gn:asciiname":"Nobuka",
    "gn:country_code":"JP",
    "gn:dem":71,
    "gn:feature_class":"P",
    "gn:feature_code":"PPL",
    "gn:name":"Nobuka",
    "gn:population":0,
    "gn:timezone":"Asia/Tokyo",
    "iso:country":"JP",
    "name:jpn_x_preferred":[
        "\u91ce\u6df1"
    ],
    "name:jpn_x_variant":[
        "\u306e\u3076\u304b",
        "\u30ce\u30d6\u30ab"
    ],
    "wof:name":"Nobuka",
    "wof:placetype":"locality"
},
  "geometry": {"coordinates":[142.75623000000004,42.26775],"type":"Point"}
}