{
  "type": "Feature",
  "properties": {
    "gn:admin1_code":"2.0",
    "gn:admin2_code":"7443156.0",
    "gn:asciiname":"Nanukaichi",
    "gn:country_code":"JP",
    "gn:dem":54,
    "gn:feature_class":"P",
    "gn:feature_code":"PPL",
    "gn:name":"Nanukaichi",
    "gn:population":0,
    "gn:timezone":"Asia/Tokyo",
    "iso:country":"JP",
    "name:jpn_x_preferred":[
        "\u4e03\u65e5\u5e02"
    ],
    "name:und_x_variant":[
        "Nanokaichi"
    ],
    "wof:name":"Nanukaichi",
    "wof:placetype":"locality"
},
  "geometry": {"coordinates":[140.40461000000002,40.17847],"type":"Point"}
}