{
  "type": "Feature",
  "properties": {
    "gn:admin1_code":"21.0",
    "gn:admin2_code":"1848441.0",
    "gn:asciiname":"Daifukujimachi",
    "gn:country_code":"JP",
    "gn:dem":1,
    "gn:feature_class":"P",
    "gn:feature_code":"PPL",
    "gn:name":"Daifukujimachi",
    "gn:population":0,
    "gn:timezone":"Asia/Tokyo",
    "iso:country":"JP",
    "name:jpn_x_preferred":[
        "\u5927\u798f\u5bfa\u753a"
    ],
    "wof:name":"Daifukujimachi",
    "wof:placetype":"locality"
},
  "geometry": {"coordinates":[130.60263999999998,32.48741],"type":"Point"}
}