{
  "type": "Feature",
  "properties": {
    "gn:admin1_code":"10.0",
    "gn:admin2_code":"1859339.0",
    "gn:admin3_code":"10345.0",
    "gn:asciiname":"Tonotsuji",
    "gn:country_code":"JP",
    "gn:dem":490,
    "gn:feature_class":"P",
    "gn:feature_code":"PPLL",
    "gn:name":"T\u014dnotsuji",
    "gn:population":0,
    "gn:timezone":"Asia/Tokyo",
    "iso:country":"JP",
    "name:jpn_x_preferred":[
        "\u5854\u4e4b\u8fbb"
    ],
    "name:und_x_variant":[
        "T\u014dnotsuji"
    ],
    "wof:name":"Tonotsuji",
    "wof:placetype":"locality"
},
  "geometry": {"coordinates":[138.95785000000001,36.47111],"type":"Point"}
}