{
  "type": "Feature",
  "properties": {
    "gn:admin1_code":"25.0",
    "gn:admin2_code":"1864313.0",
    "gn:asciiname":"Minakuchinoshita",
    "gn:country_code":"JP",
    "gn:dem":232,
    "gn:feature_class":"P",
    "gn:feature_code":"PPLL",
    "gn:name":"Minakuchinoshita",
    "gn:population":0,
    "gn:timezone":"Asia/Tokyo",
    "iso:country":"JP",
    "name:jpn_x_preferred":[
        "\u6c34\u7121\u53e3\u30ce\u4e0b"
    ],
    "name:jpn_x_variant":[
        "\u307f\u306a\u304f\u3061\u306e\u3057\u305f",
        "\u30df\u30ca\u30af\u30c1\u30ce\u30b7\u30bf"
    ],
    "wof:name":"Minakuchinoshita",
    "wof:placetype":"locality"
},
  "geometry": {"coordinates":[130.82043000000002,32.03933],"type":"Point"}
}