{
  "type": "Feature",
  "properties": {
    "gn:admin1_code":"33.0",
    "gn:admin2_code":"7391358.0",
    "gn:admin3_code":"41424.0",
    "gn:asciiname":"Hanamatsuri",
    "gn:country_code":"JP",
    "gn:dem":72,
    "gn:feature_class":"P",
    "gn:feature_code":"PPLL",
    "gn:name":"Hanamatsuri",
    "gn:population":0,
    "gn:timezone":"Asia/Tokyo",
    "iso:country":"JP",
    "name:jpn_x_preferred":[
        "\u82b1\u796d"
    ],
    "wof:name":"Hanamatsuri",
    "wof:placetype":"locality"
},
  "geometry": {"coordinates":[130.15541999999999,33.24466],"type":"Point"}
}