{
  "type": "Feature",
  "properties": {
    "gn:admin1_code":"7.0",
    "gn:admin2_code":"1855902.0",
    "gn:asciiname":"Sunayama",
    "gn:country_code":"JP",
    "gn:dem":4,
    "gn:feature_class":"P",
    "gn:feature_code":"PPLL",
    "gn:name":"Sunayama",
    "gn:population":0,
    "gn:timezone":"Asia/Tokyo",
    "iso:country":"JP",
    "name:jpn_x_preferred":[
        "\u7802\u5c71"
    ],
    "wof:name":"Sunayama",
    "wof:placetype":"locality"
},
  "geometry": {"coordinates":[130.69546,33.8244],"type":"Point"}
}