{
  "type": "Feature",
  "properties": {
    "gn:admin1_code":"16",
    "gn:admin2_code":"2112655.0",
    "gn:asciiname":"Yokamachi",
    "gn:country_code":"JP",
    "gn:dem":132,
    "gn:feature_class":"P",
    "gn:feature_code":"PPL",
    "gn:name":"Y\u014dkamachi",
    "gn:population":0,
    "gn:timezone":"Asia/Tokyo",
    "iso:country":"JP",
    "name:und_x_variant":[
        "Y\u014dkamachi"
    ],
    "wof:name":"Yokamachi",
    "wof:placetype":"locality"
},
  "geometry": {"coordinates":[141.36667,39.05],"type":"Point"}
}