{
  "type": "Feature",
  "properties": {
    "gn:admin1_code":"33.0",
    "gn:admin2_code":"1853274.0",
    "gn:asciiname":"Fujicho-kamimutsuro",
    "gn:country_code":"JP",
    "gn:dem":397,
    "gn:feature_class":"P",
    "gn:feature_code":"PPL",
    "gn:name":"Fujich\u014d-kamimutsuro",
    "gn:population":0,
    "gn:timezone":"Asia/Tokyo",
    "iso:country":"JP",
    "name:jpn_x_preferred":[
        "\u5bcc\u58eb\u753a\u4e0a\u7121\u6d25\u5442"
    ],
    "name:und_x_variant":[
        "Fujich\u014d-kamimutsuro"
    ],
    "wof:name":"Fujicho-kamimutsuro",
    "wof:placetype":"locality"
},
  "geometry": {"coordinates":[130.19553999999999,33.45904],"type":"Point"}
}