{
  "type": "Feature",
  "properties": {
    "gn:admin1_code":"18.0",
    "gn:admin2_code":"1853737.0",
    "gn:admin3_code":"46525.0",
    "gn:asciiname":"Katetsu",
    "gn:country_code":"JP",
    "gn:dem":6,
    "gn:feature_class":"P",
    "gn:feature_code":"PPL",
    "gn:name":"Katetsu",
    "gn:population":0,
    "gn:timezone":"Asia/Tokyo",
    "iso:country":"JP",
    "name:jpn_x_preferred":[
        "\u5609\u9244"
    ],
    "wof:name":"Katetsu",
    "wof:placetype":"locality"
},
  "geometry": {"coordinates":[129.34181999999998,28.14028],"type":"Point"}
}