{
  "type": "Feature",
  "properties": {
    "gn:admin1_code":"21.0",
    "gn:admin2_code":"7412708.0",
    "gn:admin3_code":"43505.0",
    "gn:asciiname":"Waki",
    "gn:country_code":"JP",
    "gn:dem":164,
    "gn:feature_class":"P",
    "gn:feature_code":"PPLL",
    "gn:name":"Waki",
    "gn:population":0,
    "gn:timezone":"Asia/Tokyo",
    "iso:country":"JP",
    "name:ceb_x_preferred":[
        "Waki"
    ],
    "name:fra_x_preferred":[
        "Waki"
    ],
    "name:jpn_x_preferred":[
        "\u8107"
    ],
    "name:jpn_x_variant":[
        "\u308f\u304d",
        "\u30ef\u30ad"
    ],
    "name:ukr_x_preferred":[
        "\u0412\u0430\u043a\u0456"
    ],
    "wof:name":"Waki",
    "wof:placetype":"locality"
},
  "geometry": {"coordinates":[130.93353999999999,32.2749],"type":"Point"}
}