{
  "type": "Feature",
  "properties": {
    "gn:admin1_code":"3.0",
    "gn:admin2_code":"2130056.0",
    "gn:asciiname":"Tsukano",
    "gn:country_code":"JP",
    "gn:dem":22,
    "gn:feature_class":"P",
    "gn:feature_code":"PPL",
    "gn:name":"Tsukano",
    "gn:population":0,
    "gn:timezone":"Asia/Tokyo",
    "iso:country":"JP",
    "name:jpn_x_preferred":[
        "\u6d25\u8cc0\u91ce"
    ],
    "name:jpn_x_variant":[
        "\u3064\u304b\u306e",
        "\u30c4\u30ab\u30ce"
    ],
    "wof:name":"Tsukano",
    "wof:placetype":"locality"
},
  "geometry": {"coordinates":[140.49131,40.63707],"type":"Point"}
}