{
  "type": "Feature",
  "properties": {
    "gn:admin1_code":"21.0",
    "gn:admin2_code":"1865358.0",
    "gn:asciiname":"Kama",
    "gn:country_code":"JP",
    "gn:dem":1,
    "gn:feature_class":"P",
    "gn:feature_code":"PPLL",
    "gn:name":"Kama",
    "gn:population":0,
    "gn:timezone":"Asia/Tokyo",
    "iso:country":"JP",
    "name:jpn_x_preferred":[
        "\u304b\u307e"
    ],
    "name:jpn_x_variant":[
        "\u30ab\u30de",
        "\u91dc"
    ],
    "wof:name":"Kama",
    "wof:placetype":"locality"
},
  "geometry": {"coordinates":[130.20966000000001,32.42618],"type":"Point"}
}