{
  "type": "Feature",
  "properties": {
    "gn:admin1_code":"7.0",
    "gn:admin2_code":"1851269.0",
    "gn:admin3_code":"40610.0",
    "gn:asciiname":"Okubo",
    "gn:country_code":"JP",
    "gn:dem":26,
    "gn:feature_class":"P",
    "gn:feature_code":"PPLL",
    "gn:name":"\u014ckubo",
    "gn:population":0,
    "gn:timezone":"Asia/Tokyo",
    "iso:country":"JP",
    "name:jpn_x_preferred":[
        "\u5927\u4e45\u4fdd"
    ],
    "name:und_x_variant":[
        "\u014ckubo"
    ],
    "wof:name":"Okubo",
    "wof:placetype":"locality"
},
  "geometry": {"coordinates":[130.76671999999999,33.7121],"type":"Point"}
}