{
  "type": "Feature",
  "properties": {
    "gn:admin1_code":"37",
    "gn:admin2_code":"1860327.0",
    "gn:admin3_code":"22302.0",
    "gn:asciiname":"Shimosagano",
    "gn:country_code":"JP",
    "gn:dem":62,
    "gn:feature_class":"P",
    "gn:feature_code":"PPL",
    "gn:name":"Shimosagano",
    "gn:population":0,
    "gn:timezone":"Asia/Tokyo",
    "iso:country":"JP",
    "name:jpn_x_preferred":[
        "\u4e0b\u4f50\u30f6\u91ce"
    ],
    "name:und_x_variant":[
        "Shimo-sagano"
    ],
    "wof:name":"Shimosagano",
    "wof:placetype":"locality"
},
  "geometry": {"coordinates":[138.95721,34.77513],"type":"Point"}
}