{
  "type": "Feature",
  "properties": {
    "gn:admin1_code":"21",
    "gn:admin2_code":"7412708.0",
    "gn:admin3_code":"43505.0",
    "gn:asciiname":"Shimotsukigi",
    "gn:country_code":"JP",
    "gn:dem":433,
    "gn:feature_class":"P",
    "gn:feature_code":"PPLL",
    "gn:name":"Shimotsukigi",
    "gn:population":0,
    "gn:timezone":"Asia/Tokyo",
    "iso:country":"JP",
    "name:jpn_x_preferred":[
        "\u4e0b\u69fb\u6728"
    ],
    "name:jpn_x_variant":[
        "\u3057\u3082\u3064\u304d\u304e",
        "\u30b7\u30e2\u30c4\u30ad\u30ae"
    ],
    "name:und_x_variant":[
        "Shimo-tsukiki",
        "Shimo-tsukigi",
        "Shimotsukigi"
    ],
    "wof:name":"Shimotsukigi",
    "wof:placetype":"locality"
},
  "geometry": {"coordinates":[131.06501,32.18687],"type":"Point"}
}