{
  "type": "Feature",
  "properties": {
    "gn:admin1_code":"21.0",
    "gn:admin2_code":"1865168.0",
    "gn:asciiname":"Kuramitsu",
    "gn:country_code":"JP",
    "gn:dem":9,
    "gn:feature_class":"P",
    "gn:feature_code":"PPL",
    "gn:name":"Kuramitsu",
    "gn:population":0,
    "gn:timezone":"Asia/Tokyo",
    "iso:country":"JP",
    "name:jpn_x_preferred":[
        "\u8535\u6e80"
    ],
    "name:jpn_x_variant":[
        "\u304f\u3089\u307f\u3064",
        "\u30af\u30e9\u30df\u30c4"
    ],
    "wof:name":"Kuramitsu",
    "wof:placetype":"locality"
},
  "geometry": {"coordinates":[130.43898000000002,32.95944],"type":"Point"}
}