{
  "type": "Feature",
  "properties": {
    "gn:admin1_code":"21.0",
    "gn:admin2_code":"1849062.0",
    "gn:asciiname":"Iwaguma",
    "gn:country_code":"JP",
    "gn:dem":2,
    "gn:feature_class":"P",
    "gn:feature_code":"PPLL",
    "gn:name":"Iwaguma",
    "gn:population":0,
    "gn:timezone":"Asia/Tokyo",
    "iso:country":"JP",
    "name:jpn_x_preferred":[
        "\u5ca9\u718a"
    ],
    "name:jpn_x_variant":[
        "\u3044\u308f\u3050\u307e",
        "\u30a4\u30ef\u30b0\u30de"
    ],
    "wof:name":"Iwaguma",
    "wof:placetype":"locality"
},
  "geometry": {"coordinates":[130.6807,32.69302],"type":"Point"}
}