{
  "type": "Feature",
  "properties": {
    "iso:country":"JP",
    "name:eng_x_preferred":[
        "Numata City"
    ],
    "name:jpn_x_preferred":[
        "\u6cbc\u7530\u5e02"
    ],
    "qs:name":"\u6cbc\u7530\u5e02",
    "qs:name_adm0":"\u65e5\u672c",
    "qs:name_adm1":"\u7fa4\u99ac\u770c",
    "qs:photos":1584,
    "qs:photos_1k":321,
    "qs:photos_9k":7,
    "qs:photos_9r":8,
    "qs:photos_all":1584,
    "qs:photos_sr":13,
    "qs:placetype":"Town",
    "qs:pop_sr":"0",
    "wof:name":"Numata City",
    "wof:placetype":"locality"
},
  "geometry": {"coordinates":[139.20639,36.693199],"type":"Point"}
}