{
  "type": "Feature",
  "properties": {
    "gn:admin1_code":"21.0",
    "gn:admin2_code":"7413150.0",
    "gn:asciiname":"Kamotomachi-tsubukuro",
    "gn:country_code":"JP",
    "gn:dem":56,
    "gn:feature_class":"P",
    "gn:feature_code":"PPL",
    "gn:name":"Kamotomachi-tsubukuro",
    "gn:population":0,
    "gn:timezone":"Asia/Tokyo",
    "iso:country":"JP",
    "name:jpn_x_preferred":[
        "\u9e7f\u672c\u753a\u6d25\u888b"
    ],
    "name:jpn_x_variant":[
        "\u304b\u3082\u3068\u307e\u3061\u3064\u3076\u304f\u308d",
        "\u30ab\u30e2\u30c8\u30de\u30c1\u30c4\u30d6\u30af\u30ed"
    ],
    "wof:name":"Kamotomachi-tsubukuro",
    "wof:placetype":"locality"
},
  "geometry": {"coordinates":[130.75933999999998,33.01433],"type":"Point"}
}