{
  "type": "Feature",
  "properties": {
    "gn:admin1_code":"18",
    "gn:admin2_code":"1853737.0",
    "gn:admin3_code":"46523.0",
    "gn:asciiname":"Naon",
    "gn:country_code":"JP",
    "gn:dem":7,
    "gn:feature_class":"P",
    "gn:feature_code":"PPL",
    "gn:name":"Naon",
    "gn:population":0,
    "gn:timezone":"Asia/Tokyo",
    "iso:country":"JP",
    "name:jpn_x_preferred":[
        "\u540d\u97f3"
    ],
    "wof:name":"Naon",
    "wof:placetype":"locality"
},
  "geometry": {"coordinates":[129.31666999999999,28.33333],"type":"Point"}
}