{
  "type": "Feature",
  "properties": {
    "gn:admin1_code":"38",
    "gn:admin2_code":"1861696.0",
    "gn:asciiname":"Yumoto",
    "gn:country_code":"JP",
    "gn:dem":1491,
    "gn:feature_class":"P",
    "gn:feature_code":"PPL",
    "gn:name":"Yumoto",
    "gn:population":0,
    "gn:timezone":"Asia/Tokyo",
    "iso:country":"JP",
    "name:jpn_x_preferred":[
        "\u6e6f\u5143"
    ],
    "wof:name":"Yumoto",
    "wof:placetype":"locality"
},
  "geometry": {"coordinates":[139.42346000000001,36.80682],"type":"Point"}
}