{
  "type": "Feature",
  "properties": {
    "gn:admin1_code":"21.0",
    "gn:admin2_code":"1858418.0",
    "gn:admin3_code":"43103.0",
    "gn:asciiname":"Matsuomachi-chikozu",
    "gn:country_code":"JP",
    "gn:dem":39,
    "gn:feature_class":"P",
    "gn:feature_code":"PPL",
    "gn:name":"Matsuomachi-chik\u014dzu",
    "gn:population":0,
    "gn:timezone":"Asia/Tokyo",
    "iso:country":"JP",
    "name:jpn_x_preferred":[
        "\u677e\u5c3e\u753a\u8fd1\u6d25"
    ],
    "name:jpn_x_variant":[
        "\u307e\u3064\u304a\u307e\u3061\u3061\u3053\u3046\u3065",
        "\u30de\u30c4\u30aa\u30de\u30c1\u30c1\u30b3\u30a6\u30c5"
    ],
    "name:und_x_variant":[
        "Matsuomachi-chik\u014dzu"
    ],
    "wof:name":"Matsuomachi-chikozu",
    "wof:placetype":"locality"
},
  "geometry": {"coordinates":[130.61165,32.80789],"type":"Point"}
}