{
  "type": "Feature",
  "properties": {
    "gn:admin1_code":"21.0",
    "gn:admin2_code":"1850744.0",
    "gn:admin3_code":"43368.0",
    "gn:asciiname":"Miyano",
    "gn:country_code":"JP",
    "gn:dem":12,
    "gn:feature_class":"P",
    "gn:feature_code":"PPL",
    "gn:name":"Miyano",
    "gn:population":0,
    "gn:timezone":"Asia/Tokyo",
    "iso:country":"JP",
    "name:jpn_x_preferred":[
        "\u5bae\u91ce"
    ],
    "name:jpn_x_variant":[
        "\u307f\u3084\u306e",
        "\u30df\u30e4\u30ce"
    ],
    "wof:name":"Miyano",
    "wof:placetype":"locality"
},
  "geometry": {"coordinates":[130.48304999999999,32.93448],"type":"Point"}
}