{
  "type": "Feature",
  "properties": {
    "gn:admin1_code":"24.0",
    "gn:admin2_code":"2112261.0",
    "gn:asciiname":"Katomari",
    "gn:country_code":"JP",
    "gn:dem":23,
    "gn:feature_class":"P",
    "gn:feature_code":"PPL",
    "gn:name":"Katomari",
    "gn:population":0,
    "gn:timezone":"Asia/Tokyo",
    "iso:country":"JP",
    "name:jpn_x_preferred":[
        "\u795e\u6b62"
    ],
    "name:jpn_x_variant":[
        "\u304b\u3068\u307e\u308a",
        "\u30ab\u30c8\u30de\u30ea"
    ],
    "wof:name":"Katomari",
    "wof:placetype":"locality"
},
  "geometry": {"coordinates":[141.64675,38.88057],"type":"Point"}
}