{
  "type": "Feature",
  "properties": {
    "gn:admin1_code":"33.0",
    "gn:admin2_code":"1856784.0",
    "gn:admin3_code":"41346.0",
    "gn:asciiname":"Tashima",
    "gn:country_code":"JP",
    "gn:dem":5,
    "gn:feature_class":"P",
    "gn:feature_code":"PPLL",
    "gn:name":"Tashima",
    "gn:population":0,
    "gn:timezone":"Asia/Tokyo",
    "iso:country":"JP",
    "name:jpn_x_preferred":[
        "\u7530\u5cf6"
    ],
    "wof:name":"Tashima",
    "wof:placetype":"locality"
},
  "geometry": {"coordinates":[130.44788,33.30843],"type":"Point"}
}