{
  "type": "Feature",
  "properties": {
    "iso:country":"JP",
    "name:eng_x_preferred":[
        "Higashiyamagata 2 Chome"
    ],
    "name:eng_x_variant":[
        "Higashiyamagata 2 Choume",
        "Higashiyamagata 2 Chome"
    ],
    "name:jpn_x_preferred":[
        "\uff12\u4e01\u76ee"
    ],
    "name:jpn_x_variant":[
        "\u3072\u304c\u3057\u3084\u307e\u304c\u305f \uff12\u3061\u3087\u3046\u3081",
        "\u6771\u5c71\u5f62 \uff12\u4e01\u76ee",
        "\uff12\u3061\u3087\u3046\u3081"
    ],
    "name:unk_x_variant":[
        "\uff12\u4e01\u76ee"
    ],
    "qs:gn_local":0,
    "qs:local_max":308,
    "qs:local_sum":653,
    "qs:localhoods":7,
    "qs:name":"\uff12\u4e01\u76ee",
    "qs:name_adm0":"\u65e5\u672c",
    "qs:name_adm1":"\u5c71\u5f62\u770c",
    "qs:name_en":"Higashiyamagata 2 Chome",
    "qs:name_lau":"\u6771\u5c71\u5f62",
    "qs:name_local":"\u5c71\u5f62\u5e02",
    "qs:photo_max":8,
    "qs:photo_sum":26,
    "qs:placetype":"Suburb",
    "qs:quad_count":6,
    "qs:woe_adm0":23424856,
    "qs:woe_adm1":2345893,
    "qs:woe_adm2":0,
    "qs:woe_lau":28396303,
    "qs:woe_local":1118515,
    "qs:woe_ver":"7.10.0",
    "wof:lang":[
        "jpn"
    ],
    "wof:name":"\uff12\u4e01\u76ee",
    "wof:placetype":"neighbourhood"
},
  "geometry": {"coordinates":[140.39048199999999,38.241498],"type":"Point"}
}