{
  "type": "Feature",
  "properties": {
    "gn:admin1_code":"3.0",
    "gn:admin2_code":"2130200.0",
    "gn:asciiname":"Manota",
    "gn:country_code":"JP",
    "gn:dem":7,
    "gn:feature_class":"P",
    "gn:feature_code":"PPL",
    "gn:name":"Manota",
    "gn:population":0,
    "gn:timezone":"Asia/Tokyo",
    "iso:country":"JP",
    "name:jpn_x_preferred":[
        "\u9593\u30ce\u7530"
    ],
    "name:jpn_x_variant":[
        "\u307e\u306e\u305f",
        "\u30de\u30ce\u30bf"
    ],
    "wof:name":"Manota",
    "wof:placetype":"locality"
},
  "geometry": {"coordinates":[141.50981000000004,40.49714],"type":"Point"}
}