{
  "type": "Feature",
  "properties": {
    "gn:admin1_code":"7.0",
    "gn:admin2_code":"7407413.0",
    "gn:asciiname":"Hira-daiichi",
    "gn:country_code":"JP",
    "gn:dem":29,
    "gn:feature_class":"P",
    "gn:feature_code":"PPLL",
    "gn:name":"Hira-daiichi",
    "gn:population":0,
    "gn:timezone":"Asia/Tokyo",
    "iso:country":"JP",
    "name:jpn_x_preferred":[
        "\u5e73\u7b2c\u4e00"
    ],
    "wof:name":"Hira-daiichi",
    "wof:placetype":"locality"
},
  "geometry": {"coordinates":[130.7337,33.59542],"type":"Point"}
}