{
  "type": "Feature",
  "properties": {
    "gn:admin1_code":"21.0",
    "gn:admin2_code":"7412708.0",
    "gn:admin3_code":"43501.0",
    "gn:asciiname":"Yamashita",
    "gn:country_code":"JP",
    "gn:dem":122,
    "gn:feature_class":"P",
    "gn:feature_code":"PPLL",
    "gn:name":"Yamashita",
    "gn:population":0,
    "gn:timezone":"Asia/Tokyo",
    "iso:country":"JP",
    "name:jpn_x_preferred":[
        "\u5c71\u4e0b"
    ],
    "name:jpn_x_variant":[
        "\u3084\u307e\u3057\u305f",
        "\u30e4\u30de\u30b7\u30bf"
    ],
    "wof:name":"Yamashita",
    "wof:placetype":"locality"
},
  "geometry": {"coordinates":[130.82398999999998,32.22535999999999],"type":"Point"}
}