{
  "type": "Feature",
  "properties": {
    "gn:admin1_code":"16.0",
    "gn:admin2_code":"2112822.0",
    "gn:asciiname":"Futatsuya",
    "gn:country_code":"JP",
    "gn:dem":69,
    "gn:feature_class":"P",
    "gn:feature_code":"PPL",
    "gn:name":"Futatsuya",
    "gn:population":0,
    "gn:timezone":"Asia/Tokyo",
    "iso:country":"JP",
    "name:jpn_x_preferred":[
        "\u4e8c\u30c4\u5c4b"
    ],
    "name:jpn_x_variant":[
        "\u3075\u305f\u3064\u3084",
        "\u30d5\u30bf\u30c4\u30e4"
    ],
    "wof:name":"Futatsuya",
    "wof:placetype":"locality"
},
  "geometry": {"coordinates":[141.14871000000005,39.36102],"type":"Point"}
}