{
  "type": "Feature",
  "properties": {
    "gn:admin1_code":"21.0",
    "gn:admin2_code":"7413152.0",
    "gn:asciiname":"Kitahagio",
    "gn:country_code":"JP",
    "gn:dem":25,
    "gn:feature_class":"P",
    "gn:feature_code":"PPLL",
    "gn:name":"Kitahagio",
    "gn:population":0,
    "gn:timezone":"Asia/Tokyo",
    "iso:country":"JP",
    "name:jpn_x_preferred":[
        "\u5317\u8429\u5c3e"
    ],
    "name:jpn_x_variant":[
        "\u304d\u305f\u306f\u304e\u304a",
        "\u30ad\u30bf\u30cf\u30ae\u30aa"
    ],
    "wof:name":"Kitahagio",
    "wof:placetype":"locality"
},
  "geometry": {"coordinates":[130.71696,32.65858],"type":"Point"}
}