{
  "type": "Feature",
  "properties": {
    "gn:admin1_code":"29",
    "gn:admin2_code":"1853313.0",
    "gn:asciiname":"Hatano",
    "gn:country_code":"JP",
    "gn:dem":40,
    "gn:feature_class":"P",
    "gn:feature_code":"PPL",
    "gn:name":"Hatano",
    "gn:population":0,
    "gn:timezone":"Asia/Tokyo",
    "iso:country":"JP",
    "name:jpn_x_preferred":[
        "\u7551\u91ce"
    ],
    "wof:name":"Hatano",
    "wof:placetype":"locality"
},
  "geometry": {"coordinates":[138.39473000000001,37.9876],"type":"Point"}
}