{
  "type": "Feature",
  "properties": {
    "iso:country":"JP",
    "name:eng_x_preferred":[
        "Kobuchi 2 Chome"
    ],
    "name:eng_x_variant":[
        "Kobuchi 2 Choume",
        "Kobuchi 2 Chome"
    ],
    "name:jpn_x_preferred":[
        "\uff12\u4e01\u76ee"
    ],
    "name:jpn_x_variant":[
        "\u3053\u3076\u3061 \uff12\u3061\u3087\u3046\u3081",
        "\u53e4\u6df5 \uff12\u4e01\u76ee",
        "\uff12\u3061\u3087\u3046\u3081"
    ],
    "qs:gn_local":0,
    "qs:local_max":428,
    "qs:local_sum":2008,
    "qs:localhoods":25,
    "qs:name":"\uff12\u4e01\u76ee",
    "qs:name_adm0":"\u65e5\u672c",
    "qs:name_adm1":"\u795e\u5948\u5ddd\u770c",
    "qs:name_en":"Kobuchi 2 Chome",
    "qs:name_lau":"\u53e4\u6df5",
    "qs:name_local":"\u76f8\u6a21\u539f\u5e02",
    "qs:photo_max":17,
    "qs:photo_sum":35,
    "qs:placetype":"Suburb",
    "qs:quad_count":6,
    "qs:woe_adm0":23424856,
    "qs:woe_adm1":2345868,
    "qs:woe_adm2":0,
    "qs:woe_lau":28417001,
    "qs:woe_local":1118072,
    "qs:woe_ver":"7.10.0",
    "wof:lang":[
        "jpn"
    ],
    "wof:name":"\uff12\u4e01\u76ee",
    "wof:placetype":"neighbourhood"
},
  "geometry": {"coordinates":[139.41913600000001,35.553458],"type":"Point"}
}