{
  "type": "Feature",
  "properties": {
    "gn:admin1_code":"27",
    "gn:admin2_code":"7418804.0",
    "gn:asciiname":"Hama",
    "gn:country_code":"JP",
    "gn:dem":4,
    "gn:feature_class":"P",
    "gn:feature_code":"PPL",
    "gn:name":"Hama",
    "gn:population":0,
    "gn:timezone":"Asia/Tokyo",
    "iso:country":"JP",
    "name:jpn_x_preferred":[
        "\u6d5c"
    ],
    "name:und_x_variant":[
        "\u014chama",
        "Hama"
    ],
    "wof:name":"Hama",
    "wof:placetype":"locality"
},
  "geometry": {"coordinates":[128.81291000000002,32.65092],"type":"Point"}
}