{
  "type": "Feature",
  "properties": {
    "gn:admin1_code":"43",
    "gn:admin2_code":"1861287.0",
    "gn:admin3_code":"30341.0",
    "gn:asciiname":"Kaseda-naka",
    "gn:country_code":"JP",
    "gn:dem":41,
    "gn:feature_class":"P",
    "gn:feature_code":"PPL",
    "gn:name":"Kaseda-naka",
    "gn:population":0,
    "gn:timezone":"Asia/Tokyo",
    "iso:country":"JP",
    "wof:name":"Kaseda-naka",
    "wof:placetype":"locality"
},
  "geometry": {"coordinates":[135.46666999999999,34.28333],"type":"Point"}
}