{
  "type": "Feature",
  "properties": {
    "gn:admin1_code":"16.0",
    "gn:admin2_code":"2128941.0",
    "gn:admin3_code":"3524.0",
    "gn:asciiname":"Jigiri",
    "gn:country_code":"JP",
    "gn:dem":251,
    "gn:feature_class":"P",
    "gn:feature_code":"PPL",
    "gn:name":"Jigiri",
    "gn:population":0,
    "gn:timezone":"Asia/Tokyo",
    "iso:country":"JP",
    "name:jpn_x_preferred":[
        "\u5730\u5207"
    ],
    "name:jpn_x_variant":[
        "\u3058\u304e\u308a",
        "\u30b8\u30ae\u30ea"
    ],
    "wof:name":"Jigiri",
    "wof:placetype":"locality"
},
  "geometry": {"coordinates":[141.31929,40.2005],"type":"Point"}
}