{
  "type": "Feature",
  "properties": {
    "iso:country":"JP",
    "name:eng_x_preferred":[
        "Saitozaki 6 Chome"
    ],
    "name:eng_x_variant":[
        "Saitozaki 6 Choume",
        "Saitozaki 6 Chome"
    ],
    "name:jpn_x_preferred":[
        "\uff16\u4e01\u76ee"
    ],
    "name:jpn_x_variant":[
        "\u3055\u3044\u3068\u3056\u304d \uff16\u3061\u3087\u3046\u3081",
        "\u897f\u6238\u5d0e \uff16\u4e01\u76ee",
        "\uff16\u3061\u3087\u3046\u3081"
    ],
    "qs:gn_adm0_cc":"JP",
    "qs:gn_local":1863967,
    "qs:gn_nam_loc":"\u798f\u5ca1\u5e02, \u798f\u5ca1\u770c, JP",
    "qs:gn_namadm1":"07",
    "qs:local_max":4714,
    "qs:local_sum":31201,
    "qs:localhoods":64,
    "qs:name":"\uff16\u4e01\u76ee",
    "qs:name_adm0":"\u65e5\u672c",
    "qs:name_adm1":"\u798f\u5ca1\u770c",
    "qs:name_adm2":"\u6771\u533a",
    "qs:name_en":"Saitozaki 6 Chome",
    "qs:name_lau":"\u897f\u6238\u5d0e",
    "qs:name_local":"\u798f\u5ca1\u5e02",
    "qs:photo_max":130,
    "qs:photo_sum":250,
    "qs:placetype":"Suburb",
    "qs:quad_count":10,
    "qs:woe_adm0":23424856,
    "qs:woe_adm1":58646425,
    "qs:woe_adm2":15015571,
    "qs:woe_lau":1113996,
    "qs:woe_local":1117099,
    "qs:woe_ver":"7.10.0",
    "wof:lang":[
        "jpn"
    ],
    "wof:name":"\uff16\u4e01\u76ee",
    "wof:placetype":"neighbourhood"
},
  "geometry": {"coordinates":[130.35284799999999,33.659726],"type":"Point"}
}