{
  "type": "Feature",
  "properties": {
    "gn:admin1_code":"21.0",
    "gn:admin2_code":"1857206.0",
    "gn:asciiname":"Ogayama",
    "gn:country_code":"JP",
    "gn:dem":406,
    "gn:feature_class":"P",
    "gn:feature_code":"PPLL",
    "gn:name":"Ogayama",
    "gn:population":0,
    "gn:timezone":"Asia/Tokyo",
    "iso:country":"JP",
    "name:jpn_x_preferred":[
        "\u5c3e\u30f6\u5c71"
    ],
    "name:jpn_x_variant":[
        "\u304a\u304c\u3084\u307e",
        "\u30aa\u30ac\u30e4\u30de"
    ],
    "wof:name":"Ogayama",
    "wof:placetype":"locality"
},
  "geometry": {"coordinates":[130.57084,32.166],"type":"Point"}
}