{
  "type": "Feature",
  "properties": {
    "gn:admin1_code":"11",
    "gn:admin2_code":"1857327.0",
    "gn:asciiname":"Egi",
    "gn:cc2":"JP",
    "gn:country_code":"JP",
    "gn:dem":443,
    "gn:feature_class":"P",
    "gn:feature_code":"PPL",
    "gn:name":"Egi",
    "gn:population":0,
    "gn:timezone":"Asia/Tokyo",
    "iso:country":"JP",
    "name:und_x_variant":[
        "Eki",
        "Egi"
    ],
    "wof:name":"Egi",
    "wof:placetype":"locality"
},
  "geometry": {"coordinates":[133.03333000000001,34.53333],"type":"Point"}
}