{
  "type": "Feature",
  "properties": {
    "gn:admin1_code":"4.0",
    "gn:admin2_code":"2112997.0",
    "gn:admin3_code":"12422.0",
    "gn:asciiname":"Omote",
    "gn:country_code":"JP",
    "gn:dem":22,
    "gn:feature_class":"P",
    "gn:feature_code":"PPLL",
    "gn:name":"Omote",
    "gn:population":0,
    "gn:timezone":"Asia/Tokyo",
    "iso:country":"JP",
    "name:jpn_x_preferred":[
        "\u8868"
    ],
    "name:jpn_x_variant":[
        "\u304a\u3082\u3066",
        "\u30aa\u30e2\u30c6"
    ],
    "wof:name":"Omote",
    "wof:placetype":"locality"
},
  "geometry": {"coordinates":[140.32013000000001,35.37189],"type":"Point"}
}