{
  "type": "Feature",
  "properties": {
    "gn:admin1_code":"3.0",
    "gn:admin2_code":"7439937.0",
    "gn:asciiname":"Hosoya",
    "gn:country_code":"JP",
    "gn:dem":11,
    "gn:feature_class":"P",
    "gn:feature_code":"PPL",
    "gn:name":"Hosoya",
    "gn:population":0,
    "gn:timezone":"Asia/Tokyo",
    "iso:country":"JP",
    "name:jpn_x_preferred":[
        "\u7d30\u8c37"
    ],
    "name:jpn_x_variant":[
        "\u307b\u305d\u3084",
        "\u30db\u30bd\u30e4"
    ],
    "wof:name":"Hosoya",
    "wof:placetype":"locality"
},
  "geometry": {"coordinates":[141.40780000000001,40.75609],"type":"Point"}
}