{
  "type": "Feature",
  "properties": {
    "gn:admin1_code":"32.0",
    "gn:admin2_code":"1863476.0",
    "gn:asciiname":"Tsuhoji",
    "gn:country_code":"JP",
    "gn:dem":38,
    "gn:feature_class":"P",
    "gn:feature_code":"PPL",
    "gn:name":"Ts\u016bh\u014dji",
    "gn:population":0,
    "gn:timezone":"Asia/Tokyo",
    "iso:country":"JP",
    "name:jpn_x_preferred":[
        "\u901a\u6cd5\u5bfa"
    ],
    "name:und_x_variant":[
        "Ts\u016bh\u014dji"
    ],
    "wof:name":"Tsuhoji",
    "wof:placetype":"locality"
},
  "geometry": {"coordinates":[135.62578999999999,34.52945],"type":"Point"}
}