{
  "type": "Feature",
  "properties": {
    "gn:admin1_code":"18.0",
    "gn:admin2_code":"7383987.0",
    "gn:asciiname":"Sumiyocho-ishihara",
    "gn:country_code":"JP",
    "gn:dem":39,
    "gn:feature_class":"P",
    "gn:feature_code":"PPL",
    "gn:name":"Sumiy\u014dch\u014d-ishihara",
    "gn:population":0,
    "gn:timezone":"Asia/Tokyo",
    "iso:country":"JP",
    "name:jpn_x_preferred":[
        "\u4f4f\u7528\u753a\u77f3\u539f"
    ],
    "name:und_x_variant":[
        "Sumiy\u014dch\u014d-ishihara"
    ],
    "wof:name":"Sumiyocho-ishihara",
    "wof:placetype":"locality"
},
  "geometry": {"coordinates":[129.40974,28.26602],"type":"Point"}
}