{
  "type": "Feature",
  "properties": {
    "gn:admin1_code":"21.0",
    "gn:admin2_code":"1864973.0",
    "gn:asciiname":"Kaminishikawahara",
    "gn:country_code":"JP",
    "gn:dem":502,
    "gn:feature_class":"P",
    "gn:feature_code":"PPLL",
    "gn:name":"Kaminishikawahara",
    "gn:population":0,
    "gn:timezone":"Asia/Tokyo",
    "iso:country":"JP",
    "name:jpn_x_preferred":[
        "\u4e0a\u897f\u6cb3\u539f"
    ],
    "name:jpn_x_variant":[
        "\u304b\u307f\u306b\u3057\u304b\u308f\u306f\u3089",
        "\u30ab\u30df\u30cb\u30b7\u30ab\u30ef\u30cf\u30e9"
    ],
    "wof:name":"Kaminishikawahara",
    "wof:placetype":"locality"
},
  "geometry": {"coordinates":[131.10523999999998,32.95783],"type":"Point"}
}