{
  "type": "Feature",
  "properties": {
    "gn:admin1_code":"37.0",
    "gn:admin2_code":"9036693.0",
    "gn:asciiname":"Jo",
    "gn:country_code":"JP",
    "gn:dem":166,
    "gn:feature_class":"P",
    "gn:feature_code":"PPL",
    "gn:name":"J\u014d",
    "gn:population":0,
    "gn:timezone":"Asia/Tokyo",
    "iso:country":"JP",
    "name:hun_x_preferred":[
        "Jo"
    ],
    "name:jpn_x_preferred":[
        "J\u014d"
    ],
    "name:jpn_x_variant":[
        "\u57ce"
    ],
    "name:nno_x_preferred":[
        "Jo"
    ],
    "name:rus_x_preferred":[
        "\u0414\u0437\u0451"
    ],
    "name:ukr_x_preferred":[
        "\u0414\u0437\u044c\u043e"
    ],
    "wof:name":"Jo",
    "wof:placetype":"locality"
},
  "geometry": {"coordinates":[139.00461999999999,34.96385],"type":"Point"}
}