{
  "type": "Feature",
  "properties": {
    "iso:country":"JP",
    "name:eng_x_preferred":[
        "Jindaijimotomachi 3 Chome"
    ],
    "name:eng_x_variant":[
        "Jindaijimotomachi 3 Choume",
        "Jindaijimotomachi 3 Chome"
    ],
    "name:jpn_x_preferred":[
        "\uff13\u4e01\u76ee"
    ],
    "name:jpn_x_variant":[
        "\u3058\u3093\u3060\u3044\u3058\u3082\u3068\u307e\u3061 \uff13\u3061\u3087\u3046\u3081",
        "\u6df1\u5927\u5bfa\u5143\u753a \uff13\u4e01\u76ee",
        "\uff13\u3061\u3087\u3046\u3081"
    ],
    "name:unk_x_variant":[
        "\uff13\u4e01\u76ee"
    ],
    "qs:gn_local":0,
    "qs:local_max":1845,
    "qs:local_sum":7669,
    "qs:localhoods":21,
    "qs:name":"\uff13\u4e01\u76ee",
    "qs:name_adm0":"\u65e5\u672c",
    "qs:name_adm1":"\u6771\u4eac\u90fd",
    "qs:name_en":"Jindaijimotomachi 3 Chome",
    "qs:name_lau":"\u6df1\u5927\u5bfa\u5143\u753a",
    "qs:name_local":"\u8abf\u5e03\u5e02",
    "qs:photo_max":10,
    "qs:photo_sum":19,
    "qs:placetype":"Suburb",
    "qs:quad_count":2,
    "qs:woe_adm0":23424856,
    "qs:woe_adm1":2345889,
    "qs:woe_adm2":0,
    "qs:woe_lau":28415074,
    "qs:woe_local":1107816,
    "qs:woe_ver":"7.10.0",
    "wof:lang":[
        "jpn"
    ],
    "wof:name":"\uff13\u4e01\u76ee",
    "wof:placetype":"neighbourhood"
},
  "geometry": {"coordinates":[139.54490699999999,35.665665],"type":"Point"}
}