{
  "type": "Feature",
  "properties": {
    "gn:admin1_code":"21.0",
    "gn:admin2_code":"1858418.0",
    "gn:admin3_code":"43102.0",
    "gn:asciiname":"Nakahara",
    "gn:country_code":"JP",
    "gn:dem":48,
    "gn:feature_class":"P",
    "gn:feature_code":"PPLL",
    "gn:name":"Nakahara",
    "gn:population":0,
    "gn:timezone":"Asia/Tokyo",
    "iso:country":"JP",
    "name:jpn_x_preferred":[
        "\u4e2d\u539f"
    ],
    "name:jpn_x_variant":[
        "\u306a\u304b\u306f\u3089",
        "\u30ca\u30ab\u30cf\u30e9"
    ],
    "wof:name":"Nakahara",
    "wof:placetype":"locality"
},
  "geometry": {"coordinates":[130.77566999999999,32.84478],"type":"Point"}
}