{
  "type": "Feature",
  "properties": {
    "gn:admin1_code":"27",
    "gn:admin2_code":"7418810.0",
    "gn:asciiname":"Kamiagatacho-ina",
    "gn:country_code":"JP",
    "gn:dem":129,
    "gn:feature_class":"P",
    "gn:feature_code":"PPL",
    "gn:name":"Kamiagatach\u014d-ina",
    "gn:population":0,
    "gn:timezone":"Asia/Tokyo",
    "iso:country":"JP",
    "name:jpn_x_preferred":[
        "\u4e0a\u770c\u753a\u4f0a\u5948"
    ],
    "name:und_x_variant":[
        "Kamiagatach\u014d-ina",
        "Ina"
    ],
    "wof:name":"Kamiagatacho-ina",
    "wof:placetype":"locality"
},
  "geometry": {"coordinates":[129.31575000000001,34.56356],"type":"Point"}
}