{
  "type": "Feature",
  "properties": {
    "gn:admin1_code":"18",
    "gn:admin2_code":"7383994.0",
    "gn:asciiname":"Nakama",
    "gn:country_code":"JP",
    "gn:dem":99,
    "gn:feature_class":"P",
    "gn:feature_code":"PPL",
    "gn:name":"Nakama",
    "gn:population":0,
    "gn:timezone":"Asia/Tokyo",
    "iso:country":"JP",
    "name:ast_x_preferred":[
        "Nakama"
    ],
    "name:fra_x_preferred":[
        "Nakama"
    ],
    "name:kor_x_preferred":[
        "\ub098\uce74\ub9c8"
    ],
    "name:mlg_x_preferred":[
        "Nakama"
    ],
    "name:spa_x_preferred":[
        "Nakama"
    ],
    "wof:name":"Nakama",
    "wof:placetype":"locality"
},
  "geometry": {"coordinates":[130.28333000000001,31.35],"type":"Point"}
}