{
  "type": "Feature",
  "properties": {
    "gn:admin1_code":"7.0",
    "gn:admin2_code":"1851269.0",
    "gn:admin3_code":"40605.0",
    "gn:asciiname":"Tashiro",
    "gn:country_code":"JP",
    "gn:dem":291,
    "gn:feature_class":"P",
    "gn:feature_code":"PPLL",
    "gn:name":"Tashiro",
    "gn:population":0,
    "gn:timezone":"Asia/Tokyo",
    "iso:country":"JP",
    "name:deu_x_preferred":[
        "Tashiro"
    ],
    "name:ita_x_preferred":[
        "Tashiro"
    ],
    "name:jpn_x_preferred":[
        "\u7530\u4ee3"
    ],
    "name:kor_x_preferred":[
        "\ub2e4\uc2dc\ub85c"
    ],
    "name:rus_x_preferred":[
        "\u0422\u0430\u0441\u0438\u0440\u043e"
    ],
    "wof:name":"Tashiro",
    "wof:placetype":"locality"
},
  "geometry": {"coordinates":[130.82968,33.54232],"type":"Point"}
}