{
  "type": "Feature",
  "properties": {
    "gn:admin1_code":"14",
    "gn:admin2_code":"7452809.0",
    "gn:asciiname":"Yoshinuma",
    "gn:country_code":"JP",
    "gn:dem":28,
    "gn:feature_class":"P",
    "gn:feature_code":"PPL",
    "gn:name":"Yoshinuma",
    "gn:population":0,
    "gn:timezone":"Asia/Tokyo",
    "iso:country":"JP",
    "wof:name":"Yoshinuma",
    "wof:placetype":"locality"
},
  "geometry": {"coordinates":[140.01667,36.13333],"type":"Point"}
}