{
  "type": "Feature",
  "properties": {
    "iso:country":"JP",
    "name:eng_x_preferred":[
        "Namamugi 1 Chome"
    ],
    "name:eng_x_variant":[
        "Namamugi 1 Choume",
        "Namamugi 1 Chome"
    ],
    "name:jpn_x_preferred":[
        "\uff11\u4e01\u76ee"
    ],
    "name:jpn_x_variant":[
        "\u306a\u307e\u3080\u304e \uff11\u3061\u3087\u3046\u3081",
        "\u751f\u9ea6 \uff11\u4e01\u76ee",
        "\uff11\u3061\u3087\u3046\u3081"
    ],
    "qs:gn_local":0,
    "qs:local_max":6208,
    "qs:local_sum":82309,
    "qs:localhoods":190,
    "qs:name":"\uff11\u4e01\u76ee",
    "qs:name_adm0":"\u65e5\u672c",
    "qs:name_adm1":"\u795e\u5948\u5ddd\u770c",
    "qs:name_adm2":"\u9db4\u898b\u533a",
    "qs:name_en":"Namamugi 1 Chome",
    "qs:name_lau":"\u751f\u9ea6",
    "qs:name_local":"\u6a2a\u6d5c\u5e02",
    "qs:photo_max":51,
    "qs:photo_sum":151,
    "qs:placetype":"Suburb",
    "qs:quad_count":13,
    "qs:woe_adm0":23424856,
    "qs:woe_adm1":2345868,
    "qs:woe_adm2":15015540,
    "qs:woe_lau":28415568,
    "qs:woe_local":1118550,
    "qs:woe_ver":"7.10.0",
    "wof:lang":[
        "jpn"
    ],
    "wof:name":"\uff11\u4e01\u76ee",
    "wof:placetype":"neighbourhood"
},
  "geometry": {"coordinates":[139.66084799999999,35.490484],"type":"Point"}
}