{
  "type": "Feature",
  "properties": {
    "gn:admin1_code":"7.0",
    "gn:admin2_code":"1851269.0",
    "gn:admin3_code":"40602.0",
    "gn:asciiname":"Chuganji",
    "gn:country_code":"JP",
    "gn:dem":608,
    "gn:feature_class":"P",
    "gn:feature_code":"PPL",
    "gn:name":"Ch\u016bganji",
    "gn:population":0,
    "gn:timezone":"Asia/Tokyo",
    "iso:country":"JP",
    "name:jpn_x_preferred":[
        "\u4e2d\u5143\u5bfa"
    ],
    "name:und_x_variant":[
        "Ch\u016bganji"
    ],
    "wof:name":"Chuganji",
    "wof:placetype":"locality"
},
  "geometry": {"coordinates":[130.83573000000001,33.50111],"type":"Point"}
}