{
  "type": "Feature",
  "properties": {
    "gn:admin1_code":"16.0",
    "gn:admin2_code":"2112822.0",
    "gn:asciiname":"Fudo",
    "gn:country_code":"JP",
    "gn:dem":80,
    "gn:feature_class":"P",
    "gn:feature_code":"PPL",
    "gn:name":"Fud\u014d",
    "gn:population":0,
    "gn:timezone":"Asia/Tokyo",
    "iso:country":"JP",
    "name:jpn_x_preferred":[
        "\u4e0d\u52d5"
    ],
    "name:jpn_x_variant":[
        "\u3075\u3069\u3046",
        "\u30d5\u30c9\u30a6"
    ],
    "name:und_x_variant":[
        "Fud\u014d"
    ],
    "wof:name":"Fudo",
    "wof:placetype":"locality"
},
  "geometry": {"coordinates":[141.10849999999999,39.37758],"type":"Point"}
}