{
  "type": "Feature",
  "properties": {
    "gn:admin1_code":"33.0",
    "gn:admin2_code":"1853274.0",
    "gn:asciiname":"Narata",
    "gn:country_code":"JP",
    "gn:dem":4,
    "gn:feature_class":"P",
    "gn:feature_code":"PPLL",
    "gn:name":"Narata",
    "gn:population":0,
    "gn:timezone":"Asia/Tokyo",
    "iso:country":"JP",
    "name:jpn_x_preferred":[
        "\u6962\u7530\u3000"
    ],
    "wof:name":"Narata",
    "wof:placetype":"locality"
},
  "geometry": {"coordinates":[130.24639999999999,33.28570999999999],"type":"Point"}
}