{
  "type": "Feature",
  "properties": {
    "gn:admin1_code":"04",
    "gn:admin2_code":"1864901.0",
    "gn:admin3_code":"12463.0",
    "gn:asciiname":"Katsuyama",
    "gn:country_code":"JP",
    "gn:dem":8,
    "gn:feature_class":"P",
    "gn:feature_code":"PPL",
    "gn:name":"Katsuyama",
    "gn:population":0,
    "gn:timezone":"Asia/Tokyo",
    "iso:country":"JP",
    "name:ceb_x_preferred":[
        "Katsuyama"
    ],
    "name:deu_x_preferred":[
        "Katsuyama"
    ],
    "name:jpn_x_preferred":[
        "\u52dd\u5c71"
    ],
    "name:jpn_x_variant":[
        "\u304b\u3064\u3084\u307e",
        "\u30ab\u30c4\u30e4\u30de"
    ],
    "name:mlg_x_preferred":[
        "Katsuyama"
    ],
    "name:nld_x_preferred":[
        "Katsuyama"
    ],
    "name:ron_x_preferred":[
        "Katsuyama"
    ],
    "name:und_x_variant":[
        "Kachiyama"
    ],
    "wof:name":"Katsuyama",
    "wof:placetype":"locality"
},
  "geometry": {"coordinates":[139.82848999999999,35.11153],"type":"Point"}
}