{
  "type": "Feature",
  "properties": {
    "gn:admin1_code":"43.0",
    "gn:admin2_code":"1861287.0",
    "gn:admin3_code":"30341.0",
    "gn:asciiname":"Miyamoto",
    "gn:country_code":"JP",
    "gn:dem":378,
    "gn:feature_class":"P",
    "gn:feature_code":"PPL",
    "gn:name":"Miyamoto",
    "gn:population":0,
    "gn:timezone":"Asia/Tokyo",
    "iso:country":"JP",
    "name:jpn_x_preferred":[
        "\u5bae\u672c"
    ],
    "wof:name":"Miyamoto",
    "wof:placetype":"locality"
},
  "geometry": {"coordinates":[135.49981,34.27033],"type":"Point"}
}