{
  "type": "Feature",
  "properties": {
    "gn:admin1_code":"13",
    "gn:admin2_code":"7370821.0",
    "gn:asciiname":"Tenjin",
    "gn:country_code":"JP",
    "gn:dem":84,
    "gn:feature_class":"P",
    "gn:feature_code":"PPL",
    "gn:name":"Tenjin",
    "gn:population":0,
    "gn:timezone":"Asia/Tokyo",
    "iso:country":"JP",
    "name:jpn_x_preferred":[
        "\u5929\u795e"
    ],
    "wof:name":"Tenjin",
    "wof:placetype":"locality"
},
  "geometry": {"coordinates":[135.06493,34.90883],"type":"Point"}
}