{
  "type": "Feature",
  "properties": {
    "gn:admin1_code":"5.0",
    "gn:admin2_code":"1926135.0",
    "gn:asciiname":"Boze",
    "gn:country_code":"JP",
    "gn:dem":1,
    "gn:feature_class":"P",
    "gn:feature_code":"PPL",
    "gn:name":"B\u014dze",
    "gn:population":0,
    "gn:timezone":"Asia/Tokyo",
    "iso:country":"JP",
    "name:und_x_variant":[
        "B\u014dze"
    ],
    "wof:name":"Boze",
    "wof:placetype":"locality"
},
  "geometry": {"coordinates":[133.01528000000002,34.14167],"type":"Point"}
}