{
  "type": "Feature",
  "properties": {
    "iso:country":"JP",
    "name:eng_x_preferred":[
        "Nakazato 2 Chome"
    ],
    "name:eng_x_variant":[
        "Nakazato 2 Choume",
        "Nakazato 2 Chome"
    ],
    "name:jpn_x_preferred":[
        "\uff12\u4e01\u76ee"
    ],
    "name:jpn_x_variant":[
        "\u306a\u304b\u3056\u3068 \uff12\u3061\u3087\u3046\u3081",
        "\u4e2d\u91cc \uff12\u4e01\u76ee",
        "\uff12\u3061\u3087\u3046\u3081"
    ],
    "qs:gn_local":0,
    "qs:local_max":6,
    "qs:local_sum":6,
    "qs:localhoods":1,
    "qs:name":"\uff12\u4e01\u76ee",
    "qs:name_adm0":"\u65e5\u672c",
    "qs:name_adm1":"\u8328\u57ce\u770c",
    "qs:name_en":"Nakazato 2 Chome",
    "qs:name_lau":"\u4e2d\u91cc",
    "qs:name_local":"\u9f8d\u30f6\u5d0e\u5e02",
    "qs:photo_max":4,
    "qs:photo_sum":6,
    "qs:placetype":"Suburb",
    "qs:quad_count":2,
    "qs:woe_adm0":23424856,
    "qs:woe_adm1":2345863,
    "qs:woe_adm2":0,
    "qs:woe_lau":28402290,
    "qs:woe_local":1113961,
    "qs:woe_ver":"7.10.0",
    "wof:lang":[
        "jpn"
    ],
    "wof:name":"\uff12\u4e01\u76ee",
    "wof:placetype":"neighbourhood"
},
  "geometry": {"coordinates":[140.20477299999999,35.928351],"type":"Point"}
}