{
  "type": "Feature",
  "properties": {
    "gn:admin1_code":"43",
    "gn:admin2_code":"1855225.0",
    "gn:admin3_code":"30406.0",
    "gn:asciiname":"Esumi",
    "gn:country_code":"JP",
    "gn:dem":10,
    "gn:feature_class":"P",
    "gn:feature_code":"PPL",
    "gn:name":"Esumi",
    "gn:population":0,
    "gn:timezone":"Asia/Tokyo",
    "iso:country":"JP",
    "wof:name":"Esumi",
    "wof:placetype":"locality"
},
  "geometry": {"coordinates":[135.58999,33.50751],"type":"Point"}
}