{
  "type": "Feature",
  "properties": {
    "gn:admin1_code":"12.0",
    "gn:admin2_code":"7428095.0",
    "gn:admin3_code":"1561.0",
    "gn:asciiname":"Toyohata Ikku",
    "gn:country_code":"JP",
    "gn:dem":59,
    "gn:feature_class":"P",
    "gn:feature_code":"PPL",
    "gn:name":"Toyohata Ikku",
    "gn:population":0,
    "gn:timezone":"Asia/Tokyo",
    "iso:country":"JP",
    "name:jpn_x_preferred":[
        "\u8c4a\u7551\u4e00\u533a"
    ],
    "name:jpn_x_variant":[
        "\u3068\u3088\u306f\u305f\u3044\u3063\u304f",
        "\u30c8\u30e8\u30cf\u30bf\u30a4\u30c3\u30af"
    ],
    "name:und_x_variant":[
        "Kami-rutochi",
        "Kami-rurochi",
        "Toyohata-ikku",
        "Toyohata Ikku"
    ],
    "wof:name":"Toyohata Ikku",
    "wof:placetype":"locality"
},
  "geometry": {"coordinates":[143.13333,44.38333],"type":"Point"}
}