{
  "type": "Feature",
  "properties": {
    "gn:admin1_code":"7.0",
    "gn:admin2_code":"1861834.0",
    "gn:asciiname":"Sayo",
    "gn:country_code":"JP",
    "gn:dem":10,
    "gn:feature_class":"P",
    "gn:feature_code":"PPL",
    "gn:name":"Sayo",
    "gn:population":0,
    "gn:timezone":"Asia/Tokyo",
    "iso:country":"JP",
    "name:jpn_x_preferred":[
        "\u4f50\u4e0e"
    ],
    "wof:name":"Sayo",
    "wof:placetype":"locality"
},
  "geometry": {"coordinates":[130.72114999999999,33.67043],"type":"Point"}
}