{
  "type": "Feature",
  "properties": {
    "gn:admin1_code":"21.0",
    "gn:admin2_code":"1848441.0",
    "gn:asciiname":"Kagamimachi-shiohama",
    "gn:country_code":"JP",
    "gn:dem":-1,
    "gn:feature_class":"P",
    "gn:feature_code":"PPL",
    "gn:name":"Kagamimachi-shiohama",
    "gn:population":0,
    "gn:timezone":"Asia/Tokyo",
    "iso:country":"JP",
    "name:jpn_x_preferred":[
        "\u93e1\u753a\u5869\u6d5c"
    ],
    "name:jpn_x_variant":[
        "\u304b\u304c\u307f\u307e\u3061\u3057\u304a\u306f\u307e",
        "\u30ab\u30ac\u30df\u30de\u30c1\u30b7\u30aa\u30cf\u30de"
    ],
    "wof:name":"Kagamimachi-shiohama",
    "wof:placetype":"locality"
},
  "geometry": {"coordinates":[130.62392,32.55877],"type":"Point"}
}