{
  "type": "Feature",
  "properties": {
    "gn:admin1_code":"16.0",
    "gn:admin2_code":"2129400.0",
    "gn:admin3_code":"3506.0",
    "gn:asciiname":"Minamida",
    "gn:country_code":"JP",
    "gn:dem":287,
    "gn:feature_class":"P",
    "gn:feature_code":"PPL",
    "gn:name":"Minamida",
    "gn:population":0,
    "gn:timezone":"Asia/Tokyo",
    "iso:country":"JP",
    "name:jpn_x_preferred":[
        "\u5357\u7530"
    ],
    "name:jpn_x_variant":[
        "\u307f\u306a\u307f\u3060",
        "\u30df\u30ca\u30df\u30c0"
    ],
    "wof:name":"Minamida",
    "wof:placetype":"locality"
},
  "geometry": {"coordinates":[141.41845000000001,40.21516],"type":"Point"}
}