{
  "type": "Feature",
  "properties": {
    "gn:admin1_code":"12.0",
    "gn:admin2_code":"7428109.0",
    "gn:admin3_code":"1668.0",
    "gn:asciiname":"Futamata",
    "gn:country_code":"JP",
    "gn:dem":149,
    "gn:feature_class":"P",
    "gn:feature_code":"PPL",
    "gn:name":"Futamata",
    "gn:population":0,
    "gn:timezone":"Asia/Tokyo",
    "iso:country":"JP",
    "name:jpn_x_preferred":[
        "\u4e8c\u80a1"
    ],
    "name:jpn_x_variant":[
        "\u3075\u305f\u307e\u305f",
        "\u30d5\u30bf\u30de\u30bf"
    ],
    "wof:name":"Futamata",
    "wof:placetype":"locality"
},
  "geometry": {"coordinates":[143.89131,43.15741],"type":"Point"}
}