{
  "type": "Feature",
  "properties": {
    "gn:admin1_code":"19.0",
    "gn:admin2_code":"1859635.0",
    "gn:admin3_code":"14131.0",
    "gn:asciiname":"Daishi Koen",
    "gn:country_code":"JP",
    "gn:dem":1,
    "gn:feature_class":"P",
    "gn:feature_code":"PPL",
    "gn:name":"Daishi K\u014den",
    "gn:population":0,
    "gn:timezone":"Asia/Tokyo",
    "iso:country":"JP",
    "name:jpn_x_preferred":[
        "\u5927\u5e2b\u516c\u5712"
    ],
    "name:und_x_variant":[
        "Daishi K\u014den"
    ],
    "wof:name":"Daishi Koen",
    "wof:placetype":"locality"
},
  "geometry": {"coordinates":[139.73176000000001,35.53181],"type":"Point"}
}