{
  "type": "Feature",
  "properties": {
    "gn:admin1_code":"3.0",
    "gn:admin2_code":"2130056.0",
    "gn:asciiname":"Aburaden",
    "gn:country_code":"JP",
    "gn:dem":35,
    "gn:feature_class":"P",
    "gn:feature_code":"PPL",
    "gn:name":"Aburaden",
    "gn:population":0,
    "gn:timezone":"Asia/Tokyo",
    "iso:country":"JP",
    "name:jpn_x_preferred":[
        "\u6cb9\u4f1d"
    ],
    "name:jpn_x_variant":[
        "\u3042\u3076\u3089\u3067\u3093",
        "\u30a2\u30d6\u30e9\u30c7\u30f3"
    ],
    "wof:name":"Aburaden",
    "wof:placetype":"locality"
},
  "geometry": {"coordinates":[140.43093000000002,40.62653],"type":"Point"}
}