{
  "type": "Feature",
  "properties": {
    "gn:admin1_code":"21.0",
    "gn:admin2_code":"7413150.0",
    "gn:asciiname":"Takaike",
    "gn:country_code":"JP",
    "gn:dem":226,
    "gn:feature_class":"P",
    "gn:feature_code":"PPLL",
    "gn:name":"Takaike",
    "gn:population":0,
    "gn:timezone":"Asia/Tokyo",
    "iso:country":"JP",
    "name:jpn_x_preferred":[
        "\u9ad8\u6c60"
    ],
    "name:jpn_x_variant":[
        "\u305f\u304b\u3044\u3051",
        "\u30bf\u30ab\u30a4\u30b1"
    ],
    "wof:name":"Takaike",
    "wof:placetype":"locality"
},
  "geometry": {"coordinates":[130.79196000000002,33.0506],"type":"Point"}
}