{
  "type": "Feature",
  "properties": {
    "gn:admin1_code":"19.0",
    "gn:admin2_code":"1865009.0",
    "gn:admin3_code":"14382.0",
    "gn:asciiname":"Sukumogawa",
    "gn:country_code":"JP",
    "gn:dem":258,
    "gn:feature_class":"P",
    "gn:feature_code":"PPL",
    "gn:name":"Sukumogawa",
    "gn:population":0,
    "gn:timezone":"Asia/Tokyo",
    "iso:country":"JP",
    "name:jpn_x_preferred":[
        "\u9808\u96f2\u5ddd"
    ],
    "wof:name":"Sukumogawa",
    "wof:placetype":"locality"
},
  "geometry": {"coordinates":[139.07553999999999,35.22112],"type":"Point"}
}