{
  "type": "Feature",
  "properties": {
    "gn:admin1_code":"32.0",
    "gn:admin2_code":"1853897.0",
    "gn:admin3_code":"27114.0",
    "gn:asciiname":"Kamishinjo",
    "gn:country_code":"JP",
    "gn:dem":5,
    "gn:feature_class":"P",
    "gn:feature_code":"PPL",
    "gn:name":"Kamishinj\u014d",
    "gn:population":0,
    "gn:timezone":"Asia/Tokyo",
    "iso:country":"JP",
    "name:jpn_x_preferred":[
        "\u4e0a\u65b0\u5e84"
    ],
    "name:und_x_variant":[
        "Kamishinj\u014d"
    ],
    "wof:name":"Kamishinjo",
    "wof:placetype":"locality"
},
  "geometry": {"coordinates":[135.52909,34.74754],"type":"Point"}
}