{
  "type": "Feature",
  "properties": {
    "gn:admin1_code":"2.0",
    "gn:admin2_code":"2110504.0",
    "gn:asciiname":"Yoshiyachi",
    "gn:country_code":"JP",
    "gn:dem":171,
    "gn:feature_class":"P",
    "gn:feature_code":"PPL",
    "gn:name":"Yoshiyachi",
    "gn:population":0,
    "gn:timezone":"Asia/Tokyo",
    "iso:country":"JP",
    "name:jpn_x_preferred":[
        "\u5409\u8c37\u5730"
    ],
    "wof:name":"Yoshiyachi",
    "wof:placetype":"locality"
},
  "geometry": {"coordinates":[140.61909,39.24605],"type":"Point"}
}