{
  "type": "Feature",
  "properties": {
    "gn:admin1_code":"17.0",
    "gn:admin2_code":"1856906.0",
    "gn:asciiname":"Takumacho-ohama",
    "gn:country_code":"JP",
    "gn:dem":26,
    "gn:feature_class":"P",
    "gn:feature_code":"PPL",
    "gn:name":"Takumach\u014d-\u014dhama",
    "gn:population":0,
    "gn:timezone":"Asia/Tokyo",
    "iso:country":"JP",
    "name:jpn_x_preferred":[
        "\u8a6b\u9593\u753a\u5927\u6d5c"
    ],
    "name:und_x_variant":[
        "Takumach\u014d-\u014dhama"
    ],
    "wof:name":"Takumacho-ohama",
    "wof:placetype":"locality"
},
  "geometry": {"coordinates":[133.61809,34.23231],"type":"Point"}
}