{
  "type": "Feature",
  "properties": {
    "gn:admin1_code":"40.0",
    "gn:admin2_code":"7475135.0",
    "gn:asciiname":"Senkawa",
    "gn:country_code":"JP",
    "gn:dem":38,
    "gn:feature_class":"P",
    "gn:feature_code":"PPL",
    "gn:name":"Senkawa",
    "gn:population":0,
    "gn:timezone":"Asia/Tokyo",
    "iso:country":"JP",
    "name:jpn_x_preferred":[
        "\u5343\u5ddd"
    ],
    "name:jpn_x_variant":[
        "\u305b\u3093\u304b\u308f",
        "\u30bb\u30f3\u30ab\u30ef"
    ],
    "wof:name":"Senkawa",
    "wof:placetype":"locality"
},
  "geometry": {"coordinates":[139.69262000000001,35.73854],"type":"Point"}
}