{
  "type": "Feature",
  "properties": {
    "gn:admin1_code":"24.0",
    "gn:admin2_code":"2112261.0",
    "gn:asciiname":"Iwatsuki-hokisawa",
    "gn:country_code":"JP",
    "gn:dem":56,
    "gn:feature_class":"P",
    "gn:feature_code":"PPL",
    "gn:name":"Iwatsuki-h\u014dkisawa",
    "gn:population":0,
    "gn:timezone":"Asia/Tokyo",
    "iso:country":"JP",
    "name:jpn_x_preferred":[
        "\u5ca9\u6708\u7b92\u6ca2"
    ],
    "name:jpn_x_variant":[
        "\u3044\u308f\u3064\u304d\u307b\u3046\u304d\u3055\u308f",
        "\u30a4\u30ef\u30c4\u30ad\u30db\u30a6\u30ad\u30b5\u30ef"
    ],
    "name:und_x_variant":[
        "Iwatsuki-h\u014dkisawa"
    ],
    "wof:name":"Iwatsuki-hokisawa",
    "wof:placetype":"locality"
},
  "geometry": {"coordinates":[141.55826999999999,38.86189],"type":"Point"}
}