{
  "type": "Feature",
  "properties": {
    "gn:admin1_code":"46.0",
    "gn:asciiname":"Terataira",
    "gn:country_code":"JP",
    "gn:dem":145,
    "gn:feature_class":"P",
    "gn:feature_code":"PPLL",
    "gn:name":"Terataira",
    "gn:population":0,
    "gn:timezone":"Asia/Tokyo",
    "iso:country":"JP",
    "name:jpn_x_preferred":[
        "\u5bfa\u5e73\u3000"
    ],
    "wof:name":"Terataira",
    "wof:placetype":"locality"
},
  "geometry": {"coordinates":[138.53353999999999,35.25207],"type":"Point"}
}