{
  "type": "Feature",
  "properties": {
    "gn:admin1_code":"45",
    "gn:asciiname":"Dairi-shinmachi",
    "gn:country_code":"JP",
    "gn:dem":1,
    "gn:feature_class":"P",
    "gn:feature_code":"PPL",
    "gn:name":"Dairi-shinmachi",
    "gn:population":0,
    "gn:timezone":"Asia/Tokyo",
    "iso:country":"JP",
    "name:jpn_x_preferred":[
        "\u5927\u91cc\u65b0\u753a"
    ],
    "name:und_x_variant":[
        "Dairi",
        "Dairi-shimmachi",
        "Dairi-shinmachi"
    ],
    "wof:name":"Dairi-shinmachi",
    "wof:placetype":"locality"
},
  "geometry": {"coordinates":[130.91945000000001,33.89457],"type":"Point"}
}