{
  "type": "Feature",
  "properties": {
    "gn:admin1_code":"16.0",
    "gn:admin2_code":"2112822.0",
    "gn:asciiname":"Sekibukuro",
    "gn:country_code":"JP",
    "gn:dem":79,
    "gn:feature_class":"P",
    "gn:feature_code":"PPL",
    "gn:name":"Sekibukuro",
    "gn:population":0,
    "gn:timezone":"Asia/Tokyo",
    "iso:country":"JP",
    "name:jpn_x_preferred":[
        "\u5830\u888b"
    ],
    "name:jpn_x_variant":[
        "\u305b\u304d\u3076\u304f\u308d",
        "\u30bb\u30ad\u30d6\u30af\u30ed"
    ],
    "wof:name":"Sekibukuro",
    "wof:placetype":"locality"
},
  "geometry": {"coordinates":[141.14725000000001,39.39289],"type":"Point"}
}