{
  "type": "Feature",
  "properties": {
    "gn:admin1_code":"12.0",
    "gn:admin2_code":"7428103.0",
    "gn:admin3_code":"1601.0",
    "gn:asciiname":"Ikuchise",
    "gn:country_code":"JP",
    "gn:dem":24,
    "gn:feature_class":"P",
    "gn:feature_code":"PPL",
    "gn:name":"Ikuchise",
    "gn:population":0,
    "gn:timezone":"Asia/Tokyo",
    "iso:country":"JP",
    "name:jpn_x_preferred":[
        "\u5e7e\u5343\u4e16"
    ],
    "wof:name":"Ikuchise",
    "wof:placetype":"locality"
},
  "geometry": {"coordinates":[142.11822000000001,42.50466],"type":"Point"}
}