{
  "type": "Feature",
  "properties": {
    "gn:admin1_code":"15.0",
    "gn:admin2_code":"1851337.0",
    "gn:asciiname":"Kouraizuru",
    "gn:country_code":"JP",
    "gn:dem":20,
    "gn:feature_class":"P",
    "gn:feature_code":"PPL",
    "gn:name":"Kouraizuru",
    "gn:population":0,
    "gn:timezone":"Asia/Tokyo",
    "iso:country":"JP",
    "name:jpn_x_preferred":[
        "\u5c0f\u6d66\u51fa"
    ],
    "wof:name":"Kouraizuru",
    "wof:placetype":"locality"
},
  "geometry": {"coordinates":[137.23407,37.51583],"type":"Point"}
}