{
  "type": "Feature",
  "properties": {
    "gn:admin1_code":"22.0",
    "gn:admin2_code":"1857906.0",
    "gn:admin3_code":"26109.0",
    "gn:asciiname":"Ishida",
    "gn:country_code":"JP",
    "gn:dem":20,
    "gn:feature_class":"P",
    "gn:feature_code":"PPL",
    "gn:name":"Ishida",
    "gn:population":0,
    "gn:timezone":"Asia/Tokyo",
    "iso:country":"JP",
    "name:jpn_x_preferred":[
        "\u77f3\u7530"
    ],
    "wof:name":"Ishida",
    "wof:placetype":"locality"
},
  "geometry": {"coordinates":[135.80244999999999,34.93885],"type":"Point"}
}