{
  "type": "Feature",
  "properties": {
    "gn:admin1_code":"12.0",
    "gn:admin2_code":"2129869.0",
    "gn:asciiname":"Horomui",
    "gn:country_code":"JP",
    "gn:dem":8,
    "gn:feature_class":"P",
    "gn:feature_code":"PPL",
    "gn:name":"Horomui",
    "gn:population":0,
    "gn:timezone":"Asia/Tokyo",
    "iso:country":"JP",
    "name:jpn_x_preferred":[
        "\u5e4c\u5411"
    ],
    "name:jpn_x_variant":[
        "\u307b\u308d\u3080\u3044",
        "\u30db\u30ed\u30e0\u30a4",
        "\uff8e\uff9b\uff91\uff72"
    ],
    "wof:name":"Horomui",
    "wof:placetype":"locality"
},
  "geometry": {"coordinates":[141.65000000000001,43.15],"type":"Point"}
}