{
  "type": "Feature",
  "properties": {
    "gn:admin1_code":"12.0",
    "gn:admin2_code":"2130724.0",
    "gn:admin3_code":"1398.0",
    "gn:asciiname":"Kawakami",
    "gn:country_code":"JP",
    "gn:dem":682,
    "gn:feature_class":"P",
    "gn:feature_code":"PPL",
    "gn:name":"Kawakami",
    "gn:population":0,
    "gn:timezone":"Asia/Tokyo",
    "iso:country":"JP",
    "name:ceb_x_preferred":[
        "Kawakami"
    ],
    "name:deu_x_preferred":[
        "Kawakami"
    ],
    "name:fra_x_preferred":[
        "Kawakami"
    ],
    "name:ita_x_preferred":[
        "Kawakami"
    ],
    "name:jpn_x_preferred":[
        "\u5ddd\u4e0a\u6751"
    ],
    "name:kor_x_preferred":[
        "\uac00\uc640\uce74\ubbf8\ucd0c"
    ],
    "name:rus_x_preferred":[
        "\u041a\u0430\u0432\u0430\u043a\u0430\u043c\u0438"
    ],
    "name:ukr_x_preferred":[
        "\u041a\u0430\u0432\u0430\u043a\u0430\u043c\u0456"
    ],
    "name:und_x_variant":[
        "Kurohashi"
    ],
    "wof:name":"Kawakami",
    "wof:placetype":"locality"
},
  "geometry": {"coordinates":[141.0444,42.84157],"type":"Point"}
}