{
  "type": "Feature",
  "properties": {
    "gn:admin1_code":"02",
    "gn:admin2_code":"7443160.0",
    "gn:asciiname":"Takadoya",
    "gn:cc2":"JP",
    "gn:country_code":"JP",
    "gn:dem":133,
    "gn:feature_class":"P",
    "gn:feature_code":"PPL",
    "gn:name":"Takadoya",
    "gn:population":0,
    "gn:timezone":"Asia/Tokyo",
    "iso:country":"JP",
    "name:jpn_x_preferred":[
        "\u9ad8\u6238\u5c4b"
    ],
    "name:und_x_variant":[
        "Takatoya",
        "Takadoya"
    ],
    "wof:name":"Takadoya",
    "wof:placetype":"locality"
},
  "geometry": {"coordinates":[140.26667,39.26667],"type":"Point"}
}