{
  "type": "Feature",
  "properties": {
    "iso:country":"JP",
    "name:eng_x_preferred":[
        "Shimowadamachi 5 Chome"
    ],
    "name:eng_x_variant":[
        "Shimowadamachi 5 Choume",
        "Shimowadamachi 5 Chome"
    ],
    "name:jpn_x_preferred":[
        "\uff15\u4e01\u76ee"
    ],
    "name:jpn_x_variant":[
        "\u3057\u3082\u308f\u3060\u307e\u3061 \uff15\u3061\u3087\u3046\u3081",
        "\u4e0b\u548c\u7530\u753a \uff15\u4e01\u76ee",
        "\uff15\u3061\u3087\u3046\u3081"
    ],
    "qs:gn_local":0,
    "qs:local_max":2625,
    "qs:local_sum":3292,
    "qs:localhoods":8,
    "qs:name":"\uff15\u4e01\u76ee",
    "qs:name_adm0":"\u65e5\u672c",
    "qs:name_adm1":"\u7fa4\u99ac\u770c",
    "qs:name_en":"Shimowadamachi 5 Chome",
    "qs:name_lau":"\u4e0b\u548c\u7530\u753a",
    "qs:name_local":"\u9ad8\u5d0e\u5e02",
    "qs:photo_max":1995,
    "qs:photo_sum":2625,
    "qs:placetype":"Suburb",
    "qs:quad_count":22,
    "qs:woe_adm0":23424856,
    "qs:woe_adm1":2345860,
    "qs:woe_adm2":0,
    "qs:woe_lau":28406411,
    "qs:woe_local":1118295,
    "qs:woe_ver":"7.10.0",
    "wof:lang":[
        "jpn"
    ],
    "wof:name":"\uff15\u4e01\u76ee",
    "wof:placetype":"neighbourhood"
},
  "geometry": {"coordinates":[139.007181,36.32452],"type":"Point"}
}