{
  "type": "Feature",
  "properties": {
    "gn:admin1_code":"23.0",
    "gn:admin2_code":"1859297.0",
    "gn:admin3_code":"24543.0",
    "gn:asciiname":"Miyamaku-umaze",
    "gn:country_code":"JP",
    "gn:dem":54,
    "gn:feature_class":"P",
    "gn:feature_code":"PPL",
    "gn:name":"Miyamaku-umaze",
    "gn:population":0,
    "gn:timezone":"Asia/Tokyo",
    "iso:country":"JP",
    "name:jpn_x_preferred":[
        "\u6d77\u5c71\u533a\u99ac\u702c"
    ],
    "wof:name":"Miyamaku-umaze",
    "wof:placetype":"locality"
},
  "geometry": {"coordinates":[136.24645000000001,34.14628],"type":"Point"}
}