{
  "type": "Feature",
  "properties": {
    "gn:admin1_code":"12.0",
    "gn:admin2_code":"7428109.0",
    "gn:admin3_code":"1668.0",
    "gn:asciiname":"Koitoi",
    "gn:country_code":"JP",
    "gn:dem":2,
    "gn:feature_class":"P",
    "gn:feature_code":"PPL",
    "gn:name":"Koitoi",
    "gn:population":0,
    "gn:timezone":"Asia/Tokyo",
    "iso:country":"JP",
    "name:jpn_x_preferred":[
        "\u604b\u554f"
    ],
    "name:jpn_x_variant":[
        "\u3053\u3044\u3068\u3044",
        "\u30b3\u30a4\u30c8\u30a4"
    ],
    "wof:name":"Koitoi",
    "wof:placetype":"locality"
},
  "geometry": {"coordinates":[144.14891,42.98285],"type":"Point"}
}