{
  "type": "Feature",
  "properties": {
    "iso:country":"JP",
    "name:eng_x_preferred":[
        "Sakurayama 7 Chome"
    ],
    "name:eng_x_variant":[
        "Sakurayama 7 Choume",
        "Sakurayama 7 Chome"
    ],
    "name:jpn_x_preferred":[
        "\uff17\u4e01\u76ee"
    ],
    "name:jpn_x_variant":[
        "\u3055\u304f\u3089\u3084\u307e \uff17\u3061\u3087\u3046\u3081",
        "\u685c\u5c71 \uff17\u4e01\u76ee",
        "\uff17\u3061\u3087\u3046\u3081"
    ],
    "name:unk_x_variant":[
        "\uff17\u4e01\u76ee"
    ],
    "qs:gn_local":0,
    "qs:local_max":794,
    "qs:local_sum":2082,
    "qs:localhoods":7,
    "qs:name":"\uff17\u4e01\u76ee",
    "qs:name_adm0":"\u65e5\u672c",
    "qs:name_adm1":"\u795e\u5948\u5ddd\u770c",
    "qs:name_en":"Sakurayama 7 Chome",
    "qs:name_lau":"\u685c\u5c71",
    "qs:name_local":"\u9017\u5b50\u5e02",
    "qs:photo_max":116,
    "qs:photo_sum":231,
    "qs:placetype":"Suburb",
    "qs:quad_count":13,
    "qs:woe_adm0":23424856,
    "qs:woe_adm1":2345868,
    "qs:woe_adm2":0,
    "qs:woe_lau":28416976,
    "qs:woe_local":1118594,
    "qs:woe_ver":"7.10.0",
    "wof:lang":[
        "jpn"
    ],
    "wof:name":"\uff17\u4e01\u76ee",
    "wof:placetype":"neighbourhood"
},
  "geometry": {"coordinates":[139.58675199999999,35.289063],"type":"Point"}
}