{
  "type": "Feature",
  "properties": {
    "gn:admin1_code":"34.0",
    "gn:admin2_code":"10942180.0",
    "gn:asciiname":"Mida",
    "gn:country_code":"JP",
    "gn:dem":20,
    "gn:feature_class":"P",
    "gn:feature_code":"PPL",
    "gn:name":"Mida",
    "gn:population":0,
    "gn:timezone":"Asia/Tokyo",
    "iso:country":"JP",
    "name:ceb_x_preferred":[
        "Mida"
    ],
    "name:deu_x_preferred":[
        "Mida"
    ],
    "name:ita_x_preferred":[
        "Mida"
    ],
    "name:jpn_x_preferred":[
        "\u7b95\u7530"
    ],
    "name:jpn_x_variant":[
        "\u307f\u3060",
        "\u30df\u30c0"
    ],
    "name:swe_x_preferred":[
        "Mida"
    ],
    "wof:name":"Mida",
    "wof:placetype":"locality"
},
  "geometry": {"coordinates":[139.49916999999999,36.06984],"type":"Point"}
}