{
  "type": "Feature",
  "properties": {
    "gn:admin1_code":"19.0",
    "gn:admin2_code":"1848308.0",
    "gn:asciiname":"Nishihemicho",
    "gn:country_code":"JP",
    "gn:dem":44,
    "gn:feature_class":"P",
    "gn:feature_code":"PPL",
    "gn:name":"Nishihemich\u014d",
    "gn:population":0,
    "gn:timezone":"Asia/Tokyo",
    "iso:country":"JP",
    "name:jpn_x_preferred":[
        "\u897f\u9038\u898b\u753a"
    ],
    "name:und_x_variant":[
        "Nishihemich\u014d"
    ],
    "wof:name":"Nishihemicho",
    "wof:placetype":"locality"
},
  "geometry": {"coordinates":[139.64767000000001,35.28344],"type":"Point"}
}