{
  "type": "Feature",
  "properties": {
    "gn:admin1_code":"29.0",
    "gn:admin2_code":"1863539.0",
    "gn:asciiname":"Maruta",
    "gn:country_code":"JP",
    "gn:dem":11,
    "gn:feature_class":"P",
    "gn:feature_code":"PPL",
    "gn:name":"Maruta",
    "gn:population":0,
    "gn:timezone":"Asia/Tokyo",
    "iso:country":"JP",
    "name:deu_x_preferred":[
        "Maruta"
    ],
    "name:ita_x_preferred":[
        "Maruta"
    ],
    "name:jpn_x_preferred":[
        "\u4e38\u7530"
    ],
    "wof:name":"Maruta",
    "wof:placetype":"locality"
},
  "geometry": {"coordinates":[139.14318,37.74454],"type":"Point"}
}