{
  "type": "Feature",
  "properties": {
    "gn:admin1_code":"2.0",
    "gn:admin2_code":"2113122.0",
    "gn:asciiname":"Tegata",
    "gn:country_code":"JP",
    "gn:dem":9,
    "gn:feature_class":"P",
    "gn:feature_code":"PPL",
    "gn:name":"Tegata",
    "gn:population":0,
    "gn:timezone":"Asia/Tokyo",
    "iso:country":"JP",
    "name:jpn_x_preferred":[
        "\u624b\u5f62"
    ],
    "name:jpn_x_variant":[
        "\u3066\u304c\u305f",
        "\u30c6\u30ac\u30bf"
    ],
    "wof:name":"Tegata",
    "wof:placetype":"locality"
},
  "geometry": {"coordinates":[140.1354,39.71987],"type":"Point"}
}