{
  "type": "Feature",
  "properties": {
    "gn:admin1_code":"16.0",
    "gn:admin2_code":"2128940.0",
    "gn:asciiname":"Itsukamachi",
    "gn:country_code":"JP",
    "gn:dem":138,
    "gn:feature_class":"P",
    "gn:feature_code":"PPL",
    "gn:name":"Itsukamachi",
    "gn:population":0,
    "gn:timezone":"Asia/Tokyo",
    "iso:country":"JP",
    "name:jpn_x_preferred":[
        "\u4e94\u65e5\u753a"
    ],
    "name:jpn_x_variant":[
        "\u3044\u3064\u304b\u307e\u3061",
        "\u30a4\u30c4\u30ab\u30de\u30c1"
    ],
    "wof:name":"Itsukamachi",
    "wof:placetype":"locality"
},
  "geometry": {"coordinates":[141.30074999999999,40.26664],"type":"Point"}
}