{
  "type": "Feature",
  "properties": {
    "gn:admin1_code":"23.0",
    "gn:admin2_code":"1849544.0",
    "gn:asciiname":"Katada-shibukurocho",
    "gn:country_code":"JP",
    "gn:dem":28,
    "gn:feature_class":"P",
    "gn:feature_code":"PPL",
    "gn:name":"Katada-shibukuroch\u014d",
    "gn:population":0,
    "gn:timezone":"Asia/Tokyo",
    "iso:country":"JP",
    "name:jpn_x_preferred":[
        "\u7247\u7530\u5fd7\u888b\u753a"
    ],
    "name:und_x_variant":[
        "Katada-shibukuroch\u014d"
    ],
    "wof:name":"Katada-shibukurocho",
    "wof:placetype":"locality"
},
  "geometry": {"coordinates":[136.43858999999998,34.71442],"type":"Point"}
}