{
  "type": "Feature",
  "properties": {
    "gn:admin1_code":"7.0",
    "gn:admin2_code":"1859874.0",
    "gn:admin3_code":"40342.0",
    "gn:asciiname":"Hanamawari",
    "gn:country_code":"JP",
    "gn:dem":210,
    "gn:feature_class":"P",
    "gn:feature_code":"PPLL",
    "gn:name":"Hanamawari",
    "gn:population":0,
    "gn:timezone":"Asia/Tokyo",
    "iso:country":"JP",
    "name:jpn_x_preferred":[
        "\u82b1\u5efb"
    ],
    "wof:name":"Hanamawari",
    "wof:placetype":"locality"
},
  "geometry": {"coordinates":[130.58129,33.61087],"type":"Point"}
}