{
  "type": "Feature",
  "properties": {
    "gn:admin1_code":"18.0",
    "gn:admin2_code":"1862007.0",
    "gn:asciiname":"Yajigayu",
    "gn:country_code":"JP",
    "gn:dem":4,
    "gn:feature_class":"P",
    "gn:feature_code":"PPLL",
    "gn:name":"Yajigayu",
    "gn:population":0,
    "gn:timezone":"Asia/Tokyo",
    "iso:country":"JP",
    "name:jpn_x_preferred":[
        "\u5f25\u6b21\u30f6\u6e6f"
    ],
    "wof:name":"Yajigayu",
    "wof:placetype":"locality"
},
  "geometry": {"coordinates":[130.63890000000001,31.24732],"type":"Point"}
}