{
  "type": "Feature",
  "properties": {
    "gn:admin1_code":"4.0",
    "gn:admin2_code":"2113012.0",
    "gn:admin3_code":"12101.0",
    "gn:asciiname":"Kawasaki-cho",
    "gn:country_code":"JP",
    "gn:dem":7,
    "gn:feature_class":"P",
    "gn:feature_code":"PPL",
    "gn:name":"Kawasaki-ch\u014d",
    "gn:population":0,
    "gn:timezone":"Asia/Tokyo",
    "iso:country":"JP",
    "name:jpn_x_preferred":[
        "\u5ddd\u5d0e\u753a"
    ],
    "name:jpn_x_variant":[
        "\u304b\u308f\u3055\u304d\u3061\u3087\u3046"
    ],
    "name:und_x_variant":[
        "Kawasaki-ch\u014d",
        "Kawasaki"
    ],
    "wof:name":"Kawasaki-cho",
    "wof:placetype":"locality"
},
  "geometry": {"coordinates":[140.12267,35.58259],"type":"Point"}
}