{
  "type": "Feature",
  "properties": {
    "gn:admin1_code":"21.0",
    "gn:admin2_code":"7413151.0",
    "gn:asciiname":"Sobara",
    "gn:country_code":"JP",
    "gn:dem":12,
    "gn:feature_class":"P",
    "gn:feature_code":"PPLL",
    "gn:name":"S\u014dbara",
    "gn:population":0,
    "gn:timezone":"Asia/Tokyo",
    "iso:country":"JP",
    "name:jpn_x_preferred":[
        "\u53cc\u539f"
    ],
    "name:jpn_x_variant":[
        "\u305d\u3046\u3070\u3089",
        "\u30bd\u30a6\u30d0\u30e9"
    ],
    "name:und_x_variant":[
        "S\u014dbara"
    ],
    "wof:name":"Sobara",
    "wof:placetype":"locality"
},
  "geometry": {"coordinates":[130.4402,32.60079],"type":"Point"}
}