{
  "type": "Feature",
  "properties": {
    "gn:admin1_code":"12.0",
    "gn:admin2_code":"2128971.0",
    "gn:asciiname":"Shikishimacho",
    "gn:country_code":"JP",
    "gn:dem":22,
    "gn:feature_class":"P",
    "gn:feature_code":"PPL",
    "gn:name":"Shikishimach\u014d",
    "gn:population":0,
    "gn:timezone":"Asia/Tokyo",
    "iso:country":"JP",
    "name:jpn_x_preferred":[
        "\u6577\u5cf6\u753a"
    ],
    "name:jpn_x_variant":[
        "\u3057\u304d\u3057\u307e\u3061\u3087\u3046",
        "\u30b7\u30ad\u30b7\u30de\u30c1\u30e7\u30a6"
    ],
    "name:und_x_variant":[
        "Shikishimach\u014d"
    ],
    "wof:name":"Shikishimacho",
    "wof:placetype":"locality"
},
  "geometry": {"coordinates":[145.57693999999995,43.32429000000001],"type":"Point"}
}