{
  "type": "Feature",
  "properties": {
    "iso:country":"JP",
    "name:eng_x_preferred":[
        "Takasago 5 Chome"
    ],
    "name:eng_x_variant":[
        "Takasago 5 Choume",
        "Takasago 5 Chome"
    ],
    "name:jpn_x_preferred":[
        "\uff15\u4e01\u76ee"
    ],
    "name:jpn_x_variant":[
        "\u305f\u304b\u3055\u3054 \uff15\u3061\u3087\u3046\u3081",
        "\u9ad8\u7802 \uff15\u4e01\u76ee",
        "\uff15\u3061\u3087\u3046\u3081"
    ],
    "qs:gn_adm0_cc":"JP",
    "qs:gn_local":1850147,
    "qs:local_max":18112,
    "qs:local_sum":895907,
    "qs:localhoods":857,
    "qs:name":"\uff15\u4e01\u76ee",
    "qs:name_adm0":"\u65e5\u672c",
    "qs:name_adm1":"\u6771\u4eac\u90fd",
    "qs:name_adm2":"\u845b\u98fe\u533a",
    "qs:name_en":"Takasago 5 Chome",
    "qs:name_lau":"\u9ad8\u7802",
    "qs:name_local":"\u6771\u4eac",
    "qs:photo_max":18,
    "qs:photo_sum":31,
    "qs:placetype":"Suburb",
    "qs:quad_count":3,
    "qs:woe_adm0":23424856,
    "qs:woe_adm1":2345889,
    "qs:woe_adm2":15015375,
    "qs:woe_lau":28414723,
    "qs:woe_local":1118370,
    "qs:woe_ver":"7.10.0",
    "qs_pg:name":"\uff15\u4e01\u76ee",
    "qs_pg:name_adm0":"\u65e5\u672c",
    "qs_pg:name_adm1":"\u6771\u4eac\u90fd",
    "qs_pg:photos":38,
    "qs_pg:photos_1k":8,
    "qs_pg:photos_9k":1,
    "qs_pg:photos_9r":2,
    "qs_pg:photos_all":38,
    "qs_pg:photos_sr":2,
    "qs_pg:pop_sr":0,
    "qs_pg:qs_pg_placetype":"neighbourhood",
    "qs_pg:qs_pg_placetype_gp":"Suburb",
    "qs_pg:woe_adm0":23424856,
    "woe:adm0_id":23424856,
    "woe:name_adm0":"\u65e5\u672c",
    "woe:name_adm1":"\u6771\u4eac\u90fd",
    "woe:placetype":"Suburb",
    "wof:lang":[
        "jpn"
    ],
    "wof:name":"\uff15\u4e01\u76ee",
    "wof:placetype":"neighbourhood"
},
  "geometry": {"coordinates":[139.866604,35.74896],"type":"Point"}
}