{
  "type": "Feature",
  "properties": {
    "gn:admin1_code":"21.0",
    "gn:admin2_code":"1865358.0",
    "gn:asciiname":"Kawauramachi-imatomi",
    "gn:country_code":"JP",
    "gn:dem":116,
    "gn:feature_class":"P",
    "gn:feature_code":"PPL",
    "gn:name":"Kawauramachi-imatomi",
    "gn:population":0,
    "gn:timezone":"Asia/Tokyo",
    "iso:country":"JP",
    "name:jpn_x_preferred":[
        "\u6cb3\u6d66\u753a\u4eca\u5bcc"
    ],
    "name:jpn_x_variant":[
        "\u304b\u308f\u3046\u3089\u307e\u3061\u3044\u307e\u3068\u307f",
        "\u30ab\u30ef\u30a6\u30e9\u30de\u30c1\u30a4\u30de\u30c8\u30df"
    ],
    "wof:name":"Kawauramachi-imatomi",
    "wof:placetype":"locality"
},
  "geometry": {"coordinates":[130.03919999999999,32.29578],"type":"Point"}
}