{
  "type": "Feature",
  "properties": {
    "gn:admin1_code":"4.0",
    "gn:admin2_code":"2112557.0",
    "gn:admin3_code":"12443.0",
    "gn:asciiname":"Ogimachi",
    "gn:country_code":"JP",
    "gn:dem":12,
    "gn:feature_class":"P",
    "gn:feature_code":"PPLL",
    "gn:name":"\u014cgimachi",
    "gn:population":0,
    "gn:timezone":"Asia/Tokyo",
    "iso:country":"JP",
    "name:jpn_x_preferred":[
        "\u6247\u753a"
    ],
    "name:jpn_x_variant":[
        "\u304a\u3046\u304e\u307e\u3061",
        "\u30aa\u30a6\u30ae\u30de\u30c1"
    ],
    "name:und_x_variant":[
        "\u014cgimachi"
    ],
    "wof:name":"Ogimachi",
    "wof:placetype":"locality"
},
  "geometry": {"coordinates":[140.36473999999998,35.18496],"type":"Point"}
}