{
  "type": "Feature",
  "properties": {
    "gn:admin1_code":"25",
    "gn:admin2_code":"1855094.0",
    "gn:asciiname":"Hirabaru",
    "gn:cc2":"JP",
    "gn:country_code":"JP",
    "gn:dem":11,
    "gn:feature_class":"P",
    "gn:feature_code":"PPL",
    "gn:name":"Hirabaru",
    "gn:population":0,
    "gn:timezone":"Asia/Tokyo",
    "iso:country":"JP",
    "name:und_x_variant":[
        "Hirahara",
        "Hirabaru"
    ],
    "wof:name":"Hirabaru",
    "wof:placetype":"locality"
},
  "geometry": {"coordinates":[131.68333000000001,32.55],"type":"Point"}
}