{
  "type": "Feature",
  "properties": {
    "gn:admin1_code":"3.0",
    "gn:admin2_code":"2130654.0",
    "gn:asciiname":"Toyama",
    "gn:country_code":"JP",
    "gn:dem":11,
    "gn:feature_class":"P",
    "gn:feature_code":"PPL",
    "gn:name":"Toyama",
    "gn:population":0,
    "gn:timezone":"Asia/Tokyo",
    "iso:country":"JP",
    "name:aze_x_preferred":[
        "Toyama"
    ],
    "name:ceb_x_preferred":[
        "Toyama"
    ],
    "name:deu_x_preferred":[
        "Toyama"
    ],
    "name:fas_x_preferred":[
        "\u062a\u0648\u06cc\u0627\u0645\u0627"
    ],
    "name:jpn_x_preferred":[
        "\u6238\u5c71"
    ],
    "name:jpn_x_variant":[
        "\u3068\u3084\u307e",
        "\u30c8\u30e4\u30de"
    ],
    "name:kor_x_preferred":[
        "\ub3c4\uc57c\ub9c8"
    ],
    "name:mlg_x_preferred":[
        "Toyama"
    ],
    "name:nld_x_preferred":[
        "Toyama"
    ],
    "name:nor_x_preferred":[
        "Toyama"
    ],
    "name:por_x_preferred":[
        "Toyama"
    ],
    "name:ron_x_preferred":[
        "Toyama"
    ],
    "name:rus_x_preferred":[
        "\u0422\u043e\u044f\u043c\u0430"
    ],
    "name:slk_x_preferred":[
        "Tojama"
    ],
    "name:swa_x_preferred":[
        "Toyama"
    ],
    "name:ukr_x_preferred":[
        "\u0422\u043e\u044f\u043c\u0430"
    ],
    "name:zho_x_preferred":[
        "\u5bcc\u5c71"
    ],
    "wof:name":"Toyama",
    "wof:placetype":"locality"
},
  "geometry": {"coordinates":[140.80215000000001,40.80414],"type":"Point"}
}