{
  "type": "Feature",
  "properties": {
    "gn:admin1_code":"36.0",
    "gn:admin2_code":"1857549.0",
    "gn:asciiname":"Hongo",
    "gn:country_code":"JP",
    "gn:dem":6,
    "gn:feature_class":"P",
    "gn:feature_code":"PPL",
    "gn:name":"Hong\u014d",
    "gn:population":0,
    "gn:timezone":"Asia/Tokyo",
    "iso:country":"JP",
    "name:jpn_x_preferred":[
        "\u672c\u90f7"
    ],
    "name:und_x_variant":[
        "Hong\u014d"
    ],
    "wof:name":"Hongo",
    "wof:placetype":"locality"
},
  "geometry": {"coordinates":[132.98886999999999,35.42576],"type":"Point"}
}