{
  "type": "Feature",
  "properties": {
    "gn:admin1_code":"3.0",
    "gn:admin2_code":"2130056.0",
    "gn:asciiname":"Kawabukuro",
    "gn:country_code":"JP",
    "gn:dem":64,
    "gn:feature_class":"P",
    "gn:feature_code":"PPL",
    "gn:name":"Kawabukuro",
    "gn:population":0,
    "gn:timezone":"Asia/Tokyo",
    "iso:country":"JP",
    "name:jpn_x_preferred":[
        "\u5ddd\u888b"
    ],
    "name:jpn_x_variant":[
        "\u304b\u308f\u3076\u304f\u308d",
        "\u30ab\u30ef\u30d6\u30af\u30ed"
    ],
    "wof:name":"Kawabukuro",
    "wof:placetype":"locality"
},
  "geometry": {"coordinates":[140.38841000000002,40.58133],"type":"Point"}
}