{
  "type": "Feature",
  "properties": {
    "gn:admin1_code":"19.0",
    "gn:admin2_code":"1848308.0",
    "gn:asciiname":"Kugocho",
    "gn:country_code":"JP",
    "gn:dem":23,
    "gn:feature_class":"P",
    "gn:feature_code":"PPL",
    "gn:name":"Kug\u014dch\u014d",
    "gn:population":0,
    "gn:timezone":"Asia/Tokyo",
    "iso:country":"JP",
    "name:jpn_x_preferred":[
        "\u516c\u90f7\u753a"
    ],
    "name:jpn_x_variant":[
        "\u304f\u3054\u3046\u3061\u3087\u3046",
        "\u30af\u30b4\u30a6\u30c1\u30e7\u30a6"
    ],
    "name:und_x_variant":[
        "Kug\u014dch\u014d"
    ],
    "wof:name":"Kugocho",
    "wof:placetype":"locality"
},
  "geometry": {"coordinates":[139.67527999999999,35.25625],"type":"Point"}
}