{
  "type": "Feature",
  "properties": {
    "gn:admin1_code":"8.0",
    "gn:admin2_code":"7451503.0",
    "gn:admin3_code":"7342.0",
    "gn:asciiname":"Kasaishi",
    "gn:country_code":"JP",
    "gn:dem":274,
    "gn:feature_class":"P",
    "gn:feature_code":"PPL",
    "gn:name":"Kasaishi",
    "gn:population":0,
    "gn:timezone":"Asia/Tokyo",
    "iso:country":"JP",
    "name:jpn_x_preferred":[
        "\u7b20\u77f3"
    ],
    "wof:name":"Kasaishi",
    "wof:placetype":"locality"
},
  "geometry": {"coordinates":[140.33591000000001,37.2419],"type":"Point"}
}