{
  "type": "Feature",
  "properties": {
    "gn:admin1_code":"4.0",
    "gn:admin2_code":"1859468.0",
    "gn:asciiname":"Ozawa",
    "gn:country_code":"JP",
    "gn:dem":79,
    "gn:feature_class":"P",
    "gn:feature_code":"PPLL",
    "gn:name":"Ozawa",
    "gn:population":0,
    "gn:timezone":"Asia/Tokyo",
    "iso:country":"JP",
    "name:ara_x_preferred":[
        "\u0623\u0648\u0632\u0627\u0648\u0627"
    ],
    "name:deu_x_preferred":[
        "Ozawa"
    ],
    "name:fra_x_preferred":[
        "Ozawa"
    ],
    "name:ita_x_preferred":[
        "Ozawa"
    ],
    "name:jpn_x_preferred":[
        "\u5c0f\u6ca2"
    ],
    "name:jpn_x_variant":[
        "\u304a\u3056\u308f",
        "\u30aa\u30b6\u30ef"
    ],
    "name:nld_x_preferred":[
        "Ozawa"
    ],
    "name:rus_x_preferred":[
        "\u041e\u0434\u0437\u0430\u0432\u0430"
    ],
    "name:ukr_x_preferred":[
        "\u041e\u0434\u0437\u0430\u0432\u0430"
    ],
    "name:vie_x_preferred":[
        "Ozawa"
    ],
    "wof:name":"Ozawa",
    "wof:placetype":"locality"
},
  "geometry": {"coordinates":[140.07578999999998,35.34198],"type":"Point"}
}