{
  "type": "Feature",
  "properties": {
    "gn:admin1_code":"21.0",
    "gn:admin2_code":"1850744.0",
    "gn:admin3_code":"43368.0",
    "gn:asciiname":"Haraka-shinmachi",
    "gn:country_code":"JP",
    "gn:dem":-1,
    "gn:feature_class":"P",
    "gn:feature_code":"PPLL",
    "gn:name":"Haraka-shinmachi",
    "gn:population":0,
    "gn:timezone":"Asia/Tokyo",
    "iso:country":"JP",
    "name:jpn_x_preferred":[
        "\u8179\u8d64\u65b0\u753a"
    ],
    "name:jpn_x_variant":[
        "\u306f\u3089\u304b\u3057\u3093\u307e\u3061",
        "\u30cf\u30e9\u30ab\u30b7\u30f3\u30de\u30c1"
    ],
    "wof:name":"Haraka-shinmachi",
    "wof:placetype":"locality"
},
  "geometry": {"coordinates":[130.4785,32.91874],"type":"Point"}
}