{
  "type": "Feature",
  "properties": {
    "gn:admin1_code":"21.0",
    "gn:admin2_code":"1850743.0",
    "gn:asciiname":"Ikura-kitakata",
    "gn:country_code":"JP",
    "gn:dem":29,
    "gn:feature_class":"P",
    "gn:feature_code":"PPL",
    "gn:name":"Ikura-kitakata",
    "gn:population":0,
    "gn:timezone":"Asia/Tokyo",
    "iso:country":"JP",
    "name:jpn_x_preferred":[
        "\u4f0a\u5009\u5317\u65b9"
    ],
    "name:jpn_x_variant":[
        "\u3044\u304f\u3089\u304d\u305f\u304b\u305f",
        "\u30a4\u30af\u30e9\u30ad\u30bf\u30ab\u30bf"
    ],
    "wof:name":"Ikura-kitakata",
    "wof:placetype":"locality"
},
  "geometry": {"coordinates":[130.57617999999999,32.90782],"type":"Point"}
}