{
  "type": "Feature",
  "properties": {
    "gn:admin1_code":"26",
    "gn:admin2_code":"7417078.0",
    "gn:asciiname":"Togura",
    "gn:country_code":"JP",
    "gn:dem":374,
    "gn:feature_class":"P",
    "gn:feature_code":"PPL",
    "gn:name":"Togura",
    "gn:population":0,
    "gn:timezone":"Asia/Tokyo",
    "iso:country":"JP",
    "name:jpn_x_preferred":[
        "\u6238\u5009"
    ],
    "name:und_x_variant":[
        "Toguramachi",
        "Tokura",
        "Togura"
    ],
    "wof:name":"Togura",
    "wof:placetype":"locality"
},
  "geometry": {"coordinates":[138.15483999999998,36.49062],"type":"Point"}
}