{
  "type": "Feature",
  "properties": {
    "gn:admin1_code":"37.0",
    "gn:admin2_code":"1851714.0",
    "gn:admin3_code":"22103.0",
    "gn:asciiname":"Nakaisshiki",
    "gn:country_code":"JP",
    "gn:dem":172,
    "gn:feature_class":"P",
    "gn:feature_code":"PPLL",
    "gn:name":"Nakaisshiki",
    "gn:population":0,
    "gn:timezone":"Asia/Tokyo",
    "iso:country":"JP",
    "name:jpn_x_preferred":[
        "\u4e2d\u4e00\u8272"
    ],
    "wof:name":"Nakaisshiki",
    "wof:placetype":"locality"
},
  "geometry": {"coordinates":[138.50395,35.12481],"type":"Point"}
}