{
  "type": "Feature",
  "properties": {
    "gn:admin1_code":"4.0",
    "gn:admin2_code":"7465524.0",
    "gn:asciiname":"Yamada",
    "gn:country_code":"JP",
    "gn:dem":86,
    "gn:feature_class":"P",
    "gn:feature_code":"PPL",
    "gn:name":"Yamada",
    "gn:population":0,
    "gn:timezone":"Asia/Tokyo",
    "iso:country":"JP",
    "name:jpn_x_preferred":[
        "\u5c71\u7530"
    ],
    "name:jpn_x_variant":[
        "\u3084\u307e\u3060",
        "\u30e4\u30de\u30c0"
    ],
    "wof:name":"Yamada",
    "wof:placetype":"locality"
},
  "geometry": {"coordinates":[140.31136999999998,35.24641],"type":"Point"}
}