{
  "type": "Feature",
  "properties": {
    "gn:admin1_code":"34",
    "gn:admin2_code":"1859739.0",
    "gn:asciiname":"Furuichiba",
    "gn:country_code":"JP",
    "gn:dem":11,
    "gn:feature_class":"P",
    "gn:feature_code":"PPL",
    "gn:name":"Furuichiba",
    "gn:population":0,
    "gn:timezone":"Asia/Tokyo",
    "iso:country":"JP",
    "name:jpn_x_preferred":[
        "\u53e4\u5e02\u5834"
    ],
    "name:jpn_x_variant":[
        "\u3075\u308b\u3044\u3061\u3070",
        "\u30d5\u30eb\u30a4\u30c1\u30d0"
    ],
    "wof:name":"Furuichiba",
    "wof:placetype":"locality"
},
  "geometry": {"coordinates":[139.52756000000002,35.88715999999999],"type":"Point"}
}