{
  "type": "Feature",
  "properties": {
    "gn:admin1_code":"19",
    "gn:admin2_code":"1860670.0",
    "gn:asciiname":"Ueki",
    "gn:country_code":"JP",
    "gn:dem":17,
    "gn:feature_class":"P",
    "gn:feature_code":"PPL",
    "gn:name":"Ueki",
    "gn:population":0,
    "gn:timezone":"Asia/Tokyo",
    "iso:country":"JP",
    "name:jpn_x_preferred":[
        "\u690d\u6728"
    ],
    "name:jpn_x_variant":[
        "\u3046\u3048\u304d",
        "\u30a6\u30a8\u30ad"
    ],
    "wof:name":"Ueki",
    "wof:placetype":"locality"
},
  "geometry": {"coordinates":[139.51563999999999,35.35029],"type":"Point"}
}