{
  "type": "Feature",
  "properties": {
    "gn:admin1_code":"18.0",
    "gn:admin2_code":"7383987.0",
    "gn:asciiname":"Sumiyocho-kamiya",
    "gn:country_code":"JP",
    "gn:dem":73,
    "gn:feature_class":"P",
    "gn:feature_code":"PPL",
    "gn:name":"Sumiy\u014dch\u014d-kamiya",
    "gn:population":0,
    "gn:timezone":"Asia/Tokyo",
    "iso:country":"JP",
    "name:jpn_x_preferred":[
        "\u4f4f\u7528\u753a\u795e\u5c4b"
    ],
    "name:und_x_variant":[
        "Sumiy\u014dch\u014d-kamiya"
    ],
    "wof:name":"Sumiyocho-kamiya",
    "wof:placetype":"locality"
},
  "geometry": {"coordinates":[129.40348999999998,28.28101],"type":"Point"}
}