{
  "type": "Feature",
  "properties": {
    "gn:admin1_code":"28.0",
    "gn:admin2_code":"1855604.0",
    "gn:asciiname":"Tokujocho",
    "gn:country_code":"JP",
    "gn:dem":59,
    "gn:feature_class":"P",
    "gn:feature_code":"PPL",
    "gn:name":"T\u014dkuj\u014dch\u014d",
    "gn:population":0,
    "gn:timezone":"Asia/Tokyo",
    "iso:country":"JP",
    "name:jpn_x_preferred":[
        "\u6771\u4e5d\u6761\u753a"
    ],
    "name:und_x_variant":[
        "T\u014dkuj\u014dch\u014d"
    ],
    "wof:name":"Tokujocho",
    "wof:placetype":"locality"
},
  "geometry": {"coordinates":[135.81228000000002,34.65933],"type":"Point"}
}