{
  "type": "Feature",
  "properties": {
    "gn:admin1_code":"27.0",
    "gn:admin2_code":"1852895.0",
    "gn:asciiname":"Shingyoecho",
    "gn:country_code":"JP",
    "gn:dem":55,
    "gn:feature_class":"P",
    "gn:feature_code":"PPL",
    "gn:name":"Shingy\u014dech\u014d",
    "gn:population":0,
    "gn:timezone":"Asia/Tokyo",
    "iso:country":"JP",
    "name:jpn_x_preferred":[
        "\u65b0\u884c\u6c5f\u753a"
    ],
    "name:und_x_variant":[
        "Shingy\u014dech\u014d"
    ],
    "wof:name":"Shingyoecho",
    "wof:placetype":"locality"
},
  "geometry": {"coordinates":[129.83500000000001,33.15156],"type":"Point"}
}