{
  "type": "Feature",
  "properties": {
    "gn:admin1_code":"24.0",
    "gn:admin2_code":"2112574.0",
    "gn:asciiname":"Tashirohama",
    "gn:country_code":"JP",
    "gn:dem":42,
    "gn:feature_class":"P",
    "gn:feature_code":"PPL",
    "gn:name":"Tashirohama",
    "gn:population":0,
    "gn:timezone":"Asia/Tokyo",
    "iso:country":"JP",
    "name:jpn_x_preferred":[
        "\u7530\u4ee3\u6d5c"
    ],
    "name:jpn_x_variant":[
        "\u305f\u3057\u308d\u306f\u307e",
        "\u30bf\u30b7\u30ed\u30cf\u30de"
    ],
    "wof:name":"Tashirohama",
    "wof:placetype":"locality"
},
  "geometry": {"coordinates":[141.42188999999999,38.29982],"type":"Point"}
}