{
  "type": "Feature",
  "properties": {
    "gn:admin1_code":"21.0",
    "gn:admin2_code":"1849062.0",
    "gn:asciiname":"Koaimachi",
    "gn:country_code":"JP",
    "gn:dem":27,
    "gn:feature_class":"P",
    "gn:feature_code":"PPL",
    "gn:name":"K\u014daimachi",
    "gn:population":0,
    "gn:timezone":"Asia/Tokyo",
    "iso:country":"JP",
    "name:jpn_x_preferred":[
        "\u795e\u5408\u753a"
    ],
    "name:jpn_x_variant":[
        "\u3053\u3046\u3042\u3044\u307e\u3061",
        "\u30b3\u30a6\u30a2\u30a4\u30de\u30c1"
    ],
    "name:und_x_variant":[
        "K\u014daimachi"
    ],
    "wof:name":"Koaimachi",
    "wof:placetype":"locality"
},
  "geometry": {"coordinates":[130.64265,32.67154],"type":"Point"}
}