{
  "type": "Feature",
  "properties": {
    "gn:admin1_code":"21.0",
    "gn:admin2_code":"7413152.0",
    "gn:asciiname":"Mukaikubaru",
    "gn:country_code":"JP",
    "gn:dem":9,
    "gn:feature_class":"P",
    "gn:feature_code":"PPLL",
    "gn:name":"Mukaikubaru",
    "gn:population":0,
    "gn:timezone":"Asia/Tokyo",
    "iso:country":"JP",
    "name:jpn_x_preferred":[
        "\u5411\u4e45\u539f"
    ],
    "name:jpn_x_variant":[
        "\u3080\u304b\u3044\u304f\u3070\u308b",
        "\u30e0\u30ab\u30a4\u30af\u30d0\u30eb"
    ],
    "wof:name":"Mukaikubaru",
    "wof:placetype":"locality"
},
  "geometry": {"coordinates":[130.69006000000002,32.66370999999999],"type":"Point"}
}