{
  "type": "Feature",
  "properties": {
    "gn:admin1_code":"3.0",
    "gn:admin2_code":"7439944.0",
    "gn:asciiname":"Kizukuri-kanedate",
    "gn:country_code":"JP",
    "gn:dem":3,
    "gn:feature_class":"P",
    "gn:feature_code":"PPL",
    "gn:name":"Kizukuri-kanedate",
    "gn:population":0,
    "gn:timezone":"Asia/Tokyo",
    "iso:country":"JP",
    "name:jpn_x_preferred":[
        "\u6728\u9020\u517c\u9928"
    ],
    "name:jpn_x_variant":[
        "\u304d\u3065\u304f\u308a\u304b\u306d\u3060\u3066",
        "\u30ad\u30c5\u30af\u30ea\u30ab\u30cd\u30c0\u30c6"
    ],
    "wof:name":"Kizukuri-kanedate",
    "wof:placetype":"locality"
},
  "geometry": {"coordinates":[140.37926000000002,40.85026],"type":"Point"}
}