{
  "type": "Feature",
  "properties": {
    "gn:admin1_code":"21.0",
    "gn:admin2_code":"7412708.0",
    "gn:admin3_code":"43514.0",
    "gn:asciiname":"Tsukawaki",
    "gn:country_code":"JP",
    "gn:dem":169,
    "gn:feature_class":"P",
    "gn:feature_code":"PPLL",
    "gn:name":"Tsukawaki",
    "gn:population":0,
    "gn:timezone":"Asia/Tokyo",
    "iso:country":"JP",
    "name:jpn_x_preferred":[
        "\u585a\u8107"
    ],
    "name:jpn_x_variant":[
        "\u3064\u304b\u308f\u304d",
        "\u30c4\u30ab\u30ef\u30ad"
    ],
    "wof:name":"Tsukawaki",
    "wof:placetype":"locality"
},
  "geometry": {"coordinates":[130.89326,32.21548],"type":"Point"}
}