{
  "type": "Feature",
  "properties": {
    "gn:admin1_code":"21.0",
    "gn:admin2_code":"7412706.0",
    "gn:admin3_code":"43444.0",
    "gn:asciiname":"Kazato",
    "gn:country_code":"JP",
    "gn:dem":318,
    "gn:feature_class":"P",
    "gn:feature_code":"PPLL",
    "gn:name":"Kazato",
    "gn:population":0,
    "gn:timezone":"Asia/Tokyo",
    "iso:country":"JP",
    "name:jpn_x_preferred":[
        "\u9e7f\u91cc"
    ],
    "name:jpn_x_variant":[
        "\u304b\u3056\u3068",
        "\u30ab\u30b6\u30c8"
    ],
    "wof:name":"Kazato",
    "wof:placetype":"locality"
},
  "geometry": {"coordinates":[130.84729999999999,32.66945],"type":"Point"}
}