{
  "type": "Feature",
  "properties": {
    "gn:admin1_code":"4.0",
    "gn:admin2_code":"7465521.0",
    "gn:asciiname":"Tomiuracho-fukana",
    "gn:country_code":"JP",
    "gn:dem":63,
    "gn:feature_class":"P",
    "gn:feature_code":"PPL",
    "gn:name":"Tomiurach\u014d-fukana",
    "gn:population":0,
    "gn:timezone":"Asia/Tokyo",
    "iso:country":"JP",
    "name:jpn_x_preferred":[
        "\u5bcc\u6d66\u753a\u6df1\u540d"
    ],
    "name:jpn_x_variant":[
        "\u3068\u307f\u3046\u3089\u3061\u3087\u3046\u3075\u304b\u306a",
        "\u30c8\u30df\u30a6\u30e9\u30c1\u30e7\u30a6\u30d5\u30ab\u30ca"
    ],
    "name:und_x_variant":[
        "Tomiurach\u014d-fukana"
    ],
    "wof:name":"Tomiuracho-fukana",
    "wof:placetype":"locality"
},
  "geometry": {"coordinates":[139.84950000000001,35.04468],"type":"Point"}
}