{
  "type": "Feature",
  "properties": {
    "gn:admin1_code":"19.0",
    "gn:admin2_code":"1848308.0",
    "gn:asciiname":"Ikegami",
    "gn:country_code":"JP",
    "gn:dem":39,
    "gn:feature_class":"P",
    "gn:feature_code":"PPL",
    "gn:name":"Ikegami",
    "gn:population":0,
    "gn:timezone":"Asia/Tokyo",
    "iso:country":"JP",
    "name:deu_x_preferred":[
        "Ikegami"
    ],
    "name:fra_x_preferred":[
        "Ikegami"
    ],
    "name:ita_x_preferred":[
        "Ikegami"
    ],
    "name:jpn_x_preferred":[
        "\u6c60\u4e0a"
    ],
    "name:jpn_x_variant":[
        "\u3044\u3051\u304c\u307f",
        "\u30a4\u30b1\u30ac\u30df"
    ],
    "wof:name":"Ikegami",
    "wof:placetype":"locality"
},
  "geometry": {"coordinates":[139.64417,35.2653],"type":"Point"}
}