{
  "type": "Feature",
  "properties": {
    "gn:admin1_code":"12.0",
    "gn:admin2_code":"2129370.0",
    "gn:asciiname":"Onbetsu-motomachi",
    "gn:country_code":"JP",
    "gn:dem":5,
    "gn:feature_class":"P",
    "gn:feature_code":"PPL",
    "gn:name":"Onbetsu-motomachi",
    "gn:population":0,
    "gn:timezone":"Asia/Tokyo",
    "iso:country":"JP",
    "name:jpn_x_preferred":[
        "\u97f3\u5225\u672c\u753a"
    ],
    "name:jpn_x_variant":[
        "\u304a\u3093\u3079\u3064\u3082\u3068\u307e\u3061",
        "\u30aa\u30f3\u30d9\u30c4\u30e2\u30c8\u30de\u30c1"
    ],
    "name:und_x_variant":[
        "Otobetsu",
        "Ombetsushigai",
        "Ombetsu",
        "Onbetsu-motomachi"
    ],
    "wof:name":"Onbetsu-motomachi",
    "wof:placetype":"locality"
},
  "geometry": {"coordinates":[143.92899,42.89057],"type":"Point"}
}