{
  "type": "Feature",
  "properties": {
    "gn:admin1_code":"28.0",
    "gn:admin2_code":"7411377.0",
    "gn:admin3_code":"29322.0",
    "gn:asciiname":"Matono",
    "gn:country_code":"JP",
    "gn:dem":380,
    "gn:feature_class":"P",
    "gn:feature_code":"PPL",
    "gn:name":"Matono",
    "gn:population":0,
    "gn:timezone":"Asia/Tokyo",
    "iso:country":"JP",
    "name:jpn_x_preferred":[
        "\u7684\u91ce"
    ],
    "wof:name":"Matono",
    "wof:placetype":"locality"
},
  "geometry": {"coordinates":[135.96619999999999,34.67115],"type":"Point"}
}