{
  "type": "Feature",
  "properties": {
    "gn:admin1_code":"26",
    "gn:admin2_code":"1849427.0",
    "gn:asciiname":"Oya",
    "gn:country_code":"JP",
    "gn:dem":488,
    "gn:feature_class":"P",
    "gn:feature_code":"PPL",
    "gn:name":"\u014cya",
    "gn:population":0,
    "gn:timezone":"Asia/Tokyo",
    "iso:country":"JP",
    "name:deu_x_preferred":[
        "Oy\u00e1"
    ],
    "name:fra_x_preferred":[
        "Oya"
    ],
    "name:ita_x_preferred":[
        "Oy\u00e1"
    ],
    "name:jpn_x_preferred":[
        "\u5927\u5c4b"
    ],
    "name:por_x_preferred":[
        "Oy\u00e1"
    ],
    "name:spa_x_preferred":[
        "Oi\u00e1"
    ],
    "name:und_x_variant":[
        "\u014cya"
    ],
    "name:yor_x_preferred":[
        "\u1eccya"
    ],
    "wof:name":"Oya",
    "wof:placetype":"locality"
},
  "geometry": {"coordinates":[138.29316,36.37284],"type":"Point"}
}