{
  "type": "Feature",
  "properties": {
    "gn:admin1_code":"12.0",
    "gn:admin2_code":"2130044.0",
    "gn:admin3_code":"1362.0",
    "gn:asciiname":"Matsunoki",
    "gn:country_code":"JP",
    "gn:dem":166,
    "gn:feature_class":"P",
    "gn:feature_code":"PPL",
    "gn:name":"Matsunoki",
    "gn:population":0,
    "gn:timezone":"Asia/Tokyo",
    "iso:country":"JP",
    "wof:name":"Matsunoki",
    "wof:placetype":"locality"
},
  "geometry": {"coordinates":[140.18333000000001,41.75],"type":"Point"}
}