{
  "type": "Feature",
  "properties": {
    "gn:admin1_code":"3.0",
    "gn:admin2_code":"7439937.0",
    "gn:asciiname":"Minamiyama",
    "gn:country_code":"JP",
    "gn:dem":32,
    "gn:feature_class":"P",
    "gn:feature_code":"PPL",
    "gn:name":"Minamiyama",
    "gn:population":0,
    "gn:timezone":"Asia/Tokyo",
    "iso:country":"JP",
    "name:jpn_x_preferred":[
        "\u5357\u5c71"
    ],
    "name:jpn_x_variant":[
        "\u307f\u306a\u307f\u3084\u307e",
        "\u30df\u30ca\u30df\u30e4\u30de"
    ],
    "wof:name":"Minamiyama",
    "wof:placetype":"locality"
},
  "geometry": {"coordinates":[141.39611000000005,40.67983],"type":"Point"}
}