{
  "type": "Feature",
  "properties": {
    "gn:admin1_code":"2.0",
    "gn:admin2_code":"1854681.0",
    "gn:asciiname":"Tsuchibana",
    "gn:country_code":"JP",
    "gn:dem":9,
    "gn:feature_class":"P",
    "gn:feature_code":"PPL",
    "gn:name":"Tsuchibana",
    "gn:population":0,
    "gn:timezone":"Asia/Tokyo",
    "iso:country":"JP",
    "name:jpn_x_preferred":[
        "\u571f\u82b1"
    ],
    "wof:name":"Tsuchibana",
    "wof:placetype":"locality"
},
  "geometry": {"coordinates":[139.93498,40.00582],"type":"Point"}
}