{
  "type": "Feature",
  "properties": {
    "gn:admin1_code":"07",
    "gn:admin2_code":"9035649.0",
    "gn:asciiname":"Shima-funakoshi",
    "gn:country_code":"JP",
    "gn:dem":3,
    "gn:feature_class":"P",
    "gn:feature_code":"PPL",
    "gn:name":"Shima-funakoshi",
    "gn:population":0,
    "gn:timezone":"Asia/Tokyo",
    "iso:country":"JP",
    "name:jpn_x_preferred":[
        "\u5fd7\u6469\u8239\u8d8a"
    ],
    "name:und_x_variant":[
        "Funakoshi"
    ],
    "wof:name":"Shima-funakoshi",
    "wof:placetype":"locality"
},
  "geometry": {"coordinates":[130.12669,33.55754],"type":"Point"}
}