{
  "type": "Feature",
  "properties": {
    "gn:admin1_code":"32.0",
    "gn:admin2_code":"1853167.0",
    "gn:admin3_code":"27144.0",
    "gn:asciiname":"Hishiki",
    "gn:country_code":"JP",
    "gn:dem":24,
    "gn:feature_class":"P",
    "gn:feature_code":"PPL",
    "gn:name":"Hishiki",
    "gn:population":0,
    "gn:timezone":"Asia/Tokyo",
    "iso:country":"JP",
    "name:jpn_x_preferred":[
        "\u83f1\u6728"
    ],
    "wof:name":"Hishiki",
    "wof:placetype":"locality"
},
  "geometry": {"coordinates":[135.47367,34.51344],"type":"Point"}
}