{
  "type": "Feature",
  "properties": {
    "gn:admin1_code":"21.0",
    "gn:admin2_code":"7413151.0",
    "gn:asciiname":"Yamada",
    "gn:country_code":"JP",
    "gn:dem":15,
    "gn:feature_class":"P",
    "gn:feature_code":"PPLL",
    "gn:name":"Yamada",
    "gn:population":0,
    "gn:timezone":"Asia/Tokyo",
    "iso:country":"JP",
    "name:jpn_x_preferred":[
        "\u5c71\u7530"
    ],
    "name:jpn_x_variant":[
        "\u3084\u307e\u3060",
        "\u30e4\u30de\u30c0"
    ],
    "name:kor_x_preferred":[
        "\uc57c\ub9c8\ub2e4"
    ],
    "name:mlg_x_preferred":[
        "Yamada"
    ],
    "wof:name":"Yamada",
    "wof:placetype":"locality"
},
  "geometry": {"coordinates":[130.42542,32.50194],"type":"Point"}
}