{
  "type": "Feature",
  "properties": {
    "gn:admin1_code":"29",
    "gn:admin2_code":"1859907.0",
    "gn:asciiname":"Biwajima",
    "gn:country_code":"JP",
    "gn:dem":7,
    "gn:feature_class":"P",
    "gn:feature_code":"PPL",
    "gn:name":"Biwajima",
    "gn:population":0,
    "gn:timezone":"Asia/Tokyo",
    "iso:country":"JP",
    "name:jpn_x_preferred":[
        "\u6787\u6777\u5cf6"
    ],
    "wof:name":"Biwajima",
    "wof:placetype":"locality"
},
  "geometry": {"coordinates":[138.57101,37.36585],"type":"Point"}
}