{
  "type": "Feature",
  "properties": {
    "gn:admin1_code":"21.0",
    "gn:admin2_code":"7412706.0",
    "gn:admin3_code":"43444.0",
    "gn:asciiname":"Sunadome",
    "gn:country_code":"JP",
    "gn:dem":31,
    "gn:feature_class":"P",
    "gn:feature_code":"PPLL",
    "gn:name":"Sunadome",
    "gn:population":0,
    "gn:timezone":"Asia/Tokyo",
    "iso:country":"JP",
    "name:jpn_x_preferred":[
        "\u7802\u6e9c"
    ],
    "name:jpn_x_variant":[
        "\u3059\u306a\u3069\u3081",
        "\u30b9\u30ca\u30c9\u30e1"
    ],
    "wof:name":"Sunadome",
    "wof:placetype":"locality"
},
  "geometry": {"coordinates":[130.81601000000001,32.66476],"type":"Point"}
}