{
  "type": "Feature",
  "properties": {
    "gn:admin1_code":"29.0",
    "gn:admin2_code":"1853313.0",
    "gn:asciiname":"Hamochi-ohashi",
    "gn:country_code":"JP",
    "gn:dem":6,
    "gn:feature_class":"P",
    "gn:feature_code":"PPL",
    "gn:name":"Hamochi-\u014dhashi",
    "gn:population":0,
    "gn:timezone":"Asia/Tokyo",
    "iso:country":"JP",
    "name:jpn_x_preferred":[
        "\u7fbd\u8302\u5927\u6a4b"
    ],
    "name:und_x_variant":[
        "Hamochi-\u014dhashi"
    ],
    "wof:name":"Hamochi-ohashi",
    "wof:placetype":"locality"
},
  "geometry": {"coordinates":[138.30471,37.83975],"type":"Point"}
}