{
  "type": "Feature",
  "properties": {
    "gn:admin1_code":"18.0",
    "gn:admin2_code":"7383991.0",
    "gn:asciiname":"Oguchi-motomachi",
    "gn:country_code":"JP",
    "gn:dem":184,
    "gn:feature_class":"P",
    "gn:feature_code":"PPL",
    "gn:name":"\u014cguchi-motomachi",
    "gn:population":0,
    "gn:timezone":"Asia/Tokyo",
    "iso:country":"JP",
    "name:jpn_x_preferred":[
        "\u5927\u53e3\u5143\u753a"
    ],
    "name:jpn_x_variant":[
        "\u304a\u304a\u3050\u3061\u3082\u3068\u307e\u3061",
        "\u30aa\u30aa\u30b0\u30c1\u30e2\u30c8\u30de\u30c1"
    ],
    "name:und_x_variant":[
        "\u014cguchi-motomachi"
    ],
    "wof:name":"Oguchi-motomachi",
    "wof:placetype":"locality"
},
  "geometry": {"coordinates":[130.60811000000001,32.05725],"type":"Point"}
}