{
  "type": "Feature",
  "properties": {
    "gn:admin1_code":"27.0",
    "gn:admin2_code":"7418810.0",
    "gn:asciiname":"Inohashi",
    "gn:country_code":"JP",
    "gn:dem":21,
    "gn:feature_class":"P",
    "gn:feature_code":"PPL",
    "gn:name":"Inohashi",
    "gn:population":0,
    "gn:timezone":"Asia/Tokyo",
    "iso:country":"JP",
    "name:jpn_x_preferred":[
        "\u4f4d\u30ce\u7aef"
    ],
    "wof:name":"Inohashi",
    "wof:placetype":"locality"
},
  "geometry": {"coordinates":[129.36510000000001,34.42991],"type":"Point"}
}