{
  "type": "Feature",
  "properties": {
    "gn:admin1_code":"15.0",
    "gn:admin2_code":"7467882.0",
    "gn:asciiname":"Onaganomachi",
    "gn:country_code":"JP",
    "gn:dem":7,
    "gn:feature_class":"P",
    "gn:feature_code":"PPL",
    "gn:name":"\u014cnaganomachi",
    "gn:population":0,
    "gn:timezone":"Asia/Tokyo",
    "iso:country":"JP",
    "name:jpn_x_preferred":[
        "\u5927\u9577\u91ce\u753a"
    ],
    "name:und_x_variant":[
        "\u014cnaganomachi"
    ],
    "wof:name":"Onaganomachi",
    "wof:placetype":"locality"
},
  "geometry": {"coordinates":[136.49102999999999,36.43038],"type":"Point"}
}