{
  "type": "Feature",
  "properties": {
    "iso:country":"JP",
    "name:eng_x_preferred":[
        "Inokashira 2 Chome"
    ],
    "name:eng_x_variant":[
        "Inokashira 2 Choume",
        "Inokashira 2 Chome"
    ],
    "name:jpn_x_preferred":[
        "\uff12\u4e01\u76ee"
    ],
    "name:jpn_x_variant":[
        "\u3044\u306e\u304b\u3057\u3089 \uff12\u3061\u3087\u3046\u3081",
        "\u4e95\u306e\u982d \uff12\u4e01\u76ee",
        "\uff12\u3061\u3087\u3046\u3081"
    ],
    "name:unk_x_variant":[
        "\uff12\u4e01\u76ee"
    ],
    "qs:gn_adm0_cc":"JP",
    "qs:gn_local":1856942,
    "qs:gn_nam_loc":"\u4e09\u9df9\u5e02, \u6771\u4eac\u90fd, JP",
    "qs:gn_namadm1":"40",
    "qs:local_max":1442,
    "qs:local_sum":5491,
    "qs:localhoods":16,
    "qs:name":"\uff12\u4e01\u76ee",
    "qs:name_adm0":"\u65e5\u672c",
    "qs:name_adm1":"\u6771\u4eac\u90fd",
    "qs:name_en":"Inokashira 2 Chome",
    "qs:name_lau":"\u4e95\u306e\u982d",
    "qs:name_local":"\u4e09\u9df9\u5e02",
    "qs:photo_max":37,
    "qs:photo_sum":157,
    "qs:placetype":"Suburb",
    "qs:quad_count":10,
    "qs:woe_adm0":23424856,
    "qs:woe_adm1":2345889,
    "qs:woe_adm2":0,
    "qs:woe_lau":28414938,
    "qs:woe_local":1110112,
    "qs:woe_ver":"7.10.0",
    "wof:lang":[
        "jpn"
    ],
    "wof:name":"\uff12\u4e01\u76ee",
    "wof:placetype":"neighbourhood"
},
  "geometry": {"coordinates":[139.587413,35.692402],"type":"Point"}
}