{
  "type": "Feature",
  "properties": {
    "gn:admin1_code":"4.0",
    "gn:admin2_code":"1863711.0",
    "gn:asciiname":"Somegawa",
    "gn:country_code":"JP",
    "gn:dem":46,
    "gn:feature_class":"P",
    "gn:feature_code":"PPLL",
    "gn:name":"Somegawa",
    "gn:population":0,
    "gn:timezone":"Asia/Tokyo",
    "iso:country":"JP",
    "name:jpn_x_preferred":[
        "\u67d3\u5ddd"
    ],
    "name:jpn_x_variant":[
        "\u305d\u3081\u304c\u308f",
        "\u30bd\u30e1\u30ac\u30ef"
    ],
    "wof:name":"Somegawa",
    "wof:placetype":"locality"
},
  "geometry": {"coordinates":[139.90143999999998,35.26456],"type":"Point"}
}