{
  "type": "Feature",
  "properties": {
    "iso:country":"JP",
    "name:eng_x_preferred":[
        "Taibi 2 Chome"
    ],
    "name:eng_x_variant":[
        "Taibi 2 Choume",
        "Taibi 2 Chome"
    ],
    "name:jpn_x_preferred":[
        "\uff12\u4e01\u76ee"
    ],
    "name:jpn_x_variant":[
        "\u305f\u3044\u3073 \uff12\u3061\u3087\u3046\u3081",
        "\u9bdb\u5c3e \uff12\u4e01\u76ee",
        "\uff12\u3061\u3087\u3046\u3081"
    ],
    "qs:gn_local":0,
    "qs:local_max":147,
    "qs:local_sum":147,
    "qs:localhoods":1,
    "qs:name":"\uff12\u4e01\u76ee",
    "qs:name_adm0":"\u65e5\u672c",
    "qs:name_adm1":"\u5e83\u5cf6\u770c",
    "qs:name_adm2":"\u5b89\u82b8\u90e1",
    "qs:name_en":"Taibi 2 Chome",
    "qs:name_lau":"\u9bdb\u5c3e",
    "qs:name_local":"\u5742\u753a",
    "qs:photo_max":104,
    "qs:photo_sum":147,
    "qs:placetype":"Suburb",
    "qs:quad_count":6,
    "qs:woe_adm0":23424856,
    "qs:woe_adm1":2345861,
    "qs:woe_adm2":24857169,
    "qs:woe_lau":28475610,
    "qs:woe_local":1108530,
    "qs:woe_ver":"7.10.0",
    "qs_pg:name":"\uff12\u4e01\u76ee",
    "qs_pg:name_adm0":"\u65e5\u672c",
    "qs_pg:name_adm1":"\u5e83\u5cf6\u770c",
    "qs_pg:photos":146,
    "qs_pg:photos_1k":30,
    "qs_pg:photos_9k":1,
    "qs_pg:photos_9r":3,
    "qs_pg:photos_all":146,
    "qs_pg:photos_sr":3,
    "qs_pg:pop_sr":0,
    "qs_pg:qs_pg_placetype":"neighbourhood",
    "qs_pg:qs_pg_placetype_gp":"Suburb",
    "qs_pg:woe_adm0":23424856,
    "woe:adm0_id":23424856,
    "woe:name_adm0":"\u65e5\u672c",
    "woe:name_adm1":"\u5e83\u5cf6\u770c",
    "woe:placetype":"Suburb",
    "wof:lang":[
        "jpn"
    ],
    "wof:name":"\uff12\u4e01\u76ee",
    "wof:placetype":"neighbourhood"
},
  "geometry": {"coordinates":[132.482191,34.340551],"type":"Point"}
}