{
  "type": "Feature",
  "properties": {
    "gn:admin1_code":"31",
    "gn:admin2_code":"1850741.0",
    "gn:asciiname":"Uno",
    "gn:country_code":"JP",
    "gn:dem":7,
    "gn:feature_class":"P",
    "gn:feature_code":"PPL",
    "gn:name":"Uno",
    "gn:population":0,
    "gn:timezone":"Asia/Tokyo",
    "iso:country":"JP",
    "name:ast_x_preferred":[
        "Uno"
    ],
    "name:ceb_x_preferred":[
        "Uno"
    ],
    "name:dan_x_preferred":[
        "Uno"
    ],
    "name:deu_x_preferred":[
        "Uno"
    ],
    "name:fas_x_preferred":[
        "\u0627\u0648\u0646\u0648"
    ],
    "name:fin_x_preferred":[
        "Uno"
    ],
    "name:fra_x_preferred":[
        "Uno"
    ],
    "name:jpn_x_preferred":[
        "\u5b87\u91ce"
    ],
    "name:kor_x_preferred":[
        "Uno"
    ],
    "name:nld_x_preferred":[
        "Uno"
    ],
    "name:nor_x_preferred":[
        "Uno"
    ],
    "name:pol_x_preferred":[
        "Uno"
    ],
    "name:por_x_preferred":[
        "Uno"
    ],
    "name:spa_x_preferred":[
        "Uno"
    ],
    "name:srp_x_preferred":[
        "\u0423\u043d\u043e"
    ],
    "name:swe_x_preferred":[
        "Uno"
    ],
    "name:tgl_x_preferred":[
        "Uno"
    ],
    "name:tur_x_preferred":[
        "Uno"
    ],
    "wof:name":"Uno",
    "wof:placetype":"locality"
},
  "geometry": {"coordinates":[133.94933,34.49438],"type":"Point"}
}