{
  "type": "Feature",
  "properties": {
    "gn:admin1_code":"21.0",
    "gn:admin2_code":"7412706.0",
    "gn:admin3_code":"43447.0",
    "gn:asciiname":"Kumizaki",
    "gn:country_code":"JP",
    "gn:dem":643,
    "gn:feature_class":"P",
    "gn:feature_code":"PPLL",
    "gn:name":"Kumizaki",
    "gn:population":0,
    "gn:timezone":"Asia/Tokyo",
    "iso:country":"JP",
    "name:jpn_x_preferred":[
        "\u7d44\u5d0e"
    ],
    "name:jpn_x_variant":[
        "\u304f\u307f\u3056\u304d",
        "\u30af\u30df\u30b6\u30ad"
    ],
    "wof:name":"Kumizaki",
    "wof:placetype":"locality"
},
  "geometry": {"coordinates":[131.11571000000001,32.73217],"type":"Point"}
}