{
  "type": "Feature",
  "properties": {
    "gn:admin1_code":"8.0",
    "gn:admin2_code":"2110958.0",
    "gn:asciiname":"Kinosaki",
    "gn:country_code":"JP",
    "gn:dem":276,
    "gn:feature_class":"P",
    "gn:feature_code":"PPL",
    "gn:name":"Kinosaki",
    "gn:population":0,
    "gn:timezone":"Asia/Tokyo",
    "iso:country":"JP",
    "name:jpn_x_preferred":[
        "\u6728\u4e4b\u5d0e"
    ],
    "wof:name":"Kinosaki",
    "wof:placetype":"locality"
},
  "geometry": {"coordinates":[140.27808999999999,37.27623],"type":"Point"}
}