{
  "type": "Feature",
  "properties": {
    "iso:country":"JP",
    "name:eng_x_preferred":[
        "Ekimaechuo 1 Chome"
    ],
    "name:eng_x_variant":[
        "Ekimaechuuou 1 Choume",
        "Ekimaechuo 1 Chome"
    ],
    "name:jpn_x_preferred":[
        "\uff11\u4e01\u76ee"
    ],
    "name:jpn_x_variant":[
        "\u3048\u304d\u307e\u3048\u3061\u3085\u3046\u304a\u3046 \uff11\u3061\u3087\u3046\u3081",
        "\u99c5\u524d\u4e2d\u592e \uff11\u4e01\u76ee",
        "\uff11\u3061\u3087\u3046\u3081"
    ],
    "qs:gn_adm0_cc":"JP",
    "qs:gn_local":1853303,
    "qs:gn_nam_loc":"\u4f50\u8cc0\u5e02, \u4f50\u8cc0\u770c, JP",
    "qs:gn_namadm1":"33",
    "qs:local_max":135,
    "qs:local_sum":246,
    "qs:localhoods":3,
    "qs:name":"\uff11\u4e01\u76ee",
    "qs:name_adm0":"\u65e5\u672c",
    "qs:name_adm1":"\u4f50\u8cc0\u770c",
    "qs:name_en":"Ekimaechuo 1 Chome",
    "qs:name_lau":"\u99c5\u524d\u4e2d\u592e",
    "qs:name_local":"\u4f50\u8cc0\u5e02",
    "qs:photo_max":37,
    "qs:photo_sum":75,
    "qs:placetype":"Suburb",
    "qs:quad_count":3,
    "qs:woe_adm0":23424856,
    "qs:woe_adm1":2345882,
    "qs:woe_adm2":0,
    "qs:woe_lau":28485537,
    "qs:woe_local":1118068,
    "qs:woe_ver":"7.10.0",
    "wof:lang":[
        "jpn"
    ],
    "wof:name":"\uff11\u4e01\u76ee",
    "wof:placetype":"neighbourhood"
},
  "geometry": {"coordinates":[130.29774499999999,33.263556],"type":"Point"}
}