{
  "type": "Feature",
  "properties": {
    "gn:admin1_code":"21.0",
    "gn:admin2_code":"7413150.0",
    "gn:asciiname":"Suishobira",
    "gn:country_code":"JP",
    "gn:dem":282,
    "gn:feature_class":"P",
    "gn:feature_code":"PPLL",
    "gn:name":"Suish\u014dbira",
    "gn:population":0,
    "gn:timezone":"Asia/Tokyo",
    "iso:country":"JP",
    "name:jpn_x_preferred":[
        "\u6c34\u6676\u5e73"
    ],
    "name:jpn_x_variant":[
        "\u3059\u3044\u3057\u3087\u3046\u3073\u3089",
        "\u30b9\u30a4\u30b7\u30e7\u30a6\u30d3\u30e9"
    ],
    "name:und_x_variant":[
        "Suish\u014dbira"
    ],
    "wof:name":"Suishobira",
    "wof:placetype":"locality"
},
  "geometry": {"coordinates":[130.79522,33.08419],"type":"Point"}
}