{
  "type": "Feature",
  "properties": {
    "gn:admin1_code":"16.0",
    "gn:admin2_code":"2112822.0",
    "gn:asciiname":"Shimonakanai",
    "gn:country_code":"JP",
    "gn:dem":209,
    "gn:feature_class":"P",
    "gn:feature_code":"PPL",
    "gn:name":"Shimonakanai",
    "gn:population":0,
    "gn:timezone":"Asia/Tokyo",
    "iso:country":"JP",
    "name:jpn_x_preferred":[
        "\u4e0b\u4e2d\u5185"
    ],
    "name:jpn_x_variant":[
        "\u3057\u3082\u306a\u304b\u306a\u3044",
        "\u30b7\u30e2\u30ca\u30ab\u30ca\u30a4"
    ],
    "wof:name":"Shimonakanai",
    "wof:placetype":"locality"
},
  "geometry": {"coordinates":[141.22191000000001,39.34747],"type":"Point"}
}