{
  "type": "Feature",
  "properties": {
    "gn:admin1_code":"27",
    "gn:admin2_code":"7418810.0",
    "gn:asciiname":"Toyotamacho-ta",
    "gn:country_code":"JP",
    "gn:dem":4,
    "gn:feature_class":"P",
    "gn:feature_code":"PPL",
    "gn:name":"Toyotamach\u014d-ta",
    "gn:population":0,
    "gn:timezone":"Asia/Tokyo",
    "iso:country":"JP",
    "name:jpn_x_preferred":[
        "\u8c4a\u7389\u753a\u7530"
    ],
    "name:und_x_variant":[
        "Toyotamach\u014d-ta",
        "Ta"
    ],
    "wof:name":"Toyotamacho-ta",
    "wof:placetype":"locality"
},
  "geometry": {"coordinates":[129.29868000000002,34.42931],"type":"Point"}
}