{
  "type": "Feature",
  "properties": {
    "gn:admin1_code":"3.0",
    "gn:admin2_code":"2128302.0",
    "gn:admin3_code":"2450.0",
    "gn:asciiname":"Shimoyokosawa",
    "gn:country_code":"JP",
    "gn:dem":199,
    "gn:feature_class":"P",
    "gn:feature_code":"PPL",
    "gn:name":"Shimoyokosawa",
    "gn:population":0,
    "gn:timezone":"Asia/Tokyo",
    "iso:country":"JP",
    "name:jpn_x_preferred":[
        "\u4e0b\u6a2a\u6ca2"
    ],
    "name:jpn_x_variant":[
        "\u3057\u3082\u3088\u3053\u3055\u308f",
        "\u30b7\u30e2\u30e8\u30b3\u30b5\u30ef"
    ],
    "wof:name":"Shimoyokosawa",
    "wof:placetype":"locality"
},
  "geometry": {"coordinates":[141.15762000000001,40.42136],"type":"Point"}
}