{
  "type": "Feature",
  "properties": {
    "gn:admin1_code":"27",
    "gn:admin2_code":"7418808.0",
    "gn:asciiname":"Saikaicho-omodakago",
    "gn:country_code":"JP",
    "gn:dem":18,
    "gn:feature_class":"P",
    "gn:feature_code":"PPL",
    "gn:name":"Saikaich\u014d-omodakag\u014d",
    "gn:population":0,
    "gn:timezone":"Asia/Tokyo",
    "iso:country":"JP",
    "name:jpn_x_preferred":[
        "\u897f\u6d77\u753a\u9762\u9ad8\u90f7"
    ],
    "name:und_x_variant":[
        "Omotaka",
        "Omadaka",
        "Omodaka",
        "Saikaich\u014d-omodakag\u014d"
    ],
    "wof:name":"Saikaicho-omodakago",
    "wof:placetype":"locality"
},
  "geometry": {"coordinates":[129.67391999999998,33.08014],"type":"Point"}
}