{
  "type": "Feature",
  "properties": {
    "gn:admin1_code":"12.0",
    "gn:admin2_code":"7428097.0",
    "gn:admin3_code":"1643.0",
    "gn:asciiname":"Otoyo",
    "gn:country_code":"JP",
    "gn:dem":131,
    "gn:feature_class":"P",
    "gn:feature_code":"PPL",
    "gn:name":"\u014ctoyo",
    "gn:population":0,
    "gn:timezone":"Asia/Tokyo",
    "iso:country":"JP",
    "name:jpn_x_preferred":[
        "\u5927\u8c4a"
    ],
    "name:jpn_x_variant":[
        "\u304a\u304a\u3068\u3088",
        "\u30aa\u30aa\u30c8\u30e8"
    ],
    "name:und_x_variant":[
        "\u014ctoyo"
    ],
    "wof:name":"Otoyo",
    "wof:placetype":"locality"
},
  "geometry": {"coordinates":[143.37823,42.86865],"type":"Point"}
}