{
  "type": "Feature",
  "properties": {
    "gn:admin1_code":"40.0",
    "gn:admin2_code":"1853655.0",
    "gn:asciiname":"Sanno",
    "gn:country_code":"JP",
    "gn:dem":28,
    "gn:feature_class":"P",
    "gn:feature_code":"PPL",
    "gn:name":"Sann\u014d",
    "gn:population":0,
    "gn:timezone":"Asia/Tokyo",
    "iso:country":"JP",
    "name:jpn_x_preferred":[
        "\u5c71\u738b"
    ],
    "name:und_x_variant":[
        "Sann\u014d"
    ],
    "wof:name":"Sanno",
    "wof:placetype":"locality"
},
  "geometry": {"coordinates":[139.72485,35.58944],"type":"Point"}
}