{
  "type": "Feature",
  "properties": {
    "gn:admin1_code":"4.0",
    "gn:admin2_code":"2112997.0",
    "gn:admin3_code":"12427.0",
    "gn:asciiname":"Iwakawa-shimo",
    "gn:country_code":"JP",
    "gn:dem":16,
    "gn:feature_class":"P",
    "gn:feature_code":"PPLL",
    "gn:name":"Iwakawa-shimo",
    "gn:population":0,
    "gn:timezone":"Asia/Tokyo",
    "iso:country":"JP",
    "name:jpn_x_preferred":[
        "\u5ca9\u5ddd\u4e0b"
    ],
    "name:jpn_x_variant":[
        "\u3044\u308f\u304b\u308f\u3057\u3082",
        "\u30a4\u30ef\u30ab\u30ef\u30b7\u30e2"
    ],
    "wof:name":"Iwakawa-shimo",
    "wof:placetype":"locality"
},
  "geometry": {"coordinates":[140.24361000000002,35.42558],"type":"Point"}
}