{
  "type": "Feature",
  "properties": {
    "gn:admin1_code":"38.0",
    "gn:admin2_code":"2111674.0",
    "gn:admin3_code":"9407.0",
    "gn:asciiname":"Morinaga",
    "gn:country_code":"JP",
    "gn:dem":420,
    "gn:feature_class":"P",
    "gn:feature_code":"PPLL",
    "gn:name":"Morinaga",
    "gn:population":0,
    "gn:timezone":"Asia/Tokyo",
    "iso:country":"JP",
    "name:jpn_x_preferred":[
        "\u68ee\u6c38"
    ],
    "wof:name":"Morinaga",
    "wof:placetype":"locality"
},
  "geometry": {"coordinates":[140.13319999999999,37.07049],"type":"Point"}
}