{
  "type": "Feature",
  "properties": {
    "gn:admin1_code":"19.0",
    "gn:admin2_code":"1863429.0",
    "gn:asciiname":"Matsubara",
    "gn:country_code":"JP",
    "gn:dem":174,
    "gn:feature_class":"P",
    "gn:feature_code":"PPL",
    "gn:name":"Matsubara",
    "gn:population":0,
    "gn:timezone":"Asia/Tokyo",
    "iso:country":"JP",
    "name:jpn_x_preferred":[
        "\u677e\u539f"
    ],
    "wof:name":"Matsubara",
    "wof:placetype":"locality"
},
  "geometry": {"coordinates":[139.20359999999999,35.39398],"type":"Point"}
}