{
  "type": "Feature",
  "properties": {
    "gn:admin1_code":"36",
    "gn:admin2_code":"1863519.0",
    "gn:asciiname":"Ichiyama",
    "gn:country_code":"JP",
    "gn:dem":22,
    "gn:feature_class":"P",
    "gn:feature_code":"PPL",
    "gn:name":"Ichiyama",
    "gn:population":0,
    "gn:timezone":"Asia/Tokyo",
    "iso:country":"JP",
    "wof:name":"Ichiyama",
    "wof:placetype":"locality"
},
  "geometry": {"coordinates":[132.31666999999999,34.93333],"type":"Point"}
}