{
  "type": "Feature",
  "properties": {
    "gn:admin1_code":"13",
    "gn:admin2_code":"1862625.0",
    "gn:asciiname":"Shikamaku-kamominami",
    "gn:country_code":"JP",
    "gn:dem":2,
    "gn:feature_class":"P",
    "gn:feature_code":"PPL",
    "gn:name":"Shikamaku-kamominami",
    "gn:population":0,
    "gn:timezone":"Asia/Tokyo",
    "iso:country":"JP",
    "name:jpn_x_preferred":[
        "\u98fe\u78e8\u533a\u52a0\u8302\u5357"
    ],
    "name:und_x_variant":[
        "Shikama-ku"
    ],
    "wof:name":"Shikamaku-kamominami",
    "wof:placetype":"locality"
},
  "geometry": {"coordinates":[134.66338000000002,34.80016],"type":"Point"}
}