{
  "type": "Feature",
  "properties": {
    "iso:country":"JP",
    "qs:name":"\uff11\u4e01\u76ee",
    "qs:name_adm0":"\u65e5\u672c",
    "qs:name_adm1":"\u798f\u4e95\u770c",
    "qs:photos":70,
    "qs:photos_1k":14,
    "qs:photos_9k":1,
    "qs:photos_9r":2,
    "qs:photos_all":70,
    "qs:photos_sr":2,
    "qs:placetype":"Suburb",
    "qs:pop_sr":"0",
    "wof:name":"\uff11\u4e01\u76ee",
    "wof:placetype":"neighbourhood"
},
  "geometry": {"coordinates":[136.22106550000001,36.061713],"type":"Point"}
}