{
  "type": "Feature",
  "properties": {
    "gn:admin1_code":"24.0",
    "gn:admin2_code":"7447001.0",
    "gn:asciiname":"Hasama",
    "gn:country_code":"JP",
    "gn:dem":29,
    "gn:feature_class":"P",
    "gn:feature_code":"PPL",
    "gn:name":"Hasama",
    "gn:population":0,
    "gn:timezone":"Asia/Tokyo",
    "iso:country":"JP",
    "name:jpn_x_preferred":[
        "\u8feb"
    ],
    "name:jpn_x_variant":[
        "\u306f\u3055\u307e",
        "\u30cf\u30b5\u30de"
    ],
    "wof:name":"Hasama",
    "wof:placetype":"locality"
},
  "geometry": {"coordinates":[141.11472000000001,38.49053],"type":"Point"}
}