{
  "type": "Feature",
  "properties": {
    "iso:country":"JP",
    "label:eng_x_preferred_longname":[
        "Gero City"
    ],
    "label:eng_x_preferred_placetype":[
        "city"
    ],
    "name:eng_x_preferred":[
        "Gero"
    ],
    "name:eng_x_variant":[
        "Gero City"
    ],
    "name:jpn_x_preferred":[
        "\u4e0b\u5442\u5e02"
    ],
    "qs:name":"\u4e0b\u5442\u5e02",
    "qs:name_adm0":"\u65e5\u672c",
    "qs:name_adm1":"\u5c90\u961c\u770c",
    "qs:photos":694,
    "qs:photos_1k":141,
    "qs:photos_9k":3,
    "qs:photos_9r":5,
    "qs:photos_all":709,
    "qs:photos_sr":8,
    "qs:placetype":"Town",
    "qs:pop_sr":"0",
    "wof:name":"Gero",
    "wof:placetype":"locality"
},
  "geometry": {"coordinates":[137.24157600000001,35.8075],"type":"Point"}
}