{
  "type": "Feature",
  "properties": {
    "gn:admin1_code":"7.0",
    "gn:admin2_code":"1859306.0",
    "gn:admin3_code":"40109.0",
    "gn:asciiname":"Einomaru-minamimachi",
    "gn:country_code":"JP",
    "gn:dem":39,
    "gn:feature_class":"P",
    "gn:feature_code":"PPL",
    "gn:name":"Einomaru-minamimachi",
    "gn:population":0,
    "gn:timezone":"Asia/Tokyo",
    "iso:country":"JP",
    "name:jpn_x_preferred":[
        "\u6c38\u72ac\u4e38\u5357\u753a"
    ],
    "name:jpn_x_variant":[
        "\u3048\u3044\u306e\u307e\u308b\u307f\u306a\u307f\u307e\u3061"
    ],
    "wof:name":"Einomaru-minamimachi",
    "wof:placetype":"locality"
},
  "geometry": {"coordinates":[130.73085,33.83021],"type":"Point"}
}