{
  "type": "Feature",
  "properties": {
    "gn:admin1_code":"13",
    "gn:admin2_code":"1862625.0",
    "gn:asciiname":"Toyotomicho-toyotomi",
    "gn:country_code":"JP",
    "gn:dem":50,
    "gn:feature_class":"P",
    "gn:feature_code":"PPL",
    "gn:name":"Toyotomich\u014d-toyotomi",
    "gn:population":0,
    "gn:timezone":"Asia/Tokyo",
    "iso:country":"JP",
    "name:jpn_x_preferred":[
        "\u8c4a\u5bcc\u753a\u8c4a\u5bcc"
    ],
    "name:und_x_variant":[
        "Toyotomich\u014d-toyotomi",
        "Toyotomi"
    ],
    "wof:name":"Toyotomicho-toyotomi",
    "wof:placetype":"locality"
},
  "geometry": {"coordinates":[134.75,34.88333],"type":"Point"}
}