{
  "type": "Feature",
  "properties": {
    "gn:admin1_code":"24.0",
    "gn:admin2_code":"2110755.0",
    "gn:asciiname":"Kurosawa",
    "gn:country_code":"JP",
    "gn:dem":36,
    "gn:feature_class":"P",
    "gn:feature_code":"PPLL",
    "gn:name":"Kurosawa",
    "gn:population":0,
    "gn:timezone":"Asia/Tokyo",
    "iso:country":"JP",
    "name:jpn_x_preferred":[
        "\u9ed2\u6ca2"
    ],
    "wof:name":"Kurosawa",
    "wof:placetype":"locality"
},
  "geometry": {"coordinates":[141.36626999999999,38.63835],"type":"Point"}
}