{
  "type": "Feature",
  "properties": {
    "gn:admin1_code":"31",
    "gn:admin2_code":"1854380.0",
    "gn:admin3_code":"33101.0",
    "gn:asciiname":"Natsukawa",
    "gn:country_code":"JP",
    "gn:dem":4,
    "gn:feature_class":"P",
    "gn:feature_code":"PPL",
    "gn:name":"Natsukawa",
    "gn:population":0,
    "gn:timezone":"Asia/Tokyo",
    "iso:country":"JP",
    "name:jpn_x_preferred":[
        "\u64ab\u5ddd"
    ],
    "name:und_x_variant":[
        "Shimo-natsukawa",
        "Nazukawa"
    ],
    "wof:name":"Natsukawa",
    "wof:placetype":"locality"
},
  "geometry": {"coordinates":[133.84083000000001,34.64221],"type":"Point"}
}