{
  "type": "Feature",
  "properties": {
    "iso:country":"JP",
    "name:eng_x_preferred":[
        "Ashidamachi 2 Chome"
    ],
    "name:eng_x_variant":[
        "Ashidamachi 2 Choume",
        "Ashidamachi 2 Chome"
    ],
    "name:jpn_x_preferred":[
        "\uff12\u4e01\u76ee"
    ],
    "name:jpn_x_variant":[
        "\u3042\u3057\u3060\u307e\u3061 \uff12\u3061\u3087\u3046\u3081",
        "\u82a6\u7530\u753a \uff12\u4e01\u76ee",
        "\uff12\u3061\u3087\u3046\u3081"
    ],
    "qs:gn_local":0,
    "qs:local_max":44,
    "qs:local_sum":75,
    "qs:localhoods":3,
    "qs:name":"\uff12\u4e01\u76ee",
    "qs:name_adm0":"\u65e5\u672c",
    "qs:name_adm1":"\u77f3\u5ddd\u770c",
    "qs:name_en":"Ashidamachi 2 Chome",
    "qs:name_lau":"\u82a6\u7530\u753a",
    "qs:name_local":"\u5c0f\u677e\u5e02",
    "qs:photo_max":8,
    "qs:photo_sum":18,
    "qs:placetype":"Suburb",
    "qs:quad_count":4,
    "qs:woe_adm0":23424856,
    "qs:woe_adm1":2345864,
    "qs:woe_adm2":0,
    "qs:woe_lau":28426553,
    "qs:woe_local":1117565,
    "qs:woe_ver":"7.10.0",
    "wof:lang":[
        "jpn"
    ],
    "wof:name":"\uff12\u4e01\u76ee",
    "wof:placetype":"neighbourhood"
},
  "geometry": {"coordinates":[136.433716,36.405075],"type":"Point"}
}