{
  "type": "Feature",
  "properties": {
    "gn:admin1_code":"12.0",
    "gn:admin2_code":"7428102.0",
    "gn:admin3_code":"1608.0",
    "gn:asciiname":"Kotoni",
    "gn:country_code":"JP",
    "gn:dem":24,
    "gn:feature_class":"P",
    "gn:feature_code":"PPLL",
    "gn:name":"Kotoni",
    "gn:population":0,
    "gn:timezone":"Asia/Tokyo",
    "iso:country":"JP",
    "name:jpn_x_preferred":[
        "\u30b3\u30c8\u30cb"
    ],
    "name:jpn_x_variant":[
        "\u3053\u3068\u306b"
    ],
    "wof:name":"Kotoni",
    "wof:placetype":"locality"
},
  "geometry": {"coordinates":[142.99775,42.09483],"type":"Point"}
}