{
  "type": "Feature",
  "properties": {
    "gn:admin1_code":"21.0",
    "gn:admin2_code":"1858418.0",
    "gn:admin3_code":"43104.0",
    "gn:asciiname":"Tomiaimachi-enokizu",
    "gn:country_code":"JP",
    "gn:dem":3,
    "gn:feature_class":"P",
    "gn:feature_code":"PPL",
    "gn:name":"Tomiaimachi-enokizu",
    "gn:population":0,
    "gn:timezone":"Asia/Tokyo",
    "iso:country":"JP",
    "name:jpn_x_preferred":[
        "\u5bcc\u5408\u753a\u698e\u6d25"
    ],
    "name:jpn_x_variant":[
        "\u3068\u307f\u3042\u3044\u307e\u3061\u3048\u306e\u304d\u3065",
        "\u30c8\u30df\u30a2\u30a4\u30de\u30c1\u30a8\u30ce\u30ad\u30c5"
    ],
    "wof:name":"Tomiaimachi-enokizu",
    "wof:placetype":"locality"
},
  "geometry": {"coordinates":[130.69550000000001,32.71399],"type":"Point"}
}