{
  "type": "Feature",
  "properties": {
    "iso:country":"JP",
    "name:eng_x_preferred":[
        "Katsuradaiminami 1 Chome"
    ],
    "name:eng_x_variant":[
        "Katsuradaiminami 1 Choume",
        "Katsuradaiminami 1 Chome"
    ],
    "name:jpn_x_preferred":[
        "\uff11\u4e01\u76ee"
    ],
    "name:jpn_x_variant":[
        "\u304b\u3064\u3089\u3060\u3044\u307f\u306a\u307f \uff11\u3061\u3087\u3046\u3081",
        "\u6842\u53f0\u5357 \uff11\u4e01\u76ee",
        "\uff11\u3061\u3087\u3046\u3081"
    ],
    "qs:gn_local":0,
    "qs:local_max":6208,
    "qs:local_sum":82309,
    "qs:localhoods":190,
    "qs:name":"\uff11\u4e01\u76ee",
    "qs:name_adm0":"\u65e5\u672c",
    "qs:name_adm1":"\u795e\u5948\u5ddd\u770c",
    "qs:name_adm2":"\u6804\u533a",
    "qs:name_en":"Katsuradaiminami 1 Chome",
    "qs:name_lau":"\u6842\u53f0\u5357",
    "qs:name_local":"\u6a2a\u6d5c\u5e02",
    "qs:photo_max":1,
    "qs:photo_sum":1,
    "qs:placetype":"Suburb",
    "qs:quad_count":1,
    "qs:woe_adm0":23424856,
    "qs:woe_adm1":2345868,
    "qs:woe_adm2":15015426,
    "qs:woe_lau":28416167,
    "qs:woe_local":1118550,
    "qs:woe_ver":"7.10.0",
    "wof:lang":[
        "jpn"
    ],
    "wof:name":"\uff11\u4e01\u76ee",
    "wof:placetype":"neighbourhood"
},
  "geometry": {"coordinates":[139.562073,35.350975],"type":"Point"}
}