{
  "type": "Feature",
  "properties": {
    "iso:country":"JP",
    "name:eng_x_preferred":[
        "Kanan Town"
    ],
    "name:jpn_x_preferred":[
        "\u6cb3\u5357\u753a"
    ],
    "qs:name":"\u6cb3\u5357\u753a",
    "qs:name_adm0":"\u65e5\u672c",
    "qs:name_adm1":"\u5927\u962a\u5e9c",
    "qs:photos":22,
    "qs:photos_1k":4,
    "qs:photos_9k":1,
    "qs:photos_9r":2,
    "qs:photos_all":43,
    "qs:photos_sr":1,
    "qs:placetype":"Town",
    "qs:pop_sr":"0",
    "wof:name":"Kanan Town",
    "wof:placetype":"locality"
},
  "geometry": {"coordinates":[135.648696,34.48067],"type":"Point"}
}