{
  "type": "Feature",
  "properties": {
    "gn:admin1_code":"40.0",
    "gn:admin2_code":"1864514.0",
    "gn:asciiname":"Midorigaoka",
    "gn:country_code":"JP",
    "gn:dem":49,
    "gn:feature_class":"P",
    "gn:feature_code":"PPL",
    "gn:name":"Midorigaoka",
    "gn:population":0,
    "gn:timezone":"Asia/Tokyo",
    "iso:country":"JP",
    "name:jpn_x_preferred":[
        "\u7dd1\u30f6\u4e18"
    ],
    "wof:name":"Midorigaoka",
    "wof:placetype":"locality"
},
  "geometry": {"coordinates":[139.58393999999998,35.66891],"type":"Point"}
}