{
  "type": "Feature",
  "properties": {
    "gn:admin1_code":"8.0",
    "gn:admin2_code":"1848677.0",
    "gn:admin3_code":"7408.0",
    "gn:asciiname":"Nakanosawa",
    "gn:country_code":"JP",
    "gn:dem":745,
    "gn:feature_class":"P",
    "gn:feature_code":"PPLL",
    "gn:name":"Nakanosawa",
    "gn:population":0,
    "gn:timezone":"Asia/Tokyo",
    "iso:country":"JP",
    "name:jpn_x_preferred":[
        "\u4e2d\u306e\u6ca2"
    ],
    "wof:name":"Nakanosawa",
    "wof:placetype":"locality"
},
  "geometry": {"coordinates":[140.20917,37.61553],"type":"Point"}
}