{
  "type": "Feature",
  "properties": {
    "iso:country":"JP",
    "name:eng_x_preferred":[
        "Yurinokidai 6 Chome"
    ],
    "name:eng_x_variant":[
        "Yurinokidai 6 Choume",
        "Yurinokidai 6 Chome"
    ],
    "name:jpn_x_preferred":[
        "\uff16\u4e01\u76ee"
    ],
    "name:jpn_x_variant":[
        "\u3086\u308a\u306e\u304d\u3060\u3044 \uff16\u3061\u3087\u3046\u3081",
        "\u3086\u308a\u306e\u304d\u53f0 \uff16\u4e01\u76ee",
        "\uff16\u3061\u3087\u3046\u3081"
    ],
    "qs:gn_local":0,
    "qs:local_max":12,
    "qs:local_sum":23,
    "qs:localhoods":3,
    "qs:name":"\uff16\u4e01\u76ee",
    "qs:name_adm0":"\u65e5\u672c",
    "qs:name_adm1":"\u5175\u5eab\u770c",
    "qs:name_en":"Yurinokidai 6 Chome",
    "qs:name_lau":"\u3086\u308a\u306e\u304d\u53f0",
    "qs:name_local":"\u4e09\u7530\u5e02",
    "qs:photo_max":1,
    "qs:photo_sum":1,
    "qs:placetype":"Suburb",
    "qs:quad_count":1,
    "qs:woe_adm0":23424856,
    "qs:woe_adm1":2345862,
    "qs:woe_adm2":0,
    "qs:woe_lau":28463873,
    "qs:woe_local":1118100,
    "qs:woe_ver":"7.10.0",
    "wof:lang":[
        "jpn"
    ],
    "wof:name":"\uff16\u4e01\u76ee",
    "wof:placetype":"neighbourhood"
},
  "geometry": {"coordinates":[135.189514,34.937733],"type":"Point"}
}