{
  "type": "Feature",
  "properties": {
    "gn:admin1_code":"4.0",
    "gn:admin2_code":"7465521.0",
    "gn:asciiname":"Nishinosawa",
    "gn:country_code":"JP",
    "gn:dem":136,
    "gn:feature_class":"P",
    "gn:feature_code":"PPL",
    "gn:name":"Nishinosawa",
    "gn:population":0,
    "gn:timezone":"Asia/Tokyo",
    "iso:country":"JP",
    "name:jpn_x_preferred":[
        "\u897f\u30ce\u6ca2"
    ],
    "name:jpn_x_variant":[
        "\u306b\u3057\u306e\u3055\u308f",
        "\u30cb\u30b7\u30ce\u30b5\u30ef"
    ],
    "wof:name":"Nishinosawa",
    "wof:placetype":"locality"
},
  "geometry": {"coordinates":[139.88681,35.10072],"type":"Point"}
}