{
  "type": "Feature",
  "properties": {
    "gn:admin1_code":"16.0",
    "gn:admin2_code":"2128940.0",
    "gn:asciiname":"Odaigahara",
    "gn:country_code":"JP",
    "gn:dem":284,
    "gn:feature_class":"P",
    "gn:feature_code":"PPL",
    "gn:name":"\u014cdaigahara",
    "gn:population":0,
    "gn:timezone":"Asia/Tokyo",
    "iso:country":"JP",
    "name:jpn_x_preferred":[
        "\u5927\u5e73\u30f6\u539f"
    ],
    "name:jpn_x_variant":[
        "\u304a\u304a\u3060\u3044\u304c\u306f\u3089",
        "\u30aa\u30aa\u30c0\u30a4\u30ac\u30cf\u30e9"
    ],
    "name:und_x_variant":[
        "\u014cdaigahara"
    ],
    "wof:name":"Odaigahara",
    "wof:placetype":"locality"
},
  "geometry": {"coordinates":[141.16606000000004,40.30163],"type":"Point"}
}