{
  "type": "Feature",
  "properties": {
    "gn:admin1_code":"18.0",
    "gn:admin2_code":"7383991.0",
    "gn:asciiname":"Hishikari-ichiyama",
    "gn:country_code":"JP",
    "gn:dem":178,
    "gn:feature_class":"P",
    "gn:feature_code":"PPL",
    "gn:name":"Hishikari-ichiyama",
    "gn:population":0,
    "gn:timezone":"Asia/Tokyo",
    "iso:country":"JP",
    "name:jpn_x_preferred":[
        "\u83f1\u5208\u5e02\u5c71"
    ],
    "name:jpn_x_variant":[
        "\u3072\u3057\u304b\u308a\u3044\u3061\u3084\u307e",
        "\u30d2\u30b7\u30ab\u30ea\u30a4\u30c1\u30e4\u30de"
    ],
    "wof:name":"Hishikari-ichiyama",
    "wof:placetype":"locality"
},
  "geometry": {"coordinates":[130.64341000000002,32.04808],"type":"Point"}
}