{
  "type": "Feature",
  "properties": {
    "gn:admin1_code":"4.0",
    "gn:admin2_code":"1864901.0",
    "gn:admin3_code":"12463.0",
    "gn:asciiname":"Mizunodai",
    "gn:country_code":"JP",
    "gn:dem":186,
    "gn:feature_class":"P",
    "gn:feature_code":"PPLL",
    "gn:name":"Mizunodai",
    "gn:population":0,
    "gn:timezone":"Asia/Tokyo",
    "iso:country":"JP",
    "name:jpn_x_preferred":[
        "\u6c34\u30ce\u53f0"
    ],
    "name:jpn_x_variant":[
        "\u307f\u305a\u306e\u3060\u3044",
        "\u30df\u30ba\u30ce\u30c0\u30a4"
    ],
    "wof:name":"Mizunodai",
    "wof:placetype":"locality"
},
  "geometry": {"coordinates":[139.9222,35.1357],"type":"Point"}
}