{
  "type": "Feature",
  "properties": {
    "gn:admin1_code":"4.0",
    "gn:admin2_code":"1859468.0",
    "gn:asciiname":"Okuda",
    "gn:country_code":"JP",
    "gn:dem":61,
    "gn:feature_class":"P",
    "gn:feature_code":"PPLL",
    "gn:name":"Okuda",
    "gn:population":0,
    "gn:timezone":"Asia/Tokyo",
    "iso:country":"JP",
    "name:jpn_x_preferred":[
        "\u5965\u7530"
    ],
    "name:jpn_x_variant":[
        "\u304a\u304f\u3060",
        "\u30aa\u30af\u30c0"
    ],
    "wof:name":"Okuda",
    "wof:placetype":"locality"
},
  "geometry": {"coordinates":[140.08004,35.32045],"type":"Point"}
}