{
  "type": "Feature",
  "properties": {
    "gn:admin1_code":"34.0",
    "gn:admin2_code":"8304213.0",
    "gn:asciiname":"Guya",
    "gn:country_code":"JP",
    "gn:dem":6,
    "gn:feature_class":"P",
    "gn:feature_code":"PPLL",
    "gn:name":"Guya",
    "gn:population":0,
    "gn:timezone":"Asia/Tokyo",
    "iso:country":"JP",
    "name:jpn_x_preferred":[
        "\u4e94\u5c4b"
    ],
    "wof:name":"Guya",
    "wof:placetype":"locality"
},
  "geometry": {"coordinates":[139.77860000000001,35.97027999999999],"type":"Point"}
}