{
  "type": "Feature",
  "properties": {
    "gn:admin1_code":"15.0",
    "gn:admin2_code":"1854977.0",
    "gn:asciiname":"Tokumotomachi",
    "gn:country_code":"JP",
    "gn:dem":19,
    "gn:feature_class":"P",
    "gn:feature_code":"PPL",
    "gn:name":"Tokumotomachi",
    "gn:population":0,
    "gn:timezone":"Asia/Tokyo",
    "iso:country":"JP",
    "name:jpn_x_preferred":[
        "\u5fb3\u7528\u753a"
    ],
    "wof:name":"Tokumotomachi",
    "wof:placetype":"locality"
},
  "geometry": {"coordinates":[136.59195,36.53406],"type":"Point"}
}