{
  "type": "Feature",
  "properties": {
    "gn:admin1_code":"7.0",
    "gn:admin2_code":"1863955.0",
    "gn:admin3_code":"40135.0",
    "gn:asciiname":"Taromaru",
    "gn:country_code":"JP",
    "gn:dem":-8,
    "gn:feature_class":"P",
    "gn:feature_code":"PPL",
    "gn:name":"Tar\u014dmaru",
    "gn:population":0,
    "gn:timezone":"Asia/Tokyo",
    "iso:country":"JP",
    "name:jpn_x_preferred":[
        "\u592a\u90ce\u4e38"
    ],
    "name:und_x_variant":[
        "Tar\u014dmaru"
    ],
    "wof:name":"Taromaru",
    "wof:placetype":"locality"
},
  "geometry": {"coordinates":[130.23738,33.58768],"type":"Point"}
}