{
  "type": "Feature",
  "properties": {
    "gn:admin1_code":"12.0",
    "gn:admin2_code":"7428107.0",
    "gn:admin3_code":"1693.0",
    "gn:asciiname":"Kotanuka",
    "gn:cc2":"JP",
    "gn:country_code":"JP",
    "gn:dem":69,
    "gn:feature_class":"P",
    "gn:feature_code":"PPL",
    "gn:name":"Kotanuka",
    "gn:population":0,
    "gn:timezone":"Asia/Tokyo",
    "iso:country":"JP",
    "name:und_x_variant":[
        "Churuigenya"
    ],
    "wof:name":"Kotanuka",
    "wof:placetype":"locality"
},
  "geometry": {"coordinates":[145.03043,43.74927],"type":"Point"}
}