{
  "type": "Feature",
  "properties": {
    "iso:country":"JP",
    "name:eng_x_preferred":[
        "Ka 5 Chome"
    ],
    "name:eng_x_variant":[
        "Ka 5 Choume",
        "Ka 5 Chome"
    ],
    "name:jpn_x_preferred":[
        "\uff15\u4e01\u76ee"
    ],
    "name:jpn_x_variant":[
        "\u304b \uff15\u3061\u3087\u3046\u3081",
        "\u52a0 \uff15\u4e01\u76ee",
        "\uff15\u3061\u3087\u3046\u3081"
    ],
    "qs:gn_local":0,
    "qs:local_max":164,
    "qs:local_sum":643,
    "qs:localhoods":8,
    "qs:name":"\uff15\u4e01\u76ee",
    "qs:name_adm0":"\u65e5\u672c",
    "qs:name_adm1":"\u5343\u8449\u770c",
    "qs:name_en":"Ka 5 Chome",
    "qs:name_lau":"\u52a0",
    "qs:name_local":"\u6d41\u5c71\u5e02",
    "qs:photo_max":10,
    "qs:photo_sum":14,
    "qs:placetype":"Suburb",
    "qs:quad_count":3,
    "qs:woe_adm0":23424856,
    "qs:woe_adm1":2345854,
    "qs:woe_adm2":0,
    "qs:woe_lau":28412318,
    "qs:woe_local":1112344,
    "qs:woe_ver":"7.10.0",
    "wof:lang":[
        "jpn"
    ],
    "wof:name":"\uff15\u4e01\u76ee",
    "wof:placetype":"neighbourhood"
},
  "geometry": {"coordinates":[139.89636899999999,35.86457],"type":"Point"}
}