{
  "type": "Feature",
  "properties": {
    "gn:admin1_code":"19.0",
    "gn:admin2_code":"1864091.0",
    "gn:asciiname":"Miyanoshita",
    "gn:country_code":"JP",
    "gn:dem":42,
    "gn:feature_class":"P",
    "gn:feature_code":"PPLL",
    "gn:name":"Miyanoshita",
    "gn:population":0,
    "gn:timezone":"Asia/Tokyo",
    "iso:country":"JP",
    "name:jpn_x_preferred":[
        "\u5bae\u30ce\u4e0b"
    ],
    "wof:name":"Miyanoshita",
    "wof:placetype":"locality"
},
  "geometry": {"coordinates":[139.49825000000001,35.35332000000001],"type":"Point"}
}