{
  "type": "Feature",
  "properties": {
    "gn:admin1_code":"33",
    "gn:asciiname":"Katsumotocho-tateishi-nishifure",
    "gn:country_code":"JP",
    "gn:dem":83,
    "gn:feature_class":"P",
    "gn:feature_code":"PPL",
    "gn:name":"Katsumotoch\u014d-tateishi-nishifure",
    "gn:population":0,
    "gn:timezone":"Asia/Tokyo",
    "iso:country":"JP",
    "name:jpn_x_preferred":[
        "\u52dd\u672c\u753a\u7acb\u77f3\u897f\u89e6"
    ],
    "name:und_x_variant":[
        "Nishi-bure",
        "Nishi-fure",
        "Katsumotoch\u014d-tateishi-nishifure"
    ],
    "wof:name":"Katsumotocho-tateishi-nishifure",
    "wof:placetype":"locality"
},
  "geometry": {"coordinates":[129.67962,33.80154],"type":"Point"}
}