{
  "type": "Feature",
  "properties": {
    "gn:admin1_code":"21.0",
    "gn:admin2_code":"7412706.0",
    "gn:admin3_code":"43447.0",
    "gn:asciiname":"Mantan",
    "gn:country_code":"JP",
    "gn:dem":448,
    "gn:feature_class":"P",
    "gn:feature_code":"PPLL",
    "gn:name":"Mantan",
    "gn:population":0,
    "gn:timezone":"Asia/Tokyo",
    "iso:country":"JP",
    "name:jpn_x_preferred":[
        "\u4e07\u8c37"
    ],
    "name:jpn_x_variant":[
        "\u307e\u3093\u305f\u3093",
        "\u30de\u30f3\u30bf\u30f3"
    ],
    "name:und_x_variant":[
        "Mantani"
    ],
    "wof:name":"Mantan",
    "wof:placetype":"locality"
},
  "geometry": {"coordinates":[130.92856,32.70779],"type":"Point"}
}