{
  "type": "Feature",
  "properties": {
    "gn:admin1_code":"3.0",
    "gn:admin2_code":"2128302.0",
    "gn:admin3_code":"2450.0",
    "gn:asciiname":"Matsukida",
    "gn:country_code":"JP",
    "gn:dem":125,
    "gn:feature_class":"P",
    "gn:feature_code":"PPL",
    "gn:name":"Matsukida",
    "gn:population":0,
    "gn:timezone":"Asia/Tokyo",
    "iso:country":"JP",
    "name:jpn_x_preferred":[
        "\u677e\u6728\u7530"
    ],
    "name:jpn_x_variant":[
        "\u307e\u3064\u304d\u3060",
        "\u30de\u30c4\u30ad\u30c0"
    ],
    "wof:name":"Matsukida",
    "wof:placetype":"locality"
},
  "geometry": {"coordinates":[141.19135,40.46943],"type":"Point"}
}