{
  "type": "Feature",
  "properties": {
    "gn:admin1_code":"21.0",
    "gn:admin2_code":"1848441.0",
    "gn:asciiname":"Hachimancho",
    "gn:country_code":"JP",
    "gn:dem":2,
    "gn:feature_class":"P",
    "gn:feature_code":"PPL",
    "gn:name":"Hachimanch\u014d",
    "gn:population":0,
    "gn:timezone":"Asia/Tokyo",
    "iso:country":"JP",
    "name:jpn_x_preferred":[
        "\u516b\u5e61\u753a"
    ],
    "name:jpn_x_variant":[
        "\u306f\u3061\u307e\u3093\u3061\u3087\u3046",
        "\u30cf\u30c1\u30de\u30f3\u30c1\u30e7\u30a6"
    ],
    "name:und_x_variant":[
        "Hachimanch\u014d"
    ],
    "wof:name":"Hachimancho",
    "wof:placetype":"locality"
},
  "geometry": {"coordinates":[130.59133,32.5058],"type":"Point"}
}