{
  "type": "Feature",
  "properties": {
    "gn:admin1_code":"3.0",
    "gn:admin2_code":"8534376.0",
    "gn:admin3_code":"2321.0",
    "gn:asciiname":"Matsudaimachi",
    "gn:country_code":"JP",
    "gn:dem":232,
    "gn:feature_class":"P",
    "gn:feature_code":"PPL",
    "gn:name":"Matsudaimachi",
    "gn:population":0,
    "gn:timezone":"Asia/Tokyo",
    "iso:country":"JP",
    "name:jpn_x_preferred":[
        "\u677e\u4ee3\u753a"
    ],
    "name:jpn_x_variant":[
        "\u307e\u3064\u3060\u3044\u307e\u3061",
        "\u30de\u30c4\u30c0\u30a4\u30de\u30c1"
    ],
    "wof:name":"Matsudaimachi",
    "wof:placetype":"locality"
},
  "geometry": {"coordinates":[140.22657000000001,40.67662],"type":"Point"}
}