{
  "type": "Feature",
  "properties": {
    "gn:admin1_code":"37.0",
    "gn:admin2_code":"1851401.0",
    "gn:admin3_code":"22344.0",
    "gn:asciiname":"Fujimagari",
    "gn:country_code":"JP",
    "gn:dem":314,
    "gn:feature_class":"P",
    "gn:feature_code":"PPL",
    "gn:name":"Fujimagari",
    "gn:population":0,
    "gn:timezone":"Asia/Tokyo",
    "iso:country":"JP",
    "name:jpn_x_preferred":[
        "\u85e4\u66f2"
    ],
    "wof:name":"Fujimagari",
    "wof:placetype":"locality"
},
  "geometry": {"coordinates":[138.98336,35.3633],"type":"Point"}
}