{
  "type": "Feature",
  "properties": {
    "gn:admin1_code":"13",
    "gn:admin2_code":"1851005.0",
    "gn:asciiname":"Ihozaki",
    "gn:country_code":"JP",
    "gn:dem":1,
    "gn:feature_class":"P",
    "gn:feature_code":"PPL",
    "gn:name":"Ihozaki",
    "gn:population":0,
    "gn:timezone":"Asia/Tokyo",
    "iso:country":"JP",
    "name:jpn_x_preferred":[
        "\u4f0a\u4fdd\u5d0e"
    ],
    "name:und_x_variant":[
        "Ihosaki",
        "Iosaki",
        "Ihozaki"
    ],
    "wof:name":"Ihozaki",
    "wof:placetype":"locality"
},
  "geometry": {"coordinates":[134.78278,34.77386],"type":"Point"}
}