{
  "type": "Feature",
  "properties": {
    "gn:admin1_code":"7.0",
    "gn:admin2_code":"1859306.0",
    "gn:admin3_code":"40101.0",
    "gn:asciiname":"Hamamachi",
    "gn:country_code":"JP",
    "gn:dem":2,
    "gn:feature_class":"P",
    "gn:feature_code":"PPL",
    "gn:name":"Hamamachi",
    "gn:population":0,
    "gn:timezone":"Asia/Tokyo",
    "iso:country":"JP",
    "name:jpn_x_preferred":[
        "\u6d5c\u753a"
    ],
    "wof:name":"Hamamachi",
    "wof:placetype":"locality"
},
  "geometry": {"coordinates":[130.96673999999999,33.94875],"type":"Point"}
}