{
  "type": "Feature",
  "properties": {
    "gn:admin1_code":"07",
    "gn:admin2_code":"1851269.0",
    "gn:admin3_code":"40602.0",
    "gn:asciiname":"Hikosan",
    "gn:country_code":"JP",
    "gn:dem":534,
    "gn:feature_class":"P",
    "gn:feature_code":"PPL",
    "gn:name":"Hikosan",
    "gn:population":0,
    "gn:timezone":"Asia/Tokyo",
    "iso:country":"JP",
    "name:jpn_x_preferred":[
        "\u82f1\u5f66\u5c71"
    ],
    "wof:name":"Hikosan",
    "wof:placetype":"locality"
},
  "geometry": {"coordinates":[130.90000000000001,33.48333],"type":"Point"}
}