{
  "type": "Feature",
  "properties": {
    "gn:admin1_code":"24.0",
    "gn:admin2_code":"2111147.0",
    "gn:admin3_code":"4104.0",
    "gn:asciiname":"Nojiri",
    "gn:country_code":"JP",
    "gn:dem":392,
    "gn:feature_class":"P",
    "gn:feature_code":"PPLL",
    "gn:name":"Nojiri",
    "gn:population":0,
    "gn:timezone":"Asia/Tokyo",
    "iso:country":"JP",
    "name:jpn_x_preferred":[
        "\u91ce\u5c3b"
    ],
    "name:por_x_preferred":[
        "Nojiri"
    ],
    "wof:name":"Nojiri",
    "wof:placetype":"locality"
},
  "geometry": {"coordinates":[140.57221999999999,38.26861],"type":"Point"}
}