{
  "type": "Feature",
  "properties": {
    "gn:admin1_code":"24.0",
    "gn:admin2_code":"2112574.0",
    "gn:asciiname":"Kitakamicho-jusanhama",
    "gn:country_code":"JP",
    "gn:dem":38,
    "gn:feature_class":"P",
    "gn:feature_code":"PPL",
    "gn:name":"Kitakamich\u014d-j\u016bsanhama",
    "gn:population":0,
    "gn:timezone":"Asia/Tokyo",
    "iso:country":"JP",
    "name:jpn_x_preferred":[
        "\u5317\u4e0a\u753a\u5341\u4e09\u6d5c"
    ],
    "name:und_x_variant":[
        "Kitakamich\u014d-j\u016bsanhama",
        "Kitakami"
    ],
    "wof:name":"Kitakamicho-jusanhama",
    "wof:placetype":"locality"
},
  "geometry": {"coordinates":[141.46132,38.58574],"type":"Point"}
}