{
  "type": "Feature",
  "properties": {
    "gn:admin1_code":"19.0",
    "gn:admin2_code":"1864091.0",
    "gn:asciiname":"Tsuzukiyama",
    "gn:country_code":"JP",
    "gn:dem":38,
    "gn:feature_class":"P",
    "gn:feature_code":"PPLL",
    "gn:name":"Tsuzukiyama",
    "gn:population":0,
    "gn:timezone":"Asia/Tokyo",
    "iso:country":"JP",
    "name:jpn_x_preferred":[
        "\u90fd\u7bc9\u5c71"
    ],
    "wof:name":"Tsuzukiyama",
    "wof:placetype":"locality"
},
  "geometry": {"coordinates":[139.43136999999999,35.376],"type":"Point"}
}