{
  "type": "Feature",
  "properties": {
    "gn:admin1_code":"2.0",
    "gn:admin2_code":"2129594.0",
    "gn:admin3_code":"5303.0",
    "gn:asciiname":"Kosaka-kozan",
    "gn:country_code":"JP",
    "gn:dem":219,
    "gn:feature_class":"P",
    "gn:feature_code":"PPL",
    "gn:name":"Kosaka-k\u014dzan",
    "gn:population":0,
    "gn:timezone":"Asia/Tokyo",
    "iso:country":"JP",
    "name:jpn_x_preferred":[
        "\u5c0f\u5742\u9271\u5c71"
    ],
    "name:und_x_variant":[
        "Kosaka-k\u014dzan"
    ],
    "wof:name":"Kosaka-kozan",
    "wof:placetype":"locality"
},
  "geometry": {"coordinates":[140.74963,40.33078],"type":"Point"}
}