{
  "type": "Feature",
  "properties": {
    "gn:admin1_code":"34.0",
    "gn:admin2_code":"1848915.0",
    "gn:asciiname":"Chuo",
    "gn:country_code":"JP",
    "gn:dem":36,
    "gn:feature_class":"P",
    "gn:feature_code":"PPL",
    "gn:name":"Ch\u016b\u014d",
    "gn:population":0,
    "gn:timezone":"Asia/Tokyo",
    "iso:country":"JP",
    "name:jpn_x_preferred":[
        "Ch\u016b\u014d"
    ],
    "name:jpn_x_variant":[
        "\u4e2d\u592e",
        "\u3061\u3085\u3046\u304a\u3046",
        "\u30c1\u30e5\u30a6\u30aa\u30a6"
    ],
    "wof:name":"Chuo",
    "wof:placetype":"locality"
},
  "geometry": {"coordinates":[139.61642000000001,35.78258],"type":"Point"}
}