{
  "type": "Feature",
  "properties": {
    "gn:admin1_code":"28.0",
    "gn:admin2_code":"7411377.0",
    "gn:admin3_code":"29322.0",
    "gn:asciiname":"Zemyo",
    "gn:country_code":"JP",
    "gn:dem":402,
    "gn:feature_class":"P",
    "gn:feature_code":"PPL",
    "gn:name":"Zemy\u014d",
    "gn:population":0,
    "gn:timezone":"Asia/Tokyo",
    "iso:country":"JP",
    "name:jpn_x_preferred":[
        "\u52a9\u547d"
    ],
    "name:und_x_variant":[
        "Zemy\u014d"
    ],
    "wof:name":"Zemyo",
    "wof:placetype":"locality"
},
  "geometry": {"coordinates":[136.00918999999999,34.66068],"type":"Point"}
}