{
  "type": "Feature",
  "properties": {
    "iso:country":"JP",
    "qs:name":"\u90a3\u73c2\u5e02",
    "qs:name_adm0":"\u65e5\u672c",
    "qs:name_adm1":"\u8328\u57ce\u770c",
    "qs:photos":209,
    "qs:photos_1k":42,
    "qs:photos_9k":1,
    "qs:photos_9r":4,
    "qs:photos_all":236,
    "qs:photos_sr":4,
    "qs:placetype":"Town",
    "qs:pop_sr":"0",
    "wof:name":"\u90a3\u73c2\u5e02",
    "wof:placetype":"locality"
},
  "geometry": {"coordinates":[140.429134,36.480932],"type":"Point"}
}