{
  "type": "Feature",
  "properties": {
    "iso:country":"JP",
    "label:eng_x_preferred_longname":[
        "Hanyu City"
    ],
    "label:eng_x_preferred_placetype":[
        "city"
    ],
    "name:eng_x_preferred":[
        "Hanyu"
    ],
    "name:eng_x_variant":[
        "Hanyu City"
    ],
    "name:jpn_x_preferred":[
        "\u7fbd\u751f\u5e02"
    ],
    "qs:name":"\u7fbd\u751f\u5e02",
    "qs:name_adm0":"\u65e5\u672c",
    "qs:name_adm1":"\u57fc\u7389\u770c",
    "qs:photos":45,
    "qs:photos_1k":9,
    "qs:photos_9k":2,
    "qs:photos_9r":5,
    "qs:photos_all":346,
    "qs:photos_sr":2,
    "qs:placetype":"Town",
    "qs:pop_sr":"0",
    "wof:name":"Hanyu",
    "wof:placetype":"locality"
},
  "geometry": {"coordinates":[139.59790699999999,36.173511],"type":"Point"}
}