{
  "type": "Feature",
  "properties": {
    "gn:admin1_code":"3.0",
    "gn:admin2_code":"2130200.0",
    "gn:asciiname":"Nagase",
    "gn:country_code":"JP",
    "gn:dem":49,
    "gn:feature_class":"P",
    "gn:feature_code":"PPL",
    "gn:name":"Nagase",
    "gn:population":0,
    "gn:timezone":"Asia/Tokyo",
    "iso:country":"JP",
    "name:jpn_x_preferred":[
        "\u9577\u702c"
    ],
    "name:jpn_x_variant":[
        "\u306a\u304c\u305b",
        "\u30ca\u30ac\u30bb"
    ],
    "wof:name":"Nagase",
    "wof:placetype":"locality"
},
  "geometry": {"coordinates":[141.48828,40.42219],"type":"Point"}
}