{
  "type": "Feature",
  "properties": {
    "gn:admin1_code":"7.0",
    "gn:admin2_code":"1859306.0",
    "gn:admin3_code":"40108.0",
    "gn:asciiname":"Omiyamachi",
    "gn:country_code":"JP",
    "gn:dem":95,
    "gn:feature_class":"P",
    "gn:feature_code":"PPL",
    "gn:name":"\u014cmiyamachi",
    "gn:population":0,
    "gn:timezone":"Asia/Tokyo",
    "iso:country":"JP",
    "name:jpn_x_preferred":[
        "\u5927\u5bae\u753a"
    ],
    "name:und_x_variant":[
        "\u014cmiyamachi"
    ],
    "wof:name":"Omiyamachi",
    "wof:placetype":"locality"
},
  "geometry": {"coordinates":[130.81995000000001,33.87911],"type":"Point"}
}