{
  "type": "Feature",
  "properties": {
    "iso:country":"JP",
    "name:eng_x_preferred":[
        "Misawa 4 Chome"
    ],
    "name:eng_x_variant":[
        "Misawa 4 Choume",
        "Misawa 4 Chome"
    ],
    "name:jpn_x_preferred":[
        "\uff14\u4e01\u76ee"
    ],
    "name:jpn_x_variant":[
        "\u307f\u3055\u308f \uff14\u3061\u3087\u3046\u3081",
        "\u4e09\u6ca2 \uff14\u4e01\u76ee",
        "\uff14\u3061\u3087\u3046\u3081"
    ],
    "qs:gn_local":0,
    "qs:local_max":4098,
    "qs:local_sum":8464,
    "qs:localhoods":15,
    "qs:name":"\uff14\u4e01\u76ee",
    "qs:name_adm0":"\u65e5\u672c",
    "qs:name_adm1":"\u6771\u4eac\u90fd",
    "qs:name_en":"Misawa 4 Chome",
    "qs:name_lau":"\u4e09\u6ca2",
    "qs:name_local":"\u65e5\u91ce\u5e02",
    "qs:photo_max":219,
    "qs:photo_sum":815,
    "qs:placetype":"Suburb",
    "qs:quad_count":29,
    "qs:woe_adm0":23424856,
    "qs:woe_adm1":2345889,
    "qs:woe_adm2":0,
    "qs:woe_lau":28415174,
    "qs:woe_local":1108923,
    "qs:woe_ver":"7.10.0",
    "wof:lang":[
        "jpn"
    ],
    "wof:name":"\uff14\u4e01\u76ee",
    "wof:placetype":"neighbourhood"
},
  "geometry": {"coordinates":[139.41063399999999,35.661314],"type":"Point"}
}