{
  "type": "Feature",
  "properties": {
    "gn:admin1_code":"21.0",
    "gn:admin2_code":"7413150.0",
    "gn:asciiname":"Kawakubo",
    "gn:country_code":"JP",
    "gn:dem":73,
    "gn:feature_class":"P",
    "gn:feature_code":"PPLL",
    "gn:name":"Kawakubo",
    "gn:population":0,
    "gn:timezone":"Asia/Tokyo",
    "iso:country":"JP",
    "name:jpn_x_preferred":[
        "\u5ddd\u4e45\u4fdd"
    ],
    "name:jpn_x_variant":[
        "\u304b\u308f\u304f\u307c",
        "\u30ab\u30ef\u30af\u30dc"
    ],
    "wof:name":"Kawakubo",
    "wof:placetype":"locality"
},
  "geometry": {"coordinates":[130.71108000000001,33.07757],"type":"Point"}
}