{
  "type": "Feature",
  "properties": {
    "gn:admin1_code":"37.0",
    "gn:admin2_code":"1864104.0",
    "gn:asciiname":"Mine",
    "gn:country_code":"JP",
    "gn:dem":340,
    "gn:feature_class":"P",
    "gn:feature_code":"PPLL",
    "gn:name":"Mine",
    "gn:population":0,
    "gn:timezone":"Asia/Tokyo",
    "iso:country":"JP",
    "name:jpn_x_preferred":[
        "\u5cf0"
    ],
    "wof:name":"Mine",
    "wof:placetype":"locality"
},
  "geometry": {"coordinates":[138.60855000000001,35.28105],"type":"Point"}
}