{
  "type": "Feature",
  "properties": {
    "gn:admin1_code":"30",
    "gn:admin2_code":"7414051.0",
    "gn:asciiname":"Obirakozan",
    "gn:cc2":"JP",
    "gn:country_code":"JP",
    "gn:dem":839,
    "gn:feature_class":"P",
    "gn:feature_code":"PPL",
    "gn:name":"Obirak\u014dzan",
    "gn:population":0,
    "gn:timezone":"Asia/Tokyo",
    "iso:country":"JP",
    "name:und_x_variant":[
        "\u014cbira",
        "Ohira-k\u014dzan",
        "Obirak\u014dzan"
    ],
    "wof:name":"Obirakozan",
    "wof:placetype":"locality"
},
  "geometry": {"coordinates":[131.38333,32.81667],"type":"Point"}
}