{
  "type": "Feature",
  "properties": {
    "gn:admin1_code":"3.0",
    "gn:admin2_code":"2128302.0",
    "gn:admin3_code":"2442.0",
    "gn:asciiname":"Matsuyama",
    "gn:country_code":"JP",
    "gn:dem":81,
    "gn:feature_class":"P",
    "gn:feature_code":"PPL",
    "gn:name":"Matsuyama",
    "gn:population":0,
    "gn:timezone":"Asia/Tokyo",
    "iso:country":"JP",
    "name:jpn_x_preferred":[
        "\u677e\u5c71"
    ],
    "name:jpn_x_variant":[
        "\u307e\u3064\u3084\u307e",
        "\u30de\u30c4\u30e4\u30de"
    ],
    "wof:name":"Matsuyama",
    "wof:placetype":"locality"
},
  "geometry": {"coordinates":[141.26936000000001,40.50725],"type":"Point"}
}