{
  "type": "Feature",
  "properties": {
    "gn:admin1_code":"12.0",
    "gn:admin2_code":"7428080.0",
    "gn:admin3_code":"1512.0",
    "gn:asciiname":"Kyu-hamatombetsu",
    "gn:country_code":"JP",
    "gn:dem":0,
    "gn:feature_class":"P",
    "gn:feature_code":"PPL",
    "gn:name":"Ky\u016b-hamatombetsu",
    "gn:population":0,
    "gn:timezone":"Asia/Tokyo",
    "iso:country":"JP",
    "name:und_x_variant":[
        "Ky\u016b-hamatombetsu"
    ],
    "wof:name":"Kyu-hamatombetsu",
    "wof:placetype":"locality"
},
  "geometry": {"coordinates":[142.39028000000005,45.12111],"type":"Point"}
}