{
  "type": "Feature",
  "properties": {
    "gn:admin1_code":"14.0",
    "gn:admin2_code":"2112705.0",
    "gn:asciiname":"Okada",
    "gn:country_code":"JP",
    "gn:dem":6,
    "gn:feature_class":"P",
    "gn:feature_code":"PPL",
    "gn:name":"Okada",
    "gn:population":0,
    "gn:timezone":"Asia/Tokyo",
    "iso:country":"JP",
    "wof:name":"Okada",
    "wof:placetype":"locality"
},
  "geometry": {"coordinates":[140.55000000000001,36.51667],"type":"Point"}
}