{
  "type": "Feature",
  "properties": {
    "gn:admin1_code":"43.0",
    "gn:admin2_code":"1848936.0",
    "gn:asciiname":"Ueno",
    "gn:country_code":"JP",
    "gn:dem":11,
    "gn:feature_class":"P",
    "gn:feature_code":"PPL",
    "gn:name":"Ueno",
    "gn:population":0,
    "gn:timezone":"Asia/Tokyo",
    "iso:country":"JP",
    "name:ara_x_preferred":[
        "\u0623\u0648\u064a\u0646\u0648"
    ],
    "name:deu_x_preferred":[
        "Ueno"
    ],
    "name:epo_x_preferred":[
        "Ueno"
    ],
    "name:fas_x_preferred":[
        "\u0627\u0648\u0626\u0646\u0648"
    ],
    "name:fin_x_preferred":[
        "Ueno"
    ],
    "name:fra_x_preferred":[
        "Ueno"
    ],
    "name:hun_x_preferred":[
        "Ueno"
    ],
    "name:jpn_x_preferred":[
        "\u4e0a\u91ce"
    ],
    "name:kor_x_preferred":[
        "\uc6b0\uc5d0\ub178"
    ],
    "name:nld_x_preferred":[
        "Ueno"
    ],
    "name:spa_x_preferred":[
        "Ueno"
    ],
    "name:swe_x_preferred":[
        "Ueno"
    ],
    "name:tha_x_preferred":[
        "\u0e2d\u0e39\u0e40\u0e2d\u0e42\u0e19\u0e30"
    ],
    "name:tur_x_preferred":[
        "Ueno"
    ],
    "wof:name":"Ueno",
    "wof:placetype":"locality"
},
  "geometry": {"coordinates":[135.25128999999998,34.26699],"type":"Point"}
}