{
  "type": "Feature",
  "properties": {
    "gn:admin1_code":"12.0",
    "gn:admin2_code":"7428080.0",
    "gn:admin3_code":"1514.0",
    "gn:asciiname":"Sansen",
    "gn:country_code":"JP",
    "gn:dem":2,
    "gn:feature_class":"P",
    "gn:feature_code":"PPL",
    "gn:name":"Sansen",
    "gn:population":0,
    "gn:timezone":"Asia/Tokyo",
    "iso:country":"JP",
    "wof:name":"Sansen",
    "wof:placetype":"locality"
},
  "geometry": {"coordinates":[142.59999999999999,44.88333],"type":"Point"}
}