{
  "type": "Feature",
  "properties": {
    "gn:admin1_code":"21.0",
    "gn:admin2_code":"1848441.0",
    "gn:asciiname":"Shimokataiwa",
    "gn:country_code":"JP",
    "gn:dem":37,
    "gn:feature_class":"P",
    "gn:feature_code":"PPLL",
    "gn:name":"Shimokataiwa",
    "gn:population":0,
    "gn:timezone":"Asia/Tokyo",
    "iso:country":"JP",
    "name:jpn_x_preferred":[
        "\u4e0b\u7247\u5ca9"
    ],
    "wof:name":"Shimokataiwa",
    "wof:placetype":"locality"
},
  "geometry": {"coordinates":[130.6677,32.44041],"type":"Point"}
}