{
  "type": "Feature",
  "properties": {
    "iso:country":"JP",
    "name:eng_x_preferred":[
        "Nishishindo 4 Chome"
    ],
    "name:eng_x_variant":[
        "Nishishindo 4 Choume",
        "Nishishindo 4 Chome"
    ],
    "name:jpn_x_preferred":[
        "\uff14\u4e01\u76ee"
    ],
    "name:jpn_x_variant":[
        "\u306b\u3057\u3057\u3093\u3069 \uff14\u3061\u3087\u3046\u3081",
        "\u897f\u771f\u571f \uff14\u4e01\u76ee",
        "\uff14\u3061\u3087\u3046\u3081"
    ],
    "qs:gn_adm0_cc":"JP",
    "qs:gn_local":1862462,
    "qs:gn_nam_loc":"\u5e73\u585a\u5e02, \u795e\u5948\u5ddd\u770c, JP",
    "qs:gn_namadm1":"19",
    "qs:local_max":1157,
    "qs:local_sum":4372,
    "qs:localhoods":14,
    "qs:name":"\uff14\u4e01\u76ee",
    "qs:name_adm0":"\u65e5\u672c",
    "qs:name_adm1":"\u795e\u5948\u5ddd\u770c",
    "qs:name_en":"Nishishindo 4 Chome",
    "qs:name_lau":"\u897f\u771f\u571f",
    "qs:name_local":"\u5e73\u585a\u5e02",
    "qs:photo_max":94,
    "qs:photo_sum":1157,
    "qs:placetype":"Suburb",
    "qs:quad_count":48,
    "qs:woe_adm0":23424856,
    "qs:woe_adm1":2345868,
    "qs:woe_adm2":0,
    "qs:woe_lau":28416717,
    "qs:woe_local":1117220,
    "qs:woe_ver":"7.10.0",
    "wof:lang":[
        "jpn"
    ],
    "wof:name":"\uff14\u4e01\u76ee",
    "wof:placetype":"neighbourhood"
},
  "geometry": {"coordinates":[139.339292,35.366475],"type":"Point"}
}