{
  "type": "Feature",
  "properties": {
    "gn:admin1_code":"34.0",
    "gn:admin2_code":"1849187.0",
    "gn:admin3_code":"11107.0",
    "gn:asciiname":"Higashikishicho",
    "gn:country_code":"JP",
    "gn:dem":11,
    "gn:feature_class":"P",
    "gn:feature_code":"PPL",
    "gn:name":"Higashikishich\u014d",
    "gn:population":0,
    "gn:timezone":"Asia/Tokyo",
    "iso:country":"JP",
    "name:jpn_x_preferred":[
        "\u6771\u5cb8\u753a"
    ],
    "name:jpn_x_variant":[
        "\u3072\u304c\u3057\u304d\u3057\u3061\u3087\u3046",
        "\u30d2\u30ac\u30b7\u30ad\u30b7\u30c1\u30e7\u30a6"
    ],
    "name:und_x_variant":[
        "Higashikishich\u014d"
    ],
    "wof:name":"Higashikishicho",
    "wof:placetype":"locality"
},
  "geometry": {"coordinates":[139.66449,35.85318],"type":"Point"}
}