{
  "type": "Feature",
  "properties": {
    "gn:admin1_code":"18",
    "gn:admin2_code":"7383987.0",
    "gn:asciiname":"Sani",
    "gn:country_code":"JP",
    "gn:dem":114,
    "gn:feature_class":"P",
    "gn:feature_code":"PPL",
    "gn:name":"Sani",
    "gn:population":0,
    "gn:timezone":"Asia/Tokyo",
    "iso:country":"JP",
    "name:ceb_x_preferred":[
        "Sani"
    ],
    "name:deu_x_preferred":[
        "Sani"
    ],
    "name:fra_x_preferred":[
        "Sani"
    ],
    "name:ind_x_preferred":[
        "Sani"
    ],
    "name:ita_x_preferred":[
        "Sani"
    ],
    "name:swe_x_preferred":[
        "Sani"
    ],
    "wof:name":"Sani",
    "wof:placetype":"locality"
},
  "geometry": {"coordinates":[129.68333000000001,28.51667],"type":"Point"}
}