{
  "type": "Feature",
  "properties": {
    "gn:admin1_code":"19.0",
    "gn:admin2_code":"1848350.0",
    "gn:admin3_code":"14118.0",
    "gn:asciiname":"Kitayamata",
    "gn:country_code":"JP",
    "gn:dem":35,
    "gn:feature_class":"P",
    "gn:feature_code":"PPL",
    "gn:name":"Kitayamata",
    "gn:population":0,
    "gn:timezone":"Asia/Tokyo",
    "iso:country":"JP",
    "name:jpn_x_preferred":[
        "\u5317\u5c71\u7530"
    ],
    "wof:name":"Kitayamata",
    "wof:placetype":"locality"
},
  "geometry": {"coordinates":[139.58874,35.561],"type":"Point"}
}