{
  "type": "Feature",
  "properties": {
    "gn:admin1_code":"33",
    "gn:admin2_code":"7391363.0",
    "gn:asciiname":"Shiotacho-matsusaki",
    "gn:country_code":"JP",
    "gn:dem":4,
    "gn:feature_class":"P",
    "gn:feature_code":"PPL",
    "gn:name":"Shiotach\u014d-matsusaki",
    "gn:population":0,
    "gn:timezone":"Asia/Tokyo",
    "iso:country":"JP",
    "name:deu_x_preferred":[
        "Shiota"
    ],
    "name:fas_x_preferred":[
        "\u0634\u06cc\u0631\u0648\u062a\u0627"
    ],
    "name:jpn_x_preferred":[
        "\u5869\u7530\u753a\u771f\u5d0e"
    ],
    "name:jpn_x_variant":[
        "\u5869\u7530\u753a"
    ],
    "name:und_x_variant":[
        "Shioda",
        "Shiotach\u014d-matsusaki"
    ],
    "wof:name":"Shiotacho-matsusaki",
    "wof:placetype":"locality"
},
  "geometry": {"coordinates":[130.07144,33.12415],"type":"Point"}
}