{
  "type": "Feature",
  "properties": {
    "gn:admin1_code":"21.0",
    "gn:admin2_code":"7412708.0",
    "gn:admin3_code":"43513.0",
    "gn:asciiname":"Konose",
    "gn:country_code":"JP",
    "gn:dem":306,
    "gn:feature_class":"P",
    "gn:feature_code":"PPL",
    "gn:name":"K\u014dnose",
    "gn:population":0,
    "gn:timezone":"Asia/Tokyo",
    "iso:country":"JP",
    "name:jpn_x_preferred":[
        "\u795e\u702c"
    ],
    "name:jpn_x_variant":[
        "\u3053\u3046\u306e\u305b",
        "\u30b3\u30a6\u30ce\u30bb"
    ],
    "name:und_x_variant":[
        "K\u014dnose"
    ],
    "wof:name":"Konose",
    "wof:placetype":"locality"
},
  "geometry": {"coordinates":[130.63679999999999,32.3295],"type":"Point"}
}