{
  "type": "Feature",
  "properties": {
    "gn:admin1_code":"12.0",
    "gn:admin2_code":"7428121.0",
    "gn:admin3_code":"1586.0",
    "gn:asciiname":"Hobetsu-osawa",
    "gn:country_code":"JP",
    "gn:dem":274,
    "gn:feature_class":"P",
    "gn:feature_code":"PPL",
    "gn:name":"Hobetsu-osawa",
    "gn:population":0,
    "gn:timezone":"Asia/Tokyo",
    "iso:country":"JP",
    "name:jpn_x_preferred":[
        "\u7a42\u5225\u9577\u548c"
    ],
    "wof:name":"Hobetsu-osawa",
    "wof:placetype":"locality"
},
  "geometry": {"coordinates":[142.20191,42.93600000000001],"type":"Point"}
}