{
  "type": "Feature",
  "properties": {
    "gn:admin1_code":"40.0",
    "gn:admin2_code":"1853655.0",
    "gn:asciiname":"Chuo",
    "gn:country_code":"JP",
    "gn:dem":10,
    "gn:feature_class":"P",
    "gn:feature_code":"PPL",
    "gn:name":"Ch\u016b\u014d",
    "gn:population":0,
    "gn:timezone":"Asia/Tokyo",
    "iso:country":"JP",
    "name:jpn_x_preferred":[
        "\u4e2d\u592e"
    ],
    "name:und_x_variant":[
        "Ch\u016b\u014d"
    ],
    "wof:name":"Chuo",
    "wof:placetype":"locality"
},
  "geometry": {"coordinates":[139.71684999999999,35.57779],"type":"Point"}
}