{
  "type": "Feature",
  "properties": {
    "gn:admin1_code":"3.0",
    "gn:admin2_code":"2130088.0",
    "gn:admin3_code":"2304.0",
    "gn:asciiname":"Namigaeshi",
    "gn:country_code":"JP",
    "gn:dem":4,
    "gn:feature_class":"P",
    "gn:feature_code":"PPL",
    "gn:name":"Namigaeshi",
    "gn:population":0,
    "gn:timezone":"Asia/Tokyo",
    "iso:country":"JP",
    "name:jpn_x_preferred":[
        "\u6d6a\u8fd4"
    ],
    "name:jpn_x_variant":[
        "\u306a\u307f\u304c\u3048\u3057",
        "\u30ca\u30df\u30ac\u30a8\u30b7"
    ],
    "wof:name":"Namigaeshi",
    "wof:placetype":"locality"
},
  "geometry": {"coordinates":[140.65836999999999,40.95364],"type":"Point"}
}