{
  "type": "Feature",
  "properties": {
    "iso:country":"JP",
    "name:eng_x_preferred":[
        "Azamino 2 Chome"
    ],
    "name:eng_x_variant":[
        "Azamino 2 Choume",
        "Azamino 2 Chome"
    ],
    "name:jpn_x_preferred":[
        "\uff12\u4e01\u76ee"
    ],
    "name:jpn_x_variant":[
        "\u3042\u3056\u307f\u306e \uff12\u3061\u3087\u3046\u3081",
        "\u3042\u3056\u307f\u91ce \uff12\u4e01\u76ee",
        "\uff12\u3061\u3087\u3046\u3081"
    ],
    "qs:gn_local":0,
    "qs:local_max":6208,
    "qs:local_sum":82309,
    "qs:localhoods":190,
    "qs:name":"\uff12\u4e01\u76ee",
    "qs:name_adm0":"\u65e5\u672c",
    "qs:name_adm1":"\u795e\u5948\u5ddd\u770c",
    "qs:name_adm2":"\u9752\u8449\u533a",
    "qs:name_en":"Azamino 2 Chome",
    "qs:name_lau":"\u3042\u3056\u307f\u91ce",
    "qs:name_local":"\u6a2a\u6d5c\u5e02",
    "qs:photo_max":20,
    "qs:photo_sum":20,
    "qs:placetype":"Suburb",
    "qs:quad_count":1,
    "qs:woe_adm0":23424856,
    "qs:woe_adm1":2345868,
    "qs:woe_adm2":15015376,
    "qs:woe_lau":28416188,
    "qs:woe_local":1118550,
    "qs:woe_ver":"7.10.0",
    "wof:lang":[
        "jpn"
    ],
    "wof:name":"\uff12\u4e01\u76ee",
    "wof:placetype":"neighbourhood"
},
  "geometry": {"coordinates":[139.545593,35.570213],"type":"Point"}
}