{
  "type": "Feature",
  "properties": {
    "gn:admin1_code":"25",
    "gn:admin2_code":"1862036.0",
    "gn:asciiname":"Tomitaka",
    "gn:cc2":"JP",
    "gn:country_code":"JP",
    "gn:dem":5,
    "gn:feature_class":"P",
    "gn:feature_code":"PPL",
    "gn:name":"Tomitaka",
    "gn:population":0,
    "gn:timezone":"Asia/Tokyo",
    "iso:country":"JP",
    "name:und_x_variant":[
        "Tomishima",
        "Tomitaka"
    ],
    "wof:name":"Tomitaka",
    "wof:placetype":"locality"
},
  "geometry": {"coordinates":[131.63333,32.41667],"type":"Point"}
}