{
  "type": "Feature",
  "properties": {
    "gn:admin1_code":"42.0",
    "gn:admin2_code":"1849870.0",
    "gn:asciiname":"Fuchumachi-naruko",
    "gn:country_code":"JP",
    "gn:dem":47,
    "gn:feature_class":"P",
    "gn:feature_code":"PPL",
    "gn:name":"Fuch\u016bmachi-naruko",
    "gn:population":0,
    "gn:timezone":"Asia/Tokyo",
    "iso:country":"JP",
    "name:jpn_x_preferred":[
        "\u5a66\u4e2d\u753a\u6210\u5b50"
    ],
    "name:und_x_variant":[
        "Fuch\u016bmachi-naruko"
    ],
    "wof:name":"Fuchumachi-naruko",
    "wof:placetype":"locality"
},
  "geometry": {"coordinates":[137.1798,36.61296],"type":"Point"}
}