{
  "type": "Feature",
  "properties": {
    "gn:admin1_code":"16.0",
    "gn:admin2_code":"2129400.0",
    "gn:admin3_code":"3506.0",
    "gn:asciiname":"Ibonai",
    "gn:country_code":"JP",
    "gn:dem":283,
    "gn:feature_class":"P",
    "gn:feature_code":"PPL",
    "gn:name":"Ibonai",
    "gn:population":0,
    "gn:timezone":"Asia/Tokyo",
    "iso:country":"JP",
    "name:jpn_x_preferred":[
        "\u4f0a\u4fdd\u5185"
    ],
    "name:jpn_x_variant":[
        "\u3044\u307c\u306a\u3044",
        "\u30a4\u30dc\u30ca\u30a4"
    ],
    "wof:name":"Ibonai",
    "wof:placetype":"locality"
},
  "geometry": {"coordinates":[141.42445000000001,40.20871],"type":"Point"}
}