{
  "type": "Feature",
  "properties": {
    "gn:admin1_code":"35.0",
    "gn:admin2_code":"1858984.0",
    "gn:asciiname":"Tsuchiyamacho-tongu",
    "gn:country_code":"JP",
    "gn:dem":231,
    "gn:feature_class":"P",
    "gn:feature_code":"PPL",
    "gn:name":"Tsuchiyamach\u014d-tong\u016b",
    "gn:population":0,
    "gn:timezone":"Asia/Tokyo",
    "iso:country":"JP",
    "name:jpn_x_preferred":[
        "\u571f\u5c71\u753a\u9813\u5bae"
    ],
    "name:und_x_variant":[
        "Tsuchiyamach\u014d-tong\u016b"
    ],
    "wof:name":"Tsuchiyamacho-tongu",
    "wof:placetype":"locality"
},
  "geometry": {"coordinates":[136.25788,34.94294],"type":"Point"}
}