{
  "type": "Feature",
  "properties": {
    "iso:country":"JP",
    "label:eng_x_preferred_longname":[
        "Kiyotake Town"
    ],
    "label:eng_x_preferred_placetype":[
        "town"
    ],
    "name:eng_x_preferred":[
        "Kiyotake"
    ],
    "name:eng_x_variant":[
        "Kiyotake Town"
    ],
    "name:jpn_x_preferred":[
        "\u6e05\u6b66\u753a"
    ],
    "qs:name":"\u6e05\u6b66\u753a",
    "qs:name_adm0":"\u65e5\u672c",
    "qs:name_adm1":"\u5bae\u5d0e\u770c",
    "qs:photos":11,
    "qs:photos_1k":2,
    "qs:photos_9k":1,
    "qs:photos_9r":2,
    "qs:photos_all":33,
    "qs:photos_sr":1,
    "qs:placetype":"Town",
    "qs:pop_sr":"0",
    "wof:name":"Kiyotake",
    "wof:placetype":"locality"
},
  "geometry": {"coordinates":[131.41364999999999,31.81861],"type":"Point"}
}