{
  "type": "Feature",
  "properties": {
    "gn:admin1_code":"4.0",
    "gn:admin2_code":"2112663.0",
    "gn:asciiname":"Soja",
    "gn:country_code":"JP",
    "gn:dem":12,
    "gn:feature_class":"P",
    "gn:feature_code":"PPL",
    "gn:name":"S\u014dja",
    "gn:population":0,
    "gn:timezone":"Asia/Tokyo",
    "iso:country":"JP",
    "name:jpn_x_preferred":[
        "\u60e3\u793e"
    ],
    "name:jpn_x_variant":[
        "\u305d\u3046\u3058\u3083",
        "\u30bd\u30a6\u30b8\u30e3"
    ],
    "name:und_x_variant":[
        "S\u014dja"
    ],
    "wof:name":"Soja",
    "wof:placetype":"locality"
},
  "geometry": {"coordinates":[140.10713999999999,35.49612],"type":"Point"}
}