{
  "type": "Feature",
  "properties": {
    "gn:admin1_code":"29.0",
    "gn:admin2_code":"7468182.0",
    "gn:asciiname":"Araihama",
    "gn:country_code":"JP",
    "gn:dem":11,
    "gn:feature_class":"P",
    "gn:feature_code":"PPL",
    "gn:name":"Araihama",
    "gn:population":0,
    "gn:timezone":"Asia/Tokyo",
    "iso:country":"JP",
    "name:jpn_x_preferred":[
        "\u8352\u4e95\u6d5c"
    ],
    "wof:name":"Araihama",
    "wof:placetype":"locality"
},
  "geometry": {"coordinates":[139.38123000000002,38.11104],"type":"Point"}
}