{
  "type": "Feature",
  "properties": {
    "iso:country":"JP",
    "name:eng_x_preferred":[
        "Hiraya Village"
    ],
    "name:jpn_x_preferred":[
        "\u5e73\u8c37\u6751"
    ],
    "qs:name":"\u5e73\u8c37\u6751",
    "qs:name_adm0":"\u65e5\u672c",
    "qs:name_adm1":"\u9577\u91ce\u770c",
    "qs:photos":62,
    "qs:photos_1k":13,
    "qs:photos_9k":1,
    "qs:photos_9r":2,
    "qs:photos_all":62,
    "qs:photos_sr":2,
    "qs:placetype":"Town",
    "qs:pop_sr":"0",
    "wof:name":"Hiraya Village",
    "wof:placetype":"locality"
},
  "geometry": {"coordinates":[137.62987799999999,35.321148],"type":"Point"}
}