{
  "type": "Feature",
  "properties": {
    "gn:admin1_code":"12.0",
    "gn:admin2_code":"7428104.0",
    "gn:admin3_code":"1370.0",
    "gn:asciiname":"Imagane",
    "gn:cc2":"JP",
    "gn:country_code":"JP",
    "gn:dem":18,
    "gn:feature_class":"P",
    "gn:feature_code":"PPL",
    "gn:name":"Imagane",
    "gn:population":0,
    "gn:timezone":"Asia/Tokyo",
    "iso:country":"JP",
    "name:und_x_variant":[
        "Imakane",
        "Imagane"
    ],
    "wof:name":"Imagane",
    "wof:placetype":"locality"
},
  "geometry": {"coordinates":[140.00861,42.42306],"type":"Point"}
}