{
  "type": "Feature",
  "properties": {
    "gn:admin1_code":"34.0",
    "gn:admin2_code":"1859739.0",
    "gn:asciiname":"Kitatajima",
    "gn:country_code":"JP",
    "gn:dem":13,
    "gn:feature_class":"P",
    "gn:feature_code":"PPL",
    "gn:name":"Kitatajima",
    "gn:population":0,
    "gn:timezone":"Asia/Tokyo",
    "iso:country":"JP",
    "name:jpn_x_preferred":[
        "\u5317\u7530\u5cf6"
    ],
    "name:jpn_x_variant":[
        "\u304d\u305f\u305f\u3058\u307e",
        "\u30ad\u30bf\u30bf\u30b8\u30de"
    ],
    "wof:name":"Kitatajima",
    "wof:placetype":"locality"
},
  "geometry": {"coordinates":[139.50194999999999,35.93616],"type":"Point"}
}