{
  "type": "Feature",
  "properties": {
    "gn:admin1_code":"19.0",
    "gn:admin2_code":"7470890.0",
    "gn:asciiname":"Hinata",
    "gn:country_code":"JP",
    "gn:dem":42,
    "gn:feature_class":"P",
    "gn:feature_code":"PPLL",
    "gn:name":"Hinata",
    "gn:population":0,
    "gn:timezone":"Asia/Tokyo",
    "iso:country":"JP",
    "name:fra_x_preferred":[
        "Hinata"
    ],
    "name:jpn_x_preferred":[
        "\u65e5\u5411"
    ],
    "name:jpn_x_variant":[
        "\u3072\u306a\u305f"
    ],
    "name:pol_x_preferred":[
        "Hinata"
    ],
    "wof:name":"Hinata",
    "wof:placetype":"locality"
},
  "geometry": {"coordinates":[139.11953,35.30332],"type":"Point"}
}