{
  "type": "Feature",
  "properties": {
    "gn:admin1_code":"28.0",
    "gn:admin2_code":"7411377.0",
    "gn:admin3_code":"29322.0",
    "gn:asciiname":"Katahira",
    "gn:country_code":"JP",
    "gn:dem":298,
    "gn:feature_class":"P",
    "gn:feature_code":"PPL",
    "gn:name":"Katahira",
    "gn:population":0,
    "gn:timezone":"Asia/Tokyo",
    "iso:country":"JP",
    "name:jpn_x_preferred":[
        "\u7247\u5e73"
    ],
    "wof:name":"Katahira",
    "wof:placetype":"locality"
},
  "geometry": {"coordinates":[136.06788999999998,34.67058],"type":"Point"}
}