{
  "type": "Feature",
  "properties": {
    "gn:admin1_code":"25",
    "gn:admin2_code":"1858035.0",
    "gn:asciiname":"Ishikida",
    "gn:country_code":"JP",
    "gn:dem":15,
    "gn:feature_class":"P",
    "gn:feature_code":"PPL",
    "gn:name":"Ishikida",
    "gn:population":0,
    "gn:timezone":"Asia/Tokyo",
    "iso:country":"JP",
    "name:jpn_x_preferred":[
        "\u77f3\u6728\u7530"
    ],
    "wof:name":"Ishikida",
    "wof:placetype":"locality"
},
  "geometry": {"coordinates":[131.25298999999998,31.50608],"type":"Point"}
}