{
  "type": "Feature",
  "properties": {
    "gn:admin1_code":"33.0",
    "gn:admin2_code":"1854650.0",
    "gn:asciiname":"Mikatsukicho-chokanda",
    "gn:country_code":"JP",
    "gn:dem":14,
    "gn:feature_class":"P",
    "gn:feature_code":"PPL",
    "gn:name":"Mikatsukich\u014d-ch\u014dkanda",
    "gn:population":0,
    "gn:timezone":"Asia/Tokyo",
    "iso:country":"JP",
    "name:jpn_x_preferred":[
        "\u4e09\u65e5\u6708\u753a\u9577\u795e\u7530"
    ],
    "name:und_x_variant":[
        "Mikatsukich\u014d-ch\u014dkanda"
    ],
    "wof:name":"Mikatsukicho-chokanda",
    "wof:placetype":"locality"
},
  "geometry": {"coordinates":[130.21780000000001,33.28896],"type":"Point"}
}