{
  "type": "Feature",
  "properties": {
    "gn:admin1_code":"2.0",
    "gn:admin2_code":"7443156.0",
    "gn:asciiname":"Ani-kobuchi",
    "gn:country_code":"JP",
    "gn:dem":89,
    "gn:feature_class":"P",
    "gn:feature_code":"PPL",
    "gn:name":"Ani-kobuchi",
    "gn:population":0,
    "gn:timezone":"Asia/Tokyo",
    "iso:country":"JP",
    "name:jpn_x_preferred":[
        "\u963f\u4ec1\u5c0f\u6e15"
    ],
    "wof:name":"Ani-kobuchi",
    "wof:placetype":"locality"
},
  "geometry": {"coordinates":[140.40162000000001,40.03214000000001],"type":"Point"}
}