{
  "type": "Feature",
  "properties": {
    "gn:admin1_code":"2.0",
    "gn:admin2_code":"7443155.0",
    "gn:asciiname":"Furuinai",
    "gn:country_code":"JP",
    "gn:dem":33,
    "gn:feature_class":"P",
    "gn:feature_code":"PPL",
    "gn:name":"Furuinai",
    "gn:population":0,
    "gn:timezone":"Asia/Tokyo",
    "iso:country":"JP",
    "name:jpn_x_preferred":[
        "\u53e4\u4e95\u5185"
    ],
    "wof:name":"Furuinai",
    "wof:placetype":"locality"
},
  "geometry": {"coordinates":[140.13273999999998,39.85132],"type":"Point"}
}