{
  "type": "Feature",
  "properties": {
    "gn:admin1_code":"27.0",
    "gn:admin2_code":"1852895.0",
    "gn:asciiname":"Arifukucho",
    "gn:country_code":"JP",
    "gn:dem":23,
    "gn:feature_class":"P",
    "gn:feature_code":"PPL",
    "gn:name":"Arifukuch\u014d",
    "gn:population":0,
    "gn:timezone":"Asia/Tokyo",
    "iso:country":"JP",
    "name:jpn_x_preferred":[
        "\u6709\u798f\u753a"
    ],
    "name:und_x_variant":[
        "Arifukuch\u014d"
    ],
    "wof:name":"Arifukucho",
    "wof:placetype":"locality"
},
  "geometry": {"coordinates":[129.78767999999999,33.13402],"type":"Point"}
}