{
  "type": "Feature",
  "properties": {
    "gn:admin1_code":"23.0",
    "gn:admin2_code":"7417704.0",
    "gn:admin3_code":"24441.0",
    "gn:asciiname":"Furue",
    "gn:country_code":"JP",
    "gn:dem":65,
    "gn:feature_class":"P",
    "gn:feature_code":"PPL",
    "gn:name":"Furue",
    "gn:population":0,
    "gn:timezone":"Asia/Tokyo",
    "iso:country":"JP",
    "name:jpn_x_preferred":[
        "\u53e4\u6c5f"
    ],
    "wof:name":"Furue",
    "wof:placetype":"locality"
},
  "geometry": {"coordinates":[136.46881999999999,34.46153],"type":"Point"}
}