{
  "type": "Feature",
  "properties": {
    "iso:country":"JP",
    "name:eng_x_preferred":[
        "Nakamachidai 1 Chome"
    ],
    "name:eng_x_variant":[
        "Nakamachidai 1 Choume",
        "Nakamachidai 1 Chome"
    ],
    "name:jpn_x_preferred":[
        "\uff11\u4e01\u76ee"
    ],
    "name:jpn_x_variant":[
        "\u306a\u304b\u307e\u3061\u3060\u3044 \uff11\u3061\u3087\u3046\u3081",
        "\u4ef2\u753a\u53f0 \uff11\u4e01\u76ee",
        "\uff11\u3061\u3087\u3046\u3081"
    ],
    "qs:gn_local":0,
    "qs:local_max":6208,
    "qs:local_sum":82309,
    "qs:localhoods":190,
    "qs:name":"\uff11\u4e01\u76ee",
    "qs:name_adm0":"\u65e5\u672c",
    "qs:name_adm1":"\u795e\u5948\u5ddd\u770c",
    "qs:name_adm2":"\u90fd\u7b51\u533a",
    "qs:name_en":"Nakamachidai 1 Chome",
    "qs:name_lau":"\u4ef2\u753a\u53f0",
    "qs:name_local":"\u6a2a\u6d5c\u5e02",
    "qs:photo_max":49,
    "qs:photo_sum":196,
    "qs:placetype":"Suburb",
    "qs:quad_count":14,
    "qs:woe_adm0":23424856,
    "qs:woe_adm1":2345868,
    "qs:woe_adm2":15015541,
    "qs:woe_lau":28416264,
    "qs:woe_local":1118550,
    "qs:woe_ver":"7.10.0",
    "qs_pg:name":"\uff11\u4e01\u76ee",
    "qs_pg:name_adm0":"\u65e5\u672c",
    "qs_pg:name_adm1":"\u795e\u5948\u5ddd\u770c",
    "qs_pg:photos":85,
    "qs_pg:photos_1k":17,
    "qs_pg:photos_9k":1,
    "qs_pg:photos_9r":3,
    "qs_pg:photos_all":85,
    "qs_pg:photos_sr":3,
    "qs_pg:pop_sr":0,
    "qs_pg:qs_pg_placetype":"neighbourhood",
    "qs_pg:qs_pg_placetype_gp":"Suburb",
    "qs_pg:woe_adm0":23424856,
    "woe:adm0_id":23424856,
    "woe:name_adm0":"\u65e5\u672c",
    "woe:name_adm1":"\u795e\u5948\u5ddd\u770c",
    "woe:placetype":"Suburb",
    "wof:lang":[
        "jpn"
    ],
    "wof:name":"\uff11\u4e01\u76ee",
    "wof:placetype":"neighbourhood"
},
  "geometry": {"coordinates":[139.59049200000001,35.536633],"type":"Point"}
}