{
  "type": "Feature",
  "properties": {
    "gn:admin1_code":"19",
    "gn:admin2_code":"1862461.0",
    "gn:asciiname":"Nagamochi",
    "gn:country_code":"JP",
    "gn:dem":14,
    "gn:feature_class":"P",
    "gn:feature_code":"PPL",
    "gn:name":"Nagamochi",
    "gn:population":0,
    "gn:timezone":"Asia/Tokyo",
    "iso:country":"JP",
    "name:jpn_x_preferred":[
        "\u9577\u6301"
    ],
    "wof:name":"Nagamochi",
    "wof:placetype":"locality"
},
  "geometry": {"coordinates":[139.31735,35.34762],"type":"Point"}
}