{
  "type": "Feature",
  "properties": {
    "gn:admin1_code":"3.0",
    "gn:admin2_code":"8534376.0",
    "gn:admin3_code":"2321.0",
    "gn:asciiname":"Magi",
    "gn:country_code":"JP",
    "gn:dem":74,
    "gn:feature_class":"P",
    "gn:feature_code":"PPL",
    "gn:name":"Magi",
    "gn:population":0,
    "gn:timezone":"Asia/Tokyo",
    "iso:country":"JP",
    "name:aze_x_preferred":[
        "Maqlar"
    ],
    "name:cat_x_preferred":[
        "Magus"
    ],
    "name:deu_x_preferred":[
        "Magier"
    ],
    "name:fin_x_preferred":[
        "Maagi"
    ],
    "name:fra_x_preferred":[
        "Mage"
    ],
    "name:hin_x_preferred":[
        "\u092e\u093e\u0917\u0940"
    ],
    "name:hrv_x_preferred":[
        "Magi"
    ],
    "name:hun_x_preferred":[
        "M\u00e1gus"
    ],
    "name:hye_x_preferred":[
        "\u0544\u0578\u0563"
    ],
    "name:ido_x_preferred":[
        "Mago"
    ],
    "name:ind_x_preferred":[
        "Majus"
    ],
    "name:ita_x_preferred":[
        "Magi"
    ],
    "name:jpn_x_preferred":[
        "\u9593\u6728"
    ],
    "name:jpn_x_variant":[
        "\u307e\u304e",
        "\u30de\u30ae"
    ],
    "name:khm_x_preferred":[
        "\u17a0\u17c4\u179a\u17b6\u1785\u17b6\u179a\u17d2\u1799"
    ],
    "name:kur_x_preferred":[
        "Mux"
    ],
    "name:mlg_x_preferred":[
        "Magy"
    ],
    "name:oci_x_preferred":[
        "Mague"
    ],
    "name:pol_x_preferred":[
        "Mag"
    ],
    "name:por_x_preferred":[
        "Mago"
    ],
    "name:ron_x_preferred":[
        "Mag"
    ],
    "name:rus_x_preferred":[
        "\u041c\u0430\u0433\u0438"
    ],
    "name:scn_x_preferred":[
        "Magu"
    ],
    "name:slk_x_preferred":[
        "M\u00e1g"
    ],
    "name:swe_x_preferred":[
        "Magier"
    ],
    "name:ukr_x_preferred":[
        "\u041c\u0430\u0433"
    ],
    "wof:name":"Magi",
    "wof:placetype":"locality"
},
  "geometry": {"coordinates":[140.23813000000001,40.74925],"type":"Point"}
}