{
  "type": "Feature",
  "properties": {
    "gn:admin1_code":"3.0",
    "gn:admin2_code":"8534376.0",
    "gn:admin3_code":"2321.0",
    "gn:asciiname":"Magi",
    "gn:country_code":"JP",
    "gn:dem":74,
    "gn:feature_class":"P",
    "gn:feature_code":"PPL",
    "gn:name":"Magi",
    "gn:population":0,
    "gn:timezone":"Asia/Tokyo",
    "iso:country":"JP",
    "name:jpn_x_preferred":[
        "\u9593\u6728"
    ],
    "name:jpn_x_variant":[
        "\u307e\u304e",
        "\u30de\u30ae"
    ],
    "wof:name":"Magi",
    "wof:placetype":"locality"
},
  "geometry": {"coordinates":[140.23813000000001,40.74925],"type":"Point"}
}