{
  "type": "Feature",
  "properties": {
    "gn:admin1_code":"26",
    "gn:admin2_code":"1857141.0",
    "gn:admin3_code":"20303.0",
    "gn:asciiname":"Yanaike",
    "gn:country_code":"JP",
    "gn:dem":1022,
    "gn:feature_class":"P",
    "gn:feature_code":"PPLL",
    "gn:name":"Yanaike",
    "gn:population":0,
    "gn:timezone":"Asia/Tokyo",
    "iso:country":"JP",
    "name:jpn_x_preferred":[
        "\u516b\u90a3\u6c60"
    ],
    "wof:name":"Yanaike",
    "wof:placetype":"locality"
},
  "geometry": {"coordinates":[138.46566000000001,36.0598],"type":"Point"}
}