{
  "type": "Feature",
  "properties": {
    "gn:admin1_code":"27",
    "gn:admin2_code":"7418811.0",
    "gn:asciiname":"Obama",
    "gn:cc2":"JP",
    "gn:country_code":"JP",
    "gn:dem":48,
    "gn:feature_class":"P",
    "gn:feature_code":"PPL",
    "gn:name":"Obama",
    "gn:population":0,
    "gn:timezone":"Asia/Tokyo",
    "iso:country":"JP",
    "name:jpn_x_preferred":[
        "\u5c0f\u6d5c\u753a"
    ],
    "name:und_x_variant":[
        "Kohama",
        "Obama"
    ],
    "name:zho_x_preferred":[
        "\u5c0f\u6ff1\u753a"
    ],
    "wof:name":"Obama",
    "wof:placetype":"locality"
},
  "geometry": {"coordinates":[130.20778000000001,32.72194],"type":"Point"}
}