{
  "type": "Feature",
  "properties": {
    "gn:admin1_code":"21.0",
    "gn:admin2_code":"7412708.0",
    "gn:admin3_code":"43507.0",
    "gn:asciiname":"Asenosako",
    "gn:country_code":"JP",
    "gn:dem":507,
    "gn:feature_class":"P",
    "gn:feature_code":"PPLL",
    "gn:name":"Asenosako",
    "gn:population":0,
    "gn:timezone":"Asia/Tokyo",
    "iso:country":"JP",
    "name:jpn_x_preferred":[
        "\u6c57\u306e\u8feb"
    ],
    "name:jpn_x_variant":[
        "\u3042\u305b\u306e\u3055\u3053",
        "\u30a2\u30bb\u30ce\u30b5\u30b3"
    ],
    "wof:name":"Asenosako",
    "wof:placetype":"locality"
},
  "geometry": {"coordinates":[131.00803999999999,32.39897],"type":"Point"}
}