{
  "type": "Feature",
  "properties": {
    "iso:country":"JP",
    "name:eng_x_preferred":[
        "Takasucho 1 Chome"
    ],
    "name:eng_x_variant":[
        "Takasuchou 1 Choume",
        "Takasucho 1 Chome"
    ],
    "name:jpn_x_preferred":[
        "\uff11\u4e01\u76ee"
    ],
    "name:jpn_x_variant":[
        "\u305f\u304b\u3059\u3061\u3087\u3046 \uff11\u3061\u3087\u3046\u3081",
        "\u9ad8\u9808\u753a \uff11\u4e01\u76ee",
        "\uff11\u3061\u3087\u3046\u3081"
    ],
    "qs:gn_adm0_cc":"JP",
    "qs:gn_local":1855207,
    "qs:gn_nam_loc":"\u897f\u5bae\u5e02, \u5175\u5eab\u770c, JP",
    "qs:gn_namadm1":"13",
    "qs:local_max":870,
    "qs:local_sum":3110,
    "qs:localhoods":22,
    "qs:name":"\uff11\u4e01\u76ee",
    "qs:name_adm0":"\u65e5\u672c",
    "qs:name_adm1":"\u5175\u5eab\u770c",
    "qs:name_en":"Takasucho 1 Chome",
    "qs:name_lau":"\u9ad8\u9808\u753a",
    "qs:name_local":"\u897f\u5bae\u5e02",
    "qs:photo_max":113,
    "qs:photo_sum":139,
    "qs:placetype":"Suburb",
    "qs:quad_count":5,
    "qs:woe_adm0":23424856,
    "qs:woe_adm1":2345862,
    "qs:woe_adm2":0,
    "qs:woe_lau":28462305,
    "qs:woe_local":1112962,
    "qs:woe_ver":"7.10.0",
    "qs_pg:name":"\uff11\u4e01\u76ee",
    "qs_pg:name_adm0":"\u65e5\u672c",
    "qs_pg:name_adm1":"\u5175\u5eab\u770c",
    "qs_pg:photos":169,
    "qs_pg:photos_1k":34,
    "qs_pg:photos_9k":1,
    "qs_pg:photos_9r":4,
    "qs_pg:photos_all":169,
    "qs_pg:photos_sr":4,
    "qs_pg:pop_sr":0,
    "qs_pg:qs_pg_placetype":"neighbourhood",
    "qs_pg:qs_pg_placetype_gp":"Suburb",
    "qs_pg:woe_adm0":23424856,
    "woe:adm0_id":23424856,
    "woe:name_adm0":"\u65e5\u672c",
    "woe:name_adm1":"\u5175\u5eab\u770c",
    "woe:placetype":"Suburb",
    "wof:lang":[
        "jpn"
    ],
    "wof:name":"\uff11\u4e01\u76ee",
    "wof:placetype":"neighbourhood"
},
  "geometry": {"coordinates":[135.37719799999999,34.704169],"type":"Point"}
}