{
  "type": "Feature",
  "properties": {
    "gn:admin1_code":"4.0",
    "gn:admin2_code":"1859468.0",
    "gn:asciiname":"Tawarada",
    "gn:country_code":"JP",
    "gn:dem":35,
    "gn:feature_class":"P",
    "gn:feature_code":"PPL",
    "gn:name":"Tawarada",
    "gn:population":0,
    "gn:timezone":"Asia/Tokyo",
    "iso:country":"JP",
    "name:jpn_x_preferred":[
        "\u4ff5\u7530"
    ],
    "name:jpn_x_variant":[
        "\u305f\u308f\u3089\u3060",
        "\u30bf\u30ef\u30e9\u30c0"
    ],
    "wof:name":"Tawarada",
    "wof:placetype":"locality"
},
  "geometry": {"coordinates":[140.05896999999999,35.31413],"type":"Point"}
}