{
  "type": "Feature",
  "properties": {
    "gn:admin1_code":"24.0",
    "gn:admin2_code":"7446990.0",
    "gn:asciiname":"Okan",
    "gn:country_code":"JP",
    "gn:dem":4,
    "gn:feature_class":"P",
    "gn:feature_code":"PPL",
    "gn:name":"\u014ckan",
    "gn:population":0,
    "gn:timezone":"Asia/Tokyo",
    "iso:country":"JP",
    "name:jpn_x_preferred":[
        "\u5f80\u9084"
    ],
    "name:jpn_x_variant":[
        "\u304a\u3046\u304b\u3093",
        "\u30aa\u30a6\u30ab\u30f3"
    ],
    "name:und_x_variant":[
        "\u014ckan"
    ],
    "wof:name":"Okan",
    "wof:placetype":"locality"
},
  "geometry": {"coordinates":[141.17487,38.39818],"type":"Point"}
}