{
  "type": "Feature",
  "properties": {
    "iso:country":"JP",
    "label:eng_x_preferred_longname":[
        "Fukagawa City"
    ],
    "label:eng_x_preferred_placetype":[
        "city"
    ],
    "name:eng_x_preferred":[
        "Fukagawa"
    ],
    "name:eng_x_variant":[
        "Fukagawa City"
    ],
    "name:jpn_x_preferred":[
        "\u6df1\u5ddd\u5e02"
    ],
    "qs:name":"\u6df1\u5ddd\u5e02",
    "qs:name_adm0":"\u65e5\u672c",
    "qs:name_adm1":"\u5317\u6d77\u9053",
    "qs:photos":19,
    "qs:photos_1k":4,
    "qs:photos_9k":1,
    "qs:photos_9r":3,
    "qs:photos_all":119,
    "qs:photos_sr":1,
    "qs:placetype":"Town",
    "qs:pop_sr":"0",
    "wof:name":"Fukagawa",
    "wof:placetype":"locality"
},
  "geometry": {"coordinates":[142.100257,43.716527],"type":"Point"}
}