{
  "type": "Feature",
  "properties": {
    "gn:admin1_code":"18.0",
    "gn:admin2_code":"8300556.0",
    "gn:asciiname":"Monzen",
    "gn:country_code":"JP",
    "gn:dem":20,
    "gn:feature_class":"P",
    "gn:feature_code":"PPLL",
    "gn:name":"Monzen",
    "gn:population":0,
    "gn:timezone":"Asia/Tokyo",
    "iso:country":"JP",
    "name:jpn_x_preferred":[
        "\u9580\u524d"
    ],
    "wof:name":"Monzen",
    "wof:placetype":"locality"
},
  "geometry": {"coordinates":[130.90246000000002,31.30893],"type":"Point"}
}