{
  "type": "Feature",
  "properties": {
    "gn:admin1_code":"28.0",
    "gn:admin2_code":"7411377.0",
    "gn:admin3_code":"29322.0",
    "gn:asciiname":"Oshio",
    "gn:country_code":"JP",
    "gn:dem":435,
    "gn:feature_class":"P",
    "gn:feature_code":"PPL",
    "gn:name":"\u014cshio",
    "gn:population":0,
    "gn:timezone":"Asia/Tokyo",
    "iso:country":"JP",
    "name:jpn_x_preferred":[
        "\u5927\u5869"
    ],
    "name:slk_x_preferred":[
        "\u00d3\u0161io"
    ],
    "name:spa_x_preferred":[
        "\u014cshio"
    ],
    "name:und_x_variant":[
        "\u014cshio"
    ],
    "wof:name":"Oshio",
    "wof:placetype":"locality"
},
  "geometry": {"coordinates":[136.00586999999999,34.67562],"type":"Point"}
}