{
  "type": "Feature",
  "properties": {
    "gn:admin1_code":"37.0",
    "gn:admin2_code":"1856971.0",
    "gn:asciiname":"Miyoshicho",
    "gn:country_code":"JP",
    "gn:dem":26,
    "gn:feature_class":"P",
    "gn:feature_code":"PPL",
    "gn:name":"Miyoshich\u014d",
    "gn:population":0,
    "gn:timezone":"Asia/Tokyo",
    "iso:country":"JP",
    "name:jpn_x_preferred":[
        "\u4e09\u597d\u753a"
    ],
    "name:und_x_variant":[
        "Miyoshich\u014d"
    ],
    "wof:name":"Miyoshicho",
    "wof:placetype":"locality"
},
  "geometry": {"coordinates":[138.90864999999999,35.11131],"type":"Point"}
}