{
  "type": "Feature",
  "properties": {
    "gn:admin1_code":"15",
    "gn:admin2_code":"1860845.0",
    "gn:asciiname":"Iburihashimachi",
    "gn:country_code":"JP",
    "gn:dem":5,
    "gn:feature_class":"P",
    "gn:feature_code":"PPL",
    "gn:name":"Iburihashimachi",
    "gn:population":0,
    "gn:timezone":"Asia/Tokyo",
    "iso:country":"JP",
    "name:jpn_x_preferred":[
        "\u52d5\u6a4b\u753a"
    ],
    "name:und_x_variant":[
        "Iburibashi",
        "Iburihashi",
        "Iburihashimachi"
    ],
    "wof:name":"Iburihashimachi",
    "wof:placetype":"locality"
},
  "geometry": {"coordinates":[136.38516000000001,36.32747],"type":"Point"}
}