{
  "type": "Feature",
  "properties": {
    "gn:admin1_code":"23.0",
    "gn:admin2_code":"1856290.0",
    "gn:asciiname":"Kuramochicho-harade",
    "gn:country_code":"JP",
    "gn:dem":196,
    "gn:feature_class":"P",
    "gn:feature_code":"PPL",
    "gn:name":"Kuramochich\u014d-harade",
    "gn:population":0,
    "gn:timezone":"Asia/Tokyo",
    "iso:country":"JP",
    "name:jbn_x_preferred":[
        "Kuramochich\u014d-harade"
    ],
    "name:jpn_x_preferred":[
        "\u8535\u6301\u753a\u539f\u51fa"
    ],
    "wof:name":"Kuramochicho-harade",
    "wof:placetype":"locality"
},
  "geometry": {"coordinates":[136.1123,34.63629],"type":"Point"}
}