{
  "type": "Feature",
  "properties": {
    "gn:admin1_code":"7.0",
    "gn:admin2_code":"1859874.0",
    "gn:admin3_code":"40348.0",
    "gn:asciiname":"Yamada",
    "gn:country_code":"JP",
    "gn:dem":53,
    "gn:feature_class":"P",
    "gn:feature_code":"PPL",
    "gn:name":"Yamada",
    "gn:population":0,
    "gn:timezone":"Asia/Tokyo",
    "iso:country":"JP",
    "name:jpn_x_preferred":[
        "\u5c71\u7530"
    ],
    "wof:name":"Yamada",
    "wof:placetype":"locality"
},
  "geometry": {"coordinates":[130.488,33.66322],"type":"Point"}
}