{
  "type": "Feature",
  "properties": {
    "gn:admin1_code":"18.0",
    "gn:admin2_code":"7383999.0",
    "gn:admin3_code":"46491.0",
    "gn:asciiname":"Kawaminami",
    "gn:country_code":"JP",
    "gn:dem":413,
    "gn:feature_class":"P",
    "gn:feature_code":"PPLL",
    "gn:name":"Kawaminami",
    "gn:population":0,
    "gn:timezone":"Asia/Tokyo",
    "iso:country":"JP",
    "name:jpn_x_preferred":[
        "\u5ddd\u5357"
    ],
    "wof:name":"Kawaminami",
    "wof:placetype":"locality"
},
  "geometry": {"coordinates":[130.77471,31.10911],"type":"Point"}
}