{
  "type": "Feature",
  "properties": {
    "gn:admin1_code":"37.0",
    "gn:admin2_code":"1854900.0",
    "gn:asciiname":"Kosuwa",
    "gn:country_code":"JP",
    "gn:dem":6,
    "gn:feature_class":"P",
    "gn:feature_code":"PPL",
    "gn:name":"Kosuwa",
    "gn:population":0,
    "gn:timezone":"Asia/Tokyo",
    "iso:country":"JP",
    "name:jpn_x_preferred":[
        "\u5c0f\u8acf\u8a2a"
    ],
    "wof:name":"Kosuwa",
    "wof:placetype":"locality"
},
  "geometry": {"coordinates":[138.83723000000001,35.10906],"type":"Point"}
}