{
  "type": "Feature",
  "properties": {
    "gn:admin1_code":"37.0",
    "gn:admin2_code":"1864104.0",
    "gn:asciiname":"Shomisawa",
    "gn:country_code":"JP",
    "gn:dem":179,
    "gn:feature_class":"P",
    "gn:feature_code":"PPLL",
    "gn:name":"Sh\u014dmisawa",
    "gn:population":0,
    "gn:timezone":"Asia/Tokyo",
    "iso:country":"JP",
    "name:jpn_x_preferred":[
        "\u5c0f\u4e09\u6ca2"
    ],
    "name:und_x_variant":[
        "Sh\u014dmisawa"
    ],
    "wof:name":"Shomisawa",
    "wof:placetype":"locality"
},
  "geometry": {"coordinates":[138.56999999999999,35.23889000000001],"type":"Point"}
}