{
  "type": "Feature",
  "properties": {
    "gn:admin1_code":"4.0",
    "gn:admin2_code":"9062338.0",
    "gn:asciiname":"Nishihara",
    "gn:country_code":"JP",
    "gn:dem":120,
    "gn:feature_class":"P",
    "gn:feature_code":"PPLL",
    "gn:name":"Nishihara",
    "gn:population":0,
    "gn:timezone":"Asia/Tokyo",
    "iso:country":"JP",
    "name:jpn_x_preferred":[
        "\u897f\u539f"
    ],
    "name:jpn_x_variant":[
        "\u306b\u3057\u306f\u3089",
        "\u30cb\u30b7\u30cf\u30e9"
    ],
    "wof:name":"Nishihara",
    "wof:placetype":"locality"
},
  "geometry": {"coordinates":[140.23043999999999,35.15165],"type":"Point"}
}