{
  "type": "Feature",
  "properties": {
    "gn:admin1_code":"16.0",
    "gn:admin2_code":"2128940.0",
    "gn:asciiname":"Matsuoka",
    "gn:country_code":"JP",
    "gn:dem":239,
    "gn:feature_class":"P",
    "gn:feature_code":"PPL",
    "gn:name":"Matsuoka",
    "gn:population":0,
    "gn:timezone":"Asia/Tokyo",
    "iso:country":"JP",
    "name:jpn_x_preferred":[
        "\u677e\u5ca1"
    ],
    "name:jpn_x_variant":[
        "\u307e\u3064\u304a\u304b",
        "\u30de\u30c4\u30aa\u30ab"
    ],
    "wof:name":"Matsuoka",
    "wof:placetype":"locality"
},
  "geometry": {"coordinates":[141.16988999999995,40.20061],"type":"Point"}
}