{
  "type": "Feature",
  "properties": {
    "gn:admin1_code":"47",
    "gn:admin2_code":"1863626.0",
    "gn:asciiname":"Ujidomari",
    "gn:country_code":"JP",
    "gn:dem":11,
    "gn:feature_class":"P",
    "gn:feature_code":"PPL",
    "gn:name":"Ujidomari",
    "gn:population":0,
    "gn:timezone":"Asia/Tokyo",
    "iso:country":"JP",
    "name:jpn_x_preferred":[
        "\u5b87\u5730\u6cca"
    ],
    "name:jpn_x_variant":[
        "\u3046\u3058\u3069\u307e\u308a"
    ],
    "name:und_x_variant":[
        "Uchidumai",
        "Uchidomari",
        "Uchitomari",
        "Ujidomari"
    ],
    "wof:name":"Ujidomari",
    "wof:placetype":"locality"
},
  "geometry": {"coordinates":[127.73054,26.27154],"type":"Point"}
}