{
  "type": "Feature",
  "properties": {
    "gn:admin1_code":"12.0",
    "gn:admin2_code":"7428103.0",
    "gn:admin3_code":"1601.0",
    "gn:asciiname":"Tomikawa",
    "gn:country_code":"JP",
    "gn:dem":11,
    "gn:feature_class":"P",
    "gn:feature_code":"PPL",
    "gn:name":"Tomikawa",
    "gn:population":0,
    "gn:timezone":"Asia/Tokyo",
    "iso:country":"JP",
    "name:jpn_x_preferred":[
        "\u5bcc\u5ddd"
    ],
    "wof:name":"Tomikawa",
    "wof:placetype":"locality"
},
  "geometry": {"coordinates":[142.02708000000001,42.52078],"type":"Point"}
}