{
  "type": "Feature",
  "properties": {
    "gn:admin1_code":"21.0",
    "gn:admin2_code":"7412706.0",
    "gn:admin3_code":"43447.0",
    "gn:asciiname":"Kogome",
    "gn:country_code":"JP",
    "gn:dem":582,
    "gn:feature_class":"P",
    "gn:feature_code":"PPLL",
    "gn:name":"Kogome",
    "gn:population":0,
    "gn:timezone":"Asia/Tokyo",
    "iso:country":"JP",
    "name:jpn_x_preferred":[
        "\u53e4\u7c73"
    ],
    "name:jpn_x_variant":[
        "\u3053\u3054\u3081",
        "\u30b3\u30b4\u30e1"
    ],
    "wof:name":"Kogome",
    "wof:placetype":"locality"
},
  "geometry": {"coordinates":[131.17796000000001,32.7717],"type":"Point"}
}