{
  "type": "Feature",
  "properties": {
    "gn:admin1_code":"10.0",
    "gn:admin2_code":"1852593.0",
    "gn:asciiname":"Gorindaira",
    "gn:country_code":"JP",
    "gn:dem":418,
    "gn:feature_class":"P",
    "gn:feature_code":"PPLL",
    "gn:name":"Gorindaira",
    "gn:population":0,
    "gn:timezone":"Asia/Tokyo",
    "iso:country":"JP",
    "name:jpn_x_preferred":[
        "\u4e94\u8f2a\u5e73"
    ],
    "wof:name":"Gorindaira",
    "wof:placetype":"locality"
},
  "geometry": {"coordinates":[138.97092000000001,36.47218],"type":"Point"}
}