{
  "type": "Feature",
  "properties": {
    "gn:admin1_code":"3.0",
    "gn:admin2_code":"7439944.0",
    "gn:asciiname":"Kashiwa-shimokokawa",
    "gn:country_code":"JP",
    "gn:dem":10,
    "gn:feature_class":"P",
    "gn:feature_code":"PPL",
    "gn:name":"Kashiwa-shimokokawa",
    "gn:population":0,
    "gn:timezone":"Asia/Tokyo",
    "iso:country":"JP",
    "name:jpn_x_preferred":[
        "\u67cf\u4e0b\u53e4\u5ddd"
    ],
    "name:jpn_x_variant":[
        "\u304b\u3057\u308f\u3057\u3082\u3053\u304b\u308f",
        "\u30ab\u30b7\u30ef\u30b7\u30e2\u30b3\u30ab\u30ef"
    ],
    "wof:name":"Kashiwa-shimokokawa",
    "wof:placetype":"locality"
},
  "geometry": {"coordinates":[140.42883,40.79671],"type":"Point"}
}