{
  "type": "Feature",
  "properties": {
    "gn:admin1_code":"29.0",
    "gn:admin2_code":"1856195.0",
    "gn:asciiname":"Maejimamachi",
    "gn:country_code":"JP",
    "gn:dem":23,
    "gn:feature_class":"P",
    "gn:feature_code":"PPL",
    "gn:name":"Maejimamachi",
    "gn:population":0,
    "gn:timezone":"Asia/Tokyo",
    "iso:country":"JP",
    "name:jpn_x_preferred":[
        "\u524d\u5cf6\u753a"
    ],
    "wof:name":"Maejimamachi",
    "wof:placetype":"locality"
},
  "geometry": {"coordinates":[138.82459,37.40586],"type":"Point"}
}