{
  "type": "Feature",
  "properties": {
    "gn:admin1_code":"19.0",
    "gn:admin2_code":"1848350.0",
    "gn:admin3_code":"14108.0",
    "gn:asciiname":"Okawa",
    "gn:country_code":"JP",
    "gn:dem":4,
    "gn:feature_class":"P",
    "gn:feature_code":"PPL",
    "gn:name":"\u014ckawa",
    "gn:population":0,
    "gn:timezone":"Asia/Tokyo",
    "iso:country":"JP",
    "name:ceb_x_preferred":[
        "Okawa"
    ],
    "name:fas_x_preferred":[
        "\u0627\u0648\u06a9\u0627\u0648\u0627"
    ],
    "name:fra_x_preferred":[
        "Okawa"
    ],
    "name:ita_x_preferred":[
        "Okawa"
    ],
    "name:jpn_x_preferred":[
        "\u5927\u5ddd"
    ],
    "name:jpn_x_variant":[
        "\u304a\u304a\u304b\u308f",
        "\u30aa\u30aa\u30ab\u30ef"
    ],
    "name:swe_x_preferred":[
        "Okawa"
    ],
    "name:und_x_variant":[
        "\u014ckawa"
    ],
    "wof:name":"Okawa",
    "wof:placetype":"locality"
},
  "geometry": {"coordinates":[139.61881,35.33589],"type":"Point"}
}