{
  "type": "Feature",
  "properties": {
    "gn:admin1_code":"21.0",
    "gn:admin2_code":"1864973.0",
    "gn:asciiname":"Koji",
    "gn:country_code":"JP",
    "gn:dem":502,
    "gn:feature_class":"P",
    "gn:feature_code":"PPL",
    "gn:name":"K\u014dji",
    "gn:population":0,
    "gn:timezone":"Asia/Tokyo",
    "iso:country":"JP",
    "name:ceb_x_preferred":[
        "Koji"
    ],
    "name:ita_x_preferred":[
        "Koji"
    ],
    "name:jpn_x_preferred":[
        "\u5c0f\u6c60"
    ],
    "name:jpn_x_variant":[
        "\u3053\u3046\u3058",
        "\u30b3\u30a6\u30b8"
    ],
    "name:swe_x_preferred":[
        "Koji"
    ],
    "name:und_x_variant":[
        "K\u014dji"
    ],
    "wof:name":"Koji",
    "wof:placetype":"locality"
},
  "geometry": {"coordinates":[131.06518,32.97499000000001],"type":"Point"}
}