{
  "type": "Feature",
  "properties": {
    "gn:admin1_code":"34.0",
    "gn:admin2_code":"1859739.0",
    "gn:asciiname":"Shibui",
    "gn:country_code":"JP",
    "gn:dem":12,
    "gn:feature_class":"P",
    "gn:feature_code":"PPL",
    "gn:name":"Shibui",
    "gn:population":0,
    "gn:timezone":"Asia/Tokyo",
    "iso:country":"JP",
    "name:ast_x_preferred":[
        "Astrinxencia"
    ],
    "name:fra_x_preferred":[
        "Shibui"
    ],
    "name:ita_x_preferred":[
        "Shibusa"
    ],
    "name:jpn_x_preferred":[
        "\u6e0b\u4e95"
    ],
    "name:kor_x_preferred":[
        "\ub5ab\uc740\ub9db"
    ],
    "name:rus_x_preferred":[
        "\u0421\u0438\u0431\u0443\u0439"
    ],
    "name:spa_x_preferred":[
        "Astringencia"
    ],
    "name:vie_x_preferred":[
        "Shibui"
    ],
    "wof:name":"Shibui",
    "wof:placetype":"locality"
},
  "geometry": {"coordinates":[139.53733,35.8818],"type":"Point"}
}