{
  "type": "Feature",
  "properties": {
    "gn:admin1_code":"34.0",
    "gn:admin2_code":"1859739.0",
    "gn:asciiname":"Shibui",
    "gn:country_code":"JP",
    "gn:dem":12,
    "gn:feature_class":"P",
    "gn:feature_code":"PPL",
    "gn:name":"Shibui",
    "gn:population":0,
    "gn:timezone":"Asia/Tokyo",
    "iso:country":"JP",
    "name:jpn_x_preferred":[
        "\u6e0b\u4e95"
    ],
    "wof:name":"Shibui",
    "wof:placetype":"locality"
},
  "geometry": {"coordinates":[139.53733,35.8818],"type":"Point"}
}