{
  "type": "Feature",
  "properties": {
    "gn:admin1_code":"8.0",
    "gn:admin2_code":"1857203.0",
    "gn:admin3_code":"7367.0",
    "gn:asciiname":"Kumagura",
    "gn:country_code":"JP",
    "gn:dem":435,
    "gn:feature_class":"P",
    "gn:feature_code":"PPL",
    "gn:name":"Kumagura",
    "gn:population":0,
    "gn:timezone":"Asia/Tokyo",
    "iso:country":"JP",
    "name:jpn_x_preferred":[
        "\u718a\u5009"
    ],
    "wof:name":"Kumagura",
    "wof:placetype":"locality"
},
  "geometry": {"coordinates":[139.40601999999998,37.31382],"type":"Point"}
}