{
  "type": "Feature",
  "properties": {
    "gn:admin1_code":"3.0",
    "gn:admin2_code":"7439944.0",
    "gn:asciiname":"Ashiya",
    "gn:country_code":"JP",
    "gn:dem":6,
    "gn:feature_class":"P",
    "gn:feature_code":"PPL",
    "gn:name":"Ashiya",
    "gn:population":0,
    "gn:timezone":"Asia/Tokyo",
    "iso:country":"JP",
    "name:jpn_x_preferred":[
        "\u82a6\u5c4b"
    ],
    "name:jpn_x_variant":[
        "\u3042\u3057\u3084",
        "\u30a2\u30b7\u30e4"
    ],
    "wof:name":"Ashiya",
    "wof:placetype":"locality"
},
  "geometry": {"coordinates":[140.41701,40.82444],"type":"Point"}
}