{
  "type": "Feature",
  "properties": {
    "gn:admin1_code":"3.0",
    "gn:admin2_code":"7439944.0",
    "gn:asciiname":"Ashiya",
    "gn:country_code":"JP",
    "gn:dem":6,
    "gn:feature_class":"P",
    "gn:feature_code":"PPL",
    "gn:name":"Ashiya",
    "gn:population":0,
    "gn:timezone":"Asia/Tokyo",
    "iso:country":"JP",
    "name:ceb_x_preferred":[
        "Ashiya"
    ],
    "name:che_x_preferred":[
        "\u0410\u0441\u0438\u044f"
    ],
    "name:hye_x_preferred":[
        "\u0531\u057d\u056b\u0561"
    ],
    "name:jpn_x_preferred":[
        "\u82a6\u5c4b"
    ],
    "name:jpn_x_variant":[
        "\u3042\u3057\u3084",
        "\u30a2\u30b7\u30e4"
    ],
    "name:kor_x_preferred":[
        "\uc544\uc2dc\uc57c"
    ],
    "name:mlg_x_preferred":[
        "Ashiya"
    ],
    "name:nld_x_preferred":[
        "Ashiya"
    ],
    "name:por_x_preferred":[
        "Ashiya"
    ],
    "name:ron_x_preferred":[
        "Ashiya"
    ],
    "name:rus_x_preferred":[
        "\u0410\u0441\u0438\u044f"
    ],
    "wof:name":"Ashiya",
    "wof:placetype":"locality"
},
  "geometry": {"coordinates":[140.41701,40.82444],"type":"Point"}
}