{
  "type": "Feature",
  "properties": {
    "gn:admin1_code":"21.0",
    "gn:admin2_code":"1859488.0",
    "gn:asciiname":"Oka",
    "gn:country_code":"JP",
    "gn:dem":56,
    "gn:feature_class":"P",
    "gn:feature_code":"PPLL",
    "gn:name":"Oka",
    "gn:population":0,
    "gn:timezone":"Asia/Tokyo",
    "iso:country":"JP",
    "name:ara_x_preferred":[
        "\u0623\u0648\u0643\u0627"
    ],
    "name:aze_x_preferred":[
        "Oka"
    ],
    "name:bel_x_preferred":[
        "\u0410\u043a\u0430"
    ],
    "name:bul_x_preferred":[
        "\u041e\u043a\u0430"
    ],
    "name:ceb_x_preferred":[
        "Oka"
    ],
    "name:ces_x_preferred":[
        "Oka"
    ],
    "name:dan_x_preferred":[
        "Oka"
    ],
    "name:deu_x_preferred":[
        "Oka"
    ],
    "name:eus_x_preferred":[
        "Oka"
    ],
    "name:fin_x_preferred":[
        "Oka"
    ],
    "name:fra_x_preferred":[
        "Oka"
    ],
    "name:fry_x_preferred":[
        "Oka"
    ],
    "name:glg_x_preferred":[
        "Oka"
    ],
    "name:heb_x_preferred":[
        "\u05d0\u05d5\u05e7\u05d4"
    ],
    "name:hrv_x_preferred":[
        "Oka"
    ],
    "name:hun_x_preferred":[
        "Oka"
    ],
    "name:hye_x_preferred":[
        "\u0555\u056f\u0561"
    ],
    "name:jpn_x_preferred":[
        "\u5ca1"
    ],
    "name:jpn_x_variant":[
        "\u304a\u304b",
        "\u30aa\u30ab"
    ],
    "name:nld_x_preferred":[
        "Oka"
    ],
    "name:oss_x_preferred":[
        "\u041e\u043a\u0430"
    ],
    "name:pol_x_preferred":[
        "Oka"
    ],
    "name:ron_x_preferred":[
        "Oka"
    ],
    "name:rus_x_preferred":[
        "\u041e\u043a\u0430"
    ],
    "name:slk_x_preferred":[
        "Oka"
    ],
    "name:slv_x_preferred":[
        "Oka"
    ],
    "name:spa_x_preferred":[
        "Oka"
    ],
    "name:srp_x_preferred":[
        "\u041e\u043a\u0430"
    ],
    "name:swe_x_preferred":[
        "Oka"
    ],
    "name:ukr_x_preferred":[
        "\u041e\u043a\u0430"
    ],
    "wof:name":"Oka",
    "wof:placetype":"locality"
},
  "geometry": {"coordinates":[130.74352999999999,32.94116],"type":"Point"}
}