{
  "type": "Feature",
  "properties": {
    "gn:admin1_code":"21.0",
    "gn:admin2_code":"1859488.0",
    "gn:asciiname":"Oka",
    "gn:country_code":"JP",
    "gn:dem":56,
    "gn:feature_class":"P",
    "gn:feature_code":"PPLL",
    "gn:name":"Oka",
    "gn:population":0,
    "gn:timezone":"Asia/Tokyo",
    "iso:country":"JP",
    "name:jpn_x_preferred":[
        "\u5ca1"
    ],
    "name:jpn_x_variant":[
        "\u304a\u304b",
        "\u30aa\u30ab"
    ],
    "wof:name":"Oka",
    "wof:placetype":"locality"
},
  "geometry": {"coordinates":[130.74352999999999,32.94116],"type":"Point"}
}