{
  "type": "Feature",
  "properties": {
    "gn:admin1_code":"7.0",
    "gn:admin2_code":"1855902.0",
    "gn:asciiname":"Seto",
    "gn:country_code":"JP",
    "gn:dem":4,
    "gn:feature_class":"P",
    "gn:feature_code":"PPLL",
    "gn:name":"Seto",
    "gn:population":0,
    "gn:timezone":"Asia/Tokyo",
    "iso:country":"JP",
    "name:ceb_x_preferred":[
        "Seto"
    ],
    "name:ces_x_preferred":[
        "Seto"
    ],
    "name:deu_x_preferred":[
        "Seto"
    ],
    "name:epo_x_preferred":[
        "Seto"
    ],
    "name:est_x_preferred":[
        "Seto"
    ],
    "name:fra_x_preferred":[
        "Seto"
    ],
    "name:ita_x_preferred":[
        "Seto"
    ],
    "name:jpn_x_preferred":[
        "\u702c\u6238"
    ],
    "name:kaz_x_preferred":[
        "\u0421\u0435\u0442\u043e"
    ],
    "name:lit_x_preferred":[
        "Setas"
    ],
    "name:nld_x_preferred":[
        "Seto"
    ],
    "name:pol_x_preferred":[
        "Seto"
    ],
    "name:rus_x_preferred":[
        "\u0421\u0435\u0442\u043e"
    ],
    "name:spa_x_preferred":[
        "Seto"
    ],
    "name:swe_x_preferred":[
        "Seto"
    ],
    "name:ukr_x_preferred":[
        "\u0421\u0435\u0442\u043e"
    ],
    "wof:name":"Seto",
    "wof:placetype":"locality"
},
  "geometry": {"coordinates":[130.69478000000001,33.8085],"type":"Point"}
}