{
  "type": "Feature",
  "properties": {
    "gn:admin1_code":"4.0",
    "gn:admin2_code":"2112997.0",
    "gn:admin3_code":"12422.0",
    "gn:asciiname":"Kodaki",
    "gn:country_code":"JP",
    "gn:dem":13,
    "gn:feature_class":"P",
    "gn:feature_code":"PPL",
    "gn:name":"Kodaki",
    "gn:population":0,
    "gn:timezone":"Asia/Tokyo",
    "iso:country":"JP",
    "name:jpn_x_preferred":[
        "\u5c0f\u6edd"
    ],
    "name:jpn_x_variant":[
        "\u3053\u3060\u304d",
        "\u30b3\u30c0\u30ad"
    ],
    "wof:name":"Kodaki",
    "wof:placetype":"locality"
},
  "geometry": {"coordinates":[140.33458999999999,35.36575999999999],"type":"Point"}
}