{
  "type": "Feature",
  "properties": {
    "gn:admin1_code":"32.0",
    "gn:admin2_code":"1862032.0",
    "gn:asciiname":"Sawaragi",
    "gn:country_code":"JP",
    "gn:dem":7,
    "gn:feature_class":"P",
    "gn:feature_code":"PPL",
    "gn:name":"Sawaragi",
    "gn:population":0,
    "gn:timezone":"Asia/Tokyo",
    "iso:country":"JP",
    "name:jpn_x_preferred":[
        "\u6ca2\u826f\u5b9c"
    ],
    "wof:name":"Sawaragi",
    "wof:placetype":"locality"
},
  "geometry": {"coordinates":[135.57187999999999,34.79642],"type":"Point"}
}