{
  "type": "Feature",
  "properties": {
    "iso:country":"JP",
    "name:eng_x_preferred":[
        "Sakurazaka 2 Chome"
    ],
    "name:eng_x_variant":[
        "Sakurazaka 2 Choume",
        "Sakurazaka 2 Chome"
    ],
    "name:jpn_x_preferred":[
        "\uff12\u4e01\u76ee"
    ],
    "name:jpn_x_variant":[
        "\u3055\u304f\u3089\u3056\u304b \uff12\u3061\u3087\u3046\u3081",
        "\u3055\u304f\u3089\u5742 \uff12\u4e01\u76ee",
        "\uff12\u3061\u3087\u3046\u3081"
    ],
    "qs:gn_local":0,
    "qs:local_max":9,
    "qs:local_sum":9,
    "qs:localhoods":1,
    "qs:name":"\uff12\u4e01\u76ee",
    "qs:name_adm0":"\u65e5\u672c",
    "qs:name_adm1":"\u5927\u962a\u5e9c",
    "qs:name_adm2":"\u5357\u6cb3\u5185\u90e1",
    "qs:name_en":"Sakurazaka 2 Chome",
    "qs:name_lau":"\u3055\u304f\u3089\u5742",
    "qs:name_local":"\u6cb3\u5357\u753a",
    "qs:photo_max":5,
    "qs:photo_sum":9,
    "qs:placetype":"Suburb",
    "qs:quad_count":5,
    "qs:woe_adm0":23424856,
    "qs:woe_adm1":2345881,
    "qs:woe_adm2":24857859,
    "qs:woe_lau":28460540,
    "qs:woe_local":24711686,
    "qs:woe_ver":"7.10.0",
    "wof:lang":[
        "jpn"
    ],
    "wof:name":"\uff12\u4e01\u76ee",
    "wof:placetype":"neighbourhood"
},
  "geometry": {"coordinates":[135.62713600000001,34.465554],"type":"Point"}
}