{
  "type": "Feature",
  "properties": {
    "gn:admin1_code":"21.0",
    "gn:admin2_code":"1865358.0",
    "gn:asciiname":"Nagabayashi",
    "gn:country_code":"JP",
    "gn:dem":138,
    "gn:feature_class":"P",
    "gn:feature_code":"PPLL",
    "gn:name":"Nagabayashi",
    "gn:population":0,
    "gn:timezone":"Asia/Tokyo",
    "iso:country":"JP",
    "name:jpn_x_preferred":[
        "\u9577\u6797"
    ],
    "name:jpn_x_variant":[
        "\u306a\u304c\u3070\u3084\u3057",
        "\u30ca\u30ac\u30d0\u30e4\u30b7"
    ],
    "wof:name":"Nagabayashi",
    "wof:placetype":"locality"
},
  "geometry": {"coordinates":[130.04907,32.35345],"type":"Point"}
}