{
  "type": "Feature",
  "properties": {
    "gn:admin1_code":"23.0",
    "gn:admin2_code":"1857496.0",
    "gn:asciiname":"Iitakacho-shimotakino",
    "gn:country_code":"JP",
    "gn:dem":162,
    "gn:feature_class":"P",
    "gn:feature_code":"PPL",
    "gn:name":"Iitakach\u014d-shimotakino",
    "gn:population":0,
    "gn:timezone":"Asia/Tokyo",
    "iso:country":"JP",
    "name:jpn_x_preferred":[
        "\u98ef\u5357\u753a\u4e0b\u6edd\u91ce"
    ],
    "name:und_x_variant":[
        "Iitakach\u014d-shimotakino"
    ],
    "wof:name":"Iitakacho-shimotakino",
    "wof:placetype":"locality"
},
  "geometry": {"coordinates":[136.34618999999998,34.44074000000001],"type":"Point"}
}