{
  "type": "Feature",
  "properties": {
    "iso:country":"JP",
    "name:eng_x_preferred":[
        "Nishihongo 1 Chome"
    ],
    "name:eng_x_variant":[
        "Nishihongou 1 Choume",
        "Nishihongo 1 Chome"
    ],
    "name:jpn_x_preferred":[
        "\uff11\u4e01\u76ee"
    ],
    "name:jpn_x_variant":[
        "\u306b\u3057\u307b\u3093\u3054\u3046 \uff11\u3061\u3087\u3046\u3081",
        "\u897f\u672c\u90f7 \uff11\u4e01\u76ee",
        "\uff11\u3061\u3087\u3046\u3081"
    ],
    "qs:gn_local":0,
    "qs:local_max":1349,
    "qs:local_sum":1571,
    "qs:localhoods":4,
    "qs:name":"\uff11\u4e01\u76ee",
    "qs:name_adm0":"\u65e5\u672c",
    "qs:name_adm1":"\u9759\u5ca1\u770c",
    "qs:name_en":"Nishihongo 1 Chome",
    "qs:name_lau":"\u897f\u672c\u90f7",
    "qs:name_local":"\u4e0b\u7530\u5e02",
    "qs:photo_max":48,
    "qs:photo_sum":114,
    "qs:placetype":"Suburb",
    "qs:quad_count":9,
    "qs:woe_adm0":23424856,
    "qs:woe_adm1":2345886,
    "qs:woe_adm2":0,
    "qs:woe_lau":28438389,
    "qs:woe_local":1118175,
    "qs:woe_ver":"7.10.0",
    "wof:lang":[
        "jpn"
    ],
    "wof:name":"\uff11\u4e01\u76ee",
    "wof:placetype":"neighbourhood"
},
  "geometry": {"coordinates":[138.93631199999999,34.680274],"type":"Point"}
}