{
  "type": "Feature",
  "properties": {
    "iso:country":"JP",
    "name:eng_x_preferred":[
        "Yamatonijo 8 Chome"
    ],
    "name:eng_x_variant":[
        "Yamatonijou 8 Choume",
        "Yamatonijo 8 Chome"
    ],
    "name:jpn_x_preferred":[
        "\uff18\u4e01\u76ee"
    ],
    "name:jpn_x_variant":[
        "\u3084\u307e\u3068\u306b\u3058\u3087\u3046 \uff18\u3061\u3087\u3046\u3081",
        "\u5927\u548c\u4e8c\u6761 \uff18\u4e01\u76ee",
        "\uff18\u3061\u3087\u3046\u3081"
    ],
    "qs:gn_local":0,
    "qs:local_max":19,
    "qs:local_sum":30,
    "qs:localhoods":2,
    "qs:name":"\uff18\u4e01\u76ee",
    "qs:name_adm0":"\u65e5\u672c",
    "qs:name_adm1":"\u5317\u6d77\u9053",
    "qs:name_en":"Yamatonijo 8 Chome",
    "qs:name_lau":"\u5927\u548c\u4e8c\u6761",
    "qs:name_local":"\u5ca9\u898b\u6ca2\u5e02",
    "qs:photo_max":19,
    "qs:photo_sum":19,
    "qs:placetype":"Suburb",
    "qs:quad_count":1,
    "qs:woe_adm0":23424856,
    "qs:woe_adm1":7153351,
    "qs:woe_adm2":0,
    "qs:woe_lau":28381433,
    "qs:woe_local":1117346,
    "qs:woe_ver":"7.10.0",
    "wof:lang":[
        "jpn"
    ],
    "wof:name":"\uff18\u4e01\u76ee",
    "wof:placetype":"neighbourhood"
},
  "geometry": {"coordinates":[141.73736600000001,43.187157],"type":"Point"}
}