{
  "type": "Feature",
  "properties": {
    "gn:admin1_code":"21.0",
    "gn:admin2_code":"7412706.0",
    "gn:admin3_code":"43443.0",
    "gn:asciiname":"Oyatsu",
    "gn:country_code":"JP",
    "gn:dem":65,
    "gn:feature_class":"P",
    "gn:feature_code":"PPL",
    "gn:name":"Oyatsu",
    "gn:population":0,
    "gn:timezone":"Asia/Tokyo",
    "iso:country":"JP",
    "name:jpn_x_preferred":[
        "\u5c0f\u8c37"
    ],
    "name:jpn_x_variant":[
        "\u304a\u3084\u3064",
        "\u30aa\u30e4\u30c4"
    ],
    "wof:name":"Oyatsu",
    "wof:placetype":"locality"
},
  "geometry": {"coordinates":[130.85682,32.81265],"type":"Point"}
}