{
  "type": "Feature",
  "properties": {
    "gn:admin1_code":"21.0",
    "gn:admin2_code":"1859488.0",
    "gn:asciiname":"Kamihashita",
    "gn:country_code":"JP",
    "gn:dem":28,
    "gn:feature_class":"P",
    "gn:feature_code":"PPLL",
    "gn:name":"Kamihashita",
    "gn:population":0,
    "gn:timezone":"Asia/Tokyo",
    "iso:country":"JP",
    "name:jpn_x_preferred":[
        "\u4e0a\u6a4b\u7530"
    ],
    "name:jpn_x_variant":[
        "\u304b\u307f\u306f\u3057\u305f",
        "\u30ab\u30df\u30cf\u30b7\u30bf"
    ],
    "wof:name":"Kamihashita",
    "wof:placetype":"locality"
},
  "geometry": {"coordinates":[130.73998999999998,32.9654],"type":"Point"}
}