{
  "type": "Feature",
  "properties": {
    "gn:admin1_code":"12.0",
    "gn:admin2_code":"7428089.0",
    "gn:admin3_code":"1631.0",
    "gn:asciiname":"Komaba",
    "gn:country_code":"JP",
    "gn:dem":109,
    "gn:feature_class":"P",
    "gn:feature_code":"PPL",
    "gn:name":"Komaba",
    "gn:population":0,
    "gn:timezone":"Asia/Tokyo",
    "iso:country":"JP",
    "wof:name":"Komaba",
    "wof:placetype":"locality"
},
  "geometry": {"coordinates":[143.18333000000001,43.05],"type":"Point"}
}