{
  "type": "Feature",
  "properties": {
    "gn:admin1_code":"34.0",
    "gn:admin2_code":"1849187.0",
    "gn:admin3_code":"11104.0",
    "gn:asciiname":"Horisakicho",
    "gn:country_code":"JP",
    "gn:dem":14,
    "gn:feature_class":"P",
    "gn:feature_code":"PPL",
    "gn:name":"Horisakich\u014d",
    "gn:population":0,
    "gn:timezone":"Asia/Tokyo",
    "iso:country":"JP",
    "name:jpn_x_preferred":[
        "\u5800\u5d0e\u753a"
    ],
    "name:jpn_x_variant":[
        "\u307b\u308a\u3055\u304d\u3061\u3087\u3046",
        "\u30db\u30ea\u30b5\u30ad\u30c1\u30e7\u30a6"
    ],
    "name:und_x_variant":[
        "Horisakich\u014d"
    ],
    "wof:name":"Horisakicho",
    "wof:placetype":"locality"
},
  "geometry": {"coordinates":[139.65348,35.93851],"type":"Point"}
}