{
  "type": "Feature",
  "properties": {
    "gn:admin1_code":"12.0",
    "gn:admin2_code":"7428078.0",
    "gn:admin3_code":"1662.0",
    "gn:asciiname":"Kamioboro",
    "gn:country_code":"JP",
    "gn:dem":50,
    "gn:feature_class":"P",
    "gn:feature_code":"PPL",
    "gn:name":"Kamioboro",
    "gn:population":0,
    "gn:timezone":"Asia/Tokyo",
    "iso:country":"JP",
    "name:jpn_x_preferred":[
        "\u4e0a\u5c3e\u5e4c"
    ],
    "name:jpn_x_variant":[
        "\u304b\u307f\u304a\u307c\u308d",
        "\u30ab\u30df\u30aa\u30dc\u30ed"
    ],
    "name:und_x_variant":[
        "Kami-opporo",
        "Kami-oboro",
        "Kamioboro"
    ],
    "wof:name":"Kamioboro",
    "wof:placetype":"locality"
},
  "geometry": {"coordinates":[144.62031000000005,43.02779],"type":"Point"}
}