{
  "type": "Feature",
  "properties": {
    "gn:admin1_code":"19.0",
    "gn:admin2_code":"1859635.0",
    "gn:admin3_code":"14131.0",
    "gn:asciiname":"Higashidacho",
    "gn:country_code":"JP",
    "gn:dem":24,
    "gn:feature_class":"P",
    "gn:feature_code":"PPL",
    "gn:name":"Higashidach\u014d",
    "gn:population":0,
    "gn:timezone":"Asia/Tokyo",
    "iso:country":"JP",
    "name:jpn_x_preferred":[
        "\u6771\u7530\u753a"
    ],
    "name:und_x_variant":[
        "Higashidach\u014d"
    ],
    "wof:name":"Higashidacho",
    "wof:placetype":"locality"
},
  "geometry": {"coordinates":[139.70248999999998,35.5288],"type":"Point"}
}