{
  "type": "Feature",
  "properties": {
    "gn:admin1_code":"19.0",
    "gn:admin2_code":"1848350.0",
    "gn:admin3_code":"14104.0",
    "gn:asciiname":"Kashiwaba",
    "gn:country_code":"JP",
    "gn:dem":30,
    "gn:feature_class":"P",
    "gn:feature_code":"PPL",
    "gn:name":"Kashiwaba",
    "gn:population":0,
    "gn:timezone":"Asia/Tokyo",
    "iso:country":"JP",
    "name:jpn_x_preferred":[
        "\u67cf\u8449"
    ],
    "name:jpn_x_variant":[
        "\u304b\u3057\u308f\u3070",
        "\u30ab\u30b7\u30ef\u30d0"
    ],
    "wof:name":"Kashiwaba",
    "wof:placetype":"locality"
},
  "geometry": {"coordinates":[139.64230000000001,35.43193],"type":"Point"}
}