{
  "type": "Feature",
  "properties": {
    "gn:admin1_code":"4.0",
    "gn:admin2_code":"2112386.0",
    "gn:asciiname":"Uenoshiba",
    "gn:country_code":"JP",
    "gn:dem":15,
    "gn:feature_class":"P",
    "gn:feature_code":"PPLL",
    "gn:name":"Uenoshiba",
    "gn:population":0,
    "gn:timezone":"Asia/Tokyo",
    "iso:country":"JP",
    "name:jpn_x_preferred":[
        "\u4e0a\u829d"
    ],
    "name:jpn_x_variant":[
        "\u3046\u3048\u306e\u3057\u3070",
        "\u30a6\u30a8\u30ce\u30b7\u30d0"
    ],
    "wof:name":"Uenoshiba",
    "wof:placetype":"locality"
},
  "geometry": {"coordinates":[140.10461000000001,35.12298],"type":"Point"}
}