{
  "type": "Feature",
  "properties": {
    "gn:admin1_code":"28.0",
    "gn:admin2_code":"1861747.0",
    "gn:asciiname":"Higashiikoma",
    "gn:country_code":"JP",
    "gn:dem":159,
    "gn:feature_class":"P",
    "gn:feature_code":"PPL",
    "gn:name":"Higashiikoma",
    "gn:population":0,
    "gn:timezone":"Asia/Tokyo",
    "iso:country":"JP",
    "name:jpn_x_preferred":[
        "\u6771\u751f\u99d2"
    ],
    "wof:name":"Higashiikoma",
    "wof:placetype":"locality"
},
  "geometry": {"coordinates":[135.71704,34.6808],"type":"Point"}
}