{
  "type": "Feature",
  "properties": {
    "gn:admin1_code":"23.0",
    "gn:admin2_code":"1848873.0",
    "gn:admin3_code":"24471.0",
    "gn:asciiname":"Funaki",
    "gn:country_code":"JP",
    "gn:dem":100,
    "gn:feature_class":"P",
    "gn:feature_code":"PPLL",
    "gn:name":"Funaki",
    "gn:population":0,
    "gn:timezone":"Asia/Tokyo",
    "iso:country":"JP",
    "name:jpn_x_preferred":[
        "\u8239\u6728"
    ],
    "wof:name":"Funaki",
    "wof:placetype":"locality"
},
  "geometry": {"coordinates":[136.41038999999998,34.38873],"type":"Point"}
}