{
  "type": "Feature",
  "properties": {
    "iso:country":"JP",
    "name:eng_x_preferred":[
        "Kaichi 2 Chome"
    ],
    "name:eng_x_variant":[
        "Kaichi 2 Choume",
        "Kaichi 2 Chome"
    ],
    "name:jpn_x_preferred":[
        "\uff12\u4e01\u76ee"
    ],
    "name:jpn_x_variant":[
        "\u304b\u3044\u3061 \uff12\u3061\u3087\u3046\u3081",
        "\u958b\u667a \uff12\u4e01\u76ee",
        "\uff12\u3061\u3087\u3046\u3081"
    ],
    "qs:gn_local":0,
    "qs:local_max":1129,
    "qs:local_sum":4513,
    "qs:localhoods":19,
    "qs:name":"\uff12\u4e01\u76ee",
    "qs:name_adm0":"\u65e5\u672c",
    "qs:name_adm1":"\u9577\u91ce\u770c",
    "qs:name_en":"Kaichi 2 Chome",
    "qs:name_lau":"\u958b\u667a",
    "qs:name_local":"\u677e\u672c\u5e02",
    "qs:photo_max":34,
    "qs:photo_sum":144,
    "qs:placetype":"Suburb",
    "qs:quad_count":9,
    "qs:woe_adm0":23424856,
    "qs:woe_adm1":2345875,
    "qs:woe_adm2":0,
    "qs:woe_lau":28431544,
    "qs:woe_local":1117683,
    "qs:woe_ver":"7.10.0",
    "wof:lang":[
        "jpn"
    ],
    "wof:name":"\uff12\u4e01\u76ee",
    "wof:placetype":"neighbourhood"
},
  "geometry": {"coordinates":[137.97104400000001,36.240415],"type":"Point"}
}