{
  "type": "Feature",
  "properties": {
    "gn:admin1_code":"4.0",
    "gn:admin2_code":"2112557.0",
    "gn:admin3_code":"12443.0",
    "gn:asciiname":"Kamifuse",
    "gn:country_code":"JP",
    "gn:dem":39,
    "gn:feature_class":"P",
    "gn:feature_code":"PPL",
    "gn:name":"Kamifuse",
    "gn:population":0,
    "gn:timezone":"Asia/Tokyo",
    "iso:country":"JP",
    "name:jpn_x_preferred":[
        "\u4e0a\u5e03\u65bd"
    ],
    "name:jpn_x_variant":[
        "\u304b\u307f\u3075\u305b",
        "\u30ab\u30df\u30d5\u30bb"
    ],
    "wof:name":"Kamifuse",
    "wof:placetype":"locality"
},
  "geometry": {"coordinates":[140.33843000000002,35.21165],"type":"Point"}
}