{
  "type": "Feature",
  "properties": {
    "gn:admin1_code":"36",
    "gn:admin2_code":"1857549.0",
    "gn:asciiname":"Adakae",
    "gn:country_code":"JP",
    "gn:dem":2,
    "gn:feature_class":"P",
    "gn:feature_code":"PPL",
    "gn:name":"Adakae",
    "gn:population":0,
    "gn:timezone":"Asia/Tokyo",
    "iso:country":"JP",
    "name:jpn_x_preferred":[
        "\u51fa\u96f2\u90f7\u3000"
    ],
    "name:und_x_variant":[
        "Adakai",
        "Adakaya",
        "Adakae"
    ],
    "wof:name":"Adakae",
    "wof:placetype":"locality"
},
  "geometry": {"coordinates":[133.13229999999999,35.43148],"type":"Point"}
}