{
  "type": "Feature",
  "properties": {
    "gn:admin1_code":"23.0",
    "gn:admin2_code":"1857496.0",
    "gn:asciiname":"Iitakacho-tominaga",
    "gn:country_code":"JP",
    "gn:dem":230,
    "gn:feature_class":"P",
    "gn:feature_code":"PPL",
    "gn:name":"Iitakach\u014d-tominaga",
    "gn:population":0,
    "gn:timezone":"Asia/Tokyo",
    "iso:country":"JP",
    "name:jpn_x_preferred":[
        "\u98ef\u9ad8\u753a\u5bcc\u6c38"
    ],
    "name:und_x_variant":[
        "Iitakach\u014d-tominaga"
    ],
    "wof:name":"Iitakacho-tominaga",
    "wof:placetype":"locality"
},
  "geometry": {"coordinates":[136.23602,34.41826],"type":"Point"}
}