{
  "type": "Feature",
  "properties": {
    "gn:admin1_code":"47",
    "gn:admin2_code":"1856061.0",
    "gn:asciiname":"Koki",
    "gn:country_code":"JP",
    "gn:dem":7,
    "gn:feature_class":"P",
    "gn:feature_code":"PPL",
    "gn:name":"K\u014dki",
    "gn:population":0,
    "gn:timezone":"Asia/Tokyo",
    "iso:country":"JP",
    "name:ceb_x_preferred":[
        "Koki"
    ],
    "name:deu_x_preferred":[
        "Koki"
    ],
    "name:ita_x_preferred":[
        "Koki"
    ],
    "name:jpn_x_preferred":[
        "\u5e78\u559c"
    ],
    "name:jpn_x_variant":[
        "Koki"
    ],
    "name:swe_x_preferred":[
        "Koki"
    ],
    "name:und_x_variant":[
        "K\u00f4ti",
        "K\u014dchi",
        "K\u014dki"
    ],
    "wof:name":"Koki",
    "wof:placetype":"locality"
},
  "geometry": {"coordinates":[127.95021,26.53918],"type":"Point"}
}