{
  "type": "Feature",
  "properties": {
    "gn:admin1_code":"19.0",
    "gn:admin2_code":"1860670.0",
    "gn:asciiname":"Sugimoto",
    "gn:country_code":"JP",
    "gn:dem":20,
    "gn:feature_class":"P",
    "gn:feature_code":"PPLL",
    "gn:name":"Sugimoto",
    "gn:population":0,
    "gn:timezone":"Asia/Tokyo",
    "iso:country":"JP",
    "name:ces_x_preferred":[
        "Sugimoto"
    ],
    "name:jpn_x_preferred":[
        "\u6749\u672c"
    ],
    "name:jpn_x_variant":[
        "\u3059\u304e\u3082\u3068",
        "\u30b9\u30ae\u30e2\u30c8"
    ],
    "wof:name":"Sugimoto",
    "wof:placetype":"locality"
},
  "geometry": {"coordinates":[139.56623000000002,35.32277],"type":"Point"}
}