{
  "type": "Feature",
  "properties": {
    "gn:admin1_code":"45",
    "gn:admin2_code":"1863413.0",
    "gn:asciiname":"Nakayama",
    "gn:country_code":"JP",
    "gn:dem":183,
    "gn:feature_class":"P",
    "gn:feature_code":"PPL",
    "gn:name":"Nakayama",
    "gn:population":0,
    "gn:timezone":"Asia/Tokyo",
    "iso:country":"JP",
    "wof:name":"Nakayama",
    "wof:placetype":"locality"
},
  "geometry": {"coordinates":[131.53333000000001,34.46667],"type":"Point"}
}