{
  "type": "Feature",
  "properties": {
    "gn:admin1_code":"19.0",
    "gn:admin2_code":"1848350.0",
    "gn:admin3_code":"14105.0",
    "gn:asciiname":"Gumyojicho",
    "gn:country_code":"JP",
    "gn:dem":5,
    "gn:feature_class":"P",
    "gn:feature_code":"PPL",
    "gn:name":"Gumy\u014djich\u014d",
    "gn:population":0,
    "gn:timezone":"Asia/Tokyo",
    "iso:country":"JP",
    "name:jpn_x_preferred":[
        "\u5f18\u660e\u5bfa\u753a"
    ],
    "name:jpn_x_variant":[
        "\u3050\u307f\u3087\u3046\u3058\u3061\u3087\u3046",
        "\u30b0\u30df\u30e7\u30a6\u30b8\u30c1\u30e7\u30a6"
    ],
    "name:und_x_variant":[
        "Gumy\u014djich\u014d"
    ],
    "wof:name":"Gumyojicho",
    "wof:placetype":"locality"
},
  "geometry": {"coordinates":[139.59966,35.42383],"type":"Point"}
}