{
  "type": "Feature",
  "properties": {
    "gn:admin1_code":"31",
    "gn:admin2_code":"1849518.0",
    "gn:asciiname":"Yanagi",
    "gn:cc2":"JP",
    "gn:country_code":"JP",
    "gn:dem":324,
    "gn:feature_class":"P",
    "gn:feature_code":"PPL",
    "gn:name":"Yanagi",
    "gn:population":0,
    "gn:timezone":"Asia/Tokyo",
    "iso:country":"JP",
    "name:und_x_variant":[
        "Futayanagi",
        "Yanagi"
    ],
    "wof:name":"Yanagi",
    "wof:placetype":"locality"
},
  "geometry": {"coordinates":[133.88333,35.05],"type":"Point"}
}