{
  "type": "Feature",
  "properties": {
    "gn:admin1_code":"3.0",
    "gn:admin2_code":"2130056.0",
    "gn:asciiname":"Motodaikumachi",
    "gn:country_code":"JP",
    "gn:dem":49,
    "gn:feature_class":"P",
    "gn:feature_code":"PPL",
    "gn:name":"Motodaikumachi",
    "gn:population":0,
    "gn:timezone":"Asia/Tokyo",
    "iso:country":"JP",
    "name:jpn_x_preferred":[
        "\u5143\u5927\u5de5\u753a"
    ],
    "name:jpn_x_variant":[
        "\u3082\u3068\u3060\u3044\u304f\u307e\u3061",
        "\u30e2\u30c8\u30c0\u30a4\u30af\u30de\u30c1"
    ],
    "wof:name":"Motodaikumachi",
    "wof:placetype":"locality"
},
  "geometry": {"coordinates":[140.46623,40.6022],"type":"Point"}
}