{
  "type": "Feature",
  "properties": {
    "gn:admin1_code":"20",
    "gn:admin2_code":"1856197.0",
    "gn:admin3_code":"39344.0",
    "gn:asciiname":"Sugi",
    "gn:country_code":"JP",
    "gn:dem":314,
    "gn:feature_class":"P",
    "gn:feature_code":"PPL",
    "gn:name":"Sugi",
    "gn:population":0,
    "gn:timezone":"Asia/Tokyo",
    "iso:country":"JP",
    "name:jpn_x_preferred":[
        "\u6749"
    ],
    "name:und_x_variant":[
        "\u014csugi"
    ],
    "wof:name":"Sugi",
    "wof:placetype":"locality"
},
  "geometry": {"coordinates":[133.66236000000001,33.75331],"type":"Point"}
}