{
  "type": "Feature",
  "properties": {
    "gn:admin1_code":"3.0",
    "gn:admin2_code":"2130654.0",
    "gn:asciiname":"Shinoda",
    "gn:country_code":"JP",
    "gn:dem":4,
    "gn:feature_class":"P",
    "gn:feature_code":"PPL",
    "gn:name":"Shinoda",
    "gn:population":0,
    "gn:timezone":"Asia/Tokyo",
    "iso:country":"JP",
    "name:jpn_x_preferred":[
        "\u7be0\u7530"
    ],
    "name:jpn_x_variant":[
        "\u3057\u306e\u3060",
        "\u30b7\u30ce\u30c0"
    ],
    "wof:name":"Shinoda",
    "wof:placetype":"locality"
},
  "geometry": {"coordinates":[140.72655,40.828],"type":"Point"}
}