{
  "type": "Feature",
  "properties": {
    "gn:admin1_code":"21.0",
    "gn:admin2_code":"1864973.0",
    "gn:asciiname":"Kashinomure",
    "gn:country_code":"JP",
    "gn:dem":735,
    "gn:feature_class":"P",
    "gn:feature_code":"PPLL",
    "gn:name":"Kashinomure",
    "gn:population":0,
    "gn:timezone":"Asia/Tokyo",
    "iso:country":"JP",
    "name:jpn_x_preferred":[
        "\u5408\u6226\u7fa4"
    ],
    "name:jpn_x_variant":[
        "\u304b\u3057\u306e\u3080\u308c",
        "\u30ab\u30b7\u30ce\u30e0\u30ec"
    ],
    "wof:name":"Kashinomure",
    "wof:placetype":"locality"
},
  "geometry": {"coordinates":[131.12846000000002,33.04223],"type":"Point"}
}