{
  "type": "Feature",
  "properties": {
    "gn:admin1_code":"21.0",
    "gn:admin2_code":"1858418.0",
    "gn:admin3_code":"43104.0",
    "gn:asciiname":"Midorimachi",
    "gn:country_code":"JP",
    "gn:dem":-2,
    "gn:feature_class":"P",
    "gn:feature_code":"PPL",
    "gn:name":"Midorimachi",
    "gn:population":0,
    "gn:timezone":"Asia/Tokyo",
    "iso:country":"JP",
    "name:jpn_x_preferred":[
        "\u7f8e\u767b\u91cc\u753a"
    ],
    "name:jpn_x_variant":[
        "\u307f\u3069\u308a\u307e\u3061",
        "\u30df\u30c9\u30ea\u30de\u30c1"
    ],
    "wof:name":"Midorimachi",
    "wof:placetype":"locality"
},
  "geometry": {"coordinates":[130.65711999999999,32.73228],"type":"Point"}
}