{
  "type": "Feature",
  "properties": {
    "gn:admin1_code":"26",
    "gn:admin2_code":"7416554.0",
    "gn:admin3_code":"20430.0",
    "gn:asciiname":"Suhara",
    "gn:country_code":"JP",
    "gn:dem":538,
    "gn:feature_class":"P",
    "gn:feature_code":"PPL",
    "gn:name":"Suhara",
    "gn:population":0,
    "gn:timezone":"Asia/Tokyo",
    "iso:country":"JP",
    "wof:name":"Suhara",
    "wof:placetype":"locality"
},
  "geometry": {"coordinates":[137.69336999999999,35.69857000000001],"type":"Point"}
}