{
  "type": "Feature",
  "properties": {
    "gn:admin1_code":"27",
    "gn:admin2_code":"7418810.0",
    "gn:asciiname":"Kamitsushimacho-ashimi",
    "gn:country_code":"JP",
    "gn:dem":1,
    "gn:feature_class":"P",
    "gn:feature_code":"PPL",
    "gn:name":"Kamitsushimach\u014d-ashimi",
    "gn:population":0,
    "gn:timezone":"Asia/Tokyo",
    "iso:country":"JP",
    "name:jpn_x_preferred":[
        "\u4e0a\u5bfe\u99ac\u753a\u82a6\u898b"
    ],
    "name:und_x_variant":[
        "Kamitsushimach\u014d-ashimi",
        "Ashimi"
    ],
    "wof:name":"Kamitsushimacho-ashimi",
    "wof:placetype":"locality"
},
  "geometry": {"coordinates":[129.45166,34.53701],"type":"Point"}
}