{
  "type": "Feature",
  "properties": {
    "gn:admin1_code":"21.0",
    "gn:admin2_code":"1850743.0",
    "gn:asciiname":"Kamizaki",
    "gn:country_code":"JP",
    "gn:dem":-1,
    "gn:feature_class":"P",
    "gn:feature_code":"PPLL",
    "gn:name":"Kamizaki",
    "gn:population":0,
    "gn:timezone":"Asia/Tokyo",
    "iso:country":"JP",
    "name:jpn_x_preferred":[
        "\u795e\u5d0e"
    ],
    "name:jpn_x_variant":[
        "\u304b\u307f\u3056\u304d",
        "\u30ab\u30df\u30b6\u30ad"
    ],
    "wof:name":"Kamizaki",
    "wof:placetype":"locality"
},
  "geometry": {"coordinates":[130.54335,32.88015],"type":"Point"}
}