{
  "type": "Feature",
  "properties": {
    "iso:country":"JP",
    "name:eng_x_preferred":[
        "Tokiwadori 3 Chome"
    ],
    "name:eng_x_variant":[
        "Tokiwadoori 3 Choume",
        "Tokiwadori 3 Chome"
    ],
    "name:jpn_x_preferred":[
        "\uff13\u4e01\u76ee"
    ],
    "name:jpn_x_variant":[
        "\u3068\u304d\u308f\u3069\u304a\u308a \uff13\u3061\u3087\u3046\u3081",
        "\u5e38\u76e4\u901a \uff13\u4e01\u76ee",
        "\uff13\u3061\u3087\u3046\u3081"
    ],
    "name:unk_x_variant":[
        "\uff13\u4e01\u76ee"
    ],
    "qs:gn_local":0,
    "qs:local_max":1584,
    "qs:local_sum":2444,
    "qs:localhoods":13,
    "qs:name":"\uff13\u4e01\u76ee",
    "qs:name_adm0":"\u65e5\u672c",
    "qs:name_adm1":"\u5317\u6d77\u9053",
    "qs:name_en":"Tokiwadori 3 Chome",
    "qs:name_lau":"\u5e38\u76e4\u901a",
    "qs:name_local":"\u65ed\u5ddd\u5e02",
    "qs:photo_max":21,
    "qs:photo_sum":22,
    "qs:placetype":"Suburb",
    "qs:quad_count":2,
    "qs:woe_adm0":23424856,
    "qs:woe_adm1":7153351,
    "qs:woe_adm2":0,
    "qs:woe_lau":28380570,
    "qs:woe_local":1116988,
    "qs:woe_ver":"7.10.0",
    "wof:lang":[
        "jpn"
    ],
    "wof:name":"\uff13\u4e01\u76ee",
    "wof:placetype":"neighbourhood"
},
  "geometry": {"coordinates":[142.35834,43.777044],"type":"Point"}
}