{
  "type": "Feature",
  "properties": {
    "gn:admin1_code":"19.0",
    "gn:admin2_code":"1848350.0",
    "gn:admin3_code":"14113.0",
    "gn:asciiname":"Nishihassakucho",
    "gn:country_code":"JP",
    "gn:dem":41,
    "gn:feature_class":"P",
    "gn:feature_code":"PPL",
    "gn:name":"Nishihassakuch\u014d",
    "gn:population":0,
    "gn:timezone":"Asia/Tokyo",
    "iso:country":"JP",
    "name:jpn_x_preferred":[
        "\u897f\u516b\u6714\u753a"
    ],
    "name:und_x_variant":[
        "Nishihassakuch\u014d"
    ],
    "wof:name":"Nishihassakucho",
    "wof:placetype":"locality"
},
  "geometry": {"coordinates":[139.52819,35.5294],"type":"Point"}
}