{
  "type": "Feature",
  "properties": {
    "gn:admin1_code":"19.0",
    "gn:admin2_code":"1848308.0",
    "gn:asciiname":"Kumura",
    "gn:country_code":"JP",
    "gn:dem":15,
    "gn:feature_class":"P",
    "gn:feature_code":"PPL",
    "gn:name":"Kumura",
    "gn:population":0,
    "gn:timezone":"Asia/Tokyo",
    "iso:country":"JP",
    "name:jpn_x_preferred":[
        "\u4e45\u6751"
    ],
    "name:jpn_x_variant":[
        "\u304f\u3080\u3089",
        "\u30af\u30e0\u30e9"
    ],
    "wof:name":"Kumura",
    "wof:placetype":"locality"
},
  "geometry": {"coordinates":[139.6926,35.22984],"type":"Point"}
}