{
  "type": "Feature",
  "properties": {
    "gn:admin1_code":"2.0",
    "gn:admin2_code":"2129593.0",
    "gn:asciiname":"Dobukai",
    "gn:country_code":"JP",
    "gn:dem":102,
    "gn:feature_class":"P",
    "gn:feature_code":"PPL",
    "gn:name":"Dobukai",
    "gn:population":0,
    "gn:timezone":"Asia/Tokyo",
    "iso:country":"JP",
    "name:jpn_x_preferred":[
        "\u571f\u6df1\u4e95"
    ],
    "name:jpn_x_variant":[
        "\u3069\u3076\u304b\u3044",
        "\u30c9\u30d6\u30ab\u30a4"
    ],
    "wof:name":"Dobukai",
    "wof:placetype":"locality"
},
  "geometry": {"coordinates":[140.71639999999999,40.22011],"type":"Point"}
}