{
  "type": "Feature",
  "properties": {
    "gn:admin1_code":"37.0",
    "gn:admin2_code":"1864104.0",
    "gn:asciiname":"Ishinomiya",
    "gn:country_code":"JP",
    "gn:dem":59,
    "gn:feature_class":"P",
    "gn:feature_code":"PPLL",
    "gn:name":"Ishinomiya",
    "gn:population":0,
    "gn:timezone":"Asia/Tokyo",
    "iso:country":"JP",
    "name:jpn_x_preferred":[
        "\u77f3\u306e\u5bae"
    ],
    "wof:name":"Ishinomiya",
    "wof:placetype":"locality"
},
  "geometry": {"coordinates":[138.63871,35.19424],"type":"Point"}
}