{
  "type": "Feature",
  "properties": {
    "gn:admin1_code":"44.0",
    "gn:admin2_code":"2111620.0",
    "gn:admin3_code":"6322.0",
    "gn:asciiname":"Mazawa",
    "gn:country_code":"JP",
    "gn:dem":285,
    "gn:feature_class":"P",
    "gn:feature_code":"PPL",
    "gn:name":"Mazawa",
    "gn:population":0,
    "gn:timezone":"Asia/Tokyo",
    "iso:country":"JP",
    "name:jpn_x_preferred":[
        "\u9593\u6ca2"
    ],
    "wof:name":"Mazawa",
    "wof:placetype":"locality"
},
  "geometry": {"coordinates":[140.12833000000001,38.43827],"type":"Point"}
}