{
  "type": "Feature",
  "properties": {
    "gn:admin1_code":"21.0",
    "gn:admin2_code":"1864975.0",
    "gn:admin3_code":"43428.0",
    "gn:asciiname":"Kawaji",
    "gn:country_code":"JP",
    "gn:dem":775,
    "gn:feature_class":"P",
    "gn:feature_code":"PPLL",
    "gn:name":"Kawaji",
    "gn:population":0,
    "gn:timezone":"Asia/Tokyo",
    "iso:country":"JP",
    "name:jpn_x_preferred":[
        "\u6cb3\u5730"
    ],
    "name:jpn_x_variant":[
        "\u304b\u308f\u3062",
        "\u30ab\u30ef\u30c2"
    ],
    "wof:name":"Kawaji",
    "wof:placetype":"locality"
},
  "geometry": {"coordinates":[131.2627,32.82435],"type":"Point"}
}