{
  "type": "Feature",
  "properties": {
    "gn:admin1_code":"12.0",
    "gn:admin2_code":"2129370.0",
    "gn:asciiname":"Jisuicho",
    "gn:country_code":"JP",
    "gn:dem":8,
    "gn:feature_class":"P",
    "gn:feature_code":"PPL",
    "gn:name":"Jisuich\u014d",
    "gn:population":0,
    "gn:timezone":"Asia/Tokyo",
    "iso:country":"JP",
    "name:jpn_x_preferred":[
        "\u6cbb\u6c34\u753a"
    ],
    "name:jpn_x_variant":[
        "\u3058\u3059\u3044\u3061\u3087\u3046",
        "\u30b8\u30b9\u30a4\u30c1\u30e7\u30a6"
    ],
    "name:und_x_variant":[
        "Jisuich\u014d"
    ],
    "wof:name":"Jisuicho",
    "wof:placetype":"locality"
},
  "geometry": {"coordinates":[144.37129999999999,43.0089],"type":"Point"}
}