{
  "type": "Feature",
  "properties": {
    "gn:admin1_code":"4.0",
    "gn:admin2_code":"1863711.0",
    "gn:asciiname":"Aohori",
    "gn:country_code":"JP",
    "gn:dem":10,
    "gn:feature_class":"P",
    "gn:feature_code":"PPLL",
    "gn:name":"Aohori",
    "gn:population":0,
    "gn:timezone":"Asia/Tokyo",
    "iso:country":"JP",
    "name:jpn_x_preferred":[
        "\u9752\u5800"
    ],
    "name:jpn_x_variant":[
        "\u3042\u304a\u307b\u308a",
        "\u30a2\u30aa\u30db\u30ea"
    ],
    "wof:name":"Aohori",
    "wof:placetype":"locality"
},
  "geometry": {"coordinates":[139.85574,35.32971],"type":"Point"}
}