{
  "type": "Feature",
  "properties": {
    "iso:country":"JP",
    "name:eng_x_preferred":[
        "Sotokanda 3 Chome"
    ],
    "name:eng_x_variant":[
        "Sotokanda 3 Choume",
        "Sotokanda 3 Chome"
    ],
    "name:jpn_x_preferred":[
        "\uff13\u4e01\u76ee"
    ],
    "name:jpn_x_variant":[
        "\u305d\u3068\u304b\u3093\u3060 \uff13\u3061\u3087\u3046\u3081",
        "\u5916\u795e\u7530 \uff13\u4e01\u76ee",
        "\uff13\u3061\u3087\u3046\u3081"
    ],
    "qs:gn_adm0_cc":"JP",
    "qs:gn_local":1850147,
    "qs:local_max":18112,
    "qs:local_sum":895907,
    "qs:localhoods":857,
    "qs:name":"\uff13\u4e01\u76ee",
    "qs:name_adm0":"\u65e5\u672c",
    "qs:name_adm1":"\u6771\u4eac\u90fd",
    "qs:name_adm2":"\u5343\u4ee3\u7530\u533a",
    "qs:name_en":"Sotokanda 3 Chome",
    "qs:name_lau":"\u5916\u795e\u7530",
    "qs:name_local":"\u6771\u4eac",
    "qs:photo_max":954,
    "qs:photo_sum":4807,
    "qs:placetype":"Suburb",
    "qs:quad_count":16,
    "qs:woe_adm0":23424856,
    "qs:woe_adm1":2345889,
    "qs:woe_adm2":15015499,
    "qs:woe_lau":28413953,
    "qs:woe_local":1118370,
    "qs:woe_ver":"7.10.0",
    "wof:lang":[
        "jpn"
    ],
    "wof:name":"\uff13\u4e01\u76ee",
    "wof:placetype":"neighbourhood"
},
  "geometry": {"coordinates":[139.77069399999999,35.701264],"type":"Point"}
}