{
  "type": "Feature",
  "properties": {
    "gn:admin1_code":"39",
    "gn:admin2_code":"7406323.0",
    "gn:admin3_code":"36368.0",
    "gn:asciiname":"Kawamata",
    "gn:country_code":"JP",
    "gn:dem":310,
    "gn:feature_class":"P",
    "gn:feature_code":"PPL",
    "gn:name":"Kawamata",
    "gn:population":0,
    "gn:timezone":"Asia/Tokyo",
    "iso:country":"JP",
    "name:jpn_x_preferred":[
        "\u5ddd\u4fe3"
    ],
    "wof:name":"Kawamata",
    "wof:placetype":"locality"
},
  "geometry": {"coordinates":[134.3409,33.76055],"type":"Point"}
}