{
  "type": "Feature",
  "properties": {
    "gn:admin1_code":"16.0",
    "gn:admin2_code":"7441817.0",
    "gn:asciiname":"Ushirohanagai",
    "gn:country_code":"JP",
    "gn:dem":41,
    "gn:feature_class":"P",
    "gn:feature_code":"PPL",
    "gn:name":"Ushirohanagai",
    "gn:population":0,
    "gn:timezone":"Asia/Tokyo",
    "iso:country":"JP",
    "name:jpn_x_preferred":[
        "\u5f8c\u82b1\u8c9d"
    ],
    "name:jpn_x_variant":[
        "\u3046\u3057\u308d\u306f\u306a\u304c\u3044",
        "\u30a6\u30b7\u30ed\u30cf\u30ca\u30ac\u30a4"
    ],
    "wof:name":"Ushirohanagai",
    "wof:placetype":"locality"
},
  "geometry": {"coordinates":[141.69544999999999,38.97233],"type":"Point"}
}