{
  "type": "Feature",
  "properties": {
    "gn:admin1_code":"21.0",
    "gn:admin2_code":"7413150.0",
    "gn:asciiname":"Ozaka",
    "gn:country_code":"JP",
    "gn:dem":91,
    "gn:feature_class":"P",
    "gn:feature_code":"PPL",
    "gn:name":"Ozaka",
    "gn:population":0,
    "gn:timezone":"Asia/Tokyo",
    "iso:country":"JP",
    "name:jpn_x_preferred":[
        "\u5c0f\u5742"
    ],
    "name:jpn_x_variant":[
        "\u304a\u3056\u304b",
        "\u30aa\u30b6\u30ab"
    ],
    "wof:name":"Ozaka",
    "wof:placetype":"locality"
},
  "geometry": {"coordinates":[130.71190000000001,33.07308],"type":"Point"}
}