{
  "type": "Feature",
  "properties": {
    "gn:admin1_code":"21.0",
    "gn:admin2_code":"7412708.0",
    "gn:admin3_code":"43505.0",
    "gn:asciiname":"Minoda",
    "gn:country_code":"JP",
    "gn:dem":169,
    "gn:feature_class":"P",
    "gn:feature_code":"PPLL",
    "gn:name":"Minoda",
    "gn:population":0,
    "gn:timezone":"Asia/Tokyo",
    "iso:country":"JP",
    "name:jpn_x_preferred":[
        "\u84d1\u7530"
    ],
    "name:jpn_x_variant":[
        "\u307f\u306e\u3060",
        "\u30df\u30ce\u30c0"
    ],
    "wof:name":"Minoda",
    "wof:placetype":"locality"
},
  "geometry": {"coordinates":[130.94503999999998,32.27723],"type":"Point"}
}