{
  "type": "Feature",
  "properties": {
    "gn:admin1_code":"21.0",
    "gn:admin2_code":"7412706.0",
    "gn:admin3_code":"43444.0",
    "gn:asciiname":"Usazono",
    "gn:country_code":"JP",
    "gn:dem":27,
    "gn:feature_class":"P",
    "gn:feature_code":"PPLL",
    "gn:name":"Usazono",
    "gn:population":0,
    "gn:timezone":"Asia/Tokyo",
    "iso:country":"JP",
    "name:jpn_x_preferred":[
        "\u5b87\u4f50\u5712"
    ],
    "name:jpn_x_variant":[
        "\u3046\u3055\u305e\u306e",
        "\u30a6\u30b5\u30be\u30ce"
    ],
    "name:und_x_variant":[
        "Usadon"
    ],
    "wof:name":"Usazono",
    "wof:placetype":"locality"
},
  "geometry": {"coordinates":[130.81391000000002,32.67209],"type":"Point"}
}