{
  "type": "Feature",
  "properties": {
    "gn:admin1_code":"4.0",
    "gn:admin2_code":"2112663.0",
    "gn:asciiname":"Shimoyata",
    "gn:country_code":"JP",
    "gn:dem":36,
    "gn:feature_class":"P",
    "gn:feature_code":"PPL",
    "gn:name":"Shimoyata",
    "gn:population":0,
    "gn:timezone":"Asia/Tokyo",
    "iso:country":"JP",
    "name:jpn_x_preferred":[
        "\u4e0b\u77e2\u7530"
    ],
    "name:jpn_x_variant":[
        "\u3057\u3082\u3084\u305f",
        "\u30b7\u30e2\u30e4\u30bf"
    ],
    "wof:name":"Shimoyata",
    "wof:placetype":"locality"
},
  "geometry": {"coordinates":[140.15870000000001,35.3897],"type":"Point"}
}