{
  "type": "Feature",
  "properties": {
    "gn:admin1_code":"2.0",
    "gn:admin2_code":"2113122.0",
    "gn:asciiname":"Higashidori-tatenokoshi",
    "gn:country_code":"JP",
    "gn:dem":7,
    "gn:feature_class":"P",
    "gn:feature_code":"PPL",
    "gn:name":"Higashid\u014dri-tatenokoshi",
    "gn:population":0,
    "gn:timezone":"Asia/Tokyo",
    "iso:country":"JP",
    "name:jpn_x_preferred":[
        "\u6771\u901a\u9928\u30ce\u8d8a"
    ],
    "name:jpn_x_variant":[
        "\u3072\u304c\u3057\u3069\u304a\u308a\u305f\u3066\u306e\u3053\u3057",
        "\u30d2\u30ac\u30b7\u30c9\u30aa\u30ea\u30bf\u30c6\u30ce\u30b3\u30b7"
    ],
    "name:und_x_variant":[
        "Higashid\u014dri-tatenokoshi"
    ],
    "wof:name":"Higashidori-tatenokoshi",
    "wof:placetype":"locality"
},
  "geometry": {"coordinates":[140.13081,39.70962],"type":"Point"}
}