{
  "type": "Feature",
  "properties": {
    "gn:admin1_code":"34.0",
    "gn:admin2_code":"8304213.0",
    "gn:asciiname":"Mashito",
    "gn:country_code":"JP",
    "gn:dem":8,
    "gn:feature_class":"P",
    "gn:feature_code":"PPL",
    "gn:name":"Mashito",
    "gn:population":0,
    "gn:timezone":"Asia/Tokyo",
    "iso:country":"JP",
    "name:jpn_x_preferred":[
        "\u5897\u6238"
    ],
    "name:jpn_x_variant":[
        "\u307e\u3057\u3068",
        "\u30de\u30b7\u30c8"
    ],
    "wof:name":"Mashito",
    "wof:placetype":"locality"
},
  "geometry": {"coordinates":[139.72506999999999,35.95737000000001],"type":"Point"}
}