{
  "type": "Feature",
  "properties": {
    "gn:admin1_code":"21.0",
    "gn:admin2_code":"1865358.0",
    "gn:asciiname":"Oshima",
    "gn:country_code":"JP",
    "gn:dem":30,
    "gn:feature_class":"P",
    "gn:feature_code":"PPLL",
    "gn:name":"\u014cshima",
    "gn:population":0,
    "gn:timezone":"Asia/Tokyo",
    "iso:country":"JP",
    "name:jpn_x_preferred":[
        "\u5927\u5cf6"
    ],
    "name:jpn_x_variant":[
        "\u304a\u304a\u3057\u307e",
        "\u30aa\u30aa\u30b7\u30de"
    ],
    "name:und_x_variant":[
        "\u014cshima"
    ],
    "wof:name":"Oshima",
    "wof:placetype":"locality"
},
  "geometry": {"coordinates":[130.1885,32.53797],"type":"Point"}
}