{
  "type": "Feature",
  "properties": {
    "gn:admin1_code":"29",
    "gn:admin2_code":"7468179.0",
    "gn:asciiname":"Watariba",
    "gn:country_code":"JP",
    "gn:dem":20,
    "gn:feature_class":"P",
    "gn:feature_code":"PPL",
    "gn:name":"Watariba",
    "gn:population":0,
    "gn:timezone":"Asia/Tokyo",
    "iso:country":"JP",
    "name:jpn_x_preferred":[
        "\u6e21\u5834"
    ],
    "wof:name":"Watariba",
    "wof:placetype":"locality"
},
  "geometry": {"coordinates":[139.25,37.75],"type":"Point"}
}