{
  "type": "Feature",
  "properties": {
    "gn:admin1_code":"12.0",
    "gn:admin2_code":"7428116.0",
    "gn:admin3_code":"1607.0",
    "gn:asciiname":"Shiomicho",
    "gn:country_code":"JP",
    "gn:dem":46,
    "gn:feature_class":"P",
    "gn:feature_code":"PPL",
    "gn:name":"Shiomich\u014d",
    "gn:population":0,
    "gn:timezone":"Asia/Tokyo",
    "iso:country":"JP",
    "name:jpn_x_preferred":[
        "\u6f6e\u898b\u753a"
    ],
    "name:jpn_x_variant":[
        "\u3057\u304a\u307f\u3061\u3087\u3046",
        "\u30b7\u30aa\u30df\u30c1\u30e7\u30a6"
    ],
    "name:und_x_variant":[
        "Shiomich\u014d"
    ],
    "wof:name":"Shiomicho",
    "wof:placetype":"locality"
},
  "geometry": {"coordinates":[142.77804,42.16475],"type":"Point"}
}