{
  "type": "Feature",
  "properties": {
    "gn:admin1_code":"09",
    "gn:admin2_code":"1850890.0",
    "gn:asciiname":"Kamitakaracho-miza",
    "gn:country_code":"JP",
    "gn:dem":531,
    "gn:feature_class":"P",
    "gn:feature_code":"PPL",
    "gn:name":"Kamitakarach\u014d-miza",
    "gn:population":0,
    "gn:timezone":"Asia/Tokyo",
    "iso:country":"JP",
    "name:jpn_x_preferred":[
        "\u4e0a\u5b9d\u753a\u898b\u5ea7"
    ],
    "name:und_x_variant":[
        "Kamitakarach\u014d-miza",
        "Miza"
    ],
    "wof:name":"Kamitakaracho-miza",
    "wof:placetype":"locality"
},
  "geometry": {"coordinates":[137.36821,36.29198],"type":"Point"}
}