{
  "type": "Feature",
  "properties": {
    "gn:admin1_code":"19.0",
    "gn:admin2_code":"1848350.0",
    "gn:admin3_code":"14102.0",
    "gn:asciiname":"Tanmachi",
    "gn:country_code":"JP",
    "gn:dem":11,
    "gn:feature_class":"P",
    "gn:feature_code":"PPL",
    "gn:name":"Tanmachi",
    "gn:population":0,
    "gn:timezone":"Asia/Tokyo",
    "iso:country":"JP",
    "name:jpn_x_preferred":[
        "\u53cd\u753a"
    ],
    "name:jpn_x_variant":[
        "\u305f\u3093\u307e\u3061",
        "\u30bf\u30f3\u30de\u30c1"
    ],
    "wof:name":"Tanmachi",
    "wof:placetype":"locality"
},
  "geometry": {"coordinates":[139.62846000000002,35.47622],"type":"Point"}
}