{
  "type": "Feature",
  "properties": {
    "gn:admin1_code":"25",
    "gn:admin2_code":"1862717.0",
    "gn:admin3_code":"45430.0",
    "gn:asciiname":"Mochida",
    "gn:cc2":"JP",
    "gn:country_code":"JP",
    "gn:dem":740,
    "gn:feature_class":"P",
    "gn:feature_code":"PPL",
    "gn:name":"Mochida",
    "gn:population":0,
    "gn:timezone":"Asia/Tokyo",
    "iso:country":"JP",
    "name:fra_x_preferred":[
        "Mochida"
    ],
    "name:und_x_variant":[
        "Motsuda"
    ],
    "wof:name":"Mochida",
    "wof:placetype":"locality"
},
  "geometry": {"coordinates":[131.15000000000001,32.46667],"type":"Point"}
}