{
  "type": "Feature",
  "properties": {
    "gn:admin1_code":"34.0",
    "gn:admin2_code":"1849187.0",
    "gn:admin3_code":"11110.0",
    "gn:asciiname":"Funai",
    "gn:country_code":"JP",
    "gn:dem":15,
    "gn:feature_class":"P",
    "gn:feature_code":"PPL",
    "gn:name":"Funai",
    "gn:population":0,
    "gn:timezone":"Asia/Tokyo",
    "iso:country":"JP",
    "name:jpn_x_preferred":[
        "\u5e9c\u5185"
    ],
    "name:jpn_x_variant":[
        "\u3075\u306a\u3044",
        "\u30d5\u30ca\u30a4"
    ],
    "wof:name":"Funai",
    "wof:placetype":"locality"
},
  "geometry": {"coordinates":[139.71408,35.94417],"type":"Point"}
}