{
  "type": "Feature",
  "properties": {
    "gn:admin1_code":"34.0",
    "gn:admin2_code":"1856987.0",
    "gn:asciiname":"Shinmisato-LaLa-City",
    "gn:country_code":"JP",
    "gn:dem":5,
    "gn:feature_class":"P",
    "gn:feature_code":"PPL",
    "gn:name":"Shinmisato-LaLa-City",
    "gn:population":0,
    "gn:timezone":"Asia/Tokyo",
    "iso:country":"JP",
    "name:jpn_x_preferred":[
        "\u65b0\u4e09\u90f7\u3089\u3089\u30b7\u30c6\u30a3"
    ],
    "wof:name":"Shinmisato-LaLa-City",
    "wof:placetype":"locality"
},
  "geometry": {"coordinates":[139.86746000000002,35.85831],"type":"Point"}
}