{
  "type": "Feature",
  "properties": {
    "gn:admin1_code":"7.0",
    "gn:admin2_code":"7406950.0",
    "gn:admin3_code":"40621.0",
    "gn:asciiname":"Torigoecho",
    "gn:country_code":"JP",
    "gn:dem":3,
    "gn:feature_class":"P",
    "gn:feature_code":"PPL",
    "gn:name":"Torigoech\u014d",
    "gn:population":0,
    "gn:timezone":"Asia/Tokyo",
    "iso:country":"JP",
    "name:jpn_x_preferred":[
        "\u9ce5\u8d8a\u753a"
    ],
    "name:und_x_variant":[
        "Torigoech\u014d"
    ],
    "wof:name":"Torigoecho",
    "wof:placetype":"locality"
},
  "geometry": {"coordinates":[130.99743999999998,33.81196],"type":"Point"}
}