{
  "type": "Feature",
  "properties": {
    "gn:admin1_code":"43.0",
    "gn:admin2_code":"7411114.0",
    "gn:asciiname":"Kishigawacho-nishiyama",
    "gn:country_code":"JP",
    "gn:dem":52,
    "gn:feature_class":"P",
    "gn:feature_code":"PPL",
    "gn:name":"Kishigawach\u014d-nishiyama",
    "gn:population":0,
    "gn:timezone":"Asia/Tokyo",
    "iso:country":"JP",
    "name:jpn_x_preferred":[
        "\u8cb4\u5fd7\u5ddd\u753a\u897f\u5c71"
    ],
    "name:und_x_variant":[
        "Kishigawach\u014d-nishiyama"
    ],
    "wof:name":"Kishigawacho-nishiyama",
    "wof:placetype":"locality"
},
  "geometry": {"coordinates":[135.2876,34.2203],"type":"Point"}
}