{
  "type": "Feature",
  "properties": {
    "gn:admin1_code":"40.0",
    "gn:admin2_code":"1851510.0",
    "gn:asciiname":"Matsunoki",
    "gn:country_code":"JP",
    "gn:dem":47,
    "gn:feature_class":"P",
    "gn:feature_code":"PPL",
    "gn:name":"Matsunoki",
    "gn:population":0,
    "gn:timezone":"Asia/Tokyo",
    "iso:country":"JP",
    "name:jpn_x_preferred":[
        "\u677e\u30ce\u6728"
    ],
    "wof:name":"Matsunoki",
    "wof:placetype":"locality"
},
  "geometry": {"coordinates":[139.64358999999999,35.69097],"type":"Point"}
}