{
  "type": "Feature",
  "properties": {
    "gn:admin1_code":"7.0",
    "gn:admin2_code":"1848086.0",
    "gn:asciiname":"Hirashimahigashi",
    "gn:country_code":"JP",
    "gn:dem":7,
    "gn:feature_class":"P",
    "gn:feature_code":"PPL",
    "gn:name":"Hirashimahigashi",
    "gn:population":0,
    "gn:timezone":"Asia/Tokyo",
    "iso:country":"JP",
    "name:jpn_x_preferred":[
        "\u5e73\u5cf6\u6771"
    ],
    "wof:name":"Hirashimahigashi",
    "wof:placetype":"locality"
},
  "geometry": {"coordinates":[130.99572000000001,33.71004],"type":"Point"}
}