{
  "type": "Feature",
  "properties": {
    "gn:country":"JP",
    "gn:fcode":"PPL",
    "gn:pop":70339,
    "iso:country":"JP",
    "name:ceb_x_preferred":[
        "Maebaru-ch\u016b\u014d"
    ],
    "name:deu_x_preferred":[
        "Maebaru"
    ],
    "name:eng_x_preferred":[
        "Maebaru"
    ],
    "name:fas_x_preferred":[
        "\u0645\u0627\u0626\u0647\u200c\u0628\u0627\u0631\u0648"
    ],
    "name:fin_x_preferred":[
        "Maebaru"
    ],
    "name:fra_x_preferred":[
        "Maebaru"
    ],
    "name:glg_x_preferred":[
        "Maebaru"
    ],
    "name:ita_x_preferred":[
        "Maebaru"
    ],
    "name:jpn_x_preferred":[
        "\u524d\u539f\u4e2d\u592e"
    ],
    "name:jpn_x_variant":[
        "\u524d\u539f\u5e02"
    ],
    "name:kor_x_preferred":[
        "\ub9c8\uc5d0\ubc14\ub8e8 \uc2dc"
    ],
    "name:kor_x_variant":[
        "\ub9c8\uc5d0\ubc14\ub8e8\uc2dc"
    ],
    "name:mzn_x_preferred":[
        "\u0645\u0627\u0626\u0647 \u0628\u0627\u0631\u0648\u060c \u0641\u0648\u06a9\u0648\u0626\u0648\u06a9\u0627"
    ],
    "name:mzn_x_variant":[
        "\u0645\u0627\u0626\u0647 \u0628\u0627\u0631\u0648"
    ],
    "name:nld_x_preferred":[
        "Maebaru"
    ],
    "name:pol_x_preferred":[
        "Maebaru"
    ],
    "name:por_x_preferred":[
        "Maebaru"
    ],
    "name:ron_x_preferred":[
        "Maebaru"
    ],
    "name:spa_x_preferred":[
        "Maebaru"
    ],
    "name:tgk_x_preferred":[
        "\u041c\u0430\u0435\u0431\u0430\u0440\u0443"
    ],
    "name:tgl_x_preferred":[
        "Maebaru"
    ],
    "name:unk_x_variant":[
        "Maeharu"
    ],
    "name:zho_x_preferred":[
        "\u524d\u539f\u5e02"
    ],
    "qs:name":"Maebaru",
    "qs:photos_9r":0,
    "qs:photos_sr":0,
    "qs:pop_sr":"8",
    "wof:name":"Maebaru",
    "wof:placetype":"locality",
    "wof:population":70339
},
  "geometry": {"coordinates":[130.19999999999999,33.55],"type":"Point"}
}