{
  "type": "Feature",
  "properties": {
    "gn:admin1_code":"4.0",
    "gn:admin2_code":"2112386.0",
    "gn:asciiname":"Furukawa",
    "gn:country_code":"JP",
    "gn:dem":230,
    "gn:feature_class":"P",
    "gn:feature_code":"PPLL",
    "gn:name":"Furukawa",
    "gn:population":0,
    "gn:timezone":"Asia/Tokyo",
    "iso:country":"JP",
    "name:ceb_x_preferred":[
        "Furukawa"
    ],
    "name:deu_x_preferred":[
        "Furukawa"
    ],
    "name:epo_x_preferred":[
        "Furuka\u016da"
    ],
    "name:jpn_x_preferred":[
        "\u53e4\u5ddd"
    ],
    "name:jpn_x_variant":[
        "\u3075\u308b\u304b\u308f",
        "\u30d5\u30eb\u30ab\u30ef"
    ],
    "name:kor_x_preferred":[
        "\ud6c4\ub8e8\uce74\uc640"
    ],
    "name:rus_x_preferred":[
        "\u0424\u0443\u0440\u0443\u043a\u0430\u0432\u0430"
    ],
    "name:ukr_x_preferred":[
        "\u0424\u0443\u0440\u0443\u043a\u0430\u0432\u0430"
    ],
    "wof:name":"Furukawa",
    "wof:placetype":"locality"
},
  "geometry": {"coordinates":[140.13357999999999,35.1854],"type":"Point"}
}