{
  "type": "Feature",
  "properties": {
    "gn:admin1_code":"12.0",
    "gn:admin2_code":"7428097.0",
    "gn:admin3_code":"1643.0",
    "gn:asciiname":"Sarubetsu",
    "gn:country_code":"JP",
    "gn:dem":25,
    "gn:feature_class":"P",
    "gn:feature_code":"PPL",
    "gn:name":"Sarubetsu",
    "gn:population":0,
    "gn:timezone":"Asia/Tokyo",
    "iso:country":"JP",
    "name:jpn_x_preferred":[
        "\u733f\u5225"
    ],
    "name:jpn_x_variant":[
        "\u3055\u308b\u3079\u3064",
        "\u30b5\u30eb\u30d9\u30c4"
    ],
    "name:und_x_variant":[
        "Nanse",
        "Sarubetsu"
    ],
    "wof:name":"Sarubetsu",
    "wof:placetype":"locality"
},
  "geometry": {"coordinates":[143.33760000000001,42.87242],"type":"Point"}
}