{
  "type": "Feature",
  "properties": {
    "gn:admin1_code":"15",
    "gn:admin2_code":"7467879.0",
    "gn:asciiname":"Otamachi",
    "gn:country_code":"JP",
    "gn:dem":24,
    "gn:feature_class":"P",
    "gn:feature_code":"PPL",
    "gn:name":"\u014ctamachi",
    "gn:population":0,
    "gn:timezone":"Asia/Tokyo",
    "iso:country":"JP",
    "name:jpn_x_preferred":[
        "\u5927\u7530\u753a"
    ],
    "name:und_x_variant":[
        "\u014ctamachi",
        "\u014cta"
    ],
    "wof:name":"Otamachi",
    "wof:placetype":"locality"
},
  "geometry": {"coordinates":[137.00853000000001,37.06504],"type":"Point"}
}