{
  "type": "Feature",
  "properties": {
    "gn:admin1_code":"3.0",
    "gn:admin2_code":"2130225.0",
    "gn:asciiname":"Shimoiwasaki",
    "gn:country_code":"JP",
    "gn:dem":17,
    "gn:feature_class":"P",
    "gn:feature_code":"PPL",
    "gn:name":"Shimoiwasaki",
    "gn:population":0,
    "gn:timezone":"Asia/Tokyo",
    "iso:country":"JP",
    "name:jpn_x_preferred":[
        "\u4e0b\u5ca9\u5d0e"
    ],
    "name:jpn_x_variant":[
        "\u3057\u3082\u3044\u308f\u3055\u304d",
        "\u30b7\u30e2\u30a4\u30ef\u30b5\u30ad"
    ],
    "wof:name":"Shimoiwasaki",
    "wof:placetype":"locality"
},
  "geometry": {"coordinates":[140.48246,40.83804],"type":"Point"}
}