{
  "type": "Feature",
  "properties": {
    "gn:admin1_code":"28",
    "gn:admin2_code":"9036699.0",
    "gn:asciiname":"Sogacho",
    "gn:country_code":"JP",
    "gn:dem":57,
    "gn:feature_class":"P",
    "gn:feature_code":"PPL",
    "gn:name":"Sogach\u014d",
    "gn:population":0,
    "gn:timezone":"Asia/Tokyo",
    "iso:country":"JP",
    "name:jpn_x_preferred":[
        "\u66fd\u6211\u753a"
    ],
    "name:und_x_variant":[
        "Sogach\u014d",
        "Soga"
    ],
    "wof:name":"Sogacho",
    "wof:placetype":"locality"
},
  "geometry": {"coordinates":[135.77798999999999,34.51458],"type":"Point"}
}