{
  "type": "Feature",
  "properties": {
    "iso:country":"JP",
    "qs:name":"\u9ad8\u8429\u5e02",
    "qs:name_adm0":"\u65e5\u672c",
    "qs:name_adm1":"\u8328\u57ce\u770c",
    "qs:photos":60,
    "qs:photos_1k":12,
    "qs:photos_9k":1,
    "qs:photos_9r":3,
    "qs:photos_all":90,
    "qs:photos_sr":2,
    "qs:placetype":"Town",
    "qs:pop_sr":"0",
    "wof:name":"\u9ad8\u8429\u5e02",
    "wof:placetype":"locality"
},
  "geometry": {"coordinates":[140.63467399999999,36.7347525],"type":"Point"}
}