{
  "type": "Feature",
  "properties": {
    "gn:admin1_code":"21.0",
    "gn:admin2_code":"1848443.0",
    "gn:admin3_code":"43468.0",
    "gn:asciiname":"Kitakano",
    "gn:country_code":"JP",
    "gn:dem":-1,
    "gn:feature_class":"P",
    "gn:feature_code":"PPLL",
    "gn:name":"Kitakano",
    "gn:population":0,
    "gn:timezone":"Asia/Tokyo",
    "iso:country":"JP",
    "name:jpn_x_preferred":[
        "\u5317\u9e7f\u91ce"
    ],
    "name:jpn_x_variant":[
        "\u304d\u305f\u304b\u306e",
        "\u30ad\u30bf\u30ab\u30ce"
    ],
    "wof:name":"Kitakano",
    "wof:placetype":"locality"
},
  "geometry": {"coordinates":[130.67023,32.59199],"type":"Point"}
}