{
  "type": "Feature",
  "properties": {
    "gn:admin1_code":"19.0",
    "gn:admin2_code":"1864091.0",
    "gn:asciiname":"Takinosawa",
    "gn:country_code":"JP",
    "gn:dem":32,
    "gn:feature_class":"P",
    "gn:feature_code":"PPLL",
    "gn:name":"Takinosawa",
    "gn:population":0,
    "gn:timezone":"Asia/Tokyo",
    "iso:country":"JP",
    "name:jpn_x_preferred":[
        "\u6edd\u30ce\u6ca2"
    ],
    "wof:name":"Takinosawa",
    "wof:placetype":"locality"
},
  "geometry": {"coordinates":[139.46319,35.38553],"type":"Point"}
}