{
  "type": "Feature",
  "properties": {
    "gn:admin1_code":"19.0",
    "gn:admin2_code":"1859635.0",
    "gn:admin3_code":"14131.0",
    "gn:asciiname":"Oshima-kamicho",
    "gn:country_code":"JP",
    "gn:dem":5,
    "gn:feature_class":"P",
    "gn:feature_code":"PPL",
    "gn:name":"\u014cshima-kamich\u014d",
    "gn:population":0,
    "gn:timezone":"Asia/Tokyo",
    "iso:country":"JP",
    "name:jpn_x_preferred":[
        "\u5927\u5cf6\u4e0a\u753a"
    ],
    "name:und_x_variant":[
        "\u014cshima-kamich\u014d"
    ],
    "wof:name":"Oshima-kamicho",
    "wof:placetype":"locality"
},
  "geometry": {"coordinates":[139.70987,35.52077],"type":"Point"}
}