{
  "type": "Feature",
  "properties": {
    "gn:admin1_code":"13.0",
    "gn:admin2_code":"1851011.0",
    "gn:asciiname":"Hazu",
    "gn:country_code":"JP",
    "gn:dem":200,
    "gn:feature_class":"P",
    "gn:feature_code":"PPL",
    "gn:name":"Hazu",
    "gn:population":0,
    "gn:timezone":"Asia/Tokyo",
    "iso:country":"JP",
    "name:jpn_x_preferred":[
        "\u6ce2\u8c46"
    ],
    "wof:name":"Hazu",
    "wof:placetype":"locality"
},
  "geometry": {"coordinates":[135.28428,34.91116],"type":"Point"}
}