{
  "type": "Feature",
  "properties": {
    "gn:admin1_code":"34.0",
    "gn:admin2_code":"1859726.0",
    "gn:asciiname":"Maeta",
    "gn:country_code":"JP",
    "gn:dem":2,
    "gn:feature_class":"P",
    "gn:feature_code":"PPL",
    "gn:name":"Maeta",
    "gn:population":0,
    "gn:timezone":"Asia/Tokyo",
    "iso:country":"JP",
    "name:jpn_x_preferred":[
        "\u524d\u7530"
    ],
    "name:jpn_x_variant":[
        "\u307e\u3048\u305f",
        "\u30de\u30a8\u30bf"
    ],
    "wof:name":"Maeta",
    "wof:placetype":"locality"
},
  "geometry": {"coordinates":[139.72985,35.81453],"type":"Point"}
}