{
  "type": "Feature",
  "properties": {
    "gn:admin1_code":"07",
    "gn:admin2_code":"7406948.0",
    "gn:admin3_code":"40448.0",
    "gn:asciiname":"Koishiwara",
    "gn:country_code":"JP",
    "gn:dem":511,
    "gn:feature_class":"P",
    "gn:feature_code":"PPL",
    "gn:name":"Koishiwara",
    "gn:population":0,
    "gn:timezone":"Asia/Tokyo",
    "iso:country":"JP",
    "name:jpn_x_preferred":[
        "\u5c0f\u77f3\u539f"
    ],
    "wof:name":"Koishiwara",
    "wof:placetype":"locality"
},
  "geometry": {"coordinates":[130.82962000000001,33.47142],"type":"Point"}
}