{
  "type": "Feature",
  "properties": {
    "gn:admin1_code":"15.0",
    "gn:admin2_code":"7467838.0",
    "gn:admin3_code":"17384.0",
    "gn:asciiname":"Togi-urukami",
    "gn:country_code":"JP",
    "gn:dem":44,
    "gn:feature_class":"P",
    "gn:feature_code":"PPL",
    "gn:name":"Togi-urukami",
    "gn:population":0,
    "gn:timezone":"Asia/Tokyo",
    "iso:country":"JP",
    "name:jpn_x_preferred":[
        "\u5bcc\u6765\u751f\u795e"
    ],
    "wof:name":"Togi-urukami",
    "wof:placetype":"locality"
},
  "geometry": {"coordinates":[136.7287,37.11735],"type":"Point"}
}