{
  "type": "Feature",
  "properties": {
    "gn:admin1_code":"26.0",
    "gn:admin2_code":"1858856.0",
    "gn:asciiname":"Shiono",
    "gn:country_code":"JP",
    "gn:dem":952,
    "gn:feature_class":"P",
    "gn:feature_code":"PPL",
    "gn:name":"Shiono",
    "gn:population":0,
    "gn:timezone":"Asia/Tokyo",
    "iso:country":"JP",
    "name:jpn_x_preferred":[
        "\u5869\u91ce"
    ],
    "wof:name":"Shiono",
    "wof:placetype":"locality"
},
  "geometry": {"coordinates":[138.47058000000001,36.34242],"type":"Point"}
}