{
  "type": "Feature",
  "properties": {
    "iso:country":"JP",
    "name:eng_x_preferred":[
        "Ikusaka"
    ],
    "name:eng_x_variant":[
        "Ikusaka Village"
    ],
    "name:jpn_x_preferred":[
        "\u751f\u5742\u6751"
    ],
    "qs:name":"\u751f\u5742\u6751",
    "qs:name_adm0":"\u65e5\u672c",
    "qs:name_adm1":"\u9577\u91ce\u770c",
    "qs:photos":14,
    "qs:photos_1k":3,
    "qs:photos_9k":1,
    "qs:photos_9r":1,
    "qs:photos_all":14,
    "qs:photos_sr":1,
    "qs:placetype":"Town",
    "qs:pop_sr":"0",
    "wof:name":"Ikusaka",
    "wof:placetype":"locality"
},
  "geometry": {"coordinates":[137.94143299999999,36.453874],"type":"Point"}
}