{
  "type": "Feature",
  "properties": {
    "gn:admin1_code":"12.0",
    "gn:admin2_code":"7428079.0",
    "gn:admin3_code":"1648.0",
    "gn:asciiname":"Komatsunojo",
    "gn:cc2":"JP",
    "gn:country_code":"JP",
    "gn:dem":431,
    "gn:feature_class":"P",
    "gn:feature_code":"PPL",
    "gn:name":"Komatsun\u014dj\u014d",
    "gn:population":0,
    "gn:timezone":"Asia/Tokyo",
    "iso:country":"JP",
    "name:und_x_variant":[
        "Minami-tomamu",
        "Komatsun\u014dj\u014d"
    ],
    "wof:name":"Komatsunojo",
    "wof:placetype":"locality"
},
  "geometry": {"coordinates":[143.59999999999999,43.46667],"type":"Point"}
}