{
  "type": "Feature",
  "properties": {
    "gn:admin1_code":"2.0",
    "gn:admin2_code":"7443156.0",
    "gn:asciiname":"Sugiyamada",
    "gn:country_code":"JP",
    "gn:dem":54,
    "gn:feature_class":"P",
    "gn:feature_code":"PPLL",
    "gn:name":"Sugiyamada",
    "gn:population":0,
    "gn:timezone":"Asia/Tokyo",
    "iso:country":"JP",
    "name:jpn_x_preferred":[
        "\u6749\u5c71\u7530"
    ],
    "wof:name":"Sugiyamada",
    "wof:placetype":"locality"
},
  "geometry": {"coordinates":[140.31099,40.0885],"type":"Point"}
}