{
  "type": "Feature",
  "properties": {
    "gn:admin1_code":"3.0",
    "gn:admin2_code":"2130056.0",
    "gn:asciiname":"Aokicho",
    "gn:country_code":"JP",
    "gn:dem":85,
    "gn:feature_class":"P",
    "gn:feature_code":"PPL",
    "gn:name":"Aokich\u014d",
    "gn:population":0,
    "gn:timezone":"Asia/Tokyo",
    "iso:country":"JP",
    "name:jpn_x_preferred":[
        "\u9752\u6a39\u753a"
    ],
    "name:jpn_x_variant":[
        "\u3042\u304a\u304d\u3061\u3087\u3046",
        "\u30a2\u30aa\u30ad\u30c1\u30e7\u30a6"
    ],
    "name:und_x_variant":[
        "Aokich\u014d"
    ],
    "wof:name":"Aokicho",
    "wof:placetype":"locality"
},
  "geometry": {"coordinates":[140.43888999999999,40.58033],"type":"Point"}
}