{
  "type": "Feature",
  "properties": {
    "gn:admin1_code":"04",
    "gn:admin2_code":"1863711.0",
    "gn:asciiname":"Yahata",
    "gn:country_code":"JP",
    "gn:dem":23,
    "gn:feature_class":"P",
    "gn:feature_code":"PPL",
    "gn:name":"Yahata",
    "gn:population":0,
    "gn:timezone":"Asia/Tokyo",
    "iso:country":"JP",
    "name:jpn_x_preferred":[
        "\u516b\u5e61"
    ],
    "name:jpn_x_variant":[
        "\u3084\u306f\u305f",
        "\u30e4\u30cf\u30bf"
    ],
    "name:und_x_variant":[
        "Yawata"
    ],
    "wof:name":"Yahata",
    "wof:placetype":"locality"
},
  "geometry": {"coordinates":[139.87179,35.2511],"type":"Point"}
}