{
  "type": "Feature",
  "properties": {
    "gn:admin1_code":"17",
    "gn:admin2_code":"1856906.0",
    "gn:asciiname":"Tanokuchi",
    "gn:country_code":"JP",
    "gn:dem":95,
    "gn:feature_class":"P",
    "gn:feature_code":"PPLL",
    "gn:name":"Tanokuchi",
    "gn:population":0,
    "gn:timezone":"Asia/Tokyo",
    "iso:country":"JP",
    "name:jpn_x_preferred":[
        "\u7530\u306e\u53e3"
    ],
    "wof:name":"Tanokuchi",
    "wof:placetype":"locality"
},
  "geometry": {"coordinates":[133.78333000000001,34.15],"type":"Point"}
}