{
  "type": "Feature",
  "properties": {
    "gn:admin1_code":"29.0",
    "gn:admin2_code":"1856195.0",
    "gn:asciiname":"Kotsunagi",
    "gn:country_code":"JP",
    "gn:dem":62,
    "gn:feature_class":"P",
    "gn:feature_code":"PPL",
    "gn:name":"Kotsunagi",
    "gn:population":0,
    "gn:timezone":"Asia/Tokyo",
    "iso:country":"JP",
    "name:jpn_x_preferred":[
        "\u5c0f\u8cab"
    ],
    "wof:name":"Kotsunagi",
    "wof:placetype":"locality"
},
  "geometry": {"coordinates":[138.97601,37.49257],"type":"Point"}
}