{
  "type": "Feature",
  "properties": {
    "gn:admin1_code":"23",
    "gn:admin2_code":"1858408.0",
    "gn:asciiname":"Omata",
    "gn:cc2":"JP",
    "gn:country_code":"JP",
    "gn:dem":524,
    "gn:feature_class":"P",
    "gn:feature_code":"PPL",
    "gn:name":"\u014cmata",
    "gn:population":0,
    "gn:timezone":"Asia/Tokyo",
    "iso:country":"JP",
    "name:und_x_variant":[
        "\u014c-mato",
        "\u014cmata"
    ],
    "wof:name":"Omata",
    "wof:placetype":"locality"
},
  "geometry": {"coordinates":[136.09999999999999,33.96667],"type":"Point"}
}