{
  "type": "Feature",
  "properties": {
    "gn:admin1_code":"4.0",
    "gn:admin2_code":"7465521.0",
    "gn:asciiname":"Oi",
    "gn:country_code":"JP",
    "gn:dem":136,
    "gn:feature_class":"P",
    "gn:feature_code":"PPL",
    "gn:name":"\u014ci",
    "gn:population":0,
    "gn:timezone":"Asia/Tokyo",
    "iso:country":"JP",
    "name:eus_x_preferred":[
        "Oi"
    ],
    "name:jpn_x_preferred":[
        "\u5927\u4e95"
    ],
    "name:jpn_x_variant":[
        "\u304a\u304a\u3044",
        "\u30aa\u30aa\u30a4"
    ],
    "name:rus_x_preferred":[
        "\u041e\u0438"
    ],
    "name:swe_x_preferred":[
        "Oi"
    ],
    "name:und_x_variant":[
        "\u014ci"
    ],
    "wof:name":"Oi",
    "wof:placetype":"locality"
},
  "geometry": {"coordinates":[139.97711000000001,35.09816],"type":"Point"}
}