{
  "type": "Feature",
  "properties": {
    "gn:admin1_code":"34.0",
    "gn:admin2_code":"8304213.0",
    "gn:asciiname":"Atago",
    "gn:country_code":"JP",
    "gn:dem":17,
    "gn:feature_class":"P",
    "gn:feature_code":"PPLL",
    "gn:name":"Atago",
    "gn:population":0,
    "gn:timezone":"Asia/Tokyo",
    "iso:country":"JP",
    "name:ita_x_preferred":[
        "Atago"
    ],
    "name:jpn_x_preferred":[
        "\u611b\u5b95"
    ],
    "name:kor_x_preferred":[
        "\uc544\ud0c0\uace0"
    ],
    "name:pol_x_preferred":[
        "Atago"
    ],
    "name:spa_x_preferred":[
        "Atago"
    ],
    "wof:name":"Atago",
    "wof:placetype":"locality"
},
  "geometry": {"coordinates":[139.81898000000001,35.9841],"type":"Point"}
}