{
  "type": "Feature",
  "properties": {
    "gn:admin1_code":"44",
    "gn:admin2_code":"7450466.0",
    "gn:asciiname":"Takadama",
    "gn:country_code":"JP",
    "gn:dem":106,
    "gn:feature_class":"P",
    "gn:feature_code":"PPL",
    "gn:name":"Takadama",
    "gn:population":0,
    "gn:timezone":"Asia/Tokyo",
    "iso:country":"JP",
    "name:jpn_x_preferred":[
        "\u9ad8\u64f6"
    ],
    "wof:name":"Takadama",
    "wof:placetype":"locality"
},
  "geometry": {"coordinates":[140.34999999999999,38.33333],"type":"Point"}
}