{
  "type": "Feature",
  "properties": {
    "gn:admin1_code":"30",
    "gn:admin2_code":"1854480.0",
    "gn:asciiname":"Sakanoichi-chuo",
    "gn:country_code":"JP",
    "gn:dem":6,
    "gn:feature_class":"P",
    "gn:feature_code":"PPL",
    "gn:name":"Sakanoichi-ch\u016b\u014d",
    "gn:population":0,
    "gn:timezone":"Asia/Tokyo",
    "iso:country":"JP",
    "name:jpn_x_preferred":[
        "\u5742\u30ce\u5e02\u4e2d\u592e"
    ],
    "name:und_x_variant":[
        "Sakanoichi-ch\u016b\u014d",
        "Sakanoichi"
    ],
    "wof:name":"Sakanoichi-chuo",
    "wof:placetype":"locality"
},
  "geometry": {"coordinates":[131.75,33.23333],"type":"Point"}
}