{
  "type": "Feature",
  "properties": {
    "gn:admin1_code":"19.0",
    "gn:admin2_code":"1864091.0",
    "gn:asciiname":"Ogami",
    "gn:country_code":"JP",
    "gn:dem":46,
    "gn:feature_class":"P",
    "gn:feature_code":"PPLL",
    "gn:name":"\u014cgami",
    "gn:population":0,
    "gn:timezone":"Asia/Tokyo",
    "iso:country":"JP",
    "name:jpn_x_preferred":[
        "\u5927\u4e0a\u3000"
    ],
    "name:und_x_variant":[
        "\u014cgami"
    ],
    "wof:name":"Ogami",
    "wof:placetype":"locality"
},
  "geometry": {"coordinates":[139.42833000000002,35.4006],"type":"Point"}
}