{
  "type": "Feature",
  "properties": {
    "gn:admin1_code":"2.0",
    "gn:admin2_code":"2127468.0",
    "gn:admin3_code":"5348.0",
    "gn:asciiname":"Izumisawa",
    "gn:country_code":"JP",
    "gn:dem":24,
    "gn:feature_class":"P",
    "gn:feature_code":"PPLL",
    "gn:name":"Izumisawa",
    "gn:population":0,
    "gn:timezone":"Asia/Tokyo",
    "iso:country":"JP",
    "name:jpn_x_preferred":[
        "\u6cc9\u6ca2"
    ],
    "wof:name":"Izumisawa",
    "wof:placetype":"locality"
},
  "geometry": {"coordinates":[140.08921999999998,40.0671],"type":"Point"}
}