{
  "type": "Feature",
  "properties": {
    "gn:admin1_code":"21.0",
    "gn:admin2_code":"1848441.0",
    "gn:asciiname":"Hakoishi",
    "gn:country_code":"JP",
    "gn:dem":355,
    "gn:feature_class":"P",
    "gn:feature_code":"PPLL",
    "gn:name":"Hakoishi",
    "gn:population":0,
    "gn:timezone":"Asia/Tokyo",
    "iso:country":"JP",
    "name:jpn_x_preferred":[
        "\u7bb1\u77f3"
    ],
    "name:jpn_x_variant":[
        "\u306f\u3053\u3044\u3057",
        "\u30cf\u30b3\u30a4\u30b7"
    ],
    "wof:name":"Hakoishi",
    "wof:placetype":"locality"
},
  "geometry": {"coordinates":[130.71967000000001,32.51669],"type":"Point"}
}