{
  "type": "Feature",
  "properties": {
    "gn:admin1_code":"24.0",
    "gn:admin2_code":"2112261.0",
    "gn:asciiname":"Odasawa",
    "gn:country_code":"JP",
    "gn:dem":33,
    "gn:feature_class":"P",
    "gn:feature_code":"PPL",
    "gn:name":"\u014cdasawa",
    "gn:population":0,
    "gn:timezone":"Asia/Tokyo",
    "iso:country":"JP",
    "name:jpn_x_preferred":[
        "\u5927\u7530\u6ca2"
    ],
    "name:jpn_x_variant":[
        "\u304a\u304a\u3060\u3055\u308f",
        "\u30aa\u30aa\u30c0\u30b5\u30ef"
    ],
    "name:und_x_variant":[
        "\u014cdasawa"
    ],
    "wof:name":"Odasawa",
    "wof:placetype":"locality"
},
  "geometry": {"coordinates":[141.64686,38.90919],"type":"Point"}
}