{
  "type": "Feature",
  "properties": {
    "gn:admin1_code":"7.0",
    "gn:admin2_code":"1854055.0",
    "gn:admin3_code":"40383.0",
    "gn:asciiname":"Kitahara",
    "gn:country_code":"JP",
    "gn:dem":14,
    "gn:feature_class":"P",
    "gn:feature_code":"PPLL",
    "gn:name":"Kitahara",
    "gn:population":0,
    "gn:timezone":"Asia/Tokyo",
    "iso:country":"JP",
    "name:jpn_x_preferred":[
        "\u5317\u539f"
    ],
    "name:kor_x_preferred":[
        "\uae30\ud0c0\ud558\ub77c"
    ],
    "name:rus_x_preferred":[
        "\u041a\u0438\u0442\u0430\u0445\u0430\u0440\u0430"
    ],
    "wof:name":"Kitahara",
    "wof:placetype":"locality"
},
  "geometry": {"coordinates":[130.63921999999999,33.86767],"type":"Point"}
}