{
  "type": "Feature",
  "properties": {
    "gn:admin1_code":"10",
    "gn:admin2_code":"1850994.0",
    "gn:asciiname":"Kurabuchimachi-sannokura",
    "gn:country_code":"JP",
    "gn:dem":393,
    "gn:feature_class":"P",
    "gn:feature_code":"PPL",
    "gn:name":"Kurabuchimachi-sannokura",
    "gn:population":0,
    "gn:timezone":"Asia/Tokyo",
    "iso:country":"JP",
    "name:jpn_x_preferred":[
        "\u5009\u6e15\u753a\u4e09\u30ce\u5009"
    ],
    "name:und_x_variant":[
        "Sannokura"
    ],
    "wof:name":"Kurabuchimachi-sannokura",
    "wof:placetype":"locality"
},
  "geometry": {"coordinates":[138.80000000000001,36.41667],"type":"Point"}
}