{
  "type": "Feature",
  "properties": {
    "gn:admin1_code":"12.0",
    "gn:admin2_code":"2130402.0",
    "gn:asciiname":"Nopporo",
    "gn:cc2":"JP",
    "gn:country_code":"JP",
    "gn:dem":33,
    "gn:feature_class":"P",
    "gn:feature_code":"PPL",
    "gn:name":"Nopporo",
    "gn:population":0,
    "gn:timezone":"Asia/Tokyo",
    "iso:country":"JP",
    "name:und_x_variant":[
        "Noboro",
        "Nopporo-shigaichi",
        "Nopporo"
    ],
    "wof:name":"Nopporo",
    "wof:placetype":"locality"
},
  "geometry": {"coordinates":[141.53333000000001,43.08333],"type":"Point"}
}