{
  "type": "Feature",
  "properties": {
    "gn:admin1_code":"04",
    "gn:admin2_code":"2112663.0",
    "gn:asciiname":"Tsukizaki",
    "gn:country_code":"JP",
    "gn:dem":72,
    "gn:feature_class":"P",
    "gn:feature_code":"PPL",
    "gn:name":"Tsukizaki",
    "gn:population":0,
    "gn:timezone":"Asia/Tokyo",
    "iso:country":"JP",
    "name:jpn_x_preferred":[
        "\u6708\u5d0e"
    ],
    "name:jpn_x_variant":[
        "\u3064\u304d\u3056\u304d",
        "\u30c4\u30ad\u30b6\u30ad"
    ],
    "wof:name":"Tsukizaki",
    "wof:placetype":"locality"
},
  "geometry": {"coordinates":[140.14613,35.30481],"type":"Point"}
}