{
  "type": "Feature",
  "properties": {
    "gn:admin1_code":"27.0",
    "gn:admin2_code":"1862734.0",
    "gn:admin3_code":"42323.0",
    "gn:asciiname":"Shiorigo",
    "gn:country_code":"JP",
    "gn:dem":45,
    "gn:feature_class":"P",
    "gn:feature_code":"PPL",
    "gn:name":"Shiorig\u014d",
    "gn:population":0,
    "gn:timezone":"Asia/Tokyo",
    "iso:country":"JP",
    "name:jpn_x_preferred":[
        "\u5fd7\u6298\u90f7"
    ],
    "name:und_x_variant":[
        "Shiorig\u014d"
    ],
    "wof:name":"Shiorigo",
    "wof:placetype":"locality"
},
  "geometry": {"coordinates":[129.86327,33.11086],"type":"Point"}
}