{
  "type": "Feature",
  "properties": {
    "gn:admin1_code":"19.0",
    "gn:admin2_code":"1859635.0",
    "gn:admin3_code":"14133.0",
    "gn:asciiname":"Kamimaruko-tenjincho",
    "gn:country_code":"JP",
    "gn:dem":11,
    "gn:feature_class":"P",
    "gn:feature_code":"PPL",
    "gn:name":"Kamimaruko-tenjinch\u014d",
    "gn:population":0,
    "gn:timezone":"Asia/Tokyo",
    "iso:country":"JP",
    "name:jpn_x_preferred":[
        "\u4e0a\u4e38\u5b50\u5929\u795e\u753a"
    ],
    "name:und_x_variant":[
        "Kamimaruko-tenjinch\u014d"
    ],
    "wof:name":"Kamimaruko-tenjincho",
    "wof:placetype":"locality"
},
  "geometry": {"coordinates":[139.66197,35.58527],"type":"Point"}
}