{
  "type": "Feature",
  "properties": {
    "gn:admin1_code":"3.0",
    "gn:admin2_code":"7439944.0",
    "gn:asciiname":"Chikaoka",
    "gn:country_code":"JP",
    "gn:dem":8,
    "gn:feature_class":"P",
    "gn:feature_code":"PPL",
    "gn:name":"Chikaoka",
    "gn:population":0,
    "gn:timezone":"Asia/Tokyo",
    "iso:country":"JP",
    "name:jpn_x_preferred":[
        "\u8fd1\u5ca1"
    ],
    "name:jpn_x_variant":[
        "\u3061\u304b\u304a\u304b",
        "\u30c1\u30ab\u30aa\u30ab"
    ],
    "wof:name":"Chikaoka",
    "wof:placetype":"locality"
},
  "geometry": {"coordinates":[140.41783000000001,40.79889],"type":"Point"}
}