{
  "type": "Feature",
  "properties": {
    "gn:admin1_code":"37.0",
    "gn:admin2_code":"1851714.0",
    "gn:admin3_code":"22103.0",
    "gn:asciiname":"Yokosuna-honcho",
    "gn:country_code":"JP",
    "gn:dem":7,
    "gn:feature_class":"P",
    "gn:feature_code":"PPL",
    "gn:name":"Yokosuna-honch\u014d",
    "gn:population":0,
    "gn:timezone":"Asia/Tokyo",
    "iso:country":"JP",
    "name:jpn_x_preferred":[
        "\u6a2a\u7802\u672c\u753a"
    ],
    "name:und_x_variant":[
        "Yokosuna-honch\u014d"
    ],
    "wof:name":"Yokosuna-honcho",
    "wof:placetype":"locality"
},
  "geometry": {"coordinates":[138.50093000000001,35.04258],"type":"Point"}
}