{
  "type": "Feature",
  "properties": {
    "gn:admin1_code":"12.0",
    "gn:admin2_code":"2128405.0",
    "gn:admin3_code":"1519.0",
    "gn:asciiname":"Ishizaki",
    "gn:country_code":"JP",
    "gn:dem":1,
    "gn:feature_class":"P",
    "gn:feature_code":"PPL",
    "gn:name":"Ishizaki",
    "gn:population":0,
    "gn:timezone":"Asia/Tokyo",
    "iso:country":"JP",
    "name:jpn_x_preferred":[
        "\u77f3\u5d0e"
    ],
    "name:jpn_x_variant":[
        "\u3044\u3057\u3056\u304d",
        "\u30a4\u30b7\u30b6\u30ad"
    ],
    "wof:name":"Ishizaki",
    "wof:placetype":"locality"
},
  "geometry": {"coordinates":[141.32640000000001,45.16999000000001],"type":"Point"}
}