{
  "type": "Feature",
  "properties": {
    "gn:admin1_code":"4.0",
    "gn:admin2_code":"1857552.0",
    "gn:asciiname":"Shimoyakiri",
    "gn:country_code":"JP",
    "gn:dem":27,
    "gn:feature_class":"P",
    "gn:feature_code":"PPL",
    "gn:name":"Shimoyakiri",
    "gn:population":0,
    "gn:timezone":"Asia/Tokyo",
    "iso:country":"JP",
    "name:jpn_x_preferred":[
        "\u4e0b\u77e2\u5207"
    ],
    "wof:name":"Shimoyakiri",
    "wof:placetype":"locality"
},
  "geometry": {"coordinates":[139.89682999999999,35.75976],"type":"Point"}
}