{
  "type": "Feature",
  "properties": {
    "iso:country":"JP",
    "name:eng_x_preferred":[
        "Shiroyama 2 Chome"
    ],
    "name:eng_x_variant":[
        "Shiroyama 2 Choume",
        "Shiroyama 2 Chome"
    ],
    "name:jpn_x_preferred":[
        "\uff12\u4e01\u76ee"
    ],
    "name:jpn_x_variant":[
        "\u3057\u308d\u3084\u307e \uff12\u3061\u3087\u3046\u3081",
        "\u57ce\u5c71 \uff12\u4e01\u76ee",
        "\uff12\u3061\u3087\u3046\u3081"
    ],
    "name:unk_x_variant":[
        "\uff12\u4e01\u76ee"
    ],
    "qs:gn_local":0,
    "qs:local_max":1952,
    "qs:local_sum":6256,
    "qs:localhoods":14,
    "qs:name":"\uff12\u4e01\u76ee",
    "qs:name_adm0":"\u65e5\u672c",
    "qs:name_adm1":"\u9e7f\u5150\u5cf6\u770c",
    "qs:name_en":"Shiroyama 2 Chome",
    "qs:name_lau":"\u57ce\u5c71",
    "qs:name_local":"\u9e7f\u5150\u5cf6\u5e02",
    "qs:photo_max":78,
    "qs:photo_sum":517,
    "qs:placetype":"Suburb",
    "qs:quad_count":22,
    "qs:woe_adm0":23424856,
    "qs:woe_adm1":2345867,
    "qs:woe_adm2":0,
    "qs:woe_lau":28492482,
    "qs:woe_local":1117378,
    "qs:woe_ver":"7.10.0",
    "wof:lang":[
        "jpn"
    ],
    "wof:name":"\uff12\u4e01\u76ee",
    "wof:placetype":"neighbourhood"
},
  "geometry": {"coordinates":[130.55855500000001,31.598746],"type":"Point"}
}