{
  "type": "Feature",
  "properties": {
    "gn:admin1_code":"13",
    "gn:admin2_code":"1855132.0",
    "gn:asciiname":"Nakahatacho",
    "gn:cc2":"JP",
    "gn:country_code":"JP",
    "gn:dem":158,
    "gn:feature_class":"P",
    "gn:feature_code":"PPL",
    "gn:name":"Nakahatach\u014d",
    "gn:population":0,
    "gn:timezone":"Asia/Tokyo",
    "iso:country":"JP",
    "name:und_x_variant":[
        "Nakahata",
        "Nakahatach\u014d"
    ],
    "wof:name":"Nakahatacho",
    "wof:placetype":"locality"
},
  "geometry": {"coordinates":[135.03333000000001,35.01667],"type":"Point"}
}