{
  "type": "Feature",
  "properties": {
    "gn:admin1_code":"34.0",
    "gn:admin2_code":"1861470.0",
    "gn:admin3_code":"11324.0",
    "gn:asciiname":"Nakanishi",
    "gn:country_code":"JP",
    "gn:dem":47,
    "gn:feature_class":"P",
    "gn:feature_code":"PPLL",
    "gn:name":"Nakanishi",
    "gn:population":0,
    "gn:timezone":"Asia/Tokyo",
    "iso:country":"JP",
    "name:jpn_x_preferred":[
        "\u4e2d\u897f"
    ],
    "wof:name":"Nakanishi",
    "wof:placetype":"locality"
},
  "geometry": {"coordinates":[139.50059999999999,35.83071],"type":"Point"}
}