{
  "type": "Feature",
  "properties": {
    "gn:admin1_code":"28.0",
    "gn:admin2_code":"1848164.0",
    "gn:admin3_code":"29449.0",
    "gn:asciiname":"Yamasaki",
    "gn:country_code":"JP",
    "gn:dem":246,
    "gn:feature_class":"P",
    "gn:feature_code":"PPL",
    "gn:name":"Yamasaki",
    "gn:population":0,
    "gn:timezone":"Asia/Tokyo",
    "iso:country":"JP",
    "name:deu_x_preferred":[
        "Yamasaki"
    ],
    "name:fra_x_preferred":[
        "Yamasaki"
    ],
    "name:jpn_x_preferred":[
        "\u5c71\u5d0e"
    ],
    "wof:name":"Yamasaki",
    "wof:placetype":"locality"
},
  "geometry": {"coordinates":[135.78512000000001,34.02669],"type":"Point"}
}