{
  "type": "Feature",
  "properties": {
    "gn:admin1_code":"39",
    "gn:admin2_code":"7406325.0",
    "gn:asciiname":"Kawai",
    "gn:country_code":"JP",
    "gn:dem":339,
    "gn:feature_class":"P",
    "gn:feature_code":"PPL",
    "gn:name":"Kawai",
    "gn:population":0,
    "gn:timezone":"Asia/Tokyo",
    "iso:country":"JP",
    "name:jpn_x_preferred":[
        "\u5ddd\u4e95"
    ],
    "wof:name":"Kawai",
    "wof:placetype":"locality"
},
  "geometry": {"coordinates":[134.21203,33.9339],"type":"Point"}
}