{
  "type": "Feature",
  "properties": {
    "gn:admin1_code":"18",
    "gn:admin2_code":"7383992.0",
    "gn:asciiname":"Ronji",
    "gn:cc2":"JP",
    "gn:country_code":"JP",
    "gn:dem":263,
    "gn:feature_class":"P",
    "gn:feature_code":"PPL",
    "gn:name":"Ronji",
    "gn:population":0,
    "gn:timezone":"Asia/Tokyo",
    "iso:country":"JP",
    "name:und_x_variant":[
        "Ronchi",
        "Ronji"
    ],
    "wof:name":"Ronji",
    "wof:placetype":"locality"
},
  "geometry": {"coordinates":[130.71666999999999,31.78333],"type":"Point"}
}