{
  "type": "Feature",
  "properties": {
    "gn:admin1_code":"16.0",
    "gn:admin2_code":"2128940.0",
    "gn:asciiname":"Kubota",
    "gn:country_code":"JP",
    "gn:dem":351,
    "gn:feature_class":"P",
    "gn:feature_code":"PPL",
    "gn:name":"Kubota",
    "gn:population":0,
    "gn:timezone":"Asia/Tokyo",
    "iso:country":"JP",
    "name:jpn_x_preferred":[
        "\u4e45\u4fdd\u7530"
    ],
    "name:jpn_x_variant":[
        "\u304f\u307c\u305f",
        "\u30af\u30dc\u30bf"
    ],
    "wof:name":"Kubota",
    "wof:placetype":"locality"
},
  "geometry": {"coordinates":[141.11878999999999,40.22339],"type":"Point"}
}