{
  "type": "Feature",
  "properties": {
    "gn:admin1_code":"16.0",
    "gn:admin2_code":"2128940.0",
    "gn:asciiname":"Kubota",
    "gn:country_code":"JP",
    "gn:dem":351,
    "gn:feature_class":"P",
    "gn:feature_code":"PPL",
    "gn:name":"Kubota",
    "gn:population":0,
    "gn:timezone":"Asia/Tokyo",
    "iso:country":"JP",
    "name:ara_x_preferred":[
        "\u0643\u0648\u0628\u0648\u062a\u0627"
    ],
    "name:azb_x_preferred":[
        "\u06a9\u0648\u0628\u0648\u062a\u0627"
    ],
    "name:dan_x_preferred":[
        "Kubota"
    ],
    "name:deu_x_preferred":[
        "Kubota"
    ],
    "name:fas_x_preferred":[
        "\u06a9\u0648\u0628\u0648\u062a\u0627"
    ],
    "name:fra_x_preferred":[
        "Kubota"
    ],
    "name:hun_x_preferred":[
        "Kubota"
    ],
    "name:ind_x_preferred":[
        "Kubota"
    ],
    "name:ita_x_preferred":[
        "Kubota"
    ],
    "name:jpn_x_preferred":[
        "\u4e45\u4fdd\u7530"
    ],
    "name:jpn_x_variant":[
        "\u304f\u307c\u305f",
        "\u30af\u30dc\u30bf"
    ],
    "name:msa_x_preferred":[
        "Kubota"
    ],
    "name:nld_x_preferred":[
        "Kubota"
    ],
    "name:pol_x_preferred":[
        "Kubota"
    ],
    "name:rus_x_preferred":[
        "Kubota"
    ],
    "name:slk_x_preferred":[
        "Kubota"
    ],
    "name:slv_x_preferred":[
        "Kubota"
    ],
    "name:spa_x_preferred":[
        "Kubota"
    ],
    "name:swe_x_preferred":[
        "Kubota"
    ],
    "name:tur_x_preferred":[
        "Kubota"
    ],
    "name:ukr_x_preferred":[
        "Kubota"
    ],
    "name:zho_x_preferred":[
        "\u4e45\u4fdd\u7530"
    ],
    "wof:name":"Kubota",
    "wof:placetype":"locality"
},
  "geometry": {"coordinates":[141.11878999999999,40.22339],"type":"Point"}
}