{
  "type": "Feature",
  "properties": {
    "gn:admin1_code":"10.0",
    "gn:admin2_code":"7453747.0",
    "gn:admin3_code":"10429.0",
    "gn:asciiname":"Goshogaido",
    "gn:country_code":"JP",
    "gn:dem":639,
    "gn:feature_class":"P",
    "gn:feature_code":"PPLL",
    "gn:name":"Goshogaido",
    "gn:population":0,
    "gn:timezone":"Asia/Tokyo",
    "iso:country":"JP",
    "name:jpn_x_preferred":[
        "\u5f8c\u6240\u8c37\u6238"
    ],
    "wof:name":"Goshogaido",
    "wof:placetype":"locality"
},
  "geometry": {"coordinates":[138.78426000000002,36.4952],"type":"Point"}
}