{
  "type": "Feature",
  "properties": {
    "gn:admin1_code":"4.0",
    "gn:admin2_code":"2110982.0",
    "gn:asciiname":"Nagaura",
    "gn:country_code":"JP",
    "gn:dem":5,
    "gn:feature_class":"P",
    "gn:feature_code":"PPL",
    "gn:name":"Nagaura",
    "gn:population":0,
    "gn:timezone":"Asia/Tokyo",
    "iso:country":"JP",
    "name:jpn_x_preferred":[
        "\u9577\u6d66"
    ],
    "name:jpn_x_variant":[
        "\u306a\u304c\u3046\u3089",
        "\u30ca\u30ac\u30a6\u30e9"
    ],
    "wof:name":"Nagaura",
    "wof:placetype":"locality"
},
  "geometry": {"coordinates":[139.99206000000001,35.44968],"type":"Point"}
}