{
  "type": "Feature",
  "properties": {
    "gn:admin1_code":"20",
    "gn:admin2_code":"1865726.0",
    "gn:admin3_code":"39386.0",
    "gn:asciiname":"Edagawa",
    "gn:country_code":"JP",
    "gn:dem":445,
    "gn:feature_class":"P",
    "gn:feature_code":"PPL",
    "gn:name":"Edagawa",
    "gn:population":0,
    "gn:timezone":"Asia/Tokyo",
    "iso:country":"JP",
    "wof:name":"Edagawa",
    "wof:placetype":"locality"
},
  "geometry": {"coordinates":[133.33333000000002,33.65],"type":"Point"}
}