{
  "type": "Feature",
  "properties": {
    "gn:admin1_code":"21.0",
    "gn:admin2_code":"1864973.0",
    "gn:asciiname":"Minamimiyabaru",
    "gn:country_code":"JP",
    "gn:dem":502,
    "gn:feature_class":"P",
    "gn:feature_code":"PPL",
    "gn:name":"Minamimiyabaru",
    "gn:population":0,
    "gn:timezone":"Asia/Tokyo",
    "iso:country":"JP",
    "name:jpn_x_preferred":[
        "\u5357\u5bae\u539f"
    ],
    "name:jpn_x_variant":[
        "\u307f\u306a\u307f\u307f\u3084\u3070\u308b",
        "\u30df\u30ca\u30df\u30df\u30e4\u30d0\u30eb"
    ],
    "wof:name":"Minamimiyabaru",
    "wof:placetype":"locality"
},
  "geometry": {"coordinates":[131.05213000000001,32.98871],"type":"Point"}
}