{
  "type": "Feature",
  "properties": {
    "gn:admin1_code":"37.0",
    "gn:admin2_code":"1863526.0",
    "gn:asciiname":"Higashiyama",
    "gn:country_code":"JP",
    "gn:dem":461,
    "gn:feature_class":"P",
    "gn:feature_code":"PPL",
    "gn:name":"Higashiyama",
    "gn:population":0,
    "gn:timezone":"Asia/Tokyo",
    "iso:country":"JP",
    "name:jpn_x_preferred":[
        "\u6771\u5c71"
    ],
    "wof:name":"Higashiyama",
    "wof:placetype":"locality"
},
  "geometry": {"coordinates":[138.96143000000001,35.29656],"type":"Point"}
}