{
  "type": "Feature",
  "properties": {
    "iso:country":"JP",
    "name:eng_x_preferred":[
        "Inamuragasaki 1 Chome"
    ],
    "name:eng_x_variant":[
        "Inamuragasaki 1 Choume",
        "Inamuragasaki 1 Chome"
    ],
    "name:jpn_x_preferred":[
        "\uff11\u4e01\u76ee"
    ],
    "name:jpn_x_variant":[
        "\u3044\u306a\u3080\u3089\u304c\u3055\u304d \uff11\u3061\u3087\u3046\u3081",
        "\u7a32\u6751\u30ac\u5d0e \uff11\u4e01\u76ee",
        "\uff11\u3061\u3087\u3046\u3081"
    ],
    "qs:gn_local":0,
    "qs:local_max":2484,
    "qs:local_sum":33815,
    "qs:localhoods":49,
    "qs:name":"\uff11\u4e01\u76ee",
    "qs:name_adm0":"\u65e5\u672c",
    "qs:name_adm1":"\u795e\u5948\u5ddd\u770c",
    "qs:name_en":"Inamuragasaki 1 Chome",
    "qs:name_lau":"\u7a32\u6751\u30ac\u5d0e",
    "qs:name_local":"\u938c\u5009\u5e02",
    "qs:photo_max":242,
    "qs:photo_sum":827,
    "qs:placetype":"Suburb",
    "qs:quad_count":27,
    "qs:woe_adm0":23424856,
    "qs:woe_adm1":2345868,
    "qs:woe_adm2":0,
    "qs:woe_lau":28416719,
    "qs:woe_local":1117401,
    "qs:woe_ver":"7.10.0",
    "wof:lang":[
        "jpn"
    ],
    "wof:name":"\uff11\u4e01\u76ee",
    "wof:placetype":"neighbourhood"
},
  "geometry": {"coordinates":[139.52478500000001,35.303508],"type":"Point"}
}