{
  "type": "Feature",
  "properties": {
    "gn:admin1_code":"4.0",
    "gn:admin2_code":"1859468.0",
    "gn:asciiname":"Tokoshiro",
    "gn:country_code":"JP",
    "gn:dem":16,
    "gn:feature_class":"P",
    "gn:feature_code":"PPL",
    "gn:name":"Tokoshiro",
    "gn:population":0,
    "gn:timezone":"Asia/Tokyo",
    "iso:country":"JP",
    "name:jpn_x_preferred":[
        "\u5e38\u4ee3"
    ],
    "name:jpn_x_variant":[
        "\u3068\u3053\u3057\u308d",
        "\u30c8\u30b3\u30b7\u30ed"
    ],
    "wof:name":"Tokoshiro",
    "wof:placetype":"locality"
},
  "geometry": {"coordinates":[139.92339999999999,35.30812],"type":"Point"}
}