{
  "type": "Feature",
  "properties": {
    "gn:admin1_code":"35",
    "gn:admin2_code":"1853552.0",
    "gn:asciiname":"Katada",
    "gn:cc2":"JP",
    "gn:country_code":"JP",
    "gn:dem":86,
    "gn:feature_class":"P",
    "gn:feature_code":"PPL",
    "gn:name":"Katada",
    "gn:population":0,
    "gn:timezone":"Asia/Tokyo",
    "iso:country":"JP",
    "name:und_x_variant":[
        "Katata"
    ],
    "wof:name":"Katada",
    "wof:placetype":"locality"
},
  "geometry": {"coordinates":[135.91513,35.12047],"type":"Point"}
}