{
  "type": "Feature",
  "properties": {
    "gn:admin1_code":"16.0",
    "gn:admin2_code":"2129400.0",
    "gn:admin3_code":"3501.0",
    "gn:asciiname":"Kodeyamori",
    "gn:country_code":"JP",
    "gn:dem":245,
    "gn:feature_class":"P",
    "gn:feature_code":"PPL",
    "gn:name":"Kodeyamori",
    "gn:population":0,
    "gn:timezone":"Asia/Tokyo",
    "iso:country":"JP",
    "name:jpn_x_preferred":[
        "\u5c0f\u624b\u5c4b\u68ee"
    ],
    "name:jpn_x_variant":[
        "\u3053\u3067\u3084\u3082\u308a",
        "\u30b3\u30c7\u30e4\u30e2\u30ea"
    ],
    "wof:name":"Kodeyamori",
    "wof:placetype":"locality"
},
  "geometry": {"coordinates":[141.40022999999999,40.36453],"type":"Point"}
}