{
  "type": "Feature",
  "properties": {
    "gn:admin1_code":"6.0",
    "gn:admin2_code":"1863982.0",
    "gn:asciiname":"Shimizu-sugitanicho",
    "gn:country_code":"JP",
    "gn:dem":9,
    "gn:feature_class":"P",
    "gn:feature_code":"PPL",
    "gn:name":"Shimizu-sugitanich\u014d",
    "gn:population":0,
    "gn:timezone":"Asia/Tokyo",
    "iso:country":"JP",
    "name:jpn_x_preferred":[
        "\u6e05\u6c34\u6749\u8c37\u753a"
    ],
    "name:und_x_variant":[
        "Shimizu-sugitanich\u014d"
    ],
    "wof:name":"Shimizu-sugitanicho",
    "wof:placetype":"locality"
},
  "geometry": {"coordinates":[136.15691000000001,36.03603],"type":"Point"}
}