{
  "type": "Feature",
  "properties": {
    "gn:admin1_code":"19.0",
    "gn:admin2_code":"1864091.0",
    "gn:asciiname":"Shobusawa-sakai",
    "gn:country_code":"JP",
    "gn:dem":29,
    "gn:feature_class":"P",
    "gn:feature_code":"PPLL",
    "gn:name":"Sh\u014dbusawa-sakai",
    "gn:population":0,
    "gn:timezone":"Asia/Tokyo",
    "iso:country":"JP",
    "name:jpn_x_preferred":[
        "\u83d6\u84b2\u6ca2\u5883"
    ],
    "name:und_x_variant":[
        "Sh\u014dbusawa-sakai"
    ],
    "wof:name":"Shobusawa-sakai",
    "wof:placetype":"locality"
},
  "geometry": {"coordinates":[139.43812,35.39479],"type":"Point"}
}