{
  "type": "Feature",
  "properties": {
    "gn:admin1_code":"29",
    "gn:admin2_code":"1855427.0",
    "gn:admin3_code":"15108.0",
    "gn:asciiname":"Echizenhama",
    "gn:country_code":"JP",
    "gn:dem":9,
    "gn:feature_class":"P",
    "gn:feature_code":"PPL",
    "gn:name":"Echizenhama",
    "gn:population":0,
    "gn:timezone":"Asia/Tokyo",
    "iso:country":"JP",
    "name:jpn_x_preferred":[
        "\u8d8a\u524d\u6d5c"
    ],
    "wof:name":"Echizenhama",
    "wof:placetype":"locality"
},
  "geometry": {"coordinates":[138.84796,37.81278],"type":"Point"}
}