{
  "type": "Feature",
  "properties": {
    "gn:admin1_code":"16.0",
    "gn:admin2_code":"7441817.0",
    "gn:asciiname":"Nakazawa",
    "gn:country_code":"JP",
    "gn:dem":29,
    "gn:feature_class":"P",
    "gn:feature_code":"PPL",
    "gn:name":"Nakazawa",
    "gn:population":0,
    "gn:timezone":"Asia/Tokyo",
    "iso:country":"JP",
    "name:fin_x_preferred":[
        "Nakazawa"
    ],
    "name:jpn_x_preferred":[
        "\u4e2d\u6ca2"
    ],
    "name:jpn_x_variant":[
        "\u306a\u304b\u3056\u308f",
        "\u30ca\u30ab\u30b6\u30ef"
    ],
    "wof:name":"Nakazawa",
    "wof:placetype":"locality"
},
  "geometry": {"coordinates":[141.69566,38.95431],"type":"Point"}
}