{
  "type": "Feature",
  "properties": {
    "gn:admin1_code":"12.0",
    "gn:admin2_code":"7428109.0",
    "gn:admin3_code":"1668.0",
    "gn:asciiname":"Charo-kisen",
    "gn:country_code":"JP",
    "gn:dem":18,
    "gn:feature_class":"P",
    "gn:feature_code":"PPL",
    "gn:name":"Charo-kisen",
    "gn:population":0,
    "gn:timezone":"Asia/Tokyo",
    "iso:country":"JP",
    "name:jpn_x_preferred":[
        "\u8336\u8def\u57fa\u7dda"
    ],
    "name:jpn_x_variant":[
        "\u3061\u3083\u308d\u304d\u305b\u3093",
        "\u30c1\u30e3\u30ed\u30ad\u30bb\u30f3"
    ],
    "wof:name":"Charo-kisen",
    "wof:placetype":"locality"
},
  "geometry": {"coordinates":[144.0566,42.99184],"type":"Point"}
}