{
  "type": "Feature",
  "properties": {
    "gn:admin1_code":"29.0",
    "gn:admin2_code":"1850218.0",
    "gn:asciiname":"Kiriyama",
    "gn:country_code":"JP",
    "gn:dem":333,
    "gn:feature_class":"P",
    "gn:feature_code":"PPL",
    "gn:name":"Kiriyama",
    "gn:population":0,
    "gn:timezone":"Asia/Tokyo",
    "iso:country":"JP",
    "name:jpn_x_preferred":[
        "\u6850\u5c71"
    ],
    "wof:name":"Kiriyama",
    "wof:placetype":"locality"
},
  "geometry": {"coordinates":[138.65028999999998,37.17557],"type":"Point"}
}