{
  "type": "Feature",
  "properties": {
    "gn:admin1_code":"12.0",
    "gn:admin2_code":"2129370.0",
    "gn:asciiname":"Toyokawacho",
    "gn:country_code":"JP",
    "gn:dem":5,
    "gn:feature_class":"P",
    "gn:feature_code":"PPL",
    "gn:name":"Toyokawach\u014d",
    "gn:population":0,
    "gn:timezone":"Asia/Tokyo",
    "iso:country":"JP",
    "name:jpn_x_preferred":[
        "\u8c4a\u5ddd\u753a"
    ],
    "name:jpn_x_variant":[
        "\u3068\u3088\u304b\u308f\u3061\u3087\u3046",
        "\u30c8\u30e8\u30ab\u30ef\u30c1\u30e7\u30a6"
    ],
    "name:und_x_variant":[
        "Toyokawach\u014d"
    ],
    "wof:name":"Toyokawacho",
    "wof:placetype":"locality"
},
  "geometry": {"coordinates":[144.38022000000001,43.00871],"type":"Point"}
}