{
  "type": "Feature",
  "properties": {
    "gn:admin1_code":"33.0",
    "gn:admin2_code":"1850771.0",
    "gn:asciiname":"Hasama",
    "gn:country_code":"JP",
    "gn:dem":2,
    "gn:feature_class":"P",
    "gn:feature_code":"PPLL",
    "gn:name":"Hasama",
    "gn:population":0,
    "gn:timezone":"Asia/Tokyo",
    "iso:country":"JP",
    "name:jpn_x_preferred":[
        "\u7fbd\u4f50\u9593"
    ],
    "wof:name":"Hasama",
    "wof:placetype":"locality"
},
  "geometry": {"coordinates":[130.14988,33.27343],"type":"Point"}
}