{
  "type": "Feature",
  "properties": {
    "iso:country":"JP",
    "name:eng_x_preferred":[
        "Furukawacho 1 Chome"
    ],
    "name:eng_x_variant":[
        "Furukawachou 1 Choume",
        "Furukawacho 1 Chome"
    ],
    "name:jpn_x_preferred":[
        "\uff11\u4e01\u76ee"
    ],
    "name:jpn_x_variant":[
        "\u3075\u308b\u304b\u308f\u3061\u3087\u3046 \uff11\u3061\u3087\u3046\u3081",
        "\u53e4\u5ddd\u753a \uff11\u4e01\u76ee",
        "\uff11\u3061\u3087\u3046\u3081"
    ],
    "qs:gn_local":0,
    "qs:local_max":18,
    "qs:local_sum":38,
    "qs:localhoods":3,
    "qs:name":"\uff11\u4e01\u76ee",
    "qs:name_adm0":"\u65e5\u672c",
    "qs:name_adm1":"\u5c71\u53e3\u770c",
    "qs:name_en":"Furukawacho 1 Chome",
    "qs:name_lau":"\u53e4\u5ddd\u753a",
    "qs:name_local":"\u4e0b\u677e\u5e02",
    "qs:photo_max":11,
    "qs:photo_sum":13,
    "qs:placetype":"Suburb",
    "qs:quad_count":2,
    "qs:woe_adm0":23424856,
    "qs:woe_adm1":2345894,
    "qs:woe_adm2":0,
    "qs:woe_lau":28476607,
    "qs:woe_local":1117595,
    "qs:woe_ver":"7.10.0",
    "wof:lang":[
        "jpn"
    ],
    "wof:name":"\uff11\u4e01\u76ee",
    "wof:placetype":"neighbourhood"
},
  "geometry": {"coordinates":[131.86614800000001,34.00871],"type":"Point"}
}