{
  "type": "Feature",
  "properties": {
    "gn:admin1_code":"41",
    "gn:admin2_code":"1850247.0",
    "gn:admin3_code":"31371.0",
    "gn:asciiname":"Akasaki",
    "gn:cc2":"JP",
    "gn:country_code":"JP",
    "gn:dem":12,
    "gn:feature_class":"P",
    "gn:feature_code":"PPL",
    "gn:name":"Akasaki",
    "gn:population":0,
    "gn:timezone":"Asia/Tokyo",
    "iso:country":"JP",
    "name:und_x_variant":[
        "Akazaki",
        "Akasaki"
    ],
    "wof:name":"Akasaki",
    "wof:placetype":"locality"
},
  "geometry": {"coordinates":[133.63333,35.51667],"type":"Point"}
}