{
  "type": "Feature",
  "properties": {
    "iso:country":"JP",
    "name:eng_x_preferred":[
        "Motomachihigashi 1 Chome"
    ],
    "name:eng_x_variant":[
        "Motomachihigashi 1 Choume",
        "Motomachihigashi 1 Chome"
    ],
    "name:jpn_x_preferred":[
        "\uff11\u4e01\u76ee"
    ],
    "name:jpn_x_variant":[
        "\u3082\u3068\u307e\u3061\u3072\u304c\u3057 \uff11\u3061\u3087\u3046\u3081",
        "\u5143\u753a\u6771 \uff11\u4e01\u76ee",
        "\uff11\u3061\u3087\u3046\u3081"
    ],
    "qs:gn_local":0,
    "qs:local_max":201,
    "qs:local_sum":214,
    "qs:localhoods":3,
    "qs:name":"\uff11\u4e01\u76ee",
    "qs:name_adm0":"\u65e5\u672c",
    "qs:name_adm1":"\u9752\u68ee\u770c",
    "qs:name_en":"Motomachihigashi 1 Chome",
    "qs:name_lau":"\u5143\u753a\u6771",
    "qs:name_local":"\u5341\u548c\u7530\u5e02",
    "qs:photo_max":6,
    "qs:photo_sum":12,
    "qs:placetype":"Suburb",
    "qs:quad_count":4,
    "qs:woe_adm0":23424856,
    "qs:woe_adm1":2345853,
    "qs:woe_adm2":0,
    "qs:woe_lau":28387959,
    "qs:woe_local":1118398,
    "qs:woe_ver":"7.10.0",
    "wof:lang":[
        "jpn"
    ],
    "wof:name":"\uff11\u4e01\u76ee",
    "wof:placetype":"neighbourhood"
},
  "geometry": {"coordinates":[141.21139500000001,40.621598],"type":"Point"}
}