{
  "type": "Feature",
  "properties": {
    "gn:admin1_code":"29",
    "gn:admin2_code":"1856195.0",
    "gn:asciiname":"Hanzogane",
    "gn:country_code":"JP",
    "gn:dem":268,
    "gn:feature_class":"P",
    "gn:feature_code":"PPL",
    "gn:name":"Hanz\u014dgane",
    "gn:population":0,
    "gn:timezone":"Asia/Tokyo",
    "iso:country":"JP",
    "name:jpn_x_preferred":[
        "\u534a\u8535\u91d1"
    ],
    "name:und_x_variant":[
        "Hanz\u014dgane",
        "Hanz\u014dkane"
    ],
    "wof:name":"Hanzogane",
    "wof:placetype":"locality"
},
  "geometry": {"coordinates":[138.94723999999999,37.38259],"type":"Point"}
}