{
  "type": "Feature",
  "properties": {
    "gn:admin1_code":"18",
    "gn:admin2_code":"7383990.0",
    "gn:asciiname":"Shirahama",
    "gn:country_code":"JP",
    "gn:dem":43,
    "gn:feature_class":"P",
    "gn:feature_code":"PPL",
    "gn:name":"Shirahama",
    "gn:population":0,
    "gn:timezone":"Asia/Tokyo",
    "iso:country":"JP",
    "name:jpn_x_preferred":[
        "\u767d\u6d5c"
    ],
    "wof:name":"Shirahama",
    "wof:placetype":"locality"
},
  "geometry": {"coordinates":[130.22298000000001,31.75262],"type":"Point"}
}