{
  "type": "Feature",
  "properties": {
    "gn:admin1_code":"27.0",
    "gn:admin2_code":"7418808.0",
    "gn:asciiname":"Nakato",
    "gn:country_code":"JP",
    "gn:dem":6,
    "gn:feature_class":"P",
    "gn:feature_code":"PPLL",
    "gn:name":"Nakato",
    "gn:population":0,
    "gn:timezone":"Asia/Tokyo",
    "iso:country":"JP",
    "name:jpn_x_preferred":[
        "\u4e2d\u6238"
    ],
    "wof:name":"Nakato",
    "wof:placetype":"locality"
},
  "geometry": {"coordinates":[129.58896999999999,33.02912],"type":"Point"}
}