{
  "type": "Feature",
  "properties": {
    "gn:admin1_code":"3.0",
    "gn:admin2_code":"2128302.0",
    "gn:admin3_code":"2442.0",
    "gn:asciiname":"Kamitaira",
    "gn:country_code":"JP",
    "gn:dem":81,
    "gn:feature_class":"P",
    "gn:feature_code":"PPL",
    "gn:name":"Kamitaira",
    "gn:population":0,
    "gn:timezone":"Asia/Tokyo",
    "iso:country":"JP",
    "name:jpn_x_preferred":[
        "\u4e0a\u5e73"
    ],
    "name:jpn_x_variant":[
        "\u304b\u307f\u305f\u3044\u3089",
        "\u30ab\u30df\u30bf\u30a4\u30e9"
    ],
    "wof:name":"Kamitaira",
    "wof:placetype":"locality"
},
  "geometry": {"coordinates":[141.30288000000004,40.47809],"type":"Point"}
}