{
  "type": "Feature",
  "properties": {
    "gn:admin1_code":"4.0",
    "gn:admin2_code":"7465522.0",
    "gn:asciiname":"Sosa",
    "gn:country_code":"JP",
    "gn:dem":36,
    "gn:feature_class":"P",
    "gn:feature_code":"PPLA2",
    "gn:name":"S\u014dsa",
    "gn:population":0,
    "gn:timezone":"Asia/Tokyo",
    "iso:country":"JP",
    "name:ara_x_preferred":[
        "\u0633\u0648\u0633\u0627"
    ],
    "name:azb_x_preferred":[
        "\u0633\u0648\u0633\u0627"
    ],
    "name:deu_x_preferred":[
        "S\u014dsa"
    ],
    "name:est_x_preferred":[
        "S\u014dsa"
    ],
    "name:fas_x_preferred":[
        "\u0633\u0648\u0633\u0627\u060c \u0686\u06cc\u0628\u0627"
    ],
    "name:fas_x_variant":[
        "\u0633\u0648\u0633\u0627"
    ],
    "name:fra_x_preferred":[
        "S\u014dsa"
    ],
    "name:glg_x_preferred":[
        "S\u014dsa"
    ],
    "name:ita_x_preferred":[
        "S\u014dsa"
    ],
    "name:jpn_x_preferred":[
        "\u531d\u7473"
    ],
    "name:jpn_x_variant":[
        "\u531d\u7473\u5e02"
    ],
    "name:kor_x_preferred":[
        "\uc18c\uc0ac \uc2dc"
    ],
    "name:kor_x_variant":[
        "\uc18c\uc0ac\uc2dc"
    ],
    "name:mzn_x_preferred":[
        "\u0633\u0648\u0633\u0627\u060c \u0686\u06cc\u0628\u0627"
    ],
    "name:mzn_x_variant":[
        "\u0633\u0648\u0633\u0627"
    ],
    "name:nan_x_preferred":[
        "S\u00f4sa-chh\u012b"
    ],
    "name:nld_x_preferred":[
        "Sosa"
    ],
    "name:pol_x_preferred":[
        "S\u014dsa"
    ],
    "name:por_x_preferred":[
        "Sosa"
    ],
    "name:ron_x_preferred":[
        "S\u014dsa"
    ],
    "name:rus_x_preferred":[
        "\u0421\u043e\u0441\u0430"
    ],
    "name:spa_x_preferred":[
        "S\u014dsa"
    ],
    "name:swa_x_preferred":[
        "S\u014dsa"
    ],
    "name:swe_x_preferred":[
        "Sosa"
    ],
    "name:tgl_x_preferred":[
        "S\u014dsa"
    ],
    "name:tha_x_preferred":[
        "\u0e42\u0e0b\u0e0b\u0e30"
    ],
    "name:tum_x_preferred":[
        "S\u014dsa"
    ],
    "name:tur_x_preferred":[
        "S\u014dsa"
    ],
    "name:ukr_x_preferred":[
        "\u0421\u043e\u0441\u0430"
    ],
    "name:und_x_variant":[
        "S\u014dsa"
    ],
    "name:urd_x_preferred":[
        "\u0633\u0624\u0633\u0627\u060c \u0686\u06cc\u0628\u0627"
    ],
    "name:urd_x_variant":[
        "\u0633\u0624\u0633\u0627"
    ],
    "name:vie_x_preferred":[
        "S\u014dsa"
    ],
    "name:war_x_preferred":[
        "S\u014dsa"
    ],
    "name:zho_x_preferred":[
        "\u531d\u7473\u5e02"
    ],
    "wof:name":"Sosa",
    "wof:placetype":"locality"
},
  "geometry": {"coordinates":[140.55309,35.71541],"type":"Point"}
}