{
  "type": "Feature",
  "properties": {
    "iso:country":"JP",
    "name:eng_x_preferred":[
        "Yasuracho 3 Chome"
    ],
    "name:eng_x_variant":[
        "Yasuurachou 3 Choume",
        "Yasuracho 3 Chome"
    ],
    "name:jpn_x_preferred":[
        "\uff13\u4e01\u76ee"
    ],
    "name:jpn_x_variant":[
        "\u3084\u3059\u3046\u3089\u3061\u3087\u3046 \uff13\u3061\u3087\u3046\u3081",
        "\u5b89\u6d66\u753a \uff13\u4e01\u76ee",
        "\uff13\u3061\u3087\u3046\u3081"
    ],
    "name:unk_x_variant":[
        "\uff13\u4e01\u76ee"
    ],
    "qs:gn_local":0,
    "qs:local_max":1046,
    "qs:local_sum":7358,
    "qs:localhoods":30,
    "qs:name":"\uff13\u4e01\u76ee",
    "qs:name_adm0":"\u65e5\u672c",
    "qs:name_adm1":"\u795e\u5948\u5ddd\u770c",
    "qs:name_en":"Yasuracho 3 Chome",
    "qs:name_lau":"\u5b89\u6d66\u753a",
    "qs:name_local":"\u6a2a\u9808\u8cc0\u5e02",
    "qs:photo_max":32,
    "qs:photo_sum":45,
    "qs:placetype":"Suburb",
    "qs:quad_count":4,
    "qs:woe_adm0":23424856,
    "qs:woe_adm1":2345868,
    "qs:woe_adm2":0,
    "qs:woe_lau":28416596,
    "qs:woe_local":1118552,
    "qs:woe_ver":"7.10.0",
    "wof:lang":[
        "jpn"
    ],
    "wof:name":"\uff13\u4e01\u76ee",
    "wof:placetype":"neighbourhood"
},
  "geometry": {"coordinates":[139.67835600000001,35.27101],"type":"Point"}
}