{
  "type": "Feature",
  "properties": {
    "gn:admin1_code":"3.0",
    "gn:admin2_code":"2130056.0",
    "gn:asciiname":"Miyukicho",
    "gn:country_code":"JP",
    "gn:dem":45,
    "gn:feature_class":"P",
    "gn:feature_code":"PPL",
    "gn:name":"Miyukich\u014d",
    "gn:population":0,
    "gn:timezone":"Asia/Tokyo",
    "iso:country":"JP",
    "name:jpn_x_preferred":[
        "\u5fa1\u5e78\u753a"
    ],
    "name:jpn_x_variant":[
        "\u307f\u3086\u304d\u3061\u3087\u3046",
        "\u30df\u30e6\u30ad\u30c1\u30e7\u30a6"
    ],
    "name:und_x_variant":[
        "Miyukich\u014d"
    ],
    "wof:name":"Miyukicho",
    "wof:placetype":"locality"
},
  "geometry": {"coordinates":[140.47698,40.59345],"type":"Point"}
}