{
  "type": "Feature",
  "properties": {
    "gn:admin1_code":"8.0",
    "gn:admin2_code":"9035648.0",
    "gn:asciiname":"Shiraiwa",
    "gn:country_code":"JP",
    "gn:dem":309,
    "gn:feature_class":"P",
    "gn:feature_code":"PPL",
    "gn:name":"Shiraiwa",
    "gn:population":0,
    "gn:timezone":"Asia/Tokyo",
    "iso:country":"JP",
    "name:jpn_x_preferred":[
        "\u767d\u5ca9"
    ],
    "wof:name":"Shiraiwa",
    "wof:placetype":"locality"
},
  "geometry": {"coordinates":[140.47082,37.50271],"type":"Point"}
}