{
  "type": "Feature",
  "properties": {
    "gn:country":"JP",
    "iso:country":"JP",
    "name:eng_x_preferred":[
        "Shiogama City"
    ],
    "name:jpn_x_preferred":[
        "\u5869\u7ac8\u5e02"
    ],
    "qs:name":"\u5869\u7ac8\u5e02",
    "qs:name_adm0":"\u65e5\u672c",
    "qs:name_adm1":"\u5bae\u57ce\u770c",
    "qs:photos":1031,
    "qs:photos_1k":209,
    "qs:photos_9k":7,
    "qs:photos_9r":8,
    "qs:photos_all":1599,
    "qs:photos_sr":11,
    "qs:placetype":"Town",
    "qs:pop_sr":"0",
    "wof:name":"Shiogama City",
    "wof:placetype":"locality"
},
  "geometry": {"coordinates":[141.09593899999999,38.330413],"type":"Point"}
}