{
  "type": "Feature",
  "properties": {
    "gn:admin1_code":"23.0",
    "gn:admin2_code":"1857496.0",
    "gn:asciiname":"Ureshino-miyakocho",
    "gn:country_code":"JP",
    "gn:dem":10,
    "gn:feature_class":"P",
    "gn:feature_code":"PPL",
    "gn:name":"Ureshino-miyakoch\u014d",
    "gn:population":0,
    "gn:timezone":"Asia/Tokyo",
    "iso:country":"JP",
    "name:jpn_x_preferred":[
        "\u5b09\u91ce\u5bae\u53e4\u753a"
    ],
    "name:und_x_variant":[
        "Ureshino-miyakoch\u014d"
    ],
    "wof:name":"Ureshino-miyakocho",
    "wof:placetype":"locality"
},
  "geometry": {"coordinates":[136.46958000000001,34.64024000000001],"type":"Point"}
}