{
  "type": "Feature",
  "properties": {
    "gn:country":"JP",
    "gn:fcode":"PPL",
    "gn:pop":4654,
    "iso:country":"JP",
    "name:unk_x_variant":[
        "Niseko\u0101"
    ],
    "qs:name":"Niseko Town",
    "qs:photos_9r":0,
    "qs:photos_sr":0,
    "qs:pop_sr":"4",
    "wof:name":"Niseko Town",
    "wof:placetype":"locality",
    "wof:population":4654
},
  "geometry": {"coordinates":[140.66902999999999,42.77871],"type":"Point"}
}