{
  "type": "Feature",
  "properties": {
    "gn:admin1_code":"21.0",
    "gn:admin2_code":"7413151.0",
    "gn:asciiname":"Funagura",
    "gn:country_code":"JP",
    "gn:dem":32,
    "gn:feature_class":"P",
    "gn:feature_code":"PPLL",
    "gn:name":"Funagura",
    "gn:population":0,
    "gn:timezone":"Asia/Tokyo",
    "iso:country":"JP",
    "name:jpn_x_preferred":[
        "\u8239\u5009"
    ],
    "name:jpn_x_variant":[
        "\u3075\u306a\u3050\u3089",
        "\u30d5\u30ca\u30b0\u30e9"
    ],
    "wof:name":"Funagura",
    "wof:placetype":"locality"
},
  "geometry": {"coordinates":[130.40035,32.46277],"type":"Point"}
}