{
  "type": "Feature",
  "properties": {
    "gn:admin1_code":"2.0",
    "gn:admin2_code":"2113122.0",
    "gn:asciiname":"Koyo-aoyagicho",
    "gn:country_code":"JP",
    "gn:dem":6,
    "gn:feature_class":"P",
    "gn:feature_code":"PPL",
    "gn:name":"K\u014dy\u014d-aoyagich\u014d",
    "gn:population":0,
    "gn:timezone":"Asia/Tokyo",
    "iso:country":"JP",
    "name:jpn_x_preferred":[
        "\u9ad8\u967d\u9752\u67f3\u753a"
    ],
    "name:jpn_x_variant":[
        "\u3053\u3046\u3088\u3046\u3042\u304a\u3084\u304e\u3061\u3087\u3046",
        "\u30b3\u30a6\u30e8\u30a6\u30a2\u30aa\u30e4\u30ae\u30c1\u30e7\u30a6"
    ],
    "name:und_x_variant":[
        "K\u014dy\u014d-aoyagich\u014d"
    ],
    "wof:name":"Koyo-aoyagicho",
    "wof:placetype":"locality"
},
  "geometry": {"coordinates":[140.10266999999999,39.72519000000001],"type":"Point"}
}