{
  "type": "Feature",
  "properties": {
    "gn:admin1_code":"37.0",
    "gn:admin2_code":"1864104.0",
    "gn:asciiname":"Habuna",
    "gn:country_code":"JP",
    "gn:dem":121,
    "gn:feature_class":"P",
    "gn:feature_code":"PPL",
    "gn:name":"Habuna",
    "gn:population":0,
    "gn:timezone":"Asia/Tokyo",
    "iso:country":"JP",
    "name:jpn_x_preferred":[
        "\u7fbd\u9b92"
    ],
    "wof:name":"Habuna",
    "wof:placetype":"locality"
},
  "geometry": {"coordinates":[138.57239999999999,35.20446],"type":"Point"}
}