{
  "type": "Feature",
  "properties": {
    "gn:admin1_code":"3.0",
    "gn:admin2_code":"7439934.0",
    "gn:asciiname":"Mitsumoriyama",
    "gn:country_code":"JP",
    "gn:dem":389,
    "gn:feature_class":"P",
    "gn:feature_code":"PPL",
    "gn:name":"Mitsumoriyama",
    "gn:population":0,
    "gn:timezone":"Asia/Tokyo",
    "iso:country":"JP",
    "name:jpn_x_preferred":[
        "\u4e09\u30c3\u68ee\u5c71"
    ],
    "name:jpn_x_variant":[
        "\u307f\u3064\u3082\u308a\u3084\u307e",
        "\u30df\u30c4\u30e2\u30ea\u30e4\u30de"
    ],
    "wof:name":"Mitsumoriyama",
    "wof:placetype":"locality"
},
  "geometry": {"coordinates":[140.67559,40.49175],"type":"Point"}
}