{
  "type": "Feature",
  "properties": {
    "gn:admin1_code":"21.0",
    "gn:admin2_code":"7413150.0",
    "gn:asciiname":"Hiraogi",
    "gn:country_code":"JP",
    "gn:dem":72,
    "gn:feature_class":"P",
    "gn:feature_code":"PPLL",
    "gn:name":"Hiraogi",
    "gn:population":0,
    "gn:timezone":"Asia/Tokyo",
    "iso:country":"JP",
    "name:jpn_x_preferred":[
        "\u5e73\u5c0f\u57ce"
    ],
    "name:jpn_x_variant":[
        "\u3072\u3089\u304a\u304e",
        "\u30d2\u30e9\u30aa\u30ae"
    ],
    "wof:name":"Hiraogi",
    "wof:placetype":"locality"
},
  "geometry": {"coordinates":[130.66613000000001,33.05085],"type":"Point"}
}