{
  "type": "Feature",
  "properties": {
    "gn:admin1_code":"19.0",
    "gn:admin2_code":"1848350.0",
    "gn:admin3_code":"14113.0",
    "gn:asciiname":"Kamiyama",
    "gn:country_code":"JP",
    "gn:dem":39,
    "gn:feature_class":"P",
    "gn:feature_code":"PPL",
    "gn:name":"Kamiyama",
    "gn:population":0,
    "gn:timezone":"Asia/Tokyo",
    "iso:country":"JP",
    "name:jpn_x_preferred":[
        "\u4e0a\u5c71"
    ],
    "wof:name":"Kamiyama",
    "wof:placetype":"locality"
},
  "geometry": {"coordinates":[139.54776000000001,35.50631],"type":"Point"}
}