{
  "type": "Feature",
  "properties": {
    "gn:admin1_code":"3.0",
    "gn:admin2_code":"2130056.0",
    "gn:asciiname":"Take",
    "gn:country_code":"JP",
    "gn:dem":454,
    "gn:feature_class":"P",
    "gn:feature_code":"PPL",
    "gn:name":"Take",
    "gn:population":0,
    "gn:timezone":"Asia/Tokyo",
    "iso:country":"JP",
    "name:jpn_x_preferred":[
        "\u5dbd"
    ],
    "name:jpn_x_variant":[
        "\u305f\u3051",
        "\u30bf\u30b1"
    ],
    "wof:name":"Take",
    "wof:placetype":"locality"
},
  "geometry": {"coordinates":[140.26575,40.63039000000001],"type":"Point"}
}