{
  "type": "Feature",
  "properties": {
    "gn:admin1_code":"7.0",
    "gn:admin2_code":"1861834.0",
    "gn:asciiname":"Kurobaru",
    "gn:country_code":"JP",
    "gn:dem":99,
    "gn:feature_class":"P",
    "gn:feature_code":"PPLL",
    "gn:name":"Kur\u014dbaru",
    "gn:population":0,
    "gn:timezone":"Asia/Tokyo",
    "iso:country":"JP",
    "name:jpn_x_preferred":[
        "\u4e5d\u90ce\u539f"
    ],
    "name:und_x_variant":[
        "Kur\u014dbaru"
    ],
    "wof:name":"Kurobaru",
    "wof:placetype":"locality"
},
  "geometry": {"coordinates":[130.61252999999999,33.59442],"type":"Point"}
}