{
  "type": "Feature",
  "properties": {
    "gn:admin1_code":"37.0",
    "gn:admin2_code":"1854900.0",
    "gn:asciiname":"Banba",
    "gn:country_code":"JP",
    "gn:dem":6,
    "gn:feature_class":"P",
    "gn:feature_code":"PPLL",
    "gn:name":"Banba",
    "gn:population":0,
    "gn:timezone":"Asia/Tokyo",
    "iso:country":"JP",
    "name:deu_x_preferred":[
        "Banba"
    ],
    "name:fin_x_preferred":[
        "Banbha"
    ],
    "name:fra_x_preferred":[
        "Banba"
    ],
    "name:gle_x_preferred":[
        "Banbha"
    ],
    "name:ita_x_preferred":[
        "Banba"
    ],
    "name:jpn_x_preferred":[
        "\u99ac\u5834"
    ],
    "name:jpn_x_variant":[
        "\u3070\u3093\u3070",
        "\u30d0\u30f3\u30d0"
    ],
    "name:nld_x_preferred":[
        "Banba"
    ],
    "name:pol_x_preferred":[
        "Banba"
    ],
    "name:por_x_preferred":[
        "Banba"
    ],
    "wof:name":"Banba",
    "wof:placetype":"locality"
},
  "geometry": {"coordinates":[138.86976000000001,35.08389],"type":"Point"}
}