{
  "type": "Feature",
  "properties": {
    "gn:admin1_code":"16.0",
    "gn:admin2_code":"2128940.0",
    "gn:asciiname":"Natsumagi",
    "gn:country_code":"JP",
    "gn:dem":281,
    "gn:feature_class":"P",
    "gn:feature_code":"PPL",
    "gn:name":"Natsumagi",
    "gn:population":0,
    "gn:timezone":"Asia/Tokyo",
    "iso:country":"JP",
    "name:jpn_x_preferred":[
        "\u590f\u9593\u6728"
    ],
    "name:jpn_x_variant":[
        "\u306a\u3064\u307e\u304e",
        "\u30ca\u30c4\u30de\u30ae"
    ],
    "wof:name":"Natsumagi",
    "wof:placetype":"locality"
},
  "geometry": {"coordinates":[141.3305,40.28649],"type":"Point"}
}