{
  "type": "Feature",
  "properties": {
    "iso:country":"JP",
    "qs:name":"\u6771\u901a\u6751",
    "qs:name_adm0":"\u65e5\u672c",
    "qs:name_adm1":"\u9752\u68ee\u770c",
    "qs:photos":175,
    "qs:photos_1k":35,
    "qs:photos_9k":1,
    "qs:photos_9r":4,
    "qs:photos_all":175,
    "qs:photos_sr":4,
    "qs:placetype":"Town",
    "qs:pop_sr":"0",
    "wof:name":"\u6771\u901a\u6751",
    "wof:placetype":"locality"
},
  "geometry": {"coordinates":[141.45944499999999,41.424163],"type":"Point"}
}