{
  "type": "Feature",
  "properties": {
    "gn:admin1_code":"37.0",
    "gn:admin2_code":"1848772.0",
    "gn:asciiname":"Aikawa",
    "gn:country_code":"JP",
    "gn:dem":24,
    "gn:feature_class":"P",
    "gn:feature_code":"PPL",
    "gn:name":"Aikawa",
    "gn:population":0,
    "gn:timezone":"Asia/Tokyo",
    "iso:country":"JP",
    "name:jpn_x_preferred":[
        "\u76f8\u5ddd"
    ],
    "wof:name":"Aikawa",
    "wof:placetype":"locality"
},
  "geometry": {"coordinates":[138.26008999999999,34.80573],"type":"Point"}
}