{
  "type": "Feature",
  "properties": {
    "gn:admin1_code":"3.0",
    "gn:admin2_code":"2128302.0",
    "gn:admin3_code":"2445.0",
    "gn:asciiname":"Kobashi",
    "gn:country_code":"JP",
    "gn:dem":116,
    "gn:feature_class":"P",
    "gn:feature_code":"PPL",
    "gn:name":"Kobashi",
    "gn:population":0,
    "gn:timezone":"Asia/Tokyo",
    "iso:country":"JP",
    "name:jpn_x_preferred":[
        "\u5c0f\u6a4b"
    ],
    "name:jpn_x_variant":[
        "\u3053\u3070\u3057",
        "\u30b3\u30d0\u30b7"
    ],
    "wof:name":"Kobashi",
    "wof:placetype":"locality"
},
  "geometry": {"coordinates":[141.42596,40.45263],"type":"Point"}
}