{
  "type": "Feature",
  "properties": {
    "gn:admin1_code":"6.0",
    "gn:admin2_code":"1863982.0",
    "gn:asciiname":"Fuchi",
    "gn:country_code":"JP",
    "gn:dem":5,
    "gn:feature_class":"P",
    "gn:feature_code":"PPL",
    "gn:name":"Fuchi",
    "gn:population":0,
    "gn:timezone":"Asia/Tokyo",
    "iso:country":"JP",
    "name:ceb_x_preferred":[
        "Fuchi"
    ],
    "name:jpn_x_preferred":[
        "\u6e15"
    ],
    "name:swe_x_preferred":[
        "Fuchi"
    ],
    "wof:name":"Fuchi",
    "wof:placetype":"locality"
},
  "geometry": {"coordinates":[136.18691000000001,36.04171],"type":"Point"}
}