{
  "type": "Feature",
  "properties": {
    "gn:admin1_code":"3.0",
    "gn:admin2_code":"2127674.0",
    "gn:asciiname":"Sakaemori",
    "gn:country_code":"JP",
    "gn:dem":55,
    "gn:feature_class":"P",
    "gn:feature_code":"PPL",
    "gn:name":"Sakaemori",
    "gn:population":0,
    "gn:timezone":"Asia/Tokyo",
    "iso:country":"JP",
    "name:jpn_x_preferred":[
        "\u6804\u68ee"
    ],
    "name:jpn_x_variant":[
        "\u3055\u304b\u3048\u3082\u308a",
        "\u30b5\u30ab\u30a8\u30e2\u30ea"
    ],
    "wof:name":"Sakaemori",
    "wof:placetype":"locality"
},
  "geometry": {"coordinates":[141.19110000000001,40.65468],"type":"Point"}
}