{
  "type": "Feature",
  "properties": {
    "gn:admin1_code":"19",
    "gn:admin2_code":"1860670.0",
    "gn:asciiname":"Koshigoe",
    "gn:country_code":"JP",
    "gn:dem":11,
    "gn:feature_class":"P",
    "gn:feature_code":"PPL",
    "gn:name":"Koshigoe",
    "gn:population":0,
    "gn:timezone":"Asia/Tokyo",
    "iso:country":"JP",
    "name:jpn_x_preferred":[
        "\u8170\u8d8a"
    ],
    "wof:name":"Koshigoe",
    "wof:placetype":"locality"
},
  "geometry": {"coordinates":[139.49476999999999,35.30935],"type":"Point"}
}