{
  "type": "Feature",
  "properties": {
    "gn:admin1_code":"13",
    "gn:admin2_code":"1865383.0",
    "gn:asciiname":"Nishinagasucho",
    "gn:country_code":"JP",
    "gn:dem":0,
    "gn:feature_class":"P",
    "gn:feature_code":"PPL",
    "gn:name":"Nishinagasuch\u014d",
    "gn:population":0,
    "gn:timezone":"Asia/Tokyo",
    "iso:country":"JP",
    "name:jpn_x_preferred":[
        "\u897f\u9577\u6d32\u753a"
    ],
    "name:und_x_variant":[
        "Nishinagasuch\u014d",
        "Nishi-nagasu"
    ],
    "wof:name":"Nishinagasucho",
    "wof:placetype":"locality"
},
  "geometry": {"coordinates":[135.41945000000001,34.7248],"type":"Point"}
}