{
  "type": "Feature",
  "properties": {
    "gn:admin1_code":"21.0",
    "gn:admin2_code":"1865358.0",
    "gn:asciiname":"Yokohama",
    "gn:country_code":"JP",
    "gn:dem":3,
    "gn:feature_class":"P",
    "gn:feature_code":"PPLL",
    "gn:name":"Yokohama",
    "gn:population":0,
    "gn:timezone":"Asia/Tokyo",
    "iso:country":"JP",
    "name:jpn_x_preferred":[
        "\u6a2a\u6d5c"
    ],
    "name:jpn_x_variant":[
        "\u3088\u3053\u306f\u307e",
        "\u30e8\u30b3\u30cf\u30de"
    ],
    "wof:name":"Yokohama",
    "wof:placetype":"locality"
},
  "geometry": {"coordinates":[130.29495,32.48879],"type":"Point"}
}