{
  "type": "Feature",
  "properties": {
    "gn:admin1_code":"10",
    "gn:admin2_code":"7453747.0",
    "gn:admin3_code":"10429.0",
    "gn:asciiname":"Haramachi",
    "gn:country_code":"JP",
    "gn:dem":404,
    "gn:feature_class":"P",
    "gn:feature_code":"PPL",
    "gn:name":"Haramachi",
    "gn:population":0,
    "gn:timezone":"Asia/Tokyo",
    "iso:country":"JP",
    "wof:name":"Haramachi",
    "wof:placetype":"locality"
},
  "geometry": {"coordinates":[138.83333000000002,36.56667],"type":"Point"}
}