{
  "type": "Feature",
  "properties": {
    "gn:admin1_code":"25",
    "gn:admin2_code":"1862717.0",
    "gn:admin3_code":"45431.0",
    "gn:asciiname":"Kurogi",
    "gn:cc2":"JP",
    "gn:country_code":"JP",
    "gn:dem":114,
    "gn:feature_class":"P",
    "gn:feature_code":"PPL",
    "gn:name":"Kurogi",
    "gn:population":0,
    "gn:timezone":"Asia/Tokyo",
    "iso:country":"JP",
    "name:und_x_variant":[
        "Kuroki",
        "Kurogi"
    ],
    "wof:name":"Kurogi",
    "wof:placetype":"locality"
},
  "geometry": {"coordinates":[131.51667,32.51667],"type":"Point"}
}