{
  "type": "Feature",
  "properties": {
    "iso:country":"JP",
    "name:eng_x_preferred":[
        "Hashiridani 1 Chome"
    ],
    "name:eng_x_variant":[
        "Hashiridani 1 Choume",
        "Hashiridani 1 Chome"
    ],
    "name:jpn_x_preferred":[
        "\uff11\u4e01\u76ee"
    ],
    "name:jpn_x_variant":[
        "\u306f\u3057\u308a\u3060\u306b \uff11\u3061\u3087\u3046\u3081",
        "\u8d70\u8c37 \uff11\u4e01\u76ee",
        "\uff11\u3061\u3087\u3046\u3081"
    ],
    "qs:gn_local":0,
    "qs:local_max":291,
    "qs:local_sum":517,
    "qs:localhoods":8,
    "qs:name":"\uff11\u4e01\u76ee",
    "qs:name_adm0":"\u65e5\u672c",
    "qs:name_adm1":"\u5927\u962a\u5e9c",
    "qs:name_en":"Hashiridani 1 Chome",
    "qs:name_lau":"\u8d70\u8c37",
    "qs:name_local":"\u679a\u65b9\u5e02",
    "qs:photo_max":20,
    "qs:photo_sum":41,
    "qs:placetype":"Suburb",
    "qs:quad_count":5,
    "qs:woe_adm0":23424856,
    "qs:woe_adm1":2345881,
    "qs:woe_adm2":0,
    "qs:woe_lau":28458921,
    "qs:woe_local":1108951,
    "qs:woe_ver":"7.10.0",
    "wof:lang":[
        "jpn"
    ],
    "wof:name":"\uff11\u4e01\u76ee",
    "wof:placetype":"neighbourhood"
},
  "geometry": {"coordinates":[135.63781,34.804948],"type":"Point"}
}