{
  "type": "Feature",
  "properties": {
    "gn:admin1_code":"4.0",
    "gn:admin2_code":"7465524.0",
    "gn:asciiname":"Minamishitamichi",
    "gn:country_code":"JP",
    "gn:dem":7,
    "gn:feature_class":"P",
    "gn:feature_code":"PPLL",
    "gn:name":"Minamishitamichi",
    "gn:population":0,
    "gn:timezone":"Asia/Tokyo",
    "iso:country":"JP",
    "name:jpn_x_preferred":[
        "\u5357\u4e0b\u9053"
    ],
    "name:jpn_x_variant":[
        "\u307f\u306a\u307f\u3057\u305f\u307f\u3061",
        "\u30df\u30ca\u30df\u30b7\u30bf\u30df\u30c1"
    ],
    "wof:name":"Minamishitamichi",
    "wof:placetype":"locality"
},
  "geometry": {"coordinates":[140.39458999999999,35.26694000000001],"type":"Point"}
}