{
  "type": "Feature",
  "properties": {
    "gn:admin1_code":"4.0",
    "gn:admin2_code":"1859468.0",
    "gn:asciiname":"Tanaka",
    "gn:country_code":"JP",
    "gn:dem":21,
    "gn:feature_class":"P",
    "gn:feature_code":"PPLL",
    "gn:name":"Tanaka",
    "gn:population":0,
    "gn:timezone":"Asia/Tokyo",
    "iso:country":"JP",
    "name:jpn_x_preferred":[
        "\u7530\u4e2d"
    ],
    "name:jpn_x_variant":[
        "\u305f\u306a\u304b",
        "\u30bf\u30ca\u30ab"
    ],
    "wof:name":"Tanaka",
    "wof:placetype":"locality"
},
  "geometry": {"coordinates":[139.96475000000001,35.3088],"type":"Point"}
}