{
  "type": "Feature",
  "properties": {
    "gn:admin1_code":"21.0",
    "gn:admin2_code":"1865358.0",
    "gn:asciiname":"Nakanoshioya",
    "gn:country_code":"JP",
    "gn:dem":13,
    "gn:feature_class":"P",
    "gn:feature_code":"PPLL",
    "gn:name":"Nakanoshioya",
    "gn:population":0,
    "gn:timezone":"Asia/Tokyo",
    "iso:country":"JP",
    "name:jpn_x_preferred":[
        "\u4e2d\u306e\u5869\u5c4b"
    ],
    "name:jpn_x_variant":[
        "\u306a\u304b\u306e\u3057\u304a\u3084",
        "\u30ca\u30ab\u30ce\u30b7\u30aa\u30e4"
    ],
    "wof:name":"Nakanoshioya",
    "wof:placetype":"locality"
},
  "geometry": {"coordinates":[130.24611999999999,32.46634],"type":"Point"}
}