{
  "type": "Feature",
  "properties": {
    "gn:admin1_code":"21.0",
    "gn:admin2_code":"1850744.0",
    "gn:admin3_code":"43364.0",
    "gn:asciiname":"Zasu",
    "gn:country_code":"JP",
    "gn:dem":71,
    "gn:feature_class":"P",
    "gn:feature_code":"PPLL",
    "gn:name":"Zasu",
    "gn:population":0,
    "gn:timezone":"Asia/Tokyo",
    "iso:country":"JP",
    "name:jpn_x_preferred":[
        "\u5ea7\u4e3b"
    ],
    "name:jpn_x_variant":[
        "\u3056\u3059",
        "\u30b6\u30b9"
    ],
    "wof:name":"Zasu",
    "wof:placetype":"locality"
},
  "geometry": {"coordinates":[130.63012000000001,32.89654],"type":"Point"}
}