{
  "type": "Feature",
  "properties": {
    "gn:admin1_code":"21.0",
    "gn:admin2_code":"7413152.0",
    "gn:asciiname":"Tatsuda",
    "gn:country_code":"JP",
    "gn:dem":20,
    "gn:feature_class":"P",
    "gn:feature_code":"PPLL",
    "gn:name":"Tatsuda",
    "gn:population":0,
    "gn:timezone":"Asia/Tokyo",
    "iso:country":"JP",
    "name:jpn_x_preferred":[
        "\u7acb\u7530"
    ],
    "name:jpn_x_variant":[
        "\u305f\u3064\u3060",
        "\u30bf\u30c4\u30c0"
    ],
    "wof:name":"Tatsuda",
    "wof:placetype":"locality"
},
  "geometry": {"coordinates":[130.7116,32.64713],"type":"Point"}
}