{
  "type": "Feature",
  "properties": {
    "gn:admin1_code":"21.0",
    "gn:admin2_code":"1859490.0",
    "gn:admin3_code":"43404.0",
    "gn:asciiname":"Okino",
    "gn:country_code":"JP",
    "gn:dem":74,
    "gn:feature_class":"P",
    "gn:feature_code":"PPL",
    "gn:name":"Okino",
    "gn:population":0,
    "gn:timezone":"Asia/Tokyo",
    "iso:country":"JP",
    "name:jpn_x_preferred":[
        "\u6c96\u91ce"
    ],
    "name:jpn_x_variant":[
        "\u304a\u304d\u306e",
        "\u30aa\u30ad\u30ce"
    ],
    "wof:name":"Okino",
    "wof:placetype":"locality"
},
  "geometry": {"coordinates":[130.79169999999999,32.87009],"type":"Point"}
}