{
  "type": "Feature",
  "properties": {
    "gn:admin1_code":"21",
    "gn:admin2_code":"1857206.0",
    "gn:asciiname":"Umedocho",
    "gn:country_code":"JP",
    "gn:dem":7,
    "gn:feature_class":"P",
    "gn:feature_code":"PPL",
    "gn:name":"Umedoch\u014d",
    "gn:population":0,
    "gn:timezone":"Asia/Tokyo",
    "iso:country":"JP",
    "name:jpn_x_preferred":[
        "\u6885\u6238\u753a"
    ],
    "name:jpn_x_variant":[
        "\u3046\u3081\u3069\u3061\u3087\u3046",
        "\u30a6\u30e1\u30c9\u30c1\u30e7\u30a6"
    ],
    "name:und_x_variant":[
        "Umedoch\u014d",
        "Umedo"
    ],
    "wof:name":"Umedocho",
    "wof:placetype":"locality"
},
  "geometry": {"coordinates":[130.38548,32.20871],"type":"Point"}
}