{
  "type": "Feature",
  "properties": {
    "gn:admin1_code":"8.0",
    "gn:admin2_code":"7451488.0",
    "gn:admin3_code":"7543.0",
    "gn:asciiname":"Hinago",
    "gn:country_code":"JP",
    "gn:dem":88,
    "gn:feature_class":"P",
    "gn:feature_code":"PPLL",
    "gn:name":"Hinag\u014d",
    "gn:population":0,
    "gn:timezone":"Asia/Tokyo",
    "iso:country":"JP",
    "name:jpn_x_preferred":[
        "\u65e5\u5357\u90f7"
    ],
    "name:und_x_variant":[
        "Hinag\u014d"
    ],
    "wof:name":"Hinago",
    "wof:placetype":"locality"
},
  "geometry": {"coordinates":[140.96382,37.36786],"type":"Point"}
}