{
  "type": "Feature",
  "properties": {
    "gn:admin1_code":"19.0",
    "gn:admin2_code":"1864091.0",
    "gn:asciiname":"Furusato",
    "gn:country_code":"JP",
    "gn:dem":33,
    "gn:feature_class":"P",
    "gn:feature_code":"PPLL",
    "gn:name":"Furusato",
    "gn:population":0,
    "gn:timezone":"Asia/Tokyo",
    "iso:country":"JP",
    "name:fra_x_preferred":[
        "Furusato"
    ],
    "name:jpn_x_preferred":[
        "\u53e4\u91cc"
    ],
    "name:jpn_x_variant":[
        "\u3075\u308b\u3055\u3068"
    ],
    "name:kor_x_preferred":[
        "\ud6c4\ub8e8\uc0ac\ud1a0"
    ],
    "wof:name":"Furusato",
    "wof:placetype":"locality"
},
  "geometry": {"coordinates":[139.41967,35.39937000000001],"type":"Point"}
}