{
  "type": "Feature",
  "properties": {
    "gn:admin1_code":"18.0",
    "gn:admin2_code":"1862007.0",
    "gn:asciiname":"Kaimon-kawashiri",
    "gn:country_code":"JP",
    "gn:dem":17,
    "gn:feature_class":"P",
    "gn:feature_code":"PPL",
    "gn:name":"Kaimon-kawashiri",
    "gn:population":0,
    "gn:timezone":"Asia/Tokyo",
    "iso:country":"JP",
    "name:jpn_x_preferred":[
        "\u958b\u805e\u5ddd\u5c3b"
    ],
    "wof:name":"Kaimon-kawashiri",
    "wof:placetype":"locality"
},
  "geometry": {"coordinates":[130.55946,31.18096],"type":"Point"}
}