{
  "type": "Feature",
  "properties": {
    "iso:country":"JP",
    "name:eng_x_preferred":[
        "Arai 2 Chome"
    ],
    "name:eng_x_variant":[
        "Arai 2 Choume",
        "Arai 2 Chome"
    ],
    "name:jpn_x_preferred":[
        "\uff12\u4e01\u76ee"
    ],
    "name:jpn_x_variant":[
        "\u3042\u3089\u3044 \uff12\u3061\u3087\u3046\u3081",
        "\u65b0\u4e95 \uff12\u4e01\u76ee",
        "\uff12\u3061\u3087\u3046\u3081"
    ],
    "qs:gn_local":0,
    "qs:local_max":488,
    "qs:local_sum":1345,
    "qs:localhoods":6,
    "qs:name":"\uff12\u4e01\u76ee",
    "qs:name_adm0":"\u65e5\u672c",
    "qs:name_adm1":"\u9759\u5ca1\u770c",
    "qs:name_en":"Arai 2 Chome",
    "qs:name_lau":"\u65b0\u4e95",
    "qs:name_local":"\u4f0a\u6771\u5e02",
    "qs:photo_max":61,
    "qs:photo_sum":216,
    "qs:placetype":"Suburb",
    "qs:quad_count":13,
    "qs:woe_adm0":23424856,
    "qs:woe_adm1":2345886,
    "qs:woe_adm2":0,
    "qs:woe_lau":28437504,
    "qs:woe_local":1117332,
    "qs:woe_ver":"7.10.0",
    "wof:lang":[
        "jpn"
    ],
    "wof:name":"\uff12\u4e01\u76ee",
    "wof:placetype":"neighbourhood"
},
  "geometry": {"coordinates":[139.10879399999999,34.972447],"type":"Point"}
}