{
  "type": "Feature",
  "properties": {
    "gn:admin1_code":"2.0",
    "gn:admin2_code":"2128864.0",
    "gn:asciiname":"Tokiwa",
    "gn:country_code":"JP",
    "gn:dem":15,
    "gn:feature_class":"P",
    "gn:feature_code":"PPL",
    "gn:name":"Tokiwa",
    "gn:population":0,
    "gn:timezone":"Asia/Tokyo",
    "iso:country":"JP",
    "name:jpn_x_preferred":[
        "\u5e38\u76e4"
    ],
    "name:spa_x_preferred":[
        "Tokiwa"
    ],
    "wof:name":"Tokiwa",
    "wof:placetype":"locality"
},
  "geometry": {"coordinates":[140.14193999999998,40.22668],"type":"Point"}
}