{
  "type": "Feature",
  "properties": {
    "gn:admin1_code":"27.0",
    "gn:admin2_code":"1852895.0",
    "gn:asciiname":"Nishishimotake",
    "gn:country_code":"JP",
    "gn:dem":375,
    "gn:feature_class":"P",
    "gn:feature_code":"PPLL",
    "gn:name":"Nishishimotake",
    "gn:population":0,
    "gn:timezone":"Asia/Tokyo",
    "iso:country":"JP",
    "name:jpn_x_preferred":[
        "\u897f\u4e0b\u5cb3"
    ],
    "wof:name":"Nishishimotake",
    "wof:placetype":"locality"
},
  "geometry": {"coordinates":[129.78666000000001,33.22364],"type":"Point"}
}