{
  "type": "Feature",
  "properties": {
    "gn:admin1_code":"7.0",
    "gn:admin2_code":"1863955.0",
    "gn:admin3_code":"40136.0",
    "gn:asciiname":"Higashiaburayama",
    "gn:country_code":"JP",
    "gn:dem":33,
    "gn:feature_class":"P",
    "gn:feature_code":"PPL",
    "gn:name":"Higashiaburayama",
    "gn:population":0,
    "gn:timezone":"Asia/Tokyo",
    "iso:country":"JP",
    "name:jpn_x_preferred":[
        "\u6771\u6cb9\u5c71"
    ],
    "wof:name":"Higashiaburayama",
    "wof:placetype":"locality"
},
  "geometry": {"coordinates":[130.37906000000001,33.53536],"type":"Point"}
}