{
  "type": "Feature",
  "properties": {
    "gn:admin1_code":"40.0",
    "gn:admin2_code":"1865425.0",
    "gn:asciiname":"Akishima",
    "gn:country_code":"JP",
    "gn:dem":110,
    "gn:feature_class":"P",
    "gn:feature_code":"PPLA2",
    "gn:name":"Akishima",
    "gn:population":0,
    "gn:timezone":"Asia/Tokyo",
    "iso:country":"JP",
    "name:ara_x_preferred":[
        "\u0623\u0643\u064a\u0634\u064a\u0645\u0627"
    ],
    "name:azb_x_preferred":[
        "\u0622\u06a9\u06cc\u0634\u06cc\u0645\u0627"
    ],
    "name:cat_x_preferred":[
        "Akishima"
    ],
    "name:ceb_x_preferred":[
        "Akishima-shi"
    ],
    "name:ces_x_preferred":[
        "Aki\u0161ima"
    ],
    "name:deu_x_preferred":[
        "Akishima"
    ],
    "name:epo_x_preferred":[
        "Aki\u015dima"
    ],
    "name:est_x_preferred":[
        "Akishima"
    ],
    "name:eus_x_preferred":[
        "Akishima"
    ],
    "name:fas_x_preferred":[
        "\u0622\u06a9\u06cc\u0634\u06cc\u0645\u0627\u060c \u062a\u0648\u06a9\u06cc\u0648"
    ],
    "name:fas_x_variant":[
        "\u0622\u06a9\u06cc\u0634\u06cc\u0645\u0627"
    ],
    "name:fin_x_preferred":[
        "Akishima"
    ],
    "name:fra_x_preferred":[
        "Akishima"
    ],
    "name:glg_x_preferred":[
        "Akishima"
    ],
    "name:hye_x_preferred":[
        "\u0531\u056f\u056b\u057d\u056b\u0574\u0561"
    ],
    "name:ita_x_preferred":[
        "Akishima"
    ],
    "name:jpn_x_preferred":[
        "\u662d\u5cf6"
    ],
    "name:jpn_x_variant":[
        "\u662d\u5cf6\u5e02"
    ],
    "name:kor_x_preferred":[
        "\uc544\ud0a4\uc2dc\ub9c8 \uc2dc"
    ],
    "name:kor_x_variant":[
        "\uc544\ud0a4\uc2dc\ub9c8\uc2dc"
    ],
    "name:lit_x_preferred":[
        "Aki\u0161ima"
    ],
    "name:msa_x_preferred":[
        "Akishima"
    ],
    "name:mzn_x_preferred":[
        "\u0622\u06a9\u06cc\u0634\u06cc\u0645\u0627\u060c \u062a\u0648\u06a9\u06cc\u0648"
    ],
    "name:mzn_x_variant":[
        "\u0622\u06a9\u06cc\u0634\u06cc\u0645\u0627"
    ],
    "name:nan_x_preferred":[
        "Akisima-chh\u012b"
    ],
    "name:nld_x_preferred":[
        "Akishima"
    ],
    "name:pol_x_preferred":[
        "Akishima"
    ],
    "name:por_x_preferred":[
        "Akishima"
    ],
    "name:ron_x_preferred":[
        "Akishima"
    ],
    "name:rus_x_preferred":[
        "\u0410\u043a\u0438\u0441\u0438\u043c\u0430"
    ],
    "name:spa_x_preferred":[
        "Akishima"
    ],
    "name:srp_x_preferred":[
        "\u0410\u043a\u0438\u0448\u0438\u043c\u0430"
    ],
    "name:swe_x_preferred":[
        "Akishima"
    ],
    "name:tgk_x_preferred":[
        "\u0410\u043a\u0438\u0448\u0438\u043c\u0430"
    ],
    "name:tgl_x_preferred":[
        "Akishima"
    ],
    "name:tha_x_preferred":[
        "\u0e2d\u0e30\u0e01\u0e34\u0e0a\u0e34\u0e21\u0e30"
    ],
    "name:tha_x_variant":[
        "\u0e2d\u0e32\u0e01\u0e34\u0e0a\u0e34\u0e21\u0e30"
    ],
    "name:tum_x_preferred":[
        "Akishima"
    ],
    "name:tur_x_preferred":[
        "Akishima"
    ],
    "name:ukr_x_preferred":[
        "\u0410\u043a\u0456\u0441\u0456\u043c\u0430"
    ],
    "name:vie_x_preferred":[
        "Akishima"
    ],
    "name:war_x_preferred":[
        "Akishima"
    ],
    "name:yue_x_preferred":[
        "\u662d\u5cf6\u5e02"
    ],
    "name:zho_x_preferred":[
        "\u662d\u5cf6\u5e02"
    ],
    "wof:name":"Akishima",
    "wof:placetype":"locality"
},
  "geometry": {"coordinates":[139.37998999999999,35.72085],"type":"Point"}
}