{
  "type": "Feature",
  "properties": {
    "gn:admin1_code":"40.0",
    "gn:admin2_code":"1865425.0",
    "gn:asciiname":"Akishima",
    "gn:country_code":"JP",
    "gn:dem":110,
    "gn:feature_class":"P",
    "gn:feature_code":"PPLA2",
    "gn:name":"Akishima",
    "gn:population":0,
    "gn:timezone":"Asia/Tokyo",
    "iso:country":"JP",
    "name:ara_x_preferred":[
        "\u0623\u0643\u064a\u0634\u064a\u0645\u0627"
    ],
    "name:epo_x_preferred":[
        "Aki\u015dima"
    ],
    "name:fas_x_preferred":[
        "\u0622\u06a9\u06cc\u0634\u06cc\u0645\u0627\u060c \u062a\u0648\u06a9\u06cc\u0648"
    ],
    "name:hye_x_preferred":[
        "\u0531\u056f\u056b\u057d\u056b\u0574\u0561"
    ],
    "name:jpn_x_preferred":[
        "\u662d\u5cf6"
    ],
    "name:jpn_x_variant":[
        "\u662d\u5cf6\u5e02"
    ],
    "name:kor_x_preferred":[
        "\uc544\ud0a4\uc2dc\ub9c8 \uc2dc"
    ],
    "name:lit_x_preferred":[
        "Aki\u0161ima"
    ],
    "name:mzn_x_preferred":[
        "\u0622\u06a9\u06cc\u0634\u06cc\u0645\u0627\u060c \u062a\u0648\u06a9\u06cc\u0648"
    ],
    "name:nan_x_preferred":[
        "Akisima-chh\u012b"
    ],
    "name:rus_x_preferred":[
        "\u0410\u043a\u0438\u0441\u0438\u043c\u0430"
    ],
    "name:srp_x_preferred":[
        "\u0410\u043a\u0438\u0448\u0438\u043c\u0430"
    ],
    "name:tgk_x_preferred":[
        "\u0410\u043a\u0438\u0448\u0438\u043c\u0430"
    ],
    "name:tha_x_preferred":[
        "\u0e2d\u0e30\u0e01\u0e34\u0e0a\u0e34\u0e21\u0e30"
    ],
    "name:ukr_x_preferred":[
        "\u0410\u043a\u0456\u0441\u0456\u043c\u0430"
    ],
    "name:yue_x_preferred":[
        "\u662d\u5cf6\u5e02"
    ],
    "name:zho_x_preferred":[
        "\u662d\u5cf6\u5e02"
    ],
    "wof:name":"Akishima",
    "wof:placetype":"locality"
},
  "geometry": {"coordinates":[139.37998999999999,35.72085],"type":"Point"}
}