{
  "type": "Feature",
  "properties": {
    "gn:admin1_code":"21.0",
    "gn:admin2_code":"1859490.0",
    "gn:admin3_code":"43404.0",
    "gn:asciiname":"Musashigaoka-kita",
    "gn:country_code":"JP",
    "gn:dem":66,
    "gn:feature_class":"P",
    "gn:feature_code":"PPL",
    "gn:name":"Musashigaoka-kita",
    "gn:population":0,
    "gn:timezone":"Asia/Tokyo",
    "iso:country":"JP",
    "name:jpn_x_preferred":[
        "\u6b66\u8535\u30f6\u4e18\u5317"
    ],
    "name:jpn_x_variant":[
        "\u3080\u3055\u3057\u304c\u304a\u304b\u304d\u305f",
        "\u30e0\u30b5\u30b7\u30ac\u30aa\u30ab\u30ad\u30bf"
    ],
    "wof:name":"Musashigaoka-kita",
    "wof:placetype":"locality"
},
  "geometry": {"coordinates":[130.76518000000002,32.85967],"type":"Point"}
}