{
  "type": "Feature",
  "properties": {
    "gn:admin1_code":"40.0",
    "gn:admin2_code":"8304376.0",
    "gn:asciiname":"Midoricho",
    "gn:country_code":"JP",
    "gn:dem":66,
    "gn:feature_class":"P",
    "gn:feature_code":"PPL",
    "gn:name":"Midorich\u014d",
    "gn:population":0,
    "gn:timezone":"Asia/Tokyo",
    "iso:country":"JP",
    "name:jpn_x_preferred":[
        "\u7dd1\u753a"
    ],
    "name:und_x_variant":[
        "Midorich\u014d"
    ],
    "wof:name":"Midoricho",
    "wof:placetype":"locality"
},
  "geometry": {"coordinates":[139.53846999999999,35.73840999999999],"type":"Point"}
}