{
  "type": "Feature",
  "properties": {
    "iso:country":"JP",
    "name:eng_x_preferred":[
        "Okamotomachi 4 Chome"
    ],
    "name:eng_x_variant":[
        "Okamotomachi 4 Choume",
        "Okamotomachi 4 Chome"
    ],
    "name:jpn_x_preferred":[
        "\uff14\u4e01\u76ee"
    ],
    "name:jpn_x_variant":[
        "\u304a\u304b\u3082\u3068\u307e\u3061 \uff14\u3061\u3087\u3046\u3081",
        "\u5ca1\u672c\u753a \uff14\u4e01\u76ee",
        "\uff14\u3061\u3087\u3046\u3081"
    ],
    "qs:gn_local":0,
    "qs:local_max":1694,
    "qs:local_sum":11339,
    "qs:localhoods":18,
    "qs:name":"\uff14\u4e01\u76ee",
    "qs:name_adm0":"\u65e5\u672c",
    "qs:name_adm1":"\u5c90\u961c\u770c",
    "qs:name_en":"Okamotomachi 4 Chome",
    "qs:name_lau":"\u5ca1\u672c\u753a",
    "qs:name_local":"\u9ad8\u5c71\u5e02",
    "qs:photo_max":231,
    "qs:photo_sum":1293,
    "qs:placetype":"Suburb",
    "qs:quad_count":29,
    "qs:woe_adm0":23424856,
    "qs:woe_adm1":2345859,
    "qs:woe_adm2":0,
    "qs:woe_lau":28434002,
    "qs:woe_local":1115345,
    "qs:woe_ver":"7.10.0",
    "wof:lang":[
        "jpn"
    ],
    "wof:name":"\uff14\u4e01\u76ee",
    "wof:placetype":"neighbourhood"
},
  "geometry": {"coordinates":[137.246318,36.150439],"type":"Point"}
}