{
  "type": "Feature",
  "properties": {
    "iso:country":"JP",
    "label:eng_x_preferred_longname":[
        "Fujisawa Town"
    ],
    "label:eng_x_preferred_placetype":[
        "town"
    ],
    "name:eng_x_preferred":[
        "Fujisawa"
    ],
    "name:eng_x_variant":[
        "Fujisawa Town"
    ],
    "name:jpn_x_preferred":[
        "\u85e4\u6ca2\u753a"
    ],
    "qs:name":"\u85e4\u6ca2\u753a",
    "qs:name_adm0":"\u65e5\u672c",
    "qs:name_adm1":"\u5ca9\u624b\u770c",
    "qs:photos":186,
    "qs:photos_1k":38,
    "qs:photos_9k":1,
    "qs:photos_9r":4,
    "qs:photos_all":186,
    "qs:photos_sr":4,
    "qs:placetype":"Town",
    "qs:pop_sr":"0",
    "wof:name":"Fujisawa",
    "wof:placetype":"locality"
},
  "geometry": {"coordinates":[141.337909,38.887425],"type":"Point"}
}