{
  "type": "Feature",
  "properties": {
    "gn:admin1_code":"40.0",
    "gn:admin2_code":"1851510.0",
    "gn:asciiname":"Shoan",
    "gn:country_code":"JP",
    "gn:dem":55,
    "gn:feature_class":"P",
    "gn:feature_code":"PPL",
    "gn:name":"Sh\u014dan",
    "gn:population":0,
    "gn:timezone":"Asia/Tokyo",
    "iso:country":"JP",
    "name:jpn_x_preferred":[
        "\u677e\u5eb5"
    ],
    "name:jpn_x_variant":[
        "\u3057\u3087\u3046\u3042\u3093",
        "\u30b7\u30e7\u30a6\u30a2\u30f3"
    ],
    "name:und_x_variant":[
        "Sh\u014dan"
    ],
    "wof:name":"Shoan",
    "wof:placetype":"locality"
},
  "geometry": {"coordinates":[139.59496999999999,35.69812],"type":"Point"}
}