{
  "type": "Feature",
  "properties": {
    "gn:admin1_code":"43",
    "gn:admin2_code":"1850706.0",
    "gn:asciiname":"Kami-misu",
    "gn:country_code":"JP",
    "gn:dem":98,
    "gn:feature_class":"P",
    "gn:feature_code":"PPL",
    "gn:name":"Kami-misu",
    "gn:population":0,
    "gn:timezone":"Asia/Tokyo",
    "iso:country":"JP",
    "wof:name":"Kami-misu",
    "wof:placetype":"locality"
},
  "geometry": {"coordinates":[135.43333000000001,33.75],"type":"Point"}
}