{
  "type": "Feature",
  "properties": {
    "gn:admin1_code":"21.0",
    "gn:admin2_code":"7412705.0",
    "gn:admin3_code":"43482.0",
    "gn:asciiname":"Matsubara",
    "gn:country_code":"JP",
    "gn:dem":35,
    "gn:feature_class":"P",
    "gn:feature_code":"PPLL",
    "gn:name":"Matsubara",
    "gn:population":0,
    "gn:timezone":"Asia/Tokyo",
    "iso:country":"JP",
    "name:jpn_x_preferred":[
        "\u677e\u539f"
    ],
    "name:jpn_x_variant":[
        "\u307e\u3064\u3070\u3089",
        "\u30de\u30c4\u30d0\u30e9"
    ],
    "wof:name":"Matsubara",
    "wof:placetype":"locality"
},
  "geometry": {"coordinates":[130.52508999999998,32.27942],"type":"Point"}
}