{
  "type": "Feature",
  "properties": {
    "gn:admin1_code":"34.0",
    "gn:admin2_code":"1849187.0",
    "gn:admin3_code":"11106.0",
    "gn:asciiname":"Sakawa",
    "gn:country_code":"JP",
    "gn:dem":9,
    "gn:feature_class":"P",
    "gn:feature_code":"PPL",
    "gn:name":"Sakawa",
    "gn:population":0,
    "gn:timezone":"Asia/Tokyo",
    "iso:country":"JP",
    "name:jpn_x_preferred":[
        "\u6804\u548c"
    ],
    "name:jpn_x_variant":[
        "\u3055\u304b\u308f",
        "\u30b5\u30ab\u30ef"
    ],
    "wof:name":"Sakawa",
    "wof:placetype":"locality"
},
  "geometry": {"coordinates":[139.61547999999999,35.86473],"type":"Point"}
}