{
  "type": "Feature",
  "properties": {
    "gn:admin1_code":"35",
    "gn:admin2_code":"1858984.0",
    "gn:asciiname":"Shigarakicho-maki",
    "gn:country_code":"JP",
    "gn:dem":268,
    "gn:feature_class":"P",
    "gn:feature_code":"PPL",
    "gn:name":"Shigarakich\u014d-maki",
    "gn:population":0,
    "gn:timezone":"Asia/Tokyo",
    "iso:country":"JP",
    "name:jpn_x_preferred":[
        "\u4fe1\u697d\u753a\u7267"
    ],
    "name:und_x_variant":[
        "Shigarakich\u014d-maki",
        "Maki"
    ],
    "wof:name":"Shigarakicho-maki",
    "wof:placetype":"locality"
},
  "geometry": {"coordinates":[136.07717,34.9091],"type":"Point"}
}