{
  "type": "Feature",
  "properties": {
    "gn:admin1_code":"21.0",
    "gn:admin2_code":"7412709.0",
    "gn:admin3_code":"43348.0",
    "gn:asciiname":"Otao",
    "gn:country_code":"JP",
    "gn:dem":660,
    "gn:feature_class":"P",
    "gn:feature_code":"PPLL",
    "gn:name":"Otao",
    "gn:population":0,
    "gn:timezone":"Asia/Tokyo",
    "iso:country":"JP",
    "name:jpn_x_preferred":[
        "\u5c0f\u7530\u5c3e"
    ],
    "name:jpn_x_variant":[
        "\u304a\u305f\u304a",
        "\u30aa\u30bf\u30aa"
    ],
    "wof:name":"Otao",
    "wof:placetype":"locality"
},
  "geometry": {"coordinates":[130.85459,32.58271],"type":"Point"}
}