{
  "type": "Feature",
  "properties": {
    "gn:admin1_code":"3.0",
    "gn:admin2_code":"2127674.0",
    "gn:asciiname":"Hareyama",
    "gn:country_code":"JP",
    "gn:dem":69,
    "gn:feature_class":"P",
    "gn:feature_code":"PPL",
    "gn:name":"Hareyama",
    "gn:population":0,
    "gn:timezone":"Asia/Tokyo",
    "iso:country":"JP",
    "name:jpn_x_preferred":[
        "\u6674\u5c71"
    ],
    "name:jpn_x_variant":[
        "\u306f\u308c\u3084\u307e",
        "\u30cf\u30ec\u30e4\u30de"
    ],
    "wof:name":"Hareyama",
    "wof:placetype":"locality"
},
  "geometry": {"coordinates":[141.18126999999996,40.62924],"type":"Point"}
}