{
  "type": "Feature",
  "properties": {
    "gn:admin1_code":"05",
    "gn:admin2_code":"1857121.0",
    "gn:admin3_code":"38506.0",
    "gn:asciiname":"Nakaura",
    "gn:country_code":"JP",
    "gn:dem":9,
    "gn:feature_class":"P",
    "gn:feature_code":"PPL",
    "gn:name":"Nakaura",
    "gn:population":0,
    "gn:timezone":"Asia/Tokyo",
    "iso:country":"JP",
    "name:und_x_variant":[
        "\u4e2d\u6d66"
    ],
    "wof:name":"Nakaura",
    "wof:placetype":"locality"
},
  "geometry": {"coordinates":[132.49104,32.9646],"type":"Point"}
}