{
  "type": "Feature",
  "properties": {
    "iso:country":"JP",
    "qs:name":"\uff11\u4e01\u76ee",
    "qs:name_adm0":"\u65e5\u672c",
    "qs:name_adm1":"\u6771\u4eac\u90fd",
    "qs:photos":499,
    "qs:photos_1k":101,
    "qs:photos_9k":2,
    "qs:photos_9r":5,
    "qs:photos_all":499,
    "qs:photos_sr":7,
    "qs:placetype":"Suburb",
    "qs:pop_sr":"0",
    "wof:name":"\uff11\u4e01\u76ee",
    "wof:placetype":"neighbourhood"
},
  "geometry": {"coordinates":[139.68689000000001,35.6825],"type":"Point"}
}