{
  "type": "Feature",
  "properties": {
    "iso:country":"JP",
    "name:eng_x_preferred":[
        "Sugoro 2 Chome"
    ],
    "name:eng_x_variant":[
        "Sugoro 2 Choume",
        "Sugoro 2 Chome"
    ],
    "name:jpn_x_preferred":[
        "\uff12\u4e01\u76ee"
    ],
    "name:jpn_x_variant":[
        "\u3059\u3054\u308d \uff12\u3061\u3087\u3046\u3081",
        "\u9808\u9803 \uff12\u4e01\u76ee",
        "\uff12\u3061\u3087\u3046\u3081"
    ],
    "qs:gn_local":0,
    "qs:local_max":813,
    "qs:local_sum":1387,
    "qs:localhoods":7,
    "qs:name":"\uff12\u4e01\u76ee",
    "qs:name_adm0":"\u65e5\u672c",
    "qs:name_adm1":"\u65b0\u6f5f\u770c",
    "qs:name_en":"Sugoro 2 Chome",
    "qs:name_lau":"\u9808\u9803",
    "qs:name_local":"\u4e09\u6761\u5e02",
    "qs:photo_max":28,
    "qs:photo_sum":44,
    "qs:placetype":"Suburb",
    "qs:quad_count":7,
    "qs:woe_adm0":23424856,
    "qs:woe_adm1":2345878,
    "qs:woe_adm2":0,
    "qs:woe_lau":28419244,
    "qs:woe_local":1118103,
    "qs:woe_ver":"7.10.0",
    "qs_pg:name":"\uff12\u4e01\u76ee",
    "qs_pg:name_adm0":"\u65e5\u672c",
    "qs_pg:name_adm1":"\u65b0\u6f5f\u770c",
    "qs_pg:photos":36,
    "qs_pg:photos_1k":7,
    "qs_pg:photos_9k":1,
    "qs_pg:photos_9r":2,
    "qs_pg:photos_all":36,
    "qs_pg:photos_sr":2,
    "qs_pg:pop_sr":0,
    "qs_pg:qs_pg_placetype":"neighbourhood",
    "qs_pg:qs_pg_placetype_gp":"Suburb",
    "qs_pg:woe_adm0":23424856,
    "woe:adm0_id":23424856,
    "woe:name_adm0":"\u65e5\u672c",
    "woe:name_adm1":"\u65b0\u6f5f\u770c",
    "woe:placetype":"Suburb",
    "wof:lang":[
        "jpn"
    ],
    "wof:name":"\uff12\u4e01\u76ee",
    "wof:placetype":"neighbourhood"
},
  "geometry": {"coordinates":[138.94049100000001,37.647052],"type":"Point"}
}