{
  "type": "Feature",
  "properties": {
    "gn:admin1_code":"22.0",
    "gn:admin2_code":"1848224.0",
    "gn:admin3_code":"26463.0",
    "gn:asciiname":"Hide",
    "gn:country_code":"JP",
    "gn:dem":71,
    "gn:feature_class":"P",
    "gn:feature_code":"PPL",
    "gn:name":"Hide",
    "gn:population":0,
    "gn:timezone":"Asia/Tokyo",
    "iso:country":"JP",
    "name:dan_x_preferred":[
        "Hide"
    ],
    "name:deu_x_preferred":[
        "Hide"
    ],
    "name:fra_x_preferred":[
        "Hide"
    ],
    "name:ita_x_preferred":[
        "Hide"
    ],
    "name:kor_x_preferred":[
        "\ud558\uc774\ub4dc"
    ],
    "name:nld_x_preferred":[
        "Hide"
    ],
    "name:swe_x_preferred":[
        "Hide"
    ],
    "wof:name":"Hide",
    "wof:placetype":"locality"
},
  "geometry": {"coordinates":[135.28,35.67167],"type":"Point"}
}