{
  "type": "Feature",
  "properties": {
    "gn:admin1_code":"12.0",
    "gn:admin2_code":"2127440.0",
    "gn:admin3_code":"1408.0",
    "gn:asciiname":"Kurokawamachi",
    "gn:cc2":"JP",
    "gn:country_code":"JP",
    "gn:dem":4,
    "gn:feature_class":"P",
    "gn:feature_code":"PPL",
    "gn:name":"Kurokawamachi",
    "gn:population":0,
    "gn:timezone":"Asia/Tokyo",
    "iso:country":"JP",
    "name:und_x_variant":[
        "Kurokawa",
        "Kurokawach\u014d",
        "Kurokawamachi"
    ],
    "wof:name":"Kurokawamachi",
    "wof:placetype":"locality"
},
  "geometry": {"coordinates":[140.80000000000001,43.18333],"type":"Point"}
}