{
  "type": "Feature",
  "properties": {
    "gn:admin1_code":"34.0",
    "gn:admin2_code":"8304213.0",
    "gn:asciiname":"Sakaecho",
    "gn:country_code":"JP",
    "gn:dem":8,
    "gn:feature_class":"P",
    "gn:feature_code":"PPL",
    "gn:name":"Sakaech\u014d",
    "gn:population":0,
    "gn:timezone":"Asia/Tokyo",
    "iso:country":"JP",
    "name:jpn_x_preferred":[
        "\u6804\u753a"
    ],
    "name:jpn_x_variant":[
        "\u3055\u304b\u3048\u3061\u3087\u3046",
        "\u30b5\u30ab\u30a8\u30c1\u30e7\u30a6"
    ],
    "name:und_x_variant":[
        "Sakaech\u014d"
    ],
    "wof:name":"Sakaecho",
    "wof:placetype":"locality"
},
  "geometry": {"coordinates":[139.73459,35.98818],"type":"Point"}
}