{
  "type": "Feature",
  "properties": {
    "gn:admin1_code":"24.0",
    "gn:admin2_code":"2112261.0",
    "gn:asciiname":"Minato",
    "gn:country_code":"JP",
    "gn:dem":5,
    "gn:feature_class":"P",
    "gn:feature_code":"PPL",
    "gn:name":"Minato",
    "gn:population":0,
    "gn:timezone":"Asia/Tokyo",
    "iso:country":"JP",
    "name:deu_x_preferred":[
        "Minato"
    ],
    "name:fin_x_preferred":[
        "Minato"
    ],
    "name:fra_x_preferred":[
        "Minato"
    ],
    "name:ind_x_preferred":[
        "Minato"
    ],
    "name:ita_x_preferred":[
        "Minato"
    ],
    "name:jpn_x_preferred":[
        "\u6e2f"
    ],
    "name:jpn_x_variant":[
        "\u307f\u306a\u3068",
        "\u30df\u30ca\u30c8"
    ],
    "name:kor_x_preferred":[
        "\ubbf8\ub098\ud1a0"
    ],
    "name:mlg_x_preferred":[
        "Minato"
    ],
    "name:pol_x_preferred":[
        "Minato"
    ],
    "name:sco_x_preferred":[
        "Minato"
    ],
    "wof:name":"Minato",
    "wof:placetype":"locality"
},
  "geometry": {"coordinates":[141.63224,38.96284],"type":"Point"}
}