{
  "type": "Feature",
  "properties": {
    "gn:admin1_code":"47",
    "gn:admin2_code":"1858371.0",
    "gn:admin3_code":"47306.0",
    "gn:asciiname":"Yonamine",
    "gn:country_code":"JP",
    "gn:dem":14,
    "gn:feature_class":"P",
    "gn:feature_code":"PPL",
    "gn:name":"Yonamine",
    "gn:population":0,
    "gn:timezone":"Asia/Tokyo",
    "iso:country":"JP",
    "name:jpn_x_preferred":[
        "\u4e0e\u90a3\u5dba"
    ],
    "name:und_x_variant":[
        "Yonanmi",
        "Yunanmi",
        "Yonamine"
    ],
    "wof:name":"Yonamine",
    "wof:placetype":"locality"
},
  "geometry": {"coordinates":[127.94913,26.69527],"type":"Point"}
}