{
  "type": "Feature",
  "properties": {
    "gn:admin1_code":"38.0",
    "gn:admin2_code":"2111324.0",
    "gn:asciiname":"Chikasono",
    "gn:cc2":"JP",
    "gn:country_code":"JP",
    "gn:dem":181,
    "gn:feature_class":"P",
    "gn:feature_code":"PPL",
    "gn:name":"Chikasono",
    "gn:population":0,
    "gn:timezone":"Asia/Tokyo",
    "iso:country":"JP",
    "name:und_x_variant":[
        "Chikazono",
        "Chikasono"
    ],
    "wof:name":"Chikasono",
    "wof:placetype":"locality"
},
  "geometry": {"coordinates":[140.01667,36.81667],"type":"Point"}
}