{
  "type": "Feature",
  "properties": {
    "iso:country":"JP",
    "name:eng_x_preferred":[
        "Hamada 2 Chome"
    ],
    "name:eng_x_variant":[
        "Hamada 2 Choume",
        "Hamada 2 Chome"
    ],
    "name:jpn_x_preferred":[
        "\uff12\u4e01\u76ee"
    ],
    "name:jpn_x_variant":[
        "\u306f\u307e\u3060 \uff12\u3061\u3087\u3046\u3081",
        "\u6d5c\u7530 \uff12\u4e01\u76ee",
        "\uff12\u3061\u3087\u3046\u3081"
    ],
    "qs:gn_adm0_cc":"JP",
    "qs:gn_local":2113015,
    "qs:gn_nam_loc":"\u5343\u8449\u5e02, \u5343\u8449\u770c, JP",
    "qs:gn_namadm1":"04",
    "qs:local_max":7724,
    "qs:local_sum":19805,
    "qs:localhoods":49,
    "qs:name":"\uff12\u4e01\u76ee",
    "qs:name_adm0":"\u65e5\u672c",
    "qs:name_adm1":"\u5343\u8449\u770c",
    "qs:name_adm2":"\u7f8e\u6d5c\u533a",
    "qs:name_en":"Hamada 2 Chome",
    "qs:name_lau":"\u6d5c\u7530",
    "qs:name_local":"\u5343\u8449\u5e02",
    "qs:photo_max":49,
    "qs:photo_sum":127,
    "qs:placetype":"Suburb",
    "qs:quad_count":7,
    "qs:woe_adm0":23424856,
    "qs:woe_adm1":2345854,
    "qs:woe_adm2":15015423,
    "qs:woe_lau":28410708,
    "qs:woe_local":1117034,
    "qs:woe_ver":"7.10.0",
    "wof:lang":[
        "jpn"
    ],
    "wof:name":"\uff12\u4e01\u76ee",
    "wof:placetype":"neighbourhood"
},
  "geometry": {"coordinates":[140.03350599999999,35.656051],"type":"Point"}
}