{
  "type": "Feature",
  "properties": {
    "iso:country":"JP",
    "name:eng_x_preferred":[
        "Zaimokuza 5 Chome"
    ],
    "name:eng_x_variant":[
        "Zaimokuza 5 Choume",
        "Zaimokuza 5 Chome"
    ],
    "name:jpn_x_preferred":[
        "\uff15\u4e01\u76ee"
    ],
    "name:jpn_x_variant":[
        "\u3056\u3044\u3082\u304f\u3056 \uff15\u3061\u3087\u3046\u3081",
        "\u6750\u6728\u5ea7 \uff15\u4e01\u76ee",
        "\uff15\u3061\u3087\u3046\u3081"
    ],
    "qs:gn_local":0,
    "qs:local_max":2484,
    "qs:local_sum":33815,
    "qs:localhoods":49,
    "qs:name":"\uff15\u4e01\u76ee",
    "qs:name_adm0":"\u65e5\u672c",
    "qs:name_adm1":"\u795e\u5948\u5ddd\u770c",
    "qs:name_en":"Zaimokuza 5 Chome",
    "qs:name_lau":"\u6750\u6728\u5ea7",
    "qs:name_local":"\u938c\u5009\u5e02",
    "qs:photo_max":152,
    "qs:photo_sum":277,
    "qs:placetype":"Suburb",
    "qs:quad_count":3,
    "qs:woe_adm0":23424856,
    "qs:woe_adm1":2345868,
    "qs:woe_adm2":0,
    "qs:woe_lau":28416738,
    "qs:woe_local":1117401,
    "qs:woe_ver":"7.10.0",
    "wof:lang":[
        "jpn"
    ],
    "wof:name":"\uff15\u4e01\u76ee",
    "wof:placetype":"neighbourhood"
},
  "geometry": {"coordinates":[139.54846000000001,35.30691],"type":"Point"}
}