{
  "type": "Feature",
  "properties": {
    "gn:admin1_code":"4.0",
    "gn:admin2_code":"1850520.0",
    "gn:asciiname":"Yawata",
    "gn:country_code":"JP",
    "gn:dem":7,
    "gn:feature_class":"P",
    "gn:feature_code":"PPL",
    "gn:name":"Yawata",
    "gn:population":0,
    "gn:timezone":"Asia/Tokyo",
    "iso:country":"JP",
    "name:jpn_x_preferred":[
        "\u516b\u5e61"
    ],
    "name:jpn_x_variant":[
        "\u3084\u308f\u305f",
        "\u30e4\u30ef\u30bf"
    ],
    "wof:name":"Yawata",
    "wof:placetype":"locality"
},
  "geometry": {"coordinates":[139.86476000000002,35.00383],"type":"Point"}
}