{
  "type": "Feature",
  "properties": {
    "gn:admin1_code":"3.0",
    "gn:admin2_code":"2129754.0",
    "gn:admin3_code":"2405.0",
    "gn:asciiname":"Horikiri",
    "gn:country_code":"JP",
    "gn:dem":67,
    "gn:feature_class":"P",
    "gn:feature_code":"PPL",
    "gn:name":"Horikiri",
    "gn:population":0,
    "gn:timezone":"Asia/Tokyo",
    "iso:country":"JP",
    "name:jpn_x_preferred":[
        "\u5800\u5207"
    ],
    "name:jpn_x_variant":[
        "\u307b\u308a\u304d\u308a",
        "\u30db\u30ea\u30ad\u30ea"
    ],
    "wof:name":"Horikiri",
    "wof:placetype":"locality"
},
  "geometry": {"coordinates":[141.29443999999995,40.63611],"type":"Point"}
}