{
  "type": "Feature",
  "properties": {
    "gn:admin1_code":"4.0",
    "gn:admin2_code":"7465521.0",
    "gn:asciiname":"Kawasaki",
    "gn:country_code":"JP",
    "gn:dem":40,
    "gn:feature_class":"P",
    "gn:feature_code":"PPLL",
    "gn:name":"Kawasaki",
    "gn:population":0,
    "gn:timezone":"Asia/Tokyo",
    "iso:country":"JP",
    "name:jpn_x_preferred":[
        "\u5ddd\u5d0e"
    ],
    "name:jpn_x_variant":[
        "\u304b\u308f\u3055\u304d",
        "\u30ab\u30ef\u30b5\u30ad"
    ],
    "wof:name":"Kawasaki",
    "wof:placetype":"locality"
},
  "geometry": {"coordinates":[139.99462,35.051],"type":"Point"}
}