{
  "type": "Feature",
  "properties": {
    "gn:admin1_code":"4.0",
    "gn:admin2_code":"2110982.0",
    "gn:asciiname":"Onodai",
    "gn:country_code":"JP",
    "gn:dem":32,
    "gn:feature_class":"P",
    "gn:feature_code":"PPLL",
    "gn:name":"\u014cnodai",
    "gn:population":0,
    "gn:timezone":"Asia/Tokyo",
    "iso:country":"JP",
    "name:jpn_x_preferred":[
        "\u5927\u91ce\u53f0"
    ],
    "name:jpn_x_variant":[
        "\u304a\u304a\u306e\u3060\u3044",
        "\u30aa\u30aa\u30ce\u30c0\u30a4"
    ],
    "name:und_x_variant":[
        "\u014cnodai"
    ],
    "wof:name":"Onodai",
    "wof:placetype":"locality"
},
  "geometry": {"coordinates":[139.97999999999999,35.42817],"type":"Point"}
}