{
  "type": "Feature",
  "properties": {
    "gn:admin1_code":"19.0",
    "gn:admin2_code":"1864928.0",
    "gn:asciiname":"Asahicho",
    "gn:country_code":"JP",
    "gn:dem":21,
    "gn:feature_class":"P",
    "gn:feature_code":"PPL",
    "gn:name":"Asahich\u014d",
    "gn:population":0,
    "gn:timezone":"Asia/Tokyo",
    "iso:country":"JP",
    "name:jpn_x_preferred":[
        "\u65ed\u753a"
    ],
    "name:und_x_variant":[
        "Asahich\u014d"
    ],
    "wof:name":"Asahicho",
    "wof:placetype":"locality"
},
  "geometry": {"coordinates":[139.36578,35.43427],"type":"Point"}
}