{
  "type": "Feature",
  "properties": {
    "gn:admin1_code":"2.0",
    "gn:admin2_code":"2111935.0",
    "gn:admin3_code":"5361.0",
    "gn:asciiname":"Urayokomachi",
    "gn:country_code":"JP",
    "gn:dem":10,
    "gn:feature_class":"P",
    "gn:feature_code":"PPL",
    "gn:name":"Urayokomachi",
    "gn:population":0,
    "gn:timezone":"Asia/Tokyo",
    "iso:country":"JP",
    "name:jpn_x_preferred":[
        "\u6d66\u6a2a\u753a"
    ],
    "wof:name":"Urayokomachi",
    "wof:placetype":"locality"
},
  "geometry": {"coordinates":[140.09898999999999,39.96442],"type":"Point"}
}