{
  "type": "Feature",
  "properties": {
    "gn:admin1_code":"32.0",
    "gn:admin2_code":"1862538.0",
    "gn:asciiname":"Koriencho",
    "gn:country_code":"JP",
    "gn:dem":20,
    "gn:feature_class":"P",
    "gn:feature_code":"PPL",
    "gn:name":"K\u014driench\u014d",
    "gn:population":0,
    "gn:timezone":"Asia/Tokyo",
    "iso:country":"JP",
    "name:jpn_x_preferred":[
        "\u9999\u91cc\u5712\u753a"
    ],
    "name:und_x_variant":[
        "K\u014driench\u014d"
    ],
    "wof:name":"Koriencho",
    "wof:placetype":"locality"
},
  "geometry": {"coordinates":[135.63471999999999,34.78638],"type":"Point"}
}