{
  "type": "Feature",
  "properties": {
    "gn:admin1_code":"29.0",
    "gn:admin2_code":"1856876.0",
    "gn:asciiname":"Tochikubomachi",
    "gn:country_code":"JP",
    "gn:dem":200,
    "gn:feature_class":"P",
    "gn:feature_code":"PPL",
    "gn:name":"Tochikubomachi",
    "gn:population":0,
    "gn:timezone":"Asia/Tokyo",
    "iso:country":"JP",
    "name:jpn_x_preferred":[
        "\u6803\u7aaa\u753a"
    ],
    "wof:name":"Tochikubomachi",
    "wof:placetype":"locality"
},
  "geometry": {"coordinates":[138.95005,37.47373],"type":"Point"}
}