{
  "type": "Feature",
  "properties": {
    "gn:admin1_code":"37.0",
    "gn:admin2_code":"1864104.0",
    "gn:asciiname":"Nakaharacho",
    "gn:country_code":"JP",
    "gn:dem":206,
    "gn:feature_class":"P",
    "gn:feature_code":"PPL",
    "gn:name":"Nakaharach\u014d",
    "gn:population":0,
    "gn:timezone":"Asia/Tokyo",
    "iso:country":"JP",
    "name:jpn_x_preferred":[
        "\u4e2d\u539f\u753a"
    ],
    "name:und_x_variant":[
        "Nakaharach\u014d"
    ],
    "wof:name":"Nakaharacho",
    "wof:placetype":"locality"
},
  "geometry": {"coordinates":[138.62045000000001,35.24310999999999],"type":"Point"}
}