{
  "type": "Feature",
  "properties": {
    "gn:admin1_code":"27.0",
    "gn:admin2_code":"1862734.0",
    "gn:admin3_code":"42323.0",
    "gn:asciiname":"Nakaogo",
    "gn:country_code":"JP",
    "gn:dem":164,
    "gn:feature_class":"P",
    "gn:feature_code":"PPL",
    "gn:name":"Nakaog\u014d",
    "gn:population":0,
    "gn:timezone":"Asia/Tokyo",
    "iso:country":"JP",
    "name:jpn_x_preferred":[
        "\u4e2d\u5c3e\u90f7"
    ],
    "name:und_x_variant":[
        "Nakaog\u014d"
    ],
    "wof:name":"Nakaogo",
    "wof:placetype":"locality"
},
  "geometry": {"coordinates":[129.93031999999999,33.12221],"type":"Point"}
}