{
  "type": "Feature",
  "properties": {
    "gn:admin1_code":"4.0",
    "gn:admin2_code":"7465524.0",
    "gn:asciiname":"Masuda",
    "gn:country_code":"JP",
    "gn:dem":17,
    "gn:feature_class":"P",
    "gn:feature_code":"PPL",
    "gn:name":"Masuda",
    "gn:population":0,
    "gn:timezone":"Asia/Tokyo",
    "iso:country":"JP",
    "name:jpn_x_preferred":[
        "\u5897\u7530"
    ],
    "name:jpn_x_variant":[
        "\u307e\u3059\u3060",
        "\u30de\u30b9\u30c0"
    ],
    "wof:name":"Masuda",
    "wof:placetype":"locality"
},
  "geometry": {"coordinates":[140.26873999999998,35.2843],"type":"Point"}
}