{
  "type": "Feature",
  "properties": {
    "gn:admin1_code":"21.0",
    "gn:admin2_code":"7412708.0",
    "gn:admin3_code":"43501.0",
    "gn:asciiname":"Taira",
    "gn:country_code":"JP",
    "gn:dem":128,
    "gn:feature_class":"P",
    "gn:feature_code":"PPLL",
    "gn:name":"Taira",
    "gn:population":0,
    "gn:timezone":"Asia/Tokyo",
    "iso:country":"JP",
    "name:jpn_x_preferred":[
        "\u5e73\u826f"
    ],
    "wof:name":"Taira",
    "wof:placetype":"locality"
},
  "geometry": {"coordinates":[130.85176000000001,32.21708],"type":"Point"}
}