{
  "type": "Feature",
  "properties": {
    "iso:country":"JP",
    "name:eng_x_preferred":[
        "Hashimoto 2 Chome"
    ],
    "name:eng_x_variant":[
        "Hashimoto 2 Choume",
        "Hashimoto 2 Chome"
    ],
    "name:jpn_x_preferred":[
        "\uff12\u4e01\u76ee"
    ],
    "name:jpn_x_variant":[
        "\u306f\u3057\u3082\u3068 \uff12\u3061\u3087\u3046\u3081",
        "\u6a4b\u672c \uff12\u4e01\u76ee",
        "\uff12\u3061\u3087\u3046\u3081"
    ],
    "qs:gn_local":0,
    "qs:local_max":428,
    "qs:local_sum":2008,
    "qs:localhoods":25,
    "qs:name":"\uff12\u4e01\u76ee",
    "qs:name_adm0":"\u65e5\u672c",
    "qs:name_adm1":"\u795e\u5948\u5ddd\u770c",
    "qs:name_en":"Hashimoto 2 Chome",
    "qs:name_lau":"\u6a4b\u672c",
    "qs:name_local":"\u76f8\u6a21\u539f\u5e02",
    "qs:photo_max":36,
    "qs:photo_sum":83,
    "qs:placetype":"Suburb",
    "qs:quad_count":8,
    "qs:woe_adm0":23424856,
    "qs:woe_adm1":2345868,
    "qs:woe_adm2":0,
    "qs:woe_lau":28417026,
    "qs:woe_local":1118072,
    "qs:woe_ver":"7.10.0",
    "wof:lang":[
        "jpn"
    ],
    "wof:name":"\uff12\u4e01\u76ee",
    "wof:placetype":"neighbourhood"
},
  "geometry": {"coordinates":[139.345483,35.594244],"type":"Point"}
}