{
  "type": "Feature",
  "properties": {
    "gn:admin1_code":"18.0",
    "gn:admin2_code":"8300556.0",
    "gn:asciiname":"Ikezonocho",
    "gn:country_code":"JP",
    "gn:dem":27,
    "gn:feature_class":"P",
    "gn:feature_code":"PPL",
    "gn:name":"Ikezonoch\u014d",
    "gn:population":0,
    "gn:timezone":"Asia/Tokyo",
    "iso:country":"JP",
    "name:jpn_x_preferred":[
        "\u6c60\u5712\u753a"
    ],
    "name:und_x_variant":[
        "Ikezonoch\u014d"
    ],
    "wof:name":"Ikezonocho",
    "wof:placetype":"locality"
},
  "geometry": {"coordinates":[130.85910000000001,31.33663],"type":"Point"}
}