{
  "type": "Feature",
  "properties": {
    "gn:admin1_code":"27",
    "gn:admin2_code":"7418806.0",
    "gn:asciiname":"Urada",
    "gn:cc2":"JP",
    "gn:country_code":"JP",
    "gn:dem":4,
    "gn:feature_class":"P",
    "gn:feature_code":"PPL",
    "gn:name":"Urada",
    "gn:population":0,
    "gn:timezone":"Asia/Tokyo",
    "iso:country":"JP",
    "name:und_x_variant":[
        "Urata",
        "Urada"
    ],
    "wof:name":"Urada",
    "wof:placetype":"locality"
},
  "geometry": {"coordinates":[130.25,32.63333],"type":"Point"}
}