{
  "type": "Feature",
  "properties": {
    "gn:admin1_code":"3.0",
    "gn:admin2_code":"2130225.0",
    "gn:asciiname":"Karakasayanagi",
    "gn:country_code":"JP",
    "gn:dem":12,
    "gn:feature_class":"P",
    "gn:feature_code":"PPL",
    "gn:name":"Karakasayanagi",
    "gn:population":0,
    "gn:timezone":"Asia/Tokyo",
    "iso:country":"JP",
    "name:jpn_x_preferred":[
        "\u5510\u7b20\u67f3"
    ],
    "name:jpn_x_variant":[
        "\u304b\u3089\u304b\u3055\u3084\u306a\u304e",
        "\u30ab\u30e9\u30ab\u30b5\u30e4\u30ca\u30ae"
    ],
    "wof:name":"Karakasayanagi",
    "wof:placetype":"locality"
},
  "geometry": {"coordinates":[140.46849,40.8003],"type":"Point"}
}