{
  "type": "Feature",
  "properties": {
    "gn:admin1_code":"3.0",
    "gn:admin2_code":"7439944.0",
    "gn:asciiname":"Odawara",
    "gn:country_code":"JP",
    "gn:dem":2,
    "gn:feature_class":"P",
    "gn:feature_code":"PPL",
    "gn:name":"Odawara",
    "gn:population":0,
    "gn:timezone":"Asia/Tokyo",
    "iso:country":"JP",
    "name:jpn_x_preferred":[
        "\u5c0f\u7530\u539f"
    ],
    "name:jpn_x_variant":[
        "\u304a\u3060\u308f\u3089",
        "\u30aa\u30c0\u30ef\u30e9"
    ],
    "wof:name":"Odawara",
    "wof:placetype":"locality"
},
  "geometry": {"coordinates":[140.33170000000001,40.83999],"type":"Point"}
}