{
  "type": "Feature",
  "properties": {
    "gn:admin1_code":"3.0",
    "gn:admin2_code":"7439944.0",
    "gn:asciiname":"Odawara",
    "gn:country_code":"JP",
    "gn:dem":2,
    "gn:feature_class":"P",
    "gn:feature_code":"PPL",
    "gn:name":"Odawara",
    "gn:population":0,
    "gn:timezone":"Asia/Tokyo",
    "iso:country":"JP",
    "name:ara_x_preferred":[
        "\u0623\u0648\u062f\u0627\u0648\u0627\u0631\u0627"
    ],
    "name:azb_x_preferred":[
        "\u0627\u0648\u062f\u0627\u0648\u0627\u0631\u0627"
    ],
    "name:cat_x_preferred":[
        "Odawara"
    ],
    "name:ceb_x_preferred":[
        "Odawara"
    ],
    "name:deu_x_preferred":[
        "Odawara"
    ],
    "name:ell_x_preferred":[
        "\u039f\u03bd\u03c4\u03b1\u03b3\u03bf\u03c5\u03ac\u03c1\u03b1"
    ],
    "name:epo_x_preferred":[
        "Oda\u016dara"
    ],
    "name:eus_x_preferred":[
        "Odawara"
    ],
    "name:fas_x_preferred":[
        "\u0627\u0648\u062f\u0627\u0648\u0627\u0631\u0627"
    ],
    "name:fin_x_preferred":[
        "Odawara"
    ],
    "name:fra_x_preferred":[
        "Odawara"
    ],
    "name:gle_x_preferred":[
        "Odawara"
    ],
    "name:glg_x_preferred":[
        "Odawara"
    ],
    "name:hrv_x_preferred":[
        "Odavara"
    ],
    "name:hun_x_preferred":[
        "Odavara"
    ],
    "name:ind_x_preferred":[
        "Odawara"
    ],
    "name:ita_x_preferred":[
        "Odawara"
    ],
    "name:jpn_x_preferred":[
        "\u5c0f\u7530\u539f"
    ],
    "name:jpn_x_variant":[
        "\u304a\u3060\u308f\u3089",
        "\u30aa\u30c0\u30ef\u30e9",
        "\u5c0f\u7530\u539f\u5e02"
    ],
    "name:kor_x_preferred":[
        "\uc624\ub2e4\uc640\ub77c\uc2dc"
    ],
    "name:lit_x_preferred":[
        "Odavara"
    ],
    "name:mlg_x_preferred":[
        "Odawara"
    ],
    "name:mzn_x_preferred":[
        "\u0627\u0648\u062f\u0627\u0648\u0627\u0631\u0627"
    ],
    "name:nld_x_preferred":[
        "Odawara"
    ],
    "name:pnt_x_preferred":[
        "\u039f\u03bd\u03c4\u03b1\u03b3\u03bf\u03c5\u03ac\u03c1\u03b1"
    ],
    "name:pol_x_preferred":[
        "Odawara"
    ],
    "name:por_x_preferred":[
        "Odawara"
    ],
    "name:ron_x_preferred":[
        "Odawara"
    ],
    "name:rus_x_preferred":[
        "\u041e\u0434\u0430\u0432\u0430\u0440\u0430"
    ],
    "name:spa_x_preferred":[
        "Odawara"
    ],
    "name:srp_x_preferred":[
        "\u041e\u0434\u0430\u0432\u0430\u0440\u0430"
    ],
    "name:swe_x_preferred":[
        "Odawara"
    ],
    "name:tgk_x_preferred":[
        "\u041e\u0434\u0430\u0432\u0430\u0440\u0430"
    ],
    "name:tgl_x_preferred":[
        "Odawara"
    ],
    "name:tha_x_preferred":[
        "\u0e42\u0e2d\u0e14\u0e32\u0e27\u0e32\u0e23\u0e30"
    ],
    "name:tum_x_preferred":[
        "Odawara"
    ],
    "name:tur_x_preferred":[
        "Odawara"
    ],
    "name:ukr_x_preferred":[
        "\u041e\u0434\u0430\u0432\u0430\u0440\u0430"
    ],
    "name:urd_x_preferred":[
        "\u0627\u0648\u062f\u0627\u0648\u0627\u0631\u0627"
    ],
    "name:vie_x_preferred":[
        "Odawara"
    ],
    "name:war_x_preferred":[
        "Odawara"
    ],
    "name:zho_x_preferred":[
        "\u5c0f\u7530\u539f\u5e02"
    ],
    "wof:name":"Odawara",
    "wof:placetype":"locality"
},
  "geometry": {"coordinates":[140.33170000000001,40.83999],"type":"Point"}
}