{
  "type": "Feature",
  "properties": {
    "gn:admin1_code":"45.0",
    "gn:admin2_code":"1852222.0",
    "gn:asciiname":"Ushirodacho",
    "gn:country_code":"JP",
    "gn:dem":24,
    "gn:feature_class":"P",
    "gn:feature_code":"PPL",
    "gn:name":"Ushirodach\u014d",
    "gn:population":0,
    "gn:timezone":"Asia/Tokyo",
    "iso:country":"JP",
    "name:jpn_x_preferred":[
        "\u5f8c\u7530\u753a"
    ],
    "name:und_x_variant":[
        "Ushirodach\u014d"
    ],
    "wof:name":"Ushirodacho",
    "wof:placetype":"locality"
},
  "geometry": {"coordinates":[130.93083999999999,33.97134],"type":"Point"}
}