{
  "type": "Feature",
  "properties": {
    "gn:admin1_code":"19.0",
    "gn:admin2_code":"1848350.0",
    "gn:admin3_code":"14104.0",
    "gn:asciiname":"Horaicho",
    "gn:country_code":"JP",
    "gn:dem":16,
    "gn:feature_class":"P",
    "gn:feature_code":"PPL",
    "gn:name":"H\u014draich\u014d",
    "gn:population":0,
    "gn:timezone":"Asia/Tokyo",
    "iso:country":"JP",
    "name:jpn_x_preferred":[
        "\u84ec\u83b1\u753a"
    ],
    "name:jpn_x_variant":[
        "\u307b\u3046\u3089\u3044\u3061\u3087\u3046",
        "\u30db\u30a6\u30e9\u30a4\u30c1\u30e7\u30a6"
    ],
    "name:und_x_variant":[
        "H\u014draich\u014d"
    ],
    "wof:name":"Horaicho",
    "wof:placetype":"locality"
},
  "geometry": {"coordinates":[139.63416999999998,35.44237000000001],"type":"Point"}
}