{
  "type": "Feature",
  "properties": {
    "gn:admin1_code":"13.0",
    "gn:admin2_code":"7370812.0",
    "gn:asciiname":"Wakimotocho",
    "gn:country_code":"JP",
    "gn:dem":151,
    "gn:feature_class":"P",
    "gn:feature_code":"PPL",
    "gn:name":"Wakimotoch\u014d",
    "gn:population":0,
    "gn:timezone":"Asia/Tokyo",
    "iso:country":"JP",
    "name:jpn_x_preferred":[
        "\u8107\u672c\u753a"
    ],
    "name:und_x_variant":[
        "Wakimotoch\u014d"
    ],
    "wof:name":"Wakimotocho",
    "wof:placetype":"locality"
},
  "geometry": {"coordinates":[135.01111,34.85913],"type":"Point"}
}