{
  "type": "Feature",
  "properties": {
    "gn:admin1_code":"12.0",
    "gn:admin2_code":"2129373.0",
    "gn:admin3_code":"1661.0",
    "gn:asciiname":"Beppohigashi",
    "gn:country_code":"JP",
    "gn:dem":8,
    "gn:feature_class":"P",
    "gn:feature_code":"PPL",
    "gn:name":"Beppohigashi",
    "gn:population":0,
    "gn:timezone":"Asia/Tokyo",
    "iso:country":"JP",
    "name:jpn_x_preferred":[
        "\u5225\u4fdd\u6771"
    ],
    "name:jpn_x_variant":[
        "\u3079\u3063\u307d\u3072\u304c\u3057",
        "\u30d9\u30c3\u30dd\u30d2\u30ac\u30b7"
    ],
    "wof:name":"Beppohigashi",
    "wof:placetype":"locality"
},
  "geometry": {"coordinates":[144.47717,42.99851],"type":"Point"}
}