{
  "type": "Feature",
  "properties": {
    "iso:country":"JP",
    "name:eng_x_preferred":[
        "Sato 3 Chome"
    ],
    "name:eng_x_variant":[
        "Satou 3 Choume",
        "Sato 3 Chome"
    ],
    "name:jpn_x_preferred":[
        "\uff13\u4e01\u76ee"
    ],
    "name:jpn_x_variant":[
        "\u3055\u3068\u3046 \uff13\u3061\u3087\u3046\u3081",
        "\u4f50\u85e4 \uff13\u4e01\u76ee",
        "\uff13\u3061\u3087\u3046\u3081"
    ],
    "qs:gn_adm0_cc":"JP",
    "qs:gn_local":1863289,
    "qs:local_max":2240,
    "qs:local_sum":3455,
    "qs:localhoods":15,
    "qs:name":"\uff13\u4e01\u76ee",
    "qs:name_adm0":"\u65e5\u672c",
    "qs:name_adm1":"\u9759\u5ca1\u770c",
    "qs:name_adm2":"\u4e2d\u533a",
    "qs:name_en":"Sato 3 Chome",
    "qs:name_lau":"\u4f50\u85e4",
    "qs:name_local":"\u6d5c\u677e\u5e02",
    "qs:photo_max":12,
    "qs:photo_sum":25,
    "qs:placetype":"Suburb",
    "qs:quad_count":8,
    "qs:woe_adm0":23424856,
    "qs:woe_adm1":2345886,
    "qs:woe_adm2":55805809,
    "qs:woe_lau":55808690,
    "qs:woe_local":1117155,
    "qs:woe_ver":"7.10.0",
    "wof:lang":[
        "jpn"
    ],
    "wof:name":"\uff13\u4e01\u76ee",
    "wof:placetype":"neighbourhood"
},
  "geometry": {"coordinates":[137.754819,34.717504],"type":"Point"}
}