{
  "type": "Feature",
  "properties": {
    "iso:country":"JP",
    "name:eng_x_preferred":[
        "Kanonshinmachi 4 Chome"
    ],
    "name:eng_x_variant":[
        "Kanonshinmachi 4 Choume",
        "Kanonshinmachi 4 Chome"
    ],
    "name:jpn_x_preferred":[
        "\uff14\u4e01\u76ee"
    ],
    "name:jpn_x_variant":[
        "\u304b\u3093\u304a\u3093\u3057\u3093\u307e\u3061 \uff14\u3061\u3087\u3046\u3081",
        "\u89b3\u97f3\u65b0\u753a \uff14\u4e01\u76ee",
        "\uff14\u3061\u3087\u3046\u3081"
    ],
    "name:unk_x_variant":[
        "\uff14\u4e01\u76ee"
    ],
    "qs:gn_adm0_cc":"JP",
    "qs:gn_local":1862415,
    "qs:gn_nam_loc":"\u5e83\u5cf6\u5e02, \u5e83\u5cf6\u770c, JP",
    "qs:gn_namadm1":"11",
    "qs:local_max":2245,
    "qs:local_sum":19695,
    "qs:localhoods":32,
    "qs:name":"\uff14\u4e01\u76ee",
    "qs:name_adm0":"\u65e5\u672c",
    "qs:name_adm1":"\u5e83\u5cf6\u770c",
    "qs:name_adm2":"\u897f\u533a",
    "qs:name_en":"Kanonshinmachi 4 Chome",
    "qs:name_lau":"\u89b3\u97f3\u65b0\u753a",
    "qs:name_local":"\u5e83\u5cf6\u5e02",
    "qs:photo_max":245,
    "qs:photo_sum":313,
    "qs:placetype":"Suburb",
    "qs:quad_count":8,
    "qs:woe_adm0":23424856,
    "qs:woe_adm1":2345861,
    "qs:woe_adm2":15015566,
    "qs:woe_lau":28473915,
    "qs:woe_local":1117227,
    "qs:woe_ver":"7.10.0",
    "wof:lang":[
        "jpn"
    ],
    "wof:name":"\uff14\u4e01\u76ee",
    "wof:placetype":"neighbourhood"
},
  "geometry": {"coordinates":[132.414815,34.361243],"type":"Point"}
}