{
  "type": "Feature",
  "properties": {
    "gn:admin1_code":"18.0",
    "gn:admin2_code":"1860823.0",
    "gn:asciiname":"Kiire-hitokuracho",
    "gn:country_code":"JP",
    "gn:dem":177,
    "gn:feature_class":"P",
    "gn:feature_code":"PPL",
    "gn:name":"Kiire-hitokurach\u014d",
    "gn:population":0,
    "gn:timezone":"Asia/Tokyo",
    "iso:country":"JP",
    "name:jpn_x_preferred":[
        "\u559c\u5165\u4e00\u5009\u753a"
    ],
    "name:und_x_variant":[
        "Kiire-hitokurach\u014d"
    ],
    "wof:name":"Kiire-hitokuracho",
    "wof:placetype":"locality"
},
  "geometry": {"coordinates":[130.51490000000001,31.35043],"type":"Point"}
}