{
  "type": "Feature",
  "properties": {
    "gn:admin1_code":"4.0",
    "gn:admin2_code":"1855071.0",
    "gn:asciiname":"Mefuki-niku",
    "gn:country_code":"JP",
    "gn:dem":20,
    "gn:feature_class":"P",
    "gn:feature_code":"PPLL",
    "gn:name":"Mefuki-niku",
    "gn:population":0,
    "gn:timezone":"Asia/Tokyo",
    "iso:country":"JP",
    "name:jpn_x_preferred":[
        "\u76ee\u5439\u4e8c\u533a"
    ],
    "wof:name":"Mefuki-niku",
    "wof:placetype":"locality"
},
  "geometry": {"coordinates":[139.89876000000001,35.96705],"type":"Point"}
}