{
  "type": "Feature",
  "properties": {
    "gn:admin1_code":"25.0",
    "gn:admin2_code":"1864313.0",
    "gn:asciiname":"Oderaotoshi",
    "gn:country_code":"JP",
    "gn:dem":279,
    "gn:feature_class":"P",
    "gn:feature_code":"PPLL",
    "gn:name":"\u014cderaotoshi",
    "gn:population":0,
    "gn:timezone":"Asia/Tokyo",
    "iso:country":"JP",
    "name:jpn_x_preferred":[
        "\u5927\u5e73\u843d"
    ],
    "name:jpn_x_variant":[
        "\u304a\u304a\u3067\u3089\u304a\u3068\u3057",
        "\u30aa\u30aa\u30c7\u30e9\u30aa\u30c8\u30b7"
    ],
    "name:und_x_variant":[
        "\u014cderaotoshi"
    ],
    "wof:name":"Oderaotoshi",
    "wof:placetype":"locality"
},
  "geometry": {"coordinates":[130.88262,32.03911],"type":"Point"}
}