{
  "type": "Feature",
  "properties": {
    "gn:admin1_code":"44.0",
    "gn:admin2_code":"2111850.0",
    "gn:admin3_code":"6362.0",
    "gn:asciiname":"Hiyama",
    "gn:country_code":"JP",
    "gn:dem":294,
    "gn:feature_class":"P",
    "gn:feature_code":"PPL",
    "gn:name":"Hiyama",
    "gn:population":0,
    "gn:timezone":"Asia/Tokyo",
    "iso:country":"JP",
    "name:jpn_x_preferred":[
        "\u65e5\u5c71"
    ],
    "name:jpn_x_variant":[
        "\u3072\u3084\u307e",
        "\u30d2\u30e4\u30de"
    ],
    "wof:name":"Hiyama",
    "wof:placetype":"locality"
},
  "geometry": {"coordinates":[140.55043999999998,38.70683],"type":"Point"}
}