{
  "type": "Feature",
  "properties": {
    "gn:admin1_code":"21.0",
    "gn:admin2_code":"7413152.0",
    "gn:asciiname":"Ogawamachi-minamikaito",
    "gn:country_code":"JP",
    "gn:dem":41,
    "gn:feature_class":"P",
    "gn:feature_code":"PPL",
    "gn:name":"Ogawamachi-minamikait\u014d",
    "gn:population":0,
    "gn:timezone":"Asia/Tokyo",
    "iso:country":"JP",
    "name:jpn_x_preferred":[
        "\u5c0f\u5ddd\u753a\u5357\u6d77\u6771"
    ],
    "name:jpn_x_variant":[
        "\u304a\u304c\u308f\u307e\u3061\u307f\u306a\u307f\u304b\u3044\u3068\u3046",
        "\u30aa\u30ac\u30ef\u30de\u30c1\u30df\u30ca\u30df\u30ab\u30a4\u30c8\u30a6"
    ],
    "name:und_x_variant":[
        "Ogawamachi-minamikait\u014d"
    ],
    "wof:name":"Ogawamachi-minamikaito",
    "wof:placetype":"locality"
},
  "geometry": {"coordinates":[130.74187000000001,32.57913],"type":"Point"}
}