{
  "type": "Feature",
  "properties": {
    "gn:admin1_code":"12.0",
    "gn:admin2_code":"7428077.0",
    "gn:admin3_code":"1667.0",
    "gn:asciiname":"Kyowa",
    "gn:country_code":"JP",
    "gn:dem":33,
    "gn:feature_class":"P",
    "gn:feature_code":"PPLL",
    "gn:name":"Ky\u014dwa",
    "gn:population":0,
    "gn:timezone":"Asia/Tokyo",
    "iso:country":"JP",
    "name:jpn_x_preferred":[
        "\u5354\u548c"
    ],
    "name:jpn_x_variant":[
        "\u304d\u3087\u3046\u308f",
        "\u30ad\u30e7\u30a6\u30ef"
    ],
    "name:und_x_variant":[
        "Ky\u014dwa"
    ],
    "wof:name":"Kyowa",
    "wof:placetype":"locality"
},
  "geometry": {"coordinates":[144.42214999999999,43.23684],"type":"Point"}
}