{
  "type": "Feature",
  "properties": {
    "gn:admin1_code":"3.0",
    "gn:admin2_code":"8534376.0",
    "gn:admin3_code":"2321.0",
    "gn:asciiname":"Ubafukuromachi",
    "gn:country_code":"JP",
    "gn:dem":72,
    "gn:feature_class":"P",
    "gn:feature_code":"PPL",
    "gn:name":"Ubafukuromachi",
    "gn:population":0,
    "gn:timezone":"Asia/Tokyo",
    "iso:country":"JP",
    "name:jpn_x_preferred":[
        "\u59e5\u888b\u753a"
    ],
    "name:jpn_x_variant":[
        "\u3046\u3070\u3075\u304f\u308d\u307e\u3061",
        "\u30a6\u30d0\u30d5\u30af\u30ed\u30de\u30c1"
    ],
    "wof:name":"Ubafukuromachi",
    "wof:placetype":"locality"
},
  "geometry": {"coordinates":[140.16605000000001,40.74667],"type":"Point"}
}