{
  "type": "Feature",
  "properties": {
    "iso:country":"JP",
    "label:eng_x_preferred_longname":[
        "Mikawa Town"
    ],
    "label:eng_x_preferred_placetype":[
        "town"
    ],
    "name:eng_x_preferred":[
        "Mikawa"
    ],
    "name:eng_x_variant":[
        "Mikawa Town"
    ],
    "name:jpn_x_preferred":[
        "\u4e09\u5ddd\u753a"
    ],
    "qs:name":"\u4e09\u5ddd\u753a",
    "qs:name_adm0":"\u65e5\u672c",
    "qs:name_adm1":"\u5c71\u5f62\u770c",
    "qs:photos":106,
    "qs:photos_1k":21,
    "qs:photos_9k":1,
    "qs:photos_9r":3,
    "qs:photos_all":106,
    "qs:photos_sr":3,
    "qs:placetype":"Town",
    "qs:pop_sr":"0",
    "wof:name":"Mikawa",
    "wof:placetype":"locality"
},
  "geometry": {"coordinates":[139.84866099999999,38.797042],"type":"Point"}
}