{
  "type": "Feature",
  "properties": {
    "gn:admin1_code":"7.0",
    "gn:admin2_code":"7407417.0",
    "gn:asciiname":"Yamabe",
    "gn:country_code":"JP",
    "gn:dem":18,
    "gn:feature_class":"P",
    "gn:feature_code":"PPL",
    "gn:name":"Yamabe",
    "gn:population":0,
    "gn:timezone":"Asia/Tokyo",
    "iso:country":"JP",
    "name:deu_x_preferred":[
        "Yamabe"
    ],
    "name:fin_x_preferred":[
        "Yamabe"
    ],
    "name:jpn_x_preferred":[
        "\u5c71\u90e8"
    ],
    "name:kor_x_preferred":[
        "\uc57c\ub9c8\ubca0"
    ],
    "name:spa_x_preferred":[
        "Yamabe"
    ],
    "wof:name":"Yamabe",
    "wof:placetype":"locality"
},
  "geometry": {"coordinates":[130.71773999999999,33.74179],"type":"Point"}
}