{
  "type": "Feature",
  "properties": {
    "gn:admin1_code":"7.0",
    "gn:admin2_code":"7407416.0",
    "gn:asciiname":"Wakita-onsen",
    "gn:country_code":"JP",
    "gn:dem":101,
    "gn:feature_class":"P",
    "gn:feature_code":"PPLL",
    "gn:name":"Wakita-onsen",
    "gn:population":0,
    "gn:timezone":"Asia/Tokyo",
    "iso:country":"JP",
    "name:jpn_x_preferred":[
        "\u8107\u7530\u6e29\u6cc9"
    ],
    "wof:name":"Wakita-onsen",
    "wof:placetype":"locality"
},
  "geometry": {"coordinates":[130.58976999999999,33.69128],"type":"Point"}
}