{
  "type": "Feature",
  "properties": {
    "gn:admin1_code":"21.0",
    "gn:admin2_code":"1848443.0",
    "gn:admin3_code":"43468.0",
    "gn:asciiname":"Kitanozu",
    "gn:country_code":"JP",
    "gn:dem":6,
    "gn:feature_class":"P",
    "gn:feature_code":"PPLL",
    "gn:name":"Kitanozu",
    "gn:population":0,
    "gn:timezone":"Asia/Tokyo",
    "iso:country":"JP",
    "name:jpn_x_preferred":[
        "\u5317\u91ce\u6d25"
    ],
    "name:jpn_x_variant":[
        "\u304d\u305f\u306e\u3065",
        "\u30ad\u30bf\u30ce\u30c5"
    ],
    "wof:name":"Kitanozu",
    "wof:placetype":"locality"
},
  "geometry": {"coordinates":[130.68061,32.56967],"type":"Point"}
}