{
  "type": "Feature",
  "properties": {
    "iso:country":"JP",
    "qs:name":"\uff11\u4e01\u76ee",
    "qs:name_adm0":"\u65e5\u672c",
    "qs:name_adm1":"\u6ecb\u8cc0\u770c",
    "qs:photos":325,
    "qs:photos_1k":66,
    "qs:photos_9k":1,
    "qs:photos_9r":5,
    "qs:photos_all":325,
    "qs:photos_sr":5,
    "qs:placetype":"Suburb",
    "qs:pop_sr":"0",
    "wof:name":"\uff11\u4e01\u76ee",
    "wof:placetype":"neighbourhood"
},
  "geometry": {"coordinates":[136.25217499999999,35.278137],"type":"Point"}
}