{
  "type": "Feature",
  "properties": {
    "gn:admin1_code":"22.0",
    "gn:admin2_code":"7412197.0",
    "gn:asciiname":"Joshi",
    "gn:country_code":"JP",
    "gn:dem":3,
    "gn:feature_class":"P",
    "gn:feature_code":"PPL",
    "gn:name":"J\u014dshi",
    "gn:population":0,
    "gn:timezone":"Asia/Tokyo",
    "iso:country":"JP",
    "name:und_x_variant":[
        "J\u014dshi"
    ],
    "wof:name":"Joshi",
    "wof:placetype":"locality"
},
  "geometry": {"coordinates":[135.23643999999999,35.54640999999999],"type":"Point"}
}