{
  "type": "Feature",
  "properties": {
    "gn:admin1_code":"27.0",
    "gn:admin2_code":"1852895.0",
    "gn:asciiname":"Tsutsuicho",
    "gn:country_code":"JP",
    "gn:dem":296,
    "gn:feature_class":"P",
    "gn:feature_code":"PPL",
    "gn:name":"Tsutsuich\u014d",
    "gn:population":0,
    "gn:timezone":"Asia/Tokyo",
    "iso:country":"JP",
    "name:jpn_x_preferred":[
        "\u7b52\u4e95\u753a"
    ],
    "name:und_x_variant":[
        "Tsutsuich\u014d"
    ],
    "wof:name":"Tsutsuicho",
    "wof:placetype":"locality"
},
  "geometry": {"coordinates":[129.76611,33.2203],"type":"Point"}
}