{
  "type": "Feature",
  "properties": {
    "gn:admin1_code":"26.0",
    "gn:admin2_code":"1849427.0",
    "gn:asciiname":"Fukuta",
    "gn:country_code":"JP",
    "gn:dem":445,
    "gn:feature_class":"P",
    "gn:feature_code":"PPL",
    "gn:name":"Fukuta",
    "gn:population":0,
    "gn:timezone":"Asia/Tokyo",
    "iso:country":"JP",
    "name:jpn_x_preferred":[
        "\u798f\u7530"
    ],
    "wof:name":"Fukuta",
    "wof:placetype":"locality"
},
  "geometry": {"coordinates":[138.20496,36.38799],"type":"Point"}
}