{
  "type": "Feature",
  "properties": {
    "gn:admin1_code":"14",
    "gn:admin2_code":"2111899.0",
    "gn:asciiname":"Sugisaki",
    "gn:country_code":"JP",
    "gn:dem":45,
    "gn:feature_class":"P",
    "gn:feature_code":"PPL",
    "gn:name":"Sugisaki",
    "gn:population":0,
    "gn:timezone":"Asia/Tokyo",
    "iso:country":"JP",
    "wof:name":"Sugisaki",
    "wof:placetype":"locality"
},
  "geometry": {"coordinates":[140.34999999999999,36.38333],"type":"Point"}
}