{
  "type": "Feature",
  "properties": {
    "gn:admin1_code":"4.0",
    "gn:admin2_code":"7465524.0",
    "gn:asciiname":"Furuyaniwa",
    "gn:country_code":"JP",
    "gn:dem":8,
    "gn:feature_class":"P",
    "gn:feature_code":"PPLL",
    "gn:name":"Furuyaniwa",
    "gn:population":0,
    "gn:timezone":"Asia/Tokyo",
    "iso:country":"JP",
    "name:jpn_x_preferred":[
        "\u53e4\u5c4b\u5ead"
    ],
    "name:jpn_x_variant":[
        "\u3075\u308b\u3084\u306b\u308f",
        "\u30d5\u30eb\u30e4\u30cb\u30ef"
    ],
    "wof:name":"Furuyaniwa",
    "wof:placetype":"locality"
},
  "geometry": {"coordinates":[140.38741999999999,35.27244],"type":"Point"}
}