{
  "type": "Feature",
  "properties": {
    "gn:admin1_code":"18.0",
    "gn:admin2_code":"1850587.0",
    "gn:asciiname":"Mizunoue",
    "gn:country_code":"JP",
    "gn:dem":4,
    "gn:feature_class":"P",
    "gn:feature_code":"PPLL",
    "gn:name":"Mizunoue",
    "gn:population":0,
    "gn:timezone":"Asia/Tokyo",
    "iso:country":"JP",
    "name:jpn_x_preferred":[
        "\u6c34\u4e4b\u4e0a"
    ],
    "wof:name":"Mizunoue",
    "wof:placetype":"locality"
},
  "geometry": {"coordinates":[130.72001,31.48312],"type":"Point"}
}