{
  "type": "Feature",
  "properties": {
    "gn:admin1_code":"18.0",
    "gn:admin2_code":"7383999.0",
    "gn:admin3_code":"46482.0",
    "gn:asciiname":"Iwahiro",
    "gn:country_code":"JP",
    "gn:dem":8,
    "gn:feature_class":"P",
    "gn:feature_code":"PPL",
    "gn:name":"Iwahiro",
    "gn:population":0,
    "gn:timezone":"Asia/Tokyo",
    "iso:country":"JP",
    "name:jpn_x_preferred":[
        "\u5ca9\u5f18"
    ],
    "wof:name":"Iwahiro",
    "wof:placetype":"locality"
},
  "geometry": {"coordinates":[130.95909,31.41341],"type":"Point"}
}