{
  "type": "Feature",
  "properties": {
    "gn:admin1_code":"4.0",
    "gn:admin2_code":"2110982.0",
    "gn:asciiname":"Kajiyama",
    "gn:country_code":"JP",
    "gn:dem":70,
    "gn:feature_class":"P",
    "gn:feature_code":"PPLL",
    "gn:name":"Kajiyama",
    "gn:population":0,
    "gn:timezone":"Asia/Tokyo",
    "iso:country":"JP",
    "name:jpn_x_preferred":[
        "\u935b\u6cbb\u5c71"
    ],
    "name:jpn_x_variant":[
        "\u304b\u3058\u3084\u307e",
        "\u30ab\u30b8\u30e4\u30de"
    ],
    "wof:name":"Kajiyama",
    "wof:placetype":"locality"
},
  "geometry": {"coordinates":[140.01931000000002,35.359],"type":"Point"}
}