{
  "type": "Feature",
  "properties": {
    "gn:admin1_code":"21.0",
    "gn:admin2_code":"7412706.0",
    "gn:admin3_code":"43443.0",
    "gn:asciiname":"Shimada",
    "gn:country_code":"JP",
    "gn:dem":4,
    "gn:feature_class":"P",
    "gn:feature_code":"PPL",
    "gn:name":"Shimada",
    "gn:population":0,
    "gn:timezone":"Asia/Tokyo",
    "iso:country":"JP",
    "name:deu_x_preferred":[
        "Shimada"
    ],
    "name:fra_x_preferred":[
        "Shimada"
    ],
    "name:jpn_x_preferred":[
        "\u5cf6\u7530"
    ],
    "name:jpn_x_variant":[
        "\u3057\u307e\u3060",
        "\u30b7\u30de\u30c0"
    ],
    "name:kor_x_preferred":[
        "\uc2dc\ub9c8\ub2e4"
    ],
    "name:mlg_x_preferred":[
        "Shimada"
    ],
    "name:ron_x_preferred":[
        "Shimada"
    ],
    "name:rus_x_preferred":[
        "\u0421\u0438\u043c\u0430\u0434\u0430"
    ],
    "name:swe_x_preferred":[
        "Shimada"
    ],
    "name:ukr_x_preferred":[
        "\u0421\u0456\u043c\u0430\u0434\u0430"
    ],
    "wof:name":"Shimada",
    "wof:placetype":"locality"
},
  "geometry": {"coordinates":[130.79042999999999,32.75684],"type":"Point"}
}