{
  "type": "Feature",
  "properties": {
    "gn:admin1_code":"3.0",
    "gn:admin2_code":"2127674.0",
    "gn:asciiname":"Kiyose",
    "gn:country_code":"JP",
    "gn:dem":90,
    "gn:feature_class":"P",
    "gn:feature_code":"PPL",
    "gn:name":"Kiyose",
    "gn:population":0,
    "gn:timezone":"Asia/Tokyo",
    "iso:country":"JP",
    "name:jpn_x_preferred":[
        "\u6e05\u702c"
    ],
    "name:jpn_x_variant":[
        "\u304d\u3088\u305b",
        "\u30ad\u30e8\u30bb"
    ],
    "wof:name":"Kiyose",
    "wof:placetype":"locality"
},
  "geometry": {"coordinates":[141.19996,40.55464],"type":"Point"}
}