{
  "type": "Feature",
  "properties": {
    "gn:admin1_code":"47",
    "gn:admin2_code":"7415819.0",
    "gn:asciiname":"Ueno",
    "gn:country_code":"JP",
    "gn:dem":53,
    "gn:feature_class":"P",
    "gn:feature_code":"PPL",
    "gn:name":"Ueno",
    "gn:population":0,
    "gn:timezone":"Asia/Tokyo",
    "iso:country":"JP",
    "name:fra_x_preferred":[
        "Ueno"
    ],
    "name:jpn_x_preferred":[
        "\u4e0a\u91ce"
    ],
    "name:jpn_x_variant":[
        "\u3046\u3048\u306e",
        "\u4e0a\u91ce\u6751"
    ],
    "name:und_x_variant":[
        "Unatoo"
    ],
    "wof:name":"Ueno",
    "wof:placetype":"locality"
},
  "geometry": {"coordinates":[125.31567,24.73715],"type":"Point"}
}