{
  "type": "Feature",
  "properties": {
    "gn:admin1_code":"18.0",
    "gn:admin2_code":"1850587.0",
    "gn:asciiname":"Hamabira",
    "gn:country_code":"JP",
    "gn:dem":26,
    "gn:feature_class":"P",
    "gn:feature_code":"PPL",
    "gn:name":"Hamabira",
    "gn:population":0,
    "gn:timezone":"Asia/Tokyo",
    "iso:country":"JP",
    "name:jpn_x_preferred":[
        "\u6d5c\u5e73"
    ],
    "wof:name":"Hamabira",
    "wof:placetype":"locality"
},
  "geometry": {"coordinates":[130.70095000000001,31.47532],"type":"Point"}
}