{
  "type": "Feature",
  "properties": {
    "gn:admin1_code":"33.0",
    "gn:admin2_code":"7391358.0",
    "gn:admin3_code":"41425.0",
    "gn:asciiname":"Tsutsumi",
    "gn:country_code":"JP",
    "gn:dem":9,
    "gn:feature_class":"P",
    "gn:feature_code":"PPL",
    "gn:name":"Tsutsumi",
    "gn:population":0,
    "gn:timezone":"Asia/Tokyo",
    "iso:country":"JP",
    "name:jpn_x_preferred":[
        "\u5824"
    ],
    "wof:name":"Tsutsumi",
    "wof:placetype":"locality"
},
  "geometry": {"coordinates":[130.10407000000001,33.18094],"type":"Point"}
}