{
  "type": "Feature",
  "properties": {
    "gn:admin1_code":"40.0",
    "gn:admin2_code":"1865750.0",
    "gn:asciiname":"Kohoku",
    "gn:country_code":"JP",
    "gn:dem":7,
    "gn:feature_class":"P",
    "gn:feature_code":"PPL",
    "gn:name":"K\u014dhoku",
    "gn:population":0,
    "gn:timezone":"Asia/Tokyo",
    "iso:country":"JP",
    "name:jpn_x_preferred":[
        "\u6c5f\u5317"
    ],
    "name:kor_x_preferred":[
        "\uace0\ud638\ucfe0\uc815"
    ],
    "name:ukr_x_preferred":[
        "\u041a\u043e\u0445\u043e\u043a\u0443"
    ],
    "name:und_x_variant":[
        "K\u014dhoku"
    ],
    "wof:name":"Kohoku",
    "wof:placetype":"locality"
},
  "geometry": {"coordinates":[139.76561999999998,35.77672000000001],"type":"Point"}
}