{
  "type": "Feature",
  "properties": {
    "gn:admin1_code":"3.0",
    "gn:admin2_code":"2130654.0",
    "gn:asciiname":"Satomi",
    "gn:country_code":"JP",
    "gn:dem":8,
    "gn:feature_class":"P",
    "gn:feature_code":"PPL",
    "gn:name":"Satomi",
    "gn:population":0,
    "gn:timezone":"Asia/Tokyo",
    "iso:country":"JP",
    "name:jpn_x_preferred":[
        "\u91cc\u898b"
    ],
    "name:jpn_x_variant":[
        "\u3055\u3068\u307f",
        "\u30b5\u30c8\u30df"
    ],
    "wof:name":"Satomi",
    "wof:placetype":"locality"
},
  "geometry": {"coordinates":[140.71190000000001,40.81711],"type":"Point"}
}