{
  "type": "Feature",
  "properties": {
    "iso:country":"JP",
    "name:eng_x_preferred":[
        "Kujiranami 3 Chome"
    ],
    "name:eng_x_variant":[
        "Kujiranami 3 Choume",
        "Kujiranami 3 Chome"
    ],
    "name:jpn_x_preferred":[
        "\uff13\u4e01\u76ee"
    ],
    "name:jpn_x_variant":[
        "\u304f\u3058\u3089\u306a\u307f \uff13\u3061\u3087\u3046\u3081",
        "\u9be8\u6ce2 \uff13\u4e01\u76ee",
        "\uff13\u3061\u3087\u3046\u3081"
    ],
    "name:unk_x_variant":[
        "\uff13\u4e01\u76ee"
    ],
    "qs:gn_local":0,
    "qs:local_max":180,
    "qs:local_sum":255,
    "qs:localhoods":4,
    "qs:name":"\uff13\u4e01\u76ee",
    "qs:name_adm0":"\u65e5\u672c",
    "qs:name_adm1":"\u65b0\u6f5f\u770c",
    "qs:name_en":"Kujiranami 3 Chome",
    "qs:name_lau":"\u9be8\u6ce2",
    "qs:name_local":"\u67cf\u5d0e\u5e02",
    "qs:photo_max":10,
    "qs:photo_sum":28,
    "qs:placetype":"Suburb",
    "qs:quad_count":10,
    "qs:woe_adm0":23424856,
    "qs:woe_adm1":2345878,
    "qs:woe_adm2":0,
    "qs:woe_lau":28419389,
    "qs:woe_local":1117470,
    "qs:woe_ver":"7.10.0",
    "wof:lang":[
        "jpn"
    ],
    "wof:name":"\uff13\u4e01\u76ee",
    "wof:placetype":"neighbourhood"
},
  "geometry": {"coordinates":[138.496399,37.349106],"type":"Point"}
}