{
  "type": "Feature",
  "properties": {
    "gn:admin1_code":"21.0",
    "gn:admin2_code":"1859488.0",
    "gn:asciiname":"Kitamuki",
    "gn:country_code":"JP",
    "gn:dem":165,
    "gn:feature_class":"P",
    "gn:feature_code":"PPLL",
    "gn:name":"Kitamuki",
    "gn:population":0,
    "gn:timezone":"Asia/Tokyo",
    "iso:country":"JP",
    "name:jpn_x_preferred":[
        "\u5317\u5411"
    ],
    "name:jpn_x_variant":[
        "\u304d\u305f\u3080\u304d",
        "\u30ad\u30bf\u30e0\u30ad"
    ],
    "wof:name":"Kitamuki",
    "wof:placetype":"locality"
},
  "geometry": {"coordinates":[130.83676,33.01377],"type":"Point"}
}