{
  "type": "Feature",
  "properties": {
    "gn:admin1_code":"16.0",
    "gn:admin2_code":"7441817.0",
    "gn:asciiname":"Yogai",
    "gn:country_code":"JP",
    "gn:dem":15,
    "gn:feature_class":"P",
    "gn:feature_code":"PPL",
    "gn:name":"Y\u014dgai",
    "gn:population":0,
    "gn:timezone":"Asia/Tokyo",
    "iso:country":"JP",
    "name:jpn_x_preferred":[
        "\u8981\u8c37"
    ],
    "name:jpn_x_variant":[
        "\u3088\u3046\u304c\u3044",
        "\u30e8\u30a6\u30ac\u30a4"
    ],
    "name:und_x_variant":[
        "Y\u014dgai"
    ],
    "wof:name":"Yogai",
    "wof:placetype":"locality"
},
  "geometry": {"coordinates":[141.62423999999999,38.9814],"type":"Point"}
}