{
  "type": "Feature",
  "properties": {
    "gn:admin1_code":"43.0",
    "gn:admin2_code":"1865123.0",
    "gn:admin3_code":"30366.0",
    "gn:asciiname":"Oki",
    "gn:country_code":"JP",
    "gn:dem":36,
    "gn:feature_class":"P",
    "gn:feature_code":"PPL",
    "gn:name":"Oki",
    "gn:population":0,
    "gn:timezone":"Asia/Tokyo",
    "iso:country":"JP",
    "name:jbn_x_preferred":[
        "Oki"
    ],
    "name:jpn_x_preferred":[
        "\u5965"
    ],
    "wof:name":"Oki",
    "wof:placetype":"locality"
},
  "geometry": {"coordinates":[135.21381,34.05075],"type":"Point"}
}