{
  "type": "Feature",
  "properties": {
    "gn:admin1_code":"43.0",
    "gn:admin2_code":"1865123.0",
    "gn:admin3_code":"30366.0",
    "gn:asciiname":"Oki",
    "gn:country_code":"JP",
    "gn:dem":36,
    "gn:feature_class":"P",
    "gn:feature_code":"PPL",
    "gn:name":"Oki",
    "gn:population":0,
    "gn:timezone":"Asia/Tokyo",
    "iso:country":"JP",
    "name:ceb_x_preferred":[
        "Oki"
    ],
    "name:deu_x_preferred":[
        "Oki"
    ],
    "name:fra_x_preferred":[
        "Oki"
    ],
    "name:jbn_x_preferred":[
        "Oki"
    ],
    "name:jpn_x_preferred":[
        "\u5965"
    ],
    "name:nld_x_preferred":[
        "Oki"
    ],
    "name:nor_x_preferred":[
        "Oki"
    ],
    "name:pol_x_preferred":[
        "Oki"
    ],
    "name:por_x_preferred":[
        "Oki"
    ],
    "name:rus_x_preferred":[
        "\u041e\u043a\u0438"
    ],
    "name:swe_x_preferred":[
        "Oki"
    ],
    "wof:name":"Oki",
    "wof:placetype":"locality"
},
  "geometry": {"coordinates":[135.21381,34.05075],"type":"Point"}
}