{
  "type": "Feature",
  "properties": {
    "gn:admin1_code":"27.0",
    "gn:admin2_code":"1852895.0",
    "gn:asciiname":"Shimomotoyamacho",
    "gn:country_code":"JP",
    "gn:dem":39,
    "gn:feature_class":"P",
    "gn:feature_code":"PPL",
    "gn:name":"Shimomotoyamach\u014d",
    "gn:population":0,
    "gn:timezone":"Asia/Tokyo",
    "iso:country":"JP",
    "name:jpn_x_preferred":[
        "\u4e0b\u672c\u5c71\u753a"
    ],
    "name:und_x_variant":[
        "Shimomotoyamach\u014d"
    ],
    "wof:name":"Shimomotoyamacho",
    "wof:placetype":"locality"
},
  "geometry": {"coordinates":[129.6815,33.20903],"type":"Point"}
}