{
  "type": "Feature",
  "properties": {
    "gn:admin1_code":"14.0",
    "gn:admin2_code":"2112705.0",
    "gn:asciiname":"Nishitari",
    "gn:cc2":"JP",
    "gn:country_code":"JP",
    "gn:dem":111,
    "gn:feature_class":"P",
    "gn:feature_code":"PPL",
    "gn:name":"Nishitari",
    "gn:population":0,
    "gn:timezone":"Asia/Tokyo",
    "iso:country":"JP",
    "name:und_x_variant":[
        "Nishiashi",
        "Nishitari"
    ],
    "wof:name":"Nishitari",
    "wof:placetype":"locality"
},
  "geometry": {"coordinates":[140.48333,36.63333],"type":"Point"}
}