{
  "type": "Feature",
  "properties": {
    "gn:admin1_code":"32.0",
    "gn:admin2_code":"1851482.0",
    "gn:asciiname":"Aoyamadai",
    "gn:country_code":"JP",
    "gn:dem":84,
    "gn:feature_class":"P",
    "gn:feature_code":"PPL",
    "gn:name":"Aoyamadai",
    "gn:population":0,
    "gn:timezone":"Asia/Tokyo",
    "iso:country":"JP",
    "name:jpn_x_preferred":[
        "\u9752\u5c71\u53f0"
    ],
    "wof:name":"Aoyamadai",
    "wof:placetype":"locality"
},
  "geometry": {"coordinates":[135.50064,34.82312],"type":"Point"}
}