{
  "type": "Feature",
  "properties": {
    "iso:country":"JP",
    "name:eng_x_preferred":[
        "Myojocho 1 Chome"
    ],
    "name:eng_x_variant":[
        "Myoujouchou 1 Choume",
        "Myojocho 1 Chome"
    ],
    "name:jpn_x_preferred":[
        "\uff11\u4e01\u76ee"
    ],
    "name:jpn_x_variant":[
        "\u307f\u3087\u3046\u3058\u3087\u3046\u3061\u3087\u3046 \uff11\u3061\u3087\u3046\u3081",
        "\u660e\u661f\u753a \uff11\u4e01\u76ee",
        "\uff11\u3061\u3087\u3046\u3081"
    ],
    "qs:gn_local":0,
    "qs:local_max":2097,
    "qs:local_sum":5940,
    "qs:localhoods":11,
    "qs:name":"\uff11\u4e01\u76ee",
    "qs:name_adm0":"\u65e5\u672c",
    "qs:name_adm1":"\u4eac\u90fd\u5e9c",
    "qs:name_en":"Myojocho 1 Chome",
    "qs:name_lau":"\u660e\u661f\u753a",
    "qs:name_local":"\u5b87\u6cbb\u5e02",
    "qs:photo_max":294,
    "qs:photo_sum":513,
    "qs:placetype":"Suburb",
    "qs:quad_count":5,
    "qs:woe_adm0":23424856,
    "qs:woe_adm1":2345871,
    "qs:woe_adm2":0,
    "qs:woe_lau":28455368,
    "qs:woe_local":1118462,
    "qs:woe_ver":"7.10.0",
    "wof:lang":[
        "jpn"
    ],
    "wof:name":"\uff11\u4e01\u76ee",
    "wof:placetype":"neighbourhood"
},
  "geometry": {"coordinates":[135.81873300000001,34.900072],"type":"Point"}
}