{
  "type": "Feature",
  "properties": {
    "gn:admin1_code":"16.0",
    "gn:admin2_code":"2112822.0",
    "gn:asciiname":"Kajimachi",
    "gn:country_code":"JP",
    "gn:dem":81,
    "gn:feature_class":"P",
    "gn:feature_code":"PPL",
    "gn:name":"Kajimachi",
    "gn:population":0,
    "gn:timezone":"Asia/Tokyo",
    "iso:country":"JP",
    "name:jpn_x_preferred":[
        "\u935b\u6cbb\u753a"
    ],
    "name:jpn_x_variant":[
        "\u304b\u3058\u307e\u3061",
        "\u30ab\u30b8\u30de\u30c1"
    ],
    "wof:name":"Kajimachi",
    "wof:placetype":"locality"
},
  "geometry": {"coordinates":[141.11354,39.38539],"type":"Point"}
}