{
  "type": "Feature",
  "properties": {
    "gn:admin1_code":"2.0",
    "gn:admin2_code":"7443156.0",
    "gn:asciiname":"Obata",
    "gn:country_code":"JP",
    "gn:dem":57,
    "gn:feature_class":"P",
    "gn:feature_code":"PPLL",
    "gn:name":"\u014cbata",
    "gn:population":0,
    "gn:timezone":"Asia/Tokyo",
    "iso:country":"JP",
    "name:jpn_x_preferred":[
        "\u5927\u7551"
    ],
    "name:und_x_variant":[
        "\u014cbata"
    ],
    "wof:name":"Obata",
    "wof:placetype":"locality"
},
  "geometry": {"coordinates":[140.39179999999999,40.2772],"type":"Point"}
}