{
  "type": "Feature",
  "properties": {
    "gn:admin1_code":"15.0",
    "gn:admin2_code":"7467879.0",
    "gn:asciiname":"Notojima-enomemachi",
    "gn:country_code":"JP",
    "gn:dem":2,
    "gn:feature_class":"P",
    "gn:feature_code":"PPL",
    "gn:name":"Notojima-enomemachi",
    "gn:population":0,
    "gn:timezone":"Asia/Tokyo",
    "iso:country":"JP",
    "name:jpn_x_preferred":[
        "\u80fd\u767b\u5cf6\u9c00\u76ee\u753a"
    ],
    "wof:name":"Notojima-enomemachi",
    "wof:placetype":"locality"
},
  "geometry": {"coordinates":[137.04809,37.15353],"type":"Point"}
}