{
  "type": "Feature",
  "properties": {
    "gn:admin1_code":"40.0",
    "gn:admin2_code":"1862785.0",
    "gn:asciiname":"Kanayamacho",
    "gn:country_code":"JP",
    "gn:dem":54,
    "gn:feature_class":"P",
    "gn:feature_code":"PPL",
    "gn:name":"Kanayamach\u014d",
    "gn:population":0,
    "gn:timezone":"Asia/Tokyo",
    "iso:country":"JP",
    "name:jpn_x_preferred":[
        "\u91d1\u5c71\u753a"
    ],
    "name:und_x_variant":[
        "Kanayamach\u014d"
    ],
    "wof:name":"Kanayamacho",
    "wof:placetype":"locality"
},
  "geometry": {"coordinates":[139.53946000000002,35.76815999999999],"type":"Point"}
}