{
  "type": "Feature",
  "properties": {
    "gn:admin1_code":"07",
    "gn:admin2_code":"9035649.0",
    "gn:asciiname":"Nijo-ishizaki",
    "gn:country_code":"JP",
    "gn:dem":26,
    "gn:feature_class":"P",
    "gn:feature_code":"PPL",
    "gn:name":"Nij\u014d-ishizaki",
    "gn:population":0,
    "gn:timezone":"Asia/Tokyo",
    "iso:country":"JP",
    "name:jpn_x_preferred":[
        "\u4e8c\u4e08\u77f3\u5d0e"
    ],
    "name:und_x_variant":[
        "Nij\u014d-ishizaki",
        "Ishizaki"
    ],
    "wof:name":"Nijo-ishizaki",
    "wof:placetype":"locality"
},
  "geometry": {"coordinates":[130.16256999999999,33.51686],"type":"Point"}
}