{
  "type": "Feature",
  "properties": {
    "gn:admin1_code":"7.0",
    "gn:admin2_code":"1856443.0",
    "gn:asciiname":"Hirukake",
    "gn:country_code":"JP",
    "gn:dem":43,
    "gn:feature_class":"P",
    "gn:feature_code":"PPLL",
    "gn:name":"Hirukake",
    "gn:population":0,
    "gn:timezone":"Asia/Tokyo",
    "iso:country":"JP",
    "name:jpn_x_preferred":[
        "\u663c\u639b"
    ],
    "wof:name":"Hirukake",
    "wof:placetype":"locality"
},
  "geometry": {"coordinates":[130.58858000000001,33.77264],"type":"Point"}
}