{
  "type": "Feature",
  "properties": {
    "gn:admin1_code":"43.0",
    "gn:admin2_code":"1860782.0",
    "gn:asciiname":"Asso",
    "gn:country_code":"JP",
    "gn:dem":13,
    "gn:feature_class":"P",
    "gn:feature_code":"PPL",
    "gn:name":"Asso",
    "gn:population":0,
    "gn:timezone":"Asia/Tokyo",
    "iso:country":"JP",
    "name:jpn_x_preferred":[
        "\u4e14\u6765"
    ],
    "wof:name":"Asso",
    "wof:placetype":"locality"
},
  "geometry": {"coordinates":[135.23571000000001,34.17054],"type":"Point"}
}