{
  "type": "Feature",
  "properties": {
    "gn:admin1_code":"43.0",
    "gn:admin2_code":"1860782.0",
    "gn:asciiname":"Asso",
    "gn:country_code":"JP",
    "gn:dem":13,
    "gn:feature_class":"P",
    "gn:feature_code":"PPL",
    "gn:name":"Asso",
    "gn:population":0,
    "gn:timezone":"Asia/Tokyo",
    "iso:country":"JP",
    "name:azb_x_preferred":[
        "\u0627\u0633\u0633\u0648"
    ],
    "name:deu_x_preferred":[
        "Asso"
    ],
    "name:epo_x_preferred":[
        "Asso"
    ],
    "name:eus_x_preferred":[
        "Asso"
    ],
    "name:fas_x_preferred":[
        "\u0627\u0633\u0633\u0648"
    ],
    "name:fra_x_preferred":[
        "Asso"
    ],
    "name:hun_x_preferred":[
        "Asso"
    ],
    "name:hye_x_preferred":[
        "\u0531\u057d\u057d\u0578"
    ],
    "name:ita_x_preferred":[
        "Asso"
    ],
    "name:jpn_x_preferred":[
        "\u4e14\u6765"
    ],
    "name:jpn_x_variant":[
        "\u30a2\u30c3\u30bd"
    ],
    "name:kaz_x_preferred":[
        "\u0410\u0441\u0441\u043e"
    ],
    "name:lat_x_preferred":[
        "Ascium"
    ],
    "name:lmo_x_preferred":[
        "Ass"
    ],
    "name:msa_x_preferred":[
        "Asso"
    ],
    "name:nap_x_preferred":[
        "Asso"
    ],
    "name:nld_x_preferred":[
        "Asso"
    ],
    "name:pms_x_preferred":[
        "Asso"
    ],
    "name:pol_x_preferred":[
        "Asso"
    ],
    "name:por_x_preferred":[
        "Asso"
    ],
    "name:ron_x_preferred":[
        "Asso"
    ],
    "name:rus_x_preferred":[
        "\u0410\u0441\u0441\u043e"
    ],
    "name:scn_x_preferred":[
        "Asso"
    ],
    "name:spa_x_preferred":[
        "Asso"
    ],
    "name:srd_x_preferred":[
        "Asso"
    ],
    "name:srp_x_preferred":[
        "\u0410\u0441\u043e"
    ],
    "name:tgl_x_preferred":[
        "Asso"
    ],
    "name:ukr_x_preferred":[
        "\u0410\u0441\u0441\u043e"
    ],
    "name:uzb_x_preferred":[
        "Asso"
    ],
    "name:vie_x_preferred":[
        "Asso"
    ],
    "name:vol_x_preferred":[
        "Asso"
    ],
    "name:war_x_preferred":[
        "Asso"
    ],
    "wof:name":"Asso",
    "wof:placetype":"locality"
},
  "geometry": {"coordinates":[135.23571000000001,34.17054],"type":"Point"}
}