{
  "type": "Feature",
  "properties": {
    "gn:admin1_code":"43",
    "gn:admin2_code":"1860782.0",
    "gn:asciiname":"Shimotsucho-karegawa",
    "gn:country_code":"JP",
    "gn:dem":68,
    "gn:feature_class":"P",
    "gn:feature_code":"PPL",
    "gn:name":"Shimotsuch\u014d-karegawa",
    "gn:population":0,
    "gn:timezone":"Asia/Tokyo",
    "iso:country":"JP",
    "name:jpn_x_preferred":[
        "\u4e0b\u6d25\u753a\u9c08\u5ddd"
    ],
    "name:und_x_variant":[
        "Shimotsuch\u014d-karegawa",
        "Karekawa"
    ],
    "wof:name":"Shimotsucho-karegawa",
    "wof:placetype":"locality"
},
  "geometry": {"coordinates":[135.14336,34.10123],"type":"Point"}
}