{
  "type": "Feature",
  "properties": {
    "gn:admin1_code":"21",
    "gn:admin2_code":"1864975.0",
    "gn:admin3_code":"43433.0",
    "gn:asciiname":"Kurokawa",
    "gn:country_code":"JP",
    "gn:dem":435,
    "gn:feature_class":"P",
    "gn:feature_code":"PPLL",
    "gn:name":"Kurokawa",
    "gn:population":0,
    "gn:timezone":"Asia/Tokyo",
    "iso:country":"JP",
    "name:deu_x_preferred":[
        "Kurokawa"
    ],
    "name:jpn_x_preferred":[
        "\u9ed2\u5ddd"
    ],
    "name:jpn_x_variant":[
        "\u304f\u308d\u304b\u308f",
        "\u30af\u30ed\u30ab\u30ef"
    ],
    "name:und_x_variant":[
        "Kurogawa"
    ],
    "wof:name":"Kurokawa",
    "wof:placetype":"locality"
},
  "geometry": {"coordinates":[130.99421999999998,32.88494],"type":"Point"}
}