{
  "type": "Feature",
  "properties": {
    "gn:admin1_code":"21.0",
    "gn:admin2_code":"1862350.0",
    "gn:asciiname":"Daikumachi",
    "gn:country_code":"JP",
    "gn:dem":105,
    "gn:feature_class":"P",
    "gn:feature_code":"PPL",
    "gn:name":"Daikumachi",
    "gn:population":0,
    "gn:timezone":"Asia/Tokyo",
    "iso:country":"JP",
    "name:jpn_x_preferred":[
        "\u5927\u5de5\u753a"
    ],
    "name:jpn_x_variant":[
        "\u3060\u3044\u304f\u307e\u3061",
        "\u30c0\u30a4\u30af\u30de\u30c1"
    ],
    "wof:name":"Daikumachi",
    "wof:placetype":"locality"
},
  "geometry": {"coordinates":[130.75987000000001,32.21568],"type":"Point"}
}