{
  "type": "Feature",
  "properties": {
    "gn:admin1_code":"40.0",
    "gn:admin2_code":"1856786.0",
    "gn:admin3_code":"13381.0",
    "gn:asciiname":"Izu",
    "gn:country_code":"JP",
    "gn:dem":88,
    "gn:feature_class":"P",
    "gn:feature_code":"PPL",
    "gn:name":"Izu",
    "gn:population":0,
    "gn:timezone":"Asia/Tokyo",
    "iso:country":"JP",
    "name:ara_x_preferred":[
        "\u0625\u0632\u0648"
    ],
    "name:cat_x_preferred":[
        "Izu"
    ],
    "name:ceb_x_preferred":[
        "Izu"
    ],
    "name:ces_x_preferred":[
        "Izu"
    ],
    "name:deu_x_preferred":[
        "Izu"
    ],
    "name:epo_x_preferred":[
        "Izu"
    ],
    "name:eus_x_preferred":[
        "Izu"
    ],
    "name:fin_x_preferred":[
        "Izu"
    ],
    "name:jpn_x_preferred":[
        "\u4f0a\u8c46"
    ],
    "name:lit_x_preferred":[
        "Idzu"
    ],
    "name:nld_x_preferred":[
        "Izu"
    ],
    "name:pol_x_preferred":[
        "Izu"
    ],
    "name:por_x_preferred":[
        "Izu"
    ],
    "name:rus_x_preferred":[
        "\u0418\u0434\u0437\u0443"
    ],
    "name:slk_x_preferred":[
        "Izu"
    ],
    "name:spa_x_preferred":[
        "Izu"
    ],
    "wof:name":"Izu",
    "wof:placetype":"locality"
},
  "geometry": {"coordinates":[139.50183000000001,34.11335],"type":"Point"}
}