{
  "type": "Feature",
  "properties": {
    "gn:admin1_code":"40.0",
    "gn:admin2_code":"1856786.0",
    "gn:admin3_code":"13381.0",
    "gn:asciiname":"Izu",
    "gn:country_code":"JP",
    "gn:dem":88,
    "gn:feature_class":"P",
    "gn:feature_code":"PPL",
    "gn:name":"Izu",
    "gn:population":0,
    "gn:timezone":"Asia/Tokyo",
    "iso:country":"JP",
    "name:jpn_x_preferred":[
        "\u4f0a\u8c46"
    ],
    "wof:name":"Izu",
    "wof:placetype":"locality"
},
  "geometry": {"coordinates":[139.50183000000001,34.11335],"type":"Point"}
}