{
  "type": "Feature",
  "properties": {
    "gn:admin1_code":"7.0",
    "gn:admin2_code":"1856443.0",
    "gn:asciiname":"Fukusaki",
    "gn:country_code":"JP",
    "gn:dem":5,
    "gn:feature_class":"P",
    "gn:feature_code":"PPLL",
    "gn:name":"Fukusaki",
    "gn:population":0,
    "gn:timezone":"Asia/Tokyo",
    "iso:country":"JP",
    "name:jpn_x_preferred":[
        "\u798f\u5d0e"
    ],
    "wof:name":"Fukusaki",
    "wof:placetype":"locality"
},
  "geometry": {"coordinates":[130.54202000000001,33.8179],"type":"Point"}
}