{
  "type": "Feature",
  "properties": {
    "gn:admin1_code":"19.0",
    "gn:admin2_code":"1856849.0",
    "gn:asciiname":"Higashinodai",
    "gn:country_code":"JP",
    "gn:dem":5,
    "gn:feature_class":"P",
    "gn:feature_code":"PPLL",
    "gn:name":"Higashinodai",
    "gn:population":0,
    "gn:timezone":"Asia/Tokyo",
    "iso:country":"JP",
    "name:jpn_x_preferred":[
        "\u6771\u30ce\u53f0"
    ],
    "name:jpn_x_variant":[
        "\u3072\u304c\u3057\u306e\u3060\u3044",
        "\u30d2\u30ac\u30b7\u30ce\u30c0\u30a4"
    ],
    "wof:name":"Higashinodai",
    "wof:placetype":"locality"
},
  "geometry": {"coordinates":[139.62572,35.16162],"type":"Point"}
}