{
  "type": "Feature",
  "properties": {
    "gn:admin1_code":"24.0",
    "gn:admin2_code":"2112261.0",
    "gn:asciiname":"Oura",
    "gn:country_code":"JP",
    "gn:dem":30,
    "gn:feature_class":"P",
    "gn:feature_code":"PPL",
    "gn:name":"\u014cura",
    "gn:population":0,
    "gn:timezone":"Asia/Tokyo",
    "iso:country":"JP",
    "name:ceb_x_preferred":[
        "Oura"
    ],
    "name:fra_x_preferred":[
        "Oura"
    ],
    "name:jpn_x_preferred":[
        "\u5927\u6d66"
    ],
    "name:jpn_x_variant":[
        "\u304a\u304a\u3046\u3089",
        "\u30aa\u30aa\u30a6\u30e9"
    ],
    "name:swe_x_preferred":[
        "Oura"
    ],
    "name:und_x_variant":[
        "\u014cura"
    ],
    "wof:name":"Oura",
    "wof:placetype":"locality"
},
  "geometry": {"coordinates":[141.59059999999999,38.89814000000001],"type":"Point"}
}