{
  "type": "Feature",
  "properties": {
    "gn:admin1_code":"15.0",
    "gn:admin2_code":"1858904.0",
    "gn:asciiname":"Ugawamachi",
    "gn:country_code":"JP",
    "gn:dem":54,
    "gn:feature_class":"P",
    "gn:feature_code":"PPL",
    "gn:name":"Ugawamachi",
    "gn:population":0,
    "gn:timezone":"Asia/Tokyo",
    "iso:country":"JP",
    "name:jpn_x_preferred":[
        "\u9d5c\u5ddd\u753a"
    ],
    "wof:name":"Ugawamachi",
    "wof:placetype":"locality"
},
  "geometry": {"coordinates":[136.53298999999998,36.40471],"type":"Point"}
}