{
  "type": "Feature",
  "properties": {
    "gn:admin1_code":"16.0",
    "gn:admin2_code":"2112822.0",
    "gn:asciiname":"Futatsuzeki",
    "gn:country_code":"JP",
    "gn:dem":122,
    "gn:feature_class":"P",
    "gn:feature_code":"PPL",
    "gn:name":"Futatsuzeki",
    "gn:population":0,
    "gn:timezone":"Asia/Tokyo",
    "iso:country":"JP",
    "name:jpn_x_preferred":[
        "\u4e8c\u30c4\u5830"
    ],
    "name:jpn_x_variant":[
        "\u3075\u305f\u3064\u305c\u304d",
        "\u30d5\u30bf\u30c4\u30bc\u30ad"
    ],
    "wof:name":"Futatsuzeki",
    "wof:placetype":"locality"
},
  "geometry": {"coordinates":[141.04316,39.39194000000001],"type":"Point"}
}