{
  "type": "Feature",
  "properties": {
    "gn:admin1_code":"16.0",
    "gn:admin2_code":"2128941.0",
    "gn:admin3_code":"3524.0",
    "gn:asciiname":"Mukaimachi",
    "gn:country_code":"JP",
    "gn:dem":142,
    "gn:feature_class":"P",
    "gn:feature_code":"PPL",
    "gn:name":"Mukaimachi",
    "gn:population":0,
    "gn:timezone":"Asia/Tokyo",
    "iso:country":"JP",
    "name:jpn_x_preferred":[
        "\u5411\u753a"
    ],
    "name:jpn_x_variant":[
        "\u3080\u304b\u3044\u307e\u3061",
        "\u30e0\u30ab\u30a4\u30de\u30c1"
    ],
    "wof:name":"Mukaimachi",
    "wof:placetype":"locality"
},
  "geometry": {"coordinates":[141.30111000000005,40.2144],"type":"Point"}
}