{
  "type": "Feature",
  "properties": {
    "iso:country":"JP",
    "name:eng_x_preferred":[
        "Kojiyahoncho 4 Chome"
    ],
    "name:eng_x_variant":[
        "Kojiyahonchou 4 Choume",
        "Kojiyahoncho 4 Chome"
    ],
    "name:jpn_x_preferred":[
        "\uff14\u4e01\u76ee"
    ],
    "name:jpn_x_variant":[
        "\u3053\u3062\u3084\u307b\u3093\u3061\u3087\u3046 \uff14\u3061\u3087\u3046\u3081",
        "\u53e4\u5343\u8c37\u672c\u753a \uff14\u4e01\u76ee",
        "\uff14\u3061\u3087\u3046\u3081"
    ],
    "qs:gn_adm0_cc":"JP",
    "qs:gn_local":1850147,
    "qs:local_max":18112,
    "qs:local_sum":895907,
    "qs:localhoods":857,
    "qs:name":"\uff14\u4e01\u76ee",
    "qs:name_adm0":"\u65e5\u672c",
    "qs:name_adm1":"\u6771\u4eac\u90fd",
    "qs:name_adm2":"\u8db3\u7acb\u533a",
    "qs:name_en":"Kojiyahoncho 4 Chome",
    "qs:name_lau":"\u53e4\u5343\u8c37\u672c\u753a",
    "qs:name_local":"\u6771\u4eac",
    "qs:photo_max":20,
    "qs:photo_sum":28,
    "qs:placetype":"Suburb",
    "qs:quad_count":3,
    "qs:woe_adm0":23424856,
    "qs:woe_adm1":2345889,
    "qs:woe_adm2":1118608,
    "qs:woe_lau":28414711,
    "qs:woe_local":1118370,
    "qs:woe_ver":"7.10.0",
    "wof:lang":[
        "jpn"
    ],
    "wof:name":"\uff14\u4e01\u76ee",
    "wof:placetype":"neighbourhood"
},
  "geometry": {"coordinates":[139.781992,35.807948],"type":"Point"}
}