{
  "type": "Feature",
  "properties": {
    "gn:admin1_code":"3.0",
    "gn:admin2_code":"8534376.0",
    "gn:admin3_code":"2321.0",
    "gn:asciiname":"Nozoki",
    "gn:country_code":"JP",
    "gn:dem":92,
    "gn:feature_class":"P",
    "gn:feature_code":"PPL",
    "gn:name":"Nozoki",
    "gn:population":0,
    "gn:timezone":"Asia/Tokyo",
    "iso:country":"JP",
    "name:jpn_x_preferred":[
        "\u9664\u6728"
    ],
    "name:jpn_x_variant":[
        "\u306e\u305e\u304d",
        "\u30ce\u30be\u30ad"
    ],
    "wof:name":"Nozoki",
    "wof:placetype":"locality"
},
  "geometry": {"coordinates":[140.2413,40.70871],"type":"Point"}
}