{
  "type": "Feature",
  "properties": {
    "gn:admin1_code":"4.0",
    "gn:admin2_code":"2110982.0",
    "gn:asciiname":"Nakazushidai",
    "gn:country_code":"JP",
    "gn:dem":33,
    "gn:feature_class":"P",
    "gn:feature_code":"PPLL",
    "gn:name":"Nakazushidai",
    "gn:population":0,
    "gn:timezone":"Asia/Tokyo",
    "iso:country":"JP",
    "name:jpn_x_preferred":[
        "\u4e2d\u8fbb\u5b50\u53f0"
    ],
    "name:jpn_x_variant":[
        "\u306a\u304b\u305a\u3057\u3060\u3044",
        "\u30ca\u30ab\u30ba\u30b7\u30c0\u30a4"
    ],
    "wof:name":"Nakazushidai",
    "wof:placetype":"locality"
},
  "geometry": {"coordinates":[139.97086000000002,35.42954],"type":"Point"}
}