{
  "type": "Feature",
  "properties": {
    "gn:admin1_code":"7.0",
    "gn:admin2_code":"1859306.0",
    "gn:admin3_code":"40103.0",
    "gn:asciiname":"Dojimaru",
    "gn:country_code":"JP",
    "gn:dem":19,
    "gn:feature_class":"P",
    "gn:feature_code":"PPL",
    "gn:name":"D\u014djimaru",
    "gn:population":0,
    "gn:timezone":"Asia/Tokyo",
    "iso:country":"JP",
    "name:jpn_x_preferred":[
        "\u7ae5\u5b50\u4e38"
    ],
    "name:und_x_variant":[
        "D\u014djimaru"
    ],
    "wof:name":"Dojimaru",
    "wof:placetype":"locality"
},
  "geometry": {"coordinates":[130.76499999999999,33.89118],"type":"Point"}
}