{
  "type": "Feature",
  "properties": {
    "gn:admin1_code":"34.0",
    "gn:admin2_code":"7458572.0",
    "gn:admin3_code":"11383.0",
    "gn:asciiname":"Hamanokai",
    "gn:country_code":"JP",
    "gn:dem":379,
    "gn:feature_class":"P",
    "gn:feature_code":"PPLL",
    "gn:name":"Hamanokai",
    "gn:population":0,
    "gn:timezone":"Asia/Tokyo",
    "iso:country":"JP",
    "name:jpn_x_preferred":[
        "\u6d5c\u306e\u8c37"
    ],
    "wof:name":"Hamanokai",
    "wof:placetype":"locality"
},
  "geometry": {"coordinates":[139.03478999999999,36.11566],"type":"Point"}
}