{
  "type": "Feature",
  "properties": {
    "gn:admin1_code":"25.0",
    "gn:admin2_code":"1864313.0",
    "gn:asciiname":"Mukae",
    "gn:country_code":"JP",
    "gn:dem":218,
    "gn:feature_class":"P",
    "gn:feature_code":"PPL",
    "gn:name":"Mukae",
    "gn:population":0,
    "gn:timezone":"Asia/Tokyo",
    "iso:country":"JP",
    "name:jpn_x_preferred":[
        "\u5411\u6c5f"
    ],
    "name:jpn_x_variant":[
        "\u3080\u304b\u3048",
        "\u30e0\u30ab\u30a8"
    ],
    "wof:name":"Mukae",
    "wof:placetype":"locality"
},
  "geometry": {"coordinates":[130.76778000000002,32.04682],"type":"Point"}
}