{
  "type": "Feature",
  "properties": {
    "gn:admin1_code":"28.0",
    "gn:admin2_code":"1855604.0",
    "gn:asciiname":"Takahicho",
    "gn:country_code":"JP",
    "gn:dem":125,
    "gn:feature_class":"P",
    "gn:feature_code":"PPL",
    "gn:name":"Takahich\u014d",
    "gn:population":0,
    "gn:timezone":"Asia/Tokyo",
    "iso:country":"JP",
    "name:jpn_x_preferred":[
        "\u9ad8\u6a0b\u753a"
    ],
    "name:und_x_variant":[
        "Takahich\u014d"
    ],
    "wof:name":"Takahicho",
    "wof:placetype":"locality"
},
  "geometry": {"coordinates":[135.85511,34.63261],"type":"Point"}
}