{
  "type": "Feature",
  "properties": {
    "gn:admin1_code":"37",
    "gn:admin2_code":"1851714.0",
    "gn:admin3_code":"22103.0",
    "gn:asciiname":"Yamahara",
    "gn:cc2":"JP",
    "gn:country_code":"JP",
    "gn:dem":5,
    "gn:feature_class":"P",
    "gn:feature_code":"PPL",
    "gn:name":"Yamahara",
    "gn:population":0,
    "gn:timezone":"Asia/Tokyo",
    "iso:country":"JP",
    "name:und_x_variant":[
        "Yambara",
        "Yamahara"
    ],
    "wof:name":"Yamahara",
    "wof:placetype":"locality"
},
  "geometry": {"coordinates":[138.46666999999999,35.03333],"type":"Point"}
}