{
  "type": "Feature",
  "properties": {
    "gn:admin1_code":"21.0",
    "gn:admin2_code":"7413152.0",
    "gn:asciiname":"Horikiri",
    "gn:country_code":"JP",
    "gn:dem":16,
    "gn:feature_class":"P",
    "gn:feature_code":"PPLL",
    "gn:name":"Horikiri",
    "gn:population":0,
    "gn:timezone":"Asia/Tokyo",
    "iso:country":"JP",
    "name:jpn_x_preferred":[
        "\u5800\u5207"
    ],
    "name:jpn_x_variant":[
        "\u307b\u308a\u304d\u308a",
        "\u30db\u30ea\u30ad\u30ea"
    ],
    "wof:name":"Horikiri",
    "wof:placetype":"locality"
},
  "geometry": {"coordinates":[130.70344,32.65013],"type":"Point"}
}