{
  "type": "Feature",
  "properties": {
    "gn:admin1_code":"12.0",
    "gn:admin2_code":"7428095.0",
    "gn:admin3_code":"1563.0",
    "gn:asciiname":"Hassen",
    "gn:country_code":"JP",
    "gn:dem":150,
    "gn:feature_class":"P",
    "gn:feature_code":"PPL",
    "gn:name":"Hassen",
    "gn:population":0,
    "gn:timezone":"Asia/Tokyo",
    "iso:country":"JP",
    "wof:name":"Hassen",
    "wof:placetype":"locality"
},
  "geometry": {"coordinates":[142.74194,44.51861],"type":"Point"}
}