{
  "type": "Feature",
  "properties": {
    "gn:admin1_code":"29",
    "gn:admin2_code":"1865200.0",
    "gn:asciiname":"Suginosawa",
    "gn:country_code":"JP",
    "gn:dem":732,
    "gn:feature_class":"P",
    "gn:feature_code":"PPL",
    "gn:name":"Suginosawa",
    "gn:population":0,
    "gn:timezone":"Asia/Tokyo",
    "iso:country":"JP",
    "name:jpn_x_preferred":[
        "\u6749\u91ce\u6ca2"
    ],
    "wof:name":"Suginosawa",
    "wof:placetype":"locality"
},
  "geometry": {"coordinates":[138.16006999999999,36.84945],"type":"Point"}
}