{
  "type": "Feature",
  "properties": {
    "gn:admin1_code":"18",
    "gn:admin2_code":"1853737.0",
    "gn:admin3_code":"46525.0",
    "gn:asciiname":"Saneku",
    "gn:country_code":"JP",
    "gn:dem":33,
    "gn:feature_class":"P",
    "gn:feature_code":"PPL",
    "gn:name":"Saneku",
    "gn:population":0,
    "gn:timezone":"Asia/Tokyo",
    "iso:country":"JP",
    "name:jpn_x_preferred":[
        "\u5b9f\u4e45"
    ],
    "wof:name":"Saneku",
    "wof:placetype":"locality"
},
  "geometry": {"coordinates":[129.18631999999999,28.185],"type":"Point"}
}