{
  "type": "Feature",
  "properties": {
    "gn:admin1_code":"19.0",
    "gn:admin2_code":"1853293.0",
    "gn:admin3_code":"14153.0",
    "gn:asciiname":"Shindogawara",
    "gn:country_code":"JP",
    "gn:dem":33,
    "gn:feature_class":"P",
    "gn:feature_code":"PPLL",
    "gn:name":"Shindogawara",
    "gn:population":0,
    "gn:timezone":"Asia/Tokyo",
    "iso:country":"JP",
    "name:jpn_x_preferred":[
        "\u65b0\u6238\u6cb3\u539f\u3000"
    ],
    "wof:name":"Shindogawara",
    "wof:placetype":"locality"
},
  "geometry": {"coordinates":[139.37963999999999,35.49394],"type":"Point"}
}