{
  "type": "Feature",
  "properties": {
    "gn:admin1_code":"19",
    "gn:admin2_code":"1856849.0",
    "gn:asciiname":"Makuchi",
    "gn:country_code":"JP",
    "gn:dem":15,
    "gn:feature_class":"P",
    "gn:feature_code":"PPL",
    "gn:name":"Makuchi",
    "gn:population":0,
    "gn:timezone":"Asia/Tokyo",
    "iso:country":"JP",
    "name:jpn_x_preferred":[
        "\u9593\u53e3"
    ],
    "name:jpn_x_variant":[
        "\u307e\u304f\u3061",
        "\u30de\u30af\u30c1"
    ],
    "name:und_x_variant":[
        "Maguchi",
        "Makuchi"
    ],
    "wof:name":"Makuchi",
    "wof:placetype":"locality"
},
  "geometry": {"coordinates":[139.67881,35.14619],"type":"Point"}
}