{
  "type": "Feature",
  "properties": {
    "gn:admin1_code":"23.0",
    "gn:admin2_code":"7417711.0",
    "gn:asciiname":"Anodacho",
    "gn:country_code":"JP",
    "gn:dem":44,
    "gn:feature_class":"P",
    "gn:feature_code":"PPL",
    "gn:name":"Anodach\u014d",
    "gn:population":0,
    "gn:timezone":"Asia/Tokyo",
    "iso:country":"JP",
    "name:jpn_x_preferred":[
        "\u963f\u91ce\u7530\u753a"
    ],
    "name:und_x_variant":[
        "Anodach\u014d"
    ],
    "wof:name":"Anodacho",
    "wof:placetype":"locality"
},
  "geometry": {"coordinates":[136.46485000000001,34.84472],"type":"Point"}
}