{
  "type": "Feature",
  "properties": {
    "iso:country":"JP",
    "name:eng_x_preferred":[
        "Kanzeonji 4 Chome"
    ],
    "name:eng_x_variant":[
        "Kanzeonji 4 Choume",
        "Kanzeonji 4 Chome"
    ],
    "name:jpn_x_preferred":[
        "\uff14\u4e01\u76ee"
    ],
    "name:jpn_x_variant":[
        "\u304b\u3093\u305c\u304a\u3093\u3058 \uff14\u3061\u3087\u3046\u3081",
        "\u89b3\u4e16\u97f3\u5bfa \uff14\u4e01\u76ee",
        "\uff14\u3061\u3087\u3046\u3081"
    ],
    "qs:gn_local":0,
    "qs:local_max":830,
    "qs:local_sum":2653,
    "qs:localhoods":9,
    "qs:name":"\uff14\u4e01\u76ee",
    "qs:name_adm0":"\u65e5\u672c",
    "qs:name_adm1":"\u798f\u5ca1\u770c",
    "qs:name_en":"Kanzeonji 4 Chome",
    "qs:name_lau":"\u89b3\u4e16\u97f3\u5bfa",
    "qs:name_local":"\u592a\u5bb0\u5e9c\u5e02",
    "qs:photo_max":48,
    "qs:photo_sum":94,
    "qs:placetype":"Suburb",
    "qs:quad_count":6,
    "qs:woe_adm0":23424856,
    "qs:woe_adm1":58646425,
    "qs:woe_adm2":0,
    "qs:woe_lau":28484546,
    "qs:woe_local":1117057,
    "qs:woe_ver":"7.10.0",
    "qs_pg:name":"\uff14\u4e01\u76ee",
    "qs_pg:name_adm0":"\u65e5\u672c",
    "qs_pg:name_adm1":"\u798f\u5ca1\u770c",
    "qs_pg:photos":93,
    "qs_pg:photos_1k":19,
    "qs_pg:photos_9k":1,
    "qs_pg:photos_9r":3,
    "qs_pg:photos_all":93,
    "qs_pg:photos_sr":3,
    "qs_pg:pop_sr":0,
    "qs_pg:qs_pg_placetype":"neighbourhood",
    "qs_pg:qs_pg_placetype_gp":"Suburb",
    "qs_pg:woe_adm0":23424856,
    "woe:adm0_id":23424856,
    "woe:name_adm0":"\u65e5\u672c",
    "woe:name_adm1":"\u798f\u5ca1\u770c",
    "woe:placetype":"Suburb",
    "wof:lang":[
        "jpn"
    ],
    "wof:name":"\uff14\u4e01\u76ee",
    "wof:placetype":"neighbourhood"
},
  "geometry": {"coordinates":[130.51665800000001,33.515816],"type":"Point"}
}