{
  "type": "Feature",
  "properties": {
    "gn:admin1_code":"33",
    "gn:admin2_code":"8300623.0",
    "gn:asciiname":"Yobukocho-odomo",
    "gn:country_code":"JP",
    "gn:dem":31,
    "gn:feature_class":"P",
    "gn:feature_code":"PPL",
    "gn:name":"Yobukoch\u014d-\u014ddomo",
    "gn:population":0,
    "gn:timezone":"Asia/Tokyo",
    "iso:country":"JP",
    "name:jpn_x_preferred":[
        "\u547c\u5b50\u753a\u5927\u53cb"
    ],
    "name:und_x_variant":[
        "Yobukoch\u014d-\u014ddomo",
        "\u014cdomo"
    ],
    "wof:name":"Yobukocho-odomo",
    "wof:placetype":"locality"
},
  "geometry": {"coordinates":[129.91301000000001,33.54035],"type":"Point"}
}