{
  "type": "Feature",
  "properties": {
    "gn:admin1_code":"07",
    "gn:admin2_code":"7407411.0",
    "gn:asciiname":"Kurogawa",
    "gn:country_code":"JP",
    "gn:dem":341,
    "gn:feature_class":"P",
    "gn:feature_code":"PPL",
    "gn:name":"Kurogawa",
    "gn:population":0,
    "gn:timezone":"Asia/Tokyo",
    "iso:country":"JP",
    "name:jpn_x_preferred":[
        "\u9ed2\u5ddd"
    ],
    "name:und_x_variant":[
        "Kurokawa"
    ],
    "wof:name":"Kurogawa",
    "wof:placetype":"locality"
},
  "geometry": {"coordinates":[130.76436000000001,33.41493],"type":"Point"}
}