{
  "type": "Feature",
  "properties": {
    "gn:admin1_code":"4.0",
    "gn:admin2_code":"1859468.0",
    "gn:asciiname":"Miyanoshiro",
    "gn:country_code":"JP",
    "gn:dem":70,
    "gn:feature_class":"P",
    "gn:feature_code":"PPLL",
    "gn:name":"Miyanoshiro",
    "gn:population":0,
    "gn:timezone":"Asia/Tokyo",
    "iso:country":"JP",
    "name:jpn_x_preferred":[
        "\u5bae\u30ce\u4ee3"
    ],
    "name:jpn_x_variant":[
        "\u307f\u3084\u306e\u3057\u308d",
        "\u30df\u30e4\u30ce\u30b7\u30ed"
    ],
    "wof:name":"Miyanoshiro",
    "wof:placetype":"locality"
},
  "geometry": {"coordinates":[140.07267999999999,35.27815],"type":"Point"}
}