{
  "type": "Feature",
  "properties": {
    "gn:admin1_code":"3.0",
    "gn:admin2_code":"2127674.0",
    "gn:asciiname":"Iyasawa",
    "gn:country_code":"JP",
    "gn:dem":66,
    "gn:feature_class":"P",
    "gn:feature_code":"PPL",
    "gn:name":"Iyasawa",
    "gn:population":0,
    "gn:timezone":"Asia/Tokyo",
    "iso:country":"JP",
    "name:jpn_x_preferred":[
        "\u4f0a\u8c37\u6ca2"
    ],
    "name:jpn_x_variant":[
        "\u3044\u3084\u3055\u308f",
        "\u30a4\u30e4\u30b5\u30ef"
    ],
    "wof:name":"Iyasawa",
    "wof:placetype":"locality"
},
  "geometry": {"coordinates":[141.262,40.66627],"type":"Point"}
}