{
  "type": "Feature",
  "properties": {
    "gn:admin1_code":"34.0",
    "gn:admin2_code":"1858728.0",
    "gn:asciiname":"Maehata",
    "gn:country_code":"JP",
    "gn:dem":3,
    "gn:feature_class":"P",
    "gn:feature_code":"PPL",
    "gn:name":"Maehata",
    "gn:population":0,
    "gn:timezone":"Asia/Tokyo",
    "iso:country":"JP",
    "name:jpn_x_preferred":[
        "\u524d\u7551"
    ],
    "wof:name":"Maehata",
    "wof:placetype":"locality"
},
  "geometry": {"coordinates":[139.82639,35.8952],"type":"Point"}
}