{
  "type": "Feature",
  "properties": {
    "gn:admin1_code":"12.0",
    "gn:admin2_code":"2129370.0",
    "gn:asciiname":"Futamata",
    "gn:country_code":"JP",
    "gn:dem":39,
    "gn:feature_class":"P",
    "gn:feature_code":"PPL",
    "gn:name":"Futamata",
    "gn:population":0,
    "gn:timezone":"Asia/Tokyo",
    "iso:country":"JP",
    "name:jpn_x_preferred":[
        "\u4e8c\u4fe3"
    ],
    "name:jpn_x_variant":[
        "\u3075\u305f\u307e\u305f",
        "\u30d5\u30bf\u30de\u30bf"
    ],
    "name:und_x_variant":[
        "Kami-ombetsu",
        "Futamata"
    ],
    "wof:name":"Futamata",
    "wof:placetype":"locality"
},
  "geometry": {"coordinates":[143.87762000000001,42.97095],"type":"Point"}
}