{
  "type": "Feature",
  "properties": {
    "gn:admin1_code":"21.0",
    "gn:admin2_code":"1864975.0",
    "gn:admin3_code":"43424.0",
    "gn:asciiname":"Nanbira",
    "gn:country_code":"JP",
    "gn:dem":698,
    "gn:feature_class":"P",
    "gn:feature_code":"PPLL",
    "gn:name":"Nanbira",
    "gn:population":0,
    "gn:timezone":"Asia/Tokyo",
    "iso:country":"JP",
    "name:jpn_x_preferred":[
        "\u5357\u5e73"
    ],
    "name:jpn_x_variant":[
        "\u306a\u3093\u3073\u3089",
        "\u30ca\u30f3\u30d3\u30e9"
    ],
    "wof:name":"Nanbira",
    "wof:placetype":"locality"
},
  "geometry": {"coordinates":[131.1206,33.11315],"type":"Point"}
}