{
  "type": "Feature",
  "properties": {
    "gn:admin1_code":"3.0",
    "gn:admin2_code":"2130200.0",
    "gn:asciiname":"Minamiruike",
    "gn:country_code":"JP",
    "gn:dem":13,
    "gn:feature_class":"P",
    "gn:feature_code":"PPL",
    "gn:name":"Minamiruike",
    "gn:population":0,
    "gn:timezone":"Asia/Tokyo",
    "iso:country":"JP",
    "name:jpn_x_preferred":[
        "\u5357\u985e\u5bb6"
    ],
    "name:jpn_x_variant":[
        "\u307f\u306a\u307f\u308b\u3044\u3051",
        "\u30df\u30ca\u30df\u30eb\u30a4\u30b1"
    ],
    "wof:name":"Minamiruike",
    "wof:placetype":"locality"
},
  "geometry": {"coordinates":[141.49975000000001,40.5047],"type":"Point"}
}