{
  "type": "Feature",
  "properties": {
    "gn:admin1_code":"19.0",
    "gn:admin2_code":"1862461.0",
    "gn:asciiname":"Tatsunocho",
    "gn:country_code":"JP",
    "gn:dem":8,
    "gn:feature_class":"P",
    "gn:feature_code":"PPL",
    "gn:name":"Tatsunoch\u014d",
    "gn:population":0,
    "gn:timezone":"Asia/Tokyo",
    "iso:country":"JP",
    "name:jpn_x_preferred":[
        "\u7acb\u91ce\u753a"
    ],
    "name:und_x_variant":[
        "Tatsunoch\u014d"
    ],
    "wof:name":"Tatsunocho",
    "wof:placetype":"locality"
},
  "geometry": {"coordinates":[139.34083999999999,35.33423],"type":"Point"}
}