{
  "type": "Feature",
  "properties": {
    "gn:admin1_code":"3.0",
    "gn:admin2_code":"2130200.0",
    "gn:asciiname":"Maeda",
    "gn:country_code":"JP",
    "gn:dem":7,
    "gn:feature_class":"P",
    "gn:feature_code":"PPL",
    "gn:name":"Maeda",
    "gn:population":0,
    "gn:timezone":"Asia/Tokyo",
    "iso:country":"JP",
    "name:deu_x_preferred":[
        "Maeda"
    ],
    "name:fra_x_preferred":[
        "Maeda"
    ],
    "name:jpn_x_preferred":[
        "\u524d\u7530"
    ],
    "name:jpn_x_variant":[
        "\u307e\u3048\u3060",
        "\u30de\u30a8\u30c0"
    ],
    "name:kor_x_preferred":[
        "\ub9c8\uc5d0\ub2e4"
    ],
    "name:rus_x_preferred":[
        "\u041c\u0430\u044d\u0434\u0430"
    ],
    "name:ukr_x_preferred":[
        "\u041c\u0430\u0435\u0434\u0430"
    ],
    "wof:name":"Maeda",
    "wof:placetype":"locality"
},
  "geometry": {"coordinates":[141.45178999999999,40.51681],"type":"Point"}
}