{
  "type": "Feature",
  "properties": {
    "gn:admin1_code":"7.0",
    "gn:admin2_code":"1851269.0",
    "gn:admin3_code":"40609.0",
    "gn:asciiname":"Tsunemitsu",
    "gn:country_code":"JP",
    "gn:dem":80,
    "gn:feature_class":"P",
    "gn:feature_code":"PPLL",
    "gn:name":"Tsunemitsu",
    "gn:population":0,
    "gn:timezone":"Asia/Tokyo",
    "iso:country":"JP",
    "name:jpn_x_preferred":[
        "\u5e38\u5149"
    ],
    "wof:name":"Tsunemitsu",
    "wof:placetype":"locality"
},
  "geometry": {"coordinates":[130.87911,33.60393],"type":"Point"}
}