{
  "type": "Feature",
  "properties": {
    "gn:admin1_code":"21.0",
    "gn:admin2_code":"1848441.0",
    "gn:asciiname":"Daira",
    "gn:country_code":"JP",
    "gn:dem":774,
    "gn:feature_class":"P",
    "gn:feature_code":"PPLL",
    "gn:name":"Daira",
    "gn:population":0,
    "gn:timezone":"Asia/Tokyo",
    "iso:country":"JP",
    "name:deu_x_preferred":[
        "Daira"
    ],
    "name:jpn_x_preferred":[
        "\u5e73"
    ],
    "name:jpn_x_variant":[
        "\u3060\u3044\u3089",
        "\u30c0\u30a4\u30e9"
    ],
    "name:nld_x_preferred":[
        "Daira"
    ],
    "wof:name":"Daira",
    "wof:placetype":"locality"
},
  "geometry": {"coordinates":[130.95029,32.5469],"type":"Point"}
}