{
  "type": "Feature",
  "properties": {
    "gn:admin1_code":"47.0",
    "gn:admin2_code":"7415821.0",
    "gn:asciiname":"Akamichi",
    "gn:country_code":"JP",
    "gn:dem":58,
    "gn:feature_class":"P",
    "gn:feature_code":"PPL",
    "gn:name":"Akamichi",
    "gn:population":0,
    "gn:timezone":"Asia/Tokyo",
    "iso:country":"JP",
    "name:jpn_x_preferred":[
        "\u8d64\u9053"
    ],
    "wof:name":"Akamichi",
    "wof:placetype":"locality"
},
  "geometry": {"coordinates":[127.82919,26.35965],"type":"Point"}
}