{
  "type": "Feature",
  "properties": {
    "gn:admin1_code":"7.0",
    "gn:admin2_code":"7407413.0",
    "gn:asciiname":"Higashiiwasaki",
    "gn:country_code":"JP",
    "gn:dem":26,
    "gn:feature_class":"P",
    "gn:feature_code":"PPLL",
    "gn:name":"Higashiiwasaki",
    "gn:population":0,
    "gn:timezone":"Asia/Tokyo",
    "iso:country":"JP",
    "name:jpn_x_preferred":[
        "\u6771\u5ca9\u5d0e"
    ],
    "wof:name":"Higashiiwasaki",
    "wof:placetype":"locality"
},
  "geometry": {"coordinates":[130.72218000000001,33.59678],"type":"Point"}
}