{
  "type": "Feature",
  "properties": {
    "iso:country":"JP",
    "name:eng_x_preferred":[
        "Tenjin 1 Chome"
    ],
    "name:eng_x_variant":[
        "Tenjin 1 Choume",
        "Tenjin 1 Chome"
    ],
    "name:jpn_x_preferred":[
        "\uff11\u4e01\u76ee"
    ],
    "name:jpn_x_variant":[
        "\u3066\u3093\u3058\u3093 \uff11\u3061\u3087\u3046\u3081",
        "\u5929\u795e \uff11\u4e01\u76ee",
        "\uff11\u3061\u3087\u3046\u3081"
    ],
    "name:unk_x_variant":[
        "\uff11\u4e01\u76ee"
    ],
    "qs:gn_adm0_cc":"JP",
    "qs:gn_local":1852899,
    "qs:gn_nam_loc":"\u4f50\u4e16\u4fdd\u5e02, \u9577\u5d0e\u770c, JP",
    "qs:gn_namadm1":"27",
    "qs:local_max":138,
    "qs:local_sum":139,
    "qs:localhoods":2,
    "qs:name":"\uff11\u4e01\u76ee",
    "qs:name_adm0":"\u65e5\u672c",
    "qs:name_adm1":"\u9577\u5d0e\u770c",
    "qs:name_en":"Tenjin 1 Chome",
    "qs:name_lau":"\u5929\u795e",
    "qs:name_local":"\u4f50\u4e16\u4fdd\u5e02",
    "qs:photo_max":79,
    "qs:photo_sum":138,
    "qs:placetype":"Suburb",
    "qs:quad_count":10,
    "qs:woe_adm0":23424856,
    "qs:woe_adm1":2345876,
    "qs:woe_adm2":0,
    "qs:woe_lau":28486883,
    "qs:woe_local":1118112,
    "qs:woe_ver":"7.10.0",
    "wof:lang":[
        "jpn"
    ],
    "wof:name":"\uff11\u4e01\u76ee",
    "wof:placetype":"neighbourhood"
},
  "geometry": {"coordinates":[129.72658100000001,33.163255],"type":"Point"}
}