{
  "type": "Feature",
  "properties": {
    "gn:admin1_code":"18.0",
    "gn:admin2_code":"7383991.0",
    "gn:asciiname":"Kyoshin",
    "gn:country_code":"JP",
    "gn:dem":179,
    "gn:feature_class":"P",
    "gn:feature_code":"PPLL",
    "gn:name":"Ky\u014dshin",
    "gn:population":0,
    "gn:timezone":"Asia/Tokyo",
    "iso:country":"JP",
    "name:jpn_x_preferred":[
        "\u5171\u9032"
    ],
    "name:jpn_x_variant":[
        "\u304d\u3087\u3046\u3057\u3093",
        "\u30ad\u30e7\u30a6\u30b7\u30f3"
    ],
    "name:und_x_variant":[
        "Ky\u014dshin"
    ],
    "wof:name":"Kyoshin",
    "wof:placetype":"locality"
},
  "geometry": {"coordinates":[130.65461000000002,31.9986],"type":"Point"}
}