{
  "type": "Feature",
  "properties": {
    "gn:admin1_code":"4.0",
    "gn:admin2_code":"7465521.0",
    "gn:asciiname":"Nenjin",
    "gn:country_code":"JP",
    "gn:dem":108,
    "gn:feature_class":"P",
    "gn:feature_code":"PPLL",
    "gn:name":"Nenjin",
    "gn:population":0,
    "gn:timezone":"Asia/Tokyo",
    "iso:country":"JP",
    "name:jpn_x_preferred":[
        "\u5b50\u795e"
    ],
    "name:jpn_x_variant":[
        "\u306d\u3093\u3058\u3093",
        "\u30cd\u30f3\u30b8\u30f3"
    ],
    "wof:name":"Nenjin",
    "wof:placetype":"locality"
},
  "geometry": {"coordinates":[139.93520000000001,35.05127],"type":"Point"}
}