{
  "type": "Feature",
  "properties": {
    "gn:admin1_code":"05",
    "gn:admin2_code":"1853240.0",
    "gn:asciiname":"Myoguchi",
    "gn:cc2":"JP",
    "gn:country_code":"JP",
    "gn:dem":43,
    "gn:feature_class":"P",
    "gn:feature_code":"PPL",
    "gn:name":"My\u014dguchi",
    "gn:population":0,
    "gn:timezone":"Asia/Tokyo",
    "iso:country":"JP",
    "name:und_x_variant":[
        "My\u014dkuchi",
        "My\u014dguchi"
    ],
    "wof:name":"Myoguchi",
    "wof:placetype":"locality"
},
  "geometry": {"coordinates":[133.08333000000002,33.88333],"type":"Point"}
}