{
  "type": "Feature",
  "properties": {
    "iso:country":"JP",
    "name:eng_x_preferred":[
        "Asakura Hei"
    ],
    "name:eng_x_variant":[
        "Asakura Asakura Hei",
        "Asakura Hei"
    ],
    "name:jpn_x_preferred":[
        "\u4e19"
    ],
    "name:jpn_x_variant":[
        "\u3042\u3055\u304f\u3089 \u3078\u3044",
        "\u3078\u3044",
        "\u671d\u5009 \u4e19"
    ],
    "qs:gn_local":0,
    "qs:local_max":565,
    "qs:local_sum":1354,
    "qs:localhoods":19,
    "qs:name":"\u4e19",
    "qs:name_adm0":"\u65e5\u672c",
    "qs:name_adm1":"\u9ad8\u77e5\u770c",
    "qs:name_en":"Asakura Hei",
    "qs:name_lau":"\u671d\u5009",
    "qs:name_local":"\u9ad8\u77e5\u5e02",
    "qs:photo_max":1,
    "qs:photo_sum":1,
    "qs:placetype":"Suburb",
    "qs:quad_count":1,
    "qs:woe_adm0":23424856,
    "qs:woe_adm1":2345869,
    "qs:woe_adm2":0,
    "qs:woe_lau":28480735,
    "qs:woe_local":1117548,
    "qs:woe_ver":"7.10.0",
    "wof:lang":[
        "jpn"
    ],
    "wof:name":"\u4e19",
    "wof:placetype":"neighbourhood"
},
  "geometry": {"coordinates":[133.47015400000001,33.571148],"type":"Point"}
}