{
  "type": "Feature",
  "properties": {
    "gn:admin1_code":"21.0",
    "gn:admin2_code":"7413153.0",
    "gn:asciiname":"Yokomachi",
    "gn:country_code":"JP",
    "gn:dem":89,
    "gn:feature_class":"P",
    "gn:feature_code":"PPLL",
    "gn:name":"Yokomachi",
    "gn:population":0,
    "gn:timezone":"Asia/Tokyo",
    "iso:country":"JP",
    "name:jpn_x_preferred":[
        "\u6a2a\u753a"
    ],
    "name:jpn_x_variant":[
        "\u3088\u3053\u307e\u3061",
        "\u30e8\u30b3\u30de\u30c1"
    ],
    "wof:name":"Yokomachi",
    "wof:placetype":"locality"
},
  "geometry": {"coordinates":[130.80002999999999,32.89103],"type":"Point"}
}