{
  "type": "Feature",
  "properties": {
    "gn:admin1_code":"4.0",
    "gn:admin2_code":"2112997.0",
    "gn:admin3_code":"12427.0",
    "gn:asciiname":"Kuramochi",
    "gn:country_code":"JP",
    "gn:dem":56,
    "gn:feature_class":"P",
    "gn:feature_code":"PPL",
    "gn:name":"Kuramochi",
    "gn:population":0,
    "gn:timezone":"Asia/Tokyo",
    "iso:country":"JP",
    "name:jpn_x_preferred":[
        "\u8535\u6301"
    ],
    "name:jpn_x_variant":[
        "\u304f\u3089\u3082\u3061",
        "\u30af\u30e9\u30e2\u30c1"
    ],
    "name:rus_x_preferred":[
        "\u041a\u0443\u0440\u0430\u043c\u043e\u0442\u0438"
    ],
    "wof:name":"Kuramochi",
    "wof:placetype":"locality"
},
  "geometry": {"coordinates":[140.21326999999999,35.38553],"type":"Point"}
}