{
  "type": "Feature",
  "properties": {
    "gn:admin1_code":"21.0",
    "gn:admin2_code":"1865358.0",
    "gn:asciiname":"Higashitatara",
    "gn:country_code":"JP",
    "gn:dem":19,
    "gn:feature_class":"P",
    "gn:feature_code":"PPLL",
    "gn:name":"Higashitatara",
    "gn:population":0,
    "gn:timezone":"Asia/Tokyo",
    "iso:country":"JP",
    "name:jpn_x_preferred":[
        "\u6771\u591a\u3005\u826f"
    ],
    "name:jpn_x_variant":[
        "\u3072\u304c\u3057\u305f\u305f\u3089",
        "\u30d2\u30ac\u30b7\u30bf\u30bf\u30e9"
    ],
    "wof:name":"Higashitatara",
    "wof:placetype":"locality"
},
  "geometry": {"coordinates":[130.09451999999999,32.2566],"type":"Point"}
}