{
  "type": "Feature",
  "properties": {
    "gn:admin1_code":"33",
    "gn:admin2_code":"7391358.0",
    "gn:admin3_code":"41424.0",
    "gn:asciiname":"Shuku",
    "gn:country_code":"JP",
    "gn:dem":3,
    "gn:feature_class":"P",
    "gn:feature_code":"PPLL",
    "gn:name":"Shuku",
    "gn:population":0,
    "gn:timezone":"Asia/Tokyo",
    "iso:country":"JP",
    "name:jpn_x_preferred":[
        "\u5bbf"
    ],
    "name:und_x_variant":[
        "Sarushi",
        "Shuku"
    ],
    "wof:name":"Shuku",
    "wof:placetype":"locality"
},
  "geometry": {"coordinates":[130.16631999999998,33.21993],"type":"Point"}
}