{
  "type": "Feature",
  "properties": {
    "gn:admin1_code":"24",
    "gn:admin2_code":"2111817.0",
    "gn:admin3_code":"4606.0",
    "gn:asciiname":"Tanoura",
    "gn:country_code":"JP",
    "gn:dem":23,
    "gn:feature_class":"P",
    "gn:feature_code":"PPLL",
    "gn:name":"Tanoura",
    "gn:population":0,
    "gn:timezone":"Asia/Tokyo",
    "iso:country":"JP",
    "name:jpn_x_preferred":[
        "\u7530\u306e\u6d66"
    ],
    "wof:name":"Tanoura",
    "wof:placetype":"locality"
},
  "geometry": {"coordinates":[141.53363000000004,38.74305],"type":"Point"}
}