{
  "type": "Feature",
  "properties": {
    "gn:admin1_code":"21.0",
    "gn:admin2_code":"1865358.0",
    "gn:asciiname":"Hashirasaki",
    "gn:country_code":"JP",
    "gn:dem":41,
    "gn:feature_class":"P",
    "gn:feature_code":"PPLL",
    "gn:name":"Hashirasaki",
    "gn:population":0,
    "gn:timezone":"Asia/Tokyo",
    "iso:country":"JP",
    "name:jpn_x_preferred":[
        "\u67f1\u5d0e"
    ],
    "name:jpn_x_variant":[
        "\u306f\u3057\u3089\u3055\u304d",
        "\u30cf\u30b7\u30e9\u30b5\u30ad"
    ],
    "wof:name":"Hashirasaki",
    "wof:placetype":"locality"
},
  "geometry": {"coordinates":[130.18440000000001,32.36704],"type":"Point"}
}