{
  "type": "Feature",
  "properties": {
    "gn:admin1_code":"21.0",
    "gn:admin2_code":"1850743.0",
    "gn:asciiname":"Enokibaru",
    "gn:country_code":"JP",
    "gn:dem":49,
    "gn:feature_class":"P",
    "gn:feature_code":"PPLL",
    "gn:name":"Enokibaru",
    "gn:population":0,
    "gn:timezone":"Asia/Tokyo",
    "iso:country":"JP",
    "name:jpn_x_preferred":[
        "\u698e\u539f"
    ],
    "name:jpn_x_variant":[
        "\u3048\u306e\u304d\u3070\u308b",
        "\u30a8\u30ce\u30ad\u30d0\u30eb"
    ],
    "wof:name":"Enokibaru",
    "wof:placetype":"locality"
},
  "geometry": {"coordinates":[130.58989,32.92151],"type":"Point"}
}