{
  "type": "Feature",
  "properties": {
    "gn:admin1_code":"23.0",
    "gn:admin2_code":"1857496.0",
    "gn:asciiname":"Kojiyama",
    "gn:country_code":"JP",
    "gn:dem":237,
    "gn:feature_class":"P",
    "gn:feature_code":"PPLL",
    "gn:name":"K\u014djiyama",
    "gn:population":0,
    "gn:timezone":"Asia/Tokyo",
    "iso:country":"JP",
    "name:jpn_x_preferred":[
        "\u795e\u8def\u5c71"
    ],
    "name:und_x_variant":[
        "K\u014djiyama"
    ],
    "wof:name":"Kojiyama",
    "wof:placetype":"locality"
},
  "geometry": {"coordinates":[136.39424,34.48942],"type":"Point"}
}