{
  "type": "Feature",
  "properties": {
    "gn:country":"JP",
    "gn:fcode":"ADM3",
    "gn:pop":0,
    "iso:country":"JP",
    "name:jpn_x_preferred":[
        "\u5c71\u5f62\u6751"
    ],
    "name:jpn_x_variant":[
        "\u3084\u307e\u304c\u305f\u3080\u3089"
    ],
    "name:unk_x_variant":[
        "Yamagata Mura"
    ],
    "qs:name":"Yamagata-mura",
    "qs:photos_9r":0,
    "qs:photos_sr":0,
    "qs:pop_sr":"0",
    "wof:name":"Yamagata-mura",
    "wof:placetype":"localadmin",
    "wof:population":0
},
  "geometry": {"coordinates":[137.86231000000001,36.16084],"type":"Point"}
}