{
  "type": "Feature",
  "properties": {
    "gn:admin1_code":"8.0",
    "gn:admin2_code":"2112139.0",
    "gn:asciiname":"Konanmachi-fukura",
    "gn:country_code":"JP",
    "gn:dem":529,
    "gn:feature_class":"P",
    "gn:feature_code":"PPL",
    "gn:name":"Konanmachi-fukura",
    "gn:population":0,
    "gn:timezone":"Asia/Tokyo",
    "iso:country":"JP",
    "name:jpn_x_preferred":[
        "\u6e56\u5357\u753a\u798f\u826f"
    ],
    "name:und_x_variant":[
        "Fukura"
    ],
    "wof:name":"Konanmachi-fukura",
    "wof:placetype":"locality"
},
  "geometry": {"coordinates":[140.08729,37.39311],"type":"Point"}
}