{
  "type": "Feature",
  "properties": {
    "gn:admin1_code":"32.0",
    "gn:admin2_code":"1852716.0",
    "gn:admin3_code":"27361.0",
    "gn:asciiname":"Tsubasagaoka-nishi",
    "gn:country_code":"JP",
    "gn:dem":127,
    "gn:feature_class":"P",
    "gn:feature_code":"PPL",
    "gn:name":"Tsubasagaoka-nishi",
    "gn:population":0,
    "gn:timezone":"Asia/Tokyo",
    "iso:country":"JP",
    "name:jpn_x_preferred":[
        "\u3064\u3070\u3055\u304c\u4e18\u897f"
    ],
    "wof:name":"Tsubasagaoka-nishi",
    "wof:placetype":"locality"
},
  "geometry": {"coordinates":[135.36888999999999,34.38401],"type":"Point"}
}