{
  "type": "Feature",
  "properties": {
    "gn:admin1_code":"12.0",
    "gn:admin2_code":"7428083.0",
    "gn:admin3_code":"1610.0",
    "gn:asciiname":"Takami",
    "gn:country_code":"JP",
    "gn:dem":210,
    "gn:feature_class":"P",
    "gn:feature_code":"PPL",
    "gn:name":"Takami",
    "gn:population":0,
    "gn:timezone":"Asia/Tokyo",
    "iso:country":"JP",
    "wof:name":"Takami",
    "wof:placetype":"locality"
},
  "geometry": {"coordinates":[142.68333000000001,42.45],"type":"Point"}
}