{
  "type": "Feature",
  "properties": {
    "gn:admin1_code":"40.0",
    "gn:admin2_code":"8304376.0",
    "gn:asciiname":"Nishitokyo",
    "gn:country_code":"JP",
    "gn:dem":58,
    "gn:feature_class":"P",
    "gn:feature_code":"PPLA2",
    "gn:name":"Nishit\u014dky\u014d",
    "gn:population":0,
    "gn:timezone":"Asia/Tokyo",
    "iso:country":"JP",
    "name:jpn_x_preferred":[
        "\u897f\u6771\u4eac"
    ],
    "wof:name":"Nishitokyo",
    "wof:placetype":"locality"
},
  "geometry": {"coordinates":[139.54761000000002,35.73355],"type":"Point"}
}