{
  "type": "Feature",
  "properties": {
    "iso:country":"JP",
    "name:jpn_x_preferred":[
        "\uff08\u4e01\u76ee\u306a\u3057\uff09"
    ],
    "name:unk_x_variant":[
        "\uff08\u4e01\u76ee\u306a\u3057\uff09"
    ],
    "qs:gn_local":0,
    "qs:local_max":183,
    "qs:local_sum":240,
    "qs:localhoods":3,
    "qs:name":"\uff08\u4e01\u76ee\u306a\u3057\uff09",
    "qs:name_adm0":"\u65e5\u672c",
    "qs:name_adm1":"\u5e83\u5cf6\u770c",
    "qs:name_lau":"\u5c71\u624b\u753a",
    "qs:name_local":"\u798f\u5c71\u5e02",
    "qs:photo_max":32,
    "qs:photo_sum":48,
    "qs:placetype":"Suburb",
    "qs:quad_count":4,
    "qs:woe_adm0":23424856,
    "qs:woe_adm1":2345861,
    "qs:woe_adm2":0,
    "qs:woe_lau":28474809,
    "qs:woe_local":1117108,
    "qs:woe_ver":"7.10.0",
    "wof:lang":[
        "jpn"
    ],
    "wof:name":"\uff08\u4e01\u76ee\u306a\u3057\uff09",
    "wof:placetype":"neighbourhood"
},
  "geometry": {"coordinates":[133.314571,34.491324],"type":"Point"}
}