{
  "type": "Feature",
  "properties": {
    "gn:admin1_code":"19.0",
    "gn:admin2_code":"1864091.0",
    "gn:asciiname":"Gotanda",
    "gn:country_code":"JP",
    "gn:dem":16,
    "gn:feature_class":"P",
    "gn:feature_code":"PPLL",
    "gn:name":"Gotanda",
    "gn:population":0,
    "gn:timezone":"Asia/Tokyo",
    "iso:country":"JP",
    "name:fas_x_preferred":[
        "\u06af\u0648\u062a\u0627\u0646\u062f\u0627"
    ],
    "name:fra_x_preferred":[
        "Gotanda"
    ],
    "name:jpn_x_preferred":[
        "\u4e94\u53cd\u7530"
    ],
    "name:kor_x_preferred":[
        "\uace0\ud0c4\ub2e4"
    ],
    "name:rus_x_preferred":[
        "\u0413\u043e\u0442\u0430\u043d\u0434\u0430"
    ],
    "name:zho_x_preferred":[
        "\u4e94\u53cd\u7530"
    ],
    "wof:name":"Gotanda",
    "wof:placetype":"locality"
},
  "geometry": {"coordinates":[139.45331999999999,35.36828],"type":"Point"}
}