{
  "type": "Feature",
  "properties": {
    "gn:admin1_code":"29.0",
    "gn:admin2_code":"1865200.0",
    "gn:asciiname":"Higashinagamori",
    "gn:country_code":"JP",
    "gn:dem":107,
    "gn:feature_class":"P",
    "gn:feature_code":"PPL",
    "gn:name":"Higashinagamori",
    "gn:population":0,
    "gn:timezone":"Asia/Tokyo",
    "iso:country":"JP",
    "name:jpn_x_preferred":[
        "\u6771\u9577\u68ee"
    ],
    "wof:name":"Higashinagamori",
    "wof:placetype":"locality"
},
  "geometry": {"coordinates":[138.23005000000001,37.02302],"type":"Point"}
}