{
  "type": "Feature",
  "properties": {
    "gn:admin1_code":"7.0",
    "gn:admin2_code":"1859874.0",
    "gn:admin3_code":"40344.0",
    "gn:asciiname":"Koueki",
    "gn:country_code":"JP",
    "gn:dem":31,
    "gn:feature_class":"P",
    "gn:feature_code":"PPLL",
    "gn:name":"K\u014dueki",
    "gn:population":0,
    "gn:timezone":"Asia/Tokyo",
    "iso:country":"JP",
    "name:jpn_x_preferred":[
        "\u7532\u690d\u6728"
    ],
    "name:und_x_variant":[
        "K\u014dueki"
    ],
    "wof:name":"Koueki",
    "wof:placetype":"locality"
},
  "geometry": {"coordinates":[130.50333000000001,33.59689],"type":"Point"}
}