{
  "type": "Feature",
  "properties": {
    "gn:admin1_code":"4.0",
    "gn:admin2_code":"2110982.0",
    "gn:asciiname":"Tamano",
    "gn:country_code":"JP",
    "gn:dem":58,
    "gn:feature_class":"P",
    "gn:feature_code":"PPL",
    "gn:name":"Tamano",
    "gn:population":0,
    "gn:timezone":"Asia/Tokyo",
    "iso:country":"JP",
    "name:ara_x_preferred":[
        "\u062a\u0627\u0645\u0627\u0646\u0648"
    ],
    "name:ceb_x_preferred":[
        "Tamano Shi"
    ],
    "name:deu_x_preferred":[
        "Tamano"
    ],
    "name:fas_x_preferred":[
        "\u062a\u0627\u0645\u0627\u0646\u0648"
    ],
    "name:fin_x_preferred":[
        "Tamano"
    ],
    "name:fra_x_preferred":[
        "Tamano"
    ],
    "name:glg_x_preferred":[
        "Tamano"
    ],
    "name:ita_x_preferred":[
        "Tamano"
    ],
    "name:jpn_x_preferred":[
        "\u7389\u91ce"
    ],
    "name:jpn_x_variant":[
        "\u305f\u307e\u306e",
        "\u30bf\u30de\u30ce",
        "\u7389\u91ce\u5e02"
    ],
    "name:kor_x_preferred":[
        "\ub2e4\ub9c8\ub178\uc2dc"
    ],
    "name:mlg_x_preferred":[
        "Tamano"
    ],
    "name:mzn_x_preferred":[
        "\u062a\u0627\u0645\u0627\u0646\u0648"
    ],
    "name:nld_x_preferred":[
        "Tamano"
    ],
    "name:pol_x_preferred":[
        "Tamano"
    ],
    "name:por_x_preferred":[
        "Tamano"
    ],
    "name:ron_x_preferred":[
        "Tamano"
    ],
    "name:rus_x_preferred":[
        "\u0422\u0430\u043c\u0430\u043d\u043e"
    ],
    "name:spa_x_preferred":[
        "Tamano"
    ],
    "name:swe_x_preferred":[
        "Tamano"
    ],
    "name:tgk_x_preferred":[
        "\u0422\u0430\u043c\u0430\u043d\u043e"
    ],
    "name:tgl_x_preferred":[
        "Tamano"
    ],
    "name:tur_x_preferred":[
        "Tamano"
    ],
    "name:ukr_x_preferred":[
        "\u0422\u0430\u043c\u0430\u043d\u043e"
    ],
    "name:vie_x_preferred":[
        "Tamano"
    ],
    "name:war_x_preferred":[
        "Tamano"
    ],
    "name:zho_x_preferred":[
        "\u7389\u91ce\u5e02"
    ],
    "wof:name":"Tamano",
    "wof:placetype":"locality"
},
  "geometry": {"coordinates":[140.00388999999998,35.36685],"type":"Point"}
}