{
  "type": "Feature",
  "properties": {
    "gn:admin1_code":"4.0",
    "gn:admin2_code":"2110982.0",
    "gn:asciiname":"Tamano",
    "gn:country_code":"JP",
    "gn:dem":58,
    "gn:feature_class":"P",
    "gn:feature_code":"PPL",
    "gn:name":"Tamano",
    "gn:population":0,
    "gn:timezone":"Asia/Tokyo",
    "iso:country":"JP",
    "name:jpn_x_preferred":[
        "\u7389\u91ce"
    ],
    "name:jpn_x_variant":[
        "\u305f\u307e\u306e",
        "\u30bf\u30de\u30ce"
    ],
    "wof:name":"Tamano",
    "wof:placetype":"locality"
},
  "geometry": {"coordinates":[140.00388999999998,35.36685],"type":"Point"}
}