{
  "type": "Feature",
  "properties": {
    "gn:admin1_code":"21.0",
    "gn:admin2_code":"1865358.0",
    "gn:asciiname":"Tashiro",
    "gn:country_code":"JP",
    "gn:dem":125,
    "gn:feature_class":"P",
    "gn:feature_code":"PPLL",
    "gn:name":"Tashiro",
    "gn:population":0,
    "gn:timezone":"Asia/Tokyo",
    "iso:country":"JP",
    "name:jpn_x_preferred":[
        "\u7530\u4ee3"
    ],
    "name:jpn_x_variant":[
        "\u305f\u3057\u308d",
        "\u30bf\u30b7\u30ed"
    ],
    "wof:name":"Tashiro",
    "wof:placetype":"locality"
},
  "geometry": {"coordinates":[129.97897,32.35758],"type":"Point"}
}