{
  "type": "Feature",
  "properties": {
    "gn:admin1_code":"2.0",
    "gn:admin2_code":"2129594.0",
    "gn:admin3_code":"5303.0",
    "gn:asciiname":"Hosogoe",
    "gn:country_code":"JP",
    "gn:dem":182,
    "gn:feature_class":"P",
    "gn:feature_code":"PPLL",
    "gn:name":"Hosogoe",
    "gn:population":0,
    "gn:timezone":"Asia/Tokyo",
    "iso:country":"JP",
    "name:jpn_x_preferred":[
        "\u7d30\u8d8a"
    ],
    "name:jpn_x_variant":[
        "\u307b\u305d\u3054\u3048",
        "\u30db\u30bd\u30b4\u30a8"
    ],
    "wof:name":"Hosogoe",
    "wof:placetype":"locality"
},
  "geometry": {"coordinates":[140.73719,40.3434],"type":"Point"}
}