{
  "type": "Feature",
  "properties": {
    "gn:admin1_code":"21.0",
    "gn:admin2_code":"7412708.0",
    "gn:admin3_code":"43510.0",
    "gn:asciiname":"Yanase",
    "gn:country_code":"JP",
    "gn:dem":122,
    "gn:feature_class":"P",
    "gn:feature_code":"PPL",
    "gn:name":"Yanase",
    "gn:population":0,
    "gn:timezone":"Asia/Tokyo",
    "iso:country":"JP",
    "name:deu_x_preferred":[
        "Yanase"
    ],
    "name:jpn_x_preferred":[
        "\u67f3\u702c"
    ],
    "name:nds_x_preferred":[
        "Yanase"
    ],
    "wof:name":"Yanase",
    "wof:placetype":"locality"
},
  "geometry": {"coordinates":[130.79384999999999,32.21923],"type":"Point"}
}