{
  "type": "Feature",
  "properties": {
    "gn:admin1_code":"29.0",
    "gn:admin2_code":"1856195.0",
    "gn:asciiname":"Kamegaimachi",
    "gn:country_code":"JP",
    "gn:dem":13,
    "gn:feature_class":"P",
    "gn:feature_code":"PPL",
    "gn:name":"Kamegaimachi",
    "gn:population":0,
    "gn:timezone":"Asia/Tokyo",
    "iso:country":"JP",
    "name:jpn_x_preferred":[
        "\u4e80\u8c9d\u753a"
    ],
    "wof:name":"Kamegaimachi",
    "wof:placetype":"locality"
},
  "geometry": {"coordinates":[138.88168999999999,37.47613],"type":"Point"}
}