{
  "type": "Feature",
  "properties": {
    "gn:admin1_code":"29",
    "gn:admin2_code":"1849786.0",
    "gn:asciiname":"Aozu",
    "gn:country_code":"JP",
    "gn:dem":10,
    "gn:feature_class":"P",
    "gn:feature_code":"PPL",
    "gn:name":"A\u014dzu",
    "gn:population":0,
    "gn:timezone":"Asia/Tokyo",
    "iso:country":"JP",
    "name:jpn_x_preferred":[
        "\u7c9f\u751f\u6d25"
    ],
    "name:und_x_variant":[
        "Okutsu",
        "Aouzu",
        "A\u014dzu"
    ],
    "wof:name":"Aozu",
    "wof:placetype":"locality"
},
  "geometry": {"coordinates":[138.86667,37.65],"type":"Point"}
}