{
  "type": "Feature",
  "properties": {
    "gn:admin1_code":"33.0",
    "gn:admin2_code":"1850771.0",
    "gn:asciiname":"Funayama",
    "gn:country_code":"JP",
    "gn:dem":396,
    "gn:feature_class":"P",
    "gn:feature_code":"PPLL",
    "gn:name":"Funayama",
    "gn:population":0,
    "gn:timezone":"Asia/Tokyo",
    "iso:country":"JP",
    "name:jpn_x_preferred":[
        "\u8239\u5c71"
    ],
    "wof:name":"Funayama",
    "wof:placetype":"locality"
},
  "geometry": {"coordinates":[130.05786000000001,33.28446],"type":"Point"}
}