{
  "type": "Feature",
  "properties": {
    "gn:admin1_code":"32.0",
    "gn:admin2_code":"1853167.0",
    "gn:admin3_code":"27146.0",
    "gn:asciiname":"Mozu-honmachi",
    "gn:country_code":"JP",
    "gn:dem":20,
    "gn:feature_class":"P",
    "gn:feature_code":"PPL",
    "gn:name":"Mozu-honmachi",
    "gn:population":0,
    "gn:timezone":"Asia/Tokyo",
    "iso:country":"JP",
    "name:jpn_x_preferred":[
        "\u767e\u820c\u9ce5\u672c\u753a"
    ],
    "wof:name":"Mozu-honmachi",
    "wof:placetype":"locality"
},
  "geometry": {"coordinates":[135.48766000000001,34.55492],"type":"Point"}
}