{
  "type": "Feature",
  "properties": {
    "gn:admin1_code":"4.0",
    "gn:admin2_code":"1859468.0",
    "gn:asciiname":"Hirata",
    "gn:country_code":"JP",
    "gn:dem":54,
    "gn:feature_class":"P",
    "gn:feature_code":"PPL",
    "gn:name":"Hirata",
    "gn:population":0,
    "gn:timezone":"Asia/Tokyo",
    "iso:country":"JP",
    "name:deu_x_preferred":[
        "Hirata"
    ],
    "name:fra_x_preferred":[
        "Hirata"
    ],
    "name:jpn_x_preferred":[
        "\u5e73\u7530"
    ],
    "name:jpn_x_variant":[
        "\u3072\u3089\u305f",
        "\u30d2\u30e9\u30bf"
    ],
    "name:kor_x_preferred":[
        "\ud788\ub77c\ud0c0"
    ],
    "wof:name":"Hirata",
    "wof:placetype":"locality"
},
  "geometry": {"coordinates":[140.08158,35.32437],"type":"Point"}
}