{
  "type": "Feature",
  "properties": {
    "gn:admin1_code":"21.0",
    "gn:admin2_code":"7412705.0",
    "gn:admin3_code":"43482.0",
    "gn:asciiname":"Okoba",
    "gn:country_code":"JP",
    "gn:dem":48,
    "gn:feature_class":"P",
    "gn:feature_code":"PPLL",
    "gn:name":"\u014ckoba",
    "gn:population":0,
    "gn:timezone":"Asia/Tokyo",
    "iso:country":"JP",
    "name:jpn_x_preferred":[
        "\u5927\u6728\u5834"
    ],
    "name:und_x_variant":[
        "\u014ckoba"
    ],
    "wof:name":"Okoba",
    "wof:placetype":"locality"
},
  "geometry": {"coordinates":[130.52423000000002,32.35116],"type":"Point"}
}