{
  "type": "Feature",
  "properties": {
    "gn:admin1_code":"34.0",
    "gn:admin2_code":"1863058.0",
    "gn:asciiname":"Nakanohara",
    "gn:country_code":"JP",
    "gn:dem":17,
    "gn:feature_class":"P",
    "gn:feature_code":"PPLL",
    "gn:name":"Nakanohara",
    "gn:population":0,
    "gn:timezone":"Asia/Tokyo",
    "iso:country":"JP",
    "name:jpn_x_preferred":[
        "\u4e2d\u91ce\u539f"
    ],
    "name:jpn_x_variant":[
        "\u306a\u304b\u306e\u306f\u3089",
        "\u30ca\u30ab\u30ce\u30cf\u30e9"
    ],
    "wof:name":"Nakanohara",
    "wof:placetype":"locality"
},
  "geometry": {"coordinates":[139.66884999999999,35.99103],"type":"Point"}
}