{
  "type": "Feature",
  "properties": {
    "gn:admin1_code":"19.0",
    "gn:admin2_code":"1855966.0",
    "gn:admin3_code":"14342.0",
    "gn:asciiname":"Kitashindo",
    "gn:country_code":"JP",
    "gn:dem":28,
    "gn:feature_class":"P",
    "gn:feature_code":"PPLL",
    "gn:name":"Kitashind\u014d",
    "gn:population":0,
    "gn:timezone":"Asia/Tokyo",
    "iso:country":"JP",
    "name:jpn_x_preferred":[
        "\u5317\u65b0\u9053"
    ],
    "name:und_x_variant":[
        "Kitashind\u014d"
    ],
    "wof:name":"Kitashindo",
    "wof:placetype":"locality"
},
  "geometry": {"coordinates":[139.25474,35.30721],"type":"Point"}
}