{
  "type": "Feature",
  "properties": {
    "gn:admin1_code":"08",
    "gn:admin2_code":"2112535.0",
    "gn:asciiname":"Towada",
    "gn:country_code":"JP",
    "gn:dem":494,
    "gn:feature_class":"P",
    "gn:feature_code":"PPL",
    "gn:name":"Towada",
    "gn:population":0,
    "gn:timezone":"Asia/Tokyo",
    "iso:country":"JP",
    "name:jpn_x_preferred":[
        "\u6238\u6e21"
    ],
    "name:und_x_variant":[
        "Towata",
        "Towada"
    ],
    "wof:name":"Towada",
    "wof:placetype":"locality"
},
  "geometry": {"coordinates":[140.84831,37.24269],"type":"Point"}
}