{
  "type": "Feature",
  "properties": {
    "iso:country":"JP",
    "name:eng_x_preferred":[
        "Shinochoumahoriekimae 2 Chome"
    ],
    "name:eng_x_variant":[
        "Shinochouumahoriekimae 2 Choume",
        "Shinochoumahoriekimae 2 Chome"
    ],
    "name:jpn_x_preferred":[
        "\uff12\u4e01\u76ee"
    ],
    "name:jpn_x_variant":[
        "\u3057\u306e\u3061\u3087\u3046\u3046\u307e\u307b\u308a\u3048\u304d\u307e\u3048 \uff12\u3061\u3087\u3046\u3081",
        "\u7be0\u753a\u99ac\u5800\u99c5\u524d \uff12\u4e01\u76ee",
        "\uff12\u3061\u3087\u3046\u3081"
    ],
    "name:unk_x_variant":[
        "\uff12\u4e01\u76ee"
    ],
    "qs:gn_local":0,
    "qs:local_max":252,
    "qs:local_sum":835,
    "qs:localhoods":7,
    "qs:name":"\uff12\u4e01\u76ee",
    "qs:name_adm0":"\u65e5\u672c",
    "qs:name_adm1":"\u4eac\u90fd\u5e9c",
    "qs:name_en":"Shinochoumahoriekimae 2 Chome",
    "qs:name_lau":"\u7be0\u753a\u99ac\u5800\u99c5\u524d",
    "qs:name_local":"\u4e80\u5ca1\u5e02",
    "qs:photo_max":20,
    "qs:photo_sum":111,
    "qs:placetype":"Suburb",
    "qs:quad_count":13,
    "qs:woe_adm0":23424856,
    "qs:woe_adm1":2345871,
    "qs:woe_adm2":0,
    "qs:woe_lau":28455586,
    "qs:woe_local":1117403,
    "qs:woe_ver":"7.10.0",
    "wof:lang":[
        "jpn"
    ],
    "wof:name":"\uff12\u4e01\u76ee",
    "wof:placetype":"neighbourhood"
},
  "geometry": {"coordinates":[135.60280399999999,35.012569],"type":"Point"}
}