{
  "type": "Feature",
  "properties": {
    "gn:admin1_code":"7.0",
    "gn:admin2_code":"1848572.0",
    "gn:asciiname":"Nanatsue",
    "gn:country_code":"JP",
    "gn:dem":0,
    "gn:feature_class":"P",
    "gn:feature_code":"PPL",
    "gn:name":"Nanatsue",
    "gn:population":0,
    "gn:timezone":"Asia/Tokyo",
    "iso:country":"JP",
    "name:jpn_x_preferred":[
        "\u4e03\u30c3\u5bb6"
    ],
    "wof:name":"Nanatsue",
    "wof:placetype":"locality"
},
  "geometry": {"coordinates":[130.36983000000001,33.16651],"type":"Point"}
}