{
  "type": "Feature",
  "properties": {
    "gn:admin1_code":"4.0",
    "gn:admin2_code":"7465521.0",
    "gn:asciiname":"Ino",
    "gn:country_code":"JP",
    "gn:dem":60,
    "gn:feature_class":"P",
    "gn:feature_code":"PPL",
    "gn:name":"Ino",
    "gn:population":0,
    "gn:timezone":"Asia/Tokyo",
    "iso:country":"JP",
    "name:bul_x_preferred":[
        "\u0418\u043d\u043e"
    ],
    "name:ceb_x_preferred":[
        "Ino"
    ],
    "name:fin_x_preferred":[
        "Ino"
    ],
    "name:fra_x_preferred":[
        "Ino"
    ],
    "name:heb_x_preferred":[
        "\u05d0\u05d9\u05e0\u05d5"
    ],
    "name:jpn_x_preferred":[
        "\u4e95\u91ce"
    ],
    "name:jpn_x_variant":[
        "\u3044\u306e",
        "\u30a4\u30ce"
    ],
    "name:lat_x_preferred":[
        "Ino"
    ],
    "name:mlg_x_preferred":[
        "Ino"
    ],
    "name:nld_x_preferred":[
        "Ino"
    ],
    "name:por_x_preferred":[
        "Ino"
    ],
    "name:rus_x_preferred":[
        "\u0418\u043d\u043e"
    ],
    "name:swe_x_preferred":[
        "Ino"
    ],
    "name:ukr_x_preferred":[
        "\u0406\u043d\u043e"
    ],
    "wof:name":"Ino",
    "wof:placetype":"locality"
},
  "geometry": {"coordinates":[139.89358999999999,35.10476],"type":"Point"}
}