{
  "type": "Feature",
  "properties": {
    "gn:admin1_code":"4.0",
    "gn:admin2_code":"7465521.0",
    "gn:asciiname":"Ino",
    "gn:country_code":"JP",
    "gn:dem":60,
    "gn:feature_class":"P",
    "gn:feature_code":"PPL",
    "gn:name":"Ino",
    "gn:population":0,
    "gn:timezone":"Asia/Tokyo",
    "iso:country":"JP",
    "name:jpn_x_preferred":[
        "\u4e95\u91ce"
    ],
    "name:jpn_x_variant":[
        "\u3044\u306e",
        "\u30a4\u30ce"
    ],
    "wof:name":"Ino",
    "wof:placetype":"locality"
},
  "geometry": {"coordinates":[139.89358999999999,35.10476],"type":"Point"}
}