{
  "type": "Feature",
  "properties": {
    "gn:admin1_code":"21.0",
    "gn:admin2_code":"1849062.0",
    "gn:asciiname":"Nakabase",
    "gn:country_code":"JP",
    "gn:dem":3,
    "gn:feature_class":"P",
    "gn:feature_code":"PPLL",
    "gn:name":"Nakabase",
    "gn:population":0,
    "gn:timezone":"Asia/Tokyo",
    "iso:country":"JP",
    "name:jpn_x_preferred":[
        "\u4e2d\u6a4b"
    ],
    "name:jpn_x_variant":[
        "\u306a\u304b\u3070\u305b",
        "\u30ca\u30ab\u30d0\u30bb"
    ],
    "wof:name":"Nakabase",
    "wof:placetype":"locality"
},
  "geometry": {"coordinates":[130.67559,32.69528],"type":"Point"}
}