{
  "type": "Feature",
  "properties": {
    "gn:admin1_code":"4.0",
    "gn:admin2_code":"2112557.0",
    "gn:admin3_code":"12441.0",
    "gn:asciiname":"Nishibeta",
    "gn:country_code":"JP",
    "gn:dem":34,
    "gn:feature_class":"P",
    "gn:feature_code":"PPL",
    "gn:name":"Nishibeta",
    "gn:population":0,
    "gn:timezone":"Asia/Tokyo",
    "iso:country":"JP",
    "name:jpn_x_preferred":[
        "\u897f\u90e8\u7530"
    ],
    "name:jpn_x_variant":[
        "\u306b\u3057\u3079\u305f",
        "\u30cb\u30b7\u30d9\u30bf"
    ],
    "wof:name":"Nishibeta",
    "wof:placetype":"locality"
},
  "geometry": {"coordinates":[140.23677000000001,35.2754],"type":"Point"}
}