{
  "type": "Feature",
  "properties": {
    "gn:admin1_code":"19.0",
    "gn:admin2_code":"1865011.0",
    "gn:admin3_code":"14364.0",
    "gn:asciiname":"Harakochi",
    "gn:country_code":"JP",
    "gn:dem":79,
    "gn:feature_class":"P",
    "gn:feature_code":"PPLL",
    "gn:name":"Harak\u014dchi",
    "gn:population":0,
    "gn:timezone":"Asia/Tokyo",
    "iso:country":"JP",
    "name:jpn_x_preferred":[
        "\u539f\u8015\u5730"
    ],
    "name:und_x_variant":[
        "Harak\u014dchi"
    ],
    "wof:name":"Harakochi",
    "wof:placetype":"locality"
},
  "geometry": {"coordinates":[139.09888999999998,35.35623],"type":"Point"}
}