{
  "type": "Feature",
  "properties": {
    "gn:admin1_code":"28.0",
    "gn:admin2_code":"1848164.0",
    "gn:admin3_code":"29441.0",
    "gn:asciiname":"Tonogawa",
    "gn:country_code":"JP",
    "gn:dem":478,
    "gn:feature_class":"P",
    "gn:feature_code":"PPLL",
    "gn:name":"Tonogawa",
    "gn:population":0,
    "gn:timezone":"Asia/Tokyo",
    "iso:country":"JP",
    "name:jpn_x_preferred":[
        "\u6bbf\u5ddd"
    ],
    "wof:name":"Tonogawa",
    "wof:placetype":"locality"
},
  "geometry": {"coordinates":[135.95439999999999,34.41535],"type":"Point"}
}