{
  "type": "Feature",
  "properties": {
    "gn:admin1_code":"4.0",
    "gn:admin2_code":"2111854.0",
    "gn:asciiname":"Tanaga",
    "gn:country_code":"JP",
    "gn:dem":6,
    "gn:feature_class":"P",
    "gn:feature_code":"PPLL",
    "gn:name":"Tanaga",
    "gn:population":0,
    "gn:timezone":"Asia/Tokyo",
    "iso:country":"JP",
    "name:jpn_x_preferred":[
        "\u7530\u6c38"
    ],
    "name:jpn_x_variant":[
        "\u305f\u306a\u304c",
        "\u30bf\u30ca\u30ac"
    ],
    "name:lfn_x_preferred":[
        "Tanaga"
    ],
    "name:rus_x_preferred":[
        "\u0422\u0430\u043d\u0430\u0433\u0430"
    ],
    "name:tgl_x_preferred":[
        "Tanaga"
    ],
    "name:ukr_x_preferred":[
        "\u0422\u0430\u043d\u0430\u0433\u0430"
    ],
    "wof:name":"Tanaga",
    "wof:placetype":"locality"
},
  "geometry": {"coordinates":[140.33518000000001,35.44075],"type":"Point"}
}