{
  "type": "Feature",
  "properties": {
    "gn:admin1_code":"7.0",
    "gn:admin2_code":"1854081.0",
    "gn:asciiname":"Iwamoto",
    "gn:country_code":"JP",
    "gn:dem":16,
    "gn:feature_class":"P",
    "gn:feature_code":"PPL",
    "gn:name":"Iwamoto",
    "gn:population":0,
    "gn:timezone":"Asia/Tokyo",
    "iso:country":"JP",
    "name:jpn_x_preferred":[
        "\u5ca9\u672c"
    ],
    "wof:name":"Iwamoto",
    "wof:placetype":"locality"
},
  "geometry": {"coordinates":[130.49128000000002,33.06969],"type":"Point"}
}