{
  "type": "Feature",
  "properties": {
    "gn:admin1_code":"3.0",
    "gn:admin2_code":"2130088.0",
    "gn:admin3_code":"2301.0",
    "gn:asciiname":"Shinmichi",
    "gn:country_code":"JP",
    "gn:dem":11,
    "gn:feature_class":"P",
    "gn:feature_code":"PPL",
    "gn:name":"Shinmichi",
    "gn:population":0,
    "gn:timezone":"Asia/Tokyo",
    "iso:country":"JP",
    "name:jpn_x_preferred":[
        "\u65b0\u9053"
    ],
    "name:jpn_x_variant":[
        "\u3057\u3093\u307f\u3061",
        "\u30b7\u30f3\u30df\u30c1"
    ],
    "wof:name":"Shinmichi",
    "wof:placetype":"locality"
},
  "geometry": {"coordinates":[140.96395000000001,40.9248],"type":"Point"}
}