{
  "type": "Feature",
  "properties": {
    "gn:admin1_code":"3.0",
    "gn:admin2_code":"2130225.0",
    "gn:asciiname":"Shimohiraimachi",
    "gn:country_code":"JP",
    "gn:dem":8,
    "gn:feature_class":"P",
    "gn:feature_code":"PPL",
    "gn:name":"Shimohiraimachi",
    "gn:population":0,
    "gn:timezone":"Asia/Tokyo",
    "iso:country":"JP",
    "name:jpn_x_preferred":[
        "\u4e0b\u5e73\u4e95\u753a"
    ],
    "name:jpn_x_variant":[
        "\u3057\u3082\u3072\u3089\u3044\u307e\u3061",
        "\u30b7\u30e2\u30d2\u30e9\u30a4\u30de\u30c1"
    ],
    "wof:name":"Shimohiraimachi",
    "wof:placetype":"locality"
},
  "geometry": {"coordinates":[140.44902999999999,40.82014],"type":"Point"}
}