{
  "type": "Feature",
  "properties": {
    "gn:admin1_code":"19.0",
    "gn:admin2_code":"1865011.0",
    "gn:admin3_code":"14363.0",
    "gn:asciiname":"Nakamachiya",
    "gn:country_code":"JP",
    "gn:dem":55,
    "gn:feature_class":"P",
    "gn:feature_code":"PPLL",
    "gn:name":"Nakamachiya",
    "gn:population":0,
    "gn:timezone":"Asia/Tokyo",
    "iso:country":"JP",
    "name:jpn_x_preferred":[
        "\u4ef2\u753a\u5c4b"
    ],
    "wof:name":"Nakamachiya",
    "wof:placetype":"locality"
},
  "geometry": {"coordinates":[139.13789,35.34293],"type":"Point"}
}