{
  "type": "Feature",
  "properties": {
    "gn:admin1_code":"26.0",
    "gn:admin2_code":"1849427.0",
    "gn:asciiname":"Tanakagumi",
    "gn:country_code":"JP",
    "gn:dem":492,
    "gn:feature_class":"P",
    "gn:feature_code":"PPLL",
    "gn:name":"Tanakagumi",
    "gn:population":0,
    "gn:timezone":"Asia/Tokyo",
    "iso:country":"JP",
    "name:jpn_x_preferred":[
        "\u7530\u4e2d\u7d44"
    ],
    "wof:name":"Tanakagumi",
    "wof:placetype":"locality"
},
  "geometry": {"coordinates":[138.16551999999999,36.39696],"type":"Point"}
}