{
  "type": "Feature",
  "properties": {
    "gn:admin1_code":"7.0",
    "gn:admin2_code":"1856443.0",
    "gn:asciiname":"Tsujimotoura",
    "gn:country_code":"JP",
    "gn:dem":12,
    "gn:feature_class":"P",
    "gn:feature_code":"PPLL",
    "gn:name":"Tsujimotoura",
    "gn:population":0,
    "gn:timezone":"Asia/Tokyo",
    "iso:country":"JP",
    "name:jpn_x_preferred":[
        "\u8fbb\u5143\u672b"
    ],
    "name:jpn_x_variant":[
        "\u3064\u3058\u3082\u3068\u3046\u3089"
    ],
    "wof:name":"Tsujimotoura",
    "wof:placetype":"locality"
},
  "geometry": {"coordinates":[130.53138999999999,33.867],"type":"Point"}
}