{
  "type": "Feature",
  "properties": {
    "gn:admin1_code":"23",
    "gn:admin2_code":"7417703.0",
    "gn:admin3_code":"24562.0",
    "gn:asciiname":"Udono",
    "gn:country_code":"JP",
    "gn:dem":2,
    "gn:feature_class":"P",
    "gn:feature_code":"PPL",
    "gn:name":"Udono",
    "gn:population":0,
    "gn:timezone":"Asia/Tokyo",
    "iso:country":"JP",
    "name:fas_x_preferred":[
        "\u0627\u0648\u062f\u0648\u0646\u0648"
    ],
    "name:jpn_x_preferred":[
        "\u9d5c\u6bbf\u6751"
    ],
    "wof:name":"Udono",
    "wof:placetype":"locality"
},
  "geometry": {"coordinates":[136.01113000000001,33.73699999999999],"type":"Point"}
}