{
  "type": "Feature",
  "properties": {
    "gn:admin1_code":"19",
    "gn:admin2_code":"1863429.0",
    "gn:asciiname":"Magarimatsu",
    "gn:country_code":"JP",
    "gn:dem":167,
    "gn:feature_class":"P",
    "gn:feature_code":"PPL",
    "gn:name":"Magarimatsu",
    "gn:population":0,
    "gn:timezone":"Asia/Tokyo",
    "iso:country":"JP",
    "name:jpn_x_preferred":[
        "\u66f2\u677e"
    ],
    "wof:name":"Magarimatsu",
    "wof:placetype":"locality"
},
  "geometry": {"coordinates":[139.18566000000001,35.37163],"type":"Point"}
}