{
  "type": "Feature",
  "properties": {
    "gn:admin1_code":"6.0",
    "gn:admin2_code":"7467387.0",
    "gn:asciiname":"Maruokacho-tsuboe",
    "gn:country_code":"JP",
    "gn:dem":18,
    "gn:feature_class":"P",
    "gn:feature_code":"PPL",
    "gn:name":"Maruokach\u014d-tsuboe",
    "gn:population":0,
    "gn:timezone":"Asia/Tokyo",
    "iso:country":"JP",
    "name:jpn_x_preferred":[
        "\u4e38\u5ca1\u753a\u576a\u6c5f"
    ],
    "name:und_x_variant":[
        "Maruokach\u014d-tsuboe"
    ],
    "wof:name":"Maruokacho-tsuboe",
    "wof:placetype":"locality"
},
  "geometry": {"coordinates":[136.27826000000002,36.17496],"type":"Point"}
}