{
  "type": "Feature",
  "properties": {
    "gn:admin1_code":"19.0",
    "gn:admin2_code":"1848595.0",
    "gn:asciiname":"Fukuda",
    "gn:country_code":"JP",
    "gn:dem":44,
    "gn:feature_class":"P",
    "gn:feature_code":"PPL",
    "gn:name":"Fukuda",
    "gn:population":0,
    "gn:timezone":"Asia/Tokyo",
    "iso:country":"JP",
    "name:fin_x_preferred":[
        "Fukuda"
    ],
    "name:ita_x_preferred":[
        "Fukuda"
    ],
    "name:jpn_x_preferred":[
        "\u798f\u7530"
    ],
    "name:lit_x_preferred":[
        "Fukuda"
    ],
    "wof:name":"Fukuda",
    "wof:placetype":"locality"
},
  "geometry": {"coordinates":[139.46271999999999,35.44531],"type":"Point"}
}