{
  "type": "Feature",
  "properties": {
    "gn:admin1_code":"21.0",
    "gn:admin2_code":"1848441.0",
    "gn:asciiname":"Nagaikarimachi",
    "gn:country_code":"JP",
    "gn:dem":0,
    "gn:feature_class":"P",
    "gn:feature_code":"PPL",
    "gn:name":"Nagaikarimachi",
    "gn:population":0,
    "gn:timezone":"Asia/Tokyo",
    "iso:country":"JP",
    "name:jpn_x_preferred":[
        "\u6c38\u7887\u753a"
    ],
    "name:jpn_x_variant":[
        "\u306a\u304c\u3044\u304b\u308a\u307e\u3061",
        "\u30ca\u30ac\u30a4\u30ab\u30ea\u30de\u30c1"
    ],
    "wof:name":"Nagaikarimachi",
    "wof:placetype":"locality"
},
  "geometry": {"coordinates":[130.59180000000001,32.52179],"type":"Point"}
}