{
  "type": "Feature",
  "properties": {
    "gn:admin1_code":"8.0",
    "gn:admin2_code":"2112921.0",
    "gn:asciiname":"Kakiba",
    "gn:country_code":"JP",
    "gn:dem":92,
    "gn:feature_class":"P",
    "gn:feature_code":"PPLL",
    "gn:name":"Kakiba",
    "gn:population":0,
    "gn:timezone":"Asia/Tokyo",
    "iso:country":"JP",
    "name:jpn_x_preferred":[
        "\u67ff\u5834"
    ],
    "wof:name":"Kakiba",
    "wof:placetype":"locality"
},
  "geometry": {"coordinates":[140.44175000000001,37.69161],"type":"Point"}
}