{
  "type": "Feature",
  "properties": {
    "gn:admin1_code":"30",
    "gn:admin2_code":"1859233.0",
    "gn:asciiname":"Shimokutsukake",
    "gn:country_code":"JP",
    "gn:dem":159,
    "gn:feature_class":"P",
    "gn:feature_code":"PPLL",
    "gn:name":"Shimokutsukake",
    "gn:population":0,
    "gn:timezone":"Asia/Tokyo",
    "iso:country":"JP",
    "name:jpn_x_preferred":[
        "\u4e0b\u6c93\u639b"
    ],
    "name:und_x_variant":[
        "Shimo-kutsukake"
    ],
    "wof:name":"Shimokutsukake",
    "wof:placetype":"locality"
},
  "geometry": {"coordinates":[131.56686000000002,33.48518],"type":"Point"}
}