{
  "type": "Feature",
  "properties": {
    "gn:admin1_code":"19.0",
    "gn:admin2_code":"1848350.0",
    "gn:admin3_code":"14111.0",
    "gn:asciiname":"Konan-chuodori",
    "gn:country_code":"JP",
    "gn:dem":12,
    "gn:feature_class":"P",
    "gn:feature_code":"PPL",
    "gn:name":"K\u014dnan-ch\u016b\u014dd\u014dri",
    "gn:population":0,
    "gn:timezone":"Asia/Tokyo",
    "iso:country":"JP",
    "name:jpn_x_preferred":[
        "\u6e2f\u5357\u4e2d\u592e\u901a"
    ],
    "name:jpn_x_variant":[
        "\u3053\u3046\u306a\u3093\u3061\u3085\u3046\u304a\u3046\u3069\u304a\u308a",
        "\u30b3\u30a6\u30ca\u30f3\u30c1\u30e5\u30a6\u30aa\u30a6\u30c9\u30aa\u30ea"
    ],
    "name:und_x_variant":[
        "K\u014dnan-ch\u016b\u014dd\u014dri"
    ],
    "wof:name":"Konan-chuodori",
    "wof:placetype":"locality"
},
  "geometry": {"coordinates":[139.59228999999999,35.40303],"type":"Point"}
}