{
  "type": "Feature",
  "properties": {
    "gn:admin1_code":"4.0",
    "gn:admin2_code":"7465521.0",
    "gn:asciiname":"Kogoji",
    "gn:country_code":"JP",
    "gn:dem":13,
    "gn:feature_class":"P",
    "gn:feature_code":"PPLL",
    "gn:name":"Kog\u014dji",
    "gn:population":0,
    "gn:timezone":"Asia/Tokyo",
    "iso:country":"JP",
    "name:jpn_x_preferred":[
        "\u6545\u90f7\u6c60"
    ],
    "name:jpn_x_variant":[
        "\u3053\u3054\u3046\u3058",
        "\u30b3\u30b4\u30a6\u30b8"
    ],
    "name:und_x_variant":[
        "Kog\u014dji"
    ],
    "wof:name":"Kogoji",
    "wof:placetype":"locality"
},
  "geometry": {"coordinates":[139.82897,35.06039000000001],"type":"Point"}
}