{
  "type": "Feature",
  "properties": {
    "gn:admin1_code":"4.0",
    "gn:admin2_code":"2112997.0",
    "gn:admin3_code":"12423.0",
    "gn:asciiname":"Minaminakaze",
    "gn:country_code":"JP",
    "gn:dem":1,
    "gn:feature_class":"P",
    "gn:feature_code":"PPLL",
    "gn:name":"Minaminakaze",
    "gn:population":0,
    "gn:timezone":"Asia/Tokyo",
    "iso:country":"JP",
    "name:jpn_x_preferred":[
        "\u5357\u4e2d\u702c"
    ],
    "name:jpn_x_variant":[
        "\u307f\u306a\u307f\u306a\u304b\u305c",
        "\u30df\u30ca\u30df\u30ca\u30ab\u30bc"
    ],
    "wof:name":"Minaminakaze",
    "wof:placetype":"locality"
},
  "geometry": {"coordinates":[140.38721000000001,35.394],"type":"Point"}
}