{
  "type": "Feature",
  "properties": {
    "gn:admin1_code":"23.0",
    "gn:admin2_code":"1859297.0",
    "gn:admin3_code":"24543.0",
    "gn:asciiname":"Kujira",
    "gn:country_code":"JP",
    "gn:dem":12,
    "gn:feature_class":"P",
    "gn:feature_code":"PPLL",
    "gn:name":"Kujira",
    "gn:population":0,
    "gn:timezone":"Asia/Tokyo",
    "iso:country":"JP",
    "name:ara_x_preferred":[
        "\u0643\u0648\u062c\u064a\u0631\u0627"
    ],
    "name:fra_x_preferred":[
        "Kujira"
    ],
    "name:jpn_x_preferred":[
        "\u9be8"
    ],
    "name:jpn_x_variant":[
        "\u304f\u3058\u3089"
    ],
    "name:kor_x_preferred":[
        "\ucfe0\uc9c0\ub77c"
    ],
    "name:pol_x_preferred":[
        "Kujira"
    ],
    "name:rus_x_preferred":[
        "\u041a\u0443\u0434\u0437\u0438\u0440\u0430"
    ],
    "name:spa_x_preferred":[
        "Kujira"
    ],
    "name:zho_x_preferred":[
        "\u9be8"
    ],
    "wof:name":"Kujira",
    "wof:placetype":"locality"
},
  "geometry": {"coordinates":[136.24933999999999,34.13948],"type":"Point"}
}