{
  "type": "Feature",
  "properties": {
    "gn:admin1_code":"21.0",
    "gn:admin2_code":"7412708.0",
    "gn:admin3_code":"43510.0",
    "gn:asciiname":"Shiiba",
    "gn:country_code":"JP",
    "gn:dem":411,
    "gn:feature_class":"P",
    "gn:feature_code":"PPLL",
    "gn:name":"Shiiba",
    "gn:population":0,
    "gn:timezone":"Asia/Tokyo",
    "iso:country":"JP",
    "name:jpn_x_preferred":[
        "\u690e\u8449"
    ],
    "name:jpn_x_variant":[
        "\u3057\u3044\u3070",
        "\u30b7\u30a4\u30d0"
    ],
    "wof:name":"Shiiba",
    "wof:placetype":"locality"
},
  "geometry": {"coordinates":[130.81358999999998,32.35832],"type":"Point"}
}