{
  "type": "Feature",
  "properties": {
    "gn:admin1_code":"21.0",
    "gn:admin2_code":"1850743.0",
    "gn:asciiname":"Nakashima",
    "gn:country_code":"JP",
    "gn:dem":5,
    "gn:feature_class":"P",
    "gn:feature_code":"PPLL",
    "gn:name":"Nakashima",
    "gn:population":0,
    "gn:timezone":"Asia/Tokyo",
    "iso:country":"JP",
    "name:jpn_x_preferred":[
        "\u4e2d\u5cf6"
    ],
    "name:jpn_x_variant":[
        "\u306a\u304b\u3057\u307e",
        "\u30ca\u30ab\u30b7\u30de"
    ],
    "wof:name":"Nakashima",
    "wof:placetype":"locality"
},
  "geometry": {"coordinates":[130.52211,32.90472],"type":"Point"}
}