{
  "type": "Feature",
  "properties": {
    "gn:country":"JP",
    "gn:fcode":"ADM3",
    "gn:pop":0,
    "iso:country":"JP",
    "name:eng_x_preferred":[
        "Kami-cho"
    ],
    "name:jpn_x_preferred":[
        "\u9999\u7f8e\u753a"
    ],
    "name:jpn_x_variant":[
        "\u304b\u307f\u3061\u3087\u3046"
    ],
    "qs:name":"Kami-ch\u014d",
    "qs:photos_9r":0,
    "qs:photos_sr":0,
    "qs:pop_sr":"0",
    "wof:name":"Kami-ch\u014d",
    "wof:placetype":"localadmin",
    "wof:population":0
},
  "geometry": {"coordinates":[134.5891,35.52452],"type":"Point"}
}