{
  "type": "Feature",
  "properties": {
    "gn:admin1_code":"3.0",
    "gn:admin2_code":"2130225.0",
    "gn:asciiname":"Obiraki",
    "gn:country_code":"JP",
    "gn:dem":42,
    "gn:feature_class":"P",
    "gn:feature_code":"PPL",
    "gn:name":"\u014cbiraki",
    "gn:population":0,
    "gn:timezone":"Asia/Tokyo",
    "iso:country":"JP",
    "name:jpn_x_preferred":[
        "\u5927\u958b"
    ],
    "name:jpn_x_variant":[
        "\u304a\u304a\u3073\u3089\u304d",
        "\u30aa\u30aa\u30d3\u30e9\u30ad"
    ],
    "name:und_x_variant":[
        "\u014cbiraki"
    ],
    "wof:name":"Obiraki",
    "wof:placetype":"locality"
},
  "geometry": {"coordinates":[140.50569999999999,40.8087],"type":"Point"}
}