{
  "type": "Feature",
  "properties": {
    "gn:admin1_code":"21.0",
    "gn:admin2_code":"1850744.0",
    "gn:admin3_code":"43364.0",
    "gn:asciiname":"Imayama",
    "gn:country_code":"JP",
    "gn:dem":86,
    "gn:feature_class":"P",
    "gn:feature_code":"PPLL",
    "gn:name":"Imayama",
    "gn:population":0,
    "gn:timezone":"Asia/Tokyo",
    "iso:country":"JP",
    "name:jpn_x_preferred":[
        "\u4eca\u5c71"
    ],
    "name:jpn_x_variant":[
        "\u3044\u307e\u3084\u307e",
        "\u30a4\u30de\u30e4\u30de"
    ],
    "wof:name":"Imayama",
    "wof:placetype":"locality"
},
  "geometry": {"coordinates":[130.63051000000002,32.89344000000001],"type":"Point"}
}