{
  "type": "Feature",
  "properties": {
    "gn:admin1_code":"26",
    "gn:admin2_code":"1857516.0",
    "gn:asciiname":"Minamiozuma",
    "gn:country_code":"JP",
    "gn:dem":628,
    "gn:feature_class":"P",
    "gn:feature_code":"PPL",
    "gn:name":"Minami\u014dzuma",
    "gn:population":0,
    "gn:timezone":"Asia/Tokyo",
    "iso:country":"JP",
    "name:jpn_x_preferred":[
        "\u5357\u5927\u59bb"
    ],
    "name:und_x_variant":[
        "Minami-\u014dtsuma",
        "Minami-\u014dzuma",
        "Minami\u014dzuma"
    ],
    "wof:name":"Minamiozuma",
    "wof:placetype":"locality"
},
  "geometry": {"coordinates":[137.89103,36.22915],"type":"Point"}
}