{
  "type": "Feature",
  "properties": {
    "gn:admin1_code":"12.0",
    "gn:admin2_code":"7428118.0",
    "gn:admin3_code":"1575.0",
    "gn:asciiname":"Sobetsu",
    "gn:cc2":"JP",
    "gn:country_code":"JP",
    "gn:dem":51,
    "gn:feature_class":"P",
    "gn:feature_code":"PPL",
    "gn:name":"S\u014dbetsu",
    "gn:population":0,
    "gn:timezone":"Asia/Tokyo",
    "iso:country":"JP",
    "name:ceb_x_preferred":[
        "S\u014dbetsu-machi"
    ],
    "name:fas_x_preferred":[
        "\u0633\u0648\u0628\u062a\u0633\u0648"
    ],
    "name:fin_x_preferred":[
        "S\u014dbetsu"
    ],
    "name:fra_x_preferred":[
        "S\u014dbetsu"
    ],
    "name:ido_x_preferred":[
        "Soubetsu"
    ],
    "name:ita_x_preferred":[
        "S\u014dbetsu"
    ],
    "name:jpn_x_preferred":[
        "\u58ee\u77a5\u753a"
    ],
    "name:kor_x_preferred":[
        "\uc18c\ubca0\uc4f0\uc815"
    ],
    "name:msa_x_preferred":[
        "S\u014dbetsu"
    ],
    "name:mya_x_preferred":[
        "\u1006\u102d\u102f\u1038\u1018\u1032\u1006\u103d\u1010\u103a\u1019\u103c\u102d\u102f\u1037\u104a \u101f\u1031\u102c\u1037\u1000\u102d\u102f\u1004\u103a\u1038\u1012\u102d\u102f\u1038"
    ],
    "name:rus_x_preferred":[
        "\u0421\u043e\u0431\u0435\u0446\u0443"
    ],
    "name:ukr_x_preferred":[
        "\u0421\u043e\u0431\u0435\u0446\u0443"
    ],
    "name:und_x_variant":[
        "T\u014dya-kohan"
    ],
    "name:zho_x_preferred":[
        "\u58ef\u77a5\u753a"
    ],
    "wof:name":"Sobetsu",
    "wof:placetype":"locality"
},
  "geometry": {"coordinates":[140.88611,42.55583],"type":"Point"}
}