{
  "type": "Feature",
  "properties": {
    "gn:admin1_code":"12.0",
    "gn:admin2_code":"7428118.0",
    "gn:admin3_code":"1575.0",
    "gn:asciiname":"Sobetsu",
    "gn:cc2":"JP",
    "gn:country_code":"JP",
    "gn:dem":51,
    "gn:feature_class":"P",
    "gn:feature_code":"PPL",
    "gn:name":"S\u014dbetsu",
    "gn:population":0,
    "gn:timezone":"Asia/Tokyo",
    "iso:country":"JP",
    "name:und_x_variant":[
        "T\u014dya-kohan",
        "S\u014dbetsu"
    ],
    "wof:name":"Sobetsu",
    "wof:placetype":"locality"
},
  "geometry": {"coordinates":[140.88611,42.55583],"type":"Point"}
}