{
  "type": "Feature",
  "properties": {
    "gn:admin1_code":"2.0",
    "gn:admin2_code":"7443156.0",
    "gn:asciiname":"Sannowatari",
    "gn:country_code":"JP",
    "gn:dem":125,
    "gn:feature_class":"P",
    "gn:feature_code":"PPL",
    "gn:name":"Sannowatari",
    "gn:population":0,
    "gn:timezone":"Asia/Tokyo",
    "iso:country":"JP",
    "name:jpn_x_preferred":[
        "\u4e09\u30ce\u6e21"
    ],
    "wof:name":"Sannowatari",
    "wof:placetype":"locality"
},
  "geometry": {"coordinates":[140.46263999999999,40.11109],"type":"Point"}
}