{
  "type": "Feature",
  "properties": {
    "gn:admin1_code":"16.0",
    "gn:admin2_code":"2112223.0",
    "gn:asciiname":"Okada",
    "gn:country_code":"JP",
    "gn:dem":92,
    "gn:feature_class":"P",
    "gn:feature_code":"PPL",
    "gn:name":"Okada",
    "gn:population":0,
    "gn:timezone":"Asia/Tokyo",
    "iso:country":"JP",
    "name:jpn_x_preferred":[
        "\u5ca1\u7530"
    ],
    "name:jpn_x_variant":[
        "\u304a\u304b\u3060",
        "\u30aa\u30ab\u30c0"
    ],
    "wof:name":"Okada",
    "wof:placetype":"locality"
},
  "geometry": {"coordinates":[141.08902,39.33487],"type":"Point"}
}