{
  "type": "Feature",
  "properties": {
    "gn:admin1_code":"33",
    "gn:admin2_code":"8300623.0",
    "gn:asciiname":"Hatogawa",
    "gn:country_code":"JP",
    "gn:dem":24,
    "gn:feature_class":"P",
    "gn:feature_code":"PPL",
    "gn:name":"Hatogawa",
    "gn:population":0,
    "gn:timezone":"Asia/Tokyo",
    "iso:country":"JP",
    "name:jpn_x_preferred":[
        "\u9ce9\u5ddd"
    ],
    "wof:name":"Hatogawa",
    "wof:placetype":"locality"
},
  "geometry": {"coordinates":[129.94148000000001,33.49424],"type":"Point"}
}