{
  "type": "Feature",
  "properties": {
    "gn:admin1_code":"18",
    "gn:admin2_code":"1853737.0",
    "gn:admin3_code":"46525.0",
    "gn:asciiname":"Agina",
    "gn:country_code":"JP",
    "gn:dem":7,
    "gn:feature_class":"P",
    "gn:feature_code":"PPL",
    "gn:name":"Agina",
    "gn:population":0,
    "gn:timezone":"Asia/Tokyo",
    "iso:country":"JP",
    "name:jpn_x_preferred":[
        "\u963f\u6728\u540d"
    ],
    "name:und_x_variant":[
        "Akina"
    ],
    "wof:name":"Agina",
    "wof:placetype":"locality"
},
  "geometry": {"coordinates":[129.33503999999999,28.17054000000001],"type":"Point"}
}