{
  "type": "Feature",
  "properties": {
    "gn:admin1_code":"21.0",
    "gn:admin2_code":"7413150.0",
    "gn:asciiname":"Koganoshita",
    "gn:country_code":"JP",
    "gn:dem":50,
    "gn:feature_class":"P",
    "gn:feature_code":"PPLL",
    "gn:name":"Koganoshita",
    "gn:population":0,
    "gn:timezone":"Asia/Tokyo",
    "iso:country":"JP",
    "name:jpn_x_preferred":[
        "\u53e4\u9591\u30ce\u4e0b"
    ],
    "name:jpn_x_variant":[
        "\u3053\u304c\u306e\u3057\u305f",
        "\u30b3\u30ac\u30ce\u30b7\u30bf"
    ],
    "wof:name":"Koganoshita",
    "wof:placetype":"locality"
},
  "geometry": {"coordinates":[130.67248000000001,33.03999],"type":"Point"}
}