{
  "type": "Feature",
  "properties": {
    "gn:admin1_code":"4.0",
    "gn:admin2_code":"1855071.0",
    "gn:asciiname":"Mitsubori",
    "gn:country_code":"JP",
    "gn:dem":17,
    "gn:feature_class":"P",
    "gn:feature_code":"PPL",
    "gn:name":"Mitsubori",
    "gn:population":0,
    "gn:timezone":"Asia/Tokyo",
    "iso:country":"JP",
    "name:jpn_x_preferred":[
        "\u4e09\u30c4\u5800"
    ],
    "wof:name":"Mitsubori",
    "wof:placetype":"locality"
},
  "geometry": {"coordinates":[139.91874000000001,35.94396],"type":"Point"}
}