{
  "type": "Feature",
  "properties": {
    "gn:admin1_code":"37.0",
    "gn:admin2_code":"7418320.0",
    "gn:asciiname":"Kitanagoya",
    "gn:country_code":"JP",
    "gn:dem":28,
    "gn:feature_class":"P",
    "gn:feature_code":"PPLL",
    "gn:name":"Kitanagoya",
    "gn:population":0,
    "gn:timezone":"Asia/Tokyo",
    "iso:country":"JP",
    "name:jpn_x_preferred":[
        "\u5317\u5948\u53e4\u8c37"
    ],
    "wof:name":"Kitanagoya",
    "wof:placetype":"locality"
},
  "geometry": {"coordinates":[138.97333999999998,35.07489],"type":"Point"}
}