{
  "type": "Feature",
  "properties": {
    "gn:admin1_code":"37.0",
    "gn:admin2_code":"7418320.0",
    "gn:asciiname":"Kitanagoya",
    "gn:country_code":"JP",
    "gn:dem":28,
    "gn:feature_class":"P",
    "gn:feature_code":"PPLL",
    "gn:name":"Kitanagoya",
    "gn:population":0,
    "gn:timezone":"Asia/Tokyo",
    "iso:country":"JP",
    "name:ara_x_preferred":[
        "\u0643\u064a\u062a\u0627\u0646\u0627\u063a\u0648\u064a\u0627"
    ],
    "name:azb_x_preferred":[
        "\u06a9\u06cc\u062a\u0627\u0646\u0627\u0642\u0648\u06cc\u0627"
    ],
    "name:ceb_x_preferred":[
        "Kitanagoya"
    ],
    "name:deu_x_preferred":[
        "Kitanagoya"
    ],
    "name:fas_x_preferred":[
        "\u06a9\u06cc\u062a\u0627\u0646\u0627\u06af\u0648\u06cc\u0627"
    ],
    "name:fra_x_preferred":[
        "Kitanagoya"
    ],
    "name:glg_x_preferred":[
        "Kitanagoya"
    ],
    "name:ita_x_preferred":[
        "Kitanagoya"
    ],
    "name:jpn_x_preferred":[
        "\u5317\u5948\u53e4\u8c37"
    ],
    "name:jpn_x_variant":[
        "\u5317\u540d\u53e4\u5c4b\u5e02"
    ],
    "name:kaz_x_preferred":[
        "\u041a\u0438\u0442\u0430\u043d\u0430\u0433\u043e\u044f"
    ],
    "name:kor_x_preferred":[
        "\uae30\ud0c0\ub098\uace0\uc57c\uc2dc"
    ],
    "name:mzn_x_preferred":[
        "\u06a9\u06cc\u062a\u0627\u0646\u0627\u06af\u0648\u06cc\u0627"
    ],
    "name:nld_x_preferred":[
        "Kitanagoya"
    ],
    "name:pol_x_preferred":[
        "Kitanagoya"
    ],
    "name:por_x_preferred":[
        "Kitanagoya"
    ],
    "name:ron_x_preferred":[
        "Kitanagoya"
    ],
    "name:rus_x_preferred":[
        "\u041a\u0438\u0442\u0430\u043d\u0430\u0433\u043e\u044f"
    ],
    "name:spa_x_preferred":[
        "Kitanagoya"
    ],
    "name:swe_x_preferred":[
        "Kitanagoya"
    ],
    "name:tgl_x_preferred":[
        "Kitanagoya"
    ],
    "name:tum_x_preferred":[
        "Kitanagoya"
    ],
    "name:tur_x_preferred":[
        "Kitanagoya"
    ],
    "name:ukr_x_preferred":[
        "\u041a\u0456\u0442\u0430-\u041d\u0430\u0491\u043e\u044f"
    ],
    "name:urd_x_preferred":[
        "\u06a9\u06cc\u062a\u0627\u0646\u0627\u06af\u0648\u06cc\u0627"
    ],
    "name:vie_x_preferred":[
        "Kitanagoya"
    ],
    "name:war_x_preferred":[
        "Kitanagoya"
    ],
    "name:zho_x_preferred":[
        "\u5317\u540d\u53e4\u5c4b\u5e02"
    ],
    "wof:name":"Kitanagoya",
    "wof:placetype":"locality"
},
  "geometry": {"coordinates":[138.97333999999998,35.07489],"type":"Point"}
}