{
  "type": "Feature",
  "properties": {
    "gn:admin1_code":"32.0",
    "gn:admin2_code":"1850033.0",
    "gn:asciiname":"Takabedai",
    "gn:country_code":"JP",
    "gn:dem":104,
    "gn:feature_class":"P",
    "gn:feature_code":"PPL",
    "gn:name":"Takabedai",
    "gn:population":0,
    "gn:timezone":"Asia/Tokyo",
    "iso:country":"JP",
    "name:jpn_x_preferred":[
        "\u9ad8\u8fba\u53f0"
    ],
    "wof:name":"Takabedai",
    "wof:placetype":"locality"
},
  "geometry": {"coordinates":[135.56942000000001,34.50125999999999],"type":"Point"}
}