{
  "type": "Feature",
  "properties": {
    "iso:country":"JP",
    "name:eng_x_preferred":[
        "Furukawachowakamiya 2 Chome"
    ],
    "name:eng_x_variant":[
        "Furukawachouwakamiya 2 Choume",
        "Furukawachowakamiya 2 Chome"
    ],
    "name:jpn_x_preferred":[
        "\uff12\u4e01\u76ee"
    ],
    "name:jpn_x_variant":[
        "\u3075\u308b\u304b\u308f\u3061\u3087\u3046\u308f\u304b\u307f\u3084 \uff12\u3061\u3087\u3046\u3081",
        "\u53e4\u5ddd\u753a\u82e5\u5bae \uff12\u4e01\u76ee",
        "\uff12\u3061\u3087\u3046\u3081"
    ],
    "qs:gn_local":0,
    "qs:local_max":51,
    "qs:local_sum":51,
    "qs:localhoods":1,
    "qs:name":"\uff12\u4e01\u76ee",
    "qs:name_adm0":"\u65e5\u672c",
    "qs:name_adm1":"\u5c90\u961c\u770c",
    "qs:name_en":"Furukawachowakamiya 2 Chome",
    "qs:name_lau":"\u53e4\u5ddd\u753a\u82e5\u5bae",
    "qs:name_local":"\u98db\u9a28\u5e02",
    "qs:photo_max":15,
    "qs:photo_sum":51,
    "qs:placetype":"Suburb",
    "qs:quad_count":5,
    "qs:woe_adm0":23424856,
    "qs:woe_adm1":2345859,
    "qs:woe_adm2":0,
    "qs:woe_lau":28435362,
    "qs:woe_local":28379222,
    "qs:woe_ver":"7.10.0",
    "wof:lang":[
        "jpn"
    ],
    "wof:name":"\uff12\u4e01\u76ee",
    "wof:placetype":"neighbourhood"
},
  "geometry": {"coordinates":[137.18754799999999,36.236694],"type":"Point"}
}