{
  "type": "Feature",
  "properties": {
    "gn:admin1_code":"12.0",
    "gn:admin2_code":"2128418.0",
    "gn:admin3_code":"1517.0",
    "gn:asciiname":"Nishiuedomari",
    "gn:country_code":"JP",
    "gn:dem":51,
    "gn:feature_class":"P",
    "gn:feature_code":"PPL",
    "gn:name":"Nishiuedomari",
    "gn:population":0,
    "gn:timezone":"Asia/Tokyo",
    "iso:country":"JP",
    "name:jpn_x_preferred":[
        "\u897f\u4e0a\u6cca"
    ],
    "name:jpn_x_variant":[
        "\u306b\u3057\u3046\u3048\u3069\u307e\u308a",
        "\u30cb\u30b7\u30a6\u30a8\u30c9\u30de\u30ea"
    ],
    "name:und_x_variant":[
        "Nishi-kamitomari",
        "Nishi-uedomari",
        "Nishiuedomari",
        "Nishiuendomari"
    ],
    "wof:name":"Nishiuedomari",
    "wof:placetype":"locality"
},
  "geometry": {"coordinates":[140.98743999999999,45.41351],"type":"Point"}
}