{
  "type": "Feature",
  "properties": {
    "gn:admin1_code":"21.0",
    "gn:admin2_code":"1864973.0",
    "gn:asciiname":"Yunoura",
    "gn:country_code":"JP",
    "gn:dem":487,
    "gn:feature_class":"P",
    "gn:feature_code":"PPL",
    "gn:name":"Yunoura",
    "gn:population":0,
    "gn:timezone":"Asia/Tokyo",
    "iso:country":"JP",
    "name:jpn_x_preferred":[
        "\u6e6f\u6d66"
    ],
    "name:jpn_x_variant":[
        "\u3086\u306e\u3046\u3089",
        "\u30e6\u30ce\u30a6\u30e9"
    ],
    "wof:name":"Yunoura",
    "wof:placetype":"locality"
},
  "geometry": {"coordinates":[131.04671999999999,32.99335],"type":"Point"}
}