{
  "type": "Feature",
  "properties": {
    "gn:country":"JP",
    "gn:fcode":"ADM3",
    "gn:population":0,
    "iso:country":"JP",
    "name:jpn_x_preferred":[
        "\u5357\u6728\u66fd\u753a"
    ],
    "name:jpn_x_variant":[
        "\u306a\u304e\u305d\u307e\u3061"
    ],
    "qs:name":"Nagiso-machi",
    "qs:photos_9r":0,
    "qs:photos_sr":0,
    "qs:pop_sr":"0",
    "wof:name":"Nagiso-machi",
    "wof:placetype":"localadmin",
    "wof:population":0
},
  "geometry": {"coordinates":[137.61794,35.60361],"type":"Point"}
}