{
  "type": "Feature",
  "properties": {
    "gn:admin1_code":"9.0",
    "gn:admin2_code":"7418820.0",
    "gn:admin3_code":"21604.0",
    "gn:asciiname":"Hokiwaki",
    "gn:country_code":"JP",
    "gn:dem":568,
    "gn:feature_class":"P",
    "gn:feature_code":"PPL",
    "gn:name":"Hokiwaki",
    "gn:population":0,
    "gn:timezone":"Asia/Tokyo",
    "iso:country":"JP",
    "name:jpn_x_preferred":[
        "\u4fdd\u6728\u8107"
    ],
    "wof:name":"Hokiwaki",
    "wof:placetype":"locality"
},
  "geometry": {"coordinates":[136.89693,36.20781],"type":"Point"}
}