{
  "type": "Feature",
  "properties": {
    "gn:admin1_code":"12.0",
    "gn:admin2_code":"7428100.0",
    "gn:admin3_code":"1691.0",
    "gn:asciiname":"Shumbetsu",
    "gn:cc2":"JP",
    "gn:country_code":"JP",
    "gn:dem":4,
    "gn:feature_class":"P",
    "gn:feature_code":"PPL",
    "gn:name":"Shumbetsu",
    "gn:population":0,
    "gn:timezone":"Asia/Tokyo",
    "iso:country":"JP",
    "name:und_x_variant":[
        "Harubetsu"
    ],
    "wof:name":"Shumbetsu",
    "wof:placetype":"locality"
},
  "geometry": {"coordinates":[145.24458000000001,43.51308],"type":"Point"}
}