{
  "type": "Feature",
  "properties": {
    "gn:admin1_code":"27.0",
    "gn:admin2_code":"7418805.0",
    "gn:asciiname":"Shibunecho",
    "gn:country_code":"JP",
    "gn:dem":18,
    "gn:feature_class":"P",
    "gn:feature_code":"PPL",
    "gn:name":"Shibunech\u014d",
    "gn:population":0,
    "gn:timezone":"Asia/Tokyo",
    "iso:country":"JP",
    "name:jpn_x_preferred":[
        "\u795e\u8239\u753a"
    ],
    "name:und_x_variant":[
        "Shibunech\u014d"
    ],
    "wof:name":"Shibunecho",
    "wof:placetype":"locality"
},
  "geometry": {"coordinates":[129.42806000000002,33.23064],"type":"Point"}
}