{
  "type": "Feature",
  "properties": {
    "gn:admin1_code":"34.0",
    "gn:admin2_code":"7464124.0",
    "gn:asciiname":"Kamikiyoku",
    "gn:country_code":"JP",
    "gn:dem":11,
    "gn:feature_class":"P",
    "gn:feature_code":"PPL",
    "gn:name":"Kamikiyoku",
    "gn:population":0,
    "gn:timezone":"Asia/Tokyo",
    "iso:country":"JP",
    "name:jpn_x_preferred":[
        "\u4e0a\u6e05\u4e45"
    ],
    "name:jpn_x_variant":[
        "\u304b\u307f\u304d\u3088\u304f",
        "\u30ab\u30df\u30ad\u30e8\u30af"
    ],
    "wof:name":"Kamikiyoku",
    "wof:placetype":"locality"
},
  "geometry": {"coordinates":[139.64608000000001,36.07963],"type":"Point"}
}