{
  "type": "Feature",
  "properties": {
    "gn:admin1_code":"34.0",
    "gn:admin2_code":"1859316.0",
    "gn:admin3_code":"11465.0",
    "gn:asciiname":"Yashikizuki",
    "gn:country_code":"JP",
    "gn:dem":5,
    "gn:feature_class":"P",
    "gn:feature_code":"PPLL",
    "gn:name":"Yashikizuki",
    "gn:population":0,
    "gn:timezone":"Asia/Tokyo",
    "iso:country":"JP",
    "name:jpn_x_preferred":[
        "\u5c4b\u6577\u9644"
    ],
    "wof:name":"Yashikizuki",
    "wof:placetype":"locality"
},
  "geometry": {"coordinates":[139.82888,35.91064],"type":"Point"}
}