{
  "type": "Feature",
  "properties": {
    "gn:admin1_code":"21.0",
    "gn:admin2_code":"1864973.0",
    "gn:asciiname":"Sadogasato",
    "gn:country_code":"JP",
    "gn:dem":854,
    "gn:feature_class":"P",
    "gn:feature_code":"PPLL",
    "gn:name":"Sadogasato",
    "gn:population":0,
    "gn:timezone":"Asia/Tokyo",
    "iso:country":"JP",
    "name:jpn_x_preferred":[
        "\u4f50\u6e21\u30f6\u8feb"
    ],
    "name:jpn_x_variant":[
        "\u3055\u3069\u304c\u3055\u3053",
        "\u30b5\u30c9\u30ac\u30b5\u30b3"
    ],
    "wof:name":"Sadogasato",
    "wof:placetype":"locality"
},
  "geometry": {"coordinates":[131.17358000000002,32.89899],"type":"Point"}
}