{
  "type": "Feature",
  "properties": {
    "gn:admin1_code":"4.0",
    "gn:admin2_code":"2112330.0",
    "gn:asciiname":"Matsubacho",
    "gn:country_code":"JP",
    "gn:dem":16,
    "gn:feature_class":"P",
    "gn:feature_code":"PPL",
    "gn:name":"Matsubach\u014d",
    "gn:population":0,
    "gn:timezone":"Asia/Tokyo",
    "iso:country":"JP",
    "name:jpn_x_preferred":[
        "\u677e\u8449\u753a"
    ],
    "name:und_x_variant":[
        "Matsubach\u014d"
    ],
    "wof:name":"Matsubacho",
    "wof:placetype":"locality"
},
  "geometry": {"coordinates":[139.97198,35.88886],"type":"Point"}
}