{
  "type": "Feature",
  "properties": {
    "gn:admin1_code":"16.0",
    "gn:admin2_code":"2129400.0",
    "gn:admin3_code":"3506.0",
    "gn:asciiname":"Hinowaki",
    "gn:country_code":"JP",
    "gn:dem":258,
    "gn:feature_class":"P",
    "gn:feature_code":"PPL",
    "gn:name":"Hinowaki",
    "gn:population":0,
    "gn:timezone":"Asia/Tokyo",
    "iso:country":"JP",
    "name:jpn_x_preferred":[
        "\u65e5\u30ce\u8107"
    ],
    "name:jpn_x_variant":[
        "\u3072\u306e\u308f\u304d",
        "\u30d2\u30ce\u30ef\u30ad"
    ],
    "wof:name":"Hinowaki",
    "wof:placetype":"locality"
},
  "geometry": {"coordinates":[141.40523000000005,40.26814],"type":"Point"}
}