{
  "type": "Feature",
  "properties": {
    "gn:admin1_code":"12.0",
    "gn:admin2_code":"7428076.0",
    "gn:admin3_code":"1543.0",
    "gn:asciiname":"Hinami",
    "gn:country_code":"JP",
    "gn:dem":120,
    "gn:feature_class":"P",
    "gn:feature_code":"PPL",
    "gn:name":"Hinami",
    "gn:population":0,
    "gn:timezone":"Asia/Tokyo",
    "iso:country":"JP",
    "name:jpn_x_preferred":[
        "\u65e5\u4e26"
    ],
    "name:jpn_x_variant":[
        "\u3072\u306a\u307f",
        "\u30d2\u30ca\u30df"
    ],
    "wof:name":"Hinami",
    "wof:placetype":"locality"
},
  "geometry": {"coordinates":[144.21461000000005,43.78911],"type":"Point"}
}