{
  "type": "Feature",
  "properties": {
    "gn:admin1_code":"21.0",
    "gn:admin2_code":"1864975.0",
    "gn:admin3_code":"43432.0",
    "gn:asciiname":"Ioji",
    "gn:country_code":"JP",
    "gn:dem":311,
    "gn:feature_class":"P",
    "gn:feature_code":"PPLL",
    "gn:name":"Ioji",
    "gn:population":0,
    "gn:timezone":"Asia/Tokyo",
    "iso:country":"JP",
    "name:jpn_x_preferred":[
        "\u533b\u738b\u5bfa"
    ],
    "name:jpn_x_variant":[
        "\u3044\u304a\u3058",
        "\u30a4\u30aa\u30b8"
    ],
    "wof:name":"Ioji",
    "wof:placetype":"locality"
},
  "geometry": {"coordinates":[130.91390000000001,32.81511],"type":"Point"}
}