{
  "type": "Feature",
  "properties": {
    "iso:country":"JP",
    "name:eng_x_preferred":[
        "Minamidai 5 Chome"
    ],
    "name:eng_x_variant":[
        "Minamidai 5 Choume",
        "Minamidai 5 Chome"
    ],
    "name:jpn_x_preferred":[
        "\uff15\u4e01\u76ee"
    ],
    "name:jpn_x_variant":[
        "\u307f\u306a\u307f\u3060\u3044 \uff15\u3061\u3087\u3046\u3081",
        "\u5357\u53f0 \uff15\u4e01\u76ee",
        "\uff15\u3061\u3087\u3046\u3081"
    ],
    "qs:gn_local":0,
    "qs:local_max":428,
    "qs:local_sum":2008,
    "qs:localhoods":25,
    "qs:name":"\uff15\u4e01\u76ee",
    "qs:name_adm0":"\u65e5\u672c",
    "qs:name_adm1":"\u795e\u5948\u5ddd\u770c",
    "qs:name_en":"Minamidai 5 Chome",
    "qs:name_lau":"\u5357\u53f0",
    "qs:name_local":"\u76f8\u6a21\u539f\u5e02",
    "qs:photo_max":104,
    "qs:photo_sum":136,
    "qs:placetype":"Suburb",
    "qs:quad_count":5,
    "qs:woe_adm0":23424856,
    "qs:woe_adm1":2345868,
    "qs:woe_adm2":0,
    "qs:woe_lau":28417041,
    "qs:woe_local":1118072,
    "qs:woe_ver":"7.10.0",
    "wof:lang":[
        "jpn"
    ],
    "wof:name":"\uff15\u4e01\u76ee",
    "wof:placetype":"neighbourhood"
},
  "geometry": {"coordinates":[139.42263199999999,35.515579],"type":"Point"}
}