{
  "type": "Feature",
  "properties": {
    "gn:admin1_code":"21.0",
    "gn:admin2_code":"1864975.0",
    "gn:admin3_code":"43423.0",
    "gn:asciiname":"Nakazono",
    "gn:country_code":"JP",
    "gn:dem":635,
    "gn:feature_class":"P",
    "gn:feature_code":"PPLL",
    "gn:name":"Nakazono",
    "gn:population":0,
    "gn:timezone":"Asia/Tokyo",
    "iso:country":"JP",
    "name:jpn_x_preferred":[
        "\u4e2d\u5712"
    ],
    "name:jpn_x_variant":[
        "\u306a\u304b\u305e\u306e",
        "\u30ca\u30ab\u30be\u30ce"
    ],
    "wof:name":"Nakazono",
    "wof:placetype":"locality"
},
  "geometry": {"coordinates":[131.10998000000001,33.06826],"type":"Point"}
}