{
  "type": "Feature",
  "properties": {
    "gn:admin1_code":"4.0",
    "gn:admin2_code":"1855071.0",
    "gn:asciiname":"Tsutsumine",
    "gn:country_code":"JP",
    "gn:dem":19,
    "gn:feature_class":"P",
    "gn:feature_code":"PPL",
    "gn:name":"Tsutsumine",
    "gn:population":0,
    "gn:timezone":"Asia/Tokyo",
    "iso:country":"JP",
    "name:jpn_x_preferred":[
        "\u5824\u6839"
    ],
    "wof:name":"Tsutsumine",
    "wof:placetype":"locality"
},
  "geometry": {"coordinates":[139.88749999999999,35.94018],"type":"Point"}
}