{
  "type": "Feature",
  "properties": {
    "gn:admin1_code":"47",
    "gn:admin2_code":"7415819.0",
    "gn:asciiname":"Nagama",
    "gn:country_code":"JP",
    "gn:dem":69,
    "gn:feature_class":"P",
    "gn:feature_code":"PPLL",
    "gn:name":"Nagama",
    "gn:population":0,
    "gn:timezone":"Asia/Tokyo",
    "iso:country":"JP",
    "name:jpn_x_preferred":[
        "\u9577\u9593"
    ],
    "name:jpn_x_variant":[
        "\u306a\u304c\u307e"
    ],
    "wof:name":"Nagama",
    "wof:placetype":"locality"
},
  "geometry": {"coordinates":[125.36103,24.77914],"type":"Point"}
}