{
  "type": "Feature",
  "properties": {
    "gn:admin1_code":"18.0",
    "gn:admin2_code":"7383999.0",
    "gn:admin3_code":"46491.0",
    "gn:asciiname":"Matsuyama",
    "gn:country_code":"JP",
    "gn:dem":205,
    "gn:feature_class":"P",
    "gn:feature_code":"PPLL",
    "gn:name":"Matsuyama",
    "gn:population":0,
    "gn:timezone":"Asia/Tokyo",
    "iso:country":"JP",
    "name:jpn_x_preferred":[
        "\u677e\u5c71"
    ],
    "wof:name":"Matsuyama",
    "wof:placetype":"locality"
},
  "geometry": {"coordinates":[130.7302,31.08644],"type":"Point"}
}