{
  "type": "Feature",
  "properties": {
    "gn:admin1_code":"36.0",
    "gn:admin2_code":"1854361.0",
    "gn:admin3_code":"32527.0",
    "gn:asciiname":"Usuge",
    "gn:country_code":"JP",
    "gn:dem":5,
    "gn:feature_class":"P",
    "gn:feature_code":"PPL",
    "gn:name":"Usuge",
    "gn:population":0,
    "gn:timezone":"Asia/Tokyo",
    "iso:country":"JP",
    "name:jpn_x_preferred":[
        "\u8584\u6bdb"
    ],
    "wof:name":"Usuge",
    "wof:placetype":"locality"
},
  "geometry": {"coordinates":[133.05686,36.00599000000001],"type":"Point"}
}