{
  "type": "Feature",
  "properties": {
    "gn:admin1_code":"2.0",
    "gn:admin2_code":"2113122.0",
    "gn:asciiname":"Yamatedai",
    "gn:country_code":"JP",
    "gn:dem":27,
    "gn:feature_class":"P",
    "gn:feature_code":"PPL",
    "gn:name":"Yamatedai",
    "gn:population":0,
    "gn:timezone":"Asia/Tokyo",
    "iso:country":"JP",
    "name:jpn_x_preferred":[
        "\u5c71\u624b\u53f0"
    ],
    "name:jpn_x_variant":[
        "\u3084\u307e\u3066\u3060\u3044",
        "\u30e4\u30de\u30c6\u30c0\u30a4"
    ],
    "wof:name":"Yamatedai",
    "wof:placetype":"locality"
},
  "geometry": {"coordinates":[140.15087,39.69373],"type":"Point"}
}