{
  "type": "Feature",
  "properties": {
    "gn:admin1_code":"19.0",
    "gn:admin2_code":"1860670.0",
    "gn:asciiname":"Sasuke",
    "gn:country_code":"JP",
    "gn:dem":34,
    "gn:feature_class":"P",
    "gn:feature_code":"PPL",
    "gn:name":"Sasuke",
    "gn:population":0,
    "gn:timezone":"Asia/Tokyo",
    "iso:country":"JP",
    "name:fra_x_preferred":[
        "Sasuke"
    ],
    "name:hin_x_preferred":[
        "\u0938\u093e\u0938\u0941\u0915\u0947"
    ],
    "name:ita_x_preferred":[
        "Sasuke"
    ],
    "name:jpn_x_preferred":[
        "\u4f50\u52a9"
    ],
    "name:jpn_x_variant":[
        "\u3055\u3059\u3051",
        "\u30b5\u30b9\u30b1"
    ],
    "name:msa_x_preferred":[
        "Sasuke"
    ],
    "name:spa_x_preferred":[
        "Sasuke"
    ],
    "name:tha_x_preferred":[
        "\u0e0b\u0e32\u0e2a\u0e36\u0e40\u0e01\u0e30"
    ],
    "name:zho_x_preferred":[
        "Sasuke"
    ],
    "wof:name":"Sasuke",
    "wof:placetype":"locality"
},
  "geometry": {"coordinates":[139.54227,35.32243],"type":"Point"}
}