{
  "type": "Feature",
  "properties": {
    "gn:admin1_code":"3.0",
    "gn:admin2_code":"2130225.0",
    "gn:asciiname":"Iwamicho",
    "gn:country_code":"JP",
    "gn:dem":23,
    "gn:feature_class":"P",
    "gn:feature_code":"PPL",
    "gn:name":"Iwamich\u014d",
    "gn:population":0,
    "gn:timezone":"Asia/Tokyo",
    "iso:country":"JP",
    "name:jpn_x_preferred":[
        "\u5ca9\u898b\u753a"
    ],
    "name:jpn_x_variant":[
        "\u3044\u308f\u307f\u3061\u3087\u3046",
        "\u30a4\u30ef\u30df\u30c1\u30e7\u30a6"
    ],
    "name:und_x_variant":[
        "Iwamich\u014d"
    ],
    "wof:name":"Iwamicho",
    "wof:placetype":"locality"
},
  "geometry": {"coordinates":[140.47648999999998,40.90428],"type":"Point"}
}