{
  "type": "Feature",
  "properties": {
    "gn:admin1_code":"4.0",
    "gn:admin2_code":"2112663.0",
    "gn:asciiname":"Isogaya",
    "gn:country_code":"JP",
    "gn:dem":21,
    "gn:feature_class":"P",
    "gn:feature_code":"PPL",
    "gn:name":"Isogaya",
    "gn:population":0,
    "gn:timezone":"Asia/Tokyo",
    "iso:country":"JP",
    "name:jpn_x_preferred":[
        "\u78ef\u30f6\u8c37"
    ],
    "name:jpn_x_variant":[
        "\u3044\u305d\u304c\u3084",
        "\u30a4\u30bd\u30ac\u30e4"
    ],
    "wof:name":"Isogaya",
    "wof:placetype":"locality"
},
  "geometry": {"coordinates":[140.13825,35.45681],"type":"Point"}
}