{
  "type": "Feature",
  "properties": {
    "gn:admin1_code":"10.0",
    "gn:admin2_code":"1861435.0",
    "gn:asciiname":"Yattajimamachi",
    "gn:country_code":"JP",
    "gn:dem":49,
    "gn:feature_class":"P",
    "gn:feature_code":"PPL",
    "gn:name":"Yattajimamachi",
    "gn:population":0,
    "gn:timezone":"Asia/Tokyo",
    "iso:country":"JP",
    "name:jpn_x_preferred":[
        "\u516b\u6597\u5cf6\u753a"
    ],
    "wof:name":"Yattajimamachi",
    "wof:placetype":"locality"
},
  "geometry": {"coordinates":[139.18940000000001,36.27155],"type":"Point"}
}