{
  "type": "Feature",
  "properties": {
    "gn:admin1_code":"01",
    "gn:admin2_code":"1849840.0",
    "gn:asciiname":"Akasaka",
    "gn:country_code":"JP",
    "gn:dem":160,
    "gn:feature_class":"P",
    "gn:feature_code":"PPL",
    "gn:name":"Akasaka",
    "gn:population":0,
    "gn:timezone":"Asia/Tokyo",
    "iso:country":"JP",
    "name:deu_x_preferred":[
        "Akasaka"
    ],
    "name:fra_x_preferred":[
        "Akasaka"
    ],
    "name:ita_x_preferred":[
        "Akasaka"
    ],
    "name:kor_x_preferred":[
        "\uc544\uce74\uc0ac\uce74"
    ],
    "name:rus_x_preferred":[
        "\u0410\u043a\u0430\u0441\u0430\u043a\u0430"
    ],
    "name:ukr_x_preferred":[
        "\u0410\u043a\u0430\u0441\u0430\u043a\u0430"
    ],
    "wof:name":"Akasaka",
    "wof:placetype":"locality"
},
  "geometry": {"coordinates":[137.30000000000001,34.85],"type":"Point"}
}