{
  "type": "Feature",
  "properties": {
    "gn:admin1_code":"01",
    "gn:admin2_code":"1849840.0",
    "gn:asciiname":"Akasaka",
    "gn:country_code":"JP",
    "gn:dem":160,
    "gn:feature_class":"P",
    "gn:feature_code":"PPL",
    "gn:name":"Akasaka",
    "gn:population":0,
    "gn:timezone":"Asia/Tokyo",
    "iso:country":"JP",
    "wof:name":"Akasaka",
    "wof:placetype":"locality"
},
  "geometry": {"coordinates":[137.30000000000001,34.85],"type":"Point"}
}