{
  "type": "Feature",
  "properties": {
    "gn:admin1_code":"28.0",
    "gn:admin2_code":"1848164.0",
    "gn:admin3_code":"29443.0",
    "gn:asciiname":"Tochihara",
    "gn:country_code":"JP",
    "gn:dem":272,
    "gn:feature_class":"P",
    "gn:feature_code":"PPL",
    "gn:name":"Tochihara",
    "gn:population":0,
    "gn:timezone":"Asia/Tokyo",
    "iso:country":"JP",
    "name:jpn_x_preferred":[
        "\u6803\u539f"
    ],
    "wof:name":"Tochihara",
    "wof:placetype":"locality"
},
  "geometry": {"coordinates":[135.77961000000002,34.3515],"type":"Point"}
}