{
  "type": "Feature",
  "properties": {
    "gn:admin1_code":"21.0",
    "gn:admin2_code":"1865358.0",
    "gn:asciiname":"Nishinokoba",
    "gn:country_code":"JP",
    "gn:dem":43,
    "gn:feature_class":"P",
    "gn:feature_code":"PPLL",
    "gn:name":"Nishinokoba",
    "gn:population":0,
    "gn:timezone":"Asia/Tokyo",
    "iso:country":"JP",
    "name:jpn_x_preferred":[
        "\u897f\u30ce\u6728\u5834"
    ],
    "name:jpn_x_variant":[
        "\u306b\u3057\u306e\u3053\u3070",
        "\u30cb\u30b7\u30ce\u30b3\u30d0"
    ],
    "wof:name":"Nishinokoba",
    "wof:placetype":"locality"
},
  "geometry": {"coordinates":[130.13456000000002,32.49983],"type":"Point"}
}