{
  "type": "Feature",
  "properties": {
    "iso:country":"JP",
    "name:eng_x_preferred":[
        "Nakamichi 1 Chome"
    ],
    "name:eng_x_variant":[
        "Nakamichi 1 Choume",
        "Nakamichi 1 Chome"
    ],
    "name:jpn_x_preferred":[
        "\uff11\u4e01\u76ee"
    ],
    "name:jpn_x_variant":[
        "\u306a\u304b\u307f\u3061 \uff11\u3061\u3087\u3046\u3081",
        "\u4e2d\u9053 \uff11\u4e01\u76ee",
        "\uff11\u3061\u3087\u3046\u3081"
    ],
    "qs:gn_local":0,
    "qs:local_max":1014,
    "qs:local_sum":3289,
    "qs:localhoods":8,
    "qs:name":"\uff11\u4e01\u76ee",
    "qs:name_adm0":"\u65e5\u672c",
    "qs:name_adm1":"\u5317\u6d77\u9053",
    "qs:name_en":"Nakamichi 1 Chome",
    "qs:name_lau":"\u4e2d\u9053",
    "qs:name_local":"\u51fd\u9928\u5e02",
    "qs:photo_max":322,
    "qs:photo_sum":1014,
    "qs:placetype":"Suburb",
    "qs:quad_count":25,
    "qs:woe_adm0":23424856,
    "qs:woe_adm1":7153351,
    "qs:woe_adm2":0,
    "qs:woe_lau":28380262,
    "qs:woe_local":1117148,
    "qs:woe_ver":"7.10.0",
    "wof:lang":[
        "jpn"
    ],
    "wof:name":"\uff11\u4e01\u76ee",
    "wof:placetype":"neighbourhood"
},
  "geometry": {"coordinates":[140.748628,41.799044],"type":"Point"}
}