{
  "type": "Feature",
  "properties": {
    "gn:admin1_code":"2.0",
    "gn:admin2_code":"9035660.0",
    "gn:asciiname":"Arayashiki",
    "gn:country_code":"JP",
    "gn:dem":58,
    "gn:feature_class":"P",
    "gn:feature_code":"PPL",
    "gn:name":"Arayashiki",
    "gn:population":0,
    "gn:timezone":"Asia/Tokyo",
    "iso:country":"JP",
    "name:jpn_x_preferred":[
        "\u8352\u5c4b\u6577"
    ],
    "wof:name":"Arayashiki",
    "wof:placetype":"locality"
},
  "geometry": {"coordinates":[140.55255,39.59095],"type":"Point"}
}