{
  "type": "Feature",
  "properties": {
    "gn:admin1_code":"4.0",
    "gn:admin2_code":"2112663.0",
    "gn:asciiname":"Yabu",
    "gn:country_code":"JP",
    "gn:dem":29,
    "gn:feature_class":"P",
    "gn:feature_code":"PPL",
    "gn:name":"Yabu",
    "gn:population":0,
    "gn:timezone":"Asia/Tokyo",
    "iso:country":"JP",
    "name:jpn_x_preferred":[
        "\u85ea"
    ],
    "name:jpn_x_variant":[
        "\u3084\u3076",
        "\u30e4\u30d6"
    ],
    "wof:name":"Yabu",
    "wof:placetype":"locality"
},
  "geometry": {"coordinates":[140.14909,35.3807],"type":"Point"}
}