{
  "type": "Feature",
  "properties": {
    "gn:admin1_code":"28.0",
    "gn:admin2_code":"1852501.0",
    "gn:admin3_code":"29362.0",
    "gn:asciiname":"Oyanagi",
    "gn:country_code":"JP",
    "gn:dem":36,
    "gn:feature_class":"P",
    "gn:feature_code":"PPL",
    "gn:name":"Oyanagi",
    "gn:population":0,
    "gn:timezone":"Asia/Tokyo",
    "iso:country":"JP",
    "name:jpn_x_preferred":[
        "\u5c0f\u67f3"
    ],
    "wof:name":"Oyanagi",
    "wof:placetype":"locality"
},
  "geometry": {"coordinates":[135.75686000000002,34.57762],"type":"Point"}
}