{
  "type": "Feature",
  "properties": {
    "gn:admin1_code":"32.0",
    "gn:admin2_code":"1857043.0",
    "gn:asciiname":"Nishijuku",
    "gn:country_code":"JP",
    "gn:dem":100,
    "gn:feature_class":"P",
    "gn:feature_code":"PPL",
    "gn:name":"Nishijuku",
    "gn:population":0,
    "gn:timezone":"Asia/Tokyo",
    "iso:country":"JP",
    "name:jpn_x_preferred":[
        "\u897f\u5bbf"
    ],
    "wof:name":"Nishijuku",
    "wof:placetype":"locality"
},
  "geometry": {"coordinates":[135.49266,34.82702],"type":"Point"}
}