{
  "type": "Feature",
  "properties": {
    "gn:admin1_code":"7.0",
    "gn:admin2_code":"1864591.0",
    "gn:asciiname":"Chikugo",
    "gn:country_code":"JP",
    "gn:dem":11,
    "gn:feature_class":"P",
    "gn:feature_code":"PPLA2",
    "gn:name":"Chikugo",
    "gn:population":0,
    "gn:timezone":"Asia/Tokyo",
    "iso:country":"JP",
    "name:ceb_x_preferred":[
        "Chikugo"
    ],
    "name:deu_x_preferred":[
        "Chikugo"
    ],
    "name:jpn_x_preferred":[
        "\u7b51\u5f8c"
    ],
    "name:kor_x_preferred":[
        "\uc9c0\ucfe0\uace0"
    ],
    "name:nld_x_preferred":[
        "Chikugo"
    ],
    "name:rus_x_preferred":[
        "\u0422\u0438\u043a\u0443\u0433\u043e"
    ],
    "wof:name":"Chikugo",
    "wof:placetype":"locality"
},
  "geometry": {"coordinates":[130.49182999999999,33.20537],"type":"Point"}
}