{
  "type": "Feature",
  "properties": {
    "gn:admin1_code":"19.0",
    "gn:admin2_code":"1861448.0",
    "gn:asciiname":"Nishiya",
    "gn:country_code":"JP",
    "gn:dem":13,
    "gn:feature_class":"P",
    "gn:feature_code":"PPLL",
    "gn:name":"Nishiya",
    "gn:population":0,
    "gn:timezone":"Asia/Tokyo",
    "iso:country":"JP",
    "name:jpn_x_preferred":[
        "\u897f\u5c4b"
    ],
    "wof:name":"Nishiya",
    "wof:placetype":"locality"
},
  "geometry": {"coordinates":[139.35017999999999,35.39645],"type":"Point"}
}