{
  "type": "Feature",
  "properties": {
    "gn:admin1_code":"21.0",
    "gn:admin2_code":"1864975.0",
    "gn:admin3_code":"43424.0",
    "gn:asciiname":"Suginohira",
    "gn:country_code":"JP",
    "gn:dem":477,
    "gn:feature_class":"P",
    "gn:feature_code":"PPLL",
    "gn:name":"Suginohira",
    "gn:population":0,
    "gn:timezone":"Asia/Tokyo",
    "iso:country":"JP",
    "name:jpn_x_preferred":[
        "\u6749\u5e73"
    ],
    "name:jpn_x_variant":[
        "\u3059\u304e\u306e\u3072\u3089",
        "\u30b9\u30ae\u30ce\u30d2\u30e9"
    ],
    "wof:name":"Suginohira",
    "wof:placetype":"locality"
},
  "geometry": {"coordinates":[131.00148999999999,33.12761],"type":"Point"}
}