{
  "type": "Feature",
  "properties": {
    "gn:admin1_code":"28.0",
    "gn:admin2_code":"1848164.0",
    "gn:admin3_code":"29446.0",
    "gn:asciiname":"Okigane",
    "gn:country_code":"JP",
    "gn:dem":604,
    "gn:feature_class":"P",
    "gn:feature_code":"PPL",
    "gn:name":"Okigane",
    "gn:population":0,
    "gn:timezone":"Asia/Tokyo",
    "iso:country":"JP",
    "name:jpn_x_preferred":[
        "\u6c96\u91d1"
    ],
    "wof:name":"Okigane",
    "wof:placetype":"locality"
},
  "geometry": {"coordinates":[135.85227,34.24117],"type":"Point"}
}