{
  "type": "Feature",
  "properties": {
    "iso:country":"JP",
    "name:eng_x_preferred":[
        "Myojincho 4 Chome"
    ],
    "name:eng_x_variant":[
        "Myoujinchou 4 Choume",
        "Myojincho 4 Chome"
    ],
    "name:jpn_x_preferred":[
        "\uff14\u4e01\u76ee"
    ],
    "name:jpn_x_variant":[
        "\u307f\u3087\u3046\u3058\u3093\u3061\u3087\u3046 \uff14\u3061\u3087\u3046\u3081",
        "\u660e\u795e\u753a \uff14\u4e01\u76ee",
        "\uff14\u3061\u3087\u3046\u3081"
    ],
    "qs:gn_adm0_cc":"JP",
    "qs:gn_local":1863440,
    "qs:local_max":1810,
    "qs:local_sum":4340,
    "qs:localhoods":23,
    "qs:name":"\uff14\u4e01\u76ee",
    "qs:name_adm0":"\u65e5\u672c",
    "qs:name_adm1":"\u6771\u4eac\u90fd",
    "qs:name_en":"Myojincho 4 Chome",
    "qs:name_lau":"\u660e\u795e\u753a",
    "qs:name_local":"\u516b\u738b\u5b50\u5e02",
    "qs:photo_max":45,
    "qs:photo_sum":124,
    "qs:placetype":"Suburb",
    "qs:quad_count":10,
    "qs:woe_adm0":23424856,
    "qs:woe_adm1":2345889,
    "qs:woe_adm2":0,
    "qs:woe_lau":28414883,
    "qs:woe_local":15015371,
    "qs:woe_ver":"7.10.0",
    "wof:lang":[
        "jpn"
    ],
    "wof:name":"\uff14\u4e01\u76ee",
    "wof:placetype":"neighbourhood"
},
  "geometry": {"coordinates":[139.34091900000001,35.6603],"type":"Point"}
}