{
  "type": "Feature",
  "properties": {
    "gn:admin1_code":"4.0",
    "gn:admin2_code":"2111854.0",
    "gn:asciiname":"Nagao",
    "gn:country_code":"JP",
    "gn:dem":15,
    "gn:feature_class":"P",
    "gn:feature_code":"PPL",
    "gn:name":"Nagao",
    "gn:population":0,
    "gn:timezone":"Asia/Tokyo",
    "iso:country":"JP",
    "name:jpn_x_preferred":[
        "\u9577\u5c3e"
    ],
    "name:jpn_x_variant":[
        "\u306a\u304c\u304a",
        "\u30ca\u30ac\u30aa"
    ],
    "wof:name":"Nagao",
    "wof:placetype":"locality"
},
  "geometry": {"coordinates":[140.29053999999999,35.46],"type":"Point"}
}