{
  "type": "Feature",
  "properties": {
    "gn:admin1_code":"23.0",
    "gn:admin2_code":"7417711.0",
    "gn:asciiname":"Nobonocho",
    "gn:country_code":"JP",
    "gn:dem":55,
    "gn:feature_class":"P",
    "gn:feature_code":"PPL",
    "gn:name":"Nobonoch\u014d",
    "gn:population":0,
    "gn:timezone":"Asia/Tokyo",
    "iso:country":"JP",
    "name:jpn_x_preferred":[
        "\u80fd\u8912\u91ce\u753a"
    ],
    "name:und_x_variant":[
        "Nobonoch\u014d"
    ],
    "wof:name":"Nobonocho",
    "wof:placetype":"locality"
},
  "geometry": {"coordinates":[136.48514,34.89403],"type":"Point"}
}