{
  "type": "Feature",
  "properties": {
    "gn:admin1_code":"16.0",
    "gn:admin2_code":"2112822.0",
    "gn:asciiname":"Minamisasama",
    "gn:country_code":"JP",
    "gn:dem":99,
    "gn:feature_class":"P",
    "gn:feature_code":"PPL",
    "gn:name":"Minamisasama",
    "gn:population":0,
    "gn:timezone":"Asia/Tokyo",
    "iso:country":"JP",
    "name:jpn_x_preferred":[
        "\u5357\u7b39\u9593"
    ],
    "name:jpn_x_variant":[
        "\u307f\u306a\u307f\u3055\u3055\u307e",
        "\u30df\u30ca\u30df\u30b5\u30b5\u30de"
    ],
    "wof:name":"Minamisasama",
    "wof:placetype":"locality"
},
  "geometry": {"coordinates":[141.05098999999996,39.33147],"type":"Point"}
}