{
  "type": "Feature",
  "properties": {
    "gn:admin1_code":"32.0",
    "gn:admin2_code":"1862751.0",
    "gn:asciiname":"Morigawachi-higashi",
    "gn:country_code":"JP",
    "gn:dem":3,
    "gn:feature_class":"P",
    "gn:feature_code":"PPL",
    "gn:name":"Morigawachi-higashi",
    "gn:population":0,
    "gn:timezone":"Asia/Tokyo",
    "iso:country":"JP",
    "name:jpn_x_preferred":[
        "\u68ee\u6cb3\u5185\u6771"
    ],
    "wof:name":"Morigawachi-higashi",
    "wof:placetype":"locality"
},
  "geometry": {"coordinates":[135.57154,34.68315],"type":"Point"}
}