{
  "type": "Feature",
  "properties": {
    "iso:country":"JP",
    "qs:name":"\u90a3\u73c2\u5ddd\u753a",
    "qs:name_adm0":"\u65e5\u672c",
    "qs:name_adm1":"\u6803\u6728\u770c",
    "qs:photos":249,
    "qs:photos_1k":50,
    "qs:photos_9k":1,
    "qs:photos_9r":4,
    "qs:photos_all":249,
    "qs:photos_sr":4,
    "qs:placetype":"Town",
    "qs:pop_sr":"0",
    "wof:name":"\u90a3\u73c2\u5ddd\u753a",
    "wof:placetype":"locality"
},
  "geometry": {"coordinates":[140.23215200000001,36.701755],"type":"Point"}
}