{
  "type": "Feature",
  "properties": {
    "gn:admin1_code":"18.0",
    "gn:admin2_code":"1851576.0",
    "gn:admin3_code":"46468.0",
    "gn:asciiname":"Kuroishi",
    "gn:country_code":"JP",
    "gn:dem":164,
    "gn:feature_class":"P",
    "gn:feature_code":"PPLL",
    "gn:name":"Kuroishi",
    "gn:population":0,
    "gn:timezone":"Asia/Tokyo",
    "iso:country":"JP",
    "name:jpn_x_preferred":[
        "\u9ed2\u77f3"
    ],
    "wof:name":"Kuroishi",
    "wof:placetype":"locality"
},
  "geometry": {"coordinates":[130.94519,31.46694],"type":"Point"}
}