{
  "type": "Feature",
  "properties": {
    "gn:admin1_code":"2.0",
    "gn:admin2_code":"2111153.0",
    "gn:admin3_code":"5434.0",
    "gn:asciiname":"Kanezawa",
    "gn:country_code":"JP",
    "gn:dem":74,
    "gn:feature_class":"P",
    "gn:feature_code":"PPL",
    "gn:name":"Kanezawa",
    "gn:population":0,
    "gn:timezone":"Asia/Tokyo",
    "iso:country":"JP",
    "name:jpn_x_preferred":[
        "\u91d1\u6ca2"
    ],
    "name:und_x_variant":[
        "Kanesawa",
        "Kanezawa"
    ],
    "wof:name":"Kanezawa",
    "wof:placetype":"locality"
},
  "geometry": {"coordinates":[140.57041999999998,39.3887],"type":"Point"}
}