{
  "type": "Feature",
  "properties": {
    "iso:country":"JP",
    "name:eng_x_preferred":[
        "Sugamo 1 Chome"
    ],
    "name:eng_x_variant":[
        "Sugamo 1 Choume",
        "Sugamo 1 Chome"
    ],
    "name:jpn_x_preferred":[
        "\uff11\u4e01\u76ee"
    ],
    "name:jpn_x_variant":[
        "\u3059\u304c\u3082 \uff11\u3061\u3087\u3046\u3081",
        "\u5de3\u9d28 \uff11\u4e01\u76ee",
        "\uff11\u3061\u3087\u3046\u3081"
    ],
    "qs:gn_adm0_cc":"JP",
    "qs:gn_local":1850147,
    "qs:local_max":18112,
    "qs:local_sum":895907,
    "qs:localhoods":857,
    "qs:name":"\uff11\u4e01\u76ee",
    "qs:name_adm0":"\u65e5\u672c",
    "qs:name_adm1":"\u6771\u4eac\u90fd",
    "qs:name_adm2":"\u8c4a\u5cf6\u533a",
    "qs:name_en":"Sugamo 1 Chome",
    "qs:name_lau":"\u5de3\u9d28",
    "qs:name_local":"\u6771\u4eac",
    "qs:photo_max":77,
    "qs:photo_sum":178,
    "qs:placetype":"Suburb",
    "qs:quad_count":6,
    "qs:woe_adm0":23424856,
    "qs:woe_adm1":2345889,
    "qs:woe_adm2":15015509,
    "qs:woe_lau":28414482,
    "qs:woe_local":1118370,
    "qs:woe_ver":"7.10.0",
    "qs_pg:name":"\uff11\u4e01\u76ee",
    "qs_pg:name_adm0":"\u65e5\u672c",
    "qs_pg:name_adm1":"\u6771\u4eac\u90fd",
    "qs_pg:photos":171,
    "qs_pg:photos_1k":35,
    "qs_pg:photos_9k":1,
    "qs_pg:photos_9r":4,
    "qs_pg:photos_all":171,
    "qs_pg:photos_sr":4,
    "qs_pg:pop_sr":0,
    "qs_pg:qs_pg_placetype":"neighbourhood",
    "qs_pg:qs_pg_placetype_gp":"Suburb",
    "qs_pg:woe_adm0":23424856,
    "woe:adm0_id":23424856,
    "woe:name_adm0":"\u65e5\u672c",
    "woe:name_adm1":"\u6771\u4eac\u90fd",
    "woe:placetype":"Suburb",
    "wof:lang":[
        "jpn"
    ],
    "wof:name":"\uff11\u4e01\u76ee",
    "wof:placetype":"neighbourhood"
},
  "geometry": {"coordinates":[139.739631,35.732971],"type":"Point"}
}