{
  "type": "Feature",
  "properties": {
    "gn:admin1_code":"18.0",
    "gn:admin2_code":"7383999.0",
    "gn:admin3_code":"46491.0",
    "gn:asciiname":"Myosako",
    "gn:country_code":"JP",
    "gn:dem":203,
    "gn:feature_class":"P",
    "gn:feature_code":"PPLL",
    "gn:name":"My\u014dsako",
    "gn:population":0,
    "gn:timezone":"Asia/Tokyo",
    "iso:country":"JP",
    "name:jpn_x_preferred":[
        "\u540d\u8feb"
    ],
    "name:und_x_variant":[
        "My\u014dsako"
    ],
    "wof:name":"Myosako",
    "wof:placetype":"locality"
},
  "geometry": {"coordinates":[130.82973999999999,31.22104],"type":"Point"}
}