{
  "type": "Feature",
  "properties": {
    "gn:admin1_code":"13.0",
    "gn:admin2_code":"1851005.0",
    "gn:asciiname":"Takasago",
    "gn:country_code":"JP",
    "gn:dem":2,
    "gn:feature_class":"P",
    "gn:feature_code":"PPLA2",
    "gn:name":"Takasago",
    "gn:population":0,
    "gn:timezone":"Asia/Tokyo",
    "iso:country":"JP",
    "name:ceb_x_preferred":[
        "Takasago"
    ],
    "name:deu_x_preferred":[
        "Takasago"
    ],
    "name:fin_x_preferred":[
        "Takasago"
    ],
    "name:jpn_x_preferred":[
        "\u9ad8\u7802"
    ],
    "name:kor_x_preferred":[
        "\ub2e4\uce74\uc0ac\uace0"
    ],
    "name:nld_x_preferred":[
        "Takasago"
    ],
    "name:rus_x_preferred":[
        "\u0422\u0430\u043a\u0430\u0441\u0430\u0433\u043e"
    ],
    "name:zho_x_preferred":[
        "\u9ad8\u7802"
    ],
    "wof:name":"Takasago",
    "wof:placetype":"locality"
},
  "geometry": {"coordinates":[134.79228999999998,34.76298],"type":"Point"}
}