{
  "type": "Feature",
  "properties": {
    "gn:admin1_code":"14.0",
    "gn:admin2_code":"6950859.0",
    "gn:asciiname":"Matsugaoka",
    "gn:country_code":"JP",
    "gn:dem":21,
    "gn:feature_class":"P",
    "gn:feature_code":"PPL",
    "gn:name":"Matsugaoka",
    "gn:population":0,
    "gn:timezone":"Asia/Tokyo",
    "iso:country":"JP",
    "name:jpn_x_preferred":[
        "\u677e\u30f6\u4e18"
    ],
    "wof:name":"Matsugaoka",
    "wof:placetype":"locality"
},
  "geometry": {"coordinates":[139.9838,35.94112],"type":"Point"}
}