{
  "type": "Feature",
  "properties": {
    "gn:admin1_code":"46.0",
    "gn:admin2_code":"7415914.0",
    "gn:asciiname":"Minami-Alps",
    "gn:country_code":"JP",
    "gn:dem":298,
    "gn:feature_class":"P",
    "gn:feature_code":"PPLA2",
    "gn:name":"Minami-Alps",
    "gn:population":0,
    "gn:timezone":"Asia/Tokyo",
    "iso:country":"JP",
    "name:jpn_x_preferred":[
        "\u5357\u30a2\u30eb\u30d7\u30b9"
    ],
    "wof:name":"Minami-Alps",
    "wof:placetype":"locality"
},
  "geometry": {"coordinates":[138.46343999999999,35.616],"type":"Point"}
}