{
  "type": "Feature",
  "properties": {
    "gn:admin1_code":"43.0",
    "gn:admin2_code":"1848936.0",
    "gn:asciiname":"Yata",
    "gn:country_code":"JP",
    "gn:dem":31,
    "gn:feature_class":"P",
    "gn:feature_code":"PPL",
    "gn:name":"Yata",
    "gn:population":0,
    "gn:timezone":"Asia/Tokyo",
    "iso:country":"JP",
    "name:jpn_x_preferred":[
        "\u77e2\u7530"
    ],
    "wof:name":"Yata",
    "wof:placetype":"locality"
},
  "geometry": {"coordinates":[135.25919999999999,34.21944000000001],"type":"Point"}
}