{
  "type": "Feature",
  "properties": {
    "gn:admin1_code":"42",
    "gn:admin2_code":"7391183.0",
    "gn:asciiname":"Inami",
    "gn:country_code":"JP",
    "gn:dem":139,
    "gn:feature_class":"P",
    "gn:feature_code":"PPL",
    "gn:name":"Inami",
    "gn:population":0,
    "gn:timezone":"Asia/Tokyo",
    "iso:country":"JP",
    "name:jpn_x_preferred":[
        "\u4e95\u6ce2"
    ],
    "wof:name":"Inami",
    "wof:placetype":"locality"
},
  "geometry": {"coordinates":[136.97543999999999,36.56258],"type":"Point"}
}