{
  "type": "Feature",
  "properties": {
    "gn:admin1_code":"47",
    "gn:admin2_code":"1858371.0",
    "gn:admin3_code":"47313.0",
    "gn:asciiname":"Sokei",
    "gn:country_code":"JP",
    "gn:dem":24,
    "gn:feature_class":"P",
    "gn:feature_code":"PPL",
    "gn:name":"Sokei",
    "gn:population":0,
    "gn:timezone":"Asia/Tokyo",
    "iso:country":"JP",
    "name:jpn_x_preferred":[
        "\u60e3\u6176"
    ],
    "name:und_x_variant":[
        "S\u014dkei",
        "S\u016bki",
        "S\u014dke",
        "Sokei"
    ],
    "wof:name":"Sokei",
    "wof:placetype":"locality"
},
  "geometry": {"coordinates":[127.97056000000001,26.47278],"type":"Point"}
}