{
  "type": "Feature",
  "properties": {
    "gn:admin1_code":"26.0",
    "gn:admin2_code":"7417078.0",
    "gn:asciiname":"Chikuma",
    "gn:country_code":"JP",
    "gn:dem":388,
    "gn:feature_class":"P",
    "gn:feature_code":"PPLA2",
    "gn:name":"Chikuma",
    "gn:population":0,
    "gn:timezone":"Asia/Tokyo",
    "iso:country":"JP",
    "name:ara_x_preferred":[
        "\u062a\u0634\u064a\u0643\u0648\u0645\u0627"
    ],
    "name:fas_x_preferred":[
        "\u0686\u06cc\u06a9\u0648\u0645\u0627\u060c \u0646\u0627\u06af\u0627\u0646\u0648"
    ],
    "name:hye_x_preferred":[
        "\u054f\u056b\u056f\u0578\u0582\u0574\u0561"
    ],
    "name:jpn_x_preferred":[
        "\u5343\u66f2"
    ],
    "name:jpn_x_variant":[
        "\u5343\u66f2\u5e02"
    ],
    "name:kor_x_preferred":[
        "\uc9c0\ucfe0\ub9c8 \uc2dc"
    ],
    "name:mzn_x_preferred":[
        "\u0686\u06cc\u06a9\u0648\u0645\u0627\u060c \u0646\u0627\u06af\u0627\u0646\u0648"
    ],
    "name:nan_x_preferred":[
        "Tikuma-chh\u012b"
    ],
    "name:rus_x_preferred":[
        "\u0422\u0438\u043a\u0443\u043c\u0430"
    ],
    "name:tgk_x_preferred":[
        "\u0427\u0438\u043a\u0443\u043c\u0430"
    ],
    "name:tha_x_preferred":[
        "\u0e0a\u0e34\u0e01\u0e38\u0e21\u0e30"
    ],
    "name:ukr_x_preferred":[
        "\u0422\u0456\u043a\u0443\u043c\u0430"
    ],
    "name:yue_x_preferred":[
        "\u5343\u66f2\u5e02"
    ],
    "name:zho_x_preferred":[
        "\u5343\u66f2\u5e02"
    ],
    "wof:name":"Chikuma",
    "wof:placetype":"locality"
},
  "geometry": {"coordinates":[138.08942999999999,36.52715],"type":"Point"}
}