{
  "type": "Feature",
  "properties": {
    "gn:admin1_code":"40.0",
    "gn:asciiname":"Kitamura",
    "gn:cc2":"JP",
    "gn:country_code":"JP",
    "gn:dem":-9999,
    "gn:feature_class":"P",
    "gn:feature_code":"PPL",
    "gn:name":"Kitamura",
    "gn:population":0,
    "gn:timezone":"Asia/Tokyo",
    "iso:country":"JP",
    "name:rus_x_preferred":[
        "\u041a\u0438\u0442\u0430\u043c\u0443\u0440\u0430"
    ],
    "name:und_x_variant":[
        "Kita",
        "Kitamura"
    ],
    "wof:name":"Kitamura",
    "wof:placetype":"locality"
},
  "geometry": {"coordinates":[142.11667,26.71667],"type":"Point"}
}