{
  "type": "Feature",
  "properties": {
    "gn:admin1_code":"19.0",
    "gn:admin2_code":"1848350.0",
    "gn:admin3_code":"14105.0",
    "gn:asciiname":"Idogaya-nakamachi",
    "gn:country_code":"JP",
    "gn:dem":6,
    "gn:feature_class":"P",
    "gn:feature_code":"PPL",
    "gn:name":"Idogaya-nakamachi",
    "gn:population":0,
    "gn:timezone":"Asia/Tokyo",
    "iso:country":"JP",
    "name:jpn_x_preferred":[
        "\u4e95\u571f\u30f6\u8c37\u4e2d\u753a"
    ],
    "name:jpn_x_variant":[
        "\u3044\u3069\u304c\u3084\u306a\u304b\u307e\u3061",
        "\u30a4\u30c9\u30ac\u30e4\u30ca\u30ab\u30de\u30c1"
    ],
    "wof:name":"Idogaya-nakamachi",
    "wof:placetype":"locality"
},
  "geometry": {"coordinates":[139.60263999999998,35.42968],"type":"Point"}
}