{
  "type": "Feature",
  "properties": {
    "gn:admin1_code":"35",
    "gn:admin2_code":"1856237.0",
    "gn:asciiname":"Kawamichicho",
    "gn:country_code":"JP",
    "gn:dem":89,
    "gn:feature_class":"P",
    "gn:feature_code":"PPL",
    "gn:name":"Kawamichich\u014d",
    "gn:population":0,
    "gn:timezone":"Asia/Tokyo",
    "iso:country":"JP",
    "name:und_x_variant":[
        "Kawamichich\u014d"
    ],
    "wof:name":"Kawamichicho",
    "wof:placetype":"locality"
},
  "geometry": {"coordinates":[136.23431000000002,35.399],"type":"Point"}
}