{
  "type": "Feature",
  "properties": {
    "gn:admin1_code":"4.0",
    "gn:admin2_code":"7465524.0",
    "gn:asciiname":"Sawazaki",
    "gn:country_code":"JP",
    "gn:dem":64,
    "gn:feature_class":"P",
    "gn:feature_code":"PPLL",
    "gn:name":"Sawazaki",
    "gn:population":0,
    "gn:timezone":"Asia/Tokyo",
    "iso:country":"JP",
    "name:jpn_x_preferred":[
        "\u6ca2\u5d0e"
    ],
    "name:jpn_x_variant":[
        "\u3055\u308f\u3056\u304d",
        "\u30b5\u30ef\u30b6\u30ad"
    ],
    "wof:name":"Sawazaki",
    "wof:placetype":"locality"
},
  "geometry": {"coordinates":[140.38061999999999,35.20078],"type":"Point"}
}