{
  "type": "Feature",
  "properties": {
    "gn:admin1_code":"21.0",
    "gn:admin2_code":"7412709.0",
    "gn:admin3_code":"43348.0",
    "gn:asciiname":"Shimobaru",
    "gn:country_code":"JP",
    "gn:dem":78,
    "gn:feature_class":"P",
    "gn:feature_code":"PPLL",
    "gn:name":"Shimobaru",
    "gn:population":0,
    "gn:timezone":"Asia/Tokyo",
    "iso:country":"JP",
    "name:jpn_x_preferred":[
        "\u4e0b\u539f"
    ],
    "name:jpn_x_variant":[
        "\u3057\u3082\u3070\u308b",
        "\u30b7\u30e2\u30d0\u30eb"
    ],
    "wof:name":"Shimobaru",
    "wof:placetype":"locality"
},
  "geometry": {"coordinates":[130.79751999999999,32.65448],"type":"Point"}
}