{
  "type": "Feature",
  "properties": {
    "gn:admin1_code":"2.0",
    "gn:admin2_code":"7443156.0",
    "gn:asciiname":"Maeyama",
    "gn:country_code":"JP",
    "gn:dem":29,
    "gn:feature_class":"P",
    "gn:feature_code":"PPL",
    "gn:name":"Maeyama",
    "gn:population":0,
    "gn:timezone":"Asia/Tokyo",
    "iso:country":"JP",
    "name:jpn_x_preferred":[
        "\u524d\u5c71"
    ],
    "wof:name":"Maeyama",
    "wof:placetype":"locality"
},
  "geometry": {"coordinates":[140.31691999999998,40.22169],"type":"Point"}
}