{
  "type": "Feature",
  "properties": {
    "gn:admin1_code":"21.0",
    "gn:admin2_code":"1848441.0",
    "gn:asciiname":"Sakamotomachi-fukami",
    "gn:country_code":"JP",
    "gn:dem":339,
    "gn:feature_class":"P",
    "gn:feature_code":"PPL",
    "gn:name":"Sakamotomachi-fukami",
    "gn:population":0,
    "gn:timezone":"Asia/Tokyo",
    "iso:country":"JP",
    "name:jpn_x_preferred":[
        "\u5742\u672c\u753a\u6df1\u6c34"
    ],
    "name:jpn_x_variant":[
        "\u3055\u304b\u3082\u3068\u307e\u3061\u3075\u304b\u307f",
        "\u30b5\u30ab\u30e2\u30c8\u30de\u30c1\u30d5\u30ab\u30df"
    ],
    "wof:name":"Sakamotomachi-fukami",
    "wof:placetype":"locality"
},
  "geometry": {"coordinates":[130.69399999999999,32.47503],"type":"Point"}
}