{
  "type": "Feature",
  "properties": {
    "gn:admin1_code":"24.0",
    "gn:admin2_code":"2111130.0",
    "gn:admin3_code":"4324.0",
    "gn:asciiname":"Nojomachi",
    "gn:country_code":"JP",
    "gn:dem":253,
    "gn:feature_class":"P",
    "gn:feature_code":"PPL",
    "gn:name":"Noj\u014dmachi",
    "gn:population":0,
    "gn:timezone":"Asia/Tokyo",
    "iso:country":"JP",
    "name:jpn_x_preferred":[
        "\u91ce\u4e0a\u753a"
    ],
    "name:und_x_variant":[
        "Noj\u014dmachi",
        "Noj\u014d"
    ],
    "wof:name":"Nojomachi",
    "wof:placetype":"locality"
},
  "geometry": {"coordinates":[140.59927999999999,38.19251],"type":"Point"}
}