{
  "type": "Feature",
  "properties": {
    "iso:country":"JP",
    "name:eng_x_preferred":[
        "Naritahigashi 3 Chome"
    ],
    "name:eng_x_variant":[
        "Naritahigashi 3 Choume",
        "Naritahigashi 3 Chome"
    ],
    "name:jpn_x_preferred":[
        "\uff13\u4e01\u76ee"
    ],
    "name:jpn_x_variant":[
        "\u306a\u308a\u305f\u3072\u304c\u3057 \uff13\u3061\u3087\u3046\u3081",
        "\u6210\u7530\u6771 \uff13\u4e01\u76ee",
        "\uff13\u3061\u3087\u3046\u3081"
    ],
    "qs:gn_adm0_cc":"JP",
    "qs:gn_local":1850147,
    "qs:local_max":18112,
    "qs:local_sum":895907,
    "qs:localhoods":857,
    "qs:name":"\uff13\u4e01\u76ee",
    "qs:name_adm0":"\u65e5\u672c",
    "qs:name_adm1":"\u6771\u4eac\u90fd",
    "qs:name_adm2":"\u6749\u4e26\u533a",
    "qs:name_en":"Naritahigashi 3 Chome",
    "qs:name_lau":"\u6210\u7530\u6771",
    "qs:name_local":"\u6771\u4eac",
    "qs:photo_max":303,
    "qs:photo_sum":811,
    "qs:placetype":"Suburb",
    "qs:quad_count":7,
    "qs:woe_adm0":23424856,
    "qs:woe_adm1":2345889,
    "qs:woe_adm2":15015379,
    "qs:woe_lau":28414465,
    "qs:woe_local":1118370,
    "qs:woe_ver":"7.10.0",
    "qs_pg:name":"\uff13\u4e01\u76ee",
    "qs_pg:name_adm0":"\u65e5\u672c",
    "qs_pg:name_adm1":"\u6771\u4eac\u90fd",
    "qs_pg:photos":316,
    "qs_pg:photos_1k":64,
    "qs_pg:photos_9k":1,
    "qs_pg:photos_9r":5,
    "qs_pg:photos_all":316,
    "qs_pg:photos_sr":5,
    "qs_pg:pop_sr":0,
    "qs_pg:qs_pg_placetype":"neighbourhood",
    "qs_pg:qs_pg_placetype_gp":"Suburb",
    "qs_pg:woe_adm0":23424856,
    "woe:adm0_id":23424856,
    "woe:name_adm0":"\u65e5\u672c",
    "woe:name_adm1":"\u6771\u4eac\u90fd",
    "woe:placetype":"Suburb",
    "wof:lang":[
        "jpn"
    ],
    "wof:name":"\uff13\u4e01\u76ee",
    "wof:placetype":"neighbourhood"
},
  "geometry": {"coordinates":[139.636202,35.694672],"type":"Point"}
}