{
  "type": "Feature",
  "properties": {
    "gn:admin1_code":"32.0",
    "gn:admin2_code":"1857043.0",
    "gn:asciiname":"Makiochi",
    "gn:country_code":"JP",
    "gn:dem":67,
    "gn:feature_class":"P",
    "gn:feature_code":"PPL",
    "gn:name":"Makiochi",
    "gn:population":0,
    "gn:timezone":"Asia/Tokyo",
    "iso:country":"JP",
    "name:jpn_x_preferred":[
        "\u7267\u843d"
    ],
    "wof:name":"Makiochi",
    "wof:placetype":"locality"
},
  "geometry": {"coordinates":[135.46950000000001,34.8236],"type":"Point"}
}