{
  "type": "Feature",
  "properties": {
    "gn:admin1_code":"2.0",
    "gn:admin2_code":"2129593.0",
    "gn:asciiname":"Takaya",
    "gn:country_code":"JP",
    "gn:dem":114,
    "gn:feature_class":"P",
    "gn:feature_code":"PPLL",
    "gn:name":"Takaya",
    "gn:population":0,
    "gn:timezone":"Asia/Tokyo",
    "iso:country":"JP",
    "name:jpn_x_preferred":[
        "\u9ad8\u5c4b"
    ],
    "name:jpn_x_variant":[
        "\u30bf\u30ab\u30e4"
    ],
    "wof:name":"Takaya",
    "wof:placetype":"locality"
},
  "geometry": {"coordinates":[140.77327,40.23565],"type":"Point"}
}