{
  "type": "Feature",
  "properties": {
    "gn:admin1_code":"28.0",
    "gn:admin2_code":"1863590.0",
    "gn:asciiname":"Higashiadacho",
    "gn:country_code":"JP",
    "gn:dem":145,
    "gn:feature_class":"P",
    "gn:feature_code":"PPL",
    "gn:name":"Higashiadach\u014d",
    "gn:population":0,
    "gn:timezone":"Asia/Tokyo",
    "iso:country":"JP",
    "name:jpn_x_preferred":[
        "\u6771\u963f\u7530\u753a"
    ],
    "name:und_x_variant":[
        "Higashiadach\u014d"
    ],
    "wof:name":"Higashiadacho",
    "wof:placetype":"locality"
},
  "geometry": {"coordinates":[135.75068999999999,34.37694],"type":"Point"}
}