{
  "type": "Feature",
  "properties": {
    "gn:admin1_code":"35.0",
    "gn:admin2_code":"1858984.0",
    "gn:asciiname":"Minakuchicho-kitanaiki",
    "gn:country_code":"JP",
    "gn:dem":163,
    "gn:feature_class":"P",
    "gn:feature_code":"PPL",
    "gn:name":"Minakuchich\u014d-kitanaiki",
    "gn:population":0,
    "gn:timezone":"Asia/Tokyo",
    "iso:country":"JP",
    "name:jpn_x_preferred":[
        "\u6c34\u53e3\u753a\u5317\u5185\u8cb4"
    ],
    "name:und_x_variant":[
        "Minakuchich\u014d-kitanaiki"
    ],
    "wof:name":"Minakuchicho-kitanaiki",
    "wof:placetype":"locality"
},
  "geometry": {"coordinates":[136.15386999999998,34.96213],"type":"Point"}
}