{
  "type": "Feature",
  "properties": {
    "gn:admin1_code":"21.0",
    "gn:admin2_code":"7413152.0",
    "gn:asciiname":"Matsubasemachi-matsuyama",
    "gn:country_code":"JP",
    "gn:dem":31,
    "gn:feature_class":"P",
    "gn:feature_code":"PPL",
    "gn:name":"Matsubasemachi-matsuyama",
    "gn:population":0,
    "gn:timezone":"Asia/Tokyo",
    "iso:country":"JP",
    "name:jpn_x_preferred":[
        "\u677e\u6a4b\u753a\u677e\u5c71"
    ],
    "name:jpn_x_variant":[
        "\u307e\u3064\u3070\u305b\u307e\u3061\u307e\u3064\u3084\u307e",
        "\u30de\u30c4\u30d0\u30bb\u30de\u30c1\u30de\u30c4\u30e4\u30de"
    ],
    "wof:name":"Matsubasemachi-matsuyama",
    "wof:placetype":"locality"
},
  "geometry": {"coordinates":[130.68169,32.65919],"type":"Point"}
}