{
  "type": "Feature",
  "properties": {
    "gn:admin1_code":"37.0",
    "gn:admin2_code":"1854900.0",
    "gn:asciiname":"Yanagihara",
    "gn:country_code":"JP",
    "gn:dem":6,
    "gn:feature_class":"P",
    "gn:feature_code":"PPLL",
    "gn:name":"Yanagihara",
    "gn:population":0,
    "gn:timezone":"Asia/Tokyo",
    "iso:country":"JP",
    "name:jpn_x_preferred":[
        "\u694a\u539f\u3000"
    ],
    "name:und_x_variant":[
        "Yanakihara"
    ],
    "wof:name":"Yanagihara",
    "wof:placetype":"locality"
},
  "geometry": {"coordinates":[138.87648000000002,35.08373],"type":"Point"}
}