{
  "type": "Feature",
  "properties": {
    "gn:admin1_code":"21.0",
    "gn:admin2_code":"1858418.0",
    "gn:admin3_code":"43104.0",
    "gn:asciiname":"Miyuki-nishi",
    "gn:country_code":"JP",
    "gn:dem":3,
    "gn:feature_class":"P",
    "gn:feature_code":"PPL",
    "gn:name":"Miyuki-nishi",
    "gn:population":0,
    "gn:timezone":"Asia/Tokyo",
    "iso:country":"JP",
    "name:jpn_x_preferred":[
        "\u5fa1\u5e78\u897f"
    ],
    "name:jpn_x_variant":[
        "\u307f\u3086\u304d\u306b\u3057",
        "\u30df\u30e6\u30ad\u30cb\u30b7"
    ],
    "wof:name":"Miyuki-nishi",
    "wof:placetype":"locality"
},
  "geometry": {"coordinates":[130.70417,32.75857],"type":"Point"}
}