{
  "type": "Feature",
  "properties": {
    "gn:admin1_code":"4.0",
    "gn:admin2_code":"2111854.0",
    "gn:asciiname":"Hayano",
    "gn:country_code":"JP",
    "gn:dem":10,
    "gn:feature_class":"P",
    "gn:feature_code":"PPL",
    "gn:name":"Hayano",
    "gn:population":0,
    "gn:timezone":"Asia/Tokyo",
    "iso:country":"JP",
    "name:jpn_x_preferred":[
        "\u65e9\u91ce"
    ],
    "name:jpn_x_variant":[
        "\u306f\u3084\u306e",
        "\u30cf\u30e4\u30ce"
    ],
    "wof:name":"Hayano",
    "wof:placetype":"locality"
},
  "geometry": {"coordinates":[140.2971,35.41562000000001],"type":"Point"}
}