{
  "type": "Feature",
  "properties": {
    "gn:admin1_code":"39.0",
    "gn:admin2_code":"1861303.0",
    "gn:admin3_code":"36403.0",
    "gn:asciiname":"Yakami",
    "gn:country_code":"JP",
    "gn:dem":6,
    "gn:feature_class":"P",
    "gn:feature_code":"PPL",
    "gn:name":"Yakami",
    "gn:population":0,
    "gn:timezone":"Asia/Tokyo",
    "iso:country":"JP",
    "name:jpn_x_preferred":[
        "\u77e2\u4e0a"
    ],
    "wof:name":"Yakami",
    "wof:placetype":"locality"
},
  "geometry": {"coordinates":[134.50184999999999,34.1385],"type":"Point"}
}