{
  "type": "Feature",
  "properties": {
    "gn:admin1_code":"9.0",
    "gn:admin2_code":"1850890.0",
    "gn:asciiname":"Kokufucho-nabari",
    "gn:country_code":"JP",
    "gn:dem":510,
    "gn:feature_class":"P",
    "gn:feature_code":"PPL",
    "gn:name":"Kokufuch\u014d-nabari",
    "gn:population":0,
    "gn:timezone":"Asia/Tokyo",
    "iso:country":"JP",
    "name:jpn_x_preferred":[
        "\u56fd\u5e9c\u753a\u540d\u5f35"
    ],
    "name:und_x_variant":[
        "Kokufuch\u014d-nabari"
    ],
    "wof:name":"Kokufucho-nabari",
    "wof:placetype":"locality"
},
  "geometry": {"coordinates":[137.21369999999999,36.206],"type":"Point"}
}