{
  "type": "Feature",
  "properties": {
    "iso:country":"JP",
    "name:eng_x_preferred":[
        "Seishin 3 Chome"
    ],
    "name:eng_x_variant":[
        "Seishin 3 Choume",
        "Seishin 3 Chome"
    ],
    "name:jpn_x_preferred":[
        "\uff13\u4e01\u76ee"
    ],
    "name:jpn_x_variant":[
        "\u305b\u3044\u3057\u3093 \uff13\u3061\u3087\u3046\u3081",
        "\u6e05\u65b0 \uff13\u4e01\u76ee",
        "\uff13\u3061\u3087\u3046\u3081"
    ],
    "qs:gn_local":0,
    "qs:local_max":428,
    "qs:local_sum":2008,
    "qs:localhoods":25,
    "qs:name":"\uff13\u4e01\u76ee",
    "qs:name_adm0":"\u65e5\u672c",
    "qs:name_adm1":"\u795e\u5948\u5ddd\u770c",
    "qs:name_en":"Seishin 3 Chome",
    "qs:name_lau":"\u6e05\u65b0",
    "qs:name_local":"\u76f8\u6a21\u539f\u5e02",
    "qs:photo_max":11,
    "qs:photo_sum":35,
    "qs:placetype":"Suburb",
    "qs:quad_count":6,
    "qs:woe_adm0":23424856,
    "qs:woe_adm1":2345868,
    "qs:woe_adm2":0,
    "qs:woe_lau":28417013,
    "qs:woe_local":1118072,
    "qs:woe_ver":"7.10.0",
    "wof:lang":[
        "jpn"
    ],
    "wof:name":"\uff13\u4e01\u76ee",
    "wof:placetype":"neighbourhood"
},
  "geometry": {"coordinates":[139.36737099999999,35.576569],"type":"Point"}
}