{
  "type": "Feature",
  "properties": {
    "gn:admin1_code":"24.0",
    "gn:admin2_code":"2112574.0",
    "gn:asciiname":"Samuraihama",
    "gn:country_code":"JP",
    "gn:dem":11,
    "gn:feature_class":"P",
    "gn:feature_code":"PPL",
    "gn:name":"Samuraihama",
    "gn:population":0,
    "gn:timezone":"Asia/Tokyo",
    "iso:country":"JP",
    "name:jpn_x_preferred":[
        "\u4f8d\u6d5c"
    ],
    "name:jpn_x_variant":[
        "\u3055\u3080\u3089\u3044\u306f\u307e",
        "\u30b5\u30e0\u30e9\u30a4\u30cf\u30de"
    ],
    "wof:name":"Samuraihama",
    "wof:placetype":"locality"
},
  "geometry": {"coordinates":[141.43393999999995,38.3836],"type":"Point"}
}