{
  "type": "Feature",
  "properties": {
    "gn:admin1_code":"21.0",
    "gn:admin2_code":"1865168.0",
    "gn:asciiname":"Nobarakita",
    "gn:country_code":"JP",
    "gn:dem":18,
    "gn:feature_class":"P",
    "gn:feature_code":"PPLL",
    "gn:name":"Nobarakita",
    "gn:population":0,
    "gn:timezone":"Asia/Tokyo",
    "iso:country":"JP",
    "name:jpn_x_preferred":[
        "\u91ce\u539f\u5317"
    ],
    "name:jpn_x_variant":[
        "\u306e\u3070\u3089\u304d\u305f",
        "\u30ce\u30d0\u30e9\u30ad\u30bf"
    ],
    "wof:name":"Nobarakita",
    "wof:placetype":"locality"
},
  "geometry": {"coordinates":[130.48331000000002,32.96044000000001],"type":"Point"}
}