{
  "type": "Feature",
  "properties": {
    "gn:admin1_code":"24.0",
    "gn:admin2_code":"2112092.0",
    "gn:asciiname":"Ohayashi",
    "gn:cc2":"JP",
    "gn:country_code":"JP",
    "gn:dem":12,
    "gn:feature_class":"P",
    "gn:feature_code":"PPL",
    "gn:name":"\u014chayashi",
    "gn:population":0,
    "gn:timezone":"Asia/Tokyo",
    "iso:country":"JP",
    "name:und_x_variant":[
        "\u014cbayashi",
        "\u014chayashi"
    ],
    "wof:name":"Ohayashi",
    "wof:placetype":"locality"
},
  "geometry": {"coordinates":[141.08333000000005,38.78333],"type":"Point"}
}