{
  "type": "Feature",
  "properties": {
    "gn:admin1_code":"7.0",
    "gn:admin2_code":"7407416.0",
    "gn:asciiname":"Isomitsu",
    "gn:country_code":"JP",
    "gn:dem":27,
    "gn:feature_class":"P",
    "gn:feature_code":"PPL",
    "gn:name":"Isomitsu",
    "gn:population":0,
    "gn:timezone":"Asia/Tokyo",
    "iso:country":"JP",
    "name:jpn_x_preferred":[
        "\u78ef\u5149"
    ],
    "wof:name":"Isomitsu",
    "wof:placetype":"locality"
},
  "geometry": {"coordinates":[130.68239,33.71669],"type":"Point"}
}