{
  "type": "Feature",
  "properties": {
    "gn:admin1_code":"19.0",
    "gn:admin2_code":"1848350.0",
    "gn:admin3_code":"14102.0",
    "gn:asciiname":"Matsumicho",
    "gn:country_code":"JP",
    "gn:dem":18,
    "gn:feature_class":"P",
    "gn:feature_code":"PPL",
    "gn:name":"Matsumich\u014d",
    "gn:population":0,
    "gn:timezone":"Asia/Tokyo",
    "iso:country":"JP",
    "name:jpn_x_preferred":[
        "\u677e\u898b\u753a"
    ],
    "name:jpn_x_variant":[
        "\u307e\u3064\u307f\u3061\u3087\u3046",
        "\u30de\u30c4\u30df\u30c1\u30e7\u30a6"
    ],
    "name:und_x_variant":[
        "Matsumich\u014d"
    ],
    "wof:name":"Matsumicho",
    "wof:placetype":"locality"
},
  "geometry": {"coordinates":[139.64064999999999,35.49928],"type":"Point"}
}