{
  "type": "Feature",
  "properties": {
    "gn:admin1_code":"19.0",
    "gn:admin2_code":"1864622.0",
    "gn:asciiname":"Enzo",
    "gn:country_code":"JP",
    "gn:dem":6,
    "gn:feature_class":"P",
    "gn:feature_code":"PPL",
    "gn:name":"Enz\u014d",
    "gn:population":0,
    "gn:timezone":"Asia/Tokyo",
    "iso:country":"JP",
    "name:deu_x_preferred":[
        "Enzo"
    ],
    "name:ita_x_preferred":[
        "Enzo"
    ],
    "name:jpn_x_preferred":[
        "\u5186\u8535"
    ],
    "name:spa_x_preferred":[
        "Enzo"
    ],
    "name:und_x_variant":[
        "Enz\u014d"
    ],
    "wof:name":"Enzo",
    "wof:placetype":"locality"
},
  "geometry": {"coordinates":[139.40522000000001,35.34429],"type":"Point"}
}