{
  "type": "Feature",
  "properties": {
    "gn:admin1_code":"37.0",
    "gn:admin2_code":"8301106.0",
    "gn:asciiname":"Tomata",
    "gn:country_code":"JP",
    "gn:dem":27,
    "gn:feature_class":"P",
    "gn:feature_code":"PPLL",
    "gn:name":"Tomata",
    "gn:population":0,
    "gn:timezone":"Asia/Tokyo",
    "iso:country":"JP",
    "name:jpn_x_preferred":[
        "\u7559\u7530"
    ],
    "wof:name":"Tomata",
    "wof:placetype":"locality"
},
  "geometry": {"coordinates":[139.08949999999999,35.01088],"type":"Point"}
}