{
  "type": "Feature",
  "properties": {
    "gn:admin1_code":"18.0",
    "gn:admin2_code":"7383999.0",
    "gn:admin3_code":"46491.0",
    "gn:asciiname":"Magarisako",
    "gn:country_code":"JP",
    "gn:dem":216,
    "gn:feature_class":"P",
    "gn:feature_code":"PPLL",
    "gn:name":"Magarisako",
    "gn:population":0,
    "gn:timezone":"Asia/Tokyo",
    "iso:country":"JP",
    "name:jpn_x_preferred":[
        "\u66f2\u8feb"
    ],
    "wof:name":"Magarisako",
    "wof:placetype":"locality"
},
  "geometry": {"coordinates":[130.81966,31.18254],"type":"Point"}
}