{
  "type": "Feature",
  "properties": {
    "gn:admin1_code":"4.0",
    "gn:admin2_code":"2112997.0",
    "gn:admin3_code":"12426.0",
    "gn:asciiname":"Oiwake",
    "gn:country_code":"JP",
    "gn:dem":115,
    "gn:feature_class":"P",
    "gn:feature_code":"PPLL",
    "gn:name":"Oiwake",
    "gn:population":0,
    "gn:timezone":"Asia/Tokyo",
    "iso:country":"JP",
    "name:jpn_x_preferred":[
        "\u8ffd\u5206"
    ],
    "name:jpn_x_variant":[
        "\u304a\u3044\u308f\u3051",
        "\u30aa\u30a4\u30ef\u30b1"
    ],
    "wof:name":"Oiwake",
    "wof:placetype":"locality"
},
  "geometry": {"coordinates":[140.19623000000001,35.46174],"type":"Point"}
}