{
  "type": "Feature",
  "properties": {
    "gn:admin1_code":"23.0",
    "gn:admin2_code":"1861901.0",
    "gn:asciiname":"Onogi",
    "gn:country_code":"JP",
    "gn:dem":144,
    "gn:feature_class":"P",
    "gn:feature_code":"PPL",
    "gn:name":"\u014cnogi",
    "gn:population":0,
    "gn:timezone":"Asia/Tokyo",
    "iso:country":"JP",
    "name:jpn_x_preferred":[
        "\u5927\u91ce\u6728"
    ],
    "name:und_x_variant":[
        "\u014cnogi"
    ],
    "wof:name":"Onogi",
    "wof:placetype":"locality"
},
  "geometry": {"coordinates":[136.10838000000001,34.74704000000001],"type":"Point"}
}