{
  "type": "Feature",
  "properties": {
    "gn:admin1_code":"3.0",
    "gn:admin2_code":"2130654.0",
    "gn:asciiname":"Nyunai",
    "gn:country_code":"JP",
    "gn:dem":151,
    "gn:feature_class":"P",
    "gn:feature_code":"PPL",
    "gn:name":"Ny\u016bnai",
    "gn:population":0,
    "gn:timezone":"Asia/Tokyo",
    "iso:country":"JP",
    "name:jpn_x_preferred":[
        "\u5165\u5185"
    ],
    "name:jpn_x_variant":[
        "\u306b\u3085\u3046\u306a\u3044",
        "\u30cb\u30e5\u30a6\u30ca\u30a4"
    ],
    "name:und_x_variant":[
        "Ny\u016bnai"
    ],
    "wof:name":"Nyunai",
    "wof:placetype":"locality"
},
  "geometry": {"coordinates":[140.71995999999999,40.72266],"type":"Point"}
}