{
  "type": "Feature",
  "properties": {
    "gn:admin1_code":"19",
    "gn:admin2_code":"1848308.0",
    "gn:asciiname":"Hinata",
    "gn:country_code":"JP",
    "gn:dem":4,
    "gn:feature_class":"P",
    "gn:feature_code":"PPLL",
    "gn:name":"Hinata",
    "gn:population":0,
    "gn:timezone":"Asia/Tokyo",
    "iso:country":"JP",
    "name:fra_x_preferred":[
        "Hinata"
    ],
    "name:jpn_x_preferred":[
        "\u65e5\u5411"
    ],
    "name:jpn_x_variant":[
        "\u3072\u306a\u305f",
        "\u30d2\u30ca\u30bf"
    ],
    "name:pol_x_preferred":[
        "Hinata"
    ],
    "name:und_x_variant":[
        "Hy\u016bga"
    ],
    "wof:name":"Hinata",
    "wof:placetype":"locality"
},
  "geometry": {"coordinates":[139.63564,35.30817000000001],"type":"Point"}
}