{
  "type": "Feature",
  "properties": {
    "gn:admin1_code":"46.0",
    "gn:admin2_code":"1864076.0",
    "gn:asciiname":"Fuji-yoshida",
    "gn:country_code":"JP",
    "gn:dem":777,
    "gn:feature_class":"P",
    "gn:feature_code":"PPLA2",
    "gn:name":"Fuji-yoshida",
    "gn:population":0,
    "gn:timezone":"Asia/Tokyo",
    "iso:country":"JP",
    "name:jpn_x_preferred":[
        "\u5bcc\u58eb\u5409\u7530"
    ],
    "wof:name":"Fuji-yoshida",
    "wof:placetype":"locality"
},
  "geometry": {"coordinates":[138.81122999999999,35.48486],"type":"Point"}
}