{
  "type": "Feature",
  "properties": {
    "gn:admin1_code":"4.0",
    "gn:admin2_code":"7465521.0",
    "gn:asciiname":"Mikado",
    "gn:country_code":"JP",
    "gn:dem":35,
    "gn:feature_class":"P",
    "gn:feature_code":"PPLL",
    "gn:name":"Mikado",
    "gn:population":0,
    "gn:timezone":"Asia/Tokyo",
    "iso:country":"JP",
    "name:cat_x_preferred":[
        "Mikado"
    ],
    "name:ces_x_preferred":[
        "Mik\u00e1do"
    ],
    "name:dan_x_preferred":[
        "Mikado"
    ],
    "name:deu_x_preferred":[
        "Mikado"
    ],
    "name:fra_x_preferred":[
        "Mikado"
    ],
    "name:hrv_x_preferred":[
        "Mikado"
    ],
    "name:hun_x_preferred":[
        "Mikado"
    ],
    "name:ita_x_preferred":[
        "Mikado"
    ],
    "name:jpn_x_preferred":[
        "\u795e\u9580"
    ],
    "name:jpn_x_variant":[
        "\u307f\u304b\u3069",
        "\u30df\u30ab\u30c9"
    ],
    "name:kor_x_preferred":[
        "\ubbf8\uce74\ub3c4"
    ],
    "name:ltz_x_preferred":[
        "Mikado"
    ],
    "name:nld_x_preferred":[
        "Mikado"
    ],
    "name:por_x_preferred":[
        "Mikado"
    ],
    "name:rus_x_preferred":[
        "\u041c\u0438\u043a\u0430\u0434\u043e"
    ],
    "name:slk_x_preferred":[
        "Mik\u00e1do"
    ],
    "name:spa_x_preferred":[
        "Mikado"
    ],
    "name:tur_x_preferred":[
        "Mikado"
    ],
    "wof:name":"Mikado",
    "wof:placetype":"locality"
},
  "geometry": {"coordinates":[139.94782000000001,35.0175],"type":"Point"}
}