{
  "type": "Feature",
  "properties": {
    "gn:admin1_code":"27",
    "gn:admin2_code":"7418804.0",
    "gn:asciiname":"Kamisakiyamacho",
    "gn:country_code":"JP",
    "gn:dem":10,
    "gn:feature_class":"P",
    "gn:feature_code":"PPL",
    "gn:name":"Kamisakiyamach\u014d",
    "gn:population":0,
    "gn:timezone":"Asia/Tokyo",
    "iso:country":"JP",
    "name:jpn_x_preferred":[
        "\u4e0a\u5d0e\u5c71\u753a"
    ],
    "name:und_x_variant":[
        "Kami-sakiyamag\u014d",
        "Kami-sakiyama",
        "Kamisakiyamach\u014d"
    ],
    "wof:name":"Kamisakiyamacho",
    "wof:placetype":"locality"
},
  "geometry": {"coordinates":[128.87461000000002,32.65239],"type":"Point"}
}