{
  "type": "Feature",
  "properties": {
    "gn:admin1_code":"34.0",
    "gn:admin2_code":"8304212.0",
    "gn:asciiname":"Beppu",
    "gn:country_code":"JP",
    "gn:dem":36,
    "gn:feature_class":"P",
    "gn:feature_code":"PPL",
    "gn:name":"Beppu",
    "gn:population":0,
    "gn:timezone":"Asia/Tokyo",
    "iso:country":"JP",
    "name:ara_x_preferred":[
        "\u0628\u064a\u0628\u0648"
    ],
    "name:azb_x_preferred":[
        "\u0628\u067e\u0648"
    ],
    "name:cat_x_preferred":[
        "Beppu"
    ],
    "name:ceb_x_preferred":[
        "Beppu"
    ],
    "name:ces_x_preferred":[
        "Beppu"
    ],
    "name:deu_x_preferred":[
        "Beppu"
    ],
    "name:est_x_preferred":[
        "Beppu"
    ],
    "name:eus_x_preferred":[
        "Beppu"
    ],
    "name:fas_x_preferred":[
        "\u0628\u067e\u0648"
    ],
    "name:fin_x_preferred":[
        "Beppu"
    ],
    "name:fra_x_preferred":[
        "Beppu"
    ],
    "name:glg_x_preferred":[
        "Beppu"
    ],
    "name:heb_x_preferred":[
        "\u05d1\u05e4\u05d5"
    ],
    "name:hun_x_preferred":[
        "Beppu"
    ],
    "name:ita_x_preferred":[
        "Beppu"
    ],
    "name:jpn_x_preferred":[
        "\u5225\u5e9c"
    ],
    "name:jpn_x_variant":[
        "\u5225\u5e9c\u5e02"
    ],
    "name:kat_x_preferred":[
        "\u10d1\u10d4\u10de\u10e3"
    ],
    "name:kor_x_preferred":[
        "\ubcb3\ud478\uc2dc"
    ],
    "name:lav_x_preferred":[
        "Bepu"
    ],
    "name:lit_x_preferred":[
        "Bepu"
    ],
    "name:mlg_x_preferred":[
        "Beppu"
    ],
    "name:mzn_x_preferred":[
        "\u0628\u067e\u0648"
    ],
    "name:nld_x_preferred":[
        "Beppu"
    ],
    "name:pol_x_preferred":[
        "Beppu"
    ],
    "name:por_x_preferred":[
        "Beppu"
    ],
    "name:ron_x_preferred":[
        "Beppu"
    ],
    "name:rus_x_preferred":[
        "\u0411\u0435\u043f\u043f\u0443"
    ],
    "name:spa_x_preferred":[
        "Beppu"
    ],
    "name:srp_x_preferred":[
        "\u0411\u0435\u043f\u0443"
    ],
    "name:swe_x_preferred":[
        "Beppu"
    ],
    "name:tgk_x_preferred":[
        "\u0411\u0435\u043f\u043f\u0443"
    ],
    "name:tgl_x_preferred":[
        "Beppu"
    ],
    "name:tha_x_preferred":[
        "\u0e40\u0e1a\u0e47\u0e1b\u0e1b\u0e38"
    ],
    "name:tum_x_preferred":[
        "Beppu"
    ],
    "name:tur_x_preferred":[
        "Beppu"
    ],
    "name:ukr_x_preferred":[
        "\u0411\u0435\u043f\u043f\u0443"
    ],
    "name:uzb_x_preferred":[
        "Beppu"
    ],
    "name:vie_x_preferred":[
        "Beppu"
    ],
    "name:war_x_preferred":[
        "Beppu"
    ],
    "name:zho_x_preferred":[
        "\u5225\u5e9c\u5e02"
    ],
    "wof:name":"Beppu",
    "wof:placetype":"locality"
},
  "geometry": {"coordinates":[139.33760000000001,36.1863],"type":"Point"}
}