{
  "type": "Feature",
  "properties": {
    "gn:admin1_code":"34.0",
    "gn:admin2_code":"8304212.0",
    "gn:asciiname":"Beppu",
    "gn:country_code":"JP",
    "gn:dem":36,
    "gn:feature_class":"P",
    "gn:feature_code":"PPL",
    "gn:name":"Beppu",
    "gn:population":0,
    "gn:timezone":"Asia/Tokyo",
    "iso:country":"JP",
    "name:jpn_x_preferred":[
        "\u5225\u5e9c"
    ],
    "wof:name":"Beppu",
    "wof:placetype":"locality"
},
  "geometry": {"coordinates":[139.33760000000001,36.1863],"type":"Point"}
}