{
  "type": "Feature",
  "properties": {
    "gn:admin1_code":"35.0",
    "gn:admin2_code":"1858063.0",
    "gn:asciiname":"Okamotocho",
    "gn:country_code":"JP",
    "gn:dem":112,
    "gn:feature_class":"P",
    "gn:feature_code":"PPL",
    "gn:name":"Okamotoch\u014d",
    "gn:population":0,
    "gn:timezone":"Asia/Tokyo",
    "iso:country":"JP",
    "name:jpn_x_preferred":[
        "\u5ca1\u672c\u753a"
    ],
    "name:und_x_variant":[
        "Okamotoch\u014d"
    ],
    "wof:name":"Okamotocho",
    "wof:placetype":"locality"
},
  "geometry": {"coordinates":[135.97922,34.99819],"type":"Point"}
}