{
  "type": "Feature",
  "properties": {
    "gn:admin1_code":"12.0",
    "gn:admin2_code":"7428087.0",
    "gn:admin3_code":"1432.0",
    "gn:asciiname":"Ruku",
    "gn:country_code":"JP",
    "gn:dem":208,
    "gn:feature_class":"P",
    "gn:feature_code":"PPL",
    "gn:name":"R\u016bku",
    "gn:population":0,
    "gn:timezone":"Asia/Tokyo",
    "iso:country":"JP",
    "wof:name":"Ruku",
    "wof:placetype":"locality"
},
  "geometry": {"coordinates":[141.68333000000001,43.58333],"type":"Point"}
}