{
  "type": "Feature",
  "properties": {
    "gn:admin1_code":"36.0",
    "gn:admin2_code":"7392548.0",
    "gn:admin3_code":"32343.0",
    "gn:asciiname":"Sakane",
    "gn:country_code":"JP",
    "gn:dem":538,
    "gn:feature_class":"P",
    "gn:feature_code":"PPL",
    "gn:name":"Sakane",
    "gn:population":0,
    "gn:timezone":"Asia/Tokyo",
    "iso:country":"JP",
    "name:jpn_x_preferred":[
        "\u5742\u6839"
    ],
    "wof:name":"Sakane",
    "wof:placetype":"locality"
},
  "geometry": {"coordinates":[133.11285000000001,35.10493],"type":"Point"}
}