{
  "type": "Feature",
  "properties": {
    "iso:country":"JP",
    "qs:name":"\u5927\u4e95",
    "qs:name_adm0":"\u65e5\u672c",
    "qs:name_adm1":"\u57fc\u7389\u770c",
    "qs:photos":7,
    "qs:photos_1k":1,
    "qs:photos_9k":1,
    "qs:photos_9r":2,
    "qs:photos_all":46,
    "qs:photos_sr":1,
    "qs:placetype":"LocalAdmin",
    "qs:pop_sr":"0",
    "wof:name":"\u5927\u4e95",
    "wof:placetype":"localadmin"
},
  "geometry": {"coordinates":[139.520309,35.836608],"type":"Point"}
}