{
  "type": "Feature",
  "properties": {
    "gn:admin1_code":"25",
    "gn:admin2_code":"1858035.0",
    "gn:asciiname":"Toi",
    "gn:country_code":"JP",
    "gn:dem":36,
    "gn:feature_class":"P",
    "gn:feature_code":"PPL",
    "gn:name":"Toi",
    "gn:population":0,
    "gn:timezone":"Asia/Tokyo",
    "iso:country":"JP",
    "name:ceb_x_preferred":[
        "Toi"
    ],
    "name:fra_x_preferred":[
        "Toi"
    ],
    "name:jpn_x_preferred":[
        "\u90fd\u4e95"
    ],
    "name:nld_x_preferred":[
        "Toi"
    ],
    "name:swe_x_preferred":[
        "Toi"
    ],
    "wof:name":"Toi",
    "wof:placetype":"locality"
},
  "geometry": {"coordinates":[131.31218000000001,31.39375],"type":"Point"}
}