{
  "type": "Feature",
  "properties": {
    "gn:admin1_code":"3.0",
    "gn:admin2_code":"2127674.0",
    "gn:asciiname":"Kitatai",
    "gn:country_code":"JP",
    "gn:dem":71,
    "gn:feature_class":"P",
    "gn:feature_code":"PPL",
    "gn:name":"Kitatai",
    "gn:population":0,
    "gn:timezone":"Asia/Tokyo",
    "iso:country":"JP",
    "name:jpn_x_preferred":[
        "\u5317\u5e73"
    ],
    "name:jpn_x_variant":[
        "\u304d\u305f\u305f\u3044",
        "\u30ad\u30bf\u30bf\u30a4"
    ],
    "wof:name":"Kitatai",
    "wof:placetype":"locality"
},
  "geometry": {"coordinates":[141.21870000000001,40.63291],"type":"Point"}
}