{
  "type": "Feature",
  "properties": {
    "gn:admin1_code":"36",
    "gn:admin2_code":"1857590.0",
    "gn:asciiname":"Motogumi",
    "gn:cc2":"JP",
    "gn:country_code":"JP",
    "gn:dem":676,
    "gn:feature_class":"P",
    "gn:feature_code":"PPL",
    "gn:name":"Motogumi",
    "gn:population":0,
    "gn:timezone":"Asia/Tokyo",
    "iso:country":"JP",
    "name:und_x_variant":[
        "Kami-michikawa",
        "Motogumi"
    ],
    "wof:name":"Motogumi",
    "wof:placetype":"locality"
},
  "geometry": {"coordinates":[132.08333000000002,34.63333],"type":"Point"}
}