{
  "type": "Feature",
  "properties": {
    "gn:admin1_code":"7.0",
    "gn:admin2_code":"7407412.0",
    "gn:asciiname":"Watari",
    "gn:country_code":"JP",
    "gn:dem":6,
    "gn:feature_class":"P",
    "gn:feature_code":"PPL",
    "gn:name":"Watari",
    "gn:population":0,
    "gn:timezone":"Asia/Tokyo",
    "iso:country":"JP",
    "name:ceb_x_preferred":[
        "Watari"
    ],
    "name:jpn_x_preferred":[
        "\u6e21"
    ],
    "wof:name":"Watari",
    "wof:placetype":"locality"
},
  "geometry": {"coordinates":[130.45699999999999,33.79187],"type":"Point"}
}