{
  "type": "Feature",
  "properties": {
    "gn:admin1_code":"21.0",
    "gn:admin2_code":"1848441.0",
    "gn:asciiname":"Agetsuchi",
    "gn:country_code":"JP",
    "gn:dem":2,
    "gn:feature_class":"P",
    "gn:feature_code":"PPLL",
    "gn:name":"Agetsuchi",
    "gn:population":0,
    "gn:timezone":"Asia/Tokyo",
    "iso:country":"JP",
    "name:jpn_x_preferred":[
        "\u4e0a\u571f"
    ],
    "name:jpn_x_variant":[
        "\u3042\u3052\u3064\u3061",
        "\u30a2\u30b2\u30c4\u30c1"
    ],
    "wof:name":"Agetsuchi",
    "wof:placetype":"locality"
},
  "geometry": {"coordinates":[130.65960999999999,32.54339],"type":"Point"}
}