{
  "type": "Feature",
  "properties": {
    "gn:admin1_code":"17.0",
    "gn:admin2_code":"9036694.0",
    "gn:asciiname":"Izuka",
    "gn:country_code":"JP",
    "gn:dem":11,
    "gn:feature_class":"P",
    "gn:feature_code":"PPLL",
    "gn:name":"Izuka",
    "gn:population":0,
    "gn:timezone":"Asia/Tokyo",
    "iso:country":"JP",
    "name:ceb_x_preferred":[
        "Iizuka"
    ],
    "name:deu_x_preferred":[
        "Iizuka"
    ],
    "name:ita_x_preferred":[
        "Iizuka"
    ],
    "name:jpn_x_preferred":[
        "\u732a\u585a"
    ],
    "wof:name":"Izuka",
    "wof:placetype":"locality"
},
  "geometry": {"coordinates":[134.26167000000001,34.32833],"type":"Point"}
}