{
  "type": "Feature",
  "properties": {
    "gn:admin1_code":"4.0",
    "gn:admin2_code":"8304237.0",
    "gn:asciiname":"Mafune",
    "gn:country_code":"JP",
    "gn:dem":28,
    "gn:feature_class":"P",
    "gn:feature_code":"PPL",
    "gn:name":"Mafune",
    "gn:population":0,
    "gn:timezone":"Asia/Tokyo",
    "iso:country":"JP",
    "name:jpn_x_preferred":[
        "\u771f\u821f"
    ],
    "name:jpn_x_variant":[
        "\u307e\u3075\u306d",
        "\u30de\u30d5\u30cd"
    ],
    "wof:name":"Mafune",
    "wof:placetype":"locality"
},
  "geometry": {"coordinates":[139.93362999999999,35.36009],"type":"Point"}
}