{
  "type": "Feature",
  "properties": {
    "iso:country":"JP",
    "name:eng_x_preferred":[
        "Honcho 6 Chome"
    ],
    "name:eng_x_variant":[
        "Honchou 6 Choume",
        "Honcho 6 Chome"
    ],
    "name:jpn_x_preferred":[
        "\uff16\u4e01\u76ee"
    ],
    "name:jpn_x_variant":[
        "\u307b\u3093\u3061\u3087\u3046 \uff16\u3061\u3087\u3046\u3081",
        "\u672c\u753a \uff16\u4e01\u76ee",
        "\uff16\u3061\u3087\u3046\u3081"
    ],
    "qs:gn_adm0_cc":"JP",
    "qs:gn_local":1859088,
    "qs:gn_nam_loc":"\u5c0f\u91d1\u4e95\u5e02, \u6771\u4eac\u90fd, JP",
    "qs:gn_namadm1":"40",
    "qs:local_max":1225,
    "qs:local_sum":2455,
    "qs:localhoods":9,
    "qs:name":"\uff16\u4e01\u76ee",
    "qs:name_adm0":"\u65e5\u672c",
    "qs:name_adm1":"\u6771\u4eac\u90fd",
    "qs:name_en":"Honcho 6 Chome",
    "qs:name_lau":"\u672c\u753a",
    "qs:name_local":"\u5c0f\u91d1\u4e95\u5e02",
    "qs:photo_max":33,
    "qs:photo_sum":86,
    "qs:placetype":"Suburb",
    "qs:quad_count":7,
    "qs:woe_adm0":23424856,
    "qs:woe_adm1":2345889,
    "qs:woe_adm2":0,
    "qs:woe_lau":28415128,
    "qs:woe_local":1110933,
    "qs:woe_ver":"7.10.0",
    "wof:lang":[
        "jpn"
    ],
    "wof:name":"\uff16\u4e01\u76ee",
    "wof:placetype":"neighbourhood"
},
  "geometry": {"coordinates":[139.50299799999999,35.699795],"type":"Point"}
}