{
  "type": "Feature",
  "properties": {
    "gn:admin1_code":"21.0",
    "gn:admin2_code":"1859488.0",
    "gn:asciiname":"Kitamiya",
    "gn:country_code":"JP",
    "gn:dem":57,
    "gn:feature_class":"P",
    "gn:feature_code":"PPL",
    "gn:name":"Kitamiya",
    "gn:population":0,
    "gn:timezone":"Asia/Tokyo",
    "iso:country":"JP",
    "name:jpn_x_preferred":[
        "\u5317\u5bae"
    ],
    "name:jpn_x_variant":[
        "\u304d\u305f\u307f\u3084",
        "\u30ad\u30bf\u30df\u30e4"
    ],
    "wof:name":"Kitamiya",
    "wof:placetype":"locality"
},
  "geometry": {"coordinates":[130.81088,32.97438],"type":"Point"}
}