{
  "type": "Feature",
  "properties": {
    "gn:admin1_code":"7.0",
    "gn:admin2_code":"1863955.0",
    "gn:admin3_code":"40135.0",
    "gn:asciiname":"Myobaru",
    "gn:country_code":"JP",
    "gn:dem":25,
    "gn:feature_class":"P",
    "gn:feature_code":"PPL",
    "gn:name":"My\u014dbaru",
    "gn:population":0,
    "gn:timezone":"Asia/Tokyo",
    "iso:country":"JP",
    "name:jpn_x_preferred":[
        "\u5973\u539f"
    ],
    "name:und_x_variant":[
        "My\u014dbaru"
    ],
    "wof:name":"Myobaru",
    "wof:placetype":"locality"
},
  "geometry": {"coordinates":[130.26598000000001,33.57088],"type":"Point"}
}