{
  "type": "Feature",
  "properties": {
    "gn:admin1_code":"21.0",
    "gn:admin2_code":"1864973.0",
    "gn:asciiname":"Okura",
    "gn:country_code":"JP",
    "gn:dem":494,
    "gn:feature_class":"P",
    "gn:feature_code":"PPL",
    "gn:name":"Okura",
    "gn:population":0,
    "gn:timezone":"Asia/Tokyo",
    "iso:country":"JP",
    "name:ceb_x_preferred":[
        "Okura"
    ],
    "name:deu_x_preferred":[
        "Okura"
    ],
    "name:jpn_x_preferred":[
        "\u5c0f\u5009"
    ],
    "name:jpn_x_variant":[
        "\u304a\u304f\u3089",
        "\u30aa\u30af\u30e9"
    ],
    "name:swe_x_preferred":[
        "Okura"
    ],
    "wof:name":"Okura",
    "wof:placetype":"locality"
},
  "geometry": {"coordinates":[131.07973000000001,32.98205],"type":"Point"}
}