{
  "type": "Feature",
  "properties": {
    "iso:country":"JP",
    "qs:name":"\uff11\u4e01\u76ee",
    "qs:name_adm0":"\u65e5\u672c",
    "qs:name_adm1":"\u6c96\u7e04\u770c",
    "qs:photos":1148,
    "qs:photos_1k":233,
    "qs:photos_9k":5,
    "qs:photos_9r":7,
    "qs:photos_all":1148,
    "qs:photos_sr":11,
    "qs:placetype":"Suburb",
    "qs:pop_sr":"0",
    "wof:name":"\uff11\u4e01\u76ee",
    "wof:placetype":"neighbourhood"
},
  "geometry": {"coordinates":[127.704644,26.228893],"type":"Point"}
}