{
  "type": "Feature",
  "properties": {
    "gn:admin1_code":"24.0",
    "gn:admin2_code":"2112261.0",
    "gn:asciiname":"Budo",
    "gn:country_code":"JP",
    "gn:dem":40,
    "gn:feature_class":"P",
    "gn:feature_code":"PPL",
    "gn:name":"Bud\u014d",
    "gn:population":0,
    "gn:timezone":"Asia/Tokyo",
    "iso:country":"JP",
    "name:jpn_x_preferred":[
        "\u8461\u8404"
    ],
    "name:jpn_x_variant":[
        "\u3076\u3069\u3046",
        "\u30d6\u30c9\u30a6"
    ],
    "name:und_x_variant":[
        "Bud\u014d"
    ],
    "wof:name":"Budo",
    "wof:placetype":"locality"
},
  "geometry": {"coordinates":[141.61671000000001,38.87783],"type":"Point"}
}