{
  "type": "Feature",
  "properties": {
    "gn:admin1_code":"29",
    "gn:admin2_code":"1855427.0",
    "gn:admin3_code":"15103.0",
    "gn:asciiname":"Nishifunamicho",
    "gn:country_code":"JP",
    "gn:dem":18,
    "gn:feature_class":"P",
    "gn:feature_code":"PPL",
    "gn:name":"Nishifunamich\u014d",
    "gn:population":0,
    "gn:timezone":"Asia/Tokyo",
    "iso:country":"JP",
    "name:jpn_x_preferred":[
        "\u897f\u8239\u898b\u753a"
    ],
    "name:und_x_variant":[
        "Nishifunamich\u014d",
        "Nishi-funamich\u014d"
    ],
    "wof:name":"Nishifunamicho",
    "wof:placetype":"locality"
},
  "geometry": {"coordinates":[139.03034,37.92313],"type":"Point"}
}