{
  "type": "Feature",
  "properties": {
    "gn:admin1_code":"12.0",
    "gn:admin2_code":"7428085.0",
    "gn:admin3_code":"1303.0",
    "gn:asciiname":"Nakagoya",
    "gn:country_code":"JP",
    "gn:dem":10,
    "gn:feature_class":"P",
    "gn:feature_code":"PPL",
    "gn:name":"Nakagoya",
    "gn:population":0,
    "gn:timezone":"Asia/Tokyo",
    "iso:country":"JP",
    "wof:name":"Nakagoya",
    "wof:placetype":"locality"
},
  "geometry": {"coordinates":[141.59999999999999,43.28333],"type":"Point"}
}