{
  "type": "Feature",
  "properties": {
    "gn:admin1_code":"47",
    "gn:admin2_code":"1855990.0",
    "gn:admin3_code":"47326.0",
    "gn:asciiname":"Sunabe",
    "gn:country_code":"JP",
    "gn:dem":11,
    "gn:feature_class":"P",
    "gn:feature_code":"PPL",
    "gn:name":"Sunabe",
    "gn:population":0,
    "gn:timezone":"Asia/Tokyo",
    "iso:country":"JP",
    "name:jpn_x_preferred":[
        "\u7802\u8fba"
    ],
    "name:jpn_x_variant":[
        "\u3059\u306a\u3079"
    ],
    "name:und_x_variant":[
        "Sunabi",
        "Sunabie",
        "Sunabe"
    ],
    "wof:name":"Sunabe",
    "wof:placetype":"locality"
},
  "geometry": {"coordinates":[127.74863999999999,26.33361],"type":"Point"}
}