{
  "type": "Feature",
  "properties": {
    "gn:admin1_code":"14.0",
    "gn:admin2_code":"6950859.0",
    "gn:asciiname":"Shimokawagishi",
    "gn:country_code":"JP",
    "gn:dem":8,
    "gn:feature_class":"P",
    "gn:feature_code":"PPLL",
    "gn:name":"Shimokawagishi",
    "gn:population":0,
    "gn:timezone":"Asia/Tokyo",
    "iso:country":"JP",
    "name:jpn_x_preferred":[
        "\u4e0b\u5ddd\u5cb8\u3000"
    ],
    "wof:name":"Shimokawagishi",
    "wof:placetype":"locality"
},
  "geometry": {"coordinates":[139.95967999999999,35.93733],"type":"Point"}
}