{
  "type": "Feature",
  "properties": {
    "gn:admin1_code":"29.0",
    "gn:admin2_code":"1849786.0",
    "gn:asciiname":"Yotsuya",
    "gn:country_code":"JP",
    "gn:dem":4,
    "gn:feature_class":"P",
    "gn:feature_code":"PPL",
    "gn:name":"Yotsuya",
    "gn:population":0,
    "gn:timezone":"Asia/Tokyo",
    "iso:country":"JP",
    "name:jpn_x_preferred":[
        "\u56db\u30c4\u5c4b"
    ],
    "wof:name":"Yotsuya",
    "wof:placetype":"locality"
},
  "geometry": {"coordinates":[138.95665,37.67916],"type":"Point"}
}