{
  "type": "Feature",
  "properties": {
    "gn:admin1_code":"47.0",
    "gn:admin2_code":"1850107.0",
    "gn:asciiname":"Bin",
    "gn:country_code":"JP",
    "gn:dem":25,
    "gn:feature_class":"P",
    "gn:feature_code":"PPL",
    "gn:name":"Bin",
    "gn:population":0,
    "gn:timezone":"Asia/Tokyo",
    "iso:country":"JP",
    "name:jpn_x_preferred":[
        "\u4fdd\u6804\u8302"
    ],
    "wof:name":"Bin",
    "wof:placetype":"locality"
},
  "geometry": {"coordinates":[127.67542,26.16603],"type":"Point"}
}