{
  "type": "Feature",
  "properties": {
    "gn:admin1_code":"34.0",
    "gn:admin2_code":"1859726.0",
    "gn:asciiname":"Genzaemon-shinden",
    "gn:country_code":"JP",
    "gn:dem":17,
    "gn:feature_class":"P",
    "gn:feature_code":"PPL",
    "gn:name":"Genzaemon-shinden",
    "gn:population":0,
    "gn:timezone":"Asia/Tokyo",
    "iso:country":"JP",
    "name:jpn_x_preferred":[
        "\u6e90\u5de6\u885b\u9580\u65b0\u7530"
    ],
    "name:jpn_x_variant":[
        "\u3052\u3093\u3056\u3048\u3082\u3093\u3057\u3093\u3067\u3093",
        "\u30b2\u30f3\u30b6\u30a8\u30e2\u30f3\u30b7\u30f3\u30c7\u30f3"
    ],
    "wof:name":"Genzaemon-shinden",
    "wof:placetype":"locality"
},
  "geometry": {"coordinates":[139.72927000000001,35.8628],"type":"Point"}
}