{
  "type": "Feature",
  "properties": {
    "gn:admin1_code":"21.0",
    "gn:admin2_code":"1848443.0",
    "gn:admin3_code":"43468.0",
    "gn:asciiname":"Nakaamido",
    "gn:country_code":"JP",
    "gn:dem":-2,
    "gn:feature_class":"P",
    "gn:feature_code":"PPLL",
    "gn:name":"Nakaamid\u014d",
    "gn:population":0,
    "gn:timezone":"Asia/Tokyo",
    "iso:country":"JP",
    "name:jpn_x_preferred":[
        "\u4e2d\u7db2\u9053"
    ],
    "name:jpn_x_variant":[
        "\u306a\u304b\u3042\u307f\u3069\u3046",
        "\u30ca\u30ab\u30a2\u30df\u30c9\u30a6"
    ],
    "name:und_x_variant":[
        "Nakaamid\u014d"
    ],
    "wof:name":"Nakaamido",
    "wof:placetype":"locality"
},
  "geometry": {"coordinates":[130.66370000000001,32.59658],"type":"Point"}
}