{
  "type": "Feature",
  "properties": {
    "gn:admin1_code":"18",
    "gn:admin2_code":"7383991.0",
    "gn:asciiname":"Harimochi",
    "gn:country_code":"JP",
    "gn:dem":343,
    "gn:feature_class":"P",
    "gn:feature_code":"PPL",
    "gn:name":"Harimochi",
    "gn:population":0,
    "gn:timezone":"Asia/Tokyo",
    "iso:country":"JP",
    "wof:name":"Harimochi",
    "wof:placetype":"locality"
},
  "geometry": {"coordinates":[130.58333000000002,31.96667],"type":"Point"}
}