{
  "type": "Feature",
  "properties": {
    "gn:admin1_code":"16.0",
    "gn:admin2_code":"2128940.0",
    "gn:asciiname":"Koiwai",
    "gn:country_code":"JP",
    "gn:dem":363,
    "gn:feature_class":"P",
    "gn:feature_code":"PPL",
    "gn:name":"Koiwai",
    "gn:population":0,
    "gn:timezone":"Asia/Tokyo",
    "iso:country":"JP",
    "name:jpn_x_preferred":[
        "\u5c0f\u795d"
    ],
    "name:jpn_x_variant":[
        "\u3053\u3044\u308f\u3044",
        "\u30b3\u30a4\u30ef\u30a4"
    ],
    "wof:name":"Koiwai",
    "wof:placetype":"locality"
},
  "geometry": {"coordinates":[141.35897,40.24679],"type":"Point"}
}