{
  "type": "Feature",
  "properties": {
    "gn:admin1_code":"34.0",
    "gn:admin2_code":"1849187.0",
    "gn:admin3_code":"11104.0",
    "gn:asciiname":"Higashimiyashita",
    "gn:country_code":"JP",
    "gn:dem":13,
    "gn:feature_class":"P",
    "gn:feature_code":"PPL",
    "gn:name":"Higashimiyashita",
    "gn:population":0,
    "gn:timezone":"Asia/Tokyo",
    "iso:country":"JP",
    "name:jpn_x_preferred":[
        "\u6771\u5bae\u4e0b"
    ],
    "name:jpn_x_variant":[
        "\u3072\u304c\u3057\u307f\u3084\u3057\u305f",
        "\u30d2\u30ac\u30b7\u30df\u30e4\u30b7\u30bf"
    ],
    "wof:name":"Higashimiyashita",
    "wof:placetype":"locality"
},
  "geometry": {"coordinates":[139.67948999999999,35.93125],"type":"Point"}
}