{
  "type": "Feature",
  "properties": {
    "gn:admin1_code":"19.0",
    "gn:admin2_code":"1848350.0",
    "gn:admin3_code":"14105.0",
    "gn:asciiname":"Mutsukawa",
    "gn:country_code":"JP",
    "gn:dem":41,
    "gn:feature_class":"P",
    "gn:feature_code":"PPL",
    "gn:name":"Mutsukawa",
    "gn:population":0,
    "gn:timezone":"Asia/Tokyo",
    "iso:country":"JP",
    "name:jpn_x_preferred":[
        "\u516d\u30c3\u5ddd"
    ],
    "name:jpn_x_variant":[
        "\u3080\u3064\u304b\u308f",
        "\u30e0\u30c4\u30ab\u30ef"
    ],
    "wof:name":"Mutsukawa",
    "wof:placetype":"locality"
},
  "geometry": {"coordinates":[139.58299,35.42429],"type":"Point"}
}