{
  "type": "Feature",
  "properties": {
    "gn:admin1_code":"21.0",
    "gn:admin2_code":"7412705.0",
    "gn:admin3_code":"43482.0",
    "gn:asciiname":"Ebirase",
    "gn:country_code":"JP",
    "gn:dem":78,
    "gn:feature_class":"P",
    "gn:feature_code":"PPL",
    "gn:name":"Ebirase",
    "gn:population":0,
    "gn:timezone":"Asia/Tokyo",
    "iso:country":"JP",
    "name:jpn_x_preferred":[
        "\u7b99\u702c"
    ],
    "name:jpn_x_variant":[
        "\u3048\u3073\u3089\u305b",
        "\u30a8\u30d3\u30e9\u30bb"
    ],
    "wof:name":"Ebirase",
    "wof:placetype":"locality"
},
  "geometry": {"coordinates":[130.60248999999999,32.32163],"type":"Point"}
}