{
  "type": "Feature",
  "properties": {
    "gn:admin1_code":"32.0",
    "gn:admin2_code":"1848519.0",
    "gn:asciiname":"Kinomoto",
    "gn:country_code":"JP",
    "gn:dem":13,
    "gn:feature_class":"P",
    "gn:feature_code":"PPL",
    "gn:name":"Kinomoto",
    "gn:population":0,
    "gn:timezone":"Asia/Tokyo",
    "iso:country":"JP",
    "name:jpn_x_preferred":[
        "\u6728\u306e\u672c"
    ],
    "wof:name":"Kinomoto",
    "wof:placetype":"locality"
},
  "geometry": {"coordinates":[135.58701000000002,34.60071],"type":"Point"}
}