{
  "type": "Feature",
  "properties": {
    "gn:admin1_code":"42.0",
    "gn:admin2_code":"1851028.0",
    "gn:asciiname":"Fukuokamachi-torikura",
    "gn:country_code":"JP",
    "gn:dem":16,
    "gn:feature_class":"P",
    "gn:feature_code":"PPL",
    "gn:name":"Fukuokamachi-torikura",
    "gn:population":0,
    "gn:timezone":"Asia/Tokyo",
    "iso:country":"JP",
    "name:jpn_x_preferred":[
        "\u798f\u5ca1\u753a\u9ce5\u5009"
    ],
    "wof:name":"Fukuokamachi-torikura",
    "wof:placetype":"locality"
},
  "geometry": {"coordinates":[136.91883999999999,36.72125],"type":"Point"}
}