{
  "type": "Feature",
  "properties": {
    "gn:admin1_code":"33.0",
    "gn:admin2_code":"1855238.0",
    "gn:admin3_code":"41401.0",
    "gn:asciiname":"Kusunokibaru",
    "gn:country_code":"JP",
    "gn:dem":85,
    "gn:feature_class":"P",
    "gn:feature_code":"PPL",
    "gn:name":"Kusunokibaru",
    "gn:population":0,
    "gn:timezone":"Asia/Tokyo",
    "iso:country":"JP",
    "name:jpn_x_preferred":[
        "\u6960\u6728\u539f"
    ],
    "wof:name":"Kusunokibaru",
    "wof:placetype":"locality"
},
  "geometry": {"coordinates":[129.83826999999999,33.17851],"type":"Point"}
}