{
  "type": "Feature",
  "properties": {
    "iso:country":"JP",
    "name:eng_x_preferred":[
        "Shinsenrinishimachi 3 Chome"
    ],
    "name:eng_x_variant":[
        "Shinsenrinishimachi 3 Choume",
        "Shinsenrinishimachi 3 Chome"
    ],
    "name:jpn_x_preferred":[
        "\uff13\u4e01\u76ee"
    ],
    "name:jpn_x_variant":[
        "\u3057\u3093\u305b\u3093\u308a\u306b\u3057\u307e\u3061 \uff13\u3061\u3087\u3046\u3081",
        "\u65b0\u5343\u91cc\u897f\u753a \uff13\u4e01\u76ee",
        "\uff13\u3061\u3087\u3046\u3081"
    ],
    "qs:gn_local":0,
    "qs:local_max":319,
    "qs:local_sum":1183,
    "qs:localhoods":13,
    "qs:name":"\uff13\u4e01\u76ee",
    "qs:name_adm0":"\u65e5\u672c",
    "qs:name_adm1":"\u5927\u962a\u5e9c",
    "qs:name_en":"Shinsenrinishimachi 3 Chome",
    "qs:name_lau":"\u65b0\u5343\u91cc\u897f\u753a",
    "qs:name_local":"\u8c4a\u4e2d\u5e02",
    "qs:photo_max":40,
    "qs:photo_sum":186,
    "qs:placetype":"Suburb",
    "qs:quad_count":9,
    "qs:woe_adm0":23424856,
    "qs:woe_adm1":2345881,
    "qs:woe_adm2":0,
    "qs:woe_lau":28458168,
    "qs:woe_local":1118409,
    "qs:woe_ver":"7.10.0",
    "wof:lang":[
        "jpn"
    ],
    "wof:name":"\uff13\u4e01\u76ee",
    "wof:placetype":"neighbourhood"
},
  "geometry": {"coordinates":[135.492266,34.813954],"type":"Point"}
}