{
  "type": "Feature",
  "properties": {
    "iso:country":"JP",
    "name:eng_x_preferred":[
        "Gion 1 Chome"
    ],
    "name:eng_x_variant":[
        "Gion 1 Choume",
        "Gion 1 Chome"
    ],
    "name:jpn_x_preferred":[
        "\uff11\u4e01\u76ee"
    ],
    "name:jpn_x_variant":[
        "\u304e\u304a\u3093 \uff11\u3061\u3087\u3046\u3081",
        "\u7947\u5712 \uff11\u4e01\u76ee",
        "\uff11\u3061\u3087\u3046\u3081"
    ],
    "qs:gn_local":0,
    "qs:local_max":37,
    "qs:local_sum":37,
    "qs:localhoods":1,
    "qs:name":"\uff11\u4e01\u76ee",
    "qs:name_adm0":"\u65e5\u672c",
    "qs:name_adm1":"\u798f\u5ca1\u770c",
    "qs:name_en":"Gion 1 Chome",
    "qs:name_lau":"\u7947\u5712",
    "qs:name_local":"\u5c0f\u90e1\u5e02",
    "qs:photo_max":15,
    "qs:photo_sum":37,
    "qs:placetype":"Suburb",
    "qs:quad_count":6,
    "qs:woe_adm0":23424856,
    "qs:woe_adm1":58646425,
    "qs:woe_adm2":0,
    "qs:woe_lau":28484311,
    "qs:woe_local":1117948,
    "qs:woe_ver":"7.10.0",
    "wof:lang":[
        "jpn"
    ],
    "wof:name":"\uff11\u4e01\u76ee",
    "wof:placetype":"neighbourhood"
},
  "geometry": {"coordinates":[130.55417399999999,33.396928],"type":"Point"}
}