{
  "type": "Feature",
  "properties": {
    "gn:admin1_code":"14.0",
    "gn:admin2_code":"6950859.0",
    "gn:asciiname":"Suzuka",
    "gn:country_code":"JP",
    "gn:dem":26,
    "gn:feature_class":"P",
    "gn:feature_code":"PPLL",
    "gn:name":"Suzuka",
    "gn:population":0,
    "gn:timezone":"Asia/Tokyo",
    "iso:country":"JP",
    "name:jpn_x_preferred":[
        "\u9234\u585a"
    ],
    "name:jpn_x_variant":[
        "\u3059\u3065\u304b"
    ],
    "wof:name":"Suzuka",
    "wof:placetype":"locality"
},
  "geometry": {"coordinates":[139.98366999999999,35.93764],"type":"Point"}
}