{
  "type": "Feature",
  "properties": {
    "gn:admin1_code":"14.0",
    "gn:admin2_code":"6950859.0",
    "gn:asciiname":"Suzuka",
    "gn:country_code":"JP",
    "gn:dem":26,
    "gn:feature_class":"P",
    "gn:feature_code":"PPLL",
    "gn:name":"Suzuka",
    "gn:population":0,
    "gn:timezone":"Asia/Tokyo",
    "iso:country":"JP",
    "name:deu_x_preferred":[
        "Suzuka"
    ],
    "name:fra_x_preferred":[
        "Suzuka"
    ],
    "name:jpn_x_preferred":[
        "\u9234\u585a"
    ],
    "name:jpn_x_variant":[
        "\u3059\u3065\u304b"
    ],
    "name:kor_x_preferred":[
        "\uc2a4\uc988\uce74"
    ],
    "name:mlg_x_preferred":[
        "Suzuka"
    ],
    "name:msa_x_preferred":[
        "Suzuka"
    ],
    "name:nld_x_preferred":[
        "Suzuka"
    ],
    "name:pol_x_preferred":[
        "Suzuka"
    ],
    "name:ron_x_preferred":[
        "Suzuka"
    ],
    "name:rus_x_preferred":[
        "\u0421\u0443\u0434\u0437\u0443\u043a\u0430"
    ],
    "name:spa_x_preferred":[
        "Suzuka"
    ],
    "name:ukr_x_preferred":[
        "\u0421\u0443\u0434\u0437\u0443\u043a\u0430"
    ],
    "wof:name":"Suzuka",
    "wof:placetype":"locality"
},
  "geometry": {"coordinates":[139.98366999999999,35.93764],"type":"Point"}
}