{
  "type": "Feature",
  "properties": {
    "gn:admin1_code":"37.0",
    "gn:admin2_code":"1851714.0",
    "gn:admin3_code":"22103.0",
    "gn:asciiname":"Kojuta",
    "gn:country_code":"JP",
    "gn:dem":215,
    "gn:feature_class":"P",
    "gn:feature_code":"PPLL",
    "gn:name":"Koj\u016bta",
    "gn:population":0,
    "gn:timezone":"Asia/Tokyo",
    "iso:country":"JP",
    "name:jpn_x_preferred":[
        "\u53e4\u4f4f\u7530"
    ],
    "name:und_x_variant":[
        "Koj\u016bta"
    ],
    "wof:name":"Kojuta",
    "wof:placetype":"locality"
},
  "geometry": {"coordinates":[138.51541,35.18952],"type":"Point"}
}