{
  "type": "Feature",
  "properties": {
    "gn:admin1_code":"19.0",
    "gn:admin2_code":"1848350.0",
    "gn:admin3_code":"14112.0",
    "gn:asciiname":"Oikecho",
    "gn:country_code":"JP",
    "gn:dem":84,
    "gn:feature_class":"P",
    "gn:feature_code":"PPL",
    "gn:name":"\u014cikech\u014d",
    "gn:population":0,
    "gn:timezone":"Asia/Tokyo",
    "iso:country":"JP",
    "name:jpn_x_preferred":[
        "\u5927\u6c60\u753a"
    ],
    "name:jpn_x_variant":[
        "\u304a\u304a\u3044\u3051\u3061\u3087\u3046",
        "\u30aa\u30aa\u30a4\u30b1\u30c1\u30e7\u30a6"
    ],
    "name:und_x_variant":[
        "\u014cikech\u014d"
    ],
    "wof:name":"Oikecho",
    "wof:placetype":"locality"
},
  "geometry": {"coordinates":[139.53585000000001,35.44856],"type":"Point"}
}