{
  "type": "Feature",
  "properties": {
    "gn:admin1_code":"18.0",
    "gn:admin2_code":"8300556.0",
    "gn:asciiname":"Obori",
    "gn:country_code":"JP",
    "gn:dem":160,
    "gn:feature_class":"P",
    "gn:feature_code":"PPLL",
    "gn:name":"\u014cbori",
    "gn:population":0,
    "gn:timezone":"Asia/Tokyo",
    "iso:country":"JP",
    "name:jpn_x_preferred":[
        "\u5927\u5800"
    ],
    "name:und_x_variant":[
        "\u014cbori"
    ],
    "wof:name":"Obori",
    "wof:placetype":"locality"
},
  "geometry": {"coordinates":[130.88193000000001,31.45949],"type":"Point"}
}