{
  "type": "Feature",
  "properties": {
    "gn:admin1_code":"3.0",
    "gn:admin2_code":"7439944.0",
    "gn:asciiname":"Inagakicho-numadate",
    "gn:country_code":"JP",
    "gn:dem":0,
    "gn:feature_class":"P",
    "gn:feature_code":"PPL",
    "gn:name":"Inagakich\u014d-numadate",
    "gn:population":0,
    "gn:timezone":"Asia/Tokyo",
    "iso:country":"JP",
    "name:jpn_x_preferred":[
        "\u7a32\u57a3\u753a\u6cbc\u9928"
    ],
    "name:jpn_x_variant":[
        "\u3044\u306a\u304c\u304d\u3061\u3087\u3046\u306c\u307e\u3060\u3066",
        "\u30a4\u30ca\u30ac\u30ad\u30c1\u30e7\u30a6\u30cc\u30de\u30c0\u30c6"
    ],
    "name:und_x_variant":[
        "Inagakich\u014d-numadate"
    ],
    "wof:name":"Inagakicho-numadate",
    "wof:placetype":"locality"
},
  "geometry": {"coordinates":[140.3852,40.87989],"type":"Point"}
}