{
  "type": "Feature",
  "properties": {
    "gn:admin1_code":"19.0",
    "gn:admin2_code":"1848350.0",
    "gn:admin3_code":"14116.0",
    "gn:asciiname":"Shimoizumi",
    "gn:country_code":"JP",
    "gn:dem":39,
    "gn:feature_class":"P",
    "gn:feature_code":"PPL",
    "gn:name":"Shimoizumi",
    "gn:population":0,
    "gn:timezone":"Asia/Tokyo",
    "iso:country":"JP",
    "name:jpn_x_preferred":[
        "\u4e0b\u548c\u6cc9"
    ],
    "wof:name":"Shimoizumi",
    "wof:placetype":"locality"
},
  "geometry": {"coordinates":[139.49432999999999,35.39584],"type":"Point"}
}