{
  "type": "Feature",
  "properties": {
    "gn:admin1_code":"27",
    "gn:admin2_code":"7418810.0",
    "gn:asciiname":"Kamitsushimacho-hitakatsu",
    "gn:country_code":"JP",
    "gn:dem":47,
    "gn:feature_class":"P",
    "gn:feature_code":"PPL",
    "gn:name":"Kamitsushimach\u014d-hitakatsu",
    "gn:population":0,
    "gn:timezone":"Asia/Tokyo",
    "iso:country":"JP",
    "name:jpn_x_preferred":[
        "\u4e0a\u5bfe\u99ac\u753a\u6bd4\u7530\u52dd"
    ],
    "name:und_x_variant":[
        "Toyosaki",
        "Hidakatsu",
        "Hitakatsu",
        "Kamitsushimach\u014d-hitakatsu"
    ],
    "wof:name":"Kamitsushimacho-hitakatsu",
    "wof:placetype":"locality"
},
  "geometry": {"coordinates":[129.45889,34.65083],"type":"Point"}
}