{
  "type": "Feature",
  "properties": {
    "gn:admin1_code":"17",
    "gn:admin2_code":"1860119.0",
    "gn:asciiname":"Ibukicho",
    "gn:country_code":"JP",
    "gn:dem":53,
    "gn:feature_class":"P",
    "gn:feature_code":"PPL",
    "gn:name":"Ibukich\u014d",
    "gn:population":0,
    "gn:timezone":"Asia/Tokyo",
    "iso:country":"JP",
    "name:jpn_x_preferred":[
        "\u4f0a\u5439\u753a"
    ],
    "name:und_x_variant":[
        "Ibukijima",
        "Ibuki",
        "Ibukich\u014d"
    ],
    "wof:name":"Ibukicho",
    "wof:placetype":"locality"
},
  "geometry": {"coordinates":[133.53552999999999,34.1283],"type":"Point"}
}