{
  "type": "Feature",
  "properties": {
    "gn:admin1_code":"12.0",
    "gn:admin2_code":"7428100.0",
    "gn:admin3_code":"1691.0",
    "gn:asciiname":"Kamishunbetsu-midoricho",
    "gn:country_code":"JP",
    "gn:dem":75,
    "gn:feature_class":"P",
    "gn:feature_code":"PPL",
    "gn:name":"Kamishunbetsu-midorich\u014d",
    "gn:population":0,
    "gn:timezone":"Asia/Tokyo",
    "iso:country":"JP",
    "name:jpn_x_preferred":[
        "\u4e0a\u6625\u5225\u7dd1\u753a"
    ],
    "name:jpn_x_variant":[
        "\u304b\u307f\u3057\u3085\u3093\u3079\u3064\u307f\u3069\u308a\u3061\u3087\u3046",
        "\u30ab\u30df\u30b7\u30e5\u30f3\u30d9\u30c4\u30df\u30c9\u30ea\u30c1\u30e7\u30a6"
    ],
    "name:und_x_variant":[
        "Kamishunbetsu-midorich\u014d"
    ],
    "wof:name":"Kamishunbetsu-midoricho",
    "wof:placetype":"locality"
},
  "geometry": {"coordinates":[144.8981,43.43234],"type":"Point"}
}