{
  "type": "Feature",
  "properties": {
    "gn:admin1_code":"32.0",
    "gn:admin2_code":"1862032.0",
    "gn:asciiname":"Yasumoto",
    "gn:country_code":"JP",
    "gn:dem":279,
    "gn:feature_class":"P",
    "gn:feature_code":"PPL",
    "gn:name":"Yasumoto",
    "gn:population":0,
    "gn:timezone":"Asia/Tokyo",
    "iso:country":"JP",
    "name:jpn_x_preferred":[
        "\u5b89\u5143"
    ],
    "wof:name":"Yasumoto",
    "wof:placetype":"locality"
},
  "geometry": {"coordinates":[135.54478,34.89182],"type":"Point"}
}