{
  "type": "Feature",
  "properties": {
    "gn:admin1_code":"40.0",
    "gn:admin2_code":"1862785.0",
    "gn:asciiname":"Shinkawacho",
    "gn:country_code":"JP",
    "gn:dem":49,
    "gn:feature_class":"P",
    "gn:feature_code":"PPL",
    "gn:name":"Shinkawach\u014d",
    "gn:population":0,
    "gn:timezone":"Asia/Tokyo",
    "iso:country":"JP",
    "name:jpn_x_preferred":[
        "\u65b0\u5ddd\u753a"
    ],
    "name:jpn_x_variant":[
        "\u3057\u3093\u304b\u308f\u3061\u3087\u3046",
        "\u30b7\u30f3\u30ab\u30ef\u30c1\u30e7\u30a6"
    ],
    "name:und_x_variant":[
        "Shinkawach\u014d"
    ],
    "wof:name":"Shinkawacho",
    "wof:placetype":"locality"
},
  "geometry": {"coordinates":[139.5386,35.76029000000001],"type":"Point"}
}