{
  "type": "Feature",
  "properties": {
    "gn:admin1_code":"3.0",
    "gn:admin2_code":"2130654.0",
    "gn:asciiname":"Tsurugasaka",
    "gn:country_code":"JP",
    "gn:dem":84,
    "gn:feature_class":"P",
    "gn:feature_code":"PPL",
    "gn:name":"Tsurugasaka",
    "gn:population":0,
    "gn:timezone":"Asia/Tokyo",
    "iso:country":"JP",
    "name:jpn_x_preferred":[
        "\u9db4\u30f6\u5742"
    ],
    "name:jpn_x_variant":[
        "\u3064\u308b\u304c\u3055\u304b",
        "\u30c4\u30eb\u30ac\u30b5\u30ab"
    ],
    "wof:name":"Tsurugasaka",
    "wof:placetype":"locality"
},
  "geometry": {"coordinates":[140.63585,40.7887],"type":"Point"}
}