{
  "type": "Feature",
  "properties": {
    "gn:admin1_code":"16.0",
    "gn:admin2_code":"2128941.0",
    "gn:admin3_code":"3524.0",
    "gn:asciiname":"Inari",
    "gn:country_code":"JP",
    "gn:dem":252,
    "gn:feature_class":"P",
    "gn:feature_code":"PPL",
    "gn:name":"Inari",
    "gn:population":0,
    "gn:timezone":"Asia/Tokyo",
    "iso:country":"JP",
    "name:jpn_x_preferred":[
        "\u7a32\u8377"
    ],
    "name:jpn_x_variant":[
        "\u3044\u306a\u308a",
        "\u30a4\u30ca\u30ea"
    ],
    "wof:name":"Inari",
    "wof:placetype":"locality"
},
  "geometry": {"coordinates":[141.24879000000001,40.19252],"type":"Point"}
}