{
  "type": "Feature",
  "properties": {
    "gn:admin1_code":"16.0",
    "gn:admin2_code":"2128941.0",
    "gn:admin3_code":"3524.0",
    "gn:asciiname":"Inari",
    "gn:country_code":"JP",
    "gn:dem":252,
    "gn:feature_class":"P",
    "gn:feature_code":"PPL",
    "gn:name":"Inari",
    "gn:population":0,
    "gn:timezone":"Asia/Tokyo",
    "iso:country":"JP",
    "name:cat_x_preferred":[
        "Inari"
    ],
    "name:ceb_x_preferred":[
        "Inari"
    ],
    "name:ces_x_preferred":[
        "Inari"
    ],
    "name:deu_x_preferred":[
        "Inari"
    ],
    "name:epo_x_preferred":[
        "Inari"
    ],
    "name:fas_x_preferred":[
        "\u0627\u06cc\u0646\u0627\u0631\u06cc"
    ],
    "name:fin_x_preferred":[
        "Inari"
    ],
    "name:fra_x_preferred":[
        "Inari"
    ],
    "name:ind_x_preferred":[
        "Inari"
    ],
    "name:ita_x_preferred":[
        "Inari"
    ],
    "name:jpn_x_preferred":[
        "\u7a32\u8377"
    ],
    "name:jpn_x_variant":[
        "\u3044\u306a\u308a",
        "\u30a4\u30ca\u30ea"
    ],
    "name:kor_x_preferred":[
        "\uc774\ub098\ub9ac"
    ],
    "name:nld_x_preferred":[
        "Inari"
    ],
    "name:pol_x_preferred":[
        "Inari"
    ],
    "name:por_x_preferred":[
        "Inari"
    ],
    "name:ron_x_preferred":[
        "Inari"
    ],
    "name:rus_x_preferred":[
        "\u0418\u043d\u0430\u0440\u0438"
    ],
    "name:sco_x_preferred":[
        "Inari"
    ],
    "name:slv_x_preferred":[
        "Inari"
    ],
    "name:spa_x_preferred":[
        "Inari"
    ],
    "name:ukr_x_preferred":[
        "\u0406\u043d\u0430\u0440\u0456"
    ],
    "wof:name":"Inari",
    "wof:placetype":"locality"
},
  "geometry": {"coordinates":[141.24879000000001,40.19252],"type":"Point"}
}