{
  "type": "Feature",
  "properties": {
    "gn:admin1_code":"21.0",
    "gn:admin2_code":"7412705.0",
    "gn:admin3_code":"43482.0",
    "gn:asciiname":"Hirano",
    "gn:country_code":"JP",
    "gn:dem":110,
    "gn:feature_class":"P",
    "gn:feature_code":"PPLL",
    "gn:name":"Hirano",
    "gn:population":0,
    "gn:timezone":"Asia/Tokyo",
    "iso:country":"JP",
    "name:ces_x_preferred":[
        "Hirano"
    ],
    "name:deu_x_preferred":[
        "Hirano"
    ],
    "name:fra_x_preferred":[
        "Hirano"
    ],
    "name:jpn_x_preferred":[
        "\u5e73\u91ce"
    ],
    "name:jpn_x_variant":[
        "\u3072\u3089\u306e",
        "\u30d2\u30e9\u30ce"
    ],
    "name:kor_x_preferred":[
        "\ud788\ub77c\ub178"
    ],
    "name:rus_x_preferred":[
        "\u0425\u0438\u0440\u0430\u043d\u043e"
    ],
    "name:ukr_x_preferred":[
        "\u0425\u0456\u0440\u0430\u043d\u043e"
    ],
    "wof:name":"Hirano",
    "wof:placetype":"locality"
},
  "geometry": {"coordinates":[130.58151999999998,32.33387],"type":"Point"}
}