{
  "type": "Feature",
  "properties": {
    "gn:admin1_code":"3.0",
    "gn:admin2_code":"2130200.0",
    "gn:asciiname":"Magojiro",
    "gn:country_code":"JP",
    "gn:dem":202,
    "gn:feature_class":"P",
    "gn:feature_code":"PPL",
    "gn:name":"Magojir\u014d",
    "gn:population":0,
    "gn:timezone":"Asia/Tokyo",
    "iso:country":"JP",
    "name:jpn_x_preferred":[
        "\u5b6b\u6b21\u90ce"
    ],
    "name:jpn_x_variant":[
        "\u307e\u3054\u3058\u308d\u3046",
        "\u30de\u30b4\u30b8\u30ed\u30a6"
    ],
    "name:und_x_variant":[
        "Magojir\u014d"
    ],
    "wof:name":"Magojiro",
    "wof:placetype":"locality"
},
  "geometry": {"coordinates":[141.42538000000005,40.41842000000001],"type":"Point"}
}