{
  "type": "Feature",
  "properties": {
    "gn:admin1_code":"19.0",
    "gn:admin2_code":"1864091.0",
    "gn:asciiname":"Shibusawa",
    "gn:country_code":"JP",
    "gn:dem":49,
    "gn:feature_class":"P",
    "gn:feature_code":"PPLL",
    "gn:name":"Shibusawa",
    "gn:population":0,
    "gn:timezone":"Asia/Tokyo",
    "iso:country":"JP",
    "name:jpn_x_preferred":[
        "\u6e0b\u6ca2\u3000"
    ],
    "wof:name":"Shibusawa",
    "wof:placetype":"locality"
},
  "geometry": {"coordinates":[139.48038,35.36939],"type":"Point"}
}