{
  "type": "Feature",
  "properties": {
    "gn:admin1_code":"3.0",
    "gn:admin2_code":"2130200.0",
    "gn:asciiname":"Ningyomori",
    "gn:country_code":"JP",
    "gn:dem":209,
    "gn:feature_class":"P",
    "gn:feature_code":"PPL",
    "gn:name":"Ningy\u014dmori",
    "gn:population":0,
    "gn:timezone":"Asia/Tokyo",
    "iso:country":"JP",
    "name:jpn_x_preferred":[
        "\u4eba\u5f62\u68ee"
    ],
    "name:jpn_x_variant":[
        "\u306b\u3093\u304e\u3087\u3046\u3082\u308a",
        "\u30cb\u30f3\u30ae\u30e7\u30a6\u30e2\u30ea"
    ],
    "name:und_x_variant":[
        "Ningy\u014dmori"
    ],
    "wof:name":"Ningyomori",
    "wof:placetype":"locality"
},
  "geometry": {"coordinates":[141.38891999999996,40.39021],"type":"Point"}
}