{
  "type": "Feature",
  "properties": {
    "gn:admin1_code":"27",
    "gn:admin2_code":"1856152.0",
    "gn:asciiname":"Yagami",
    "gn:cc2":"JP",
    "gn:country_code":"JP",
    "gn:dem":30,
    "gn:feature_class":"P",
    "gn:feature_code":"PPL",
    "gn:name":"Yagami",
    "gn:population":0,
    "gn:timezone":"Asia/Tokyo",
    "iso:country":"JP",
    "name:deu_x_preferred":[
        "Yagami"
    ],
    "name:und_x_variant":[
        "Yakami"
    ],
    "wof:name":"Yagami",
    "wof:placetype":"locality"
},
  "geometry": {"coordinates":[129.94999999999999,32.76667],"type":"Point"}
}