{
  "type": "Feature",
  "properties": {
    "gn:admin1_code":"4.0",
    "gn:admin2_code":"2111854.0",
    "gn:asciiname":"Shibana",
    "gn:country_code":"JP",
    "gn:dem":48,
    "gn:feature_class":"P",
    "gn:feature_code":"PPL",
    "gn:name":"Shibana",
    "gn:population":0,
    "gn:timezone":"Asia/Tokyo",
    "iso:country":"JP",
    "name:jpn_x_preferred":[
        "\u67f4\u540d"
    ],
    "name:jpn_x_variant":[
        "\u3057\u3070\u306a",
        "\u30b7\u30d0\u30ca"
    ],
    "wof:name":"Shibana",
    "wof:placetype":"locality"
},
  "geometry": {"coordinates":[140.27761999999998,35.48603],"type":"Point"}
}