{
  "type": "Feature",
  "properties": {
    "gn:admin1_code":"28.0",
    "gn:admin2_code":"7412211.0",
    "gn:asciiname":"Katsuragi",
    "gn:country_code":"JP",
    "gn:dem":270,
    "gn:feature_class":"P",
    "gn:feature_code":"PPLA2",
    "gn:name":"Katsuragi",
    "gn:population":0,
    "gn:timezone":"Asia/Tokyo",
    "iso:country":"JP",
    "name:ara_x_preferred":[
        "\u0643\u0627\u062a\u0633\u0648\u0631\u0627\u063a\u064a"
    ],
    "name:azb_x_preferred":[
        "\u06a9\u0627\u062a\u0633\u0648\u0631\u0627\u0642\u06cc"
    ],
    "name:ceb_x_preferred":[
        "Katsuragi"
    ],
    "name:deu_x_preferred":[
        "Katsuragi"
    ],
    "name:epo_x_preferred":[
        "Kacuragi"
    ],
    "name:fas_x_preferred":[
        "\u06a9\u0627\u062a\u0633\u0648\u0631\u0627\u06af\u06cc\u060c \u0646\u0627\u0631\u0627"
    ],
    "name:fas_x_variant":[
        "\u06a9\u0627\u062a\u0633\u0648\u0631\u0627\u06af\u06cc"
    ],
    "name:fra_x_preferred":[
        "Katsuragi"
    ],
    "name:glg_x_preferred":[
        "Katsuragi"
    ],
    "name:hye_x_preferred":[
        "\u053f\u0561\u0581\u0578\u0582\u0580\u0561\u0563\u056b"
    ],
    "name:ita_x_preferred":[
        "Katsuragi"
    ],
    "name:jpn_x_preferred":[
        "\u845b\u57ce"
    ],
    "name:jpn_x_variant":[
        "\u845b\u57ce\u5e02"
    ],
    "name:kor_x_preferred":[
        "\uac00\uc4f0\ub77c\uae30 \uc2dc"
    ],
    "name:kor_x_variant":[
        "\uac00\uc4f0\ub77c\uae30\uc2dc"
    ],
    "name:mzn_x_preferred":[
        "\u06a9\u0627\u062a\u0633\u0648\u0631\u0627\u06af\u06cc\u060c \u0646\u0627\u0631\u0627"
    ],
    "name:mzn_x_variant":[
        "\u06a9\u0627\u062a\u0633\u0648\u0631\u0627\u06af\u06cc"
    ],
    "name:nan_x_preferred":[
        "Katuragi-chh\u012b"
    ],
    "name:nld_x_preferred":[
        "Katsuragi"
    ],
    "name:pol_x_preferred":[
        "Katsuragi"
    ],
    "name:por_x_preferred":[
        "Katsuragi"
    ],
    "name:ron_x_preferred":[
        "Katsuragi"
    ],
    "name:rus_x_preferred":[
        "\u041a\u0430\u0446\u0443\u0440\u0430\u0433\u0438"
    ],
    "name:spa_x_preferred":[
        "Katsuragi"
    ],
    "name:swe_x_preferred":[
        "Katsuragi"
    ],
    "name:tgk_x_preferred":[
        "\u041a\u0430\u0442\u0441\u0443\u0440\u0430\u0433\u0438"
    ],
    "name:tgl_x_preferred":[
        "Katsuragi"
    ],
    "name:tur_x_preferred":[
        "Katsuragi"
    ],
    "name:ukr_x_preferred":[
        "\u041a\u0430\u0446\u0443\u0440\u0430\u0491\u0456"
    ],
    "name:vie_x_preferred":[
        "Katsuragi"
    ],
    "name:war_x_preferred":[
        "Katsuragi"
    ],
    "name:zho_x_preferred":[
        "\u845b\u57ce\u5e02"
    ],
    "wof:name":"Katsuragi",
    "wof:placetype":"locality"
},
  "geometry": {"coordinates":[135.69698,34.48562],"type":"Point"}
}