{
  "type": "Feature",
  "properties": {
    "gn:admin1_code":"3.0",
    "gn:admin2_code":"2130654.0",
    "gn:asciiname":"Nijigaoka",
    "gn:country_code":"JP",
    "gn:dem":12,
    "gn:feature_class":"P",
    "gn:feature_code":"PPL",
    "gn:name":"Nijigaoka",
    "gn:population":0,
    "gn:timezone":"Asia/Tokyo",
    "iso:country":"JP",
    "name:jpn_x_preferred":[
        "\u8679\u30f6\u4e18"
    ],
    "name:jpn_x_variant":[
        "\u306b\u3058\u304c\u304a\u304b",
        "\u30cb\u30b8\u30ac\u30aa\u30ab"
    ],
    "wof:name":"Nijigaoka",
    "wof:placetype":"locality"
},
  "geometry": {"coordinates":[140.79390000000001,40.81147],"type":"Point"}
}