{
  "type": "Feature",
  "properties": {
    "gn:admin1_code":"3.0",
    "gn:admin2_code":"2130225.0",
    "gn:asciiname":"Ubayachi",
    "gn:country_code":"JP",
    "gn:dem":10,
    "gn:feature_class":"P",
    "gn:feature_code":"PPL",
    "gn:name":"Ubayachi",
    "gn:population":0,
    "gn:timezone":"Asia/Tokyo",
    "iso:country":"JP",
    "name:jpn_x_preferred":[
        "\u59e5\u8422"
    ],
    "name:jpn_x_variant":[
        "\u3046\u3070\u3084\u3061",
        "\u30a6\u30d0\u30e4\u30c1"
    ],
    "wof:name":"Ubayachi",
    "wof:placetype":"locality"
},
  "geometry": {"coordinates":[140.44277,40.78997],"type":"Point"}
}