{
  "type": "Feature",
  "properties": {
    "gn:admin1_code":"24.0",
    "gn:admin2_code":"7447001.0",
    "gn:asciiname":"Yamazaki",
    "gn:country_code":"JP",
    "gn:dem":22,
    "gn:feature_class":"P",
    "gn:feature_code":"PPL",
    "gn:name":"Yamazaki",
    "gn:population":0,
    "gn:timezone":"Asia/Tokyo",
    "iso:country":"JP",
    "name:jpn_x_preferred":[
        "\u5c71\u5d0e"
    ],
    "name:jpn_x_variant":[
        "\u3084\u307e\u3056\u304d",
        "\u30e4\u30de\u30b6\u30ad"
    ],
    "wof:name":"Yamazaki",
    "wof:placetype":"locality"
},
  "geometry": {"coordinates":[141.10532000000001,38.49996],"type":"Point"}
}