{
  "type": "Feature",
  "properties": {
    "gn:admin1_code":"16.0",
    "gn:admin2_code":"2112655.0",
    "gn:asciiname":"Aikawa",
    "gn:country_code":"JP",
    "gn:dem":114,
    "gn:feature_class":"P",
    "gn:feature_code":"PPL",
    "gn:name":"Aikawa",
    "gn:population":0,
    "gn:timezone":"Asia/Tokyo",
    "iso:country":"JP",
    "wof:name":"Aikawa",
    "wof:placetype":"locality"
},
  "geometry": {"coordinates":[141.21666999999999,38.96667],"type":"Point"}
}