{
  "type": "Feature",
  "properties": {
    "gn:admin1_code":"7.0",
    "gn:admin2_code":"1861834.0",
    "gn:asciiname":"Kamimio",
    "gn:country_code":"JP",
    "gn:dem":22,
    "gn:feature_class":"P",
    "gn:feature_code":"PPL",
    "gn:name":"Kamimio",
    "gn:population":0,
    "gn:timezone":"Asia/Tokyo",
    "iso:country":"JP",
    "name:jpn_x_preferred":[
        "\u4e0a\u4e09\u7dd2"
    ],
    "wof:name":"Kamimio",
    "wof:placetype":"locality"
},
  "geometry": {"coordinates":[130.71218000000002,33.62323],"type":"Point"}
}