{
  "type": "Feature",
  "properties": {
    "gn:admin1_code":"21.0",
    "gn:admin2_code":"1859488.0",
    "gn:asciiname":"Kaminishidera",
    "gn:country_code":"JP",
    "gn:dem":42,
    "gn:feature_class":"P",
    "gn:feature_code":"PPLL",
    "gn:name":"Kaminishidera",
    "gn:population":0,
    "gn:timezone":"Asia/Tokyo",
    "iso:country":"JP",
    "name:jpn_x_preferred":[
        "\u4e0a\u897f\u5bfa"
    ],
    "name:jpn_x_variant":[
        "\u304b\u307f\u306b\u3057\u3067\u3089",
        "\u30ab\u30df\u30cb\u30b7\u30c7\u30e9"
    ],
    "wof:name":"Kaminishidera",
    "wof:placetype":"locality"
},
  "geometry": {"coordinates":[130.79336999999998,32.97058],"type":"Point"}
}