{
  "type": "Feature",
  "properties": {
    "gn:admin1_code":"25.0",
    "gn:admin2_code":"1864313.0",
    "gn:asciiname":"Makinoharu",
    "gn:country_code":"JP",
    "gn:dem":300,
    "gn:feature_class":"P",
    "gn:feature_code":"PPLL",
    "gn:name":"Makinoharu",
    "gn:population":0,
    "gn:timezone":"Asia/Tokyo",
    "iso:country":"JP",
    "name:jpn_x_preferred":[
        "\u7267\u306e\u539f"
    ],
    "name:jpn_x_variant":[
        "\u307e\u304d\u306e\u306f\u308b",
        "\u30de\u30ad\u30ce\u30cf\u30eb"
    ],
    "wof:name":"Makinoharu",
    "wof:placetype":"locality"
},
  "geometry": {"coordinates":[130.81142,32.06634],"type":"Point"}
}