{
  "type": "Feature",
  "properties": {
    "gn:admin1_code":"21.0",
    "gn:admin2_code":"7412709.0",
    "gn:admin3_code":"43348.0",
    "gn:asciiname":"Katashida",
    "gn:country_code":"JP",
    "gn:dem":66,
    "gn:feature_class":"P",
    "gn:feature_code":"PPL",
    "gn:name":"Katashida",
    "gn:population":0,
    "gn:timezone":"Asia/Tokyo",
    "iso:country":"JP",
    "name:jpn_x_preferred":[
        "\u5805\u5fd7\u7530"
    ],
    "name:jpn_x_variant":[
        "\u304b\u305f\u3057\u3060",
        "\u30ab\u30bf\u30b7\u30c0"
    ],
    "wof:name":"Katashida",
    "wof:placetype":"locality"
},
  "geometry": {"coordinates":[130.78795,32.64747],"type":"Point"}
}