{
  "type": "Feature",
  "properties": {
    "gn:admin1_code":"30",
    "gn:admin2_code":"1862367.0",
    "gn:asciiname":"Amagasemachi-yuyama",
    "gn:country_code":"JP",
    "gn:dem":286,
    "gn:feature_class":"P",
    "gn:feature_code":"PPL",
    "gn:name":"Amagasemachi-yuyama",
    "gn:population":0,
    "gn:timezone":"Asia/Tokyo",
    "iso:country":"JP",
    "name:jpn_x_preferred":[
        "\u5929\u702c\u753a\u6e6f\u5c71"
    ],
    "name:und_x_variant":[
        "Yunoyama",
        "Yuyama",
        "Amagasemachi-yuyama"
    ],
    "wof:name":"Amagasemachi-yuyama",
    "wof:placetype":"locality"
},
  "geometry": {"coordinates":[131.02534,33.2593],"type":"Point"}
}