{
  "type": "Feature",
  "properties": {
    "gn:admin1_code":"47.0",
    "gn:admin2_code":"1856061.0",
    "gn:asciiname":"Uchiyama",
    "gn:country_code":"JP",
    "gn:dem":151,
    "gn:feature_class":"P",
    "gn:feature_code":"PPL",
    "gn:name":"Uchiyama",
    "gn:population":0,
    "gn:timezone":"Asia/Tokyo",
    "iso:country":"JP",
    "name:cat_x_preferred":[
        "Uchiyama"
    ],
    "name:deu_x_preferred":[
        "Uchiyama"
    ],
    "name:jpn_x_preferred":[
        "\u5185\u5c71"
    ],
    "name:lav_x_preferred":[
        "U\u010dijama"
    ],
    "name:rus_x_preferred":[
        "\u0423\u0442\u0438\u044f\u043c\u0430"
    ],
    "wof:name":"Uchiyama",
    "wof:placetype":"locality"
},
  "geometry": {"coordinates":[127.95610000000001,26.6363],"type":"Point"}
}