{
  "type": "Feature",
  "properties": {
    "gn:admin1_code":"16.0",
    "gn:admin2_code":"2128940.0",
    "gn:asciiname":"Aburako",
    "gn:country_code":"JP",
    "gn:dem":148,
    "gn:feature_class":"P",
    "gn:feature_code":"PPL",
    "gn:name":"Aburako",
    "gn:population":0,
    "gn:timezone":"Asia/Tokyo",
    "iso:country":"JP",
    "name:jpn_x_preferred":[
        "\u6cb9\u5b50"
    ],
    "name:jpn_x_variant":[
        "\u3042\u3076\u3089\u3053",
        "\u30a2\u30d6\u30e9\u30b3"
    ],
    "wof:name":"Aburako",
    "wof:placetype":"locality"
},
  "geometry": {"coordinates":[141.23086999999995,40.31211],"type":"Point"}
}