{
  "type": "Feature",
  "properties": {
    "gn:admin1_code":"40",
    "gn:admin2_code":"1864487.0",
    "gn:asciiname":"Nihonbashi-Kayabacho",
    "gn:country_code":"JP",
    "gn:dem":14,
    "gn:feature_class":"P",
    "gn:feature_code":"PPL",
    "gn:name":"Nihonbashi-Kayabach\u014d",
    "gn:population":0,
    "gn:timezone":"Asia/Tokyo",
    "iso:country":"JP",
    "name:jpn_x_preferred":[
        "\u65e5\u672c\u6a4b\u8305\u5834\u753a"
    ],
    "name:und_x_variant":[
        "Kayabach\u014d",
        "Nihombashi-Kayabach\u014d",
        "Nihonbashi-Kayabach\u014d"
    ],
    "wof:name":"Nihonbashi-Kayabacho",
    "wof:placetype":"locality"
},
  "geometry": {"coordinates":[139.77871999999999,35.67923],"type":"Point"}
}