{
  "type": "Feature",
  "properties": {
    "gn:admin1_code":"6.0",
    "gn:admin2_code":"1863982.0",
    "gn:asciiname":"Fusedacho",
    "gn:country_code":"JP",
    "gn:dem":4,
    "gn:feature_class":"P",
    "gn:feature_code":"PPL",
    "gn:name":"Fusedach\u014d",
    "gn:population":0,
    "gn:timezone":"Asia/Tokyo",
    "iso:country":"JP",
    "name:jpn_x_preferred":[
        "\u5e03\u65bd\u7530\u753a"
    ],
    "name:und_x_variant":[
        "Fusedach\u014d"
    ],
    "wof:name":"Fusedacho",
    "wof:placetype":"locality"
},
  "geometry": {"coordinates":[136.16218000000001,36.14363],"type":"Point"}
}