{
  "type": "Feature",
  "properties": {
    "gn:admin1_code":"21",
    "gn:admin2_code":"7413150.0",
    "gn:asciiname":"Kikukamachi-shimouchida",
    "gn:country_code":"JP",
    "gn:dem":128,
    "gn:feature_class":"P",
    "gn:feature_code":"PPL",
    "gn:name":"Kikukamachi-shimouchida",
    "gn:population":0,
    "gn:timezone":"Asia/Tokyo",
    "iso:country":"JP",
    "name:jpn_x_preferred":[
        "\u83ca\u9e7f\u753a\u4e0b\u5185\u7530"
    ],
    "name:und_x_variant":[
        "Shimo-uchida"
    ],
    "wof:name":"Kikukamachi-shimouchida",
    "wof:placetype":"locality"
},
  "geometry": {"coordinates":[130.75,33.03333],"type":"Point"}
}