{
  "type": "Feature",
  "properties": {
    "gn:admin1_code":"37.0",
    "gn:admin2_code":"1864104.0",
    "gn:asciiname":"Nishikurabone",
    "gn:country_code":"JP",
    "gn:dem":469,
    "gn:feature_class":"P",
    "gn:feature_code":"PPLL",
    "gn:name":"Nishikurabone",
    "gn:population":0,
    "gn:timezone":"Asia/Tokyo",
    "iso:country":"JP",
    "name:jpn_x_preferred":[
        "\u897f\u978d\u9aa8"
    ],
    "wof:name":"Nishikurabone",
    "wof:placetype":"locality"
},
  "geometry": {"coordinates":[138.62171000000001,35.29470999999999],"type":"Point"}
}