{
  "type": "Feature",
  "properties": {
    "gn:admin1_code":"39",
    "gn:admin2_code":"7406326.0",
    "gn:asciiname":"Ikawacho-tsuji",
    "gn:country_code":"JP",
    "gn:dem":113,
    "gn:feature_class":"P",
    "gn:feature_code":"PPL",
    "gn:name":"Ikawach\u014d-tsuji",
    "gn:population":0,
    "gn:timezone":"Asia/Tokyo",
    "iso:country":"JP",
    "name:jpn_x_preferred":[
        "\u4e95\u5ddd\u753a\u8fbb"
    ],
    "name:und_x_variant":[
        "Ikawach\u014d-tsuji",
        "Tsuji"
    ],
    "wof:name":"Ikawacho-tsuji",
    "wof:placetype":"locality"
},
  "geometry": {"coordinates":[133.86754999999999,34.02876],"type":"Point"}
}