{
  "type": "Feature",
  "properties": {
    "gn:admin1_code":"16.0",
    "gn:admin2_code":"2128940.0",
    "gn:asciiname":"Magitaira",
    "gn:country_code":"JP",
    "gn:dem":209,
    "gn:feature_class":"P",
    "gn:feature_code":"PPL",
    "gn:name":"Magitaira",
    "gn:population":0,
    "gn:timezone":"Asia/Tokyo",
    "iso:country":"JP",
    "name:jpn_x_preferred":[
        "\u69c7\u6728\u5e73"
    ],
    "name:jpn_x_variant":[
        "\u307e\u304e\u305f\u3044\u3089",
        "\u30de\u30ae\u30bf\u30a4\u30e9"
    ],
    "wof:name":"Magitaira",
    "wof:placetype":"locality"
},
  "geometry": {"coordinates":[141.18434999999999,40.25053],"type":"Point"}
}