{
  "type": "Feature",
  "properties": {
    "gn:admin1_code":"40.0",
    "gn:admin2_code":"1861322.0",
    "gn:asciiname":"Nakamarucho",
    "gn:country_code":"JP",
    "gn:dem":34,
    "gn:feature_class":"P",
    "gn:feature_code":"PPL",
    "gn:name":"Nakamaruch\u014d",
    "gn:population":0,
    "gn:timezone":"Asia/Tokyo",
    "iso:country":"JP",
    "name:jpn_x_preferred":[
        "\u4e2d\u4e38\u753a"
    ],
    "name:und_x_variant":[
        "Nakamaruch\u014d"
    ],
    "wof:name":"Nakamarucho",
    "wof:placetype":"locality"
},
  "geometry": {"coordinates":[139.70343,35.74224],"type":"Point"}
}