{
  "type": "Feature",
  "properties": {
    "gn:admin1_code":"3.0",
    "gn:admin2_code":"2130088.0",
    "gn:admin3_code":"2307.0",
    "gn:asciiname":"Kadonosawa",
    "gn:country_code":"JP",
    "gn:dem":5,
    "gn:feature_class":"P",
    "gn:feature_code":"PPL",
    "gn:name":"Kadonosawa",
    "gn:population":0,
    "gn:timezone":"Asia/Tokyo",
    "iso:country":"JP",
    "name:jpn_x_preferred":[
        "\u9580\u30ce\u6ca2"
    ],
    "name:jpn_x_variant":[
        "\u304b\u3069\u306e\u3055\u308f",
        "\u30ab\u30c9\u30ce\u30b5\u30ef"
    ],
    "wof:name":"Kadonosawa",
    "wof:placetype":"locality"
},
  "geometry": {"coordinates":[140.63978,41.16237],"type":"Point"}
}