{
  "type": "Feature",
  "properties": {
    "gn:admin1_code":"3.0",
    "gn:admin2_code":"2130654.0",
    "gn:asciiname":"Hagurotai",
    "gn:country_code":"JP",
    "gn:dem":48,
    "gn:feature_class":"P",
    "gn:feature_code":"PPL",
    "gn:name":"Hagurotai",
    "gn:population":0,
    "gn:timezone":"Asia/Tokyo",
    "iso:country":"JP",
    "name:jpn_x_preferred":[
        "\u7fbd\u9ed2\u5e73"
    ],
    "name:jpn_x_variant":[
        "\u306f\u3050\u308d\u305f\u3044",
        "\u30cf\u30b0\u30ed\u30bf\u30a4"
    ],
    "wof:name":"Hagurotai",
    "wof:placetype":"locality"
},
  "geometry": {"coordinates":[140.61056000000002,40.72212],"type":"Point"}
}