{
  "type": "Feature",
  "properties": {
    "iso:country":"JP",
    "name:eng_x_preferred":[
        "Shimanto Town"
    ],
    "name:jpn_x_preferred":[
        "\u56db\u4e07\u5341\u753a"
    ],
    "qs:name":"\u56db\u4e07\u5341\u753a",
    "qs:name_adm0":"\u65e5\u672c",
    "qs:name_adm1":"\u9ad8\u77e5\u770c",
    "qs:photos":118,
    "qs:photos_1k":24,
    "qs:photos_9k":1,
    "qs:photos_9r":3,
    "qs:photos_all":119,
    "qs:photos_sr":3,
    "qs:placetype":"Town",
    "qs:pop_sr":"0",
    "wof:name":"Shimanto Town",
    "wof:placetype":"locality"
},
  "geometry": {"coordinates":[132.90473549999999,33.223866],"type":"Point"}
}