{
  "type": "Feature",
  "properties": {
    "gn:admin1_code":"12.0",
    "gn:admin2_code":"2129370.0",
    "gn:asciiname":"Onbetsucho-shakubetsugen'ya",
    "gn:country_code":"JP",
    "gn:dem":27,
    "gn:feature_class":"P",
    "gn:feature_code":"PPL",
    "gn:name":"Onbetsuch\u014d-shakubetsugen\u2019ya",
    "gn:population":0,
    "gn:timezone":"Asia/Tokyo",
    "iso:country":"JP",
    "name:jpn_x_preferred":[
        "\u97f3\u5225\u753a\u5c3a\u5225\u539f\u91ce"
    ],
    "name:jpn_x_variant":[
        "\u304a\u3093\u3079\u3064\u3061\u3087\u3046\u3057\u3083\u304f\u3079\u3064\u3052\u3093\u3084",
        "\u30aa\u30f3\u30d9\u30c4\u30c1\u30e7\u30a6\u30b7\u30e3\u30af\u30d9\u30c4\u30b2\u30f3\u30e4"
    ],
    "name:und_x_variant":[
        "Shakubetsu-tank\u014d",
        "Shakubetsu",
        "Onbetsuch\u014d-shakubetsugen\u2019ya"
    ],
    "wof:name":"Onbetsucho-shakubetsugen'ya",
    "wof:placetype":"locality"
},
  "geometry": {"coordinates":[143.86879999999999,42.89852],"type":"Point"}
}