{
  "type": "Feature",
  "properties": {
    "gn:admin1_code":"4.0",
    "gn:admin2_code":"7465521.0",
    "gn:asciiname":"Sagashi",
    "gn:country_code":"JP",
    "gn:dem":52,
    "gn:feature_class":"P",
    "gn:feature_code":"PPLL",
    "gn:name":"Sagashi",
    "gn:population":0,
    "gn:timezone":"Asia/Tokyo",
    "iso:country":"JP",
    "name:jpn_x_preferred":[
        "\u5d6f\u5ce8\u5fd7"
    ],
    "name:jpn_x_variant":[
        "\u3055\u304c\u3057",
        "\u30b5\u30ac\u30b7"
    ],
    "wof:name":"Sagashi",
    "wof:placetype":"locality"
},
  "geometry": {"coordinates":[139.934,35.04266],"type":"Point"}
}