{
  "type": "Feature",
  "properties": {
    "gn:admin1_code":"27",
    "gn:admin2_code":"7418810.0",
    "gn:asciiname":"Toyotamacho-kaifuna",
    "gn:country_code":"JP",
    "gn:dem":20,
    "gn:feature_class":"P",
    "gn:feature_code":"PPL",
    "gn:name":"Toyotamach\u014d-kaifuna",
    "gn:population":0,
    "gn:timezone":"Asia/Tokyo",
    "iso:country":"JP",
    "name:jpn_x_preferred":[
        "\u8c4a\u7389\u753a\u8c9d\u9b92"
    ],
    "name:und_x_variant":[
        "Toyotamach\u014d-kaifuna",
        "Kaifuna"
    ],
    "wof:name":"Toyotamacho-kaifuna",
    "wof:placetype":"locality"
},
  "geometry": {"coordinates":[129.30636000000001,34.34665],"type":"Point"}
}