{
  "type": "Feature",
  "properties": {
    "gn:admin1_code":"32.0",
    "gn:admin2_code":"1860764.0",
    "gn:asciiname":"Mikayama",
    "gn:country_code":"JP",
    "gn:dem":85,
    "gn:feature_class":"P",
    "gn:feature_code":"PPL",
    "gn:name":"Mikayama",
    "gn:population":0,
    "gn:timezone":"Asia/Tokyo",
    "iso:country":"JP",
    "name:jpn_x_preferred":[
        "\u4e09\u30f6\u5c71"
    ],
    "wof:name":"Mikayama",
    "wof:placetype":"locality"
},
  "geometry": {"coordinates":[135.39535000000001,34.40826],"type":"Point"}
}