{
  "type": "Feature",
  "properties": {
    "gn:admin1_code":"12.0",
    "gn:admin2_code":"2128971.0",
    "gn:asciiname":"Misakicho",
    "gn:country_code":"JP",
    "gn:dem":13,
    "gn:feature_class":"P",
    "gn:feature_code":"PPL",
    "gn:name":"Misakich\u014d",
    "gn:population":0,
    "gn:timezone":"Asia/Tokyo",
    "iso:country":"JP",
    "name:jpn_x_preferred":[
        "\u5cac\u753a"
    ],
    "name:jpn_x_variant":[
        "\u307f\u3055\u304d\u3061\u3087\u3046",
        "\u30df\u30b5\u30ad\u30c1\u30e7\u30a6"
    ],
    "name:und_x_variant":[
        "Misakich\u014d"
    ],
    "wof:name":"Misakicho",
    "wof:placetype":"locality"
},
  "geometry": {"coordinates":[145.57033000000001,43.3291],"type":"Point"}
}