{
  "type": "Feature",
  "properties": {
    "gn:admin1_code":"7.0",
    "gn:admin2_code":"1859306.0",
    "gn:admin3_code":"40103.0",
    "gn:asciiname":"Koishi-honmuramachi",
    "gn:country_code":"JP",
    "gn:dem":19,
    "gn:feature_class":"P",
    "gn:feature_code":"PPL",
    "gn:name":"Koishi-honmuramachi",
    "gn:population":0,
    "gn:timezone":"Asia/Tokyo",
    "iso:country":"JP",
    "name:jpn_x_preferred":[
        "\u5c0f\u77f3\u672c\u6751\u753a"
    ],
    "wof:name":"Koishi-honmuramachi",
    "wof:placetype":"locality"
},
  "geometry": {"coordinates":[130.78243000000001,33.91729],"type":"Point"}
}