{
  "type": "Feature",
  "properties": {
    "gn:admin1_code":"21.0",
    "gn:admin2_code":"1859488.0",
    "gn:asciiname":"Imuta",
    "gn:country_code":"JP",
    "gn:dem":477,
    "gn:feature_class":"P",
    "gn:feature_code":"PPLL",
    "gn:name":"Imuta",
    "gn:population":0,
    "gn:timezone":"Asia/Tokyo",
    "iso:country":"JP",
    "name:jpn_x_preferred":[
        "\u4f0a\u725f\u7530"
    ],
    "name:jpn_x_variant":[
        "\u3044\u3080\u305f",
        "\u30a4\u30e0\u30bf"
    ],
    "wof:name":"Imuta",
    "wof:placetype":"locality"
},
  "geometry": {"coordinates":[130.92122000000001,32.99605],"type":"Point"}
}