{
  "type": "Feature",
  "properties": {
    "gn:country":"JP",
    "gn:fcode":"ADM3",
    "gn:population":0,
    "iso:country":"JP",
    "name:eng_x_preferred":[
        "Sugito"
    ],
    "name:eng_x_variant":[
        "Sugito-machi"
    ],
    "name:jpn_x_preferred":[
        "\u6749\u6238\u753a"
    ],
    "name:jpn_x_variant":[
        "\u3059\u304e\u3068\u307e\u3061",
        "\u30b9\u30ae\u30c8\u30de\u30c1"
    ],
    "name:und_x_variant":[
        "Sugito Machi"
    ],
    "qs:name":"Sugito-machi",
    "qs:photos_9r":0,
    "qs:photos_sr":0,
    "qs:pop_sr":"0",
    "wof:name":"Sugito",
    "wof:placetype":"localadmin",
    "wof:population":0
},
  "geometry": {"coordinates":[139.75470999999999,36.0341],"type":"Point"}
}