{
  "type": "Feature",
  "properties": {
    "gn:admin1_code":"19.0",
    "gn:admin2_code":"1848308.0",
    "gn:asciiname":"Highland",
    "gn:country_code":"JP",
    "gn:dem":80,
    "gn:feature_class":"P",
    "gn:feature_code":"PPL",
    "gn:name":"Highland",
    "gn:population":0,
    "gn:timezone":"Asia/Tokyo",
    "iso:country":"JP",
    "name:jpn_x_preferred":[
        "\u30cf\u30a4\u30e9\u30f3\u30c9"
    ],
    "name:jpn_x_variant":[
        "\u306f\u3044\u3089\u3093\u3069"
    ],
    "wof:name":"Highland",
    "wof:placetype":"locality"
},
  "geometry": {"coordinates":[139.69038,35.22472],"type":"Point"}
}