{
  "type": "Feature",
  "properties": {
    "gn:admin1_code":"21.0",
    "gn:admin2_code":"7412708.0",
    "gn:admin3_code":"43513.0",
    "gn:asciiname":"Hashizume",
    "gn:country_code":"JP",
    "gn:dem":94,
    "gn:feature_class":"P",
    "gn:feature_code":"PPLL",
    "gn:name":"Hashizume",
    "gn:population":0,
    "gn:timezone":"Asia/Tokyo",
    "iso:country":"JP",
    "name:jpn_x_preferred":[
        "\u6a4b\u8a70"
    ],
    "name:jpn_x_variant":[
        "\u306f\u3057\u3065\u3081",
        "\u30cf\u30b7\u30c5\u30e1"
    ],
    "wof:name":"Hashizume",
    "wof:placetype":"locality"
},
  "geometry": {"coordinates":[130.64771999999999,32.24471],"type":"Point"}
}