{
  "type": "Feature",
  "properties": {
    "gn:admin1_code":"21.0",
    "gn:admin2_code":"1864973.0",
    "gn:asciiname":"Yoshigaudo",
    "gn:country_code":"JP",
    "gn:dem":743,
    "gn:feature_class":"P",
    "gn:feature_code":"PPLL",
    "gn:name":"Yoshigaudo",
    "gn:population":0,
    "gn:timezone":"Asia/Tokyo",
    "iso:country":"JP",
    "name:jpn_x_preferred":[
        "\u82b3\u30f6\u5b87\u571f"
    ],
    "name:jpn_x_variant":[
        "\u3088\u3057\u304c\u3046\u3069",
        "\u30e8\u30b7\u30ac\u30a6\u30c9"
    ],
    "wof:name":"Yoshigaudo",
    "wof:placetype":"locality"
},
  "geometry": {"coordinates":[131.1516,33.0402],"type":"Point"}
}