{
  "type": "Feature",
  "properties": {
    "gn:admin1_code":"29",
    "gn:admin2_code":"7468181.0",
    "gn:asciiname":"Myogasawa",
    "gn:country_code":"JP",
    "gn:dem":186,
    "gn:feature_class":"P",
    "gn:feature_code":"PPL",
    "gn:name":"My\u014dgasawa",
    "gn:population":0,
    "gn:timezone":"Asia/Tokyo",
    "iso:country":"JP",
    "name:jpn_x_preferred":[
        "\u8317\u8377\u6ca2"
    ],
    "name:und_x_variant":[
        "Myogazawa",
        "My\u014dgasawa"
    ],
    "wof:name":"Myogasawa",
    "wof:placetype":"locality"
},
  "geometry": {"coordinates":[138.96985000000001,37.16282],"type":"Point"}
}