{
  "type": "Feature",
  "properties": {
    "gn:admin1_code":"01",
    "gn:admin2_code":"7369802.0",
    "gn:asciiname":"Urigocho",
    "gn:cc2":"JP",
    "gn:country_code":"JP",
    "gn:dem":4,
    "gn:feature_class":"P",
    "gn:feature_code":"PPL",
    "gn:name":"Urig\u014dch\u014d",
    "gn:population":0,
    "gn:timezone":"Asia/Tokyo",
    "iso:country":"JP",
    "name:und_x_variant":[
        "Urigo",
        "Urig\u014dch\u014d"
    ],
    "wof:name":"Urigocho",
    "wof:placetype":"locality"
},
  "geometry": {"coordinates":[137.38333,34.78333],"type":"Point"}
}