{
  "type": "Feature",
  "properties": {
    "gn:admin1_code":"47",
    "gn:admin2_code":"1848816.0",
    "gn:admin3_code":"47381.0",
    "gn:asciiname":"Urauchi",
    "gn:country_code":"JP",
    "gn:dem":8,
    "gn:feature_class":"P",
    "gn:feature_code":"PPL",
    "gn:name":"Urauchi",
    "gn:population":0,
    "gn:timezone":"Asia/Tokyo",
    "iso:country":"JP",
    "name:jpn_x_preferred":[
        "\u6d66\u5185"
    ],
    "name:jpn_x_variant":[
        "\u3046\u3089\u3046\u3061"
    ],
    "name:und_x_variant":[
        "Honai",
        "Urauti",
        "Urachi",
        "Urauchi"
    ],
    "wof:name":"Urauchi",
    "wof:placetype":"locality"
},
  "geometry": {"coordinates":[123.77811,24.4244],"type":"Point"}
}