{
  "type": "Feature",
  "properties": {
    "gn:admin1_code":"7.0",
    "gn:admin2_code":"1855902.0",
    "gn:asciiname":"Otsujimachi",
    "gn:country_code":"JP",
    "gn:dem":18,
    "gn:feature_class":"P",
    "gn:feature_code":"PPL",
    "gn:name":"\u014ctsujimachi",
    "gn:population":0,
    "gn:timezone":"Asia/Tokyo",
    "iso:country":"JP",
    "name:jpn_x_preferred":[
        "\u5927\u8fbb\u753a"
    ],
    "name:und_x_variant":[
        "\u014ctsujimachi"
    ],
    "wof:name":"Otsujimachi",
    "wof:placetype":"locality"
},
  "geometry": {"coordinates":[130.72576000000001,33.80754],"type":"Point"}
}