{
  "type": "Feature",
  "properties": {
    "gn:admin1_code":"46.0",
    "gn:admin2_code":"1857168.0",
    "gn:admin3_code":"19365.0",
    "gn:asciiname":"Michi",
    "gn:country_code":"JP",
    "gn:dem":312,
    "gn:feature_class":"P",
    "gn:feature_code":"PPL",
    "gn:name":"Michi",
    "gn:population":0,
    "gn:timezone":"Asia/Tokyo",
    "iso:country":"JP",
    "name:jpn_x_preferred":[
        "\u9053"
    ],
    "wof:name":"Michi",
    "wof:placetype":"locality"
},
  "geometry": {"coordinates":[138.51050000000001,35.48097999999999],"type":"Point"}
}