{
  "type": "Feature",
  "properties": {
    "gn:admin1_code":"19.0",
    "gn:admin2_code":"1848308.0",
    "gn:asciiname":"Taura-osakucho",
    "gn:country_code":"JP",
    "gn:dem":49,
    "gn:feature_class":"P",
    "gn:feature_code":"PPL",
    "gn:name":"Taura-\u014dsakuch\u014d",
    "gn:population":0,
    "gn:timezone":"Asia/Tokyo",
    "iso:country":"JP",
    "name:jpn_x_preferred":[
        "\u7530\u6d66\u5927\u4f5c\u753a"
    ],
    "name:jpn_x_variant":[
        "\u305f\u3046\u3089\u304a\u304a\u3055\u304f\u3061\u3087\u3046",
        "\u30bf\u30a6\u30e9\u30aa\u30aa\u30b5\u30af\u30c1\u30e7\u30a6"
    ],
    "name:und_x_variant":[
        "Taura-\u014dsakuch\u014d"
    ],
    "wof:name":"Taura-osakucho",
    "wof:placetype":"locality"
},
  "geometry": {"coordinates":[139.62881000000002,35.28849],"type":"Point"}
}