{
  "type": "Feature",
  "properties": {
    "gn:admin1_code":"7.0",
    "gn:admin2_code":"1854385.0",
    "gn:asciiname":"Uchibiraki",
    "gn:country_code":"JP",
    "gn:dem":0,
    "gn:feature_class":"P",
    "gn:feature_code":"PPL",
    "gn:name":"Uchibiraki",
    "gn:population":0,
    "gn:timezone":"Asia/Tokyo",
    "iso:country":"JP",
    "name:jpn_x_preferred":[
        "\u5185\u958b"
    ],
    "wof:name":"Uchibiraki",
    "wof:placetype":"locality"
},
  "geometry": {"coordinates":[130.34797,33.19079],"type":"Point"}
}