{
  "type": "Feature",
  "properties": {
    "gn:admin1_code":"05",
    "gn:admin2_code":"1859256.0",
    "gn:admin3_code":"38484.0",
    "gn:asciiname":"Yoshino",
    "gn:country_code":"JP",
    "gn:dem":77,
    "gn:feature_class":"P",
    "gn:feature_code":"PPL",
    "gn:name":"Yoshino",
    "gn:population":0,
    "gn:timezone":"Asia/Tokyo",
    "iso:country":"JP",
    "wof:name":"Yoshino",
    "wof:placetype":"locality"
},
  "geometry": {"coordinates":[132.73063999999999,33.22203],"type":"Point"}
}