{
  "type": "Feature",
  "properties": {
    "gn:admin1_code":"05",
    "gn:admin2_code":"1859256.0",
    "gn:admin3_code":"38484.0",
    "gn:asciiname":"Yoshino",
    "gn:country_code":"JP",
    "gn:dem":77,
    "gn:feature_class":"P",
    "gn:feature_code":"PPL",
    "gn:name":"Yoshino",
    "gn:population":0,
    "gn:timezone":"Asia/Tokyo",
    "iso:country":"JP",
    "name:ces_x_preferred":[
        "Jo\u0161ino"
    ],
    "name:deu_x_preferred":[
        "Yoshino"
    ],
    "name:fra_x_preferred":[
        "Yoshino"
    ],
    "name:ind_x_preferred":[
        "Yoshino"
    ],
    "name:ita_x_preferred":[
        "Yoshino"
    ],
    "name:jpn_x_preferred":[
        "\u5409\u91ce"
    ],
    "name:kor_x_preferred":[
        "\uc694\uc2dc\ub178"
    ],
    "name:nld_x_preferred":[
        "Yoshino"
    ],
    "name:rus_x_preferred":[
        "\u0419\u043e\u0441\u0438\u043d\u043e"
    ],
    "name:spa_x_preferred":[
        "Yoshino"
    ],
    "name:ukr_x_preferred":[
        "\u0419\u043e\u0441\u0456\u043d\u043e"
    ],
    "name:zho_x_preferred":[
        "\u5409\u91ce"
    ],
    "wof:name":"Yoshino",
    "wof:placetype":"locality"
},
  "geometry": {"coordinates":[132.73063999999999,33.22203],"type":"Point"}
}