{
  "type": "Feature",
  "properties": {
    "gn:admin1_code":"4.0",
    "gn:admin2_code":"7465524.0",
    "gn:asciiname":"Teranoshita",
    "gn:country_code":"JP",
    "gn:dem":20,
    "gn:feature_class":"P",
    "gn:feature_code":"PPLL",
    "gn:name":"Teranoshita",
    "gn:population":0,
    "gn:timezone":"Asia/Tokyo",
    "iso:country":"JP",
    "name:jpn_x_preferred":[
        "\u5bfa\u30ce\u4e0b"
    ],
    "name:jpn_x_variant":[
        "\u3066\u3089\u306e\u3057\u305f",
        "\u30c6\u30e9\u30ce\u30b7\u30bf"
    ],
    "wof:name":"Teranoshita",
    "wof:placetype":"locality"
},
  "geometry": {"coordinates":[140.28985,35.27264],"type":"Point"}
}