{
  "type": "Feature",
  "properties": {
    "gn:admin1_code":"36.0",
    "gn:admin2_code":"1854361.0",
    "gn:admin3_code":"32528.0",
    "gn:asciiname":"Minaichi",
    "gn:country_code":"JP",
    "gn:dem":83,
    "gn:feature_class":"P",
    "gn:feature_code":"PPL",
    "gn:name":"Minaichi",
    "gn:population":0,
    "gn:timezone":"Asia/Tokyo",
    "iso:country":"JP",
    "name:jpn_x_preferred":[
        "\u7686\u5e02"
    ],
    "wof:name":"Minaichi",
    "wof:placetype":"locality"
},
  "geometry": {"coordinates":[133.26993000000002,36.239],"type":"Point"}
}