{
  "type": "Feature",
  "properties": {
    "gn:admin1_code":"12.0",
    "gn:admin2_code":"7428083.0",
    "gn:admin3_code":"1610.0",
    "gn:asciiname":"Shizunai-harutachi",
    "gn:country_code":"JP",
    "gn:dem":7,
    "gn:feature_class":"P",
    "gn:feature_code":"PPL",
    "gn:name":"Shizunai-harutachi",
    "gn:population":0,
    "gn:timezone":"Asia/Tokyo",
    "iso:country":"JP",
    "name:jpn_x_preferred":[
        "\u9759\u5185\u6625\u7acb"
    ],
    "wof:name":"Shizunai-harutachi",
    "wof:placetype":"locality"
},
  "geometry": {"coordinates":[142.49653000000001,42.26972],"type":"Point"}
}