{
  "type": "Feature",
  "properties": {
    "gn:admin1_code":"21.0",
    "gn:admin2_code":"7413152.0",
    "gn:asciiname":"Jugosha",
    "gn:country_code":"JP",
    "gn:dem":4,
    "gn:feature_class":"P",
    "gn:feature_code":"PPLL",
    "gn:name":"J\u016bgosha",
    "gn:population":0,
    "gn:timezone":"Asia/Tokyo",
    "iso:country":"JP",
    "name:jpn_x_preferred":[
        "\u5341\u4e94\u793e"
    ],
    "name:jpn_x_variant":[
        "\u3058\u3085\u3046\u3054\u3057\u3083",
        "\u30b8\u30e5\u30a6\u30b4\u30b7\u30e3"
    ],
    "name:und_x_variant":[
        "J\u016bgosha"
    ],
    "wof:name":"Jugosha",
    "wof:placetype":"locality"
},
  "geometry": {"coordinates":[130.66332,32.64698],"type":"Point"}
}