{
  "type": "Feature",
  "properties": {
    "gn:admin1_code":"3.0",
    "gn:admin2_code":"2129224.0",
    "gn:admin3_code":"2361.0",
    "gn:asciiname":"Wakamatsu",
    "gn:country_code":"JP",
    "gn:dem":23,
    "gn:feature_class":"P",
    "gn:feature_code":"PPL",
    "gn:name":"Wakamatsu",
    "gn:population":0,
    "gn:timezone":"Asia/Tokyo",
    "iso:country":"JP",
    "name:ceb_x_preferred":[
        "Wakamatsu"
    ],
    "name:deu_x_preferred":[
        "Wakamatsu"
    ],
    "name:ita_x_preferred":[
        "Wakamatsu"
    ],
    "name:jpn_x_preferred":[
        "\u82e5\u677e"
    ],
    "name:jpn_x_variant":[
        "\u308f\u304b\u307e\u3064",
        "\u30ef\u30ab\u30de\u30c4"
    ],
    "name:kor_x_preferred":[
        "\uc640\uce74\ub9c8\uc4f0"
    ],
    "name:rus_x_preferred":[
        "\u0412\u0430\u043a\u0430\u043c\u0430\u0446\u0443"
    ],
    "wof:name":"Wakamatsu",
    "wof:placetype":"locality"
},
  "geometry": {"coordinates":[140.5351,40.66737],"type":"Point"}
}