{
  "type": "Feature",
  "properties": {
    "gn:admin1_code":"37",
    "gn:admin2_code":"1854181.0",
    "gn:asciiname":"Shitamisaki",
    "gn:country_code":"JP",
    "gn:dem":45,
    "gn:feature_class":"P",
    "gn:feature_code":"PPL",
    "gn:name":"Shitamisaki",
    "gn:population":0,
    "gn:timezone":"Asia/Tokyo",
    "iso:country":"JP",
    "name:jpn_x_preferred":[
        "\u4e0b\u5cac"
    ],
    "name:und_x_variant":[
        "Shimo-misaki",
        "Shita-misaki",
        "Shitamisaki"
    ],
    "wof:name":"Shitamisaki",
    "wof:placetype":"locality"
},
  "geometry": {"coordinates":[138.22873999999999,34.60101],"type":"Point"}
}