{
  "type": "Feature",
  "properties": {
    "gn:country":"JP",
    "gn:fcode":"PPL",
    "gn:population":101133,
    "iso:country":"JP",
    "name:ces_x_preferred":[
        "Tokujama"
    ],
    "name:eng_x_preferred":[
        "Tokuyama"
    ],
    "name:fra_x_preferred":[
        "Tokuyama"
    ],
    "name:ind_x_preferred":[
        "Tokuyama"
    ],
    "name:jpn_x_preferred":[
        "\u5fb3\u5c71\u5e02"
    ],
    "name:kor_x_preferred":[
        "\ub3c4\ucfe0\uc57c\ub9c8 \uc2dc"
    ],
    "name:kor_x_variant":[
        "\ub3c4\ucfe0\uc57c\ub9c8\uc2dc"
    ],
    "name:pol_x_preferred":[
        "Tokuyama"
    ],
    "name:rus_x_preferred":[
        "\u0422\u043e\u043a\u0443\u044f\u043c\u0430"
    ],
    "name:und_x_variant":[
        "Kakuyama"
    ],
    "name:war_x_preferred":[
        "Tokuyama"
    ],
    "name:zho_x_preferred":[
        "\u5fb7\u5c71\u5e02"
    ],
    "qs:name":"Tokuyama",
    "qs:photos_9r":0,
    "qs:photos_sr":0,
    "qs:pop_sr":"9",
    "wd:wordcount":81,
    "wof:name":"Tokuyama",
    "wof:placetype":"locality",
    "wof:population":101133
},
  "geometry": {"coordinates":[131.81666999999999,34.05],"type":"Point"}
}