{
  "type": "Feature",
  "properties": {
    "iso:country":"JP",
    "name:eng_x_preferred":[
        "Shibusawa 3 Chome"
    ],
    "name:eng_x_variant":[
        "Shibusawa 3 Choume",
        "Shibusawa 3 Chome"
    ],
    "name:jpn_x_preferred":[
        "\uff13\u4e01\u76ee"
    ],
    "name:jpn_x_variant":[
        "\u3057\u3076\u3055\u308f \uff13\u3061\u3087\u3046\u3081",
        "\u6e0b\u6ca2 \uff13\u4e01\u76ee",
        "\uff13\u3061\u3087\u3046\u3081"
    ],
    "qs:gn_local":0,
    "qs:local_max":377,
    "qs:local_sum":913,
    "qs:localhoods":11,
    "qs:name":"\uff13\u4e01\u76ee",
    "qs:name_adm0":"\u65e5\u672c",
    "qs:name_adm1":"\u795e\u5948\u5ddd\u770c",
    "qs:name_en":"Shibusawa 3 Chome",
    "qs:name_lau":"\u6e0b\u6ca2",
    "qs:name_local":"\u79e6\u91ce\u5e02",
    "qs:photo_max":41,
    "qs:photo_sum":77,
    "qs:placetype":"Suburb",
    "qs:quad_count":13,
    "qs:woe_adm0":23424856,
    "qs:woe_adm1":2345868,
    "qs:woe_adm2":0,
    "qs:woe_lau":28417122,
    "qs:woe_local":1117144,
    "qs:woe_ver":"7.10.0",
    "wof:lang":[
        "jpn"
    ],
    "wof:name":"\uff13\u4e01\u76ee",
    "wof:placetype":"neighbourhood"
},
  "geometry": {"coordinates":[139.20443599999999,35.374176],"type":"Point"}
}