{
  "type": "Feature",
  "properties": {
    "gn:admin1_code":"33.0",
    "gn:admin2_code":"8300623.0",
    "gn:asciiname":"Ochicho-sari",
    "gn:country_code":"JP",
    "gn:dem":24,
    "gn:feature_class":"P",
    "gn:feature_code":"PPL",
    "gn:name":"\u014cchich\u014d-sari",
    "gn:population":0,
    "gn:timezone":"Asia/Tokyo",
    "iso:country":"JP",
    "name:jpn_x_preferred":[
        "\u76f8\u77e5\u753a\u4f50\u91cc"
    ],
    "name:und_x_variant":[
        "\u014cchich\u014d-sari"
    ],
    "wof:name":"Ochicho-sari",
    "wof:placetype":"locality"
},
  "geometry": {"coordinates":[129.98729,33.33965999999999],"type":"Point"}
}