{
  "type": "Feature",
  "properties": {
    "gn:admin1_code":"19.0",
    "gn:admin2_code":"1856849.0",
    "gn:asciiname":"Nagahata",
    "gn:country_code":"JP",
    "gn:dem":39,
    "gn:feature_class":"P",
    "gn:feature_code":"PPLL",
    "gn:name":"Nagahata",
    "gn:population":0,
    "gn:timezone":"Asia/Tokyo",
    "iso:country":"JP",
    "name:jpn_x_preferred":[
        "\u9577\u7551"
    ],
    "name:jpn_x_variant":[
        "\u306a\u304c\u306f\u305f",
        "\u30ca\u30ac\u30cf\u30bf"
    ],
    "wof:name":"Nagahata",
    "wof:placetype":"locality"
},
  "geometry": {"coordinates":[139.62868,35.15951],"type":"Point"}
}