{
  "type": "Feature",
  "properties": {
    "gn:admin1_code":"34.0",
    "gn:admin2_code":"1859726.0",
    "gn:asciiname":"Kitada",
    "gn:country_code":"JP",
    "gn:dem":18,
    "gn:feature_class":"P",
    "gn:feature_code":"PPLL",
    "gn:name":"Kitada",
    "gn:population":0,
    "gn:timezone":"Asia/Tokyo",
    "iso:country":"JP",
    "name:jpn_x_preferred":[
        "\u5317\u7530"
    ],
    "name:jpn_x_variant":[
        "\u304d\u305f\u3060",
        "\u30ad\u30bf\u30c0"
    ],
    "wof:name":"Kitada",
    "wof:placetype":"locality"
},
  "geometry": {"coordinates":[139.73533999999998,35.85085],"type":"Point"}
}