{
  "type": "Feature",
  "properties": {
    "gn:admin1_code":"18.0",
    "gn:admin2_code":"1853737.0",
    "gn:admin3_code":"46532.0",
    "gn:asciiname":"Bane",
    "gn:country_code":"JP",
    "gn:dem":141,
    "gn:feature_class":"P",
    "gn:feature_code":"PPL",
    "gn:name":"Bane",
    "gn:population":0,
    "gn:timezone":"Asia/Tokyo",
    "iso:country":"JP",
    "name:jpn_x_preferred":[
        "\u99ac\u6839"
    ],
    "wof:name":"Bane",
    "wof:placetype":"locality"
},
  "geometry": {"coordinates":[128.94159999999999,27.71229000000001],"type":"Point"}
}