{
  "type": "Feature",
  "properties": {
    "gn:admin1_code":"18.0",
    "gn:admin2_code":"1853737.0",
    "gn:admin3_code":"46532.0",
    "gn:asciiname":"Bane",
    "gn:country_code":"JP",
    "gn:dem":141,
    "gn:feature_class":"P",
    "gn:feature_code":"PPL",
    "gn:name":"Bane",
    "gn:population":0,
    "gn:timezone":"Asia/Tokyo",
    "iso:country":"JP",
    "name:ceb_x_preferred":[
        "Bane"
    ],
    "name:ces_x_preferred":[
        "Bane"
    ],
    "name:dan_x_preferred":[
        "Bane"
    ],
    "name:deu_x_preferred":[
        "Bane"
    ],
    "name:fra_x_preferred":[
        "Bane"
    ],
    "name:hye_x_preferred":[
        "\u0532\u0561\u0576\u0565"
    ],
    "name:ita_x_preferred":[
        "Bane"
    ],
    "name:jpn_x_preferred":[
        "\u99ac\u6839"
    ],
    "name:kur_x_preferred":[
        "Bane"
    ],
    "name:nld_x_preferred":[
        "Bane"
    ],
    "name:pol_x_preferred":[
        "Bane"
    ],
    "name:por_x_preferred":[
        "Bane"
    ],
    "name:slv_x_preferred":[
        "Bane"
    ],
    "name:spa_x_preferred":[
        "Bane"
    ],
    "name:swe_x_preferred":[
        "Bane"
    ],
    "name:tha_x_preferred":[
        "\u0e40\u0e1a\u0e19"
    ],
    "name:ukr_x_preferred":[
        "\u0411\u0430\u043d\u0435"
    ],
    "wof:name":"Bane",
    "wof:placetype":"locality"
},
  "geometry": {"coordinates":[128.94159999999999,27.71229000000001],"type":"Point"}
}