{
  "type": "Feature",
  "properties": {
    "gn:admin1_code":"40.0",
    "gn:admin2_code":"1864242.0",
    "gn:asciiname":"Kitakasai",
    "gn:country_code":"JP",
    "gn:dem":0,
    "gn:feature_class":"P",
    "gn:feature_code":"PPL",
    "gn:name":"Kitakasai",
    "gn:population":0,
    "gn:timezone":"Asia/Tokyo",
    "iso:country":"JP",
    "name:jpn_x_preferred":[
        "\u5317\u845b\u897f"
    ],
    "wof:name":"Kitakasai",
    "wof:placetype":"locality"
},
  "geometry": {"coordinates":[139.86104,35.67391],"type":"Point"}
}