{
  "type": "Feature",
  "properties": {
    "gn:admin1_code":"32",
    "gn:admin2_code":"1853897.0",
    "gn:admin3_code":"27108.0",
    "gn:asciiname":"Kitamura",
    "gn:country_code":"JP",
    "gn:dem":4,
    "gn:feature_class":"P",
    "gn:feature_code":"PPL",
    "gn:name":"Kitamura",
    "gn:population":0,
    "gn:timezone":"Asia/Tokyo",
    "iso:country":"JP",
    "name:jpn_x_preferred":[
        "\u5317\u6751"
    ],
    "name:rus_x_preferred":[
        "\u041a\u0438\u0442\u0430\u043c\u0443\u0440\u0430"
    ],
    "name:und_x_variant":[
        "Izumio-Kitamurach\u014d",
        "Izuo-kitamurach\u014d",
        "Kitamura"
    ],
    "wof:name":"Kitamura",
    "wof:placetype":"locality"
},
  "geometry": {"coordinates":[135.46695,34.65182],"type":"Point"}
}