{
  "type": "Feature",
  "properties": {
    "gn:admin1_code":"24.0",
    "gn:admin2_code":"2112074.0",
    "gn:admin3_code":"4423.0",
    "gn:asciiname":"Shitoda",
    "gn:country_code":"JP",
    "gn:dem":21,
    "gn:feature_class":"P",
    "gn:feature_code":"PPL",
    "gn:name":"Shitoda",
    "gn:population":0,
    "gn:timezone":"Asia/Tokyo",
    "iso:country":"JP",
    "name:jpn_x_preferred":[
        "\u5fd7\u6238\u7530"
    ],
    "wof:name":"Shitoda",
    "wof:placetype":"locality"
},
  "geometry": {"coordinates":[140.88648000000001,38.4242],"type":"Point"}
}