{
  "type": "Feature",
  "properties": {
    "gn:country":"JP",
    "gn:fcode":"ADM3",
    "gn:pop":0,
    "iso:country":"JP",
    "name:jpn_x_preferred":[
        "\u5b9c\u91ce\u5ea7\u6751"
    ],
    "name:jpn_x_variant":[
        "\u304e\u306e\u3056\u305d\u3093"
    ],
    "name:unk_x_variant":[
        "Ginoza"
    ],
    "qs:name":"Ginoza-son",
    "qs:photos_9r":0,
    "qs:photos_sr":0,
    "qs:pop_sr":"0",
    "wof:name":"Ginoza-son",
    "wof:placetype":"localadmin",
    "wof:population":0
},
  "geometry": {"coordinates":[127.96646,26.49483],"type":"Point"}
}