{
  "type": "Feature",
  "properties": {
    "gn:admin1_code":"29.0",
    "gn:admin2_code":"1854443.0",
    "gn:asciiname":"Tsubono",
    "gn:country_code":"JP",
    "gn:dem":91,
    "gn:feature_class":"P",
    "gn:feature_code":"PPL",
    "gn:name":"Tsubono",
    "gn:population":0,
    "gn:timezone":"Asia/Tokyo",
    "iso:country":"JP",
    "name:jpn_x_preferred":[
        "\u576a\u91ce"
    ],
    "wof:name":"Tsubono",
    "wof:placetype":"locality"
},
  "geometry": {"coordinates":[138.77334999999999,37.3398],"type":"Point"}
}