{
  "type": "Feature",
  "properties": {
    "gn:admin1_code":"19.0",
    "gn:admin2_code":"1860670.0",
    "gn:asciiname":"Shichirigahama-higashi",
    "gn:country_code":"JP",
    "gn:dem":47,
    "gn:feature_class":"P",
    "gn:feature_code":"PPL",
    "gn:name":"Shichirigahama-higashi",
    "gn:population":0,
    "gn:timezone":"Asia/Tokyo",
    "iso:country":"JP",
    "name:jpn_x_preferred":[
        "\u4e03\u91cc\u30ac\u6d5c\u6771"
    ],
    "name:jpn_x_variant":[
        "\u3057\u3061\u308a\u304c\u306f\u307e\u3072\u304c\u3057",
        "\u30b7\u30c1\u30ea\u30ac\u30cf\u30de\u30d2\u30ac\u30b7"
    ],
    "wof:name":"Shichirigahama-higashi",
    "wof:placetype":"locality"
},
  "geometry": {"coordinates":[139.51658999999998,35.31047],"type":"Point"}
}