{
  "type": "Feature",
  "properties": {
    "gn:admin1_code":"8.0",
    "gn:admin2_code":"9035647.0",
    "gn:asciiname":"Funehikimachi-niitate",
    "gn:country_code":"JP",
    "gn:dem":394,
    "gn:feature_class":"P",
    "gn:feature_code":"PPL",
    "gn:name":"Funehikimachi-niitate",
    "gn:population":0,
    "gn:timezone":"Asia/Tokyo",
    "iso:country":"JP",
    "name:jpn_x_preferred":[
        "\u8239\u5f15\u753a\u65b0\u8218"
    ],
    "name:und_x_variant":[
        "Niitate",
        "Niidade",
        "Niidate",
        "Funehikimachi-niitate"
    ],
    "wof:name":"Funehikimachi-niitate",
    "wof:placetype":"locality"
},
  "geometry": {"coordinates":[140.58211,37.49707],"type":"Point"}
}