{
  "type": "Feature",
  "properties": {
    "gn:admin1_code":"37.0",
    "gn:admin2_code":"1864943.0",
    "gn:asciiname":"Hibarigaoka",
    "gn:country_code":"JP",
    "gn:dem":321,
    "gn:feature_class":"P",
    "gn:feature_code":"PPLL",
    "gn:name":"Hibarigaoka",
    "gn:population":0,
    "gn:timezone":"Asia/Tokyo",
    "iso:country":"JP",
    "name:jpn_x_preferred":[
        "\u3072\u3070\u308a\u30f6\u4e18"
    ],
    "wof:name":"Hibarigaoka",
    "wof:placetype":"locality"
},
  "geometry": {"coordinates":[139.04689999999999,35.08655],"type":"Point"}
}