{
  "type": "Feature",
  "properties": {
    "gn:admin1_code":"10",
    "gn:admin2_code":"1861435.0",
    "gn:asciiname":"Tabeicho",
    "gn:country_code":"JP",
    "gn:dem":90,
    "gn:feature_class":"P",
    "gn:feature_code":"PPL",
    "gn:name":"Tabeich\u014d",
    "gn:population":0,
    "gn:timezone":"Asia/Tokyo",
    "iso:country":"JP",
    "name:jpn_x_preferred":[
        "\u7530\u90e8\u4e95\u753a"
    ],
    "name:und_x_variant":[
        "Tanagai",
        "Tamegai",
        "Tabeich\u014d"
    ],
    "wof:name":"Tabeicho",
    "wof:placetype":"locality"
},
  "geometry": {"coordinates":[139.25,36.35],"type":"Point"}
}