{
  "type": "Feature",
  "properties": {
    "gn:admin1_code":"21.0",
    "gn:admin2_code":"1857206.0",
    "gn:asciiname":"Hiramachi",
    "gn:country_code":"JP",
    "gn:dem":6,
    "gn:feature_class":"P",
    "gn:feature_code":"PPL",
    "gn:name":"Hiramachi",
    "gn:population":0,
    "gn:timezone":"Asia/Tokyo",
    "iso:country":"JP",
    "name:jpn_x_preferred":[
        "\u5e73\u753a"
    ],
    "name:jpn_x_variant":[
        "\u3072\u3089\u307e\u3061",
        "\u30d2\u30e9\u30de\u30c1"
    ],
    "wof:name":"Hiramachi",
    "wof:placetype":"locality"
},
  "geometry": {"coordinates":[130.40308000000002,32.2065],"type":"Point"}
}