{
  "type": "Feature",
  "properties": {
    "gn:admin1_code":"34.0",
    "gn:admin2_code":"1859726.0",
    "gn:asciiname":"Zaikecho",
    "gn:country_code":"JP",
    "gn:dem":6,
    "gn:feature_class":"P",
    "gn:feature_code":"PPL",
    "gn:name":"Zaikech\u014d",
    "gn:population":0,
    "gn:timezone":"Asia/Tokyo",
    "iso:country":"JP",
    "name:jpn_x_preferred":[
        "\u5728\u5bb6\u753a"
    ],
    "name:jpn_x_variant":[
        "\u3056\u3044\u3051\u3061\u3087\u3046",
        "\u30b6\u30a4\u30b1\u30c1\u30e7\u30a6"
    ],
    "name:und_x_variant":[
        "Zaikech\u014d"
    ],
    "wof:name":"Zaikecho",
    "wof:placetype":"locality"
},
  "geometry": {"coordinates":[139.70891,35.85662],"type":"Point"}
}