{
  "type": "Feature",
  "properties": {
    "gn:admin1_code":"34.0",
    "gn:admin2_code":"1861470.0",
    "gn:admin3_code":"11324.0",
    "gn:asciiname":"Nishizume",
    "gn:country_code":"JP",
    "gn:dem":41,
    "gn:feature_class":"P",
    "gn:feature_code":"PPLL",
    "gn:name":"Nishizume",
    "gn:population":0,
    "gn:timezone":"Asia/Tokyo",
    "iso:country":"JP",
    "name:jpn_x_preferred":[
        "\u897f\u8a70"
    ],
    "name:jpn_x_variant":[
        "\u306b\u3057\u3065\u3081"
    ],
    "wof:name":"Nishizume",
    "wof:placetype":"locality"
},
  "geometry": {"coordinates":[139.51883999999998,35.82903],"type":"Point"}
}