{
  "type": "Feature",
  "properties": {
    "gn:admin1_code":"35.0",
    "gn:admin2_code":"1858984.0",
    "gn:asciiname":"Tsuchiyamacho-kurotaki",
    "gn:country_code":"JP",
    "gn:dem":349,
    "gn:feature_class":"P",
    "gn:feature_code":"PPL",
    "gn:name":"Tsuchiyamach\u014d-kurotaki",
    "gn:population":0,
    "gn:timezone":"Asia/Tokyo",
    "iso:country":"JP",
    "name:jpn_x_preferred":[
        "\u571f\u5c71\u753a\u9ed2\u6edd"
    ],
    "name:und_x_variant":[
        "Tsuchiyamach\u014d-kurotaki"
    ],
    "wof:name":"Tsuchiyamacho-kurotaki",
    "wof:placetype":"locality"
},
  "geometry": {"coordinates":[136.34796,34.93601],"type":"Point"}
}