{
  "type": "Feature",
  "properties": {
    "gn:admin1_code":"37.0",
    "gn:admin2_code":"1864089.0",
    "gn:asciiname":"Aioicho",
    "gn:country_code":"JP",
    "gn:dem":70,
    "gn:feature_class":"P",
    "gn:feature_code":"PPLL",
    "gn:name":"Aioich\u014d",
    "gn:population":0,
    "gn:timezone":"Asia/Tokyo",
    "iso:country":"JP",
    "name:jpn_x_preferred":[
        "\u76f8\u751f\u753a"
    ],
    "name:und_x_variant":[
        "Aioich\u014d"
    ],
    "wof:name":"Aioicho",
    "wof:placetype":"locality"
},
  "geometry": {"coordinates":[138.61694,35.1499],"type":"Point"}
}