{
  "type": "Feature",
  "properties": {
    "gn:admin1_code":"7.0",
    "gn:admin2_code":"1854055.0",
    "gn:admin3_code":"40381.0",
    "gn:asciiname":"Okimi",
    "gn:country_code":"JP",
    "gn:dem":5,
    "gn:feature_class":"P",
    "gn:feature_code":"PPLL",
    "gn:name":"\u014ckimi",
    "gn:population":0,
    "gn:timezone":"Asia/Tokyo",
    "iso:country":"JP",
    "name:jpn_x_preferred":[
        "\u5927\u541b\u3000"
    ],
    "name:und_x_variant":[
        "\u014ckimi"
    ],
    "wof:name":"Okimi",
    "wof:placetype":"locality"
},
  "geometry": {"coordinates":[130.67994999999999,33.89389],"type":"Point"}
}