{
  "type": "Feature",
  "properties": {
    "gn:admin1_code":"21.0",
    "gn:admin2_code":"7412706.0",
    "gn:admin3_code":"43447.0",
    "gn:asciiname":"Kakoi",
    "gn:country_code":"JP",
    "gn:dem":404,
    "gn:feature_class":"P",
    "gn:feature_code":"PPLL",
    "gn:name":"Kakoi",
    "gn:population":0,
    "gn:timezone":"Asia/Tokyo",
    "iso:country":"JP",
    "name:jpn_x_preferred":[
        "\u56f2"
    ],
    "name:jpn_x_variant":[
        "\u304b\u3053\u3044",
        "\u30ab\u30b3\u30a4"
    ],
    "wof:name":"Kakoi",
    "wof:placetype":"locality"
},
  "geometry": {"coordinates":[131.00901999999999,32.64698],"type":"Point"}
}