{
  "type": "Feature",
  "properties": {
    "iso:country":"JP",
    "name:eng_x_preferred":[
        "Futago 3 Chome"
    ],
    "name:eng_x_variant":[
        "Futago 3 Choume",
        "Futago 3 Chome"
    ],
    "name:jpn_x_preferred":[
        "\uff13\u4e01\u76ee"
    ],
    "name:jpn_x_variant":[
        "\u3075\u305f\u3054 \uff13\u3061\u3087\u3046\u3081",
        "\u4e8c\u30bf\u5b50 \uff13\u4e01\u76ee",
        "\uff13\u3061\u3087\u3046\u3081"
    ],
    "name:unk_x_variant":[
        "\uff13\u4e01\u76ee"
    ],
    "qs:gn_local":0,
    "qs:local_max":814,
    "qs:local_sum":1092,
    "qs:localhoods":4,
    "qs:name":"\uff13\u4e01\u76ee",
    "qs:name_adm0":"\u65e5\u672c",
    "qs:name_adm1":"\u4f50\u8cc0\u770c",
    "qs:name_en":"Futago 3 Chome",
    "qs:name_lau":"\u4e8c\u30bf\u5b50",
    "qs:name_local":"\u5510\u6d25\u5e02",
    "qs:photo_max":16,
    "qs:photo_sum":24,
    "qs:placetype":"Suburb",
    "qs:quad_count":2,
    "qs:woe_adm0":23424856,
    "qs:woe_adm1":2345882,
    "qs:woe_adm2":0,
    "qs:woe_lau":28485766,
    "qs:woe_local":1117451,
    "qs:woe_ver":"7.10.0",
    "wof:lang":[
        "jpn"
    ],
    "wof:name":"\uff13\u4e01\u76ee",
    "wof:placetype":"neighbourhood"
},
  "geometry": {"coordinates":[129.980164,33.473452],"type":"Point"}
}