{
  "type": "Feature",
  "properties": {
    "gn:admin1_code":"46.0",
    "gn:asciiname":"Kadono",
    "gn:country_code":"JP",
    "gn:dem":255,
    "gn:feature_class":"P",
    "gn:feature_code":"PPLL",
    "gn:name":"Kadono",
    "gn:population":0,
    "gn:timezone":"Asia/Tokyo",
    "iso:country":"JP",
    "name:jpn_x_preferred":[
        "\u9580\u91ce"
    ],
    "wof:name":"Kadono",
    "wof:placetype":"locality"
},
  "geometry": {"coordinates":[138.53097,35.28104000000001],"type":"Point"}
}