{
  "type": "Feature",
  "properties": {
    "iso:country":"JP",
    "name:eng_x_preferred":[
        "Tobitakyu 1 Chome"
    ],
    "name:eng_x_variant":[
        "Tobitakyuu 1 Choume",
        "Tobitakyu 1 Chome"
    ],
    "name:jpn_x_preferred":[
        "\uff11\u4e01\u76ee"
    ],
    "name:jpn_x_variant":[
        "\u3068\u3073\u305f\u304d\u3085\u3046 \uff11\u3061\u3087\u3046\u3081",
        "\u98db\u7530\u7d66 \uff11\u4e01\u76ee",
        "\uff11\u3061\u3087\u3046\u3081"
    ],
    "qs:gn_local":0,
    "qs:local_max":1845,
    "qs:local_sum":7669,
    "qs:localhoods":21,
    "qs:name":"\uff11\u4e01\u76ee",
    "qs:name_adm0":"\u65e5\u672c",
    "qs:name_adm1":"\u6771\u4eac\u90fd",
    "qs:name_en":"Tobitakyu 1 Chome",
    "qs:name_lau":"\u98db\u7530\u7d66",
    "qs:name_local":"\u8abf\u5e03\u5e02",
    "qs:photo_max":969,
    "qs:photo_sum":1121,
    "qs:placetype":"Suburb",
    "qs:quad_count":3,
    "qs:woe_adm0":23424856,
    "qs:woe_adm1":2345889,
    "qs:woe_adm2":0,
    "qs:woe_lau":28415061,
    "qs:woe_local":1107816,
    "qs:woe_ver":"7.10.0",
    "wof:lang":[
        "jpn"
    ],
    "wof:name":"\uff11\u4e01\u76ee",
    "wof:placetype":"neighbourhood"
},
  "geometry": {"coordinates":[139.52736999999999,35.665065],"type":"Point"}
}