{
  "type": "Feature",
  "properties": {
    "gn:admin1_code":"21.0",
    "gn:admin2_code":"1864975.0",
    "gn:admin3_code":"43424.0",
    "gn:asciiname":"Takenoyu",
    "gn:country_code":"JP",
    "gn:dem":693,
    "gn:feature_class":"P",
    "gn:feature_code":"PPLL",
    "gn:name":"Takenoyu",
    "gn:population":0,
    "gn:timezone":"Asia/Tokyo",
    "iso:country":"JP",
    "name:jpn_x_preferred":[
        "\u5cb3\u6e6f"
    ],
    "name:jpn_x_variant":[
        "\u305f\u3051\u306e\u3086",
        "\u30bf\u30b1\u30ce\u30e6"
    ],
    "wof:name":"Takenoyu",
    "wof:placetype":"locality"
},
  "geometry": {"coordinates":[131.13622000000001,33.15581],"type":"Point"}
}