{
  "type": "Feature",
  "properties": {
    "gn:admin1_code":"7.0",
    "gn:admin2_code":"1858305.0",
    "gn:admin3_code":"40402.0",
    "gn:asciiname":"Minamiku",
    "gn:country_code":"JP",
    "gn:dem":4,
    "gn:feature_class":"P",
    "gn:feature_code":"PPLL",
    "gn:name":"Minamiku",
    "gn:population":0,
    "gn:timezone":"Asia/Tokyo",
    "iso:country":"JP",
    "name:jpn_x_preferred":[
        "\u5357\u533a"
    ],
    "wof:name":"Minamiku",
    "wof:placetype":"locality"
},
  "geometry": {"coordinates":[130.68516,33.79028],"type":"Point"}
}