{
  "type": "Feature",
  "properties": {
    "gn:admin1_code":"4.0",
    "gn:admin2_code":"2112557.0",
    "gn:admin3_code":"12441.0",
    "gn:asciiname":"Yumigi",
    "gn:country_code":"JP",
    "gn:dem":145,
    "gn:feature_class":"P",
    "gn:feature_code":"PPL",
    "gn:name":"Yumigi",
    "gn:population":0,
    "gn:timezone":"Asia/Tokyo",
    "iso:country":"JP",
    "name:jpn_x_preferred":[
        "\u5f13\u6728"
    ],
    "name:jpn_x_variant":[
        "\u3086\u307f\u304e",
        "\u30e6\u30df\u30ae"
    ],
    "wof:name":"Yumigi",
    "wof:placetype":"locality"
},
  "geometry": {"coordinates":[140.21288000000001,35.21472],"type":"Point"}
}