{
  "type": "Feature",
  "properties": {
    "gn:admin1_code":"32.0",
    "gn:admin2_code":"1862538.0",
    "gn:asciiname":"Yamanoue",
    "gn:country_code":"JP",
    "gn:dem":19,
    "gn:feature_class":"P",
    "gn:feature_code":"PPL",
    "gn:name":"Yamanoue",
    "gn:population":0,
    "gn:timezone":"Asia/Tokyo",
    "iso:country":"JP",
    "name:deu_x_preferred":[
        "Yamanoue"
    ],
    "name:jpn_x_preferred":[
        "\u5c71\u4e4b\u4e0a"
    ],
    "wof:name":"Yamanoue",
    "wof:placetype":"locality"
},
  "geometry": {"coordinates":[135.65588,34.79955],"type":"Point"}
}