{
  "type": "Feature",
  "properties": {
    "gn:admin1_code":"24.0",
    "gn:admin2_code":"2112574.0",
    "gn:asciiname":"Nagaru",
    "gn:country_code":"JP",
    "gn:dem":14,
    "gn:feature_class":"P",
    "gn:feature_code":"PPL",
    "gn:name":"Nagaru",
    "gn:population":0,
    "gn:timezone":"Asia/Tokyo",
    "iso:country":"JP",
    "name:jpn_x_preferred":[
        "\u6d41\u7559"
    ],
    "name:jpn_x_variant":[
        "\u306a\u304c\u308b",
        "\u30ca\u30ac\u30eb"
    ],
    "wof:name":"Nagaru",
    "wof:placetype":"locality"
},
  "geometry": {"coordinates":[141.37419,38.43087],"type":"Point"}
}