{
  "type": "Feature",
  "properties": {
    "iso:country":"JP",
    "name:eng_x_preferred":[
        "Fujigaoka 1 Chome"
    ],
    "name:eng_x_variant":[
        "Fujigaoka 1 Choume",
        "Fujigaoka 1 Chome"
    ],
    "name:jpn_x_preferred":[
        "\uff11\u4e01\u76ee"
    ],
    "name:jpn_x_variant":[
        "\u3075\u3058\u304c\u304a\u304b \uff11\u3061\u3087\u3046\u3081",
        "\u85e4\u30b1\u4e18 \uff11\u4e01\u76ee",
        "\uff11\u3061\u3087\u3046\u3081"
    ],
    "name:unk_x_variant":[
        "\uff11\u4e01\u76ee"
    ],
    "qs:gn_local":0,
    "qs:local_max":95,
    "qs:local_sum":98,
    "qs:localhoods":2,
    "qs:name":"\uff11\u4e01\u76ee",
    "qs:name_adm0":"\u65e5\u672c",
    "qs:name_adm1":"\u611b\u77e5\u770c",
    "qs:name_en":"Fujigaoka 1 Chome",
    "qs:name_lau":"\u85e4\u30b1\u4e18",
    "qs:name_local":"\u6c5f\u5357\u5e02",
    "qs:photo_max":26,
    "qs:photo_sum":95,
    "qs:placetype":"Suburb",
    "qs:quad_count":9,
    "qs:woe_adm0":23424856,
    "qs:woe_adm1":2345851,
    "qs:woe_adm2":0,
    "qs:woe_lau":28443482,
    "qs:woe_local":1111070,
    "qs:woe_ver":"7.10.0",
    "wof:lang":[
        "jpn"
    ],
    "wof:name":"\uff11\u4e01\u76ee",
    "wof:placetype":"neighbourhood"
},
  "geometry": {"coordinates":[136.856458,35.349302],"type":"Point"}
}