{
  "type": "Feature",
  "properties": {
    "gn:admin1_code":"36",
    "gn:admin2_code":"1863308.0",
    "gn:asciiname":"Kurokawa",
    "gn:country_code":"JP",
    "gn:dem":17,
    "gn:feature_class":"P",
    "gn:feature_code":"PPL",
    "gn:name":"Kurokawa",
    "gn:population":0,
    "gn:timezone":"Asia/Tokyo",
    "iso:country":"JP",
    "name:deu_x_preferred":[
        "Kurokawa"
    ],
    "name:und_x_variant":[
        "Kurokawa-machi"
    ],
    "wof:name":"Kurokawa",
    "wof:placetype":"locality"
},
  "geometry": {"coordinates":[132.09153999999998,34.90114000000001],"type":"Point"}
}