{
  "type": "Feature",
  "properties": {
    "gn:admin1_code":"16.0",
    "gn:admin2_code":"2128940.0",
    "gn:asciiname":"Kawara",
    "gn:country_code":"JP",
    "gn:dem":240,
    "gn:feature_class":"P",
    "gn:feature_code":"PPL",
    "gn:name":"Kawara",
    "gn:population":0,
    "gn:timezone":"Asia/Tokyo",
    "iso:country":"JP",
    "name:jpn_x_preferred":[
        "\u5ddd\u539f"
    ],
    "name:jpn_x_variant":[
        "\u304b\u308f\u3089",
        "\u30ab\u30ef\u30e9"
    ],
    "wof:name":"Kawara",
    "wof:placetype":"locality"
},
  "geometry": {"coordinates":[141.15674000000001,40.17984000000001],"type":"Point"}
}