{
  "type": "Feature",
  "properties": {
    "gn:admin1_code":"4.0",
    "gn:admin2_code":"2112997.0",
    "gn:admin3_code":"12423.0",
    "gn:asciiname":"Kanimichi",
    "gn:country_code":"JP",
    "gn:dem":4,
    "gn:feature_class":"P",
    "gn:feature_code":"PPLL",
    "gn:name":"Kanimichi",
    "gn:population":0,
    "gn:timezone":"Asia/Tokyo",
    "iso:country":"JP",
    "name:jpn_x_preferred":[
        "\u87f9\u9053"
    ],
    "name:jpn_x_variant":[
        "\u304b\u306b\u307f\u3061",
        "\u30ab\u30cb\u30df\u30c1"
    ],
    "wof:name":"Kanimichi",
    "wof:placetype":"locality"
},
  "geometry": {"coordinates":[140.38583,35.41200999999999],"type":"Point"}
}