{
  "type": "Feature",
  "properties": {
    "gn:admin1_code":"14.0",
    "gn:admin2_code":"7452808.0",
    "gn:asciiname":"Hiranuma",
    "gn:country_code":"JP",
    "gn:dem":11,
    "gn:feature_class":"P",
    "gn:feature_code":"PPL",
    "gn:name":"Hiranuma",
    "gn:population":0,
    "gn:timezone":"Asia/Tokyo",
    "iso:country":"JP",
    "name:jpn_x_preferred":[
        "\u5e73\u6cbc"
    ],
    "wof:name":"Hiranuma",
    "wof:placetype":"locality"
},
  "geometry": {"coordinates":[139.99791999999999,35.97127000000001],"type":"Point"}
}