{
  "type": "Feature",
  "properties": {
    "gn:admin1_code":"16.0",
    "gn:admin2_code":"7441805.0",
    "gn:admin3_code":"3402.0",
    "gn:asciiname":"ping quan",
    "gn:country_code":"JP",
    "gn:dem":22,
    "gn:feature_class":"P",
    "gn:feature_code":"PPL",
    "gn:name":"\u5e73\u6cc9",
    "gn:population":0,
    "gn:timezone":"Asia/Tokyo",
    "iso:country":"JP",
    "name:jpn_x_preferred":[
        "\u5e73\u6cc9"
    ],
    "wof:name":"ping quan",
    "wof:placetype":"locality"
},
  "geometry": {"coordinates":[141.11667,38.98333],"type":"Point"}
}