{
  "type": "Feature",
  "properties": {
    "gn:admin1_code":"7.0",
    "gn:admin2_code":"1859874.0",
    "gn:admin3_code":"40349.0",
    "gn:asciiname":"Harumachi",
    "gn:country_code":"JP",
    "gn:dem":16,
    "gn:feature_class":"P",
    "gn:feature_code":"PPL",
    "gn:name":"Harumachi",
    "gn:population":0,
    "gn:timezone":"Asia/Tokyo",
    "iso:country":"JP",
    "name:jpn_x_preferred":[
        "\u539f\u753a"
    ],
    "wof:name":"Harumachi",
    "wof:placetype":"locality"
},
  "geometry": {"coordinates":[130.46833000000001,33.61183],"type":"Point"}
}