{
  "type": "Feature",
  "properties": {
    "gn:admin1_code":"40.0",
    "gn:admin2_code":"1859779.0",
    "gn:asciiname":"Ohanajaya",
    "gn:country_code":"JP",
    "gn:dem":1,
    "gn:feature_class":"P",
    "gn:feature_code":"PPL",
    "gn:name":"Ohanajaya",
    "gn:population":0,
    "gn:timezone":"Asia/Tokyo",
    "iso:country":"JP",
    "name:jpn_x_preferred":[
        "\u304a\u82b1\u8336\u5c4b"
    ],
    "wof:name":"Ohanajaya",
    "wof:placetype":"locality"
},
  "geometry": {"coordinates":[139.84034,35.75362],"type":"Point"}
}