{
  "type": "Feature",
  "properties": {
    "gn:admin1_code":"18.0",
    "gn:admin2_code":"1862007.0",
    "gn:asciiname":"Toriyama",
    "gn:country_code":"JP",
    "gn:dem":45,
    "gn:feature_class":"P",
    "gn:feature_code":"PPLL",
    "gn:name":"Toriyama",
    "gn:population":0,
    "gn:timezone":"Asia/Tokyo",
    "iso:country":"JP",
    "name:jpn_x_preferred":[
        "\u9ce5\u5c71"
    ],
    "name:ukr_x_preferred":[
        "\u0422\u043e\u0440\u0456\u044f\u043c\u0430"
    ],
    "wof:name":"Toriyama",
    "wof:placetype":"locality"
},
  "geometry": {"coordinates":[130.59788999999998,31.28209],"type":"Point"}
}