{
  "type": "Feature",
  "properties": {
    "gn:admin1_code":"27.0",
    "gn:admin2_code":"1852895.0",
    "gn:asciiname":"Jomacho",
    "gn:country_code":"JP",
    "gn:dem":58,
    "gn:feature_class":"P",
    "gn:feature_code":"PPL",
    "gn:name":"J\u014dmach\u014d",
    "gn:population":0,
    "gn:timezone":"Asia/Tokyo",
    "iso:country":"JP",
    "name:jpn_x_preferred":[
        "\u57ce\u9593\u753a"
    ],
    "name:und_x_variant":[
        "J\u014dmach\u014d"
    ],
    "wof:name":"Jomacho",
    "wof:placetype":"locality"
},
  "geometry": {"coordinates":[129.81511,33.09717],"type":"Point"}
}