{
  "type": "Feature",
  "properties": {
    "gn:admin1_code":"15",
    "gn:admin2_code":"7467838.0",
    "gn:admin3_code":"17384.0",
    "gn:asciiname":"Konmachi",
    "gn:country_code":"JP",
    "gn:dem":29,
    "gn:feature_class":"P",
    "gn:feature_code":"PPL",
    "gn:name":"Konmachi",
    "gn:population":0,
    "gn:timezone":"Asia/Tokyo",
    "iso:country":"JP",
    "name:jpn_x_preferred":[
        "\u7c73\u753a"
    ],
    "name:und_x_variant":[
        "Kommachi"
    ],
    "wof:name":"Konmachi",
    "wof:placetype":"locality"
},
  "geometry": {"coordinates":[136.78083999999998,37.05844],"type":"Point"}
}