{
  "type": "Feature",
  "properties": {
    "gn:admin1_code":"47",
    "gn:admin2_code":"7415820.0",
    "gn:asciiname":"Kudaka",
    "gn:country_code":"JP",
    "gn:dem":14,
    "gn:feature_class":"P",
    "gn:feature_code":"PPLL",
    "gn:name":"Kudaka",
    "gn:population":0,
    "gn:timezone":"Asia/Tokyo",
    "iso:country":"JP",
    "name:jpn_x_preferred":[
        "\u4e45\u9ad8"
    ],
    "name:und_x_variant":[
        "Gaima",
        "Kutaka",
        "Kudaka"
    ],
    "wof:name":"Kudaka",
    "wof:placetype":"locality"
},
  "geometry": {"coordinates":[127.88703999999998,26.15911],"type":"Point"}
}