{
  "type": "Feature",
  "properties": {
    "gn:admin1_code":"15.0",
    "gn:admin2_code":"1858904.0",
    "gn:asciiname":"Kusanomachi",
    "gn:country_code":"JP",
    "gn:dem":6,
    "gn:feature_class":"P",
    "gn:feature_code":"PPL",
    "gn:name":"Kusanomachi",
    "gn:population":0,
    "gn:timezone":"Asia/Tokyo",
    "iso:country":"JP",
    "name:jpn_x_preferred":[
        "\u8349\u91ce\u753a"
    ],
    "wof:name":"Kusanomachi",
    "wof:placetype":"locality"
},
  "geometry": {"coordinates":[136.41161,36.4109],"type":"Point"}
}