{
  "type": "Feature",
  "properties": {
    "gn:admin1_code":"23.0",
    "gn:admin2_code":"1856290.0",
    "gn:asciiname":"Todo",
    "gn:country_code":"JP",
    "gn:dem":330,
    "gn:feature_class":"P",
    "gn:feature_code":"PPLL",
    "gn:name":"Todo",
    "gn:population":0,
    "gn:timezone":"Asia/Tokyo",
    "iso:country":"JP",
    "name:ceb_x_preferred":[
        "Todo"
    ],
    "name:deu_x_preferred":[
        "Todo"
    ],
    "name:fra_x_preferred":[
        "Todo"
    ],
    "name:jpn_x_preferred":[
        "\u767e\u3005"
    ],
    "name:spa_x_preferred":[
        "Todo"
    ],
    "name:swe_x_preferred":[
        "Todo"
    ],
    "name:zho_x_preferred":[
        "Todo"
    ],
    "wof:name":"Todo",
    "wof:placetype":"locality"
},
  "geometry": {"coordinates":[136.13191,34.5876],"type":"Point"}
}