{
  "type": "Feature",
  "properties": {
    "gn:admin1_code":"15.0",
    "gn:admin2_code":"7467879.0",
    "gn:asciiname":"Nakajimamachi-tagishi",
    "gn:country_code":"JP",
    "gn:dem":10,
    "gn:feature_class":"P",
    "gn:feature_code":"PPL",
    "gn:name":"Nakajimamachi-tagishi",
    "gn:population":0,
    "gn:timezone":"Asia/Tokyo",
    "iso:country":"JP",
    "name:jpn_x_preferred":[
        "\u4e2d\u5cf6\u753a\u7530\u5cb8"
    ],
    "wof:name":"Nakajimamachi-tagishi",
    "wof:placetype":"locality"
},
  "geometry": {"coordinates":[136.88241000000002,37.15872],"type":"Point"}
}