{
  "type": "Feature",
  "properties": {
    "gn:admin1_code":"4.0",
    "gn:admin2_code":"1863711.0",
    "gn:asciiname":"Kazuma",
    "gn:country_code":"JP",
    "gn:dem":11,
    "gn:feature_class":"P",
    "gn:feature_code":"PPL",
    "gn:name":"Kazuma",
    "gn:population":0,
    "gn:timezone":"Asia/Tokyo",
    "iso:country":"JP",
    "name:jpn_x_preferred":[
        "\u6570\u99ac"
    ],
    "name:jpn_x_variant":[
        "\u304b\u305a\u307e",
        "\u30ab\u30ba\u30de"
    ],
    "name:pol_x_preferred":[
        "Kazuma"
    ],
    "wof:name":"Kazuma",
    "wof:placetype":"locality"
},
  "geometry": {"coordinates":[139.88121000000001,35.21626],"type":"Point"}
}