{
  "type": "Feature",
  "properties": {
    "gn:admin1_code":"12.0",
    "gn:admin2_code":"7428077.0",
    "gn:admin3_code":"1667.0",
    "gn:asciiname":"Tsuruikita",
    "gn:country_code":"JP",
    "gn:dem":39,
    "gn:feature_class":"P",
    "gn:feature_code":"PPL",
    "gn:name":"Tsuruikita",
    "gn:population":0,
    "gn:timezone":"Asia/Tokyo",
    "iso:country":"JP",
    "name:jpn_x_preferred":[
        "\u9db4\u5c45\u5317"
    ],
    "name:jpn_x_variant":[
        "\u3064\u308b\u3044\u304d\u305f",
        "\u30c4\u30eb\u30a4\u30ad\u30bf"
    ],
    "wof:name":"Tsuruikita",
    "wof:placetype":"locality"
},
  "geometry": {"coordinates":[144.32211000000001,43.24123],"type":"Point"}
}