{
  "type": "Feature",
  "properties": {
    "gn:admin1_code":"12.0",
    "gn:admin2_code":"2128570.0",
    "gn:asciiname":"Otanegawa",
    "gn:cc2":"JP",
    "gn:country_code":"JP",
    "gn:dem":5,
    "gn:feature_class":"P",
    "gn:feature_code":"PPL",
    "gn:name":"Otanegawa",
    "gn:population":0,
    "gn:timezone":"Asia/Tokyo",
    "iso:country":"JP",
    "name:und_x_variant":[
        "Otarunaigawa",
        "Otanegawa"
    ],
    "wof:name":"Otanegawa",
    "wof:placetype":"locality"
},
  "geometry": {"coordinates":[141.23333,43.16667],"type":"Point"}
}