{
  "type": "Feature",
  "properties": {
    "gn:admin1_code":"25.0",
    "gn:admin2_code":"7413970.0",
    "gn:asciiname":"Hoyojibaru",
    "gn:country_code":"JP",
    "gn:dem":248,
    "gn:feature_class":"P",
    "gn:feature_code":"PPLL",
    "gn:name":"Hoy\u014djibaru",
    "gn:population":0,
    "gn:timezone":"Asia/Tokyo",
    "iso:country":"JP",
    "name:jpn_x_preferred":[
        "\u4fdd\u63da\u679d\u539f"
    ],
    "name:jpn_x_variant":[
        "\u307b\u3088\u3046\u3058\u3070\u308b",
        "\u30db\u30e8\u30a6\u30b8\u30d0\u30eb"
    ],
    "name:und_x_variant":[
        "Hoy\u014djibaru"
    ],
    "wof:name":"Hoyojibaru",
    "wof:placetype":"locality"
},
  "geometry": {"coordinates":[130.98131999999998,32.03058],"type":"Point"}
}