{
  "type": "Feature",
  "properties": {
    "gn:admin1_code":"18.0",
    "gn:admin2_code":"7383991.0",
    "gn:asciiname":"Hagitani",
    "gn:country_code":"JP",
    "gn:dem":209,
    "gn:feature_class":"P",
    "gn:feature_code":"PPLL",
    "gn:name":"Hagitani",
    "gn:population":0,
    "gn:timezone":"Asia/Tokyo",
    "iso:country":"JP",
    "name:jpn_x_preferred":[
        "\u8429\u8c37"
    ],
    "name:jpn_x_variant":[
        "\u306f\u304e\u305f\u306b",
        "\u30cf\u30ae\u30bf\u30cb"
    ],
    "wof:name":"Hagitani",
    "wof:placetype":"locality"
},
  "geometry": {"coordinates":[130.58257,32.04393],"type":"Point"}
}