{
  "type": "Feature",
  "properties": {
    "gn:admin1_code":"47",
    "gn:admin2_code":"7415821.0",
    "gn:asciiname":"Yonashiro-ikei",
    "gn:country_code":"JP",
    "gn:dem":12,
    "gn:feature_class":"P",
    "gn:feature_code":"PPL",
    "gn:name":"Yonashiro-ikei",
    "gn:population":0,
    "gn:timezone":"Asia/Tokyo",
    "iso:country":"JP",
    "name:jpn_x_preferred":[
        "\u4e0e\u90a3\u57ce\u4f0a\u8a08"
    ],
    "name:und_x_variant":[
        "Ike",
        "Ikeshima",
        "Ichi",
        "Ikei",
        "Yonashiro-ikei"
    ],
    "wof:name":"Yonashiro-ikei",
    "wof:placetype":"locality"
},
  "geometry": {"coordinates":[127.99418,26.38493],"type":"Point"}
}