{
  "type": "Feature",
  "properties": {
    "gn:admin1_code":"19.0",
    "gn:admin2_code":"1864091.0",
    "gn:asciiname":"Shin'yashiki",
    "gn:country_code":"JP",
    "gn:dem":38,
    "gn:feature_class":"P",
    "gn:feature_code":"PPLL",
    "gn:name":"Shin\u2019yashiki",
    "gn:population":0,
    "gn:timezone":"Asia/Tokyo",
    "iso:country":"JP",
    "name:jpn_x_preferred":[
        "\u65b0\u5c4b\u6577"
    ],
    "name:und_x_variant":[
        "Shin\u2019yashiki"
    ],
    "wof:name":"Shin'yashiki",
    "wof:placetype":"locality"
},
  "geometry": {"coordinates":[139.46194,35.40841],"type":"Point"}
}