{
  "type": "Feature",
  "properties": {
    "gn:admin1_code":"33.0",
    "gn:admin2_code":"1850832.0",
    "gn:asciiname":"Motai",
    "gn:country_code":"JP",
    "gn:dem":54,
    "gn:feature_class":"P",
    "gn:feature_code":"PPLL",
    "gn:name":"M\u014dtai",
    "gn:population":0,
    "gn:timezone":"Asia/Tokyo",
    "iso:country":"JP",
    "name:jpn_x_preferred":[
        "\u99ac\u6e21\u3000"
    ],
    "name:und_x_variant":[
        "M\u014dtai"
    ],
    "wof:name":"Motai",
    "wof:placetype":"locality"
},
  "geometry": {"coordinates":[129.97346000000002,33.24193],"type":"Point"}
}