{
  "type": "Feature",
  "properties": {
    "gn:admin1_code":"7.0",
    "gn:admin2_code":"7407413.0",
    "gn:asciiname":"Kamiokuma",
    "gn:country_code":"JP",
    "gn:dem":78,
    "gn:feature_class":"P",
    "gn:feature_code":"PPLL",
    "gn:name":"Kami\u014dkuma",
    "gn:population":0,
    "gn:timezone":"Asia/Tokyo",
    "iso:country":"JP",
    "name:jpn_x_preferred":[
        "\u4e0a\u5927\u9688"
    ],
    "name:und_x_variant":[
        "Kami\u014dkuma"
    ],
    "wof:name":"Kamiokuma",
    "wof:placetype":"locality"
},
  "geometry": {"coordinates":[130.75819999999999,33.53703],"type":"Point"}
}