{
  "type": "Feature",
  "properties": {
    "gn:admin1_code":"31",
    "gn:admin2_code":"1854380.0",
    "gn:admin3_code":"33104.0",
    "gn:asciiname":"Seno'o",
    "gn:country_code":"JP",
    "gn:dem":4,
    "gn:feature_class":"P",
    "gn:feature_code":"PPL",
    "gn:name":"Seno\u2019o",
    "gn:population":0,
    "gn:timezone":"Asia/Tokyo",
    "iso:country":"JP",
    "name:jpn_x_preferred":[
        "\u59b9\u5c3e"
    ],
    "name:und_x_variant":[
        "Sen\u014d",
        "Senoo",
        "Seno\u2019o",
        "Seno"
    ],
    "wof:name":"Seno'o",
    "wof:placetype":"locality"
},
  "geometry": {"coordinates":[133.86467999999999,34.61234],"type":"Point"}
}