{
  "type": "Feature",
  "properties": {
    "gn:admin1_code":"21.0",
    "gn:admin2_code":"7412705.0",
    "gn:admin3_code":"43482.0",
    "gn:asciiname":"Shiohitashi",
    "gn:country_code":"JP",
    "gn:dem":76,
    "gn:feature_class":"P",
    "gn:feature_code":"PPL",
    "gn:name":"Shiohitashi",
    "gn:population":0,
    "gn:timezone":"Asia/Tokyo",
    "iso:country":"JP",
    "name:jpn_x_preferred":[
        "\u5869\u6d78"
    ],
    "name:jpn_x_variant":[
        "\u3057\u304a\u3072\u305f\u3057",
        "\u30b7\u30aa\u30d2\u30bf\u30b7"
    ],
    "wof:name":"Shiohitashi",
    "wof:placetype":"locality"
},
  "geometry": {"coordinates":[130.55517,32.28447],"type":"Point"}
}