{
  "type": "Feature",
  "properties": {
    "gn:admin1_code":"4.0",
    "gn:admin2_code":"1863711.0",
    "gn:asciiname":"Yokomine",
    "gn:country_code":"JP",
    "gn:dem":26,
    "gn:feature_class":"P",
    "gn:feature_code":"PPLL",
    "gn:name":"Yokomine",
    "gn:population":0,
    "gn:timezone":"Asia/Tokyo",
    "iso:country":"JP",
    "name:jpn_x_preferred":[
        "\u6a2a\u5cf0"
    ],
    "name:jpn_x_variant":[
        "\u3088\u3053\u307f\u306d",
        "\u30e8\u30b3\u30df\u30cd"
    ],
    "wof:name":"Yokomine",
    "wof:placetype":"locality"
},
  "geometry": {"coordinates":[139.89571999999998,35.22566],"type":"Point"}
}