{
  "type": "Feature",
  "properties": {
    "gn:admin1_code":"32",
    "gn:admin2_code":"1853897.0",
    "gn:admin3_code":"27104.0",
    "gn:asciiname":"Shikanjima",
    "gn:country_code":"JP",
    "gn:dem":2,
    "gn:feature_class":"P",
    "gn:feature_code":"PPL",
    "gn:name":"Shikanjima",
    "gn:population":0,
    "gn:timezone":"Asia/Tokyo",
    "iso:country":"JP",
    "name:jpn_x_preferred":[
        "\u56db\u8cab\u5cf6"
    ],
    "wof:name":"Shikanjima",
    "wof:placetype":"locality"
},
  "geometry": {"coordinates":[135.45417,34.68465],"type":"Point"}
}