{
  "type": "Feature",
  "properties": {
    "iso:country":"JP",
    "name:eng_x_preferred":[
        "Mikurajima"
    ],
    "name:eng_x_variant":[
        "Mikurajima Village"
    ],
    "name:jpn_x_preferred":[
        "\u5fa1\u8535\u5cf6\u6751"
    ],
    "qs:name":"\u5fa1\u8535\u5cf6\u6751",
    "qs:name_adm0":"\u65e5\u672c",
    "qs:name_adm1":"\u6771\u4eac\u90fd",
    "qs:photos":505,
    "qs:photos_1k":102,
    "qs:photos_9k":2,
    "qs:photos_9r":5,
    "qs:photos_all":505,
    "qs:photos_sr":7,
    "qs:placetype":"Town",
    "qs:pop_sr":"0",
    "wof:name":"Mikurajima",
    "wof:placetype":"locality"
},
  "geometry": {"coordinates":[139.60464400000001,33.878278],"type":"Point"}
}