{
  "type": "Feature",
  "properties": {
    "gn:admin1_code":"21.0",
    "gn:admin2_code":"1862350.0",
    "gn:asciiname":"Kamitashiromachi",
    "gn:country_code":"JP",
    "gn:dem":197,
    "gn:feature_class":"P",
    "gn:feature_code":"PPL",
    "gn:name":"Kamitashiromachi",
    "gn:population":0,
    "gn:timezone":"Asia/Tokyo",
    "iso:country":"JP",
    "name:jpn_x_preferred":[
        "\u4e0a\u7530\u4ee3\u753a"
    ],
    "name:jpn_x_variant":[
        "\u304b\u307f\u305f\u3057\u308d\u307e\u3061",
        "\u30ab\u30df\u30bf\u30b7\u30ed\u30de\u30c1"
    ],
    "wof:name":"Kamitashiromachi",
    "wof:placetype":"locality"
},
  "geometry": {"coordinates":[130.80895000000001,32.1684],"type":"Point"}
}