{
  "type": "Feature",
  "properties": {
    "iso:country":"JP",
    "name:eng_x_preferred":[
        "Yotsuya 1 Chome"
    ],
    "name:eng_x_variant":[
        "Yotsuya 1 Choume",
        "Yotsuya 1 Chome"
    ],
    "name:jpn_x_preferred":[
        "\uff11\u4e01\u76ee"
    ],
    "name:jpn_x_variant":[
        "\u3088\u3064\u3084 \uff11\u3061\u3087\u3046\u3081",
        "\u56db\u8c37 \uff11\u4e01\u76ee",
        "\uff11\u3061\u3087\u3046\u3081"
    ],
    "qs:gn_adm0_cc":"JP",
    "qs:gn_local":1850147,
    "qs:local_max":18112,
    "qs:local_sum":895907,
    "qs:localhoods":857,
    "qs:name":"\uff11\u4e01\u76ee",
    "qs:name_adm0":"\u65e5\u672c",
    "qs:name_adm1":"\u6771\u4eac\u90fd",
    "qs:name_adm2":"\u65b0\u5bbf\u533a",
    "qs:name_en":"Yotsuya 1 Chome",
    "qs:name_lau":"\u56db\u8c37",
    "qs:name_local":"\u6771\u4eac",
    "qs:photo_max":21,
    "qs:photo_sum":21,
    "qs:placetype":"Suburb",
    "qs:quad_count":1,
    "qs:woe_adm0":23424856,
    "qs:woe_adm1":2345889,
    "qs:woe_adm2":15015378,
    "qs:woe_lau":28414098,
    "qs:woe_local":1118370,
    "qs:woe_ver":"7.10.0",
    "wof:lang":[
        "jpn"
    ],
    "wof:name":"\uff11\u4e01\u76ee",
    "wof:placetype":"neighbourhood"
},
  "geometry": {"coordinates":[139.725494,35.685188],"type":"Point"}
}