{
  "type": "Feature",
  "properties": {
    "gn:admin1_code":"21.0",
    "gn:admin2_code":"1862350.0",
    "gn:asciiname":"Hizoe",
    "gn:country_code":"JP",
    "gn:dem":533,
    "gn:feature_class":"P",
    "gn:feature_code":"PPLL",
    "gn:name":"Hizoe",
    "gn:population":0,
    "gn:timezone":"Asia/Tokyo",
    "iso:country":"JP",
    "name:jpn_x_preferred":[
        "\u65e5\u6dfb"
    ],
    "name:jpn_x_variant":[
        "\u3072\u305e\u3048",
        "\u30d2\u30be\u30a8"
    ],
    "wof:name":"Hizoe",
    "wof:placetype":"locality"
},
  "geometry": {"coordinates":[130.69699,32.13699],"type":"Point"}
}