{
  "type": "Feature",
  "properties": {
    "gn:admin1_code":"34.0",
    "gn:admin2_code":"1850180.0",
    "gn:asciiname":"Sakanoshita",
    "gn:country_code":"JP",
    "gn:dem":41,
    "gn:feature_class":"P",
    "gn:feature_code":"PPL",
    "gn:name":"Sakanoshita",
    "gn:population":0,
    "gn:timezone":"Asia/Tokyo",
    "iso:country":"JP",
    "name:jpn_x_preferred":[
        "\u5742\u30ce\u4e0b"
    ],
    "name:jpn_x_variant":[
        "\u3055\u304b\u306e\u3057\u305f",
        "\u30b5\u30ab\u30ce\u30b7\u30bf"
    ],
    "wof:name":"Sakanoshita",
    "wof:placetype":"locality"
},
  "geometry": {"coordinates":[139.53569999999999,35.80889000000001],"type":"Point"}
}