{
  "type": "Feature",
  "properties": {
    "gn:admin1_code":"3.0",
    "gn:admin2_code":"2130654.0",
    "gn:asciiname":"Asuka",
    "gn:country_code":"JP",
    "gn:dem":3,
    "gn:feature_class":"P",
    "gn:feature_code":"PPL",
    "gn:name":"Asuka",
    "gn:population":0,
    "gn:timezone":"Asia/Tokyo",
    "iso:country":"JP",
    "name:deu_x_preferred":[
        "Asuka"
    ],
    "name:fra_x_preferred":[
        "Asuka"
    ],
    "name:hrv_x_preferred":[
        "Asuka"
    ],
    "name:ita_x_preferred":[
        "Asuka"
    ],
    "name:jpn_x_preferred":[
        "\u98db\u9ce5"
    ],
    "name:jpn_x_variant":[
        "\u3042\u3059\u304b",
        "\u30a2\u30b9\u30ab"
    ],
    "name:kor_x_preferred":[
        "\uc544\uc2a4\uce74"
    ],
    "name:nld_x_preferred":[
        "Asuka"
    ],
    "name:pol_x_preferred":[
        "Asuka"
    ],
    "name:ron_x_preferred":[
        "Asuka"
    ],
    "name:rus_x_preferred":[
        "\u0410\u0441\u0443\u043a\u0430"
    ],
    "name:spa_x_preferred":[
        "Asuka"
    ],
    "name:zho_x_preferred":[
        "Asuka"
    ],
    "wof:name":"Asuka",
    "wof:placetype":"locality"
},
  "geometry": {"coordinates":[140.67487,40.87617],"type":"Point"}
}