{
  "type": "Feature",
  "properties": {
    "gn:admin1_code":"3.0",
    "gn:admin2_code":"2130654.0",
    "gn:asciiname":"Asuka",
    "gn:country_code":"JP",
    "gn:dem":3,
    "gn:feature_class":"P",
    "gn:feature_code":"PPL",
    "gn:name":"Asuka",
    "gn:population":0,
    "gn:timezone":"Asia/Tokyo",
    "iso:country":"JP",
    "name:jpn_x_preferred":[
        "\u98db\u9ce5"
    ],
    "name:jpn_x_variant":[
        "\u3042\u3059\u304b",
        "\u30a2\u30b9\u30ab"
    ],
    "wof:name":"Asuka",
    "wof:placetype":"locality"
},
  "geometry": {"coordinates":[140.67487,40.87617],"type":"Point"}
}