{
  "type": "Feature",
  "properties": {
    "iso:country":"JP",
    "qs:name":"\u6e0b\u5ddd\u5e02",
    "qs:name_adm0":"\u65e5\u672c",
    "qs:name_adm1":"\u7fa4\u99ac\u770c",
    "qs:photos":914,
    "qs:photos_1k":185,
    "qs:photos_9k":4,
    "qs:photos_9r":6,
    "qs:photos_all":914,
    "qs:photos_sr":10,
    "qs:placetype":"Town",
    "qs:pop_sr":"0",
    "wof:name":"\u6e0b\u5ddd\u5e02",
    "wof:placetype":"locality"
},
  "geometry": {"coordinates":[138.94666599999999,36.498597],"type":"Point"}
}