{
  "type": "Feature",
  "properties": {
    "gn:admin1_code":"4.0",
    "gn:admin2_code":"1863711.0",
    "gn:asciiname":"Shippara",
    "gn:country_code":"JP",
    "gn:dem":157,
    "gn:feature_class":"P",
    "gn:feature_code":"PPLL",
    "gn:name":"Shippara",
    "gn:population":0,
    "gn:timezone":"Asia/Tokyo",
    "iso:country":"JP",
    "name:jpn_x_preferred":[
        "\u9e7f\u539f"
    ],
    "name:jpn_x_variant":[
        "\u3057\u3063\u3071\u3089",
        "\u30b7\u30c3\u30d1\u30e9"
    ],
    "wof:name":"Shippara",
    "wof:placetype":"locality"
},
  "geometry": {"coordinates":[139.90916999999999,35.18256],"type":"Point"}
}