{
  "type": "Feature",
  "properties": {
    "gn:admin1_code":"32.0",
    "gn:admin2_code":"1857043.0",
    "gn:asciiname":"Kayano",
    "gn:country_code":"JP",
    "gn:dem":71,
    "gn:feature_class":"P",
    "gn:feature_code":"PPL",
    "gn:name":"Kayano",
    "gn:population":0,
    "gn:timezone":"Asia/Tokyo",
    "iso:country":"JP",
    "name:jpn_x_preferred":[
        "\u8431\u91ce"
    ],
    "wof:name":"Kayano",
    "wof:placetype":"locality"
},
  "geometry": {"coordinates":[135.48341000000002,34.82761],"type":"Point"}
}