{
  "type": "Feature",
  "properties": {
    "gn:admin1_code":"28",
    "gn:admin2_code":"1848164.0",
    "gn:admin3_code":"29449.0",
    "gn:asciiname":"Oritachi",
    "gn:cc2":"JP",
    "gn:country_code":"JP",
    "gn:dem":137,
    "gn:feature_class":"P",
    "gn:feature_code":"PPL",
    "gn:name":"Oritachi",
    "gn:population":0,
    "gn:timezone":"Asia/Tokyo",
    "iso:country":"JP",
    "name:und_x_variant":[
        "Oritate",
        "Oritachi"
    ],
    "wof:name":"Oritachi",
    "wof:placetype":"locality"
},
  "geometry": {"coordinates":[135.80000000000001,33.95],"type":"Point"}
}