{
  "type": "Feature",
  "properties": {
    "gn:admin1_code":"2.0",
    "gn:admin2_code":"2129593.0",
    "gn:asciiname":"Kamishinden",
    "gn:country_code":"JP",
    "gn:dem":234,
    "gn:feature_class":"P",
    "gn:feature_code":"PPL",
    "gn:name":"Kamishinden",
    "gn:population":0,
    "gn:timezone":"Asia/Tokyo",
    "iso:country":"JP",
    "name:jpn_x_preferred":[
        "\u4e0a\u65b0\u7530"
    ],
    "name:jpn_x_variant":[
        "\u304b\u307f\u3057\u3093\u3067\u3093",
        "\u30ab\u30df\u30b7\u30f3\u30c7\u30f3"
    ],
    "wof:name":"Kamishinden",
    "wof:placetype":"locality"
},
  "geometry": {"coordinates":[140.73137,40.17277],"type":"Point"}
}