{
  "type": "Feature",
  "properties": {
    "gn:admin1_code":"24.0",
    "gn:admin2_code":"7447001.0",
    "gn:asciiname":"Kurumayu",
    "gn:country_code":"JP",
    "gn:dem":150,
    "gn:feature_class":"P",
    "gn:feature_code":"PPL",
    "gn:name":"Kurumayu",
    "gn:population":0,
    "gn:timezone":"Asia/Tokyo",
    "iso:country":"JP",
    "name:jpn_x_preferred":[
        "\u8eca\u6e6f"
    ],
    "name:jpn_x_variant":[
        "\u304f\u308b\u307e\u3086",
        "\u30af\u30eb\u30de\u30e6"
    ],
    "wof:name":"Kurumayu",
    "wof:placetype":"locality"
},
  "geometry": {"coordinates":[140.72575000000001,38.7477],"type":"Point"}
}