{
  "type": "Feature",
  "properties": {
    "gn:admin1_code":"12.0",
    "gn:admin2_code":"7428098.0",
    "gn:admin3_code":"1604.0",
    "gn:asciiname":"Okaribe",
    "gn:country_code":"JP",
    "gn:dem":78,
    "gn:feature_class":"P",
    "gn:feature_code":"PPL",
    "gn:name":"\u014ckaribe",
    "gn:population":0,
    "gn:timezone":"Asia/Tokyo",
    "iso:country":"JP",
    "name:jpn_x_preferred":[
        "\u5927\u72e9\u90e8"
    ],
    "name:und_x_variant":[
        "\u014ckaribe"
    ],
    "wof:name":"Okaribe",
    "wof:placetype":"locality"
},
  "geometry": {"coordinates":[142.25393,42.40833],"type":"Point"}
}