{
  "type": "Feature",
  "properties": {
    "gn:admin1_code":"25",
    "gn:admin2_code":"1862717.0",
    "gn:admin3_code":"45431.0",
    "gn:asciiname":"Naka-bae",
    "gn:country_code":"JP",
    "gn:dem":510,
    "gn:feature_class":"P",
    "gn:feature_code":"PPL",
    "gn:name":"Naka-bae",
    "gn:population":0,
    "gn:timezone":"Asia/Tokyo",
    "iso:country":"JP",
    "wof:name":"Naka-bae",
    "wof:placetype":"locality"
},
  "geometry": {"coordinates":[131.34999999999999,32.48333],"type":"Point"}
}