{
  "type": "Feature",
  "properties": {
    "iso:country":"JP",
    "name:eng_x_preferred":[
        "Kamirengeji 4 Chome"
    ],
    "name:eng_x_variant":[
        "Kamirengeji 4 Choume",
        "Kamirengeji 4 Chome"
    ],
    "name:jpn_x_preferred":[
        "\uff14\u4e01\u76ee"
    ],
    "name:jpn_x_variant":[
        "\u304b\u307f\u308c\u3093\u3052\u3058 \uff14\u3061\u3087\u3046\u3081",
        "\u4e0a\u84ee\u82b1\u5bfa \uff14\u4e01\u76ee",
        "\uff14\u3061\u3087\u3046\u3081"
    ],
    "name:unk_x_variant":[
        "\uff14\u4e01\u76ee"
    ],
    "qs:gn_local":0,
    "qs:local_max":63,
    "qs:local_sum":68,
    "qs:localhoods":2,
    "qs:name":"\uff14\u4e01\u76ee",
    "qs:name_adm0":"\u65e5\u672c",
    "qs:name_adm1":"\u798f\u5ca1\u770c",
    "qs:name_en":"Kamirengeji 4 Chome",
    "qs:name_lau":"\u4e0a\u84ee\u82b1\u5bfa",
    "qs:name_local":"\u4e2d\u9593\u5e02",
    "qs:photo_max":4,
    "qs:photo_sum":5,
    "qs:placetype":"Suburb",
    "qs:quad_count":2,
    "qs:woe_adm0":23424856,
    "qs:woe_adm1":58646425,
    "qs:woe_adm2":0,
    "qs:woe_lau":28484248,
    "qs:woe_local":1117830,
    "qs:woe_ver":"7.10.0",
    "wof:lang":[
        "jpn"
    ],
    "wof:name":"\uff14\u4e01\u76ee",
    "wof:placetype":"neighbourhood"
},
  "geometry": {"coordinates":[130.72247300000001,33.822513],"type":"Point"}
}