{
  "type": "Feature",
  "properties": {
    "gn:admin1_code":"14.0",
    "gn:admin2_code":"2112704.0",
    "gn:asciiname":"Ose",
    "gn:country_code":"JP",
    "gn:dem":0,
    "gn:feature_class":"P",
    "gn:feature_code":"PPL",
    "gn:name":"\u014cse",
    "gn:population":0,
    "gn:timezone":"Asia/Tokyo",
    "iso:country":"JP",
    "name:ceb_x_preferred":[
        "Ose"
    ],
    "name:fra_x_preferred":[
        "Ose"
    ],
    "name:swe_x_preferred":[
        "Ose"
    ],
    "name:ukr_x_preferred":[
        "\u041e\u0441\u0435"
    ],
    "name:und_x_variant":[
        "\u014cse"
    ],
    "wof:name":"Ose",
    "wof:placetype":"locality"
},
  "geometry": {"coordinates":[140.65000000000001,36.56667],"type":"Point"}
}