{
  "type": "Feature",
  "properties": {
    "gn:admin1_code":"27",
    "gn:admin2_code":"1852895.0",
    "gn:asciiname":"Ukumachi-odae",
    "gn:country_code":"JP",
    "gn:dem":38,
    "gn:feature_class":"P",
    "gn:feature_code":"PPL",
    "gn:name":"Ukumachi-\u014ddae",
    "gn:population":0,
    "gn:timezone":"Asia/Tokyo",
    "iso:country":"JP",
    "name:jpn_x_preferred":[
        "\u5b87\u4e45\u753a\u592a\u7530\u6c5f"
    ],
    "name:und_x_variant":[
        "Uku",
        "Ukumachi-\u014ddae"
    ],
    "wof:name":"Ukumachi-odae",
    "wof:placetype":"locality"
},
  "geometry": {"coordinates":[129.12298999999999,33.27616],"type":"Point"}
}