{
  "type": "Feature",
  "properties": {
    "gn:admin1_code":"4.0",
    "gn:admin2_code":"2112997.0",
    "gn:admin3_code":"12424.0",
    "gn:asciiname":"Furutokoro-taka",
    "gn:country_code":"JP",
    "gn:dem":0,
    "gn:feature_class":"P",
    "gn:feature_code":"PPLL",
    "gn:name":"Furutokoro-taka",
    "gn:population":0,
    "gn:timezone":"Asia/Tokyo",
    "iso:country":"JP",
    "name:jpn_x_preferred":[
        "\u53e4\u6240\u9ad8"
    ],
    "name:jpn_x_variant":[
        "\u3075\u308b\u3068\u3053\u308d\u305f\u304b",
        "\u30d5\u30eb\u30c8\u30b3\u30ed\u30bf\u30ab"
    ],
    "wof:name":"Furutokoro-taka",
    "wof:placetype":"locality"
},
  "geometry": {"coordinates":[140.38841000000002,35.45224],"type":"Point"}
}