{
  "type": "Feature",
  "properties": {
    "iso:country":"JP",
    "name:eng_x_preferred":[
        "Takayanagi 1 Chome"
    ],
    "name:eng_x_variant":[
        "Takayanagi 1 Choume",
        "Takayanagi 1 Chome"
    ],
    "name:jpn_x_preferred":[
        "\uff11\u4e01\u76ee"
    ],
    "name:jpn_x_variant":[
        "\u305f\u304b\u3084\u306a\u304e \uff11\u3061\u3087\u3046\u3081",
        "\u9ad8\u67f3 \uff11\u4e01\u76ee",
        "\uff11\u3061\u3087\u3046\u3081"
    ],
    "qs:gn_adm0_cc":"JP",
    "qs:gn_local":6697563,
    "qs:gn_nam_loc":"\u5bdd\u5c4b\u5ddd\u5e02, \u5927\u962a\u5e9c, JP",
    "qs:gn_namadm1":"32",
    "qs:local_max":73,
    "qs:local_sum":121,
    "qs:localhoods":4,
    "qs:name":"\uff11\u4e01\u76ee",
    "qs:name_adm0":"\u65e5\u672c",
    "qs:name_adm1":"\u5927\u962a\u5e9c",
    "qs:name_en":"Takayanagi 1 Chome",
    "qs:name_lau":"\u9ad8\u67f3",
    "qs:name_local":"\u5bdd\u5c4b\u5ddd\u5e02",
    "qs:photo_max":9,
    "qs:photo_sum":36,
    "qs:placetype":"Suburb",
    "qs:quad_count":7,
    "qs:woe_adm0":23424856,
    "qs:woe_adm1":2345881,
    "qs:woe_adm2":0,
    "qs:woe_lau":28459508,
    "qs:woe_local":1117874,
    "qs:woe_ver":"7.10.0",
    "wof:lang":[
        "jpn"
    ],
    "wof:name":"\uff11\u4e01\u76ee",
    "wof:placetype":"neighbourhood"
},
  "geometry": {"coordinates":[135.62132500000001,34.764766],"type":"Point"}
}