{
  "type": "Feature",
  "properties": {
    "gn:admin1_code":"39.0",
    "gn:admin2_code":"1850156.0",
    "gn:asciiname":"Kokufucho-higashitakawa",
    "gn:country_code":"JP",
    "gn:dem":6,
    "gn:feature_class":"P",
    "gn:feature_code":"PPL",
    "gn:name":"Kokufuch\u014d-higashitakawa",
    "gn:population":0,
    "gn:timezone":"Asia/Tokyo",
    "iso:country":"JP",
    "name:jpn_x_preferred":[
        "\u56fd\u5e9c\u753a\u6771\u9ad8\u8f2a"
    ],
    "name:und_x_variant":[
        "Kokufuch\u014d-higashitakawa"
    ],
    "wof:name":"Kokufucho-higashitakawa",
    "wof:placetype":"locality"
},
  "geometry": {"coordinates":[134.48193999999998,34.09395],"type":"Point"}
}