{
  "type": "Feature",
  "properties": {
    "gn:admin1_code":"29",
    "gn:admin2_code":"1855427.0",
    "gn:admin3_code":"15102.0",
    "gn:asciiname":"Yamanoshitamachi",
    "gn:country_code":"JP",
    "gn:dem":-1,
    "gn:feature_class":"P",
    "gn:feature_code":"PPL",
    "gn:name":"Yamanoshitamachi",
    "gn:population":0,
    "gn:timezone":"Asia/Tokyo",
    "iso:country":"JP",
    "name:jpn_x_preferred":[
        "\u5c71\u306e\u4e0b\u753a"
    ],
    "name:und_x_variant":[
        "Yamanoshita"
    ],
    "wof:name":"Yamanoshitamachi",
    "wof:placetype":"locality"
},
  "geometry": {"coordinates":[139.0729,37.9402],"type":"Point"}
}