{
  "type": "Feature",
  "properties": {
    "gn:admin1_code":"23.0",
    "gn:admin2_code":"1848873.0",
    "gn:admin3_code":"24472.0",
    "gn:asciiname":"Murayama",
    "gn:country_code":"JP",
    "gn:dem":37,
    "gn:feature_class":"P",
    "gn:feature_code":"PPL",
    "gn:name":"Murayama",
    "gn:population":0,
    "gn:timezone":"Asia/Tokyo",
    "iso:country":"JP",
    "name:jpn_x_preferred":[
        "\u6751\u5c71"
    ],
    "wof:name":"Murayama",
    "wof:placetype":"locality"
},
  "geometry": {"coordinates":[136.49399,34.27970999999999],"type":"Point"}
}