{
  "type": "Feature",
  "properties": {
    "gn:admin1_code":"21.0",
    "gn:admin2_code":"1858418.0",
    "gn:admin3_code":"43103.0",
    "gn:asciiname":"Nakagawachi",
    "gn:country_code":"JP",
    "gn:dem":12,
    "gn:feature_class":"P",
    "gn:feature_code":"PPLL",
    "gn:name":"Nakagawachi",
    "gn:population":0,
    "gn:timezone":"Asia/Tokyo",
    "iso:country":"JP",
    "name:jpn_x_preferred":[
        "\u4e2d\u5ddd\u5185"
    ],
    "name:jpn_x_variant":[
        "\u306a\u304b\u304c\u308f\u3061",
        "\u30ca\u30ab\u30ac\u30ef\u30c1"
    ],
    "wof:name":"Nakagawachi",
    "wof:placetype":"locality"
},
  "geometry": {"coordinates":[130.59361999999999,32.82856],"type":"Point"}
}