{
  "type": "Feature",
  "properties": {
    "gn:admin1_code":"21.0",
    "gn:admin2_code":"7412708.0",
    "gn:admin3_code":"43505.0",
    "gn:asciiname":"Kogo",
    "gn:country_code":"JP",
    "gn:dem":175,
    "gn:feature_class":"P",
    "gn:feature_code":"PPLL",
    "gn:name":"Kog\u014d",
    "gn:population":0,
    "gn:timezone":"Asia/Tokyo",
    "iso:country":"JP",
    "name:ceb_x_preferred":[
        "Kogo"
    ],
    "name:deu_x_preferred":[
        "Kogo"
    ],
    "name:fra_x_preferred":[
        "Kogo"
    ],
    "name:ita_x_preferred":[
        "Kogo"
    ],
    "name:jpn_x_preferred":[
        "\u5c0f\u5ddd"
    ],
    "name:jpn_x_variant":[
        "\u3053\u3054\u3046",
        "\u30b3\u30b4\u30a6"
    ],
    "name:rus_x_preferred":[
        "\u041a\u043e\u0433\u043e"
    ],
    "name:swe_x_preferred":[
        "Kogo"
    ],
    "name:und_x_variant":[
        "Kog\u014d"
    ],
    "wof:name":"Kogo",
    "wof:placetype":"locality"
},
  "geometry": {"coordinates":[130.93598,32.2835],"type":"Point"}
}