{
  "type": "Feature",
  "properties": {
    "gn:admin1_code":"29.0",
    "gn:admin2_code":"1852604.0",
    "gn:asciiname":"Hitobashi",
    "gn:country_code":"JP",
    "gn:dem":4,
    "gn:feature_class":"P",
    "gn:feature_code":"PPL",
    "gn:name":"Hitobashi",
    "gn:population":0,
    "gn:timezone":"Asia/Tokyo",
    "iso:country":"JP",
    "name:jpn_x_preferred":[
        "\u4eba\u6a4b"
    ],
    "wof:name":"Hitobashi",
    "wof:placetype":"locality"
},
  "geometry": {"coordinates":[139.28899999999999,38.00671],"type":"Point"}
}