{
  "type": "Feature",
  "properties": {
    "gn:admin1_code":"8.0",
    "gn:admin2_code":"7451504.0",
    "gn:admin3_code":"7445.0",
    "gn:asciiname":"Numazawa",
    "gn:country_code":"JP",
    "gn:dem":486,
    "gn:feature_class":"P",
    "gn:feature_code":"PPL",
    "gn:name":"Numazawa",
    "gn:population":0,
    "gn:timezone":"Asia/Tokyo",
    "iso:country":"JP",
    "name:jpn_x_preferred":[
        "\u6cbc\u6ca2"
    ],
    "wof:name":"Numazawa",
    "wof:placetype":"locality"
},
  "geometry": {"coordinates":[139.58848,37.44814],"type":"Point"}
}