{
  "type": "Feature",
  "properties": {
    "gn:admin1_code":"23.0",
    "gn:admin2_code":"1851345.0",
    "gn:asciiname":"Mihatacho",
    "gn:country_code":"JP",
    "gn:dem":73,
    "gn:feature_class":"P",
    "gn:feature_code":"PPL",
    "gn:name":"Mihatach\u014d",
    "gn:population":0,
    "gn:timezone":"Asia/Tokyo",
    "iso:country":"JP",
    "name:jpn_x_preferred":[
        "\u4e09\u7551\u753a"
    ],
    "name:und_x_variant":[
        "Mihatach\u014d"
    ],
    "wof:name":"Mihatacho",
    "wof:placetype":"locality"
},
  "geometry": {"coordinates":[136.49494000000001,34.9098],"type":"Point"}
}