{
  "type": "Feature",
  "properties": {
    "gn:admin1_code":"21.0",
    "gn:admin2_code":"1858418.0",
    "gn:admin3_code":"43105.0",
    "gn:asciiname":"Mizuguchi",
    "gn:country_code":"JP",
    "gn:dem":79,
    "gn:feature_class":"P",
    "gn:feature_code":"PPLL",
    "gn:name":"Mizuguchi",
    "gn:population":0,
    "gn:timezone":"Asia/Tokyo",
    "iso:country":"JP",
    "name:jpn_x_preferred":[
        "\u6c34\u53e3"
    ],
    "name:jpn_x_variant":[
        "\u307f\u305a\u3050\u3061",
        "\u30df\u30ba\u30b0\u30c1"
    ],
    "wof:name":"Mizuguchi",
    "wof:placetype":"locality"
},
  "geometry": {"coordinates":[130.71871999999999,32.89168],"type":"Point"}
}