{
  "type": "Feature",
  "properties": {
    "gn:admin1_code":"21.0",
    "gn:admin2_code":"7413150.0",
    "gn:asciiname":"Kikukamachi-ikenaga",
    "gn:country_code":"JP",
    "gn:dem":161,
    "gn:feature_class":"P",
    "gn:feature_code":"PPL",
    "gn:name":"Kikukamachi-ikenaga",
    "gn:population":0,
    "gn:timezone":"Asia/Tokyo",
    "iso:country":"JP",
    "name:jpn_x_preferred":[
        "\u83ca\u9e7f\u753a\u6c60\u6c38"
    ],
    "name:jpn_x_variant":[
        "\u304d\u304f\u304b\u307e\u3061\u3044\u3051\u306a\u304c",
        "\u30ad\u30af\u30ab\u30de\u30c1\u30a4\u30b1\u30ca\u30ac"
    ],
    "wof:name":"Kikukamachi-ikenaga",
    "wof:placetype":"locality"
},
  "geometry": {"coordinates":[130.79186999999999,33.02984],"type":"Point"}
}