{
  "type": "Feature",
  "properties": {
    "gn:admin1_code":"21.0",
    "gn:admin2_code":"1858418.0",
    "gn:admin3_code":"43104.0",
    "gn:asciiname":"Araki",
    "gn:country_code":"JP",
    "gn:dem":0,
    "gn:feature_class":"P",
    "gn:feature_code":"PPLL",
    "gn:name":"Araki",
    "gn:population":0,
    "gn:timezone":"Asia/Tokyo",
    "iso:country":"JP",
    "name:jpn_x_preferred":[
        "\u8352\u6728"
    ],
    "name:jpn_x_variant":[
        "\u3042\u3089\u304d",
        "\u30a2\u30e9\u30ad"
    ],
    "wof:name":"Araki",
    "wof:placetype":"locality"
},
  "geometry": {"coordinates":[130.64196999999999,32.73644],"type":"Point"}
}