{
  "type": "Feature",
  "properties": {
    "gn:admin1_code":"4.0",
    "gn:admin2_code":"7465521.0",
    "gn:asciiname":"Toriibatake",
    "gn:country_code":"JP",
    "gn:dem":87,
    "gn:feature_class":"P",
    "gn:feature_code":"PPLL",
    "gn:name":"Toriibatake",
    "gn:population":0,
    "gn:timezone":"Asia/Tokyo",
    "iso:country":"JP",
    "name:jpn_x_preferred":[
        "\u9ce5\u4e95\u7551"
    ],
    "name:jpn_x_variant":[
        "\u3068\u308a\u3044\u3070\u305f\u3051",
        "\u30c8\u30ea\u30a4\u30d0\u30bf\u30b1"
    ],
    "wof:name":"Toriibatake",
    "wof:placetype":"locality"
},
  "geometry": {"coordinates":[139.99758,35.07059],"type":"Point"}
}