{
  "type": "Feature",
  "properties": {
    "gn:admin1_code":"19.0",
    "gn:admin2_code":"1865011.0",
    "gn:admin3_code":"14364.0",
    "gn:asciiname":"Furujuku",
    "gn:country_code":"JP",
    "gn:dem":332,
    "gn:feature_class":"P",
    "gn:feature_code":"PPLL",
    "gn:name":"Furujuku",
    "gn:population":0,
    "gn:timezone":"Asia/Tokyo",
    "iso:country":"JP",
    "name:jpn_x_preferred":[
        "\u53e4\u5bbf"
    ],
    "wof:name":"Furujuku",
    "wof:placetype":"locality"
},
  "geometry": {"coordinates":[139.06406000000001,35.37288],"type":"Point"}
}