{
  "type": "Feature",
  "properties": {
    "gn:admin1_code":"15.0",
    "gn:admin2_code":"7467881.0",
    "gn:asciiname":"Mikawa-hamamachi",
    "gn:country_code":"JP",
    "gn:dem":13,
    "gn:feature_class":"P",
    "gn:feature_code":"PPL",
    "gn:name":"Mikawa-hamamachi",
    "gn:population":0,
    "gn:timezone":"Asia/Tokyo",
    "iso:country":"JP",
    "name:jpn_x_preferred":[
        "\u7f8e\u5ddd\u6d5c\u753a"
    ],
    "wof:name":"Mikawa-hamamachi",
    "wof:placetype":"locality"
},
  "geometry": {"coordinates":[136.49087,36.48859],"type":"Point"}
}