{
  "type": "Feature",
  "properties": {
    "gn:admin1_code":"37.0",
    "gn:admin2_code":"1864104.0",
    "gn:asciiname":"Naganuki",
    "gn:country_code":"JP",
    "gn:dem":131,
    "gn:feature_class":"P",
    "gn:feature_code":"PPL",
    "gn:name":"Naganuki",
    "gn:population":0,
    "gn:timezone":"Asia/Tokyo",
    "iso:country":"JP",
    "name:jpn_x_preferred":[
        "\u9577\u8cab"
    ],
    "wof:name":"Naganuki",
    "wof:placetype":"locality"
},
  "geometry": {"coordinates":[138.55884,35.20625],"type":"Point"}
}