{
  "type": "Feature",
  "properties": {
    "gn:admin1_code":"34.0",
    "gn:admin2_code":"7464124.0",
    "gn:asciiname":"Ueuchi",
    "gn:country_code":"JP",
    "gn:dem":11,
    "gn:feature_class":"P",
    "gn:feature_code":"PPL",
    "gn:name":"Ueuchi",
    "gn:population":0,
    "gn:timezone":"Asia/Tokyo",
    "iso:country":"JP",
    "name:jpn_x_preferred":[
        "\u4e0a\u5185"
    ],
    "name:jpn_x_variant":[
        "\u3046\u3048\u3046\u3061",
        "\u30a6\u30a8\u30a6\u30c1"
    ],
    "wof:name":"Ueuchi",
    "wof:placetype":"locality"
},
  "geometry": {"coordinates":[139.66480000000001,36.08675],"type":"Point"}
}