{
  "type": "Feature",
  "properties": {
    "gn:country":"JP",
    "gn:fcode":"PPL",
    "gn:population":27481,
    "iso:country":"JP",
    "name:deu_x_preferred":[
        "Arai"
    ],
    "name:fra_x_preferred":[
        "Arai"
    ],
    "name:ita_x_preferred":[
        "Arai"
    ],
    "name:jpn_x_preferred":[
        "\u65b0\u4e95"
    ],
    "name:kor_x_preferred":[
        "\uc544\ub77c\uc774"
    ],
    "name:mlg_x_preferred":[
        "Arai"
    ],
    "name:rus_x_preferred":[
        "\u0410\u0440\u0430\u0438"
    ],
    "name:spa_x_preferred":[
        "Arai"
    ],
    "name:swe_x_preferred":[
        "Arai"
    ],
    "name:ukr_x_preferred":[
        "\u0410\u0440\u0430\u0457"
    ],
    "qs:name":"Arai",
    "qs:photos_9r":0,
    "qs:photos_sr":0,
    "qs:pop_sr":"7",
    "wof:name":"Arai",
    "wof:placetype":"locality",
    "wof:population":27481
},
  "geometry": {"coordinates":[138.25,37.01667],"type":"Point"}
}