{
  "type": "Feature",
  "properties": {
    "gn:country":"JP",
    "gn:fcode":"PPL",
    "gn:pop":27481,
    "iso:country":"JP",
    "name:jpn_x_preferred":[
        "\u65b0\u4e95"
    ],
    "qs:name":"Arai",
    "qs:photos_9r":0,
    "qs:photos_sr":0,
    "qs:pop_sr":"7",
    "wof:name":"Arai",
    "wof:placetype":"locality",
    "wof:population":27481
},
  "geometry": {"coordinates":[138.25,37.01667],"type":"Point"}
}