{
  "type": "Feature",
  "properties": {
    "gn:admin1_code":"3.0",
    "gn:admin2_code":"2130225.0",
    "gn:asciiname":"Isono",
    "gn:country_code":"JP",
    "gn:dem":4,
    "gn:feature_class":"P",
    "gn:feature_code":"PPL",
    "gn:name":"Isono",
    "gn:population":0,
    "gn:timezone":"Asia/Tokyo",
    "iso:country":"JP",
    "name:jpn_x_preferred":[
        "\u78ef\u91ce"
    ],
    "name:jpn_x_variant":[
        "\u3044\u305d\u306e",
        "\u30a4\u30bd\u30ce"
    ],
    "wof:name":"Isono",
    "wof:placetype":"locality"
},
  "geometry": {"coordinates":[140.32443000000001,41.07432],"type":"Point"}
}