{
  "type": "Feature",
  "properties": {
    "gn:admin1_code":"21.0",
    "gn:admin2_code":"7412706.0",
    "gn:admin3_code":"43447.0",
    "gn:asciiname":"Yanagi",
    "gn:country_code":"JP",
    "gn:dem":721,
    "gn:feature_class":"P",
    "gn:feature_code":"PPLL",
    "gn:name":"Yanagi",
    "gn:population":0,
    "gn:timezone":"Asia/Tokyo",
    "iso:country":"JP",
    "name:deu_x_preferred":[
        "Yanagi"
    ],
    "name:jpn_x_preferred":[
        "\u67f3"
    ],
    "name:jpn_x_variant":[
        "\u3084\u306a\u304e",
        "\u30e4\u30ca\u30ae"
    ],
    "wof:name":"Yanagi",
    "wof:placetype":"locality"
},
  "geometry": {"coordinates":[131.16817,32.8023],"type":"Point"}
}