{
  "type": "Feature",
  "properties": {
    "gn:admin1_code":"3.0",
    "gn:admin2_code":"2128302.0",
    "gn:admin3_code":"2445.0",
    "gn:asciiname":"Goku",
    "gn:country_code":"JP",
    "gn:dem":29,
    "gn:feature_class":"P",
    "gn:feature_code":"PPL",
    "gn:name":"Goku",
    "gn:population":0,
    "gn:timezone":"Asia/Tokyo",
    "iso:country":"JP",
    "name:ara_x_preferred":[
        "\u0633\u0648\u0646 \u063a\u0648\u0643\u0648"
    ],
    "name:cat_x_preferred":[
        "Son Goku"
    ],
    "name:ckb_x_preferred":[
        "\u0633\u06c6\u0646 \u06af\u06c6\u06a9\u0648"
    ],
    "name:dan_x_preferred":[
        "Son Gok\u016b"
    ],
    "name:eus_x_preferred":[
        "Son Goku"
    ],
    "name:fin_x_preferred":[
        "Son Goku"
    ],
    "name:fra_x_preferred":[
        "Son Goku"
    ],
    "name:glg_x_preferred":[
        "Son Goku"
    ],
    "name:heb_x_preferred":[
        "\u05e1\u05d5\u05df \u05d2\u05d5\u05e7\u05d5"
    ],
    "name:hin_x_preferred":[
        "\u0938\u0928 \u0917\u094b\u0915\u0942"
    ],
    "name:hrv_x_preferred":[
        "Goku"
    ],
    "name:hun_x_preferred":[
        "Son Goku"
    ],
    "name:hye_x_preferred":[
        "\u054d\u0578\u0576 \u0533\u0578\u056f\u0578\u0582"
    ],
    "name:ind_x_preferred":[
        "Goku"
    ],
    "name:ita_x_preferred":[
        "Son Goku"
    ],
    "name:jav_x_preferred":[
        "Son Goku"
    ],
    "name:jpn_x_preferred":[
        "\u4e94\u533a"
    ],
    "name:jpn_x_variant":[
        "\u3054\u304f",
        "\u30b4\u30af",
        "\u5b6b\u609f\u7a7a"
    ],
    "name:kat_x_preferred":[
        "\u10d2\u10dd\u10d9\u10e3"
    ],
    "name:kor_x_preferred":[
        "\uc190\uc624\uacf5"
    ],
    "name:lit_x_preferred":[
        "Son Gokas"
    ],
    "name:mal_x_preferred":[
        "\u0d17\u0d4b\u0d15\u0d42"
    ],
    "name:mar_x_preferred":[
        "\u0917\u094b\u0915\u0941"
    ],
    "name:msa_x_preferred":[
        "Son Goku"
    ],
    "name:nld_x_preferred":[
        "Son Goku"
    ],
    "name:nor_x_preferred":[
        "Son Gok\u016b"
    ],
    "name:pol_x_preferred":[
        "Son Gok\u016b"
    ],
    "name:por_x_preferred":[
        "Son Goku"
    ],
    "name:que_x_preferred":[
        "Goku"
    ],
    "name:ron_x_preferred":[
        "Goku"
    ],
    "name:rus_x_preferred":[
        "\u0421\u043e\u043d \u0413\u043e\u043a\u0443"
    ],
    "name:spa_x_preferred":[
        "Son Gok\u016b"
    ],
    "name:sqi_x_preferred":[
        "Goku"
    ],
    "name:srp_x_preferred":[
        "Goku"
    ],
    "name:swe_x_preferred":[
        "Son-Goku"
    ],
    "name:tel_x_preferred":[
        "\u0c38\u0c28\u0c4d \u0c17\u0c4b\u0c15\u0c41"
    ],
    "name:tha_x_preferred":[
        "\u0e0b\u0e07 \u0e42\u0e01\u0e04\u0e39"
    ],
    "name:ukr_x_preferred":[
        "\u0421\u043e\u043d \u0413\u043e\u043a\u0443"
    ],
    "name:vie_x_preferred":[
        "Son Goku"
    ],
    "name:wuu_x_preferred":[
        "\u5b59\u609f\u7a7a"
    ],
    "name:zho_x_preferred":[
        "\u5b59\u609f\u7a7a"
    ],
    "wof:name":"Goku",
    "wof:placetype":"locality"
},
  "geometry": {"coordinates":[141.27358999999996,40.40422],"type":"Point"}
}