{
  "type": "Feature",
  "properties": {
    "gn:admin1_code":"3.0",
    "gn:admin2_code":"2128302.0",
    "gn:admin3_code":"2445.0",
    "gn:asciiname":"Goku",
    "gn:country_code":"JP",
    "gn:dem":29,
    "gn:feature_class":"P",
    "gn:feature_code":"PPL",
    "gn:name":"Goku",
    "gn:population":0,
    "gn:timezone":"Asia/Tokyo",
    "iso:country":"JP",
    "name:jpn_x_preferred":[
        "\u4e94\u533a"
    ],
    "name:jpn_x_variant":[
        "\u3054\u304f",
        "\u30b4\u30af"
    ],
    "wof:name":"Goku",
    "wof:placetype":"locality"
},
  "geometry": {"coordinates":[141.27358999999996,40.40422],"type":"Point"}
}