{
  "type": "Feature",
  "properties": {
    "gn:admin1_code":"4.0",
    "gn:admin2_code":"2112997.0",
    "gn:admin3_code":"12427.0",
    "gn:asciiname":"Nakanodai",
    "gn:country_code":"JP",
    "gn:dem":46,
    "gn:feature_class":"P",
    "gn:feature_code":"PPLL",
    "gn:name":"Nakanodai",
    "gn:population":0,
    "gn:timezone":"Asia/Tokyo",
    "iso:country":"JP",
    "name:jpn_x_preferred":[
        "\u4e2d\u4e4b\u53f0"
    ],
    "name:jpn_x_variant":[
        "\u306a\u304b\u306e\u3060\u3044",
        "\u30ca\u30ab\u30ce\u30c0\u30a4"
    ],
    "wof:name":"Nakanodai",
    "wof:placetype":"locality"
},
  "geometry": {"coordinates":[140.24293,35.3766],"type":"Point"}
}