{
  "type": "Feature",
  "properties": {
    "gn:admin1_code":"16.0",
    "gn:admin2_code":"2112822.0",
    "gn:asciiname":"Soichi",
    "gn:country_code":"JP",
    "gn:dem":84,
    "gn:feature_class":"P",
    "gn:feature_code":"PPL",
    "gn:name":"Soichi",
    "gn:population":0,
    "gn:timezone":"Asia/Tokyo",
    "iso:country":"JP",
    "name:jpn_x_preferred":[
        "\u6dfb\u5e02"
    ],
    "name:jpn_x_variant":[
        "\u305d\u3044\u3061",
        "\u30bd\u30a4\u30c1"
    ],
    "wof:name":"Soichi",
    "wof:placetype":"locality"
},
  "geometry": {"coordinates":[141.17928999999995,39.4221],"type":"Point"}
}