{
  "type": "Feature",
  "properties": {
    "gn:admin1_code":"10",
    "gn:admin2_code":"7453747.0",
    "gn:admin3_code":"10421.0",
    "gn:asciiname":"Isemachi",
    "gn:country_code":"JP",
    "gn:dem":329,
    "gn:feature_class":"P",
    "gn:feature_code":"PPL",
    "gn:name":"Isemachi",
    "gn:population":0,
    "gn:timezone":"Asia/Tokyo",
    "iso:country":"JP",
    "name:jpn_x_preferred":[
        "\u4f0a\u52e2\u753a"
    ],
    "name:und_x_variant":[
        "Ise",
        "Isemachi"
    ],
    "wof:name":"Isemachi",
    "wof:placetype":"locality"
},
  "geometry": {"coordinates":[138.85480000000001,36.58447],"type":"Point"}
}