{
  "type": "Feature",
  "properties": {
    "gn:admin1_code":"19.0",
    "gn:admin2_code":"7470889.0",
    "gn:asciiname":"Oyakita",
    "gn:country_code":"JP",
    "gn:dem":48,
    "gn:feature_class":"P",
    "gn:feature_code":"PPL",
    "gn:name":"\u014cyakita",
    "gn:population":0,
    "gn:timezone":"Asia/Tokyo",
    "iso:country":"JP",
    "name:jpn_x_preferred":[
        "\u5927\u8c37\u5317"
    ],
    "name:und_x_variant":[
        "\u014cyakita"
    ],
    "wof:name":"Oyakita",
    "wof:placetype":"locality"
},
  "geometry": {"coordinates":[139.39874,35.44052999999999],"type":"Point"}
}