{
  "type": "Feature",
  "properties": {
    "gn:admin1_code":"4.0",
    "gn:admin2_code":"2112386.0",
    "gn:asciiname":"Miyayatsu",
    "gn:country_code":"JP",
    "gn:dem":61,
    "gn:feature_class":"P",
    "gn:feature_code":"PPLL",
    "gn:name":"Miyayatsu",
    "gn:population":0,
    "gn:timezone":"Asia/Tokyo",
    "iso:country":"JP",
    "name:jpn_x_preferred":[
        "\u5bae\u8c37"
    ],
    "name:jpn_x_variant":[
        "\u307f\u3084\u3084\u3064",
        "\u30df\u30e4\u30e4\u30c4"
    ],
    "wof:name":"Miyayatsu",
    "wof:placetype":"locality"
},
  "geometry": {"coordinates":[140.01124999999999,35.12495],"type":"Point"}
}