{
  "type": "Feature",
  "properties": {
    "gn:admin1_code":"29",
    "gn:admin2_code":"1855427.0",
    "gn:admin3_code":"15107.0",
    "gn:asciiname":"Chugonji",
    "gn:country_code":"JP",
    "gn:dem":0,
    "gn:feature_class":"P",
    "gn:feature_code":"PPL",
    "gn:name":"Ch\u016bgonji",
    "gn:population":0,
    "gn:timezone":"Asia/Tokyo",
    "iso:country":"JP",
    "name:jpn_x_preferred":[
        "\u4e2d\u6a29\u5bfa"
    ],
    "name:und_x_variant":[
        "Ch\u016bgonji"
    ],
    "wof:name":"Chugonji",
    "wof:placetype":"locality"
},
  "geometry": {"coordinates":[138.91407000000001,37.84035],"type":"Point"}
}