{
  "type": "Feature",
  "properties": {
    "gn:admin1_code":"21.0",
    "gn:admin2_code":"1859488.0",
    "gn:asciiname":"Fukunomoto-ikku",
    "gn:country_code":"JP",
    "gn:dem":61,
    "gn:feature_class":"P",
    "gn:feature_code":"PPLL",
    "gn:name":"Fukunomoto-ikku",
    "gn:population":0,
    "gn:timezone":"Asia/Tokyo",
    "iso:country":"JP",
    "name:jpn_x_preferred":[
        "\u798f\u672c\u4e00\u533a"
    ],
    "name:jpn_x_variant":[
        "\u3075\u304f\u306e\u3082\u3068\u3044\u3063\u304f",
        "\u30d5\u30af\u30ce\u30e2\u30c8\u30a4\u30c3\u30af"
    ],
    "wof:name":"Fukunomoto-ikku",
    "wof:placetype":"locality"
},
  "geometry": {"coordinates":[130.77903999999998,32.91931],"type":"Point"}
}