{
  "type": "Feature",
  "properties": {
    "gn:admin1_code":"21.0",
    "gn:admin2_code":"1858418.0",
    "gn:admin3_code":"43105.0",
    "gn:asciiname":"Takaseguchi",
    "gn:country_code":"JP",
    "gn:dem":102,
    "gn:feature_class":"P",
    "gn:feature_code":"PPLL",
    "gn:name":"Takaseguchi",
    "gn:population":0,
    "gn:timezone":"Asia/Tokyo",
    "iso:country":"JP",
    "name:jpn_x_preferred":[
        "\u9ad8\u702c\u53e3"
    ],
    "name:jpn_x_variant":[
        "\u305f\u304b\u305b\u3050\u3061",
        "\u30bf\u30ab\u30bb\u30b0\u30c1"
    ],
    "wof:name":"Takaseguchi",
    "wof:placetype":"locality"
},
  "geometry": {"coordinates":[130.69113000000002,32.89856],"type":"Point"}
}