{
  "type": "Feature",
  "properties": {
    "gn:admin1_code":"46.0",
    "gn:admin2_code":"7415908.0",
    "gn:admin3_code":"19425.0",
    "gn:asciiname":"Fudosaka",
    "gn:country_code":"JP",
    "gn:dem":1020,
    "gn:feature_class":"P",
    "gn:feature_code":"PPLL",
    "gn:name":"Fud\u014dsaka",
    "gn:population":0,
    "gn:timezone":"Asia/Tokyo",
    "iso:country":"JP",
    "name:jpn_x_preferred":[
        "\u4e0d\u52d5\u5742"
    ],
    "name:und_x_variant":[
        "Fud\u014dsaka"
    ],
    "wof:name":"Fudosaka",
    "wof:placetype":"locality"
},
  "geometry": {"coordinates":[138.88407000000001,35.42371],"type":"Point"}
}