{
  "type": "Feature",
  "properties": {
    "gn:admin1_code":"21.0",
    "gn:admin2_code":"7413150.0",
    "gn:asciiname":"Jusan",
    "gn:country_code":"JP",
    "gn:dem":41,
    "gn:feature_class":"P",
    "gn:feature_code":"PPLL",
    "gn:name":"J\u016bsan",
    "gn:population":0,
    "gn:timezone":"Asia/Tokyo",
    "iso:country":"JP",
    "name:jpn_x_preferred":[
        "\u5341\u4e09"
    ],
    "name:jpn_x_variant":[
        "\u3058\u3085\u3046\u3055\u3093",
        "\u30b8\u30e5\u30a6\u30b5\u30f3"
    ],
    "name:und_x_variant":[
        "J\u016bsan"
    ],
    "wof:name":"Jusan",
    "wof:placetype":"locality"
},
  "geometry": {"coordinates":[130.71281999999999,33.01037],"type":"Point"}
}