{
  "type": "Feature",
  "properties": {
    "gn:admin1_code":"3.0",
    "gn:admin2_code":"2128302.0",
    "gn:admin3_code":"2441.0",
    "gn:asciiname":"Tsujigatai",
    "gn:country_code":"JP",
    "gn:dem":104,
    "gn:feature_class":"P",
    "gn:feature_code":"PPL",
    "gn:name":"Tsujigatai",
    "gn:population":0,
    "gn:timezone":"Asia/Tokyo",
    "iso:country":"JP",
    "name:jpn_x_preferred":[
        "\u8fbb\u30f6\u5e73"
    ],
    "name:jpn_x_variant":[
        "\u3064\u3058\u304c\u305f\u3044",
        "\u30c4\u30b8\u30ac\u30bf\u30a4"
    ],
    "wof:name":"Tsujigatai",
    "wof:placetype":"locality"
},
  "geometry": {"coordinates":[141.21797000000001,40.3539],"type":"Point"}
}