{
  "type": "Feature",
  "properties": {
    "gn:admin1_code":"31",
    "gn:admin2_code":"1858309.0",
    "gn:asciiname":"Chayamachi",
    "gn:country_code":"JP",
    "gn:dem":1,
    "gn:feature_class":"P",
    "gn:feature_code":"PPL",
    "gn:name":"Chayamachi",
    "gn:population":0,
    "gn:timezone":"Asia/Tokyo",
    "iso:country":"JP",
    "name:jbn_x_preferred":[
        "Chaya"
    ],
    "name:jpn_x_preferred":[
        "\u8336\u5c4b\u753a"
    ],
    "wof:name":"Chayamachi",
    "wof:placetype":"locality"
},
  "geometry": {"coordinates":[133.82758999999999,34.57888],"type":"Point"}
}