{
  "type": "Feature",
  "properties": {
    "gn:admin1_code":"13.0",
    "gn:admin2_code":"7370821.0",
    "gn:asciiname":"Nagasada",
    "gn:country_code":"JP",
    "gn:dem":100,
    "gn:feature_class":"P",
    "gn:feature_code":"PPL",
    "gn:name":"Nagasada",
    "gn:population":0,
    "gn:timezone":"Asia/Tokyo",
    "iso:country":"JP",
    "name:jpn_x_preferred":[
        "\u9577\u8c9e"
    ],
    "wof:name":"Nagasada",
    "wof:placetype":"locality"
},
  "geometry": {"coordinates":[135.08033999999998,34.91734],"type":"Point"}
}