{
  "type": "Feature",
  "properties": {
    "gn:admin1_code":"46.0",
    "gn:admin2_code":"7415908.0",
    "gn:admin3_code":"19425.0",
    "gn:asciiname":"Mikokirizume",
    "gn:country_code":"JP",
    "gn:dem":1049,
    "gn:feature_class":"P",
    "gn:feature_code":"PPLL",
    "gn:name":"Mik\u014dkirizume",
    "gn:population":0,
    "gn:timezone":"Asia/Tokyo",
    "iso:country":"JP",
    "name:jpn_x_preferred":[
        "\u5411\u5207\u8a70"
    ],
    "name:und_x_variant":[
        "Mik\u014dkirizume"
    ],
    "wof:name":"Mikokirizume",
    "wof:placetype":"locality"
},
  "geometry": {"coordinates":[138.87656000000001,35.40091],"type":"Point"}
}