{
  "type": "Feature",
  "properties": {
    "gn:admin1_code":"7.0",
    "gn:admin2_code":"1855902.0",
    "gn:asciiname":"Oneto",
    "gn:country_code":"JP",
    "gn:dem":7,
    "gn:feature_class":"P",
    "gn:feature_code":"PPL",
    "gn:name":"\u014cneto",
    "gn:population":0,
    "gn:timezone":"Asia/Tokyo",
    "iso:country":"JP",
    "name:jpn_x_preferred":[
        "\u5927\u6839\u571f"
    ],
    "name:und_x_variant":[
        "\u014cneto"
    ],
    "wof:name":"Oneto",
    "wof:placetype":"locality"
},
  "geometry": {"coordinates":[130.71736999999999,33.82258],"type":"Point"}
}