{
  "type": "Feature",
  "properties": {
    "gn:admin1_code":"39.0",
    "gn:admin2_code":"1850156.0",
    "gn:asciiname":"Kawauchicho",
    "gn:country_code":"JP",
    "gn:dem":1,
    "gn:feature_class":"P",
    "gn:feature_code":"PPL",
    "gn:name":"Kawauchich\u014d",
    "gn:population":0,
    "gn:timezone":"Asia/Tokyo",
    "iso:country":"JP",
    "name:jpn_x_preferred":[
        "\u5ddd\u5185\u753a"
    ],
    "name:und_x_variant":[
        "Kawauchich\u014d"
    ],
    "wof:name":"Kawauchicho",
    "wof:placetype":"locality"
},
  "geometry": {"coordinates":[134.57636000000002,34.11014],"type":"Point"}
}