{
  "type": "Feature",
  "properties": {
    "gn:admin1_code":"24.0",
    "gn:admin2_code":"2112261.0",
    "gn:asciiname":"Yoshinokuchi",
    "gn:country_code":"JP",
    "gn:dem":123,
    "gn:feature_class":"P",
    "gn:feature_code":"PPL",
    "gn:name":"Yoshinokuchi",
    "gn:population":0,
    "gn:timezone":"Asia/Tokyo",
    "iso:country":"JP",
    "name:jpn_x_preferred":[
        "\u82b3\u30ce\u53e3"
    ],
    "name:jpn_x_variant":[
        "\u3088\u3057\u306e\u304f\u3061",
        "\u30e8\u30b7\u30ce\u30af\u30c1"
    ],
    "wof:name":"Yoshinokuchi",
    "wof:placetype":"locality"
},
  "geometry": {"coordinates":[141.52118000000004,38.96307],"type":"Point"}
}