{
  "type": "Feature",
  "properties": {
    "gn:admin1_code":"21.0",
    "gn:admin2_code":"1848441.0",
    "gn:asciiname":"Shirakibira",
    "gn:country_code":"JP",
    "gn:dem":153,
    "gn:feature_class":"P",
    "gn:feature_code":"PPLL",
    "gn:name":"Shirakibira",
    "gn:population":0,
    "gn:timezone":"Asia/Tokyo",
    "iso:country":"JP",
    "name:jpn_x_preferred":[
        "\u767d\u6728\u5e73"
    ],
    "name:jpn_x_variant":[
        "\u3057\u3089\u304d\u3073\u3089",
        "\u30b7\u30e9\u30ad\u30d3\u30e9"
    ],
    "wof:name":"Shirakibira",
    "wof:placetype":"locality"
},
  "geometry": {"coordinates":[130.75861,32.56191],"type":"Point"}
}