{
  "type": "Feature",
  "properties": {
    "gn:admin1_code":"32.0",
    "gn:admin2_code":"1850907.0",
    "gn:asciiname":"Imashirocho",
    "gn:country_code":"JP",
    "gn:dem":17,
    "gn:feature_class":"P",
    "gn:feature_code":"PPL",
    "gn:name":"Imashiroch\u014d",
    "gn:population":0,
    "gn:timezone":"Asia/Tokyo",
    "iso:country":"JP",
    "name:jpn_x_preferred":[
        "\u4eca\u57ce\u753a"
    ],
    "name:und_x_variant":[
        "Imashiroch\u014d"
    ],
    "wof:name":"Imashirocho",
    "wof:placetype":"locality"
},
  "geometry": {"coordinates":[135.60045,34.84722],"type":"Point"}
}