{
  "type": "Feature",
  "properties": {
    "gn:admin1_code":"7.0",
    "gn:admin2_code":"7407420.0",
    "gn:asciiname":"Ukiha",
    "gn:country_code":"JP",
    "gn:dem":27,
    "gn:feature_class":"P",
    "gn:feature_code":"PPLA2",
    "gn:name":"Ukiha",
    "gn:population":0,
    "gn:timezone":"Asia/Tokyo",
    "iso:country":"JP",
    "name:jpn_x_preferred":[
        "\u3046\u304d\u306f"
    ],
    "wof:name":"Ukiha",
    "wof:placetype":"locality"
},
  "geometry": {"coordinates":[130.74966000000001,33.35634],"type":"Point"}
}