{
  "type": "Feature",
  "properties": {
    "gn:admin1_code":"27.0",
    "gn:admin2_code":"7418805.0",
    "gn:asciiname":"Nakanobaru",
    "gn:country_code":"JP",
    "gn:dem":35,
    "gn:feature_class":"P",
    "gn:feature_code":"PPLL",
    "gn:name":"Nakanobaru",
    "gn:population":0,
    "gn:timezone":"Asia/Tokyo",
    "iso:country":"JP",
    "name:jpn_x_preferred":[
        "\u4e2d\u30ce\u539f"
    ],
    "wof:name":"Nakanobaru",
    "wof:placetype":"locality"
},
  "geometry": {"coordinates":[129.55736999999999,33.38154],"type":"Point"}
}