{
  "type": "Feature",
  "properties": {
    "gn:admin1_code":"34.0",
    "gn:admin2_code":"1849187.0",
    "gn:admin3_code":"11107.0",
    "gn:asciiname":"Daito",
    "gn:country_code":"JP",
    "gn:dem":16,
    "gn:feature_class":"P",
    "gn:feature_code":"PPL",
    "gn:name":"Dait\u014d",
    "gn:population":0,
    "gn:timezone":"Asia/Tokyo",
    "iso:country":"JP",
    "name:jpn_x_preferred":[
        "\u5927\u6771"
    ],
    "name:jpn_x_variant":[
        "\u3060\u3044\u3068\u3046",
        "\u30c0\u30a4\u30c8\u30a6"
    ],
    "name:und_x_variant":[
        "Dait\u014d"
    ],
    "wof:name":"Daito",
    "wof:placetype":"locality"
},
  "geometry": {"coordinates":[139.66153,35.88222000000001],"type":"Point"}
}