{
  "type": "Feature",
  "properties": {
    "gn:admin1_code":"37.0",
    "gn:admin2_code":"1864089.0",
    "gn:asciiname":"Harakata",
    "gn:country_code":"JP",
    "gn:dem":52,
    "gn:feature_class":"P",
    "gn:feature_code":"PPLL",
    "gn:name":"Harakata",
    "gn:population":0,
    "gn:timezone":"Asia/Tokyo",
    "iso:country":"JP",
    "name:jpn_x_preferred":[
        "\u539f\u65b9\u3000"
    ],
    "wof:name":"Harakata",
    "wof:placetype":"locality"
},
  "geometry": {"coordinates":[138.59922,35.185],"type":"Point"}
}