{
  "type": "Feature",
  "properties": {
    "gn:admin1_code":"27.0",
    "gn:admin2_code":"1852895.0",
    "gn:asciiname":"Shimonoharucho",
    "gn:country_code":"JP",
    "gn:dem":51,
    "gn:feature_class":"P",
    "gn:feature_code":"PPL",
    "gn:name":"Shimonoharuch\u014d",
    "gn:population":0,
    "gn:timezone":"Asia/Tokyo",
    "iso:country":"JP",
    "name:jpn_x_preferred":[
        "\u4e0b\u306e\u539f\u753a"
    ],
    "name:und_x_variant":[
        "Shimonoharuch\u014d"
    ],
    "wof:name":"Shimonoharucho",
    "wof:placetype":"locality"
},
  "geometry": {"coordinates":[129.81874999999999,33.13744000000001],"type":"Point"}
}