{
  "type": "Feature",
  "properties": {
    "gn:admin1_code":"4.0",
    "gn:admin2_code":"1863711.0",
    "gn:asciiname":"Funabashi",
    "gn:country_code":"JP",
    "gn:dem":20,
    "gn:feature_class":"P",
    "gn:feature_code":"PPLL",
    "gn:name":"Funabashi",
    "gn:population":0,
    "gn:timezone":"Asia/Tokyo",
    "iso:country":"JP",
    "name:ara_x_preferred":[
        "\u0641\u0648\u0646\u0627\u0628\u0627\u0634\u064a"
    ],
    "name:azb_x_preferred":[
        "\u0641\u0648\u0646\u0627\u0628\u0627\u0634\u06cc"
    ],
    "name:aze_x_preferred":[
        "Funaba\u015fi"
    ],
    "name:bul_x_preferred":[
        "\u0424\u0443\u043d\u0430\u0431\u0430\u0448\u0438"
    ],
    "name:ceb_x_preferred":[
        "Funabashi"
    ],
    "name:ces_x_preferred":[
        "Funaba\u0161i"
    ],
    "name:deu_x_preferred":[
        "Funabashi"
    ],
    "name:epo_x_preferred":[
        "Funaba\u015di"
    ],
    "name:est_x_preferred":[
        "Funabashi"
    ],
    "name:eus_x_preferred":[
        "Funabashi"
    ],
    "name:fas_x_preferred":[
        "\u0641\u0648\u0646\u0627\u0628\u0627\u0634\u06cc"
    ],
    "name:fin_x_preferred":[
        "Funabashi"
    ],
    "name:fra_x_preferred":[
        "Funabashi"
    ],
    "name:gle_x_preferred":[
        "Funabashi"
    ],
    "name:glg_x_preferred":[
        "Funabashi"
    ],
    "name:hye_x_preferred":[
        "\u0556\u0578\u0582\u0576\u0561\u0562\u0561\u057d\u056b"
    ],
    "name:ita_x_preferred":[
        "Funabashi"
    ],
    "name:jpn_x_preferred":[
        "\u8239\u7aef"
    ],
    "name:jpn_x_variant":[
        "\u3075\u306a\u3070\u3057",
        "\u30d5\u30ca\u30d0\u30b7",
        "\u8239\u6a4b\u5e02"
    ],
    "name:kor_x_preferred":[
        "\ud6c4\ub098\ubc14\uc2dc\uc2dc"
    ],
    "name:msa_x_preferred":[
        "Funabashi"
    ],
    "name:mzn_x_preferred":[
        "\u0641\u0648\u0646\u0627\u0628\u0627\u0634\u06cc"
    ],
    "name:nld_x_preferred":[
        "Funabashi"
    ],
    "name:pol_x_preferred":[
        "Funabashi"
    ],
    "name:por_x_preferred":[
        "Funabashi"
    ],
    "name:ron_x_preferred":[
        "Funabashi"
    ],
    "name:rus_x_preferred":[
        "\u0424\u0443\u043d\u0430\u0431\u0430\u0441\u0438"
    ],
    "name:sco_x_preferred":[
        "Funabashi"
    ],
    "name:spa_x_preferred":[
        "Funabashi"
    ],
    "name:srp_x_preferred":[
        "\u0424\u0443\u043d\u0430\u0431\u0430\u0448\u0438"
    ],
    "name:swa_x_preferred":[
        "Funabashi"
    ],
    "name:swe_x_preferred":[
        "Funabashi"
    ],
    "name:tgk_x_preferred":[
        "\u0424\u0443\u043d\u0430\u0431\u0430\u0448\u0438"
    ],
    "name:tgl_x_preferred":[
        "Funabashi"
    ],
    "name:tha_x_preferred":[
        "\u0e1f\u0e39\u0e19\u0e32\u0e1a\u0e32\u0e0a\u0e34"
    ],
    "name:tum_x_preferred":[
        "Funabashi"
    ],
    "name:tur_x_preferred":[
        "Funabashi"
    ],
    "name:ukr_x_preferred":[
        "\u0424\u0443\u043d\u0430\u0431\u0430\u0441\u0456"
    ],
    "name:urd_x_preferred":[
        "\u0641\u0648\u0646\u0627\u0628\u0627\u0634\u06cc"
    ],
    "name:vie_x_preferred":[
        "Funabashi"
    ],
    "name:war_x_preferred":[
        "Funabashi"
    ],
    "name:zho_x_preferred":[
        "\u8239\u6a4b\u5e02"
    ],
    "wof:name":"Funabashi",
    "wof:placetype":"locality"
},
  "geometry": {"coordinates":[139.86977999999999,35.247],"type":"Point"}
}