{
  "type": "Feature",
  "properties": {
    "gn:admin1_code":"24.0",
    "gn:admin2_code":"2112574.0",
    "gn:asciiname":"Kyubunhama",
    "gn:country_code":"JP",
    "gn:dem":14,
    "gn:feature_class":"P",
    "gn:feature_code":"PPL",
    "gn:name":"Ky\u016bbunhama",
    "gn:population":0,
    "gn:timezone":"Asia/Tokyo",
    "iso:country":"JP",
    "name:jpn_x_preferred":[
        "\u7d66\u5206\u6d5c"
    ],
    "name:jpn_x_variant":[
        "\u304d\u3085\u3046\u3076\u3093\u306f\u307e",
        "\u30ad\u30e5\u30a6\u30d6\u30f3\u30cf\u30de"
    ],
    "name:und_x_variant":[
        "Ky\u016bbunhama"
    ],
    "wof:name":"Kyubunhama",
    "wof:placetype":"locality"
},
  "geometry": {"coordinates":[141.47496000000001,38.32706],"type":"Point"}
}