{
  "type": "Feature",
  "properties": {
    "gn:admin1_code":"21.0",
    "gn:admin2_code":"1848441.0",
    "gn:asciiname":"Sakayorikami",
    "gn:country_code":"JP",
    "gn:dem":332,
    "gn:feature_class":"P",
    "gn:feature_code":"PPL",
    "gn:name":"Sakayorikami",
    "gn:population":0,
    "gn:timezone":"Asia/Tokyo",
    "iso:country":"JP",
    "name:jpn_x_preferred":[
        "\u5742\u3088\u308a\u4e0a"
    ],
    "name:jpn_x_variant":[
        "\u3055\u304b\u3088\u308a\u304b\u307f",
        "\u30b5\u30ab\u30e8\u30ea\u30ab\u30df"
    ],
    "wof:name":"Sakayorikami",
    "wof:placetype":"locality"
},
  "geometry": {"coordinates":[130.75908000000001,32.49844],"type":"Point"}
}