{
  "type": "Feature",
  "properties": {
    "gn:admin1_code":"21.0",
    "gn:admin2_code":"7413151.0",
    "gn:asciiname":"Konoshigaura",
    "gn:country_code":"JP",
    "gn:dem":-1,
    "gn:feature_class":"P",
    "gn:feature_code":"PPLL",
    "gn:name":"Konoshigaura",
    "gn:population":0,
    "gn:timezone":"Asia/Tokyo",
    "iso:country":"JP",
    "name:jpn_x_preferred":[
        "\u9b97\u30b1\u6d66"
    ],
    "name:jpn_x_variant":[
        "\u3053\u306e\u3057\u304c\u3046\u3089",
        "\u30b3\u30ce\u30b7\u30ac\u30a6\u30e9"
    ],
    "wof:name":"Konoshigaura",
    "wof:placetype":"locality"
},
  "geometry": {"coordinates":[130.42737,32.55052],"type":"Point"}
}