{
  "type": "Feature",
  "properties": {
    "iso:country":"JP",
    "name:eng_x_preferred":[
        "Minato 5 Chome"
    ],
    "name:eng_x_variant":[
        "Minato 5 Choume",
        "Minato 5 Chome"
    ],
    "name:jpn_x_preferred":[
        "\uff15\u4e01\u76ee"
    ],
    "name:jpn_x_variant":[
        "\u307f\u306a\u3068 \uff15\u3061\u3087\u3046\u3081",
        "\u6e4a \uff15\u4e01\u76ee",
        "\uff15\u3061\u3087\u3046\u3081"
    ],
    "name:unk_x_variant":[
        "\uff15\u4e01\u76ee"
    ],
    "qs:gn_local":0,
    "qs:local_max":170,
    "qs:local_sum":447,
    "qs:localhoods":4,
    "qs:name":"\uff15\u4e01\u76ee",
    "qs:name_adm0":"\u65e5\u672c",
    "qs:name_adm1":"\u9577\u91ce\u770c",
    "qs:name_en":"Minato 5 Chome",
    "qs:name_lau":"\u6e4a",
    "qs:name_local":"\u5ca1\u8c37\u5e02",
    "qs:photo_max":57,
    "qs:photo_sum":168,
    "qs:placetype":"Suburb",
    "qs:quad_count":11,
    "qs:woe_adm0":23424856,
    "qs:woe_adm1":2345875,
    "qs:woe_adm2":0,
    "qs:woe_lau":28431745,
    "qs:woe_local":1113450,
    "qs:woe_ver":"7.10.0",
    "wof:lang":[
        "jpn"
    ],
    "wof:name":"\uff15\u4e01\u76ee",
    "wof:placetype":"neighbourhood"
},
  "geometry": {"coordinates":[138.077496,36.026334],"type":"Point"}
}