{
  "type": "Feature",
  "properties": {
    "gn:admin1_code":"21.0",
    "gn:admin2_code":"1864975.0",
    "gn:admin3_code":"43432.0",
    "gn:asciiname":"Keshozuka",
    "gn:country_code":"JP",
    "gn:dem":167,
    "gn:feature_class":"P",
    "gn:feature_code":"PPLL",
    "gn:name":"Kesh\u014dzuka",
    "gn:population":0,
    "gn:timezone":"Asia/Tokyo",
    "iso:country":"JP",
    "name:jpn_x_preferred":[
        "\u5316\u7ca7\u585a"
    ],
    "name:jpn_x_variant":[
        "\u3051\u3057\u3087\u3046\u3065\u304b",
        "\u30b1\u30b7\u30e7\u30a6\u30c5\u30ab"
    ],
    "name:und_x_variant":[
        "Kesh\u014dzuka"
    ],
    "wof:name":"Keshozuka",
    "wof:placetype":"locality"
},
  "geometry": {"coordinates":[130.88695000000001,32.82975],"type":"Point"}
}