{
  "type": "Feature",
  "properties": {
    "gn:admin1_code":"3.0",
    "gn:admin2_code":"2128302.0",
    "gn:admin3_code":"2445.0",
    "gn:asciiname":"Tai",
    "gn:country_code":"JP",
    "gn:dem":53,
    "gn:feature_class":"P",
    "gn:feature_code":"PPL",
    "gn:name":"Tai",
    "gn:population":0,
    "gn:timezone":"Asia/Tokyo",
    "iso:country":"JP",
    "name:cat_x_preferred":[
        "Tai"
    ],
    "name:ceb_x_preferred":[
        "Tai"
    ],
    "name:fin_x_preferred":[
        "Tai"
    ],
    "name:fur_x_preferred":[
        "Tai"
    ],
    "name:jpn_x_preferred":[
        "\u5e73"
    ],
    "name:jpn_x_variant":[
        "\u305f\u3044",
        "\u30bf\u30a4"
    ],
    "name:kor_x_preferred":[
        "\ud0c0\uc774"
    ],
    "name:oci_x_preferred":[
        "Tai"
    ],
    "name:rus_x_preferred":[
        "\u0422\u0430\u0439"
    ],
    "name:spa_x_preferred":[
        "Tai"
    ],
    "name:swe_x_preferred":[
        "Tai"
    ],
    "name:tur_x_preferred":[
        "Tai"
    ],
    "name:ukr_x_preferred":[
        "\u0422\u0430\u0439"
    ],
    "wof:name":"Tai",
    "wof:placetype":"locality"
},
  "geometry": {"coordinates":[141.40316999999999,40.46205],"type":"Point"}
}