{
  "type": "Feature",
  "properties": {
    "gn:admin1_code":"46",
    "gn:admin2_code":"1859096.0",
    "gn:asciiname":"Ubaguchi",
    "gn:cc2":"JP",
    "gn:country_code":"JP",
    "gn:dem":434,
    "gn:feature_class":"P",
    "gn:feature_code":"PPL",
    "gn:name":"Ubaguchi",
    "gn:population":0,
    "gn:timezone":"Asia/Tokyo",
    "iso:country":"JP",
    "name:und_x_variant":[
        "Ubakuchi",
        "Ubaguchi"
    ],
    "wof:name":"Ubaguchi",
    "wof:placetype":"locality"
},
  "geometry": {"coordinates":[138.59999999999999,35.56667],"type":"Point"}
}