{
  "type": "Feature",
  "properties": {
    "gn:admin1_code":"21.0",
    "gn:admin2_code":"1865168.0",
    "gn:asciiname":"Myoken",
    "gn:country_code":"JP",
    "gn:dem":12,
    "gn:feature_class":"P",
    "gn:feature_code":"PPLL",
    "gn:name":"My\u014dken",
    "gn:population":0,
    "gn:timezone":"Asia/Tokyo",
    "iso:country":"JP",
    "name:jpn_x_preferred":[
        "\u5999\u898b"
    ],
    "name:jpn_x_variant":[
        "\u307f\u3087\u3046\u3051\u3093",
        "\u30df\u30e7\u30a6\u30b1\u30f3"
    ],
    "name:und_x_variant":[
        "My\u014dken"
    ],
    "wof:name":"Myoken",
    "wof:placetype":"locality"
},
  "geometry": {"coordinates":[130.44669999999999,33.0022],"type":"Point"}
}