{
  "type": "Feature",
  "properties": {
    "gn:admin1_code":"6.0",
    "gn:admin2_code":"1859762.0",
    "gn:asciiname":"Kitadanicho-tani",
    "gn:country_code":"JP",
    "gn:dem":456,
    "gn:feature_class":"P",
    "gn:feature_code":"PPL",
    "gn:name":"Kitadanich\u014d-tani",
    "gn:population":0,
    "gn:timezone":"Asia/Tokyo",
    "iso:country":"JP",
    "name:jpn_x_preferred":[
        "\u5317\u8c37\u753a\u8c37"
    ],
    "name:und_x_variant":[
        "Kitadanich\u014d-tani"
    ],
    "wof:name":"Kitadanicho-tani",
    "wof:placetype":"locality"
},
  "geometry": {"coordinates":[136.56896,36.11549],"type":"Point"}
}