{
  "type": "Feature",
  "properties": {
    "gn:admin1_code":"47.0",
    "gn:admin2_code":"1856061.0",
    "gn:asciiname":"Buma",
    "gn:country_code":"JP",
    "gn:dem":11,
    "gn:feature_class":"P",
    "gn:feature_code":"PPL",
    "gn:name":"Buma",
    "gn:population":0,
    "gn:timezone":"Asia/Tokyo",
    "iso:country":"JP",
    "name:ceb_x_preferred":[
        "Buma"
    ],
    "name:jpn_x_preferred":[
        "\u90e8\u9593"
    ],
    "name:nld_x_preferred":[
        "Buma"
    ],
    "name:swe_x_preferred":[
        "Buma"
    ],
    "wof:name":"Buma",
    "wof:placetype":"locality"
},
  "geometry": {"coordinates":[127.90145,26.60609],"type":"Point"}
}