{
  "type": "Feature",
  "properties": {
    "gn:admin1_code":"21.0",
    "gn:admin2_code":"1864975.0",
    "gn:admin3_code":"43428.0",
    "gn:asciiname":"Fuyuno",
    "gn:country_code":"JP",
    "gn:dem":544,
    "gn:feature_class":"P",
    "gn:feature_code":"PPLL",
    "gn:name":"Fuyuno",
    "gn:population":0,
    "gn:timezone":"Asia/Tokyo",
    "iso:country":"JP",
    "name:jpn_x_preferred":[
        "\u51ac\u91ce"
    ],
    "name:jpn_x_variant":[
        "\u3075\u3086\u306e",
        "\u30d5\u30e6\u30ce"
    ],
    "wof:name":"Fuyuno",
    "wof:placetype":"locality"
},
  "geometry": {"coordinates":[131.12429,32.81119],"type":"Point"}
}