{
  "type": "Feature",
  "properties": {
    "gn:admin1_code":"13",
    "gn:admin2_code":"7370809.0",
    "gn:admin3_code":"28585.0",
    "gn:asciiname":"Fukuoka",
    "gn:country_code":"JP",
    "gn:dem":330,
    "gn:feature_class":"P",
    "gn:feature_code":"PPL",
    "gn:name":"Fukuoka",
    "gn:population":0,
    "gn:timezone":"Asia/Tokyo",
    "iso:country":"JP",
    "wof:name":"Fukuoka",
    "wof:placetype":"locality"
},
  "geometry": {"coordinates":[134.59999999999999,35.41667],"type":"Point"}
}