{
  "type": "Feature",
  "properties": {
    "gn:admin1_code":"43.0",
    "gn:admin2_code":"7411113.0",
    "gn:asciiname":"Nakajima",
    "gn:country_code":"JP",
    "gn:dem":14,
    "gn:feature_class":"P",
    "gn:feature_code":"PPL",
    "gn:name":"Nakajima",
    "gn:population":0,
    "gn:timezone":"Asia/Tokyo",
    "iso:country":"JP",
    "name:jpn_x_preferred":[
        "\u4e2d\u5cf6"
    ],
    "wof:name":"Nakajima",
    "wof:placetype":"locality"
},
  "geometry": {"coordinates":[135.28179,34.26149],"type":"Point"}
}