{
  "type": "Feature",
  "properties": {
    "gn:admin1_code":"43.0",
    "gn:admin2_code":"7411113.0",
    "gn:asciiname":"Nakajima",
    "gn:country_code":"JP",
    "gn:dem":14,
    "gn:feature_class":"P",
    "gn:feature_code":"PPL",
    "gn:name":"Nakajima",
    "gn:population":0,
    "gn:timezone":"Asia/Tokyo",
    "iso:country":"JP",
    "name:deu_x_preferred":[
        "Nakajima"
    ],
    "name:fra_x_preferred":[
        "Nakajima"
    ],
    "name:ita_x_preferred":[
        "Nakajima"
    ],
    "name:jpn_x_preferred":[
        "\u4e2d\u5cf6"
    ],
    "name:lav_x_preferred":[
        "Nakad\u017eima"
    ],
    "name:pol_x_preferred":[
        "Nakajima"
    ],
    "name:por_x_preferred":[
        "Nakajima"
    ],
    "name:rus_x_preferred":[
        "\u041d\u0430\u043a\u0430\u0434\u0437\u0438\u043c\u0430"
    ],
    "name:spa_x_preferred":[
        "Nakajima"
    ],
    "wof:name":"Nakajima",
    "wof:placetype":"locality"
},
  "geometry": {"coordinates":[135.28179,34.26149],"type":"Point"}
}