{
  "type": "Feature",
  "properties": {
    "gn:admin1_code":"45",
    "gn:admin2_code":"1861209.0",
    "gn:asciiname":"Mikawamachi-naguwa",
    "gn:country_code":"JP",
    "gn:dem":173,
    "gn:feature_class":"P",
    "gn:feature_code":"PPL",
    "gn:name":"Mikawamachi-naguwa",
    "gn:population":0,
    "gn:timezone":"Asia/Tokyo",
    "iso:country":"JP",
    "name:jpn_x_preferred":[
        "\u7f8e\u5ddd\u753a\u5357\u6851"
    ],
    "name:und_x_variant":[
        "Naguwa"
    ],
    "wof:name":"Mikawamachi-naguwa",
    "wof:placetype":"locality"
},
  "geometry": {"coordinates":[132.02266,34.21269],"type":"Point"}
}