{
  "type": "Feature",
  "properties": {
    "gn:admin1_code":"28.0",
    "gn:admin2_code":"7412212.0",
    "gn:asciiname":"Todachi",
    "gn:country_code":"JP",
    "gn:dem":433,
    "gn:feature_class":"P",
    "gn:feature_code":"PPL",
    "gn:name":"T\u014ddachi",
    "gn:population":0,
    "gn:timezone":"Asia/Tokyo",
    "iso:country":"JP",
    "name:jpn_x_preferred":[
        "\u7389\u7acb"
    ],
    "name:und_x_variant":[
        "T\u014ddachi"
    ],
    "wof:name":"Todachi",
    "wof:placetype":"locality"
},
  "geometry": {"coordinates":[135.95552000000001,34.54855999999999],"type":"Point"}
}