{
  "type": "Feature",
  "properties": {
    "gn:admin1_code":"4.0",
    "gn:admin2_code":"1861964.0",
    "gn:asciiname":"Minamiono",
    "gn:country_code":"JP",
    "gn:dem":9,
    "gn:feature_class":"P",
    "gn:feature_code":"PPL",
    "gn:name":"Minami\u014dno",
    "gn:population":0,
    "gn:timezone":"Asia/Tokyo",
    "iso:country":"JP",
    "name:jpn_x_preferred":[
        "\u5357\u5927\u91ce"
    ],
    "name:und_x_variant":[
        "Minami\u014dno"
    ],
    "wof:name":"Minamiono",
    "wof:placetype":"locality"
},
  "geometry": {"coordinates":[139.95448000000002,35.74351],"type":"Point"}
}