{
  "type": "Feature",
  "properties": {
    "gn:admin1_code":"42.0",
    "gn:admin2_code":"1862610.0",
    "gn:asciiname":"Nakao",
    "gn:country_code":"JP",
    "gn:dem":10,
    "gn:feature_class":"P",
    "gn:feature_code":"PPL",
    "gn:name":"Nakao",
    "gn:population":0,
    "gn:timezone":"Asia/Tokyo",
    "iso:country":"JP",
    "name:fra_x_preferred":[
        "Nakao"
    ],
    "name:jpn_x_preferred":[
        "\u4e2d\u5c3e"
    ],
    "name:kor_x_preferred":[
        "\ub098\uce74\uc624"
    ],
    "wof:name":"Nakao",
    "wof:placetype":"locality"
},
  "geometry": {"coordinates":[136.94963999999999,36.85285],"type":"Point"}
}