{
  "type": "Feature",
  "properties": {
    "gn:admin1_code":"21.0",
    "gn:admin2_code":"1865358.0",
    "gn:asciiname":"Matsuo",
    "gn:country_code":"JP",
    "gn:dem":22,
    "gn:feature_class":"P",
    "gn:feature_code":"PPLL",
    "gn:name":"Matsuo",
    "gn:population":0,
    "gn:timezone":"Asia/Tokyo",
    "iso:country":"JP",
    "name:deu_x_preferred":[
        "Matsuo"
    ],
    "name:jpn_x_preferred":[
        "\u677e\u5c3e"
    ],
    "name:jpn_x_variant":[
        "\u307e\u3064\u304a",
        "\u30de\u30c4\u30aa"
    ],
    "name:kor_x_preferred":[
        "\ub9c8\uc4f0\uc624"
    ],
    "wof:name":"Matsuo",
    "wof:placetype":"locality"
},
  "geometry": {"coordinates":[130.27071000000001,32.42281],"type":"Point"}
}