{
  "type": "Feature",
  "properties": {
    "iso:country":"JP",
    "name:eng_x_preferred":[
        "Nonakaminami 1 Chome"
    ],
    "name:eng_x_variant":[
        "Nonakaminami 1 Choume",
        "Nonakaminami 1 Chome"
    ],
    "name:jpn_x_preferred":[
        "\uff11\u4e01\u76ee"
    ],
    "name:jpn_x_variant":[
        "\u306e\u306a\u304b\u307f\u306a\u307f \uff11\u3061\u3087\u3046\u3081",
        "\u91ce\u4e2d\u5357 \uff11\u4e01\u76ee",
        "\uff11\u3061\u3087\u3046\u3081"
    ],
    "qs:gn_local":0,
    "qs:local_max":5466,
    "qs:local_sum":82256,
    "qs:localhoods":141,
    "qs:name":"\uff11\u4e01\u76ee",
    "qs:name_adm0":"\u65e5\u672c",
    "qs:name_adm1":"\u5927\u962a\u5e9c",
    "qs:name_adm2":"\u6dc0\u5ddd\u533a",
    "qs:name_en":"Nonakaminami 1 Chome",
    "qs:name_lau":"\u91ce\u4e2d\u5357",
    "qs:name_local":"\u5927\u962a\u5e02",
    "qs:photo_max":7,
    "qs:photo_sum":7,
    "qs:placetype":"Suburb",
    "qs:quad_count":1,
    "qs:woe_adm0":23424856,
    "qs:woe_adm1":2345881,
    "qs:woe_adm2":1118623,
    "qs:woe_lau":28457478,
    "qs:woe_local":15015370,
    "qs:woe_ver":"7.10.0",
    "wof:lang":[
        "jpn"
    ],
    "wof:name":"\uff11\u4e01\u76ee",
    "wof:placetype":"neighbourhood"
},
  "geometry": {"coordinates":[135.47515899999999,34.730328],"type":"Point"}
}