{
  "type": "Feature",
  "properties": {
    "iso:country":"JP",
    "name:jpn_x_preferred":[
        "\uff08\u4e01\u76ee\u306a\u3057\uff09"
    ],
    "name:unk_x_variant":[
        "\uff08\u4e01\u76ee\u306a\u3057\uff09"
    ],
    "qs:gn_local":0,
    "qs:local_max":36,
    "qs:local_sum":93,
    "qs:localhoods":3,
    "qs:name":"\uff08\u4e01\u76ee\u306a\u3057\uff09",
    "qs:name_adm0":"\u65e5\u672c",
    "qs:name_adm1":"\u6ecb\u8cc0\u770c",
    "qs:name_lau":"\u65b0\u65ed\u753a\u5317\u7551",
    "qs:name_local":"\u9ad8\u5cf6\u5e02",
    "qs:photo_max":26,
    "qs:photo_sum":28,
    "qs:placetype":"Suburb",
    "qs:quad_count":2,
    "qs:woe_adm0":23424856,
    "qs:woe_adm1":2345884,
    "qs:woe_adm2":0,
    "qs:woe_lau":28449065,
    "qs:woe_local":28379368,
    "qs:woe_ver":"7.10.0",
    "wof:lang":[
        "jpn"
    ],
    "wof:name":"\uff08\u4e01\u76ee\u306a\u3057\uff09",
    "wof:placetype":"neighbourhood"
},
  "geometry": {"coordinates":[136.06724600000001,35.350655],"type":"Point"}
}