{
  "type": "Feature",
  "properties": {
    "gn:admin1_code":"09",
    "gn:admin2_code":"7419032.0",
    "gn:asciiname":"Kamiokacho-yamada",
    "gn:country_code":"JP",
    "gn:dem":680,
    "gn:feature_class":"P",
    "gn:feature_code":"PPL",
    "gn:name":"Kamiokach\u014d-yamada",
    "gn:population":0,
    "gn:timezone":"Asia/Tokyo",
    "iso:country":"JP",
    "name:jpn_x_preferred":[
        "\u795e\u5ca1\u753a\u5c71\u7530"
    ],
    "name:und_x_variant":[
        "Kamiokach\u014d-yamada",
        "Yamada"
    ],
    "wof:name":"Kamiokacho-yamada",
    "wof:placetype":"locality"
},
  "geometry": {"coordinates":[137.25402,36.29543],"type":"Point"}
}