{
  "type": "Feature",
  "properties": {
    "gn:admin1_code":"19",
    "gn:admin2_code":"1859635.0",
    "gn:admin3_code":"14131.0",
    "gn:asciiname":"Minami-wataridacho",
    "gn:country_code":"JP",
    "gn:dem":3,
    "gn:feature_class":"P",
    "gn:feature_code":"PPL",
    "gn:name":"Minami-wataridach\u014d",
    "gn:population":0,
    "gn:timezone":"Asia/Tokyo",
    "iso:country":"JP",
    "name:jpn_x_preferred":[
        "\u5357\u6e21\u7530\u753a"
    ],
    "name:und_x_variant":[
        "Nishiborich\u014d",
        "Minami-watarida",
        "Minami-Waterida",
        "Minami-wataridach\u014d"
    ],
    "wof:name":"Minami-wataridacho",
    "wof:placetype":"locality"
},
  "geometry": {"coordinates":[139.71733999999998,35.50959],"type":"Point"}
}