{
  "type": "Feature",
  "properties": {
    "iso:country":"JP",
    "qs:name":"\u845b\u57ce\u5e02",
    "qs:name_adm0":"\u65e5\u672c",
    "qs:name_adm1":"\u5948\u826f\u770c",
    "qs:photos":120,
    "qs:photos_1k":24,
    "qs:photos_9k":1,
    "qs:photos_9r":3,
    "qs:photos_all":120,
    "qs:photos_sr":3,
    "qs:placetype":"Town",
    "qs:pop_sr":"0",
    "wof:name":"\u845b\u57ce\u5e02",
    "wof:placetype":"locality"
},
  "geometry": {"coordinates":[135.71199999999999,34.485],"type":"Point"}
}