{
  "type": "Feature",
  "properties": {
    "gn:admin1_code":"7.0",
    "gn:admin2_code":"1864574.0",
    "gn:admin3_code":"40305.0",
    "gn:asciiname":"Goromaru",
    "gn:country_code":"JP",
    "gn:dem":22,
    "gn:feature_class":"P",
    "gn:feature_code":"PPL",
    "gn:name":"Gor\u014dmaru",
    "gn:population":0,
    "gn:timezone":"Asia/Tokyo",
    "iso:country":"JP",
    "name:jpn_x_preferred":[
        "\u4e94\u90ce\u4e38"
    ],
    "name:und_x_variant":[
        "Gor\u014dmaru"
    ],
    "wof:name":"Goromaru",
    "wof:placetype":"locality"
},
  "geometry": {"coordinates":[130.42743000000002,33.51065999999999],"type":"Point"}
}