{
  "type": "Feature",
  "properties": {
    "gn:admin1_code":"26",
    "gn:admin2_code":"1853055.0",
    "gn:asciiname":"Nakagomi",
    "gn:country_code":"JP",
    "gn:dem":665,
    "gn:feature_class":"P",
    "gn:feature_code":"PPL",
    "gn:name":"Nakagomi",
    "gn:population":0,
    "gn:timezone":"Asia/Tokyo",
    "iso:country":"JP",
    "name:jpn_x_preferred":[
        "\u4e2d\u8fbc"
    ],
    "name:und_x_variant":[
        "Nakagome",
        "Nakagomi"
    ],
    "wof:name":"Nakagomi",
    "wof:placetype":"locality"
},
  "geometry": {"coordinates":[138.46931000000001,36.23792],"type":"Point"}
}