{
  "type": "Feature",
  "properties": {
    "gn:admin1_code":"4.0",
    "gn:admin2_code":"1859468.0",
    "gn:asciiname":"Sotominowa",
    "gn:country_code":"JP",
    "gn:dem":16,
    "gn:feature_class":"P",
    "gn:feature_code":"PPL",
    "gn:name":"Sotominowa",
    "gn:population":0,
    "gn:timezone":"Asia/Tokyo",
    "iso:country":"JP",
    "name:jpn_x_preferred":[
        "\u5916\u7b95\u8f2a"
    ],
    "name:jpn_x_variant":[
        "\u305d\u3068\u307f\u306e\u308f",
        "\u30bd\u30c8\u30df\u30ce\u30ef"
    ],
    "wof:name":"Sotominowa",
    "wof:placetype":"locality"
},
  "geometry": {"coordinates":[139.92401999999998,35.31668],"type":"Point"}
}