{
  "type": "Feature",
  "properties": {
    "gn:admin1_code":"19.0",
    "gn:admin2_code":"1848350.0",
    "gn:admin3_code":"14117.0",
    "gn:asciiname":"Tanacho",
    "gn:country_code":"JP",
    "gn:dem":35,
    "gn:feature_class":"P",
    "gn:feature_code":"PPL",
    "gn:name":"Tanach\u014d",
    "gn:population":0,
    "gn:timezone":"Asia/Tokyo",
    "iso:country":"JP",
    "name:jpn_x_preferred":[
        "\u7530\u5948\u753a"
    ],
    "name:und_x_variant":[
        "Tanach\u014d"
    ],
    "wof:name":"Tanacho",
    "wof:placetype":"locality"
},
  "geometry": {"coordinates":[139.50547,35.53856],"type":"Point"}
}