{
  "type": "Feature",
  "properties": {
    "gn:admin1_code":"17.0",
    "gn:admin2_code":"1856906.0",
    "gn:asciiname":"Takumacho-namari",
    "gn:country_code":"JP",
    "gn:dem":8,
    "gn:feature_class":"P",
    "gn:feature_code":"PPL",
    "gn:name":"Takumach\u014d-namari",
    "gn:population":0,
    "gn:timezone":"Asia/Tokyo",
    "iso:country":"JP",
    "name:jpn_x_preferred":[
        "\u8a6b\u9593\u753a\u751f\u91cc"
    ],
    "name:und_x_variant":[
        "Takumach\u014d-namari",
        "Namari"
    ],
    "wof:name":"Takumacho-namari",
    "wof:placetype":"locality"
},
  "geometry": {"coordinates":[133.58122,34.25153],"type":"Point"}
}