{
  "type": "Feature",
  "properties": {
    "gn:admin1_code":"7.0",
    "gn:admin2_code":"1854055.0",
    "gn:admin3_code":"40383.0",
    "gn:asciiname":"Oishi",
    "gn:country_code":"JP",
    "gn:dem":57,
    "gn:feature_class":"P",
    "gn:feature_code":"PPLL",
    "gn:name":"Oishi",
    "gn:population":0,
    "gn:timezone":"Asia/Tokyo",
    "iso:country":"JP",
    "name:deu_x_preferred":[
        "\u014cishi"
    ],
    "name:ita_x_preferred":[
        "Oishi"
    ],
    "name:jpn_x_preferred":[
        "\u7537\u77f3"
    ],
    "name:por_x_preferred":[
        "Oishi"
    ],
    "wof:name":"Oishi",
    "wof:placetype":"locality"
},
  "geometry": {"coordinates":[130.63439,33.83741],"type":"Point"}
}