{
  "type": "Feature",
  "properties": {
    "gn:admin1_code":"29",
    "gn:admin2_code":"1853313.0",
    "gn:asciiname":"Haniu",
    "gn:country_code":"JP",
    "gn:dem":25,
    "gn:feature_class":"P",
    "gn:feature_code":"PPL",
    "gn:name":"Haniu",
    "gn:population":0,
    "gn:timezone":"Asia/Tokyo",
    "iso:country":"JP",
    "name:jpn_x_preferred":[
        "\u7fbd\u4e8c\u751f"
    ],
    "name:und_x_variant":[
        "Sawane",
        "Hany\u016b",
        "Haniu"
    ],
    "wof:name":"Haniu",
    "wof:placetype":"locality"
},
  "geometry": {"coordinates":[138.26656,37.9933],"type":"Point"}
}