{
  "type": "Feature",
  "properties": {
    "gn:admin1_code":"27.0",
    "gn:admin2_code":"1862734.0",
    "gn:admin3_code":"42323.0",
    "gn:asciiname":"Onikigo",
    "gn:country_code":"JP",
    "gn:dem":165,
    "gn:feature_class":"P",
    "gn:feature_code":"PPL",
    "gn:name":"Onikig\u014d",
    "gn:population":0,
    "gn:timezone":"Asia/Tokyo",
    "iso:country":"JP",
    "name:jpn_x_preferred":[
        "\u9b3c\u6728\u90f7"
    ],
    "name:und_x_variant":[
        "Onikig\u014d"
    ],
    "wof:name":"Onikigo",
    "wof:placetype":"locality"
},
  "geometry": {"coordinates":[129.9204,33.11853],"type":"Point"}
}