{
  "type": "Feature",
  "properties": {
    "gn:admin1_code":"13.0",
    "gn:admin2_code":"7370813.0",
    "gn:asciiname":"Tsutsujigaoka-kita",
    "gn:country_code":"JP",
    "gn:dem":192,
    "gn:feature_class":"P",
    "gn:feature_code":"PPL",
    "gn:name":"Tsutsujigaoka-kita",
    "gn:population":0,
    "gn:timezone":"Asia/Tokyo",
    "iso:country":"JP",
    "name:jpn_x_preferred":[
        "\u3064\u3064\u3058\u304c\u4e18\u5317"
    ],
    "wof:name":"Tsutsujigaoka-kita",
    "wof:placetype":"locality"
},
  "geometry": {"coordinates":[135.12968000000001,34.94828],"type":"Point"}
}