{
  "type": "Feature",
  "properties": {
    "gn:admin1_code":"3.0",
    "gn:admin2_code":"2130200.0",
    "gn:asciiname":"Sawasatoyama",
    "gn:country_code":"JP",
    "gn:dem":85,
    "gn:feature_class":"P",
    "gn:feature_code":"PPL",
    "gn:name":"Sawasatoyama",
    "gn:population":0,
    "gn:timezone":"Asia/Tokyo",
    "iso:country":"JP",
    "name:jpn_x_preferred":[
        "\u6ca2\u91cc\u5c71"
    ],
    "name:jpn_x_variant":[
        "\u3055\u308f\u3055\u3068\u3084\u307e",
        "\u30b5\u30ef\u30b5\u30c8\u30e4\u30de"
    ],
    "wof:name":"Sawasatoyama",
    "wof:placetype":"locality"
},
  "geometry": {"coordinates":[141.47717,40.49241],"type":"Point"}
}