{
  "type": "Feature",
  "properties": {
    "gn:admin1_code":"26.0",
    "gn:admin2_code":"1852001.0",
    "gn:asciiname":"Nagasaki",
    "gn:country_code":"JP",
    "gn:dem":785,
    "gn:feature_class":"P",
    "gn:feature_code":"PPL",
    "gn:name":"Nagasaki",
    "gn:population":0,
    "gn:timezone":"Asia/Tokyo",
    "iso:country":"JP",
    "name:jpn_x_preferred":[
        "\u9577\u5d0e"
    ],
    "wof:name":"Nagasaki",
    "wof:placetype":"locality"
},
  "geometry": {"coordinates":[137.8948,36.10716],"type":"Point"}
}