{
  "type": "Feature",
  "properties": {
    "gn:admin1_code":"18.0",
    "gn:admin2_code":"1862007.0",
    "gn:asciiname":"Daito",
    "gn:country_code":"JP",
    "gn:dem":17,
    "gn:feature_class":"P",
    "gn:feature_code":"PPLL",
    "gn:name":"Dait\u014d",
    "gn:population":0,
    "gn:timezone":"Asia/Tokyo",
    "iso:country":"JP",
    "name:jpn_x_preferred":[
        "\u5927\u5f53"
    ],
    "name:und_x_variant":[
        "Dait\u014d"
    ],
    "wof:name":"Daito",
    "wof:placetype":"locality"
},
  "geometry": {"coordinates":[130.62088,31.27244],"type":"Point"}
}