{
  "type": "Feature",
  "properties": {
    "gn:admin1_code":"12.0",
    "gn:admin2_code":"7428097.0",
    "gn:admin3_code":"1643.0",
    "gn:asciiname":"Satsunai-higashimachi",
    "gn:country_code":"JP",
    "gn:dem":29,
    "gn:feature_class":"P",
    "gn:feature_code":"PPL",
    "gn:name":"Satsunai-higashimachi",
    "gn:population":0,
    "gn:timezone":"Asia/Tokyo",
    "iso:country":"JP",
    "name:jpn_x_preferred":[
        "\u672d\u5185\u6771\u753a"
    ],
    "name:jpn_x_variant":[
        "\u3055\u3064\u306a\u3044\u3072\u304c\u3057\u307e\u3061",
        "\u30b5\u30c4\u30ca\u30a4\u30d2\u30ac\u30b7\u30de\u30c1"
    ],
    "wof:name":"Satsunai-higashimachi",
    "wof:placetype":"locality"
},
  "geometry": {"coordinates":[143.26253,42.9248],"type":"Point"}
}