{
  "type": "Feature",
  "properties": {
    "gn:admin1_code":"19.0",
    "gn:admin2_code":"1848595.0",
    "gn:asciiname":"Maruyama",
    "gn:country_code":"JP",
    "gn:dem":71,
    "gn:feature_class":"P",
    "gn:feature_code":"PPLL",
    "gn:name":"Maruyama",
    "gn:population":0,
    "gn:timezone":"Asia/Tokyo",
    "iso:country":"JP",
    "name:deu_x_preferred":[
        "Maruyama"
    ],
    "name:fra_x_preferred":[
        "Maruyama"
    ],
    "name:jpn_x_preferred":[
        "\u4e38\u5c71"
    ],
    "name:rus_x_preferred":[
        "\u041c\u0430\u0440\u0443\u044f\u043c\u0430"
    ],
    "name:ukr_x_preferred":[
        "\u041c\u0430\u0440\u0443\u044f\u043c\u0430"
    ],
    "wof:name":"Maruyama",
    "wof:placetype":"locality"
},
  "geometry": {"coordinates":[139.44673999999998,35.47851],"type":"Point"}
}