{
  "type": "Feature",
  "properties": {
    "iso:country":"JP",
    "qs:name":"\u5317\u5869\u539f\u6751",
    "qs:name_adm0":"\u65e5\u672c",
    "qs:name_adm1":"\u798f\u5cf6\u770c",
    "qs:photos":669,
    "qs:photos_1k":136,
    "qs:photos_9k":3,
    "qs:photos_9r":5,
    "qs:photos_all":669,
    "qs:photos_sr":8,
    "qs:placetype":"Town",
    "qs:pop_sr":"0",
    "wof:name":"\u5317\u5869\u539f\u6751",
    "wof:placetype":"locality"
},
  "geometry": {"coordinates":[140.07605000000001,37.658275],"type":"Point"}
}