{
  "type": "Feature",
  "properties": {
    "gn:admin1_code":"19.0",
    "gn:admin2_code":"1848350.0",
    "gn:admin3_code":"14103.0",
    "gn:asciiname":"Momijigaoka",
    "gn:country_code":"JP",
    "gn:dem":13,
    "gn:feature_class":"P",
    "gn:feature_code":"PPL",
    "gn:name":"Momijigaoka",
    "gn:population":0,
    "gn:timezone":"Asia/Tokyo",
    "iso:country":"JP",
    "name:jpn_x_preferred":[
        "\u7d05\u8449\u30f6\u4e18"
    ],
    "name:jpn_x_variant":[
        "\u3082\u307f\u3058\u304c\u304a\u304b",
        "\u30e2\u30df\u30b8\u30ac\u30aa\u30ab"
    ],
    "wof:name":"Momijigaoka",
    "wof:placetype":"locality"
},
  "geometry": {"coordinates":[139.62427,35.45310999999999],"type":"Point"}
}