{
  "type": "Feature",
  "properties": {
    "gn:admin1_code":"3.0",
    "gn:admin2_code":"2129754.0",
    "gn:admin3_code":"2405.0",
    "gn:asciiname":"Kanaya",
    "gn:country_code":"JP",
    "gn:dem":45,
    "gn:feature_class":"P",
    "gn:feature_code":"PPL",
    "gn:name":"Kanaya",
    "gn:population":0,
    "gn:timezone":"Asia/Tokyo",
    "iso:country":"JP",
    "name:deu_x_preferred":[
        "Kanaya"
    ],
    "name:ita_x_preferred":[
        "Kanaya"
    ],
    "name:jpn_x_preferred":[
        "\u91d1\u77e2"
    ],
    "name:jpn_x_variant":[
        "\u304b\u306a\u3084",
        "\u30ab\u30ca\u30e4"
    ],
    "wof:name":"Kanaya",
    "wof:placetype":"locality"
},
  "geometry": {"coordinates":[141.31576999999999,40.67307],"type":"Point"}
}