{
  "type": "Feature",
  "properties": {
    "gn:admin1_code":"3.0",
    "gn:admin2_code":"2130225.0",
    "gn:asciiname":"Kanagicho-sawabe",
    "gn:country_code":"JP",
    "gn:dem":6,
    "gn:feature_class":"P",
    "gn:feature_code":"PPL",
    "gn:name":"Kanagich\u014d-sawabe",
    "gn:population":0,
    "gn:timezone":"Asia/Tokyo",
    "iso:country":"JP",
    "name:jpn_x_preferred":[
        "\u91d1\u6728\u753a\u6ca2\u90e8"
    ],
    "name:jpn_x_variant":[
        "\u304b\u306a\u304e\u3061\u3087\u3046\u3055\u308f\u3079",
        "\u30ab\u30ca\u30ae\u30c1\u30e7\u30a6\u30b5\u30ef\u30d9"
    ],
    "name:und_x_variant":[
        "Kanagich\u014d-sawabe"
    ],
    "wof:name":"Kanagicho-sawabe",
    "wof:placetype":"locality"
},
  "geometry": {"coordinates":[140.44257999999999,40.9076],"type":"Point"}
}