{
  "type": "Feature",
  "properties": {
    "gn:admin1_code":"35.0",
    "gn:admin2_code":"1858984.0",
    "gn:asciiname":"Konancho-koshi",
    "gn:country_code":"JP",
    "gn:dem":214,
    "gn:feature_class":"P",
    "gn:feature_code":"PPL",
    "gn:name":"K\u014dnanch\u014d-k\u014dshi",
    "gn:population":0,
    "gn:timezone":"Asia/Tokyo",
    "iso:country":"JP",
    "name:jpn_x_preferred":[
        "\u7532\u5357\u753a\u67d1\u5b50"
    ],
    "name:und_x_variant":[
        "K\u014dnanch\u014d-k\u014dshi"
    ],
    "wof:name":"Konancho-koshi",
    "wof:placetype":"locality"
},
  "geometry": {"coordinates":[136.1754,34.90047],"type":"Point"}
}