{
  "type": "Feature",
  "properties": {
    "gn:admin1_code":"06",
    "gn:admin2_code":"1854875.0",
    "gn:admin3_code":"18423.0",
    "gn:asciiname":"Ko-konogi",
    "gn:cc2":"JP",
    "gn:country_code":"JP",
    "gn:dem":5,
    "gn:feature_class":"P",
    "gn:feature_code":"PPL",
    "gn:name":"Ko-konogi",
    "gn:population":0,
    "gn:timezone":"Asia/Tokyo",
    "iso:country":"JP",
    "name:und_x_variant":[
        "Ko-kunugi",
        "Konogi"
    ],
    "wof:name":"Ko-konogi",
    "wof:placetype":"locality"
},
  "geometry": {"coordinates":[135.99229,35.94118],"type":"Point"}
}