{
  "type": "Feature",
  "properties": {
    "gn:admin1_code":"21.0",
    "gn:admin2_code":"7412706.0",
    "gn:admin3_code":"43447.0",
    "gn:asciiname":"Shiiya",
    "gn:country_code":"JP",
    "gn:dem":517,
    "gn:feature_class":"P",
    "gn:feature_code":"PPLL",
    "gn:name":"Shiiya",
    "gn:population":0,
    "gn:timezone":"Asia/Tokyo",
    "iso:country":"JP",
    "name:jpn_x_preferred":[
        "\u690e\u5c4b"
    ],
    "name:jpn_x_variant":[
        "\u3057\u3044\u3084",
        "\u30b7\u30a4\u30e4"
    ],
    "wof:name":"Shiiya",
    "wof:placetype":"locality"
},
  "geometry": {"coordinates":[131.21581,32.74735],"type":"Point"}
}