{
  "type": "Feature",
  "properties": {
    "iso:country":"JP",
    "name:eng_x_preferred":[
        "Tamagawa 3 Chome"
    ],
    "name:eng_x_variant":[
        "Tamagawa 3 Choume",
        "Tamagawa 3 Chome"
    ],
    "name:jpn_x_preferred":[
        "\uff13\u4e01\u76ee"
    ],
    "name:jpn_x_variant":[
        "\u305f\u307e\u304c\u308f \uff13\u3061\u3087\u3046\u3081",
        "\u591a\u6469\u5ddd \uff13\u4e01\u76ee",
        "\uff13\u3061\u3087\u3046\u3081"
    ],
    "qs:gn_local":0,
    "qs:local_max":1845,
    "qs:local_sum":7669,
    "qs:localhoods":21,
    "qs:name":"\uff13\u4e01\u76ee",
    "qs:name_adm0":"\u65e5\u672c",
    "qs:name_adm1":"\u6771\u4eac\u90fd",
    "qs:name_en":"Tamagawa 3 Chome",
    "qs:name_lau":"\u591a\u6469\u5ddd",
    "qs:name_local":"\u8abf\u5e03\u5e02",
    "qs:photo_max":43,
    "qs:photo_sum":66,
    "qs:placetype":"Suburb",
    "qs:quad_count":2,
    "qs:woe_adm0":23424856,
    "qs:woe_adm1":2345889,
    "qs:woe_adm2":0,
    "qs:woe_lau":28415059,
    "qs:woe_local":1107816,
    "qs:woe_ver":"7.10.0",
    "wof:lang":[
        "jpn"
    ],
    "wof:name":"\uff13\u4e01\u76ee",
    "wof:placetype":"neighbourhood"
},
  "geometry": {"coordinates":[139.53227200000001,35.642789],"type":"Point"}
}