{
  "type": "Feature",
  "properties": {
    "gn:admin1_code":"11",
    "gn:admin2_code":"1863914.0",
    "gn:asciiname":"Matsunagacho",
    "gn:country_code":"JP",
    "gn:dem":2,
    "gn:feature_class":"P",
    "gn:feature_code":"PPL",
    "gn:name":"Matsunagach\u014d",
    "gn:population":0,
    "gn:timezone":"Asia/Tokyo",
    "iso:country":"JP",
    "name:jpn_x_preferred":[
        "\u677e\u6c38\u753a"
    ],
    "name:und_x_variant":[
        "Matsunagach\u014d",
        "Matsunaga"
    ],
    "wof:name":"Matsunagacho",
    "wof:placetype":"locality"
},
  "geometry": {"coordinates":[133.25697,34.4468],"type":"Point"}
}