{
  "type": "Feature",
  "properties": {
    "gn:admin1_code":"40",
    "gn:admin2_code":"1853724.0",
    "gn:admin3_code":"13361.0",
    "gn:asciiname":"Okata",
    "gn:country_code":"JP",
    "gn:dem":46,
    "gn:feature_class":"P",
    "gn:feature_code":"PPL",
    "gn:name":"Okata",
    "gn:population":0,
    "gn:timezone":"Asia/Tokyo",
    "iso:country":"JP",
    "name:jpn_x_preferred":[
        "\u5ca1\u7530"
    ],
    "name:und_x_variant":[
        "Okada",
        "Okata"
    ],
    "wof:name":"Okata",
    "wof:placetype":"locality"
},
  "geometry": {"coordinates":[139.39263,34.78631],"type":"Point"}
}