{
  "type": "Feature",
  "properties": {
    "gn:admin1_code":"37.0",
    "gn:admin2_code":"9036693.0",
    "gn:asciiname":"Kodachino",
    "gn:country_code":"JP",
    "gn:dem":86,
    "gn:feature_class":"P",
    "gn:feature_code":"PPL",
    "gn:name":"Kodachino",
    "gn:population":0,
    "gn:timezone":"Asia/Tokyo",
    "iso:country":"JP",
    "name:jpn_x_preferred":[
        "\u5c0f\u7acb\u91ce"
    ],
    "wof:name":"Kodachino",
    "wof:placetype":"locality"
},
  "geometry": {"coordinates":[138.94466,34.97393],"type":"Point"}
}