{
  "type": "Feature",
  "properties": {
    "gn:admin1_code":"01",
    "gn:admin2_code":"1849809.0",
    "gn:asciiname":"Shimo-ibo",
    "gn:country_code":"JP",
    "gn:dem":66,
    "gn:feature_class":"P",
    "gn:feature_code":"PPL",
    "gn:name":"Shimo-ibo",
    "gn:population":0,
    "gn:timezone":"Asia/Tokyo",
    "iso:country":"JP",
    "wof:name":"Shimo-ibo",
    "wof:placetype":"locality"
},
  "geometry": {"coordinates":[137.15000000000001,35.13333],"type":"Point"}
}