{
  "type": "Feature",
  "properties": {
    "gn:admin1_code":"36",
    "gn:admin2_code":"1854361.0",
    "gn:admin3_code":"32528.0",
    "gn:asciiname":"Fuse",
    "gn:country_code":"JP",
    "gn:dem":0,
    "gn:feature_class":"P",
    "gn:feature_code":"PPL",
    "gn:name":"Fuse",
    "gn:population":0,
    "gn:timezone":"Asia/Tokyo",
    "iso:country":"JP",
    "name:jpn_x_preferred":[
        "\u5e03\u65bd"
    ],
    "wof:name":"Fuse",
    "wof:placetype":"locality"
},
  "geometry": {"coordinates":[133.35157000000001,36.29292],"type":"Point"}
}