{
  "type": "Feature",
  "properties": {
    "gn:admin1_code":"37.0",
    "gn:admin2_code":"1863526.0",
    "gn:asciiname":"Kazaana",
    "gn:country_code":"JP",
    "gn:dem":358,
    "gn:feature_class":"P",
    "gn:feature_code":"PPLL",
    "gn:name":"Kazaana",
    "gn:population":0,
    "gn:timezone":"Asia/Tokyo",
    "iso:country":"JP",
    "name:jpn_x_preferred":[
        "\u98a8\u7a74"
    ],
    "wof:name":"Kazaana",
    "wof:placetype":"locality"
},
  "geometry": {"coordinates":[138.91386,35.25182],"type":"Point"}
}