{
  "type": "Feature",
  "properties": {
    "gn:admin1_code":"21.0",
    "gn:admin2_code":"1858418.0",
    "gn:admin3_code":"43104.0",
    "gn:asciiname":"Ogori",
    "gn:country_code":"JP",
    "gn:dem":-3,
    "gn:feature_class":"P",
    "gn:feature_code":"PPLL",
    "gn:name":"Og\u014dri",
    "gn:population":0,
    "gn:timezone":"Asia/Tokyo",
    "iso:country":"JP",
    "name:jpn_x_preferred":[
        "\u5fa1\u90e1"
    ],
    "name:jpn_x_variant":[
        "\u304a\u3054\u304a\u308a",
        "\u30aa\u30b4\u30aa\u30ea"
    ],
    "name:und_x_variant":[
        "Og\u014dri"
    ],
    "wof:name":"Ogori",
    "wof:placetype":"locality"
},
  "geometry": {"coordinates":[130.61345,32.74334],"type":"Point"}
}