{
  "type": "Feature",
  "properties": {
    "gn:admin1_code":"21.0",
    "gn:admin2_code":"1850743.0",
    "gn:asciiname":"Aono",
    "gn:country_code":"JP",
    "gn:dem":45,
    "gn:feature_class":"P",
    "gn:feature_code":"PPL",
    "gn:name":"Aono",
    "gn:population":0,
    "gn:timezone":"Asia/Tokyo",
    "iso:country":"JP",
    "name:deu_x_preferred":[
        "Aono"
    ],
    "name:jpn_x_preferred":[
        "\u9752\u91ce"
    ],
    "name:jpn_x_variant":[
        "\u3042\u304a\u306e",
        "\u30a2\u30aa\u30ce"
    ],
    "name:kor_x_preferred":[
        "\uc544\uc624\ub178"
    ],
    "wof:name":"Aono",
    "wof:placetype":"locality"
},
  "geometry": {"coordinates":[130.59571,32.90494],"type":"Point"}
}