{
  "type": "Feature",
  "properties": {
    "gn:admin1_code":"10.0",
    "gn:admin2_code":"7453747.0",
    "gn:admin3_code":"10429.0",
    "gn:asciiname":"Takahinata",
    "gn:country_code":"JP",
    "gn:dem":744,
    "gn:feature_class":"P",
    "gn:feature_code":"PPLL",
    "gn:name":"Takahinata",
    "gn:population":0,
    "gn:timezone":"Asia/Tokyo",
    "iso:country":"JP",
    "name:jpn_x_preferred":[
        "\u9ad8\u65e5\u5411"
    ],
    "wof:name":"Takahinata",
    "wof:placetype":"locality"
},
  "geometry": {"coordinates":[138.71520000000001,36.58299],"type":"Point"}
}