{
  "type": "Feature",
  "properties": {
    "gn:admin1_code":"8.0",
    "gn:admin2_code":"7451488.0",
    "gn:admin3_code":"7541.0",
    "gn:asciiname":"Shimohokidaira",
    "gn:country_code":"JP",
    "gn:dem":376,
    "gn:feature_class":"P",
    "gn:feature_code":"PPLL",
    "gn:name":"Shimoh\u014dkidaira",
    "gn:population":0,
    "gn:timezone":"Asia/Tokyo",
    "iso:country":"JP",
    "name:jpn_x_preferred":[
        "\u4e0b\u7b92\u5e73"
    ],
    "name:und_x_variant":[
        "Shimoh\u014dkidaira"
    ],
    "wof:name":"Shimohokidaira",
    "wof:placetype":"locality"
},
  "geometry": {"coordinates":[140.91148000000001,37.23781],"type":"Point"}
}