{
  "type": "Feature",
  "properties": {
    "gn:admin1_code":"18",
    "gn:admin2_code":"1853737.0",
    "gn:admin3_code":"46524.0",
    "gn:asciiname":"Yadon",
    "gn:country_code":"JP",
    "gn:dem":42,
    "gn:feature_class":"P",
    "gn:feature_code":"PPL",
    "gn:name":"Yadon",
    "gn:population":0,
    "gn:timezone":"Asia/Tokyo",
    "iso:country":"JP",
    "name:jpn_x_preferred":[
        "\u5c4b\u920d"
    ],
    "name:und_x_variant":[
        "Yaton",
        "Yadon"
    ],
    "wof:name":"Yadon",
    "wof:placetype":"locality"
},
  "geometry": {"coordinates":[129.18598,28.26121],"type":"Point"}
}