{
  "type": "Feature",
  "properties": {
    "gn:admin1_code":"3.0",
    "gn:admin2_code":"2130654.0",
    "gn:asciiname":"Tarusawa",
    "gn:country_code":"JP",
    "gn:dem":23,
    "gn:feature_class":"P",
    "gn:feature_code":"PPL",
    "gn:name":"Tarusawa",
    "gn:population":0,
    "gn:timezone":"Asia/Tokyo",
    "iso:country":"JP",
    "name:jpn_x_preferred":[
        "\u6a3d\u6ca2"
    ],
    "name:jpn_x_variant":[
        "\u305f\u308b\u3055\u308f",
        "\u30bf\u30eb\u30b5\u30ef"
    ],
    "wof:name":"Tarusawa",
    "wof:placetype":"locality"
},
  "geometry": {"coordinates":[140.55448000000001,40.70889],"type":"Point"}
}