{
  "type": "Feature",
  "properties": {
    "gn:admin1_code":"2.0",
    "gn:admin2_code":"2113122.0",
    "gn:asciiname":"Hodono-nakamachi",
    "gn:country_code":"JP",
    "gn:dem":10,
    "gn:feature_class":"P",
    "gn:feature_code":"PPL",
    "gn:name":"Hodono-nakamachi",
    "gn:population":0,
    "gn:timezone":"Asia/Tokyo",
    "iso:country":"JP",
    "name:jpn_x_preferred":[
        "\u4fdd\u6238\u91ce\u4e2d\u753a"
    ],
    "name:jpn_x_variant":[
        "\u307b\u3069\u306e\u306a\u304b\u307e\u3061",
        "\u30db\u30c9\u30ce\u30ca\u30ab\u30de\u30c1"
    ],
    "wof:name":"Hodono-nakamachi",
    "wof:placetype":"locality"
},
  "geometry": {"coordinates":[140.11833999999999,39.72313],"type":"Point"}
}