{
  "type": "Feature",
  "properties": {
    "gn:admin1_code":"19.0",
    "gn:admin2_code":"1848350.0",
    "gn:admin3_code":"14104.0",
    "gn:asciiname":"Mameguchidai",
    "gn:country_code":"JP",
    "gn:dem":44,
    "gn:feature_class":"P",
    "gn:feature_code":"PPL",
    "gn:name":"Mameguchidai",
    "gn:population":0,
    "gn:timezone":"Asia/Tokyo",
    "iso:country":"JP",
    "name:jpn_x_preferred":[
        "\u8c46\u53e3\u53f0"
    ],
    "name:jpn_x_variant":[
        "\u307e\u3081\u3050\u3061\u3060\u3044",
        "\u30de\u30e1\u30b0\u30c1\u30c0\u30a4"
    ],
    "wof:name":"Mameguchidai",
    "wof:placetype":"locality"
},
  "geometry": {"coordinates":[139.64632,35.42123],"type":"Point"}
}