{
  "type": "Feature",
  "properties": {
    "gn:admin1_code":"21.0",
    "gn:admin2_code":"1857206.0",
    "gn:asciiname":"Tataracho",
    "gn:country_code":"JP",
    "gn:dem":18,
    "gn:feature_class":"P",
    "gn:feature_code":"PPL",
    "gn:name":"Tatarach\u014d",
    "gn:population":0,
    "gn:timezone":"Asia/Tokyo",
    "iso:country":"JP",
    "name:jpn_x_preferred":[
        "\u591a\u3005\u826f\u753a"
    ],
    "name:jpn_x_variant":[
        "\u305f\u305f\u3089\u3061\u3087\u3046",
        "\u30bf\u30bf\u30e9\u30c1\u30e7\u30a6"
    ],
    "name:und_x_variant":[
        "Tatarach\u014d"
    ],
    "wof:name":"Tataracho",
    "wof:placetype":"locality"
},
  "geometry": {"coordinates":[130.39506,32.20254],"type":"Point"}
}