{
  "type": "Feature",
  "properties": {
    "gn:admin1_code":"27.0",
    "gn:admin2_code":"7418805.0",
    "gn:asciiname":"Yamano",
    "gn:country_code":"JP",
    "gn:dem":260,
    "gn:feature_class":"P",
    "gn:feature_code":"PPL",
    "gn:name":"Yamano",
    "gn:population":0,
    "gn:timezone":"Asia/Tokyo",
    "iso:country":"JP",
    "name:jpn_x_preferred":[
        "\u5c71\u91ce"
    ],
    "wof:name":"Yamano",
    "wof:placetype":"locality"
},
  "geometry": {"coordinates":[129.46942000000001,33.34394],"type":"Point"}
}