{
  "type": "Feature",
  "properties": {
    "gn:admin1_code":"3.0",
    "gn:admin2_code":"2129754.0",
    "gn:admin3_code":"2412.0",
    "gn:asciiname":"Fukasawatai",
    "gn:country_code":"JP",
    "gn:dem":26,
    "gn:feature_class":"P",
    "gn:feature_code":"PPL",
    "gn:name":"Fukasawatai",
    "gn:population":0,
    "gn:timezone":"Asia/Tokyo",
    "iso:country":"JP",
    "name:jpn_x_preferred":[
        "\u6df1\u6ca2\u5e73"
    ],
    "name:jpn_x_variant":[
        "\u3075\u304b\u3055\u308f\u305f\u3044",
        "\u30d5\u30ab\u30b5\u30ef\u30bf\u30a4"
    ],
    "wof:name":"Fukasawatai",
    "wof:placetype":"locality"
},
  "geometry": {"coordinates":[141.43414000000001,40.62317],"type":"Point"}
}