{
  "type": "Feature",
  "properties": {
    "gn:admin1_code":"18.0",
    "gn:admin2_code":"8300556.0",
    "gn:asciiname":"Shihinomecho",
    "gn:country_code":"JP",
    "gn:dem":53,
    "gn:feature_class":"P",
    "gn:feature_code":"PPL",
    "gn:name":"Shihinomech\u014d",
    "gn:population":0,
    "gn:timezone":"Asia/Tokyo",
    "iso:country":"JP",
    "name:jpn_x_preferred":[
        "\u7345\u5b50\u76ee\u753a"
    ],
    "name:und_x_variant":[
        "Shihinomech\u014d"
    ],
    "wof:name":"Shihinomecho",
    "wof:placetype":"locality"
},
  "geometry": {"coordinates":[130.84455,31.32549],"type":"Point"}
}