{
  "type": "Feature",
  "properties": {
    "gn:admin1_code":"33.0",
    "gn:admin2_code":"1853274.0",
    "gn:asciiname":"Yamatocho-kuruma",
    "gn:country_code":"JP",
    "gn:dem":19,
    "gn:feature_class":"P",
    "gn:feature_code":"PPL",
    "gn:name":"Yamatoch\u014d-kuruma",
    "gn:population":0,
    "gn:timezone":"Asia/Tokyo",
    "iso:country":"JP",
    "name:jpn_x_preferred":[
        "\u5927\u548c\u753a\u4e45\u7559\u9593"
    ],
    "name:und_x_variant":[
        "Yamatoch\u014d-kuruma"
    ],
    "wof:name":"Yamatocho-kuruma",
    "wof:placetype":"locality"
},
  "geometry": {"coordinates":[130.23811000000001,33.306],"type":"Point"}
}