{
  "type": "Feature",
  "properties": {
    "gn:admin1_code":"2.0",
    "gn:admin2_code":"2111153.0",
    "gn:admin3_code":"5434.0",
    "gn:asciiname":"Koarakawa",
    "gn:country_code":"JP",
    "gn:dem":52,
    "gn:feature_class":"P",
    "gn:feature_code":"PPL",
    "gn:name":"Koarakawa",
    "gn:population":0,
    "gn:timezone":"Asia/Tokyo",
    "iso:country":"JP",
    "name:jpn_x_preferred":[
        "\u5c0f\u8352\u5ddd"
    ],
    "wof:name":"Koarakawa",
    "wof:placetype":"locality"
},
  "geometry": {"coordinates":[140.57526999999999,39.45667],"type":"Point"}
}