{
  "type": "Feature",
  "properties": {
    "gn:admin1_code":"29.0",
    "gn:admin2_code":"1859323.0",
    "gn:admin3_code":"15307.0",
    "gn:asciiname":"Shidaihama",
    "gn:country_code":"JP",
    "gn:dem":2,
    "gn:feature_class":"P",
    "gn:feature_code":"PPL",
    "gn:name":"Shidaihama",
    "gn:population":0,
    "gn:timezone":"Asia/Tokyo",
    "iso:country":"JP",
    "name:jpn_x_preferred":[
        "\u6b21\u7b2c\u6d5c"
    ],
    "wof:name":"Shidaihama",
    "wof:placetype":"locality"
},
  "geometry": {"coordinates":[139.27545000000001,38.01981],"type":"Point"}
}