{
  "type": "Feature",
  "properties": {
    "gn:admin1_code":"3.0",
    "gn:admin2_code":"2130200.0",
    "gn:asciiname":"Ippaimori",
    "gn:country_code":"JP",
    "gn:dem":45,
    "gn:feature_class":"P",
    "gn:feature_code":"PPL",
    "gn:name":"Ippaimori",
    "gn:population":0,
    "gn:timezone":"Asia/Tokyo",
    "iso:country":"JP",
    "name:jpn_x_preferred":[
        "\u4e00\u76c3\u68ee"
    ],
    "name:jpn_x_variant":[
        "\u3044\u3063\u3071\u3044\u3082\u308a",
        "\u30a4\u30c3\u30d1\u30a4\u30e2\u30ea"
    ],
    "wof:name":"Ippaimori",
    "wof:placetype":"locality"
},
  "geometry": {"coordinates":[141.4727,40.50111],"type":"Point"}
}