{
  "type": "Feature",
  "properties": {
    "iso:country":"JP",
    "name:eng_x_preferred":[
        "Marunochi 1 Chome"
    ],
    "name:eng_x_variant":[
        "Marunouchi 1 Choume",
        "Marunochi 1 Chome"
    ],
    "name:jpn_x_preferred":[
        "\uff11\u4e01\u76ee"
    ],
    "name:jpn_x_variant":[
        "\u307e\u308b\u306e\u3046\u3061 \uff11\u3061\u3087\u3046\u3081",
        "\u4e38\u30ce\u5185 \uff11\u4e01\u76ee",
        "\uff11\u3061\u3087\u3046\u3081"
    ],
    "qs:gn_local":0,
    "qs:local_max":565,
    "qs:local_sum":1354,
    "qs:localhoods":19,
    "qs:name":"\uff11\u4e01\u76ee",
    "qs:name_adm0":"\u65e5\u672c",
    "qs:name_adm1":"\u9ad8\u77e5\u770c",
    "qs:name_en":"Marunochi 1 Chome",
    "qs:name_lau":"\u4e38\u30ce\u5185",
    "qs:name_local":"\u9ad8\u77e5\u5e02",
    "qs:photo_max":164,
    "qs:photo_sum":242,
    "qs:placetype":"Suburb",
    "qs:quad_count":7,
    "qs:woe_adm0":23424856,
    "qs:woe_adm1":2345869,
    "qs:woe_adm2":0,
    "qs:woe_lau":28480900,
    "qs:woe_local":1117548,
    "qs:woe_ver":"7.10.0",
    "wof:lang":[
        "jpn"
    ],
    "wof:name":"\uff11\u4e01\u76ee",
    "wof:placetype":"neighbourhood"
},
  "geometry": {"coordinates":[133.532006,33.56046],"type":"Point"}
}