{
  "type": "Feature",
  "properties": {
    "gn:admin1_code":"19.0",
    "gn:admin2_code":"1848308.0",
    "gn:asciiname":"Nagasawa-sanchome",
    "gn:country_code":"JP",
    "gn:dem":46,
    "gn:feature_class":"P",
    "gn:feature_code":"PPLL",
    "gn:name":"Nagasawa-sanch\u014dme",
    "gn:population":0,
    "gn:timezone":"Asia/Tokyo",
    "iso:country":"JP",
    "name:jpn_x_preferred":[
        "\u9577\u6ca2\u4e09\u4e01\u76ee"
    ],
    "name:jpn_x_variant":[
        "\u306a\u304c\u3055\u308f\u3055\u3093\u3061\u3087\u3046\u3081",
        "\u30ca\u30ac\u30b5\u30ef\u30b5\u30f3\u30c1\u30e7\u30a6\u30e1"
    ],
    "name:und_x_variant":[
        "Nagasawa-sanch\u014dme"
    ],
    "wof:name":"Nagasawa-sanchome",
    "wof:placetype":"locality"
},
  "geometry": {"coordinates":[139.68213,35.21219],"type":"Point"}
}