{
  "type": "Feature",
  "properties": {
    "gn:admin1_code":"21.0",
    "gn:admin2_code":"7412708.0",
    "gn:admin3_code":"43506.0",
    "gn:asciiname":"Nakai",
    "gn:country_code":"JP",
    "gn:dem":221,
    "gn:feature_class":"P",
    "gn:feature_code":"PPL",
    "gn:name":"Nakai",
    "gn:population":0,
    "gn:timezone":"Asia/Tokyo",
    "iso:country":"JP",
    "name:cat_x_preferred":[
        "Nakai"
    ],
    "name:deu_x_preferred":[
        "Nakai"
    ],
    "name:fra_x_preferred":[
        "Nakai"
    ],
    "name:jpn_x_preferred":[
        "\u4e2d\u732a"
    ],
    "name:jpn_x_variant":[
        "\u306a\u304b\u3044",
        "\u30ca\u30ab\u30a4"
    ],
    "name:rus_x_preferred":[
        "\u041d\u0430\u043a\u0430\u0438"
    ],
    "name:spa_x_preferred":[
        "Nakai"
    ],
    "name:ukr_x_preferred":[
        "\u041d\u0430\u043a\u0430\u0457"
    ],
    "wof:name":"Nakai",
    "wof:placetype":"locality"
},
  "geometry": {"coordinates":[131.00613000000001,32.27594000000001],"type":"Point"}
}