{
  "type": "Feature",
  "properties": {
    "gn:admin1_code":"37.0",
    "gn:admin2_code":"1854900.0",
    "gn:asciiname":"Uchiura-mito",
    "gn:country_code":"JP",
    "gn:dem":31,
    "gn:feature_class":"P",
    "gn:feature_code":"PPL",
    "gn:name":"Uchiura-mito",
    "gn:population":0,
    "gn:timezone":"Asia/Tokyo",
    "iso:country":"JP",
    "name:jpn_x_preferred":[
        "\u5185\u6d66\u4e09\u6d25"
    ],
    "name:jpn_x_variant":[
        "\u3046\u3061\u3046\u3089\u307f\u3068"
    ],
    "wof:name":"Uchiura-mito",
    "wof:placetype":"locality"
},
  "geometry": {"coordinates":[138.90029999999999,35.02269],"type":"Point"}
}