{
  "type": "Feature",
  "properties": {
    "gn:admin1_code":"21.0",
    "gn:admin2_code":"7413150.0",
    "gn:asciiname":"Miyazako",
    "gn:country_code":"JP",
    "gn:dem":90,
    "gn:feature_class":"P",
    "gn:feature_code":"PPLL",
    "gn:name":"Miyazako",
    "gn:population":0,
    "gn:timezone":"Asia/Tokyo",
    "iso:country":"JP",
    "name:jpn_x_preferred":[
        "\u5bae\u8feb"
    ],
    "name:jpn_x_variant":[
        "\u307f\u3084\u3056\u3053",
        "\u30df\u30e4\u30b6\u30b3"
    ],
    "wof:name":"Miyazako",
    "wof:placetype":"locality"
},
  "geometry": {"coordinates":[130.69703000000001,33.11525],"type":"Point"}
}