{
  "type": "Feature",
  "properties": {
    "iso:country":"JP",
    "name:eng_x_preferred":[
        "Tsurukawa 1 Chome"
    ],
    "name:eng_x_variant":[
        "Tsurukawa 1 Choume",
        "Tsurukawa 1 Chome"
    ],
    "name:jpn_x_preferred":[
        "\uff11\u4e01\u76ee"
    ],
    "name:jpn_x_variant":[
        "\u3064\u308b\u304b\u308f \uff11\u3061\u3087\u3046\u3081",
        "\u9db4\u5ddd \uff11\u4e01\u76ee",
        "\uff11\u3061\u3087\u3046\u3081"
    ],
    "qs:gn_local":0,
    "qs:local_max":1601,
    "qs:local_sum":3692,
    "qs:localhoods":21,
    "qs:name":"\uff11\u4e01\u76ee",
    "qs:name_adm0":"\u65e5\u672c",
    "qs:name_adm1":"\u6771\u4eac\u90fd",
    "qs:name_en":"Tsurukawa 1 Chome",
    "qs:name_lau":"\u9db4\u5ddd",
    "qs:name_local":"\u753a\u7530\u5e02",
    "qs:photo_max":32,
    "qs:photo_sum":73,
    "qs:placetype":"Suburb",
    "qs:quad_count":12,
    "qs:woe_adm0":23424856,
    "qs:woe_adm1":2345889,
    "qs:woe_adm2":0,
    "qs:woe_lau":28415093,
    "qs:woe_local":1111475,
    "qs:woe_ver":"7.10.0",
    "wof:lang":[
        "jpn"
    ],
    "wof:name":"\uff11\u4e01\u76ee",
    "wof:placetype":"neighbourhood"
},
  "geometry": {"coordinates":[139.48088000000001,35.584085],"type":"Point"}
}