{
  "type": "Feature",
  "properties": {
    "gn:admin1_code":"23.0",
    "gn:admin2_code":"1849544.0",
    "gn:asciiname":"Kotsukuricho",
    "gn:country_code":"JP",
    "gn:dem":6,
    "gn:feature_class":"P",
    "gn:feature_code":"PPL",
    "gn:name":"Kotsukurich\u014d",
    "gn:population":0,
    "gn:timezone":"Asia/Tokyo",
    "iso:country":"JP",
    "name:jpn_x_preferred":[
        "\u6728\u9020\u753a"
    ],
    "name:und_x_variant":[
        "Kotsukurich\u014d"
    ],
    "wof:name":"Kotsukuricho",
    "wof:placetype":"locality"
},
  "geometry": {"coordinates":[136.4966,34.6551],"type":"Point"}
}