{
  "type": "Feature",
  "properties": {
    "gn:admin1_code":"19.0",
    "gn:admin2_code":"1863429.0",
    "gn:asciiname":"Miyashita",
    "gn:country_code":"JP",
    "gn:dem":55,
    "gn:feature_class":"P",
    "gn:feature_code":"PPLL",
    "gn:name":"Miyashita",
    "gn:population":0,
    "gn:timezone":"Asia/Tokyo",
    "iso:country":"JP",
    "name:jpn_x_preferred":[
        "\u5bae\u4e0b"
    ],
    "name:rus_x_preferred":[
        "\u041c\u0438\u044f\u0441\u0438\u0442\u0430"
    ],
    "wof:name":"Miyashita",
    "wof:placetype":"locality"
},
  "geometry": {"coordinates":[139.25503,35.36025],"type":"Point"}
}