{
  "type": "Feature",
  "properties": {
    "gn:admin1_code":"31.0",
    "gn:admin2_code":"7405225.0",
    "gn:asciiname":"Kaminakaso",
    "gn:country_code":"JP",
    "gn:dem":335,
    "gn:feature_class":"P",
    "gn:feature_code":"PPL",
    "gn:name":"Kaminakaso",
    "gn:population":0,
    "gn:timezone":"Asia/Tokyo",
    "iso:country":"JP",
    "name:jpn_x_preferred":[
        "\u4e0a\u4e2d\u66fd"
    ],
    "wof:name":"Kaminakaso",
    "wof:placetype":"locality"
},
  "geometry": {"coordinates":[133.57058999999998,35.07636],"type":"Point"}
}