{
  "type": "Feature",
  "properties": {
    "iso:country":"JP",
    "name:eng_x_preferred":[
        "Nakacho 3 Chome"
    ],
    "name:eng_x_variant":[
        "Nakachou 3 Choume",
        "Nakacho 3 Chome"
    ],
    "name:jpn_x_preferred":[
        "\uff13\u4e01\u76ee"
    ],
    "name:jpn_x_variant":[
        "\u306a\u304b\u3061\u3087\u3046 \uff13\u3061\u3087\u3046\u3081",
        "\u4ef2\u753a \uff13\u4e01\u76ee",
        "\uff13\u3061\u3087\u3046\u3081"
    ],
    "qs:gn_local":0,
    "qs:local_max":581,
    "qs:local_sum":6772,
    "qs:localhoods":52,
    "qs:name":"\uff13\u4e01\u76ee",
    "qs:name_adm0":"\u65e5\u672c",
    "qs:name_adm1":"\u57fc\u7389\u770c",
    "qs:name_adm2":"\u6d66\u548c\u533a",
    "qs:name_en":"Nakacho 3 Chome",
    "qs:name_lau":"\u4ef2\u753a",
    "qs:name_local":"\u3055\u3044\u305f\u307e\u5e02",
    "qs:photo_max":27,
    "qs:photo_sum":79,
    "qs:placetype":"Suburb",
    "qs:quad_count":7,
    "qs:woe_adm0":23424856,
    "qs:woe_adm1":2345883,
    "qs:woe_adm2":24727517,
    "qs:woe_lau":28407775,
    "qs:woe_local":1116753,
    "qs:woe_ver":"7.10.0",
    "wof:lang":[
        "jpn"
    ],
    "wof:name":"\uff13\u4e01\u76ee",
    "wof:placetype":"neighbourhood"
},
  "geometry": {"coordinates":[139.64868999999999,35.859985],"type":"Point"}
}