{
  "type": "Feature",
  "properties": {
    "gn:admin1_code":"47.0",
    "gn:admin2_code":"1856030.0",
    "gn:asciiname":"Furujima",
    "gn:country_code":"JP",
    "gn:dem":30,
    "gn:feature_class":"P",
    "gn:feature_code":"PPL",
    "gn:name":"Furujima",
    "gn:population":0,
    "gn:timezone":"Asia/Tokyo",
    "iso:country":"JP",
    "name:jpn_x_preferred":[
        "\u53e4\u5cf6"
    ],
    "wof:name":"Furujima",
    "wof:placetype":"locality"
},
  "geometry": {"coordinates":[127.70474,26.22777],"type":"Point"}
}