{
  "type": "Feature",
  "properties": {
    "gn:admin1_code":"37.0",
    "gn:admin2_code":"1864089.0",
    "gn:asciiname":"Sengen-honcho",
    "gn:country_code":"JP",
    "gn:dem":12,
    "gn:feature_class":"P",
    "gn:feature_code":"PPL",
    "gn:name":"Sengen-honch\u014d",
    "gn:population":0,
    "gn:timezone":"Asia/Tokyo",
    "iso:country":"JP",
    "name:jpn_x_preferred":[
        "\u6d45\u9593\u672c\u753a"
    ],
    "name:und_x_variant":[
        "Sengen-honch\u014d"
    ],
    "wof:name":"Sengen-honcho",
    "wof:placetype":"locality"
},
  "geometry": {"coordinates":[138.67784,35.16614000000001],"type":"Point"}
}