{
  "type": "Feature",
  "properties": {
    "gn:admin1_code":"3.0",
    "gn:admin2_code":"2127674.0",
    "gn:asciiname":"Nakanowatari",
    "gn:country_code":"JP",
    "gn:dem":91,
    "gn:feature_class":"P",
    "gn:feature_code":"PPL",
    "gn:name":"Nakanowatari",
    "gn:population":0,
    "gn:timezone":"Asia/Tokyo",
    "iso:country":"JP",
    "name:jpn_x_preferred":[
        "\u4e2d\u30ce\u6e21"
    ],
    "name:jpn_x_variant":[
        "\u306a\u304b\u306e\u308f\u305f\u308a",
        "\u30ca\u30ab\u30ce\u30ef\u30bf\u30ea"
    ],
    "wof:name":"Nakanowatari",
    "wof:placetype":"locality"
},
  "geometry": {"coordinates":[141.12921,40.58915],"type":"Point"}
}