{
  "type": "Feature",
  "properties": {
    "iso:country":"JP",
    "name:eng_x_preferred":[
        "Nishikawa"
    ],
    "name:eng_x_variant":[
        "Nishikawa Town"
    ],
    "name:jpn_x_preferred":[
        "\u897f\u5ddd\u753a"
    ],
    "qs:name":"\u897f\u5ddd\u753a",
    "qs:name_adm0":"\u65e5\u672c",
    "qs:name_adm1":"\u5c71\u5f62\u770c",
    "qs:photos":242,
    "qs:photos_1k":49,
    "qs:photos_9k":1,
    "qs:photos_9r":4,
    "qs:photos_all":242,
    "qs:photos_sr":4,
    "qs:placetype":"Town",
    "qs:pop_sr":"0",
    "wof:name":"Nishikawa",
    "wof:placetype":"locality"
},
  "geometry": {"coordinates":[140.00890699999999,38.49713],"type":"Point"}
}