{
  "type": "Feature",
  "properties": {
    "gn:admin1_code":"4.0",
    "gn:admin2_code":"1850520.0",
    "gn:asciiname":"Takinoyatsu",
    "gn:country_code":"JP",
    "gn:dem":43,
    "gn:feature_class":"P",
    "gn:feature_code":"PPLL",
    "gn:name":"Takinoyatsu",
    "gn:population":0,
    "gn:timezone":"Asia/Tokyo",
    "iso:country":"JP",
    "name:jpn_x_preferred":[
        "\u6edd\u30ce\u8c37"
    ],
    "name:jpn_x_variant":[
        "\u305f\u304d\u306e\u3084\u3064",
        "\u30bf\u30ad\u30ce\u30e4\u30c4"
    ],
    "wof:name":"Takinoyatsu",
    "wof:placetype":"locality"
},
  "geometry": {"coordinates":[139.92823000000001,35.0207],"type":"Point"}
}