{
  "type": "Feature",
  "properties": {
    "iso:country":"JP",
    "name:eng_x_preferred":[
        "Ote 4 Chome"
    ],
    "name:eng_x_variant":[
        "Oote 4 Choume",
        "Ote 4 Chome"
    ],
    "name:jpn_x_preferred":[
        "\uff14\u4e01\u76ee"
    ],
    "name:jpn_x_variant":[
        "\u304a\u304a\u3066 \uff14\u3061\u3087\u3046\u3081",
        "\u5927\u624b \uff14\u4e01\u76ee",
        "\uff14\u3061\u3087\u3046\u3081"
    ],
    "qs:gn_local":0,
    "qs:local_max":1129,
    "qs:local_sum":4513,
    "qs:localhoods":19,
    "qs:name":"\uff14\u4e01\u76ee",
    "qs:name_adm0":"\u65e5\u672c",
    "qs:name_adm1":"\u9577\u91ce\u770c",
    "qs:name_en":"Ote 4 Chome",
    "qs:name_lau":"\u5927\u624b",
    "qs:name_local":"\u677e\u672c\u5e02",
    "qs:photo_max":121,
    "qs:photo_sum":121,
    "qs:placetype":"Suburb",
    "qs:quad_count":1,
    "qs:woe_adm0":23424856,
    "qs:woe_adm1":2345875,
    "qs:woe_adm2":0,
    "qs:woe_lau":28431538,
    "qs:woe_local":1117683,
    "qs:woe_ver":"7.10.0",
    "wof:lang":[
        "jpn"
    ],
    "wof:name":"\uff14\u4e01\u76ee",
    "wof:placetype":"neighbourhood"
},
  "geometry": {"coordinates":[137.970428,36.236519],"type":"Point"}
}