{
  "type": "Feature",
  "properties": {
    "gn:admin1_code":"32.0",
    "gn:admin2_code":"1855493.0",
    "gn:asciiname":"Naritacho",
    "gn:country_code":"JP",
    "gn:dem":37,
    "gn:feature_class":"P",
    "gn:feature_code":"PPL",
    "gn:name":"Naritach\u014d",
    "gn:population":0,
    "gn:timezone":"Asia/Tokyo",
    "iso:country":"JP",
    "name:jpn_x_preferred":[
        "\u6210\u7530\u753a"
    ],
    "name:und_x_variant":[
        "Naritach\u014d"
    ],
    "wof:name":"Naritacho",
    "wof:placetype":"locality"
},
  "geometry": {"coordinates":[135.64131,34.77985],"type":"Point"}
}