{
  "type": "Feature",
  "properties": {
    "gn:admin1_code":"21.0",
    "gn:admin2_code":"1858418.0",
    "gn:admin3_code":"43105.0",
    "gn:asciiname":"Miyamoto",
    "gn:country_code":"JP",
    "gn:dem":72,
    "gn:feature_class":"P",
    "gn:feature_code":"PPLL",
    "gn:name":"Miyamoto",
    "gn:population":0,
    "gn:timezone":"Asia/Tokyo",
    "iso:country":"JP",
    "name:jpn_x_preferred":[
        "\u5bae\u672c"
    ],
    "name:jpn_x_variant":[
        "\u307f\u3084\u3082\u3068",
        "\u30df\u30e4\u30e2\u30c8"
    ],
    "name:lav_x_preferred":[
        "Mijamoto"
    ],
    "wof:name":"Miyamoto",
    "wof:placetype":"locality"
},
  "geometry": {"coordinates":[130.67786999999998,32.9419],"type":"Point"}
}