{
  "type": "Feature",
  "properties": {
    "gn:admin1_code":"24.0",
    "gn:admin2_code":"2111147.0",
    "gn:admin3_code":"4104.0",
    "gn:asciiname":"Moniwa",
    "gn:country_code":"JP",
    "gn:dem":67,
    "gn:feature_class":"P",
    "gn:feature_code":"PPL",
    "gn:name":"Moniwa",
    "gn:population":0,
    "gn:timezone":"Asia/Tokyo",
    "iso:country":"JP",
    "name:jpn_x_preferred":[
        "\u8302\u5ead"
    ],
    "wof:name":"Moniwa",
    "wof:placetype":"locality"
},
  "geometry": {"coordinates":[140.78738000000001,38.22219000000001],"type":"Point"}
}