{
  "type": "Feature",
  "properties": {
    "gn:admin1_code":"8.0",
    "gn:admin2_code":"9035647.0",
    "gn:asciiname":"Funehikimachi-yokomichi",
    "gn:country_code":"JP",
    "gn:dem":640,
    "gn:feature_class":"P",
    "gn:feature_code":"PPL",
    "gn:name":"Funehikimachi-yokomichi",
    "gn:population":0,
    "gn:timezone":"Asia/Tokyo",
    "iso:country":"JP",
    "name:jpn_x_preferred":[
        "\u8239\u5f15\u753a\u6a2a\u9053"
    ],
    "wof:name":"Funehikimachi-yokomichi",
    "wof:placetype":"locality"
},
  "geometry": {"coordinates":[140.68591000000001,37.47647],"type":"Point"}
}