{
  "type": "Feature",
  "properties": {
    "gn:admin1_code":"27",
    "gn:admin2_code":"7418808.0",
    "gn:asciiname":"Seihicho-yagiharago",
    "gn:country_code":"JP",
    "gn:dem":34,
    "gn:feature_class":"P",
    "gn:feature_code":"PPL",
    "gn:name":"Seihich\u014d-yagiharag\u014d",
    "gn:population":0,
    "gn:timezone":"Asia/Tokyo",
    "iso:country":"JP",
    "name:jpn_x_preferred":[
        "\u897f\u5f7c\u753a\u516b\u6728\u539f\u90f7"
    ],
    "name:und_x_variant":[
        "Yagihara",
        "Yagiharag\u014d",
        "Yakihara",
        "Yagiwara",
        "Seihich\u014d-yagiharag\u014d"
    ],
    "wof:name":"Seihicho-yagiharago",
    "wof:placetype":"locality"
},
  "geometry": {"coordinates":[129.73411000000002,33.02112],"type":"Point"}
}