{
  "type": "Feature",
  "properties": {
    "gn:admin1_code":"06",
    "gn:admin2_code":"1854875.0",
    "gn:admin3_code":"18423.0",
    "gn:asciiname":"Ota",
    "gn:cc2":"JP",
    "gn:country_code":"JP",
    "gn:dem":119,
    "gn:feature_class":"P",
    "gn:feature_code":"PPL",
    "gn:name":"Ota",
    "gn:population":0,
    "gn:timezone":"Asia/Tokyo",
    "iso:country":"JP",
    "name:jpn_x_preferred":[
        "\u7e54\u7530"
    ],
    "name:jpn_x_variant":[
        "\u304a\u305f"
    ],
    "wof:name":"Ota",
    "wof:placetype":"locality"
},
  "geometry": {"coordinates":[136.05606,35.958],"type":"Point"}
}