{
  "type": "Feature",
  "properties": {
    "gn:admin1_code":"12.0",
    "gn:admin2_code":"7428113.0",
    "gn:admin3_code":"1392.0",
    "gn:asciiname":"Biya",
    "gn:country_code":"JP",
    "gn:dem":56,
    "gn:feature_class":"P",
    "gn:feature_code":"PPL",
    "gn:name":"Biya",
    "gn:population":0,
    "gn:timezone":"Asia/Tokyo",
    "iso:country":"JP",
    "name:ceb_x_preferred":[
        "Biya"
    ],
    "name:deu_x_preferred":[
        "Biya"
    ],
    "name:fra_x_preferred":[
        "Biya"
    ],
    "name:swe_x_preferred":[
        "Biya"
    ],
    "name:uzb_x_preferred":[
        "Biya"
    ],
    "wof:name":"Biya",
    "wof:placetype":"locality"
},
  "geometry": {"coordinates":[140.30864,42.82158],"type":"Point"}
}