{
  "type": "Feature",
  "properties": {
    "gn:admin1_code":"8.0",
    "gn:admin2_code":"2112979.0",
    "gn:admin3_code":"7308.0",
    "gn:asciiname":"Yamakiya",
    "gn:country_code":"JP",
    "gn:dem":583,
    "gn:feature_class":"P",
    "gn:feature_code":"PPL",
    "gn:name":"Yamakiya",
    "gn:population":0,
    "gn:timezone":"Asia/Tokyo",
    "iso:country":"JP",
    "name:jpn_x_preferred":[
        "\u5c71\u6728\u5c4b"
    ],
    "wof:name":"Yamakiya",
    "wof:placetype":"locality"
},
  "geometry": {"coordinates":[140.66054,37.60526],"type":"Point"}
}