{
  "type": "Feature",
  "properties": {
    "gn:admin1_code":"15.0",
    "gn:admin2_code":"1860845.0",
    "gn:asciiname":"Nakatsuharamachi",
    "gn:country_code":"JP",
    "gn:dem":61,
    "gn:feature_class":"P",
    "gn:feature_code":"PPLL",
    "gn:name":"Nakatsuharamachi",
    "gn:population":0,
    "gn:timezone":"Asia/Tokyo",
    "iso:country":"JP",
    "name:jpn_x_preferred":[
        "\u4e2d\u6d25\u539f\u753a"
    ],
    "wof:name":"Nakatsuharamachi",
    "wof:placetype":"locality"
},
  "geometry": {"coordinates":[136.39789999999999,36.26295],"type":"Point"}
}