{
  "type": "Feature",
  "properties": {
    "gn:admin1_code":"3.0",
    "gn:admin2_code":"2129393.0",
    "gn:asciiname":"Fukutami",
    "gn:country_code":"JP",
    "gn:dem":78,
    "gn:feature_class":"P",
    "gn:feature_code":"PPL",
    "gn:name":"Fukutami",
    "gn:population":0,
    "gn:timezone":"Asia/Tokyo",
    "iso:country":"JP",
    "name:jpn_x_preferred":[
        "\u798f\u6c11"
    ],
    "name:jpn_x_variant":[
        "\u3075\u304f\u305f\u307f",
        "\u30d5\u30af\u30bf\u30df"
    ],
    "wof:name":"Fukutami",
    "wof:placetype":"locality"
},
  "geometry": {"coordinates":[140.61753999999999,40.63802],"type":"Point"}
}