{
  "type": "Feature",
  "properties": {
    "gn:admin1_code":"7.0",
    "gn:admin2_code":"1861834.0",
    "gn:asciiname":"Edakuni-ikku",
    "gn:country_code":"JP",
    "gn:dem":17,
    "gn:feature_class":"P",
    "gn:feature_code":"PPLL",
    "gn:name":"Edakuni-ikku",
    "gn:population":0,
    "gn:timezone":"Asia/Tokyo",
    "iso:country":"JP",
    "name:jpn_x_preferred":[
        "\u679d\u56fd\u4e00\u533a"
    ],
    "wof:name":"Edakuni-ikku",
    "wof:placetype":"locality"
},
  "geometry": {"coordinates":[130.67723999999998,33.63227],"type":"Point"}
}