{
  "type": "Feature",
  "properties": {
    "gn:country":"JP",
    "gn:fcode":"PPL",
    "gn:pop":23180,
    "iso:country":"JP",
    "name:eng_x_preferred":[
        "Shirahama"
    ],
    "name:jpn_x_preferred":[
        "\u767d\u6d5c\u753a\u5b87\u4f50\u5d0e\u5357"
    ],
    "name:rus_x_preferred":[
        "\u0428\u0438\u0440\u0430\u0445\u0430\u043c\u0430"
    ],
    "name:unk_x_variant":[
        "Shirahama-ku"
    ],
    "qs:name":"Shirahama",
    "qs:photos_9r":0,
    "qs:photos_sr":0,
    "qs:pop_sr":"7",
    "wof:name":"Shirahama",
    "wof:placetype":"locality",
    "wof:population":23180
},
  "geometry": {"coordinates":[134.71666999999999,34.78333],"type":"Point"}
}