{
  "type": "Feature",
  "properties": {
    "gn:admin1_code":"8.0",
    "gn:admin2_code":"7451502.0",
    "gn:admin3_code":"7505.0",
    "gn:asciiname":"Takinodaira",
    "gn:country_code":"JP",
    "gn:dem":442,
    "gn:feature_class":"P",
    "gn:feature_code":"PPLL",
    "gn:name":"Takinodaira",
    "gn:population":0,
    "gn:timezone":"Asia/Tokyo",
    "iso:country":"JP",
    "name:jpn_x_preferred":[
        "\u6edd\u30ce\u5e73"
    ],
    "wof:name":"Takinodaira",
    "wof:placetype":"locality"
},
  "geometry": {"coordinates":[140.56972999999999,37.02079000000001],"type":"Point"}
}