{
  "type": "Feature",
  "properties": {
    "gn:admin1_code":"44.0",
    "gn:admin2_code":"2110552.0",
    "gn:asciiname":"Kitakawara",
    "gn:country_code":"JP",
    "gn:dem":110,
    "gn:feature_class":"P",
    "gn:feature_code":"PPL",
    "gn:name":"Kitakawara",
    "gn:population":0,
    "gn:timezone":"Asia/Tokyo",
    "iso:country":"JP",
    "wof:name":"Kitakawara",
    "wof:placetype":"locality"
},
  "geometry": {"coordinates":[140.34999999999999,38.28333],"type":"Point"}
}