{
  "type": "Feature",
  "properties": {
    "gn:admin1_code":"20",
    "gn:admin2_code":"7405897.0",
    "gn:asciiname":"Shimizu",
    "gn:cc2":"JP",
    "gn:country_code":"JP",
    "gn:dem":26,
    "gn:feature_class":"P",
    "gn:feature_code":"PPL",
    "gn:name":"Shimizu",
    "gn:population":0,
    "gn:timezone":"Asia/Tokyo",
    "iso:country":"JP",
    "name:deu_x_preferred":[
        "Shimizu"
    ],
    "name:fra_x_preferred":[
        "Shimizu"
    ],
    "name:kor_x_preferred":[
        "\uc2dc\ubbf8\uc988"
    ],
    "name:nld_x_preferred":[
        "Thanh Th\u1ee7y"
    ],
    "name:por_x_preferred":[
        "Shimizu"
    ],
    "name:rus_x_preferred":[
        "\u0421\u0438\u043c\u0438\u0434\u0437\u0443"
    ],
    "name:ukr_x_preferred":[
        "\u0421\u0456\u043c\u0456\u0434\u0437\u0443"
    ],
    "name:und_x_variant":[
        "Henai"
    ],
    "name:vie_x_preferred":[
        "Thanh Th\u1ee7y"
    ],
    "wof:name":"Shimizu",
    "wof:placetype":"locality"
},
  "geometry": {"coordinates":[132.80000000000001,32.95],"type":"Point"}
}