{
  "type": "Feature",
  "properties": {
    "gn:admin1_code":"21.0",
    "gn:admin2_code":"7412708.0",
    "gn:admin3_code":"43510.0",
    "gn:asciiname":"Nakanohara",
    "gn:country_code":"JP",
    "gn:dem":443,
    "gn:feature_class":"P",
    "gn:feature_code":"PPLL",
    "gn:name":"Nakanohara",
    "gn:population":0,
    "gn:timezone":"Asia/Tokyo",
    "iso:country":"JP",
    "name:jpn_x_preferred":[
        "\u4e2d\u30ce\u539f"
    ],
    "name:jpn_x_variant":[
        "\u306a\u304b\u306e\u306f\u3089",
        "\u30ca\u30ab\u30ce\u30cf\u30e9"
    ],
    "name:und_x_variant":[
        "Nakaharu",
        "Nakanohara"
    ],
    "wof:name":"Nakanohara",
    "wof:placetype":"locality"
},
  "geometry": {"coordinates":[130.83097000000001,32.34389],"type":"Point"}
}