{
  "type": "Feature",
  "properties": {
    "gn:admin1_code":"46",
    "gn:admin2_code":"1848648.0",
    "gn:asciiname":"Kami-kanogawa",
    "gn:cc2":"JP",
    "gn:country_code":"JP",
    "gn:dem":329,
    "gn:feature_class":"P",
    "gn:feature_code":"PPL",
    "gn:name":"Kami-kanogawa",
    "gn:population":0,
    "gn:timezone":"Asia/Tokyo",
    "iso:country":"JP",
    "name:und_x_variant":[
        "Kanoiwa",
        "Kami-kanagawa",
        "Kami-kannagawa",
        "Kami-kanogawa"
    ],
    "wof:name":"Kami-kanogawa",
    "wof:placetype":"locality"
},
  "geometry": {"coordinates":[138.68333000000001,35.68333],"type":"Point"}
}