{
  "type": "Feature",
  "properties": {
    "gn:admin1_code":"21.0",
    "gn:admin2_code":"1857206.0",
    "gn:asciiname":"Akiyabashi",
    "gn:country_code":"JP",
    "gn:dem":126,
    "gn:feature_class":"P",
    "gn:feature_code":"PPLL",
    "gn:name":"Akiyabashi",
    "gn:population":0,
    "gn:timezone":"Asia/Tokyo",
    "iso:country":"JP",
    "name:jpn_x_preferred":[
        "\u8d64\u6797"
    ],
    "name:jpn_x_variant":[
        "\u3042\u304d\u3084\u3070\u3057",
        "\u30a2\u30ad\u30e4\u30d0\u30b7"
    ],
    "wof:name":"Akiyabashi",
    "wof:placetype":"locality"
},
  "geometry": {"coordinates":[130.43753999999998,32.16363],"type":"Point"}
}