{
  "type": "Feature",
  "properties": {
    "gn:admin1_code":"2.0",
    "gn:admin2_code":"7443160.0",
    "gn:asciiname":"Iwaki-futago",
    "gn:country_code":"JP",
    "gn:dem":14,
    "gn:feature_class":"P",
    "gn:feature_code":"PPL",
    "gn:name":"Iwaki-futago",
    "gn:population":0,
    "gn:timezone":"Asia/Tokyo",
    "iso:country":"JP",
    "name:jpn_x_preferred":[
        "\u5ca9\u57ce\u4e8c\u53e4"
    ],
    "wof:name":"Iwaki-futago",
    "wof:placetype":"locality"
},
  "geometry": {"coordinates":[140.05476000000002,39.53099],"type":"Point"}
}