{
  "type": "Feature",
  "properties": {
    "gn:admin1_code":"3.0",
    "gn:admin2_code":"2130200.0",
    "gn:asciiname":"Yanase",
    "gn:country_code":"JP",
    "gn:dem":50,
    "gn:feature_class":"P",
    "gn:feature_code":"PPL",
    "gn:name":"Yanase",
    "gn:population":0,
    "gn:timezone":"Asia/Tokyo",
    "iso:country":"JP",
    "name:deu_x_preferred":[
        "Yanase"
    ],
    "name:jpn_x_preferred":[
        "\u7c17\u702c"
    ],
    "name:jpn_x_variant":[
        "\u3084\u306a\u305b",
        "\u30e4\u30ca\u30bb"
    ],
    "name:nds_x_preferred":[
        "Yanase"
    ],
    "wof:name":"Yanase",
    "wof:placetype":"locality"
},
  "geometry": {"coordinates":[141.49286999999995,40.42209],"type":"Point"}
}