{
  "type": "Feature",
  "properties": {
    "gn:admin1_code":"24",
    "gn:admin2_code":"2111889.0",
    "gn:admin3_code":"4401.0",
    "gn:asciiname":"Takagi",
    "gn:country_code":"JP",
    "gn:dem":40,
    "gn:feature_class":"P",
    "gn:feature_code":"PPL",
    "gn:name":"Takagi",
    "gn:population":0,
    "gn:timezone":"Asia/Tokyo",
    "iso:country":"JP",
    "name:deu_x_preferred":[
        "Takagi"
    ],
    "name:fra_x_preferred":[
        "Takagi"
    ],
    "name:ita_x_preferred":[
        "Takagi"
    ],
    "name:jpn_x_preferred":[
        "\u9ad8\u57ce"
    ],
    "name:jpn_x_variant":[
        "\u305f\u304b\u304e",
        "\u30bf\u30ab\u30ae",
        "\u9ad8\u6728"
    ],
    "name:kor_x_preferred":[
        "\ub2e4\uce74\uae30"
    ],
    "name:por_x_preferred":[
        "Takagi"
    ],
    "name:rus_x_preferred":[
        "\u0422\u0430\u043a\u0430\u0433\u0438"
    ],
    "name:und_x_variant":[
        "Takaki",
        "Takagi"
    ],
    "wof:name":"Takagi",
    "wof:placetype":"locality"
},
  "geometry": {"coordinates":[141.05858000000001,38.38737],"type":"Point"}
}