{
  "type": "Feature",
  "properties": {
    "gn:admin1_code":"3.0",
    "gn:admin2_code":"7439934.0",
    "gn:asciiname":"Heiroku",
    "gn:country_code":"JP",
    "gn:dem":328,
    "gn:feature_class":"P",
    "gn:feature_code":"PPL",
    "gn:name":"Heiroku",
    "gn:population":0,
    "gn:timezone":"Asia/Tokyo",
    "iso:country":"JP",
    "name:jpn_x_preferred":[
        "\u5e73\u516d"
    ],
    "name:jpn_x_variant":[
        "\u3078\u3044\u308d\u304f",
        "\u30d8\u30a4\u30ed\u30af"
    ],
    "name:und_x_variant":[
        "Hiiroku"
    ],
    "wof:name":"Heiroku",
    "wof:placetype":"locality"
},
  "geometry": {"coordinates":[140.75916000000001,40.53202],"type":"Point"}
}