{
  "type": "Feature",
  "properties": {
    "gn:country":"JP",
    "gn:fcode":"ADM3",
    "gn:population":0,
    "iso:country":"JP",
    "name:eng_x_preferred":[
        "Yomitan"
    ],
    "name:eng_x_variant":[
        "Yomitan-son"
    ],
    "name:jpn_x_preferred":[
        "\u8aad\u8c37\u6751"
    ],
    "name:jpn_x_variant":[
        "\u3088\u307f\u305f\u3093\u305d\u3093"
    ],
    "name:und_x_variant":[
        "Yontan"
    ],
    "qs:name":"Yomitan-son",
    "qs:photos_9r":0,
    "qs:photos_sr":0,
    "qs:pop_sr":"0",
    "wof:name":"Yomitan",
    "wof:placetype":"localadmin",
    "wof:population":0
},
  "geometry": {"coordinates":[127.74634,26.40008],"type":"Point"}
}