{
  "type": "Feature",
  "properties": {
    "gn:admin1_code":"4.0",
    "gn:admin2_code":"2111854.0",
    "gn:asciiname":"Misono",
    "gn:country_code":"JP",
    "gn:dem":5,
    "gn:feature_class":"P",
    "gn:feature_code":"PPLL",
    "gn:name":"Misono",
    "gn:population":0,
    "gn:timezone":"Asia/Tokyo",
    "iso:country":"JP",
    "name:jpn_x_preferred":[
        "\u5fa1\u5712"
    ],
    "name:jpn_x_variant":[
        "\u307f\u305d\u306e",
        "\u30df\u30bd\u30ce"
    ],
    "wof:name":"Misono",
    "wof:placetype":"locality"
},
  "geometry": {"coordinates":[140.36018999999999,35.48262000000001],"type":"Point"}
}