{
  "type": "Feature",
  "properties": {
    "gn:admin1_code":"21.0",
    "gn:admin2_code":"7413152.0",
    "gn:asciiname":"Ogawamachi-minamiono",
    "gn:country_code":"JP",
    "gn:dem":13,
    "gn:feature_class":"P",
    "gn:feature_code":"PPL",
    "gn:name":"Ogawamachi-minamiono",
    "gn:population":0,
    "gn:timezone":"Asia/Tokyo",
    "iso:country":"JP",
    "name:jpn_x_preferred":[
        "\u5c0f\u5ddd\u753a\u5357\u5c0f\u91ce"
    ],
    "name:jpn_x_variant":[
        "\u304a\u304c\u308f\u307e\u3061\u307f\u306a\u307f\u304a\u306e",
        "\u30aa\u30ac\u30ef\u30de\u30c1\u30df\u30ca\u30df\u30aa\u30ce"
    ],
    "wof:name":"Ogawamachi-minamiono",
    "wof:placetype":"locality"
},
  "geometry": {"coordinates":[130.71898000000002,32.60961],"type":"Point"}
}