{
  "type": "Feature",
  "properties": {
    "gn:admin1_code":"19.0",
    "gn:admin2_code":"1848350.0",
    "gn:admin3_code":"14118.0",
    "gn:asciiname":"Odanacho",
    "gn:country_code":"JP",
    "gn:dem":8,
    "gn:feature_class":"P",
    "gn:feature_code":"PPL",
    "gn:name":"\u014cdanach\u014d",
    "gn:population":0,
    "gn:timezone":"Asia/Tokyo",
    "iso:country":"JP",
    "name:jpn_x_preferred":[
        "\u5927\u68da\u753a"
    ],
    "name:und_x_variant":[
        "\u014cdanach\u014d"
    ],
    "wof:name":"Odanacho",
    "wof:placetype":"locality"
},
  "geometry": {"coordinates":[139.59394,35.54835999999999],"type":"Point"}
}