{
  "type": "Feature",
  "properties": {
    "gn:admin1_code":"45.0",
    "gn:admin2_code":"1852222.0",
    "gn:asciiname":"Chofu-kawabata",
    "gn:country_code":"JP",
    "gn:dem":29,
    "gn:feature_class":"P",
    "gn:feature_code":"PPL",
    "gn:name":"Ch\u014dfu-kawabata",
    "gn:population":0,
    "gn:timezone":"Asia/Tokyo",
    "iso:country":"JP",
    "name:jpn_x_preferred":[
        "\u9577\u5e9c\u5ddd\u7aef"
    ],
    "name:und_x_variant":[
        "Ch\u014dfu-kawabata"
    ],
    "wof:name":"Chofu-kawabata",
    "wof:placetype":"locality"
},
  "geometry": {"coordinates":[130.9821,33.99513],"type":"Point"}
}