{
  "type": "Feature",
  "properties": {
    "iso:country":"JP",
    "name:eng_x_preferred":[
        "Senamionsen 2 Chome"
    ],
    "name:eng_x_variant":[
        "Senamionsen 2 Choume",
        "Senamionsen 2 Chome"
    ],
    "name:jpn_x_preferred":[
        "\uff12\u4e01\u76ee"
    ],
    "name:jpn_x_variant":[
        "\u305b\u306a\u307f\u304a\u3093\u305b\u3093 \uff12\u3061\u3087\u3046\u3081",
        "\u702c\u6ce2\u6e29\u6cc9 \uff12\u4e01\u76ee",
        "\uff12\u3061\u3087\u3046\u3081"
    ],
    "qs:gn_local":0,
    "qs:local_max":311,
    "qs:local_sum":410,
    "qs:localhoods":3,
    "qs:name":"\uff12\u4e01\u76ee",
    "qs:name_adm0":"\u65e5\u672c",
    "qs:name_adm1":"\u65b0\u6f5f\u770c",
    "qs:name_en":"Senamionsen 2 Chome",
    "qs:name_lau":"\u702c\u6ce2\u6e29\u6cc9",
    "qs:name_local":"\u6751\u4e0a\u5e02",
    "qs:photo_max":9,
    "qs:photo_sum":21,
    "qs:placetype":"Suburb",
    "qs:quad_count":9,
    "qs:woe_adm0":23424856,
    "qs:woe_adm1":2345878,
    "qs:woe_adm2":0,
    "qs:woe_lau":28420326,
    "qs:woe_local":1117794,
    "qs:woe_ver":"7.10.0",
    "wof:lang":[
        "jpn"
    ],
    "wof:name":"\uff12\u4e01\u76ee",
    "wof:placetype":"neighbourhood"
},
  "geometry": {"coordinates":[139.441225,38.212597],"type":"Point"}
}