{
  "type": "Feature",
  "properties": {
    "gn:admin1_code":"33.0",
    "gn:admin2_code":"1853274.0",
    "gn:asciiname":"Morodomicho-tameshige",
    "gn:country_code":"JP",
    "gn:dem":5,
    "gn:feature_class":"P",
    "gn:feature_code":"PPL",
    "gn:name":"Morodomich\u014d-tameshige",
    "gn:population":0,
    "gn:timezone":"Asia/Tokyo",
    "iso:country":"JP",
    "name:jpn_x_preferred":[
        "\u8af8\u5bcc\u753a\u70ba\u91cd"
    ],
    "name:und_x_variant":[
        "Morodomich\u014d-tameshige"
    ],
    "wof:name":"Morodomicho-tameshige",
    "wof:placetype":"locality"
},
  "geometry": {"coordinates":[130.35013999999998,33.21491],"type":"Point"}
}