{
  "type": "Feature",
  "properties": {
    "gn:admin1_code":"2.0",
    "gn:admin2_code":"2128864.0",
    "gn:asciiname":"Matsubara",
    "gn:country_code":"JP",
    "gn:dem":6,
    "gn:feature_class":"P",
    "gn:feature_code":"PPL",
    "gn:name":"Matsubara",
    "gn:population":0,
    "gn:timezone":"Asia/Tokyo",
    "iso:country":"JP",
    "name:jpn_x_preferred":[
        "\u677e\u539f"
    ],
    "wof:name":"Matsubara",
    "wof:placetype":"locality"
},
  "geometry": {"coordinates":[140.04973000000001,40.21514000000001],"type":"Point"}
}