{
  "type": "Feature",
  "properties": {
    "gn:admin1_code":"37.0",
    "gn:admin2_code":"1864104.0",
    "gn:asciiname":"Sumigaito",
    "gn:country_code":"JP",
    "gn:dem":335,
    "gn:feature_class":"P",
    "gn:feature_code":"PPLL",
    "gn:name":"Sumigaito",
    "gn:population":0,
    "gn:timezone":"Asia/Tokyo",
    "iso:country":"JP",
    "name:jpn_x_preferred":[
        "\u89d2\u30f6\u8c37\u6238"
    ],
    "wof:name":"Sumigaito",
    "wof:placetype":"locality"
},
  "geometry": {"coordinates":[138.57674,35.28259],"type":"Point"}
}