{
  "type": "Feature",
  "properties": {
    "gn:admin1_code":"28.0",
    "gn:admin2_code":"1863590.0",
    "gn:asciiname":"Inukaicho",
    "gn:country_code":"JP",
    "gn:dem":105,
    "gn:feature_class":"P",
    "gn:feature_code":"PPL",
    "gn:name":"Inukaich\u014d",
    "gn:population":0,
    "gn:timezone":"Asia/Tokyo",
    "iso:country":"JP",
    "name:jpn_x_preferred":[
        "\u72ac\u98fc\u753a"
    ],
    "name:und_x_variant":[
        "Inukaich\u014d"
    ],
    "wof:name":"Inukaicho",
    "wof:placetype":"locality"
},
  "geometry": {"coordinates":[135.67668999999998,34.33895],"type":"Point"}
}