{
  "type": "Feature",
  "properties": {
    "iso:country":"JP",
    "name:eng_x_preferred":[
        "Unumaminamimachi 6 Chome"
    ],
    "name:eng_x_variant":[
        "Unumaminamimachi 6 Choume",
        "Unumaminamimachi 6 Chome"
    ],
    "name:jpn_x_preferred":[
        "\uff16\u4e01\u76ee"
    ],
    "name:jpn_x_variant":[
        "\u3046\u306c\u307e\u307f\u306a\u307f\u307e\u3061 \uff16\u3061\u3087\u3046\u3081",
        "\u9d5c\u6cbc\u5357\u753a \uff16\u4e01\u76ee",
        "\uff16\u3061\u3087\u3046\u3081"
    ],
    "name:unk_x_variant":[
        "\uff16\u4e01\u76ee"
    ],
    "qs:gn_adm0_cc":"JP",
    "qs:gn_local":1860735,
    "qs:gn_nam_loc":"\u5404\u52d9\u539f\u5e02, \u5c90\u961c\u770c, JP",
    "qs:gn_namadm1":"09",
    "qs:local_max":1099,
    "qs:local_sum":2705,
    "qs:localhoods":7,
    "qs:name":"\uff16\u4e01\u76ee",
    "qs:name_adm0":"\u65e5\u672c",
    "qs:name_adm1":"\u5c90\u961c\u770c",
    "qs:name_en":"Unumaminamimachi 6 Chome",
    "qs:name_lau":"\u9d5c\u6cbc\u5357\u753a",
    "qs:name_local":"\u5404\u52d9\u539f\u5e02",
    "qs:photo_max":39,
    "qs:photo_sum":73,
    "qs:placetype":"Suburb",
    "qs:quad_count":6,
    "qs:woe_adm0":23424856,
    "qs:woe_adm1":2345859,
    "qs:woe_adm2":0,
    "qs:woe_lau":28434945,
    "qs:woe_local":1109945,
    "qs:woe_ver":"7.10.0",
    "wof:lang":[
        "jpn"
    ],
    "wof:name":"\uff16\u4e01\u76ee",
    "wof:placetype":"neighbourhood"
},
  "geometry": {"coordinates":[136.946617,35.392021],"type":"Point"}
}