{
  "type": "Feature",
  "properties": {
    "iso:country":"JP",
    "qs:name":"\uff15\u4e01\u76ee",
    "qs:name_adm0":"\u65e5\u672c",
    "qs:name_adm1":"\u5927\u962a\u5e9c",
    "qs:photos":210,
    "qs:photos_1k":43,
    "qs:photos_9k":1,
    "qs:photos_9r":4,
    "qs:photos_all":210,
    "qs:photos_sr":4,
    "qs:placetype":"Suburb",
    "qs:pop_sr":"0",
    "wof:name":"\uff15\u4e01\u76ee",
    "wof:placetype":"neighbourhood"
},
  "geometry": {"coordinates":[135.438423,34.671022],"type":"Point"}
}