{
  "type": "Feature",
  "properties": {
    "gn:admin1_code":"4.0",
    "gn:admin2_code":"2112386.0",
    "gn:asciiname":"Fukawa",
    "gn:country_code":"JP",
    "gn:dem":87,
    "gn:feature_class":"P",
    "gn:feature_code":"PPLL",
    "gn:name":"Fukawa",
    "gn:population":0,
    "gn:timezone":"Asia/Tokyo",
    "iso:country":"JP",
    "name:jpn_x_preferred":[
        "\u5bcc\u5ddd"
    ],
    "name:jpn_x_variant":[
        "\u3075\u304b\u308f",
        "\u30d5\u30ab\u30ef"
    ],
    "wof:name":"Fukawa",
    "wof:placetype":"locality"
},
  "geometry": {"coordinates":[140.00519,35.12259],"type":"Point"}
}