{
  "type": "Feature",
  "properties": {
    "gn:admin1_code":"21.0",
    "gn:admin2_code":"1864975.0",
    "gn:admin3_code":"43432.0",
    "gn:asciiname":"Minamibaru",
    "gn:country_code":"JP",
    "gn:dem":415,
    "gn:feature_class":"P",
    "gn:feature_code":"PPLL",
    "gn:name":"Minamibaru",
    "gn:population":0,
    "gn:timezone":"Asia/Tokyo",
    "iso:country":"JP",
    "name:jpn_x_preferred":[
        "\u5357\u539f"
    ],
    "name:jpn_x_variant":[
        "\u307f\u306a\u307f\u3070\u308b",
        "\u30df\u30ca\u30df\u30d0\u30eb"
    ],
    "wof:name":"Minamibaru",
    "wof:placetype":"locality"
},
  "geometry": {"coordinates":[130.89382000000001,32.78783],"type":"Point"}
}