{
  "type": "Feature",
  "properties": {
    "gn:admin1_code":"14.0",
    "gn:admin2_code":"2111742.0",
    "gn:admin3_code":"8341.0",
    "gn:asciiname":"Ishigami-tojuku",
    "gn:cc2":"JP",
    "gn:country_code":"JP",
    "gn:dem":16,
    "gn:feature_class":"P",
    "gn:feature_code":"PPL",
    "gn:name":"Ishigami-tojuku",
    "gn:population":0,
    "gn:timezone":"Asia/Tokyo",
    "iso:country":"JP",
    "name:und_x_variant":[
        "Ishigami-tojiku",
        "Ishikami-toshuku",
        "Ishikami-tojuku",
        "Ishigami-tojuku"
    ],
    "wof:name":"Ishigami-tojuku",
    "wof:placetype":"locality"
},
  "geometry": {"coordinates":[140.55000000000001,36.48333],"type":"Point"}
}