{
  "type": "Feature",
  "properties": {
    "gn:admin1_code":"44.0",
    "gn:admin2_code":"7450018.0",
    "gn:asciiname":"Natagiri",
    "gn:country_code":"JP",
    "gn:dem":412,
    "gn:feature_class":"P",
    "gn:feature_code":"PPL",
    "gn:name":"Natagiri",
    "gn:population":0,
    "gn:timezone":"Asia/Tokyo",
    "iso:country":"JP",
    "name:jpn_x_preferred":[
        "\u5c71\u5200\u4f10"
    ],
    "name:jpn_x_variant":[
        "\u306a\u305f\u304e\u308a",
        "\u30ca\u30bf\u30ae\u30ea"
    ],
    "wof:name":"Natagiri",
    "wof:placetype":"locality"
},
  "geometry": {"coordinates":[140.52472,38.68458],"type":"Point"}
}