{
  "type": "Feature",
  "properties": {
    "gn:admin1_code":"23.0",
    "gn:admin2_code":"1849544.0",
    "gn:asciiname":"Geinoho-hagino",
    "gn:country_code":"JP",
    "gn:dem":43,
    "gn:feature_class":"P",
    "gn:feature_code":"PPL",
    "gn:name":"Gein\u014dh\u014d-hagino",
    "gn:population":0,
    "gn:timezone":"Asia/Tokyo",
    "iso:country":"JP",
    "name:jpn_x_preferred":[
        "\u82b8\u6fc3\u753a\u8429\u91ce"
    ],
    "name:und_x_variant":[
        "Gein\u014dh\u014d-hagino"
    ],
    "wof:name":"Geinoho-hagino",
    "wof:placetype":"locality"
},
  "geometry": {"coordinates":[136.43661,34.79469],"type":"Point"}
}