{
  "type": "Feature",
  "properties": {
    "gn:admin1_code":"05",
    "gn:admin2_code":"1926135.0",
    "gn:asciiname":"Kitamura",
    "gn:country_code":"JP",
    "gn:dem":4,
    "gn:feature_class":"P",
    "gn:feature_code":"PPL",
    "gn:name":"Kitamura",
    "gn:population":0,
    "gn:timezone":"Asia/Tokyo",
    "iso:country":"JP",
    "name:und_x_variant":[
        "Kito"
    ],
    "wof:name":"Kitamura",
    "wof:placetype":"locality"
},
  "geometry": {"coordinates":[133.02392,34.04501],"type":"Point"}
}