{
  "type": "Feature",
  "properties": {
    "gn:admin1_code":"18",
    "gn:admin2_code":"1853737.0",
    "gn:admin3_code":"46525.0",
    "gn:asciiname":"Ikeji",
    "gn:country_code":"JP",
    "gn:dem":5,
    "gn:feature_class":"P",
    "gn:feature_code":"PPL",
    "gn:name":"Ikeji",
    "gn:population":0,
    "gn:timezone":"Asia/Tokyo",
    "iso:country":"JP",
    "name:jpn_x_preferred":[
        "\u6c60\u5730"
    ],
    "name:und_x_variant":[
        "Ikezi",
        "Ikeji",
        "Ikechi"
    ],
    "wof:name":"Ikeji",
    "wof:placetype":"locality"
},
  "geometry": {"coordinates":[129.23268999999999,28.02981],"type":"Point"}
}