{
  "type": "Feature",
  "properties": {
    "gn:admin1_code":"43",
    "gn:admin2_code":"1860782.0",
    "gn:asciiname":"Shimotsucho-kominami",
    "gn:country_code":"JP",
    "gn:dem":11,
    "gn:feature_class":"P",
    "gn:feature_code":"PPL",
    "gn:name":"Shimotsuch\u014d-kominami",
    "gn:population":0,
    "gn:timezone":"Asia/Tokyo",
    "iso:country":"JP",
    "name:jpn_x_preferred":[
        "\u4e0b\u6d25\u753a\u5c0f\u5357"
    ],
    "name:und_x_variant":[
        "Konan",
        "Kominami",
        "Shimotsuch\u014d-kominami"
    ],
    "wof:name":"Shimotsucho-kominami",
    "wof:placetype":"locality"
},
  "geometry": {"coordinates":[135.17216000000002,34.12568],"type":"Point"}
}