{
  "type": "Feature",
  "properties": {
    "gn:admin1_code":"21.0",
    "gn:admin2_code":"1858418.0",
    "gn:admin3_code":"43102.0",
    "gn:asciiname":"Kubo",
    "gn:country_code":"JP",
    "gn:dem":52,
    "gn:feature_class":"P",
    "gn:feature_code":"PPLL",
    "gn:name":"Kubo",
    "gn:population":0,
    "gn:timezone":"Asia/Tokyo",
    "iso:country":"JP",
    "name:jpn_x_preferred":[
        "\u4e45\u4fdd"
    ],
    "name:jpn_x_variant":[
        "\u304f\u307c",
        "\u30af\u30dc"
    ],
    "wof:name":"Kubo",
    "wof:placetype":"locality"
},
  "geometry": {"coordinates":[130.78743,32.84561],"type":"Point"}
}