{
  "type": "Feature",
  "properties": {
    "gn:admin1_code":"3.0",
    "gn:admin2_code":"2127674.0",
    "gn:asciiname":"Dannodai",
    "gn:country_code":"JP",
    "gn:dem":146,
    "gn:feature_class":"P",
    "gn:feature_code":"PPL",
    "gn:name":"Dannodai",
    "gn:population":0,
    "gn:timezone":"Asia/Tokyo",
    "iso:country":"JP",
    "name:jpn_x_preferred":[
        "\u6bb5\u30ce\u53f0"
    ],
    "name:jpn_x_variant":[
        "\u3060\u3093\u306e\u3060\u3044",
        "\u30c0\u30f3\u30ce\u30c0\u30a4"
    ],
    "wof:name":"Dannodai",
    "wof:placetype":"locality"
},
  "geometry": {"coordinates":[141.11285000000001,40.59663],"type":"Point"}
}