{
  "type": "Feature",
  "properties": {
    "gn:admin1_code":"7.0",
    "gn:admin2_code":"7406950.0",
    "gn:admin3_code":"40621.0",
    "gn:asciiname":"Kinomoto",
    "gn:country_code":"JP",
    "gn:dem":0,
    "gn:feature_class":"P",
    "gn:feature_code":"PPLL",
    "gn:name":"Kinomoto",
    "gn:population":0,
    "gn:timezone":"Asia/Tokyo",
    "iso:country":"JP",
    "name:jpn_x_preferred":[
        "\u6728\u30ce\u5143"
    ],
    "wof:name":"Kinomoto",
    "wof:placetype":"locality"
},
  "geometry": {"coordinates":[130.96066000000002,33.73962],"type":"Point"}
}