{
  "type": "Feature",
  "properties": {
    "gn:admin1_code":"8.0",
    "gn:admin2_code":"2111029.0",
    "gn:asciiname":"Tozura",
    "gn:country_code":"JP",
    "gn:dem":326,
    "gn:feature_class":"P",
    "gn:feature_code":"PPLL",
    "gn:name":"Tozura",
    "gn:population":0,
    "gn:timezone":"Asia/Tokyo",
    "iso:country":"JP",
    "name:jpn_x_preferred":[
        "\u5916\u9762"
    ],
    "wof:name":"Tozura",
    "wof:placetype":"locality"
},
  "geometry": {"coordinates":[140.22228000000001,37.18506],"type":"Point"}
}