{
  "type": "Feature",
  "properties": {
    "gn:admin1_code":"37.0",
    "gn:admin2_code":"1864089.0",
    "gn:asciiname":"Manno",
    "gn:country_code":"JP",
    "gn:dem":104,
    "gn:feature_class":"P",
    "gn:feature_code":"PPLL",
    "gn:name":"Manno",
    "gn:population":0,
    "gn:timezone":"Asia/Tokyo",
    "iso:country":"JP",
    "name:jpn_x_preferred":[
        "\u4e07\u91ce"
    ],
    "wof:name":"Manno",
    "wof:placetype":"locality"
},
  "geometry": {"coordinates":[138.62096,35.17903],"type":"Point"}
}