{
  "type": "Feature",
  "properties": {
    "gn:admin1_code":"37.0",
    "gn:admin2_code":"9036693.0",
    "gn:asciiname":"Tokunaga",
    "gn:country_code":"JP",
    "gn:dem":224,
    "gn:feature_class":"P",
    "gn:feature_code":"PPL",
    "gn:name":"Tokunaga",
    "gn:population":0,
    "gn:timezone":"Asia/Tokyo",
    "iso:country":"JP",
    "name:jpn_x_preferred":[
        "\u5fb3\u6c38"
    ],
    "wof:name":"Tokunaga",
    "wof:placetype":"locality"
},
  "geometry": {"coordinates":[139.03086999999999,34.94574],"type":"Point"}
}