{
  "type": "Feature",
  "properties": {
    "gn:admin1_code":"32.0",
    "gn:admin2_code":"1852716.0",
    "gn:admin3_code":"27366.0",
    "gn:asciiname":"Tanagawa-nishibata",
    "gn:country_code":"JP",
    "gn:dem":95,
    "gn:feature_class":"P",
    "gn:feature_code":"PPL",
    "gn:name":"Tanagawa-nishibata",
    "gn:population":0,
    "gn:timezone":"Asia/Tokyo",
    "iso:country":"JP",
    "name:jpn_x_preferred":[
        "\u591a\u5948\u5ddd\u897f\u7551"
    ],
    "wof:name":"Tanagawa-nishibata",
    "wof:placetype":"locality"
},
  "geometry": {"coordinates":[135.11342999999999,34.28694],"type":"Point"}
}