{
  "type": "Feature",
  "properties": {
    "gn:admin1_code":"4.0",
    "gn:admin2_code":"2112997.0",
    "gn:admin3_code":"12427.0",
    "gn:asciiname":"Miyamoto",
    "gn:country_code":"JP",
    "gn:dem":82,
    "gn:feature_class":"P",
    "gn:feature_code":"PPLL",
    "gn:name":"Miyamoto",
    "gn:population":0,
    "gn:timezone":"Asia/Tokyo",
    "iso:country":"JP",
    "name:jpn_x_preferred":[
        "\u5bae\u672c"
    ],
    "name:jpn_x_variant":[
        "\u307f\u3084\u3082\u3068",
        "\u30df\u30e4\u30e2\u30c8"
    ],
    "name:lav_x_preferred":[
        "Mijamoto"
    ],
    "wof:name":"Miyamoto",
    "wof:placetype":"locality"
},
  "geometry": {"coordinates":[140.21893,35.354],"type":"Point"}
}