{
  "type": "Feature",
  "properties": {
    "gn:admin1_code":"18.0",
    "gn:admin2_code":"1865649.0",
    "gn:admin3_code":"46452.0",
    "gn:asciiname":"Furukawa",
    "gn:country_code":"JP",
    "gn:dem":211,
    "gn:feature_class":"P",
    "gn:feature_code":"PPLL",
    "gn:name":"Furukawa",
    "gn:population":0,
    "gn:timezone":"Asia/Tokyo",
    "iso:country":"JP",
    "name:jpn_x_preferred":[
        "\u53e4\u5ddd"
    ],
    "name:jpn_x_variant":[
        "\u3075\u308b\u304b\u308f",
        "\u30d5\u30eb\u30ab\u30ef"
    ],
    "wof:name":"Furukawa",
    "wof:placetype":"locality"
},
  "geometry": {"coordinates":[130.74788000000001,32.01152],"type":"Point"}
}