{
  "type": "Feature",
  "properties": {
    "gn:admin1_code":"37.0",
    "gn:admin2_code":"1864089.0",
    "gn:asciiname":"Atsuharaminami",
    "gn:country_code":"JP",
    "gn:dem":41,
    "gn:feature_class":"P",
    "gn:feature_code":"PPLL",
    "gn:name":"Atsuharaminami",
    "gn:population":0,
    "gn:timezone":"Asia/Tokyo",
    "iso:country":"JP",
    "name:jpn_x_preferred":[
        "\u539a\u539f\u5357"
    ],
    "wof:name":"Atsuharaminami",
    "wof:placetype":"locality"
},
  "geometry": {"coordinates":[138.65698999999998,35.18063],"type":"Point"}
}