{
  "type": "Feature",
  "properties": {
    "gn:admin1_code":"7.0",
    "gn:admin2_code":"7406950.0",
    "gn:admin3_code":"40621.0",
    "gn:asciiname":"Atsumari",
    "gn:country_code":"JP",
    "gn:dem":10,
    "gn:feature_class":"P",
    "gn:feature_code":"PPL",
    "gn:name":"Atsumari",
    "gn:population":0,
    "gn:timezone":"Asia/Tokyo",
    "iso:country":"JP",
    "name:jpn_x_preferred":[
        "\u96c6"
    ],
    "wof:name":"Atsumari",
    "wof:placetype":"locality"
},
  "geometry": {"coordinates":[130.97391999999999,33.76905],"type":"Point"}
}