{
  "type": "Feature",
  "properties": {
    "gn:admin1_code":"4.0",
    "gn:admin2_code":"1856183.0",
    "gn:asciiname":"Mihara",
    "gn:country_code":"JP",
    "gn:dem":23,
    "gn:feature_class":"P",
    "gn:feature_code":"PPL",
    "gn:name":"Mihara",
    "gn:population":0,
    "gn:timezone":"Asia/Tokyo",
    "iso:country":"JP",
    "name:ceb_x_preferred":[
        "Mihara"
    ],
    "name:deu_x_preferred":[
        "Mihara"
    ],
    "name:fra_x_preferred":[
        "Mihara"
    ],
    "name:jpn_x_preferred":[
        "\u7f8e\u539f"
    ],
    "name:mlg_x_preferred":[
        "Mihara"
    ],
    "name:pol_x_preferred":[
        "Mihara"
    ],
    "name:rus_x_preferred":[
        "\u041c\u0438\u0445\u0430\u0440\u0430"
    ],
    "name:spa_x_preferred":[
        "Mihara"
    ],
    "wof:name":"Mihara",
    "wof:placetype":"locality"
},
  "geometry": {"coordinates":[139.90430000000001,35.9011],"type":"Point"}
}