{
  "type": "Feature",
  "properties": {
    "gn:admin1_code":"40.0",
    "gn:admin2_code":"1858665.0",
    "gn:asciiname":"Sumiyoshi",
    "gn:country_code":"JP",
    "gn:dem":7,
    "gn:feature_class":"P",
    "gn:feature_code":"PPL",
    "gn:name":"Sumiyoshi",
    "gn:population":0,
    "gn:timezone":"Asia/Tokyo",
    "iso:country":"JP",
    "name:jpn_x_preferred":[
        "\u4f4f\u5409"
    ],
    "wof:name":"Sumiyoshi",
    "wof:placetype":"locality"
},
  "geometry": {"coordinates":[139.81471000000002,35.68868],"type":"Point"}
}