{
  "type": "Feature",
  "properties": {
    "gn:admin1_code":"21.0",
    "gn:admin2_code":"1859488.0",
    "gn:asciiname":"Nagayama",
    "gn:country_code":"JP",
    "gn:dem":389,
    "gn:feature_class":"P",
    "gn:feature_code":"PPLL",
    "gn:name":"Nagayama",
    "gn:population":0,
    "gn:timezone":"Asia/Tokyo",
    "iso:country":"JP",
    "name:jpn_x_preferred":[
        "\u6c38\u5c71"
    ],
    "name:jpn_x_variant":[
        "\u306a\u304c\u3084\u307e",
        "\u30ca\u30ac\u30e4\u30de"
    ],
    "wof:name":"Nagayama",
    "wof:placetype":"locality"
},
  "geometry": {"coordinates":[130.90756999999999,33.01082],"type":"Point"}
}