{
  "type": "Feature",
  "properties": {
    "gn:admin1_code":"21.0",
    "gn:admin2_code":"1858418.0",
    "gn:admin3_code":"43105.0",
    "gn:asciiname":"Taromaru",
    "gn:country_code":"JP",
    "gn:dem":88,
    "gn:feature_class":"P",
    "gn:feature_code":"PPLL",
    "gn:name":"Tar\u014dmaru",
    "gn:population":0,
    "gn:timezone":"Asia/Tokyo",
    "iso:country":"JP",
    "name:jpn_x_preferred":[
        "\u592a\u90ce\u4e38"
    ],
    "name:jpn_x_variant":[
        "\u305f\u308d\u3046\u307e\u308b",
        "\u30bf\u30ed\u30a6\u30de\u30eb"
    ],
    "name:und_x_variant":[
        "Tar\u014dmaru"
    ],
    "wof:name":"Taromaru",
    "wof:placetype":"locality"
},
  "geometry": {"coordinates":[130.69696000000002,32.93484],"type":"Point"}
}