{
  "type": "Feature",
  "properties": {
    "gn:admin1_code":"4.0",
    "gn:admin2_code":"1856183.0",
    "gn:asciiname":"Hiregasaki",
    "gn:country_code":"JP",
    "gn:dem":5,
    "gn:feature_class":"P",
    "gn:feature_code":"PPL",
    "gn:name":"Hiregasaki",
    "gn:population":0,
    "gn:timezone":"Asia/Tokyo",
    "iso:country":"JP",
    "name:jpn_x_preferred":[
        "\u9c2d\u30f6\u5d0e"
    ],
    "wof:name":"Hiregasaki",
    "wof:placetype":"locality"
},
  "geometry": {"coordinates":[139.91130000000001,35.8394],"type":"Point"}
}