{
  "type": "Feature",
  "properties": {
    "gn:admin1_code":"6.0",
    "gn:admin2_code":"1859762.0",
    "gn:asciiname":"Osowacho-obukuro",
    "gn:country_code":"JP",
    "gn:dem":159,
    "gn:feature_class":"P",
    "gn:feature_code":"PPL",
    "gn:name":"Osowach\u014d-\u014dbukuro",
    "gn:population":0,
    "gn:timezone":"Asia/Tokyo",
    "iso:country":"JP",
    "name:jpn_x_preferred":[
        "\u9045\u7fbd\u753a\u5927\u888b"
    ],
    "name:und_x_variant":[
        "Osowach\u014d-\u014dbukuro"
    ],
    "wof:name":"Osowacho-obukuro",
    "wof:placetype":"locality"
},
  "geometry": {"coordinates":[136.48625000000001,36.0357],"type":"Point"}
}