{
  "type": "Feature",
  "properties": {
    "gn:admin1_code":"42.0",
    "gn:admin2_code":"1851028.0",
    "gn:asciiname":"Saida",
    "gn:country_code":"JP",
    "gn:dem":26,
    "gn:feature_class":"P",
    "gn:feature_code":"PPL",
    "gn:name":"Saida",
    "gn:population":0,
    "gn:timezone":"Asia/Tokyo",
    "iso:country":"JP",
    "name:jpn_x_preferred":[
        "\u897f\u7530"
    ],
    "wof:name":"Saida",
    "wof:placetype":"locality"
},
  "geometry": {"coordinates":[137.00599,36.81037],"type":"Point"}
}