{
  "type": "Feature",
  "properties": {
    "gn:admin1_code":"24.0",
    "gn:admin2_code":"2112574.0",
    "gn:asciiname":"Yotsuya",
    "gn:country_code":"JP",
    "gn:dem":2,
    "gn:feature_class":"P",
    "gn:feature_code":"PPL",
    "gn:name":"Yotsuya",
    "gn:population":0,
    "gn:timezone":"Asia/Tokyo",
    "iso:country":"JP",
    "name:fas_x_preferred":[
        "\u06cc\u0648\u062a\u0633\u0648\u06cc\u0627"
    ],
    "name:fra_x_preferred":[
        "Yotsuya"
    ],
    "name:jpn_x_preferred":[
        "\u56db\u30c4\u5bb6"
    ],
    "name:jpn_x_variant":[
        "\u3088\u3064\u3084",
        "\u30e8\u30c4\u30e4"
    ],
    "wof:name":"Yotsuya",
    "wof:placetype":"locality"
},
  "geometry": {"coordinates":[141.26910000000001,38.48801],"type":"Point"}
}