{
  "type": "Feature",
  "properties": {
    "gn:admin1_code":"34.0",
    "gn:admin2_code":"1859739.0",
    "gn:asciiname":"Takashima",
    "gn:country_code":"JP",
    "gn:dem":11,
    "gn:feature_class":"P",
    "gn:feature_code":"PPL",
    "gn:name":"Takashima",
    "gn:population":0,
    "gn:timezone":"Asia/Tokyo",
    "iso:country":"JP",
    "name:ces_x_preferred":[
        "Taka\u0161ima"
    ],
    "name:deu_x_preferred":[
        "Takashima"
    ],
    "name:fas_x_preferred":[
        "\u062a\u0627\u06a9\u0627\u0634\u06cc\u0645\u0627"
    ],
    "name:jpn_x_preferred":[
        "\u9ad8\u5cf6"
    ],
    "name:kor_x_preferred":[
        "\ub2e4\uce74\uc2dc\ub9c8"
    ],
    "name:por_x_preferred":[
        "Takashima"
    ],
    "name:ron_x_preferred":[
        "Takashima"
    ],
    "name:ukr_x_preferred":[
        "\u0422\u0430\u043a\u0430\u0441\u0456\u043c\u0430"
    ],
    "wof:name":"Takashima",
    "wof:placetype":"locality"
},
  "geometry": {"coordinates":[139.50867,35.9142],"type":"Point"}
}