{
  "type": "Feature",
  "properties": {
    "gn:admin1_code":"25.0",
    "gn:admin2_code":"1864313.0",
    "gn:asciiname":"Shimosuenaga",
    "gn:country_code":"JP",
    "gn:dem":251,
    "gn:feature_class":"P",
    "gn:feature_code":"PPLL",
    "gn:name":"Shimosuenaga",
    "gn:population":0,
    "gn:timezone":"Asia/Tokyo",
    "iso:country":"JP",
    "name:jpn_x_preferred":[
        "\u4e0b\u672b\u6c38"
    ],
    "name:jpn_x_variant":[
        "\u3057\u3082\u3059\u3048\u306a\u304c",
        "\u30b7\u30e2\u30b9\u30a8\u30ca\u30ac"
    ],
    "wof:name":"Shimosuenaga",
    "wof:placetype":"locality"
},
  "geometry": {"coordinates":[130.82622000000001,32.03333],"type":"Point"}
}