{
  "type": "Feature",
  "properties": {
    "gn:admin1_code":"21.0",
    "gn:admin2_code":"1850743.0",
    "gn:asciiname":"Tsuijinishi",
    "gn:country_code":"JP",
    "gn:dem":20,
    "gn:feature_class":"P",
    "gn:feature_code":"PPLL",
    "gn:name":"Tsuijinishi",
    "gn:population":0,
    "gn:timezone":"Asia/Tokyo",
    "iso:country":"JP",
    "name:jpn_x_preferred":[
        "\u7bc9\u5730\u897f"
    ],
    "name:jpn_x_variant":[
        "\u3064\u3044\u3058\u306b\u3057",
        "\u30c4\u30a4\u30b8\u30cb\u30b7"
    ],
    "wof:name":"Tsuijinishi",
    "wof:placetype":"locality"
},
  "geometry": {"coordinates":[130.52721,32.93419],"type":"Point"}
}