{
  "type": "Feature",
  "properties": {
    "gn:admin1_code":"24.0",
    "gn:admin2_code":"7446987.0",
    "gn:admin3_code":"4505.0",
    "gn:asciiname":"Kogota-ekimae",
    "gn:cc2":"JP",
    "gn:country_code":"JP",
    "gn:dem":15,
    "gn:feature_class":"P",
    "gn:feature_code":"PPL",
    "gn:name":"Kogota-ekimae",
    "gn:population":0,
    "gn:timezone":"Asia/Tokyo",
    "iso:country":"JP",
    "name:und_x_variant":[
        "Fujigasaki",
        "Kogota-ekimae"
    ],
    "wof:name":"Kogota-ekimae",
    "wof:placetype":"locality"
},
  "geometry": {"coordinates":[141.06666999999999,38.53333],"type":"Point"}
}