{
  "type": "Feature",
  "properties": {
    "gn:admin1_code":"43.0",
    "gn:admin2_code":"7411114.0",
    "gn:asciiname":"Nishiwaki",
    "gn:country_code":"JP",
    "gn:dem":44,
    "gn:feature_class":"P",
    "gn:feature_code":"PPL",
    "gn:name":"Nishiwaki",
    "gn:population":0,
    "gn:timezone":"Asia/Tokyo",
    "iso:country":"JP",
    "name:jpn_x_preferred":[
        "\u897f\u8107"
    ],
    "wof:name":"Nishiwaki",
    "wof:placetype":"locality"
},
  "geometry": {"coordinates":[135.43547000000001,34.26263],"type":"Point"}
}