{
  "type": "Feature",
  "properties": {
    "gn:admin1_code":"6.0",
    "gn:admin2_code":"7465770.0",
    "gn:admin3_code":"18322.0",
    "gn:asciiname":"Yoshimine",
    "gn:country_code":"JP",
    "gn:dem":135,
    "gn:feature_class":"P",
    "gn:feature_code":"PPL",
    "gn:name":"Yoshimine",
    "gn:population":0,
    "gn:timezone":"Asia/Tokyo",
    "iso:country":"JP",
    "name:jpn_x_preferred":[
        "\u5409\u5cf0"
    ],
    "wof:name":"Yoshimine",
    "wof:placetype":"locality"
},
  "geometry": {"coordinates":[136.42256,36.06253],"type":"Point"}
}