{
  "type": "Feature",
  "properties": {
    "gn:admin1_code":"3.0",
    "gn:admin2_code":"2128302.0",
    "gn:admin3_code":"2443.0",
    "gn:asciiname":"Shirakaba",
    "gn:country_code":"JP",
    "gn:dem":222,
    "gn:feature_class":"P",
    "gn:feature_code":"PPL",
    "gn:name":"Shirakaba",
    "gn:population":0,
    "gn:timezone":"Asia/Tokyo",
    "iso:country":"JP",
    "name:jpn_x_preferred":[
        "\u767d\u691b"
    ],
    "name:jpn_x_variant":[
        "\u3057\u3089\u304b\u3070",
        "\u30b7\u30e9\u30ab\u30d0"
    ],
    "wof:name":"Shirakaba",
    "wof:placetype":"locality"
},
  "geometry": {"coordinates":[141.09962999999999,40.36805],"type":"Point"}
}