{
  "type": "Feature",
  "properties": {
    "gn:admin1_code":"7.0",
    "gn:admin2_code":"1859306.0",
    "gn:admin3_code":"40106.0",
    "gn:asciiname":"Kurobaru",
    "gn:country_code":"JP",
    "gn:dem":19,
    "gn:feature_class":"P",
    "gn:feature_code":"PPL",
    "gn:name":"Kurobaru",
    "gn:population":0,
    "gn:timezone":"Asia/Tokyo",
    "iso:country":"JP",
    "name:jpn_x_preferred":[
        "\u9ed2\u539f"
    ],
    "wof:name":"Kurobaru",
    "wof:placetype":"locality"
},
  "geometry": {"coordinates":[130.89943,33.86129],"type":"Point"}
}