{
  "type": "Feature",
  "properties": {
    "gn:admin1_code":"4.0",
    "gn:admin2_code":"8304237.0",
    "gn:asciiname":"Hachimandai",
    "gn:country_code":"JP",
    "gn:dem":122,
    "gn:feature_class":"P",
    "gn:feature_code":"PPLL",
    "gn:name":"Hachimandai",
    "gn:population":0,
    "gn:timezone":"Asia/Tokyo",
    "iso:country":"JP",
    "name:jpn_x_preferred":[
        "\u516b\u4e07\u53f0"
    ],
    "name:jpn_x_variant":[
        "\u306f\u3061\u307e\u3093\u3060\u3044",
        "\u30cf\u30c1\u30de\u30f3\u30c0\u30a4"
    ],
    "wof:name":"Hachimandai",
    "wof:placetype":"locality"
},
  "geometry": {"coordinates":[140.01498000000001,35.32962],"type":"Point"}
}