{
  "type": "Feature",
  "properties": {
    "gn:admin1_code":"42.0",
    "gn:admin2_code":"1852239.0",
    "gn:admin3_code":"16342.0",
    "gn:asciiname":"Yoshiwara",
    "gn:country_code":"JP",
    "gn:dem":6,
    "gn:feature_class":"P",
    "gn:feature_code":"PPL",
    "gn:name":"Yoshiwara",
    "gn:population":0,
    "gn:timezone":"Asia/Tokyo",
    "iso:country":"JP",
    "name:jpn_x_preferred":[
        "\u5409\u539f"
    ],
    "wof:name":"Yoshiwara",
    "wof:placetype":"locality"
},
  "geometry": {"coordinates":[137.48011,36.94132000000001],"type":"Point"}
}