{
  "type": "Feature",
  "properties": {
    "gn:admin1_code":"24.0",
    "gn:admin2_code":"2111045.0",
    "gn:asciiname":"Ishida",
    "gn:country_code":"JP",
    "gn:dem":20,
    "gn:feature_class":"P",
    "gn:feature_code":"PPL",
    "gn:name":"Ishida",
    "gn:population":0,
    "gn:timezone":"Asia/Tokyo",
    "iso:country":"JP",
    "name:jpn_x_preferred":[
        "\u77f3\u7530"
    ],
    "name:jpn_x_variant":[
        "\u3044\u3057\u3060",
        "\u30a4\u30b7\u30c0"
    ],
    "wof:name":"Ishida",
    "wof:placetype":"locality"
},
  "geometry": {"coordinates":[141.03113999999999,38.33711],"type":"Point"}
}