{
  "type": "Feature",
  "properties": {
    "gn:admin1_code":"2.0",
    "gn:admin2_code":"2128783.0",
    "gn:asciiname":"Shigenai-yashiki",
    "gn:country_code":"JP",
    "gn:dem":179,
    "gn:feature_class":"P",
    "gn:feature_code":"PPLL",
    "gn:name":"Shigenai-yashiki",
    "gn:population":0,
    "gn:timezone":"Asia/Tokyo",
    "iso:country":"JP",
    "name:jpn_x_preferred":[
        "\u8302\u5185\u5c4b\u6577"
    ],
    "name:jpn_x_variant":[
        "\u3057\u3052\u306a\u3044\u3084\u3057\u304d",
        "\u30b7\u30b2\u30ca\u30a4\u30e4\u30b7\u30ad"
    ],
    "name:und_x_variant":[
        "Shigenai"
    ],
    "wof:name":"Shigenai-yashiki",
    "wof:placetype":"locality"
},
  "geometry": {"coordinates":[140.68771999999998,40.29292],"type":"Point"}
}