{
  "type": "Feature",
  "properties": {
    "gn:admin1_code":"47",
    "gn:admin2_code":"1855990.0",
    "gn:admin3_code":"47324.0",
    "gn:asciiname":"Furugen",
    "gn:country_code":"JP",
    "gn:dem":24,
    "gn:feature_class":"P",
    "gn:feature_code":"PPL",
    "gn:name":"Furugen",
    "gn:population":0,
    "gn:timezone":"Asia/Tokyo",
    "iso:country":"JP",
    "name:jpn_x_preferred":[
        "\u53e4\u5805"
    ],
    "name:jpn_x_variant":[
        "\u3075\u308b\u3052\u3093"
    ],
    "name:und_x_variant":[
        "Furugan",
        "Furugin",
        "Furuken",
        "Furugen"
    ],
    "wof:name":"Furugen",
    "wof:placetype":"locality"
},
  "geometry": {"coordinates":[127.75111,26.36859],"type":"Point"}
}