{
  "type": "Feature",
  "properties": {
    "gn:admin1_code":"34",
    "gn:admin2_code":"1863182.0",
    "gn:asciiname":"Shomaru",
    "gn:country_code":"JP",
    "gn:dem":259,
    "gn:feature_class":"P",
    "gn:feature_code":"PPL",
    "gn:name":"Sh\u014dmaru",
    "gn:population":0,
    "gn:timezone":"Asia/Tokyo",
    "iso:country":"JP",
    "name:und_x_variant":[
        "Sh\u014dmaru"
    ],
    "wof:name":"Shomaru",
    "wof:placetype":"locality"
},
  "geometry": {"coordinates":[139.20056,35.93444],"type":"Point"}
}