{
  "type": "Feature",
  "properties": {
    "iso:country":"JP",
    "name:eng_x_preferred":[
        "Higashigatacho 1 Chome"
    ],
    "name:eng_x_variant":[
        "Higashigatachou 1 Choume",
        "Higashigatacho 1 Chome"
    ],
    "name:jpn_x_preferred":[
        "\uff11\u4e01\u76ee"
    ],
    "name:jpn_x_variant":[
        "\u3072\u304c\u3057\u304c\u305f\u3061\u3087\u3046 \uff11\u3061\u3087\u3046\u3081",
        "\u6771\u65b9\u753a \uff11\u4e01\u76ee",
        "\uff11\u3061\u3087\u3046\u3081"
    ],
    "qs:gn_local":0,
    "qs:local_max":551,
    "qs:local_sum":644,
    "qs:localhoods":2,
    "qs:name":"\uff11\u4e01\u76ee",
    "qs:name_adm0":"\u65e5\u672c",
    "qs:name_adm1":"\u57fc\u7389\u770c",
    "qs:name_en":"Higashigatacho 1 Chome",
    "qs:name_lau":"\u6771\u65b9\u753a",
    "qs:name_local":"\u6df1\u8c37\u5e02",
    "qs:photo_max":43,
    "qs:photo_sum":93,
    "qs:placetype":"Suburb",
    "qs:quad_count":11,
    "qs:woe_adm0":23424856,
    "qs:woe_adm1":2345883,
    "qs:woe_adm2":0,
    "qs:woe_lau":28409050,
    "qs:woe_local":1117092,
    "qs:woe_ver":"7.10.0",
    "wof:lang":[
        "jpn"
    ],
    "wof:name":"\uff11\u4e01\u76ee",
    "wof:placetype":"neighbourhood"
},
  "geometry": {"coordinates":[139.31166200000001,36.194667],"type":"Point"}
}