{
  "type": "Feature",
  "properties": {
    "gn:admin1_code":"40.0",
    "gn:admin2_code":"1852675.0",
    "gn:asciiname":"Nozawa",
    "gn:country_code":"JP",
    "gn:dem":39,
    "gn:feature_class":"P",
    "gn:feature_code":"PPL",
    "gn:name":"Nozawa",
    "gn:population":0,
    "gn:timezone":"Asia/Tokyo",
    "iso:country":"JP",
    "name:jpn_x_preferred":[
        "\u91ce\u6ca2"
    ],
    "wof:name":"Nozawa",
    "wof:placetype":"locality"
},
  "geometry": {"coordinates":[139.67185000000001,35.63314000000001],"type":"Point"}
}