{
  "type": "Feature",
  "properties": {
    "gn:admin1_code":"2.0",
    "gn:admin2_code":"2128864.0",
    "gn:asciiname":"Nihata",
    "gn:country_code":"JP",
    "gn:dem":29,
    "gn:feature_class":"P",
    "gn:feature_code":"PPL",
    "gn:name":"Nihata",
    "gn:population":0,
    "gn:timezone":"Asia/Tokyo",
    "iso:country":"JP",
    "name:jpn_x_preferred":[
        "\u8377\u516b\u7530"
    ],
    "wof:name":"Nihata",
    "wof:placetype":"locality"
},
  "geometry": {"coordinates":[140.06995000000001,40.22643],"type":"Point"}
}