{
  "type": "Feature",
  "properties": {
    "gn:admin1_code":"21.0",
    "gn:admin2_code":"1848441.0",
    "gn:asciiname":"Okawachi",
    "gn:country_code":"JP",
    "gn:dem":126,
    "gn:feature_class":"P",
    "gn:feature_code":"PPLL",
    "gn:name":"Okawachi",
    "gn:population":0,
    "gn:timezone":"Asia/Tokyo",
    "iso:country":"JP",
    "name:jpn_x_preferred":[
        "\u5c0f\u5ddd\u5185"
    ],
    "wof:name":"Okawachi",
    "wof:placetype":"locality"
},
  "geometry": {"coordinates":[130.57804999999999,32.3885],"type":"Point"}
}