{
  "type": "Feature",
  "properties": {
    "gn:admin1_code":"12.0",
    "gn:admin2_code":"2127817.0",
    "gn:admin3_code":"1486.0",
    "gn:asciiname":"Utakoshi",
    "gn:country_code":"JP",
    "gn:dem":11,
    "gn:feature_class":"P",
    "gn:feature_code":"PPL",
    "gn:name":"Utakoshi",
    "gn:population":0,
    "gn:timezone":"Asia/Tokyo",
    "iso:country":"JP",
    "name:eng_x_preferred":[
        "Utakoshi"
    ],
    "name:jpn_x_preferred":[
        "\u6b4c\u8d8a"
    ],
    "name:jpn_x_variant":[
        "\u3046\u305f\u3053\u3057",
        "\u30a6\u30bf\u30b3\u30b7"
    ],
    "name:rus_x_preferred":[
        "\u0423\u0442\u0430\u0433\u043e\u0441\u0438"
    ],
    "name:und_x_variant":[
        "Otakoshibetsu",
        "Utakoshibetsu",
        "Utakoshi"
    ],
    "wof:name":"Utakoshi",
    "wof:placetype":"locality"
},
  "geometry": {"coordinates":[141.80410000000001,44.64299000000001],"type":"Point"}
}