{
  "type": "Feature",
  "properties": {
    "gn:admin1_code":"44.0",
    "gn:admin2_code":"2111778.0",
    "gn:asciiname":"Miya",
    "gn:country_code":"JP",
    "gn:dem":205,
    "gn:feature_class":"P",
    "gn:feature_code":"PPL",
    "gn:name":"Miya",
    "gn:population":0,
    "gn:timezone":"Asia/Tokyo",
    "iso:country":"JP",
    "name:jpn_x_preferred":[
        "\u5bae"
    ],
    "wof:name":"Miya",
    "wof:placetype":"locality"
},
  "geometry": {"coordinates":[140.03030999999999,38.10535],"type":"Point"}
}