{
  "type": "Feature",
  "properties": {
    "gn:admin1_code":"4.0",
    "gn:admin2_code":"8304237.0",
    "gn:asciiname":"Otera",
    "gn:country_code":"JP",
    "gn:dem":10,
    "gn:feature_class":"P",
    "gn:feature_code":"PPL",
    "gn:name":"\u014ctera",
    "gn:population":0,
    "gn:timezone":"Asia/Tokyo",
    "iso:country":"JP",
    "name:jpn_x_preferred":[
        "\u5927\u5bfa"
    ],
    "name:jpn_x_variant":[
        "\u304a\u304a\u3066\u3089",
        "\u30aa\u30aa\u30c6\u30e9"
    ],
    "name:und_x_variant":[
        "\u014ctera"
    ],
    "wof:name":"Otera",
    "wof:placetype":"locality"
},
  "geometry": {"coordinates":[139.97311999999999,35.3975],"type":"Point"}
}