{
  "type": "Feature",
  "properties": {
    "gn:admin1_code":"21.0",
    "gn:admin2_code":"1865168.0",
    "gn:asciiname":"Shimoakada",
    "gn:country_code":"JP",
    "gn:dem":22,
    "gn:feature_class":"P",
    "gn:feature_code":"PPLL",
    "gn:name":"Shimoakada",
    "gn:population":0,
    "gn:timezone":"Asia/Tokyo",
    "iso:country":"JP",
    "name:jpn_x_preferred":[
        "\u4e0b\u8d64\u7530"
    ],
    "name:jpn_x_variant":[
        "\u3057\u3082\u3042\u304b\u3060",
        "\u30b7\u30e2\u30a2\u30ab\u30c0"
    ],
    "wof:name":"Shimoakada",
    "wof:placetype":"locality"
},
  "geometry": {"coordinates":[130.48241000000002,32.95357],"type":"Point"}
}