{
  "type": "Feature",
  "properties": {
    "gn:admin1_code":"27.0",
    "gn:admin2_code":"1852895.0",
    "gn:asciiname":"Shikamachicho-nagushi",
    "gn:country_code":"JP",
    "gn:dem":11,
    "gn:feature_class":"P",
    "gn:feature_code":"PPL",
    "gn:name":"Shikamachich\u014d-nagushi",
    "gn:population":0,
    "gn:timezone":"Asia/Tokyo",
    "iso:country":"JP",
    "name:jpn_x_preferred":[
        "\u9e7f\u753a\u753a\u9577\u4e32"
    ],
    "name:und_x_variant":[
        "Shikamachich\u014d-nagushi"
    ],
    "wof:name":"Shikamachicho-nagushi",
    "wof:placetype":"locality"
},
  "geometry": {"coordinates":[129.57095000000001,33.25282],"type":"Point"}
}