{
  "type": "Feature",
  "properties": {
    "iso:country":"JP",
    "name:eng_x_preferred":[
        "Sannohe Town"
    ],
    "name:jpn_x_preferred":[
        "\u4e09\u6238\u753a"
    ],
    "qs:name":"\u4e09\u6238\u753a",
    "qs:name_adm0":"\u65e5\u672c",
    "qs:name_adm1":"\u9752\u68ee\u770c",
    "qs:photos":12,
    "qs:photos_1k":2,
    "qs:photos_9k":1,
    "qs:photos_9r":1,
    "qs:photos_all":15,
    "qs:photos_sr":1,
    "qs:placetype":"Town",
    "qs:pop_sr":"0",
    "wof:name":"Sannohe Town",
    "wof:placetype":"locality"
},
  "geometry": {"coordinates":[141.24960799999999,40.3818505],"type":"Point"}
}