{
  "type": "Feature",
  "properties": {
    "gn:admin1_code":"12.0",
    "gn:admin2_code":"7428116.0",
    "gn:admin3_code":"1607.0",
    "gn:asciiname":"Kyoei",
    "gn:country_code":"JP",
    "gn:dem":2,
    "gn:feature_class":"P",
    "gn:feature_code":"PPLL",
    "gn:name":"Ky\u014dei",
    "gn:population":0,
    "gn:timezone":"Asia/Tokyo",
    "iso:country":"JP",
    "name:jpn_x_preferred":[
        "\u5171\u6804"
    ],
    "name:jpn_x_variant":[
        "\u304d\u3087\u3046\u3048\u3044",
        "\u30ad\u30e7\u30a6\u30a8\u30a4"
    ],
    "name:und_x_variant":[
        "Ky\u014dei"
    ],
    "wof:name":"Kyoei",
    "wof:placetype":"locality"
},
  "geometry": {"coordinates":[142.68708000000001,42.19551],"type":"Point"}
}