{
  "type": "Feature",
  "properties": {
    "gn:admin1_code":"40",
    "gn:admin2_code":"8304376.0",
    "gn:asciiname":"Yagisawa",
    "gn:country_code":"JP",
    "gn:dem":61,
    "gn:feature_class":"P",
    "gn:feature_code":"PPL",
    "gn:name":"Yagisawa",
    "gn:population":0,
    "gn:timezone":"Asia/Tokyo",
    "iso:country":"JP",
    "name:jpn_x_preferred":[
        "\u67f3\u6ca2"
    ],
    "wof:name":"Yagisawa",
    "wof:placetype":"locality"
},
  "geometry": {"coordinates":[139.55205000000001,35.72421],"type":"Point"}
}