{
  "type": "Feature",
  "properties": {
    "gn:admin1_code":"12.0",
    "gn:admin2_code":"7428100.0",
    "gn:admin3_code":"1691.0",
    "gn:asciiname":"Taisei",
    "gn:country_code":"JP",
    "gn:dem":101,
    "gn:feature_class":"P",
    "gn:feature_code":"PPL",
    "gn:name":"Taisei",
    "gn:population":0,
    "gn:timezone":"Asia/Tokyo",
    "iso:country":"JP",
    "name:jpn_x_preferred":[
        "\u5927\u6210"
    ],
    "name:jpn_x_variant":[
        "\u305f\u3044\u305b\u3044",
        "\u30bf\u30a4\u30bb\u30a4"
    ],
    "wof:name":"Taisei",
    "wof:placetype":"locality"
},
  "geometry": {"coordinates":[144.82521,43.44859],"type":"Point"}
}