{
  "type": "Feature",
  "properties": {
    "gn:admin1_code":"16.0",
    "gn:admin2_code":"2128940.0",
    "gn:asciiname":"Sakainosawa",
    "gn:country_code":"JP",
    "gn:dem":222,
    "gn:feature_class":"P",
    "gn:feature_code":"PPL",
    "gn:name":"Sakainosawa",
    "gn:population":0,
    "gn:timezone":"Asia/Tokyo",
    "iso:country":"JP",
    "name:jpn_x_preferred":[
        "\u5883\u30ce\u6ca2"
    ],
    "name:jpn_x_variant":[
        "\u3055\u304b\u3044\u306e\u3055\u308f",
        "\u30b5\u30ab\u30a4\u30ce\u30b5\u30ef"
    ],
    "wof:name":"Sakainosawa",
    "wof:placetype":"locality"
},
  "geometry": {"coordinates":[141.33463,40.25117],"type":"Point"}
}