{
  "type": "Feature",
  "properties": {
    "gn:admin1_code":"31.0",
    "gn:admin2_code":"7405225.0",
    "gn:asciiname":"Shimoyuno",
    "gn:country_code":"JP",
    "gn:dem":500,
    "gn:feature_class":"P",
    "gn:feature_code":"PPL",
    "gn:name":"Shimoyuno",
    "gn:population":0,
    "gn:timezone":"Asia/Tokyo",
    "iso:country":"JP",
    "name:jpn_x_preferred":[
        "\u4e0b\u6cb9\u91ce"
    ],
    "wof:name":"Shimoyuno",
    "wof:placetype":"locality"
},
  "geometry": {"coordinates":[133.35836,35.04798],"type":"Point"}
}