{
  "type": "Feature",
  "properties": {
    "gn:admin1_code":"21.0",
    "gn:admin2_code":"1859490.0",
    "gn:admin3_code":"43403.0",
    "gn:asciiname":"Terasaki",
    "gn:country_code":"JP",
    "gn:dem":87,
    "gn:feature_class":"P",
    "gn:feature_code":"PPLL",
    "gn:name":"Terasaki",
    "gn:population":0,
    "gn:timezone":"Asia/Tokyo",
    "iso:country":"JP",
    "name:jpn_x_preferred":[
        "\u5bfa\u5d0e"
    ],
    "name:jpn_x_variant":[
        "\u3066\u3089\u3055\u304d",
        "\u30c6\u30e9\u30b5\u30ad"
    ],
    "wof:name":"Terasaki",
    "wof:placetype":"locality"
},
  "geometry": {"coordinates":[130.87164999999999,32.85505999999999],"type":"Point"}
}