{
  "type": "Feature",
  "properties": {
    "gn:admin1_code":"21",
    "gn:admin2_code":"7413151.0",
    "gn:asciiname":"Senzoku",
    "gn:country_code":"JP",
    "gn:dem":3,
    "gn:feature_class":"P",
    "gn:feature_code":"PPL",
    "gn:name":"Senzoku",
    "gn:population":0,
    "gn:timezone":"Asia/Tokyo",
    "iso:country":"JP",
    "name:jpn_x_preferred":[
        "\u5343\u675f"
    ],
    "name:jpn_x_variant":[
        "\u305b\u3093\u305e\u304f",
        "\u30bb\u30f3\u30be\u30af"
    ],
    "wof:name":"Senzoku",
    "wof:placetype":"locality"
},
  "geometry": {"coordinates":[130.46610000000001,32.56408],"type":"Point"}
}