{
  "type": "Feature",
  "properties": {
    "gn:admin1_code":"12.0",
    "gn:admin2_code":"7428105.0",
    "gn:admin3_code":"1405.0",
    "gn:asciiname":"Yobetsu",
    "gn:country_code":"JP",
    "gn:dem":101,
    "gn:feature_class":"P",
    "gn:feature_code":"PPL",
    "gn:name":"Yobetsu",
    "gn:population":0,
    "gn:timezone":"Asia/Tokyo",
    "iso:country":"JP",
    "wof:name":"Yobetsu",
    "wof:placetype":"locality"
},
  "geometry": {"coordinates":[140.38388999999998,43.32194000000001],"type":"Point"}
}