{
  "type": "Feature",
  "properties": {
    "gn:admin1_code":"23.0",
    "gn:admin2_code":"1848873.0",
    "gn:admin3_code":"24471.0",
    "gn:asciiname":"Kasagi",
    "gn:country_code":"JP",
    "gn:dem":181,
    "gn:feature_class":"P",
    "gn:feature_code":"PPL",
    "gn:name":"Kasagi",
    "gn:population":0,
    "gn:timezone":"Asia/Tokyo",
    "iso:country":"JP",
    "name:jpn_x_preferred":[
        "\u7b20\u6728"
    ],
    "wof:name":"Kasagi",
    "wof:placetype":"locality"
},
  "geometry": {"coordinates":[136.38419999999999,34.31496],"type":"Point"}
}