{
  "type": "Feature",
  "properties": {
    "iso:country":"JP",
    "name:eng_x_preferred":[
        "Kawakami Village"
    ],
    "name:jpn_x_preferred":[
        "\u5ddd\u4e0a\u6751"
    ],
    "qs:name":"\u5ddd\u4e0a\u6751",
    "qs:name_adm0":"\u65e5\u672c",
    "qs:name_adm1":"\u9577\u91ce\u770c",
    "qs:photos":390,
    "qs:photos_1k":79,
    "qs:photos_9k":2,
    "qs:photos_9r":5,
    "qs:photos_all":390,
    "qs:photos_sr":6,
    "qs:placetype":"Town",
    "qs:pop_sr":"0",
    "wof:name":"Kawakami Village",
    "wof:placetype":"locality"
},
  "geometry": {"coordinates":[138.716297,35.907361],"type":"Point"}
}