{
  "type": "Feature",
  "properties": {
    "iso:country":"JP",
    "name:eng_x_preferred":[
        "Terauchi 1 Chome"
    ],
    "name:eng_x_variant":[
        "Terauchi 1 Choume",
        "Terauchi 1 Chome"
    ],
    "name:jpn_x_preferred":[
        "\uff11\u4e01\u76ee"
    ],
    "name:jpn_x_variant":[
        "\u3066\u3089\u3046\u3061 \uff11\u3061\u3087\u3046\u3081",
        "\u5bfa\u5185 \uff11\u4e01\u76ee",
        "\uff11\u3061\u3087\u3046\u3081"
    ],
    "name:unk_x_variant":[
        "\uff11\u4e01\u76ee"
    ],
    "qs:gn_local":0,
    "qs:local_max":319,
    "qs:local_sum":1183,
    "qs:localhoods":13,
    "qs:name":"\uff11\u4e01\u76ee",
    "qs:name_adm0":"\u65e5\u672c",
    "qs:name_adm1":"\u5927\u962a\u5e9c",
    "qs:name_en":"Terauchi 1 Chome",
    "qs:name_lau":"\u5bfa\u5185",
    "qs:name_local":"\u8c4a\u4e2d\u5e02",
    "qs:photo_max":105,
    "qs:photo_sum":253,
    "qs:placetype":"Suburb",
    "qs:quad_count":12,
    "qs:woe_adm0":23424856,
    "qs:woe_adm1":2345881,
    "qs:woe_adm2":0,
    "qs:woe_lau":28458183,
    "qs:woe_local":1118409,
    "qs:woe_ver":"7.10.0",
    "wof:lang":[
        "jpn"
    ],
    "wof:name":"\uff11\u4e01\u76ee",
    "wof:placetype":"neighbourhood"
},
  "geometry": {"coordinates":[135.487426,34.777104],"type":"Point"}
}