{
  "type": "Feature",
  "properties": {
    "gn:admin1_code":"21.0",
    "gn:admin2_code":"7412706.0",
    "gn:admin3_code":"43447.0",
    "gn:asciiname":"Akagi",
    "gn:country_code":"JP",
    "gn:dem":690,
    "gn:feature_class":"P",
    "gn:feature_code":"PPLL",
    "gn:name":"Akagi",
    "gn:population":0,
    "gn:timezone":"Asia/Tokyo",
    "iso:country":"JP",
    "name:ces_x_preferred":[
        "Akagi"
    ],
    "name:deu_x_preferred":[
        "Akagi"
    ],
    "name:fra_x_preferred":[
        "Akagi"
    ],
    "name:heb_x_preferred":[
        "\u05d0\u05e7\u05d0\u05d2\u05d9"
    ],
    "name:hun_x_preferred":[
        "Akagi"
    ],
    "name:ita_x_preferred":[
        "Akagi"
    ],
    "name:jpn_x_preferred":[
        "\u8d64\u6728"
    ],
    "name:jpn_x_variant":[
        "\u3042\u304b\u304e",
        "\u30a2\u30ab\u30ae"
    ],
    "name:pol_x_preferred":[
        "Akagi"
    ],
    "name:rus_x_preferred":[
        "\u0410\u043a\u0430\u0433\u0438"
    ],
    "name:slk_x_preferred":[
        "Akagi"
    ],
    "name:spa_x_preferred":[
        "Akagi"
    ],
    "name:ukr_x_preferred":[
        "\u0410\u043a\u0430\u0491\u0456"
    ],
    "name:vie_x_preferred":[
        "Akagi"
    ],
    "wof:name":"Akagi",
    "wof:placetype":"locality"
},
  "geometry": {"coordinates":[131.10404,32.6287],"type":"Point"}
}