{
  "type": "Feature",
  "properties": {
    "gn:admin1_code":"21.0",
    "gn:admin2_code":"7413150.0",
    "gn:asciiname":"Kuginohana",
    "gn:country_code":"JP",
    "gn:dem":49,
    "gn:feature_class":"P",
    "gn:feature_code":"PPLL",
    "gn:name":"Kuginohana",
    "gn:population":0,
    "gn:timezone":"Asia/Tokyo",
    "iso:country":"JP",
    "name:jpn_x_preferred":[
        "\u91d8\u30ce\u82b1"
    ],
    "name:jpn_x_variant":[
        "\u304f\u304e\u306e\u306f\u306a",
        "\u30af\u30ae\u30ce\u30cf\u30ca"
    ],
    "wof:name":"Kuginohana",
    "wof:placetype":"locality"
},
  "geometry": {"coordinates":[130.69141000000002,33.07671],"type":"Point"}
}