{
  "type": "Feature",
  "properties": {
    "gn:admin1_code":"47.0",
    "gn:admin2_code":"1858371.0",
    "gn:admin3_code":"47302.0",
    "gn:asciiname":"Oshikawa",
    "gn:country_code":"JP",
    "gn:dem":120,
    "gn:feature_class":"P",
    "gn:feature_code":"PPL",
    "gn:name":"Oshikawa",
    "gn:population":0,
    "gn:timezone":"Asia/Tokyo",
    "iso:country":"JP",
    "name:jpn_x_preferred":[
        "\u62bc\u5ddd"
    ],
    "wof:name":"Oshikawa",
    "wof:placetype":"locality"
},
  "geometry": {"coordinates":[128.13172,26.67309],"type":"Point"}
}