{
  "type": "Feature",
  "properties": {
    "gn:admin1_code":"47",
    "gn:admin2_code":"1855990.0",
    "gn:admin3_code":"47324.0",
    "gn:asciiname":"Irammiya",
    "gn:cc2":"JP",
    "gn:country_code":"JP",
    "gn:dem":54,
    "gn:feature_class":"P",
    "gn:feature_code":"PPL",
    "gn:name":"Irammiya",
    "gn:population":0,
    "gn:timezone":"Asia/Tokyo",
    "iso:country":"JP",
    "name:und_x_variant":[
        "Iramina",
        "Irammiya"
    ],
    "wof:name":"Irammiya",
    "wof:placetype":"locality"
},
  "geometry": {"coordinates":[127.75,26.38333],"type":"Point"}
}