{
  "type": "Feature",
  "properties": {
    "gn:admin1_code":"16.0",
    "gn:admin2_code":"2112822.0",
    "gn:asciiname":"Numahata",
    "gn:country_code":"JP",
    "gn:dem":124,
    "gn:feature_class":"P",
    "gn:feature_code":"PPL",
    "gn:name":"Numahata",
    "gn:population":0,
    "gn:timezone":"Asia/Tokyo",
    "iso:country":"JP",
    "name:jpn_x_preferred":[
        "\u6cbc\u7551"
    ],
    "name:jpn_x_variant":[
        "\u306c\u307e\u306f\u305f",
        "\u30cc\u30de\u30cf\u30bf"
    ],
    "wof:name":"Numahata",
    "wof:placetype":"locality"
},
  "geometry": {"coordinates":[141.22852,39.47432],"type":"Point"}
}