{
  "type": "Feature",
  "properties": {
    "gn:admin1_code":"24.0",
    "gn:admin2_code":"7446990.0",
    "gn:asciiname":"Hachiyamae",
    "gn:country_code":"JP",
    "gn:dem":5,
    "gn:feature_class":"P",
    "gn:feature_code":"PPL",
    "gn:name":"Hachiyamae",
    "gn:population":0,
    "gn:timezone":"Asia/Tokyo",
    "iso:country":"JP",
    "name:jpn_x_preferred":[
        "\u8702\u8c37\u524d"
    ],
    "name:jpn_x_variant":[
        "\u306f\u3061\u3084\u307e\u3048",
        "\u30cf\u30c1\u30e4\u30de\u30a8"
    ],
    "wof:name":"Hachiyamae",
    "wof:placetype":"locality"
},
  "geometry": {"coordinates":[141.22534999999999,38.41918],"type":"Point"}
}