{
  "type": "Feature",
  "properties": {
    "gn:admin1_code":"7.0",
    "gn:admin2_code":"7407416.0",
    "gn:asciiname":"Nakahata",
    "gn:country_code":"JP",
    "gn:dem":133,
    "gn:feature_class":"P",
    "gn:feature_code":"PPLL",
    "gn:name":"Nakahata",
    "gn:population":0,
    "gn:timezone":"Asia/Tokyo",
    "iso:country":"JP",
    "name:jpn_x_preferred":[
        "\u4e2d\u7551"
    ],
    "wof:name":"Nakahata",
    "wof:placetype":"locality"
},
  "geometry": {"coordinates":[130.60741999999999,33.66689],"type":"Point"}
}