{
  "type": "Feature",
  "properties": {
    "gn:admin1_code":"18",
    "gn:admin2_code":"1853737.0",
    "gn:admin3_code":"46529.0",
    "gn:asciiname":"Akaren",
    "gn:cc2":"JP",
    "gn:country_code":"JP",
    "gn:dem":6,
    "gn:feature_class":"P",
    "gn:feature_code":"PPL",
    "gn:name":"Akaren",
    "gn:population":0,
    "gn:timezone":"Asia/Tokyo",
    "iso:country":"JP",
    "name:und_x_variant":[
        "Akare",
        "Agare",
        "Akaren"
    ],
    "wof:name":"Akaren",
    "wof:placetype":"locality"
},
  "geometry": {"coordinates":[129.93333000000001,28.31667],"type":"Point"}
}