{
  "type": "Feature",
  "properties": {
    "gn:admin1_code":"4.0",
    "gn:admin2_code":"7465524.0",
    "gn:asciiname":"Rakumachi",
    "gn:country_code":"JP",
    "gn:dem":12,
    "gn:feature_class":"P",
    "gn:feature_code":"PPL",
    "gn:name":"Rakumachi",
    "gn:population":0,
    "gn:timezone":"Asia/Tokyo",
    "iso:country":"JP",
    "name:jpn_x_preferred":[
        "\u697d\u753a"
    ],
    "name:jpn_x_variant":[
        "\u3089\u304f\u307e\u3061",
        "\u30e9\u30af\u30de\u30c1"
    ],
    "wof:name":"Rakumachi",
    "wof:placetype":"locality"
},
  "geometry": {"coordinates":[140.31616,35.29383],"type":"Point"}
}