{
  "type": "Feature",
  "properties": {
    "gn:admin1_code":"10",
    "gn:admin2_code":"1857842.0",
    "gn:asciiname":"Motosojamachi",
    "gn:country_code":"JP",
    "gn:dem":110,
    "gn:feature_class":"P",
    "gn:feature_code":"PPL",
    "gn:name":"Motos\u014djamachi",
    "gn:population":0,
    "gn:timezone":"Asia/Tokyo",
    "iso:country":"JP",
    "name:jpn_x_preferred":[
        "\u5143\u7dcf\u793e"
    ],
    "name:jpn_x_variant":[
        "\u5143\u7dcf\u793e\u753a"
    ],
    "name:und_x_variant":[
        "Moto-s\u014dja",
        "Motos\u014djamachi"
    ],
    "wof:name":"Motosojamachi",
    "wof:placetype":"locality"
},
  "geometry": {"coordinates":[139.03887,36.38676],"type":"Point"}
}