{
  "type": "Feature",
  "properties": {
    "gn:admin1_code":"3.0",
    "gn:admin2_code":"2129525.0",
    "gn:admin3_code":"2387.0",
    "gn:asciiname":"Kamitakane",
    "gn:country_code":"JP",
    "gn:dem":30,
    "gn:feature_class":"P",
    "gn:feature_code":"PPL",
    "gn:name":"Kamitakane",
    "gn:population":0,
    "gn:timezone":"Asia/Tokyo",
    "iso:country":"JP",
    "name:jpn_x_preferred":[
        "\u4e0a\u9ad8\u6839"
    ],
    "name:jpn_x_variant":[
        "\u304b\u307f\u305f\u304b\u306d",
        "\u30ab\u30df\u30bf\u30ab\u30cd"
    ],
    "wof:name":"Kamitakane",
    "wof:placetype":"locality"
},
  "geometry": {"coordinates":[140.42881,40.9884],"type":"Point"}
}