{
  "type": "Feature",
  "properties": {
    "gn:admin1_code":"21.0",
    "gn:admin2_code":"1848441.0",
    "gn:asciiname":"Uchino",
    "gn:country_code":"JP",
    "gn:dem":74,
    "gn:feature_class":"P",
    "gn:feature_code":"PPLL",
    "gn:name":"Uchino",
    "gn:population":0,
    "gn:timezone":"Asia/Tokyo",
    "iso:country":"JP",
    "name:jpn_x_preferred":[
        "\u5185\u91ce"
    ],
    "wof:name":"Uchino",
    "wof:placetype":"locality"
},
  "geometry": {"coordinates":[130.58131,32.4098],"type":"Point"}
}