{
  "type": "Feature",
  "properties": {
    "gn:admin1_code":"18.0",
    "gn:admin2_code":"1851576.0",
    "gn:admin3_code":"46468.0",
    "gn:asciiname":"Shinondan",
    "gn:country_code":"JP",
    "gn:dem":163,
    "gn:feature_class":"P",
    "gn:feature_code":"PPLL",
    "gn:name":"Shinondan",
    "gn:population":0,
    "gn:timezone":"Asia/Tokyo",
    "iso:country":"JP",
    "name:jpn_x_preferred":[
        "\u7be0\u6bb5"
    ],
    "wof:name":"Shinondan",
    "wof:placetype":"locality"
},
  "geometry": {"coordinates":[130.96261000000001,31.49285],"type":"Point"}
}