{
  "type": "Feature",
  "properties": {
    "gn:admin1_code":"7.0",
    "gn:admin2_code":"1859874.0",
    "gn:admin3_code":"40348.0",
    "gn:asciiname":"Yuzuriha",
    "gn:country_code":"JP",
    "gn:dem":156,
    "gn:feature_class":"P",
    "gn:feature_code":"PPLL",
    "gn:name":"Yuzuriha",
    "gn:population":0,
    "gn:timezone":"Asia/Tokyo",
    "iso:country":"JP",
    "name:jpn_x_preferred":[
        "\u696a\u8449"
    ],
    "wof:name":"Yuzuriha",
    "wof:placetype":"locality"
},
  "geometry": {"coordinates":[130.51616999999999,33.67094],"type":"Point"}
}