{
  "type": "Feature",
  "properties": {
    "gn:admin1_code":"09",
    "gn:admin2_code":"1860326.0",
    "gn:admin3_code":"21503.0",
    "gn:asciiname":"Naka-kawabe",
    "gn:country_code":"JP",
    "gn:dem":100,
    "gn:feature_class":"P",
    "gn:feature_code":"PPL",
    "gn:name":"Naka-kawabe",
    "gn:population":0,
    "gn:timezone":"Asia/Tokyo",
    "iso:country":"JP",
    "wof:name":"Naka-kawabe",
    "wof:placetype":"locality"
},
  "geometry": {"coordinates":[137.06666999999999,35.48333],"type":"Point"}
}