{
  "type": "Feature",
  "properties": {
    "gn:admin1_code":"25",
    "gn:admin2_code":"1855094.0",
    "gn:asciiname":"Kawachimyo",
    "gn:country_code":"JP",
    "gn:dem":111,
    "gn:feature_class":"P",
    "gn:feature_code":"PPL",
    "gn:name":"Kawachimy\u014d",
    "gn:population":0,
    "gn:timezone":"Asia/Tokyo",
    "iso:country":"JP",
    "name:und_x_variant":[
        "Kawachimy\u014d"
    ],
    "wof:name":"Kawachimyo",
    "wof:placetype":"locality"
},
  "geometry": {"coordinates":[131.69999999999999,32.68333],"type":"Point"}
}