{
  "type": "Feature",
  "properties": {
    "iso:country":"JP",
    "label:eng_x_preferred_longname":[
        "Tateyama Town"
    ],
    "label:eng_x_preferred_placetype":[
        "town"
    ],
    "name:eng_x_preferred":[
        "Tateyama"
    ],
    "name:eng_x_variant":[
        "Tateyama Town"
    ],
    "name:jpn_x_preferred":[
        "\u7acb\u5c71\u753a"
    ],
    "qs:name":"\u7acb\u5c71\u753a",
    "qs:name_adm0":"\u65e5\u672c",
    "qs:name_adm1":"\u5bcc\u5c71\u770c",
    "qs:photos":4999,
    "qs:photos_1k":1000,
    "qs:photos_9k":22,
    "qs:photos_9r":14,
    "qs:photos_all":4999,
    "qs:photos_sr":24,
    "qs:placetype":"Town",
    "qs:pop_sr":"0",
    "wof:name":"Tateyama",
    "wof:placetype":"locality"
},
  "geometry": {"coordinates":[137.65000000000001,36.567753],"type":"Point"}
}