{
  "type": "Feature",
  "properties": {
    "gn:admin1_code":"21",
    "gn:admin2_code":"1859490.0",
    "gn:admin3_code":"43403.0",
    "gn:asciiname":"Sugimizu",
    "gn:country_code":"JP",
    "gn:dem":163,
    "gn:feature_class":"P",
    "gn:feature_code":"PPL",
    "gn:name":"Sugimizu",
    "gn:population":0,
    "gn:timezone":"Asia/Tokyo",
    "iso:country":"JP",
    "name:jpn_x_preferred":[
        "\u6749\u6c34"
    ],
    "name:jpn_x_variant":[
        "\u3059\u304e\u307f\u305a",
        "\u30b9\u30ae\u30df\u30ba"
    ],
    "name:und_x_variant":[
        "Kagimizu",
        "Sugimi",
        "Sugimizu"
    ],
    "wof:name":"Sugimizu",
    "wof:placetype":"locality"
},
  "geometry": {"coordinates":[130.84801000000002,32.91351],"type":"Point"}
}