{
  "type": "Feature",
  "properties": {
    "gn:admin1_code":"18.0",
    "gn:admin2_code":"7383991.0",
    "gn:asciiname":"Kusumoto",
    "gn:country_code":"JP",
    "gn:dem":228,
    "gn:feature_class":"P",
    "gn:feature_code":"PPLL",
    "gn:name":"Kusumoto",
    "gn:population":0,
    "gn:timezone":"Asia/Tokyo",
    "iso:country":"JP",
    "name:jpn_x_preferred":[
        "\u6960\u672c"
    ],
    "name:jpn_x_variant":[
        "\u304f\u3059\u3082\u3068",
        "\u30af\u30b9\u30e2\u30c8"
    ],
    "wof:name":"Kusumoto",
    "wof:placetype":"locality"
},
  "geometry": {"coordinates":[130.67345,32.03564],"type":"Point"}
}