{
  "type": "Feature",
  "properties": {
    "gn:admin1_code":"4.0",
    "gn:admin2_code":"2112997.0",
    "gn:admin3_code":"12427.0",
    "gn:asciiname":"Atagocho",
    "gn:country_code":"JP",
    "gn:dem":29,
    "gn:feature_class":"P",
    "gn:feature_code":"PPLL",
    "gn:name":"Atagoch\u014d",
    "gn:population":0,
    "gn:timezone":"Asia/Tokyo",
    "iso:country":"JP",
    "name:jpn_x_preferred":[
        "\u611b\u5b95\u753a"
    ],
    "name:jpn_x_variant":[
        "\u3042\u305f\u3054\u3061\u3087\u3046",
        "\u30a2\u30bf\u30b4\u30c1\u30e7\u30a6"
    ],
    "name:und_x_variant":[
        "Atagoch\u014d"
    ],
    "wof:name":"Atagocho",
    "wof:placetype":"locality"
},
  "geometry": {"coordinates":[140.23266999999998,35.39998],"type":"Point"}
}