{
  "type": "Feature",
  "properties": {
    "gn:admin1_code":"4.0",
    "gn:admin2_code":"1856183.0",
    "gn:asciiname":"Matsugaoka",
    "gn:country_code":"JP",
    "gn:dem":19,
    "gn:feature_class":"P",
    "gn:feature_code":"PPL",
    "gn:name":"Matsugaoka",
    "gn:population":0,
    "gn:timezone":"Asia/Tokyo",
    "iso:country":"JP",
    "name:jpn_x_preferred":[
        "\u677e\u30f6\u4e18"
    ],
    "name:jpn_x_variant":[
        "\u677e\u304c\u4e18"
    ],
    "wof:name":"Matsugaoka",
    "wof:placetype":"locality"
},
  "geometry": {"coordinates":[139.94852,35.8492],"type":"Point"}
}