{
  "type": "Feature",
  "properties": {
    "gn:admin1_code":"4.0",
    "gn:admin2_code":"1863903.0",
    "gn:asciiname":"Motonakayama",
    "gn:country_code":"JP",
    "gn:dem":12,
    "gn:feature_class":"P",
    "gn:feature_code":"PPL",
    "gn:name":"Motonakayama",
    "gn:population":0,
    "gn:timezone":"Asia/Tokyo",
    "iso:country":"JP",
    "name:jpn_x_preferred":[
        "\u672c\u4e2d\u5c71"
    ],
    "wof:name":"Motonakayama",
    "wof:placetype":"locality"
},
  "geometry": {"coordinates":[139.94443000000001,35.7138],"type":"Point"}
}