{
  "type": "Feature",
  "properties": {
    "gn:admin1_code":"34.0",
    "gn:admin2_code":"8304213.0",
    "gn:asciiname":"Oba",
    "gn:country_code":"JP",
    "gn:dem":6,
    "gn:feature_class":"P",
    "gn:feature_code":"PPL",
    "gn:name":"\u014cba",
    "gn:population":0,
    "gn:timezone":"Asia/Tokyo",
    "iso:country":"JP",
    "name:jpn_x_preferred":[
        "\u5927\u5834"
    ],
    "name:und_x_variant":[
        "\u014cba"
    ],
    "wof:name":"Oba",
    "wof:placetype":"locality"
},
  "geometry": {"coordinates":[139.76499999999999,35.94819000000001],"type":"Point"}
}