{
  "type": "Feature",
  "properties": {
    "gn:admin1_code":"43.0",
    "gn:admin2_code":"1860774.0",
    "gn:admin3_code":"30304.0",
    "gn:asciiname":"Nakata",
    "gn:country_code":"JP",
    "gn:dem":229,
    "gn:feature_class":"P",
    "gn:feature_code":"PPL",
    "gn:name":"Nakata",
    "gn:population":0,
    "gn:timezone":"Asia/Tokyo",
    "iso:country":"JP",
    "name:jpn_x_preferred":[
        "\u4e2d\u7530"
    ],
    "wof:name":"Nakata",
    "wof:placetype":"locality"
},
  "geometry": {"coordinates":[135.31944999999999,34.12448],"type":"Point"}
}