{
  "type": "Feature",
  "properties": {
    "gn:admin1_code":"23.0",
    "gn:admin2_code":"7417711.0",
    "gn:asciiname":"Sekicho-sakashita",
    "gn:country_code":"JP",
    "gn:dem":237,
    "gn:feature_class":"P",
    "gn:feature_code":"PPL",
    "gn:name":"Sekich\u014d-sakashita",
    "gn:population":0,
    "gn:timezone":"Asia/Tokyo",
    "iso:country":"JP",
    "name:jpn_x_preferred":[
        "\u95a2\u753a\u5742\u4e0b"
    ],
    "name:und_x_variant":[
        "Sekich\u014d-sakashita"
    ],
    "wof:name":"Sekicho-sakashita",
    "wof:placetype":"locality"
},
  "geometry": {"coordinates":[136.35398000000001,34.88968],"type":"Point"}
}