{
  "type": "Feature",
  "properties": {
    "gn:admin1_code":"21.0",
    "gn:admin2_code":"7413151.0",
    "gn:asciiname":"Ura",
    "gn:country_code":"JP",
    "gn:dem":63,
    "gn:feature_class":"P",
    "gn:feature_code":"PPLL",
    "gn:name":"Ura",
    "gn:population":0,
    "gn:timezone":"Asia/Tokyo",
    "iso:country":"JP",
    "name:cat_x_preferred":[
        "Ur\u00e0"
    ],
    "name:ceb_x_preferred":[
        "Ura"
    ],
    "name:chv_x_preferred":[
        "\u0423\u0440\u0430"
    ],
    "name:fra_x_preferred":[
        "Ura"
    ],
    "name:jpn_x_preferred":[
        "\u6d66"
    ],
    "name:jpn_x_variant":[
        "\u3046\u3089",
        "\u30a6\u30e9"
    ],
    "name:nno_x_preferred":[
        "Ura"
    ],
    "name:que_x_preferred":[
        "Ura"
    ],
    "name:rus_x_preferred":[
        "\u0423\u0440\u0430"
    ],
    "name:slv_x_preferred":[
        "Ura"
    ],
    "name:swe_x_preferred":[
        "Ura"
    ],
    "name:ukr_x_preferred":[
        "\u0423\u0440\u0430"
    ],
    "wof:name":"Ura",
    "wof:placetype":"locality"
},
  "geometry": {"coordinates":[130.40434999999999,32.44036],"type":"Point"}
}