{
  "type": "Feature",
  "properties": {
    "gn:admin1_code":"7.0",
    "gn:admin2_code":"1864574.0",
    "gn:admin3_code":"40305.0",
    "gn:asciiname":"Katanawa",
    "gn:country_code":"JP",
    "gn:dem":17,
    "gn:feature_class":"P",
    "gn:feature_code":"PPL",
    "gn:name":"Katanawa",
    "gn:population":0,
    "gn:timezone":"Asia/Tokyo",
    "iso:country":"JP",
    "name:jpn_x_preferred":[
        "\u7247\u7e04"
    ],
    "wof:name":"Katanawa",
    "wof:placetype":"locality"
},
  "geometry": {"coordinates":[130.42444,33.52111],"type":"Point"}
}