{
  "type": "Feature",
  "properties": {
    "gn:admin1_code":"29.0",
    "gn:admin2_code":"1850218.0",
    "gn:asciiname":"Fukujima",
    "gn:country_code":"JP",
    "gn:dem":317,
    "gn:feature_class":"P",
    "gn:feature_code":"PPL",
    "gn:name":"Fukujima",
    "gn:population":0,
    "gn:timezone":"Asia/Tokyo",
    "iso:country":"JP",
    "name:jpn_x_preferred":[
        "\u798f\u5cf6"
    ],
    "wof:name":"Fukujima",
    "wof:placetype":"locality"
},
  "geometry": {"coordinates":[138.56360000000001,37.10222],"type":"Point"}
}