{
  "type": "Feature",
  "properties": {
    "iso:country":"JP",
    "qs:name":"\uff08\u4e01\u76ee\u306a\u3057\uff09",
    "qs:name_adm0":"\u65e5\u672c",
    "qs:name_adm1":"\u5175\u5eab\u770c",
    "qs:photos":538,
    "qs:photos_1k":109,
    "qs:photos_9k":2,
    "qs:photos_9r":5,
    "qs:photos_all":538,
    "qs:photos_sr":7,
    "qs:placetype":"Suburb",
    "qs:pop_sr":"0",
    "wof:name":"\uff08\u4e01\u76ee\u306a\u3057\uff09",
    "wof:placetype":"neighbourhood"
},
  "geometry": {"coordinates":[134.690494,34.831207],"type":"Point"}
}