{
  "type": "Feature",
  "properties": {
    "iso:country":"JP",
    "name:eng_x_preferred":[
        "Biei"
    ],
    "name:eng_x_variant":[
        "Biei Town"
    ],
    "name:jpn_x_preferred":[
        "\u7f8e\u745b\u753a"
    ],
    "qs:name":"\u7f8e\u745b\u753a",
    "qs:name_adm0":"\u65e5\u672c",
    "qs:name_adm1":"\u5317\u6d77\u9053",
    "qs:photos":3896,
    "qs:photos_1k":789,
    "qs:photos_9k":23,
    "qs:photos_9r":14,
    "qs:photos_all":5192,
    "qs:photos_sr":22,
    "qs:placetype":"Town",
    "qs:pop_sr":"0",
    "wof:name":"Biei",
    "wof:placetype":"locality"
},
  "geometry": {"coordinates":[142.539367,43.530467],"type":"Point"}
}