{
  "type": "Feature",
  "properties": {
    "gn:admin1_code":"14.0",
    "gn:admin2_code":"6950859.0",
    "gn:asciiname":"Matsumaedai",
    "gn:country_code":"JP",
    "gn:dem":21,
    "gn:feature_class":"P",
    "gn:feature_code":"PPL",
    "gn:name":"Matsumaedai",
    "gn:population":0,
    "gn:timezone":"Asia/Tokyo",
    "iso:country":"JP",
    "name:jpn_x_preferred":[
        "\u677e\u524d\u53f0"
    ],
    "wof:name":"Matsumaedai",
    "wof:placetype":"locality"
},
  "geometry": {"coordinates":[139.96372,35.96891],"type":"Point"}
}