{
  "type": "Feature",
  "properties": {
    "gn:admin1_code":"16.0",
    "gn:admin2_code":"2128940.0",
    "gn:asciiname":"Appi-uwano",
    "gn:country_code":"JP",
    "gn:dem":196,
    "gn:feature_class":"P",
    "gn:feature_code":"PPL",
    "gn:name":"Appi-uwano",
    "gn:population":0,
    "gn:timezone":"Asia/Tokyo",
    "iso:country":"JP",
    "name:jpn_x_preferred":[
        "\u5b89\u6bd4\u4e0a\u91ce"
    ],
    "name:jpn_x_variant":[
        "\u3042\u3063\u3074\u3046\u308f\u306e",
        "\u30a2\u30c3\u30d4\u30a6\u30ef\u30ce"
    ],
    "wof:name":"Appi-uwano",
    "wof:placetype":"locality"
},
  "geometry": {"coordinates":[141.22002000000001,40.24052],"type":"Point"}
}