{
  "type": "Feature",
  "properties": {
    "gn:admin1_code":"07",
    "gn:admin2_code":"1848578.0",
    "gn:asciiname":"Honda",
    "gn:country_code":"JP",
    "gn:dem":164,
    "gn:feature_class":"P",
    "gn:feature_code":"PPLL",
    "gn:name":"Honda",
    "gn:population":0,
    "gn:timezone":"Asia/Tokyo",
    "iso:country":"JP",
    "name:jpn_x_preferred":[
        "\u672c\u7530"
    ],
    "wof:name":"Honda",
    "wof:placetype":"locality"
},
  "geometry": {"coordinates":[130.71666999999999,33.18333],"type":"Point"}
}