{
  "type": "Feature",
  "properties": {
    "gn:admin1_code":"28.0",
    "gn:admin2_code":"1848164.0",
    "gn:admin3_code":"29452.0",
    "gn:asciiname":"Ido",
    "gn:country_code":"JP",
    "gn:dem":409,
    "gn:feature_class":"P",
    "gn:feature_code":"PPL",
    "gn:name":"Ido",
    "gn:population":0,
    "gn:timezone":"Asia/Tokyo",
    "iso:country":"JP",
    "name:ben_x_preferred":[
        "\u0987\u09a6\u09cb"
    ],
    "name:cat_x_preferred":[
        "Ido"
    ],
    "name:ceb_x_preferred":[
        "Ido"
    ],
    "name:deu_x_preferred":[
        "Ido"
    ],
    "name:fra_x_preferred":[
        "Ido"
    ],
    "name:ina_x_preferred":[
        "Ido"
    ],
    "name:ind_x_preferred":[
        "Ido"
    ],
    "name:jpn_x_preferred":[
        "\u4e95\u6238"
    ],
    "name:nld_x_preferred":[
        "Ido"
    ],
    "wof:name":"Ido",
    "wof:placetype":"locality"
},
  "geometry": {"coordinates":[135.97538,34.31737],"type":"Point"}
}