{
  "type": "Feature",
  "properties": {
    "gn:admin1_code":"37.0",
    "gn:admin2_code":"1851274.0",
    "gn:admin3_code":"22325.0",
    "gn:asciiname":"Kanbara",
    "gn:country_code":"JP",
    "gn:dem":154,
    "gn:feature_class":"P",
    "gn:feature_code":"PPLL",
    "gn:name":"Kanbara",
    "gn:population":0,
    "gn:timezone":"Asia/Tokyo",
    "iso:country":"JP",
    "name:jpn_x_preferred":[
        "\u795e\u539f"
    ],
    "wof:name":"Kanbara",
    "wof:placetype":"locality"
},
  "geometry": {"coordinates":[138.97720000000001,35.11721],"type":"Point"}
}