{
  "type": "Feature",
  "properties": {
    "gn:admin1_code":"19.0",
    "gn:admin2_code":"1848350.0",
    "gn:admin3_code":"14107.0",
    "gn:asciiname":"Isogodai",
    "gn:country_code":"JP",
    "gn:dem":61,
    "gn:feature_class":"P",
    "gn:feature_code":"PPL",
    "gn:name":"Isogodai",
    "gn:population":0,
    "gn:timezone":"Asia/Tokyo",
    "iso:country":"JP",
    "name:jpn_x_preferred":[
        "\u78ef\u5b50\u53f0"
    ],
    "name:jpn_x_variant":[
        "\u3044\u305d\u3054\u3060\u3044",
        "\u30a4\u30bd\u30b4\u30c0\u30a4"
    ],
    "wof:name":"Isogodai",
    "wof:placetype":"locality"
},
  "geometry": {"coordinates":[139.61301,35.40369000000001],"type":"Point"}
}