{
  "type": "Feature",
  "properties": {
    "gn:admin1_code":"24.0",
    "gn:admin2_code":"2112261.0",
    "gn:asciiname":"Shirahama",
    "gn:country_code":"JP",
    "gn:dem":41,
    "gn:feature_class":"P",
    "gn:feature_code":"PPL",
    "gn:name":"Shirahama",
    "gn:population":0,
    "gn:timezone":"Asia/Tokyo",
    "iso:country":"JP",
    "name:jpn_x_preferred":[
        "\u767d\u6d5c"
    ],
    "name:jpn_x_variant":[
        "\u3057\u3089\u306f\u307e",
        "\u30b7\u30e9\u30cf\u30de"
    ],
    "wof:name":"Shirahama",
    "wof:placetype":"locality"
},
  "geometry": {"coordinates":[141.63697999999999,38.92648],"type":"Point"}
}