{
  "type": "Feature",
  "properties": {
    "gn:admin1_code":"40.0",
    "gn:admin2_code":"1864514.0",
    "gn:asciiname":"Fuda",
    "gn:country_code":"JP",
    "gn:dem":38,
    "gn:feature_class":"P",
    "gn:feature_code":"PPL",
    "gn:name":"Fuda",
    "gn:population":0,
    "gn:timezone":"Asia/Tokyo",
    "iso:country":"JP",
    "name:ceb_x_preferred":[
        "Fuda"
    ],
    "name:jpn_x_preferred":[
        "\u5e03\u7530"
    ],
    "name:swe_x_preferred":[
        "Fuda"
    ],
    "wof:name":"Fuda",
    "wof:placetype":"locality"
},
  "geometry": {"coordinates":[139.54724999999999,35.64861],"type":"Point"}
}