{
  "type": "Feature",
  "properties": {
    "gn:admin1_code":"27.0",
    "gn:admin2_code":"7418810.0",
    "gn:asciiname":"Tsuwa",
    "gn:country_code":"JP",
    "gn:dem":11,
    "gn:feature_class":"P",
    "gn:feature_code":"PPL",
    "gn:name":"Tsuwa",
    "gn:population":0,
    "gn:timezone":"Asia/Tokyo",
    "iso:country":"JP",
    "name:jpn_x_preferred":[
        "\u6d25\u548c"
    ],
    "wof:name":"Tsuwa",
    "wof:placetype":"locality"
},
  "geometry": {"coordinates":[129.46600000000001,34.63563],"type":"Point"}
}