{
  "type": "Feature",
  "properties": {
    "gn:admin1_code":"40",
    "gn:admin2_code":"1856786.0",
    "gn:admin3_code":"13381.0",
    "gn:asciiname":"Tsubota",
    "gn:country_code":"JP",
    "gn:dem":86,
    "gn:feature_class":"P",
    "gn:feature_code":"PPL",
    "gn:name":"Tsubota",
    "gn:population":0,
    "gn:timezone":"Asia/Tokyo",
    "iso:country":"JP",
    "name:jpn_x_preferred":[
        "\u576a\u7530"
    ],
    "name:und_x_variant":[
        "Tubota",
        "Tsubota"
    ],
    "wof:name":"Tsubota",
    "wof:placetype":"locality"
},
  "geometry": {"coordinates":[139.53381000000002,34.05724],"type":"Point"}
}