{
  "type": "Feature",
  "properties": {
    "gn:admin1_code":"19",
    "gn:admin2_code":"1859635.0",
    "gn:admin3_code":"14133.0",
    "gn:asciiname":"Shimonumabe",
    "gn:country_code":"JP",
    "gn:dem":10,
    "gn:feature_class":"P",
    "gn:feature_code":"PPL",
    "gn:name":"Shimonumabe",
    "gn:population":0,
    "gn:timezone":"Asia/Tokyo",
    "iso:country":"JP",
    "name:jpn_x_preferred":[
        "\u4e0b\u6cbc\u90e8"
    ],
    "name:und_x_variant":[
        "Tamagawa Mukai",
        "Shimonumabe"
    ],
    "wof:name":"Shimonumabe",
    "wof:placetype":"locality"
},
  "geometry": {"coordinates":[139.66946999999999,35.57425],"type":"Point"}
}