{
  "type": "Feature",
  "properties": {
    "gn:admin1_code":"3.0",
    "gn:admin2_code":"7439944.0",
    "gn:asciiname":"Tsuruno",
    "gn:country_code":"JP",
    "gn:dem":9,
    "gn:feature_class":"P",
    "gn:feature_code":"PPL",
    "gn:name":"Tsuruno",
    "gn:population":0,
    "gn:timezone":"Asia/Tokyo",
    "iso:country":"JP",
    "name:jpn_x_preferred":[
        "\u9db4\u91ce"
    ],
    "name:jpn_x_variant":[
        "\u3064\u308b\u306e",
        "\u30c4\u30eb\u30ce"
    ],
    "wof:name":"Tsuruno",
    "wof:placetype":"locality"
},
  "geometry": {"coordinates":[140.41412,40.78968],"type":"Point"}
}