{
  "type": "Feature",
  "properties": {
    "gn:admin1_code":"34.0",
    "gn:admin2_code":"1862655.0",
    "gn:admin3_code":"11346.0",
    "gn:asciiname":"Demaru-shimogo",
    "gn:country_code":"JP",
    "gn:dem":10,
    "gn:feature_class":"P",
    "gn:feature_code":"PPL",
    "gn:name":"Demaru-shimog\u014d",
    "gn:population":0,
    "gn:timezone":"Asia/Tokyo",
    "iso:country":"JP",
    "name:jpn_x_preferred":[
        "\u51fa\u4e38\u4e0b\u90f7"
    ],
    "name:jpn_x_variant":[
        "\u3067\u307e\u308b\u3057\u3082\u3054\u3046",
        "\u30c7\u30de\u30eb\u30b7\u30e2\u30b4\u30a6"
    ],
    "name:und_x_variant":[
        "Demaru-shimog\u014d"
    ],
    "wof:name":"Demaru-shimogo",
    "wof:placetype":"locality"
},
  "geometry": {"coordinates":[139.51208,35.9732],"type":"Point"}
}