{
  "type": "Feature",
  "properties": {
    "iso:country":"JP",
    "name:eng_x_preferred":[
        "Kotake Town"
    ],
    "name:jpn_x_preferred":[
        "\u5c0f\u7af9\u753a"
    ],
    "qs:name":"\u5c0f\u7af9\u753a",
    "qs:name_adm0":"\u65e5\u672c",
    "qs:name_adm1":"\u798f\u5ca1\u770c",
    "qs:photos":62,
    "qs:photos_1k":13,
    "qs:photos_9k":1,
    "qs:photos_9r":2,
    "qs:photos_all":62,
    "qs:photos_sr":2,
    "qs:placetype":"Town",
    "qs:pop_sr":"0",
    "wof:name":"Kotake Town",
    "wof:placetype":"locality"
},
  "geometry": {"coordinates":[130.705547,33.704491],"type":"Point"}
}