{
  "type": "Feature",
  "properties": {
    "gn:admin1_code":"21.0",
    "gn:admin2_code":"7412706.0",
    "gn:admin3_code":"43442.0",
    "gn:asciiname":"Idera",
    "gn:country_code":"JP",
    "gn:dem":6,
    "gn:feature_class":"P",
    "gn:feature_code":"PPL",
    "gn:name":"Idera",
    "gn:population":0,
    "gn:timezone":"Asia/Tokyo",
    "iso:country":"JP",
    "name:jpn_x_preferred":[
        "\u4e95\u5bfa"
    ],
    "name:jpn_x_variant":[
        "\u3044\u3067\u3089",
        "\u30a4\u30c7\u30e9"
    ],
    "wof:name":"Idera",
    "wof:placetype":"locality"
},
  "geometry": {"coordinates":[130.77597,32.75076],"type":"Point"}
}