{
  "type": "Feature",
  "properties": {
    "gn:admin1_code":"18.0",
    "gn:admin2_code":"7383999.0",
    "gn:admin3_code":"46491.0",
    "gn:asciiname":"Kadonoki",
    "gn:country_code":"JP",
    "gn:dem":228,
    "gn:feature_class":"P",
    "gn:feature_code":"PPLL",
    "gn:name":"Kadonoki",
    "gn:population":0,
    "gn:timezone":"Asia/Tokyo",
    "iso:country":"JP",
    "name:jpn_x_preferred":[
        "\u9580\u6728"
    ],
    "wof:name":"Kadonoki",
    "wof:placetype":"locality"
},
  "geometry": {"coordinates":[130.81788,31.17545],"type":"Point"}
}