{
  "type": "Feature",
  "properties": {
    "gn:admin1_code":"7.0",
    "gn:admin2_code":"1861834.0",
    "gn:asciiname":"Chaya",
    "gn:country_code":"JP",
    "gn:dem":246,
    "gn:feature_class":"P",
    "gn:feature_code":"PPLL",
    "gn:name":"Chaya",
    "gn:population":0,
    "gn:timezone":"Asia/Tokyo",
    "iso:country":"JP",
    "name:jpn_x_preferred":[
        "\u8336\u5c4b"
    ],
    "wof:name":"Chaya",
    "wof:placetype":"locality"
},
  "geometry": {"coordinates":[130.62141,33.64146],"type":"Point"}
}