{
  "type": "Feature",
  "properties": {
    "gn:admin1_code":"3.0",
    "gn:admin2_code":"2130056.0",
    "gn:asciiname":"Waseda",
    "gn:country_code":"JP",
    "gn:dem":23,
    "gn:feature_class":"P",
    "gn:feature_code":"PPL",
    "gn:name":"Waseda",
    "gn:population":0,
    "gn:timezone":"Asia/Tokyo",
    "iso:country":"JP",
    "name:jpn_x_preferred":[
        "\u65e9\u7a32\u7530"
    ],
    "name:jpn_x_variant":[
        "\u308f\u305b\u3060",
        "\u30ef\u30bb\u30c0"
    ],
    "wof:name":"Waseda",
    "wof:placetype":"locality"
},
  "geometry": {"coordinates":[140.51421000000002,40.60299000000001],"type":"Point"}
}