{
  "type": "Feature",
  "properties": {
    "gn:admin1_code":"42",
    "gn:admin2_code":"1849235.0",
    "gn:asciiname":"Motoshinmachi",
    "gn:country_code":"JP",
    "gn:dem":7,
    "gn:feature_class":"P",
    "gn:feature_code":"PPL",
    "gn:name":"Motoshinmachi",
    "gn:population":0,
    "gn:timezone":"Asia/Tokyo",
    "iso:country":"JP",
    "name:jpn_x_preferred":[
        "\u672c\u65b0\u753a"
    ],
    "name:und_x_variant":[
        "Motoshin"
    ],
    "wof:name":"Motoshinmachi",
    "wof:placetype":"locality"
},
  "geometry": {"coordinates":[137.39948999999999,36.81585],"type":"Point"}
}