{
  "type": "Feature",
  "properties": {
    "gn:admin1_code":"4.0",
    "gn:admin2_code":"1864901.0",
    "gn:admin3_code":"12463.0",
    "gn:asciiname":"Wami",
    "gn:country_code":"JP",
    "gn:dem":21,
    "gn:feature_class":"P",
    "gn:feature_code":"PPLL",
    "gn:name":"Wami",
    "gn:population":0,
    "gn:timezone":"Asia/Tokyo",
    "iso:country":"JP",
    "name:jpn_x_preferred":[
        "\u548c\u898b"
    ],
    "name:jpn_x_variant":[
        "\u308f\u307f",
        "\u30ef\u30df"
    ],
    "wof:name":"Wami",
    "wof:placetype":"locality"
},
  "geometry": {"coordinates":[139.84226999999998,35.11505],"type":"Point"}
}