{
  "type": "Feature",
  "properties": {
    "gn:admin1_code":"12.0",
    "gn:admin2_code":"7428106.0",
    "gn:admin3_code":"1547.0",
    "gn:asciiname":"Kamitoku",
    "gn:country_code":"JP",
    "gn:dem":91,
    "gn:feature_class":"P",
    "gn:feature_code":"PPL",
    "gn:name":"Kamitoku",
    "gn:population":0,
    "gn:timezone":"Asia/Tokyo",
    "iso:country":"JP",
    "name:jpn_x_preferred":[
        "\u4e0a\u5fb3"
    ],
    "name:jpn_x_variant":[
        "\u304b\u307f\u3068\u304f",
        "\u30ab\u30df\u30c8\u30af"
    ],
    "name:und_x_variant":[
        "Kami-tokusabara",
        "Kami-tokusawara",
        "Kamitoku"
    ],
    "wof:name":"Kamitoku",
    "wof:placetype":"locality"
},
  "geometry": {"coordinates":[144.43283,43.81176],"type":"Point"}
}