{
  "type": "Feature",
  "properties": {
    "gn:admin1_code":"33.0",
    "gn:admin2_code":"1850771.0",
    "gn:asciiname":"Kitatakumachi-takubaru",
    "gn:country_code":"JP",
    "gn:dem":76,
    "gn:feature_class":"P",
    "gn:feature_code":"PPL",
    "gn:name":"Kitatakumachi-takubaru",
    "gn:population":0,
    "gn:timezone":"Asia/Tokyo",
    "iso:country":"JP",
    "name:jpn_x_preferred":[
        "\u5317\u591a\u4e45\u753a\u591a\u4e45\u539f"
    ],
    "wof:name":"Kitatakumachi-takubaru",
    "wof:placetype":"locality"
},
  "geometry": {"coordinates":[130.12360000000001,33.29327],"type":"Point"}
}