{
  "type": "Feature",
  "properties": {
    "gn:admin1_code":"21.0",
    "gn:admin2_code":"1865358.0",
    "gn:asciiname":"Kuwanoura",
    "gn:country_code":"JP",
    "gn:dem":15,
    "gn:feature_class":"P",
    "gn:feature_code":"PPLL",
    "gn:name":"Kuwanoura",
    "gn:population":0,
    "gn:timezone":"Asia/Tokyo",
    "iso:country":"JP",
    "name:jpn_x_preferred":[
        "\u6851\u306e\u6d66"
    ],
    "name:jpn_x_variant":[
        "\u304f\u308f\u306e\u3046\u3089",
        "\u30af\u30ef\u30ce\u30a6\u30e9"
    ],
    "wof:name":"Kuwanoura",
    "wof:placetype":"locality"
},
  "geometry": {"coordinates":[130.36725000000001,32.51713],"type":"Point"}
}