{
  "type": "Feature",
  "properties": {
    "gn:admin1_code":"43.0",
    "gn:admin2_code":"1865123.0",
    "gn:admin3_code":"30366.0",
    "gn:asciiname":"Miyagawa",
    "gn:country_code":"JP",
    "gn:dem":326,
    "gn:feature_class":"P",
    "gn:feature_code":"PPL",
    "gn:name":"Miyagawa",
    "gn:population":0,
    "gn:timezone":"Asia/Tokyo",
    "iso:country":"JP",
    "name:deu_x_preferred":[
        "Miyagawa"
    ],
    "name:fra_x_preferred":[
        "Miyagawa"
    ],
    "name:jpn_x_preferred":[
        "\u5bae\u5ddd"
    ],
    "wof:name":"Miyagawa",
    "wof:placetype":"locality"
},
  "geometry": {"coordinates":[135.4332,34.10292],"type":"Point"}
}