{
  "type": "Feature",
  "properties": {
    "gn:admin1_code":"07",
    "gn:admin2_code":"1859306.0",
    "gn:admin3_code":"40101.0",
    "gn:asciiname":"Kyumoji",
    "gn:country_code":"JP",
    "gn:dem":0,
    "gn:feature_class":"P",
    "gn:feature_code":"PPL",
    "gn:name":"Ky\u016bmoji",
    "gn:population":0,
    "gn:timezone":"Asia/Tokyo",
    "iso:country":"JP",
    "name:jpn_x_preferred":[
        "\u9580\u53f8"
    ],
    "name:jpn_x_variant":[
        "\u65e7\u9580\u53f8"
    ],
    "name:und_x_variant":[
        "Mozi",
        "Moji",
        "Ky\u016bmoji"
    ],
    "wof:name":"Kyumoji",
    "wof:placetype":"locality"
},
  "geometry": {"coordinates":[130.96584999999999,33.95373],"type":"Point"}
}