{
  "type": "Feature",
  "properties": {
    "gn:admin1_code":"2.0",
    "gn:admin2_code":"7443156.0",
    "gn:asciiname":"Fukaseki",
    "gn:country_code":"JP",
    "gn:dem":40,
    "gn:feature_class":"P",
    "gn:feature_code":"PPLL",
    "gn:name":"Fukaseki",
    "gn:population":0,
    "gn:timezone":"Asia/Tokyo",
    "iso:country":"JP",
    "name:jpn_x_preferred":[
        "\u6df1\u95a2"
    ],
    "wof:name":"Fukaseki",
    "wof:placetype":"locality"
},
  "geometry": {"coordinates":[140.35666000000001,40.241],"type":"Point"}
}