{
  "type": "Feature",
  "properties": {
    "gn:admin1_code":"29.0",
    "gn:admin2_code":"7468177.0",
    "gn:asciiname":"Obazawa",
    "gn:country_code":"JP",
    "gn:dem":27,
    "gn:feature_class":"P",
    "gn:feature_code":"PPL",
    "gn:name":"\u014cbazawa",
    "gn:population":0,
    "gn:timezone":"Asia/Tokyo",
    "iso:country":"JP",
    "name:jpn_x_preferred":[
        "\u5927\u5834\u6ca2"
    ],
    "name:und_x_variant":[
        "\u014cbazawa"
    ],
    "wof:name":"Obazawa",
    "wof:placetype":"locality"
},
  "geometry": {"coordinates":[139.53063999999998,38.24658],"type":"Point"}
}