{
  "type": "Feature",
  "properties": {
    "iso:country":"JP",
    "name:eng_x_preferred":[
        "Rokkakubashi 6 Chome"
    ],
    "name:eng_x_variant":[
        "Rokkakubashi 6 Choume",
        "Rokkakubashi 6 Chome"
    ],
    "name:jpn_x_preferred":[
        "\uff16\u4e01\u76ee"
    ],
    "name:jpn_x_variant":[
        "\u308d\u3063\u304b\u304f\u3070\u3057 \uff16\u3061\u3087\u3046\u3081",
        "\u516d\u89d2\u6a4b \uff16\u4e01\u76ee",
        "\uff16\u3061\u3087\u3046\u3081"
    ],
    "qs:gn_local":0,
    "qs:local_max":6208,
    "qs:local_sum":82309,
    "qs:localhoods":190,
    "qs:name":"\uff16\u4e01\u76ee",
    "qs:name_adm0":"\u65e5\u672c",
    "qs:name_adm1":"\u795e\u5948\u5ddd\u770c",
    "qs:name_adm2":"\u795e\u5948\u5ddd\u533a",
    "qs:name_en":"Rokkakubashi 6 Chome",
    "qs:name_lau":"\u516d\u89d2\u6a4b",
    "qs:name_local":"\u6a2a\u6d5c\u5e02",
    "qs:photo_max":36,
    "qs:photo_sum":129,
    "qs:placetype":"Suburb",
    "qs:quad_count":13,
    "qs:woe_adm0":23424856,
    "qs:woe_adm1":2345868,
    "qs:woe_adm2":15015382,
    "qs:woe_lau":28415655,
    "qs:woe_local":1118550,
    "qs:woe_ver":"7.10.0",
    "wof:lang":[
        "jpn"
    ],
    "wof:name":"\uff16\u4e01\u76ee",
    "wof:placetype":"neighbourhood"
},
  "geometry": {"coordinates":[139.615488,35.495603],"type":"Point"}
}