{
  "type": "Feature",
  "properties": {
    "gn:admin1_code":"24.0",
    "gn:admin2_code":"2111147.0",
    "gn:admin3_code":"4102.0",
    "gn:asciiname":"Wada-shinden",
    "gn:country_code":"JP",
    "gn:dem":2,
    "gn:feature_class":"P",
    "gn:feature_code":"PPL",
    "gn:name":"Wada-shinden",
    "gn:population":0,
    "gn:timezone":"Asia/Tokyo",
    "iso:country":"JP",
    "wof:name":"Wada-shinden",
    "wof:placetype":"locality"
},
  "geometry": {"coordinates":[140.98972000000001,38.25611],"type":"Point"}
}