{
  "type": "Feature",
  "properties": {
    "iso:country":"JP",
    "name:eng_x_preferred":[
        "Nagaoka City"
    ],
    "name:jpn_x_preferred":[
        "\u9577\u5ca1\u5e02"
    ],
    "qs:name":"\u9577\u5ca1\u5e02",
    "qs:name_adm0":"\u65e5\u672c",
    "qs:name_adm1":"\u65b0\u6f5f\u770c",
    "qs:photos":1477,
    "qs:photos_1k":299,
    "qs:photos_9k":31,
    "qs:photos_9r":15,
    "qs:photos_all":6961,
    "qs:photos_sr":12,
    "qs:placetype":"Town",
    "qs:pop_sr":"0",
    "wof:name":"Nagaoka City",
    "wof:placetype":"locality"
},
  "geometry": {"coordinates":[138.77297300000001,37.413664],"type":"Point"}
}