{
  "type": "Feature",
  "properties": {
    "gn:admin1_code":"19.0",
    "gn:admin2_code":"1848350.0",
    "gn:admin3_code":"14108.0",
    "gn:asciiname":"Yatsucho",
    "gn:country_code":"JP",
    "gn:dem":6,
    "gn:feature_class":"P",
    "gn:feature_code":"PPL",
    "gn:name":"Yatsuch\u014d",
    "gn:population":0,
    "gn:timezone":"Asia/Tokyo",
    "iso:country":"JP",
    "name:jpn_x_preferred":[
        "\u8c37\u6d25\u753a"
    ],
    "name:jpn_x_variant":[
        "\u3084\u3064\u3061\u3087\u3046",
        "\u30e4\u30c4\u30c1\u30e7\u30a6"
    ],
    "name:und_x_variant":[
        "Yatsuch\u014d"
    ],
    "wof:name":"Yatsucho",
    "wof:placetype":"locality"
},
  "geometry": {"coordinates":[139.62353000000002,35.34480999999999],"type":"Point"}
}