{
  "type": "Feature",
  "properties": {
    "gn:admin1_code":"30",
    "gn:admin2_code":"7414051.0",
    "gn:asciiname":"Makiguchi",
    "gn:country_code":"JP",
    "gn:dem":181,
    "gn:feature_class":"P",
    "gn:feature_code":"PPL",
    "gn:name":"Makiguchi",
    "gn:population":0,
    "gn:timezone":"Asia/Tokyo",
    "iso:country":"JP",
    "wof:name":"Makiguchi",
    "wof:placetype":"locality"
},
  "geometry": {"coordinates":[131.51667,32.96667],"type":"Point"}
}