{
  "type": "Feature",
  "properties": {
    "gn:admin1_code":"18",
    "gn:admin2_code":"1852852.0",
    "gn:admin3_code":"46392.0",
    "gn:asciiname":"Idebara",
    "gn:cc2":"JP",
    "gn:country_code":"JP",
    "gn:dem":80,
    "gn:feature_class":"P",
    "gn:feature_code":"PPL",
    "gn:name":"Idebara",
    "gn:population":0,
    "gn:timezone":"Asia/Tokyo",
    "iso:country":"JP",
    "name:und_x_variant":[
        "Itehara",
        "Itenaro",
        "Idebara"
    ],
    "wof:name":"Idebara",
    "wof:placetype":"locality"
},
  "geometry": {"coordinates":[130.44999999999999,31.95],"type":"Point"}
}