{
  "type": "Feature",
  "properties": {
    "gn:admin1_code":"28.0",
    "gn:admin2_code":"1855604.0",
    "gn:asciiname":"Sugawacho",
    "gn:country_code":"JP",
    "gn:dem":210,
    "gn:feature_class":"P",
    "gn:feature_code":"PPL",
    "gn:name":"Sugawach\u014d",
    "gn:population":0,
    "gn:timezone":"Asia/Tokyo",
    "iso:country":"JP",
    "name:jpn_x_preferred":[
        "\u9808\u5ddd\u753a"
    ],
    "name:und_x_variant":[
        "Sugawach\u014d"
    ],
    "wof:name":"Sugawacho",
    "wof:placetype":"locality"
},
  "geometry": {"coordinates":[135.90965,34.71646],"type":"Point"}
}