{
  "type": "Feature",
  "properties": {
    "gn:admin1_code":"4.0",
    "gn:admin2_code":"2111854.0",
    "gn:asciiname":"Takashidai",
    "gn:country_code":"JP",
    "gn:dem":13,
    "gn:feature_class":"P",
    "gn:feature_code":"PPL",
    "gn:name":"Takashidai",
    "gn:population":0,
    "gn:timezone":"Asia/Tokyo",
    "iso:country":"JP",
    "name:jpn_x_preferred":[
        "\u9ad8\u5e2b\u53f0"
    ],
    "name:jpn_x_variant":[
        "\u305f\u304b\u3057\u3060\u3044",
        "\u30bf\u30ab\u30b7\u30c0\u30a4"
    ],
    "wof:name":"Takashidai",
    "wof:placetype":"locality"
},
  "geometry": {"coordinates":[140.29008999999999,35.43793],"type":"Point"}
}