{
  "type": "Feature",
  "properties": {
    "gn:admin1_code":"24.0",
    "gn:admin2_code":"2112574.0",
    "gn:asciiname":"Oginohama",
    "gn:country_code":"JP",
    "gn:dem":5,
    "gn:feature_class":"P",
    "gn:feature_code":"PPL",
    "gn:name":"Oginohama",
    "gn:population":0,
    "gn:timezone":"Asia/Tokyo",
    "iso:country":"JP",
    "name:jpn_x_preferred":[
        "\u837b\u6d5c"
    ],
    "name:jpn_x_variant":[
        "\u304a\u304e\u306e\u306f\u307e",
        "\u30aa\u30ae\u30ce\u30cf\u30de"
    ],
    "wof:name":"Oginohama",
    "wof:placetype":"locality"
},
  "geometry": {"coordinates":[141.44784999999999,38.37759000000001],"type":"Point"}
}