{
  "type": "Feature",
  "properties": {
    "gn:admin1_code":"30",
    "gn:admin2_code":"1858008.0",
    "gn:admin3_code":"44462.0",
    "gn:asciiname":"Bungo-Mori",
    "gn:country_code":"JP",
    "gn:dem":346,
    "gn:feature_class":"P",
    "gn:feature_code":"PPL",
    "gn:name":"Bungo-Mori",
    "gn:population":0,
    "gn:timezone":"Asia/Tokyo",
    "iso:country":"JP",
    "wof:name":"Bungo-Mori",
    "wof:placetype":"locality"
},
  "geometry": {"coordinates":[131.15111000000002,33.27472],"type":"Point"}
}