{
  "type": "Feature",
  "properties": {
    "iso:country":"JP",
    "name:eng_x_preferred":[
        "Yakumo Town"
    ],
    "name:jpn_x_preferred":[
        "\u516b\u96f2\u753a"
    ],
    "qs:name":"\u516b\u96f2\u753a",
    "qs:name_adm0":"\u65e5\u672c",
    "qs:name_adm1":"\u5317\u6d77\u9053",
    "qs:photos":318,
    "qs:photos_1k":64,
    "qs:photos_9k":1,
    "qs:photos_9r":5,
    "qs:photos_all":334,
    "qs:photos_sr":5,
    "qs:placetype":"Town",
    "qs:pop_sr":"0",
    "wof:name":"Yakumo Town",
    "wof:placetype":"locality"
},
  "geometry": {"coordinates":[140.27171999999999,42.260181],"type":"Point"}
}