{
  "type": "Feature",
  "properties": {
    "iso:country":"JP",
    "name:eng_x_preferred":[
        "Asahino 2 Chome"
    ],
    "name:eng_x_variant":[
        "Asahino 2 Choume",
        "Asahino 2 Chome"
    ],
    "name:jpn_x_preferred":[
        "\uff12\u4e01\u76ee"
    ],
    "name:jpn_x_variant":[
        "\u3042\u3055\u3072\u306e \uff12\u3061\u3087\u3046\u3081",
        "\u671d\u65e5\u91ce \uff12\u4e01\u76ee",
        "\uff12\u3061\u3087\u3046\u3081"
    ],
    "name:unk_x_variant":[
        "\uff12\u4e01\u76ee"
    ],
    "qs:gn_local":0,
    "qs:local_max":27,
    "qs:local_sum":27,
    "qs:localhoods":1,
    "qs:name":"\uff12\u4e01\u76ee",
    "qs:name_adm0":"\u65e5\u672c",
    "qs:name_adm1":"\u7fa4\u99ac\u770c",
    "qs:name_adm2":"\u9091\u697d\u90e1",
    "qs:name_en":"Asahino 2 Chome",
    "qs:name_lau":"\u671d\u65e5\u91ce",
    "qs:name_local":"\u677f\u5009\u753a",
    "qs:photo_max":11,
    "qs:photo_sum":27,
    "qs:placetype":"Suburb",
    "qs:quad_count":8,
    "qs:woe_adm0":23424856,
    "qs:woe_adm1":2345860,
    "qs:woe_adm2":24857136,
    "qs:woe_lau":28407550,
    "qs:woe_local":24710164,
    "qs:woe_ver":"7.10.0",
    "wof:lang":[
        "jpn"
    ],
    "wof:name":"\uff12\u4e01\u76ee",
    "wof:placetype":"neighbourhood"
},
  "geometry": {"coordinates":[139.665831,36.230408],"type":"Point"}
}