{
  "type": "Feature",
  "properties": {
    "gn:admin1_code":"18",
    "gn:admin2_code":"7383993.0",
    "gn:asciiname":"Matsunaga",
    "gn:country_code":"JP",
    "gn:dem":93,
    "gn:feature_class":"P",
    "gn:feature_code":"PPL",
    "gn:name":"Matsunaga",
    "gn:population":0,
    "gn:timezone":"Asia/Tokyo",
    "iso:country":"JP",
    "wof:name":"Matsunaga",
    "wof:placetype":"locality"
},
  "geometry": {"coordinates":[130.43333000000001,31.28333],"type":"Point"}
}