{
  "type": "Feature",
  "properties": {
    "iso:country":"JP",
    "name:eng_x_preferred":[
        "Hibikimachi 3 Chome"
    ],
    "name:eng_x_variant":[
        "Hibikimachi 3 Choume",
        "Hibikimachi 3 Chome"
    ],
    "name:jpn_x_preferred":[
        "\uff13\u4e01\u76ee"
    ],
    "name:jpn_x_variant":[
        "\u3072\u3073\u304d\u307e\u3061 \uff13\u3061\u3087\u3046\u3081",
        "\u97ff\u753a \uff13\u4e01\u76ee",
        "\uff13\u3061\u3087\u3046\u3081"
    ],
    "qs:gn_local":0,
    "qs:local_max":819,
    "qs:local_sum":3269,
    "qs:localhoods":25,
    "qs:name":"\uff13\u4e01\u76ee",
    "qs:name_adm0":"\u65e5\u672c",
    "qs:name_adm1":"\u798f\u5ca1\u770c",
    "qs:name_adm2":"\u82e5\u677e\u533a",
    "qs:name_en":"Hibikimachi 3 Chome",
    "qs:name_lau":"\u97ff\u753a",
    "qs:name_local":"\u5317\u4e5d\u5dde\u5e02",
    "qs:photo_max":8,
    "qs:photo_sum":13,
    "qs:placetype":"Suburb",
    "qs:quad_count":5,
    "qs:woe_adm0":23424856,
    "qs:woe_adm1":58646425,
    "qs:woe_adm2":15015568,
    "qs:woe_lau":28482481,
    "qs:woe_local":1110809,
    "qs:woe_ver":"7.10.0",
    "wof:lang":[
        "jpn"
    ],
    "wof:name":"\uff13\u4e01\u76ee",
    "wof:placetype":"neighbourhood"
},
  "geometry": {"coordinates":[130.731176,33.929511],"type":"Point"}
}