{
  "type": "Feature",
  "properties": {
    "gn:admin1_code":"18.0",
    "gn:admin2_code":"8300556.0",
    "gn:asciiname":"Yanagidani",
    "gn:country_code":"JP",
    "gn:dem":19,
    "gn:feature_class":"P",
    "gn:feature_code":"PPLL",
    "gn:name":"Yanagidani",
    "gn:population":0,
    "gn:timezone":"Asia/Tokyo",
    "iso:country":"JP",
    "name:jpn_x_preferred":[
        "\u67f3\u8c37"
    ],
    "wof:name":"Yanagidani",
    "wof:placetype":"locality"
},
  "geometry": {"coordinates":[130.9315,31.37469],"type":"Point"}
}