{
  "type": "Feature",
  "properties": {
    "gn:admin1_code":"27",
    "gn:admin2_code":"7418810.0",
    "gn:asciiname":"Toyotamacho-itose",
    "gn:country_code":"JP",
    "gn:dem":12,
    "gn:feature_class":"P",
    "gn:feature_code":"PPL",
    "gn:name":"Toyotamach\u014d-itose",
    "gn:population":0,
    "gn:timezone":"Asia/Tokyo",
    "iso:country":"JP",
    "name:jpn_x_preferred":[
        "\u8c4a\u7389\u753a\u7cf8\u702c"
    ],
    "name:und_x_variant":[
        "Itosi",
        "Itose",
        "Toyotamach\u014d-itose"
    ],
    "wof:name":"Toyotamacho-itose",
    "wof:placetype":"locality"
},
  "geometry": {"coordinates":[129.32021,34.37175],"type":"Point"}
}