{
  "type": "Feature",
  "properties": {
    "gn:admin1_code":"32.0",
    "gn:admin2_code":"1862032.0",
    "gn:asciiname":"Yamatedai",
    "gn:country_code":"JP",
    "gn:dem":81,
    "gn:feature_class":"P",
    "gn:feature_code":"PPL",
    "gn:name":"Yamatedai",
    "gn:population":0,
    "gn:timezone":"Asia/Tokyo",
    "iso:country":"JP",
    "name:jpn_x_preferred":[
        "\u5c71\u624b\u53f0"
    ],
    "wof:name":"Yamatedai",
    "wof:placetype":"locality"
},
  "geometry": {"coordinates":[135.55633,34.85875],"type":"Point"}
}