{
  "type": "Feature",
  "properties": {
    "gn:admin1_code":"32",
    "gn:admin2_code":"1853897.0",
    "gn:admin3_code":"27102.0",
    "gn:asciiname":"Tomobuchicho",
    "gn:country_code":"JP",
    "gn:dem":5,
    "gn:feature_class":"P",
    "gn:feature_code":"PPL",
    "gn:name":"Tomobuchich\u014d",
    "gn:population":0,
    "gn:timezone":"Asia/Tokyo",
    "iso:country":"JP",
    "name:jpn_x_preferred":[
        "\u53cb\u6e15\u753a"
    ],
    "name:und_x_variant":[
        "Tomobuchi",
        "Tomofuchich\u014d",
        "Tomobuchimachi",
        "Tomobuchich\u014d"
    ],
    "wof:name":"Tomobuchicho",
    "wof:placetype":"locality"
},
  "geometry": {"coordinates":[135.52677,34.71739],"type":"Point"}
}