{
  "type": "Feature",
  "properties": {
    "gn:admin1_code":"21.0",
    "gn:admin2_code":"1850743.0",
    "gn:asciiname":"Yamabeta",
    "gn:country_code":"JP",
    "gn:dem":6,
    "gn:feature_class":"P",
    "gn:feature_code":"PPL",
    "gn:name":"Yamabeta",
    "gn:population":0,
    "gn:timezone":"Asia/Tokyo",
    "iso:country":"JP",
    "name:jpn_x_preferred":[
        "\u5c71\u90e8\u7530"
    ],
    "name:jpn_x_variant":[
        "\u3084\u307e\u3079\u305f",
        "\u30e4\u30de\u30d9\u30bf"
    ],
    "wof:name":"Yamabeta",
    "wof:placetype":"locality"
},
  "geometry": {"coordinates":[130.60036000000002,32.94935],"type":"Point"}
}