{
  "type": "Feature",
  "properties": {
    "gn:admin1_code":"24.0",
    "gn:admin2_code":"7446986.0",
    "gn:admin3_code":"4581.0",
    "gn:asciiname":"Kirigasaki",
    "gn:country_code":"JP",
    "gn:dem":11,
    "gn:feature_class":"P",
    "gn:feature_code":"PPL",
    "gn:name":"Kirigasaki",
    "gn:population":0,
    "gn:timezone":"Asia/Tokyo",
    "iso:country":"JP",
    "name:jpn_x_preferred":[
        "\u6850\u30f6\u5d0e"
    ],
    "name:jpn_x_variant":[
        "\u304d\u308a\u304c\u3055\u304d",
        "\u30ad\u30ea\u30ac\u30b5\u30ad"
    ],
    "wof:name":"Kirigasaki",
    "wof:placetype":"locality"
},
  "geometry": {"coordinates":[141.47843999999995,38.44147],"type":"Point"}
}