{
  "type": "Feature",
  "properties": {
    "gn:admin1_code":"39",
    "gn:admin2_code":"1860803.0",
    "gn:admin3_code":"36388.0",
    "gn:asciiname":"Shishikuiura",
    "gn:country_code":"JP",
    "gn:dem":3,
    "gn:feature_class":"P",
    "gn:feature_code":"PPL",
    "gn:name":"Shishikuiura",
    "gn:population":0,
    "gn:timezone":"Asia/Tokyo",
    "iso:country":"JP",
    "name:jpn_x_preferred":[
        "\u5b8d\u55b0\u6d66"
    ],
    "name:und_x_variant":[
        "Siskui",
        "Shishikui",
        "Shishikuiura"
    ],
    "wof:name":"Shishikuiura",
    "wof:placetype":"locality"
},
  "geometry": {"coordinates":[134.30000000000001,33.56667],"type":"Point"}
}