{
  "type": "Feature",
  "properties": {
    "gn:admin1_code":"15.0",
    "gn:admin2_code":"1858904.0",
    "gn:asciiname":"Matsuokamachi",
    "gn:country_code":"JP",
    "gn:dem":98,
    "gn:feature_class":"P",
    "gn:feature_code":"PPL",
    "gn:name":"Matsuokamachi",
    "gn:population":0,
    "gn:timezone":"Asia/Tokyo",
    "iso:country":"JP",
    "name:jpn_x_preferred":[
        "\u677e\u5ca1\u753a"
    ],
    "wof:name":"Matsuokamachi",
    "wof:placetype":"locality"
},
  "geometry": {"coordinates":[136.53322,36.34425],"type":"Point"}
}