{
  "type": "Feature",
  "properties": {
    "iso:country":"JP",
    "name:eng_x_preferred":[
        "Minamigojonishi 4 Chome"
    ],
    "name:eng_x_variant":[
        "Minamigojounishi 4 Choume",
        "Minamigojonishi 4 Chome"
    ],
    "name:jpn_x_preferred":[
        "\uff14\u4e01\u76ee"
    ],
    "name:jpn_x_variant":[
        "\u307f\u306a\u307f\u3054\u3058\u3087\u3046\u306b\u3057 \uff14\u3061\u3087\u3046\u3081",
        "\u5357\u4e94\u6761\u897f \uff14\u4e01\u76ee",
        "\uff14\u3061\u3087\u3046\u3081"
    ],
    "qs:gn_local":0,
    "qs:local_max":2554,
    "qs:local_sum":22076,
    "qs:localhoods":97,
    "qs:name":"\uff14\u4e01\u76ee",
    "qs:name_adm0":"\u65e5\u672c",
    "qs:name_adm1":"\u5317\u6d77\u9053",
    "qs:name_adm2":"\u4e2d\u592e\u533a",
    "qs:name_en":"Minamigojonishi 4 Chome",
    "qs:name_lau":"\u5357\u4e94\u6761\u897f",
    "qs:name_local":"\u672d\u5e4c\u5e02",
    "qs:photo_max":62,
    "qs:photo_sum":500,
    "qs:placetype":"Suburb",
    "qs:quad_count":24,
    "qs:woe_adm0":23424856,
    "qs:woe_adm1":7153351,
    "qs:woe_adm2":15015394,
    "qs:woe_lau":28379455,
    "qs:woe_local":1118108,
    "qs:woe_ver":"7.10.0",
    "wof:lang":[
        "jpn"
    ],
    "wof:name":"\uff14\u4e01\u76ee",
    "wof:placetype":"neighbourhood"
},
  "geometry": {"coordinates":[141.35264699999999,43.053673],"type":"Point"}
}