{
  "type": "Feature",
  "properties": {
    "iso:country":"JP",
    "name:eng_x_preferred":[
        "Saijodoyomaru 1 Chome"
    ],
    "name:eng_x_variant":[
        "Saijoudoyomaru 1 Choume",
        "Saijodoyomaru 1 Chome"
    ],
    "name:jpn_x_preferred":[
        "\uff11\u4e01\u76ee"
    ],
    "name:jpn_x_variant":[
        "\u3055\u3044\u3058\u3087\u3046\u3069\u3088\u307e\u308b \uff11\u3061\u3087\u3046\u3081",
        "\u897f\u6761\u571f\u4e0e\u4e38 \uff11\u4e01\u76ee",
        "\uff11\u3061\u3087\u3046\u3081"
    ],
    "qs:gn_local":0,
    "qs:local_max":56,
    "qs:local_sum":98,
    "qs:localhoods":3,
    "qs:name":"\uff11\u4e01\u76ee",
    "qs:name_adm0":"\u65e5\u672c",
    "qs:name_adm1":"\u5e83\u5cf6\u770c",
    "qs:name_en":"Saijodoyomaru 1 Chome",
    "qs:name_lau":"\u897f\u6761\u571f\u4e0e\u4e38",
    "qs:name_local":"\u6771\u5e83\u5cf6\u5e02",
    "qs:photo_max":25,
    "qs:photo_sum":28,
    "qs:placetype":"Suburb",
    "qs:quad_count":3,
    "qs:woe_adm0":23424856,
    "qs:woe_adm1":2345861,
    "qs:woe_adm2":0,
    "qs:woe_lau":28475248,
    "qs:woe_local":15015442,
    "qs:woe_ver":"7.10.0",
    "wof:lang":[
        "jpn"
    ],
    "wof:name":"\uff11\u4e01\u76ee",
    "wof:placetype":"neighbourhood"
},
  "geometry": {"coordinates":[132.745643,34.431508],"type":"Point"}
}