{
  "type": "Feature",
  "properties": {
    "gn:admin1_code":"4.0",
    "gn:admin2_code":"2111211.0",
    "gn:asciiname":"Sannan",
    "gn:country_code":"JP",
    "gn:dem":3,
    "gn:feature_class":"P",
    "gn:feature_code":"PPLL",
    "gn:name":"Sannan",
    "gn:population":0,
    "gn:timezone":"Asia/Tokyo",
    "iso:country":"JP",
    "name:jpn_x_preferred":[
        "\u4e09\u5357"
    ],
    "name:jpn_x_variant":[
        "\u3055\u3093\u306a\u3093",
        "\u30b5\u30f3\u30ca\u30f3"
    ],
    "wof:name":"Sannan",
    "wof:placetype":"locality"
},
  "geometry": {"coordinates":[140.41879,35.48520999999999],"type":"Point"}
}