{
  "type": "Feature",
  "properties": {
    "iso:country":"JP",
    "name:eng_x_preferred":[
        "Gotsu"
    ],
    "name:eng_x_variant":[
        "Gotsu City"
    ],
    "name:jpn_x_preferred":[
        "\u6c5f\u6d25\u5e02"
    ],
    "qs:name":"\u6c5f\u6d25\u5e02",
    "qs:name_adm0":"\u65e5\u672c",
    "qs:name_adm1":"\u5cf6\u6839\u770c",
    "qs:photos":502,
    "qs:photos_1k":102,
    "qs:photos_9k":2,
    "qs:photos_9r":5,
    "qs:photos_all":502,
    "qs:photos_sr":7,
    "qs:placetype":"Town",
    "qs:pop_sr":"0",
    "wof:name":"Gotsu",
    "wof:placetype":"locality"
},
  "geometry": {"coordinates":[132.14636899999999,34.955108],"type":"Point"}
}