{
  "type": "Feature",
  "properties": {
    "gn:admin1_code":"27",
    "gn:admin2_code":"1852895.0",
    "gn:asciiname":"Sakihario",
    "gn:country_code":"JP",
    "gn:dem":10,
    "gn:feature_class":"P",
    "gn:feature_code":"PPLL",
    "gn:name":"Sakihario",
    "gn:population":0,
    "gn:timezone":"Asia/Tokyo",
    "iso:country":"JP",
    "name:jpn_x_preferred":[
        "\u5d0e\u91dd\u5c3e"
    ],
    "name:und_x_variant":[
        "Hario",
        "Sakihario"
    ],
    "wof:name":"Sakihario",
    "wof:placetype":"locality"
},
  "geometry": {"coordinates":[129.76401000000001,33.05305],"type":"Point"}
}