{
  "type": "Feature",
  "properties": {
    "gn:admin1_code":"19",
    "gn:admin2_code":"1848308.0",
    "gn:asciiname":"Nagai",
    "gn:country_code":"JP",
    "gn:dem":1,
    "gn:feature_class":"P",
    "gn:feature_code":"PPL",
    "gn:name":"Nagai",
    "gn:population":0,
    "gn:timezone":"Asia/Tokyo",
    "iso:country":"JP",
    "name:jpn_x_preferred":[
        "\u9577\u4e95"
    ],
    "name:jpn_x_variant":[
        "\u306a\u304c\u3044",
        "\u30ca\u30ac\u30a4"
    ],
    "name:und_x_variant":[
        "Nagaich\u014d"
    ],
    "wof:name":"Nagai",
    "wof:placetype":"locality"
},
  "geometry": {"coordinates":[139.62273000000002,35.20323],"type":"Point"}
}