{
  "type": "Feature",
  "properties": {
    "gn:admin1_code":"27",
    "gn:asciiname":"Ichikira",
    "gn:country_code":"JP",
    "gn:dem":-9999,
    "gn:feature_class":"P",
    "gn:feature_code":"PPL",
    "gn:name":"Ichikira",
    "gn:population":0,
    "gn:timezone":"Asia/Tokyo",
    "iso:country":"JP",
    "wof:name":"Ichikira",
    "wof:placetype":"locality"
},
  "geometry": {"coordinates":[128.94999999999999,32.88333],"type":"Point"}
}