{
  "type": "Feature",
  "properties": {
    "gn:admin1_code":"32.0",
    "gn:admin2_code":"1851482.0",
    "gn:asciiname":"Suitocho",
    "gn:country_code":"JP",
    "gn:dem":7,
    "gn:feature_class":"P",
    "gn:feature_code":"PPL",
    "gn:name":"Suit\u014dch\u014d",
    "gn:population":0,
    "gn:timezone":"Asia/Tokyo",
    "iso:country":"JP",
    "name:jpn_x_preferred":[
        "\u5439\u6771\u753a"
    ],
    "name:und_x_variant":[
        "Suit\u014dch\u014d"
    ],
    "wof:name":"Suitocho",
    "wof:placetype":"locality"
},
  "geometry": {"coordinates":[135.53776999999999,34.76586],"type":"Point"}
}