{
  "type": "Feature",
  "properties": {
    "gn:admin1_code":"13.0",
    "gn:admin2_code":"7370811.0",
    "gn:asciiname":"Jiyugaoka-honmachi",
    "gn:country_code":"JP",
    "gn:dem":117,
    "gn:feature_class":"P",
    "gn:feature_code":"PPL",
    "gn:name":"Jiy\u016bgaoka-honmachi",
    "gn:population":0,
    "gn:timezone":"Asia/Tokyo",
    "iso:country":"JP",
    "name:jpn_x_preferred":[
        "\u81ea\u7531\u304c\u4e18\u672c\u753a"
    ],
    "name:und_x_variant":[
        "Jiy\u016bgaoka-honmachi"
    ],
    "wof:name":"Jiyugaoka-honmachi",
    "wof:placetype":"locality"
},
  "geometry": {"coordinates":[135.00538,34.78943],"type":"Point"}
}