{
  "type": "Feature",
  "properties": {
    "gn:admin1_code":"28.0",
    "gn:admin2_code":"1863590.0",
    "gn:asciiname":"Minamiadacho",
    "gn:country_code":"JP",
    "gn:dem":136,
    "gn:feature_class":"P",
    "gn:feature_code":"PPL",
    "gn:name":"Minamiadach\u014d",
    "gn:population":0,
    "gn:timezone":"Asia/Tokyo",
    "iso:country":"JP",
    "name:jpn_x_preferred":[
        "\u5357\u963f\u7530\u753a"
    ],
    "name:und_x_variant":[
        "Minamiadach\u014d"
    ],
    "wof:name":"Minamiadacho",
    "wof:placetype":"locality"
},
  "geometry": {"coordinates":[135.75128000000001,34.37057],"type":"Point"}
}