{
  "type": "Feature",
  "properties": {
    "gn:admin1_code":"35.0",
    "gn:admin2_code":"1863686.0",
    "gn:admin3_code":"25383.0",
    "gn:asciiname":"Hasama",
    "gn:country_code":"JP",
    "gn:dem":187,
    "gn:feature_class":"P",
    "gn:feature_code":"PPL",
    "gn:name":"Hasama",
    "gn:population":0,
    "gn:timezone":"Asia/Tokyo",
    "iso:country":"JP",
    "name:jpn_x_preferred":[
        "\u8feb"
    ],
    "wof:name":"Hasama",
    "wof:placetype":"locality"
},
  "geometry": {"coordinates":[136.22215,34.98496],"type":"Point"}
}