{
  "type": "Feature",
  "properties": {
    "iso:country":"JP",
    "qs:name":"\u6642\u6d25\u753a",
    "qs:name_adm0":"\u65e5\u672c",
    "qs:name_adm1":"\u9577\u5d0e\u770c",
    "qs:photos":360,
    "qs:photos_1k":73,
    "qs:photos_9k":2,
    "qs:photos_9r":5,
    "qs:photos_all":360,
    "qs:photos_sr":6,
    "qs:placetype":"Town",
    "qs:pop_sr":"0",
    "wof:name":"\u6642\u6d25\u753a",
    "wof:placetype":"locality"
},
  "geometry": {"coordinates":[129.84209000000001,32.8224075],"type":"Point"}
}