{
  "type": "Feature",
  "properties": {
    "iso:country":"JP",
    "name:eng_x_preferred":[
        "Togitsu"
    ],
    "name:eng_x_variant":[
        "Togitsu Town"
    ],
    "name:jpn_x_preferred":[
        "\u6642\u6d25\u753a"
    ],
    "qs:name":"\u6642\u6d25\u753a",
    "qs:name_adm0":"\u65e5\u672c",
    "qs:name_adm1":"\u9577\u5d0e\u770c",
    "qs:photos":360,
    "qs:photos_1k":73,
    "qs:photos_9k":2,
    "qs:photos_9r":5,
    "qs:photos_all":360,
    "qs:photos_sr":6,
    "qs:placetype":"Town",
    "qs:pop_sr":"0",
    "wof:name":"Togitsu",
    "wof:placetype":"locality"
},
  "geometry": {"coordinates":[129.84209000000001,32.822407],"type":"Point"}
}