{
  "type": "Feature",
  "properties": {
    "gn:admin1_code":"19.0",
    "gn:admin2_code":"1854744.0",
    "gn:asciiname":"Nakacho",
    "gn:country_code":"JP",
    "gn:dem":10,
    "gn:feature_class":"P",
    "gn:feature_code":"PPL",
    "gn:name":"Nakach\u014d",
    "gn:population":0,
    "gn:timezone":"Asia/Tokyo",
    "iso:country":"JP",
    "name:jpn_x_preferred":[
        "\u4e2d\u753a"
    ],
    "name:und_x_variant":[
        "Nakach\u014d"
    ],
    "wof:name":"Nakacho",
    "wof:placetype":"locality"
},
  "geometry": {"coordinates":[139.16395,35.25862],"type":"Point"}
}