{
  "type": "Feature",
  "properties": {
    "gn:admin1_code":"24.0",
    "gn:admin2_code":"7446990.0",
    "gn:asciiname":"Donoyama",
    "gn:country_code":"JP",
    "gn:dem":12,
    "gn:feature_class":"P",
    "gn:feature_code":"PPL",
    "gn:name":"D\u014dnoyama",
    "gn:population":0,
    "gn:timezone":"Asia/Tokyo",
    "iso:country":"JP",
    "name:jpn_x_preferred":[
        "\u7b52\u306e\u5c71"
    ],
    "name:jpn_x_variant":[
        "\u3069\u3046\u306e\u3084\u307e",
        "\u30c9\u30a6\u30ce\u30e4\u30de"
    ],
    "name:und_x_variant":[
        "D\u014dnoyama",
        "T\u014dnoyama"
    ],
    "wof:name":"Donoyama",
    "wof:placetype":"locality"
},
  "geometry": {"coordinates":[141.11954,38.44263],"type":"Point"}
}