{
  "type": "Feature",
  "properties": {
    "iso:country":"JP",
    "name:eng_x_preferred":[
        "Shinmachi 1 Chome"
    ],
    "name:eng_x_variant":[
        "Shinmachi 1 Choume",
        "Shinmachi 1 Chome"
    ],
    "name:jpn_x_preferred":[
        "\uff11\u4e01\u76ee"
    ],
    "name:jpn_x_variant":[
        "\u3057\u3093\u307e\u3061 \uff11\u3061\u3087\u3046\u3081",
        "\u65b0\u753a \uff11\u4e01\u76ee",
        "\uff11\u3061\u3087\u3046\u3081"
    ],
    "qs:gn_local":0,
    "qs:local_max":5466,
    "qs:local_sum":82256,
    "qs:localhoods":141,
    "qs:name":"\uff11\u4e01\u76ee",
    "qs:name_adm0":"\u65e5\u672c",
    "qs:name_adm1":"\u5927\u962a\u5e9c",
    "qs:name_adm2":"\u897f\u533a",
    "qs:name_en":"Shinmachi 1 Chome",
    "qs:name_lau":"\u65b0\u753a",
    "qs:name_local":"\u5927\u962a\u5e02",
    "qs:photo_max":71,
    "qs:photo_sum":163,
    "qs:photos":10,
    "qs:photos_1k":2,
    "qs:photos_9k":1,
    "qs:photos_9r":1,
    "qs:photos_all":10,
    "qs:photos_sr":1,
    "qs:placetype":"Suburb",
    "qs:pop_sr":"0",
    "qs:quad_count":7,
    "qs:woe_adm0":23424856,
    "qs:woe_adm1":2345881,
    "qs:woe_adm2":15015526,
    "qs:woe_lau":28457163,
    "qs:woe_local":15015370,
    "qs:woe_ver":"7.10.0",
    "qs_pg:name":"\uff11\u4e01\u76ee",
    "qs_pg:name_adm0":"\u65e5\u672c",
    "qs_pg:name_adm1":"\u5927\u962a\u5e9c",
    "qs_pg:photos":131,
    "qs_pg:photos_1k":27,
    "qs_pg:photos_9k":1,
    "qs_pg:photos_9r":3,
    "qs_pg:photos_all":131,
    "qs_pg:photos_sr":3,
    "qs_pg:pop_sr":0,
    "qs_pg:qs_pg_placetype":"neighbourhood",
    "qs_pg:qs_pg_placetype_gp":"Suburb",
    "qs_pg:woe_adm0":23424856,
    "woe:adm0_id":23424856,
    "woe:name_adm0":"\u65e5\u672c",
    "woe:name_adm1":"\u5927\u962a\u5e9c",
    "woe:placetype":"Suburb",
    "wof:lang":[
        "jpn"
    ],
    "wof:name":"\uff11\u4e01\u76ee",
    "wof:placetype":"neighbourhood"
},
  "geometry": {"coordinates":[135.493764,34.677346],"type":"Point"}
}