{
  "type": "Feature",
  "properties": {
    "gn:admin1_code":"20",
    "gn:admin2_code":"7405899.0",
    "gn:asciiname":"Noichicho-nishisako",
    "gn:country_code":"JP",
    "gn:dem":42,
    "gn:feature_class":"P",
    "gn:feature_code":"PPL",
    "gn:name":"Noichich\u014d-nishisako",
    "gn:population":0,
    "gn:timezone":"Asia/Tokyo",
    "iso:country":"JP",
    "name:jpn_x_preferred":[
        "\u91ce\u5e02\u753a\u897f\u4f50\u53e4"
    ],
    "name:und_x_variant":[
        "Sako",
        "Nishi-sako",
        "Noichich\u014d-nishisako"
    ],
    "wof:name":"Noichicho-nishisako",
    "wof:placetype":"locality"
},
  "geometry": {"coordinates":[133.70065,33.58942],"type":"Point"}
}