{
  "type": "Feature",
  "properties": {
    "gn:admin1_code":"09",
    "gn:admin2_code":"1850890.0",
    "gn:asciiname":"Mio",
    "gn:country_code":"JP",
    "gn:dem":824,
    "gn:feature_class":"P",
    "gn:feature_code":"PPLL",
    "gn:name":"Mio",
    "gn:population":0,
    "gn:timezone":"Asia/Tokyo",
    "iso:country":"JP",
    "name:ceb_x_preferred":[
        "Mio"
    ],
    "name:deu_x_preferred":[
        "Mio"
    ],
    "name:fra_x_preferred":[
        "Mio"
    ],
    "name:jpn_x_preferred":[
        "\u4e09\u5c3e"
    ],
    "name:nld_x_preferred":[
        "Mio"
    ],
    "name:swe_x_preferred":[
        "Mio"
    ],
    "wof:name":"Mio",
    "wof:placetype":"locality"
},
  "geometry": {"coordinates":[137.13664,36.14998],"type":"Point"}
}