{
  "type": "Feature",
  "properties": {
    "gn:admin1_code":"11",
    "gn:admin2_code":"7372274.0",
    "gn:asciiname":"Yoshida",
    "gn:country_code":"JP",
    "gn:dem":204,
    "gn:feature_class":"P",
    "gn:feature_code":"PPL",
    "gn:name":"Yoshida",
    "gn:population":0,
    "gn:timezone":"Asia/Tokyo",
    "iso:country":"JP",
    "wof:name":"Yoshida",
    "wof:placetype":"locality"
},
  "geometry": {"coordinates":[132.69999999999999,34.66667],"type":"Point"}
}