{
  "type": "Feature",
  "properties": {
    "gn:admin1_code":"02",
    "gn:admin2_code":"1854681.0",
    "gn:asciiname":"Kakumazaki",
    "gn:cc2":"JP",
    "gn:country_code":"JP",
    "gn:dem":4,
    "gn:feature_class":"P",
    "gn:feature_code":"PPL",
    "gn:name":"Kakumazaki",
    "gn:population":0,
    "gn:timezone":"Asia/Tokyo",
    "iso:country":"JP",
    "name:jpn_x_preferred":[
        "\u89d2\u9593\u5d0e"
    ],
    "name:und_x_variant":[
        "Kakumasaki",
        "Kakumazaki"
    ],
    "wof:name":"Kakumazaki",
    "wof:placetype":"locality"
},
  "geometry": {"coordinates":[139.91666999999998,39.95],"type":"Point"}
}