{
  "type": "Feature",
  "properties": {
    "gn:admin1_code":"28.0",
    "gn:admin2_code":"1848164.0",
    "gn:admin3_code":"29449.0",
    "gn:asciiname":"Ikeana",
    "gn:country_code":"JP",
    "gn:dem":296,
    "gn:feature_class":"P",
    "gn:feature_code":"PPL",
    "gn:name":"Ikeana",
    "gn:population":0,
    "gn:timezone":"Asia/Tokyo",
    "iso:country":"JP",
    "name:jpn_x_preferred":[
        "\u6c60\u7a74"
    ],
    "wof:name":"Ikeana",
    "wof:placetype":"locality"
},
  "geometry": {"coordinates":[135.78121000000002,34.02216],"type":"Point"}
}