{
  "type": "Feature",
  "properties": {
    "gn:admin1_code":"21.0",
    "gn:admin2_code":"1848441.0",
    "gn:asciiname":"Yonagu",
    "gn:country_code":"JP",
    "gn:dem":67,
    "gn:feature_class":"P",
    "gn:feature_code":"PPLL",
    "gn:name":"Yonagu",
    "gn:population":0,
    "gn:timezone":"Asia/Tokyo",
    "iso:country":"JP",
    "name:jpn_x_preferred":[
        "\u4e0e\u5948\u4e45"
    ],
    "wof:name":"Yonagu",
    "wof:placetype":"locality"
},
  "geometry": {"coordinates":[130.64695,32.40603],"type":"Point"}
}