{
  "type": "Feature",
  "properties": {
    "gn:admin1_code":"34.0",
    "gn:admin2_code":"8304213.0",
    "gn:asciiname":"Kamurouchi",
    "gn:country_code":"JP",
    "gn:dem":6,
    "gn:feature_class":"P",
    "gn:feature_code":"PPLL",
    "gn:name":"Kamurouchi",
    "gn:population":0,
    "gn:timezone":"Asia/Tokyo",
    "iso:country":"JP",
    "name:jpn_x_preferred":[
        "\u79bf\u5730"
    ],
    "name:jpn_x_variant":[
        "\u304b\u3080\u308d\u3046\u3061"
    ],
    "wof:name":"Kamurouchi",
    "wof:placetype":"locality"
},
  "geometry": {"coordinates":[139.79809,35.9866],"type":"Point"}
}