{
  "type": "Feature",
  "properties": {
    "gn:admin1_code":"21",
    "gn:admin2_code":"1865358.0",
    "gn:asciiname":"Ariakemachi-koshimago",
    "gn:country_code":"JP",
    "gn:dem":64,
    "gn:feature_class":"P",
    "gn:feature_code":"PPL",
    "gn:name":"Ariakemachi-koshimago",
    "gn:population":0,
    "gn:timezone":"Asia/Tokyo",
    "iso:country":"JP",
    "name:jpn_x_preferred":[
        "\u6709\u660e\u753a\u5c0f\u5cf6\u5b50"
    ],
    "name:jpn_x_variant":[
        "\u3042\u308a\u3042\u3051\u307e\u3061\u3053\u3057\u307e\u3054",
        "\u30a2\u30ea\u30a2\u30b1\u30de\u30c1\u30b3\u30b7\u30de\u30b4"
    ],
    "name:und_x_variant":[
        "Ko-shimako",
        "Ko-shimago",
        "Ariakemachi-koshimago"
    ],
    "wof:name":"Ariakemachi-koshimago",
    "wof:placetype":"locality"
},
  "geometry": {"coordinates":[130.27902,32.47863],"type":"Point"}
}