{
  "type": "Feature",
  "properties": {
    "iso:country":"JP",
    "name:eng_x_preferred":[
        "Tenpakuchooazashimada Azayamanoiri"
    ],
    "name:eng_x_variant":[
        "Tenpakuchouooazashimada Tenpakuchooazashimada Azayamanoiri",
        "Tenpakuchooazashimada Azayamanoiri"
    ],
    "name:jpn_x_preferred":[
        "\u5b57\u5c71\u30ce\u6741"
    ],
    "name:jpn_x_variant":[
        "\u3042\u3056\u3084\u307e\u306e\u3044\u308a",
        "\u3066\u3093\u3071\u304f\u3061\u3087\u3046\u304a\u304a\u3042\u3056\u3057\u307e\u3060 \u3042\u3056\u3084\u307e\u306e\u3044\u308a",
        "\u5929\u767d\u753a\u5927\u5b57\u5cf6\u7530 \u5b57\u5c71\u30ce\u6741"
    ],
    "qs:gn_local":0,
    "qs:local_max":3194,
    "qs:local_sum":30209,
    "qs:localhoods":92,
    "qs:name":"\u5b57\u5c71\u30ce\u6741",
    "qs:name_adm0":"\u65e5\u672c",
    "qs:name_adm1":"\u611b\u77e5\u770c",
    "qs:name_adm2":"\u5929\u767d\u533a",
    "qs:name_en":"Tenpakuchooazashimada Azayamanoiri",
    "qs:name_lau":"\u5929\u767d\u753a\u5927\u5b57\u5cf6\u7530",
    "qs:name_local":"\u540d\u53e4\u5c4b\u5e02",
    "qs:photo_max":18,
    "qs:photo_sum":18,
    "qs:placetype":"Suburb",
    "qs:quad_count":1,
    "qs:woe_adm0":23424856,
    "qs:woe_adm1":2345851,
    "qs:woe_adm2":1115595,
    "qs:woe_lau":28440341,
    "qs:woe_local":1117817,
    "qs:woe_ver":"7.10.0",
    "wof:lang":[
        "jpn"
    ],
    "wof:name":"\u5b57\u5c71\u30ce\u6741",
    "wof:placetype":"neighbourhood"
},
  "geometry": {"coordinates":[136.99127200000001,35.117661],"type":"Point"}
}