{
  "type": "Feature",
  "properties": {
    "gn:admin1_code":"26",
    "gn:admin2_code":"7417078.0",
    "gn:asciiname":"Chikaraishi",
    "gn:country_code":"JP",
    "gn:dem":389,
    "gn:feature_class":"P",
    "gn:feature_code":"PPL",
    "gn:name":"Chikaraishi",
    "gn:population":0,
    "gn:timezone":"Asia/Tokyo",
    "iso:country":"JP",
    "name:jpn_x_preferred":[
        "\u529b\u77f3"
    ],
    "wof:name":"Chikaraishi",
    "wof:placetype":"locality"
},
  "geometry": {"coordinates":[138.16068000000001,36.46232],"type":"Point"}
}