{
  "type": "Feature",
  "properties": {
    "gn:admin1_code":"18",
    "gn:admin2_code":"1855201.0",
    "gn:asciiname":"Azako",
    "gn:country_code":"JP",
    "gn:dem":35,
    "gn:feature_class":"P",
    "gn:feature_code":"PPLL",
    "gn:name":"Azak\u014d",
    "gn:population":0,
    "gn:timezone":"Asia/Tokyo",
    "iso:country":"JP",
    "name:jpn_x_preferred":[
        "\u6d45\u5ddd"
    ],
    "name:und_x_variant":[
        "Asakawa",
        "Azaka",
        "Azak\u014d"
    ],
    "wof:name":"Azako",
    "wof:placetype":"locality"
},
  "geometry": {"coordinates":[131.06101999999998,30.68503],"type":"Point"}
}