{
  "type": "Feature",
  "properties": {
    "iso:country":"JP",
    "qs:name":"\u67cf\u5d0e\u5e02",
    "qs:name_adm0":"\u65e5\u672c",
    "qs:name_adm1":"\u65b0\u6f5f\u770c",
    "qs:photos":581,
    "qs:photos_1k":118,
    "qs:photos_9k":7,
    "qs:photos_9r":8,
    "qs:photos_all":1503,
    "qs:photos_sr":8,
    "qs:placetype":"Town",
    "qs:pop_sr":"0",
    "wof:name":"\u67cf\u5d0e\u5e02",
    "wof:placetype":"locality"
},
  "geometry": {"coordinates":[138.627486,37.224587],"type":"Point"}
}