{
  "type": "Feature",
  "properties": {
    "gn:admin1_code":"16.0",
    "gn:admin2_code":"2128940.0",
    "gn:asciiname":"Ishibashi",
    "gn:country_code":"JP",
    "gn:dem":267,
    "gn:feature_class":"P",
    "gn:feature_code":"PPL",
    "gn:name":"Ishibashi",
    "gn:population":0,
    "gn:timezone":"Asia/Tokyo",
    "iso:country":"JP",
    "name:jpn_x_preferred":[
        "\u77f3\u6a4b"
    ],
    "name:jpn_x_variant":[
        "\u3044\u3057\u3070\u3057",
        "\u30a4\u30b7\u30d0\u30b7"
    ],
    "wof:name":"Ishibashi",
    "wof:placetype":"locality"
},
  "geometry": {"coordinates":[141.12835999999999,40.17105],"type":"Point"}
}