{
  "type": "Feature",
  "properties": {
    "gn:admin1_code":"21.0",
    "gn:admin2_code":"1857206.0",
    "gn:asciiname":"Daikokucho",
    "gn:country_code":"JP",
    "gn:dem":5,
    "gn:feature_class":"P",
    "gn:feature_code":"PPL",
    "gn:name":"Daikokuch\u014d",
    "gn:population":0,
    "gn:timezone":"Asia/Tokyo",
    "iso:country":"JP",
    "name:jpn_x_preferred":[
        "\u5927\u9ed2\u753a"
    ],
    "name:jpn_x_variant":[
        "\u3060\u3044\u3053\u304f\u3061\u3087\u3046",
        "\u30c0\u30a4\u30b3\u30af\u30c1\u30e7\u30a6"
    ],
    "name:und_x_variant":[
        "Daikokuch\u014d"
    ],
    "wof:name":"Daikokucho",
    "wof:placetype":"locality"
},
  "geometry": {"coordinates":[130.40016,32.20864],"type":"Point"}
}