{
  "type": "Feature",
  "properties": {
    "gn:admin1_code":"3.0",
    "gn:admin2_code":"2128134.0",
    "gn:admin3_code":"2423.0",
    "gn:asciiname":"Oinocho",
    "gn:country_code":"JP",
    "gn:dem":11,
    "gn:feature_class":"P",
    "gn:feature_code":"PPL",
    "gn:name":"Oinoch\u014d",
    "gn:population":0,
    "gn:timezone":"Asia/Tokyo",
    "iso:country":"JP",
    "name:jpn_x_preferred":[
        "\u72fc\u4e01"
    ],
    "name:jpn_x_variant":[
        "\u304a\u3044\u306e\u3061\u3087\u3046",
        "\u30aa\u30a4\u30ce\u30c1\u30e7\u30a6"
    ],
    "name:und_x_variant":[
        "Oinoch\u014d"
    ],
    "wof:name":"Oinocho",
    "wof:placetype":"locality"
},
  "geometry": {"coordinates":[140.91207,41.52682],"type":"Point"}
}