{
  "type": "Feature",
  "properties": {
    "gn:admin1_code":"12.0",
    "gn:admin2_code":"7428095.0",
    "gn:admin3_code":"1563.0",
    "gn:asciiname":"Otoineppu",
    "gn:country_code":"JP",
    "gn:dem":52,
    "gn:feature_class":"P",
    "gn:feature_code":"PPL",
    "gn:name":"Otoineppu",
    "gn:population":0,
    "gn:timezone":"Asia/Tokyo",
    "iso:country":"JP",
    "name:jpn_x_preferred":[
        "\u97f3\u7a32\u5e9c"
    ],
    "name:jpn_x_variant":[
        "\u304a\u3068\u3044\u306d\u3063\u3077",
        "\u30aa\u30c8\u30a4\u30cd\u30c3\u30d7"
    ],
    "wof:name":"Otoineppu",
    "wof:placetype":"locality"
},
  "geometry": {"coordinates":[142.89036000000004,44.61151],"type":"Point"}
}