{
  "type": "Feature",
  "properties": {
    "gn:admin1_code":"34.0",
    "gn:admin2_code":"1864112.0",
    "gn:asciiname":"Midorino-nishi",
    "gn:country_code":"JP",
    "gn:dem":8,
    "gn:feature_class":"P",
    "gn:feature_code":"PPL",
    "gn:name":"Midorino-nishi",
    "gn:population":0,
    "gn:timezone":"Asia/Tokyo",
    "iso:country":"JP",
    "name:jpn_x_preferred":[
        "\u307f\u3069\u308a\u91ce\u897f"
    ],
    "wof:name":"Midorino-nishi",
    "wof:placetype":"locality"
},
  "geometry": {"coordinates":[139.55556999999999,35.86831],"type":"Point"}
}