{
  "type": "Feature",
  "properties": {
    "gn:admin1_code":"4.0",
    "gn:admin2_code":"7465524.0",
    "gn:asciiname":"Fukahori",
    "gn:country_code":"JP",
    "gn:dem":1,
    "gn:feature_class":"P",
    "gn:feature_code":"PPL",
    "gn:name":"Fukahori",
    "gn:population":0,
    "gn:timezone":"Asia/Tokyo",
    "iso:country":"JP",
    "name:jpn_x_preferred":[
        "\u6df1\u5800"
    ],
    "name:jpn_x_variant":[
        "\u3075\u304b\u307b\u308a",
        "\u30d5\u30ab\u30db\u30ea"
    ],
    "wof:name":"Fukahori",
    "wof:placetype":"locality"
},
  "geometry": {"coordinates":[140.39266000000001,35.25787000000001],"type":"Point"}
}