{
  "type": "Feature",
  "properties": {
    "gn:admin1_code":"32",
    "gn:admin2_code":"7391698.0",
    "gn:asciiname":"Sanodai",
    "gn:country_code":"JP",
    "gn:dem":21,
    "gn:feature_class":"P",
    "gn:feature_code":"PPL",
    "gn:name":"Sanodai",
    "gn:population":0,
    "gn:timezone":"Asia/Tokyo",
    "iso:country":"JP",
    "name:jpn_x_preferred":[
        "\u4f50\u91ce\u53f0"
    ],
    "name:und_x_variant":[
        "Sano"
    ],
    "wof:name":"Sanodai",
    "wof:placetype":"locality"
},
  "geometry": {"coordinates":[135.34276,34.41146],"type":"Point"}
}