{
  "type": "Feature",
  "properties": {
    "gn:admin1_code":"21.0",
    "gn:admin2_code":"1864973.0",
    "gn:asciiname":"Mikubo",
    "gn:country_code":"JP",
    "gn:dem":488,
    "gn:feature_class":"P",
    "gn:feature_code":"PPL",
    "gn:name":"Mikubo",
    "gn:population":0,
    "gn:timezone":"Asia/Tokyo",
    "iso:country":"JP",
    "name:jpn_x_preferred":[
        "\u4e09\u4e45\u4fdd"
    ],
    "name:jpn_x_variant":[
        "\u307f\u304f\u307c",
        "\u30df\u30af\u30dc"
    ],
    "wof:name":"Mikubo",
    "wof:placetype":"locality"
},
  "geometry": {"coordinates":[131.03208999999998,32.96311],"type":"Point"}
}