{
  "type": "Feature",
  "properties": {
    "gn:admin1_code":"12.0",
    "gn:admin2_code":"2130058.0",
    "gn:admin3_code":"1642.0",
    "gn:asciiname":"Nishiyonjo",
    "gn:country_code":"JP",
    "gn:dem":38,
    "gn:feature_class":"P",
    "gn:feature_code":"PPL",
    "gn:name":"Nishiyonj\u014d",
    "gn:population":0,
    "gn:timezone":"Asia/Tokyo",
    "iso:country":"JP",
    "name:jpn_x_preferred":[
        "\u897f\u56db\u6761"
    ],
    "name:jpn_x_variant":[
        "\u306b\u3057\u3088\u3093\u3058\u3087\u3046",
        "\u30cb\u30b7\u30e8\u30f3\u30b8\u30e7\u30a6"
    ],
    "name:und_x_variant":[
        "Nishiyonj\u014d"
    ],
    "wof:name":"Nishiyonjo",
    "wof:placetype":"locality"
},
  "geometry": {"coordinates":[143.31059999999999,42.28653],"type":"Point"}
}