{
  "type": "Feature",
  "properties": {
    "gn:admin1_code":"19.0",
    "gn:admin2_code":"1861448.0",
    "gn:asciiname":"Araya",
    "gn:country_code":"JP",
    "gn:dem":14,
    "gn:feature_class":"P",
    "gn:feature_code":"PPLL",
    "gn:name":"Araya",
    "gn:population":0,
    "gn:timezone":"Asia/Tokyo",
    "iso:country":"JP",
    "name:jpn_x_preferred":[
        "\u65b0\u5c4b"
    ],
    "wof:name":"Araya",
    "wof:placetype":"locality"
},
  "geometry": {"coordinates":[139.35356999999999,35.39092],"type":"Point"}
}