{
  "type": "Feature",
  "properties": {
    "iso:country":"JP",
    "qs:name":"\uff12\u4e01\u76ee",
    "qs:name_adm0":"\u65e5\u672c",
    "qs:name_adm1":"\u77f3\u5ddd\u770c",
    "qs:photos":198,
    "qs:photos_1k":40,
    "qs:photos_9k":1,
    "qs:photos_9r":4,
    "qs:photos_all":198,
    "qs:photos_sr":4,
    "qs:placetype":"Suburb",
    "qs:pop_sr":"0",
    "wof:name":"\uff12\u4e01\u76ee",
    "wof:placetype":"neighbourhood"
},
  "geometry": {"coordinates":[136.65163899999999,36.563666],"type":"Point"}
}