{
  "type": "Feature",
  "properties": {
    "gn:admin1_code":"16.0",
    "gn:admin2_code":"7441817.0",
    "gn:asciiname":"Gabata",
    "gn:country_code":"JP",
    "gn:dem":32,
    "gn:feature_class":"P",
    "gn:feature_code":"PPL",
    "gn:name":"Gabata",
    "gn:population":0,
    "gn:timezone":"Asia/Tokyo",
    "iso:country":"JP",
    "name:jpn_x_preferred":[
        "\u84b2\u7530"
    ],
    "name:jpn_x_variant":[
        "\u304c\u3070\u305f",
        "\u30ac\u30d0\u30bf"
    ],
    "wof:name":"Gabata",
    "wof:placetype":"locality"
},
  "geometry": {"coordinates":[141.71339,38.95857],"type":"Point"}
}