{
  "type": "Feature",
  "properties": {
    "gn:admin1_code":"37.0",
    "gn:admin2_code":"1852349.0",
    "gn:asciiname":"Shikine",
    "gn:country_code":"JP",
    "gn:dem":34,
    "gn:feature_class":"P",
    "gn:feature_code":"PPL",
    "gn:name":"Shikine",
    "gn:population":0,
    "gn:timezone":"Asia/Tokyo",
    "iso:country":"JP",
    "name:jpn_x_preferred":[
        "\u6577\u6839"
    ],
    "wof:name":"Shikine",
    "wof:placetype":"locality"
},
  "geometry": {"coordinates":[138.93733999999998,34.68059],"type":"Point"}
}