{
  "type": "Feature",
  "properties": {
    "gn:admin1_code":"21.0",
    "gn:admin2_code":"7412708.0",
    "gn:admin3_code":"43501.0",
    "gn:asciiname":"Mutanoharu",
    "gn:country_code":"JP",
    "gn:dem":136,
    "gn:feature_class":"P",
    "gn:feature_code":"PPLL",
    "gn:name":"Mutanoharu",
    "gn:population":0,
    "gn:timezone":"Asia/Tokyo",
    "iso:country":"JP",
    "name:jpn_x_preferred":[
        "\u7121\u7530\u539f"
    ],
    "name:jpn_x_variant":[
        "\u3080\u305f\u306e\u306f\u308b",
        "\u30e0\u30bf\u30ce\u30cf\u30eb"
    ],
    "wof:name":"Mutanoharu",
    "wof:placetype":"locality"
},
  "geometry": {"coordinates":[130.78639999999999,32.19741],"type":"Point"}
}