{
  "type": "Feature",
  "properties": {
    "gn:admin1_code":"21.0",
    "gn:admin2_code":"7412706.0",
    "gn:admin3_code":"43447.0",
    "gn:asciiname":"Shindo",
    "gn:country_code":"JP",
    "gn:dem":442,
    "gn:feature_class":"P",
    "gn:feature_code":"PPLL",
    "gn:name":"Shind\u014d",
    "gn:population":0,
    "gn:timezone":"Asia/Tokyo",
    "iso:country":"JP",
    "name:jpn_x_preferred":[
        "\u65b0\u85e4"
    ],
    "name:jpn_x_variant":[
        "\u3057\u3093\u3069\u3046",
        "\u30b7\u30f3\u30c9\u30a6"
    ],
    "name:und_x_variant":[
        "Shind\u014d"
    ],
    "wof:name":"Shindo",
    "wof:placetype":"locality"
},
  "geometry": {"coordinates":[130.99621000000002,32.66158],"type":"Point"}
}