{
  "type": "Feature",
  "properties": {
    "gn:admin1_code":"22.0",
    "gn:admin2_code":"1856196.0",
    "gn:asciiname":"Inouchi",
    "gn:country_code":"JP",
    "gn:dem":43,
    "gn:feature_class":"P",
    "gn:feature_code":"PPL",
    "gn:name":"Inouchi",
    "gn:population":0,
    "gn:timezone":"Asia/Tokyo",
    "iso:country":"JP",
    "name:jpn_x_preferred":[
        "\u4e95\u30ce\u5185"
    ],
    "wof:name":"Inouchi",
    "wof:placetype":"locality"
},
  "geometry": {"coordinates":[135.68736999999999,34.94351],"type":"Point"}
}