{
  "type": "Feature",
  "properties": {
    "gn:admin1_code":"21.0",
    "gn:admin2_code":"7412706.0",
    "gn:admin3_code":"43443.0",
    "gn:asciiname":"Kushijima",
    "gn:country_code":"JP",
    "gn:dem":8,
    "gn:feature_class":"P",
    "gn:feature_code":"PPLL",
    "gn:name":"Kushijima",
    "gn:population":0,
    "gn:timezone":"Asia/Tokyo",
    "iso:country":"JP",
    "name:jpn_x_preferred":[
        "\u6adb\u5cf6"
    ],
    "name:jpn_x_variant":[
        "\u304f\u3057\u3058\u307e",
        "\u30af\u30b7\u30b8\u30de"
    ],
    "wof:name":"Kushijima",
    "wof:placetype":"locality"
},
  "geometry": {"coordinates":[130.78595000000001,32.75715],"type":"Point"}
}