{
  "type": "Feature",
  "properties": {
    "gn:admin1_code":"47",
    "gn:admin2_code":"1852456.0",
    "gn:admin3_code":"47362.0",
    "gn:asciiname":"Tomori",
    "gn:country_code":"JP",
    "gn:dem":65,
    "gn:feature_class":"P",
    "gn:feature_code":"PPL",
    "gn:name":"Tomori",
    "gn:population":0,
    "gn:timezone":"Asia/Tokyo",
    "iso:country":"JP",
    "name:jpn_x_preferred":[
        "\u5bcc\u76db"
    ],
    "name:und_x_variant":[
        "Domui",
        "Tomui",
        "Tumui",
        "Tomoi",
        "Tomori"
    ],
    "wof:name":"Tomori",
    "wof:placetype":"locality"
},
  "geometry": {"coordinates":[127.72875999999999,26.13384],"type":"Point"}
}