{
  "type": "Feature",
  "properties": {
    "gn:admin1_code":"29.0",
    "gn:admin2_code":"1859907.0",
    "gn:asciiname":"Yamaguchi",
    "gn:country_code":"JP",
    "gn:dem":47,
    "gn:feature_class":"P",
    "gn:feature_code":"PPL",
    "gn:name":"Yamaguchi",
    "gn:population":0,
    "gn:timezone":"Asia/Tokyo",
    "iso:country":"JP",
    "name:cat_x_preferred":[
        "Yamaguchi"
    ],
    "name:ceb_x_preferred":[
        "Yamaguchi"
    ],
    "name:deu_x_preferred":[
        "Yamaguchi"
    ],
    "name:fas_x_preferred":[
        "\u06cc\u0627\u0645\u0627\u06af\u0648\u0686\u06cc"
    ],
    "name:fin_x_preferred":[
        "Yamaguchi"
    ],
    "name:fra_x_preferred":[
        "Yamaguchi"
    ],
    "name:ita_x_preferred":[
        "Yamaguchi"
    ],
    "name:jpn_x_preferred":[
        "\u5c71\u53e3"
    ],
    "name:kat_x_preferred":[
        "\u10d8\u10d0\u10db\u10d0\u10d2\u10e3\u10e2\u10d8"
    ],
    "name:kor_x_preferred":[
        "\uc57c\ub9c8\uad6c\uce58"
    ],
    "name:mlg_x_preferred":[
        "Yamaguchi"
    ],
    "name:nld_x_preferred":[
        "Yamaguchi"
    ],
    "name:nor_x_preferred":[
        "Yamaguchi"
    ],
    "name:por_x_preferred":[
        "Yamaguchi"
    ],
    "name:ron_x_preferred":[
        "Yamaguchi"
    ],
    "name:rus_x_preferred":[
        "\u042f\u043c\u0430\u0433\u0443\u0442\u0438"
    ],
    "name:slk_x_preferred":[
        "Jamagu\u010di"
    ],
    "name:spa_x_preferred":[
        "Yamaguchi"
    ],
    "name:swa_x_preferred":[
        "Yamaguchi"
    ],
    "name:swe_x_preferred":[
        "Yamaguchi"
    ],
    "name:tha_x_preferred":[
        "\u0e22\u0e32\u0e21\u0e32\u0e07\u0e39\u0e08\u0e34"
    ],
    "name:ukr_x_preferred":[
        "\u042f\u043c\u0430\u0491\u0443\u0442\u0456"
    ],
    "wof:name":"Yamaguchi",
    "wof:placetype":"locality"
},
  "geometry": {"coordinates":[138.56486999999998,37.29674],"type":"Point"}
}