{
  "type": "Feature",
  "properties": {
    "gn:admin1_code":"29.0",
    "gn:admin2_code":"1859907.0",
    "gn:asciiname":"Yamaguchi",
    "gn:country_code":"JP",
    "gn:dem":47,
    "gn:feature_class":"P",
    "gn:feature_code":"PPL",
    "gn:name":"Yamaguchi",
    "gn:population":0,
    "gn:timezone":"Asia/Tokyo",
    "iso:country":"JP",
    "name:jpn_x_preferred":[
        "\u5c71\u53e3"
    ],
    "wof:name":"Yamaguchi",
    "wof:placetype":"locality"
},
  "geometry": {"coordinates":[138.56486999999998,37.29674],"type":"Point"}
}