{
  "type": "Feature",
  "properties": {
    "gn:admin1_code":"25",
    "gn:admin2_code":"7413964.0",
    "gn:admin3_code":"45382.0",
    "gn:asciiname":"Yamashita",
    "gn:country_code":"JP",
    "gn:dem":62,
    "gn:feature_class":"P",
    "gn:feature_code":"PPL",
    "gn:name":"Yamashita",
    "gn:population":0,
    "gn:timezone":"Asia/Tokyo",
    "iso:country":"JP",
    "name:nor_x_preferred":[
        "Yamashita"
    ],
    "wof:name":"Yamashita",
    "wof:placetype":"locality"
},
  "geometry": {"coordinates":[131.31666999999999,32.03333],"type":"Point"}
}