{
  "type": "Feature",
  "properties": {
    "gn:admin1_code":"04",
    "gn:admin2_code":"1850520.0",
    "gn:asciiname":"Mera",
    "gn:country_code":"JP",
    "gn:dem":83,
    "gn:feature_class":"P",
    "gn:feature_code":"PPL",
    "gn:name":"Mera",
    "gn:population":0,
    "gn:timezone":"Asia/Tokyo",
    "iso:country":"JP",
    "name:und_x_variant":[
        "Fura",
        "Fuzaki",
        "Mera"
    ],
    "wof:name":"Mera",
    "wof:placetype":"locality"
},
  "geometry": {"coordinates":[139.83056999999999,34.91797],"type":"Point"}
}