{
  "type": "Feature",
  "properties": {
    "gn:admin1_code":"04",
    "gn:admin2_code":"1850520.0",
    "gn:asciiname":"Mera",
    "gn:country_code":"JP",
    "gn:dem":83,
    "gn:feature_class":"P",
    "gn:feature_code":"PPL",
    "gn:name":"Mera",
    "gn:population":0,
    "gn:timezone":"Asia/Tokyo",
    "iso:country":"JP",
    "name:bel_x_preferred":[
        "\u041c\u0435\u0440\u0430"
    ],
    "name:bre_x_preferred":[
        "Mera"
    ],
    "name:cat_x_preferred":[
        "Mera"
    ],
    "name:ceb_x_preferred":[
        "Mera"
    ],
    "name:ces_x_preferred":[
        "Mera"
    ],
    "name:deu_x_preferred":[
        "Mera"
    ],
    "name:fra_x_preferred":[
        "Mera"
    ],
    "name:glg_x_preferred":[
        "Mera"
    ],
    "name:hun_x_preferred":[
        "Mera"
    ],
    "name:ita_x_preferred":[
        "Mera"
    ],
    "name:nld_x_preferred":[
        "Mera"
    ],
    "name:pol_x_preferred":[
        "Mera"
    ],
    "name:por_x_preferred":[
        "Mera"
    ],
    "name:ron_x_preferred":[
        "Mera"
    ],
    "name:rus_x_preferred":[
        "\u041c\u0435\u0440\u0430"
    ],
    "name:spa_x_preferred":[
        "Mera"
    ],
    "name:srp_x_preferred":[
        "\u041c\u0435\u0440\u0430"
    ],
    "name:swe_x_preferred":[
        "Mera"
    ],
    "name:und_x_variant":[
        "Fura",
        "Fuzaki"
    ],
    "name:vie_x_preferred":[
        "Mera"
    ],
    "wof:name":"Mera",
    "wof:placetype":"locality"
},
  "geometry": {"coordinates":[139.83056999999999,34.91797],"type":"Point"}
}