{
  "type": "Feature",
  "properties": {
    "iso:country":"JP",
    "name:jpn_x_preferred":[
        "\uff08\u4e01\u76ee\u306a\u3057\uff09"
    ],
    "qs:gn_adm0_cc":"JP",
    "qs:gn_local":2112539,
    "qs:local_max":1243,
    "qs:local_sum":1536,
    "qs:localhoods":10,
    "qs:name":"\uff08\u4e01\u76ee\u306a\u3057\uff09",
    "qs:name_adm0":"\u65e5\u672c",
    "qs:name_adm1":"\u798f\u5cf6\u770c",
    "qs:name_lau":"\u5185\u90f7\u9ad8\u5742\u753a",
    "qs:name_local":"\u3044\u308f\u304d\u5e02",
    "qs:photo_max":2,
    "qs:photo_sum":2,
    "qs:placetype":"Suburb",
    "qs:quad_count":1,
    "qs:woe_adm0":23424856,
    "qs:woe_adm1":2345858,
    "qs:woe_adm2":0,
    "qs:woe_lau":28398654,
    "qs:woe_local":1117341,
    "qs:woe_ver":"7.10.0",
    "qs_pg:name":"\uff08\u4e01\u76ee\u306a\u3057\uff09",
    "qs_pg:name_adm0":"\u65e5\u672c",
    "qs_pg:name_adm1":"\u798f\u5cf6\u770c",
    "qs_pg:photos":2,
    "qs_pg:photos_1k":1,
    "qs_pg:photos_9k":1,
    "qs_pg:photos_9r":1,
    "qs_pg:photos_all":2,
    "qs_pg:photos_sr":1,
    "qs_pg:pop_sr":0,
    "qs_pg:qs_pg_placetype":"neighbourhood",
    "qs_pg:qs_pg_placetype_gp":"Suburb",
    "qs_pg:woe_adm0":23424856,
    "woe:adm0_id":23424856,
    "woe:name_adm0":"\u65e5\u672c",
    "woe:name_adm1":"\u798f\u5cf6\u770c",
    "woe:placetype":"Suburb",
    "wof:lang":[
        "jpn"
    ],
    "wof:name":"\uff08\u4e01\u76ee\u306a\u3057\uff09",
    "wof:placetype":"neighbourhood"
},
  "geometry": {"coordinates":[140.85845900000001,37.035446],"type":"Point"}
}