{
  "type": "Feature",
  "properties": {
    "iso:country":"JP",
    "name:eng_x_preferred":[
        "Toyoyama Town"
    ],
    "name:jpn_x_preferred":[
        "\u8c4a\u5c71\u753a"
    ],
    "qs:name":"\u8c4a\u5c71\u753a",
    "qs:name_adm0":"\u65e5\u672c",
    "qs:name_adm1":"\u611b\u77e5\u770c",
    "qs:photos":65,
    "qs:photos_1k":13,
    "qs:photos_9k":1,
    "qs:photos_9r":2,
    "qs:photos_all":65,
    "qs:photos_sr":2,
    "qs:placetype":"Town",
    "qs:pop_sr":"0",
    "wof:name":"Toyoyama Town",
    "wof:placetype":"locality"
},
  "geometry": {"coordinates":[136.922864,35.252628],"type":"Point"}
}