{
  "type": "Feature",
  "properties": {
    "gn:admin1_code":"21",
    "gn:admin2_code":"7412706.0",
    "gn:admin3_code":"43444.0",
    "gn:asciiname":"Iwashita",
    "gn:country_code":"JP",
    "gn:dem":75,
    "gn:feature_class":"P",
    "gn:feature_code":"PPL",
    "gn:name":"Iwashita",
    "gn:population":0,
    "gn:timezone":"Asia/Tokyo",
    "iso:country":"JP",
    "wof:name":"Iwashita",
    "wof:placetype":"locality"
},
  "geometry": {"coordinates":[130.81666999999999,32.63333],"type":"Point"}
}