{
  "type": "Feature",
  "properties": {
    "gn:admin1_code":"18.0",
    "gn:admin2_code":"8300556.0",
    "gn:asciiname":"Kosenjocho",
    "gn:country_code":"JP",
    "gn:dem":29,
    "gn:feature_class":"P",
    "gn:feature_code":"PPL",
    "gn:name":"Kosenj\u014dch\u014d",
    "gn:population":0,
    "gn:timezone":"Asia/Tokyo",
    "iso:country":"JP",
    "name:jpn_x_preferred":[
        "\u53e4\u524d\u57ce\u753a"
    ],
    "name:und_x_variant":[
        "Kosenj\u014dch\u014d"
    ],
    "wof:name":"Kosenjocho",
    "wof:placetype":"locality"
},
  "geometry": {"coordinates":[130.85213000000002,31.38791],"type":"Point"}
}