{
  "type": "Feature",
  "properties": {
    "gn:admin1_code":"19.0",
    "gn:admin2_code":"1865011.0",
    "gn:admin3_code":"14366.0",
    "gn:asciiname":"Kawaramachi",
    "gn:country_code":"JP",
    "gn:dem":52,
    "gn:feature_class":"P",
    "gn:feature_code":"PPLL",
    "gn:name":"Kawaramachi",
    "gn:population":0,
    "gn:timezone":"Asia/Tokyo",
    "iso:country":"JP",
    "name:jpn_x_preferred":[
        "\u6cb3\u539f\u753a"
    ],
    "wof:name":"Kawaramachi",
    "wof:placetype":"locality"
},
  "geometry": {"coordinates":[139.12978000000001,35.34207],"type":"Point"}
}