{
  "type": "Feature",
  "properties": {
    "gn:admin1_code":"32.0",
    "gn:admin2_code":"1848519.0",
    "gn:asciiname":"Kameicho",
    "gn:country_code":"JP",
    "gn:dem":7,
    "gn:feature_class":"P",
    "gn:feature_code":"PPL",
    "gn:name":"Kameich\u014d",
    "gn:population":0,
    "gn:timezone":"Asia/Tokyo",
    "iso:country":"JP",
    "name:jpn_x_preferred":[
        "\u4e80\u4e95\u753a"
    ],
    "name:und_x_variant":[
        "Kameich\u014d",
        "Kameicho"
    ],
    "wof:name":"Kameicho",
    "wof:placetype":"locality"
},
  "geometry": {"coordinates":[135.57738000000001,34.61831],"type":"Point"}
}