{
  "type": "Feature",
  "properties": {
    "gn:admin1_code":"4.0",
    "gn:admin2_code":"2112997.0",
    "gn:admin3_code":"12422.0",
    "gn:asciiname":"Kawashima",
    "gn:country_code":"JP",
    "gn:dem":2,
    "gn:feature_class":"P",
    "gn:feature_code":"PPL",
    "gn:name":"Kawashima",
    "gn:population":0,
    "gn:timezone":"Asia/Tokyo",
    "iso:country":"JP",
    "name:jpn_x_preferred":[
        "\u5ddd\u5cf6"
    ],
    "name:jpn_x_variant":[
        "\u304b\u308f\u3057\u307e",
        "\u30ab\u30ef\u30b7\u30de"
    ],
    "wof:name":"Kawashima",
    "wof:placetype":"locality"
},
  "geometry": {"coordinates":[140.33996000000002,35.38329],"type":"Point"}
}