{
  "type": "Feature",
  "properties": {
    "gn:admin1_code":"3.0",
    "gn:admin2_code":"2128302.0",
    "gn:admin3_code":"2441.0",
    "gn:asciiname":"Niida",
    "gn:country_code":"JP",
    "gn:dem":95,
    "gn:feature_class":"P",
    "gn:feature_code":"PPL",
    "gn:name":"Niida",
    "gn:population":0,
    "gn:timezone":"Asia/Tokyo",
    "iso:country":"JP",
    "name:jpn_x_preferred":[
        "\u65b0\u4e95\u7530"
    ],
    "name:jpn_x_variant":[
        "\u306b\u3044\u3060",
        "\u30cb\u30a4\u30c0"
    ],
    "wof:name":"Niida",
    "wof:placetype":"locality"
},
  "geometry": {"coordinates":[141.21931999999995,40.39862],"type":"Point"}
}