{
  "type": "Feature",
  "properties": {
    "gn:admin1_code":"47",
    "gn:admin2_code":"1858371.0",
    "gn:admin3_code":"47308.0",
    "gn:asciiname":"Hamamoto",
    "gn:country_code":"JP",
    "gn:dem":45,
    "gn:feature_class":"P",
    "gn:feature_code":"PPL",
    "gn:name":"Hamamoto",
    "gn:population":0,
    "gn:timezone":"Asia/Tokyo",
    "iso:country":"JP",
    "name:jpn_x_preferred":[
        "\u6d5c\u5143"
    ],
    "name:und_x_variant":[
        "Mamamoto",
        "Hamamuto",
        "Hamamoto"
    ],
    "wof:name":"Hamamoto",
    "wof:placetype":"locality"
},
  "geometry": {"coordinates":[127.8925,26.66955],"type":"Point"}
}