{
  "type": "Feature",
  "properties": {
    "gn:admin1_code":"40",
    "gn:admin2_code":"1851306.0",
    "gn:asciiname":"Samban",
    "gn:cc2":"JP",
    "gn:country_code":"JP",
    "gn:dem":100,
    "gn:feature_class":"P",
    "gn:feature_code":"PPL",
    "gn:name":"Samban",
    "gn:population":0,
    "gn:timezone":"Asia/Tokyo",
    "iso:country":"JP",
    "name:und_x_variant":[
        "Sunagawa",
        "Samban"
    ],
    "wof:name":"Samban",
    "wof:placetype":"locality"
},
  "geometry": {"coordinates":[139.40000000000001,35.71667],"type":"Point"}
}