{
  "type": "Feature",
  "properties": {
    "gn:admin1_code":"21.0",
    "gn:admin2_code":"7412708.0",
    "gn:admin3_code":"43510.0",
    "gn:asciiname":"Yoshino'o",
    "gn:country_code":"JP",
    "gn:dem":138,
    "gn:feature_class":"P",
    "gn:feature_code":"PPLL",
    "gn:name":"Yoshino\u2019o",
    "gn:population":0,
    "gn:timezone":"Asia/Tokyo",
    "iso:country":"JP",
    "name:jpn_x_preferred":[
        "\u5409\u91ce\u5c3e"
    ],
    "name:jpn_x_variant":[
        "\u3088\u3057\u306e\u304a",
        "\u30e8\u30b7\u30ce\u30aa"
    ],
    "name:und_x_variant":[
        "Yoshino\u2019o"
    ],
    "wof:name":"Yoshino'o",
    "wof:placetype":"locality"
},
  "geometry": {"coordinates":[130.80126999999999,32.23146],"type":"Point"}
}