{
  "type": "Feature",
  "properties": {
    "gn:admin1_code":"19",
    "gn:admin2_code":"1865009.0",
    "gn:admin3_code":"14382.0",
    "gn:asciiname":"Gora",
    "gn:country_code":"JP",
    "gn:dem":627,
    "gn:feature_class":"P",
    "gn:feature_code":"PPL",
    "gn:name":"G\u014dra",
    "gn:population":0,
    "gn:timezone":"Asia/Tokyo",
    "iso:country":"JP",
    "name:jpn_x_preferred":[
        "\u5f37\u7f85"
    ],
    "name:und_x_variant":[
        "G\u014dra",
        "Gora"
    ],
    "wof:name":"Gora",
    "wof:placetype":"locality"
},
  "geometry": {"coordinates":[139.04192,35.25077],"type":"Point"}
}