{
  "type": "Feature",
  "properties": {
    "gn:admin1_code":"19",
    "gn:admin2_code":"1865009.0",
    "gn:admin3_code":"14382.0",
    "gn:asciiname":"Gora",
    "gn:country_code":"JP",
    "gn:dem":627,
    "gn:feature_class":"P",
    "gn:feature_code":"PPL",
    "gn:name":"G\u014dra",
    "gn:population":0,
    "gn:timezone":"Asia/Tokyo",
    "iso:country":"JP",
    "name:bos_x_preferred":[
        "Gora"
    ],
    "name:bul_x_preferred":[
        "\u0413\u043e\u0440\u0430"
    ],
    "name:ceb_x_preferred":[
        "Gora"
    ],
    "name:deu_x_preferred":[
        "Gora"
    ],
    "name:fin_x_preferred":[
        "Gora"
    ],
    "name:fra_x_preferred":[
        "Gora"
    ],
    "name:heb_x_preferred":[
        "\u05d2\u05d5\u05e8\u05d4"
    ],
    "name:hrv_x_preferred":[
        "Gora"
    ],
    "name:hun_x_preferred":[
        "Gora"
    ],
    "name:ind_x_preferred":[
        "Gora"
    ],
    "name:ita_x_preferred":[
        "Gora"
    ],
    "name:jpn_x_preferred":[
        "\u5f37\u7f85"
    ],
    "name:nld_x_preferred":[
        "Gora"
    ],
    "name:rue_x_preferred":[
        "\u0413\u043e\u0440\u0430"
    ],
    "name:rus_x_preferred":[
        "\u0413\u043e\u0440\u0430"
    ],
    "name:slv_x_preferred":[
        "Gora"
    ],
    "name:sna_x_preferred":[
        "Gora"
    ],
    "name:srp_x_preferred":[
        "\u0413\u043e\u0440\u0430"
    ],
    "name:swe_x_preferred":[
        "Gora"
    ],
    "name:tur_x_preferred":[
        "Gora"
    ],
    "name:ukr_x_preferred":[
        "\u0413\u043e\u0440\u0430"
    ],
    "name:und_x_variant":[
        "G\u014dra"
    ],
    "wof:name":"Gora",
    "wof:placetype":"locality"
},
  "geometry": {"coordinates":[139.04192,35.25077],"type":"Point"}
}