{
  "type": "Feature",
  "properties": {
    "iso:country":"JP",
    "name:eng_x_preferred":[
        "Tennodai 3 Chome"
    ],
    "name:eng_x_variant":[
        "Tennoudai 3 Choume",
        "Tennodai 3 Chome"
    ],
    "name:jpn_x_preferred":[
        "\uff13\u4e01\u76ee"
    ],
    "name:jpn_x_variant":[
        "\u3066\u3093\u306e\u3046\u3060\u3044 \uff13\u3061\u3087\u3046\u3081",
        "\u5929\u738b\u53f0 \uff13\u4e01\u76ee",
        "\uff13\u3061\u3087\u3046\u3081"
    ],
    "qs:gn_local":0,
    "qs:local_max":374,
    "qs:local_sum":2231,
    "qs:localhoods":20,
    "qs:name":"\uff13\u4e01\u76ee",
    "qs:name_adm0":"\u65e5\u672c",
    "qs:name_adm1":"\u8328\u57ce\u770c",
    "qs:name_en":"Tennodai 3 Chome",
    "qs:name_lau":"\u5929\u738b\u53f0",
    "qs:name_local":"\u3064\u304f\u3070\u5e02",
    "qs:photo_max":30,
    "qs:photo_sum":48,
    "qs:placetype":"Suburb",
    "qs:quad_count":4,
    "qs:woe_adm0":23424856,
    "qs:woe_adm1":2345863,
    "qs:woe_adm2":0,
    "qs:woe_lau":28402794,
    "qs:woe_local":1116022,
    "qs:woe_ver":"7.10.0",
    "wof:lang":[
        "jpn"
    ],
    "wof:name":"\uff13\u4e01\u76ee",
    "wof:placetype":"neighbourhood"
},
  "geometry": {"coordinates":[140.092735,36.126689],"type":"Point"}
}