{
  "type": "Feature",
  "properties": {
    "gn:admin1_code":"21.0",
    "gn:admin2_code":"1859490.0",
    "gn:admin3_code":"43403.0",
    "gn:asciiname":"Torikogawa",
    "gn:country_code":"JP",
    "gn:dem":104,
    "gn:feature_class":"P",
    "gn:feature_code":"PPLL",
    "gn:name":"Torikogawa",
    "gn:population":0,
    "gn:timezone":"Asia/Tokyo",
    "iso:country":"JP",
    "name:jpn_x_preferred":[
        "\u9ce5\u5b50\u5ddd"
    ],
    "name:jpn_x_variant":[
        "\u3068\u308a\u3053\u304c\u308f",
        "\u30c8\u30ea\u30b3\u30ac\u30ef"
    ],
    "wof:name":"Torikogawa",
    "wof:placetype":"locality"
},
  "geometry": {"coordinates":[130.89955,32.86144],"type":"Point"}
}