{
  "type": "Feature",
  "properties": {
    "gn:admin1_code":"12.0",
    "gn:admin2_code":"2130058.0",
    "gn:admin3_code":"1642.0",
    "gn:asciiname":"Shinsei",
    "gn:country_code":"JP",
    "gn:dem":27,
    "gn:feature_class":"P",
    "gn:feature_code":"PPLL",
    "gn:name":"Shinsei",
    "gn:population":0,
    "gn:timezone":"Asia/Tokyo",
    "iso:country":"JP",
    "name:jpn_x_preferred":[
        "\u65b0\u751f"
    ],
    "name:jpn_x_variant":[
        "\u3057\u3093\u305b\u3044",
        "\u30b7\u30f3\u30bb\u30a4"
    ],
    "wof:name":"Shinsei",
    "wof:placetype":"locality"
},
  "geometry": {"coordinates":[143.3212,42.32252],"type":"Point"}
}