{
  "type": "Feature",
  "properties": {
    "gn:admin1_code":"17",
    "gn:admin2_code":"1851654.0",
    "gn:admin3_code":"37324.0",
    "gn:asciiname":"Kusakabe-honmachi",
    "gn:country_code":"JP",
    "gn:dem":5,
    "gn:feature_class":"P",
    "gn:feature_code":"PPL",
    "gn:name":"Kusakabe-honmachi",
    "gn:population":0,
    "gn:timezone":"Asia/Tokyo",
    "iso:country":"JP",
    "name:jpn_x_preferred":[
        "\u8349\u58c1\u672c\u753a"
    ],
    "name:und_x_variant":[
        "Shimomura",
        "Kusababe",
        "Shimo",
        "Kusakabe",
        "Kusakabehommachi",
        "Kusakabe-honmachi"
    ],
    "wof:name":"Kusakabe-honmachi",
    "wof:placetype":"locality"
},
  "geometry": {"coordinates":[134.30389,34.48],"type":"Point"}
}