{
  "type": "Feature",
  "properties": {
    "gn:admin1_code":"05",
    "gn:admin2_code":"1857121.0",
    "gn:admin3_code":"38506.0",
    "gn:asciiname":"Kashiwazaki",
    "gn:country_code":"JP",
    "gn:dem":38,
    "gn:feature_class":"P",
    "gn:feature_code":"PPL",
    "gn:name":"Kashiwazaki",
    "gn:population":0,
    "gn:timezone":"Asia/Tokyo",
    "iso:country":"JP",
    "name:und_x_variant":[
        "Kashiwasaki",
        "Kashiwazaki",
        "\u67cf\u5d0e"
    ],
    "wof:name":"Kashiwazaki",
    "wof:placetype":"locality"
},
  "geometry": {"coordinates":[132.49250000000001,33.01824000000001],"type":"Point"}
}