{
  "type": "Feature",
  "properties": {
    "gn:admin1_code":"37",
    "gn:admin2_code":"7418321.0",
    "gn:asciiname":"Makinohara",
    "gn:country_code":"JP",
    "gn:dem":178,
    "gn:feature_class":"P",
    "gn:feature_code":"PPLA2",
    "gn:name":"Makinohara",
    "gn:population":0,
    "gn:timezone":"Asia/Tokyo",
    "iso:country":"JP",
    "name:ara_x_preferred":[
        "\u0645\u0627\u0643\u064a\u0646\u0648\u0647\u0627\u0631\u0627"
    ],
    "name:azb_x_preferred":[
        "\u0645\u0627\u06a9\u06cc\u0646\u0648\u0647\u0627\u0631\u0627"
    ],
    "name:ceb_x_preferred":[
        "Makinohara Shi"
    ],
    "name:ces_x_preferred":[
        "Makinohara"
    ],
    "name:deu_x_preferred":[
        "Makinohara"
    ],
    "name:fas_x_preferred":[
        "\u0645\u0627\u06a9\u06cc\u0646\u0648\u0647\u0627\u0631\u0627"
    ],
    "name:fra_x_preferred":[
        "Makinohara"
    ],
    "name:glg_x_preferred":[
        "Makinohara"
    ],
    "name:ita_x_preferred":[
        "Makinohara"
    ],
    "name:jpn_x_preferred":[
        "\u7267\u4e4b\u539f"
    ],
    "name:jpn_x_variant":[
        "\u307e\u304d\u306e\u306f\u3089\u3057",
        "\u7267\u4e4b\u539f\u5e02"
    ],
    "name:kor_x_preferred":[
        "\ub9c8\ud0a4\ub178\ud558\ub77c\uc2dc"
    ],
    "name:mzn_x_preferred":[
        "\u0645\u0627\u06a9\u06cc\u0646\u0648\u0647\u0627\u0631\u0627"
    ],
    "name:nld_x_preferred":[
        "Makinohara"
    ],
    "name:pol_x_preferred":[
        "Makinohara"
    ],
    "name:por_x_preferred":[
        "Makinohara"
    ],
    "name:ron_x_preferred":[
        "Makinohara"
    ],
    "name:rus_x_preferred":[
        "\u041c\u0430\u043a\u0438\u043d\u043e\u0445\u0430\u0440\u0430"
    ],
    "name:swe_x_preferred":[
        "Makinohara"
    ],
    "name:tgl_x_preferred":[
        "Makinohara"
    ],
    "name:tum_x_preferred":[
        "Makinohara"
    ],
    "name:tur_x_preferred":[
        "Makinohara"
    ],
    "name:ukr_x_preferred":[
        "\u041c\u0430\u043a\u0456\u043d\u043e\u0445\u0430\u0440\u0430"
    ],
    "name:vie_x_preferred":[
        "Makinohara"
    ],
    "name:war_x_preferred":[
        "Makinohara"
    ],
    "name:zho_x_preferred":[
        "\u7267\u4e4b\u539f\u5e02"
    ],
    "wof:name":"Makinohara",
    "wof:placetype":"locality"
},
  "geometry": {"coordinates":[138.14831000000001,34.77437],"type":"Point"}
}