{
  "type": "Feature",
  "properties": {
    "gn:admin1_code":"37",
    "gn:admin2_code":"7418321.0",
    "gn:asciiname":"Makinohara",
    "gn:country_code":"JP",
    "gn:dem":178,
    "gn:feature_class":"P",
    "gn:feature_code":"PPLA2",
    "gn:name":"Makinohara",
    "gn:population":0,
    "gn:timezone":"Asia/Tokyo",
    "iso:country":"JP",
    "name:jpn_x_preferred":[
        "\u7267\u4e4b\u539f"
    ],
    "name:jpn_x_variant":[
        "\u307e\u304d\u306e\u306f\u3089\u3057"
    ],
    "wof:name":"Makinohara",
    "wof:placetype":"locality"
},
  "geometry": {"coordinates":[138.14831000000001,34.77437],"type":"Point"}
}