{
  "type": "Feature",
  "properties": {
    "gn:admin1_code":"12.0",
    "gn:admin2_code":"7428079.0",
    "gn:admin3_code":"1647.0",
    "gn:asciiname":"Nakaashoro",
    "gn:country_code":"JP",
    "gn:dem":164,
    "gn:feature_class":"P",
    "gn:feature_code":"PPL",
    "gn:name":"Nakaashoro",
    "gn:population":0,
    "gn:timezone":"Asia/Tokyo",
    "iso:country":"JP",
    "name:jpn_x_preferred":[
        "\u4e2d\u8db3\u5bc4"
    ],
    "name:jpn_x_variant":[
        "\u306a\u304b\u3042\u3057\u3087\u308d",
        "\u30ca\u30ab\u30a2\u30b7\u30e7\u30ed"
    ],
    "name:und_x_variant":[
        "Naka-ashiyoro",
        "Naka-ashoro",
        "Nakaashoro",
        "Shimo-ashoro",
        "Ashoro",
        "Ashiyoro"
    ],
    "wof:name":"Nakaashoro",
    "wof:placetype":"locality"
},
  "geometry": {"coordinates":[143.62530000000001,43.28444],"type":"Point"}
}