{
  "type": "Feature",
  "properties": {
    "gn:admin1_code":"3.0",
    "gn:admin2_code":"2130225.0",
    "gn:asciiname":"Inami",
    "gn:country_code":"JP",
    "gn:dem":9,
    "gn:feature_class":"P",
    "gn:feature_code":"PPL",
    "gn:name":"Inami",
    "gn:population":0,
    "gn:timezone":"Asia/Tokyo",
    "iso:country":"JP",
    "name:jpn_x_preferred":[
        "\u7a32\u5b9f"
    ],
    "name:jpn_x_variant":[
        "\u3044\u306a\u307f",
        "\u30a4\u30ca\u30df"
    ],
    "wof:name":"Inami",
    "wof:placetype":"locality"
},
  "geometry": {"coordinates":[140.46833000000001,40.79022],"type":"Point"}
}