{
  "type": "Feature",
  "properties": {
    "gn:admin1_code":"21.0",
    "gn:admin2_code":"1864973.0",
    "gn:asciiname":"Akasuna",
    "gn:country_code":"JP",
    "gn:dem":784,
    "gn:feature_class":"P",
    "gn:feature_code":"PPLL",
    "gn:name":"Akasuna",
    "gn:population":0,
    "gn:timezone":"Asia/Tokyo",
    "iso:country":"JP",
    "name:jpn_x_preferred":[
        "\u8d64\u7802"
    ],
    "name:jpn_x_variant":[
        "\u3042\u304b\u3059\u306a",
        "\u30a2\u30ab\u30b9\u30ca"
    ],
    "wof:name":"Akasuna",
    "wof:placetype":"locality"
},
  "geometry": {"coordinates":[131.17568,32.93342],"type":"Point"}
}