{
  "type": "Feature",
  "properties": {
    "iso:country":"JP",
    "qs:name":"\u5341\u65e5\u753a\u5e02",
    "qs:name_adm0":"\u65e5\u672c",
    "qs:name_adm1":"\u65b0\u6f5f\u770c",
    "qs:photos":3222,
    "qs:photos_1k":653,
    "qs:photos_9k":16,
    "qs:photos_9r":12,
    "qs:photos_all":3502,
    "qs:photos_sr":20,
    "qs:placetype":"Town",
    "qs:pop_sr":"0",
    "wof:name":"\u5341\u65e5\u753a\u5e02",
    "wof:placetype":"locality"
},
  "geometry": {"coordinates":[138.69364200000001,37.143898],"type":"Point"}
}