{
  "type": "Feature",
  "properties": {
    "gn:country":"JP",
    "gn:fcode":"ADM3",
    "gn:population":0,
    "iso:country":"JP",
    "name:jpn_x_preferred":[
        "\u9577\u6cbc\u753a"
    ],
    "name:jpn_x_variant":[
        "\u306a\u304c\u306c\u307e\u3061\u3087\u3046"
    ],
    "name:und_x_variant":[
        "Naganuma Ch\u014d"
    ],
    "qs:name":"Naganuma-ch\u014d",
    "qs:photos_9r":0,
    "qs:photos_sr":0,
    "qs:pop_sr":"0",
    "wof:name":"Naganuma-ch\u014d",
    "wof:placetype":"localadmin",
    "wof:population":0
},
  "geometry": {"coordinates":[141.69490999999999,42.98938],"type":"Point"}
}