{
  "type": "Feature",
  "properties": {
    "gn:admin1_code":"24.0",
    "gn:admin2_code":"2112261.0",
    "gn:asciiname":"Zogahana",
    "gn:country_code":"JP",
    "gn:dem":118,
    "gn:feature_class":"P",
    "gn:feature_code":"PPL",
    "gn:name":"Z\u014dgahana",
    "gn:population":0,
    "gn:timezone":"Asia/Tokyo",
    "iso:country":"JP",
    "name:jpn_x_preferred":[
        "\u8c61\u30f6\u9f3b"
    ],
    "name:jpn_x_variant":[
        "\u305e\u3046\u304c\u306f\u306a",
        "\u30be\u30a6\u30ac\u30cf\u30ca"
    ],
    "name:und_x_variant":[
        "Z\u014dgahana"
    ],
    "wof:name":"Zogahana",
    "wof:placetype":"locality"
},
  "geometry": {"coordinates":[141.49975000000001,38.912],"type":"Point"}
}