{
  "type": "Feature",
  "properties": {
    "gn:admin1_code":"21",
    "gn:admin2_code":"1858418.0",
    "gn:admin3_code":"43102.0",
    "gn:asciiname":"Ishiwara",
    "gn:country_code":"JP",
    "gn:dem":65,
    "gn:feature_class":"P",
    "gn:feature_code":"PPL",
    "gn:name":"Ishiwara",
    "gn:population":0,
    "gn:timezone":"Asia/Tokyo",
    "iso:country":"JP",
    "name:jpn_x_preferred":[
        "\u77f3\u539f"
    ],
    "name:jpn_x_variant":[
        "\u3044\u3057\u308f\u3089",
        "\u30a4\u30b7\u30ef\u30e9"
    ],
    "name:und_x_variant":[
        "Ishibaru",
        "Ishihara",
        "Ishiwara"
    ],
    "wof:name":"Ishiwara",
    "wof:placetype":"locality"
},
  "geometry": {"coordinates":[130.78099,32.84244],"type":"Point"}
}