{
  "type": "Feature",
  "properties": {
    "gn:admin1_code":"3.0",
    "gn:admin2_code":"7439944.0",
    "gn:asciiname":"Funakoshi",
    "gn:country_code":"JP",
    "gn:dem":0,
    "gn:feature_class":"P",
    "gn:feature_code":"PPL",
    "gn:name":"Funakoshi",
    "gn:population":0,
    "gn:timezone":"Asia/Tokyo",
    "iso:country":"JP",
    "name:jpn_x_preferred":[
        "\u8239\u8d8a"
    ],
    "name:jpn_x_variant":[
        "\u3075\u306a\u3053\u3057",
        "\u30d5\u30ca\u30b3\u30b7"
    ],
    "wof:name":"Funakoshi",
    "wof:placetype":"locality"
},
  "geometry": {"coordinates":[140.41018,40.92746],"type":"Point"}
}