{
  "type": "Feature",
  "properties": {
    "iso:country":"JP",
    "name:eng_x_preferred":[
        "Tajima 10 Chome"
    ],
    "name:eng_x_variant":[
        "Tajima 10 Choume",
        "Tajima 10 Chome"
    ],
    "name:jpn_x_preferred":[
        "\uff11\uff10\u4e01\u76ee"
    ],
    "name:jpn_x_variant":[
        "\u305f\u3058\u307e \uff11\uff10\u3061\u3087\u3046\u3081",
        "\u7530\u5cf6 \uff11\uff10\u4e01\u76ee",
        "\uff11\uff10\u3061\u3087\u3046\u3081"
    ],
    "qs:gn_local":0,
    "qs:local_max":581,
    "qs:local_sum":6772,
    "qs:localhoods":52,
    "qs:name":"\uff11\uff10\u4e01\u76ee",
    "qs:name_adm0":"\u65e5\u672c",
    "qs:name_adm1":"\u57fc\u7389\u770c",
    "qs:name_adm2":"\u685c\u533a",
    "qs:name_en":"Tajima 10 Chome",
    "qs:name_lau":"\u7530\u5cf6",
    "qs:name_local":"\u3055\u3044\u305f\u307e\u5e02",
    "qs:photo_max":14,
    "qs:photo_sum":38,
    "qs:placetype":"Suburb",
    "qs:quad_count":6,
    "qs:woe_adm0":23424856,
    "qs:woe_adm1":2345883,
    "qs:woe_adm2":24851612,
    "qs:woe_lau":28407749,
    "qs:woe_local":1116753,
    "qs:woe_ver":"7.10.0",
    "wof:lang":[
        "jpn"
    ],
    "wof:name":"\uff11\uff10\u4e01\u76ee",
    "wof:placetype":"neighbourhood"
},
  "geometry": {"coordinates":[139.61878999999999,35.835629],"type":"Point"}
}