{
  "type": "Feature",
  "properties": {
    "gn:admin1_code":"13.0",
    "gn:admin2_code":"1859671.0",
    "gn:asciiname":"Akamatsu",
    "gn:country_code":"JP",
    "gn:dem":133,
    "gn:feature_class":"P",
    "gn:feature_code":"PPL",
    "gn:name":"Akamatsu",
    "gn:population":0,
    "gn:timezone":"Asia/Tokyo",
    "iso:country":"JP",
    "name:fra_x_preferred":[
        "Akamatsu"
    ],
    "name:jpn_x_preferred":[
        "\u8d64\u677e"
    ],
    "wof:name":"Akamatsu",
    "wof:placetype":"locality"
},
  "geometry": {"coordinates":[135.38087999999999,34.87341],"type":"Point"}
}