{
  "type": "Feature",
  "properties": {
    "gn:admin1_code":"21.0",
    "gn:admin2_code":"1850744.0",
    "gn:admin3_code":"43367.0",
    "gn:asciiname":"Kanamaru",
    "gn:country_code":"JP",
    "gn:dem":66,
    "gn:feature_class":"P",
    "gn:feature_code":"PPLL",
    "gn:name":"Kanamaru",
    "gn:population":0,
    "gn:timezone":"Asia/Tokyo",
    "iso:country":"JP",
    "name:jpn_x_preferred":[
        "\u91d1\u4e38"
    ],
    "name:jpn_x_variant":[
        "\u304b\u306a\u307e\u308b",
        "\u30ab\u30ca\u30de\u30eb"
    ],
    "wof:name":"Kanamaru",
    "wof:placetype":"locality"
},
  "geometry": {"coordinates":[130.53971999999999,33.05395],"type":"Point"}
}