{
  "type": "Feature",
  "properties": {
    "iso:country":"JP",
    "name:eng_x_preferred":[
        "Odakicho 1 Chome"
    ],
    "name:eng_x_variant":[
        "Oodakichou 1 Choume",
        "Odakicho 1 Chome"
    ],
    "name:jpn_x_preferred":[
        "\uff11\u4e01\u76ee"
    ],
    "name:jpn_x_variant":[
        "\u304a\u304a\u3060\u304d\u3061\u3087\u3046 \uff11\u3061\u3087\u3046\u3081",
        "\u5927\u6edd\u753a \uff11\u4e01\u76ee",
        "\uff11\u3061\u3087\u3046\u3081"
    ],
    "name:unk_x_variant":[
        "\uff11\u4e01\u76ee"
    ],
    "qs:gn_local":0,
    "qs:local_max":1046,
    "qs:local_sum":7358,
    "qs:localhoods":30,
    "qs:name":"\uff11\u4e01\u76ee",
    "qs:name_adm0":"\u65e5\u672c",
    "qs:name_adm1":"\u795e\u5948\u5ddd\u770c",
    "qs:name_en":"Odakicho 1 Chome",
    "qs:name_lau":"\u5927\u6edd\u753a",
    "qs:name_local":"\u6a2a\u9808\u8cc0\u5e02",
    "qs:photo_max":146,
    "qs:photo_sum":1046,
    "qs:placetype":"Suburb",
    "qs:quad_count":32,
    "qs:woe_adm0":23424856,
    "qs:woe_adm1":2345868,
    "qs:woe_adm2":0,
    "qs:woe_lau":28416522,
    "qs:woe_local":1118552,
    "qs:woe_ver":"7.10.0",
    "wof:lang":[
        "jpn"
    ],
    "wof:name":"\uff11\u4e01\u76ee",
    "wof:placetype":"neighbourhood"
},
  "geometry": {"coordinates":[139.67282900000001,35.286229],"type":"Point"}
}