{
  "type": "Feature",
  "properties": {
    "gn:admin1_code":"7.0",
    "gn:admin2_code":"7407413.0",
    "gn:asciiname":"Madokoro",
    "gn:country_code":"JP",
    "gn:dem":109,
    "gn:feature_class":"P",
    "gn:feature_code":"PPLL",
    "gn:name":"Madokoro",
    "gn:population":0,
    "gn:timezone":"Asia/Tokyo",
    "iso:country":"JP",
    "name:jpn_x_preferred":[
        "\u653f\u6240"
    ],
    "wof:name":"Madokoro",
    "wof:placetype":"locality"
},
  "geometry": {"coordinates":[130.77284,33.52548],"type":"Point"}
}