{
  "type": "Feature",
  "properties": {
    "gn:admin1_code":"21.0",
    "gn:admin2_code":"7413152.0",
    "gn:asciiname":"Hirabaru",
    "gn:country_code":"JP",
    "gn:dem":86,
    "gn:feature_class":"P",
    "gn:feature_code":"PPLL",
    "gn:name":"Hirabaru",
    "gn:population":0,
    "gn:timezone":"Asia/Tokyo",
    "iso:country":"JP",
    "name:jpn_x_preferred":[
        "\u5e73\u539f"
    ],
    "name:jpn_x_variant":[
        "\u3072\u3089\u3070\u308b",
        "\u30d2\u30e9\u30d0\u30eb"
    ],
    "wof:name":"Hirabaru",
    "wof:placetype":"locality"
},
  "geometry": {"coordinates":[130.75693999999999,32.59887],"type":"Point"}
}