{
  "type": "Feature",
  "properties": {
    "gn:admin1_code":"21.0",
    "gn:admin2_code":"1857206.0",
    "gn:asciiname":"Ishizaka",
    "gn:country_code":"JP",
    "gn:dem":182,
    "gn:feature_class":"P",
    "gn:feature_code":"PPLL",
    "gn:name":"Ishizaka",
    "gn:population":0,
    "gn:timezone":"Asia/Tokyo",
    "iso:country":"JP",
    "name:jpn_x_preferred":[
        "\u77f3\u5742"
    ],
    "name:jpn_x_variant":[
        "\u3044\u3057\u3056\u304b",
        "\u30a4\u30b7\u30b6\u30ab"
    ],
    "wof:name":"Ishizaka",
    "wof:placetype":"locality"
},
  "geometry": {"coordinates":[130.48410000000001,32.15787],"type":"Point"}
}