{
  "type": "Feature",
  "properties": {
    "gn:admin1_code":"47",
    "gn:admin2_code":"1855990.0",
    "gn:admin3_code":"47328.0",
    "gn:asciiname":"Yagi",
    "gn:country_code":"JP",
    "gn:dem":13,
    "gn:feature_class":"P",
    "gn:feature_code":"PPL",
    "gn:name":"Yagi",
    "gn:population":0,
    "gn:timezone":"Asia/Tokyo",
    "iso:country":"JP",
    "name:deu_x_preferred":[
        "Yagi"
    ],
    "name:fra_x_preferred":[
        "Yagi"
    ],
    "name:ita_x_preferred":[
        "Yagi"
    ],
    "name:jpn_x_preferred":[
        "\u5c4b\u5b9c"
    ],
    "name:nld_x_preferred":[
        "Yagi"
    ],
    "name:nor_x_preferred":[
        "Yagi"
    ],
    "name:und_x_variant":[
        "Yaaji",
        "Y\u0101ji"
    ],
    "wof:name":"Yagi",
    "wof:placetype":"locality"
},
  "geometry": {"coordinates":[127.79366,26.26905],"type":"Point"}
}