{
  "type": "Feature",
  "properties": {
    "gn:admin1_code":"21.0",
    "gn:admin2_code":"7412705.0",
    "gn:admin3_code":"43482.0",
    "gn:asciiname":"Kamitsuge",
    "gn:country_code":"JP",
    "gn:dem":125,
    "gn:feature_class":"P",
    "gn:feature_code":"PPLL",
    "gn:name":"Kamitsuge",
    "gn:population":0,
    "gn:timezone":"Asia/Tokyo",
    "iso:country":"JP",
    "name:jpn_x_preferred":[
        "\u4e0a\u544a"
    ],
    "name:jpn_x_variant":[
        "\u304b\u307f\u3064\u3052",
        "\u30ab\u30df\u30c4\u30b2"
    ],
    "wof:name":"Kamitsuge",
    "wof:placetype":"locality"
},
  "geometry": {"coordinates":[130.59251,32.26476],"type":"Point"}
}