{
  "type": "Feature",
  "properties": {
    "gn:admin1_code":"21.0",
    "gn:admin2_code":"1848441.0",
    "gn:asciiname":"Koge-higashimachi",
    "gn:country_code":"JP",
    "gn:dem":4,
    "gn:feature_class":"P",
    "gn:feature_code":"PPL",
    "gn:name":"K\u014dge-higashimachi",
    "gn:population":0,
    "gn:timezone":"Asia/Tokyo",
    "iso:country":"JP",
    "name:jpn_x_preferred":[
        "\u9ad8\u4e0b\u6771\u753a"
    ],
    "name:und_x_variant":[
        "K\u014dge-higashimachi"
    ],
    "wof:name":"Koge-higashimachi",
    "wof:placetype":"locality"
},
  "geometry": {"coordinates":[130.61688000000001,32.49313],"type":"Point"}
}