{
  "type": "Feature",
  "properties": {
    "gn:admin1_code":"22.0",
    "gn:admin2_code":"1859202.0",
    "gn:asciiname":"Kamocho-reihei",
    "gn:country_code":"JP",
    "gn:dem":119,
    "gn:feature_class":"P",
    "gn:feature_code":"PPL",
    "gn:name":"Kamoch\u014d-reihei",
    "gn:population":0,
    "gn:timezone":"Asia/Tokyo",
    "iso:country":"JP",
    "name:jpn_x_preferred":[
        "\u52a0\u8302\u753a\u4f8b\u5f0a"
    ],
    "name:und_x_variant":[
        "Kamoch\u014d-reihei"
    ],
    "wof:name":"Kamocho-reihei",
    "wof:placetype":"locality"
},
  "geometry": {"coordinates":[135.86381,34.77332],"type":"Point"}
}