{
  "type": "Feature",
  "properties": {
    "gn:admin1_code":"21.0",
    "gn:admin2_code":"1850743.0",
    "gn:asciiname":"Taimeimachi-saishoji",
    "gn:country_code":"JP",
    "gn:dem":3,
    "gn:feature_class":"P",
    "gn:feature_code":"PPL",
    "gn:name":"Taimeimachi-saish\u014dji",
    "gn:population":0,
    "gn:timezone":"Asia/Tokyo",
    "iso:country":"JP",
    "name:jpn_x_preferred":[
        "\u5cb1\u660e\u753a\u897f\u7167\u5bfa"
    ],
    "name:jpn_x_variant":[
        "\u305f\u3044\u3081\u3044\u307e\u3061\u3055\u3044\u3057\u3087\u3046\u3058",
        "\u30bf\u30a4\u30e1\u30a4\u30de\u30c1\u30b5\u30a4\u30b7\u30e7\u30a6\u30b8"
    ],
    "name:und_x_variant":[
        "Taimeimachi-saish\u014dji"
    ],
    "wof:name":"Taimeimachi-saishoji",
    "wof:placetype":"locality"
},
  "geometry": {"coordinates":[130.50498000000002,32.93621],"type":"Point"}
}