{
  "type": "Feature",
  "properties": {
    "gn:admin1_code":"24.0",
    "gn:admin2_code":"2112261.0",
    "gn:asciiname":"Nagaiso-maebayashi",
    "gn:country_code":"JP",
    "gn:dem":20,
    "gn:feature_class":"P",
    "gn:feature_code":"PPL",
    "gn:name":"Nagaiso-maebayashi",
    "gn:population":0,
    "gn:timezone":"Asia/Tokyo",
    "iso:country":"JP",
    "name:jpn_x_preferred":[
        "\u9577\u78ef\u524d\u6797"
    ],
    "name:jpn_x_variant":[
        "\u306a\u304c\u3044\u305d\u307e\u3048\u3070\u3084\u3057",
        "\u30ca\u30ac\u30a4\u30bd\u30de\u30a8\u30d0\u30e4\u30b7"
    ],
    "wof:name":"Nagaiso-maebayashi",
    "wof:placetype":"locality"
},
  "geometry": {"coordinates":[141.57917,38.83946],"type":"Point"}
}