{
  "type": "Feature",
  "properties": {
    "gn:admin1_code":"37.0",
    "gn:admin2_code":"1854900.0",
    "gn:asciiname":"Sanmaibashicho",
    "gn:country_code":"JP",
    "gn:dem":10,
    "gn:feature_class":"P",
    "gn:feature_code":"PPL",
    "gn:name":"Sanmaibashich\u014d",
    "gn:population":0,
    "gn:timezone":"Asia/Tokyo",
    "iso:country":"JP",
    "name:jpn_x_preferred":[
        "\u4e09\u679a\u6a4b\u753a"
    ],
    "name:und_x_variant":[
        "Sanmaibashich\u014d"
    ],
    "wof:name":"Sanmaibashicho",
    "wof:placetype":"locality"
},
  "geometry": {"coordinates":[138.86410000000001,35.10057],"type":"Point"}
}