{
  "type": "Feature",
  "properties": {
    "gn:admin1_code":"28.0",
    "gn:admin2_code":"1850395.0",
    "gn:asciiname":"Joganjicho",
    "gn:country_code":"JP",
    "gn:dem":79,
    "gn:feature_class":"P",
    "gn:feature_code":"PPL",
    "gn:name":"J\u014dganjich\u014d",
    "gn:population":0,
    "gn:timezone":"Asia/Tokyo",
    "iso:country":"JP",
    "name:jpn_x_preferred":[
        "\u6210\u9858\u5bfa\u753a"
    ],
    "name:und_x_variant":[
        "J\u014dganjich\u014d"
    ],
    "wof:name":"Joganjicho",
    "wof:placetype":"locality"
},
  "geometry": {"coordinates":[135.84243000000001,34.57001],"type":"Point"}
}