{
  "type": "Feature",
  "properties": {
    "gn:admin1_code":"29",
    "gn:admin2_code":"1852981.0",
    "gn:asciiname":"Morimachi",
    "gn:country_code":"JP",
    "gn:dem":66,
    "gn:feature_class":"P",
    "gn:feature_code":"PPL",
    "gn:name":"Morimachi",
    "gn:population":0,
    "gn:timezone":"Asia/Tokyo",
    "iso:country":"JP",
    "name:jpn_x_preferred":[
        "\u68ee\u753a"
    ],
    "wof:name":"Morimachi",
    "wof:placetype":"locality"
},
  "geometry": {"coordinates":[139.0881,37.54769],"type":"Point"}
}