{
  "type": "Feature",
  "properties": {
    "gn:admin1_code":"3.0",
    "gn:admin2_code":"2130056.0",
    "gn:asciiname":"Tanaka",
    "gn:country_code":"JP",
    "gn:dem":31,
    "gn:feature_class":"P",
    "gn:feature_code":"PPL",
    "gn:name":"Tanaka",
    "gn:population":0,
    "gn:timezone":"Asia/Tokyo",
    "iso:country":"JP",
    "name:epo_x_preferred":[
        "Tanaka"
    ],
    "name:jpn_x_preferred":[
        "\u7530\u4e2d"
    ],
    "name:jpn_x_variant":[
        "\u305f\u306a\u304b",
        "\u30bf\u30ca\u30ab"
    ],
    "name:spa_x_preferred":[
        "Tanaka"
    ],
    "name:ukr_x_preferred":[
        "\u0422\u0430\u043d\u0430\u043a\u0430"
    ],
    "wof:name":"Tanaka",
    "wof:placetype":"locality"
},
  "geometry": {"coordinates":[140.45516000000001,40.6204],"type":"Point"}
}