{
  "type": "Feature",
  "properties": {
    "iso:country":"JP",
    "name:eng_x_preferred":[
        "Tsuru"
    ],
    "name:eng_x_variant":[
        "Tsuru city"
    ],
    "name:jpn_x_preferred":[
        "\u90fd\u7559\u5e02"
    ],
    "qs:name":"\u90fd\u7559\u5e02",
    "qs:name_adm0":"\u65e5\u672c",
    "qs:name_adm1":"\u5c71\u68a8\u770c",
    "qs:photos":230,
    "qs:photos_1k":47,
    "qs:photos_9k":2,
    "qs:photos_9r":5,
    "qs:photos_all":437,
    "qs:photos_sr":4,
    "qs:placetype":"Town",
    "qs:pop_sr":"0",
    "wof:name":"Tsuru",
    "wof:placetype":"locality"
},
  "geometry": {"coordinates":[138.847532,35.570842],"type":"Point"}
}