{
  "type": "Feature",
  "properties": {
    "gn:admin1_code":"4.0",
    "gn:admin2_code":"1859468.0",
    "gn:asciiname":"Sawamaki",
    "gn:country_code":"JP",
    "gn:dem":46,
    "gn:feature_class":"P",
    "gn:feature_code":"PPLL",
    "gn:name":"Sawamaki",
    "gn:population":0,
    "gn:timezone":"Asia/Tokyo",
    "iso:country":"JP",
    "name:jpn_x_preferred":[
        "\u6ca2\u5dfb"
    ],
    "name:jpn_x_variant":[
        "\u3055\u308f\u307e\u304d",
        "\u30b5\u30ef\u30de\u30ad"
    ],
    "wof:name":"Sawamaki",
    "wof:placetype":"locality"
},
  "geometry": {"coordinates":[139.99200000000002,35.27924],"type":"Point"}
}