{
  "type": "Feature",
  "properties": {
    "gn:admin1_code":"4.0",
    "gn:admin2_code":"1863711.0",
    "gn:asciiname":"Ainoyatsu",
    "gn:country_code":"JP",
    "gn:dem":16,
    "gn:feature_class":"P",
    "gn:feature_code":"PPL",
    "gn:name":"Ainoyatsu",
    "gn:population":0,
    "gn:timezone":"Asia/Tokyo",
    "iso:country":"JP",
    "name:jpn_x_preferred":[
        "\u76f8\u91ce\u8c37"
    ],
    "name:jpn_x_variant":[
        "\u3042\u3044\u306e\u3084\u3064",
        "\u30a2\u30a4\u30ce\u30e4\u30c4"
    ],
    "wof:name":"Ainoyatsu",
    "wof:placetype":"locality"
},
  "geometry": {"coordinates":[139.88114999999999,35.30043],"type":"Point"}
}