{
  "type": "Feature",
  "properties": {
    "gn:admin1_code":"32",
    "gn:admin2_code":"1860764.0",
    "gn:asciiname":"Handa",
    "gn:country_code":"JP",
    "gn:dem":28,
    "gn:feature_class":"P",
    "gn:feature_code":"PPL",
    "gn:name":"Handa",
    "gn:population":0,
    "gn:timezone":"Asia/Tokyo",
    "iso:country":"JP",
    "name:ceb_x_preferred":[
        "Handa"
    ],
    "name:ces_x_preferred":[
        "Handa"
    ],
    "name:deu_x_preferred":[
        "Handa"
    ],
    "name:fra_x_preferred":[
        "Handa"
    ],
    "name:hye_x_preferred":[
        "\u0540\u0561\u0576\u0564\u0561"
    ],
    "name:nld_x_preferred":[
        "Handa"
    ],
    "name:rus_x_preferred":[
        "\u0425\u0430\u043d\u0434\u0430"
    ],
    "name:swe_x_preferred":[
        "Handa"
    ],
    "wof:name":"Handa",
    "wof:placetype":"locality"
},
  "geometry": {"coordinates":[135.36667,34.43333],"type":"Point"}
}