{
  "type": "Feature",
  "properties": {
    "gn:admin1_code":"12.0",
    "gn:admin2_code":"7428084.0",
    "gn:admin3_code":"1609.0",
    "gn:asciiname":"Shimochikaura",
    "gn:country_code":"JP",
    "gn:dem":25,
    "gn:feature_class":"P",
    "gn:feature_code":"PPLL",
    "gn:name":"Shimochikaura",
    "gn:population":0,
    "gn:timezone":"Asia/Tokyo",
    "iso:country":"JP",
    "name:jpn_x_preferred":[
        "\u4e0b\u8fd1\u6d66"
    ],
    "name:jpn_x_variant":[
        "\u3057\u3082\u3061\u304b\u3046\u3089",
        "\u30b7\u30e2\u30c1\u30ab\u30a6\u30e9"
    ],
    "wof:name":"Shimochikaura",
    "wof:placetype":"locality"
},
  "geometry": {"coordinates":[143.09083000000001,42.05256],"type":"Point"}
}