{
  "type": "Feature",
  "properties": {
    "gn:admin1_code":"21.0",
    "gn:admin2_code":"7412708.0",
    "gn:admin3_code":"43507.0",
    "gn:asciiname":"Ishinomoto",
    "gn:country_code":"JP",
    "gn:dem":747,
    "gn:feature_class":"P",
    "gn:feature_code":"PPLL",
    "gn:name":"Ishinomoto",
    "gn:population":0,
    "gn:timezone":"Asia/Tokyo",
    "iso:country":"JP",
    "name:jpn_x_preferred":[
        "\u77f3\u306e\u672c"
    ],
    "name:jpn_x_variant":[
        "\u3044\u3057\u306e\u3082\u3068",
        "\u30a4\u30b7\u30ce\u30e2\u30c8"
    ],
    "wof:name":"Ishinomoto",
    "wof:placetype":"locality"
},
  "geometry": {"coordinates":[130.99288999999999,32.3927],"type":"Point"}
}