{
  "type": "Feature",
  "properties": {
    "iso:country":"JP",
    "name:eng_x_preferred":[
        "Sakaemachi 1 Chome"
    ],
    "name:eng_x_variant":[
        "Sakaemachi 1 Choume",
        "Sakaemachi 1 Chome"
    ],
    "name:jpn_x_preferred":[
        "\uff11\u4e01\u76ee"
    ],
    "name:jpn_x_variant":[
        "\u3055\u304b\u3048\u307e\u3061 \uff11\u3061\u3087\u3046\u3081",
        "\u6804\u753a \uff11\u4e01\u76ee",
        "\uff11\u3061\u3087\u3046\u3081"
    ],
    "qs:gn_local":0,
    "qs:local_max":134,
    "qs:local_sum":246,
    "qs:localhoods":3,
    "qs:name":"\uff11\u4e01\u76ee",
    "qs:name_adm0":"\u65e5\u672c",
    "qs:name_adm1":"\u5175\u5eab\u770c",
    "qs:name_en":"Sakaemachi 1 Chome",
    "qs:name_lau":"\u6804\u753a",
    "qs:name_local":"\u5b9d\u585a\u5e02",
    "qs:photo_max":29,
    "qs:photo_sum":29,
    "qs:placetype":"Suburb",
    "qs:quad_count":1,
    "qs:woe_adm0":23424856,
    "qs:woe_adm1":2345862,
    "qs:woe_adm2":0,
    "qs:woe_lau":28463338,
    "qs:woe_local":1115299,
    "qs:woe_ver":"7.10.0",
    "wof:lang":[
        "jpn"
    ],
    "wof:name":"\uff11\u4e01\u76ee",
    "wof:placetype":"neighbourhood"
},
  "geometry": {"coordinates":[135.348816,34.807037],"type":"Point"}
}