{
  "type": "Feature",
  "properties": {
    "gn:admin1_code":"24.0",
    "gn:admin2_code":"2111045.0",
    "gn:asciiname":"Uratokatsurashima",
    "gn:country_code":"JP",
    "gn:dem":7,
    "gn:feature_class":"P",
    "gn:feature_code":"PPL",
    "gn:name":"Uratokatsurashima",
    "gn:population":0,
    "gn:timezone":"Asia/Tokyo",
    "iso:country":"JP",
    "name:jpn_x_preferred":[
        "\u6d66\u6238\u6842\u5cf6"
    ],
    "name:jpn_x_variant":[
        "\u30a6\u30e9\u30c8\u30ab\u30c4\u30e9\u30b7\u30de",
        "\u3046\u3089\u3068\u304b\u3064\u3089\u3057\u307e"
    ],
    "name:und_x_variant":[
        "Katsurashima"
    ],
    "wof:name":"Uratokatsurashima",
    "wof:placetype":"locality"
},
  "geometry": {"coordinates":[141.08886000000001,38.33409],"type":"Point"}
}