{
  "type": "Feature",
  "properties": {
    "gn:admin1_code":"4.0",
    "gn:admin2_code":"1849185.0",
    "gn:asciiname":"Hinode",
    "gn:country_code":"JP",
    "gn:dem":11,
    "gn:feature_class":"P",
    "gn:feature_code":"PPL",
    "gn:name":"Hinode",
    "gn:population":0,
    "gn:timezone":"Asia/Tokyo",
    "iso:country":"JP",
    "name:jpn_x_preferred":[
        "\u65e5\u306e\u51fa"
    ],
    "wof:name":"Hinode",
    "wof:placetype":"locality"
},
  "geometry": {"coordinates":[139.92816000000002,35.64413],"type":"Point"}
}