{
  "type": "Feature",
  "properties": {
    "gn:admin1_code":"2.0",
    "gn:admin2_code":"2128783.0",
    "gn:asciiname":"Matsuki",
    "gn:country_code":"JP",
    "gn:dem":66,
    "gn:feature_class":"P",
    "gn:feature_code":"PPL",
    "gn:name":"Matsuki",
    "gn:population":0,
    "gn:timezone":"Asia/Tokyo",
    "iso:country":"JP",
    "name:jpn_x_preferred":[
        "\u677e\u6728"
    ],
    "name:jpn_x_variant":[
        "\u307e\u3064\u304d",
        "\u30de\u30c4\u30ad"
    ],
    "wof:name":"Matsuki",
    "wof:placetype":"locality"
},
  "geometry": {"coordinates":[140.54449,40.29736],"type":"Point"}
}