{
  "type": "Feature",
  "properties": {
    "gn:admin1_code":"32",
    "gn:admin2_code":"1853167.0",
    "gn:admin3_code":"27144.0",
    "gn:asciiname":"Koencho",
    "gn:cc2":"JP",
    "gn:country_code":"JP",
    "gn:dem":12,
    "gn:feature_class":"P",
    "gn:feature_code":"PPL",
    "gn:name":"K\u014dench\u014d",
    "gn:population":0,
    "gn:timezone":"Asia/Tokyo",
    "iso:country":"JP",
    "name:und_x_variant":[
        "Hamadera-k\u014den-ch\u014d",
        "Hamadera-k\u014den",
        "K\u014dench\u014d"
    ],
    "wof:name":"Koencho",
    "wof:placetype":"locality"
},
  "geometry": {"coordinates":[135.44999999999999,34.53333],"type":"Point"}
}