{
  "type": "Feature",
  "properties": {
    "gn:admin1_code":"19.0",
    "gn:admin2_code":"1864091.0",
    "gn:asciiname":"Osogo",
    "gn:country_code":"JP",
    "gn:dem":14,
    "gn:feature_class":"P",
    "gn:feature_code":"PPLL",
    "gn:name":"Osog\u014d",
    "gn:population":0,
    "gn:timezone":"Asia/Tokyo",
    "iso:country":"JP",
    "name:jpn_x_preferred":[
        "\u737a\u90f7"
    ],
    "name:und_x_variant":[
        "Osog\u014d"
    ],
    "wof:name":"Osogo",
    "wof:placetype":"locality"
},
  "geometry": {"coordinates":[139.40687,35.38669],"type":"Point"}
}