{
  "type": "Feature",
  "properties": {
    "gn:admin1_code":"2.0",
    "gn:admin2_code":"2111153.0",
    "gn:admin3_code":"5434.0",
    "gn:asciiname":"Rokugo",
    "gn:country_code":"JP",
    "gn:dem":59,
    "gn:feature_class":"P",
    "gn:feature_code":"PPL",
    "gn:name":"Rokug\u014d",
    "gn:population":0,
    "gn:timezone":"Asia/Tokyo",
    "iso:country":"JP",
    "name:jpn_x_preferred":[
        "\u516d\u90f7"
    ],
    "name:und_x_variant":[
        "Rokug\u014d"
    ],
    "wof:name":"Rokugo",
    "wof:placetype":"locality"
},
  "geometry": {"coordinates":[140.55000000000001,39.41667],"type":"Point"}
}