{
  "type": "Feature",
  "properties": {
    "gn:admin1_code":"12.0",
    "gn:admin2_code":"7428113.0",
    "gn:admin3_code":"1392.0",
    "gn:asciiname":"Utasutsucho",
    "gn:country_code":"JP",
    "gn:dem":13,
    "gn:feature_class":"P",
    "gn:feature_code":"PPL",
    "gn:name":"Utasutsuch\u014d",
    "gn:population":0,
    "gn:timezone":"Asia/Tokyo",
    "iso:country":"JP",
    "name:und_x_variant":[
        "Oshoro",
        "Sekiro",
        "Utasutsuch\u014d"
    ],
    "wof:name":"Utasutsucho",
    "wof:placetype":"locality"
},
  "geometry": {"coordinates":[140.30687,42.77508],"type":"Point"}
}