{
  "type": "Feature",
  "properties": {
    "gn:admin1_code":"24.0",
    "gn:admin2_code":"2112074.0",
    "gn:admin3_code":"4422.0",
    "gn:asciiname":"Sekiba",
    "gn:country_code":"JP",
    "gn:dem":36,
    "gn:feature_class":"P",
    "gn:feature_code":"PPL",
    "gn:name":"Sekiba",
    "gn:population":0,
    "gn:timezone":"Asia/Tokyo",
    "iso:country":"JP",
    "name:jpn_x_preferred":[
        "\u5830\u5834"
    ],
    "name:jpn_x_variant":[
        "\u305b\u304d\u3070",
        "\u30bb\u30ad\u30d0"
    ],
    "wof:name":"Sekiba",
    "wof:placetype":"locality"
},
  "geometry": {"coordinates":[141.00966,38.39599000000001],"type":"Point"}
}