{
  "type": "Feature",
  "properties": {
    "gn:admin1_code":"47",
    "gn:admin2_code":"7415820.0",
    "gn:asciiname":"China",
    "gn:country_code":"JP",
    "gn:dem":18,
    "gn:feature_class":"P",
    "gn:feature_code":"PPL",
    "gn:name":"China",
    "gn:population":0,
    "gn:timezone":"Asia/Tokyo",
    "iso:country":"JP",
    "name:jpn_x_preferred":[
        "\u3061\u306a"
    ],
    "name:jpn_x_variant":[
        "\u77e5\u540d"
    ],
    "name:und_x_variant":[
        "Jiha",
        "Chiwa",
        "Chiha",
        "Chifuwa"
    ],
    "wof:name":"China",
    "wof:placetype":"locality"
},
  "geometry": {"coordinates":[127.81778,26.18361],"type":"Point"}
}