{
  "type": "Feature",
  "properties": {
    "gn:admin1_code":"35",
    "gn:admin2_code":"1854152.0",
    "gn:asciiname":"Onohama",
    "gn:country_code":"JP",
    "gn:dem":101,
    "gn:feature_class":"P",
    "gn:feature_code":"PPL",
    "gn:name":"\u014cnohama",
    "gn:population":0,
    "gn:timezone":"Asia/Tokyo",
    "iso:country":"JP",
    "name:und_x_variant":[
        "\u014cnohama"
    ],
    "wof:name":"Onohama",
    "wof:placetype":"locality"
},
  "geometry": {"coordinates":[136.09999999999999,35.16667],"type":"Point"}
}