{
  "type": "Feature",
  "properties": {
    "gn:admin1_code":"16.0",
    "gn:admin2_code":"2112822.0",
    "gn:asciiname":"Kakebata",
    "gn:country_code":"JP",
    "gn:dem":92,
    "gn:feature_class":"P",
    "gn:feature_code":"PPL",
    "gn:name":"Kakebata",
    "gn:population":0,
    "gn:timezone":"Asia/Tokyo",
    "iso:country":"JP",
    "name:jpn_x_preferred":[
        "\u6b20\u7aef"
    ],
    "name:jpn_x_variant":[
        "\u304b\u3051\u3070\u305f",
        "\u30ab\u30b1\u30d0\u30bf"
    ],
    "wof:name":"Kakebata",
    "wof:placetype":"locality"
},
  "geometry": {"coordinates":[141.08216000000004,39.37957],"type":"Point"}
}