{
  "type": "Feature",
  "properties": {
    "gn:admin1_code":"27.0",
    "gn:admin2_code":"1852895.0",
    "gn:asciiname":"Hirabaru",
    "gn:country_code":"JP",
    "gn:dem":64,
    "gn:feature_class":"P",
    "gn:feature_code":"PPLL",
    "gn:name":"Hirabaru",
    "gn:population":0,
    "gn:timezone":"Asia/Tokyo",
    "iso:country":"JP",
    "name:jpn_x_preferred":[
        "\u5e73\u539f"
    ],
    "wof:name":"Hirabaru",
    "wof:placetype":"locality"
},
  "geometry": {"coordinates":[129.57334,33.24671],"type":"Point"}
}