{
  "type": "Feature",
  "properties": {
    "gn:admin1_code":"4.0",
    "gn:admin2_code":"1856183.0",
    "gn:asciiname":"Furumagi",
    "gn:country_code":"JP",
    "gn:dem":23,
    "gn:feature_class":"P",
    "gn:feature_code":"PPL",
    "gn:name":"Furumagi",
    "gn:population":0,
    "gn:timezone":"Asia/Tokyo",
    "iso:country":"JP",
    "name:jpn_x_preferred":[
        "\u53e4\u9593\u6728"
    ],
    "wof:name":"Furumagi",
    "wof:placetype":"locality"
},
  "geometry": {"coordinates":[139.92552000000001,35.85615],"type":"Point"}
}