{
  "type": "Feature",
  "properties": {
    "gn:admin1_code":"7.0",
    "gn:admin2_code":"1851269.0",
    "gn:admin3_code":"40604.0",
    "gn:asciiname":"Toishi",
    "gn:country_code":"JP",
    "gn:dem":27,
    "gn:feature_class":"P",
    "gn:feature_code":"PPL",
    "gn:name":"Toishi",
    "gn:population":0,
    "gn:timezone":"Asia/Tokyo",
    "iso:country":"JP",
    "name:jpn_x_preferred":[
        "\u6238\u77f3"
    ],
    "wof:name":"Toishi",
    "wof:placetype":"locality"
},
  "geometry": {"coordinates":[130.76886000000002,33.65766],"type":"Point"}
}