{
  "type": "Feature",
  "properties": {
    "gn:admin1_code":"39",
    "gn:admin2_code":"1860803.0",
    "gn:admin3_code":"36387.0",
    "gn:asciiname":"Higashiyuki",
    "gn:country_code":"JP",
    "gn:dem":42,
    "gn:feature_class":"P",
    "gn:feature_code":"PPL",
    "gn:name":"Higashiyuki",
    "gn:population":0,
    "gn:timezone":"Asia/Tokyo",
    "iso:country":"JP",
    "name:jpn_x_preferred":[
        "\u6771\u7531\u5c90"
    ],
    "name:und_x_variant":[
        "Yuki"
    ],
    "wof:name":"Higashiyuki",
    "wof:placetype":"locality"
},
  "geometry": {"coordinates":[134.59999999999999,33.76667],"type":"Point"}
}