{
  "type": "Feature",
  "properties": {
    "gn:admin1_code":"4.0",
    "gn:admin2_code":"9062338.0",
    "gn:asciiname":"Hoge",
    "gn:country_code":"JP",
    "gn:dem":107,
    "gn:feature_class":"P",
    "gn:feature_code":"PPL",
    "gn:name":"H\u014dge",
    "gn:population":0,
    "gn:timezone":"Asia/Tokyo",
    "iso:country":"JP",
    "name:ceb_x_preferred":[
        "Hoge"
    ],
    "name:deu_x_preferred":[
        "Hoge"
    ],
    "name:jpn_x_preferred":[
        "\u6cd5\u82b1"
    ],
    "name:jpn_x_variant":[
        "\u307b\u3046\u3052",
        "\u30db\u30a6\u30b2"
    ],
    "name:und_x_variant":[
        "H\u014dge"
    ],
    "wof:name":"Hoge",
    "wof:placetype":"locality"
},
  "geometry": {"coordinates":[140.25826999999998,35.16914000000001],"type":"Point"}
}