{
  "type": "Feature",
  "properties": {
    "gn:admin1_code":"9.0",
    "gn:admin2_code":"1850890.0",
    "gn:asciiname":"Nyukawamachi-kute",
    "gn:country_code":"JP",
    "gn:dem":1183,
    "gn:feature_class":"P",
    "gn:feature_code":"PPL",
    "gn:name":"Ny\u016bkawamachi-kute",
    "gn:population":0,
    "gn:timezone":"Asia/Tokyo",
    "iso:country":"JP",
    "name:jpn_x_preferred":[
        "\u4e39\u751f\u5ddd\u753a\u4e45\u624b"
    ],
    "name:und_x_variant":[
        "Ny\u016bkawamachi-kute"
    ],
    "wof:name":"Nyukawamachi-kute",
    "wof:placetype":"locality"
},
  "geometry": {"coordinates":[137.49171000000001,36.17759],"type":"Point"}
}