{
  "type": "Feature",
  "properties": {
    "gn:admin1_code":"12.0",
    "gn:admin2_code":"2129763.0",
    "gn:admin3_code":"1334.0",
    "gn:asciiname":"Hashikure",
    "gn:country_code":"JP",
    "gn:dem":10,
    "gn:feature_class":"P",
    "gn:feature_code":"PPL",
    "gn:name":"Hashikure",
    "gn:population":0,
    "gn:timezone":"Asia/Tokyo",
    "iso:country":"JP",
    "name:jpn_x_preferred":[
        "\u6a4b\u5449"
    ],
    "name:jpn_x_variant":[
        "\u306f\u3057\u304f\u308c",
        "\u30cf\u30b7\u30af\u30ec"
    ],
    "wof:name":"Hashikure",
    "wof:placetype":"locality"
},
  "geometry": {"coordinates":[140.49492000000001,41.70185],"type":"Point"}
}