{
  "type": "Feature",
  "properties": {
    "gn:admin1_code":"23.0",
    "gn:admin2_code":"1859297.0",
    "gn:admin3_code":"24543.0",
    "gn:asciiname":"Kotsu",
    "gn:country_code":"JP",
    "gn:dem":34,
    "gn:feature_class":"P",
    "gn:feature_code":"PPL",
    "gn:name":"Kotsu",
    "gn:population":0,
    "gn:timezone":"Asia/Tokyo",
    "iso:country":"JP",
    "name:jpn_x_preferred":[
        "\u6728\u6d25"
    ],
    "wof:name":"Kotsu",
    "wof:placetype":"locality"
},
  "geometry": {"coordinates":[136.18143999999998,34.11425999999999],"type":"Point"}
}