{
  "type": "Feature",
  "properties": {
    "gn:admin1_code":"33.0",
    "gn:admin2_code":"1853274.0",
    "gn:asciiname":"Fujicho-osoegawa",
    "gn:country_code":"JP",
    "gn:dem":120,
    "gn:feature_class":"P",
    "gn:feature_code":"PPL",
    "gn:name":"Fujich\u014d-osoegawa",
    "gn:population":0,
    "gn:timezone":"Asia/Tokyo",
    "iso:country":"JP",
    "name:jpn_x_preferred":[
        "\u5bcc\u58eb\u753a\u5c0f\u526f\u5ddd"
    ],
    "name:und_x_variant":[
        "Fujich\u014d-osoegawa"
    ],
    "wof:name":"Fujicho-osoegawa",
    "wof:placetype":"locality"
},
  "geometry": {"coordinates":[130.23466999999999,33.36638],"type":"Point"}
}