{
  "type": "Feature",
  "properties": {
    "gn:admin1_code":"19.0",
    "gn:admin2_code":"1864091.0",
    "gn:asciiname":"Ichinotsubo",
    "gn:country_code":"JP",
    "gn:dem":31,
    "gn:feature_class":"P",
    "gn:feature_code":"PPLL",
    "gn:name":"Ichinotsubo",
    "gn:population":0,
    "gn:timezone":"Asia/Tokyo",
    "iso:country":"JP",
    "name:jpn_x_preferred":[
        "\u4e00\u30ce\u576a"
    ],
    "wof:name":"Ichinotsubo",
    "wof:placetype":"locality"
},
  "geometry": {"coordinates":[139.44756000000001,35.37141],"type":"Point"}
}