{
  "type": "Feature",
  "properties": {
    "gn:admin1_code":"18.0",
    "gn:admin2_code":"1853737.0",
    "gn:admin3_code":"46525.0",
    "gn:asciiname":"Kanyu",
    "gn:country_code":"JP",
    "gn:dem":6,
    "gn:feature_class":"P",
    "gn:feature_code":"PPL",
    "gn:name":"Kany\u016b",
    "gn:population":0,
    "gn:timezone":"Asia/Tokyo",
    "iso:country":"JP",
    "name:jpn_x_preferred":[
        "\u5609\u5165"
    ],
    "name:und_x_variant":[
        "Kany\u016b"
    ],
    "wof:name":"Kanyu",
    "wof:placetype":"locality"
},
  "geometry": {"coordinates":[129.22038000000001,28.14143],"type":"Point"}
}