{
  "type": "Feature",
  "properties": {
    "iso:country":"JP",
    "name:eng_x_preferred":[
        "Nagashima 1 Chome"
    ],
    "name:eng_x_variant":[
        "Nagashima 1 Choume",
        "Nagashima 1 Chome"
    ],
    "name:jpn_x_preferred":[
        "\uff11\u4e01\u76ee"
    ],
    "name:jpn_x_variant":[
        "\u306a\u304c\u3057\u307e \uff11\u3061\u3087\u3046\u3081",
        "\u9577\u5cf6 \uff11\u4e01\u76ee",
        "\uff11\u3061\u3087\u3046\u3081"
    ],
    "qs:gn_local":0,
    "qs:local_max":933,
    "qs:local_sum":1431,
    "qs:localhoods":7,
    "qs:name":"\uff11\u4e01\u76ee",
    "qs:name_adm0":"\u65e5\u672c",
    "qs:name_adm1":"\u9752\u68ee\u770c",
    "qs:name_en":"Nagashima 1 Chome",
    "qs:name_lau":"\u9577\u5cf6",
    "qs:name_local":"\u9752\u68ee\u5e02",
    "qs:photo_max":67,
    "qs:photo_sum":127,
    "qs:placetype":"Suburb",
    "qs:quad_count":4,
    "qs:woe_adm0":23424856,
    "qs:woe_adm1":2345853,
    "qs:woe_adm2":0,
    "qs:woe_lau":1112360,
    "qs:woe_local":1116973,
    "qs:woe_ver":"7.10.0",
    "qs_pg:name":"\uff11\u4e01\u76ee",
    "qs_pg:name_adm0":"\u65e5\u672c",
    "qs_pg:name_adm1":"\u9752\u68ee\u770c",
    "qs_pg:photos":39,
    "qs_pg:photos_1k":8,
    "qs_pg:photos_9k":1,
    "qs_pg:photos_9r":2,
    "qs_pg:photos_all":39,
    "qs_pg:photos_sr":2,
    "qs_pg:pop_sr":0,
    "qs_pg:qs_pg_placetype":"neighbourhood",
    "qs_pg:qs_pg_placetype_gp":"Suburb",
    "qs_pg:woe_adm0":23424856,
    "woe:adm0_id":23424856,
    "woe:name_adm0":"\u65e5\u672c",
    "woe:name_adm1":"\u9752\u68ee\u770c",
    "woe:placetype":"Suburb",
    "wof:lang":[
        "jpn"
    ],
    "wof:name":"\uff11\u4e01\u76ee",
    "wof:placetype":"neighbourhood"
},
  "geometry": {"coordinates":[140.74354099999999,40.824816],"type":"Point"}
}