{
  "type": "Feature",
  "properties": {
    "gn:admin1_code":"23.0",
    "gn:admin2_code":"1857496.0",
    "gn:asciiname":"Fukano",
    "gn:country_code":"JP",
    "gn:dem":218,
    "gn:feature_class":"P",
    "gn:feature_code":"PPLL",
    "gn:name":"Fukano",
    "gn:population":0,
    "gn:timezone":"Asia/Tokyo",
    "iso:country":"JP",
    "name:jpn_x_preferred":[
        "\u6df1\u91ce"
    ],
    "wof:name":"Fukano",
    "wof:placetype":"locality"
},
  "geometry": {"coordinates":[136.21902,34.39733],"type":"Point"}
}