{
  "type": "Feature",
  "properties": {
    "gn:admin1_code":"37",
    "gn:admin2_code":"1864104.0",
    "gn:asciiname":"Nakaide",
    "gn:country_code":"JP",
    "gn:dem":430,
    "gn:feature_class":"P",
    "gn:feature_code":"PPL",
    "gn:name":"Nakaide",
    "gn:population":0,
    "gn:timezone":"Asia/Tokyo",
    "iso:country":"JP",
    "name:jpn_x_preferred":[
        "\u4e2d\u4e95\u51fa"
    ],
    "name:und_x_variant":[
        "Kami-ide",
        "Naka-ide",
        "Nakaide"
    ],
    "wof:name":"Nakaide",
    "wof:placetype":"locality"
},
  "geometry": {"coordinates":[138.59443000000002,35.29831],"type":"Point"}
}