{
  "type": "Feature",
  "properties": {
    "gn:country":"JP",
    "iso:country":"JP",
    "name:jpn_x_preferred":[
        "\uff08\u4e01\u76ee\u306a\u3057\uff09"
    ],
    "name:unk_x_variant":[
        "\uff08\u4e01\u76ee\u306a\u3057\uff09"
    ],
    "qs:gn_adm0_cc":"JP",
    "qs:gn_local":1858311,
    "qs:gn_nam_loc":"\u5009\u6577\u5e02, \u5ca1\u5c71\u770c, JP",
    "qs:gn_namadm1":"31",
    "qs:local_max":585,
    "qs:local_sum":2198,
    "qs:localhoods":12,
    "qs:name":"\uff08\u4e01\u76ee\u306a\u3057\uff09",
    "qs:name_adm0":"\u65e5\u672c",
    "qs:name_adm1":"\u5ca1\u5c71\u770c",
    "qs:photos":11,
    "qs:photos_1k":2,
    "qs:photos_9k":1,
    "qs:photos_9r":1,
    "qs:photos_all":11,
    "qs:photos_sr":1,
    "qs:placetype":"Suburb",
    "qs:pop_sr":"0",
    "qs:quad_count":11,
    "qs:woe_adm0":23424856,
    "qs:woe_adm1":2345880,
    "qs:woe_adm2":0,
    "qs:woe_lau":28472096,
    "qs:woe_local":1117618,
    "qs:woe_ver":"7.10.0",
    "wof:lang":[
        "jpn"
    ],
    "wof:name":"\uff08\u4e01\u76ee\u306a\u3057\uff09",
    "wof:placetype":"neighbourhood"
},
  "geometry": {"coordinates":[133.812872,34.434386],"type":"Point"}
}