{
  "type": "Feature",
  "properties": {
    "gn:admin1_code":"40.0",
    "gn:admin2_code":"1864514.0",
    "gn:asciiname":"Kamiishiwara",
    "gn:country_code":"JP",
    "gn:dem":41,
    "gn:feature_class":"P",
    "gn:feature_code":"PPL",
    "gn:name":"Kamiishiwara",
    "gn:population":0,
    "gn:timezone":"Asia/Tokyo",
    "iso:country":"JP",
    "name:jpn_x_preferred":[
        "\u4e0a\u77f3\u539f"
    ],
    "wof:name":"Kamiishiwara",
    "wof:placetype":"locality"
},
  "geometry": {"coordinates":[139.52841000000001,35.65527],"type":"Point"}
}