{
  "type": "Feature",
  "properties": {
    "gn:admin1_code":"21.0",
    "gn:admin2_code":"1849062.0",
    "gn:asciiname":"Shinmemachi",
    "gn:country_code":"JP",
    "gn:dem":1,
    "gn:feature_class":"P",
    "gn:feature_code":"PPL",
    "gn:name":"Shinmemachi",
    "gn:population":0,
    "gn:timezone":"Asia/Tokyo",
    "iso:country":"JP",
    "name:jpn_x_preferred":[
        "\u795e\u99ac\u753a"
    ],
    "name:jpn_x_variant":[
        "\u3057\u3093\u3081\u307e\u3061",
        "\u30b7\u30f3\u30e1\u30de\u30c1"
    ],
    "wof:name":"Shinmemachi",
    "wof:placetype":"locality"
},
  "geometry": {"coordinates":[130.65128000000001,32.67756],"type":"Point"}
}