{
  "type": "Feature",
  "properties": {
    "gn:admin1_code":"28.0",
    "gn:admin2_code":"1848164.0",
    "gn:admin3_code":"29452.0",
    "gn:asciiname":"Obatani",
    "gn:country_code":"JP",
    "gn:dem":478,
    "gn:feature_class":"P",
    "gn:feature_code":"PPL",
    "gn:name":"Obatani",
    "gn:population":0,
    "gn:timezone":"Asia/Tokyo",
    "iso:country":"JP",
    "name:jbn_x_preferred":[
        "Obatani"
    ],
    "name:jpn_x_preferred":[
        "\u4f2f\u6bcd\u8c37"
    ],
    "wof:name":"Obatani",
    "wof:placetype":"locality"
},
  "geometry": {"coordinates":[136.00611000000001,34.26605],"type":"Point"}
}