{
  "type": "Feature",
  "properties": {
    "iso:country":"JP",
    "name:eng_x_preferred":[
        "Kawakami 1 Chome"
    ],
    "name:eng_x_variant":[
        "Kawakami 1 Choume",
        "Kawakami 1 Chome"
    ],
    "name:jpn_x_preferred":[
        "\uff11\u4e01\u76ee"
    ],
    "name:jpn_x_variant":[
        "\u304b\u308f\u304b\u307f \uff11\u3061\u3087\u3046\u3081",
        "\u5ddd\u4e0a \uff11\u4e01\u76ee",
        "\uff11\u3061\u3087\u3046\u3081"
    ],
    "qs:gn_local":0,
    "qs:local_max":455,
    "qs:local_sum":564,
    "qs:localhoods":3,
    "qs:name":"\uff11\u4e01\u76ee",
    "qs:name_adm0":"\u65e5\u672c",
    "qs:name_adm1":"\u4e09\u91cd\u770c",
    "qs:name_en":"Kawakami 1 Chome",
    "qs:name_lau":"\u5ddd\u4e0a",
    "qs:name_local":"\u4f0a\u8cc0\u5e02",
    "qs:photo_max":32,
    "qs:photo_sum":66,
    "qs:placetype":"Suburb",
    "qs:quad_count":4,
    "qs:woe_adm0":23424856,
    "qs:woe_adm1":2345872,
    "qs:woe_adm2":0,
    "qs:woe_lau":28447447,
    "qs:woe_local":28379365,
    "qs:woe_ver":"7.10.0",
    "wof:lang":[
        "jpn"
    ],
    "wof:name":"\uff11\u4e01\u76ee",
    "wof:placetype":"neighbourhood"
},
  "geometry": {"coordinates":[136.18067199999999,34.680224],"type":"Point"}
}