{
  "type": "Feature",
  "properties": {
    "gn:admin1_code":"9.0",
    "gn:admin2_code":"7418820.0",
    "gn:admin3_code":"21604.0",
    "gn:asciiname":"Kazura",
    "gn:country_code":"JP",
    "gn:dem":536,
    "gn:feature_class":"P",
    "gn:feature_code":"PPL",
    "gn:name":"Kazura",
    "gn:population":0,
    "gn:timezone":"Asia/Tokyo",
    "iso:country":"JP",
    "name:jpn_x_preferred":[
        "\u52a0\u9808\u826f"
    ],
    "wof:name":"Kazura",
    "wof:placetype":"locality"
},
  "geometry": {"coordinates":[136.84639000000001,36.32592],"type":"Point"}
}