{
  "type": "Feature",
  "properties": {
    "gn:admin1_code":"21.0",
    "gn:admin2_code":"1865358.0",
    "gn:asciiname":"Kagebayashi",
    "gn:country_code":"JP",
    "gn:dem":323,
    "gn:feature_class":"P",
    "gn:feature_code":"PPLL",
    "gn:name":"Kagebayashi",
    "gn:population":0,
    "gn:timezone":"Asia/Tokyo",
    "iso:country":"JP",
    "name:jpn_x_preferred":[
        "\u852d\u6797"
    ],
    "name:jpn_x_variant":[
        "\u304b\u3052\u3070\u3084\u3057",
        "\u30ab\u30b2\u30d0\u30e4\u30b7"
    ],
    "wof:name":"Kagebayashi",
    "wof:placetype":"locality"
},
  "geometry": {"coordinates":[130.08840000000001,32.46301],"type":"Point"}
}