{
  "type": "Feature",
  "properties": {
    "gn:admin1_code":"13.0",
    "gn:admin2_code":"7370813.0",
    "gn:asciiname":"Tokura",
    "gn:country_code":"JP",
    "gn:dem":209,
    "gn:feature_class":"P",
    "gn:feature_code":"PPL",
    "gn:name":"Tokura",
    "gn:population":0,
    "gn:timezone":"Asia/Tokyo",
    "iso:country":"JP",
    "name:jpn_x_preferred":[
        "\u5341\u5009"
    ],
    "wof:name":"Tokura",
    "wof:placetype":"locality"
},
  "geometry": {"coordinates":[135.27536000000001,34.96692],"type":"Point"}
}