{
  "type": "Feature",
  "properties": {
    "gn:admin1_code":"19.0",
    "gn:admin2_code":"1863429.0",
    "gn:asciiname":"Kobara",
    "gn:country_code":"JP",
    "gn:dem":208,
    "gn:feature_class":"P",
    "gn:feature_code":"PPLL",
    "gn:name":"Kobara",
    "gn:population":0,
    "gn:timezone":"Asia/Tokyo",
    "iso:country":"JP",
    "name:jpn_x_preferred":[
        "\u5c0f\u539f"
    ],
    "wof:name":"Kobara",
    "wof:placetype":"locality"
},
  "geometry": {"coordinates":[139.20218,35.36165],"type":"Point"}
}