{
  "type": "Feature",
  "properties": {
    "gn:admin1_code":"4.0",
    "gn:admin2_code":"9062338.0",
    "gn:asciiname":"Konta",
    "gn:country_code":"JP",
    "gn:dem":125,
    "gn:feature_class":"P",
    "gn:feature_code":"PPLL",
    "gn:name":"Konta",
    "gn:population":0,
    "gn:timezone":"Asia/Tokyo",
    "iso:country":"JP",
    "name:jpn_x_preferred":[
        "\u53e4\u65b0\u7530"
    ],
    "name:jpn_x_variant":[
        "\u3053\u3093\u305f",
        "\u30b3\u30f3\u30bf"
    ],
    "wof:name":"Konta",
    "wof:placetype":"locality"
},
  "geometry": {"coordinates":[140.22203000000002,35.16004],"type":"Point"}
}