{
  "type": "Feature",
  "properties": {
    "gn:admin1_code":"7.0",
    "gn:admin2_code":"1859306.0",
    "gn:admin3_code":"40106.0",
    "gn:asciiname":"Takamidai",
    "gn:country_code":"JP",
    "gn:dem":8,
    "gn:feature_class":"P",
    "gn:feature_code":"PPL",
    "gn:name":"Takamidai",
    "gn:population":0,
    "gn:timezone":"Asia/Tokyo",
    "iso:country":"JP",
    "name:jpn_x_preferred":[
        "\u9ad8\u898b\u53f0"
    ],
    "wof:name":"Takamidai",
    "wof:placetype":"locality"
},
  "geometry": {"coordinates":[130.85480000000001,33.89519],"type":"Point"}
}