{
  "type": "Feature",
  "properties": {
    "gn:admin1_code":"4.0",
    "gn:admin2_code":"1863711.0",
    "gn:asciiname":"Sotohosoda",
    "gn:country_code":"JP",
    "gn:dem":7,
    "gn:feature_class":"P",
    "gn:feature_code":"PPLL",
    "gn:name":"Sotohosoda",
    "gn:population":0,
    "gn:timezone":"Asia/Tokyo",
    "iso:country":"JP",
    "name:jpn_x_preferred":[
        "\u5916\u7d30\u7530"
    ],
    "name:jpn_x_variant":[
        "\u305d\u3068\u307b\u305d\u3060",
        "\u30bd\u30c8\u30db\u30bd\u30c0"
    ],
    "wof:name":"Sotohosoda",
    "wof:placetype":"locality"
},
  "geometry": {"coordinates":[139.85453999999999,35.28521],"type":"Point"}
}