{
  "type": "Feature",
  "properties": {
    "gn:admin1_code":"21.0",
    "gn:admin2_code":"7413150.0",
    "gn:asciiname":"Shimomachi",
    "gn:country_code":"JP",
    "gn:dem":23,
    "gn:feature_class":"P",
    "gn:feature_code":"PPLL",
    "gn:name":"Shimomachi",
    "gn:population":0,
    "gn:timezone":"Asia/Tokyo",
    "iso:country":"JP",
    "name:jpn_x_preferred":[
        "\u4e0b\u753a"
    ],
    "name:jpn_x_variant":[
        "\u3057\u3082\u307e\u3061",
        "\u30b7\u30e2\u30de\u30c1"
    ],
    "wof:name":"Shimomachi",
    "wof:placetype":"locality"
},
  "geometry": {"coordinates":[130.68944999999999,33.01116],"type":"Point"}
}