{
  "type": "Feature",
  "properties": {
    "gn:admin1_code":"24.0",
    "gn:admin2_code":"2112261.0",
    "gn:asciiname":"Motoyoshicho-hikado",
    "gn:country_code":"JP",
    "gn:dem":12,
    "gn:feature_class":"P",
    "gn:feature_code":"PPL",
    "gn:name":"Motoyoshich\u014d-hikado",
    "gn:population":0,
    "gn:timezone":"Asia/Tokyo",
    "iso:country":"JP",
    "name:jpn_x_preferred":[
        "\u672c\u5409\u753a\u65e5\u9580"
    ],
    "name:und_x_variant":[
        "Motoyoshich\u014d-hikado",
        "Hikado"
    ],
    "wof:name":"Motoyoshicho-hikado",
    "wof:placetype":"locality"
},
  "geometry": {"coordinates":[141.55428000000001,38.80937],"type":"Point"}
}