{
  "type": "Feature",
  "properties": {
    "gn:admin1_code":"44",
    "gn:admin2_code":"1853136.0",
    "gn:asciiname":"Miyauchi",
    "gn:country_code":"JP",
    "gn:dem":10,
    "gn:feature_class":"P",
    "gn:feature_code":"PPL",
    "gn:name":"Miyauchi",
    "gn:population":0,
    "gn:timezone":"Asia/Tokyo",
    "iso:country":"JP",
    "name:jpn_x_preferred":[
        "\u5bae\u5185"
    ],
    "wof:name":"Miyauchi",
    "wof:placetype":"locality"
},
  "geometry": {"coordinates":[139.88928999999999,38.98944],"type":"Point"}
}