{
  "type": "Feature",
  "properties": {
    "gn:admin1_code":"21.0",
    "gn:admin2_code":"1865358.0",
    "gn:asciiname":"Itanokawachi",
    "gn:country_code":"JP",
    "gn:dem":116,
    "gn:feature_class":"P",
    "gn:feature_code":"PPLL",
    "gn:name":"Itanokawachi",
    "gn:population":0,
    "gn:timezone":"Asia/Tokyo",
    "iso:country":"JP",
    "name:jpn_x_preferred":[
        "\u677f\u4e4b\u6cb3\u5185"
    ],
    "name:jpn_x_variant":[
        "\u3044\u305f\u306e\u304b\u308f\u3061",
        "\u30a4\u30bf\u30ce\u30ab\u30ef\u30c1"
    ],
    "wof:name":"Itanokawachi",
    "wof:placetype":"locality"
},
  "geometry": {"coordinates":[130.07789,32.37719],"type":"Point"}
}