{
  "type": "Feature",
  "properties": {
    "gn:admin1_code":"10",
    "gn:admin2_code":"1852593.0",
    "gn:asciiname":"Ikahomachi-ikaho",
    "gn:country_code":"JP",
    "gn:dem":655,
    "gn:feature_class":"P",
    "gn:feature_code":"PPL",
    "gn:name":"Ikahomachi-ikaho",
    "gn:population":0,
    "gn:timezone":"Asia/Tokyo",
    "iso:country":"JP",
    "name:ces_x_preferred":[
        "Ikaho"
    ],
    "name:deu_x_preferred":[
        "Ikaho"
    ],
    "name:jpn_x_preferred":[
        "\u4f0a\u9999\u4fdd\u753a\u4f0a\u9999\u4fdd"
    ],
    "name:jpn_x_variant":[
        "\u4f0a\u9999\u4fdd\u753a"
    ],
    "name:und_x_variant":[
        "Ikao",
        "Ikaho",
        "Ikahomachi-ikaho"
    ],
    "wof:name":"Ikahomachi-ikaho",
    "wof:placetype":"locality"
},
  "geometry": {"coordinates":[138.92293000000001,36.50268],"type":"Point"}
}