{
  "type": "Feature",
  "properties": {
    "iso:country":"JP",
    "name:eng_x_preferred":[
        "Chiyagawa 2 Chome"
    ],
    "name:eng_x_variant":[
        "Chiyagawa 2 Choume",
        "Chiyagawa 2 Chome"
    ],
    "name:jpn_x_preferred":[
        "\uff12\u4e01\u76ee"
    ],
    "name:jpn_x_variant":[
        "\u3061\u3084\u304c\u308f \uff12\u3061\u3087\u3046\u3081",
        "\u5343\u8c37\u5ddd \uff12\u4e01\u76ee",
        "\uff12\u3061\u3087\u3046\u3081"
    ],
    "qs:gn_local":0,
    "qs:local_max":13,
    "qs:local_sum":13,
    "qs:localhoods":1,
    "qs:name":"\uff12\u4e01\u76ee",
    "qs:name_adm0":"\u65e5\u672c",
    "qs:name_adm1":"\u65b0\u6f5f\u770c",
    "qs:name_en":"Chiyagawa 2 Chome",
    "qs:name_lau":"\u5343\u8c37\u5ddd",
    "qs:name_local":"\u5c0f\u5343\u8c37\u5e02",
    "qs:photo_max":13,
    "qs:photo_sum":13,
    "qs:placetype":"Suburb",
    "qs:quad_count":1,
    "qs:woe_adm0":23424856,
    "qs:woe_adm1":2345878,
    "qs:woe_adm2":0,
    "qs:woe_lau":28419817,
    "qs:woe_local":1117960,
    "qs:woe_ver":"7.10.0",
    "wof:lang":[
        "jpn"
    ],
    "wof:name":"\uff12\u4e01\u76ee",
    "wof:placetype":"neighbourhood"
},
  "geometry": {"coordinates":[138.79852299999999,37.315567],"type":"Point"}
}