{
  "type": "Feature",
  "properties": {
    "gn:admin1_code":"44.0",
    "gn:admin2_code":"2111245.0",
    "gn:asciiname":"Jionji",
    "gn:country_code":"JP",
    "gn:dem":122,
    "gn:feature_class":"P",
    "gn:feature_code":"PPL",
    "gn:name":"Jionji",
    "gn:population":0,
    "gn:timezone":"Asia/Tokyo",
    "iso:country":"JP",
    "name:jpn_x_preferred":[
        "\u6148\u6069\u5bfa"
    ],
    "wof:name":"Jionji",
    "wof:placetype":"locality"
},
  "geometry": {"coordinates":[140.24931999999998,38.40622000000001],"type":"Point"}
}