{
  "type": "Feature",
  "properties": {
    "gn:admin1_code":"21.0",
    "gn:admin2_code":"7413151.0",
    "gn:asciiname":"Himedomachi-himeura",
    "gn:country_code":"JP",
    "gn:dem":66,
    "gn:feature_class":"P",
    "gn:feature_code":"PPL",
    "gn:name":"Himedomachi-himeura",
    "gn:population":0,
    "gn:timezone":"Asia/Tokyo",
    "iso:country":"JP",
    "name:jpn_x_preferred":[
        "\u59eb\u6238\u753a\u59eb\u6d66"
    ],
    "name:jpn_x_variant":[
        "\u3072\u3081\u3069\u307e\u3061\u3072\u3081\u3046\u3089",
        "\u30d2\u30e1\u30c9\u30de\u30c1\u30d2\u30e1\u30a6\u30e9"
    ],
    "wof:name":"Himedomachi-himeura",
    "wof:placetype":"locality"
},
  "geometry": {"coordinates":[130.40688,32.44492],"type":"Point"}
}