{
  "type": "Feature",
  "properties": {
    "gn:admin1_code":"23",
    "gn:admin2_code":"7417711.0",
    "gn:asciiname":"Sekicho-furumaya",
    "gn:country_code":"JP",
    "gn:dem":73,
    "gn:feature_class":"P",
    "gn:feature_code":"PPL",
    "gn:name":"Sekich\u014d-furumaya",
    "gn:population":0,
    "gn:timezone":"Asia/Tokyo",
    "iso:country":"JP",
    "name:fas_x_preferred":[
        "\u0633\u06a9\u06cc"
    ],
    "name:jpn_x_preferred":[
        "\u95a2\u753a\u53e4\u53a9"
    ],
    "name:und_x_variant":[
        "Seki",
        "Sekich\u014d-furumaya"
    ],
    "wof:name":"Sekicho-furumaya",
    "wof:placetype":"locality"
},
  "geometry": {"coordinates":[136.40000000000001,34.85],"type":"Point"}
}