{
  "type": "Feature",
  "properties": {
    "gn:admin1_code":"33.0",
    "gn:admin2_code":"1853274.0",
    "gn:asciiname":"Nabeshimamachi-morita",
    "gn:country_code":"JP",
    "gn:dem":4,
    "gn:feature_class":"P",
    "gn:feature_code":"PPL",
    "gn:name":"Nabeshimamachi-morita",
    "gn:population":0,
    "gn:timezone":"Asia/Tokyo",
    "iso:country":"JP",
    "name:jpn_x_preferred":[
        "\u934b\u5cf6\u753a\u68ee\u7530"
    ],
    "wof:name":"Nabeshimamachi-morita",
    "wof:placetype":"locality"
},
  "geometry": {"coordinates":[130.25824,33.2746],"type":"Point"}
}