{
  "type": "Feature",
  "properties": {
    "gn:admin1_code":"12.0",
    "gn:admin2_code":"7428097.0",
    "gn:admin3_code":"1643.0",
    "gn:asciiname":"Goi",
    "gn:country_code":"JP",
    "gn:dem":149,
    "gn:feature_class":"P",
    "gn:feature_code":"PPL",
    "gn:name":"Goi",
    "gn:population":0,
    "gn:timezone":"Asia/Tokyo",
    "iso:country":"JP",
    "name:jpn_x_preferred":[
        "\u4e94\u4f4d"
    ],
    "name:jpn_x_variant":[
        "\u3054\u3044",
        "\u30b4\u30a4"
    ],
    "wof:name":"Goi",
    "wof:placetype":"locality"
},
  "geometry": {"coordinates":[143.34017,42.77044],"type":"Point"}
}