{
  "type": "Feature",
  "properties": {
    "gn:admin1_code":"14.0",
    "gn:admin2_code":"7452677.0",
    "gn:asciiname":"Shimoyahagi",
    "gn:country_code":"JP",
    "gn:dem":24,
    "gn:feature_class":"P",
    "gn:feature_code":"PPLL",
    "gn:name":"Shimoyahagi",
    "gn:population":0,
    "gn:timezone":"Asia/Tokyo",
    "iso:country":"JP",
    "name:jpn_x_preferred":[
        "\u4e0b\u77e2\u4f5c"
    ],
    "name:jpn_x_variant":[
        "\u3057\u3082\u3084\u306f\u304e"
    ],
    "wof:name":"Shimoyahagi",
    "wof:placetype":"locality"
},
  "geometry": {"coordinates":[139.91203000000002,35.9957],"type":"Point"}
}