{
  "type": "Feature",
  "properties": {
    "gn:admin1_code":"27.0",
    "gn:admin2_code":"1859301.0",
    "gn:admin3_code":"42391.0",
    "gn:asciiname":"Erimen",
    "gn:country_code":"JP",
    "gn:dem":167,
    "gn:feature_class":"P",
    "gn:feature_code":"PPL",
    "gn:name":"Erimen",
    "gn:population":0,
    "gn:timezone":"Asia/Tokyo",
    "iso:country":"JP",
    "name:jpn_x_preferred":[
        "\u6c5f\u91cc\u514d"
    ],
    "wof:name":"Erimen",
    "wof:placetype":"locality"
},
  "geometry": {"coordinates":[129.65138000000002,33.2698],"type":"Point"}
}