{
  "type": "Feature",
  "properties": {
    "gn:admin1_code":"19",
    "gn:admin2_code":"1865009.0",
    "gn:admin3_code":"14382.0",
    "gn:asciiname":"Ashinoyu",
    "gn:country_code":"JP",
    "gn:dem":993,
    "gn:feature_class":"P",
    "gn:feature_code":"PPL",
    "gn:name":"Ashinoyu",
    "gn:population":0,
    "gn:timezone":"Asia/Tokyo",
    "iso:country":"JP",
    "name:jpn_x_preferred":[
        "\u82a6\u4e4b\u6e6f"
    ],
    "wof:name":"Ashinoyu",
    "wof:placetype":"locality"
},
  "geometry": {"coordinates":[139.03888999999998,35.22139],"type":"Point"}
}