{
  "type": "Feature",
  "properties": {
    "gn:admin1_code":"27",
    "gn:admin2_code":"7418804.0",
    "gn:asciiname":"Miirakumachi-ushinoura",
    "gn:country_code":"JP",
    "gn:dem":14,
    "gn:feature_class":"P",
    "gn:feature_code":"PPL",
    "gn:name":"Miirakumachi-ushinoura",
    "gn:population":0,
    "gn:timezone":"Asia/Tokyo",
    "iso:country":"JP",
    "name:jpn_x_preferred":[
        "\u4e09\u4e95\u697d\u753a\u4e11\u30ce\u6d66"
    ],
    "name:und_x_variant":[
        "Ushinoura"
    ],
    "wof:name":"Miirakumachi-ushinoura",
    "wof:placetype":"locality"
},
  "geometry": {"coordinates":[128.64973999999998,32.75302],"type":"Point"}
}