{
  "type": "Feature",
  "properties": {
    "gn:admin1_code":"39",
    "gn:admin2_code":"1864902.0",
    "gn:asciiname":"Yoshinocho-saijo",
    "gn:country_code":"JP",
    "gn:dem":16,
    "gn:feature_class":"P",
    "gn:feature_code":"PPL",
    "gn:name":"Yoshinoch\u014d-saij\u014d",
    "gn:population":0,
    "gn:timezone":"Asia/Tokyo",
    "iso:country":"JP",
    "name:jpn_x_preferred":[
        "\u5409\u91ce\u753a\u897f\u6761"
    ],
    "name:und_x_variant":[
        "Yoshinoch\u014d-saij\u014d",
        "Saij\u014d"
    ],
    "wof:name":"Yoshinocho-saijo",
    "wof:placetype":"locality"
},
  "geometry": {"coordinates":[134.38317000000001,34.10193],"type":"Point"}
}