{
  "type": "Feature",
  "properties": {
    "gn:admin1_code":"43.0",
    "gn:admin2_code":"1861287.0",
    "gn:admin3_code":"30343.0",
    "gn:asciiname":"Nakakosawa",
    "gn:country_code":"JP",
    "gn:dem":163,
    "gn:feature_class":"P",
    "gn:feature_code":"PPL",
    "gn:name":"Nakakosawa",
    "gn:population":0,
    "gn:timezone":"Asia/Tokyo",
    "iso:country":"JP",
    "name:jpn_x_preferred":[
        "\u4e2d\u53e4\u6ca2"
    ],
    "wof:name":"Nakakosawa",
    "wof:placetype":"locality"
},
  "geometry": {"coordinates":[135.55056000000002,34.26223],"type":"Point"}
}