{
  "type": "Feature",
  "properties": {
    "iso:country":"JP",
    "qs:name":"\u798f\u6d25\u5e02",
    "qs:name_adm0":"\u65e5\u672c",
    "qs:name_adm1":"\u798f\u5ca1\u770c",
    "qs:photos":354,
    "qs:photos_1k":72,
    "qs:photos_9k":6,
    "qs:photos_9r":7,
    "qs:photos_all":1310,
    "qs:photos_sr":6,
    "qs:placetype":"Town",
    "qs:pop_sr":"0",
    "wof:name":"\u798f\u6d25\u5e02",
    "wof:placetype":"locality"
},
  "geometry": {"coordinates":[130.49131800000001,33.760882],"type":"Point"}
}