{
  "type": "Feature",
  "properties": {
    "gn:admin1_code":"21.0",
    "gn:admin2_code":"1857206.0",
    "gn:asciiname":"Osako",
    "gn:country_code":"JP",
    "gn:dem":49,
    "gn:feature_class":"P",
    "gn:feature_code":"PPLL",
    "gn:name":"\u014csako",
    "gn:population":0,
    "gn:timezone":"Asia/Tokyo",
    "iso:country":"JP",
    "name:jpn_x_preferred":[
        "\u5927\u8feb"
    ],
    "name:jpn_x_variant":[
        "\u304a\u304a\u3055\u3053",
        "\u30aa\u30aa\u30b5\u30b3"
    ],
    "name:und_x_variant":[
        "\u014csako"
    ],
    "wof:name":"Osako",
    "wof:placetype":"locality"
},
  "geometry": {"coordinates":[130.42869999999999,32.21863],"type":"Point"}
}