{
  "type": "Feature",
  "properties": {
    "gn:admin1_code":"7.0",
    "gn:admin2_code":"1864588.0",
    "gn:admin3_code":"40647.0",
    "gn:asciiname":"Kamikoraku",
    "gn:country_code":"JP",
    "gn:dem":80,
    "gn:feature_class":"P",
    "gn:feature_code":"PPL",
    "gn:name":"Kamik\u014draku",
    "gn:population":0,
    "gn:timezone":"Asia/Tokyo",
    "iso:country":"JP",
    "name:jpn_x_preferred":[
        "\u4e0a\u9999\u697d"
    ],
    "name:und_x_variant":[
        "Kamik\u014draku"
    ],
    "wof:name":"Kamikoraku",
    "wof:placetype":"locality"
},
  "geometry": {"coordinates":[130.99889999999999,33.6317],"type":"Point"}
}