{
  "type": "Feature",
  "properties": {
    "gn:admin1_code":"32",
    "gn:admin2_code":"1853897.0",
    "gn:admin3_code":"27125.0",
    "gn:asciiname":"Hirabayashi-minami",
    "gn:country_code":"JP",
    "gn:dem":2,
    "gn:feature_class":"P",
    "gn:feature_code":"PPL",
    "gn:name":"Hirabayashi-minami",
    "gn:population":0,
    "gn:timezone":"Asia/Tokyo",
    "iso:country":"JP",
    "name:jpn_x_preferred":[
        "\u5e73\u6797\u5357"
    ],
    "name:und_x_variant":[
        "Hirabayashi-minaminoch\u014d"
    ],
    "wof:name":"Hirabayashi-minami",
    "wof:placetype":"locality"
},
  "geometry": {"coordinates":[135.45577,34.61308],"type":"Point"}
}