{
  "type": "Feature",
  "properties": {
    "iso:country":"JP",
    "label:eng_x_preferred_longname":[
        "Naka Town"
    ],
    "label:eng_x_preferred_placetype":[
        "town"
    ],
    "name:eng_x_preferred":[
        "Naka"
    ],
    "name:eng_x_variant":[
        "Naka Town"
    ],
    "name:jpn_x_preferred":[
        "\u90a3\u8cc0\u753a"
    ],
    "qs:name":"\u90a3\u8cc0\u753a",
    "qs:name_adm0":"\u65e5\u672c",
    "qs:name_adm1":"\u5fb3\u5cf6\u770c",
    "qs:photos":275,
    "qs:photos_1k":56,
    "qs:photos_9k":1,
    "qs:photos_9r":4,
    "qs:photos_all":275,
    "qs:photos_sr":5,
    "qs:placetype":"Town",
    "qs:pop_sr":"0",
    "wof:name":"Naka",
    "wof:placetype":"locality"
},
  "geometry": {"coordinates":[134.09235799999999,33.854947],"type":"Point"}
}