{
  "type": "Feature",
  "properties": {
    "gn:admin1_code":"4.0",
    "gn:admin2_code":"2112663.0",
    "gn:asciiname":"Harada",
    "gn:country_code":"JP",
    "gn:dem":35,
    "gn:feature_class":"P",
    "gn:feature_code":"PPL",
    "gn:name":"Harada",
    "gn:population":0,
    "gn:timezone":"Asia/Tokyo",
    "iso:country":"JP",
    "name:jpn_x_preferred":[
        "\u539f\u7530"
    ],
    "name:jpn_x_variant":[
        "\u306f\u3089\u3060",
        "\u30cf\u30e9\u30c0"
    ],
    "wof:name":"Harada",
    "wof:placetype":"locality"
},
  "geometry": {"coordinates":[140.16471000000001,35.3996],"type":"Point"}
}