{
  "type": "Feature",
  "properties": {
    "gn:admin1_code":"16.0",
    "gn:admin2_code":"2128941.0",
    "gn:admin3_code":"3524.0",
    "gn:asciiname":"Miyata",
    "gn:country_code":"JP",
    "gn:dem":314,
    "gn:feature_class":"P",
    "gn:feature_code":"PPL",
    "gn:name":"Miyata",
    "gn:population":0,
    "gn:timezone":"Asia/Tokyo",
    "iso:country":"JP",
    "name:deu_x_preferred":[
        "Miyata K\u014dgy\u014d"
    ],
    "name:jpn_x_preferred":[
        "\u5bae\u7530"
    ],
    "name:jpn_x_variant":[
        "\u307f\u3084\u305f",
        "\u30df\u30e4\u30bf",
        "\u30e2\u30ea\u30bf\u5bae\u7530\u5de5\u696d"
    ],
    "name:mlg_x_preferred":[
        "Miyata"
    ],
    "name:nld_x_preferred":[
        "Miyata"
    ],
    "wof:name":"Miyata",
    "wof:placetype":"locality"
},
  "geometry": {"coordinates":[141.22935000000001,40.17688],"type":"Point"}
}