{
  "type": "Feature",
  "properties": {
    "gn:admin1_code":"37.0",
    "gn:admin2_code":"1851401.0",
    "gn:admin3_code":"22344.0",
    "gn:asciiname":"Yato",
    "gn:country_code":"JP",
    "gn:dem":324,
    "gn:feature_class":"P",
    "gn:feature_code":"PPLL",
    "gn:name":"Yato",
    "gn:population":0,
    "gn:timezone":"Asia/Tokyo",
    "iso:country":"JP",
    "name:jpn_x_preferred":[
        "\u8c37\u6238"
    ],
    "wof:name":"Yato",
    "wof:placetype":"locality"
},
  "geometry": {"coordinates":[138.97675000000001,35.35045],"type":"Point"}
}