{
  "type": "Feature",
  "properties": {
    "gn:admin1_code":"39",
    "gn:admin2_code":"7406321.0",
    "gn:admin3_code":"36468.0",
    "gn:asciiname":"Sakodo",
    "gn:cc2":"JP",
    "gn:country_code":"JP",
    "gn:dem":357,
    "gn:feature_class":"P",
    "gn:feature_code":"PPL",
    "gn:name":"Sakodo",
    "gn:population":0,
    "gn:timezone":"Asia/Tokyo",
    "iso:country":"JP",
    "name:und_x_variant":[
        "Sakoto",
        "Sakodo"
    ],
    "wof:name":"Sakodo",
    "wof:placetype":"locality"
},
  "geometry": {"coordinates":[134.01667,33.98333],"type":"Point"}
}