{
  "type": "Feature",
  "properties": {
    "gn:admin1_code":"21.0",
    "gn:admin2_code":"1848441.0",
    "gn:asciiname":"Sakamotomachi-ichinomata",
    "gn:country_code":"JP",
    "gn:dem":401,
    "gn:feature_class":"P",
    "gn:feature_code":"PPL",
    "gn:name":"Sakamotomachi-ichinomata",
    "gn:population":0,
    "gn:timezone":"Asia/Tokyo",
    "iso:country":"JP",
    "name:jpn_x_preferred":[
        "\u5742\u672c\u753a\u5e02\u30ce\u4fe3"
    ],
    "wof:name":"Sakamotomachi-ichinomata",
    "wof:placetype":"locality"
},
  "geometry": {"coordinates":[130.67327,32.36367],"type":"Point"}
}