{
  "type": "Feature",
  "properties": {
    "iso:country":"JP",
    "name:eng_x_preferred":[
        "Umedacho 4 Chome"
    ],
    "name:eng_x_variant":[
        "Umedachou 4 Choume",
        "Umedacho 4 Chome"
    ],
    "name:jpn_x_preferred":[
        "\uff14\u4e01\u76ee"
    ],
    "name:jpn_x_variant":[
        "\u3046\u3081\u3060\u3061\u3087\u3046 \uff14\u3061\u3087\u3046\u3081",
        "\u6885\u7530\u753a \uff14\u4e01\u76ee",
        "\uff14\u3061\u3087\u3046\u3081"
    ],
    "name:unk_x_variant":[
        "\uff14\u4e01\u76ee"
    ],
    "qs:gn_local":0,
    "qs:local_max":85,
    "qs:local_sum":337,
    "qs:localhoods":10,
    "qs:name":"\uff14\u4e01\u76ee",
    "qs:name_adm0":"\u65e5\u672c",
    "qs:name_adm1":"\u7fa4\u99ac\u770c",
    "qs:name_en":"Umedacho 4 Chome",
    "qs:name_lau":"\u6885\u7530\u753a",
    "qs:name_local":"\u6850\u751f\u5e02",
    "qs:photo_max":12,
    "qs:photo_sum":30,
    "qs:placetype":"Suburb",
    "qs:quad_count":5,
    "qs:woe_adm0":23424856,
    "qs:woe_adm1":2345860,
    "qs:woe_adm2":0,
    "qs:woe_lau":28406541,
    "qs:woe_local":1117523,
    "qs:woe_ver":"7.10.0",
    "wof:lang":[
        "jpn"
    ],
    "wof:name":"\uff14\u4e01\u76ee",
    "wof:placetype":"neighbourhood"
},
  "geometry": {"coordinates":[139.39544699999999,36.499038],"type":"Point"}
}