{
  "type": "Feature",
  "properties": {
    "gn:admin1_code":"44.0",
    "gn:admin2_code":"2111850.0",
    "gn:admin3_code":"6366.0",
    "gn:asciiname":"Oashizawa",
    "gn:country_code":"JP",
    "gn:dem":124,
    "gn:feature_class":"P",
    "gn:feature_code":"PPL",
    "gn:name":"\u014cashizawa",
    "gn:population":0,
    "gn:timezone":"Asia/Tokyo",
    "iso:country":"JP",
    "name:jpn_x_preferred":[
        "\u5927\u82a6\u6ca2"
    ],
    "name:und_x_variant":[
        "\u014cashizawa",
        "\u014cashisawa"
    ],
    "wof:name":"Oashizawa",
    "wof:placetype":"locality"
},
  "geometry": {"coordinates":[140.14743999999999,38.85173],"type":"Point"}
}