{
  "type": "Feature",
  "properties": {
    "iso:country":"JP",
    "label:eng_x_preferred_longname":[
        "Green city"
    ],
    "label:eng_x_preferred_placetype":[
        "city"
    ],
    "name:eng_x_preferred":[
        "Green"
    ],
    "name:eng_x_variant":[
        "Green city"
    ],
    "name:jpn_x_preferred":[
        "\u307f\u3069\u308a\u5e02"
    ],
    "qs:name":"\u307f\u3069\u308a\u5e02",
    "qs:name_adm0":"\u65e5\u672c",
    "qs:name_adm1":"\u7fa4\u99ac\u770c",
    "qs:photos":2227,
    "qs:photos_1k":451,
    "qs:photos_9k":10,
    "qs:photos_9r":9,
    "qs:photos_all":2227,
    "qs:photos_sr":16,
    "qs:placetype":"Town",
    "qs:pop_sr":"0",
    "wof:name":"Green",
    "wof:placetype":"locality"
},
  "geometry": {"coordinates":[139.28106299999999,36.435508],"type":"Point"}
}