{
  "type": "Feature",
  "properties": {
    "gn:admin1_code":"28.0",
    "gn:admin2_code":"1861747.0",
    "gn:asciiname":"Kitataharacho",
    "gn:country_code":"JP",
    "gn:dem":160,
    "gn:feature_class":"P",
    "gn:feature_code":"PPL",
    "gn:name":"Kitataharach\u014d",
    "gn:population":0,
    "gn:timezone":"Asia/Tokyo",
    "iso:country":"JP",
    "name:jpn_x_preferred":[
        "\u5317\u7530\u539f\u753a"
    ],
    "name:und_x_variant":[
        "Kitataharach\u014d"
    ],
    "wof:name":"Kitataharacho",
    "wof:placetype":"locality"
},
  "geometry": {"coordinates":[135.70668000000001,34.73137],"type":"Point"}
}