{
  "type": "Feature",
  "properties": {
    "gn:admin1_code":"24.0",
    "gn:admin2_code":"2111889.0",
    "gn:admin3_code":"4401.0",
    "gn:asciiname":"Koishihama",
    "gn:country_code":"JP",
    "gn:dem":3,
    "gn:feature_class":"P",
    "gn:feature_code":"PPL",
    "gn:name":"Koishihama",
    "gn:population":0,
    "gn:timezone":"Asia/Tokyo",
    "iso:country":"JP",
    "name:jpn_x_preferred":[
        "\u5c0f\u77f3\u6d5c"
    ],
    "name:jpn_x_variant":[
        "\u3053\u3044\u3057\u306f\u307e",
        "\u30b3\u30a4\u30b7\u30cf\u30de"
    ],
    "wof:name":"Koishihama",
    "wof:placetype":"locality"
},
  "geometry": {"coordinates":[141.05918,38.36149],"type":"Point"}
}