{
  "type": "Feature",
  "properties": {
    "iso:country":"JP",
    "name:eng_x_preferred":[
        "Narumicho Azadenjiyama"
    ],
    "name:eng_x_variant":[
        "Narumichou Narumicho Azadenjiyama",
        "Narumicho Azadenjiyama"
    ],
    "name:jpn_x_preferred":[
        "\u5b57\u4f1d\u6cbb\u5c71"
    ],
    "name:jpn_x_variant":[
        "\u3042\u3056\u3067\u3093\u3058\u3084\u307e",
        "\u306a\u308b\u307f\u3061\u3087\u3046 \u3042\u3056\u3067\u3093\u3058\u3084\u307e",
        "\u9cf4\u6d77\u753a \u5b57\u4f1d\u6cbb\u5c71"
    ],
    "qs:gn_local":0,
    "qs:local_max":3194,
    "qs:local_sum":30209,
    "qs:localhoods":92,
    "qs:name":"\u5b57\u4f1d\u6cbb\u5c71",
    "qs:name_adm0":"\u65e5\u672c",
    "qs:name_adm1":"\u611b\u77e5\u770c",
    "qs:name_adm2":"\u7dd1\u533a",
    "qs:name_en":"Narumicho Azadenjiyama",
    "qs:name_lau":"\u9cf4\u6d77\u753a",
    "qs:name_local":"\u540d\u53e4\u5c4b\u5e02",
    "qs:photo_max":1,
    "qs:photo_sum":1,
    "qs:placetype":"Suburb",
    "qs:quad_count":1,
    "qs:woe_adm0":23424856,
    "qs:woe_adm1":2345851,
    "qs:woe_adm2":1118614,
    "qs:woe_lau":28440193,
    "qs:woe_local":1117817,
    "qs:woe_ver":"7.10.0",
    "wof:lang":[
        "jpn"
    ],
    "wof:name":"\u5b57\u4f1d\u6cbb\u5c71",
    "wof:placetype":"neighbourhood"
},
  "geometry": {"coordinates":[136.958313,35.095192],"type":"Point"}
}