{
  "type": "Feature",
  "properties": {
    "gn:admin1_code":"10.0",
    "gn:admin2_code":"1857842.0",
    "gn:asciiname":"Kamihosoimachi",
    "gn:country_code":"JP",
    "gn:dem":132,
    "gn:feature_class":"P",
    "gn:feature_code":"PPL",
    "gn:name":"Kamihosoimachi",
    "gn:population":0,
    "gn:timezone":"Asia/Tokyo",
    "iso:country":"JP",
    "name:jpn_x_preferred":[
        "\u4e0a\u7d30\u4e95\u753a"
    ],
    "wof:name":"Kamihosoimachi",
    "wof:placetype":"locality"
},
  "geometry": {"coordinates":[139.07968,36.4222],"type":"Point"}
}