{
  "type": "Feature",
  "properties": {
    "gn:admin1_code":"14.0",
    "gn:admin2_code":"6950859.0",
    "gn:asciiname":"Ogashiwa-shinden",
    "gn:country_code":"JP",
    "gn:dem":20,
    "gn:feature_class":"P",
    "gn:feature_code":"PPLL",
    "gn:name":"\u014cgashiwa-shinden",
    "gn:population":0,
    "gn:timezone":"Asia/Tokyo",
    "iso:country":"JP",
    "name:jpn_x_preferred":[
        "\u5927\u67cf\u65b0\u7530"
    ],
    "name:und_x_variant":[
        "\u014cgashiwa-shinden"
    ],
    "wof:name":"Ogashiwa-shinden",
    "wof:placetype":"locality"
},
  "geometry": {"coordinates":[139.97380000000001,35.94622000000001],"type":"Point"}
}