{
  "type": "Feature",
  "properties": {
    "iso:country":"JP",
    "name:eng_x_preferred":[
        "Komaba 2 Chome"
    ],
    "name:eng_x_variant":[
        "Komaba 2 Choume",
        "Komaba 2 Chome"
    ],
    "name:jpn_x_preferred":[
        "\uff12\u4e01\u76ee"
    ],
    "name:jpn_x_variant":[
        "\u3053\u307e\u3070 \uff12\u3061\u3087\u3046\u3081",
        "\u99d2\u5834 \uff12\u4e01\u76ee",
        "\uff12\u3061\u3087\u3046\u3081"
    ],
    "qs:gn_adm0_cc":"JP",
    "qs:gn_local":1850147,
    "qs:local_max":18112,
    "qs:local_sum":895907,
    "qs:localhoods":857,
    "qs:name":"\uff12\u4e01\u76ee",
    "qs:name_adm0":"\u65e5\u672c",
    "qs:name_adm1":"\u6771\u4eac\u90fd",
    "qs:name_adm2":"\u76ee\u9ed2\u533a",
    "qs:name_en":"Komaba 2 Chome",
    "qs:name_lau":"\u99d2\u5834",
    "qs:name_local":"\u6771\u4eac",
    "qs:photo_max":123,
    "qs:photo_sum":324,
    "qs:placetype":"Suburb",
    "qs:quad_count":17,
    "qs:woe_adm0":23424856,
    "qs:woe_adm1":2345889,
    "qs:woe_adm2":15015504,
    "qs:woe_lau":28414254,
    "qs:woe_local":1118370,
    "qs:woe_ver":"7.10.0",
    "wof:lang":[
        "jpn"
    ],
    "wof:name":"\uff12\u4e01\u76ee",
    "wof:placetype":"neighbourhood"
},
  "geometry": {"coordinates":[139.68054100000001,35.656055],"type":"Point"}
}