{
  "type": "Feature",
  "properties": {
    "gn:admin1_code":"37.0",
    "gn:admin2_code":"1864089.0",
    "gn:asciiname":"Nakanodai",
    "gn:country_code":"JP",
    "gn:dem":56,
    "gn:feature_class":"P",
    "gn:feature_code":"PPLL",
    "gn:name":"Nakanodai",
    "gn:population":0,
    "gn:timezone":"Asia/Tokyo",
    "iso:country":"JP",
    "name:jpn_x_preferred":[
        "\u4e2d\u91ce\u53f0"
    ],
    "wof:name":"Nakanodai",
    "wof:placetype":"locality"
},
  "geometry": {"coordinates":[138.60093999999998,35.18875],"type":"Point"}
}