{
  "type": "Feature",
  "properties": {
    "gn:admin1_code":"46",
    "gn:admin2_code":"7415916.0",
    "gn:asciiname":"Tonoki",
    "gn:cc2":"JP",
    "gn:country_code":"JP",
    "gn:dem":1093,
    "gn:feature_class":"P",
    "gn:feature_code":"PPL",
    "gn:name":"T\u014dnoki",
    "gn:population":0,
    "gn:timezone":"Asia/Tokyo",
    "iso:country":"JP",
    "name:und_x_variant":[
        "Fujinoki",
        "T\u014dnoki"
    ],
    "wof:name":"Tonoki",
    "wof:placetype":"locality"
},
  "geometry": {"coordinates":[138.76667,35.58333],"type":"Point"}
}