{
  "type": "Feature",
  "properties": {
    "gn:admin1_code":"4.0",
    "gn:admin2_code":"7465521.0",
    "gn:asciiname":"Minakura",
    "gn:country_code":"JP",
    "gn:dem":213,
    "gn:feature_class":"P",
    "gn:feature_code":"PPLL",
    "gn:name":"Minakura",
    "gn:population":0,
    "gn:timezone":"Asia/Tokyo",
    "iso:country":"JP",
    "name:jpn_x_preferred":[
        "\u7686\u5009"
    ],
    "name:jpn_x_variant":[
        "\u307f\u306a\u304f\u3089",
        "\u30df\u30ca\u30af\u30e9"
    ],
    "wof:name":"Minakura",
    "wof:placetype":"locality"
},
  "geometry": {"coordinates":[139.98176000000001,35.06188],"type":"Point"}
}