{
  "type": "Feature",
  "properties": {
    "gn:admin1_code":"21.0",
    "gn:admin2_code":"1848443.0",
    "gn:admin3_code":"43468.0",
    "gn:asciiname":"Kamitakatsuka",
    "gn:country_code":"JP",
    "gn:dem":32,
    "gn:feature_class":"P",
    "gn:feature_code":"PPLL",
    "gn:name":"Kamitakatsuka",
    "gn:population":0,
    "gn:timezone":"Asia/Tokyo",
    "iso:country":"JP",
    "name:jpn_x_preferred":[
        "\u4e0a\u9ad8\u585a"
    ],
    "name:jpn_x_variant":[
        "\u304b\u307f\u305f\u304b\u3064\u304b",
        "\u30ab\u30df\u30bf\u30ab\u30c4\u30ab"
    ],
    "wof:name":"Kamitakatsuka",
    "wof:placetype":"locality"
},
  "geometry": {"coordinates":[130.69821000000002,32.57868],"type":"Point"}
}