{
  "type": "Feature",
  "properties": {
    "iso:country":"JP",
    "name:eng_x_preferred":[
        "Shiramine"
    ],
    "name:jpn_x_preferred":[
        "\u767d\u5cf0"
    ],
    "qs:name":"\u767d\u5cf0",
    "qs:name_adm0":"\u65e5\u672c",
    "qs:name_adm1":"\u77f3\u5ddd\u770c",
    "qs:photos":9,
    "qs:photos_1k":2,
    "qs:photos_9k":1,
    "qs:photos_9r":1,
    "qs:photos_all":9,
    "qs:photos_sr":1,
    "qs:placetype":"LocalAdmin",
    "qs:pop_sr":"0",
    "wof:name":"Shiramine",
    "wof:placetype":"localadmin"
},
  "geometry": {"coordinates":[136.64708999999999,36.281367],"type":"Point"}
}