{
  "type": "Feature",
  "properties": {
    "gn:admin1_code":"3.0",
    "gn:admin2_code":"2127674.0",
    "gn:asciiname":"Higuchiyama-kaitaku",
    "gn:country_code":"JP",
    "gn:dem":107,
    "gn:feature_class":"P",
    "gn:feature_code":"PPLL",
    "gn:name":"Higuchiyama-kaitaku",
    "gn:population":0,
    "gn:timezone":"Asia/Tokyo",
    "iso:country":"JP",
    "name:jpn_x_preferred":[
        "\u6a0b\u53e3\u5c71\u958b\u62d3"
    ],
    "name:jpn_x_variant":[
        "\u3072\u3050\u3061\u3084\u307e\u304b\u3044\u305f\u304f",
        "\u30d2\u30b0\u30c1\u30e4\u30de\u30ab\u30a4\u30bf\u30af"
    ],
    "wof:name":"Higuchiyama-kaitaku",
    "wof:placetype":"locality"
},
  "geometry": {"coordinates":[141.15272999999999,40.57298],"type":"Point"}
}