{
  "type": "Feature",
  "properties": {
    "gn:admin1_code":"3.0",
    "gn:admin2_code":"2127674.0",
    "gn:asciiname":"Morinokoshi",
    "gn:country_code":"JP",
    "gn:dem":205,
    "gn:feature_class":"P",
    "gn:feature_code":"PPL",
    "gn:name":"Morinokoshi",
    "gn:population":0,
    "gn:timezone":"Asia/Tokyo",
    "iso:country":"JP",
    "name:jpn_x_preferred":[
        "\u68ee\u30ce\u8d8a"
    ],
    "name:jpn_x_variant":[
        "\u3082\u308a\u306e\u3053\u3057",
        "\u30e2\u30ea\u30ce\u30b3\u30b7"
    ],
    "wof:name":"Morinokoshi",
    "wof:placetype":"locality"
},
  "geometry": {"coordinates":[141.1378,40.51612],"type":"Point"}
}