{
  "type": "Feature",
  "properties": {
    "gn:admin1_code":"12.0",
    "gn:admin2_code":"2129597.0",
    "gn:admin3_code":"1345.0",
    "gn:asciiname":"Sawara",
    "gn:country_code":"JP",
    "gn:dem":1,
    "gn:feature_class":"P",
    "gn:feature_code":"PPL",
    "gn:name":"Sawara",
    "gn:population":0,
    "gn:timezone":"Asia/Tokyo",
    "iso:country":"JP",
    "name:ceb_x_preferred":[
        "Sawara"
    ],
    "name:deu_x_preferred":[
        "Sawara"
    ],
    "name:fra_x_preferred":[
        "Sawara"
    ],
    "wof:name":"Sawara",
    "wof:placetype":"locality"
},
  "geometry": {"coordinates":[140.69797,42.12738],"type":"Point"}
}