{
  "type": "Feature",
  "properties": {
    "gn:admin1_code":"15",
    "gn:admin2_code":"1848973.0",
    "gn:asciiname":"Machinomachi-awagura",
    "gn:country_code":"JP",
    "gn:dem":41,
    "gn:feature_class":"P",
    "gn:feature_code":"PPL",
    "gn:name":"Machinomachi-awagura",
    "gn:population":0,
    "gn:timezone":"Asia/Tokyo",
    "iso:country":"JP",
    "name:jpn_x_preferred":[
        "\u753a\u91ce\u753a\u7c9f\u8535"
    ],
    "name:und_x_variant":[
        "Awakura",
        "Awagura",
        "Machinomachi-awagura"
    ],
    "wof:name":"Machinomachi-awagura",
    "wof:placetype":"locality"
},
  "geometry": {"coordinates":[137.09323000000001,37.42186],"type":"Point"}
}