{
  "type": "Feature",
  "properties": {
    "gn:country":"JP",
    "gn:fcode":"PPL",
    "gn:population":27567,
    "iso:country":"JP",
    "name:ara_x_preferred":[
        "\u064a\u0648\u063a\u0627\u0648\u0627\u0631\u0627"
    ],
    "name:arz_x_preferred":[
        "\u064a\u0648\u062c\u0627\u0648\u0627\u0631\u0627"
    ],
    "name:ast_x_preferred":[
        "Yugawara"
    ],
    "name:bel_x_preferred":[
        "\u042e\u0433\u0430\u0432\u0430\u0440\u0430"
    ],
    "name:cat_x_preferred":[
        "Yugawara"
    ],
    "name:ceb_x_preferred":[
        "Yugawara"
    ],
    "name:ces_x_preferred":[
        "Jugawara"
    ],
    "name:deu_x_preferred":[
        "Yugawara"
    ],
    "name:eng_x_preferred":[
        "Yugawara"
    ],
    "name:fas_x_preferred":[
        "\u06cc\u0648\u06af\u0627\u0648\u0627\u0631\u0627"
    ],
    "name:fin_x_preferred":[
        "Yugawara"
    ],
    "name:fra_x_preferred":[
        "Yugawara"
    ],
    "name:gle_x_preferred":[
        "Yugawara"
    ],
    "name:heb_x_preferred":[
        "\u05d9\u05d5\u05d2\u05d0\u05d5\u05d5\u05e8\u05d4"
    ],
    "name:ita_x_preferred":[
        "Yugawara"
    ],
    "name:jpn_x_preferred":[
        "\u6e6f\u6cb3\u539f\u753a"
    ],
    "name:kor_x_preferred":[
        "\uc720\uac00\uc640\ub77c \uc815"
    ],
    "name:kor_x_variant":[
        "\uc720\uac00\uc640\ub77c\uc815"
    ],
    "name:mlg_x_preferred":[
        "Yugawara"
    ],
    "name:msa_x_preferred":[
        "Yugawara"
    ],
    "name:nld_x_preferred":[
        "Yugawara"
    ],
    "name:nno_x_preferred":[
        "Yugawara"
    ],
    "name:nob_x_preferred":[
        "Yugawara"
    ],
    "name:pol_x_preferred":[
        "Yugawara"
    ],
    "name:por_x_preferred":[
        "Yugawara"
    ],
    "name:rus_x_preferred":[
        "\u042e\u0433\u0430\u0432\u0430\u0440\u0430"
    ],
    "name:spa_x_preferred":[
        "Yugawara"
    ],
    "name:swe_x_preferred":[
        "Yugawara"
    ],
    "name:szl_x_preferred":[
        "Yugawara"
    ],
    "name:tgl_x_preferred":[
        "Yugawara"
    ],
    "name:tha_x_preferred":[
        "\u0e22\u0e39\u0e07\u0e32\u0e27\u0e32\u0e23\u0e30"
    ],
    "name:tur_x_preferred":[
        "Yugawara"
    ],
    "name:ukr_x_preferred":[
        "\u042e\u0491\u0430\u0432\u0430\u0440\u0430"
    ],
    "name:urd_x_preferred":[
        "\u06cc\u0648\u06af\u0648\u0627\u0631\u0627\u060c \u06a9\u0646\u0627\u06af\u0648\u0627"
    ],
    "name:urd_x_variant":[
        "\u06cc\u0648\u06af\u0648\u0627\u0631\u0627"
    ],
    "name:zho_x_preferred":[
        "\u6e6f\u6cb3\u539f\u753a"
    ],
    "qs:name":"Yugawara",
    "qs:photos_9r":0,
    "qs:photos_sr":0,
    "qs:pop_sr":"7",
    "wd:wordcount":397,
    "wof:name":"Yugawara",
    "wof:placetype":"locality",
    "wof:population":27567
},
  "geometry": {"coordinates":[139.06666999999999,35.15],"type":"Point"}
}