{
  "type": "Feature",
  "properties": {
    "gn:admin1_code":"26.0",
    "gn:admin2_code":"1854378.0",
    "gn:asciiname":"Osaka",
    "gn:country_code":"JP",
    "gn:dem":763,
    "gn:feature_class":"P",
    "gn:feature_code":"PPLL",
    "gn:name":"Osaka",
    "gn:population":0,
    "gn:timezone":"Asia/Tokyo",
    "iso:country":"JP",
    "name:jpn_x_preferred":[
        "\u5c0f\u5742"
    ],
    "wof:name":"Osaka",
    "wof:placetype":"locality"
},
  "geometry": {"coordinates":[138.06891999999999,36.03646],"type":"Point"}
}