{
  "type": "Feature",
  "properties": {
    "gn:admin1_code":"21.0",
    "gn:admin2_code":"1858418.0",
    "gn:admin3_code":"43104.0",
    "gn:asciiname":"Shonokoga",
    "gn:country_code":"JP",
    "gn:dem":3,
    "gn:feature_class":"P",
    "gn:feature_code":"PPLL",
    "gn:name":"Sh\u014dnokoga",
    "gn:population":0,
    "gn:timezone":"Asia/Tokyo",
    "iso:country":"JP",
    "name:jpn_x_preferred":[
        "\u5e84\u53e4\u9591"
    ],
    "name:jpn_x_variant":[
        "\u3057\u3087\u3046\u306e\u3053\u304c",
        "\u30b7\u30e7\u30a6\u30ce\u30b3\u30ac"
    ],
    "name:und_x_variant":[
        "Sh\u014dnokoga"
    ],
    "wof:name":"Shonokoga",
    "wof:placetype":"locality"
},
  "geometry": {"coordinates":[130.70566000000002,32.72233],"type":"Point"}
}