{
  "type": "Feature",
  "properties": {
    "iso:country":"JP",
    "name:eng_x_preferred":[
        "Ujiurata 3 Chome"
    ],
    "name:eng_x_variant":[
        "Ujiurata 3 Choume",
        "Ujiurata 3 Chome"
    ],
    "name:jpn_x_preferred":[
        "\uff13\u4e01\u76ee"
    ],
    "name:jpn_x_variant":[
        "\u3046\u3058\u3046\u3089\u305f \uff13\u3061\u3087\u3046\u3081",
        "\u5b87\u6cbb\u6d66\u7530 \uff13\u4e01\u76ee",
        "\uff13\u3061\u3087\u3046\u3081"
    ],
    "qs:gn_local":0,
    "qs:local_max":2130,
    "qs:local_sum":2937,
    "qs:localhoods":7,
    "qs:name":"\uff13\u4e01\u76ee",
    "qs:name_adm0":"\u65e5\u672c",
    "qs:name_adm1":"\u4e09\u91cd\u770c",
    "qs:name_en":"Ujiurata 3 Chome",
    "qs:name_lau":"\u5b87\u6cbb\u6d66\u7530",
    "qs:name_local":"\u4f0a\u52e2\u5e02",
    "qs:photo_max":2,
    "qs:photo_sum":2,
    "qs:placetype":"Suburb",
    "qs:quad_count":1,
    "qs:woe_adm0":23424856,
    "qs:woe_adm1":2345872,
    "qs:woe_adm2":0,
    "qs:woe_lau":28446191,
    "qs:woe_local":1117319,
    "qs:woe_ver":"7.10.0",
    "wof:lang":[
        "jpn"
    ],
    "wof:name":"\uff13\u4e01\u76ee",
    "wof:placetype":"neighbourhood"
},
  "geometry": {"coordinates":[136.71661399999999,34.449955],"type":"Point"}
}