{
  "type": "Feature",
  "properties": {
    "gn:admin1_code":"7.0",
    "gn:admin2_code":"1859306.0",
    "gn:admin3_code":"40106.0",
    "gn:asciiname":"Enamicho",
    "gn:country_code":"JP",
    "gn:dem":9,
    "gn:feature_class":"P",
    "gn:feature_code":"PPL",
    "gn:name":"Enamich\u014d",
    "gn:population":0,
    "gn:timezone":"Asia/Tokyo",
    "iso:country":"JP",
    "name:jpn_x_preferred":[
        "\u6c5f\u5357\u753a"
    ],
    "name:und_x_variant":[
        "Enamich\u014d"
    ],
    "wof:name":"Enamicho",
    "wof:placetype":"locality"
},
  "geometry": {"coordinates":[130.88253999999998,33.87583],"type":"Point"}
}