{
  "type": "Feature",
  "properties": {
    "gn:admin1_code":"24.0",
    "gn:admin2_code":"2112261.0",
    "gn:asciiname":"Saichi-moriai",
    "gn:country_code":"JP",
    "gn:dem":3,
    "gn:feature_class":"P",
    "gn:feature_code":"PPL",
    "gn:name":"Saichi-moriai",
    "gn:population":0,
    "gn:timezone":"Asia/Tokyo",
    "iso:country":"JP",
    "name:jpn_x_preferred":[
        "\u6700\u77e5\u68ee\u5408"
    ],
    "name:jpn_x_variant":[
        "\u3055\u3044\u3061\u3082\u308a\u3042\u3044",
        "\u30b5\u30a4\u30c1\u30e2\u30ea\u30a2\u30a4"
    ],
    "wof:name":"Saichi-moriai",
    "wof:placetype":"locality"
},
  "geometry": {"coordinates":[141.58256,38.85029],"type":"Point"}
}