{
  "type": "Feature",
  "properties": {
    "gn:admin1_code":"15.0",
    "gn:admin2_code":"7467881.0",
    "gn:asciiname":"Kawachimachi-yoshioka",
    "gn:country_code":"JP",
    "gn:dem":178,
    "gn:feature_class":"P",
    "gn:feature_code":"PPL",
    "gn:name":"Kawachimachi-yoshioka",
    "gn:population":0,
    "gn:timezone":"Asia/Tokyo",
    "iso:country":"JP",
    "name:jpn_x_preferred":[
        "\u6cb3\u5185\u753a\u5409\u5ca1"
    ],
    "wof:name":"Kawachimachi-yoshioka",
    "wof:placetype":"locality"
},
  "geometry": {"coordinates":[136.61489,36.37914],"type":"Point"}
}