{
  "type": "Feature",
  "properties": {
    "gn:admin1_code":"24.0",
    "gn:admin2_code":"2112574.0",
    "gn:asciiname":"Uwayachi",
    "gn:country_code":"JP",
    "gn:dem":3,
    "gn:feature_class":"P",
    "gn:feature_code":"PPL",
    "gn:name":"Uwayachi",
    "gn:population":0,
    "gn:timezone":"Asia/Tokyo",
    "iso:country":"JP",
    "name:jpn_x_preferred":[
        "\u4e0a\u8c37\u5730"
    ],
    "name:jpn_x_variant":[
        "\u3046\u308f\u3084\u3061",
        "\u30a6\u30ef\u30e4\u30c1"
    ],
    "wof:name":"Uwayachi",
    "wof:placetype":"locality"
},
  "geometry": {"coordinates":[141.25290000000001,38.4851],"type":"Point"}
}