{
  "type": "Feature",
  "properties": {
    "iso:country":"JP",
    "name:eng_x_preferred":[
        "Ritsurincho 1 Chome"
    ],
    "name:eng_x_variant":[
        "Ritsurinchou 1 Choume",
        "Ritsurincho 1 Chome"
    ],
    "name:jpn_x_preferred":[
        "\uff11\u4e01\u76ee"
    ],
    "name:jpn_x_variant":[
        "\u308a\u3064\u308a\u3093\u3061\u3087\u3046 \uff11\u3061\u3087\u3046\u3081",
        "\u6817\u6797\u753a \uff11\u4e01\u76ee",
        "\uff11\u3061\u3087\u3046\u3081"
    ],
    "name:unk_x_variant":[
        "\uff11\u4e01\u76ee"
    ],
    "qs:gn_adm0_cc":"JP",
    "qs:gn_local":1851100,
    "qs:local_max":1214,
    "qs:local_sum":2181,
    "qs:localhoods":8,
    "qs:name":"\uff11\u4e01\u76ee",
    "qs:name_adm0":"\u65e5\u672c",
    "qs:name_adm1":"\u9999\u5ddd\u770c",
    "qs:name_en":"Ritsurincho 1 Chome",
    "qs:name_lau":"\u6817\u6797\u753a",
    "qs:name_local":"\u9ad8\u677e\u5e02",
    "qs:photo_max":511,
    "qs:photo_sum":1214,
    "qs:placetype":"Suburb",
    "qs:quad_count":13,
    "qs:woe_adm0":23424856,
    "qs:woe_adm1":2345866,
    "qs:woe_adm2":0,
    "qs:woe_lau":28478501,
    "qs:woe_local":1118285,
    "qs:woe_ver":"7.10.0",
    "wof:lang":[
        "jpn"
    ],
    "wof:name":"\uff11\u4e01\u76ee",
    "wof:placetype":"neighbourhood"
},
  "geometry": {"coordinates":[134.04202100000001,34.329039],"type":"Point"}
}