{
  "type": "Feature",
  "properties": {
    "iso:country":"JP",
    "name:eng_x_preferred":[
        "Takamido 4 Chome"
    ],
    "name:eng_x_variant":[
        "Takamidou 4 Choume",
        "Takamido 4 Chome"
    ],
    "name:jpn_x_preferred":[
        "\uff14\u4e01\u76ee"
    ],
    "name:jpn_x_variant":[
        "\u305f\u304b\u307f\u3069\u3046 \uff14\u3061\u3087\u3046\u3081",
        "\u9ad8\u5fa1\u5802 \uff14\u4e01\u76ee",
        "\uff14\u3061\u3087\u3046\u3081"
    ],
    "qs:gn_local":0,
    "qs:local_max":36,
    "qs:local_sum":100,
    "qs:localhoods":4,
    "qs:name":"\uff14\u4e01\u76ee",
    "qs:name_adm0":"\u65e5\u672c",
    "qs:name_adm1":"\u611b\u77e5\u770c",
    "qs:name_en":"Takamido 4 Chome",
    "qs:name_lau":"\u9ad8\u5fa1\u5802",
    "qs:name_local":"\u7a32\u6ca2\u5e02",
    "qs:photo_max":11,
    "qs:photo_sum":13,
    "qs:placetype":"Suburb",
    "qs:quad_count":2,
    "qs:woe_adm0":23424856,
    "qs:woe_adm1":2345851,
    "qs:woe_adm2":0,
    "qs:woe_lau":28444112,
    "qs:woe_local":1109500,
    "qs:woe_ver":"7.10.0",
    "wof:lang":[
        "jpn"
    ],
    "wof:name":"\uff14\u4e01\u76ee",
    "wof:placetype":"neighbourhood"
},
  "geometry": {"coordinates":[136.804506,35.244068],"type":"Point"}
}