{
  "type": "Feature",
  "properties": {
    "gn:admin1_code":"27",
    "gn:admin2_code":"7418810.0",
    "gn:asciiname":"Izuharamachi-agami",
    "gn:country_code":"JP",
    "gn:dem":17,
    "gn:feature_class":"P",
    "gn:feature_code":"PPL",
    "gn:name":"Izuharamachi-agami",
    "gn:population":0,
    "gn:timezone":"Asia/Tokyo",
    "iso:country":"JP",
    "name:jpn_x_preferred":[
        "\u53b3\u539f\u753a\u5b89\u795e"
    ],
    "name:und_x_variant":[
        "Agami"
    ],
    "wof:name":"Izuharamachi-agami",
    "wof:placetype":"locality"
},
  "geometry": {"coordinates":[129.27164999999999,34.14849],"type":"Point"}
}