{
  "type": "Feature",
  "properties": {
    "gn:admin1_code":"33.0",
    "gn:admin2_code":"7391354.0",
    "gn:admin3_code":"41441.0",
    "gn:asciiname":"Aburatsu",
    "gn:country_code":"JP",
    "gn:dem":4,
    "gn:feature_class":"P",
    "gn:feature_code":"PPLL",
    "gn:name":"Aburatsu",
    "gn:population":0,
    "gn:timezone":"Asia/Tokyo",
    "iso:country":"JP",
    "name:jpn_x_preferred":[
        "\u6cb9\u6d25"
    ],
    "wof:name":"Aburatsu",
    "wof:placetype":"locality"
},
  "geometry": {"coordinates":[130.17894999999999,33.02662],"type":"Point"}
}