{
  "type": "Feature",
  "properties": {
    "gn:admin1_code":"43.0",
    "gn:admin2_code":"1865123.0",
    "gn:admin3_code":"30366.0",
    "gn:asciiname":"Kamimutsugawa",
    "gn:country_code":"JP",
    "gn:dem":299,
    "gn:feature_class":"P",
    "gn:feature_code":"PPL",
    "gn:name":"Kamimutsugawa",
    "gn:population":0,
    "gn:timezone":"Asia/Tokyo",
    "iso:country":"JP",
    "name:jpn_x_preferred":[
        "\u4e0a\u516d\u5ddd"
    ],
    "wof:name":"Kamimutsugawa",
    "wof:placetype":"locality"
},
  "geometry": {"coordinates":[135.25326000000001,34.10482],"type":"Point"}
}