{
  "type": "Feature",
  "properties": {
    "gn:admin1_code":"45.0",
    "gn:admin2_code":"1852222.0",
    "gn:asciiname":"Kandacho",
    "gn:country_code":"JP",
    "gn:dem":26,
    "gn:feature_class":"P",
    "gn:feature_code":"PPL",
    "gn:name":"Kandach\u014d",
    "gn:population":0,
    "gn:timezone":"Asia/Tokyo",
    "iso:country":"JP",
    "name:jpn_x_preferred":[
        "\u795e\u7530\u753a"
    ],
    "name:und_x_variant":[
        "Kandach\u014d"
    ],
    "wof:name":"Kandacho",
    "wof:placetype":"locality"
},
  "geometry": {"coordinates":[130.92407,33.96351],"type":"Point"}
}