{
  "type": "Feature",
  "properties": {
    "gn:admin1_code":"21.0",
    "gn:admin2_code":"1848441.0",
    "gn:asciiname":"Wasabi",
    "gn:country_code":"JP",
    "gn:dem":935,
    "gn:feature_class":"P",
    "gn:feature_code":"PPLL",
    "gn:name":"Wasabi",
    "gn:population":0,
    "gn:timezone":"Asia/Tokyo",
    "iso:country":"JP",
    "name:jpn_x_preferred":[
        "\u671d\u65e5"
    ],
    "name:jpn_x_variant":[
        "\u308f\u3055\u3073",
        "\u30ef\u30b5\u30d3"
    ],
    "wof:name":"Wasabi",
    "wof:placetype":"locality"
},
  "geometry": {"coordinates":[130.89160999999999,32.56336],"type":"Point"}
}