{
  "type": "Feature",
  "properties": {
    "gn:admin1_code":"21.0",
    "gn:admin2_code":"1848441.0",
    "gn:asciiname":"Wasabi",
    "gn:country_code":"JP",
    "gn:dem":935,
    "gn:feature_class":"P",
    "gn:feature_code":"PPLL",
    "gn:name":"Wasabi",
    "gn:population":0,
    "gn:timezone":"Asia/Tokyo",
    "iso:country":"JP",
    "name:afr_x_preferred":[
        "Wasabi"
    ],
    "name:ara_x_preferred":[
        "\u0648\u0633\u0627\u0628\u064a"
    ],
    "name:aze_x_preferred":[
        "Vasabi"
    ],
    "name:bul_x_preferred":[
        "\u0423\u0430\u0441\u0430\u0431\u0438"
    ],
    "name:cat_x_preferred":[
        "Rave japon\u00e8s"
    ],
    "name:ceb_x_preferred":[
        "Eutrema japonicum"
    ],
    "name:ces_x_preferred":[
        "Eutrema japonsk\u00e1"
    ],
    "name:dan_x_preferred":[
        "Wasabi"
    ],
    "name:deu_x_preferred":[
        "Wasabi"
    ],
    "name:epo_x_preferred":[
        "Vasabio"
    ],
    "name:est_x_preferred":[
        "Jaapani vasaabia"
    ],
    "name:eus_x_preferred":[
        "Wasabi"
    ],
    "name:fas_x_preferred":[
        "\u0648\u0627\u0633\u0627\u0628\u06cc"
    ],
    "name:fin_x_preferred":[
        "Maustekrassi"
    ],
    "name:fra_x_preferred":[
        "Wasabi"
    ],
    "name:heb_x_preferred":[
        "\u05d5\u05d0\u05e1\u05d0\u05d1\u05d9"
    ],
    "name:hin_x_preferred":[
        "\u0935\u0938\u093e\u092c\u0940"
    ],
    "name:hun_x_preferred":[
        "Vaszabi"
    ],
    "name:ind_x_preferred":[
        "Wasabi"
    ],
    "name:ita_x_preferred":[
        "Eutrema japonicum"
    ],
    "name:jav_x_preferred":[
        "Wasabi"
    ],
    "name:jpn_x_preferred":[
        "\u671d\u65e5"
    ],
    "name:jpn_x_variant":[
        "\u308f\u3055\u3073",
        "\u30ef\u30b5\u30d3"
    ],
    "name:kor_x_preferred":[
        "\uace0\ucd94\ub0c9\uc774"
    ],
    "name:lit_x_preferred":[
        "Japoninis pipirkrienis"
    ],
    "name:msa_x_preferred":[
        "Wasabi"
    ],
    "name:nld_x_preferred":[
        "Eutrema japonicum"
    ],
    "name:nno_x_preferred":[
        "Wasabi"
    ],
    "name:nor_x_preferred":[
        "Wasabi"
    ],
    "name:pol_x_preferred":[
        "Chrzan japo\u0144ski"
    ],
    "name:por_x_preferred":[
        "Wasabi"
    ],
    "name:ron_x_preferred":[
        "Wasabi"
    ],
    "name:rus_x_preferred":[
        "\u0412\u0430\u0441\u0430\u0431\u0438"
    ],
    "name:sco_x_preferred":[
        "Wasabi"
    ],
    "name:spa_x_preferred":[
        "Eutrema japonicum"
    ],
    "name:swe_x_preferred":[
        "Wasabi"
    ],
    "name:tgl_x_preferred":[
        "Wasabi"
    ],
    "name:tha_x_preferred":[
        "\u0e27\u0e32\u0e0b\u0e32\u0e1a\u0e34"
    ],
    "name:tur_x_preferred":[
        "Vasabi"
    ],
    "name:ukr_x_preferred":[
        "\u0412\u0430\u0441\u0430\u0431\u0456"
    ],
    "name:vec_x_preferred":[
        "Wasabi"
    ],
    "name:vie_x_preferred":[
        "Wasabi"
    ],
    "name:war_x_preferred":[
        "Wasabi"
    ],
    "name:yid_x_preferred":[
        "\u05d5\u05d5\u05d0\u05e1\u05d0\u05d1\u05d9"
    ],
    "wof:name":"Wasabi",
    "wof:placetype":"locality"
},
  "geometry": {"coordinates":[130.89160999999999,32.56336],"type":"Point"}
}