{
  "type": "Feature",
  "properties": {
    "gn:admin1_code":"19.0",
    "gn:admin2_code":"1863429.0",
    "gn:asciiname":"Shindo",
    "gn:country_code":"JP",
    "gn:dem":173,
    "gn:feature_class":"P",
    "gn:feature_code":"PPLL",
    "gn:name":"Shind\u014d",
    "gn:population":0,
    "gn:timezone":"Asia/Tokyo",
    "iso:country":"JP",
    "name:deu_x_preferred":[
        "Shindo"
    ],
    "name:fra_x_preferred":[
        "Shindo"
    ],
    "name:jpn_x_preferred":[
        "\u65b0\u9053"
    ],
    "name:und_x_variant":[
        "Shind\u014d"
    ],
    "wof:name":"Shindo",
    "wof:placetype":"locality"
},
  "geometry": {"coordinates":[139.16829999999999,35.37642],"type":"Point"}
}