{
  "type": "Feature",
  "properties": {
    "gn:admin1_code":"21.0",
    "gn:admin2_code":"7412709.0",
    "gn:admin3_code":"43348.0",
    "gn:asciiname":"Kunekusa",
    "gn:country_code":"JP",
    "gn:dem":259,
    "gn:feature_class":"P",
    "gn:feature_code":"PPLL",
    "gn:name":"Kunekusa",
    "gn:population":0,
    "gn:timezone":"Asia/Tokyo",
    "iso:country":"JP",
    "name:jpn_x_preferred":[
        "\u6960\u6839\u8349"
    ],
    "name:jpn_x_variant":[
        "\u304f\u306d\u304f\u3055",
        "\u30af\u30cd\u30af\u30b5"
    ],
    "wof:name":"Kunekusa",
    "wof:placetype":"locality"
},
  "geometry": {"coordinates":[130.91623999999999,32.61566],"type":"Point"}
}