{
  "type": "Feature",
  "properties": {
    "gn:admin1_code":"32.0",
    "gn:admin2_code":"8300631.0",
    "gn:asciiname":"Terakata-motomachi",
    "gn:country_code":"JP",
    "gn:dem":5,
    "gn:feature_class":"P",
    "gn:feature_code":"PPL",
    "gn:name":"Terakata-motomachi",
    "gn:population":0,
    "gn:timezone":"Asia/Tokyo",
    "iso:country":"JP",
    "name:jpn_x_preferred":[
        "\u5bfa\u65b9\u5143\u753a"
    ],
    "wof:name":"Terakata-motomachi",
    "wof:placetype":"locality"
},
  "geometry": {"coordinates":[135.57068000000001,34.72603],"type":"Point"}
}