{
  "type": "Feature",
  "properties": {
    "gn:admin1_code":"27.0",
    "gn:admin2_code":"1857466.0",
    "gn:asciiname":"Fukushimacho-harumen",
    "gn:country_code":"JP",
    "gn:dem":25,
    "gn:feature_class":"P",
    "gn:feature_code":"PPL",
    "gn:name":"Fukushimach\u014d-harumen",
    "gn:population":0,
    "gn:timezone":"Asia/Tokyo",
    "iso:country":"JP",
    "name:jpn_x_preferred":[
        "\u798f\u5cf6\u753a\u539f\u514d"
    ],
    "name:und_x_variant":[
        "Fukushimach\u014d-harumen"
    ],
    "wof:name":"Fukushimacho-harumen",
    "wof:placetype":"locality"
},
  "geometry": {"coordinates":[129.8152,33.40286],"type":"Point"}
}