{
  "type": "Feature",
  "properties": {
    "gn:admin1_code":"7.0",
    "gn:admin2_code":"1851269.0",
    "gn:admin3_code":"40602.0",
    "gn:asciiname":"Toya",
    "gn:country_code":"JP",
    "gn:dem":535,
    "gn:feature_class":"P",
    "gn:feature_code":"PPLL",
    "gn:name":"Toya",
    "gn:population":0,
    "gn:timezone":"Asia/Tokyo",
    "iso:country":"JP",
    "name:ceb_x_preferred":[
        "Toya"
    ],
    "name:deu_x_preferred":[
        "Toya"
    ],
    "name:fra_x_preferred":[
        "Toya"
    ],
    "name:ita_x_preferred":[
        "Toya"
    ],
    "name:jpn_x_preferred":[
        "\u6238\u8c37"
    ],
    "name:spa_x_preferred":[
        "Toya"
    ],
    "wof:name":"Toya",
    "wof:placetype":"locality"
},
  "geometry": {"coordinates":[130.81589,33.51406],"type":"Point"}
}