{
  "type": "Feature",
  "properties": {
    "gn:admin1_code":"4.0",
    "gn:admin2_code":"7465523.0",
    "gn:asciiname":"Sanmu",
    "gn:country_code":"JP",
    "gn:dem":52,
    "gn:feature_class":"P",
    "gn:feature_code":"PPLA2",
    "gn:name":"Sanmu",
    "gn:population":0,
    "gn:timezone":"Asia/Tokyo",
    "iso:country":"JP",
    "name:ara_x_preferred":[
        "\u0633\u0627\u0646\u0645\u0648"
    ],
    "name:deu_x_preferred":[
        "Sammu"
    ],
    "name:fas_x_preferred":[
        "\u0633\u0627\u0646\u200c\u0645\u0648\u060c \u0686\u06cc\u0628\u0627"
    ],
    "name:jpn_x_preferred":[
        "\u5c71\u6b66"
    ],
    "name:jpn_x_variant":[
        "\u5c71\u6b66\u5e02"
    ],
    "name:kor_x_preferred":[
        "\uc0b0\ubb34 \uc2dc"
    ],
    "name:mzn_x_preferred":[
        "\u0633\u0627\u0646\u200c\u0645\u0648\u060c \u0686\u06cc\u0628\u0627"
    ],
    "name:nan_x_preferred":[
        "Sanmu-chh\u012b"
    ],
    "name:rus_x_preferred":[
        "\u0421\u0430\u043c\u043c\u0443"
    ],
    "name:tha_x_preferred":[
        "\u0e0b\u0e31\u0e19\u0e21\u0e38"
    ],
    "name:ukr_x_preferred":[
        "\u0421\u0430\u043c\u043c\u0443"
    ],
    "name:urd_x_preferred":[
        "\u0633\u0627\u0646\u0645\u0648\u060c \u0686\u06cc\u0628\u0627"
    ],
    "name:zho_x_preferred":[
        "\u5c71\u6b66\u5e02"
    ],
    "wof:name":"Sanmu",
    "wof:placetype":"locality"
},
  "geometry": {"coordinates":[140.41762,35.62755999999999],"type":"Point"}
}