{
  "type": "Feature",
  "properties": {
    "gn:admin1_code":"7.0",
    "gn:admin2_code":"1859306.0",
    "gn:admin3_code":"40101.0",
    "gn:asciiname":"Jinai",
    "gn:country_code":"JP",
    "gn:dem":56,
    "gn:feature_class":"P",
    "gn:feature_code":"PPL",
    "gn:name":"Jinai",
    "gn:population":0,
    "gn:timezone":"Asia/Tokyo",
    "iso:country":"JP",
    "name:jpn_x_preferred":[
        "\u5bfa\u5185"
    ],
    "wof:name":"Jinai",
    "wof:placetype":"locality"
},
  "geometry": {"coordinates":[130.94784000000001,33.9065],"type":"Point"}
}