{
  "type": "Feature",
  "properties": {
    "gn:admin1_code":"21.0",
    "gn:admin2_code":"7413150.0",
    "gn:asciiname":"Himei",
    "gn:country_code":"JP",
    "gn:dem":95,
    "gn:feature_class":"P",
    "gn:feature_code":"PPLL",
    "gn:name":"Himei",
    "gn:population":0,
    "gn:timezone":"Asia/Tokyo",
    "iso:country":"JP",
    "name:jpn_x_preferred":[
        "\u59eb\u4e95"
    ],
    "name:jpn_x_variant":[
        "\u3072\u3081\u3044",
        "\u30d2\u30e1\u30a4"
    ],
    "wof:name":"Himei",
    "wof:placetype":"locality"
},
  "geometry": {"coordinates":[130.65761000000001,32.96113],"type":"Point"}
}