{
  "type": "Feature",
  "properties": {
    "gn:admin1_code":"21.0",
    "gn:admin2_code":"1848441.0",
    "gn:asciiname":"Motoyashiki",
    "gn:country_code":"JP",
    "gn:dem":125,
    "gn:feature_class":"P",
    "gn:feature_code":"PPLL",
    "gn:name":"Motoyashiki",
    "gn:population":0,
    "gn:timezone":"Asia/Tokyo",
    "iso:country":"JP",
    "name:jpn_x_preferred":[
        "\u672c\u5c4b\u6577"
    ],
    "name:jpn_x_variant":[
        "\u3082\u3068\u3084\u3057\u304d",
        "\u30e2\u30c8\u30e4\u30b7\u30ad"
    ],
    "wof:name":"Motoyashiki",
    "wof:placetype":"locality"
},
  "geometry": {"coordinates":[130.75238999999999,32.55649],"type":"Point"}
}