{
  "type": "Feature",
  "properties": {
    "gn:admin1_code":"19.0",
    "gn:admin2_code":"1848350.0",
    "gn:admin3_code":"14106.0",
    "gn:asciiname":"Iwasakicho",
    "gn:country_code":"JP",
    "gn:dem":49,
    "gn:feature_class":"P",
    "gn:feature_code":"PPL",
    "gn:name":"Iwasakich\u014d",
    "gn:population":0,
    "gn:timezone":"Asia/Tokyo",
    "iso:country":"JP",
    "name:jpn_x_preferred":[
        "\u5ca9\u5d0e\u753a"
    ],
    "name:jpn_x_variant":[
        "\u3044\u308f\u3055\u304d\u3061\u3087\u3046",
        "\u30a4\u30ef\u30b5\u30ad\u30c1\u30e7\u30a6"
    ],
    "name:und_x_variant":[
        "Iwasakich\u014d"
    ],
    "wof:name":"Iwasakicho",
    "wof:placetype":"locality"
},
  "geometry": {"coordinates":[139.58578,35.448],"type":"Point"}
}