{
  "type": "Feature",
  "properties": {
    "gn:admin1_code":"19",
    "gn:admin2_code":"1863429.0",
    "gn:asciiname":"Hirasawa",
    "gn:country_code":"JP",
    "gn:dem":125,
    "gn:feature_class":"P",
    "gn:feature_code":"PPL",
    "gn:name":"Hirasawa",
    "gn:population":0,
    "gn:timezone":"Asia/Tokyo",
    "iso:country":"JP",
    "name:jpn_x_preferred":[
        "\u5e73\u6ca2"
    ],
    "wof:name":"Hirasawa",
    "wof:placetype":"locality"
},
  "geometry": {"coordinates":[139.20861000000002,35.3672],"type":"Point"}
}