{
  "type": "Feature",
  "properties": {
    "gn:admin1_code":"21.0",
    "gn:admin2_code":"1858418.0",
    "gn:admin3_code":"43104.0",
    "gn:asciiname":"Jonanmachi-shimomiyaji",
    "gn:country_code":"JP",
    "gn:dem":16,
    "gn:feature_class":"P",
    "gn:feature_code":"PPL",
    "gn:name":"J\u014dnanmachi-shimomiyaji",
    "gn:population":0,
    "gn:timezone":"Asia/Tokyo",
    "iso:country":"JP",
    "name:jpn_x_preferred":[
        "\u57ce\u5357\u753a\u4e0b\u5bae\u5730"
    ],
    "name:jpn_x_variant":[
        "\u3058\u3087\u3046\u306a\u3093\u307e\u3061\u3057\u3082\u307f\u3084\u3058",
        "\u30b8\u30e7\u30a6\u30ca\u30f3\u30de\u30c1\u30b7\u30e2\u30df\u30e4\u30b8"
    ],
    "name:und_x_variant":[
        "J\u014dnanmachi-shimomiyaji"
    ],
    "wof:name":"Jonanmachi-shimomiyaji",
    "wof:placetype":"locality"
},
  "geometry": {"coordinates":[130.73633999999998,32.70326],"type":"Point"}
}