{
  "type": "Feature",
  "properties": {
    "gn:admin1_code":"33.0",
    "gn:admin2_code":"1859936.0",
    "gn:asciiname":"Hiranita",
    "gn:country_code":"JP",
    "gn:dem":346,
    "gn:feature_class":"P",
    "gn:feature_code":"PPLL",
    "gn:name":"Hiranita",
    "gn:population":0,
    "gn:timezone":"Asia/Tokyo",
    "iso:country":"JP",
    "name:jpn_x_preferred":[
        "\u5e73\u4ec1\u7530"
    ],
    "wof:name":"Hiranita",
    "wof:placetype":"locality"
},
  "geometry": {"coordinates":[130.09857,33.03415],"type":"Point"}
}