{
  "type": "Feature",
  "properties": {
    "gn:admin1_code":"3.0",
    "gn:admin2_code":"7439937.0",
    "gn:asciiname":"Tonan Han Kinen Kanko Mura",
    "gn:country_code":"JP",
    "gn:dem":20,
    "gn:feature_class":"P",
    "gn:feature_code":"PPL",
    "gn:name":"Tonan Han Kinen Kank\u014d Mura",
    "gn:population":0,
    "gn:timezone":"Asia/Tokyo",
    "iso:country":"JP",
    "name:jpn_x_preferred":[
        "\u6597\u5357\u85e9\u8a18\u5ff5\u89b3\u5149\u6751"
    ],
    "name:jpn_x_variant":[
        "\u3068\u306a\u3093\u306f\u3093\u304d\u306d\u3093\u304b\u3093\u3053\u3046\u3080\u3089",
        "\u30c8\u30ca\u30f3\u30cf\u30f3\u30ad\u30cd\u30f3\u30ab\u30f3\u30b3\u30a6\u30e0\u30e9"
    ],
    "name:und_x_variant":[
        "Tonan Han Kinen Kank\u014d Mura"
    ],
    "wof:name":"Tonan Han Kinen Kanko Mura",
    "wof:placetype":"locality"
},
  "geometry": {"coordinates":[141.36566000000005,40.78877],"type":"Point"}
}