{
  "type": "Feature",
  "properties": {
    "gn:admin1_code":"21.0",
    "gn:admin2_code":"7412706.0",
    "gn:admin3_code":"43447.0",
    "gn:asciiname":"Konakadake",
    "gn:country_code":"JP",
    "gn:dem":415,
    "gn:feature_class":"P",
    "gn:feature_code":"PPL",
    "gn:name":"Konakadake",
    "gn:population":0,
    "gn:timezone":"Asia/Tokyo",
    "iso:country":"JP",
    "name:jpn_x_preferred":[
        "\u5c0f\u4e2d\u7af9"
    ],
    "name:jpn_x_variant":[
        "\u3053\u306a\u304b\u3060\u3051",
        "\u30b3\u30ca\u30ab\u30c0\u30b1"
    ],
    "wof:name":"Konakadake",
    "wof:placetype":"locality"
},
  "geometry": {"coordinates":[131.05459999999999,32.66765],"type":"Point"}
}