{
  "type": "Feature",
  "properties": {
    "gn:admin1_code":"25.0",
    "gn:admin2_code":"1864313.0",
    "gn:asciiname":"Horiura",
    "gn:country_code":"JP",
    "gn:dem":363,
    "gn:feature_class":"P",
    "gn:feature_code":"PPLL",
    "gn:name":"Horiura",
    "gn:population":0,
    "gn:timezone":"Asia/Tokyo",
    "iso:country":"JP",
    "name:jpn_x_preferred":[
        "\u5800\u6d66"
    ],
    "name:jpn_x_variant":[
        "\u307b\u308a\u3046\u3089",
        "\u30db\u30ea\u30a6\u30e9"
    ],
    "wof:name":"Horiura",
    "wof:placetype":"locality"
},
  "geometry": {"coordinates":[130.92278999999999,32.04268],"type":"Point"}
}