{
  "type": "Feature",
  "properties": {
    "gn:admin1_code":"4.0",
    "gn:admin2_code":"2110982.0",
    "gn:asciiname":"Iwaimae",
    "gn:country_code":"JP",
    "gn:dem":17,
    "gn:feature_class":"P",
    "gn:feature_code":"PPLL",
    "gn:name":"Iwaimae",
    "gn:population":0,
    "gn:timezone":"Asia/Tokyo",
    "iso:country":"JP",
    "name:jpn_x_preferred":[
        "\u5ca9\u4e95\u524d"
    ],
    "name:jpn_x_variant":[
        "\u3044\u308f\u3044\u307e\u3048",
        "\u30a4\u30ef\u30a4\u30de\u30a8"
    ],
    "wof:name":"Iwaimae",
    "wof:placetype":"locality"
},
  "geometry": {"coordinates":[140.02163000000002,35.41569000000001],"type":"Point"}
}