{
  "type": "Feature",
  "properties": {
    "gn:admin1_code":"34.0",
    "gn:admin2_code":"1858728.0",
    "gn:asciiname":"Horimukai",
    "gn:country_code":"JP",
    "gn:dem":8,
    "gn:feature_class":"P",
    "gn:feature_code":"PPLL",
    "gn:name":"Horimukai",
    "gn:population":0,
    "gn:timezone":"Asia/Tokyo",
    "iso:country":"JP",
    "name:jpn_x_preferred":[
        "\u5800\u5411\u3000"
    ],
    "wof:name":"Horimukai",
    "wof:placetype":"locality"
},
  "geometry": {"coordinates":[139.79897,35.93073],"type":"Point"}
}