{
  "type": "Feature",
  "properties": {
    "gn:admin1_code":"4.0",
    "gn:admin2_code":"1859468.0",
    "gn:asciiname":"Seiwaichiba",
    "gn:country_code":"JP",
    "gn:dem":68,
    "gn:feature_class":"P",
    "gn:feature_code":"PPL",
    "gn:name":"Seiwaichiba",
    "gn:population":0,
    "gn:timezone":"Asia/Tokyo",
    "iso:country":"JP",
    "name:jpn_x_preferred":[
        "\u6e05\u548c\u5e02\u5834"
    ],
    "name:jpn_x_variant":[
        "\u305b\u3044\u308f\u3044\u3061\u3070",
        "\u30bb\u30a4\u30ef\u30a4\u30c1\u30d0"
    ],
    "wof:name":"Seiwaichiba",
    "wof:placetype":"locality"
},
  "geometry": {"coordinates":[139.99306999999999,35.25932],"type":"Point"}
}