{
  "type": "Feature",
  "properties": {
    "gn:admin1_code":"12.0",
    "gn:admin2_code":"7428089.0",
    "gn:admin3_code":"1633.0",
    "gn:asciiname":"Nukabira-gensenkyo",
    "gn:country_code":"JP",
    "gn:dem":548,
    "gn:feature_class":"P",
    "gn:feature_code":"PPL",
    "gn:name":"Nukabira-gensenky\u014d",
    "gn:population":0,
    "gn:timezone":"Asia/Tokyo",
    "iso:country":"JP",
    "name:jpn_x_preferred":[
        "\u306c\u304b\u3073\u3089\u6e90\u6cc9\u90f7"
    ],
    "name:jpn_x_variant":[
        "\u306c\u304b\u3073\u3089\u3052\u3093\u305b\u3093\u304d\u3087\u3046",
        "\u30cc\u30ab\u30d3\u30e9\u30b2\u30f3\u30bb\u30f3\u30ad\u30e7\u30a6"
    ],
    "name:und_x_variant":[
        "Nukapira",
        "Nukabira",
        "Nukabira-gensenky\u014d"
    ],
    "wof:name":"Nukabira-gensenkyo",
    "wof:placetype":"locality"
},
  "geometry": {"coordinates":[143.19054,43.36528],"type":"Point"}
}