{
  "type": "Feature",
  "properties": {
    "gn:admin1_code":"39.0",
    "gn:admin2_code":"1850156.0",
    "gn:asciiname":"Obaracho",
    "gn:country_code":"JP",
    "gn:dem":5,
    "gn:feature_class":"P",
    "gn:feature_code":"PPL",
    "gn:name":"\u014cbarach\u014d",
    "gn:population":0,
    "gn:timezone":"Asia/Tokyo",
    "iso:country":"JP",
    "name:jpn_x_preferred":[
        "\u5927\u539f\u753a"
    ],
    "name:und_x_variant":[
        "\u014cbarach\u014d"
    ],
    "wof:name":"Obaracho",
    "wof:placetype":"locality"
},
  "geometry": {"coordinates":[134.57547,34.03114],"type":"Point"}
}