{
  "type": "Feature",
  "properties": {
    "gn:admin1_code":"37.0",
    "gn:admin2_code":"7418320.0",
    "gn:asciiname":"Sokoji",
    "gn:country_code":"JP",
    "gn:dem":27,
    "gn:feature_class":"P",
    "gn:feature_code":"PPL",
    "gn:name":"S\u014dk\u014dji",
    "gn:population":0,
    "gn:timezone":"Asia/Tokyo",
    "iso:country":"JP",
    "name:jpn_x_preferred":[
        "\u5b97\u5149\u5bfa"
    ],
    "name:und_x_variant":[
        "S\u014dk\u014dji"
    ],
    "wof:name":"Sokoji",
    "wof:placetype":"locality"
},
  "geometry": {"coordinates":[138.95175,35.02578],"type":"Point"}
}