{
  "type": "Feature",
  "properties": {
    "gn:admin1_code":"7.0",
    "gn:admin2_code":"1851269.0",
    "gn:admin3_code":"40608.0",
    "gn:asciiname":"Tamagawa",
    "gn:country_code":"JP",
    "gn:dem":46,
    "gn:feature_class":"P",
    "gn:feature_code":"PPLL",
    "gn:name":"Tamagawa",
    "gn:population":0,
    "gn:timezone":"Asia/Tokyo",
    "iso:country":"JP",
    "name:deu_x_preferred":[
        "Tamagawa"
    ],
    "name:jpn_x_preferred":[
        "\u7389\u5ddd"
    ],
    "name:kor_x_preferred":[
        "\ub2e4\ub9c8\uac00\uc640"
    ],
    "wof:name":"Tamagawa",
    "wof:placetype":"locality"
},
  "geometry": {"coordinates":[130.85298,33.64024000000001],"type":"Point"}
}