{
  "type": "Feature",
  "properties": {
    "gn:admin1_code":"6.0",
    "gn:admin2_code":"1863982.0",
    "gn:asciiname":"Kidonouchicho",
    "gn:country_code":"JP",
    "gn:dem":41,
    "gn:feature_class":"P",
    "gn:feature_code":"PPL",
    "gn:name":"Kidonouchich\u014d",
    "gn:population":0,
    "gn:timezone":"Asia/Tokyo",
    "iso:country":"JP",
    "name:jpn_x_preferred":[
        "\u57ce\u6238\u30ce\u5185\u753a"
    ],
    "name:und_x_variant":[
        "Kidonouchich\u014d"
    ],
    "wof:name":"Kidonouchicho",
    "wof:placetype":"locality"
},
  "geometry": {"coordinates":[136.29854,36.00367],"type":"Point"}
}