{
  "type": "Feature",
  "properties": {
    "gn:admin1_code":"46.0",
    "gn:asciiname":"Iriyama",
    "gn:country_code":"JP",
    "gn:dem":346,
    "gn:feature_class":"P",
    "gn:feature_code":"PPLL",
    "gn:name":"Iriyama",
    "gn:population":0,
    "gn:timezone":"Asia/Tokyo",
    "iso:country":"JP",
    "name:jpn_x_preferred":[
        "\u5165\u5c71"
    ],
    "wof:name":"Iriyama",
    "wof:placetype":"locality"
},
  "geometry": {"coordinates":[138.54414,35.29478],"type":"Point"}
}