{
  "type": "Feature",
  "properties": {
    "gn:admin1_code":"08",
    "gn:admin2_code":"2112535.0",
    "gn:asciiname":"Ueda",
    "gn:country_code":"JP",
    "gn:dem":7,
    "gn:feature_class":"P",
    "gn:feature_code":"PPL",
    "gn:name":"Ueda",
    "gn:population":0,
    "gn:timezone":"Asia/Tokyo",
    "iso:country":"JP",
    "name:ara_x_preferred":[
        "\u064a\u0648\u064a\u062f\u0627"
    ],
    "name:ceb_x_preferred":[
        "Ueda"
    ],
    "name:ces_x_preferred":[
        "Ueda"
    ],
    "name:deu_x_preferred":[
        "Ueda"
    ],
    "name:ita_x_preferred":[
        "Ueda"
    ],
    "name:mlg_x_preferred":[
        "Ueda"
    ],
    "name:por_x_preferred":[
        "Ueda"
    ],
    "name:rus_x_preferred":[
        "\u0423\u044d\u0434\u0430"
    ],
    "name:swe_x_preferred":[
        "Ueda"
    ],
    "name:ukr_x_preferred":[
        "\u0423\u0435\u0434\u0430"
    ],
    "wof:name":"Ueda",
    "wof:placetype":"locality"
},
  "geometry": {"coordinates":[140.80000000000001,36.91667],"type":"Point"}
}