{
  "type": "Feature",
  "properties": {
    "gn:admin1_code":"8.0",
    "gn:admin2_code":"9035647.0",
    "gn:asciiname":"Funehikimachi-arawata",
    "gn:country_code":"JP",
    "gn:dem":407,
    "gn:feature_class":"P",
    "gn:feature_code":"PPL",
    "gn:name":"Funehikimachi-arawata",
    "gn:population":0,
    "gn:timezone":"Asia/Tokyo",
    "iso:country":"JP",
    "name:jpn_x_preferred":[
        "\u8239\u5f15\u753a\u8352\u548c\u7530"
    ],
    "wof:name":"Funehikimachi-arawata",
    "wof:placetype":"locality"
},
  "geometry": {"coordinates":[140.5334,37.46901],"type":"Point"}
}