{
  "type": "Feature",
  "properties": {
    "gn:admin1_code":"16",
    "gn:admin2_code":"2112655.0",
    "gn:asciiname":"Shimonozaike",
    "gn:country_code":"JP",
    "gn:dem":84,
    "gn:feature_class":"P",
    "gn:feature_code":"PPLL",
    "gn:name":"Shimonozaike",
    "gn:population":0,
    "gn:timezone":"Asia/Tokyo",
    "iso:country":"JP",
    "name:jpn_x_preferred":[
        "\u4e0b\u91ce\u5728\u5bb6"
    ],
    "name:und_x_variant":[
        "Shimonzaki",
        "Shimonozaike"
    ],
    "wof:name":"Shimonozaike",
    "wof:placetype":"locality"
},
  "geometry": {"coordinates":[141.41093999999995,38.78695],"type":"Point"}
}