{
  "type": "Feature",
  "properties": {
    "gn:admin1_code":"10.0",
    "gn:admin2_code":"7453747.0",
    "gn:admin3_code":"10429.0",
    "gn:asciiname":"Sugao",
    "gn:country_code":"JP",
    "gn:dem":775,
    "gn:feature_class":"P",
    "gn:feature_code":"PPL",
    "gn:name":"Sugao",
    "gn:population":0,
    "gn:timezone":"Asia/Tokyo",
    "iso:country":"JP",
    "name:jpn_x_preferred":[
        "\u9808\u8cc0\u5c3e"
    ],
    "wof:name":"Sugao",
    "wof:placetype":"locality"
},
  "geometry": {"coordinates":[138.68534,36.50241],"type":"Point"}
}