{
  "type": "Feature",
  "properties": {
    "gn:admin1_code":"19.0",
    "gn:admin2_code":"1848350.0",
    "gn:admin3_code":"14116.0",
    "gn:asciiname":"Kami'iidacho",
    "gn:country_code":"JP",
    "gn:dem":41,
    "gn:feature_class":"P",
    "gn:feature_code":"PPL",
    "gn:name":"Kami\u2019iidach\u014d",
    "gn:population":0,
    "gn:timezone":"Asia/Tokyo",
    "iso:country":"JP",
    "name:jpn_x_preferred":[
        "\u4e0a\u98ef\u7530\u753a"
    ],
    "name:und_x_variant":[
        "Kami\u2019iidach\u014d"
    ],
    "wof:name":"Kami'iidacho",
    "wof:placetype":"locality"
},
  "geometry": {"coordinates":[139.48269999999999,35.42185999999999],"type":"Point"}
}