{
  "type": "Feature",
  "properties": {
    "gn:admin1_code":"21.0",
    "gn:admin2_code":"1864975.0",
    "gn:admin3_code":"43423.0",
    "gn:asciiname":"Kurogawa",
    "gn:country_code":"JP",
    "gn:dem":717,
    "gn:feature_class":"P",
    "gn:feature_code":"PPLL",
    "gn:name":"Kurogawa",
    "gn:population":0,
    "gn:timezone":"Asia/Tokyo",
    "iso:country":"JP",
    "name:jpn_x_preferred":[
        "\u9ed2\u5ddd"
    ],
    "name:jpn_x_variant":[
        "\u304f\u308d\u304c\u308f",
        "\u30af\u30ed\u30ac\u30ef"
    ],
    "wof:name":"Kurogawa",
    "wof:placetype":"locality"
},
  "geometry": {"coordinates":[131.14058,33.07937],"type":"Point"}
}