{
  "type": "Feature",
  "properties": {
    "gn:admin1_code":"4.0",
    "gn:admin2_code":"2112663.0",
    "gn:asciiname":"Minami-kokubunjidai",
    "gn:country_code":"JP",
    "gn:dem":30,
    "gn:feature_class":"P",
    "gn:feature_code":"PPL",
    "gn:name":"Minami-kokubunjidai",
    "gn:population":0,
    "gn:timezone":"Asia/Tokyo",
    "iso:country":"JP",
    "name:jpn_x_preferred":[
        "\u5357\u56fd\u5206\u5bfa\u53f0"
    ],
    "name:jpn_x_variant":[
        "\u307f\u306a\u307f\u3053\u304f\u3076\u3093\u3058\u3060\u3044",
        "\u30df\u30ca\u30df\u30b3\u30af\u30d6\u30f3\u30b8\u30c0\u30a4"
    ],
    "wof:name":"Minami-kokubunjidai",
    "wof:placetype":"locality"
},
  "geometry": {"coordinates":[140.11452,35.4926],"type":"Point"}
}