{
  "type": "Feature",
  "properties": {
    "gn:admin1_code":"42.0",
    "gn:admin2_code":"1861653.0",
    "gn:asciiname":"Gejo Gawa",
    "gn:country_code":"JP",
    "gn:dem":4,
    "gn:feature_class":"P",
    "gn:feature_code":"PPL",
    "gn:name":"Gej\u014d Gawa",
    "gn:population":0,
    "gn:timezone":"Asia/Tokyo",
    "iso:country":"JP",
    "name:jpn_x_preferred":[
        "\u4e0b\u6761\u5ddd"
    ],
    "name:und_x_variant":[
        "Gej\u014d Gawa"
    ],
    "wof:name":"Gejo Gawa",
    "wof:placetype":"locality"
},
  "geometry": {"coordinates":[137.11151999999998,36.76208],"type":"Point"}
}