{
  "type": "Feature",
  "properties": {
    "gn:admin1_code":"12.0",
    "gn:admin2_code":"7428078.0",
    "gn:admin3_code":"1663.0",
    "gn:asciiname":"Watarichirippu",
    "gn:country_code":"JP",
    "gn:dem":25,
    "gn:feature_class":"P",
    "gn:feature_code":"PPL",
    "gn:name":"Watarichirippu",
    "gn:population":0,
    "gn:timezone":"Asia/Tokyo",
    "iso:country":"JP",
    "name:jpn_x_preferred":[
        "\u6e21\u6563\u5e03"
    ],
    "name:jpn_x_variant":[
        "\u308f\u305f\u308a\u3061\u308a\u3063\u3077",
        "\u30ef\u30bf\u30ea\u30c1\u30ea\u30c3\u30d7"
    ],
    "wof:name":"Watarichirippu",
    "wof:placetype":"locality"
},
  "geometry": {"coordinates":[145.05458999999999,43.03871],"type":"Point"}
}