{
  "type": "Feature",
  "properties": {
    "gn:admin1_code":"24.0",
    "gn:admin2_code":"2112261.0",
    "gn:asciiname":"Mone",
    "gn:country_code":"JP",
    "gn:dem":23,
    "gn:feature_class":"P",
    "gn:feature_code":"PPL",
    "gn:name":"M\u014dne",
    "gn:population":0,
    "gn:timezone":"Asia/Tokyo",
    "iso:country":"JP",
    "name:bul_x_preferred":[
        "\u041c\u043e\u043d\u0435"
    ],
    "name:ceb_x_preferred":[
        "Mone"
    ],
    "name:deu_x_preferred":[
        "Mone"
    ],
    "name:fra_x_preferred":[
        "Mone"
    ],
    "name:jpn_x_preferred":[
        "\u821e\u6839"
    ],
    "name:jpn_x_variant":[
        "\u3082\u3046\u306d",
        "\u30e2\u30a6\u30cd"
    ],
    "name:rus_x_preferred":[
        "\u041c\u043e\u043d\u0435"
    ],
    "name:swe_x_preferred":[
        "Mone"
    ],
    "name:ukr_x_preferred":[
        "\u041c\u043e\u043d\u0435"
    ],
    "name:und_x_variant":[
        "M\u014dne"
    ],
    "wof:name":"Mone",
    "wof:placetype":"locality"
},
  "geometry": {"coordinates":[141.62339,38.90176],"type":"Point"}
}