{
  "type": "Feature",
  "properties": {
    "gn:admin1_code":"12.0",
    "gn:admin2_code":"2129370.0",
    "gn:asciiname":"Nishiko",
    "gn:country_code":"JP",
    "gn:dem":5,
    "gn:feature_class":"P",
    "gn:feature_code":"PPL",
    "gn:name":"Nishik\u014d",
    "gn:population":0,
    "gn:timezone":"Asia/Tokyo",
    "iso:country":"JP",
    "name:jpn_x_preferred":[
        "\u897f\u6e2f"
    ],
    "name:jpn_x_variant":[
        "\u306b\u3057\u3053\u3046",
        "\u30cb\u30b7\u30b3\u30a6"
    ],
    "name:und_x_variant":[
        "Nishik\u014d"
    ],
    "wof:name":"Nishiko",
    "wof:placetype":"locality"
},
  "geometry": {"coordinates":[144.33163999999999,43.00168],"type":"Point"}
}