{
  "type": "Feature",
  "properties": {
    "gn:admin1_code":"21.0",
    "gn:admin2_code":"7412708.0",
    "gn:admin3_code":"43511.0",
    "gn:asciiname":"Kuryo",
    "gn:country_code":"JP",
    "gn:dem":296,
    "gn:feature_class":"P",
    "gn:feature_code":"PPL",
    "gn:name":"Kury\u014d",
    "gn:population":0,
    "gn:timezone":"Asia/Tokyo",
    "iso:country":"JP",
    "name:jpn_x_preferred":[
        "\u4e45\u9818"
    ],
    "name:jpn_x_variant":[
        "\u304f\u308a\u3087\u3046",
        "\u30af\u30ea\u30e7\u30a6"
    ],
    "name:und_x_variant":[
        "Kury\u014d"
    ],
    "wof:name":"Kuryo",
    "wof:placetype":"locality"
},
  "geometry": {"coordinates":[130.82082,32.39843],"type":"Point"}
}