{
  "type": "Feature",
  "properties": {
    "gn:admin1_code":"29.0",
    "gn:admin2_code":"1853313.0",
    "gn:asciiname":"Akadama",
    "gn:country_code":"JP",
    "gn:dem":22,
    "gn:feature_class":"P",
    "gn:feature_code":"PPL",
    "gn:name":"Akadama",
    "gn:population":0,
    "gn:timezone":"Asia/Tokyo",
    "iso:country":"JP",
    "name:jpn_x_preferred":[
        "\u8d64\u7389"
    ],
    "wof:name":"Akadama",
    "wof:placetype":"locality"
},
  "geometry": {"coordinates":[138.53249,37.99478],"type":"Point"}
}