{
  "type": "Feature",
  "properties": {
    "gn:admin1_code":"28",
    "gn:admin2_code":"1848592.0",
    "gn:asciiname":"Yamato-Takada",
    "gn:country_code":"JP",
    "gn:dem":56,
    "gn:feature_class":"P",
    "gn:feature_code":"PPLA2",
    "gn:name":"Yamato-Takada",
    "gn:population":0,
    "gn:timezone":"Asia/Tokyo",
    "iso:country":"JP",
    "name:jpn_x_preferred":[
        "\u5927\u548c\u9ad8\u7530"
    ],
    "name:und_x_variant":[
        "Takadach\u014d",
        "Takada",
        "Yamato-Takada"
    ],
    "wof:name":"Yamato-Takada",
    "wof:placetype":"locality"
},
  "geometry": {"coordinates":[135.75,34.51667],"type":"Point"}
}