{
  "type": "Feature",
  "properties": {
    "gn:admin1_code":"45.0",
    "gn:admin2_code":"1852222.0",
    "gn:asciiname":"Shioiricho",
    "gn:country_code":"JP",
    "gn:dem":22,
    "gn:feature_class":"P",
    "gn:feature_code":"PPL",
    "gn:name":"Shioirich\u014d",
    "gn:population":0,
    "gn:timezone":"Asia/Tokyo",
    "iso:country":"JP",
    "name:jpn_x_preferred":[
        "\u6c50\u5165\u753a"
    ],
    "name:und_x_variant":[
        "Shioirich\u014d"
    ],
    "wof:name":"Shioiricho",
    "wof:placetype":"locality"
},
  "geometry": {"coordinates":[130.9171,33.97228],"type":"Point"}
}