{
  "type": "Feature",
  "properties": {
    "gn:admin1_code":"21.0",
    "gn:admin2_code":"1849062.0",
    "gn:asciiname":"Iwakosomachi",
    "gn:country_code":"JP",
    "gn:dem":55,
    "gn:feature_class":"P",
    "gn:feature_code":"PPL",
    "gn:name":"Iwakosomachi",
    "gn:population":0,
    "gn:timezone":"Asia/Tokyo",
    "iso:country":"JP",
    "name:jpn_x_preferred":[
        "\u5ca9\u53e4\u66fd\u753a"
    ],
    "name:jpn_x_variant":[
        "\u3044\u308f\u3053\u305d\u307e\u3061",
        "\u30a4\u30ef\u30b3\u30bd\u30de\u30c1"
    ],
    "wof:name":"Iwakosomachi",
    "wof:placetype":"locality"
},
  "geometry": {"coordinates":[130.68681000000001,32.68919],"type":"Point"}
}