{
  "type": "Feature",
  "properties": {
    "iso:country":"JP",
    "name:eng_x_preferred":[
        "Toei 1 Chome"
    ],
    "name:eng_x_variant":[
        "Touei 1 Choume",
        "Toei 1 Chome"
    ],
    "name:jpn_x_preferred":[
        "\uff11\u4e01\u76ee"
    ],
    "name:jpn_x_variant":[
        "\u3068\u3046\u3048\u3044 \uff11\u3061\u3087\u3046\u3081",
        "\u6771\u6804 \uff11\u4e01\u76ee",
        "\uff11\u3061\u3087\u3046\u3081"
    ],
    "qs:gn_local":0,
    "qs:local_max":48,
    "qs:local_sum":55,
    "qs:localhoods":3,
    "qs:name":"\uff11\u4e01\u76ee",
    "qs:name_adm0":"\u65e5\u672c",
    "qs:name_adm1":"\u6803\u6728\u770c",
    "qs:name_en":"Toei 1 Chome",
    "qs:name_lau":"\u6771\u6804",
    "qs:name_local":"\u90a3\u9808\u5869\u539f\u5e02",
    "qs:photo_max":17,
    "qs:photo_sum":48,
    "qs:placetype":"Suburb",
    "qs:quad_count":8,
    "qs:woe_adm0":23424856,
    "qs:woe_adm1":2345887,
    "qs:woe_adm2":0,
    "qs:woe_lau":28405581,
    "qs:woe_local":28379178,
    "qs:woe_ver":"7.10.0",
    "wof:lang":[
        "jpn"
    ],
    "wof:name":"\uff11\u4e01\u76ee",
    "wof:placetype":"neighbourhood"
},
  "geometry": {"coordinates":[140.05783099999999,36.971747],"type":"Point"}
}