{
  "type": "Feature",
  "properties": {
    "iso:country":"JP",
    "qs:name":"\u732a\u82d7\u4ee3\u753a",
    "qs:name_adm0":"\u65e5\u672c",
    "qs:name_adm1":"\u798f\u5cf6\u770c",
    "qs:photos":1801,
    "qs:photos_1k":365,
    "qs:photos_9k":8,
    "qs:photos_9r":9,
    "qs:photos_all":1801,
    "qs:photos_sr":14,
    "qs:placetype":"Town",
    "qs:pop_sr":"0",
    "wof:name":"\u732a\u82d7\u4ee3\u753a",
    "wof:placetype":"locality"
},
  "geometry": {"coordinates":[140.11011099999999,37.574582],"type":"Point"}
}