{
  "type": "Feature",
  "properties": {
    "gn:admin1_code":"26",
    "gn:admin2_code":"1852001.0",
    "gn:asciiname":"Seba",
    "gn:country_code":"JP",
    "gn:dem":732,
    "gn:feature_class":"P",
    "gn:feature_code":"PPL",
    "gn:name":"Seba",
    "gn:population":0,
    "gn:timezone":"Asia/Tokyo",
    "iso:country":"JP",
    "name:jpn_x_preferred":[
        "\u6d17\u99ac"
    ],
    "name:und_x_variant":[
        "Shin-seba",
        "Seba"
    ],
    "wof:name":"Seba",
    "wof:placetype":"locality"
},
  "geometry": {"coordinates":[137.91329999999999,36.09028],"type":"Point"}
}