{
  "type": "Feature",
  "properties": {
    "gn:admin1_code":"34",
    "gn:admin2_code":"1861470.0",
    "gn:admin3_code":"11327.0",
    "gn:asciiname":"Nishi-wada",
    "gn:country_code":"JP",
    "gn:dem":65,
    "gn:feature_class":"P",
    "gn:feature_code":"PPL",
    "gn:name":"Nishi-wada",
    "gn:population":0,
    "gn:timezone":"Asia/Tokyo",
    "iso:country":"JP",
    "wof:name":"Nishi-wada",
    "wof:placetype":"locality"
},
  "geometry": {"coordinates":[139.30000000000001,35.96667],"type":"Point"}
}