{
  "type": "Feature",
  "properties": {
    "iso:country":"JP",
    "name:eng_x_preferred":[
        "Uozumichosumiyoshi 2 Chome"
    ],
    "name:eng_x_variant":[
        "Uozumichousumiyoshi 2 Choume",
        "Uozumichosumiyoshi 2 Chome"
    ],
    "name:jpn_x_preferred":[
        "\uff12\u4e01\u76ee"
    ],
    "name:jpn_x_variant":[
        "\u3046\u304a\u305a\u307f\u3061\u3087\u3046\u3059\u307f\u3088\u3057 \uff12\u3061\u3087\u3046\u3081",
        "\u9b5a\u4f4f\u753a\u4f4f\u5409 \uff12\u4e01\u76ee",
        "\uff12\u3061\u3087\u3046\u3081"
    ],
    "name:unk_x_variant":[
        "\uff12\u4e01\u76ee"
    ],
    "qs:gn_local":0,
    "qs:local_max":588,
    "qs:local_sum":1873,
    "qs:localhoods":12,
    "qs:name":"\uff12\u4e01\u76ee",
    "qs:name_adm0":"\u65e5\u672c",
    "qs:name_adm1":"\u5175\u5eab\u770c",
    "qs:name_en":"Uozumichosumiyoshi 2 Chome",
    "qs:name_lau":"\u9b5a\u4f4f\u753a\u4f4f\u5409",
    "qs:name_local":"\u660e\u77f3\u5e02",
    "qs:photo_max":15,
    "qs:photo_sum":17,
    "qs:placetype":"Suburb",
    "qs:quad_count":2,
    "qs:woe_adm0":23424856,
    "qs:woe_adm1":2345862,
    "qs:woe_adm2":0,
    "qs:woe_lau":28462128,
    "qs:woe_local":1116946,
    "qs:woe_ver":"7.10.0",
    "wof:lang":[
        "jpn"
    ],
    "wof:name":"\uff12\u4e01\u76ee",
    "wof:placetype":"neighbourhood"
},
  "geometry": {"coordinates":[134.90451899999999,34.680122],"type":"Point"}
}