{
  "type": "Feature",
  "properties": {
    "gn:country":"JP",
    "gn:fcode":"ADMD",
    "gn:population":0,
    "iso:country":"JP",
    "name:eng_x_preferred":[
        "Mizuho"
    ],
    "name:eng_x_variant":[
        "Mizuho-machi"
    ],
    "name:jpn_x_preferred":[
        "\u745e\u7a42\u753a"
    ],
    "name:und_x_variant":[
        "Mizuho"
    ],
    "qs:name":"Mizuho-machi",
    "qs:photos_9r":0,
    "qs:photos_sr":0,
    "qs:pop_sr":"0",
    "wof:name":"Mizuho",
    "wof:placetype":"localadmin",
    "wof:population":0
},
  "geometry": {"coordinates":[139.35405,35.77199],"type":"Point"}
}