{
  "type": "Feature",
  "properties": {
    "gn:admin1_code":"4.0",
    "gn:admin2_code":"2112997.0",
    "gn:admin3_code":"12424.0",
    "gn:asciiname":"Nakatomi-shinden",
    "gn:country_code":"JP",
    "gn:dem":4,
    "gn:feature_class":"P",
    "gn:feature_code":"PPLL",
    "gn:name":"Nakatomi-shinden",
    "gn:population":0,
    "gn:timezone":"Asia/Tokyo",
    "iso:country":"JP",
    "name:jpn_x_preferred":[
        "\u4e2d\u5bcc\u65b0\u7530"
    ],
    "name:jpn_x_variant":[
        "\u306a\u304b\u3068\u307f\u3057\u3093\u3067\u3093",
        "\u30ca\u30ab\u30c8\u30df\u30b7\u30f3\u30c7\u30f3"
    ],
    "wof:name":"Nakatomi-shinden",
    "wof:placetype":"locality"
},
  "geometry": {"coordinates":[140.35356000000002,35.44728],"type":"Point"}
}