{
  "type": "Feature",
  "properties": {
    "gn:admin1_code":"26",
    "gn:admin2_code":"1853055.0",
    "gn:asciiname":"Tomono",
    "gn:country_code":"JP",
    "gn:dem":644,
    "gn:feature_class":"P",
    "gn:feature_code":"PPL",
    "gn:name":"Tomono",
    "gn:population":0,
    "gn:timezone":"Asia/Tokyo",
    "iso:country":"JP",
    "name:fra_x_preferred":[
        "Tomono"
    ],
    "name:jpn_x_preferred":[
        "\u4f34\u91ce"
    ],
    "name:msa_x_preferred":[
        "Tomono"
    ],
    "name:und_x_variant":[
        "Bammachi",
        "Tomomachi",
        "Tomono"
    ],
    "wof:name":"Tomono",
    "wof:placetype":"locality"
},
  "geometry": {"coordinates":[138.42660000000001,36.24716],"type":"Point"}
}