{
  "type": "Feature",
  "properties": {
    "gn:admin1_code":"29.0",
    "gn:admin2_code":"1850218.0",
    "gn:asciiname":"Kuwagarazawa",
    "gn:country_code":"JP",
    "gn:dem":578,
    "gn:feature_class":"P",
    "gn:feature_code":"PPL",
    "gn:name":"Kuwagarazawa",
    "gn:population":0,
    "gn:timezone":"Asia/Tokyo",
    "iso:country":"JP",
    "name:jpn_x_preferred":[
        "\u936c\u67c4\u6ca2"
    ],
    "wof:name":"Kuwagarazawa",
    "wof:placetype":"locality"
},
  "geometry": {"coordinates":[138.77875,37.03937],"type":"Point"}
}