{
  "type": "Feature",
  "properties": {
    "gn:admin1_code":"29",
    "gn:admin2_code":"1855427.0",
    "gn:admin3_code":"15103.0",
    "gn:asciiname":"Dekijima",
    "gn:country_code":"JP",
    "gn:dem":2,
    "gn:feature_class":"P",
    "gn:feature_code":"PPL",
    "gn:name":"Dekijima",
    "gn:population":0,
    "gn:timezone":"Asia/Tokyo",
    "iso:country":"JP",
    "name:jpn_x_preferred":[
        "\u51fa\u6765\u5cf6"
    ],
    "name:und_x_variant":[
        "Dekishima",
        "Dekijima"
    ],
    "wof:name":"Dekijima",
    "wof:placetype":"locality"
},
  "geometry": {"coordinates":[139.02437,37.89966],"type":"Point"}
}