{
  "type": "Feature",
  "properties": {
    "gn:admin1_code":"36.0",
    "gn:admin2_code":"1857549.0",
    "gn:asciiname":"Mihonosekicho-moriyama",
    "gn:country_code":"JP",
    "gn:dem":102,
    "gn:feature_class":"P",
    "gn:feature_code":"PPL",
    "gn:name":"Mihonosekich\u014d-moriyama",
    "gn:population":0,
    "gn:timezone":"Asia/Tokyo",
    "iso:country":"JP",
    "name:jpn_x_preferred":[
        "\u7f8e\u4fdd\u95a2\u753a\u68ee\u5c71"
    ],
    "name:und_x_variant":[
        "Mihonosekich\u014d-moriyama"
    ],
    "wof:name":"Mihonosekicho-moriyama",
    "wof:placetype":"locality"
},
  "geometry": {"coordinates":[133.21376000000001,35.54989000000001],"type":"Point"}
}