{
  "type": "Feature",
  "properties": {
    "gn:admin1_code":"21.0",
    "gn:admin2_code":"1848441.0",
    "gn:asciiname":"Shimozuru",
    "gn:country_code":"JP",
    "gn:dem":456,
    "gn:feature_class":"P",
    "gn:feature_code":"PPLL",
    "gn:name":"Shimozuru",
    "gn:population":0,
    "gn:timezone":"Asia/Tokyo",
    "iso:country":"JP",
    "name:jpn_x_preferred":[
        "\u4e0b\u9db4"
    ],
    "name:jpn_x_variant":[
        "\u3057\u3082\u3065\u308b",
        "\u30b7\u30e2\u30c5\u30eb"
    ],
    "wof:name":"Shimozuru",
    "wof:placetype":"locality"
},
  "geometry": {"coordinates":[130.87450000000001,32.48788],"type":"Point"}
}