{
  "type": "Feature",
  "properties": {
    "gn:admin1_code":"3.0",
    "gn:admin2_code":"2128302.0",
    "gn:admin3_code":"2441.0",
    "gn:asciiname":"Higashimatsubara",
    "gn:country_code":"JP",
    "gn:dem":91,
    "gn:feature_class":"P",
    "gn:feature_code":"PPL",
    "gn:name":"Higashimatsubara",
    "gn:population":0,
    "gn:timezone":"Asia/Tokyo",
    "iso:country":"JP",
    "name:jpn_x_preferred":[
        "\u6771\u677e\u539f"
    ],
    "name:jpn_x_variant":[
        "\u3072\u304c\u3057\u307e\u3064\u3070\u3089",
        "\u30d2\u30ac\u30b7\u30de\u30c4\u30d0\u30e9"
    ],
    "wof:name":"Higashimatsubara",
    "wof:placetype":"locality"
},
  "geometry": {"coordinates":[141.25226999999995,40.38688],"type":"Point"}
}