{
  "type": "Feature",
  "properties": {
    "gn:admin1_code":"4.0",
    "gn:admin2_code":"2112994.0",
    "gn:asciiname":"Nojiri",
    "gn:country_code":"JP",
    "gn:dem":4,
    "gn:feature_class":"P",
    "gn:feature_code":"PPL",
    "gn:name":"Nojiri",
    "gn:population":0,
    "gn:timezone":"Asia/Tokyo",
    "iso:country":"JP",
    "name:por_x_preferred":[
        "Nojiri"
    ],
    "wof:name":"Nojiri",
    "wof:placetype":"locality"
},
  "geometry": {"coordinates":[140.75,35.76667],"type":"Point"}
}