{
  "type": "Feature",
  "properties": {
    "gn:admin1_code":"9.0",
    "gn:admin2_code":"7418820.0",
    "gn:admin3_code":"21604.0",
    "gn:asciiname":"Magari",
    "gn:country_code":"JP",
    "gn:dem":702,
    "gn:feature_class":"P",
    "gn:feature_code":"PPL",
    "gn:name":"Magari",
    "gn:population":0,
    "gn:timezone":"Asia/Tokyo",
    "iso:country":"JP",
    "name:ceb_x_preferred":[
        "Magari"
    ],
    "name:jpn_x_preferred":[
        "\u99ac\u72e9"
    ],
    "name:swe_x_preferred":[
        "Magari"
    ],
    "wof:name":"Magari",
    "wof:placetype":"locality"
},
  "geometry": {"coordinates":[136.88225,36.25728],"type":"Point"}
}