{
  "type": "Feature",
  "properties": {
    "gn:admin1_code":"21.0",
    "gn:admin2_code":"7413150.0",
    "gn:asciiname":"Fukuhara",
    "gn:country_code":"JP",
    "gn:dem":66,
    "gn:feature_class":"P",
    "gn:feature_code":"PPLL",
    "gn:name":"Fukuhara",
    "gn:population":0,
    "gn:timezone":"Asia/Tokyo",
    "iso:country":"JP",
    "name:jpn_x_preferred":[
        "\u798f\u539f"
    ],
    "name:jpn_x_variant":[
        "\u3075\u304f\u306f\u3089",
        "\u30d5\u30af\u30cf\u30e9"
    ],
    "wof:name":"Fukuhara",
    "wof:placetype":"locality"
},
  "geometry": {"coordinates":[130.72881000000001,33.02372],"type":"Point"}
}