{
  "type": "Feature",
  "properties": {
    "gn:admin1_code":"12.0",
    "gn:admin2_code":"2130058.0",
    "gn:admin3_code":"1641.0",
    "gn:asciiname":"Bisei",
    "gn:country_code":"JP",
    "gn:dem":23,
    "gn:feature_class":"P",
    "gn:feature_code":"PPL",
    "gn:name":"Bisei",
    "gn:population":0,
    "gn:timezone":"Asia/Tokyo",
    "iso:country":"JP",
    "name:jpn_x_preferred":[
        "\u7f8e\u6210"
    ],
    "name:und_x_variant":[
        "T\u014dberi",
        "Bisei"
    ],
    "wof:name":"Bisei",
    "wof:placetype":"locality"
},
  "geometry": {"coordinates":[143.41138000000001,42.50036],"type":"Point"}
}