{
  "type": "Feature",
  "properties": {
    "iso:country":"JP",
    "name:eng_x_preferred":[
        "Nishikaigan 1 Chome"
    ],
    "name:eng_x_variant":[
        "Nishikaigan 1 Choume",
        "Nishikaigan 1 Chome"
    ],
    "name:jpn_x_preferred":[
        "\uff11\u4e01\u76ee"
    ],
    "name:jpn_x_variant":[
        "\u306b\u3057\u304b\u3044\u304c\u3093 \uff11\u3061\u3087\u3046\u3081",
        "\u897f\u6d77\u5cb8 \uff11\u4e01\u76ee",
        "\uff11\u3061\u3087\u3046\u3081"
    ],
    "qs:gn_local":0,
    "qs:local_max":819,
    "qs:local_sum":3269,
    "qs:localhoods":25,
    "qs:name":"\uff11\u4e01\u76ee",
    "qs:name_adm0":"\u65e5\u672c",
    "qs:name_adm1":"\u798f\u5ca1\u770c",
    "qs:name_adm2":"\u9580\u53f8\u533a",
    "qs:name_en":"Nishikaigan 1 Chome",
    "qs:name_lau":"\u897f\u6d77\u5cb8",
    "qs:name_local":"\u5317\u4e5d\u5dde\u5e02",
    "qs:photo_max":15,
    "qs:photo_sum":46,
    "qs:placetype":"Suburb",
    "qs:quad_count":7,
    "qs:woe_adm0":23424856,
    "qs:woe_adm1":58646425,
    "qs:woe_adm2":15015567,
    "qs:woe_lau":28482378,
    "qs:woe_local":1110809,
    "qs:woe_ver":"7.10.0",
    "wof:lang":[
        "jpn"
    ],
    "wof:name":"\uff11\u4e01\u76ee",
    "wof:placetype":"neighbourhood"
},
  "geometry": {"coordinates":[130.95532800000001,33.945046],"type":"Point"}
}