{
  "type": "Feature",
  "properties": {
    "gn:admin1_code":"29",
    "gn:admin2_code":"1852604.0",
    "gn:asciiname":"Iijima",
    "gn:country_code":"JP",
    "gn:dem":4,
    "gn:feature_class":"P",
    "gn:feature_code":"PPL",
    "gn:name":"Iijima",
    "gn:population":0,
    "gn:timezone":"Asia/Tokyo",
    "iso:country":"JP",
    "name:jpn_x_preferred":[
        "\u98ef\u5cf6"
    ],
    "name:und_x_variant":[
        "Ijima",
        "Iijima"
    ],
    "wof:name":"Iijima",
    "wof:placetype":"locality"
},
  "geometry": {"coordinates":[139.28398999999999,37.93672],"type":"Point"}
}