{
  "type": "Feature",
  "properties": {
    "gn:admin1_code":"21.0",
    "gn:admin2_code":"1864975.0",
    "gn:admin3_code":"43424.0",
    "gn:asciiname":"Oyabu",
    "gn:country_code":"JP",
    "gn:dem":482,
    "gn:feature_class":"P",
    "gn:feature_code":"PPLL",
    "gn:name":"Oyabu",
    "gn:population":0,
    "gn:timezone":"Asia/Tokyo",
    "iso:country":"JP",
    "name:jpn_x_preferred":[
        "\u5c0f\u85ea"
    ],
    "name:jpn_x_variant":[
        "\u304a\u3084\u3076",
        "\u30aa\u30e4\u30d6"
    ],
    "wof:name":"Oyabu",
    "wof:placetype":"locality"
},
  "geometry": {"coordinates":[131.02784,33.11575],"type":"Point"}
}