{
  "type": "Feature",
  "properties": {
    "gn:admin1_code":"3.0",
    "gn:admin2_code":"2129525.0",
    "gn:admin3_code":"2387.0",
    "gn:asciiname":"Sunayama",
    "gn:country_code":"JP",
    "gn:dem":19,
    "gn:feature_class":"P",
    "gn:feature_code":"PPL",
    "gn:name":"Sunayama",
    "gn:population":0,
    "gn:timezone":"Asia/Tokyo",
    "iso:country":"JP",
    "name:jpn_x_preferred":[
        "\u7802\u5c71"
    ],
    "name:jpn_x_variant":[
        "\u3059\u306a\u3084\u307e",
        "\u30b9\u30ca\u30e4\u30de"
    ],
    "wof:name":"Sunayama",
    "wof:placetype":"locality"
},
  "geometry": {"coordinates":[140.31196,41.13239],"type":"Point"}
}