{
  "type": "Feature",
  "properties": {
    "gn:admin1_code":"7.0",
    "gn:admin2_code":"1851269.0",
    "gn:admin3_code":"40609.0",
    "gn:asciiname":"Uryu",
    "gn:country_code":"JP",
    "gn:dem":92,
    "gn:feature_class":"P",
    "gn:feature_code":"PPLL",
    "gn:name":"Ury\u016b",
    "gn:population":0,
    "gn:timezone":"Asia/Tokyo",
    "iso:country":"JP",
    "name:jpn_x_preferred":[
        "\u74dc\u751f"
    ],
    "name:und_x_variant":[
        "Ury\u016b"
    ],
    "wof:name":"Uryu",
    "wof:placetype":"locality"
},
  "geometry": {"coordinates":[130.8843,33.59698],"type":"Point"}
}