{
  "type": "Feature",
  "properties": {
    "gn:admin1_code":"11",
    "gn:admin2_code":"1853990.0",
    "gn:asciiname":"Ohama",
    "gn:country_code":"JP",
    "gn:dem":1,
    "gn:feature_class":"P",
    "gn:feature_code":"PPL",
    "gn:name":"\u014chama",
    "gn:population":0,
    "gn:timezone":"Asia/Tokyo",
    "iso:country":"JP",
    "name:deu_x_preferred":[
        "Ohama"
    ],
    "name:und_x_variant":[
        "\u014chama"
    ],
    "wof:name":"Ohama",
    "wof:placetype":"locality"
},
  "geometry": {"coordinates":[133.18333000000001,34.33333],"type":"Point"}
}