{
  "type": "Feature",
  "properties": {
    "gn:admin1_code":"39.0",
    "gn:admin2_code":"7406325.0",
    "gn:asciiname":"Goshono",
    "gn:country_code":"JP",
    "gn:dem":373,
    "gn:feature_class":"P",
    "gn:feature_code":"PPLL",
    "gn:name":"Goshono",
    "gn:population":0,
    "gn:timezone":"Asia/Tokyo",
    "iso:country":"JP",
    "name:jbn_x_preferred":[
        "Goshono"
    ],
    "name:jpn_x_preferred":[
        "\u5fa1\u6240\u91ce\u3000"
    ],
    "wof:name":"Goshono",
    "wof:placetype":"locality"
},
  "geometry": {"coordinates":[134.20136000000002,34.16905],"type":"Point"}
}