{
  "type": "Feature",
  "properties": {
    "gn:admin1_code":"38.0",
    "gn:admin2_code":"1865004.0",
    "gn:asciiname":"Minamiomachi",
    "gn:country_code":"JP",
    "gn:dem":38,
    "gn:feature_class":"P",
    "gn:feature_code":"PPL",
    "gn:name":"Minami\u014dmachi",
    "gn:population":0,
    "gn:timezone":"Asia/Tokyo",
    "iso:country":"JP",
    "name:jpn_x_preferred":[
        "\u5357\u5927\u753a"
    ],
    "name:und_x_variant":[
        "Minami\u014dmachi"
    ],
    "wof:name":"Minamiomachi",
    "wof:placetype":"locality"
},
  "geometry": {"coordinates":[139.42308,36.31916],"type":"Point"}
}