{
  "type": "Feature",
  "properties": {
    "iso:country":"JP",
    "label:eng_x_preferred_longname":[
        "Taishi Town"
    ],
    "label:eng_x_preferred_placetype":[
        "town"
    ],
    "name:eng_x_preferred":[
        "Taishi"
    ],
    "name:eng_x_variant":[
        "Taishi Town"
    ],
    "name:jpn_x_preferred":[
        "\u592a\u5b50\u753a"
    ],
    "qs:name":"\u592a\u5b50\u753a",
    "qs:name_adm0":"\u65e5\u672c",
    "qs:name_adm1":"\u5927\u962a\u5e9c",
    "qs:photos":39,
    "qs:photos_1k":8,
    "qs:photos_9k":1,
    "qs:photos_9r":2,
    "qs:photos_all":49,
    "qs:photos_sr":2,
    "qs:placetype":"Town",
    "qs:pop_sr":"0",
    "wof:name":"Taishi",
    "wof:placetype":"locality"
},
  "geometry": {"coordinates":[135.631349,34.510685],"type":"Point"}
}