{
  "type": "Feature",
  "properties": {
    "gn:admin1_code":"2.0",
    "gn:admin2_code":"2129594.0",
    "gn:admin3_code":"5303.0",
    "gn:asciiname":"Kanda",
    "gn:country_code":"JP",
    "gn:dem":461,
    "gn:feature_class":"P",
    "gn:feature_code":"PPLL",
    "gn:name":"Kanda",
    "gn:population":0,
    "gn:timezone":"Asia/Tokyo",
    "iso:country":"JP",
    "name:jpn_x_preferred":[
        "\u795e\u7530"
    ],
    "name:jpn_x_variant":[
        "\u304b\u3093\u3060",
        "\u30ab\u30f3\u30c0"
    ],
    "wof:name":"Kanda",
    "wof:placetype":"locality"
},
  "geometry": {"coordinates":[140.90733,40.42317],"type":"Point"}
}