{
  "type": "Feature",
  "properties": {
    "gn:admin1_code":"2.0",
    "gn:admin2_code":"2129594.0",
    "gn:admin3_code":"5303.0",
    "gn:asciiname":"Kanda",
    "gn:country_code":"JP",
    "gn:dem":461,
    "gn:feature_class":"P",
    "gn:feature_code":"PPLL",
    "gn:name":"Kanda",
    "gn:population":0,
    "gn:timezone":"Asia/Tokyo",
    "iso:country":"JP",
    "name:cat_x_preferred":[
        "Kanda"
    ],
    "name:ceb_x_preferred":[
        "Kanda"
    ],
    "name:deu_x_preferred":[
        "Kanda"
    ],
    "name:epo_x_preferred":[
        "Kanda"
    ],
    "name:fas_x_preferred":[
        "\u06a9\u0627\u0646\u062f\u0627"
    ],
    "name:fra_x_preferred":[
        "Kanda"
    ],
    "name:jpn_x_preferred":[
        "\u795e\u7530"
    ],
    "name:jpn_x_variant":[
        "\u304b\u3093\u3060",
        "\u30ab\u30f3\u30c0"
    ],
    "name:new_x_preferred":[
        "\u0915\u093e\u0901\u0921\u093e \u0917\u093e\u0935\u093f\u0938"
    ],
    "name:por_x_preferred":[
        "Kanda"
    ],
    "name:rus_x_preferred":[
        "\u041a\u0430\u043d\u0434\u0430"
    ],
    "name:swa_x_preferred":[
        "Kanda"
    ],
    "name:swe_x_preferred":[
        "Kanda"
    ],
    "name:ukr_x_preferred":[
        "\u041a\u0430\u043d\u0434\u0430"
    ],
    "wof:name":"Kanda",
    "wof:placetype":"locality"
},
  "geometry": {"coordinates":[140.90733,40.42317],"type":"Point"}
}