{
  "type": "Feature",
  "properties": {
    "gn:admin1_code":"21.0",
    "gn:admin2_code":"1865360.0",
    "gn:admin3_code":"43531.0",
    "gn:asciiname":"Takenosako",
    "gn:country_code":"JP",
    "gn:dem":86,
    "gn:feature_class":"P",
    "gn:feature_code":"PPLL",
    "gn:name":"Takenosako",
    "gn:population":0,
    "gn:timezone":"Asia/Tokyo",
    "iso:country":"JP",
    "name:jpn_x_preferred":[
        "\u7af9\u306e\u8feb"
    ],
    "name:jpn_x_variant":[
        "\u305f\u3051\u306e\u3055\u3053",
        "\u30bf\u30b1\u30ce\u30b5\u30b3"
    ],
    "wof:name":"Takenosako",
    "wof:placetype":"locality"
},
  "geometry": {"coordinates":[130.04336000000001,32.47832],"type":"Point"}
}