{
  "type": "Feature",
  "properties": {
    "gn:admin1_code":"21.0",
    "gn:admin2_code":"1848441.0",
    "gn:asciiname":"Yakatabara",
    "gn:country_code":"JP",
    "gn:dem":88,
    "gn:feature_class":"P",
    "gn:feature_code":"PPLL",
    "gn:name":"Yakatabara",
    "gn:population":0,
    "gn:timezone":"Asia/Tokyo",
    "iso:country":"JP",
    "name:jpn_x_preferred":[
        "\u9928\u539f"
    ],
    "name:jpn_x_variant":[
        "\u3084\u304b\u305f\u3070\u3089",
        "\u30e4\u30ab\u30bf\u30d0\u30e9"
    ],
    "wof:name":"Yakatabara",
    "wof:placetype":"locality"
},
  "geometry": {"coordinates":[130.70205000000001,32.52491],"type":"Point"}
}