{
  "type": "Feature",
  "properties": {
    "gn:admin1_code":"24.0",
    "gn:admin2_code":"7446985.0",
    "gn:admin3_code":"4445.0",
    "gn:asciiname":"Kirikome",
    "gn:country_code":"JP",
    "gn:dem":146,
    "gn:feature_class":"P",
    "gn:feature_code":"PPL",
    "gn:name":"Kirikome",
    "gn:population":0,
    "gn:timezone":"Asia/Tokyo",
    "iso:country":"JP",
    "name:jpn_x_preferred":[
        "\u5207\u8fbc"
    ],
    "name:und_x_variant":[
        "Kirikomi"
    ],
    "wof:name":"Kirikome",
    "wof:placetype":"locality"
},
  "geometry": {"coordinates":[140.71943999999999,38.63417000000001],"type":"Point"}
}