{
  "type": "Feature",
  "properties": {
    "gn:admin1_code":"12.0",
    "gn:admin2_code":"7428097.0",
    "gn:admin3_code":"1643.0",
    "gn:asciiname":"Churui-koshin",
    "gn:country_code":"JP",
    "gn:dem":113,
    "gn:feature_class":"P",
    "gn:feature_code":"PPL",
    "gn:name":"Ch\u016brui-k\u014dshin",
    "gn:population":0,
    "gn:timezone":"Asia/Tokyo",
    "iso:country":"JP",
    "name:jpn_x_preferred":[
        "\u5fe0\u985e\u516c\u89aa"
    ],
    "name:jpn_x_variant":[
        "\u3061\u3085\u3046\u308b\u3044\u3053\u3046\u3057\u3093",
        "\u30c1\u30e5\u30a6\u30eb\u30a4\u30b3\u30a6\u30b7\u30f3"
    ],
    "name:und_x_variant":[
        "Ch\u016brui-k\u014dshin"
    ],
    "wof:name":"Churui-koshin",
    "wof:placetype":"locality"
},
  "geometry": {"coordinates":[143.28987000000001,42.57331],"type":"Point"}
}