{
  "type": "Feature",
  "properties": {
    "gn:admin1_code":"21.0",
    "gn:admin2_code":"1864975.0",
    "gn:admin3_code":"43432.0",
    "gn:asciiname":"Komori",
    "gn:country_code":"JP",
    "gn:dem":219,
    "gn:feature_class":"P",
    "gn:feature_code":"PPL",
    "gn:name":"Komori",
    "gn:population":0,
    "gn:timezone":"Asia/Tokyo",
    "iso:country":"JP",
    "name:deu_x_preferred":[
        "Komori"
    ],
    "name:fas_x_preferred":[
        "\u06a9\u0648\u0645\u0648\u0631\u06cc"
    ],
    "name:jpn_x_preferred":[
        "\u5c0f\u68ee"
    ],
    "name:jpn_x_variant":[
        "\u3053\u3082\u308a",
        "\u30b3\u30e2\u30ea",
        "\u5c0f\u68ee\u30b3\u30fc\u30dd\u30ec\u30fc\u30b7\u30e7\u30f3"
    ],
    "wof:name":"Komori",
    "wof:placetype":"locality"
},
  "geometry": {"coordinates":[130.91824,32.83815],"type":"Point"}
}