{
  "type": "Feature",
  "properties": {
    "gn:admin1_code":"10.0",
    "gn:admin2_code":"7453748.0",
    "gn:admin3_code":"10448.0",
    "gn:asciiname":"Morishita",
    "gn:country_code":"JP",
    "gn:dem":337,
    "gn:feature_class":"P",
    "gn:feature_code":"PPL",
    "gn:name":"Morishita",
    "gn:population":0,
    "gn:timezone":"Asia/Tokyo",
    "iso:country":"JP",
    "name:jpn_x_preferred":[
        "\u68ee\u4e0b"
    ],
    "wof:name":"Morishita",
    "wof:placetype":"locality"
},
  "geometry": {"coordinates":[139.04958999999999,36.61324000000001],"type":"Point"}
}