{
  "type": "Feature",
  "properties": {
    "gn:admin1_code":"21.0",
    "gn:admin2_code":"7412708.0",
    "gn:admin3_code":"43501.0",
    "gn:asciiname":"Shintate",
    "gn:country_code":"JP",
    "gn:dem":152,
    "gn:feature_class":"P",
    "gn:feature_code":"PPLL",
    "gn:name":"Shintate",
    "gn:population":0,
    "gn:timezone":"Asia/Tokyo",
    "iso:country":"JP",
    "name:jpn_x_preferred":[
        "\u65b0\u7acb"
    ],
    "name:jpn_x_variant":[
        "\u3057\u3093\u305f\u3066",
        "\u30b7\u30f3\u30bf\u30c6"
    ],
    "wof:name":"Shintate",
    "wof:placetype":"locality"
},
  "geometry": {"coordinates":[130.81481000000002,32.22478],"type":"Point"}
}