{
  "type": "Feature",
  "properties": {
    "gn:admin1_code":"3.0",
    "gn:admin2_code":"2127674.0",
    "gn:asciiname":"Taya",
    "gn:country_code":"JP",
    "gn:dem":88,
    "gn:feature_class":"P",
    "gn:feature_code":"PPL",
    "gn:name":"Taya",
    "gn:population":0,
    "gn:timezone":"Asia/Tokyo",
    "iso:country":"JP",
    "name:ara_x_preferred":[
        "\u0637\u0627\u064a\u0629"
    ],
    "name:ceb_x_preferred":[
        "Taya"
    ],
    "name:fra_x_preferred":[
        "Taya"
    ],
    "name:ita_x_preferred":[
        "Taya"
    ],
    "name:jpn_x_preferred":[
        "\u7530\u5c4b"
    ],
    "name:jpn_x_variant":[
        "\u305f\u3084",
        "\u30bf\u30e4"
    ],
    "name:swe_x_preferred":[
        "Taya"
    ],
    "wof:name":"Taya",
    "wof:placetype":"locality"
},
  "geometry": {"coordinates":[141.1541,40.58508],"type":"Point"}
}