{
  "type": "Feature",
  "properties": {
    "gn:admin1_code":"4.0",
    "gn:admin2_code":"2112557.0",
    "gn:admin3_code":"12441.0",
    "gn:asciiname":"Awamata",
    "gn:country_code":"JP",
    "gn:dem":149,
    "gn:feature_class":"P",
    "gn:feature_code":"PPL",
    "gn:name":"Awamata",
    "gn:population":0,
    "gn:timezone":"Asia/Tokyo",
    "iso:country":"JP",
    "name:jpn_x_preferred":[
        "\u7c9f\u53c8"
    ],
    "name:jpn_x_variant":[
        "\u3042\u308f\u307e\u305f",
        "\u30a2\u30ef\u30de\u30bf"
    ],
    "wof:name":"Awamata",
    "wof:placetype":"locality"
},
  "geometry": {"coordinates":[140.18156000000002,35.21714],"type":"Point"}
}