{
  "type": "Feature",
  "properties": {
    "gn:admin1_code":"18.0",
    "gn:admin2_code":"1850587.0",
    "gn:asciiname":"Dan",
    "gn:country_code":"JP",
    "gn:dem":111,
    "gn:feature_class":"P",
    "gn:feature_code":"PPLL",
    "gn:name":"Dan",
    "gn:population":0,
    "gn:timezone":"Asia/Tokyo",
    "iso:country":"JP",
    "name:aze_x_preferred":[
        "Dan"
    ],
    "name:bre_x_preferred":[
        "Dan"
    ],
    "name:bul_x_preferred":[
        "\u0414\u0430\u043d"
    ],
    "name:cat_x_preferred":[
        "Dan"
    ],
    "name:ceb_x_preferred":[
        "Dan"
    ],
    "name:ces_x_preferred":[
        "Dan"
    ],
    "name:dan_x_preferred":[
        "Dan"
    ],
    "name:deu_x_preferred":[
        "Dan"
    ],
    "name:epo_x_preferred":[
        "Dan"
    ],
    "name:fin_x_preferred":[
        "Dan"
    ],
    "name:fra_x_preferred":[
        "Dan"
    ],
    "name:fry_x_preferred":[
        "Dan"
    ],
    "name:glg_x_preferred":[
        "Dan"
    ],
    "name:hrv_x_preferred":[
        "Dan"
    ],
    "name:ind_x_preferred":[
        "Dan"
    ],
    "name:isl_x_preferred":[
        "DAN"
    ],
    "name:jpn_x_preferred":[
        "\u6bb5"
    ],
    "name:nld_x_preferred":[
        "Dan"
    ],
    "name:nor_x_preferred":[
        "Dan"
    ],
    "name:pol_x_preferred":[
        "Dan"
    ],
    "name:por_x_preferred":[
        "Dan"
    ],
    "name:rus_x_preferred":[
        "\u0414\u0430\u043d"
    ],
    "name:slk_x_preferred":[
        "Dan"
    ],
    "name:slv_x_preferred":[
        "Dan"
    ],
    "name:spa_x_preferred":[
        "Dan"
    ],
    "name:srp_x_preferred":[
        "\u0414\u0430\u043d"
    ],
    "name:swe_x_preferred":[
        "Dan"
    ],
    "name:tur_x_preferred":[
        "Dan"
    ],
    "name:ukr_x_preferred":[
        "\u0414\u0430\u043d"
    ],
    "wof:name":"Dan",
    "wof:placetype":"locality"
},
  "geometry": {"coordinates":[130.74293,31.46456],"type":"Point"}
}