{
  "type": "Feature",
  "properties": {
    "gn:admin1_code":"29",
    "gn:admin2_code":"1860308.0",
    "gn:asciiname":"Gejo",
    "gn:country_code":"JP",
    "gn:dem":26,
    "gn:feature_class":"P",
    "gn:feature_code":"PPL",
    "gn:name":"Gej\u014d",
    "gn:population":0,
    "gn:timezone":"Asia/Tokyo",
    "iso:country":"JP",
    "name:jpn_x_preferred":[
        "\u4e0b\u6761"
    ],
    "name:und_x_variant":[
        "Shimojo",
        "Gej\u014d"
    ],
    "wof:name":"Gejo",
    "wof:placetype":"locality"
},
  "geometry": {"coordinates":[139.03958,37.6482],"type":"Point"}
}