{
  "type": "Feature",
  "properties": {
    "gn:admin1_code":"16.0",
    "gn:admin2_code":"2112822.0",
    "gn:asciiname":"Oinobora",
    "gn:country_code":"JP",
    "gn:dem":137,
    "gn:feature_class":"P",
    "gn:feature_code":"PPL",
    "gn:name":"Oinobora",
    "gn:population":0,
    "gn:timezone":"Asia/Tokyo",
    "iso:country":"JP",
    "name:jpn_x_preferred":[
        "\u72fc\u6d1e"
    ],
    "name:jpn_x_variant":[
        "\u304a\u3044\u306e\u307c\u3089",
        "\u30aa\u30a4\u30ce\u30dc\u30e9"
    ],
    "wof:name":"Oinobora",
    "wof:placetype":"locality"
},
  "geometry": {"coordinates":[141.19376,39.35781],"type":"Point"}
}