{
  "type": "Feature",
  "properties": {
    "gn:admin1_code":"16.0",
    "gn:admin2_code":"7441816.0",
    "gn:asciiname":"Hitokabe",
    "gn:country_code":"JP",
    "gn:dem":226,
    "gn:feature_class":"P",
    "gn:feature_code":"PPL",
    "gn:name":"Hitokabe",
    "gn:population":0,
    "gn:timezone":"Asia/Tokyo",
    "iso:country":"JP",
    "wof:name":"Hitokabe",
    "wof:placetype":"locality"
},
  "geometry": {"coordinates":[141.31666999999999,39.23333],"type":"Point"}
}