{
  "type": "Feature",
  "properties": {
    "iso:country":"JP",
    "label:eng_x_preferred_longname":[
        "Kikuchi City"
    ],
    "label:eng_x_preferred_placetype":[
        "city"
    ],
    "name:eng_x_preferred":[
        "Kikuchi"
    ],
    "name:eng_x_variant":[
        "Kikuchi City"
    ],
    "name:jpn_x_preferred":[
        "\u83ca\u6c60\u5e02"
    ],
    "qs:name":"\u83ca\u6c60\u5e02",
    "qs:name_adm0":"\u65e5\u672c",
    "qs:name_adm1":"\u718a\u672c\u770c",
    "qs:photos":262,
    "qs:photos_1k":53,
    "qs:photos_9k":1,
    "qs:photos_9r":4,
    "qs:photos_all":262,
    "qs:photos_sr":5,
    "qs:placetype":"Town",
    "qs:pop_sr":"0",
    "wof:name":"Kikuchi",
    "wof:placetype":"locality"
},
  "geometry": {"coordinates":[130.81420800000001,32.980172],"type":"Point"}
}