{
  "type": "Feature",
  "properties": {
    "gn:admin1_code":"4.0",
    "gn:admin2_code":"7465524.0",
    "gn:asciiname":"Takadani",
    "gn:country_code":"JP",
    "gn:dem":11,
    "gn:feature_class":"P",
    "gn:feature_code":"PPL",
    "gn:name":"Takadani",
    "gn:population":0,
    "gn:timezone":"Asia/Tokyo",
    "iso:country":"JP",
    "name:jpn_x_preferred":[
        "\u9ad8\u8c37"
    ],
    "name:jpn_x_variant":[
        "\u305f\u304b\u3060\u306b",
        "\u30bf\u30ab\u30c0\u30cb"
    ],
    "wof:name":"Takadani",
    "wof:placetype":"locality"
},
  "geometry": {"coordinates":[140.35111000000001,35.27122],"type":"Point"}
}