{
  "type": "Feature",
  "properties": {
    "gn:admin1_code":"24.0",
    "gn:admin2_code":"2112574.0",
    "gn:asciiname":"Tsuruga",
    "gn:country_code":"JP",
    "gn:dem":3,
    "gn:feature_class":"P",
    "gn:feature_code":"PPL",
    "gn:name":"Tsuruga",
    "gn:population":0,
    "gn:timezone":"Asia/Tokyo",
    "iso:country":"JP",
    "name:jpn_x_preferred":[
        "\u9db4\u5bb6"
    ],
    "name:jpn_x_variant":[
        "\u3064\u308b\u304c",
        "\u30c4\u30eb\u30ac"
    ],
    "wof:name":"Tsuruga",
    "wof:placetype":"locality"
},
  "geometry": {"coordinates":[141.27934999999999,38.49414],"type":"Point"}
}