{
  "type": "Feature",
  "properties": {
    "gn:admin1_code":"18.0",
    "gn:admin2_code":"7383991.0",
    "gn:asciiname":"Kijiyama",
    "gn:country_code":"JP",
    "gn:dem":345,
    "gn:feature_class":"P",
    "gn:feature_code":"PPLL",
    "gn:name":"Kijiyama",
    "gn:population":0,
    "gn:timezone":"Asia/Tokyo",
    "iso:country":"JP",
    "name:jpn_x_preferred":[
        "\u6728\u5730\u5c71"
    ],
    "name:jpn_x_variant":[
        "\u304d\u3058\u3084\u307e",
        "\u30ad\u30b8\u30e4\u30de"
    ],
    "wof:name":"Kijiyama",
    "wof:placetype":"locality"
},
  "geometry": {"coordinates":[130.59472,32.13672],"type":"Point"}
}