{
  "type": "Feature",
  "properties": {
    "iso:country":"JP",
    "name:eng_x_preferred":[
        "Doetsu 1 Chome"
    ],
    "name:eng_x_variant":[
        "Douetsu 1 Choume",
        "Doetsu 1 Chome"
    ],
    "name:jpn_x_preferred":[
        "\uff11\u4e01\u76ee"
    ],
    "name:jpn_x_variant":[
        "\u3069\u3046\u3048\u3064 \uff11\u3061\u3087\u3046\u3081",
        "\u9053\u60a6 \uff11\u4e01\u76ee",
        "\uff11\u3061\u3087\u3046\u3081"
    ],
    "qs:gn_local":0,
    "qs:local_max":128,
    "qs:local_sum":260,
    "qs:localhoods":7,
    "qs:name":"\uff11\u4e01\u76ee",
    "qs:name_adm0":"\u65e5\u672c",
    "qs:name_adm1":"\u9759\u5ca1\u770c",
    "qs:name_en":"Doetsu 1 Chome",
    "qs:name_lau":"\u9053\u60a6",
    "qs:name_local":"\u5cf6\u7530\u5e02",
    "qs:photo_max":11,
    "qs:photo_sum":20,
    "qs:placetype":"Suburb",
    "qs:quad_count":5,
    "qs:woe_adm0":23424856,
    "qs:woe_adm1":2345886,
    "qs:woe_adm2":0,
    "qs:woe_lau":28437610,
    "qs:woe_local":1118164,
    "qs:woe_ver":"7.10.0",
    "wof:lang":[
        "jpn"
    ],
    "wof:name":"\uff11\u4e01\u76ee",
    "wof:placetype":"neighbourhood"
},
  "geometry": {"coordinates":[138.19976800000001,34.836575],"type":"Point"}
}