{
  "type": "Feature",
  "properties": {
    "gn:admin1_code":"42",
    "gn:admin2_code":"1858253.0",
    "gn:asciiname":"Ishida",
    "gn:country_code":"JP",
    "gn:dem":3,
    "gn:feature_class":"P",
    "gn:feature_code":"PPL",
    "gn:name":"Ishida",
    "gn:population":0,
    "gn:timezone":"Asia/Tokyo",
    "iso:country":"JP",
    "name:jpn_x_preferred":[
        "\u77f3\u7530"
    ],
    "wof:name":"Ishida",
    "wof:placetype":"locality"
},
  "geometry": {"coordinates":[137.42158000000001,36.86965],"type":"Point"}
}