{
  "type": "Feature",
  "properties": {
    "gn:country":"JP",
    "gn:fcode":"ADM3",
    "gn:population":0,
    "iso:country":"JP",
    "name:eng_x_preferred":[
        "Hirokawa"
    ],
    "name:eng_x_variant":[
        "Hirokawa-machi"
    ],
    "name:jpn_x_preferred":[
        "\u5e83\u5ddd\u753a"
    ],
    "name:jpn_x_variant":[
        "\u3072\u308d\u304b\u308f\u307e\u3061"
    ],
    "name:und_x_variant":[
        "Hirokawa Machi"
    ],
    "qs:name":"Hirokawa-machi",
    "qs:photos_9r":0,
    "qs:photos_sr":0,
    "qs:pop_sr":"0",
    "wof:name":"Hirokawa",
    "wof:placetype":"localadmin",
    "wof:population":0
},
  "geometry": {"coordinates":[130.57257000000001,33.25213],"type":"Point"}
}