{
  "type": "Feature",
  "properties": {
    "gn:admin1_code":"8.0",
    "gn:admin2_code":"2112139.0",
    "gn:asciiname":"Osemachi-kozu",
    "gn:country_code":"JP",
    "gn:dem":286,
    "gn:feature_class":"P",
    "gn:feature_code":"PPL",
    "gn:name":"\u014csemachi-k\u014dzu",
    "gn:population":0,
    "gn:timezone":"Asia/Tokyo",
    "iso:country":"JP",
    "name:jpn_x_preferred":[
        "\u9022\u702c\u753a\u6cb3\u5185"
    ],
    "name:und_x_variant":[
        "K\u014dchi",
        "K\u014dzu",
        "\u014csemachi-k\u014dzu"
    ],
    "wof:name":"Osemachi-kozu",
    "wof:placetype":"locality"
},
  "geometry": {"coordinates":[140.27202,37.42003],"type":"Point"}
}