{
  "type": "Feature",
  "properties": {
    "gn:admin1_code":"18.0",
    "gn:admin2_code":"7383999.0",
    "gn:admin3_code":"46482.0",
    "gn:asciiname":"Koshinchi",
    "gn:country_code":"JP",
    "gn:dem":3,
    "gn:feature_class":"P",
    "gn:feature_code":"PPLL",
    "gn:name":"Koshinchi",
    "gn:population":0,
    "gn:timezone":"Asia/Tokyo",
    "iso:country":"JP",
    "name:jpn_x_preferred":[
        "\u5c0f\u65b0\u5730\u3000"
    ],
    "wof:name":"Koshinchi",
    "wof:placetype":"locality"
},
  "geometry": {"coordinates":[130.9889,31.35992],"type":"Point"}
}