{
  "type": "Feature",
  "properties": {
    "gn:admin1_code":"21.0",
    "gn:admin2_code":"1862350.0",
    "gn:asciiname":"Onsenmachi",
    "gn:country_code":"JP",
    "gn:dem":97,
    "gn:feature_class":"P",
    "gn:feature_code":"PPL",
    "gn:name":"Onsenmachi",
    "gn:population":0,
    "gn:timezone":"Asia/Tokyo",
    "iso:country":"JP",
    "name:jpn_x_preferred":[
        "\u6e29\u6cc9\u753a"
    ],
    "name:jpn_x_variant":[
        "\u304a\u3093\u305b\u3093\u307e\u3061",
        "\u30aa\u30f3\u30bb\u30f3\u30de\u30c1"
    ],
    "wof:name":"Onsenmachi",
    "wof:placetype":"locality"
},
  "geometry": {"coordinates":[130.72994,32.21558],"type":"Point"}
}