{
  "type": "Feature",
  "properties": {
    "iso:country":"JP",
    "name:eng_x_preferred":[
        "Minami 3 Sen"
    ],
    "name:eng_x_variant":[
        "Minami Minami 3sen",
        "Minami 3 Sen"
    ],
    "name:jpn_x_preferred":[
        "\uff13\u7dda"
    ],
    "name:jpn_x_variant":[
        "\u307f\u306a\u307f \uff13\u305b\u3093",
        "\u5357 \uff13\u7dda",
        "\uff13\u305b\u3093"
    ],
    "qs:gn_local":0,
    "qs:local_max":38,
    "qs:local_sum":38,
    "qs:localhoods":1,
    "qs:name":"\uff13\u7dda",
    "qs:name_adm0":"\u65e5\u672c",
    "qs:name_adm1":"\u5317\u6d77\u9053",
    "qs:name_adm2":"\u4e0a\u5ddd\u90e1",
    "qs:name_en":"Minami 3 Sen",
    "qs:name_lau":"\u5357",
    "qs:name_local":"\u6771\u795e\u697d\u753a",
    "qs:photo_max":26,
    "qs:photo_sum":38,
    "qs:placetype":"Suburb",
    "qs:quad_count":5,
    "qs:woe_adm0":23424856,
    "qs:woe_adm1":7153351,
    "qs:woe_adm2":24853906,
    "qs:woe_lau":28384153,
    "qs:woe_local":24847863,
    "qs:woe_ver":"7.10.0",
    "wof:lang":[
        "jpn"
    ],
    "wof:name":"\uff13\u7dda",
    "wof:placetype":"neighbourhood"
},
  "geometry": {"coordinates":[142.45335399999999,43.669857],"type":"Point"}
}