{
  "type": "Feature",
  "properties": {
    "gn:admin1_code":"2.0",
    "gn:admin2_code":"2127468.0",
    "gn:admin3_code":"5348.0",
    "gn:asciiname":"Futatsumori",
    "gn:country_code":"JP",
    "gn:dem":16,
    "gn:feature_class":"P",
    "gn:feature_code":"PPLL",
    "gn:name":"Futatsumori",
    "gn:population":0,
    "gn:timezone":"Asia/Tokyo",
    "iso:country":"JP",
    "name:jpn_x_preferred":[
        "\u4e8c\u30c4\u68ee"
    ],
    "wof:name":"Futatsumori",
    "wof:placetype":"locality"
},
  "geometry": {"coordinates":[140.06171000000001,40.07648],"type":"Point"}
}