{
  "type": "Feature",
  "properties": {
    "iso:country":"JP",
    "name:eng_x_preferred":[
        "Nakagomi 3 Chome"
    ],
    "name:eng_x_variant":[
        "Nakagomi 3 Choume",
        "Nakagomi 3 Chome"
    ],
    "name:jpn_x_preferred":[
        "\uff13\u4e01\u76ee"
    ],
    "name:jpn_x_variant":[
        "\u306a\u304b\u3054\u307f \uff13\u3061\u3087\u3046\u3081",
        "\u4e2d\u8fbc \uff13\u4e01\u76ee",
        "\uff13\u3061\u3087\u3046\u3081"
    ],
    "qs:gn_local":0,
    "qs:local_max":54,
    "qs:local_sum":75,
    "qs:localhoods":3,
    "qs:name":"\uff13\u4e01\u76ee",
    "qs:name_adm0":"\u65e5\u672c",
    "qs:name_adm1":"\u9577\u91ce\u770c",
    "qs:name_en":"Nakagomi 3 Chome",
    "qs:name_lau":"\u4e2d\u8fbc",
    "qs:name_local":"\u4f50\u4e45\u5e02",
    "qs:photo_max":4,
    "qs:photo_sum":6,
    "qs:placetype":"Suburb",
    "qs:quad_count":3,
    "qs:woe_adm0":23424856,
    "qs:woe_adm1":2345875,
    "qs:woe_adm2":0,
    "qs:woe_lau":28432202,
    "qs:woe_local":1118090,
    "qs:woe_ver":"7.10.0",
    "wof:lang":[
        "jpn"
    ],
    "wof:name":"\uff13\u4e01\u76ee",
    "wof:placetype":"neighbourhood"
},
  "geometry": {"coordinates":[138.487244,36.219902],"type":"Point"}
}