{
  "type": "Feature",
  "properties": {
    "gn:admin1_code":"4.0",
    "gn:admin2_code":"1856183.0",
    "gn:asciiname":"Miyazono",
    "gn:country_code":"JP",
    "gn:dem":9,
    "gn:feature_class":"P",
    "gn:feature_code":"PPL",
    "gn:name":"Miyazono",
    "gn:population":0,
    "gn:timezone":"Asia/Tokyo",
    "iso:country":"JP",
    "name:jpn_x_preferred":[
        "\u5bae\u5712"
    ],
    "wof:name":"Miyazono",
    "wof:placetype":"locality"
},
  "geometry": {"coordinates":[139.91477,35.84629],"type":"Point"}
}