{
  "type": "Feature",
  "properties": {
    "iso:country":"JP",
    "name:eng_x_preferred":[
        "Takasushinmachi 3 Chome"
    ],
    "name:eng_x_variant":[
        "Takasushinmachi 3 Choume",
        "Takasushinmachi 3 Chome"
    ],
    "name:jpn_x_preferred":[
        "\uff13\u4e01\u76ee"
    ],
    "name:jpn_x_variant":[
        "\u305f\u304b\u3059\u3057\u3093\u307e\u3061 \uff13\u3061\u3087\u3046\u3081",
        "\u9ad8\u9808\u65b0\u753a \uff13\u4e01\u76ee",
        "\uff13\u3061\u3087\u3046\u3081"
    ],
    "qs:gn_local":0,
    "qs:local_max":565,
    "qs:local_sum":1354,
    "qs:localhoods":19,
    "qs:name":"\uff13\u4e01\u76ee",
    "qs:name_adm0":"\u65e5\u672c",
    "qs:name_adm1":"\u9ad8\u77e5\u770c",
    "qs:name_en":"Takasushinmachi 3 Chome",
    "qs:name_lau":"\u9ad8\u9808\u65b0\u753a",
    "qs:name_local":"\u9ad8\u77e5\u5e02",
    "qs:photo_max":31,
    "qs:photo_sum":68,
    "qs:placetype":"Suburb",
    "qs:quad_count":5,
    "qs:woe_adm0":23424856,
    "qs:woe_adm1":2345869,
    "qs:woe_adm2":0,
    "qs:woe_lau":28480936,
    "qs:woe_local":1117548,
    "qs:woe_ver":"7.10.0",
    "wof:lang":[
        "jpn"
    ],
    "wof:name":"\uff13\u4e01\u76ee",
    "wof:placetype":"neighbourhood"
},
  "geometry": {"coordinates":[133.57739000000001,33.547988],"type":"Point"}
}