{
  "type": "Feature",
  "properties": {
    "gn:admin1_code":"24.0",
    "gn:admin2_code":"2110755.0",
    "gn:asciiname":"Hasamacho-kitakata",
    "gn:country_code":"JP",
    "gn:dem":19,
    "gn:feature_class":"P",
    "gn:feature_code":"PPL",
    "gn:name":"Hasamach\u014d-kitakata",
    "gn:population":0,
    "gn:timezone":"Asia/Tokyo",
    "iso:country":"JP",
    "name:jpn_x_preferred":[
        "\u8feb\u753a\u5317\u65b9"
    ],
    "name:und_x_variant":[
        "Kitakata-machi",
        "Kitakata",
        "Hasamach\u014d-kitakata"
    ],
    "wof:name":"Hasamacho-kitakata",
    "wof:placetype":"locality"
},
  "geometry": {"coordinates":[141.17859000000001,38.70319],"type":"Point"}
}