{
  "type": "Feature",
  "properties": {
    "gn:admin1_code":"3.0",
    "gn:admin2_code":"2130200.0",
    "gn:asciiname":"Jurokunichimachi",
    "gn:country_code":"JP",
    "gn:dem":26,
    "gn:feature_class":"P",
    "gn:feature_code":"PPL",
    "gn:name":"J\u016brokunichimachi",
    "gn:population":0,
    "gn:timezone":"Asia/Tokyo",
    "iso:country":"JP",
    "name:jpn_x_preferred":[
        "\u5341\u516d\u65e5\u753a"
    ],
    "name:jpn_x_variant":[
        "\u3058\u3085\u3046\u308d\u304f\u306b\u3061\u307e\u3061",
        "\u30b8\u30e5\u30a6\u30ed\u30af\u30cb\u30c1\u30de\u30c1"
    ],
    "name:und_x_variant":[
        "J\u016brokunichimachi"
    ],
    "wof:name":"Jurokunichimachi",
    "wof:placetype":"locality"
},
  "geometry": {"coordinates":[141.48707999999999,40.5074],"type":"Point"}
}