{
  "type": "Feature",
  "properties": {
    "gn:admin1_code":"29",
    "gn:admin2_code":"1860992.0",
    "gn:asciiname":"Yasuzuka",
    "gn:cc2":"JP",
    "gn:country_code":"JP",
    "gn:dem":144,
    "gn:feature_class":"P",
    "gn:feature_code":"PPL",
    "gn:name":"Yasuzuka",
    "gn:population":0,
    "gn:timezone":"Asia/Tokyo",
    "iso:country":"JP",
    "name:und_x_variant":[
        "Yasutsuka",
        "Yasuzuka"
    ],
    "wof:name":"Yasuzuka",
    "wof:placetype":"locality"
},
  "geometry": {"coordinates":[138.46666999999999,37.13333],"type":"Point"}
}