{
  "type": "Feature",
  "properties": {
    "gn:country":"JP",
    "gn:fcode":"PPL",
    "gn:pop":82112,
    "iso:country":"JP",
    "name:eng_x_preferred":[
        "Tanashi"
    ],
    "name:fra_x_preferred":[
        "Tanashi"
    ],
    "name:jpn_x_preferred":[
        "\u7530\u7121\u753a"
    ],
    "name:jpn_x_variant":[
        "\u305f\u306a\u3057\u3061\u3087\u3046",
        "\u30bf\u30ca\u30b7\u30c1\u30e7\u30a6",
        "\u7530\u7121\u5e02"
    ],
    "name:kor_x_preferred":[
        "\ub2e4\ub098\uc2dc \uc2dc"
    ],
    "name:unk_x_variant":[
        "Tanashich\u014d"
    ],
    "name:zho_x_preferred":[
        "\u7530\u7121\u5e02"
    ],
    "qs:name":"Tanashi",
    "qs:photos_9r":0,
    "qs:photos_sr":0,
    "qs:pop_sr":"8",
    "wof:name":"Tanashi",
    "wof:placetype":"locality",
    "wof:population":82112
},
  "geometry": {"coordinates":[139.52222,35.72389],"type":"Point"}
}