{
  "type": "Feature",
  "properties": {
    "gn:admin1_code":"45",
    "gn:admin2_code":"1852222.0",
    "gn:asciiname":"Futaoi",
    "gn:country_code":"JP",
    "gn:dem":6,
    "gn:feature_class":"P",
    "gn:feature_code":"PPL",
    "gn:name":"Futaoi",
    "gn:population":0,
    "gn:timezone":"Asia/Tokyo",
    "iso:country":"JP",
    "name:jpn_x_preferred":[
        "\u84cb\u4e95"
    ],
    "name:und_x_variant":[
        "Futaoijima",
        "Futaoi"
    ],
    "wof:name":"Futaoi",
    "wof:placetype":"locality"
},
  "geometry": {"coordinates":[130.78783999999999,34.10145],"type":"Point"}
}