{
  "type": "Feature",
  "properties": {
    "gn:admin1_code":"18.0",
    "gn:admin2_code":"1853737.0",
    "gn:admin3_code":"46530.0",
    "gn:asciiname":"Todoroki",
    "gn:country_code":"JP",
    "gn:dem":88,
    "gn:feature_class":"P",
    "gn:feature_code":"PPL",
    "gn:name":"Todoroki",
    "gn:population":0,
    "gn:timezone":"Asia/Tokyo",
    "iso:country":"JP",
    "name:jpn_x_preferred":[
        "\u9a6b\u6728"
    ],
    "wof:name":"Todoroki",
    "wof:placetype":"locality"
},
  "geometry": {"coordinates":[128.93615,27.83508],"type":"Point"}
}