{
  "type": "Feature",
  "properties": {
    "gn:admin1_code":"3.0",
    "gn:admin2_code":"2129754.0",
    "gn:admin3_code":"2408.0",
    "gn:asciiname":"Oinosawa",
    "gn:country_code":"JP",
    "gn:dem":45,
    "gn:feature_class":"P",
    "gn:feature_code":"PPL",
    "gn:name":"Oinosawa",
    "gn:population":0,
    "gn:timezone":"Asia/Tokyo",
    "iso:country":"JP",
    "name:jpn_x_preferred":[
        "\u72fc\u30ce\u6ca2"
    ],
    "name:jpn_x_variant":[
        "\u304a\u3044\u306e\u3055\u308f",
        "\u30aa\u30a4\u30ce\u30b5\u30ef"
    ],
    "wof:name":"Oinosawa",
    "wof:placetype":"locality"
},
  "geometry": {"coordinates":[141.28656000000001,40.80305],"type":"Point"}
}