{
  "type": "Feature",
  "properties": {
    "gn:admin1_code":"3.0",
    "gn:admin2_code":"8534376.0",
    "gn:admin3_code":"2321.0",
    "gn:asciiname":"Mukaippira",
    "gn:country_code":"JP",
    "gn:dem":10,
    "gn:feature_class":"P",
    "gn:feature_code":"PPL",
    "gn:name":"Mukaippira",
    "gn:population":0,
    "gn:timezone":"Asia/Tokyo",
    "iso:country":"JP",
    "name:jpn_x_preferred":[
        "\u5411\u5e73"
    ],
    "name:jpn_x_variant":[
        "\u3080\u304b\u3044\u3063\u3074\u3089",
        "\u30e0\u30ab\u30a4\u30c3\u30d4\u30e9"
    ],
    "wof:name":"Mukaippira",
    "wof:placetype":"locality"
},
  "geometry": {"coordinates":[140.23580999999999,40.75578],"type":"Point"}
}