{
  "type": "Feature",
  "properties": {
    "gn:admin1_code":"21.0",
    "gn:admin2_code":"1857206.0",
    "gn:asciiname":"Okubo",
    "gn:country_code":"JP",
    "gn:dem":40,
    "gn:feature_class":"P",
    "gn:feature_code":"PPLL",
    "gn:name":"\u014ckubo",
    "gn:population":0,
    "gn:timezone":"Asia/Tokyo",
    "iso:country":"JP",
    "name:jpn_x_preferred":[
        "\u5927\u7aaa"
    ],
    "name:jpn_x_variant":[
        "\u304a\u304a\u304f\u307c",
        "\u30aa\u30aa\u30af\u30dc"
    ],
    "name:und_x_variant":[
        "\u014ckubo"
    ],
    "wof:name":"Okubo",
    "wof:placetype":"locality"
},
  "geometry": {"coordinates":[130.41856999999999,32.18195],"type":"Point"}
}