{
  "type": "Feature",
  "properties": {
    "gn:admin1_code":"21.0",
    "gn:admin2_code":"7412705.0",
    "gn:admin3_code":"43484.0",
    "gn:asciiname":"Warikari",
    "gn:country_code":"JP",
    "gn:dem":14,
    "gn:feature_class":"P",
    "gn:feature_code":"PPLL",
    "gn:name":"Warikari",
    "gn:population":0,
    "gn:timezone":"Asia/Tokyo",
    "iso:country":"JP",
    "name:jpn_x_preferred":[
        "\u5272\u5208"
    ],
    "name:jpn_x_variant":[
        "\u308f\u308a\u304b\u308a",
        "\u30ef\u30ea\u30ab\u30ea"
    ],
    "wof:name":"Warikari",
    "wof:placetype":"locality"
},
  "geometry": {"coordinates":[130.45067,32.28713],"type":"Point"}
}