{
  "type": "Feature",
  "properties": {
    "gn:admin1_code":"21.0",
    "gn:admin2_code":"7413151.0",
    "gn:asciiname":"Kosaginoura",
    "gn:country_code":"JP",
    "gn:dem":3,
    "gn:feature_class":"P",
    "gn:feature_code":"PPLL",
    "gn:name":"Kosaginoura",
    "gn:population":0,
    "gn:timezone":"Asia/Tokyo",
    "iso:country":"JP",
    "name:jpn_x_preferred":[
        "\u5c0f\u9dfa\u6d66"
    ],
    "name:jpn_x_variant":[
        "\u3053\u3055\u304e\u306e\u3046\u3089",
        "\u30b3\u30b5\u30ae\u30ce\u30a6\u30e9"
    ],
    "wof:name":"Kosaginoura",
    "wof:placetype":"locality"
},
  "geometry": {"coordinates":[130.46687,32.55616],"type":"Point"}
}