{
  "type": "Feature",
  "properties": {
    "gn:admin1_code":"29",
    "gn:admin2_code":"1853313.0",
    "gn:asciiname":"Moroo",
    "gn:country_code":"JP",
    "gn:dem":9,
    "gn:feature_class":"P",
    "gn:feature_code":"PPL",
    "gn:name":"Moroo",
    "gn:population":0,
    "gn:timezone":"Asia/Tokyo",
    "iso:country":"JP",
    "name:jpn_x_preferred":[
        "\u4e21\u5c3e"
    ],
    "name:und_x_variant":[
        "Muroo",
        "Moroo"
    ],
    "wof:name":"Moroo",
    "wof:placetype":"locality"
},
  "geometry": {"coordinates":[138.5136,38.07104],"type":"Point"}
}