{
  "type": "Feature",
  "properties": {
    "gn:admin1_code":"34.0",
    "gn:admin2_code":"1855405.0",
    "gn:asciiname":"Sakae",
    "gn:country_code":"JP",
    "gn:dem":47,
    "gn:feature_class":"P",
    "gn:feature_code":"PPL",
    "gn:name":"Sakae",
    "gn:population":0,
    "gn:timezone":"Asia/Tokyo",
    "iso:country":"JP",
    "name:deu_x_preferred":[
        "Sakae"
    ],
    "name:fra_x_preferred":[
        "Sakae"
    ],
    "name:ind_x_preferred":[
        "Sakae"
    ],
    "name:jpn_x_preferred":[
        "\u6804"
    ],
    "name:jpn_x_variant":[
        "\u3055\u304b\u3048",
        "\u30b5\u30ab\u30a8"
    ],
    "name:kor_x_preferred":[
        "\uc0ac\uce74\uc5d0"
    ],
    "name:pol_x_preferred":[
        "Sakae"
    ],
    "name:rus_x_preferred":[
        "\u0421\u0430\u043a\u0430\u044d"
    ],
    "wof:name":"Sakae",
    "wof:placetype":"locality"
},
  "geometry": {"coordinates":[139.57933,35.77439000000001],"type":"Point"}
}