{
  "type": "Feature",
  "properties": {
    "gn:admin1_code":"25.0",
    "gn:admin2_code":"7413970.0",
    "gn:asciiname":"Nakano-kaitaku",
    "gn:country_code":"JP",
    "gn:dem":303,
    "gn:feature_class":"P",
    "gn:feature_code":"PPLL",
    "gn:name":"Nakano-kaitaku",
    "gn:population":0,
    "gn:timezone":"Asia/Tokyo",
    "iso:country":"JP",
    "name:jpn_x_preferred":[
        "\u4e2d\u91ce\u958b\u62d3"
    ],
    "name:jpn_x_variant":[
        "\u306a\u304b\u306e\u304b\u3044\u305f\u304f",
        "\u30ca\u30ab\u30ce\u30ab\u30a4\u30bf\u30af"
    ],
    "wof:name":"Nakano-kaitaku",
    "wof:placetype":"locality"
},
  "geometry": {"coordinates":[130.95822999999999,32.02876],"type":"Point"}
}