{
  "type": "Feature",
  "properties": {
    "gn:admin1_code":"19.0",
    "gn:admin2_code":"1861448.0",
    "gn:asciiname":"Shirane",
    "gn:country_code":"JP",
    "gn:dem":42,
    "gn:feature_class":"P",
    "gn:feature_code":"PPL",
    "gn:name":"Shirane",
    "gn:population":0,
    "gn:timezone":"Asia/Tokyo",
    "iso:country":"JP",
    "name:jpn_x_preferred":[
        "\u767d\u6839"
    ],
    "wof:name":"Shirane",
    "wof:placetype":"locality"
},
  "geometry": {"coordinates":[139.29622000000001,35.40026],"type":"Point"}
}