{
  "type": "Feature",
  "properties": {
    "iso:country":"JP",
    "name:eng_x_preferred":[
        "Fujiyamadai 2 Chome"
    ],
    "name:eng_x_variant":[
        "Fujiyamadai 2 Choume",
        "Fujiyamadai 2 Chome"
    ],
    "name:jpn_x_preferred":[
        "\uff12\u4e01\u76ee"
    ],
    "name:jpn_x_variant":[
        "\u3075\u3058\u3084\u307e\u3060\u3044 \uff12\u3061\u3087\u3046\u3081",
        "\u85e4\u5c71\u53f0 \uff12\u4e01\u76ee",
        "\uff12\u3061\u3087\u3046\u3081"
    ],
    "qs:gn_local":0,
    "qs:local_max":304,
    "qs:local_sum":441,
    "qs:localhoods":6,
    "qs:name":"\uff12\u4e01\u76ee",
    "qs:name_adm0":"\u65e5\u672c",
    "qs:name_adm1":"\u611b\u77e5\u770c",
    "qs:name_en":"Fujiyamadai 2 Chome",
    "qs:name_lau":"\u85e4\u5c71\u53f0",
    "qs:name_local":"\u6625\u65e5\u4e95\u5e02",
    "qs:photo_max":2,
    "qs:photo_sum":2,
    "qs:placetype":"Suburb",
    "qs:quad_count":1,
    "qs:woe_adm0":23424856,
    "qs:woe_adm1":2345851,
    "qs:woe_adm2":0,
    "qs:woe_lau":28441767,
    "qs:woe_local":1117472,
    "qs:woe_ver":"7.10.0",
    "wof:lang":[
        "jpn"
    ],
    "wof:name":"\uff12\u4e01\u76ee",
    "wof:placetype":"neighbourhood"
},
  "geometry": {"coordinates":[137.04620399999999,35.283741],"type":"Point"}
}