{
  "type": "Feature",
  "properties": {
    "gn:admin1_code":"34.0",
    "gn:admin2_code":"7464128.0",
    "gn:asciiname":"Tsukiji",
    "gn:country_code":"JP",
    "gn:dem":12,
    "gn:feature_class":"P",
    "gn:feature_code":"PPL",
    "gn:name":"Tsukiji",
    "gn:population":0,
    "gn:timezone":"Asia/Tokyo",
    "iso:country":"JP",
    "name:epo_x_preferred":[
        "Tsukiji"
    ],
    "name:eus_x_preferred":[
        "Tsukiji"
    ],
    "name:fas_x_preferred":[
        "\u062a\u0633\u0648\u06a9\u06cc\u062c\u06cc"
    ],
    "name:fra_x_preferred":[
        "Tsukiji"
    ],
    "name:ita_x_preferred":[
        "Tsukiji"
    ],
    "name:jpn_x_preferred":[
        "\u7bc9\u5730"
    ],
    "name:kor_x_preferred":[
        "\uc4f0\ud0a4\uc9c0"
    ],
    "name:msa_x_preferred":[
        "Tsukiji"
    ],
    "name:por_x_preferred":[
        "Tsukiji"
    ],
    "name:rus_x_preferred":[
        "\u0426\u0443\u043a\u0438\u0434\u0437\u0438"
    ],
    "name:swe_x_preferred":[
        "Tsukiji"
    ],
    "name:tur_x_preferred":[
        "Tsukiji"
    ],
    "wof:name":"Tsukiji",
    "wof:placetype":"locality"
},
  "geometry": {"coordinates":[139.53041999999999,35.87321],"type":"Point"}
}