{
  "type": "Feature",
  "properties": {
    "gn:admin1_code":"34.0",
    "gn:admin2_code":"7464128.0",
    "gn:asciiname":"Tsukiji",
    "gn:country_code":"JP",
    "gn:dem":12,
    "gn:feature_class":"P",
    "gn:feature_code":"PPL",
    "gn:name":"Tsukiji",
    "gn:population":0,
    "gn:timezone":"Asia/Tokyo",
    "iso:country":"JP",
    "name:jpn_x_preferred":[
        "\u7bc9\u5730"
    ],
    "wof:name":"Tsukiji",
    "wof:placetype":"locality"
},
  "geometry": {"coordinates":[139.53041999999999,35.87321],"type":"Point"}
}