{
  "type": "Feature",
  "properties": {
    "gn:admin1_code":"47",
    "gn:admin2_code":"1854344.0",
    "gn:asciiname":"Takahara",
    "gn:cc2":"JP",
    "gn:country_code":"JP",
    "gn:dem":28,
    "gn:feature_class":"P",
    "gn:feature_code":"PPL",
    "gn:name":"Takahara",
    "gn:population":0,
    "gn:timezone":"Asia/Tokyo",
    "iso:country":"JP",
    "name:jpn_x_preferred":[
        "\u9ad8\u539f"
    ],
    "name:und_x_variant":[
        "Takabaru",
        "Takobaru",
        "Takahara"
    ],
    "wof:name":"Takahara",
    "wof:placetype":"locality"
},
  "geometry": {"coordinates":[127.81972,26.32167],"type":"Point"}
}