{
  "type": "Feature",
  "properties": {
    "gn:admin1_code":"16",
    "gn:admin2_code":"2112655.0",
    "gn:asciiname":"Muronecho-tsuyagawa",
    "gn:country_code":"JP",
    "gn:dem":230,
    "gn:feature_class":"P",
    "gn:feature_code":"PPL",
    "gn:name":"Muronech\u014d-tsuyagawa",
    "gn:population":0,
    "gn:timezone":"Asia/Tokyo",
    "iso:country":"JP",
    "name:jpn_x_preferred":[
        "\u5ba4\u6839\u753a\u6d25\u8c37\u5ddd"
    ],
    "name:und_x_variant":[
        "Muronech\u014d-tsuyagawa",
        "Tsuyakawa"
    ],
    "wof:name":"Muronecho-tsuyagawa",
    "wof:placetype":"locality"
},
  "geometry": {"coordinates":[141.43333000000001,38.85],"type":"Point"}
}