{
  "type": "Feature",
  "properties": {
    "gn:admin1_code":"33.0",
    "gn:admin2_code":"1854650.0",
    "gn:asciiname":"Mikatsukicho-mikashima",
    "gn:country_code":"JP",
    "gn:dem":7,
    "gn:feature_class":"P",
    "gn:feature_code":"PPL",
    "gn:name":"Mikatsukich\u014d-mikashima",
    "gn:population":0,
    "gn:timezone":"Asia/Tokyo",
    "iso:country":"JP",
    "name:jpn_x_preferred":[
        "\u4e09\u65e5\u6708\u753a\u4e09\u30f6\u5cf6"
    ],
    "name:und_x_variant":[
        "Mikatsukich\u014d-mikashima"
    ],
    "wof:name":"Mikatsukicho-mikashima",
    "wof:placetype":"locality"
},
  "geometry": {"coordinates":[130.22748000000001,33.27896],"type":"Point"}
}