{
  "type": "Feature",
  "properties": {
    "gn:admin1_code":"26.0",
    "gn:admin2_code":"1856209.0",
    "gn:asciiname":"Hirade",
    "gn:country_code":"JP",
    "gn:dem":777,
    "gn:feature_class":"P",
    "gn:feature_code":"PPLL",
    "gn:name":"Hirade",
    "gn:population":0,
    "gn:timezone":"Asia/Tokyo",
    "iso:country":"JP",
    "name:jpn_x_preferred":[
        "\u5e73\u51fa"
    ],
    "wof:name":"Hirade",
    "wof:placetype":"locality"
},
  "geometry": {"coordinates":[138.08256,36.63582],"type":"Point"}
}