{
  "type": "Feature",
  "properties": {
    "gn:admin1_code":"29",
    "gn:admin2_code":"1856195.0",
    "gn:asciiname":"Nakano-naka",
    "gn:country_code":"JP",
    "gn:dem":8,
    "gn:feature_class":"P",
    "gn:feature_code":"PPL",
    "gn:name":"Nakano-naka",
    "gn:population":0,
    "gn:timezone":"Asia/Tokyo",
    "iso:country":"JP",
    "name:jpn_x_preferred":[
        "\u4e2d\u91ce\u4e2d"
    ],
    "name:und_x_variant":[
        "Nakano"
    ],
    "wof:name":"Nakano-naka",
    "wof:placetype":"locality"
},
  "geometry": {"coordinates":[138.85764,37.558],"type":"Point"}
}