{
  "type": "Feature",
  "properties": {
    "gn:admin1_code":"2.0",
    "gn:admin2_code":"2113122.0",
    "gn:asciiname":"Iijima-misunacho",
    "gn:country_code":"JP",
    "gn:dem":15,
    "gn:feature_class":"P",
    "gn:feature_code":"PPL",
    "gn:name":"Iijima-misunach\u014d",
    "gn:population":0,
    "gn:timezone":"Asia/Tokyo",
    "iso:country":"JP",
    "name:jpn_x_preferred":[
        "\u98ef\u5cf6\u7f8e\u7802\u753a"
    ],
    "name:jpn_x_variant":[
        "\u3044\u3044\u3058\u307e\u307f\u3059\u306a\u3061\u3087\u3046",
        "\u30a4\u30a4\u30b8\u30de\u30df\u30b9\u30ca\u30c1\u30e7\u30a6"
    ],
    "name:und_x_variant":[
        "Iijima-misunach\u014d"
    ],
    "wof:name":"Iijima-misunacho",
    "wof:placetype":"locality"
},
  "geometry": {"coordinates":[140.07399999999998,39.77601],"type":"Point"}
}