{
  "type": "Feature",
  "properties": {
    "gn:admin1_code":"7.0",
    "gn:admin2_code":"1859306.0",
    "gn:admin3_code":"40106.0",
    "gn:asciiname":"Kajimachi",
    "gn:country_code":"JP",
    "gn:dem":16,
    "gn:feature_class":"P",
    "gn:feature_code":"PPL",
    "gn:name":"Kajimachi",
    "gn:population":0,
    "gn:timezone":"Asia/Tokyo",
    "iso:country":"JP",
    "name:jpn_x_preferred":[
        "\u935b\u51b6\u753a"
    ],
    "wof:name":"Kajimachi",
    "wof:placetype":"locality"
},
  "geometry": {"coordinates":[130.88508999999999,33.88269],"type":"Point"}
}