{
  "type": "Feature",
  "properties": {
    "gn:admin1_code":"23.0",
    "gn:admin2_code":"1849544.0",
    "gn:asciiname":"Ichishicho-ishibashi",
    "gn:country_code":"JP",
    "gn:dem":22,
    "gn:feature_class":"P",
    "gn:feature_code":"PPL",
    "gn:name":"Ichishich\u014d-ishibashi",
    "gn:population":0,
    "gn:timezone":"Asia/Tokyo",
    "iso:country":"JP",
    "name:jpn_x_preferred":[
        "\u4e00\u5fd7\u753a\u77f3\u6a4b"
    ],
    "name:und_x_variant":[
        "Ichishich\u014d-ishibashi"
    ],
    "wof:name":"Ichishicho-ishibashi",
    "wof:placetype":"locality"
},
  "geometry": {"coordinates":[136.40766000000002,34.65833],"type":"Point"}
}