{
  "type": "Feature",
  "properties": {
    "gn:admin1_code":"3.0",
    "gn:admin2_code":"2129525.0",
    "gn:admin3_code":"2387.0",
    "gn:asciiname":"Fujinomori",
    "gn:country_code":"JP",
    "gn:dem":66,
    "gn:feature_class":"P",
    "gn:feature_code":"PPL",
    "gn:name":"Fujinomori",
    "gn:population":0,
    "gn:timezone":"Asia/Tokyo",
    "iso:country":"JP",
    "name:jpn_x_preferred":[
        "\u85e4\u30ce\u68ee"
    ],
    "name:jpn_x_variant":[
        "\u3075\u3058\u306e\u3082\u308a",
        "\u30d5\u30b8\u30ce\u30e2\u30ea"
    ],
    "wof:name":"Fujinomori",
    "wof:placetype":"locality"
},
  "geometry": {"coordinates":[140.465,41.05341],"type":"Point"}
}