{
  "type": "Feature",
  "properties": {
    "gn:admin1_code":"25.0",
    "gn:admin2_code":"7413970.0",
    "gn:asciiname":"Mukaebaba",
    "gn:country_code":"JP",
    "gn:dem":191,
    "gn:feature_class":"P",
    "gn:feature_code":"PPLL",
    "gn:name":"Mukaebaba",
    "gn:population":0,
    "gn:timezone":"Asia/Tokyo",
    "iso:country":"JP",
    "name:jpn_x_preferred":[
        "\u5411\u6c5f\u99ac\u5834"
    ],
    "name:jpn_x_variant":[
        "\u3080\u304b\u3048\u3070\u3070",
        "\u30e0\u30ab\u30a8\u30d0\u30d0"
    ],
    "wof:name":"Mukaebaba",
    "wof:placetype":"locality"
},
  "geometry": {"coordinates":[130.98042000000001,32.00205],"type":"Point"}
}