{
  "type": "Feature",
  "properties": {
    "gn:admin1_code":"2.0",
    "gn:admin2_code":"2128783.0",
    "gn:asciiname":"Terazaki",
    "gn:country_code":"JP",
    "gn:dem":55,
    "gn:feature_class":"P",
    "gn:feature_code":"PPL",
    "gn:name":"Terazaki",
    "gn:population":0,
    "gn:timezone":"Asia/Tokyo",
    "iso:country":"JP",
    "name:jpn_x_preferred":[
        "\u5bfa\u5d0e"
    ],
    "name:jpn_x_variant":[
        "\u3066\u3089\u3056\u304d",
        "\u30c6\u30e9\u30b6\u30ad"
    ],
    "wof:name":"Terazaki",
    "wof:placetype":"locality"
},
  "geometry": {"coordinates":[140.53883000000002,40.22376],"type":"Point"}
}