{
  "type": "Feature",
  "properties": {
    "iso:country":"JP",
    "name:eng_x_preferred":[
        "Suzaku 5 Chome"
    ],
    "name:eng_x_variant":[
        "Suzaku 5 Choume",
        "Suzaku 5 Chome"
    ],
    "name:jpn_x_preferred":[
        "\uff15\u4e01\u76ee"
    ],
    "name:jpn_x_variant":[
        "\u3059\u3056\u304f \uff15\u3061\u3087\u3046\u3081",
        "\u6731\u96c0 \uff15\u4e01\u76ee",
        "\uff15\u3061\u3087\u3046\u3081"
    ],
    "qs:gn_local":0,
    "qs:local_max":830,
    "qs:local_sum":2653,
    "qs:localhoods":9,
    "qs:name":"\uff15\u4e01\u76ee",
    "qs:name_adm0":"\u65e5\u672c",
    "qs:name_adm1":"\u798f\u5ca1\u770c",
    "qs:name_en":"Suzaku 5 Chome",
    "qs:name_lau":"\u6731\u96c0",
    "qs:name_local":"\u592a\u5bb0\u5e9c\u5e02",
    "qs:photo_max":270,
    "qs:photo_sum":433,
    "qs:placetype":"Suburb",
    "qs:quad_count":4,
    "qs:woe_adm0":23424856,
    "qs:woe_adm1":58646425,
    "qs:woe_adm2":0,
    "qs:woe_lau":28484548,
    "qs:woe_local":1117057,
    "qs:woe_ver":"7.10.0",
    "wof:lang":[
        "jpn"
    ],
    "wof:name":"\uff15\u4e01\u76ee",
    "wof:placetype":"neighbourhood"
},
  "geometry": {"coordinates":[130.51716500000001,33.512135],"type":"Point"}
}