{
  "type": "Feature",
  "properties": {
    "gn:admin1_code":"46",
    "gn:admin2_code":"1849556.0",
    "gn:asciiname":"Shishidome",
    "gn:cc2":"JP",
    "gn:country_code":"JP",
    "gn:dem":575,
    "gn:feature_class":"P",
    "gn:feature_code":"PPL",
    "gn:name":"Shishidome",
    "gn:population":0,
    "gn:timezone":"Asia/Tokyo",
    "iso:country":"JP",
    "name:und_x_variant":[
        "Shikadome",
        "Shishitome",
        "Shishidome"
    ],
    "wof:name":"Shishidome",
    "wof:placetype":"locality"
},
  "geometry": {"coordinates":[138.86667,35.53333],"type":"Point"}
}