{
  "type": "Feature",
  "properties": {
    "gn:admin1_code":"21.0",
    "gn:admin2_code":"7413150.0",
    "gn:asciiname":"Urayatani",
    "gn:country_code":"JP",
    "gn:dem":293,
    "gn:feature_class":"P",
    "gn:feature_code":"PPLL",
    "gn:name":"Urayatani",
    "gn:population":0,
    "gn:timezone":"Asia/Tokyo",
    "iso:country":"JP",
    "name:jpn_x_preferred":[
        "\u6d66\u77e2\u8c37"
    ],
    "name:jpn_x_variant":[
        "\u3046\u3089\u3084\u305f\u306b",
        "\u30a6\u30e9\u30e4\u30bf\u30cb"
    ],
    "wof:name":"Urayatani",
    "wof:placetype":"locality"
},
  "geometry": {"coordinates":[130.78797,33.08519],"type":"Point"}
}