{
  "type": "Feature",
  "properties": {
    "gn:admin1_code":"24.0",
    "gn:admin2_code":"7446990.0",
    "gn:asciiname":"Hedahara",
    "gn:country_code":"JP",
    "gn:dem":17,
    "gn:feature_class":"P",
    "gn:feature_code":"PPL",
    "gn:name":"Hedahara",
    "gn:population":0,
    "gn:timezone":"Asia/Tokyo",
    "iso:country":"JP",
    "name:jpn_x_preferred":[
        "\u5e73\u7530\u539f"
    ],
    "name:jpn_x_variant":[
        "\u3078\u3060\u306f\u3089",
        "\u30d8\u30c0\u30cf\u30e9"
    ],
    "wof:name":"Hedahara",
    "wof:placetype":"locality"
},
  "geometry": {"coordinates":[141.18908999999999,38.45824],"type":"Point"}
}