{
  "type": "Feature",
  "properties": {
    "gn:admin1_code":"6.0",
    "gn:admin2_code":"7467385.0",
    "gn:asciiname":"Maedani",
    "gn:country_code":"JP",
    "gn:dem":28,
    "gn:feature_class":"P",
    "gn:feature_code":"PPL",
    "gn:name":"Maedani",
    "gn:population":0,
    "gn:timezone":"Asia/Tokyo",
    "iso:country":"JP",
    "name:jpn_x_preferred":[
        "\u524d\u8c37"
    ],
    "wof:name":"Maedani",
    "wof:placetype":"locality"
},
  "geometry": {"coordinates":[136.27444,36.20257],"type":"Point"}
}