{
  "type": "Feature",
  "properties": {
    "gn:country":"JP",
    "gn:fcode":"ADM3",
    "gn:pop":0,
    "iso:country":"JP",
    "name:jpn_x_preferred":[
        "\u4e2d\u533a"
    ],
    "name:jpn_x_variant":[
        "\u306a\u304b\u304f",
        "\u6d5c\u677e\u5e02\u4e2d\u533a"
    ],
    "qs:name":"Naka-ku",
    "qs:photos_9r":0,
    "qs:photos_sr":0,
    "qs:pop_sr":"0",
    "wd:wordcount":50,
    "wof:name":"Naka-ku",
    "wof:placetype":"localadmin",
    "wof:population":0
},
  "geometry": {"coordinates":[137.7193,34.72939],"type":"Point"}
}