{
  "type": "Feature",
  "properties": {
    "gn:admin1_code":"11",
    "gn:admin2_code":"8740425.0",
    "gn:asciiname":"Nomicho-kanokawa",
    "gn:country_code":"JP",
    "gn:dem":13,
    "gn:feature_class":"P",
    "gn:feature_code":"PPL",
    "gn:name":"N\u014dmich\u014d-kanokawa",
    "gn:population":0,
    "gn:timezone":"Asia/Tokyo",
    "iso:country":"JP",
    "name:jpn_x_preferred":[
        "\u80fd\u7f8e\u753a\u9e7f\u5ddd"
    ],
    "name:und_x_variant":[
        "Hama",
        "Kanokawa",
        "N\u014dmich\u014d-kanokawa"
    ],
    "wof:name":"Nomicho-kanokawa",
    "wof:placetype":"locality"
},
  "geometry": {"coordinates":[132.44234,34.20056],"type":"Point"}
}