{
  "type": "Feature",
  "properties": {
    "gn:admin1_code":"12.0",
    "gn:admin2_code":"7428113.0",
    "gn:admin3_code":"1392.0",
    "gn:asciiname":"Kami-yubetsu",
    "gn:country_code":"JP",
    "gn:dem":9,
    "gn:feature_class":"P",
    "gn:feature_code":"PPL",
    "gn:name":"Kami-yubetsu",
    "gn:population":0,
    "gn:timezone":"Asia/Tokyo",
    "iso:country":"JP",
    "name:und_x_variant":[
        "Yubetsu",
        "Kami-yubetsu"
    ],
    "wof:name":"Kami-yubetsu",
    "wof:placetype":"locality"
},
  "geometry": {"coordinates":[140.28593999999998,42.7498],"type":"Point"}
}