{
  "type": "Feature",
  "properties": {
    "gn:admin1_code":"4.0",
    "gn:admin2_code":"1859468.0",
    "gn:asciiname":"Manobori-shinden",
    "gn:country_code":"JP",
    "gn:dem":187,
    "gn:feature_class":"P",
    "gn:feature_code":"PPLL",
    "gn:name":"Manobori-shinden",
    "gn:population":0,
    "gn:timezone":"Asia/Tokyo",
    "iso:country":"JP",
    "name:jpn_x_preferred":[
        "\u99ac\u767b\u65b0\u7530"
    ],
    "name:jpn_x_variant":[
        "\u307e\u306e\u307c\u308a\u3057\u3093\u3067\u3093",
        "\u30de\u30ce\u30dc\u30ea\u30b7\u30f3\u30c7\u30f3"
    ],
    "wof:name":"Manobori-shinden",
    "wof:placetype":"locality"
},
  "geometry": {"coordinates":[139.95231999999999,35.26763],"type":"Point"}
}