{
  "type": "Feature",
  "properties": {
    "gn:admin1_code":"13",
    "gn:admin2_code":"7370816.0",
    "gn:asciiname":"Iso",
    "gn:country_code":"JP",
    "gn:dem":105,
    "gn:feature_class":"P",
    "gn:feature_code":"PPL",
    "gn:name":"Is\u014d",
    "gn:population":0,
    "gn:timezone":"Asia/Tokyo",
    "iso:country":"JP",
    "name:jpn_x_preferred":[
        "Is\u014d"
    ],
    "wof:name":"Iso",
    "wof:placetype":"locality"
},
  "geometry": {"coordinates":[135.06666999999999,35.15],"type":"Point"}
}