{
  "type": "Feature",
  "properties": {
    "gn:admin1_code":"21.0",
    "gn:admin2_code":"7412706.0",
    "gn:admin3_code":"43441.0",
    "gn:asciiname":"Nanataki",
    "gn:country_code":"JP",
    "gn:dem":205,
    "gn:feature_class":"P",
    "gn:feature_code":"PPL",
    "gn:name":"Nanataki",
    "gn:population":0,
    "gn:timezone":"Asia/Tokyo",
    "iso:country":"JP",
    "name:jpn_x_preferred":[
        "\u4e03\u6edd"
    ],
    "name:jpn_x_variant":[
        "\u306a\u306a\u305f\u304d",
        "\u30ca\u30ca\u30bf\u30ad"
    ],
    "wof:name":"Nanataki",
    "wof:placetype":"locality"
},
  "geometry": {"coordinates":[130.86199999999999,32.72139],"type":"Point"}
}