{
  "type": "Feature",
  "properties": {
    "iso:country":"JP",
    "name:eng_x_preferred":[
        "Daishiekimae 1 Chome"
    ],
    "name:eng_x_variant":[
        "Daishiekimae 1 Choume",
        "Daishiekimae 1 Chome"
    ],
    "name:jpn_x_preferred":[
        "\uff11\u4e01\u76ee"
    ],
    "name:jpn_x_variant":[
        "\u3060\u3044\u3057\u3048\u304d\u307e\u3048 \uff11\u3061\u3087\u3046\u3081",
        "\u5927\u5e2b\u99c5\u524d \uff11\u4e01\u76ee",
        "\uff11\u3061\u3087\u3046\u3081"
    ],
    "qs:gn_adm0_cc":"JP",
    "qs:gn_local":1859642,
    "qs:local_max":4758,
    "qs:local_sum":25395,
    "qs:localhoods":83,
    "qs:name":"\uff11\u4e01\u76ee",
    "qs:name_adm0":"\u65e5\u672c",
    "qs:name_adm1":"\u795e\u5948\u5ddd\u770c",
    "qs:name_adm2":"\u5ddd\u5d0e\u533a",
    "qs:name_en":"Daishiekimae 1 Chome",
    "qs:name_lau":"\u5927\u5e2b\u99c5\u524d",
    "qs:name_local":"\u5ddd\u5d0e\u5e02",
    "qs:photo_max":200,
    "qs:photo_sum":322,
    "qs:placetype":"Suburb",
    "qs:quad_count":5,
    "qs:woe_adm0":23424856,
    "qs:woe_adm1":2345868,
    "qs:woe_adm2":15015510,
    "qs:woe_lau":28416309,
    "qs:woe_local":1117502,
    "qs:woe_ver":"7.10.0",
    "wof:lang":[
        "jpn"
    ],
    "wof:name":"\uff11\u4e01\u76ee",
    "wof:placetype":"neighbourhood"
},
  "geometry": {"coordinates":[139.724514,35.536306],"type":"Point"}
}