{
  "type": "Feature",
  "properties": {
    "gn:admin1_code":"33.0",
    "gn:admin2_code":"1854650.0",
    "gn:asciiname":"Ogimachi-funada",
    "gn:country_code":"JP",
    "gn:dem":7,
    "gn:feature_class":"P",
    "gn:feature_code":"PPL",
    "gn:name":"Ogimachi-funada",
    "gn:population":0,
    "gn:timezone":"Asia/Tokyo",
    "iso:country":"JP",
    "name:jpn_x_preferred":[
        "\u5c0f\u57ce\u753a\u8239\u7530"
    ],
    "wof:name":"Ogimachi-funada",
    "wof:placetype":"locality"
},
  "geometry": {"coordinates":[130.19035,33.27497],"type":"Point"}
}