{
  "type": "Feature",
  "properties": {
    "gn:admin1_code":"24.0",
    "gn:admin2_code":"7447001.0",
    "gn:asciiname":"Hirawata",
    "gn:country_code":"JP",
    "gn:dem":13,
    "gn:feature_class":"P",
    "gn:feature_code":"PPL",
    "gn:name":"Hirawata",
    "gn:population":0,
    "gn:timezone":"Asia/Tokyo",
    "iso:country":"JP",
    "name:jpn_x_preferred":[
        "\u5e73\u6e21"
    ],
    "name:jpn_x_variant":[
        "\u3072\u3089\u308f\u305f",
        "\u30d2\u30e9\u30ef\u30bf"
    ],
    "wof:name":"Hirawata",
    "wof:placetype":"locality"
},
  "geometry": {"coordinates":[141.09151,38.47434000000001],"type":"Point"}
}