{
  "type": "Feature",
  "properties": {
    "gn:admin1_code":"40.0",
    "gn:admin2_code":"1859308.0",
    "gn:asciiname":"Oji-honcho",
    "gn:country_code":"JP",
    "gn:dem":28,
    "gn:feature_class":"P",
    "gn:feature_code":"PPL",
    "gn:name":"\u014cji-honch\u014d",
    "gn:population":0,
    "gn:timezone":"Asia/Tokyo",
    "iso:country":"JP",
    "name:jpn_x_preferred":[
        "\u738b\u5b50\u672c\u753a"
    ],
    "name:und_x_variant":[
        "\u014cji-honch\u014d"
    ],
    "wof:name":"Oji-honcho",
    "wof:placetype":"locality"
},
  "geometry": {"coordinates":[139.73157,35.756],"type":"Point"}
}