{
  "type": "Feature",
  "properties": {
    "gn:admin1_code":"43",
    "gn:admin2_code":"1850706.0",
    "gn:asciiname":"Doyukawa",
    "gn:country_code":"JP",
    "gn:dem":702,
    "gn:feature_class":"P",
    "gn:feature_code":"PPL",
    "gn:name":"D\u014dyukawa",
    "gn:population":0,
    "gn:timezone":"Asia/Tokyo",
    "iso:country":"JP",
    "name:und_x_variant":[
        "D\u014dyukawa"
    ],
    "wof:name":"Doyukawa",
    "wof:placetype":"locality"
},
  "geometry": {"coordinates":[135.68333000000001,33.83333],"type":"Point"}
}