{
  "type": "Feature",
  "properties": {
    "gn:admin1_code":"19.0",
    "gn:admin2_code":"1865011.0",
    "gn:admin3_code":"14364.0",
    "gn:asciiname":"Koshiji",
    "gn:country_code":"JP",
    "gn:dem":108,
    "gn:feature_class":"P",
    "gn:feature_code":"PPLL",
    "gn:name":"Koshiji",
    "gn:population":0,
    "gn:timezone":"Asia/Tokyo",
    "iso:country":"JP",
    "name:jpn_x_preferred":[
        "\u8d8a\u5730"
    ],
    "wof:name":"Koshiji",
    "wof:placetype":"locality"
},
  "geometry": {"coordinates":[139.09238999999999,35.35535],"type":"Point"}
}