{
  "type": "Feature",
  "properties": {
    "gn:admin1_code":"21.0",
    "gn:admin2_code":"1865358.0",
    "gn:asciiname":"Kinnoiri",
    "gn:country_code":"JP",
    "gn:dem":119,
    "gn:feature_class":"P",
    "gn:feature_code":"PPLL",
    "gn:name":"Kinnoiri",
    "gn:population":0,
    "gn:timezone":"Asia/Tokyo",
    "iso:country":"JP",
    "name:jpn_x_preferred":[
        "\u91d1\u306e\u5165"
    ],
    "name:jpn_x_variant":[
        "\u304d\u3093\u306e\u3044\u308a",
        "\u30ad\u30f3\u30ce\u30a4\u30ea"
    ],
    "wof:name":"Kinnoiri",
    "wof:placetype":"locality"
},
  "geometry": {"coordinates":[130.1293,32.38107],"type":"Point"}
}