{
  "type": "Feature",
  "properties": {
    "gn:admin1_code":"34.0",
    "gn:admin2_code":"1858728.0",
    "gn:asciiname":"Kitakoshigaya",
    "gn:country_code":"JP",
    "gn:dem":8,
    "gn:feature_class":"P",
    "gn:feature_code":"PPL",
    "gn:name":"Kitakoshigaya",
    "gn:population":0,
    "gn:timezone":"Asia/Tokyo",
    "iso:country":"JP",
    "name:jpn_x_preferred":[
        "\u5317\u8d8a\u8c37"
    ],
    "wof:name":"Kitakoshigaya",
    "wof:placetype":"locality"
},
  "geometry": {"coordinates":[139.77645999999999,35.90195],"type":"Point"}
}