{
  "type": "Feature",
  "properties": {
    "gn:admin1_code":"21.0",
    "gn:admin2_code":"1862350.0",
    "gn:asciiname":"Ganjojimachi",
    "gn:country_code":"JP",
    "gn:dem":122,
    "gn:feature_class":"P",
    "gn:feature_code":"PPL",
    "gn:name":"Ganj\u014djimachi",
    "gn:population":0,
    "gn:timezone":"Asia/Tokyo",
    "iso:country":"JP",
    "name:jpn_x_preferred":[
        "\u9858\u6210\u5bfa\u753a"
    ],
    "name:und_x_variant":[
        "Ganj\u014djimachi"
    ],
    "wof:name":"Ganjojimachi",
    "wof:placetype":"locality"
},
  "geometry": {"coordinates":[130.7749,32.22068],"type":"Point"}
}