{
  "type": "Feature",
  "properties": {
    "gn:admin1_code":"44.0",
    "gn:admin2_code":"2112756.0",
    "gn:admin3_code":"6381.0",
    "gn:asciiname":"Kameoka",
    "gn:country_code":"JP",
    "gn:dem":226,
    "gn:feature_class":"P",
    "gn:feature_code":"PPL",
    "gn:name":"Kameoka",
    "gn:population":0,
    "gn:timezone":"Asia/Tokyo",
    "iso:country":"JP",
    "name:jpn_x_preferred":[
        "\u4e80\u5ca1"
    ],
    "wof:name":"Kameoka",
    "wof:placetype":"locality"
},
  "geometry": {"coordinates":[140.18691000000001,37.97909],"type":"Point"}
}