{
  "type": "Feature",
  "properties": {
    "iso:country":"JP",
    "qs:name":"\u795e\u6d25\u5cf6\u6751",
    "qs:name_adm0":"\u65e5\u672c",
    "qs:name_adm1":"\u6771\u4eac\u90fd",
    "qs:photos":917,
    "qs:photos_1k":186,
    "qs:photos_9k":4,
    "qs:photos_9r":6,
    "qs:photos_all":917,
    "qs:photos_sr":10,
    "qs:placetype":"Town",
    "qs:pop_sr":"0",
    "wof:name":"\u795e\u6d25\u5cf6\u6751",
    "wof:placetype":"locality"
},
  "geometry": {"coordinates":[139.137382,34.208128],"type":"Point"}
}