{
  "type": "Feature",
  "properties": {
    "gn:admin1_code":"21.0",
    "gn:admin2_code":"1864975.0",
    "gn:admin3_code":"43433.0",
    "gn:asciiname":"Hisaishi",
    "gn:country_code":"JP",
    "gn:dem":419,
    "gn:feature_class":"P",
    "gn:feature_code":"PPL",
    "gn:name":"Hisaishi",
    "gn:population":0,
    "gn:timezone":"Asia/Tokyo",
    "iso:country":"JP",
    "name:jpn_x_preferred":[
        "\u4e45\u77f3"
    ],
    "name:jpn_x_variant":[
        "\u3072\u3055\u3044\u3057",
        "\u30d2\u30b5\u30a4\u30b7"
    ],
    "wof:name":"Hisaishi",
    "wof:placetype":"locality"
},
  "geometry": {"coordinates":[131.05431999999999,32.8186],"type":"Point"}
}