{
  "type": "Feature",
  "properties": {
    "gn:admin1_code":"12",
    "gn:admin2_code":"2038726.0",
    "gn:admin3_code":"1367.0",
    "gn:asciiname":"Yunohama",
    "gn:country_code":"JP",
    "gn:dem":224,
    "gn:feature_class":"P",
    "gn:feature_code":"PPL",
    "gn:name":"Yunohama",
    "gn:population":0,
    "gn:timezone":"Asia/Tokyo",
    "iso:country":"JP",
    "name:jpn_x_preferred":[
        "\u6e6f\u6d5c"
    ],
    "name:jpn_x_variant":[
        "\u3086\u306e\u306f\u307e",
        "\u30e6\u30ce\u30cf\u30de"
    ],
    "wof:name":"Yunohama",
    "wof:placetype":"locality"
},
  "geometry": {"coordinates":[139.41908000000001,42.16886],"type":"Point"}
}