{
  "type": "Feature",
  "properties": {
    "gn:admin1_code":"3.0",
    "gn:admin2_code":"7439944.0",
    "gn:asciiname":"Kinda",
    "gn:country_code":"JP",
    "gn:dem":10,
    "gn:feature_class":"P",
    "gn:feature_code":"PPL",
    "gn:name":"Kinda",
    "gn:population":0,
    "gn:timezone":"Asia/Tokyo",
    "iso:country":"JP",
    "name:ceb_x_preferred":[
        "Kinda"
    ],
    "name:deu_x_preferred":[
        "Kinda"
    ],
    "name:jpn_x_preferred":[
        "\u91d1\u7530"
    ],
    "name:jpn_x_variant":[
        "\u304d\u3093\u3060",
        "\u30ad\u30f3\u30c0"
    ],
    "name:swe_x_preferred":[
        "Kinda"
    ],
    "wof:name":"Kinda",
    "wof:placetype":"locality"
},
  "geometry": {"coordinates":[140.40661,40.79553],"type":"Point"}
}