{
  "type": "Feature",
  "properties": {
    "gn:admin1_code":"3.0",
    "gn:admin2_code":"2130056.0",
    "gn:asciiname":"Tsuchido",
    "gn:country_code":"JP",
    "gn:dem":29,
    "gn:feature_class":"P",
    "gn:feature_code":"PPL",
    "gn:name":"Tsuchid\u014d",
    "gn:population":0,
    "gn:timezone":"Asia/Tokyo",
    "iso:country":"JP",
    "name:jpn_x_preferred":[
        "\u571f\u5802"
    ],
    "name:jpn_x_variant":[
        "\u3064\u3061\u3069\u3046",
        "\u30c4\u30c1\u30c9\u30a6"
    ],
    "name:und_x_variant":[
        "Tsuchid\u014d"
    ],
    "wof:name":"Tsuchido",
    "wof:placetype":"locality"
},
  "geometry": {"coordinates":[140.44597999999999,40.62213],"type":"Point"}
}