{
  "type": "Feature",
  "properties": {
    "gn:admin1_code":"21.0",
    "gn:admin2_code":"1864973.0",
    "gn:asciiname":"Ryuzuka",
    "gn:country_code":"JP",
    "gn:dem":825,
    "gn:feature_class":"P",
    "gn:feature_code":"PPLL",
    "gn:name":"Ry\u016bzuka",
    "gn:population":0,
    "gn:timezone":"Asia/Tokyo",
    "iso:country":"JP",
    "name:jpn_x_preferred":[
        "\u7acb\u585a"
    ],
    "name:jpn_x_variant":[
        "\u308a\u3085\u3046\u3065\u304b",
        "\u30ea\u30e5\u30a6\u30c5\u30ab"
    ],
    "name:und_x_variant":[
        "Ry\u016bzuka"
    ],
    "wof:name":"Ryuzuka",
    "wof:placetype":"locality"
},
  "geometry": {"coordinates":[131.16623999999999,32.91629],"type":"Point"}
}