{
  "type": "Feature",
  "properties": {
    "gn:admin1_code":"45.0",
    "gn:admin2_code":"1852222.0",
    "gn:asciiname":"Furuyacho",
    "gn:country_code":"JP",
    "gn:dem":12,
    "gn:feature_class":"P",
    "gn:feature_code":"PPL",
    "gn:name":"Furuyach\u014d",
    "gn:population":0,
    "gn:timezone":"Asia/Tokyo",
    "iso:country":"JP",
    "name:jpn_x_preferred":[
        "\u53e4\u5c4b\u753a"
    ],
    "name:und_x_variant":[
        "Furuyach\u014d"
    ],
    "wof:name":"Furuyacho",
    "wof:placetype":"locality"
},
  "geometry": {"coordinates":[130.92292,33.99888],"type":"Point"}
}