{
  "type": "Feature",
  "properties": {
    "gn:admin1_code":"21.0",
    "gn:admin2_code":"1865358.0",
    "gn:asciiname":"Kashi",
    "gn:country_code":"JP",
    "gn:dem":9,
    "gn:feature_class":"P",
    "gn:feature_code":"PPLL",
    "gn:name":"Kashi",
    "gn:population":0,
    "gn:timezone":"Asia/Tokyo",
    "iso:country":"JP",
    "name:cat_x_preferred":[
        "Kashi"
    ],
    "name:ceb_x_preferred":[
        "Kashi"
    ],
    "name:deu_x_preferred":[
        "Kashi"
    ],
    "name:fra_x_preferred":[
        "Kashi"
    ],
    "name:heb_x_preferred":[
        "\u05e7\u05d0\u05e9\u05d9"
    ],
    "name:hin_x_preferred":[
        "\u0915\u093e\u0936\u0940"
    ],
    "name:ita_x_preferred":[
        "Kashi"
    ],
    "name:jpn_x_preferred":[
        "\u52a0\u5fd7"
    ],
    "name:jpn_x_variant":[
        "\u304b\u3057",
        "\u30ab\u30b7"
    ],
    "name:nld_x_preferred":[
        "Kashi"
    ],
    "name:sco_x_preferred":[
        "Kashi"
    ],
    "name:swe_x_preferred":[
        "Kashi"
    ],
    "wof:name":"Kashi",
    "wof:placetype":"locality"
},
  "geometry": {"coordinates":[130.20633000000001,32.44429],"type":"Point"}
}