{
  "type": "Feature",
  "properties": {
    "iso:country":"JP",
    "name:jpn_x_preferred":[
        "\uff08\u4e01\u76ee\u306a\u3057\uff09"
    ],
    "qs:gn_local":0,
    "qs:local_max":63,
    "qs:local_sum":150,
    "qs:localhoods":3,
    "qs:name":"\uff08\u4e01\u76ee\u306a\u3057\uff09",
    "qs:name_adm0":"\u65e5\u672c",
    "qs:name_adm1":"\u9999\u5ddd\u770c",
    "qs:name_lau":"\u4e0a\u5409\u7530\u753a",
    "qs:name_local":"\u5584\u901a\u5bfa\u5e02",
    "qs:photo_max":25,
    "qs:photo_sum":63,
    "qs:placetype":"Suburb",
    "qs:quad_count":10,
    "qs:woe_adm0":23424856,
    "qs:woe_adm1":2345866,
    "qs:woe_adm2":0,
    "qs:woe_lau":28478687,
    "qs:woe_local":15015470,
    "qs:woe_ver":"7.10.0",
    "wof:lang":[
        "jpn"
    ],
    "wof:name":"\uff08\u4e01\u76ee\u306a\u3057\uff09",
    "wof:placetype":"neighbourhood"
},
  "geometry": {"coordinates":[133.78183799999999,34.228114],"type":"Point"}
}