{
  "type": "Feature",
  "properties": {
    "gn:admin1_code":"7.0",
    "gn:admin2_code":"7407413.0",
    "gn:asciiname":"Ido",
    "gn:country_code":"JP",
    "gn:dem":44,
    "gn:feature_class":"P",
    "gn:feature_code":"PPLL",
    "gn:name":"Ido",
    "gn:population":0,
    "gn:timezone":"Asia/Tokyo",
    "iso:country":"JP",
    "name:jpn_x_preferred":[
        "\u4e95\u571f"
    ],
    "wof:name":"Ido",
    "wof:placetype":"locality"
},
  "geometry": {"coordinates":[130.72498999999999,33.55416],"type":"Point"}
}