{
  "type": "Feature",
  "properties": {
    "gn:admin1_code":"7.0",
    "gn:admin2_code":"1863955.0",
    "gn:admin3_code":"40137.0",
    "gn:asciiname":"Nishijin",
    "gn:country_code":"JP",
    "gn:dem":8,
    "gn:feature_class":"P",
    "gn:feature_code":"PPL",
    "gn:name":"Nishijin",
    "gn:population":0,
    "gn:timezone":"Asia/Tokyo",
    "iso:country":"JP",
    "name:jpn_x_preferred":[
        "\u897f\u65b0"
    ],
    "wof:name":"Nishijin",
    "wof:placetype":"locality"
},
  "geometry": {"coordinates":[130.35547,33.58531],"type":"Point"}
}