{
  "type": "Feature",
  "properties": {
    "gn:country":"JP",
    "gn:fcode":"PPL",
    "gn:population":20758,
    "iso:country":"JP",
    "name:ara_x_preferred":[
        "\u063a\u0648\u062f\u0648"
    ],
    "name:arz_x_preferred":[
        "\u062c\u0648\u062f\u0648"
    ],
    "name:ast_x_preferred":[
        "G\u014ddo"
    ],
    "name:ceb_x_preferred":[
        "G\u014ddo"
    ],
    "name:ces_x_preferred":[
        "G\u00f3do"
    ],
    "name:deu_x_preferred":[
        "G\u014ddo"
    ],
    "name:eng_x_preferred":[
        "G\u014ddo"
    ],
    "name:fas_x_preferred":[
        "\u06af\u0648\u062f\u0648"
    ],
    "name:fra_x_preferred":[
        "G\u014ddo"
    ],
    "name:gle_x_preferred":[
        "G\u014ddo"
    ],
    "name:ita_x_preferred":[
        "G\u014ddo"
    ],
    "name:jpn_x_preferred":[
        "\u795e\u6238\u753a"
    ],
    "name:kor_x_preferred":[
        "\uace0\ub3c4 \uc815"
    ],
    "name:kor_x_variant":[
        "\uace0\ub3c4\uc815"
    ],
    "name:mlg_x_preferred":[
        "G\u014ddo"
    ],
    "name:msa_x_preferred":[
        "G\u014ddo"
    ],
    "name:mya_x_preferred":[
        "\u1002\u102d\u102f\u1038\u1012\u102d\u102f\u1019\u103c\u102d\u102f\u1037\u104a \u1002\u102d\u1016\u102f"
    ],
    "name:nan_x_preferred":[
        "G\u00f4do-teng"
    ],
    "name:nld_x_preferred":[
        "G\u014ddo"
    ],
    "name:por_x_preferred":[
        "Godo"
    ],
    "name:rus_x_preferred":[
        "\u0413\u043e\u0434\u0430"
    ],
    "name:rus_x_variant":[
        "\u0413\u043e\u0434\u043e"
    ],
    "name:spa_x_preferred":[
        "G\u014ddo"
    ],
    "name:tgl_x_preferred":[
        "G\u014ddo"
    ],
    "name:ukr_x_preferred":[
        "\u0490\u043e\u0434\u043e"
    ],
    "name:und_x_variant":[
        "G\u014dd\u014d-ch\u014d"
    ],
    "name:uzb_x_preferred":[
        "G\u014ddo"
    ],
    "name:zho_x_preferred":[
        "\u795e\u6236\u753a"
    ],
    "qs:name":"G\u014ddo",
    "qs:photos_9r":0,
    "qs:photos_sr":0,
    "qs:pop_sr":"7",
    "wof:name":"G\u014ddo",
    "wof:placetype":"locality",
    "wof:population":20758
},
  "geometry": {"coordinates":[136.59999999999999,35.41667],"type":"Point"}
}