{
  "type": "Feature",
  "properties": {
    "gn:admin1_code":"19.0",
    "gn:admin2_code":"1863429.0",
    "gn:asciiname":"Hassawa",
    "gn:country_code":"JP",
    "gn:dem":254,
    "gn:feature_class":"P",
    "gn:feature_code":"PPL",
    "gn:name":"Hassawa",
    "gn:population":0,
    "gn:timezone":"Asia/Tokyo",
    "iso:country":"JP",
    "name:jpn_x_preferred":[
        "\u516b\u6ca2"
    ],
    "wof:name":"Hassawa",
    "wof:placetype":"locality"
},
  "geometry": {"coordinates":[139.14991000000001,35.3781],"type":"Point"}
}