{
  "type": "Feature",
  "properties": {
    "gn:admin1_code":"05",
    "gn:admin2_code":"1854782.0",
    "gn:admin3_code":"38356.0",
    "gn:asciiname":"Yuge-habu",
    "gn:country_code":"JP",
    "gn:dem":76,
    "gn:feature_class":"P",
    "gn:feature_code":"PPL",
    "gn:name":"Yuge-habu",
    "gn:population":0,
    "gn:timezone":"Asia/Tokyo",
    "iso:country":"JP",
    "name:jpn_x_preferred":[
        "\u5f13\u524a\u571f\u751f"
    ],
    "name:und_x_variant":[
        "Shimo-yuge",
        "Yuge",
        "Yuge-habu"
    ],
    "wof:name":"Yuge-habu",
    "wof:placetype":"locality"
},
  "geometry": {"coordinates":[133.20389,34.265],"type":"Point"}
}