{
  "type": "Feature",
  "properties": {
    "iso:country":"JP",
    "name:eng_x_preferred":[
        "Aza Kanmuri Ishishita"
    ],
    "name:jpn_x_preferred":[
        "\u5b57\u51a0\u77f3\u4e0b"
    ],
    "qs:name":"\u5b57\u51a0\u77f3\u4e0b",
    "qs:name_adm0":"\u65e5\u672c",
    "qs:name_adm1":"\u79cb\u7530\u770c",
    "qs:photos":5,
    "qs:photos_1k":1,
    "qs:photos_9k":1,
    "qs:photos_9r":1,
    "qs:photos_all":5,
    "qs:photos_sr":1,
    "qs:placetype":"Suburb",
    "qs:pop_sr":"0",
    "wof:name":"Aza Kanmuri Ishishita",
    "wof:placetype":"neighbourhood"
},
  "geometry": {"coordinates":[139.89443199999999,39.206913],"type":"Point"}
}