{
  "type": "Feature",
  "properties": {
    "gn:admin1_code":"21.0",
    "gn:admin2_code":"1857206.0",
    "gn:asciiname":"Shin'yashiki",
    "gn:country_code":"JP",
    "gn:dem":118,
    "gn:feature_class":"P",
    "gn:feature_code":"PPLL",
    "gn:name":"Shin\u2019yashiki",
    "gn:population":0,
    "gn:timezone":"Asia/Tokyo",
    "iso:country":"JP",
    "name:jpn_x_preferred":[
        "\u65b0\u5c4b\u6577"
    ],
    "name:jpn_x_variant":[
        "\u3057\u3093\u3084\u3057\u304d",
        "\u30b7\u30f3\u30e4\u30b7\u30ad"
    ],
    "name:und_x_variant":[
        "Shin\u2019yashiki"
    ],
    "wof:name":"Shin'yashiki",
    "wof:placetype":"locality"
},
  "geometry": {"coordinates":[130.43406999999999,32.16996],"type":"Point"}
}