{
  "type": "Feature",
  "properties": {
    "gn:admin1_code":"3.0",
    "gn:admin2_code":"2130200.0",
    "gn:asciiname":"Kamogaike",
    "gn:country_code":"JP",
    "gn:dem":10,
    "gn:feature_class":"P",
    "gn:feature_code":"PPL",
    "gn:name":"Kamogaike",
    "gn:population":0,
    "gn:timezone":"Asia/Tokyo",
    "iso:country":"JP",
    "name:jpn_x_preferred":[
        "\u9d28\u30f6\u6c60"
    ],
    "name:jpn_x_variant":[
        "\u304b\u3082\u304c\u3044\u3051",
        "\u30ab\u30e2\u30ac\u30a4\u30b1"
    ],
    "wof:name":"Kamogaike",
    "wof:placetype":"locality"
},
  "geometry": {"coordinates":[141.43173999999999,40.5127],"type":"Point"}
}