{
  "type": "Feature",
  "properties": {
    "gn:admin1_code":"21.0",
    "gn:admin2_code":"1858418.0",
    "gn:admin3_code":"43101.0",
    "gn:asciiname":"Furukyomachi",
    "gn:country_code":"JP",
    "gn:dem":28,
    "gn:feature_class":"P",
    "gn:feature_code":"PPL",
    "gn:name":"Furuky\u014dmachi",
    "gn:population":0,
    "gn:timezone":"Asia/Tokyo",
    "iso:country":"JP",
    "name:jpn_x_preferred":[
        "\u53e4\u4eac\u753a"
    ],
    "name:jpn_x_variant":[
        "\u3075\u308b\u304d\u3087\u3046\u307e\u3061",
        "\u30d5\u30eb\u30ad\u30e7\u30a6\u30de\u30c1"
    ],
    "name:und_x_variant":[
        "Furuky\u014dmachi"
    ],
    "wof:name":"Furukyomachi",
    "wof:placetype":"locality"
},
  "geometry": {"coordinates":[130.69983999999999,32.80951],"type":"Point"}
}