{
  "type": "Feature",
  "properties": {
    "gn:admin1_code":"42",
    "gn:admin2_code":"1849870.0",
    "gn:asciiname":"Yamadayu",
    "gn:country_code":"JP",
    "gn:dem":158,
    "gn:feature_class":"P",
    "gn:feature_code":"PPL",
    "gn:name":"Yamadayu",
    "gn:population":0,
    "gn:timezone":"Asia/Tokyo",
    "iso:country":"JP",
    "name:jpn_x_preferred":[
        "\u5c71\u7530\u6e6f"
    ],
    "name:und_x_variant":[
        "Yumura",
        "Yu",
        "Yamadayu"
    ],
    "wof:name":"Yamadayu",
    "wof:placetype":"locality"
},
  "geometry": {"coordinates":[137.08080000000001,36.5783],"type":"Point"}
}