{
  "type": "Feature",
  "properties": {
    "gn:admin1_code":"7.0",
    "gn:admin2_code":"1861834.0",
    "gn:asciiname":"Nishisayo",
    "gn:country_code":"JP",
    "gn:dem":18,
    "gn:feature_class":"P",
    "gn:feature_code":"PPLL",
    "gn:name":"Nishisayo",
    "gn:population":0,
    "gn:timezone":"Asia/Tokyo",
    "iso:country":"JP",
    "name:jpn_x_preferred":[
        "\u897f\u4f50\u4e0e"
    ],
    "wof:name":"Nishisayo",
    "wof:placetype":"locality"
},
  "geometry": {"coordinates":[130.72003000000001,33.66507],"type":"Point"}
}