{
  "type": "Feature",
  "properties": {
    "gn:admin1_code":"3.0",
    "gn:admin2_code":"2130654.0",
    "gn:asciiname":"Okunai",
    "gn:country_code":"JP",
    "gn:dem":1,
    "gn:feature_class":"P",
    "gn:feature_code":"PPL",
    "gn:name":"Okunai",
    "gn:population":0,
    "gn:timezone":"Asia/Tokyo",
    "iso:country":"JP",
    "name:jpn_x_preferred":[
        "\u5965\u5185"
    ],
    "name:jpn_x_variant":[
        "\u304a\u304f\u306a\u3044",
        "\u30aa\u30af\u30ca\u30a4"
    ],
    "wof:name":"Okunai",
    "wof:placetype":"locality"
},
  "geometry": {"coordinates":[140.67311999999998,40.89257],"type":"Point"}
}