{
  "type": "Feature",
  "properties": {
    "gn:admin1_code":"23.0",
    "gn:admin2_code":"1849544.0",
    "gn:asciiname":"Ichishicho-hioki",
    "gn:country_code":"JP",
    "gn:dem":11,
    "gn:feature_class":"P",
    "gn:feature_code":"PPL",
    "gn:name":"Ichishich\u014d-hioki",
    "gn:population":0,
    "gn:timezone":"Asia/Tokyo",
    "iso:country":"JP",
    "name:jpn_x_preferred":[
        "\u4e00\u5fd7\u753a\u65e5\u7f6e"
    ],
    "name:und_x_variant":[
        "Ichishich\u014d-hioki"
    ],
    "wof:name":"Ichishicho-hioki",
    "wof:placetype":"locality"
},
  "geometry": {"coordinates":[136.44341,34.66255],"type":"Point"}
}