{
  "type": "Feature",
  "properties": {
    "gn:admin1_code":"37.0",
    "gn:admin2_code":"1864089.0",
    "gn:asciiname":"Shinbashicho",
    "gn:country_code":"JP",
    "gn:dem":4,
    "gn:feature_class":"P",
    "gn:feature_code":"PPL",
    "gn:name":"Shinbashich\u014d",
    "gn:population":0,
    "gn:timezone":"Asia/Tokyo",
    "iso:country":"JP",
    "name:jpn_x_preferred":[
        "\u65b0\u6a4b\u753a"
    ],
    "name:und_x_variant":[
        "Shinbashich\u014d"
    ],
    "wof:name":"Shinbashicho",
    "wof:placetype":"locality"
},
  "geometry": {"coordinates":[138.69832,35.16049],"type":"Point"}
}