{
  "type": "Feature",
  "properties": {
    "gn:admin1_code":"16.0",
    "gn:admin2_code":"2112822.0",
    "gn:asciiname":"Shima",
    "gn:country_code":"JP",
    "gn:dem":188,
    "gn:feature_class":"P",
    "gn:feature_code":"PPL",
    "gn:name":"Shima",
    "gn:population":0,
    "gn:timezone":"Asia/Tokyo",
    "iso:country":"JP",
    "name:ceb_x_preferred":[
        "Shima"
    ],
    "name:deu_x_preferred":[
        "Shima"
    ],
    "name:fra_x_preferred":[
        "Shima"
    ],
    "name:heb_x_preferred":[
        "\u05e9\u05d9\u05de\u05d4"
    ],
    "name:jpn_x_preferred":[
        "\u5cf6"
    ],
    "name:jpn_x_variant":[
        "\u3057\u307e",
        "\u30b7\u30de"
    ],
    "name:mlg_x_preferred":[
        "Shima"
    ],
    "name:nds_x_preferred":[
        "Shima"
    ],
    "name:por_x_preferred":[
        "Shima"
    ],
    "name:ron_x_preferred":[
        "Shima"
    ],
    "name:swe_x_preferred":[
        "Shima"
    ],
    "wof:name":"Shima",
    "wof:placetype":"locality"
},
  "geometry": {"coordinates":[141.20916,39.32538],"type":"Point"}
}