{
  "type": "Feature",
  "properties": {
    "gn:admin1_code":"39",
    "gn:admin2_code":"1860803.0",
    "gn:admin3_code":"36387.0",
    "gn:asciiname":"Hiwasaura",
    "gn:country_code":"JP",
    "gn:dem":6,
    "gn:feature_class":"P",
    "gn:feature_code":"PPL",
    "gn:name":"Hiwasaura",
    "gn:population":0,
    "gn:timezone":"Asia/Tokyo",
    "iso:country":"JP",
    "name:jpn_x_preferred":[
        "\u65e5\u548c\u4f50\u6d66"
    ],
    "name:und_x_variant":[
        "Hiwasa"
    ],
    "wof:name":"Hiwasaura",
    "wof:placetype":"locality"
},
  "geometry": {"coordinates":[134.53743,33.73255],"type":"Point"}
}