{
  "type": "Feature",
  "properties": {
    "gn:admin1_code":"21.0",
    "gn:admin2_code":"7413150.0",
    "gn:asciiname":"Tsuru",
    "gn:country_code":"JP",
    "gn:dem":32,
    "gn:feature_class":"P",
    "gn:feature_code":"PPL",
    "gn:name":"Tsuru",
    "gn:population":0,
    "gn:timezone":"Asia/Tokyo",
    "iso:country":"JP",
    "name:jpn_x_preferred":[
        "\u6d25\u7559"
    ],
    "name:jpn_x_variant":[
        "\u3064\u308b",
        "\u30c4\u30eb"
    ],
    "wof:name":"Tsuru",
    "wof:placetype":"locality"
},
  "geometry": {"coordinates":[130.6857,33.05639],"type":"Point"}
}