{
  "type": "Feature",
  "properties": {
    "gn:admin1_code":"3.0",
    "gn:admin2_code":"2130654.0",
    "gn:asciiname":"Fukuda",
    "gn:country_code":"JP",
    "gn:dem":26,
    "gn:feature_class":"P",
    "gn:feature_code":"PPL",
    "gn:name":"Fukuda",
    "gn:population":0,
    "gn:timezone":"Asia/Tokyo",
    "iso:country":"JP",
    "name:jpn_x_preferred":[
        "\u798f\u7530"
    ],
    "name:jpn_x_variant":[
        "\u3075\u304f\u3060",
        "\u30d5\u30af\u30c0"
    ],
    "wof:name":"Fukuda",
    "wof:placetype":"locality"
},
  "geometry": {"coordinates":[140.58685,40.72046],"type":"Point"}
}