{
  "type": "Feature",
  "properties": {
    "gn:admin1_code":"34.0",
    "gn:admin2_code":"1858728.0",
    "gn:asciiname":"Azumacho",
    "gn:country_code":"JP",
    "gn:dem":4,
    "gn:feature_class":"P",
    "gn:feature_code":"PPL",
    "gn:name":"Azumach\u014d",
    "gn:population":0,
    "gn:timezone":"Asia/Tokyo",
    "iso:country":"JP",
    "name:jpn_x_preferred":[
        "\u6771\u753a"
    ],
    "name:und_x_variant":[
        "Azumach\u014d"
    ],
    "wof:name":"Azumacho",
    "wof:placetype":"locality"
},
  "geometry": {"coordinates":[139.83444,35.87862],"type":"Point"}
}