{
  "type": "Feature",
  "properties": {
    "gn:admin1_code":"16.0",
    "gn:asciiname":"Tonai",
    "gn:country_code":"JP",
    "gn:dem":209,
    "gn:feature_class":"P",
    "gn:feature_code":"PPL",
    "gn:name":"Tonai",
    "gn:population":0,
    "gn:timezone":"Asia/Tokyo",
    "iso:country":"JP",
    "name:jpn_x_preferred":[
        "\u6597\u5185"
    ],
    "name:jpn_x_variant":[
        "\u3068\u306a\u3044",
        "\u30c8\u30ca\u30a4"
    ],
    "wof:name":"Tonai",
    "wof:placetype":"locality"
},
  "geometry": {"coordinates":[141.19353000000001,40.32437],"type":"Point"}
}