{
  "type": "Feature",
  "properties": {
    "gn:admin1_code":"16.0",
    "gn:admin2_code":"2112822.0",
    "gn:asciiname":"Yamane",
    "gn:country_code":"JP",
    "gn:dem":217,
    "gn:feature_class":"P",
    "gn:feature_code":"PPL",
    "gn:name":"Yamane",
    "gn:population":0,
    "gn:timezone":"Asia/Tokyo",
    "iso:country":"JP",
    "name:jpn_x_preferred":[
        "\u5c71\u6839"
    ],
    "name:jpn_x_variant":[
        "\u3084\u307e\u306d",
        "\u30e4\u30de\u30cd"
    ],
    "wof:name":"Yamane",
    "wof:placetype":"locality"
},
  "geometry": {"coordinates":[141.25640000000001,39.32518],"type":"Point"}
}