{
  "type": "Feature",
  "properties": {
    "gn:admin1_code":"2.0",
    "gn:admin2_code":"2127468.0",
    "gn:admin3_code":"5348.0",
    "gn:asciiname":"Shimosunakozawa",
    "gn:country_code":"JP",
    "gn:dem":41,
    "gn:feature_class":"P",
    "gn:feature_code":"PPLL",
    "gn:name":"Shimosunakozawa",
    "gn:population":0,
    "gn:timezone":"Asia/Tokyo",
    "iso:country":"JP",
    "name:jpn_x_preferred":[
        "\u4e0b\u7802\u5b50\u6ca2"
    ],
    "wof:name":"Shimosunakozawa",
    "wof:placetype":"locality"
},
  "geometry": {"coordinates":[140.13817,40.04238],"type":"Point"}
}