{
  "type": "Feature",
  "properties": {
    "gn:admin1_code":"21.0",
    "gn:admin2_code":"1862350.0",
    "gn:asciiname":"Minobaru",
    "gn:country_code":"JP",
    "gn:dem":167,
    "gn:feature_class":"P",
    "gn:feature_code":"PPLL",
    "gn:name":"Minobaru",
    "gn:population":0,
    "gn:timezone":"Asia/Tokyo",
    "iso:country":"JP",
    "name:jpn_x_preferred":[
        "\u84d1\u539f"
    ],
    "wof:name":"Minobaru",
    "wof:placetype":"locality"
},
  "geometry": {"coordinates":[130.78565,32.23085],"type":"Point"}
}