{
  "type": "Feature",
  "properties": {
    "iso:country":"JP",
    "label:eng_x_preferred_longname":[
        "Minamikyushu City"
    ],
    "label:eng_x_preferred_placetype":[
        "city"
    ],
    "name:eng_x_preferred":[
        "Minamikyushu"
    ],
    "name:eng_x_variant":[
        "Minamikyushu City"
    ],
    "name:jpn_x_preferred":[
        "\u5357\u4e5d\u5dde\u5e02"
    ],
    "qs:name":"\u5357\u4e5d\u5dde\u5e02",
    "qs:name_adm0":"\u65e5\u672c",
    "qs:name_adm1":"\u9e7f\u5150\u5cf6\u770c",
    "qs:photos":404,
    "qs:photos_1k":82,
    "qs:photos_9k":2,
    "qs:photos_9r":5,
    "qs:photos_all":404,
    "qs:photos_sr":6,
    "qs:placetype":"Town",
    "qs:pop_sr":"0",
    "wof:name":"Minamikyushu",
    "wof:placetype":"locality"
},
  "geometry": {"coordinates":[130.44254699999999,31.3773135],"type":"Point"}
}