{
  "type": "Feature",
  "properties": {
    "gn:admin1_code":"6.0",
    "gn:admin2_code":"1859762.0",
    "gn:asciiname":"Aradocho-shindo",
    "gn:country_code":"JP",
    "gn:dem":195,
    "gn:feature_class":"P",
    "gn:feature_code":"PPL",
    "gn:name":"Aradoch\u014d-shind\u014d",
    "gn:population":0,
    "gn:timezone":"Asia/Tokyo",
    "iso:country":"JP",
    "name:jpn_x_preferred":[
        "\u8352\u571f\u753a\u65b0\u9053"
    ],
    "name:und_x_variant":[
        "Aradoch\u014d-shind\u014d"
    ],
    "wof:name":"Aradocho-shindo",
    "wof:placetype":"locality"
},
  "geometry": {"coordinates":[136.47353000000001,36.10938],"type":"Point"}
}