{
  "type": "Feature",
  "properties": {
    "gn:admin1_code":"12.0",
    "gn:admin2_code":"7428084.0",
    "gn:admin3_code":"1609.0",
    "gn:asciiname":"Sakagishi",
    "gn:country_code":"JP",
    "gn:dem":30,
    "gn:feature_class":"P",
    "gn:feature_code":"PPLL",
    "gn:name":"Sakagishi",
    "gn:population":0,
    "gn:timezone":"Asia/Tokyo",
    "iso:country":"JP",
    "name:jpn_x_preferred":[
        "\u5742\u5cb8"
    ],
    "name:jpn_x_variant":[
        "\u3055\u304b\u304e\u3057",
        "\u30b5\u30ab\u30ae\u30b7"
    ],
    "wof:name":"Sakagishi",
    "wof:placetype":"locality"
},
  "geometry": {"coordinates":[143.18383,41.97087],"type":"Point"}
}