{
  "type": "Feature",
  "properties": {
    "gn:admin1_code":"32",
    "gn:admin2_code":"1853897.0",
    "gn:admin3_code":"27108.0",
    "gn:asciiname":"Kobayashi-higashi",
    "gn:country_code":"JP",
    "gn:dem":6,
    "gn:feature_class":"P",
    "gn:feature_code":"PPL",
    "gn:name":"Kobayashi-higashi",
    "gn:population":0,
    "gn:timezone":"Asia/Tokyo",
    "iso:country":"JP",
    "name:jpn_x_preferred":[
        "\u5c0f\u6797\u6771"
    ],
    "name:und_x_variant":[
        "Kobayashich\u014d"
    ],
    "wof:name":"Kobayashi-higashi",
    "wof:placetype":"locality"
},
  "geometry": {"coordinates":[135.47436000000002,34.64594],"type":"Point"}
}