{
  "type": "Feature",
  "properties": {
    "gn:admin1_code":"34",
    "gn:admin2_code":"1861469.0",
    "gn:asciiname":"Ogimachiya",
    "gn:country_code":"JP",
    "gn:dem":106,
    "gn:feature_class":"P",
    "gn:feature_code":"PPL",
    "gn:name":"\u014cgimachiya",
    "gn:population":0,
    "gn:timezone":"Asia/Tokyo",
    "iso:country":"JP",
    "name:jpn_x_preferred":[
        "\u6247\u753a\u5c4b"
    ],
    "name:und_x_variant":[
        "\u014cgimachiya"
    ],
    "wof:name":"Ogimachiya",
    "wof:placetype":"locality"
},
  "geometry": {"coordinates":[139.38308999999998,35.82993],"type":"Point"}
}