{
  "type": "Feature",
  "properties": {
    "gn:admin1_code":"16.0",
    "gn:admin2_code":"2112822.0",
    "gn:asciiname":"Kannonjima",
    "gn:country_code":"JP",
    "gn:dem":88,
    "gn:feature_class":"P",
    "gn:feature_code":"PPL",
    "gn:name":"Kannonjima",
    "gn:population":0,
    "gn:timezone":"Asia/Tokyo",
    "iso:country":"JP",
    "name:jpn_x_preferred":[
        "\u89b3\u97f3\u5cf6"
    ],
    "name:jpn_x_variant":[
        "\u304b\u3093\u306e\u3093\u3058\u307e",
        "\u30ab\u30f3\u30ce\u30f3\u30b8\u30de"
    ],
    "wof:name":"Kannonjima",
    "wof:placetype":"locality"
},
  "geometry": {"coordinates":[141.17128,39.48771],"type":"Point"}
}