{
  "type": "Feature",
  "properties": {
    "iso:country":"JP",
    "name:eng_x_preferred":[
        "Tenjinmachi 2 Chome"
    ],
    "name:eng_x_variant":[
        "Tenjinmachi 2 Choume",
        "Tenjinmachi 2 Chome"
    ],
    "name:jpn_x_preferred":[
        "\uff12\u4e01\u76ee"
    ],
    "name:jpn_x_variant":[
        "\u3066\u3093\u3058\u3093\u307e\u3061 \uff12\u3061\u3087\u3046\u3081",
        "\u5929\u795e\u753a \uff12\u4e01\u76ee",
        "\uff12\u3061\u3087\u3046\u3081"
    ],
    "qs:gn_adm0_cc":"JP",
    "qs:gn_local":1860243,
    "qs:gn_nam_loc":"\u91d1\u6ca2\u5e02, \u77f3\u5ddd\u770c, JP",
    "qs:gn_namadm1":"15",
    "qs:local_max":2809,
    "qs:local_sum":12445,
    "qs:localhoods":25,
    "qs:name":"\uff12\u4e01\u76ee",
    "qs:name_adm0":"\u65e5\u672c",
    "qs:name_adm1":"\u77f3\u5ddd\u770c",
    "qs:name_en":"Tenjinmachi 2 Chome",
    "qs:name_lau":"\u5929\u795e\u753a",
    "qs:name_local":"\u91d1\u6ca2\u5e02",
    "qs:photo_max":33,
    "qs:photo_sum":59,
    "qs:placetype":"Suburb",
    "qs:quad_count":5,
    "qs:woe_adm0":23424856,
    "qs:woe_adm1":2345864,
    "qs:woe_adm2":0,
    "qs:woe_lau":28426103,
    "qs:woe_local":1117438,
    "qs:woe_ver":"7.10.0",
    "wof:lang":[
        "jpn"
    ],
    "wof:name":"\uff12\u4e01\u76ee",
    "wof:placetype":"neighbourhood"
},
  "geometry": {"coordinates":[136.672943,36.561929],"type":"Point"}
}