{
  "type": "Feature",
  "properties": {
    "gn:admin1_code":"7.0",
    "gn:admin2_code":"1851269.0",
    "gn:admin3_code":"40610.0",
    "gn:asciiname":"Yamazaki",
    "gn:country_code":"JP",
    "gn:dem":18,
    "gn:feature_class":"P",
    "gn:feature_code":"PPLL",
    "gn:name":"Yamazaki",
    "gn:population":0,
    "gn:timezone":"Asia/Tokyo",
    "iso:country":"JP",
    "name:jpn_x_preferred":[
        "\u5c71\u5d0e\u3000"
    ],
    "wof:name":"Yamazaki",
    "wof:placetype":"locality"
},
  "geometry": {"coordinates":[130.77092999999999,33.70446],"type":"Point"}
}