{
  "type": "Feature",
  "properties": {
    "iso:country":"JP",
    "qs:name":"\u516b\u91cd\u702c\u753a",
    "qs:name_adm0":"\u65e5\u672c",
    "qs:name_adm1":"\u6c96\u7e04\u770c",
    "qs:photos":681,
    "qs:photos_1k":138,
    "qs:photos_9k":3,
    "qs:photos_9r":5,
    "qs:photos_all":681,
    "qs:photos_sr":8,
    "qs:placetype":"Town",
    "qs:pop_sr":"0",
    "wof:name":"\u516b\u91cd\u702c\u753a",
    "wof:placetype":"locality"
},
  "geometry": {"coordinates":[127.712266,26.151961],"type":"Point"}
}