{
  "type": "Feature",
  "properties": {
    "gn:admin1_code":"46",
    "gn:admin2_code":"1849406.0",
    "gn:asciiname":"Terashito",
    "gn:country_code":"JP",
    "gn:dem":574,
    "gn:feature_class":"P",
    "gn:feature_code":"PPL",
    "gn:name":"Terashito",
    "gn:population":0,
    "gn:timezone":"Asia/Tokyo",
    "iso:country":"JP",
    "wof:name":"Terashito",
    "wof:placetype":"locality"
},
  "geometry": {"coordinates":[139.05944,35.56778],"type":"Point"}
}