{
  "type": "Feature",
  "properties": {
    "gn:admin1_code":"23",
    "gn:admin2_code":"1857496.0",
    "gn:asciiname":"Iitakacho-miyamae",
    "gn:country_code":"JP",
    "gn:dem":162,
    "gn:feature_class":"P",
    "gn:feature_code":"PPL",
    "gn:name":"Iitakach\u014d-miyamae",
    "gn:population":0,
    "gn:timezone":"Asia/Tokyo",
    "iso:country":"JP",
    "name:jpn_x_preferred":[
        "\u98ef\u9ad8\u753a\u5bae\u524d"
    ],
    "name:und_x_variant":[
        "Miyanomae",
        "Miyamae",
        "Iitakach\u014d-miyamae"
    ],
    "wof:name":"Iitakacho-miyamae",
    "wof:placetype":"locality"
},
  "geometry": {"coordinates":[136.33333000000002,34.43333],"type":"Point"}
}