{
  "type": "Feature",
  "properties": {
    "gn:admin1_code":"12.0",
    "gn:admin2_code":"7429514.0",
    "gn:asciiname":"Barato",
    "gn:country_code":"JP",
    "gn:dem":-1,
    "gn:feature_class":"P",
    "gn:feature_code":"PPL",
    "gn:name":"Barato",
    "gn:population":0,
    "gn:timezone":"Asia/Tokyo",
    "iso:country":"JP",
    "wof:name":"Barato",
    "wof:placetype":"locality"
},
  "geometry": {"coordinates":[141.34999999999999,43.16667],"type":"Point"}
}