{
  "type": "Feature",
  "properties": {
    "gn:admin1_code":"27.0",
    "gn:admin2_code":"7418805.0",
    "gn:asciiname":"Kasugacho",
    "gn:country_code":"JP",
    "gn:dem":41,
    "gn:feature_class":"P",
    "gn:feature_code":"PPL",
    "gn:name":"Kasugach\u014d",
    "gn:population":0,
    "gn:timezone":"Asia/Tokyo",
    "iso:country":"JP",
    "name:jpn_x_preferred":[
        "\u6625\u65e5\u753a"
    ],
    "name:und_x_variant":[
        "Kasugach\u014d"
    ],
    "wof:name":"Kasugacho",
    "wof:placetype":"locality"
},
  "geometry": {"coordinates":[129.44499999999999,33.34359],"type":"Point"}
}