{
  "type": "Feature",
  "properties": {
    "gn:admin1_code":"4.0",
    "gn:admin2_code":"7465521.0",
    "gn:asciiname":"Iriuda",
    "gn:country_code":"JP",
    "gn:dem":182,
    "gn:feature_class":"P",
    "gn:feature_code":"PPLL",
    "gn:name":"Iriuda",
    "gn:population":0,
    "gn:timezone":"Asia/Tokyo",
    "iso:country":"JP",
    "name:jpn_x_preferred":[
        "\u5165\u5b87\u7530"
    ],
    "name:jpn_x_variant":[
        "\u3044\u308a\u3046\u3060",
        "\u30a4\u30ea\u30a6\u30c0"
    ],
    "wof:name":"Iriuda",
    "wof:placetype":"locality"
},
  "geometry": {"coordinates":[139.99182999999999,35.09946],"type":"Point"}
}