{
  "type": "Feature",
  "properties": {
    "gn:admin1_code":"8.0",
    "gn:admin2_code":"7451504.0",
    "gn:admin3_code":"7444.0",
    "gn:asciiname":"Idaira",
    "gn:country_code":"JP",
    "gn:dem":368,
    "gn:feature_class":"P",
    "gn:feature_code":"PPLL",
    "gn:name":"Idaira",
    "gn:population":0,
    "gn:timezone":"Asia/Tokyo",
    "iso:country":"JP",
    "name:jpn_x_preferred":[
        "\u5c45\u5e73"
    ],
    "wof:name":"Idaira",
    "wof:placetype":"locality"
},
  "geometry": {"coordinates":[139.59701000000001,37.46563],"type":"Point"}
}