{
  "type": "Feature",
  "properties": {
    "gn:admin1_code":"19.0",
    "gn:admin2_code":"1860670.0",
    "gn:asciiname":"Momijigayatsu",
    "gn:country_code":"JP",
    "gn:dem":35,
    "gn:feature_class":"P",
    "gn:feature_code":"PPLL",
    "gn:name":"Momijigayatsu",
    "gn:population":0,
    "gn:timezone":"Asia/Tokyo",
    "iso:country":"JP",
    "name:jpn_x_preferred":[
        "\u7d05\u8449\u30f6\u8c37"
    ],
    "name:jpn_x_variant":[
        "\u3082\u307f\u3058\u304c\u3084\u3064",
        "\u30e2\u30df\u30b8\u30ac\u30e4\u30c4"
    ],
    "wof:name":"Momijigayatsu",
    "wof:placetype":"locality"
},
  "geometry": {"coordinates":[139.57173999999998,35.32791],"type":"Point"}
}