{
  "type": "Feature",
  "properties": {
    "gn:admin1_code":"16.0",
    "gn:admin2_code":"2128940.0",
    "gn:asciiname":"Teguramori",
    "gn:country_code":"JP",
    "gn:dem":334,
    "gn:feature_class":"P",
    "gn:feature_code":"PPL",
    "gn:name":"Teguramori",
    "gn:population":0,
    "gn:timezone":"Asia/Tokyo",
    "iso:country":"JP",
    "name:jpn_x_preferred":[
        "\u624b\u5009\u68ee"
    ],
    "name:jpn_x_variant":[
        "\u3066\u3050\u3089\u3082\u308a",
        "\u30c6\u30b0\u30e9\u30e2\u30ea"
    ],
    "wof:name":"Teguramori",
    "wof:placetype":"locality"
},
  "geometry": {"coordinates":[141.10686999999999,40.24425],"type":"Point"}
}