{
  "type": "Feature",
  "properties": {
    "gn:admin1_code":"2.0",
    "gn:admin2_code":"2128864.0",
    "gn:asciiname":"Kunimi",
    "gn:country_code":"JP",
    "gn:dem":29,
    "gn:feature_class":"P",
    "gn:feature_code":"PPLL",
    "gn:name":"Kunimi",
    "gn:population":0,
    "gn:timezone":"Asia/Tokyo",
    "iso:country":"JP",
    "name:deu_x_preferred":[
        "Kunimi"
    ],
    "name:jpn_x_preferred":[
        "\u56fd\u898b"
    ],
    "wof:name":"Kunimi",
    "wof:placetype":"locality"
},
  "geometry": {"coordinates":[140.11303000000001,40.24556],"type":"Point"}
}