{
  "type": "Feature",
  "properties": {
    "gn:admin1_code":"44.0",
    "gn:admin2_code":"2110496.0",
    "gn:asciiname":"Osawa",
    "gn:country_code":"JP",
    "gn:dem":448,
    "gn:feature_class":"P",
    "gn:feature_code":"PPLL",
    "gn:name":"\u014csawa",
    "gn:population":0,
    "gn:timezone":"Asia/Tokyo",
    "iso:country":"JP",
    "name:jpn_x_preferred":[
        "\u5927\u6ca2"
    ],
    "name:und_x_variant":[
        "\u014csawa"
    ],
    "wof:name":"Osawa",
    "wof:placetype":"locality"
},
  "geometry": {"coordinates":[140.20029,37.84022],"type":"Point"}
}