{
  "type": "Feature",
  "properties": {
    "iso:country":"JP",
    "name:eng_x_preferred":[
        "Asahicho 1 Chome"
    ],
    "name:eng_x_variant":[
        "Asahichou 1 Choume",
        "Asahicho 1 Chome"
    ],
    "name:jpn_x_preferred":[
        "\uff11\u4e01\u76ee"
    ],
    "name:jpn_x_variant":[
        "\u3042\u3055\u3072\u3061\u3087\u3046 \uff11\u3061\u3087\u3046\u3081",
        "\u65ed\u753a \uff11\u4e01\u76ee",
        "\uff11\u3061\u3087\u3046\u3081"
    ],
    "qs:gn_local":0,
    "qs:local_max":25,
    "qs:local_sum":25,
    "qs:localhoods":1,
    "qs:name":"\uff11\u4e01\u76ee",
    "qs:name_adm0":"\u65e5\u672c",
    "qs:name_adm1":"\u5bae\u57ce\u770c",
    "qs:name_en":"Asahicho 1 Chome",
    "qs:name_lau":"\u65ed\u753a",
    "qs:name_local":"\u767d\u77f3\u5e02",
    "qs:photo_max":25,
    "qs:photo_sum":25,
    "qs:placetype":"Suburb",
    "qs:quad_count":1,
    "qs:woe_adm0":23424856,
    "qs:woe_adm1":2345873,
    "qs:woe_adm2":0,
    "qs:woe_lau":28391788,
    "qs:woe_local":1118208,
    "qs:woe_ver":"7.10.0",
    "wof:lang":[
        "jpn"
    ],
    "wof:name":"\uff11\u4e01\u76ee",
    "wof:placetype":"neighbourhood"
},
  "geometry": {"coordinates":[140.63324,37.993999],"type":"Point"}
}