{
  "type": "Feature",
  "properties": {
    "gn:admin1_code":"7.0",
    "gn:admin2_code":"1859306.0",
    "gn:admin3_code":"40105.0",
    "gn:asciiname":"Takamine",
    "gn:country_code":"JP",
    "gn:dem":28,
    "gn:feature_class":"P",
    "gn:feature_code":"PPL",
    "gn:name":"Takamine",
    "gn:population":0,
    "gn:timezone":"Asia/Tokyo",
    "iso:country":"JP",
    "name:jpn_x_preferred":[
        "\u9ad8\u5cf0"
    ],
    "wof:name":"Takamine",
    "wof:placetype":"locality"
},
  "geometry": {"coordinates":[130.82345000000001,33.88714],"type":"Point"}
}