{
  "type": "Feature",
  "properties": {
    "gn:admin1_code":"21.0",
    "gn:admin2_code":"1864973.0",
    "gn:asciiname":"Ogomori",
    "gn:country_code":"JP",
    "gn:dem":525,
    "gn:feature_class":"P",
    "gn:feature_code":"PPLL",
    "gn:name":"Ogomori",
    "gn:population":0,
    "gn:timezone":"Asia/Tokyo",
    "iso:country":"JP",
    "name:jpn_x_preferred":[
        "\u5c3e\u7c60"
    ],
    "name:jpn_x_variant":[
        "\u304a\u3054\u3082\u308a",
        "\u30aa\u30b4\u30e2\u30ea"
    ],
    "wof:name":"Ogomori",
    "wof:placetype":"locality"
},
  "geometry": {"coordinates":[131.11809,32.98178],"type":"Point"}
}