{
  "type": "Feature",
  "properties": {
    "gn:admin1_code":"16.0",
    "gn:admin2_code":"2112822.0",
    "gn:asciiname":"Shimonakano",
    "gn:country_code":"JP",
    "gn:dem":117,
    "gn:feature_class":"P",
    "gn:feature_code":"PPL",
    "gn:name":"Shimonakano",
    "gn:population":0,
    "gn:timezone":"Asia/Tokyo",
    "iso:country":"JP",
    "name:jpn_x_preferred":[
        "\u4e0b\u4e2d\u91ce"
    ],
    "name:jpn_x_variant":[
        "\u3057\u3082\u306a\u304b\u306e",
        "\u30b7\u30e2\u30ca\u30ab\u30ce"
    ],
    "wof:name":"Shimonakano",
    "wof:placetype":"locality"
},
  "geometry": {"coordinates":[141.05028999999999,39.39003],"type":"Point"}
}