{
  "type": "Feature",
  "properties": {
    "gn:admin1_code":"32",
    "gn:admin2_code":"1853897.0",
    "gn:admin3_code":"27108.0",
    "gn:asciiname":"Sangen'ya-nishi",
    "gn:country_code":"JP",
    "gn:dem":4,
    "gn:feature_class":"P",
    "gn:feature_code":"PPL",
    "gn:name":"Sangen\u2019ya-nishi",
    "gn:population":0,
    "gn:timezone":"Asia/Tokyo",
    "iso:country":"JP",
    "name:jpn_x_preferred":[
        "\u4e09\u8ed2\u5bb6\u897f"
    ],
    "name:und_x_variant":[
        "Sangen\u2019ya-nishi",
        "Sangenyach\u014d"
    ],
    "wof:name":"Sangen'ya-nishi",
    "wof:placetype":"locality"
},
  "geometry": {"coordinates":[135.47498999999999,34.66445],"type":"Point"}
}