{
  "type": "Feature",
  "properties": {
    "gn:admin1_code":"12.0",
    "gn:admin2_code":"2127817.0",
    "gn:admin3_code":"1487.0",
    "gn:asciiname":"Rokushinai",
    "gn:country_code":"JP",
    "gn:dem":24,
    "gn:feature_class":"P",
    "gn:feature_code":"PPL",
    "gn:name":"Rokushinai",
    "gn:population":0,
    "gn:timezone":"Asia/Tokyo",
    "iso:country":"JP",
    "name:jpn_x_preferred":[
        "\u516d\u5fd7\u5185"
    ],
    "name:jpn_x_variant":[
        "\u308d\u304f\u3057\u306a\u3044",
        "\u30ed\u30af\u30b7\u30ca\u30a4"
    ],
    "wof:name":"Rokushinai",
    "wof:placetype":"locality"
},
  "geometry": {"coordinates":[141.80000000000001,44.88333],"type":"Point"}
}