{
  "type": "Feature",
  "properties": {
    "iso:country":"JP",
    "name:eng_x_preferred":[
        "Aoicho 4 Chome"
    ],
    "name:eng_x_variant":[
        "Aoichou 4 Choume",
        "Aoicho 4 Chome"
    ],
    "name:jpn_x_preferred":[
        "\uff14\u4e01\u76ee"
    ],
    "name:jpn_x_variant":[
        "\u3042\u304a\u3044\u3061\u3087\u3046 \uff14\u3061\u3087\u3046\u3081",
        "\u8475\u753a \uff14\u4e01\u76ee",
        "\uff14\u3061\u3087\u3046\u3081"
    ],
    "name:unk_x_variant":[
        "\uff14\u4e01\u76ee"
    ],
    "qs:gn_local":0,
    "qs:local_max":1269,
    "qs:local_sum":1313,
    "qs:localhoods":4,
    "qs:name":"\uff14\u4e01\u76ee",
    "qs:name_adm0":"\u65e5\u672c",
    "qs:name_adm1":"\u5927\u962a\u5e9c",
    "qs:name_en":"Aoicho 4 Chome",
    "qs:name_lau":"\u8475\u753a",
    "qs:name_local":"\u6cc9\u4f50\u91ce\u5e02",
    "qs:photo_max":2,
    "qs:photo_sum":7,
    "qs:placetype":"Suburb",
    "qs:quad_count":6,
    "qs:woe_adm0":23424856,
    "qs:woe_adm1":2345881,
    "qs:woe_adm2":0,
    "qs:woe_lau":28459338,
    "qs:woe_local":1117363,
    "qs:woe_ver":"7.10.0",
    "wof:lang":[
        "jpn"
    ],
    "wof:name":"\uff14\u4e01\u76ee",
    "wof:placetype":"neighbourhood"
},
  "geometry": {"coordinates":[135.319782,34.38975],"type":"Point"}
}