{
  "type": "Feature",
  "properties": {
    "gn:admin1_code":"13.0",
    "gn:admin2_code":"7370813.0",
    "gn:asciiname":"Kogaki",
    "gn:country_code":"JP",
    "gn:dem":217,
    "gn:feature_class":"P",
    "gn:feature_code":"PPL",
    "gn:name":"Kogaki",
    "gn:population":0,
    "gn:timezone":"Asia/Tokyo",
    "iso:country":"JP",
    "name:jpn_x_preferred":[
        "\u5c0f\u67ff"
    ],
    "wof:name":"Kogaki",
    "wof:placetype":"locality"
},
  "geometry": {"coordinates":[135.26228999999998,34.98884],"type":"Point"}
}