{
  "type": "Feature",
  "properties": {
    "gn:admin1_code":"3.0",
    "gn:admin2_code":"2130056.0",
    "gn:asciiname":"Toriage",
    "gn:country_code":"JP",
    "gn:dem":53,
    "gn:feature_class":"P",
    "gn:feature_code":"PPL",
    "gn:name":"Toriage",
    "gn:population":0,
    "gn:timezone":"Asia/Tokyo",
    "iso:country":"JP",
    "name:jpn_x_preferred":[
        "\u53d6\u4e0a"
    ],
    "name:jpn_x_variant":[
        "\u3068\u308a\u3042\u3052",
        "\u30c8\u30ea\u30a2\u30b2"
    ],
    "wof:name":"Toriage",
    "wof:placetype":"locality"
},
  "geometry": {"coordinates":[140.48582999999999,40.58684],"type":"Point"}
}