{
  "type": "Feature",
  "properties": {
    "gn:admin1_code":"8.0",
    "gn:admin2_code":"2110839.0",
    "gn:admin3_code":"7522.0",
    "gn:asciiname":"Ono-niimachi",
    "gn:country_code":"JP",
    "gn:dem":472,
    "gn:feature_class":"P",
    "gn:feature_code":"PPL",
    "gn:name":"Ono-niimachi",
    "gn:population":0,
    "gn:timezone":"Asia/Tokyo",
    "iso:country":"JP",
    "name:jpn_x_preferred":[
        "\u5c0f\u91ce\u65b0\u753a"
    ],
    "name:und_x_variant":[
        "Ononii",
        "\u014cnoshimachi",
        "Ono-niimachi"
    ],
    "wof:name":"Ono-niimachi",
    "wof:placetype":"locality"
},
  "geometry": {"coordinates":[140.6328,37.28749000000001],"type":"Point"}
}