{
  "type": "Feature",
  "properties": {
    "gn:admin1_code":"21.0",
    "gn:admin2_code":"1865358.0",
    "gn:asciiname":"Ushirogote",
    "gn:country_code":"JP",
    "gn:dem":63,
    "gn:feature_class":"P",
    "gn:feature_code":"PPLL",
    "gn:name":"Ushirogote",
    "gn:population":0,
    "gn:timezone":"Asia/Tokyo",
    "iso:country":"JP",
    "name:jpn_x_preferred":[
        "\u5f8c\u5c0f\u624b"
    ],
    "name:jpn_x_variant":[
        "\u3046\u3057\u308d\u3054\u3066",
        "\u30a6\u30b7\u30ed\u30b4\u30c6"
    ],
    "wof:name":"Ushirogote",
    "wof:placetype":"locality"
},
  "geometry": {"coordinates":[130.23813000000001,32.43871],"type":"Point"}
}