{
  "type": "Feature",
  "properties": {
    "gn:admin1_code":"19.0",
    "gn:admin2_code":"1865011.0",
    "gn:admin3_code":"14363.0",
    "gn:asciiname":"Otera",
    "gn:country_code":"JP",
    "gn:dem":317,
    "gn:feature_class":"P",
    "gn:feature_code":"PPLL",
    "gn:name":"\u014ctera",
    "gn:population":0,
    "gn:timezone":"Asia/Tokyo",
    "iso:country":"JP",
    "name:jpn_x_preferred":[
        "\u5927\u5bfa"
    ],
    "name:und_x_variant":[
        "\u014ctera"
    ],
    "wof:name":"Otera",
    "wof:placetype":"locality"
},
  "geometry": {"coordinates":[139.13534000000001,35.40255],"type":"Point"}
}