{
  "type": "Feature",
  "properties": {
    "gn:admin1_code":"21.0",
    "gn:admin2_code":"7413153.0",
    "gn:asciiname":"Shimomure",
    "gn:country_code":"JP",
    "gn:dem":85,
    "gn:feature_class":"P",
    "gn:feature_code":"PPLL",
    "gn:name":"Shimomure",
    "gn:population":0,
    "gn:timezone":"Asia/Tokyo",
    "iso:country":"JP",
    "name:jpn_x_preferred":[
        "\u4e0b\u7fa4"
    ],
    "name:jpn_x_variant":[
        "\u3057\u3082\u3080\u308c",
        "\u30b7\u30e2\u30e0\u30ec"
    ],
    "wof:name":"Shimomure",
    "wof:placetype":"locality"
},
  "geometry": {"coordinates":[130.76993999999999,32.88173],"type":"Point"}
}