{
  "type": "Feature",
  "properties": {
    "gn:admin1_code":"32",
    "gn:asciiname":"Tsukuda",
    "gn:country_code":"JP",
    "gn:dem":3,
    "gn:feature_class":"P",
    "gn:feature_code":"PPL",
    "gn:name":"Tsukuda",
    "gn:population":0,
    "gn:timezone":"Asia/Tokyo",
    "iso:country":"JP",
    "name:jpn_x_preferred":[
        "\u4f43"
    ],
    "name:kor_x_preferred":[
        "\uc4f0\ucfe0\ub2e4"
    ],
    "name:und_x_variant":[
        "Tsukudamachi",
        "Tsukudach\u014d"
    ],
    "wof:name":"Tsukuda",
    "wof:placetype":"locality"
},
  "geometry": {"coordinates":[135.44051999999999,34.7133],"type":"Point"}
}