{
  "type": "Feature",
  "properties": {
    "gn:admin1_code":"3.0",
    "gn:admin2_code":"2130056.0",
    "gn:asciiname":"Tateno",
    "gn:country_code":"JP",
    "gn:dem":75,
    "gn:feature_class":"P",
    "gn:feature_code":"PPL",
    "gn:name":"Tateno",
    "gn:population":0,
    "gn:timezone":"Asia/Tokyo",
    "iso:country":"JP",
    "name:jpn_x_preferred":[
        "\u9928\u91ce"
    ],
    "name:jpn_x_variant":[
        "\u305f\u3066\u306e",
        "\u30bf\u30c6\u30ce"
    ],
    "wof:name":"Tateno",
    "wof:placetype":"locality"
},
  "geometry": {"coordinates":[140.46253000000002,40.57559000000001],"type":"Point"}
}