{
  "type": "Feature",
  "properties": {
    "gn:admin1_code":"47",
    "gn:admin2_code":"1856030.0",
    "gn:asciiname":"Omine",
    "gn:country_code":"JP",
    "gn:dem":8,
    "gn:feature_class":"P",
    "gn:feature_code":"PPL",
    "gn:name":"\u014cmine",
    "gn:population":0,
    "gn:timezone":"Asia/Tokyo",
    "iso:country":"JP",
    "name:jpn_x_preferred":[
        "\u5927\u5dba"
    ],
    "name:und_x_variant":[
        "Ufunmi",
        "\u014cmine"
    ],
    "wof:name":"Omine",
    "wof:placetype":"locality"
},
  "geometry": {"coordinates":[127.64140999999999,26.19852],"type":"Point"}
}