{
  "type": "Feature",
  "properties": {
    "gn:admin1_code":"21.0",
    "gn:admin2_code":"7413150.0",
    "gn:asciiname":"Chuodori",
    "gn:country_code":"JP",
    "gn:dem":22,
    "gn:feature_class":"P",
    "gn:feature_code":"PPL",
    "gn:name":"Ch\u016b\u014dd\u014dri",
    "gn:population":0,
    "gn:timezone":"Asia/Tokyo",
    "iso:country":"JP",
    "name:jpn_x_preferred":[
        "\u4e2d\u592e\u901a"
    ],
    "name:jpn_x_variant":[
        "\u3061\u3085\u3046\u304a\u3046\u3069\u304a\u308a",
        "\u30c1\u30e5\u30a6\u30aa\u30a6\u30c9\u30aa\u30ea"
    ],
    "name:und_x_variant":[
        "Ch\u016b\u014dd\u014dri"
    ],
    "wof:name":"Chuodori",
    "wof:placetype":"locality"
},
  "geometry": {"coordinates":[130.68357,33.01509],"type":"Point"}
}