{
  "type": "Feature",
  "properties": {
    "gn:admin1_code":"46",
    "gn:admin2_code":"7415915.0",
    "gn:asciiname":"Nagasawa",
    "gn:country_code":"JP",
    "gn:dem":872,
    "gn:feature_class":"P",
    "gn:feature_code":"PPL",
    "gn:name":"Nagasawa",
    "gn:population":0,
    "gn:timezone":"Asia/Tokyo",
    "iso:country":"JP",
    "wof:name":"Nagasawa",
    "wof:placetype":"locality"
},
  "geometry": {"coordinates":[138.43333000000001,35.86667],"type":"Point"}
}