{
  "type": "Feature",
  "properties": {
    "gn:admin1_code":"37.0",
    "gn:admin2_code":"1864089.0",
    "gn:asciiname":"Jiyugaoka",
    "gn:country_code":"JP",
    "gn:dem":8,
    "gn:feature_class":"P",
    "gn:feature_code":"PPLL",
    "gn:name":"Jiy\u016bgaoka",
    "gn:population":0,
    "gn:timezone":"Asia/Tokyo",
    "iso:country":"JP",
    "name:jpn_x_preferred":[
        "\u81ea\u7531\u30f6\u4e18"
    ],
    "name:und_x_variant":[
        "Jiy\u016bgaoka"
    ],
    "wof:name":"Jiyugaoka",
    "wof:placetype":"locality"
},
  "geometry": {"coordinates":[138.65233999999998,35.12698],"type":"Point"}
}