{
  "type": "Feature",
  "properties": {
    "gn:admin1_code":"3.0",
    "gn:admin2_code":"2129393.0",
    "gn:asciiname":"Kamitogawa",
    "gn:country_code":"JP",
    "gn:dem":50,
    "gn:feature_class":"P",
    "gn:feature_code":"PPL",
    "gn:name":"Kamitogawa",
    "gn:population":0,
    "gn:timezone":"Asia/Tokyo",
    "iso:country":"JP",
    "name:jpn_x_preferred":[
        "\u4e0a\u5341\u5ddd"
    ],
    "name:jpn_x_variant":[
        "\u304b\u307f\u3068\u304c\u308f",
        "\u30ab\u30df\u30c8\u30ac\u30ef"
    ],
    "wof:name":"Kamitogawa",
    "wof:placetype":"locality"
},
  "geometry": {"coordinates":[140.62379999999999,40.66315],"type":"Point"}
}