{
  "type": "Feature",
  "properties": {
    "gn:admin1_code":"19.0",
    "gn:admin2_code":"1865011.0",
    "gn:admin3_code":"14361.0",
    "gn:asciiname":"Goshonomiya",
    "gn:country_code":"JP",
    "gn:dem":40,
    "gn:feature_class":"P",
    "gn:feature_code":"PPLL",
    "gn:name":"Goshonomiya",
    "gn:population":0,
    "gn:timezone":"Asia/Tokyo",
    "iso:country":"JP",
    "name:jpn_x_preferred":[
        "\u4e94\u6240\u30ce\u5bae"
    ],
    "wof:name":"Goshonomiya",
    "wof:placetype":"locality"
},
  "geometry": {"coordinates":[139.22154,35.32185],"type":"Point"}
}