{
  "type": "Feature",
  "properties": {
    "gn:admin1_code":"32",
    "gn:admin2_code":"1853167.0",
    "gn:admin3_code":"27143.0",
    "gn:asciiname":"Kitanoda",
    "gn:country_code":"JP",
    "gn:dem":56,
    "gn:feature_class":"P",
    "gn:feature_code":"PPL",
    "gn:name":"Kitanoda",
    "gn:population":0,
    "gn:timezone":"Asia/Tokyo",
    "iso:country":"JP",
    "name:jpn_x_preferred":[
        "\u5317\u91ce\u7530"
    ],
    "name:und_x_variant":[
        "Kita-noda"
    ],
    "wof:name":"Kitanoda",
    "wof:placetype":"locality"
},
  "geometry": {"coordinates":[135.54775000000001,34.52863],"type":"Point"}
}