{
  "type": "Feature",
  "properties": {
    "gn:admin1_code":"25.0",
    "gn:admin2_code":"1864313.0",
    "gn:asciiname":"Shitanda",
    "gn:country_code":"JP",
    "gn:dem":249,
    "gn:feature_class":"P",
    "gn:feature_code":"PPLL",
    "gn:name":"Shitanda",
    "gn:population":0,
    "gn:timezone":"Asia/Tokyo",
    "iso:country":"JP",
    "name:jpn_x_preferred":[
        "\u56db\u53cd\u7530"
    ],
    "name:jpn_x_variant":[
        "\u3057\u305f\u3093\u3060",
        "\u30b7\u30bf\u30f3\u30c0"
    ],
    "wof:name":"Shitanda",
    "wof:placetype":"locality"
},
  "geometry": {"coordinates":[130.77455,32.06594],"type":"Point"}
}