{
  "type": "Feature",
  "properties": {
    "gn:country":"JP",
    "gn:fcode":"ADM3",
    "gn:pop":0,
    "iso:country":"JP",
    "name:jpn_x_preferred":[
        "\u65b0\u5730\u753a"
    ],
    "name:jpn_x_variant":[
        "\u3057\u3093\u3061\u307e\u3061"
    ],
    "name:unk_x_variant":[
        "Shinchi Machi"
    ],
    "qs:name":"Shinchi-machi",
    "qs:photos_9r":0,
    "qs:photos_sr":0,
    "qs:pop_sr":"0",
    "wof:name":"Shinchi-machi",
    "wof:placetype":"localadmin",
    "wof:population":0
},
  "geometry": {"coordinates":[140.90042,37.86697],"type":"Point"}
}