{
  "type": "Feature",
  "properties": {
    "iso:country":"JP",
    "name:eng_x_preferred":[
        "Aza Inuiyama"
    ],
    "name:jpn_x_preferred":[
        "\u5b57\u4e7e\u5c71"
    ],
    "qs:name":"\u5b57\u4e7e\u5c71",
    "qs:name_adm0":"\u65e5\u672c",
    "qs:name_adm1":"\u5fb3\u5cf6\u770c",
    "qs:photos":26,
    "qs:photos_1k":5,
    "qs:photos_9k":1,
    "qs:photos_9r":2,
    "qs:photos_all":26,
    "qs:photos_sr":2,
    "qs:placetype":"Suburb",
    "qs:pop_sr":"0",
    "wof:name":"Aza Inuiyama",
    "wof:placetype":"neighbourhood"
},
  "geometry": {"coordinates":[134.30401599999999,34.107725],"type":"Point"}
}