{
  "type": "Feature",
  "properties": {
    "gn:country":"JP",
    "gn:fcode":"ADM3",
    "gn:population":0,
    "iso:country":"JP",
    "name:eng_x_preferred":[
        "Ochi"
    ],
    "name:eng_x_variant":[
        "Ochi-ch\u014d"
    ],
    "name:jpn_x_preferred":[
        "\u8d8a\u77e5\u753a"
    ],
    "name:jpn_x_variant":[
        "\u304a\u3061\u3061\u3087\u3046"
    ],
    "qs:name":"Ochi-ch\u014d",
    "qs:photos_9r":0,
    "qs:photos_sr":0,
    "qs:pop_sr":"0",
    "wof:name":"Ochi",
    "wof:placetype":"localadmin",
    "wof:population":0
},
  "geometry": {"coordinates":[133.22188,33.54307],"type":"Point"}
}