{
  "type": "Feature",
  "properties": {
    "gn:admin1_code":"12.0",
    "gn:admin2_code":"7428079.0",
    "gn:admin3_code":"1648.0",
    "gn:asciiname":"Nakatomamu",
    "gn:country_code":"JP",
    "gn:dem":262,
    "gn:feature_class":"P",
    "gn:feature_code":"PPL",
    "gn:name":"Nakatomamu",
    "gn:population":0,
    "gn:timezone":"Asia/Tokyo",
    "iso:country":"JP",
    "name:jpn_x_preferred":[
        "\u4e2d\u6597\u6e80"
    ],
    "name:jpn_x_variant":[
        "\u306a\u304b\u3068\u307e\u3080",
        "\u30ca\u30ab\u30c8\u30de\u30e0"
    ],
    "name:und_x_variant":[
        "Naka-toman",
        "Naka-tomamu",
        "Nakatomamu"
    ],
    "wof:name":"Nakatomamu",
    "wof:placetype":"locality"
},
  "geometry": {"coordinates":[143.66976,43.47189],"type":"Point"}
}