{
  "type": "Feature",
  "properties": {
    "iso:country":"JP",
    "name:eng_x_preferred":[
        "Misugidai 1 Chome"
    ],
    "name:eng_x_variant":[
        "Misugidai 1 Choume",
        "Misugidai 1 Chome"
    ],
    "name:jpn_x_preferred":[
        "\uff11\u4e01\u76ee"
    ],
    "name:jpn_x_variant":[
        "\u307f\u3059\u304e\u3060\u3044 \uff11\u3061\u3087\u3046\u3081",
        "\u7f8e\u6749\u53f0 \uff11\u4e01\u76ee",
        "\uff11\u3061\u3087\u3046\u3081"
    ],
    "name:unk_x_variant":[
        "\uff11\u4e01\u76ee"
    ],
    "qs:gn_local":0,
    "qs:local_max":177,
    "qs:local_sum":210,
    "qs:localhoods":2,
    "qs:name":"\uff11\u4e01\u76ee",
    "qs:name_adm0":"\u65e5\u672c",
    "qs:name_adm1":"\u57fc\u7389\u770c",
    "qs:name_en":"Misugidai 1 Chome",
    "qs:name_lau":"\u7f8e\u6749\u53f0",
    "qs:name_local":"\u98ef\u80fd\u5e02",
    "qs:photo_max":26,
    "qs:photo_sum":177,
    "qs:placetype":"Suburb",
    "qs:quad_count":19,
    "qs:woe_adm0":23424856,
    "qs:woe_adm1":2345883,
    "qs:woe_adm2":0,
    "qs:woe_lau":28408564,
    "qs:woe_local":1108608,
    "qs:woe_ver":"7.10.0",
    "wof:lang":[
        "jpn"
    ],
    "wof:name":"\uff11\u4e01\u76ee",
    "wof:placetype":"neighbourhood"
},
  "geometry": {"coordinates":[139.31282300000001,35.849399],"type":"Point"}
}