{
  "type": "Feature",
  "properties": {
    "gn:admin1_code":"32.0",
    "gn:admin2_code":"1850907.0",
    "gn:asciiname":"Izuriha",
    "gn:country_code":"JP",
    "gn:dem":363,
    "gn:feature_class":"P",
    "gn:feature_code":"PPL",
    "gn:name":"Izuriha",
    "gn:population":0,
    "gn:timezone":"Asia/Tokyo",
    "iso:country":"JP",
    "name:jpn_x_preferred":[
        "\u51fa\u7070"
    ],
    "wof:name":"Izuriha",
    "wof:placetype":"locality"
},
  "geometry": {"coordinates":[135.60554999999999,34.93869],"type":"Point"}
}