{
  "type": "Feature",
  "properties": {
    "gn:admin1_code":"45",
    "gn:admin2_code":"1848548.0",
    "gn:asciiname":"Obatake",
    "gn:country_code":"JP",
    "gn:dem":103,
    "gn:feature_class":"P",
    "gn:feature_code":"PPL",
    "gn:name":"\u014cbatake",
    "gn:population":0,
    "gn:timezone":"Asia/Tokyo",
    "iso:country":"JP",
    "name:und_x_variant":[
        "\u014cbatake"
    ],
    "wof:name":"Obatake",
    "wof:placetype":"locality"
},
  "geometry": {"coordinates":[132.17167000000001,33.96667],"type":"Point"}
}