{
  "type": "Feature",
  "properties": {
    "gn:admin1_code":"4.0",
    "gn:admin2_code":"1855071.0",
    "gn:asciiname":"Kamihanawa",
    "gn:country_code":"JP",
    "gn:dem":16,
    "gn:feature_class":"P",
    "gn:feature_code":"PPL",
    "gn:name":"Kamihanawa",
    "gn:population":0,
    "gn:timezone":"Asia/Tokyo",
    "iso:country":"JP",
    "name:jpn_x_preferred":[
        "\u4e0a\u82b1\u8f2a"
    ],
    "wof:name":"Kamihanawa",
    "wof:placetype":"locality"
},
  "geometry": {"coordinates":[139.85952,35.93835],"type":"Point"}
}