{
  "type": "Feature",
  "properties": {
    "gn:admin1_code":"34.0",
    "gn:admin2_code":"8304213.0",
    "gn:asciiname":"Tsukauchi",
    "gn:country_code":"JP",
    "gn:dem":2,
    "gn:feature_class":"P",
    "gn:feature_code":"PPLL",
    "gn:name":"Tsukauchi",
    "gn:population":0,
    "gn:timezone":"Asia/Tokyo",
    "iso:country":"JP",
    "name:jpn_x_preferred":[
        "\u585a\u5185"
    ],
    "name:jpn_x_variant":[
        "\u3064\u304b\u3046\u3061",
        "\u30c4\u30ab\u30a6\u30c1"
    ],
    "wof:name":"Tsukauchi",
    "wof:placetype":"locality"
},
  "geometry": {"coordinates":[139.72725,35.98516],"type":"Point"}
}