{
  "type": "Feature",
  "properties": {
    "iso:country":"JP",
    "qs:name":"\u592a\u7530\u5e02",
    "qs:name_adm0":"\u65e5\u672c",
    "qs:name_adm1":"\u7fa4\u99ac\u770c",
    "qs:photos":1108,
    "qs:photos_1k":225,
    "qs:photos_9k":5,
    "qs:photos_9r":7,
    "qs:photos_all":1108,
    "qs:photos_sr":11,
    "qs:placetype":"Town",
    "qs:pop_sr":"0",
    "wof:name":"\u592a\u7530\u5e02",
    "wof:placetype":"locality"
},
  "geometry": {"coordinates":[139.361164,36.306272],"type":"Point"}
}