{
  "type": "Feature",
  "properties": {
    "gn:admin1_code":"21.0",
    "gn:admin2_code":"7413152.0",
    "gn:asciiname":"Ishiuchi",
    "gn:country_code":"JP",
    "gn:dem":76,
    "gn:feature_class":"P",
    "gn:feature_code":"PPLL",
    "gn:name":"Ishiuchi",
    "gn:population":0,
    "gn:timezone":"Asia/Tokyo",
    "iso:country":"JP",
    "name:jpn_x_preferred":[
        "\u77f3\u6253"
    ],
    "name:jpn_x_variant":[
        "\u3044\u3057\u3046\u3061",
        "\u30a4\u30b7\u30a6\u30c1"
    ],
    "wof:name":"Ishiuchi",
    "wof:placetype":"locality"
},
  "geometry": {"coordinates":[130.50718999999998,32.64406],"type":"Point"}
}