{
  "type": "Feature",
  "properties": {
    "gn:admin1_code":"2.0",
    "gn:admin2_code":"2113122.0",
    "gn:asciiname":"Kamishinjonaka",
    "gn:country_code":"JP",
    "gn:dem":39,
    "gn:feature_class":"P",
    "gn:feature_code":"PPL",
    "gn:name":"Kamishinj\u014dnaka",
    "gn:population":0,
    "gn:timezone":"Asia/Tokyo",
    "iso:country":"JP",
    "name:jpn_x_preferred":[
        "\u4e0a\u65b0\u57ce\u4e2d"
    ],
    "name:jpn_x_variant":[
        "\u304b\u307f\u3057\u3093\u3058\u3087\u3046\u306a\u304b",
        "\u30ab\u30df\u30b7\u30f3\u30b8\u30e7\u30a6\u30ca\u30ab",
        "\u4e2d"
    ],
    "name:und_x_variant":[
        "Kamishinj\u014dnaka",
        "Naka"
    ],
    "wof:name":"Kamishinjonaka",
    "wof:placetype":"locality"
},
  "geometry": {"coordinates":[140.10891999999998,39.78774],"type":"Point"}
}