{
  "type": "Feature",
  "properties": {
    "gn:admin1_code":"22.0",
    "gn:admin2_code":"1857906.0",
    "gn:admin3_code":"26109.0",
    "gn:asciiname":"Takeda",
    "gn:country_code":"JP",
    "gn:dem":18,
    "gn:feature_class":"P",
    "gn:feature_code":"PPL",
    "gn:name":"Takeda",
    "gn:population":0,
    "gn:timezone":"Asia/Tokyo",
    "iso:country":"JP",
    "name:jpn_x_preferred":[
        "\u7af9\u7530"
    ],
    "name:kor_x_preferred":[
        "\ub2e4\ucf00\ub2e4"
    ],
    "name:nld_x_preferred":[
        "Takeda"
    ],
    "name:rus_x_preferred":[
        "\u0422\u0430\u043a\u044d\u0434\u0430"
    ],
    "wof:name":"Takeda",
    "wof:placetype":"locality"
},
  "geometry": {"coordinates":[135.75387000000001,34.95338],"type":"Point"}
}