{
  "type": "Feature",
  "properties": {
    "gn:admin1_code":"2.0",
    "gn:admin2_code":"2129593.0",
    "gn:asciiname":"Togura",
    "gn:country_code":"JP",
    "gn:dem":456,
    "gn:feature_class":"P",
    "gn:feature_code":"PPLL",
    "gn:name":"Togura",
    "gn:population":0,
    "gn:timezone":"Asia/Tokyo",
    "iso:country":"JP",
    "name:jpn_x_preferred":[
        "\u6238\u5009"
    ],
    "wof:name":"Togura",
    "wof:placetype":"locality"
},
  "geometry": {"coordinates":[140.93063000000001,40.33516],"type":"Point"}
}