{
  "type": "Feature",
  "properties": {
    "gn:admin1_code":"34.0",
    "gn:admin2_code":"1855405.0",
    "gn:asciiname":"Atago",
    "gn:country_code":"JP",
    "gn:dem":42,
    "gn:feature_class":"P",
    "gn:feature_code":"PPL",
    "gn:name":"Atago",
    "gn:population":0,
    "gn:timezone":"Asia/Tokyo",
    "iso:country":"JP",
    "name:ita_x_preferred":[
        "Atago"
    ],
    "name:jpn_x_preferred":[
        "\u3042\u305f\u3054"
    ],
    "name:kor_x_preferred":[
        "\uc544\ud0c0\uace0"
    ],
    "name:pol_x_preferred":[
        "Atago"
    ],
    "name:spa_x_preferred":[
        "Atago"
    ],
    "wof:name":"Atago",
    "wof:placetype":"locality"
},
  "geometry": {"coordinates":[139.54426000000001,35.78981],"type":"Point"}
}