{
  "type": "Feature",
  "properties": {
    "gn:admin1_code":"7.0",
    "gn:admin2_code":"1860814.0",
    "gn:admin3_code":"40421.0",
    "gn:asciiname":"Kuromaru",
    "gn:country_code":"JP",
    "gn:dem":41,
    "gn:feature_class":"P",
    "gn:feature_code":"PPL",
    "gn:name":"Kur\u014dmaru",
    "gn:population":0,
    "gn:timezone":"Asia/Tokyo",
    "iso:country":"JP",
    "name:jpn_x_preferred":[
        "\u4e5d\u90ce\u4e38"
    ],
    "name:und_x_variant":[
        "Kur\u014dmaru"
    ],
    "wof:name":"Kuromaru",
    "wof:placetype":"locality"
},
  "geometry": {"coordinates":[130.66896,33.57508],"type":"Point"}
}