{
  "type": "Feature",
  "properties": {
    "iso:country":"JP",
    "name:eng_x_preferred":[
        "Kameido 6 Chome"
    ],
    "name:eng_x_variant":[
        "Kameido 6 Choume",
        "Kameido 6 Chome"
    ],
    "name:jpn_x_preferred":[
        "\uff16\u4e01\u76ee"
    ],
    "name:jpn_x_variant":[
        "\u304b\u3081\u3044\u3069 \uff16\u3061\u3087\u3046\u3081",
        "\u4e80\u6238 \uff16\u4e01\u76ee",
        "\uff16\u3061\u3087\u3046\u3081"
    ],
    "qs:gn_adm0_cc":"JP",
    "qs:gn_local":1850147,
    "qs:local_max":18112,
    "qs:local_sum":895907,
    "qs:localhoods":857,
    "qs:name":"\uff16\u4e01\u76ee",
    "qs:name_adm0":"\u65e5\u672c",
    "qs:name_adm1":"\u6771\u4eac\u90fd",
    "qs:name_adm2":"\u6c5f\u6771\u533a",
    "qs:name_en":"Kameido 6 Chome",
    "qs:name_lau":"\u4e80\u6238",
    "qs:name_local":"\u6771\u4eac",
    "qs:photo_max":46,
    "qs:photo_sum":126,
    "qs:placetype":"Suburb",
    "qs:quad_count":7,
    "qs:woe_adm0":23424856,
    "qs:woe_adm1":2345889,
    "qs:woe_adm2":15015377,
    "qs:woe_lau":28414187,
    "qs:woe_local":1118370,
    "qs:woe_ver":"7.10.0",
    "qs_pg:name":"\uff16\u4e01\u76ee",
    "qs_pg:name_adm0":"\u65e5\u672c",
    "qs_pg:name_adm1":"\u6771\u4eac\u90fd",
    "qs_pg:photos":91,
    "qs_pg:photos_1k":18,
    "qs_pg:photos_9k":1,
    "qs_pg:photos_9r":3,
    "qs_pg:photos_all":91,
    "qs_pg:photos_sr":3,
    "qs_pg:pop_sr":0,
    "qs_pg:qs_pg_placetype":"neighbourhood",
    "qs_pg:qs_pg_placetype_gp":"Suburb",
    "qs_pg:woe_adm0":23424856,
    "woe:adm0_id":23424856,
    "woe:name_adm0":"\u65e5\u672c",
    "woe:name_adm1":"\u6771\u4eac\u90fd",
    "woe:placetype":"Suburb",
    "wof:lang":[
        "jpn"
    ],
    "wof:name":"\uff16\u4e01\u76ee",
    "wof:placetype":"neighbourhood"
},
  "geometry": {"coordinates":[139.82923700000001,35.695065],"type":"Point"}
}