{
  "type": "Feature",
  "properties": {
    "gn:admin1_code":"37.0",
    "gn:admin2_code":"1854900.0",
    "gn:asciiname":"Takashima-honcho",
    "gn:country_code":"JP",
    "gn:dem":14,
    "gn:feature_class":"P",
    "gn:feature_code":"PPL",
    "gn:name":"Takashima-honch\u014d",
    "gn:population":0,
    "gn:timezone":"Asia/Tokyo",
    "iso:country":"JP",
    "name:jpn_x_preferred":[
        "\u9ad8\u5cf6\u672c\u753a"
    ],
    "name:und_x_variant":[
        "Takashima-honch\u014d"
    ],
    "wof:name":"Takashima-honcho",
    "wof:placetype":"locality"
},
  "geometry": {"coordinates":[138.85764,35.1094],"type":"Point"}
}