{
  "type": "Feature",
  "properties": {
    "iso:country":"JP",
    "name:eng_x_preferred":[
        "Sekinocho 2 Chome"
    ],
    "name:eng_x_variant":[
        "Sekinochou 2 Choume",
        "Sekinocho 2 Chome"
    ],
    "name:jpn_x_preferred":[
        "\uff12\u4e01\u76ee"
    ],
    "name:jpn_x_variant":[
        "\u305b\u304d\u306e\u3061\u3087\u3046 \uff12\u3061\u3087\u3046\u3081",
        "\u95a2\u91ce\u753a \uff12\u4e01\u76ee",
        "\uff12\u3061\u3087\u3046\u3081"
    ],
    "qs:gn_adm0_cc":"JP",
    "qs:gn_local":1859088,
    "qs:gn_nam_loc":"\u5c0f\u91d1\u4e95\u5e02, \u6771\u4eac\u90fd, JP",
    "qs:gn_namadm1":"40",
    "qs:local_max":1225,
    "qs:local_sum":2455,
    "qs:localhoods":9,
    "qs:name":"\uff12\u4e01\u76ee",
    "qs:name_adm0":"\u65e5\u672c",
    "qs:name_adm1":"\u6771\u4eac\u90fd",
    "qs:name_en":"Sekinocho 2 Chome",
    "qs:name_lau":"\u95a2\u91ce\u753a",
    "qs:name_local":"\u5c0f\u91d1\u4e95\u5e02",
    "qs:photo_max":423,
    "qs:photo_sum":1225,
    "qs:placetype":"Suburb",
    "qs:quad_count":20,
    "qs:woe_adm0":23424856,
    "qs:woe_adm1":2345889,
    "qs:woe_adm2":0,
    "qs:woe_lau":28415123,
    "qs:woe_local":1110933,
    "qs:woe_ver":"7.10.0",
    "wof:lang":[
        "jpn"
    ],
    "wof:name":"\uff12\u4e01\u76ee",
    "wof:placetype":"neighbourhood"
},
  "geometry": {"coordinates":[139.513034,35.716405],"type":"Point"}
}