{
  "type": "Feature",
  "properties": {
    "gn:admin1_code":"3.0",
    "gn:admin2_code":"2128302.0",
    "gn:admin3_code":"2443.0",
    "gn:asciiname":"Nokurozawa",
    "gn:country_code":"JP",
    "gn:dem":186,
    "gn:feature_class":"P",
    "gn:feature_code":"PPL",
    "gn:name":"Nokurozawa",
    "gn:population":0,
    "gn:timezone":"Asia/Tokyo",
    "iso:country":"JP",
    "name:jpn_x_preferred":[
        "\u91ce\u7566\u6ca2"
    ],
    "name:jpn_x_variant":[
        "\u306e\u304f\u308d\u3056\u308f",
        "\u30ce\u30af\u30ed\u30b6\u30ef"
    ],
    "wof:name":"Nokurozawa",
    "wof:placetype":"locality"
},
  "geometry": {"coordinates":[141.1198,40.34823],"type":"Point"}
}