{
  "type": "Feature",
  "properties": {
    "gn:admin1_code":"12.0",
    "gn:admin2_code":"7428116.0",
    "gn:admin3_code":"1607.0",
    "gn:asciiname":"Tomisato",
    "gn:country_code":"JP",
    "gn:dem":10,
    "gn:feature_class":"P",
    "gn:feature_code":"PPL",
    "gn:name":"Tomisato",
    "gn:population":0,
    "gn:timezone":"Asia/Tokyo",
    "iso:country":"JP",
    "name:ara_x_preferred":[
        "\u062a\u0648\u0645\u064a\u0633\u0627\u062a\u0648"
    ],
    "name:azb_x_preferred":[
        "\u062a\u0648\u0645\u06cc\u0633\u0627\u062a\u0648"
    ],
    "name:ceb_x_preferred":[
        "Tomisato-shi"
    ],
    "name:ces_x_preferred":[
        "Tomisato"
    ],
    "name:deu_x_preferred":[
        "Tomisato"
    ],
    "name:fas_x_preferred":[
        "\u062a\u0648\u0645\u06cc\u0633\u0627\u062a\u0648"
    ],
    "name:fra_x_preferred":[
        "Tomisato"
    ],
    "name:glg_x_preferred":[
        "Tomisato"
    ],
    "name:ita_x_preferred":[
        "Tomisato"
    ],
    "name:jpn_x_preferred":[
        "\u5bcc\u91cc"
    ],
    "name:jpn_x_variant":[
        "\u3068\u307f\u3055\u3068",
        "\u30c8\u30df\u30b5\u30c8",
        "\u5bcc\u91cc\u5e02"
    ],
    "name:kor_x_preferred":[
        "\ub3c4\ubbf8\uc0ac\ud1a0\uc2dc"
    ],
    "name:mzn_x_preferred":[
        "\u062a\u0648\u0645\u06cc\u0633\u0627\u062a\u0648"
    ],
    "name:nld_x_preferred":[
        "Tomisato"
    ],
    "name:pol_x_preferred":[
        "Tomisato"
    ],
    "name:por_x_preferred":[
        "Tomisato"
    ],
    "name:ron_x_preferred":[
        "Tomisato"
    ],
    "name:rus_x_preferred":[
        "\u0422\u043e\u043c\u0438\u0441\u0430\u0442\u043e"
    ],
    "name:spa_x_preferred":[
        "Tomisato"
    ],
    "name:swa_x_preferred":[
        "Tomisato"
    ],
    "name:swe_x_preferred":[
        "Tomisato"
    ],
    "name:tgk_x_preferred":[
        "\u0422\u043e\u043c\u0438\u0441\u0430\u0442\u043e"
    ],
    "name:tgl_x_preferred":[
        "Tomisato"
    ],
    "name:tha_x_preferred":[
        "\u0e42\u0e17\u0e21\u0e34\u0e0b\u0e32\u0e42\u0e15\u0e30"
    ],
    "name:tum_x_preferred":[
        "Tomisato"
    ],
    "name:tur_x_preferred":[
        "Tomisato"
    ],
    "name:ukr_x_preferred":[
        "\u0422\u043e\u043c\u0456\u0441\u0430\u0442\u043e"
    ],
    "name:urd_x_preferred":[
        "\u062a\u0648\u0645\u06cc\u0633\u0627\u062a\u0648"
    ],
    "name:vie_x_preferred":[
        "Tomisato"
    ],
    "name:war_x_preferred":[
        "Tomisato"
    ],
    "name:zho_x_preferred":[
        "\u5bcc\u91cc\u5e02"
    ],
    "wof:name":"Tomisato",
    "wof:placetype":"locality"
},
  "geometry": {"coordinates":[142.70858999999999,42.21736],"type":"Point"}
}