{
  "type": "Feature",
  "properties": {
    "gn:admin1_code":"12.0",
    "gn:admin2_code":"7428116.0",
    "gn:admin3_code":"1607.0",
    "gn:asciiname":"Tomisato",
    "gn:country_code":"JP",
    "gn:dem":10,
    "gn:feature_class":"P",
    "gn:feature_code":"PPL",
    "gn:name":"Tomisato",
    "gn:population":0,
    "gn:timezone":"Asia/Tokyo",
    "iso:country":"JP",
    "name:jpn_x_preferred":[
        "\u5bcc\u91cc"
    ],
    "name:jpn_x_variant":[
        "\u3068\u307f\u3055\u3068",
        "\u30c8\u30df\u30b5\u30c8"
    ],
    "wof:name":"Tomisato",
    "wof:placetype":"locality"
},
  "geometry": {"coordinates":[142.70858999999999,42.21736],"type":"Point"}
}