{
  "type": "Feature",
  "properties": {
    "gn:admin1_code":"36",
    "gn:admin2_code":"1854781.0",
    "gn:admin3_code":"32448.0",
    "gn:asciiname":"Ushiomura",
    "gn:country_code":"JP",
    "gn:dem":82,
    "gn:feature_class":"P",
    "gn:feature_code":"PPL",
    "gn:name":"Ushiomura",
    "gn:population":0,
    "gn:timezone":"Asia/Tokyo",
    "iso:country":"JP",
    "name:jpn_x_preferred":[
        "\u6f6e\u6751"
    ],
    "name:und_x_variant":[
        "Ushio"
    ],
    "wof:name":"Ushiomura",
    "wof:placetype":"locality"
},
  "geometry": {"coordinates":[132.63333,35.01667],"type":"Point"}
}