{
  "type": "Feature",
  "properties": {
    "gn:admin1_code":"27",
    "gn:admin2_code":"7418805.0",
    "gn:asciiname":"Ikitsukicho-tachiura",
    "gn:country_code":"JP",
    "gn:dem":3,
    "gn:feature_class":"P",
    "gn:feature_code":"PPL",
    "gn:name":"Ikitsukich\u014d-tachiura",
    "gn:population":0,
    "gn:timezone":"Asia/Tokyo",
    "iso:country":"JP",
    "name:jpn_x_preferred":[
        "\u751f\u6708\u753a\u8218\u6d66"
    ],
    "name:und_x_variant":[
        "Tateura",
        "Tachiura",
        "Ikitsukich\u014d-tachiura"
    ],
    "wof:name":"Ikitsukicho-tachiura",
    "wof:placetype":"locality"
},
  "geometry": {"coordinates":[129.43091000000001,33.36016],"type":"Point"}
}