{
  "type": "Feature",
  "properties": {
    "gn:admin1_code":"43.0",
    "gn:admin2_code":"1860782.0",
    "gn:asciiname":"Nojiri",
    "gn:country_code":"JP",
    "gn:dem":49,
    "gn:feature_class":"P",
    "gn:feature_code":"PPL",
    "gn:name":"Nojiri",
    "gn:population":0,
    "gn:timezone":"Asia/Tokyo",
    "iso:country":"JP",
    "name:jpn_x_preferred":[
        "\u91ce\u5c3b"
    ],
    "name:por_x_preferred":[
        "Nojiri"
    ],
    "wof:name":"Nojiri",
    "wof:placetype":"locality"
},
  "geometry": {"coordinates":[135.2893,34.18079],"type":"Point"}
}