{
  "type": "Feature",
  "properties": {
    "gn:admin1_code":"19.0",
    "gn:admin2_code":"1864091.0",
    "gn:asciiname":"Hatori",
    "gn:country_code":"JP",
    "gn:dem":16,
    "gn:feature_class":"P",
    "gn:feature_code":"PPL",
    "gn:name":"Hatori",
    "gn:population":0,
    "gn:timezone":"Asia/Tokyo",
    "iso:country":"JP",
    "name:jpn_x_preferred":[
        "\u7fbd\u9ce5"
    ],
    "wof:name":"Hatori",
    "wof:placetype":"locality"
},
  "geometry": {"coordinates":[139.45762999999999,35.34483],"type":"Point"}
}