{
  "type": "Feature",
  "properties": {
    "gn:admin1_code":"21.0",
    "gn:admin2_code":"7412709.0",
    "gn:admin3_code":"43348.0",
    "gn:asciiname":"Funatsu",
    "gn:country_code":"JP",
    "gn:dem":113,
    "gn:feature_class":"P",
    "gn:feature_code":"PPLL",
    "gn:name":"Funatsu",
    "gn:population":0,
    "gn:timezone":"Asia/Tokyo",
    "iso:country":"JP",
    "name:jpn_x_preferred":[
        "\u8239\u6d25"
    ],
    "name:jpn_x_variant":[
        "\u3075\u306a\u3064",
        "\u30d5\u30ca\u30c4"
    ],
    "name:kor_x_preferred":[
        "\ud6c4\ub098\uc4f0"
    ],
    "wof:name":"Funatsu",
    "wof:placetype":"locality"
},
  "geometry": {"coordinates":[130.88638999999998,32.63018],"type":"Point"}
}