{
  "type": "Feature",
  "properties": {
    "gn:admin1_code":"7.0",
    "gn:admin2_code":"1859306.0",
    "gn:admin3_code":"40108.0",
    "gn:asciiname":"Chayamachi",
    "gn:country_code":"JP",
    "gn:dem":28,
    "gn:feature_class":"P",
    "gn:feature_code":"PPL",
    "gn:name":"Chayamachi",
    "gn:population":0,
    "gn:timezone":"Asia/Tokyo",
    "iso:country":"JP",
    "name:jpn_x_preferred":[
        "\u8336\u5c4b\u753a"
    ],
    "wof:name":"Chayamachi",
    "wof:placetype":"locality"
},
  "geometry": {"coordinates":[130.84325000000001,33.86689000000001],"type":"Point"}
}