{
  "type": "Feature",
  "properties": {
    "gn:admin1_code":"21.0",
    "gn:admin2_code":"1864975.0",
    "gn:admin3_code":"43424.0",
    "gn:asciiname":"Kurazono",
    "gn:country_code":"JP",
    "gn:dem":457,
    "gn:feature_class":"P",
    "gn:feature_code":"PPLL",
    "gn:name":"Kurazono",
    "gn:population":0,
    "gn:timezone":"Asia/Tokyo",
    "iso:country":"JP",
    "name:jpn_x_preferred":[
        "\u8535\u5712"
    ],
    "name:jpn_x_variant":[
        "\u304f\u3089\u305e\u306e",
        "\u30af\u30e9\u30be\u30ce"
    ],
    "wof:name":"Kurazono",
    "wof:placetype":"locality"
},
  "geometry": {"coordinates":[131.08304999999999,33.12724],"type":"Point"}
}