{
  "type": "Feature",
  "properties": {
    "gn:admin1_code":"44.0",
    "gn:admin2_code":"2111850.0",
    "gn:admin3_code":"6364.0",
    "gn:asciiname":"Nishikawa",
    "gn:country_code":"JP",
    "gn:dem":213,
    "gn:feature_class":"P",
    "gn:feature_code":"PPLL",
    "gn:name":"Nishikawa",
    "gn:population":0,
    "gn:timezone":"Asia/Tokyo",
    "iso:country":"JP",
    "name:jpn_x_preferred":[
        "\u897f\u5ddd"
    ],
    "wof:name":"Nishikawa",
    "wof:placetype":"locality"
},
  "geometry": {"coordinates":[140.17639,38.92611],"type":"Point"}
}