{
  "type": "Feature",
  "properties": {
    "gn:admin1_code":"7.0",
    "gn:admin2_code":"1848086.0",
    "gn:asciiname":"Uranotani",
    "gn:country_code":"JP",
    "gn:dem":30,
    "gn:feature_class":"P",
    "gn:feature_code":"PPLL",
    "gn:name":"Uranotani",
    "gn:population":0,
    "gn:timezone":"Asia/Tokyo",
    "iso:country":"JP",
    "name:jpn_x_preferred":[
        "\u88cf\u30ce\u8c37"
    ],
    "wof:name":"Uranotani",
    "wof:placetype":"locality"
},
  "geometry": {"coordinates":[130.96948999999998,33.69677],"type":"Point"}
}