{
  "type": "Feature",
  "properties": {
    "gn:admin1_code":"3.0",
    "gn:admin2_code":"2129224.0",
    "gn:admin3_code":"2361.0",
    "gn:asciiname":"Kobata",
    "gn:country_code":"JP",
    "gn:dem":18,
    "gn:feature_class":"P",
    "gn:feature_code":"PPL",
    "gn:name":"Kobata",
    "gn:population":0,
    "gn:timezone":"Asia/Tokyo",
    "iso:country":"JP",
    "name:jpn_x_preferred":[
        "\u5c0f\u7551"
    ],
    "name:jpn_x_variant":[
        "\u3053\u3070\u305f",
        "\u30b3\u30d0\u30bf"
    ],
    "wof:name":"Kobata",
    "wof:placetype":"locality"
},
  "geometry": {"coordinates":[140.51913999999999,40.668],"type":"Point"}
}