{
  "type": "Feature",
  "properties": {
    "gn:admin1_code":"11",
    "gn:admin2_code":"1850858.0",
    "gn:asciiname":"Tadanoumi-tokonoura",
    "gn:country_code":"JP",
    "gn:dem":10,
    "gn:feature_class":"P",
    "gn:feature_code":"PPL",
    "gn:name":"Tadanoumi-tokonoura",
    "gn:population":0,
    "gn:timezone":"Asia/Tokyo",
    "iso:country":"JP",
    "name:jpn_x_preferred":[
        "\u5fe0\u6d77\u5e8a\u6d66"
    ],
    "name:und_x_variant":[
        "Tadanoumich\u014d",
        "Tadanoumi",
        "Tadanoumi-tokonoura"
    ],
    "wof:name":"Tadanoumi-tokonoura",
    "wof:placetype":"locality"
},
  "geometry": {"coordinates":[132.98333,34.33333],"type":"Point"}
}