{
  "type": "Feature",
  "properties": {
    "gn:admin1_code":"7.0",
    "gn:admin2_code":"9035649.0",
    "gn:asciiname":"Shima-sakurai",
    "gn:country_code":"JP",
    "gn:dem":9,
    "gn:feature_class":"P",
    "gn:feature_code":"PPL",
    "gn:name":"Shima-sakurai",
    "gn:population":0,
    "gn:timezone":"Asia/Tokyo",
    "iso:country":"JP",
    "name:jpn_x_preferred":[
        "\u5fd7\u6469\u685c\u4e95"
    ],
    "wof:name":"Shima-sakurai",
    "wof:placetype":"locality"
},
  "geometry": {"coordinates":[130.19361999999998,33.62106],"type":"Point"}
}