{
  "type": "Feature",
  "properties": {
    "iso:country":"JP",
    "name:eng_x_preferred":[
        "Tamagawagakuen 6 Chome"
    ],
    "name:eng_x_variant":[
        "Tamagawagakuen 6 Choume",
        "Tamagawagakuen 6 Chome"
    ],
    "name:jpn_x_preferred":[
        "\uff16\u4e01\u76ee"
    ],
    "name:jpn_x_variant":[
        "\u305f\u307e\u304c\u308f\u304c\u304f\u3048\u3093 \uff16\u3061\u3087\u3046\u3081",
        "\u7389\u5ddd\u5b66\u5712 \uff16\u4e01\u76ee",
        "\uff16\u3061\u3087\u3046\u3081"
    ],
    "name:unk_x_variant":[
        "\uff16\u4e01\u76ee"
    ],
    "qs:gn_local":0,
    "qs:local_max":1601,
    "qs:local_sum":3692,
    "qs:localhoods":21,
    "qs:name":"\uff16\u4e01\u76ee",
    "qs:name_adm0":"\u65e5\u672c",
    "qs:name_adm1":"\u6771\u4eac\u90fd",
    "qs:name_en":"Tamagawagakuen 6 Chome",
    "qs:name_lau":"\u7389\u5ddd\u5b66\u5712",
    "qs:name_local":"\u753a\u7530\u5e02",
    "qs:photo_max":272,
    "qs:photo_sum":288,
    "qs:placetype":"Suburb",
    "qs:quad_count":8,
    "qs:woe_adm0":23424856,
    "qs:woe_adm1":2345889,
    "qs:woe_adm2":0,
    "qs:woe_lau":28415091,
    "qs:woe_local":1111475,
    "qs:woe_ver":"7.10.0",
    "wof:lang":[
        "jpn"
    ],
    "wof:name":"\uff16\u4e01\u76ee",
    "wof:placetype":"neighbourhood"
},
  "geometry": {"coordinates":[139.46999099999999,35.569012],"type":"Point"}
}