{
  "type": "Feature",
  "properties": {
    "iso:country":"JP",
    "name:eng_x_preferred":[
        "Moriya"
    ],
    "name:eng_x_variant":[
        "Moriya City"
    ],
    "name:jpn_x_preferred":[
        "\u5b88\u8c37\u5e02"
    ],
    "qs:name":"\u5b88\u8c37\u5e02",
    "qs:name_adm0":"\u65e5\u672c",
    "qs:name_adm1":"\u8328\u57ce\u770c",
    "qs:photos":101,
    "qs:photos_1k":20,
    "qs:photos_9k":2,
    "qs:photos_9r":5,
    "qs:photos_all":535,
    "qs:photos_sr":3,
    "qs:placetype":"Town",
    "qs:pop_sr":"0",
    "wof:name":"Moriya",
    "wof:placetype":"locality"
},
  "geometry": {"coordinates":[139.97800799999999,35.937988],"type":"Point"}
}