{
  "type": "Feature",
  "properties": {
    "gn:admin1_code":"04",
    "gn:admin2_code":"8304237.0",
    "gn:asciiname":"Sakurai",
    "gn:country_code":"JP",
    "gn:dem":7,
    "gn:feature_class":"P",
    "gn:feature_code":"PPL",
    "gn:name":"Sakurai",
    "gn:population":0,
    "gn:timezone":"Asia/Tokyo",
    "iso:country":"JP",
    "name:deu_x_preferred":[
        "Sakurai"
    ],
    "name:jpn_x_preferred":[
        "\u685c\u4e95"
    ],
    "name:jpn_x_variant":[
        "\u3055\u304f\u3089\u3044",
        "\u30b5\u30af\u30e9\u30a4"
    ],
    "name:pol_x_preferred":[
        "Sakurai"
    ],
    "name:rus_x_preferred":[
        "\u0421\u0430\u043a\u0443\u0440\u0430\u0438"
    ],
    "name:spa_x_preferred":[
        "Sakurai"
    ],
    "name:ukr_x_preferred":[
        "\u0421\u0430\u043a\u0443\u0440\u0430\u0439"
    ],
    "wof:name":"Sakurai",
    "wof:placetype":"locality"
},
  "geometry": {"coordinates":[139.92332999999999,35.36184],"type":"Point"}
}