{
  "type": "Feature",
  "properties": {
    "gn:admin1_code":"28",
    "gn:admin2_code":"1848602.0",
    "gn:asciiname":"Koizumicho",
    "gn:country_code":"JP",
    "gn:dem":56,
    "gn:feature_class":"P",
    "gn:feature_code":"PPL",
    "gn:name":"Koizumich\u014d",
    "gn:population":0,
    "gn:timezone":"Asia/Tokyo",
    "iso:country":"JP",
    "name:jpn_x_preferred":[
        "\u5c0f\u6cc9\u753a"
    ],
    "name:und_x_variant":[
        "Koizumich\u014d",
        "Koizumi"
    ],
    "wof:name":"Koizumicho",
    "wof:placetype":"locality"
},
  "geometry": {"coordinates":[135.75595000000001,34.62535],"type":"Point"}
}