{
  "type": "Feature",
  "properties": {
    "gn:admin1_code":"4.0",
    "gn:admin2_code":"7465524.0",
    "gn:asciiname":"Nakanoyatsu",
    "gn:country_code":"JP",
    "gn:dem":24,
    "gn:feature_class":"P",
    "gn:feature_code":"PPLL",
    "gn:name":"Nakanoyatsu",
    "gn:population":0,
    "gn:timezone":"Asia/Tokyo",
    "iso:country":"JP",
    "name:jpn_x_preferred":[
        "\u4e2d\u30ce\u8c37"
    ],
    "name:jpn_x_variant":[
        "\u306a\u304b\u306e\u3084\u3064",
        "\u30ca\u30ab\u30ce\u30e4\u30c4"
    ],
    "wof:name":"Nakanoyatsu",
    "wof:placetype":"locality"
},
  "geometry": {"coordinates":[140.39061999999998,35.20681],"type":"Point"}
}