{
  "type": "Feature",
  "properties": {
    "gn:admin1_code":"10",
    "gn:admin2_code":"7453841.0",
    "gn:asciiname":"Azumacho-godo",
    "gn:country_code":"JP",
    "gn:dem":383,
    "gn:feature_class":"P",
    "gn:feature_code":"PPL",
    "gn:name":"Azumach\u014d-g\u014ddo",
    "gn:population":0,
    "gn:timezone":"Asia/Tokyo",
    "iso:country":"JP",
    "name:jpn_x_preferred":[
        "\u6771\u753a\u795e\u6238"
    ],
    "name:und_x_variant":[
        "Azumach\u014d-g\u014ddo",
        "G\u014ddo"
    ],
    "wof:name":"Azumacho-godo",
    "wof:placetype":"locality"
},
  "geometry": {"coordinates":[139.35199,36.53913],"type":"Point"}
}