{
  "type": "Feature",
  "properties": {
    "gn:admin1_code":"21",
    "gn:admin2_code":"7412705.0",
    "gn:admin3_code":"43482.0",
    "gn:asciiname":"Tanouramachi",
    "gn:country_code":"JP",
    "gn:dem":8,
    "gn:feature_class":"P",
    "gn:feature_code":"PPL",
    "gn:name":"Tanouramachi",
    "gn:population":0,
    "gn:timezone":"Asia/Tokyo",
    "iso:country":"JP",
    "name:jpn_x_preferred":[
        "\u7530\u6d66\u753a"
    ],
    "name:und_x_variant":[
        "Tanoura",
        "Tanouramachi"
    ],
    "wof:name":"Tanouramachi",
    "wof:placetype":"locality"
},
  "geometry": {"coordinates":[130.50613999999999,32.36584000000001],"type":"Point"}
}