{
  "type": "Feature",
  "properties": {
    "iso:country":"JP",
    "name:eng_x_preferred":[
        "Hatsuyamabetsu"
    ],
    "name:eng_x_variant":[
        "Hatsuyamabetsu Village"
    ],
    "name:jpn_x_preferred":[
        "\u521d\u5c71\u5225\u6751"
    ],
    "qs:name":"\u521d\u5c71\u5225\u6751",
    "qs:name_adm0":"\u65e5\u672c",
    "qs:name_adm1":"\u5317\u6d77\u9053",
    "qs:photos":31,
    "qs:photos_1k":6,
    "qs:photos_9k":1,
    "qs:photos_9r":2,
    "qs:photos_all":31,
    "qs:photos_sr":2,
    "qs:placetype":"Town",
    "qs:pop_sr":"0",
    "wof:name":"Hatsuyamabetsu",
    "wof:placetype":"locality"
},
  "geometry": {"coordinates":[141.77375000000001,44.5629],"type":"Point"}
}