{
  "type": "Feature",
  "properties": {
    "gn:admin1_code":"44.0",
    "gn:admin2_code":"1855187.0",
    "gn:admin3_code":"6401.0",
    "gn:asciiname":"Shirakozawa",
    "gn:country_code":"JP",
    "gn:dem":347,
    "gn:feature_class":"P",
    "gn:feature_code":"PPL",
    "gn:name":"Shirakozawa",
    "gn:population":0,
    "gn:timezone":"Asia/Tokyo",
    "iso:country":"JP",
    "name:jpn_x_preferred":[
        "\u767d\u5b50\u6ca2"
    ],
    "wof:name":"Shirakozawa",
    "wof:placetype":"locality"
},
  "geometry": {"coordinates":[139.86548999999999,38.01449],"type":"Point"}
}