{
  "type": "Feature",
  "properties": {
    "gn:admin1_code":"3.0",
    "gn:admin2_code":"2130654.0",
    "gn:asciiname":"Tsukuda",
    "gn:country_code":"JP",
    "gn:dem":5,
    "gn:feature_class":"P",
    "gn:feature_code":"PPL",
    "gn:name":"Tsukuda",
    "gn:population":0,
    "gn:timezone":"Asia/Tokyo",
    "iso:country":"JP",
    "name:jpn_x_preferred":[
        "\u4f43"
    ],
    "name:jpn_x_variant":[
        "\u3064\u304f\u3060",
        "\u30c4\u30af\u30c0"
    ],
    "name:kor_x_preferred":[
        "\uc4f0\ucfe0\ub2e4"
    ],
    "wof:name":"Tsukuda",
    "wof:placetype":"locality"
},
  "geometry": {"coordinates":[140.77858999999995,40.82122],"type":"Point"}
}