{
  "type": "Feature",
  "properties": {
    "gn:admin1_code":"7.0",
    "gn:admin2_code":"1859306.0",
    "gn:admin3_code":"40109.0",
    "gn:asciiname":"Higashihamamachi",
    "gn:country_code":"JP",
    "gn:dem":5,
    "gn:feature_class":"P",
    "gn:feature_code":"PPL",
    "gn:name":"Higashihamamachi",
    "gn:population":0,
    "gn:timezone":"Asia/Tokyo",
    "iso:country":"JP",
    "name:jpn_x_preferred":[
        "\u6771\u6d5c\u753a"
    ],
    "wof:name":"Higashihamamachi",
    "wof:placetype":"locality"
},
  "geometry": {"coordinates":[130.77844999999999,33.87023],"type":"Point"}
}