{
  "type": "Feature",
  "properties": {
    "gn:admin1_code":"3.0",
    "gn:admin2_code":"2130654.0",
    "gn:asciiname":"Moya",
    "gn:country_code":"JP",
    "gn:dem":164,
    "gn:feature_class":"P",
    "gn:feature_code":"PPL",
    "gn:name":"Moya",
    "gn:population":0,
    "gn:timezone":"Asia/Tokyo",
    "iso:country":"JP",
    "name:jpn_x_preferred":[
        "\u96f2\u8c37"
    ],
    "name:jpn_x_variant":[
        "\u3082\u3084",
        "\u30e2\u30e4"
    ],
    "wof:name":"Moya",
    "wof:placetype":"locality"
},
  "geometry": {"coordinates":[140.77882,40.7482],"type":"Point"}
}