{
  "type": "Feature",
  "properties": {
    "gn:admin1_code":"3.0",
    "gn:admin2_code":"2130654.0",
    "gn:asciiname":"Moya",
    "gn:country_code":"JP",
    "gn:dem":164,
    "gn:feature_class":"P",
    "gn:feature_code":"PPL",
    "gn:name":"Moya",
    "gn:population":0,
    "gn:timezone":"Asia/Tokyo",
    "iso:country":"JP",
    "name:cat_x_preferred":[
        "Moya"
    ],
    "name:ceb_x_preferred":[
        "Moya"
    ],
    "name:deu_x_preferred":[
        "Moya"
    ],
    "name:eus_x_preferred":[
        "Moya"
    ],
    "name:fra_x_preferred":[
        "Moya"
    ],
    "name:glg_x_preferred":[
        "Moya"
    ],
    "name:heb_x_preferred":[
        "\u05de\u05d5\u05d9\u05d4"
    ],
    "name:hun_x_preferred":[
        "Moya"
    ],
    "name:hye_x_preferred":[
        "\u0544\u0578\u0575\u0561"
    ],
    "name:ita_x_preferred":[
        "Moya"
    ],
    "name:jpn_x_preferred":[
        "\u96f2\u8c37"
    ],
    "name:jpn_x_variant":[
        "\u3082\u3084",
        "\u30e2\u30e4"
    ],
    "name:msa_x_preferred":[
        "Moya"
    ],
    "name:nld_x_preferred":[
        "Moya"
    ],
    "name:oci_x_preferred":[
        "Moya"
    ],
    "name:pol_x_preferred":[
        "Moya"
    ],
    "name:por_x_preferred":[
        "Moya"
    ],
    "name:rus_x_preferred":[
        "\u041c\u043e\u0439\u044f"
    ],
    "name:spa_x_preferred":[
        "Moya"
    ],
    "name:swe_x_preferred":[
        "Moya"
    ],
    "name:ukr_x_preferred":[
        "\u041c\u043e\u044f"
    ],
    "name:uzb_x_preferred":[
        "Moya"
    ],
    "name:vie_x_preferred":[
        "Moya"
    ],
    "name:war_x_preferred":[
        "Moya"
    ],
    "wof:name":"Moya",
    "wof:placetype":"locality"
},
  "geometry": {"coordinates":[140.77882,40.7482],"type":"Point"}
}