{
  "type": "Feature",
  "properties": {
    "gn:admin1_code":"21.0",
    "gn:admin2_code":"1849062.0",
    "gn:asciiname":"Sugutsugu",
    "gn:country_code":"JP",
    "gn:dem":-1,
    "gn:feature_class":"P",
    "gn:feature_code":"PPLL",
    "gn:name":"Sugutsugu",
    "gn:population":0,
    "gn:timezone":"Asia/Tokyo",
    "iso:country":"JP",
    "name:jpn_x_preferred":[
        "\u76f4\u7bc9"
    ],
    "name:jpn_x_variant":[
        "\u3059\u3050\u3064\u3050",
        "\u30b9\u30b0\u30c4\u30b0"
    ],
    "wof:name":"Sugutsugu",
    "wof:placetype":"locality"
},
  "geometry": {"coordinates":[130.60873000000001,32.71182],"type":"Point"}
}