{
  "type": "Feature",
  "properties": {
    "gn:admin1_code":"21.0",
    "gn:admin2_code":"7412708.0",
    "gn:admin3_code":"43514.0",
    "gn:asciiname":"Yunoharu",
    "gn:country_code":"JP",
    "gn:dem":178,
    "gn:feature_class":"P",
    "gn:feature_code":"PPLL",
    "gn:name":"Yunoharu",
    "gn:population":0,
    "gn:timezone":"Asia/Tokyo",
    "iso:country":"JP",
    "name:jpn_x_preferred":[
        "\u6e6f\u30ce\u539f"
    ],
    "name:jpn_x_variant":[
        "\u3086\u306e\u306f\u308b",
        "\u30e6\u30ce\u30cf\u30eb"
    ],
    "wof:name":"Yunoharu",
    "wof:placetype":"locality"
},
  "geometry": {"coordinates":[130.89859999999999,32.27095],"type":"Point"}
}