{
  "type": "Feature",
  "properties": {
    "gn:admin1_code":"21.0",
    "gn:admin2_code":"1865358.0",
    "gn:asciiname":"Masuno",
    "gn:country_code":"JP",
    "gn:dem":167,
    "gn:feature_class":"P",
    "gn:feature_code":"PPLL",
    "gn:name":"Masuno",
    "gn:population":0,
    "gn:timezone":"Asia/Tokyo",
    "iso:country":"JP",
    "name:jpn_x_preferred":[
        "\u5897\u91ce"
    ],
    "name:jpn_x_variant":[
        "\u307e\u3059\u306e",
        "\u30de\u30b9\u30ce"
    ],
    "wof:name":"Masuno",
    "wof:placetype":"locality"
},
  "geometry": {"coordinates":[129.99979999999999,32.26331],"type":"Point"}
}