{
  "type": "Feature",
  "properties": {
    "gn:admin1_code":"44",
    "gn:admin2_code":"1849562.0",
    "gn:asciiname":"Higashiiwamoto",
    "gn:country_code":"JP",
    "gn:dem":70,
    "gn:feature_class":"P",
    "gn:feature_code":"PPL",
    "gn:name":"Higashiiwamoto",
    "gn:population":0,
    "gn:timezone":"Asia/Tokyo",
    "iso:country":"JP",
    "name:jpn_x_preferred":[
        "\u6771\u5ca9\u672c"
    ],
    "wof:name":"Higashiiwamoto",
    "wof:placetype":"locality"
},
  "geometry": {"coordinates":[139.85182,38.62772],"type":"Point"}
}