{
  "type": "Feature",
  "properties": {
    "gn:admin1_code":"21.0",
    "gn:admin2_code":"7412706.0",
    "gn:admin3_code":"43447.0",
    "gn:asciiname":"Tamame",
    "gn:country_code":"JP",
    "gn:dem":622,
    "gn:feature_class":"P",
    "gn:feature_code":"PPLL",
    "gn:name":"Tamame",
    "gn:population":0,
    "gn:timezone":"Asia/Tokyo",
    "iso:country":"JP",
    "name:jpn_x_preferred":[
        "\u7389\u76ee"
    ],
    "name:jpn_x_variant":[
        "\u305f\u307e\u3081",
        "\u30bf\u30de\u30e1"
    ],
    "wof:name":"Tamame",
    "wof:placetype":"locality"
},
  "geometry": {"coordinates":[131.16152,32.75341],"type":"Point"}
}