{
  "type": "Feature",
  "properties": {
    "gn:admin1_code":"23",
    "gn:admin2_code":"7417710.0",
    "gn:asciiname":"Ageki",
    "gn:country_code":"JP",
    "gn:dem":99,
    "gn:feature_class":"P",
    "gn:feature_code":"PPL",
    "gn:name":"Ageki",
    "gn:population":0,
    "gn:timezone":"Asia/Tokyo",
    "iso:country":"JP",
    "wof:name":"Ageki",
    "wof:placetype":"locality"
},
  "geometry": {"coordinates":[136.51667,35.15],"type":"Point"}
}