{
  "type": "Feature",
  "properties": {
    "gn:admin1_code":"3.0",
    "gn:admin2_code":"2130200.0",
    "gn:asciiname":"Ichinosawa",
    "gn:country_code":"JP",
    "gn:dem":231,
    "gn:feature_class":"P",
    "gn:feature_code":"PPL",
    "gn:name":"Ichinosawa",
    "gn:population":0,
    "gn:timezone":"Asia/Tokyo",
    "iso:country":"JP",
    "name:jpn_x_preferred":[
        "\u5e02\u91ce\u6ca2"
    ],
    "name:jpn_x_variant":[
        "\u3044\u3061\u306e\u3055\u308f",
        "\u30a4\u30c1\u30ce\u30b5\u30ef"
    ],
    "wof:name":"Ichinosawa",
    "wof:placetype":"locality"
},
  "geometry": {"coordinates":[141.42955000000001,40.40012],"type":"Point"}
}