{
  "type": "Feature",
  "properties": {
    "gn:admin1_code":"15.0",
    "gn:admin2_code":"1863340.0",
    "gn:asciiname":"Kaminakayamamachi",
    "gn:country_code":"JP",
    "gn:dem":96,
    "gn:feature_class":"P",
    "gn:feature_code":"PPL",
    "gn:name":"Kaminakayamamachi",
    "gn:population":0,
    "gn:timezone":"Asia/Tokyo",
    "iso:country":"JP",
    "name:jpn_x_preferred":[
        "\u4e0a\u4e2d\u5c71\u753a"
    ],
    "wof:name":"Kaminakayamamachi",
    "wof:placetype":"locality"
},
  "geometry": {"coordinates":[136.80149,36.94577],"type":"Point"}
}