{
  "type": "Feature",
  "properties": {
    "gn:admin1_code":"12.0",
    "gn:admin2_code":"2129370.0",
    "gn:asciiname":"Akancho-fubushinai-minami",
    "gn:country_code":"JP",
    "gn:dem":55,
    "gn:feature_class":"P",
    "gn:feature_code":"PPL",
    "gn:name":"Akanch\u014d-fubushinai-minami",
    "gn:population":0,
    "gn:timezone":"Asia/Tokyo",
    "iso:country":"JP",
    "name:jpn_x_preferred":[
        "\u963f\u5bd2\u753a\u5e03\u4f0f\u5185\u5357"
    ],
    "name:jpn_x_variant":[
        "\u3042\u304b\u3093\u3061\u3087\u3046\u3075\u3076\u3057\u306a\u3044\u307f\u306a\u307f",
        "\u30a2\u30ab\u30f3\u30c1\u30e7\u30a6\u30d5\u30d6\u30b7\u30ca\u30a4\u30df\u30ca\u30df"
    ],
    "name:und_x_variant":[
        "Akanch\u014d-fubushinai-minami"
    ],
    "wof:name":"Akancho-fubushinai-minami",
    "wof:placetype":"locality"
},
  "geometry": {"coordinates":[144.10581999999999,43.1693],"type":"Point"}
}