{
  "type": "Feature",
  "properties": {
    "gn:admin1_code":"4.0",
    "gn:admin2_code":"1857552.0",
    "gn:asciiname":"Takegahana",
    "gn:country_code":"JP",
    "gn:dem":11,
    "gn:feature_class":"P",
    "gn:feature_code":"PPL",
    "gn:name":"Takegahana",
    "gn:population":0,
    "gn:timezone":"Asia/Tokyo",
    "iso:country":"JP",
    "name:jpn_x_preferred":[
        "\u7af9\u30f6\u82b1"
    ],
    "wof:name":"Takegahana",
    "wof:placetype":"locality"
},
  "geometry": {"coordinates":[139.90549999999999,35.79197],"type":"Point"}
}