{
  "type": "Feature",
  "properties": {
    "gn:admin1_code":"6.0",
    "gn:admin2_code":"7467385.0",
    "gn:asciiname":"Jo",
    "gn:country_code":"JP",
    "gn:dem":29,
    "gn:feature_class":"P",
    "gn:feature_code":"PPL",
    "gn:name":"J\u014d",
    "gn:population":0,
    "gn:timezone":"Asia/Tokyo",
    "iso:country":"JP",
    "name:jpn_x_preferred":[
        "\u57ce"
    ],
    "name:und_x_variant":[
        "J\u014d"
    ],
    "wof:name":"Jo",
    "wof:placetype":"locality"
},
  "geometry": {"coordinates":[136.19302999999999,36.25511],"type":"Point"}
}