{
  "type": "Feature",
  "properties": {
    "iso:country":"JP",
    "name:eng_x_preferred":[
        "Shoshadai 1 Chome"
    ],
    "name:eng_x_variant":[
        "Shoshadai 1 Choume",
        "Shoshadai 1 Chome"
    ],
    "name:jpn_x_preferred":[
        "\uff11\u4e01\u76ee"
    ],
    "name:jpn_x_variant":[
        "\u3057\u3087\u3057\u3083\u3060\u3044 \uff11\u3061\u3087\u3046\u3081",
        "\u66f8\u5199\u53f0 \uff11\u4e01\u76ee",
        "\uff11\u3061\u3087\u3046\u3081"
    ],
    "qs:gn_local":0,
    "qs:local_max":4429,
    "qs:local_sum":11099,
    "qs:localhoods":16,
    "qs:name":"\uff11\u4e01\u76ee",
    "qs:name_adm0":"\u65e5\u672c",
    "qs:name_adm1":"\u5175\u5eab\u770c",
    "qs:name_en":"Shoshadai 1 Chome",
    "qs:name_lau":"\u66f8\u5199\u53f0",
    "qs:name_local":"\u59eb\u8def\u5e02",
    "qs:photo_max":91,
    "qs:photo_sum":237,
    "qs:placetype":"Suburb",
    "qs:quad_count":7,
    "qs:woe_adm0":23424856,
    "qs:woe_adm1":2345862,
    "qs:woe_adm2":0,
    "qs:woe_lau":28461547,
    "qs:woe_local":1117200,
    "qs:woe_ver":"7.10.0",
    "wof:lang":[
        "jpn"
    ],
    "wof:name":"\uff11\u4e01\u76ee",
    "wof:placetype":"neighbourhood"
},
  "geometry": {"coordinates":[134.657633,34.89053],"type":"Point"}
}