{
  "type": "Feature",
  "properties": {
    "gn:admin1_code":"19.0",
    "gn:admin2_code":"1863429.0",
    "gn:asciiname":"Sawanoshita",
    "gn:country_code":"JP",
    "gn:dem":206,
    "gn:feature_class":"P",
    "gn:feature_code":"PPLL",
    "gn:name":"Sawanoshita",
    "gn:population":0,
    "gn:timezone":"Asia/Tokyo",
    "iso:country":"JP",
    "name:jpn_x_preferred":[
        "\u6ca2\u4e4b\u4e0b"
    ],
    "wof:name":"Sawanoshita",
    "wof:placetype":"locality"
},
  "geometry": {"coordinates":[139.15378000000001,35.37575],"type":"Point"}
}