{
  "type": "Feature",
  "properties": {
    "gn:admin1_code":"19.0",
    "gn:admin2_code":"1848350.0",
    "gn:admin3_code":"14112.0",
    "gn:asciiname":"Imagawacho",
    "gn:country_code":"JP",
    "gn:dem":60,
    "gn:feature_class":"P",
    "gn:feature_code":"PPL",
    "gn:name":"Imagawach\u014d",
    "gn:population":0,
    "gn:timezone":"Asia/Tokyo",
    "iso:country":"JP",
    "name:jpn_x_preferred":[
        "\u4eca\u5ddd\u753a"
    ],
    "name:jpn_x_variant":[
        "\u3044\u307e\u304c\u308f\u3061\u3087\u3046",
        "\u30a4\u30de\u30ac\u30ef\u30c1\u30e7\u30a6"
    ],
    "name:und_x_variant":[
        "Imagawach\u014d"
    ],
    "wof:name":"Imagawacho",
    "wof:placetype":"locality"
},
  "geometry": {"coordinates":[139.53607,35.47589],"type":"Point"}
}