{
  "type": "Feature",
  "properties": {
    "gn:admin1_code":"21.0",
    "gn:admin2_code":"1849062.0",
    "gn:asciiname":"Furuyashiki",
    "gn:country_code":"JP",
    "gn:dem":186,
    "gn:feature_class":"P",
    "gn:feature_code":"PPLL",
    "gn:name":"Furuyashiki",
    "gn:population":0,
    "gn:timezone":"Asia/Tokyo",
    "iso:country":"JP",
    "name:jpn_x_preferred":[
        "\u53e4\u5c4b\u6577"
    ],
    "name:jpn_x_variant":[
        "\u3075\u308b\u3084\u3057\u304d",
        "\u30d5\u30eb\u30e4\u30b7\u30ad"
    ],
    "wof:name":"Furuyashiki",
    "wof:placetype":"locality"
},
  "geometry": {"coordinates":[130.52566999999999,32.6549],"type":"Point"}
}