{
  "type": "Feature",
  "properties": {
    "gn:admin1_code":"21.0",
    "gn:admin2_code":"1858418.0",
    "gn:admin3_code":"43103.0",
    "gn:asciiname":"Togenochaya",
    "gn:country_code":"JP",
    "gn:dem":285,
    "gn:feature_class":"P",
    "gn:feature_code":"PPLL",
    "gn:name":"T\u014dgenochaya",
    "gn:population":0,
    "gn:timezone":"Asia/Tokyo",
    "iso:country":"JP",
    "name:jpn_x_preferred":[
        "\u5ce0\u306e\u8336\u5c4b"
    ],
    "name:jpn_x_variant":[
        "\u3068\u3046\u3052\u306e\u3061\u3083\u3084",
        "\u30c8\u30a6\u30b2\u30ce\u30c1\u30e3\u30e4"
    ],
    "name:und_x_variant":[
        "T\u014dgenochaya"
    ],
    "wof:name":"Togenochaya",
    "wof:placetype":"locality"
},
  "geometry": {"coordinates":[130.65434999999999,32.81777],"type":"Point"}
}