{
  "type": "Feature",
  "properties": {
    "gn:admin1_code":"7.0",
    "gn:admin2_code":"1851269.0",
    "gn:admin3_code":"40608.0",
    "gn:asciiname":"Koshinmachi",
    "gn:country_code":"JP",
    "gn:dem":50,
    "gn:feature_class":"P",
    "gn:feature_code":"PPLL",
    "gn:name":"K\u014dshinmachi",
    "gn:population":0,
    "gn:timezone":"Asia/Tokyo",
    "iso:country":"JP",
    "name:jpn_x_preferred":[
        "\u5e78\u795e\u753a"
    ],
    "name:und_x_variant":[
        "K\u014dshinmachi"
    ],
    "wof:name":"Koshinmachi",
    "wof:placetype":"locality"
},
  "geometry": {"coordinates":[130.84256000000002,33.60819],"type":"Point"}
}