{
  "type": "Feature",
  "properties": {
    "gn:admin1_code":"21.0",
    "gn:admin2_code":"7413152.0",
    "gn:asciiname":"Kamisubayashi",
    "gn:country_code":"JP",
    "gn:dem":79,
    "gn:feature_class":"P",
    "gn:feature_code":"PPLL",
    "gn:name":"Kamisubayashi",
    "gn:population":0,
    "gn:timezone":"Asia/Tokyo",
    "iso:country":"JP",
    "name:jpn_x_preferred":[
        "\u4e0a\u5de3\u6797"
    ],
    "name:jpn_x_variant":[
        "\u304b\u307f\u3059\u3070\u3084\u3057",
        "\u30ab\u30df\u30b9\u30d0\u30e4\u30b7"
    ],
    "wof:name":"Kamisubayashi",
    "wof:placetype":"locality"
},
  "geometry": {"coordinates":[130.77267000000001,32.64395],"type":"Point"}
}