{
  "type": "Feature",
  "properties": {
    "gn:admin1_code":"29.0",
    "gn:admin2_code":"1861238.0",
    "gn:admin3_code":"15581.0",
    "gn:asciiname":"Takada",
    "gn:country_code":"JP",
    "gn:dem":24,
    "gn:feature_class":"P",
    "gn:feature_code":"PPL",
    "gn:name":"Takada",
    "gn:population":0,
    "gn:timezone":"Asia/Tokyo",
    "iso:country":"JP",
    "name:deu_x_preferred":[
        "Takada"
    ],
    "name:jpn_x_preferred":[
        "\u9ad8\u7530"
    ],
    "name:kor_x_preferred":[
        "\ub2e4\uce74\ub2e4"
    ],
    "name:rus_x_preferred":[
        "\u0422\u0430\u043a\u0430\u0434\u0430"
    ],
    "wof:name":"Takada",
    "wof:placetype":"locality"
},
  "geometry": {"coordinates":[139.52766,38.10652],"type":"Point"}
}