{
  "type": "Feature",
  "properties": {
    "gn:admin1_code":"2.0",
    "gn:admin2_code":"2113122.0",
    "gn:asciiname":"Kamishinjo-shirayama",
    "gn:country_code":"JP",
    "gn:dem":66,
    "gn:feature_class":"P",
    "gn:feature_code":"PPL",
    "gn:name":"Kamishinj\u014d-shirayama",
    "gn:population":0,
    "gn:timezone":"Asia/Tokyo",
    "iso:country":"JP",
    "name:jpn_x_preferred":[
        "\u4e0a\u65b0\u57ce\u767d\u5c71"
    ],
    "name:jpn_x_variant":[
        "\u304b\u307f\u3057\u3093\u3058\u3087\u3046\u3057\u3089\u3084\u307e",
        "\u30ab\u30df\u30b7\u30f3\u30b8\u30e7\u30a6\u30b7\u30e9\u30e4\u30de",
        "\u767d\u5c71"
    ],
    "name:und_x_variant":[
        "Kamishinj\u014d-shirayama",
        "Shirayama"
    ],
    "wof:name":"Kamishinjo-shirayama",
    "wof:placetype":"locality"
},
  "geometry": {"coordinates":[140.14518000000001,39.8141],"type":"Point"}
}