{
  "type": "Feature",
  "properties": {
    "gn:admin1_code":"12.0",
    "gn:admin2_code":"2130184.0",
    "gn:asciiname":"Kikyo",
    "gn:country_code":"JP",
    "gn:dem":29,
    "gn:feature_class":"P",
    "gn:feature_code":"PPL",
    "gn:name":"Kiky\u014d",
    "gn:population":0,
    "gn:timezone":"Asia/Tokyo",
    "iso:country":"JP",
    "name:jpn_x_preferred":[
        "\u6854\u6897"
    ],
    "name:jpn_x_variant":[
        "\u304d\u304d\u3087\u3046",
        "\u30ad\u30ad\u30e7\u30a6"
    ],
    "name:und_x_variant":[
        "Kiky\u014d"
    ],
    "wof:name":"Kikyo",
    "wof:placetype":"locality"
},
  "geometry": {"coordinates":[140.72801999999999,41.84106],"type":"Point"}
}