{
  "type": "Feature",
  "properties": {
    "gn:admin1_code":"32",
    "gn:admin2_code":"7391701.0",
    "gn:asciiname":"Terauchi",
    "gn:country_code":"JP",
    "gn:dem":36,
    "gn:feature_class":"P",
    "gn:feature_code":"PPL",
    "gn:name":"Terauchi",
    "gn:population":0,
    "gn:timezone":"Asia/Tokyo",
    "iso:country":"JP",
    "name:jpn_x_preferred":[
        "\u5bfa\u5185"
    ],
    "name:und_x_variant":[
        "Jinai"
    ],
    "wof:name":"Terauchi",
    "wof:placetype":"locality"
},
  "geometry": {"coordinates":[135.49267,34.77448],"type":"Point"}
}