{
  "type": "Feature",
  "properties": {
    "gn:admin1_code":"8.0",
    "gn:admin2_code":"9035647.0",
    "gn:asciiname":"Tokiwamachi-hotta",
    "gn:country_code":"JP",
    "gn:dem":562,
    "gn:feature_class":"P",
    "gn:feature_code":"PPL",
    "gn:name":"Tokiwamachi-hotta",
    "gn:population":0,
    "gn:timezone":"Asia/Tokyo",
    "iso:country":"JP",
    "name:jpn_x_preferred":[
        "\u5e38\u8449\u753a\u5800\u7530"
    ],
    "wof:name":"Tokiwamachi-hotta",
    "wof:placetype":"locality"
},
  "geometry": {"coordinates":[140.6953,37.41249000000001],"type":"Point"}
}