{
  "type": "Feature",
  "properties": {
    "gn:admin1_code":"21.0",
    "gn:admin2_code":"7412708.0",
    "gn:admin3_code":"43501.0",
    "gn:asciiname":"Nishiharu",
    "gn:country_code":"JP",
    "gn:dem":154,
    "gn:feature_class":"P",
    "gn:feature_code":"PPLL",
    "gn:name":"Nishiharu",
    "gn:population":0,
    "gn:timezone":"Asia/Tokyo",
    "iso:country":"JP",
    "name:jpn_x_preferred":[
        "\u897f\u539f"
    ],
    "name:jpn_x_variant":[
        "\u306b\u3057\u306f\u308b",
        "\u30cb\u30b7\u30cf\u30eb"
    ],
    "wof:name":"Nishiharu",
    "wof:placetype":"locality"
},
  "geometry": {"coordinates":[130.84953000000002,32.20499],"type":"Point"}
}