{
  "type": "Feature",
  "properties": {
    "gn:admin1_code":"18.0",
    "gn:admin2_code":"7383999.0",
    "gn:admin3_code":"46491.0",
    "gn:asciiname":"Akasegawa",
    "gn:country_code":"JP",
    "gn:dem":199,
    "gn:feature_class":"P",
    "gn:feature_code":"PPLL",
    "gn:name":"Akasegawa",
    "gn:population":0,
    "gn:timezone":"Asia/Tokyo",
    "iso:country":"JP",
    "name:jpn_x_preferred":[
        "\u8d64\u702c\u5ddd"
    ],
    "wof:name":"Akasegawa",
    "wof:placetype":"locality"
},
  "geometry": {"coordinates":[130.80966000000001,31.18793],"type":"Point"}
}