{
  "type": "Feature",
  "properties": {
    "gn:admin1_code":"21.0",
    "gn:admin2_code":"7412706.0",
    "gn:admin3_code":"43447.0",
    "gn:asciiname":"Yunoki",
    "gn:country_code":"JP",
    "gn:dem":296,
    "gn:feature_class":"P",
    "gn:feature_code":"PPL",
    "gn:name":"Yunoki",
    "gn:population":0,
    "gn:timezone":"Asia/Tokyo",
    "iso:country":"JP",
    "name:jpn_x_preferred":[
        "\u67da\u6728"
    ],
    "name:jpn_x_variant":[
        "\u3086\u306e\u304d",
        "\u30e6\u30ce\u30ad"
    ],
    "wof:name":"Yunoki",
    "wof:placetype":"locality"
},
  "geometry": {"coordinates":[130.91461000000001,32.66506],"type":"Point"}
}