{
  "type": "Feature",
  "properties": {
    "gn:admin1_code":"12.0",
    "gn:admin2_code":"2129370.0",
    "gn:asciiname":"Onbetsucho-asahi",
    "gn:country_code":"JP",
    "gn:dem":9,
    "gn:feature_class":"P",
    "gn:feature_code":"PPL",
    "gn:name":"Onbetsuch\u014d-asahi",
    "gn:population":0,
    "gn:timezone":"Asia/Tokyo",
    "iso:country":"JP",
    "name:jpn_x_preferred":[
        "\u97f3\u5225\u753a\u671d\u65e5"
    ],
    "name:jpn_x_variant":[
        "\u304a\u3093\u3079\u3064\u3061\u3087\u3046\u3042\u3055\u3072",
        "\u30aa\u30f3\u30d9\u30c4\u30c1\u30e7\u30a6\u30a2\u30b5\u30d2"
    ],
    "name:und_x_variant":[
        "Onbetsuch\u014d-asahi"
    ],
    "wof:name":"Onbetsucho-asahi",
    "wof:placetype":"locality"
},
  "geometry": {"coordinates":[143.93581,42.89309],"type":"Point"}
}