{
  "type": "Feature",
  "properties": {
    "gn:admin1_code":"19.0",
    "gn:admin2_code":"1860670.0",
    "gn:asciiname":"Nikaido",
    "gn:country_code":"JP",
    "gn:dem":34,
    "gn:feature_class":"P",
    "gn:feature_code":"PPL",
    "gn:name":"Nikaid\u014d",
    "gn:population":0,
    "gn:timezone":"Asia/Tokyo",
    "iso:country":"JP",
    "name:deu_x_preferred":[
        "Nikaido"
    ],
    "name:jpn_x_preferred":[
        "\u4e8c\u968e\u5802"
    ],
    "name:jpn_x_variant":[
        "\u306b\u304b\u3044\u3069\u3046",
        "\u30cb\u30ab\u30a4\u30c9\u30a6"
    ],
    "name:kor_x_preferred":[
        "\ub2c8\uce74\uc774\ub3c4"
    ],
    "name:und_x_variant":[
        "Nikaid\u014d"
    ],
    "wof:name":"Nikaido",
    "wof:placetype":"locality"
},
  "geometry": {"coordinates":[139.56576000000001,35.32725],"type":"Point"}
}