{
  "type": "Feature",
  "properties": {
    "gn:admin1_code":"19.0",
    "gn:admin2_code":"1856849.0",
    "gn:asciiname":"Iimori",
    "gn:country_code":"JP",
    "gn:dem":28,
    "gn:feature_class":"P",
    "gn:feature_code":"PPLL",
    "gn:name":"Iimori",
    "gn:population":0,
    "gn:timezone":"Asia/Tokyo",
    "iso:country":"JP",
    "name:jpn_x_preferred":[
        "\u98ef\u68ee"
    ],
    "name:jpn_x_variant":[
        "\u3044\u3044\u3082\u308a",
        "\u30a4\u30a4\u30e2\u30ea"
    ],
    "wof:name":"Iimori",
    "wof:placetype":"locality"
},
  "geometry": {"coordinates":[139.6386,35.17671],"type":"Point"}
}