{
  "type": "Feature",
  "properties": {
    "gn:admin1_code":"3.0",
    "gn:admin2_code":"2128302.0",
    "gn:admin3_code":"2443.0",
    "gn:asciiname":"Uwanonoshita",
    "gn:country_code":"JP",
    "gn:dem":88,
    "gn:feature_class":"P",
    "gn:feature_code":"PPL",
    "gn:name":"Uwanonoshita",
    "gn:population":0,
    "gn:timezone":"Asia/Tokyo",
    "iso:country":"JP",
    "name:jpn_x_preferred":[
        "\u4e0a\u91ce\u30ce\u4e0b\u30bf"
    ],
    "name:jpn_x_variant":[
        "\u3046\u308f\u306e\u306e\u3057\u305f",
        "\u30a6\u30ef\u30ce\u30ce\u30b7\u30bf"
    ],
    "wof:name":"Uwanonoshita",
    "wof:placetype":"locality"
},
  "geometry": {"coordinates":[141.16151000000005,40.34483],"type":"Point"}
}