{
  "type": "Feature",
  "properties": {
    "gn:country":"JP",
    "gn:fcode":"ADMD",
    "gn:population":0,
    "iso:country":"JP",
    "name:eng_x_preferred":[
        "Fujiwara"
    ],
    "name:eng_x_variant":[
        "Fujiwara-ch\u014d"
    ],
    "name:fra_x_preferred":[
        "Fujiwara"
    ],
    "name:gle_x_preferred":[
        "Fujiwara"
    ],
    "name:jpn_x_preferred":[
        "\u85e4\u539f\u753a"
    ],
    "name:kor_x_preferred":[
        "\ud6c4\uc9c0\uc640\ub77c\uc815"
    ],
    "name:und_x_variant":[
        "Fujiwara-mura"
    ],
    "qs:name":"Fujiwara-ch\u014d",
    "qs:photos_9r":0,
    "qs:photos_sr":0,
    "qs:pop_sr":"0",
    "wd:wordcount":43,
    "wof:name":"Fujiwara",
    "wof:placetype":"localadmin",
    "wof:population":0
},
  "geometry": {"coordinates":[136.48333,35.16667],"type":"Point"}
}