{
  "type": "Feature",
  "properties": {
    "gn:country":"JP",
    "gn:fcode":"ADMD",
    "gn:pop":0,
    "iso:country":"JP",
    "name:unk_x_variant":[
        "Fujiwara-mura"
    ],
    "qs:name":"Fujiwara-ch\u014d",
    "qs:photos_9r":0,
    "qs:photos_sr":0,
    "qs:pop_sr":"0",
    "wd:wordcount":43,
    "wof:name":"Fujiwara-ch\u014d",
    "wof:placetype":"localadmin",
    "wof:population":0
},
  "geometry": {"coordinates":[136.48333,35.16667],"type":"Point"}
}