{
  "type": "Feature",
  "properties": {
    "gn:admin1_code":"7.0",
    "gn:admin2_code":"1851269.0",
    "gn:admin3_code":"40609.0",
    "gn:asciiname":"Maruguma",
    "gn:country_code":"JP",
    "gn:dem":94,
    "gn:feature_class":"P",
    "gn:feature_code":"PPLL",
    "gn:name":"Maruguma",
    "gn:population":0,
    "gn:timezone":"Asia/Tokyo",
    "iso:country":"JP",
    "name:jpn_x_preferred":[
        "\u4e38\u718a"
    ],
    "wof:name":"Maruguma",
    "wof:placetype":"locality"
},
  "geometry": {"coordinates":[130.88265000000001,33.60075],"type":"Point"}
}