{
  "type": "Feature",
  "properties": {
    "gn:admin1_code":"32.0",
    "gn:admin2_code":"1853167.0",
    "gn:admin3_code":"27145.0",
    "gn:asciiname":"Tomikura",
    "gn:country_code":"JP",
    "gn:dem":82,
    "gn:feature_class":"P",
    "gn:feature_code":"PPL",
    "gn:name":"Tomikura",
    "gn:population":0,
    "gn:timezone":"Asia/Tokyo",
    "iso:country":"JP",
    "name:jpn_x_preferred":[
        "\u5bcc\u8535"
    ],
    "wof:name":"Tomikura",
    "wof:placetype":"locality"
},
  "geometry": {"coordinates":[135.51802000000001,34.47611],"type":"Point"}
}