{
  "type": "Feature",
  "properties": {
    "iso:country":"JP",
    "name:eng_x_preferred":[
        "Jomyoji 3 Chome"
    ],
    "name:eng_x_variant":[
        "Joumyouji 3 Choume",
        "Jomyoji 3 Chome"
    ],
    "name:jpn_x_preferred":[
        "\uff13\u4e01\u76ee"
    ],
    "name:jpn_x_variant":[
        "\u3058\u3087\u3046\u307f\u3087\u3046\u3058 \uff13\u3061\u3087\u3046\u3081",
        "\u6d44\u660e\u5bfa \uff13\u4e01\u76ee",
        "\uff13\u3061\u3087\u3046\u3081"
    ],
    "qs:gn_local":0,
    "qs:local_max":2484,
    "qs:local_sum":33815,
    "qs:localhoods":49,
    "qs:name":"\uff13\u4e01\u76ee",
    "qs:name_adm0":"\u65e5\u672c",
    "qs:name_adm1":"\u795e\u5948\u5ddd\u770c",
    "qs:name_en":"Jomyoji 3 Chome",
    "qs:name_lau":"\u6d44\u660e\u5bfa",
    "qs:name_local":"\u938c\u5009\u5e02",
    "qs:photo_max":147,
    "qs:photo_sum":431,
    "qs:placetype":"Suburb",
    "qs:quad_count":9,
    "qs:woe_adm0":23424856,
    "qs:woe_adm1":2345868,
    "qs:woe_adm2":0,
    "qs:woe_lau":28416743,
    "qs:woe_local":1117401,
    "qs:woe_ver":"7.10.0",
    "wof:lang":[
        "jpn"
    ],
    "wof:name":"\uff13\u4e01\u76ee",
    "wof:placetype":"neighbourhood"
},
  "geometry": {"coordinates":[139.56953799999999,35.321729],"type":"Point"}
}