{
  "type": "Feature",
  "properties": {
    "gn:admin1_code":"24.0",
    "gn:admin2_code":"2112074.0",
    "gn:admin3_code":"4422.0",
    "gn:asciiname":"Izumida",
    "gn:country_code":"JP",
    "gn:dem":28,
    "gn:feature_class":"P",
    "gn:feature_code":"PPL",
    "gn:name":"Izumida",
    "gn:population":0,
    "gn:timezone":"Asia/Tokyo",
    "iso:country":"JP",
    "name:jpn_x_preferred":[
        "\u6cc9\u7530"
    ],
    "name:jpn_x_variant":[
        "\u3044\u305a\u307f\u3060",
        "\u30a4\u30ba\u30df\u30c0"
    ],
    "wof:name":"Izumida",
    "wof:placetype":"locality"
},
  "geometry": {"coordinates":[141.03815,38.41381],"type":"Point"}
}