{
  "type": "Feature",
  "properties": {
    "gn:admin1_code":"19.0",
    "gn:admin2_code":"1848350.0",
    "gn:admin3_code":"14104.0",
    "gn:asciiname":"Kamomecho",
    "gn:country_code":"JP",
    "gn:dem":6,
    "gn:feature_class":"P",
    "gn:feature_code":"PPL",
    "gn:name":"Kamomech\u014d",
    "gn:population":0,
    "gn:timezone":"Asia/Tokyo",
    "iso:country":"JP",
    "name:jpn_x_preferred":[
        "\u304b\u3082\u3081\u753a"
    ],
    "name:jpn_x_variant":[
        "\u304b\u3082\u3081\u3061\u3087\u3046",
        "\u30ab\u30e2\u30e1\u30c1\u30e7\u30a6"
    ],
    "name:und_x_variant":[
        "Kamomech\u014d"
    ],
    "wof:name":"Kamomecho",
    "wof:placetype":"locality"
},
  "geometry": {"coordinates":[139.67493999999999,35.41284],"type":"Point"}
}