{
  "type": "Feature",
  "properties": {
    "gn:admin1_code":"21.0",
    "gn:admin2_code":"7412708.0",
    "gn:admin3_code":"43514.0",
    "gn:asciiname":"Kodonbaru",
    "gn:country_code":"JP",
    "gn:dem":160,
    "gn:feature_class":"P",
    "gn:feature_code":"PPLL",
    "gn:name":"K\u014ddonbaru",
    "gn:population":0,
    "gn:timezone":"Asia/Tokyo",
    "iso:country":"JP",
    "name:jpn_x_preferred":[
        "\u795e\u6bbf\u539f"
    ],
    "name:und_x_variant":[
        "K\u014ddonbaru"
    ],
    "wof:name":"Kodonbaru",
    "wof:placetype":"locality"
},
  "geometry": {"coordinates":[130.90844999999999,32.23141],"type":"Point"}
}