{
  "type": "Feature",
  "properties": {
    "gn:admin1_code":"27",
    "gn:admin2_code":"1852895.0",
    "gn:asciiname":"Osaki",
    "gn:country_code":"JP",
    "gn:dem":36,
    "gn:feature_class":"P",
    "gn:feature_code":"PPL",
    "gn:name":"\u014csaki",
    "gn:population":0,
    "gn:timezone":"Asia/Tokyo",
    "iso:country":"JP",
    "name:jpn_x_preferred":[
        "\u5927\u5d0e"
    ],
    "name:jpn_x_variant":[
        "\u30aa\u30b5\u30ad"
    ],
    "name:und_x_variant":[
        "\u014csaki"
    ],
    "wof:name":"Osaki",
    "wof:placetype":"locality"
},
  "geometry": {"coordinates":[129.74603999999999,33.11362],"type":"Point"}
}