{
  "type": "Feature",
  "properties": {
    "gn:admin1_code":"16.0",
    "gn:admin2_code":"2112822.0",
    "gn:asciiname":"Yotsuyashiki",
    "gn:country_code":"JP",
    "gn:dem":127,
    "gn:feature_class":"P",
    "gn:feature_code":"PPL",
    "gn:name":"Yotsuyashiki",
    "gn:population":0,
    "gn:timezone":"Asia/Tokyo",
    "iso:country":"JP",
    "name:jpn_x_preferred":[
        "\u56db\u30c4\u5c4b\u6577"
    ],
    "name:jpn_x_variant":[
        "\u3088\u3064\u3084\u3057\u304d",
        "\u30e8\u30c4\u30e4\u30b7\u30ad"
    ],
    "wof:name":"Yotsuyashiki",
    "wof:placetype":"locality"
},
  "geometry": {"coordinates":[141.08321999999995,39.44666],"type":"Point"}
}