{
  "type": "Feature",
  "properties": {
    "gn:admin1_code":"7.0",
    "gn:admin2_code":"1851269.0",
    "gn:admin3_code":"40610.0",
    "gn:asciiname":"Noji",
    "gn:country_code":"JP",
    "gn:dem":87,
    "gn:feature_class":"P",
    "gn:feature_code":"PPLL",
    "gn:name":"Noji",
    "gn:population":0,
    "gn:timezone":"Asia/Tokyo",
    "iso:country":"JP",
    "name:jpn_x_preferred":[
        "\u91ce\u5730"
    ],
    "wof:name":"Noji",
    "wof:placetype":"locality"
},
  "geometry": {"coordinates":[130.79483000000002,33.70513],"type":"Point"}
}