{
  "type": "Feature",
  "properties": {
    "iso:country":"JP",
    "name:eng_x_preferred":[
        "Ozato Azaminei"
    ],
    "name:eng_x_variant":[
        "Oozato Ozato Azaminei",
        "Ozato Azaminei"
    ],
    "name:jpn_x_preferred":[
        "\u5b57\u5dba\u4e95"
    ],
    "name:jpn_x_variant":[
        "\u3042\u3056\u307f\u306d\u3044",
        "\u304a\u304a\u3056\u3068 \u3042\u3056\u307f\u306d\u3044",
        "\u5927\u91cc \u5b57\u5dba\u4e95"
    ],
    "name:unk_x_variant":[
        "\u5b57\u5dba\u4e95"
    ],
    "qs:gn_local":0,
    "qs:local_max":362,
    "qs:local_sum":1560,
    "qs:localhoods":11,
    "qs:name":"\u5b57\u5dba\u4e95",
    "qs:name_adm0":"\u65e5\u672c",
    "qs:name_adm1":"\u6c96\u7e04\u770c",
    "qs:name_en":"Ozato Azaminei",
    "qs:name_lau":"\u5927\u91cc",
    "qs:name_local":"\u5357\u57ce\u5e02",
    "qs:photo_max":46,
    "qs:photo_sum":196,
    "qs:placetype":"Suburb",
    "qs:quad_count":18,
    "qs:woe_adm0":23424856,
    "qs:woe_adm1":2345896,
    "qs:woe_adm2":0,
    "qs:woe_lau":1113704,
    "qs:woe_local":28379332,
    "qs:woe_ver":"7.10.0",
    "wof:lang":[
        "jpn"
    ],
    "wof:name":"\u5b57\u5dba\u4e95",
    "wof:placetype":"neighbourhood"
},
  "geometry": {"coordinates":[127.75576599999999,26.20414],"type":"Point"}
}