{
  "type": "Feature",
  "properties": {
    "gn:admin1_code":"25",
    "gn:admin2_code":"1862717.0",
    "gn:admin3_code":"45429.0",
    "gn:asciiname":"Nanatsuyama",
    "gn:country_code":"JP",
    "gn:dem":559,
    "gn:feature_class":"P",
    "gn:feature_code":"PPL",
    "gn:name":"Nanatsuyama",
    "gn:population":0,
    "gn:timezone":"Asia/Tokyo",
    "iso:country":"JP",
    "wof:name":"Nanatsuyama",
    "wof:placetype":"locality"
},
  "geometry": {"coordinates":[131.28333000000001,32.56667],"type":"Point"}
}