{
  "type": "Feature",
  "properties": {
    "gn:country":"JP",
    "gn:fcode":"ADMD",
    "gn:population":0,
    "iso:country":"JP",
    "name:jpn_x_preferred":[
        "\u795e\u5948\u5ddd\u533a"
    ],
    "name:jpn_x_variant":[
        "\u304b\u306a\u304c\u308f\u304f",
        "\u6a2a\u6d5c\u5e02\u795e\u5948\u5ddd\u533a",
        "\u30ab\u30ca\u30ac\u30ef\u30af"
    ],
    "name:und_x_variant":[
        "Kanagawa Ku"
    ],
    "qs:name":"Kanagawa-ku",
    "qs:photos_9r":0,
    "qs:photos_sr":0,
    "qs:pop_sr":"0",
    "wof:name":"Kanagawa-ku",
    "wof:placetype":"localadmin",
    "wof:population":0
},
  "geometry": {"coordinates":[139.61667,35.46667],"type":"Point"}
}