{
  "type": "Feature",
  "properties": {
    "gn:admin1_code":"21.0",
    "gn:admin2_code":"7413150.0",
    "gn:asciiname":"Terajimashita",
    "gn:country_code":"JP",
    "gn:dem":33,
    "gn:feature_class":"P",
    "gn:feature_code":"PPLL",
    "gn:name":"Terajimashita",
    "gn:population":0,
    "gn:timezone":"Asia/Tokyo",
    "iso:country":"JP",
    "name:jpn_x_preferred":[
        "\u5bfa\u5cf6\u4e0b"
    ],
    "name:jpn_x_variant":[
        "\u3066\u3089\u3058\u307e\u3057\u305f",
        "\u30c6\u30e9\u30b8\u30de\u30b7\u30bf"
    ],
    "wof:name":"Terajimashita",
    "wof:placetype":"locality"
},
  "geometry": {"coordinates":[130.68742,33.04728],"type":"Point"}
}