{
  "type": "Feature",
  "properties": {
    "gn:admin1_code":"2.0",
    "gn:admin2_code":"2113122.0",
    "gn:asciiname":"Kamikitate-aramaki",
    "gn:country_code":"JP",
    "gn:dem":39,
    "gn:feature_class":"P",
    "gn:feature_code":"PPL",
    "gn:name":"Kamikitate-aramaki",
    "gn:population":0,
    "gn:timezone":"Asia/Tokyo",
    "iso:country":"JP",
    "name:jpn_x_preferred":[
        "\u4e0a\u5317\u624b\u8352\u5dfb"
    ],
    "name:jpn_x_variant":[
        "\u304b\u307f\u304d\u305f\u3066\u3042\u3089\u307e\u304d",
        "\u30ab\u30df\u30ad\u30bf\u30c6\u30a2\u30e9\u30de\u30ad",
        "\u8352\u5dfb"
    ],
    "name:und_x_variant":[
        "Aramaki"
    ],
    "wof:name":"Kamikitate-aramaki",
    "wof:placetype":"locality"
},
  "geometry": {"coordinates":[140.14399,39.69357],"type":"Point"}
}