{
  "type": "Feature",
  "properties": {
    "gn:admin1_code":"20",
    "gn:admin2_code":"1859127.0",
    "gn:asciiname":"Hiraishi",
    "gn:country_code":"JP",
    "gn:dem":186,
    "gn:feature_class":"P",
    "gn:feature_code":"PPL",
    "gn:name":"Hiraishi",
    "gn:population":0,
    "gn:timezone":"Asia/Tokyo",
    "iso:country":"JP",
    "wof:name":"Hiraishi",
    "wof:placetype":"locality"
},
  "geometry": {"coordinates":[133.53333000000001,33.63333],"type":"Point"}
}