{
  "type": "Feature",
  "properties": {
    "gn:admin1_code":"19.0",
    "gn:admin2_code":"1859635.0",
    "gn:admin3_code":"14131.0",
    "gn:asciiname":"Watarida-shincho",
    "gn:country_code":"JP",
    "gn:dem":1,
    "gn:feature_class":"P",
    "gn:feature_code":"PPL",
    "gn:name":"Watarida-shinch\u014d",
    "gn:population":0,
    "gn:timezone":"Asia/Tokyo",
    "iso:country":"JP",
    "name:jpn_x_preferred":[
        "\u6e21\u7530\u65b0\u753a"
    ],
    "name:und_x_variant":[
        "Watarida-shinch\u014d"
    ],
    "wof:name":"Watarida-shincho",
    "wof:placetype":"locality"
},
  "geometry": {"coordinates":[139.69978999999998,35.51976],"type":"Point"}
}