{
  "type": "Feature",
  "properties": {
    "gn:admin1_code":"42.0",
    "gn:admin2_code":"1855873.0",
    "gn:admin3_code":"16323.0",
    "gn:asciiname":"Oshozu",
    "gn:country_code":"JP",
    "gn:dem":89,
    "gn:feature_class":"P",
    "gn:feature_code":"PPL",
    "gn:name":"\u014csh\u014dzu",
    "gn:population":0,
    "gn:timezone":"Asia/Tokyo",
    "iso:country":"JP",
    "name:jpn_x_preferred":[
        "\u5927\u6e05\u6c34"
    ],
    "name:und_x_variant":[
        "\u014csh\u014dzu"
    ],
    "wof:name":"Oshozu",
    "wof:placetype":"locality"
},
  "geometry": {"coordinates":[137.30080000000001,36.64999],"type":"Point"}
}