{
  "type": "Feature",
  "properties": {
    "gn:admin1_code":"4.0",
    "gn:admin2_code":"1859468.0",
    "gn:asciiname":"Sogyu",
    "gn:country_code":"JP",
    "gn:dem":88,
    "gn:feature_class":"P",
    "gn:feature_code":"PPL",
    "gn:name":"S\u014dgy\u016b",
    "gn:population":0,
    "gn:timezone":"Asia/Tokyo",
    "iso:country":"JP",
    "name:jpn_x_preferred":[
        "\u8349\u725b"
    ],
    "name:jpn_x_variant":[
        "\u305d\u3046\u304e\u3085\u3046",
        "\u30bd\u30a6\u30ae\u30e5\u30a6"
    ],
    "name:und_x_variant":[
        "S\u014dgy\u016b"
    ],
    "wof:name":"Sogyu",
    "wof:placetype":"locality"
},
  "geometry": {"coordinates":[139.95158999999998,35.28031],"type":"Point"}
}