{
  "type": "Feature",
  "properties": {
    "gn:admin1_code":"7.0",
    "gn:admin2_code":"1856443.0",
    "gn:asciiname":"Koboshibaru",
    "gn:country_code":"JP",
    "gn:dem":3,
    "gn:feature_class":"P",
    "gn:feature_code":"PPLL",
    "gn:name":"K\u014dboshibaru",
    "gn:population":0,
    "gn:timezone":"Asia/Tokyo",
    "iso:country":"JP",
    "name:jpn_x_preferred":[
        "\u5149\u661f\u539f"
    ],
    "name:und_x_variant":[
        "K\u014dboshibaru"
    ],
    "wof:name":"Koboshibaru",
    "wof:placetype":"locality"
},
  "geometry": {"coordinates":[130.51403999999999,33.85438],"type":"Point"}
}