{
  "type": "Feature",
  "properties": {
    "gn:admin1_code":"13.0",
    "gn:admin2_code":"7370813.0",
    "gn:asciiname":"Mizoguchi",
    "gn:country_code":"JP",
    "gn:dem":170,
    "gn:feature_class":"P",
    "gn:feature_code":"PPL",
    "gn:name":"Mizoguchi",
    "gn:population":0,
    "gn:timezone":"Asia/Tokyo",
    "iso:country":"JP",
    "name:jpn_x_preferred":[
        "\u6e9d\u53e3"
    ],
    "wof:name":"Mizoguchi",
    "wof:placetype":"locality"
},
  "geometry": {"coordinates":[135.17359999999999,34.93828],"type":"Point"}
}