{
  "type": "Feature",
  "properties": {
    "gn:admin1_code":"7.0",
    "gn:admin2_code":"7406950.0",
    "gn:admin3_code":"40621.0",
    "gn:asciiname":"Yobaru",
    "gn:country_code":"JP",
    "gn:dem":3,
    "gn:feature_class":"P",
    "gn:feature_code":"PPL",
    "gn:name":"Yobaru",
    "gn:population":0,
    "gn:timezone":"Asia/Tokyo",
    "iso:country":"JP",
    "name:jpn_x_preferred":[
        "\u4e0e\u539f"
    ],
    "wof:name":"Yobaru",
    "wof:placetype":"locality"
},
  "geometry": {"coordinates":[130.98327,33.75715],"type":"Point"}
}