{
  "type": "Feature",
  "properties": {
    "gn:admin1_code":"19.0",
    "gn:admin2_code":"1848350.0",
    "gn:admin3_code":"14103.0",
    "gn:asciiname":"Minatomirai",
    "gn:country_code":"JP",
    "gn:dem":3,
    "gn:feature_class":"P",
    "gn:feature_code":"PPL",
    "gn:name":"Minatomirai",
    "gn:population":0,
    "gn:timezone":"Asia/Tokyo",
    "iso:country":"JP",
    "name:jpn_x_preferred":[
        "\u307f\u306a\u3068\u307f\u3089\u3044"
    ],
    "name:jpn_x_variant":[
        "\u30df\u30ca\u30c8\u30df\u30e9\u30a4"
    ],
    "wof:name":"Minatomirai",
    "wof:placetype":"locality"
},
  "geometry": {"coordinates":[139.63030000000001,35.45957999999999],"type":"Point"}
}