{
  "type": "Feature",
  "properties": {
    "iso:country":"JP",
    "qs:name":"\u8c61\u6f5f\u753a",
    "qs:name_adm0":"\u65e5\u672c",
    "qs:name_adm1":"\u79cb\u7530\u770c",
    "qs:photos":1,
    "qs:photos_1k":1,
    "qs:photos_9k":1,
    "qs:photos_9r":2,
    "qs:photos_all":68,
    "qs:photos_sr":1,
    "qs:placetype":"LocalAdmin",
    "qs:pop_sr":"0",
    "wof:name":"\u8c61\u6f5f\u753a",
    "wof:placetype":"localadmin"
},
  "geometry": {"coordinates":[139.90067400000001,39.210404],"type":"Point"}
}