{
  "type": "Feature",
  "properties": {
    "gn:admin1_code":"21.0",
    "gn:admin2_code":"1859488.0",
    "gn:asciiname":"Matsushima",
    "gn:country_code":"JP",
    "gn:dem":89,
    "gn:feature_class":"P",
    "gn:feature_code":"PPLL",
    "gn:name":"Matsushima",
    "gn:population":0,
    "gn:timezone":"Asia/Tokyo",
    "iso:country":"JP",
    "name:aze_x_preferred":[
        "Matsu\u015fima adalar\u0131"
    ],
    "name:bel_x_preferred":[
        "\u041c\u0430\u0446\u0443\u0441\u0456\u043c\u0430"
    ],
    "name:ceb_x_preferred":[
        "Matsushima Gunt\u014d"
    ],
    "name:ces_x_preferred":[
        "Macu\u0161ima"
    ],
    "name:eus_x_preferred":[
        "Matsushima"
    ],
    "name:fra_x_preferred":[
        "Matsushima"
    ],
    "name:heb_x_preferred":[
        "\u05de\u05e6\u05d5\u05e9\u05d9\u05de\u05d4"
    ],
    "name:hun_x_preferred":[
        "Macusima"
    ],
    "name:ind_x_preferred":[
        "Matsushima"
    ],
    "name:jpn_x_preferred":[
        "\u677e\u5cf6"
    ],
    "name:jpn_x_variant":[
        "\u307e\u3064\u3057\u307e",
        "\u30de\u30c4\u30b7\u30de"
    ],
    "name:kor_x_preferred":[
        "\ub9c8\uc4f0\uc2dc\ub9c8\uc12c"
    ],
    "name:lit_x_preferred":[
        "Macu\u0161ima"
    ],
    "name:por_x_preferred":[
        "Matsushima"
    ],
    "name:rus_x_preferred":[
        "\u041c\u0430\u0446\u0443\u0441\u0438\u043c\u0430"
    ],
    "name:slk_x_preferred":[
        "Macu\u0161ima"
    ],
    "name:sun_x_preferred":[
        "Matsushima"
    ],
    "name:tur_x_preferred":[
        "Matsushima"
    ],
    "name:ukr_x_preferred":[
        "\u041c\u0430\u0446\u0443\u0441\u0456\u043c\u0430"
    ],
    "wof:name":"Matsushima",
    "wof:placetype":"locality"
},
  "geometry": {"coordinates":[130.84968000000001,32.9756],"type":"Point"}
}