{
  "type": "Feature",
  "properties": {
    "gn:admin1_code":"21.0",
    "gn:admin2_code":"1859488.0",
    "gn:asciiname":"Matsushima",
    "gn:country_code":"JP",
    "gn:dem":89,
    "gn:feature_class":"P",
    "gn:feature_code":"PPLL",
    "gn:name":"Matsushima",
    "gn:population":0,
    "gn:timezone":"Asia/Tokyo",
    "iso:country":"JP",
    "name:jpn_x_preferred":[
        "\u677e\u5cf6"
    ],
    "name:jpn_x_variant":[
        "\u307e\u3064\u3057\u307e",
        "\u30de\u30c4\u30b7\u30de"
    ],
    "wof:name":"Matsushima",
    "wof:placetype":"locality"
},
  "geometry": {"coordinates":[130.84968000000001,32.9756],"type":"Point"}
}