{
  "type": "Feature",
  "properties": {
    "gn:admin1_code":"08",
    "gn:admin2_code":"2112535.0",
    "gn:asciiname":"Taira-shimotakaku",
    "gn:country_code":"JP",
    "gn:dem":4,
    "gn:feature_class":"P",
    "gn:feature_code":"PPL",
    "gn:name":"Taira-shimotakaku",
    "gn:population":0,
    "gn:timezone":"Asia/Tokyo",
    "iso:country":"JP",
    "name:jpn_x_preferred":[
        "\u5e73\u4e0b\u9ad8\u4e45"
    ],
    "name:und_x_variant":[
        "Shimo-takaku"
    ],
    "wof:name":"Taira-shimotakaku",
    "wof:placetype":"locality"
},
  "geometry": {"coordinates":[140.95516000000001,37.0288],"type":"Point"}
}