{
  "type": "Feature",
  "properties": {
    "gn:admin1_code":"11",
    "gn:admin2_code":"1858288.0",
    "gn:asciiname":"Yutaka",
    "gn:country_code":"JP",
    "gn:dem":40,
    "gn:feature_class":"P",
    "gn:feature_code":"PPL",
    "gn:name":"Yutaka",
    "gn:population":0,
    "gn:timezone":"Asia/Tokyo",
    "iso:country":"JP",
    "name:pol_x_preferred":[
        "Yutaka"
    ],
    "wof:name":"Yutaka",
    "wof:placetype":"locality"
},
  "geometry": {"coordinates":[132.86301,34.17388],"type":"Point"}
}