{
  "type": "Feature",
  "properties": {
    "gn:admin1_code":"4.0",
    "gn:admin2_code":"7465521.0",
    "gn:asciiname":"Akashi",
    "gn:country_code":"JP",
    "gn:dem":19,
    "gn:feature_class":"P",
    "gn:feature_code":"PPL",
    "gn:name":"Akashi",
    "gn:population":0,
    "gn:timezone":"Asia/Tokyo",
    "iso:country":"JP",
    "name:jpn_x_preferred":[
        "\u660e\u77f3"
    ],
    "name:jpn_x_variant":[
        "\u3042\u304b\u3057",
        "\u30a2\u30ab\u30b7"
    ],
    "wof:name":"Akashi",
    "wof:placetype":"locality"
},
  "geometry": {"coordinates":[139.89913999999999,35.02466],"type":"Point"}
}