{
  "type": "Feature",
  "properties": {
    "gn:admin1_code":"12.0",
    "gn:admin2_code":"7428120.0",
    "gn:admin3_code":"1429.0",
    "gn:asciiname":"Futamata",
    "gn:country_code":"JP",
    "gn:dem":98,
    "gn:feature_class":"P",
    "gn:feature_code":"PPL",
    "gn:name":"Futamata",
    "gn:population":0,
    "gn:timezone":"Asia/Tokyo",
    "iso:country":"JP",
    "wof:name":"Futamata",
    "wof:placetype":"locality"
},
  "geometry": {"coordinates":[141.90000000000001,43.03333],"type":"Point"}
}