{
  "type": "Feature",
  "properties": {
    "gn:admin1_code":"19.0",
    "gn:admin2_code":"1847999.0",
    "gn:asciiname":"Yotsuya",
    "gn:country_code":"JP",
    "gn:dem":26,
    "gn:feature_class":"P",
    "gn:feature_code":"PPL",
    "gn:name":"Yotsuya",
    "gn:population":0,
    "gn:timezone":"Asia/Tokyo",
    "iso:country":"JP",
    "name:fas_x_preferred":[
        "\u06cc\u0648\u062a\u0633\u0648\u06cc\u0627"
    ],
    "name:fra_x_preferred":[
        "Yotsuya"
    ],
    "name:jpn_x_preferred":[
        "\u56db\u30c4\u8c37"
    ],
    "wof:name":"Yotsuya",
    "wof:placetype":"locality"
},
  "geometry": {"coordinates":[139.38657000000001,35.47444],"type":"Point"}
}