{
  "type": "Feature",
  "properties": {
    "gn:admin1_code":"37.0",
    "gn:admin2_code":"1854900.0",
    "gn:asciiname":"Sotohara",
    "gn:country_code":"JP",
    "gn:dem":20,
    "gn:feature_class":"P",
    "gn:feature_code":"PPLL",
    "gn:name":"Sotohara",
    "gn:population":0,
    "gn:timezone":"Asia/Tokyo",
    "iso:country":"JP",
    "name:jpn_x_preferred":[
        "\u5916\u539f\u3000"
    ],
    "name:und_x_variant":[
        "Sodohara"
    ],
    "wof:name":"Sotohara",
    "wof:placetype":"locality"
},
  "geometry": {"coordinates":[138.88478000000001,35.09117],"type":"Point"}
}