{
  "type": "Feature",
  "properties": {
    "gn:admin1_code":"21.0",
    "gn:admin2_code":"1850744.0",
    "gn:admin3_code":"43367.0",
    "gn:asciiname":"Shodera",
    "gn:country_code":"JP",
    "gn:dem":72,
    "gn:feature_class":"P",
    "gn:feature_code":"PPLL",
    "gn:name":"Sh\u014ddera",
    "gn:population":0,
    "gn:timezone":"Asia/Tokyo",
    "iso:country":"JP",
    "name:jpn_x_preferred":[
        "\u5e84\u5bfa"
    ],
    "name:jpn_x_variant":[
        "\u3057\u3087\u3046\u3067\u3089",
        "\u30b7\u30e7\u30a6\u30c7\u30e9"
    ],
    "name:und_x_variant":[
        "Sh\u014ddera"
    ],
    "wof:name":"Shodera",
    "wof:placetype":"locality"
},
  "geometry": {"coordinates":[130.53478999999999,33.03527],"type":"Point"}
}