{
  "type": "Feature",
  "properties": {
    "gn:admin1_code":"21.0",
    "gn:admin2_code":"7412706.0",
    "gn:admin3_code":"43447.0",
    "gn:asciiname":"Tamaribuchi",
    "gn:country_code":"JP",
    "gn:dem":573,
    "gn:feature_class":"P",
    "gn:feature_code":"PPLL",
    "gn:name":"Tamaribuchi",
    "gn:population":0,
    "gn:timezone":"Asia/Tokyo",
    "iso:country":"JP",
    "name:jpn_x_preferred":[
        "\u6e9c\u6df5"
    ],
    "name:jpn_x_variant":[
        "\u305f\u307e\u308a\u3076\u3061",
        "\u30bf\u30de\u30ea\u30d6\u30c1"
    ],
    "wof:name":"Tamaribuchi",
    "wof:placetype":"locality"
},
  "geometry": {"coordinates":[131.17156,32.74424],"type":"Point"}
}