{
  "type": "Feature",
  "properties": {
    "gn:admin1_code":"21.0",
    "gn:admin2_code":"7412706.0",
    "gn:admin3_code":"43441.0",
    "gn:asciiname":"Yashiki",
    "gn:country_code":"JP",
    "gn:dem":300,
    "gn:feature_class":"P",
    "gn:feature_code":"PPLL",
    "gn:name":"Yashiki",
    "gn:population":0,
    "gn:timezone":"Asia/Tokyo",
    "iso:country":"JP",
    "name:jpn_x_preferred":[
        "\u5c4b\u6577"
    ],
    "name:jpn_x_variant":[
        "\u3084\u3057\u304d",
        "\u30e4\u30b7\u30ad"
    ],
    "wof:name":"Yashiki",
    "wof:placetype":"locality"
},
  "geometry": {"coordinates":[130.86247,32.74716],"type":"Point"}
}