{
  "type": "Feature",
  "properties": {
    "gn:admin1_code":"31",
    "gn:admin2_code":"1859989.0",
    "gn:asciiname":"Yokoshima",
    "gn:country_code":"JP",
    "gn:dem":5,
    "gn:feature_class":"P",
    "gn:feature_code":"PPL",
    "gn:name":"Yokoshima",
    "gn:population":0,
    "gn:timezone":"Asia/Tokyo",
    "iso:country":"JP",
    "name:jpn_x_preferred":[
        "\u6a2a\u5cf6"
    ],
    "name:kor_x_preferred":[
        "\uc694\ucf54\uc2dc\ub9c8"
    ],
    "wof:name":"Yokoshima",
    "wof:placetype":"locality"
},
  "geometry": {"coordinates":[133.52271000000002,34.48692],"type":"Point"}
}