{
  "type": "Feature",
  "properties": {
    "iso:country":"JP",
    "qs:name":"\uff12\u4e01\u76ee",
    "qs:name_adm0":"\u65e5\u672c",
    "qs:name_adm1":"\u6771\u4eac\u90fd",
    "qs:photos":365,
    "qs:photos_1k":74,
    "qs:photos_9k":2,
    "qs:photos_9r":5,
    "qs:photos_all":365,
    "qs:photos_sr":6,
    "qs:placetype":"Suburb",
    "qs:pop_sr":"0",
    "wof:name":"\uff12\u4e01\u76ee",
    "wof:placetype":"neighbourhood"
},
  "geometry": {"coordinates":[139.80018100000001,35.764381],"type":"Point"}
}