{
  "type": "Feature",
  "properties": {
    "gn:admin1_code":"29",
    "gn:admin2_code":"1850218.0",
    "gn:asciiname":"Mizusawa",
    "gn:country_code":"JP",
    "gn:dem":164,
    "gn:feature_class":"P",
    "gn:feature_code":"PPL",
    "gn:name":"Mizusawa",
    "gn:population":0,
    "gn:timezone":"Asia/Tokyo",
    "iso:country":"JP",
    "name:deu_x_preferred":[
        "Mizusawa"
    ],
    "name:jpn_x_preferred":[
        "\u6c34\u6ca2"
    ],
    "name:mlg_x_preferred":[
        "Mizusawa"
    ],
    "wof:name":"Mizusawa",
    "wof:placetype":"locality"
},
  "geometry": {"coordinates":[138.71388999999999,37.07414],"type":"Point"}
}