{
  "type": "Feature",
  "properties": {
    "iso:country":"JP",
    "name:eng_x_preferred":[
        "Nakatsu 4 Chome"
    ],
    "name:eng_x_variant":[
        "Nakatsu 4 Choume",
        "Nakatsu 4 Chome"
    ],
    "name:jpn_x_preferred":[
        "\uff14\u4e01\u76ee"
    ],
    "name:jpn_x_variant":[
        "\u306a\u304b\u3064 \uff14\u3061\u3087\u3046\u3081",
        "\u4e2d\u6d25 \uff14\u4e01\u76ee",
        "\uff14\u3061\u3087\u3046\u3081"
    ],
    "qs:gn_local":0,
    "qs:local_max":5466,
    "qs:local_sum":82256,
    "qs:localhoods":141,
    "qs:name":"\uff14\u4e01\u76ee",
    "qs:name_adm0":"\u65e5\u672c",
    "qs:name_adm1":"\u5927\u962a\u5e9c",
    "qs:name_adm2":"\u5317\u533a",
    "qs:name_en":"Nakatsu 4 Chome",
    "qs:name_lau":"\u4e2d\u6d25",
    "qs:name_local":"\u5927\u962a\u5e02",
    "qs:photo_max":75,
    "qs:photo_sum":737,
    "qs:placetype":"Suburb",
    "qs:quad_count":23,
    "qs:woe_adm0":23424856,
    "qs:woe_adm1":2345881,
    "qs:woe_adm2":15015521,
    "qs:woe_lau":28457603,
    "qs:woe_local":15015370,
    "qs:woe_ver":"7.10.0",
    "wof:lang":[
        "jpn"
    ],
    "wof:name":"\uff14\u4e01\u76ee",
    "wof:placetype":"neighbourhood"
},
  "geometry": {"coordinates":[135.49833899999999,34.711038],"type":"Point"}
}