{
  "type": "Feature",
  "properties": {
    "gn:admin1_code":"4.0",
    "gn:admin2_code":"1861964.0",
    "gn:asciiname":"Baraki",
    "gn:country_code":"JP",
    "gn:dem":1,
    "gn:feature_class":"P",
    "gn:feature_code":"PPL",
    "gn:name":"Baraki",
    "gn:population":0,
    "gn:timezone":"Asia/Tokyo",
    "iso:country":"JP",
    "name:jpn_x_preferred":[
        "\u539f\u6728"
    ],
    "name:jpn_x_variant":[
        "\u3070\u3089\u304d"
    ],
    "wof:name":"Baraki",
    "wof:placetype":"locality"
},
  "geometry": {"coordinates":[139.95116999999999,35.69798],"type":"Point"}
}