{
  "type": "Feature",
  "properties": {
    "gn:admin1_code":"4.0",
    "gn:admin2_code":"1861964.0",
    "gn:asciiname":"Baraki",
    "gn:country_code":"JP",
    "gn:dem":1,
    "gn:feature_class":"P",
    "gn:feature_code":"PPL",
    "gn:name":"Baraki",
    "gn:population":0,
    "gn:timezone":"Asia/Tokyo",
    "iso:country":"JP",
    "name:ceb_x_preferred":[
        "Baraki"
    ],
    "name:deu_x_preferred":[
        "Baraki"
    ],
    "name:fra_x_preferred":[
        "Baraki"
    ],
    "name:jpn_x_preferred":[
        "\u539f\u6728"
    ],
    "name:jpn_x_variant":[
        "\u3070\u3089\u304d"
    ],
    "name:msa_x_preferred":[
        "Baraki"
    ],
    "name:pol_x_preferred":[
        "Baraki"
    ],
    "name:ron_x_preferred":[
        "Baraki"
    ],
    "name:rus_x_preferred":[
        "\u0411\u0430\u0440\u0430\u043a\u0438"
    ],
    "name:swe_x_preferred":[
        "Baraki"
    ],
    "name:ukr_x_preferred":[
        "\u0411\u0430\u0440\u0430\u043a\u0456"
    ],
    "name:wol_x_preferred":[
        "Baraki"
    ],
    "wof:name":"Baraki",
    "wof:placetype":"locality"
},
  "geometry": {"coordinates":[139.95116999999999,35.69798],"type":"Point"}
}