{
  "type": "Feature",
  "properties": {
    "gn:admin1_code":"22.0",
    "gn:admin2_code":"1851574.0",
    "gn:admin3_code":"26365.0",
    "gn:asciiname":"Yubune",
    "gn:country_code":"JP",
    "gn:dem":261,
    "gn:feature_class":"P",
    "gn:feature_code":"PPL",
    "gn:name":"Yubune",
    "gn:population":0,
    "gn:timezone":"Asia/Tokyo",
    "iso:country":"JP",
    "name:jpn_x_preferred":[
        "\u6e6f\u8239"
    ],
    "wof:name":"Yubune",
    "wof:placetype":"locality"
},
  "geometry": {"coordinates":[135.94631000000001,34.83143],"type":"Point"}
}