{
  "type": "Feature",
  "properties": {
    "gn:admin1_code":"10.0",
    "gn:admin2_code":"1853626.0",
    "gn:asciiname":"Narizukacho",
    "gn:country_code":"JP",
    "gn:dem":68,
    "gn:feature_class":"P",
    "gn:feature_code":"PPL",
    "gn:name":"Narizukach\u014d",
    "gn:population":0,
    "gn:timezone":"Asia/Tokyo",
    "iso:country":"JP",
    "name:jpn_x_preferred":[
        "\u6210\u585a\u753a"
    ],
    "name:und_x_variant":[
        "Narizukach\u014d"
    ],
    "wof:name":"Narizukacho",
    "wof:placetype":"locality"
},
  "geometry": {"coordinates":[139.34483999999998,36.33662],"type":"Point"}
}