{
  "type": "Feature",
  "properties": {
    "gn:admin1_code":"2.0",
    "gn:admin2_code":"2113122.0",
    "gn:asciiname":"Hirakata",
    "gn:country_code":"JP",
    "gn:dem":41,
    "gn:feature_class":"P",
    "gn:feature_code":"PPL",
    "gn:name":"Hirakata",
    "gn:population":0,
    "gn:timezone":"Asia/Tokyo",
    "iso:country":"JP",
    "name:jpn_x_preferred":[
        "\u5e73\u5f62"
    ],
    "name:jpn_x_variant":[
        "\u3072\u3089\u304b\u305f",
        "\u30d2\u30e9\u30ab\u30bf"
    ],
    "wof:name":"Hirakata",
    "wof:placetype":"locality"
},
  "geometry": {"coordinates":[140.21039999999999,39.73495],"type":"Point"}
}