{
  "type": "Feature",
  "properties": {
    "gn:admin1_code":"27.0",
    "gn:admin2_code":"7418805.0",
    "gn:asciiname":"Usuka",
    "gn:country_code":"JP",
    "gn:dem":6,
    "gn:feature_class":"P",
    "gn:feature_code":"PPLL",
    "gn:name":"Usuka",
    "gn:population":0,
    "gn:timezone":"Asia/Tokyo",
    "iso:country":"JP",
    "name:jpn_x_preferred":[
        "\u8584\u9999"
    ],
    "name:swa_x_preferred":[
        "Usuka"
    ],
    "wof:name":"Usuka",
    "wof:placetype":"locality"
},
  "geometry": {"coordinates":[129.54241999999999,33.37404],"type":"Point"}
}