{
  "type": "Feature",
  "properties": {
    "gn:admin1_code":"47",
    "gn:admin2_code":"1858371.0",
    "gn:admin3_code":"47308.0",
    "gn:asciiname":"Narishido",
    "gn:country_code":"JP",
    "gn:dem":118,
    "gn:feature_class":"P",
    "gn:feature_code":"PPL",
    "gn:name":"Narishid\u014d",
    "gn:population":0,
    "gn:timezone":"Asia/Tokyo",
    "iso:country":"JP",
    "name:jpn_x_preferred":[
        "\u6210\u5fd7\u5802"
    ],
    "name:jpn_x_variant":[
        "\u306a\u308a\u3057\u3069\u3046"
    ],
    "name:und_x_variant":[
        "Narishid\u014d"
    ],
    "wof:name":"Narishido",
    "wof:placetype":"locality"
},
  "geometry": {"coordinates":[127.95574000000001,26.64661],"type":"Point"}
}