{
  "type": "Feature",
  "properties": {
    "gn:admin1_code":"19.0",
    "gn:admin2_code":"1848350.0",
    "gn:admin3_code":"14101.0",
    "gn:asciiname":"Motomiya",
    "gn:country_code":"JP",
    "gn:dem":1,
    "gn:feature_class":"P",
    "gn:feature_code":"PPL",
    "gn:name":"Motomiya",
    "gn:population":0,
    "gn:timezone":"Asia/Tokyo",
    "iso:country":"JP",
    "name:jpn_x_preferred":[
        "\u5143\u5bae"
    ],
    "wof:name":"Motomiya",
    "wof:placetype":"locality"
},
  "geometry": {"coordinates":[139.68174999999999,35.52143],"type":"Point"}
}