{
  "type": "Feature",
  "properties": {
    "gn:admin1_code":"21.0",
    "gn:admin2_code":"7413151.0",
    "gn:asciiname":"Funae",
    "gn:country_code":"JP",
    "gn:dem":6,
    "gn:feature_class":"P",
    "gn:feature_code":"PPLL",
    "gn:name":"Funae",
    "gn:population":0,
    "gn:timezone":"Asia/Tokyo",
    "iso:country":"JP",
    "name:jpn_x_preferred":[
        "\u8239\u6c5f"
    ],
    "name:jpn_x_variant":[
        "\u3075\u306a\u3048",
        "\u30d5\u30ca\u30a8"
    ],
    "wof:name":"Funae",
    "wof:placetype":"locality"
},
  "geometry": {"coordinates":[130.44191999999998,32.60346],"type":"Point"}
}