{
  "type": "Feature",
  "properties": {
    "gn:admin1_code":"34.0",
    "gn:admin2_code":"1864112.0",
    "gn:asciiname":"Ishii",
    "gn:country_code":"JP",
    "gn:dem":10,
    "gn:feature_class":"P",
    "gn:feature_code":"PPLL",
    "gn:name":"Ishii",
    "gn:population":0,
    "gn:timezone":"Asia/Tokyo",
    "iso:country":"JP",
    "name:jpn_x_preferred":[
        "\u77f3\u4e95"
    ],
    "name:mlg_x_preferred":[
        "Ishii"
    ],
    "wof:name":"Ishii",
    "wof:placetype":"locality"
},
  "geometry": {"coordinates":[139.56521000000001,35.83991],"type":"Point"}
}