{
  "type": "Feature",
  "properties": {
    "gn:admin1_code":"12.0",
    "gn:admin2_code":"7428118.0",
    "gn:admin3_code":"1575.0",
    "gn:asciiname":"Benkei",
    "gn:cc2":"JP",
    "gn:country_code":"JP",
    "gn:dem":622,
    "gn:feature_class":"P",
    "gn:feature_code":"PPL",
    "gn:name":"Benkei",
    "gn:population":0,
    "gn:timezone":"Asia/Tokyo",
    "iso:country":"JP",
    "name:und_x_variant":[
        "K\u014dkei",
        "I\u014dyama",
        "Iozan",
        "Benkei"
    ],
    "wof:name":"Benkei",
    "wof:placetype":"locality"
},
  "geometry": {"coordinates":[141.03333000000001,42.53333],"type":"Point"}
}