{
  "type": "Feature",
  "properties": {
    "gn:admin1_code":"12.0",
    "gn:admin2_code":"7428118.0",
    "gn:admin3_code":"1575.0",
    "gn:asciiname":"Benkei",
    "gn:cc2":"JP",
    "gn:country_code":"JP",
    "gn:dem":622,
    "gn:feature_class":"P",
    "gn:feature_code":"PPL",
    "gn:name":"Benkei",
    "gn:population":0,
    "gn:timezone":"Asia/Tokyo",
    "iso:country":"JP",
    "name:deu_x_preferred":[
        "Musashib\u014d Benkei"
    ],
    "name:fas_x_preferred":[
        "\u0628\u0646\u06a9\u06cc"
    ],
    "name:fra_x_preferred":[
        "Benkei"
    ],
    "name:ind_x_preferred":[
        "Musashib\u014d Benkei"
    ],
    "name:jpn_x_preferred":[
        "\u6b66\u8535\u574a\u5f01\u6176"
    ],
    "name:kor_x_preferred":[
        "\ubb34\uc0ac\uc2dc\ubcf4 \ubca4\ucf00\uc774"
    ],
    "name:rus_x_preferred":[
        "\u0411\u044d\u043d\u043a\u044d\u0439"
    ],
    "name:sqi_x_preferred":[
        "Benkei"
    ],
    "name:swe_x_preferred":[
        "Benkei"
    ],
    "name:tha_x_preferred":[
        "\u0e40\u0e1a\u0e47\u0e07\u0e40\u0e01"
    ],
    "name:tur_x_preferred":[
        "Benkei"
    ],
    "name:ukr_x_preferred":[
        "\u0411\u0435\u043d\u043a\u0435\u0439"
    ],
    "name:und_x_variant":[
        "K\u014dkei",
        "I\u014dyama",
        "Iozan"
    ],
    "name:vie_x_preferred":[
        "Benkei"
    ],
    "name:wuu_x_preferred":[
        "\u6b66\u85cf\u574a\u5f01\u5e86"
    ],
    "name:zho_x_preferred":[
        "\u6b66\u85cf\u574a\u5f01\u6176"
    ],
    "wof:name":"Benkei",
    "wof:placetype":"locality"
},
  "geometry": {"coordinates":[141.03333000000001,42.53333],"type":"Point"}
}