{
  "type": "Feature",
  "properties": {
    "gn:admin1_code":"4.0",
    "gn:admin2_code":"1864901.0",
    "gn:admin3_code":"12463.0",
    "gn:asciiname":"Kawamuko",
    "gn:country_code":"JP",
    "gn:dem":9,
    "gn:feature_class":"P",
    "gn:feature_code":"PPLL",
    "gn:name":"Kawamuk\u014d",
    "gn:population":0,
    "gn:timezone":"Asia/Tokyo",
    "iso:country":"JP",
    "name:jpn_x_preferred":[
        "\u5ddd\u5411"
    ],
    "name:jpn_x_variant":[
        "\u304b\u308f\u3080\u3053\u3046",
        "\u30ab\u30ef\u30e0\u30b3\u30a6"
    ],
    "name:und_x_variant":[
        "Kawamuk\u014d"
    ],
    "wof:name":"Kawamuko",
    "wof:placetype":"locality"
},
  "geometry": {"coordinates":[139.83962,35.1362],"type":"Point"}
}