{
  "type": "Feature",
  "properties": {
    "gn:country":"JP",
    "gn:fcode":"ADM3",
    "gn:population":0,
    "iso:country":"JP",
    "name:eng_x_preferred":[
        "Yugawa"
    ],
    "name:eng_x_variant":[
        "Yugawa-mura"
    ],
    "name:jpn_x_preferred":[
        "\u6e6f\u5ddd\u6751"
    ],
    "name:jpn_x_variant":[
        "\u3086\u304c\u308f\u3080\u3089"
    ],
    "name:und_x_variant":[
        "Yugawa Mura"
    ],
    "qs:name":"Yugawa-mura",
    "qs:photos_9r":0,
    "qs:photos_sr":0,
    "qs:pop_sr":"0",
    "wof:name":"Yugawa",
    "wof:placetype":"localadmin",
    "wof:population":0
},
  "geometry": {"coordinates":[139.88227000000001,37.56728],"type":"Point"}
}