{
  "type": "Feature",
  "properties": {
    "gn:admin1_code":"41",
    "gn:admin2_code":"1849887.0",
    "gn:asciiname":"Shikano",
    "gn:country_code":"JP",
    "gn:dem":37,
    "gn:feature_class":"P",
    "gn:feature_code":"PPL",
    "gn:name":"Shikano",
    "gn:population":0,
    "gn:timezone":"Asia/Tokyo",
    "iso:country":"JP",
    "wof:name":"Shikano",
    "wof:placetype":"locality"
},
  "geometry": {"coordinates":[134.06666999999999,35.46667],"type":"Point"}
}