{
  "type": "Feature",
  "properties": {
    "gn:admin1_code":"02",
    "gn:admin2_code":"2127468.0",
    "gn:admin3_code":"5348.0",
    "gn:asciiname":"Kamaya",
    "gn:country_code":"JP",
    "gn:dem":6,
    "gn:feature_class":"P",
    "gn:feature_code":"PPL",
    "gn:name":"Kamaya",
    "gn:population":0,
    "gn:timezone":"Asia/Tokyo",
    "iso:country":"JP",
    "name:jpn_x_preferred":[
        "\u91dc\u8c37"
    ],
    "name:und_x_variant":[
        "Kamaishi",
        "Kamaya"
    ],
    "wof:name":"Kamaya",
    "wof:placetype":"locality"
},
  "geometry": {"coordinates":[139.96666999999999,40.10245],"type":"Point"}
}