{
  "type": "Feature",
  "properties": {
    "gn:admin1_code":"37.0",
    "gn:admin2_code":"1851714.0",
    "gn:admin3_code":"22103.0",
    "gn:asciiname":"Shin'eicho",
    "gn:country_code":"JP",
    "gn:dem":16,
    "gn:feature_class":"P",
    "gn:feature_code":"PPLL",
    "gn:name":"Shin\u2019eich\u014d",
    "gn:population":0,
    "gn:timezone":"Asia/Tokyo",
    "iso:country":"JP",
    "name:jpn_x_preferred":[
        "\u65b0\u6804\u753a"
    ],
    "name:und_x_variant":[
        "Shin\u2019eich\u014d"
    ],
    "wof:name":"Shin'eicho",
    "wof:placetype":"locality"
},
  "geometry": {"coordinates":[138.61982,35.12582],"type":"Point"}
}