{
  "type": "Feature",
  "properties": {
    "gn:admin1_code":"21.0",
    "gn:admin2_code":"1865168.0",
    "gn:asciiname":"Ichibu",
    "gn:country_code":"JP",
    "gn:dem":15,
    "gn:feature_class":"P",
    "gn:feature_code":"PPL",
    "gn:name":"Ichibu",
    "gn:population":0,
    "gn:timezone":"Asia/Tokyo",
    "iso:country":"JP",
    "name:jpn_x_preferred":[
        "\u4e00\u90e8"
    ],
    "name:jpn_x_variant":[
        "\u3044\u3061\u3076",
        "\u30a4\u30c1\u30d6"
    ],
    "wof:name":"Ichibu",
    "wof:placetype":"locality"
},
  "geometry": {"coordinates":[130.45293999999998,32.96908],"type":"Point"}
}