{
  "type": "Feature",
  "properties": {
    "gn:admin1_code":"7.0",
    "gn:admin2_code":"1851268.0",
    "gn:asciiname":"Uomachi",
    "gn:country_code":"JP",
    "gn:dem":25,
    "gn:feature_class":"P",
    "gn:feature_code":"PPL",
    "gn:name":"Uomachi",
    "gn:population":0,
    "gn:timezone":"Asia/Tokyo",
    "iso:country":"JP",
    "name:jpn_x_preferred":[
        "\u9b5a\u753a"
    ],
    "wof:name":"Uomachi",
    "wof:placetype":"locality"
},
  "geometry": {"coordinates":[130.81939,33.64313],"type":"Point"}
}