{
  "type": "Feature",
  "properties": {
    "gn:admin1_code":"16.0",
    "gn:admin2_code":"7441806.0",
    "gn:admin3_code":"3483.0",
    "gn:asciiname":"Otomo",
    "gn:country_code":"JP",
    "gn:dem":180,
    "gn:feature_class":"P",
    "gn:feature_code":"PPL",
    "gn:name":"Otomo",
    "gn:population":0,
    "gn:timezone":"Asia/Tokyo",
    "iso:country":"JP",
    "wof:name":"Otomo",
    "wof:placetype":"locality"
},
  "geometry": {"coordinates":[141.86667,39.83333],"type":"Point"}
}