{
  "type": "Feature",
  "properties": {
    "gn:admin1_code":"10.0",
    "gn:admin2_code":"7453841.0",
    "gn:asciiname":"Omamacho-kiribara",
    "gn:country_code":"JP",
    "gn:dem":261,
    "gn:feature_class":"P",
    "gn:feature_code":"PPL",
    "gn:name":"\u014cmamach\u014d-kiribara",
    "gn:population":0,
    "gn:timezone":"Asia/Tokyo",
    "iso:country":"JP",
    "name:jpn_x_preferred":[
        "\u5927\u9593\u3005\u753a\u6850\u539f"
    ],
    "name:und_x_variant":[
        "\u014cmamach\u014d-kiribara"
    ],
    "wof:name":"Omamacho-kiribara",
    "wof:placetype":"locality"
},
  "geometry": {"coordinates":[139.26917,36.44151],"type":"Point"}
}