{
  "type": "Feature",
  "properties": {
    "gn:admin1_code":"47",
    "gn:admin2_code":"1858371.0",
    "gn:admin3_code":"47302.0",
    "gn:asciiname":"Uro",
    "gn:country_code":"JP",
    "gn:dem":249,
    "gn:feature_class":"P",
    "gn:feature_code":"PPL",
    "gn:name":"Uro",
    "gn:population":0,
    "gn:timezone":"Asia/Tokyo",
    "iso:country":"JP",
    "name:ceb_x_preferred":[
        "Uro"
    ],
    "name:dan_x_preferred":[
        "Uro"
    ],
    "name:deu_x_preferred":[
        "Uro"
    ],
    "name:glg_x_preferred":[
        "Uro"
    ],
    "name:nor_x_preferred":[
        "Uro"
    ],
    "name:pol_x_preferred":[
        "Uro"
    ],
    "name:spa_x_preferred":[
        "Uro"
    ],
    "name:swe_x_preferred":[
        "Uro"
    ],
    "wof:name":"Uro",
    "wof:placetype":"locality"
},
  "geometry": {"coordinates":[128.15000000000001,26.68333],"type":"Point"}
}