{
  "type": "Feature",
  "properties": {
    "gn:admin1_code":"21.0",
    "gn:admin2_code":"1858418.0",
    "gn:admin3_code":"43101.0",
    "gn:asciiname":"Renpeicho",
    "gn:country_code":"JP",
    "gn:dem":12,
    "gn:feature_class":"P",
    "gn:feature_code":"PPL",
    "gn:name":"Renpeich\u014d",
    "gn:population":0,
    "gn:timezone":"Asia/Tokyo",
    "iso:country":"JP",
    "name:jpn_x_preferred":[
        "\u7df4\u5175\u753a"
    ],
    "name:jpn_x_variant":[
        "\u308c\u3093\u307a\u3044\u3061\u3087\u3046",
        "\u30ec\u30f3\u30da\u30a4\u30c1\u30e7\u30a6"
    ],
    "name:und_x_variant":[
        "Renpeich\u014d"
    ],
    "wof:name":"Renpeicho",
    "wof:placetype":"locality"
},
  "geometry": {"coordinates":[130.70014,32.7975],"type":"Point"}
}