{
  "type": "Feature",
  "properties": {
    "gn:admin1_code":"21.0",
    "gn:admin2_code":"1865358.0",
    "gn:asciiname":"Gonroku",
    "gn:country_code":"JP",
    "gn:dem":13,
    "gn:feature_class":"P",
    "gn:feature_code":"PPLL",
    "gn:name":"Gonroku",
    "gn:population":0,
    "gn:timezone":"Asia/Tokyo",
    "iso:country":"JP",
    "name:jpn_x_preferred":[
        "\u6a29\u516d"
    ],
    "name:jpn_x_variant":[
        "\u3054\u3093\u308d\u304f",
        "\u30b4\u30f3\u30ed\u30af"
    ],
    "wof:name":"Gonroku",
    "wof:placetype":"locality"
},
  "geometry": {"coordinates":[130.29346000000001,32.48408],"type":"Point"}
}