{
  "type": "Feature",
  "properties": {
    "gn:admin1_code":"19.0",
    "gn:admin2_code":"7470889.0",
    "gn:asciiname":"Asahi",
    "gn:country_code":"JP",
    "gn:dem":34,
    "gn:feature_class":"P",
    "gn:feature_code":"PPLL",
    "gn:name":"Asahi",
    "gn:population":0,
    "gn:timezone":"Asia/Tokyo",
    "iso:country":"JP",
    "name:jpn_x_preferred":[
        "\u65ed"
    ],
    "wof:name":"Asahi",
    "wof:placetype":"locality"
},
  "geometry": {"coordinates":[139.39389,35.41413],"type":"Point"}
}