{
  "type": "Feature",
  "properties": {
    "gn:admin1_code":"4.0",
    "gn:admin2_code":"1859468.0",
    "gn:asciiname":"Seigetsu",
    "gn:country_code":"JP",
    "gn:dem":47,
    "gn:feature_class":"P",
    "gn:feature_code":"PPLL",
    "gn:name":"Seigetsu",
    "gn:population":0,
    "gn:timezone":"Asia/Tokyo",
    "iso:country":"JP",
    "name:jpn_x_preferred":[
        "\u6e05\u6708"
    ],
    "name:jpn_x_variant":[
        "\u305b\u3044\u3052\u3064",
        "\u30bb\u30a4\u30b2\u30c4"
    ],
    "wof:name":"Seigetsu",
    "wof:placetype":"locality"
},
  "geometry": {"coordinates":[139.92747,35.28952],"type":"Point"}
}