{
  "type": "Feature",
  "properties": {
    "iso:country":"JP",
    "qs:name":"\u9999\u6625\u753a",
    "qs:name_adm0":"\u65e5\u672c",
    "qs:name_adm1":"\u798f\u5ca1\u770c",
    "qs:photos":9,
    "qs:photos_1k":2,
    "qs:photos_9k":1,
    "qs:photos_9r":1,
    "qs:photos_all":9,
    "qs:photos_sr":1,
    "qs:placetype":"Town",
    "qs:pop_sr":"0",
    "wof:name":"\u9999\u6625\u753a",
    "wof:placetype":"locality"
},
  "geometry": {"coordinates":[130.845451,33.669639],"type":"Point"}
}