{
  "type": "Feature",
  "properties": {
    "iso:country":"JP",
    "name:eng_x_preferred":[
        "Shibakawa"
    ],
    "name:eng_x_variant":[
        "Shibakawa Town"
    ],
    "name:jpn_x_preferred":[
        "\u829d\u5ddd\u753a"
    ],
    "qs:name":"\u829d\u5ddd\u753a",
    "qs:name_adm0":"\u65e5\u672c",
    "qs:name_adm1":"\u9759\u5ca1\u770c",
    "qs:photos":74,
    "qs:photos_1k":15,
    "qs:photos_9k":1,
    "qs:photos_9r":2,
    "qs:photos_all":74,
    "qs:photos_sr":2,
    "qs:placetype":"Town",
    "qs:pop_sr":"0",
    "wof:name":"Shibakawa",
    "wof:placetype":"locality"
},
  "geometry": {"coordinates":[138.559528,35.209331],"type":"Point"}
}