{
  "type": "Feature",
  "properties": {
    "gn:admin1_code":"21.0",
    "gn:admin2_code":"1862350.0",
    "gn:asciiname":"Minamiizumidamachi",
    "gn:country_code":"JP",
    "gn:dem":111,
    "gn:feature_class":"P",
    "gn:feature_code":"PPL",
    "gn:name":"Minamiizumidamachi",
    "gn:population":0,
    "gn:timezone":"Asia/Tokyo",
    "iso:country":"JP",
    "name:jpn_x_preferred":[
        "\u5357\u6cc9\u7530\u753a"
    ],
    "name:jpn_x_variant":[
        "\u307f\u306a\u307f\u3044\u305a\u307f\u3060\u307e\u3061",
        "\u30df\u30ca\u30df\u30a4\u30ba\u30df\u30c0\u30de\u30c1"
    ],
    "wof:name":"Minamiizumidamachi",
    "wof:placetype":"locality"
},
  "geometry": {"coordinates":[130.76752999999999,32.21791],"type":"Point"}
}