{
  "type": "Feature",
  "properties": {
    "gn:admin1_code":"13.0",
    "gn:admin2_code":"1865383.0",
    "gn:asciiname":"Nagasu-nakadori",
    "gn:country_code":"JP",
    "gn:dem":2,
    "gn:feature_class":"P",
    "gn:feature_code":"PPL",
    "gn:name":"Nagasu-nakad\u014dri",
    "gn:population":0,
    "gn:timezone":"Asia/Tokyo",
    "iso:country":"JP",
    "name:jpn_x_preferred":[
        "\u9577\u6d32\u4e2d\u901a"
    ],
    "name:und_x_variant":[
        "Nagasu-nakad\u014dri"
    ],
    "wof:name":"Nagasu-nakadori",
    "wof:placetype":"locality"
},
  "geometry": {"coordinates":[135.43106,34.7221],"type":"Point"}
}