{
  "type": "Feature",
  "properties": {
    "gn:admin1_code":"16.0",
    "gn:admin2_code":"2128940.0",
    "gn:asciiname":"Yachi",
    "gn:country_code":"JP",
    "gn:dem":106,
    "gn:feature_class":"P",
    "gn:feature_code":"PPL",
    "gn:name":"Yachi",
    "gn:population":0,
    "gn:timezone":"Asia/Tokyo",
    "iso:country":"JP",
    "name:jpn_x_preferred":[
        "\u8c37\u5730"
    ],
    "name:jpn_x_variant":[
        "\u3084\u3061",
        "\u30e4\u30c1"
    ],
    "wof:name":"Yachi",
    "wof:placetype":"locality"
},
  "geometry": {"coordinates":[141.26946999999996,40.33026],"type":"Point"}
}