{
  "type": "Feature",
  "properties": {
    "iso:country":"JP",
    "name:eng_x_preferred":[
        "Chuo 4 Chome"
    ],
    "name:eng_x_variant":[
        "Chuuou 4 Choume",
        "Chuo 4 Chome"
    ],
    "name:jpn_x_preferred":[
        "\uff14\u4e01\u76ee"
    ],
    "name:jpn_x_variant":[
        "\u3061\u3085\u3046\u304a\u3046 \uff14\u3061\u3087\u3046\u3081",
        "\u4e2d\u592e \uff14\u4e01\u76ee",
        "\uff14\u3061\u3087\u3046\u3081"
    ],
    "qs:gn_local":0,
    "qs:local_max":205,
    "qs:local_sum":366,
    "qs:localhoods":2,
    "qs:name":"\uff14\u4e01\u76ee",
    "qs:name_adm0":"\u65e5\u672c",
    "qs:name_adm1":"\u795e\u5948\u5ddd\u770c",
    "qs:name_adm2":"\u8db3\u67c4\u4e0b\u90e1",
    "qs:name_en":"Chuo 4 Chome",
    "qs:name_lau":"\u4e2d\u592e",
    "qs:name_local":"\u6e6f\u6cb3\u539f\u753a",
    "qs:photo_max":138,
    "qs:photo_sum":205,
    "qs:placetype":"Suburb",
    "qs:quad_count":12,
    "qs:woe_adm0":23424856,
    "qs:woe_adm1":2345868,
    "qs:woe_adm2":24857810,
    "qs:woe_lau":28417515,
    "qs:woe_local":1116831,
    "qs:woe_ver":"7.10.0",
    "wof:lang":[
        "jpn"
    ],
    "wof:name":"\uff14\u4e01\u76ee",
    "wof:placetype":"neighbourhood"
},
  "geometry": {"coordinates":[139.12110300000001,35.154011],"type":"Point"}
}