{
  "type": "Feature",
  "properties": {
    "gn:admin1_code":"40.0",
    "gn:admin2_code":"1859211.0",
    "gn:asciiname":"Asahigaoka",
    "gn:country_code":"JP",
    "gn:dem":42,
    "gn:feature_class":"P",
    "gn:feature_code":"PPL",
    "gn:name":"Asahigaoka",
    "gn:population":0,
    "gn:timezone":"Asia/Tokyo",
    "iso:country":"JP",
    "name:jpn_x_preferred":[
        "\u65ed\u304c\u4e18"
    ],
    "wof:name":"Asahigaoka",
    "wof:placetype":"locality"
},
  "geometry": {"coordinates":[139.54013,35.79566],"type":"Point"}
}