{
  "type": "Feature",
  "properties": {
    "gn:admin1_code":"4.0",
    "gn:admin2_code":"9062338.0",
    "gn:asciiname":"Shukudo",
    "gn:country_code":"JP",
    "gn:dem":79,
    "gn:feature_class":"P",
    "gn:feature_code":"PPL",
    "gn:name":"Shukudo",
    "gn:population":0,
    "gn:timezone":"Asia/Tokyo",
    "iso:country":"JP",
    "name:jpn_x_preferred":[
        "\u5bbf\u6238"
    ],
    "name:jpn_x_variant":[
        "\u3057\u3085\u304f\u3069",
        "\u30b7\u30e5\u30af\u30c9"
    ],
    "wof:name":"Shukudo",
    "wof:placetype":"locality"
},
  "geometry": {"coordinates":[140.29383999999999,35.1877],"type":"Point"}
}