{
  "type": "Feature",
  "properties": {
    "gn:admin1_code":"4.0",
    "gn:admin2_code":"1863711.0",
    "gn:asciiname":"Nagasaki",
    "gn:country_code":"JP",
    "gn:dem":19,
    "gn:feature_class":"P",
    "gn:feature_code":"PPL",
    "gn:name":"Nagasaki",
    "gn:population":0,
    "gn:timezone":"Asia/Tokyo",
    "iso:country":"JP",
    "name:jpn_x_preferred":[
        "\u9577\u5d0e"
    ],
    "name:jpn_x_variant":[
        "\u306a\u304c\u3055\u304d",
        "\u30ca\u30ac\u30b5\u30ad"
    ],
    "wof:name":"Nagasaki",
    "wof:placetype":"locality"
},
  "geometry": {"coordinates":[139.90653,35.21892000000001],"type":"Point"}
}