{
  "type": "Feature",
  "properties": {
    "gn:admin1_code":"25.0",
    "gn:admin2_code":"1864313.0",
    "gn:asciiname":"Tomezuka",
    "gn:country_code":"JP",
    "gn:dem":264,
    "gn:feature_class":"P",
    "gn:feature_code":"PPLL",
    "gn:name":"T\u014dmezuka",
    "gn:population":0,
    "gn:timezone":"Asia/Tokyo",
    "iso:country":"JP",
    "name:jpn_x_preferred":[
        "\u9060\u76ee\u585a"
    ],
    "name:jpn_x_variant":[
        "\u3068\u304a\u3081\u3065\u304b",
        "\u30c8\u30aa\u30e1\u30c5\u30ab"
    ],
    "name:und_x_variant":[
        "T\u014dmezuka"
    ],
    "wof:name":"Tomezuka",
    "wof:placetype":"locality"
},
  "geometry": {"coordinates":[130.87571,32.04424],"type":"Point"}
}