{
  "type": "Feature",
  "properties": {
    "gn:admin1_code":"21.0",
    "gn:admin2_code":"1859488.0",
    "gn:asciiname":"Yakushi",
    "gn:country_code":"JP",
    "gn:dem":48,
    "gn:feature_class":"P",
    "gn:feature_code":"PPLL",
    "gn:name":"Yakushi",
    "gn:population":0,
    "gn:timezone":"Asia/Tokyo",
    "iso:country":"JP",
    "name:jpn_x_preferred":[
        "\u85ac\u5e2b"
    ],
    "name:jpn_x_variant":[
        "\u3084\u304f\u3057",
        "\u30e4\u30af\u30b7"
    ],
    "wof:name":"Yakushi",
    "wof:placetype":"locality"
},
  "geometry": {"coordinates":[130.77703,32.92458],"type":"Point"}
}