{
  "type": "Feature",
  "properties": {
    "gn:admin1_code":"24.0",
    "gn:admin2_code":"7446990.0",
    "gn:asciiname":"Nishifukuda",
    "gn:country_code":"JP",
    "gn:dem":32,
    "gn:feature_class":"P",
    "gn:feature_code":"PPL",
    "gn:name":"Nishifukuda",
    "gn:population":0,
    "gn:timezone":"Asia/Tokyo",
    "iso:country":"JP",
    "name:jpn_x_preferred":[
        "\u897f\u798f\u7530"
    ],
    "name:jpn_x_variant":[
        "\u306b\u3057\u3075\u304f\u3060",
        "\u30cb\u30b7\u30d5\u30af\u30c0"
    ],
    "wof:name":"Nishifukuda",
    "wof:placetype":"locality"
},
  "geometry": {"coordinates":[141.13336000000001,38.43063],"type":"Point"}
}