{
  "type": "Feature",
  "properties": {
    "gn:admin1_code":"8.0",
    "gn:admin2_code":"7451504.0",
    "gn:admin3_code":"7447.0",
    "gn:asciiname":"Nakakabuto",
    "gn:country_code":"JP",
    "gn:dem":318,
    "gn:feature_class":"P",
    "gn:feature_code":"PPLL",
    "gn:name":"Nakakabuto",
    "gn:population":0,
    "gn:timezone":"Asia/Tokyo",
    "iso:country":"JP",
    "name:jpn_x_preferred":[
        "\u4e2d\u5191"
    ],
    "wof:name":"Nakakabuto",
    "wof:placetype":"locality"
},
  "geometry": {"coordinates":[139.79719,37.42385],"type":"Point"}
}