{
  "type": "Feature",
  "properties": {
    "iso:country":"JP",
    "name:eng_x_preferred":[
        "Takenoyama 1 Chome"
    ],
    "name:eng_x_variant":[
        "Takenoyama 1 Choume",
        "Takenoyama 1 Chome"
    ],
    "name:jpn_x_preferred":[
        "\uff11\u4e01\u76ee"
    ],
    "name:jpn_x_variant":[
        "\u305f\u3051\u306e\u3084\u307e \uff11\u3061\u3087\u3046\u3081",
        "\u7af9\u306e\u5c71 \uff11\u4e01\u76ee",
        "\uff11\u3061\u3087\u3046\u3081"
    ],
    "name:unk_x_variant":[
        "\uff11\u4e01\u76ee"
    ],
    "qs:gn_local":0,
    "qs:local_max":98,
    "qs:local_sum":150,
    "qs:localhoods":3,
    "qs:name":"\uff11\u4e01\u76ee",
    "qs:name_adm0":"\u65e5\u672c",
    "qs:name_adm1":"\u611b\u77e5\u770c",
    "qs:name_en":"Takenoyama 1 Chome",
    "qs:name_lau":"\u7af9\u306e\u5c71",
    "qs:name_local":"\u65e5\u9032\u5e02",
    "qs:photo_max":57,
    "qs:photo_sum":98,
    "qs:placetype":"Suburb",
    "qs:quad_count":5,
    "qs:woe_adm0":23424856,
    "qs:woe_adm1":2345851,
    "qs:woe_adm2":0,
    "qs:woe_lau":28444748,
    "qs:woe_local":15015463,
    "qs:woe_ver":"7.10.0",
    "wof:lang":[
        "jpn"
    ],
    "wof:name":"\uff11\u4e01\u76ee",
    "wof:placetype":"neighbourhood"
},
  "geometry": {"coordinates":[137.04079200000001,35.159879],"type":"Point"}
}