{
  "type": "Feature",
  "properties": {
    "gn:admin1_code":"2.0",
    "gn:admin2_code":"2129594.0",
    "gn:admin3_code":"5303.0",
    "gn:asciiname":"Hachikuro",
    "gn:country_code":"JP",
    "gn:dem":287,
    "gn:feature_class":"P",
    "gn:feature_code":"PPL",
    "gn:name":"Hachikur\u014d",
    "gn:population":0,
    "gn:timezone":"Asia/Tokyo",
    "iso:country":"JP",
    "name:jpn_x_preferred":[
        "\u516b\u4e5d\u90ce"
    ],
    "name:jpn_x_variant":[
        "\u306f\u3061\u304f\u308d\u3046",
        "\u30cf\u30c1\u30af\u30ed\u30a6"
    ],
    "name:und_x_variant":[
        "Hachikur\u014d"
    ],
    "wof:name":"Hachikuro",
    "wof:placetype":"locality"
},
  "geometry": {"coordinates":[140.74583999999999,40.39018],"type":"Point"}
}