{
  "type": "Feature",
  "properties": {
    "gn:admin1_code":"24.0",
    "gn:admin2_code":"2111889.0",
    "gn:admin3_code":"4401.0",
    "gn:asciiname":"Fujinomaki",
    "gn:country_code":"JP",
    "gn:dem":3,
    "gn:feature_class":"P",
    "gn:feature_code":"PPL",
    "gn:name":"Fujinomaki",
    "gn:population":0,
    "gn:timezone":"Asia/Tokyo",
    "iso:country":"JP",
    "name:jpn_x_preferred":[
        "\u85e4\u30ce\u5dfb"
    ],
    "name:jpn_x_variant":[
        "\u3075\u3058\u306e\u307e\u304d",
        "\u30d5\u30b8\u30ce\u30de\u30ad"
    ],
    "wof:name":"Fujinomaki",
    "wof:placetype":"locality"
},
  "geometry": {"coordinates":[141.11407,38.43293],"type":"Point"}
}