{
  "type": "Feature",
  "properties": {
    "gn:admin1_code":"3.0",
    "gn:admin2_code":"2130200.0",
    "gn:asciiname":"Takanosu",
    "gn:country_code":"JP",
    "gn:dem":62,
    "gn:feature_class":"P",
    "gn:feature_code":"PPL",
    "gn:name":"Takanosu",
    "gn:population":0,
    "gn:timezone":"Asia/Tokyo",
    "iso:country":"JP",
    "name:jpn_x_preferred":[
        "\u9df9\u30ce\u5de3"
    ],
    "name:jpn_x_variant":[
        "\u305f\u304b\u306e\u3059",
        "\u30bf\u30ab\u30ce\u30b9"
    ],
    "wof:name":"Takanosu",
    "wof:placetype":"locality"
},
  "geometry": {"coordinates":[141.38472999999999,40.50255],"type":"Point"}
}