{
  "type": "Feature",
  "properties": {
    "gn:admin1_code":"33.0",
    "gn:admin2_code":"7391363.0",
    "gn:asciiname":"Beta",
    "gn:country_code":"JP",
    "gn:dem":24,
    "gn:feature_class":"P",
    "gn:feature_code":"PPLL",
    "gn:name":"Beta",
    "gn:population":0,
    "gn:timezone":"Asia/Tokyo",
    "iso:country":"JP",
    "name:jpn_x_preferred":[
        "\u8fba\u7530"
    ],
    "wof:name":"Beta",
    "wof:placetype":"locality"
},
  "geometry": {"coordinates":[130.03068000000002,33.12371],"type":"Point"}
}