{
  "type": "Feature",
  "properties": {
    "gn:admin1_code":"7.0",
    "gn:admin2_code":"7407416.0",
    "gn:asciiname":"Daikenkyu",
    "gn:country_code":"JP",
    "gn:dem":40,
    "gn:feature_class":"P",
    "gn:feature_code":"PPLL",
    "gn:name":"Daikenky\u016b",
    "gn:population":0,
    "gn:timezone":"Asia/Tokyo",
    "iso:country":"JP",
    "name:jpn_x_preferred":[
        "\u5927\u898b\u4e45"
    ],
    "name:und_x_variant":[
        "Daikenky\u016b"
    ],
    "wof:name":"Daikenkyu",
    "wof:placetype":"locality"
},
  "geometry": {"coordinates":[130.63793000000001,33.76156],"type":"Point"}
}