{
  "type": "Feature",
  "properties": {
    "gn:admin1_code":"22",
    "gn:admin2_code":"1857764.0",
    "gn:asciiname":"Onyo",
    "gn:country_code":"JP",
    "gn:dem":81,
    "gn:feature_class":"P",
    "gn:feature_code":"PPL",
    "gn:name":"Onyo",
    "gn:population":0,
    "gn:timezone":"Asia/Tokyo",
    "iso:country":"JP",
    "name:und_x_variant":[
        "\u014ctanu",
        "\u014cny\u016b"
    ],
    "wof:name":"Onyo",
    "wof:placetype":"locality"
},
  "geometry": {"coordinates":[135.34999999999999,35.51667],"type":"Point"}
}