{
  "type": "Feature",
  "properties": {
    "gn:admin1_code":"21.0",
    "gn:admin2_code":"7412708.0",
    "gn:admin3_code":"43514.0",
    "gn:asciiname":"Karidokoro",
    "gn:country_code":"JP",
    "gn:dem":192,
    "gn:feature_class":"P",
    "gn:feature_code":"PPLL",
    "gn:name":"Karidokoro",
    "gn:population":0,
    "gn:timezone":"Asia/Tokyo",
    "iso:country":"JP",
    "name:jpn_x_preferred":[
        "\u72e9\u6240"
    ],
    "wof:name":"Karidokoro",
    "wof:placetype":"locality"
},
  "geometry": {"coordinates":[130.91978,32.21694],"type":"Point"}
}