{
  "type": "Feature",
  "properties": {
    "gn:admin1_code":"12.0",
    "gn:admin2_code":"2129370.0",
    "gn:asciiname":"Ashino",
    "gn:country_code":"JP",
    "gn:dem":5,
    "gn:feature_class":"P",
    "gn:feature_code":"PPL",
    "gn:name":"Ashino",
    "gn:population":0,
    "gn:timezone":"Asia/Tokyo",
    "iso:country":"JP",
    "name:jpn_x_preferred":[
        "\u82a6\u91ce"
    ],
    "name:jpn_x_variant":[
        "\u3042\u3057\u306e",
        "\u30a2\u30b7\u30ce"
    ],
    "wof:name":"Ashino",
    "wof:placetype":"locality"
},
  "geometry": {"coordinates":[144.39726000000005,43.01518],"type":"Point"}
}