{
  "type": "Feature",
  "properties": {
    "gn:admin1_code":"2.0",
    "gn:admin2_code":"2128783.0",
    "gn:asciiname":"Bakuromachi",
    "gn:country_code":"JP",
    "gn:dem":76,
    "gn:feature_class":"P",
    "gn:feature_code":"PPL",
    "gn:name":"Bakur\u014dmachi",
    "gn:population":0,
    "gn:timezone":"Asia/Tokyo",
    "iso:country":"JP",
    "name:jpn_x_preferred":[
        "\u99ac\u55b0\u753a"
    ],
    "name:jpn_x_variant":[
        "\u3070\u304f\u308d\u3046\u307e\u3061",
        "\u30d0\u30af\u30ed\u30a6\u30de\u30c1"
    ],
    "name:und_x_variant":[
        "Bakur\u014dmachi"
    ],
    "wof:name":"Bakuromachi",
    "wof:placetype":"locality"
},
  "geometry": {"coordinates":[140.55987999999999,40.27114],"type":"Point"}
}