{
  "type": "Feature",
  "properties": {
    "gn:country":"JP",
    "gn:fcode":"ADM3",
    "gn:population":0,
    "iso:country":"JP",
    "name:eng_x_preferred":[
        "Kawai"
    ],
    "name:eng_x_variant":[
        "Kawai-ch\u014d"
    ],
    "name:jpn_x_preferred":[
        "\u6cb3\u5408\u753a"
    ],
    "name:jpn_x_variant":[
        "\u304b\u308f\u3044\u3061\u3087\u3046"
    ],
    "name:und_x_variant":[
        "Kawai Ch\u014d"
    ],
    "qs:name":"Kawai-ch\u014d",
    "qs:photos_9r":0,
    "qs:photos_sr":0,
    "qs:pop_sr":"0",
    "wof:name":"Kawai",
    "wof:placetype":"localadmin",
    "wof:population":0
},
  "geometry": {"coordinates":[135.73215999999999,34.58007],"type":"Point"}
}