{
  "type": "Feature",
  "properties": {
    "gn:admin1_code":"41.0",
    "gn:admin2_code":"1853248.0",
    "gn:admin3_code":"31386.0",
    "gn:asciiname":"Sama",
    "gn:country_code":"JP",
    "gn:dem":207,
    "gn:feature_class":"P",
    "gn:feature_code":"PPL",
    "gn:name":"Sama",
    "gn:population":0,
    "gn:timezone":"Asia/Tokyo",
    "iso:country":"JP",
    "name:ast_x_preferred":[
        "Sama"
    ],
    "name:ceb_x_preferred":[
        "Sama"
    ],
    "name:deu_x_preferred":[
        "Sama"
    ],
    "name:fin_x_preferred":[
        "Sama"
    ],
    "name:fra_x_preferred":[
        "Sama"
    ],
    "name:ind_x_preferred":[
        "Sama"
    ],
    "name:ita_x_preferred":[
        "Sama"
    ],
    "name:jpn_x_preferred":[
        "\u4f50\u6469"
    ],
    "name:por_x_preferred":[
        "Sama"
    ],
    "name:spa_x_preferred":[
        "Sama"
    ],
    "name:swe_x_preferred":[
        "Sama"
    ],
    "name:urd_x_preferred":[
        "\u0633\u0627\u0645\u0627"
    ],
    "wof:name":"Sama",
    "wof:placetype":"locality"
},
  "geometry": {"coordinates":[133.49867,35.44495999999999],"type":"Point"}
}