{
  "type": "Feature",
  "properties": {
    "gn:admin1_code":"21.0",
    "gn:admin2_code":"7412706.0",
    "gn:admin3_code":"43444.0",
    "gn:asciiname":"Heba",
    "gn:country_code":"JP",
    "gn:dem":19,
    "gn:feature_class":"P",
    "gn:feature_code":"PPLL",
    "gn:name":"Heba",
    "gn:population":0,
    "gn:timezone":"Asia/Tokyo",
    "iso:country":"JP",
    "name:jpn_x_preferred":[
        "\u8fba\u5834"
    ],
    "name:jpn_x_variant":[
        "\u3078\u3070",
        "\u30d8\u30d0"
    ],
    "wof:name":"Heba",
    "wof:placetype":"locality"
},
  "geometry": {"coordinates":[130.78579999999999,32.70014],"type":"Point"}
}