{
  "type": "Feature",
  "properties": {
    "gn:admin1_code":"21.0",
    "gn:admin2_code":"1858418.0",
    "gn:admin3_code":"43104.0",
    "gn:asciiname":"Hirata",
    "gn:country_code":"JP",
    "gn:dem":6,
    "gn:feature_class":"P",
    "gn:feature_code":"PPL",
    "gn:name":"Hirata",
    "gn:population":0,
    "gn:timezone":"Asia/Tokyo",
    "iso:country":"JP",
    "name:jpn_x_preferred":[
        "\u5e73\u7530"
    ],
    "name:jpn_x_variant":[
        "\u3072\u3089\u305f",
        "\u30d2\u30e9\u30bf"
    ],
    "wof:name":"Hirata",
    "wof:placetype":"locality"
},
  "geometry": {"coordinates":[130.69472999999999,32.77365],"type":"Point"}
}