{
  "type": "Feature",
  "properties": {
    "gn:admin1_code":"7.0",
    "gn:admin2_code":"1859306.0",
    "gn:admin3_code":"40108.0",
    "gn:asciiname":"Suwa",
    "gn:country_code":"JP",
    "gn:dem":30,
    "gn:feature_class":"P",
    "gn:feature_code":"PPL",
    "gn:name":"Suwa",
    "gn:population":0,
    "gn:timezone":"Asia/Tokyo",
    "iso:country":"JP",
    "name:ceb_x_preferred":[
        "Suwa"
    ],
    "name:deu_x_preferred":[
        "Suwa"
    ],
    "name:epo_x_preferred":[
        "Su\u016da"
    ],
    "name:fra_x_preferred":[
        "Suwa"
    ],
    "name:jpn_x_preferred":[
        "\u8acf\u8a2a"
    ],
    "name:mlg_x_preferred":[
        "Suwa"
    ],
    "name:pol_x_preferred":[
        "Suwa"
    ],
    "name:por_x_preferred":[
        "Suwa"
    ],
    "name:swe_x_preferred":[
        "Suwa"
    ],
    "name:ukr_x_preferred":[
        "\u0421\u0443\u0432\u0430"
    ],
    "wof:name":"Suwa",
    "wof:placetype":"locality"
},
  "geometry": {"coordinates":[130.81943000000001,33.8712],"type":"Point"}
}