{
  "type": "Feature",
  "properties": {
    "gn:admin1_code":"4.0",
    "gn:admin2_code":"2112997.0",
    "gn:admin3_code":"12422.0",
    "gn:asciiname":"Yajiri",
    "gn:country_code":"JP",
    "gn:dem":9,
    "gn:feature_class":"P",
    "gn:feature_code":"PPLL",
    "gn:name":"Yajiri",
    "gn:population":0,
    "gn:timezone":"Asia/Tokyo",
    "iso:country":"JP",
    "name:jpn_x_preferred":[
        "\u77e2\u5c3b"
    ],
    "name:jpn_x_variant":[
        "\u3084\u3058\u308a",
        "\u30e4\u30b8\u30ea"
    ],
    "wof:name":"Yajiri",
    "wof:placetype":"locality"
},
  "geometry": {"coordinates":[140.31322,35.36575999999999],"type":"Point"}
}