{
  "type": "Feature",
  "properties": {
    "gn:admin1_code":"34.0",
    "gn:admin2_code":"7464124.0",
    "gn:asciiname":"Yoshiba",
    "gn:country_code":"JP",
    "gn:dem":10,
    "gn:feature_class":"P",
    "gn:feature_code":"PPL",
    "gn:name":"Yoshiba",
    "gn:population":0,
    "gn:timezone":"Asia/Tokyo",
    "iso:country":"JP",
    "name:jpn_x_preferred":[
        "\u5409\u7fbd"
    ],
    "name:jpn_x_variant":[
        "\u3088\u3057\u3070",
        "\u30e8\u30b7\u30d0"
    ],
    "wof:name":"Yoshiba",
    "wof:placetype":"locality"
},
  "geometry": {"coordinates":[139.69245000000001,36.06464],"type":"Point"}
}