{
  "type": "Feature",
  "properties": {
    "gn:admin1_code":"4.0",
    "gn:admin2_code":"1850520.0",
    "gn:asciiname":"Sono",
    "gn:country_code":"JP",
    "gn:dem":21,
    "gn:feature_class":"P",
    "gn:feature_code":"PPL",
    "gn:name":"Sono",
    "gn:population":0,
    "gn:timezone":"Asia/Tokyo",
    "iso:country":"JP",
    "name:jpn_x_preferred":[
        "\u8597"
    ],
    "name:jpn_x_variant":[
        "\u305d\u306e",
        "\u30bd\u30ce"
    ],
    "wof:name":"Sono",
    "wof:placetype":"locality"
},
  "geometry": {"coordinates":[139.91737000000001,35.00341],"type":"Point"}
}