{
  "type": "Feature",
  "properties": {
    "gn:admin1_code":"01",
    "gn:admin2_code":"1850183.0",
    "gn:asciiname":"Otani",
    "gn:country_code":"JP",
    "gn:dem":4,
    "gn:feature_class":"P",
    "gn:feature_code":"PPL",
    "gn:name":"\u014ctani",
    "gn:population":0,
    "gn:timezone":"Asia/Tokyo",
    "iso:country":"JP",
    "name:und_x_variant":[
        "\u014ctani"
    ],
    "wof:name":"Otani",
    "wof:placetype":"locality"
},
  "geometry": {"coordinates":[136.86667,34.83333],"type":"Point"}
}