{
  "type": "Feature",
  "properties": {
    "gn:admin1_code":"33.0",
    "gn:admin2_code":"8300623.0",
    "gn:asciiname":"Ochicho-ono",
    "gn:country_code":"JP",
    "gn:dem":15,
    "gn:feature_class":"P",
    "gn:feature_code":"PPL",
    "gn:name":"\u014cchich\u014d-\u014dno",
    "gn:population":0,
    "gn:timezone":"Asia/Tokyo",
    "iso:country":"JP",
    "name:jpn_x_preferred":[
        "\u76f8\u77e5\u753a\u5927\u91ce"
    ],
    "name:und_x_variant":[
        "\u014cchich\u014d-\u014dno"
    ],
    "wof:name":"Ochicho-ono",
    "wof:placetype":"locality"
},
  "geometry": {"coordinates":[129.99697,33.38118],"type":"Point"}
}