{
  "type": "Feature",
  "properties": {
    "gn:admin1_code":"46",
    "gn:admin2_code":"1849406.0",
    "gn:asciiname":"Inuma",
    "gn:country_code":"JP",
    "gn:dem":396,
    "gn:feature_class":"P",
    "gn:feature_code":"PPL",
    "gn:name":"Inuma",
    "gn:population":0,
    "gn:timezone":"Asia/Tokyo",
    "iso:country":"JP",
    "wof:name":"Inuma",
    "wof:placetype":"locality"
},
  "geometry": {"coordinates":[139.04083,35.62110999999999],"type":"Point"}
}