{
  "type": "Feature",
  "properties": {
    "gn:admin1_code":"16.0",
    "gn:admin2_code":"2128940.0",
    "gn:asciiname":"Aburakubo",
    "gn:country_code":"JP",
    "gn:dem":213,
    "gn:feature_class":"P",
    "gn:feature_code":"PPL",
    "gn:name":"Aburakubo",
    "gn:population":0,
    "gn:timezone":"Asia/Tokyo",
    "iso:country":"JP",
    "name:jpn_x_preferred":[
        "\u6cb9\u4e45\u4fdd"
    ],
    "name:jpn_x_variant":[
        "\u3042\u3076\u3089\u304f\u307c",
        "\u30a2\u30d6\u30e9\u30af\u30dc"
    ],
    "wof:name":"Aburakubo",
    "wof:placetype":"locality"
},
  "geometry": {"coordinates":[141.20733000000001,40.30571],"type":"Point"}
}