{
  "type": "Feature",
  "properties": {
    "gn:admin1_code":"21.0",
    "gn:admin2_code":"1848441.0",
    "gn:asciiname":"Ohira",
    "gn:country_code":"JP",
    "gn:dem":138,
    "gn:feature_class":"P",
    "gn:feature_code":"PPLL",
    "gn:name":"\u014chira",
    "gn:population":0,
    "gn:timezone":"Asia/Tokyo",
    "iso:country":"JP",
    "name:jpn_x_preferred":[
        "\u5927\u5e73"
    ],
    "name:jpn_x_variant":[
        "\u304a\u304a\u3072\u3089",
        "\u30aa\u30aa\u30d2\u30e9"
    ],
    "name:und_x_variant":[
        "\u014chira"
    ],
    "wof:name":"Ohira",
    "wof:placetype":"locality"
},
  "geometry": {"coordinates":[130.69776000000002,32.42793],"type":"Point"}
}