{
  "type": "Feature",
  "properties": {
    "gn:admin1_code":"2.0",
    "gn:admin2_code":"2113122.0",
    "gn:asciiname":"Senshu-kubotamachi",
    "gn:country_code":"JP",
    "gn:dem":13,
    "gn:feature_class":"P",
    "gn:feature_code":"PPL",
    "gn:name":"Sensh\u016b-kubotamachi",
    "gn:population":0,
    "gn:timezone":"Asia/Tokyo",
    "iso:country":"JP",
    "name:jpn_x_preferred":[
        "\u5343\u79cb\u4e45\u4fdd\u7530\u753a"
    ],
    "name:jpn_x_variant":[
        "\u305b\u3093\u3057\u3085\u3046\u304f\u307c\u305f\u307e\u3061",
        "\u30bb\u30f3\u30b7\u30e5\u30a6\u30af\u30dc\u30bf\u30de\u30c1"
    ],
    "name:und_x_variant":[
        "Sensh\u016b-kubotamachi"
    ],
    "wof:name":"Senshu-kubotamachi",
    "wof:placetype":"locality"
},
  "geometry": {"coordinates":[140.12768,39.71941],"type":"Point"}
}