{
  "type": "Feature",
  "properties": {
    "iso:country":"JP",
    "label:eng_x_preferred_longname":[
        "Sanyo Onoda City"
    ],
    "label:eng_x_preferred_placetype":[
        "city"
    ],
    "name:eng_x_preferred":[
        "Sanyo Onoda"
    ],
    "name:eng_x_variant":[
        "Sanyo Onoda City"
    ],
    "name:jpn_x_preferred":[
        "\u5c71\u967d\u5c0f\u91ce\u7530\u5e02"
    ],
    "qs:name":"\u5c71\u967d\u5c0f\u91ce\u7530\u5e02",
    "qs:name_adm0":"\u65e5\u672c",
    "qs:name_adm1":"\u5c71\u53e3\u770c",
    "qs:photos":53,
    "qs:photos_1k":11,
    "qs:photos_9k":1,
    "qs:photos_9r":4,
    "qs:photos_all":166,
    "qs:photos_sr":2,
    "qs:placetype":"Town",
    "qs:pop_sr":"0",
    "wof:name":"Sanyo Onoda",
    "wof:placetype":"locality"
},
  "geometry": {"coordinates":[131.16405399999999,33.994611],"type":"Point"}
}