{
  "type": "Feature",
  "properties": {
    "gn:admin1_code":"39",
    "gn:admin2_code":"7406325.0",
    "gn:asciiname":"Kubo",
    "gn:cc2":"JP",
    "gn:country_code":"JP",
    "gn:dem":451,
    "gn:feature_class":"P",
    "gn:feature_code":"PPL",
    "gn:name":"Kubo",
    "gn:population":0,
    "gn:timezone":"Asia/Tokyo",
    "iso:country":"JP",
    "name:ceb_x_preferred":[
        "Kubo"
    ],
    "name:deu_x_preferred":[
        "Kubo"
    ],
    "name:epo_x_preferred":[
        "Kubo"
    ],
    "name:fra_x_preferred":[
        "Kubo"
    ],
    "name:ita_x_preferred":[
        "Kubo"
    ],
    "name:kor_x_preferred":[
        "\uad6c\ubcf4"
    ],
    "name:rus_x_preferred":[
        "\u041a\u0443\u0431\u043e"
    ],
    "name:slk_x_preferred":[
        "Kubo"
    ],
    "name:tgl_x_preferred":[
        "Kubo"
    ],
    "name:und_x_variant":[
        "Kawai"
    ],
    "wof:name":"Kubo",
    "wof:placetype":"locality"
},
  "geometry": {"coordinates":[134.21666999999999,33.93333],"type":"Point"}
}