{
  "type": "Feature",
  "properties": {
    "gn:admin1_code":"2.0",
    "gn:admin2_code":"2129593.0",
    "gn:asciiname":"Sarugano",
    "gn:country_code":"JP",
    "gn:dem":166,
    "gn:feature_class":"P",
    "gn:feature_code":"PPLL",
    "gn:name":"Sarugano",
    "gn:population":0,
    "gn:timezone":"Asia/Tokyo",
    "iso:country":"JP",
    "name:jpn_x_preferred":[
        "\u7533\u30f6\u91ce"
    ],
    "wof:name":"Sarugano",
    "wof:placetype":"locality"
},
  "geometry": {"coordinates":[140.79686000000001,40.26191],"type":"Point"}
}