{
  "type": "Feature",
  "properties": {
    "gn:admin1_code":"42",
    "gn:admin2_code":"1850038.0",
    "gn:asciiname":"Ranjo",
    "gn:country_code":"JP",
    "gn:dem":55,
    "gn:feature_class":"P",
    "gn:feature_code":"PPL",
    "gn:name":"Ranj\u014d",
    "gn:population":0,
    "gn:timezone":"Asia/Tokyo",
    "iso:country":"JP",
    "name:jpn_x_preferred":[
        "\u983c\u6210"
    ],
    "name:und_x_variant":[
        "Ranj\u014d",
        "Tokuman"
    ],
    "wof:name":"Ranjo",
    "wof:placetype":"locality"
},
  "geometry": {"coordinates":[137.01398,36.63601],"type":"Point"}
}