{
  "type": "Feature",
  "properties": {
    "gn:admin1_code":"21.0",
    "gn:admin2_code":"1848441.0",
    "gn:asciiname":"Moyaimachi",
    "gn:country_code":"JP",
    "gn:dem":1,
    "gn:feature_class":"P",
    "gn:feature_code":"PPL",
    "gn:name":"Moyaimachi",
    "gn:population":0,
    "gn:timezone":"Asia/Tokyo",
    "iso:country":"JP",
    "name:jpn_x_preferred":[
        "\u50ac\u5408\u753a"
    ],
    "wof:name":"Moyaimachi",
    "wof:placetype":"locality"
},
  "geometry": {"coordinates":[130.58709999999999,32.46326],"type":"Point"}
}