{
  "type": "Feature",
  "properties": {
    "gn:admin1_code":"24.0",
    "gn:admin2_code":"2112261.0",
    "gn:asciiname":"Tatesawa",
    "gn:country_code":"JP",
    "gn:dem":173,
    "gn:feature_class":"P",
    "gn:feature_code":"PPL",
    "gn:name":"Tatesawa",
    "gn:population":0,
    "gn:timezone":"Asia/Tokyo",
    "iso:country":"JP",
    "name:jpn_x_preferred":[
        "\u7acb\u6ca2"
    ],
    "name:jpn_x_variant":[
        "\u305f\u3066\u3055\u308f",
        "\u30bf\u30c6\u30b5\u30ef"
    ],
    "wof:name":"Tatesawa",
    "wof:placetype":"locality"
},
  "geometry": {"coordinates":[141.52600000000001,38.88367],"type":"Point"}
}