{
  "type": "Feature",
  "properties": {
    "gn:admin1_code":"19.0",
    "gn:admin2_code":"1865011.0",
    "gn:admin3_code":"14362.0",
    "gn:asciiname":"Akada",
    "gn:country_code":"JP",
    "gn:dem":189,
    "gn:feature_class":"P",
    "gn:feature_code":"PPL",
    "gn:name":"Akada",
    "gn:population":0,
    "gn:timezone":"Asia/Tokyo",
    "iso:country":"JP",
    "name:jpn_x_preferred":[
        "\u8d64\u7530"
    ],
    "wof:name":"Akada",
    "wof:placetype":"locality"
},
  "geometry": {"coordinates":[139.18313000000001,35.33347],"type":"Point"}
}