{
  "type": "Feature",
  "properties": {
    "iso:country":"JP",
    "name:eng_x_preferred":[
        "Yokozutsumi 4 Chome"
    ],
    "name:eng_x_variant":[
        "Yokozutsumi 4 Choume",
        "Yokozutsumi 4 Chome"
    ],
    "name:jpn_x_preferred":[
        "\uff14\u4e01\u76ee"
    ],
    "name:jpn_x_variant":[
        "\u3088\u3053\u3065\u3064\u307f \uff14\u3061\u3087\u3046\u3081",
        "\u6a2a\u5824 \uff14\u4e01\u76ee",
        "\uff14\u3061\u3087\u3046\u3081"
    ],
    "qs:gn_local":0,
    "qs:local_max":5466,
    "qs:local_sum":82256,
    "qs:localhoods":141,
    "qs:name":"\uff14\u4e01\u76ee",
    "qs:name_adm0":"\u65e5\u672c",
    "qs:name_adm1":"\u5927\u962a\u5e9c",
    "qs:name_adm2":"\u9db4\u898b\u533a",
    "qs:name_en":"Yokozutsumi 4 Chome",
    "qs:name_lau":"\u6a2a\u5824",
    "qs:name_local":"\u5927\u962a\u5e02",
    "qs:photo_max":5,
    "qs:photo_sum":8,
    "qs:placetype":"Suburb",
    "qs:quad_count":3,
    "qs:woe_adm0":23424856,
    "qs:woe_adm1":2345881,
    "qs:woe_adm2":15015531,
    "qs:woe_lau":28457498,
    "qs:woe_local":15015370,
    "qs:woe_ver":"7.10.0",
    "wof:lang":[
        "jpn"
    ],
    "wof:name":"\uff14\u4e01\u76ee",
    "wof:placetype":"neighbourhood"
},
  "geometry": {"coordinates":[135.57043100000001,34.706481],"type":"Point"}
}