{
  "type": "Feature",
  "properties": {
    "iso:country":"JP",
    "name:eng_x_preferred":[
        "Kawamata 1 Chome"
    ],
    "name:eng_x_variant":[
        "Kawamata 1 Choume",
        "Kawamata 1 Chome"
    ],
    "name:jpn_x_preferred":[
        "\uff11\u4e01\u76ee"
    ],
    "name:jpn_x_variant":[
        "\u304b\u308f\u307e\u305f \uff11\u3061\u3087\u3046\u3081",
        "\u5ddd\u4fe3 \uff11\u4e01\u76ee",
        "\uff11\u3061\u3087\u3046\u3081"
    ],
    "name:unk_x_variant":[
        "\uff11\u4e01\u76ee"
    ],
    "qs:gn_adm0_cc":"JP",
    "qs:gn_local":1862752,
    "qs:gn_nam_loc":"\u6771\u5927\u962a\u5e02, \u5927\u962a\u5e9c, JP",
    "qs:gn_namadm1":"32",
    "qs:local_max":105,
    "qs:local_sum":142,
    "qs:localhoods":4,
    "qs:name":"\uff11\u4e01\u76ee",
    "qs:name_adm0":"\u65e5\u672c",
    "qs:name_adm1":"\u5927\u962a\u5e9c",
    "qs:name_en":"Kawamata 1 Chome",
    "qs:name_lau":"\u5ddd\u4fe3",
    "qs:name_local":"\u6771\u5927\u962a\u5e02",
    "qs:photo_max":2,
    "qs:photo_sum":2,
    "qs:placetype":"Suburb",
    "qs:quad_count":1,
    "qs:woe_adm0":23424856,
    "qs:woe_adm1":2345881,
    "qs:woe_adm2":0,
    "qs:woe_lau":28460093,
    "qs:woe_local":15015455,
    "qs:woe_ver":"7.10.0",
    "wof:lang":[
        "jpn"
    ],
    "wof:name":"\uff11\u4e01\u76ee",
    "wof:placetype":"neighbourhood"
},
  "geometry": {"coordinates":[135.57403600000001,34.680653],"type":"Point"}
}