{
  "type": "Feature",
  "properties": {
    "gn:admin1_code":"3.0",
    "gn:admin2_code":"8534376.0",
    "gn:admin3_code":"2323.0",
    "gn:asciiname":"Azumano",
    "gn:country_code":"JP",
    "gn:dem":89,
    "gn:feature_class":"P",
    "gn:feature_code":"PPL",
    "gn:name":"Azumano",
    "gn:population":0,
    "gn:timezone":"Asia/Tokyo",
    "iso:country":"JP",
    "name:jpn_x_preferred":[
        "\u6771\u91ce"
    ],
    "name:jpn_x_variant":[
        "\u3042\u305a\u307e\u306e",
        "\u30a2\u30ba\u30de\u30ce"
    ],
    "wof:name":"Azumano",
    "wof:placetype":"locality"
},
  "geometry": {"coordinates":[139.95155,40.65471],"type":"Point"}
}