{
  "type": "Feature",
  "properties": {
    "gn:country":"JP",
    "gn:fcode":"PPL",
    "gn:population":57896,
    "iso:country":"JP",
    "name:jpn_x_preferred":[
        "\u56fd\u5206"
    ],
    "name:jpn_x_variant":[
        "\u56fd\u5206\u677e\u6728"
    ],
    "name:rus_x_preferred":[
        "\u041a\u043e\u043a\u0443\u0431\u0443"
    ],
    "name:und_x_variant":[
        "Kokubo"
    ],
    "qs:name":"Kokubu",
    "qs:photos_9r":0,
    "qs:photos_sr":0,
    "qs:pop_sr":"8",
    "wof:name":"Kokubu",
    "wof:placetype":"locality",
    "wof:population":57896
},
  "geometry": {"coordinates":[130.76667,31.73333],"type":"Point"}
}