{
  "type": "Feature",
  "properties": {
    "gn:admin1_code":"12.0",
    "gn:admin2_code":"2129373.0",
    "gn:admin3_code":"1661.0",
    "gn:asciiname":"Katsura",
    "gn:country_code":"JP",
    "gn:dem":4,
    "gn:feature_class":"P",
    "gn:feature_code":"PPL",
    "gn:name":"Katsura",
    "gn:population":0,
    "gn:timezone":"Asia/Tokyo",
    "iso:country":"JP",
    "name:jpn_x_preferred":[
        "\u6842"
    ],
    "name:jpn_x_variant":[
        "\u304b\u3064\u3089",
        "\u30ab\u30c4\u30e9"
    ],
    "wof:name":"Katsura",
    "wof:placetype":"locality"
},
  "geometry": {"coordinates":[144.40021999999999,43.00626],"type":"Point"}
}