{
  "type": "Feature",
  "properties": {
    "gn:admin1_code":"12.0",
    "gn:admin2_code":"2129373.0",
    "gn:admin3_code":"1661.0",
    "gn:asciiname":"Katsura",
    "gn:country_code":"JP",
    "gn:dem":4,
    "gn:feature_class":"P",
    "gn:feature_code":"PPL",
    "gn:name":"Katsura",
    "gn:population":0,
    "gn:timezone":"Asia/Tokyo",
    "iso:country":"JP",
    "name:deu_x_preferred":[
        "Katsura"
    ],
    "name:fas_x_preferred":[
        "\u06a9\u0627\u062a\u0633\u0648\u0631\u0627"
    ],
    "name:jpn_x_preferred":[
        "\u6842"
    ],
    "name:jpn_x_variant":[
        "\u304b\u3064\u3089",
        "\u30ab\u30c4\u30e9"
    ],
    "name:nld_x_preferred":[
        "Katsura"
    ],
    "name:rus_x_preferred":[
        "\u041a\u0430\u0446\u0443\u0440\u0430"
    ],
    "name:spa_x_preferred":[
        "Katsura"
    ],
    "name:swe_x_preferred":[
        "Katsura"
    ],
    "name:tha_x_preferred":[
        "\u0e04\u0e30\u0e2a\u0e36\u0e23\u0e30"
    ],
    "name:ukr_x_preferred":[
        "\u041a\u0430\u0446\u0443\u0440\u0430"
    ],
    "wof:name":"Katsura",
    "wof:placetype":"locality"
},
  "geometry": {"coordinates":[144.40021999999999,43.00626],"type":"Point"}
}