{
  "type": "Feature",
  "properties": {
    "gn:admin1_code":"05",
    "gn:admin2_code":"10861187.0",
    "gn:asciiname":"Sakaishi",
    "gn:country_code":"JP",
    "gn:dem":190,
    "gn:feature_class":"P",
    "gn:feature_code":"PPL",
    "gn:name":"Sakaishi",
    "gn:population":0,
    "gn:timezone":"Asia/Tokyo",
    "iso:country":"JP",
    "wof:name":"Sakaishi",
    "wof:placetype":"locality"
},
  "geometry": {"coordinates":[132.71218000000002,33.41239],"type":"Point"}
}