{
  "type": "Feature",
  "properties": {
    "gn:admin1_code":"8.0",
    "gn:admin2_code":"2111654.0",
    "gn:asciiname":"Saiwaicho",
    "gn:country_code":"JP",
    "gn:dem":217,
    "gn:feature_class":"P",
    "gn:feature_code":"PPL",
    "gn:name":"Saiwaich\u014d",
    "gn:population":0,
    "gn:timezone":"Asia/Tokyo",
    "iso:country":"JP",
    "name:jpn_x_preferred":[
        "\u5e78\u753a"
    ],
    "name:und_x_variant":[
        "Saiwaich\u014d"
    ],
    "wof:name":"Saiwaicho",
    "wof:placetype":"locality"
},
  "geometry": {"coordinates":[140.44982999999999,37.6273],"type":"Point"}
}