{
  "type": "Feature",
  "properties": {
    "gn:admin1_code":"33.0",
    "gn:admin2_code":"1856784.0",
    "gn:admin3_code":"41346.0",
    "gn:asciiname":"Higashio",
    "gn:country_code":"JP",
    "gn:dem":9,
    "gn:feature_class":"P",
    "gn:feature_code":"PPL",
    "gn:name":"Higashio",
    "gn:population":0,
    "gn:timezone":"Asia/Tokyo",
    "iso:country":"JP",
    "name:jpn_x_preferred":[
        "\u6771\u5c3e"
    ],
    "wof:name":"Higashio",
    "wof:placetype":"locality"
},
  "geometry": {"coordinates":[130.45791,33.32849],"type":"Point"}
}