{
  "type": "Feature",
  "properties": {
    "gn:admin1_code":"19.0",
    "gn:admin2_code":"7470889.0",
    "gn:asciiname":"Kamigochi",
    "gn:country_code":"JP",
    "gn:dem":15,
    "gn:feature_class":"P",
    "gn:feature_code":"PPL",
    "gn:name":"Kamig\u014dchi",
    "gn:population":0,
    "gn:timezone":"Asia/Tokyo",
    "iso:country":"JP",
    "name:jpn_x_preferred":[
        "\u4e0a\u6cb3\u5185"
    ],
    "name:und_x_variant":[
        "Kamig\u014dchi"
    ],
    "wof:name":"Kamigochi",
    "wof:placetype":"locality"
},
  "geometry": {"coordinates":[139.38983000000002,35.42102],"type":"Point"}
}