{
  "type": "Feature",
  "properties": {
    "gn:admin1_code":"4.0",
    "gn:admin2_code":"2112386.0",
    "gn:asciiname":"Wada",
    "gn:country_code":"JP",
    "gn:dem":62,
    "gn:feature_class":"P",
    "gn:feature_code":"PPLL",
    "gn:name":"Wada",
    "gn:population":0,
    "gn:timezone":"Asia/Tokyo",
    "iso:country":"JP",
    "name:jpn_x_preferred":[
        "\u548c\u7530"
    ],
    "name:jpn_x_variant":[
        "\u308f\u3060",
        "\u30ef\u30c0"
    ],
    "wof:name":"Wada",
    "wof:placetype":"locality"
},
  "geometry": {"coordinates":[140.10092,35.13818],"type":"Point"}
}