{
  "type": "Feature",
  "properties": {
    "gn:admin1_code":"21.0",
    "gn:admin2_code":"1850744.0",
    "gn:admin3_code":"43367.0",
    "gn:asciiname":"Mukaemachi",
    "gn:country_code":"JP",
    "gn:dem":63,
    "gn:feature_class":"P",
    "gn:feature_code":"PPLL",
    "gn:name":"Mukaemachi",
    "gn:population":0,
    "gn:timezone":"Asia/Tokyo",
    "iso:country":"JP",
    "name:jpn_x_preferred":[
        "\u8fce\u753a"
    ],
    "name:jpn_x_variant":[
        "\u3080\u304b\u3048\u307e\u3061",
        "\u30e0\u30ab\u30a8\u30de\u30c1"
    ],
    "wof:name":"Mukaemachi",
    "wof:placetype":"locality"
},
  "geometry": {"coordinates":[130.54268000000002,33.05585],"type":"Point"}
}