{
  "type": "Feature",
  "properties": {
    "gn:admin1_code":"29.0",
    "gn:admin2_code":"1852981.0",
    "gn:asciiname":"Ogibori",
    "gn:country_code":"JP",
    "gn:dem":32,
    "gn:feature_class":"P",
    "gn:feature_code":"PPL",
    "gn:name":"Ogibori",
    "gn:population":0,
    "gn:timezone":"Asia/Tokyo",
    "iso:country":"JP",
    "name:jpn_x_preferred":[
        "\u837b\u5800"
    ],
    "wof:name":"Ogibori",
    "wof:placetype":"locality"
},
  "geometry": {"coordinates":[139.03086999999999,37.57335],"type":"Point"}
}