{
  "type": "Feature",
  "properties": {
    "gn:admin1_code":"21.0",
    "gn:admin2_code":"1859488.0",
    "gn:asciiname":"Kigo",
    "gn:country_code":"JP",
    "gn:dem":581,
    "gn:feature_class":"P",
    "gn:feature_code":"PPLL",
    "gn:name":"Kigo",
    "gn:population":0,
    "gn:timezone":"Asia/Tokyo",
    "iso:country":"JP",
    "name:deu_x_preferred":[
        "Kigo"
    ],
    "name:epo_x_preferred":[
        "Kigo"
    ],
    "name:fra_x_preferred":[
        "Kigo"
    ],
    "name:hrv_x_preferred":[
        "Kigo"
    ],
    "name:hun_x_preferred":[
        "Kigo"
    ],
    "name:jpn_x_preferred":[
        "\u6728\u8b77"
    ],
    "name:jpn_x_variant":[
        "\u304d\u3054",
        "\u30ad\u30b4"
    ],
    "name:ltz_x_preferred":[
        "Kigo"
    ],
    "name:nld_x_preferred":[
        "Kigo"
    ],
    "name:pan_x_preferred":[
        "\u0a15\u0a40\u0a17\u0a4b"
    ],
    "name:pol_x_preferred":[
        "Kigo"
    ],
    "name:rus_x_preferred":[
        "\u041a\u0438\u0433\u043e"
    ],
    "name:spa_x_preferred":[
        "Kigo"
    ],
    "wof:name":"Kigo",
    "wof:placetype":"locality"
},
  "geometry": {"coordinates":[130.92404999999999,33.03515],"type":"Point"}
}