{
  "type": "Feature",
  "properties": {
    "gn:admin1_code":"7.0",
    "gn:admin2_code":"1851269.0",
    "gn:admin3_code":"40602.0",
    "gn:asciiname":"Arahori",
    "gn:country_code":"JP",
    "gn:dem":236,
    "gn:feature_class":"P",
    "gn:feature_code":"PPLL",
    "gn:name":"Arahori",
    "gn:population":0,
    "gn:timezone":"Asia/Tokyo",
    "iso:country":"JP",
    "name:jpn_x_preferred":[
        "\u8352\u5800"
    ],
    "wof:name":"Arahori",
    "wof:placetype":"locality"
},
  "geometry": {"coordinates":[130.90096,33.55223],"type":"Point"}
}