{
  "type": "Feature",
  "properties": {
    "gn:admin1_code":"33.0",
    "gn:admin2_code":"1850832.0",
    "gn:asciiname":"Yunokibaru",
    "gn:country_code":"JP",
    "gn:dem":112,
    "gn:feature_class":"P",
    "gn:feature_code":"PPLL",
    "gn:name":"Yunokibaru",
    "gn:population":0,
    "gn:timezone":"Asia/Tokyo",
    "iso:country":"JP",
    "name:jpn_x_preferred":[
        "\u67da\u30ce\u6728\u539f"
    ],
    "wof:name":"Yunokibaru",
    "wof:placetype":"locality"
},
  "geometry": {"coordinates":[129.95469,33.2352],"type":"Point"}
}