{
  "type": "Feature",
  "properties": {
    "gn:admin1_code":"24.0",
    "gn:admin2_code":"2112261.0",
    "gn:asciiname":"Motoyoshicho-oya",
    "gn:country_code":"JP",
    "gn:dem":16,
    "gn:feature_class":"P",
    "gn:feature_code":"PPL",
    "gn:name":"Motoyoshich\u014d-\u014dya",
    "gn:population":0,
    "gn:timezone":"Asia/Tokyo",
    "iso:country":"JP",
    "name:jpn_x_preferred":[
        "\u672c\u5409\u753a\u5927\u8c37"
    ],
    "name:und_x_variant":[
        "Motoyoshich\u014d-\u014dya",
        "\u014cya"
    ],
    "wof:name":"Motoyoshicho-oya",
    "wof:placetype":"locality"
},
  "geometry": {"coordinates":[141.57329999999999,38.81729],"type":"Point"}
}