{
  "type": "Feature",
  "properties": {
    "gn:admin1_code":"27.0",
    "gn:admin2_code":"1852895.0",
    "gn:asciiname":"Yokotecho",
    "gn:country_code":"JP",
    "gn:dem":95,
    "gn:feature_class":"P",
    "gn:feature_code":"PPL",
    "gn:name":"Yokotech\u014d",
    "gn:population":0,
    "gn:timezone":"Asia/Tokyo",
    "iso:country":"JP",
    "name:jpn_x_preferred":[
        "\u6a2a\u624b\u753a"
    ],
    "name:und_x_variant":[
        "Yokotech\u014d"
    ],
    "wof:name":"Yokotecho",
    "wof:placetype":"locality"
},
  "geometry": {"coordinates":[129.83056000000002,33.1737],"type":"Point"}
}