{
  "type": "Feature",
  "properties": {
    "gn:admin1_code":"19",
    "gn:admin2_code":"7470888.0",
    "gn:asciiname":"Ikego",
    "gn:country_code":"JP",
    "gn:dem":36,
    "gn:feature_class":"P",
    "gn:feature_code":"PPL",
    "gn:name":"Ikego",
    "gn:population":0,
    "gn:timezone":"Asia/Tokyo",
    "iso:country":"JP",
    "name:jpn_x_preferred":[
        "\u6c60\u5b50"
    ],
    "name:jpn_x_variant":[
        "\u3044\u3051\u3054",
        "\u30a4\u30b1\u30b4"
    ],
    "wof:name":"Ikego",
    "wof:placetype":"locality"
},
  "geometry": {"coordinates":[139.59499,35.30398],"type":"Point"}
}