{
  "type": "Feature",
  "properties": {
    "gn:admin1_code":"3.0",
    "gn:admin2_code":"8534376.0",
    "gn:admin3_code":"2323.0",
    "gn:asciiname":"Tatemura",
    "gn:country_code":"JP",
    "gn:dem":74,
    "gn:feature_class":"P",
    "gn:feature_code":"PPL",
    "gn:name":"Tatemura",
    "gn:population":0,
    "gn:timezone":"Asia/Tokyo",
    "iso:country":"JP",
    "name:jpn_x_preferred":[
        "\u9928\u6751"
    ],
    "name:jpn_x_variant":[
        "\u305f\u3066\u3080\u3089",
        "\u30bf\u30c6\u30e0\u30e9"
    ],
    "wof:name":"Tatemura",
    "wof:placetype":"locality"
},
  "geometry": {"coordinates":[140.01626000000002,40.73212],"type":"Point"}
}