{
  "type": "Feature",
  "properties": {
    "gn:admin1_code":"37.0",
    "gn:admin2_code":"1863526.0",
    "gn:asciiname":"Nishikawa",
    "gn:country_code":"JP",
    "gn:dem":282,
    "gn:feature_class":"P",
    "gn:feature_code":"PPLL",
    "gn:name":"Nishikawa",
    "gn:population":0,
    "gn:timezone":"Asia/Tokyo",
    "iso:country":"JP",
    "name:jpn_x_preferred":[
        "\u897f\u5ddd"
    ],
    "wof:name":"Nishikawa",
    "wof:placetype":"locality"
},
  "geometry": {"coordinates":[138.91356000000002,35.22746],"type":"Point"}
}