{
  "type": "Feature",
  "properties": {
    "gn:admin1_code":"3.0",
    "gn:admin2_code":"2128134.0",
    "gn:admin3_code":"2425.0",
    "gn:asciiname":"Sawanokuro",
    "gn:country_code":"JP",
    "gn:dem":16,
    "gn:feature_class":"P",
    "gn:feature_code":"PPL",
    "gn:name":"Sawanokuro",
    "gn:population":0,
    "gn:timezone":"Asia/Tokyo",
    "iso:country":"JP",
    "name:jpn_x_preferred":[
        "\u6ca2\u30ce\u9ed2"
    ],
    "name:jpn_x_variant":[
        "\u3055\u308f\u306e\u304f\u308d",
        "\u30b5\u30ef\u30ce\u30af\u30ed"
    ],
    "wof:name":"Sawanokuro",
    "wof:placetype":"locality"
},
  "geometry": {"coordinates":[140.97331,41.49807],"type":"Point"}
}