{
  "type": "Feature",
  "properties": {
    "gn:admin1_code":"4.0",
    "gn:admin2_code":"2112330.0",
    "gn:asciiname":"Toyoshiki",
    "gn:country_code":"JP",
    "gn:dem":21,
    "gn:feature_class":"P",
    "gn:feature_code":"PPL",
    "gn:name":"Toyoshiki",
    "gn:population":0,
    "gn:timezone":"Asia/Tokyo",
    "iso:country":"JP",
    "name:jpn_x_preferred":[
        "\u8c4a\u56db\u5b63"
    ],
    "wof:name":"Toyoshiki",
    "wof:placetype":"locality"
},
  "geometry": {"coordinates":[139.94908000000001,35.86182],"type":"Point"}
}