{
  "type": "Feature",
  "properties": {
    "gn:admin1_code":"36.0",
    "gn:admin2_code":"1863519.0",
    "gn:asciiname":"Nakatsuchi",
    "gn:country_code":"JP",
    "gn:dem":96,
    "gn:feature_class":"P",
    "gn:feature_code":"PPL",
    "gn:name":"Nakatsuchi",
    "gn:population":0,
    "gn:timezone":"Asia/Tokyo",
    "iso:country":"JP",
    "name:jpn_x_preferred":[
        "\u4e2d\u90fd\u6cbb"
    ],
    "wof:name":"Nakatsuchi",
    "wof:placetype":"locality"
},
  "geometry": {"coordinates":[132.32048,35.03169],"type":"Point"}
}