{
  "type": "Feature",
  "properties": {
    "gn:admin1_code":"34.0",
    "gn:admin2_code":"1864112.0",
    "gn:asciiname":"Kaminanbata",
    "gn:country_code":"JP",
    "gn:dem":9,
    "gn:feature_class":"P",
    "gn:feature_code":"PPL",
    "gn:name":"Kaminanbata",
    "gn:population":0,
    "gn:timezone":"Asia/Tokyo",
    "iso:country":"JP",
    "name:jpn_x_preferred":[
        "\u4e0a\u5357\u7551"
    ],
    "name:jpn_x_variant":[
        "\u304b\u307f\u306a\u3093\u3070\u305f",
        "\u30ab\u30df\u30ca\u30f3\u30d0\u30bf"
    ],
    "wof:name":"Kaminanbata",
    "wof:placetype":"locality"
},
  "geometry": {"coordinates":[139.55883,35.86501],"type":"Point"}
}