{
  "type": "Feature",
  "properties": {
    "gn:admin1_code":"13",
    "gn:admin2_code":"1859671.0",
    "gn:asciiname":"Yamashitacho",
    "gn:country_code":"JP",
    "gn:dem":91,
    "gn:feature_class":"P",
    "gn:feature_code":"PPL",
    "gn:name":"Yamashitach\u014d",
    "gn:population":0,
    "gn:timezone":"Asia/Tokyo",
    "iso:country":"JP",
    "name:jpn_x_preferred":[
        "\u5c71\u4e0b\u753a"
    ],
    "name:und_x_variant":[
        "Yamashitamachi",
        "Yamashita",
        "Yamashitach\u014d"
    ],
    "wof:name":"Yamashitacho",
    "wof:placetype":"locality"
},
  "geometry": {"coordinates":[135.40837999999999,34.89623],"type":"Point"}
}