{
  "type": "Feature",
  "properties": {
    "gn:admin1_code":"2.0",
    "gn:admin2_code":"2110504.0",
    "gn:asciiname":"Budo",
    "gn:country_code":"JP",
    "gn:dem":169,
    "gn:feature_class":"P",
    "gn:feature_code":"PPL",
    "gn:name":"Bud\u014d",
    "gn:population":0,
    "gn:timezone":"Asia/Tokyo",
    "iso:country":"JP",
    "name:deu_x_preferred":[
        "Budo"
    ],
    "name:jpn_x_preferred":[
        "\u6b66\u9053"
    ],
    "name:und_x_variant":[
        "Bud\u014d"
    ],
    "wof:name":"Budo",
    "wof:placetype":"locality"
},
  "geometry": {"coordinates":[140.61688999999998,39.23362],"type":"Point"}
}