{
  "type": "Feature",
  "properties": {
    "gn:admin1_code":"37.0",
    "gn:admin2_code":"9036693.0",
    "gn:asciiname":"Aobane",
    "gn:country_code":"JP",
    "gn:dem":123,
    "gn:feature_class":"P",
    "gn:feature_code":"PPL",
    "gn:name":"Aobane",
    "gn:population":0,
    "gn:timezone":"Asia/Tokyo",
    "iso:country":"JP",
    "name:jpn_x_preferred":[
        "\u9752\u7fbd\u6839"
    ],
    "wof:name":"Aobane",
    "wof:placetype":"locality"
},
  "geometry": {"coordinates":[138.93254999999999,34.93518],"type":"Point"}
}