{
  "type": "Feature",
  "properties": {
    "gn:admin1_code":"15.0",
    "gn:admin2_code":"7467881.0",
    "gn:asciiname":"Kaminomachi",
    "gn:country_code":"JP",
    "gn:dem":178,
    "gn:feature_class":"P",
    "gn:feature_code":"PPL",
    "gn:name":"Kaminomachi",
    "gn:population":0,
    "gn:timezone":"Asia/Tokyo",
    "iso:country":"JP",
    "name:jpn_x_preferred":[
        "\u4e0a\u91ce\u753a"
    ],
    "wof:name":"Kaminomachi",
    "wof:placetype":"locality"
},
  "geometry": {"coordinates":[136.60371999999998,36.37283],"type":"Point"}
}