{
  "type": "Feature",
  "properties": {
    "gn:admin1_code":"32",
    "gn:admin2_code":"1862751.0",
    "gn:asciiname":"Fuse",
    "gn:country_code":"JP",
    "gn:dem":7,
    "gn:feature_class":"P",
    "gn:feature_code":"PPL",
    "gn:name":"Fuse",
    "gn:population":0,
    "gn:timezone":"Asia/Tokyo",
    "iso:country":"JP",
    "wof:name":"Fuse",
    "wof:placetype":"locality"
},
  "geometry": {"coordinates":[135.58333000000002,34.65],"type":"Point"}
}