{
  "type": "Feature",
  "properties": {
    "gn:admin1_code":"32",
    "gn:admin2_code":"1862751.0",
    "gn:asciiname":"Fuse",
    "gn:country_code":"JP",
    "gn:dem":7,
    "gn:feature_class":"P",
    "gn:feature_code":"PPL",
    "gn:name":"Fuse",
    "gn:population":0,
    "gn:timezone":"Asia/Tokyo",
    "iso:country":"JP",
    "name:ara_x_preferred":[
        "\u0641\u064a\u0648\u0632"
    ],
    "name:deu_x_preferred":[
        "Fuse"
    ],
    "name:fra_x_preferred":[
        "Fuse"
    ],
    "name:ita_x_preferred":[
        "Fuse"
    ],
    "name:nld_x_preferred":[
        "Fuse"
    ],
    "name:spa_x_preferred":[
        "Fuse"
    ],
    "name:tur_x_preferred":[
        "Fuse"
    ],
    "wof:name":"Fuse",
    "wof:placetype":"locality"
},
  "geometry": {"coordinates":[135.58333000000002,34.65],"type":"Point"}
}