{
  "type": "Feature",
  "properties": {
    "gn:admin1_code":"24.0",
    "gn:admin2_code":"2112574.0",
    "gn:asciiname":"Tawaraniwa",
    "gn:country_code":"JP",
    "gn:dem":21,
    "gn:feature_class":"P",
    "gn:feature_code":"PPL",
    "gn:name":"Tawaraniwa",
    "gn:population":0,
    "gn:timezone":"Asia/Tokyo",
    "iso:country":"JP",
    "name:jpn_x_preferred":[
        "\u4ff5\u5ead"
    ],
    "name:jpn_x_variant":[
        "\u305f\u308f\u3089\u306b\u308f",
        "\u30bf\u30ef\u30e9\u30cb\u30ef"
    ],
    "wof:name":"Tawaraniwa",
    "wof:placetype":"locality"
},
  "geometry": {"coordinates":[141.20052999999999,38.48595],"type":"Point"}
}