{
  "type": "Feature",
  "properties": {
    "gn:admin1_code":"15",
    "gn:admin2_code":"7467839.0",
    "gn:admin3_code":"17463.0",
    "gn:asciiname":"Matsunami",
    "gn:country_code":"JP",
    "gn:dem":15,
    "gn:feature_class":"P",
    "gn:feature_code":"PPL",
    "gn:name":"Matsunami",
    "gn:population":0,
    "gn:timezone":"Asia/Tokyo",
    "iso:country":"JP",
    "name:jpn_x_preferred":[
        "\u677e\u6ce2"
    ],
    "name:und_x_variant":[
        "Matsnami",
        "Matsunami"
    ],
    "wof:name":"Matsunami",
    "wof:placetype":"locality"
},
  "geometry": {"coordinates":[137.2396,37.35651],"type":"Point"}
}