{
  "type": "Feature",
  "properties": {
    "gn:admin1_code":"3.0",
    "gn:admin2_code":"2130056.0",
    "gn:asciiname":"Fukuromachi",
    "gn:country_code":"JP",
    "gn:dem":32,
    "gn:feature_class":"P",
    "gn:feature_code":"PPL",
    "gn:name":"Fukuromachi",
    "gn:population":0,
    "gn:timezone":"Asia/Tokyo",
    "iso:country":"JP",
    "name:jpn_x_preferred":[
        "\u888b\u753a"
    ],
    "name:jpn_x_variant":[
        "\u3075\u304f\u308d\u307e\u3061",
        "\u30d5\u30af\u30ed\u30de\u30c1"
    ],
    "wof:name":"Fukuromachi",
    "wof:placetype":"locality"
},
  "geometry": {"coordinates":[140.45993000000001,40.60993],"type":"Point"}
}