{
  "type": "Feature",
  "properties": {
    "gn:admin1_code":"10",
    "gn:admin2_code":"1850994.0",
    "gn:asciiname":"Kuraganomachi",
    "gn:country_code":"JP",
    "gn:dem":83,
    "gn:feature_class":"P",
    "gn:feature_code":"PPL",
    "gn:name":"Kuraganomachi",
    "gn:population":0,
    "gn:timezone":"Asia/Tokyo",
    "iso:country":"JP",
    "name:jpn_x_preferred":[
        "\u5009\u8cc0\u91ce\u753a"
    ],
    "name:und_x_variant":[
        "Kuragano"
    ],
    "wof:name":"Kuraganomachi",
    "wof:placetype":"locality"
},
  "geometry": {"coordinates":[139.04787999999999,36.29812],"type":"Point"}
}