{
  "type": "Feature",
  "properties": {
    "gn:admin1_code":"3.0",
    "gn:admin2_code":"8534376.0",
    "gn:admin3_code":"2321.0",
    "gn:asciiname":"Hamamachi",
    "gn:country_code":"JP",
    "gn:dem":5,
    "gn:feature_class":"P",
    "gn:feature_code":"PPL",
    "gn:name":"Hamamachi",
    "gn:population":0,
    "gn:timezone":"Asia/Tokyo",
    "iso:country":"JP",
    "name:jpn_x_preferred":[
        "\u6d5c\u753a"
    ],
    "name:jpn_x_variant":[
        "\u306f\u307e\u307e\u3061",
        "\u30cf\u30de\u30de\u30c1"
    ],
    "wof:name":"Hamamachi",
    "wof:placetype":"locality"
},
  "geometry": {"coordinates":[140.20399,40.7847],"type":"Point"}
}