{
  "type": "Feature",
  "properties": {
    "gn:admin1_code":"23.0",
    "gn:admin2_code":"7417704.0",
    "gn:admin3_code":"24441.0",
    "gn:asciiname":"Asagara",
    "gn:country_code":"JP",
    "gn:dem":87,
    "gn:feature_class":"P",
    "gn:feature_code":"PPL",
    "gn:name":"Asagara",
    "gn:population":0,
    "gn:timezone":"Asia/Tokyo",
    "iso:country":"JP",
    "name:jpn_x_preferred":[
        "\u671d\u67c4"
    ],
    "wof:name":"Asagara",
    "wof:placetype":"locality"
},
  "geometry": {"coordinates":[136.45006000000001,34.45869],"type":"Point"}
}