{
  "type": "Feature",
  "properties": {
    "gn:admin1_code":"3.0",
    "gn:admin2_code":"2129393.0",
    "gn:asciiname":"Oitamachi",
    "gn:country_code":"JP",
    "gn:dem":46,
    "gn:feature_class":"P",
    "gn:feature_code":"PPL",
    "gn:name":"\u014citamachi",
    "gn:population":0,
    "gn:timezone":"Asia/Tokyo",
    "iso:country":"JP",
    "name:jpn_x_preferred":[
        "\u5927\u677f\u753a"
    ],
    "name:jpn_x_variant":[
        "\u304a\u304a\u3044\u305f\u307e\u3061",
        "\u30aa\u30aa\u30a4\u30bf\u30de\u30c1"
    ],
    "name:und_x_variant":[
        "\u014citamachi"
    ],
    "wof:name":"Oitamachi",
    "wof:placetype":"locality"
},
  "geometry": {"coordinates":[140.58822000000001,40.64696],"type":"Point"}
}