{
  "type": "Feature",
  "properties": {
    "gn:admin1_code":"24",
    "gn:admin2_code":"2112261.0",
    "gn:asciiname":"Motoyoshicho-tsuya-akedo",
    "gn:country_code":"JP",
    "gn:dem":13,
    "gn:feature_class":"P",
    "gn:feature_code":"PPL",
    "gn:name":"Motoyoshich\u014d-tsuya-akedo",
    "gn:population":0,
    "gn:timezone":"Asia/Tokyo",
    "iso:country":"JP",
    "name:jpn_x_preferred":[
        "\u672c\u5409\u753a\u6d25\u8c37\u660e\u6238"
    ],
    "name:und_x_variant":[
        "Motoyoshich\u014d-tsuya-akedo",
        "Tsuya"
    ],
    "wof:name":"Motoyoshicho-tsuya-akedo",
    "wof:placetype":"locality"
},
  "geometry": {"coordinates":[141.49563999999995,38.78793],"type":"Point"}
}