{
  "type": "Feature",
  "properties": {
    "iso:country":"JP",
    "name:eng_x_preferred":[
        "Katsuragi 3 Chome"
    ],
    "name:eng_x_variant":[
        "Katsuragi 3 Choume",
        "Katsuragi 3 Chome"
    ],
    "name:jpn_x_preferred":[
        "\uff13\u4e01\u76ee"
    ],
    "name:jpn_x_variant":[
        "\u304b\u3064\u3089\u304e \uff13\u3061\u3087\u3046\u3081",
        "\u845b\u57ce \uff13\u4e01\u76ee",
        "\uff13\u3061\u3087\u3046\u3081"
    ],
    "qs:gn_adm0_cc":"JP",
    "qs:gn_local":2113015,
    "qs:gn_nam_loc":"\u5343\u8449\u5e02, \u5343\u8449\u770c, JP",
    "qs:gn_namadm1":"04",
    "qs:local_max":7724,
    "qs:local_sum":19805,
    "qs:localhoods":49,
    "qs:name":"\uff13\u4e01\u76ee",
    "qs:name_adm0":"\u65e5\u672c",
    "qs:name_adm1":"\u5343\u8449\u770c",
    "qs:name_adm2":"\u4e2d\u592e\u533a",
    "qs:name_en":"Katsuragi 3 Chome",
    "qs:name_lau":"\u845b\u57ce",
    "qs:name_local":"\u5343\u8449\u5e02",
    "qs:photo_max":35,
    "qs:photo_sum":129,
    "qs:placetype":"Suburb",
    "qs:quad_count":19,
    "qs:woe_adm0":23424856,
    "qs:woe_adm1":2345854,
    "qs:woe_adm2":15015398,
    "qs:woe_lau":28410500,
    "qs:woe_local":1117034,
    "qs:woe_ver":"7.10.0",
    "wof:lang":[
        "jpn"
    ],
    "wof:name":"\uff13\u4e01\u76ee",
    "wof:placetype":"neighbourhood"
},
  "geometry": {"coordinates":[140.140197,35.595642],"type":"Point"}
}