{
  "type": "Feature",
  "properties": {
    "iso:country":"JP",
    "name:eng_x_preferred":[
        "Itakuracho 3 Chome"
    ],
    "name:eng_x_variant":[
        "Itakurachou 3 Choume",
        "Itakuracho 3 Chome"
    ],
    "name:jpn_x_preferred":[
        "\uff13\u4e01\u76ee"
    ],
    "name:jpn_x_variant":[
        "\u3044\u305f\u304f\u3089\u3061\u3087\u3046 \uff13\u3061\u3087\u3046\u3081",
        "\u677f\u5009\u753a \uff13\u4e01\u76ee",
        "\uff13\u3061\u3087\u3046\u3081"
    ],
    "qs:gn_local":0,
    "qs:local_max":105,
    "qs:local_sum":201,
    "qs:localhoods":3,
    "qs:name":"\uff13\u4e01\u76ee",
    "qs:name_adm0":"\u65e5\u672c",
    "qs:name_adm1":"\u611b\u77e5\u770c",
    "qs:name_en":"Itakuracho 3 Chome",
    "qs:name_lau":"\u677f\u5009\u753a",
    "qs:name_local":"\u5208\u8c37\u5e02",
    "qs:photo_max":1,
    "qs:photo_sum":1,
    "qs:placetype":"Suburb",
    "qs:quad_count":1,
    "qs:woe_adm0":23424856,
    "qs:woe_adm1":2345851,
    "qs:woe_adm2":0,
    "qs:woe_lau":28442214,
    "qs:woe_local":1117455,
    "qs:woe_ver":"7.10.0",
    "wof:lang":[
        "jpn"
    ],
    "wof:name":"\uff13\u4e01\u76ee",
    "wof:placetype":"neighbourhood"
},
  "geometry": {"coordinates":[137.04070999999999,34.987255],"type":"Point"}
}