{
  "type": "Feature",
  "properties": {
    "gn:admin1_code":"29",
    "gn:admin2_code":"1859907.0",
    "gn:asciiname":"Shiiya",
    "gn:country_code":"JP",
    "gn:dem":100,
    "gn:feature_class":"P",
    "gn:feature_code":"PPL",
    "gn:name":"Shiiya",
    "gn:population":0,
    "gn:timezone":"Asia/Tokyo",
    "iso:country":"JP",
    "name:jpn_x_preferred":[
        "\u690e\u8c37"
    ],
    "wof:name":"Shiiya",
    "wof:placetype":"locality"
},
  "geometry": {"coordinates":[138.62121999999999,37.48193],"type":"Point"}
}