{
  "type": "Feature",
  "properties": {
    "gn:admin1_code":"7.0",
    "gn:admin2_code":"7407415.0",
    "gn:asciiname":"Takatamachi-tajiri",
    "gn:country_code":"JP",
    "gn:dem":5,
    "gn:feature_class":"P",
    "gn:feature_code":"PPL",
    "gn:name":"Takatamachi-tajiri",
    "gn:population":0,
    "gn:timezone":"Asia/Tokyo",
    "iso:country":"JP",
    "name:jpn_x_preferred":[
        "\u9ad8\u7530\u753a\u7530\u5c3b"
    ],
    "wof:name":"Takatamachi-tajiri",
    "wof:placetype":"locality"
},
  "geometry": {"coordinates":[130.4846,33.11658],"type":"Point"}
}