{
  "type": "Feature",
  "properties": {
    "iso:country":"JP",
    "name:eng_x_preferred":[
        "Yamauchi 4 Chome"
    ],
    "name:eng_x_variant":[
        "Yamauchi 4 Choume",
        "Yamauchi 4 Chome"
    ],
    "name:jpn_x_preferred":[
        "\uff14\u4e01\u76ee"
    ],
    "name:jpn_x_variant":[
        "\u3084\u307e\u3046\u3061 \uff14\u3061\u3087\u3046\u3081",
        "\u5c71\u5185 \uff14\u4e01\u76ee",
        "\uff14\u3061\u3087\u3046\u3081"
    ],
    "name:unk_x_variant":[
        "\uff14\u4e01\u76ee"
    ],
    "qs:gn_adm0_cc":"JP",
    "qs:gn_local":1894616,
    "qs:gn_nam_loc":"\u6c96\u7e04\u5e02, \u6c96\u7e04\u770c, JP",
    "qs:gn_namadm1":"47",
    "qs:local_max":4858,
    "qs:local_sum":8480,
    "qs:localhoods":14,
    "qs:name":"\uff14\u4e01\u76ee",
    "qs:name_adm0":"\u65e5\u672c",
    "qs:name_adm1":"\u6c96\u7e04\u770c",
    "qs:name_en":"Yamauchi 4 Chome",
    "qs:name_lau":"\u5c71\u5185",
    "qs:name_local":"\u6c96\u7e04\u5e02",
    "qs:photo_max":1,
    "qs:photo_sum":1,
    "qs:placetype":"Suburb",
    "qs:quad_count":1,
    "qs:woe_adm0":23424856,
    "qs:woe_adm1":2345896,
    "qs:woe_adm2":0,
    "qs:woe_lau":28494051,
    "qs:woe_local":1113469,
    "qs:woe_ver":"7.10.0",
    "wof:lang":[
        "jpn"
    ],
    "wof:name":"\uff14\u4e01\u76ee",
    "wof:placetype":"neighbourhood"
},
  "geometry": {"coordinates":[127.76824999999999,26.345114],"type":"Point"}
}