{
  "type": "Feature",
  "properties": {
    "gn:admin1_code":"4.0",
    "gn:admin2_code":"1857552.0",
    "gn:asciiname":"Hachigasaki",
    "gn:country_code":"JP",
    "gn:dem":29,
    "gn:feature_class":"P",
    "gn:feature_code":"PPL",
    "gn:name":"Hachigasaki",
    "gn:population":0,
    "gn:timezone":"Asia/Tokyo",
    "iso:country":"JP",
    "name:jpn_x_preferred":[
        "\u516b\u30f6\u5d0e"
    ],
    "wof:name":"Hachigasaki",
    "wof:placetype":"locality"
},
  "geometry": {"coordinates":[139.93336000000002,35.81268],"type":"Point"}
}