{
  "type": "Feature",
  "properties": {
    "gn:admin1_code":"19.0",
    "gn:admin2_code":"1861448.0",
    "gn:asciiname":"Shimohirama",
    "gn:country_code":"JP",
    "gn:dem":13,
    "gn:feature_class":"P",
    "gn:feature_code":"PPL",
    "gn:name":"Shimohirama",
    "gn:population":0,
    "gn:timezone":"Asia/Tokyo",
    "iso:country":"JP",
    "name:jpn_x_preferred":[
        "\u4e0b\u5e73\u9593"
    ],
    "wof:name":"Shimohirama",
    "wof:placetype":"locality"
},
  "geometry": {"coordinates":[139.32241999999999,35.38281],"type":"Point"}
}