{
  "type": "Feature",
  "properties": {
    "gn:admin1_code":"7.0",
    "gn:admin2_code":"7407413.0",
    "gn:asciiname":"Kamiusui-higashi",
    "gn:country_code":"JP",
    "gn:dem":37,
    "gn:feature_class":"P",
    "gn:feature_code":"PPLL",
    "gn:name":"Kamiusui-higashi",
    "gn:population":0,
    "gn:timezone":"Asia/Tokyo",
    "iso:country":"JP",
    "name:jpn_x_preferred":[
        "\u4e0a\u81fc\u4e95\u6771"
    ],
    "wof:name":"Kamiusui-higashi",
    "wof:placetype":"locality"
},
  "geometry": {"coordinates":[130.71364,33.56278],"type":"Point"}
}