{
  "type": "Feature",
  "properties": {
    "gn:admin1_code":"21.0",
    "gn:admin2_code":"7412706.0",
    "gn:admin3_code":"43447.0",
    "gn:asciiname":"Odara",
    "gn:country_code":"JP",
    "gn:dem":424,
    "gn:feature_class":"P",
    "gn:feature_code":"PPLL",
    "gn:name":"\u014cdara",
    "gn:population":0,
    "gn:timezone":"Asia/Tokyo",
    "iso:country":"JP",
    "name:jpn_x_preferred":[
        "\u5927\u591a\u826f"
    ],
    "name:jpn_x_variant":[
        "\u304a\u304a\u3060\u3089",
        "\u30aa\u30aa\u30c0\u30e9"
    ],
    "name:und_x_variant":[
        "\u014cdara"
    ],
    "wof:name":"Odara",
    "wof:placetype":"locality"
},
  "geometry": {"coordinates":[130.99361999999999,32.63616],"type":"Point"}
}