{
  "type": "Feature",
  "properties": {
    "gn:admin1_code":"4.0",
    "gn:admin2_code":"2112330.0",
    "gn:asciiname":"Midoridai",
    "gn:country_code":"JP",
    "gn:dem":22,
    "gn:feature_class":"P",
    "gn:feature_code":"PPL",
    "gn:name":"Midoridai",
    "gn:population":0,
    "gn:timezone":"Asia/Tokyo",
    "iso:country":"JP",
    "name:jpn_x_preferred":[
        "\u307f\u3069\u308a\u53f0"
    ],
    "wof:name":"Midoridai",
    "wof:placetype":"locality"
},
  "geometry": {"coordinates":[139.92306000000002,35.90294],"type":"Point"}
}