{
  "type": "Feature",
  "properties": {
    "gn:admin1_code":"35",
    "gn:admin2_code":"7394802.0",
    "gn:asciiname":"Ibuki",
    "gn:cc2":"JP",
    "gn:country_code":"JP",
    "gn:dem":181,
    "gn:feature_class":"P",
    "gn:feature_code":"PPL",
    "gn:name":"Ibuki",
    "gn:population":0,
    "gn:timezone":"Asia/Tokyo",
    "iso:country":"JP",
    "name:fra_x_preferred":[
        "Mont Ibuki"
    ],
    "name:ind_x_preferred":[
        "Gunung Ibuki"
    ],
    "name:jpn_x_preferred":[
        "\u4f0a\u5439\u5c71"
    ],
    "name:pnb_x_preferred":[
        "\u0679\u0644\u06c1 \u0627\u06cc\u0628\u0648\u06a9\u06cc"
    ],
    "name:pol_x_preferred":[
        "Ibuki"
    ],
    "name:rus_x_preferred":[
        "\u0418\u0431\u0443\u043a\u0438"
    ],
    "name:spa_x_preferred":[
        "Monte Ibuki"
    ],
    "name:ukr_x_preferred":[
        "\u0406\u0431\u0443\u043a\u0456"
    ],
    "name:und_x_variant":[
        "Ibukiyama"
    ],
    "name:vie_x_preferred":[
        "N\u00fai Ibuki"
    ],
    "name:zho_x_preferred":[
        "\u4f0a\u5439\u5c71"
    ],
    "wof:name":"Ibuki",
    "wof:placetype":"locality"
},
  "geometry": {"coordinates":[136.37809999999999,35.38891],"type":"Point"}
}