{
  "type": "Feature",
  "properties": {
    "gn:admin1_code":"21.0",
    "gn:admin2_code":"7412708.0",
    "gn:admin3_code":"43505.0",
    "gn:asciiname":"Nagahira",
    "gn:country_code":"JP",
    "gn:dem":192,
    "gn:feature_class":"P",
    "gn:feature_code":"PPLL",
    "gn:name":"Nagahira",
    "gn:population":0,
    "gn:timezone":"Asia/Tokyo",
    "iso:country":"JP",
    "name:jpn_x_preferred":[
        "\u9577\u5e73"
    ],
    "name:jpn_x_variant":[
        "\u306a\u304c\u3072\u3089",
        "\u30ca\u30ac\u30d2\u30e9"
    ],
    "wof:name":"Nagahira",
    "wof:placetype":"locality"
},
  "geometry": {"coordinates":[130.92753000000002,32.28528],"type":"Point"}
}