{
  "type": "Feature",
  "properties": {
    "iso:country":"JP",
    "qs:name":"\u660e\u548c\u753a",
    "qs:name_adm0":"\u65e5\u672c",
    "qs:name_adm1":"\u7fa4\u99ac\u770c",
    "qs:photos":21,
    "qs:photos_1k":4,
    "qs:photos_9k":1,
    "qs:photos_9r":1,
    "qs:photos_all":21,
    "qs:photos_sr":1,
    "qs:placetype":"Town",
    "qs:pop_sr":"0",
    "wof:name":"\u660e\u548c\u753a",
    "wof:placetype":"locality"
},
  "geometry": {"coordinates":[139.54619400000001,36.2145],"type":"Point"}
}