{
  "type": "Feature",
  "properties": {
    "gn:admin1_code":"12.0",
    "gn:asciiname":"Moto-wanishimachi",
    "gn:cc2":"JP",
    "gn:country_code":"JP",
    "gn:dem":1,
    "gn:feature_class":"P",
    "gn:feature_code":"PPL",
    "gn:name":"Moto-wanishimachi",
    "gn:population":0,
    "gn:timezone":"Asia/Tokyo",
    "iso:country":"JP",
    "name:und_x_variant":[
        "Moto-wanishich\u014d",
        "Moto-wanishi",
        "Moto-wanishimachi"
    ],
    "wof:name":"Moto-wanishimachi",
    "wof:placetype":"locality"
},
  "geometry": {"coordinates":[140.97528,42.35694],"type":"Point"}
}