{
  "type": "Feature",
  "properties": {
    "gn:admin1_code":"8.0",
    "gn:admin2_code":"7451502.0",
    "gn:admin3_code":"7501.0",
    "gn:asciiname":"Wagu",
    "gn:country_code":"JP",
    "gn:dem":313,
    "gn:feature_class":"P",
    "gn:feature_code":"PPL",
    "gn:name":"Wagu",
    "gn:population":0,
    "gn:timezone":"Asia/Tokyo",
    "iso:country":"JP",
    "name:jpn_x_preferred":[
        "\u548c\u4e45"
    ],
    "wof:name":"Wagu",
    "wof:placetype":"locality"
},
  "geometry": {"coordinates":[140.41997000000001,37.16272],"type":"Point"}
}