{
  "type": "Feature",
  "properties": {
    "gn:admin1_code":"34.0",
    "gn:admin2_code":"1858728.0",
    "gn:asciiname":"Sunahara",
    "gn:country_code":"JP",
    "gn:dem":5,
    "gn:feature_class":"P",
    "gn:feature_code":"PPL",
    "gn:name":"Sunahara",
    "gn:population":0,
    "gn:timezone":"Asia/Tokyo",
    "iso:country":"JP",
    "name:jpn_x_preferred":[
        "\u7802\u539f"
    ],
    "wof:name":"Sunahara",
    "wof:placetype":"locality"
},
  "geometry": {"coordinates":[139.75632999999999,35.91368],"type":"Point"}
}