{
  "type": "Feature",
  "properties": {
    "gn:admin1_code":"34.0",
    "gn:admin2_code":"1854369.0",
    "gn:asciiname":"Hinotsume",
    "gn:country_code":"JP",
    "gn:dem":10,
    "gn:feature_class":"P",
    "gn:feature_code":"PPLL",
    "gn:name":"Hinotsume",
    "gn:population":0,
    "gn:timezone":"Asia/Tokyo",
    "iso:country":"JP",
    "name:jpn_x_preferred":[
        "\u6a0b\u8a70"
    ],
    "wof:name":"Hinotsume",
    "wof:placetype":"locality"
},
  "geometry": {"coordinates":[139.53641000000002,35.97521],"type":"Point"}
}