{
  "type": "Feature",
  "properties": {
    "gn:admin1_code":"21.0",
    "gn:admin2_code":"1848441.0",
    "gn:asciiname":"Sashino",
    "gn:country_code":"JP",
    "gn:dem":52,
    "gn:feature_class":"P",
    "gn:feature_code":"PPLL",
    "gn:name":"Sashino",
    "gn:population":0,
    "gn:timezone":"Asia/Tokyo",
    "iso:country":"JP",
    "name:jpn_x_preferred":[
        "\u5dee\u91ce"
    ],
    "name:jpn_x_variant":[
        "\u3055\u3057\u306e",
        "\u30b5\u30b7\u30ce"
    ],
    "wof:name":"Sashino",
    "wof:placetype":"locality"
},
  "geometry": {"coordinates":[130.73183,32.54991],"type":"Point"}
}