{
  "type": "Feature",
  "properties": {
    "gn:admin1_code":"18.0",
    "gn:admin2_code":"7383991.0",
    "gn:asciiname":"Okuchi-tashiro",
    "gn:country_code":"JP",
    "gn:dem":236,
    "gn:feature_class":"P",
    "gn:feature_code":"PPL",
    "gn:name":"\u014ckuchi-tashiro",
    "gn:population":0,
    "gn:timezone":"Asia/Tokyo",
    "iso:country":"JP",
    "name:jpn_x_preferred":[
        "\u5927\u53e3\u7530\u4ee3"
    ],
    "name:jpn_x_variant":[
        "\u304a\u304a\u304f\u3061\u305f\u3057\u308d",
        "\u30aa\u30aa\u30af\u30c1\u30bf\u30b7\u30ed"
    ],
    "name:und_x_variant":[
        "\u014ckuchi-tashiro"
    ],
    "wof:name":"Okuchi-tashiro",
    "wof:placetype":"locality"
},
  "geometry": {"coordinates":[130.53368999999998,32.02785],"type":"Point"}
}