{
  "type": "Feature",
  "properties": {
    "gn:admin1_code":"24.0",
    "gn:admin2_code":"2112261.0",
    "gn:asciiname":"Akaiwa-monomi",
    "gn:country_code":"JP",
    "gn:dem":184,
    "gn:feature_class":"P",
    "gn:feature_code":"PPL",
    "gn:name":"Akaiwa-monomi",
    "gn:population":0,
    "gn:timezone":"Asia/Tokyo",
    "iso:country":"JP",
    "name:jpn_x_preferred":[
        "\u8d64\u5ca9\u7269\u898b"
    ],
    "name:jpn_x_variant":[
        "\u3042\u304b\u3044\u308f\u3082\u306e\u307f",
        "\u30a2\u30ab\u30a4\u30ef\u30e2\u30ce\u30df"
    ],
    "wof:name":"Akaiwa-monomi",
    "wof:placetype":"locality"
},
  "geometry": {"coordinates":[141.52003999999999,38.8466],"type":"Point"}
}