{
  "type": "Feature",
  "properties": {
    "gn:admin1_code":"33.0",
    "gn:admin2_code":"1853274.0",
    "gn:asciiname":"Fujicho-kamabaru",
    "gn:country_code":"JP",
    "gn:dem":288,
    "gn:feature_class":"P",
    "gn:feature_code":"PPL",
    "gn:name":"Fujich\u014d-kamabaru",
    "gn:population":0,
    "gn:timezone":"Asia/Tokyo",
    "iso:country":"JP",
    "name:jpn_x_preferred":[
        "\u5bcc\u58eb\u753a\u938c\u539f"
    ],
    "name:und_x_variant":[
        "Fujich\u014d-kamabaru"
    ],
    "wof:name":"Fujicho-kamabaru",
    "wof:placetype":"locality"
},
  "geometry": {"coordinates":[130.19699,33.35669],"type":"Point"}
}