{
  "type": "Feature",
  "properties": {
    "gn:admin1_code":"22.0",
    "gn:admin2_code":"1857906.0",
    "gn:admin3_code":"26111.0",
    "gn:asciiname":"Tonohatacho",
    "gn:country_code":"JP",
    "gn:dem":417,
    "gn:feature_class":"P",
    "gn:feature_code":"PPLL",
    "gn:name":"Tonohatach\u014d",
    "gn:population":0,
    "gn:timezone":"Asia/Tokyo",
    "iso:country":"JP",
    "name:jpn_x_preferred":[
        "\u5916\u7551\u753a"
    ],
    "name:und_x_variant":[
        "Tonohatach\u014d"
    ],
    "wof:name":"Tonohatacho",
    "wof:placetype":"locality"
},
  "geometry": {"coordinates":[135.62374,34.96581],"type":"Point"}
}