{
  "type": "Feature",
  "properties": {
    "gn:admin1_code":"7.0",
    "gn:admin2_code":"7406950.0",
    "gn:admin3_code":"40621.0",
    "gn:asciiname":"Nagahamacho",
    "gn:country_code":"JP",
    "gn:dem":4,
    "gn:feature_class":"P",
    "gn:feature_code":"PPL",
    "gn:name":"Nagahamach\u014d",
    "gn:population":0,
    "gn:timezone":"Asia/Tokyo",
    "iso:country":"JP",
    "name:jpn_x_preferred":[
        "\u9577\u6d5c\u753a"
    ],
    "name:und_x_variant":[
        "Nagahamach\u014d"
    ],
    "wof:name":"Nagahamacho",
    "wof:placetype":"locality"
},
  "geometry": {"coordinates":[130.99579,33.78316],"type":"Point"}
}