{
  "type": "Feature",
  "properties": {
    "iso:country":"JP",
    "name:eng_x_preferred":[
        "Asahicho 3 Chome"
    ],
    "name:eng_x_variant":[
        "Asahichou 3 Choume",
        "Asahicho 3 Chome"
    ],
    "name:jpn_x_preferred":[
        "\uff13\u4e01\u76ee"
    ],
    "name:jpn_x_variant":[
        "\u3042\u3055\u3072\u3061\u3087\u3046 \uff13\u3061\u3087\u3046\u3081",
        "\u671d\u65e5\u753a \uff13\u4e01\u76ee",
        "\uff13\u3061\u3087\u3046\u3081"
    ],
    "qs:gn_local":0,
    "qs:local_max":1792,
    "qs:local_sum":5754,
    "qs:localhoods":16,
    "qs:name":"\uff13\u4e01\u76ee",
    "qs:name_adm0":"\u65e5\u672c",
    "qs:name_adm1":"\u6771\u4eac\u90fd",
    "qs:name_en":"Asahicho 3 Chome",
    "qs:name_lau":"\u671d\u65e5\u753a",
    "qs:name_local":"\u5e9c\u4e2d\u5e02",
    "qs:photo_max":12,
    "qs:photo_sum":26,
    "qs:placetype":"Suburb",
    "qs:quad_count":5,
    "qs:woe_adm0":23424856,
    "qs:woe_adm1":2345889,
    "qs:woe_adm2":0,
    "qs:woe_lau":28414992,
    "qs:woe_local":1108027,
    "qs:woe_ver":"7.10.0",
    "wof:lang":[
        "jpn"
    ],
    "wof:name":"\uff13\u4e01\u76ee",
    "wof:placetype":"neighbourhood"
},
  "geometry": {"coordinates":[139.52057300000001,35.666042],"type":"Point"}
}