{
  "type": "Feature",
  "properties": {
    "gn:admin1_code":"44.0",
    "gn:admin2_code":"2111850.0",
    "gn:admin3_code":"6362.0",
    "gn:asciiname":"Maginohara",
    "gn:country_code":"JP",
    "gn:dem":261,
    "gn:feature_class":"P",
    "gn:feature_code":"PPL",
    "gn:name":"Maginohara",
    "gn:population":0,
    "gn:timezone":"Asia/Tokyo",
    "iso:country":"JP",
    "name:jpn_x_preferred":[
        "\u4e07\u9a0e\u30ce\u539f"
    ],
    "name:jpn_x_variant":[
        "\u307e\u304e\u306e\u306f\u3089",
        "\u30de\u30ae\u30ce\u30cf\u30e9"
    ],
    "wof:name":"Maginohara",
    "wof:placetype":"locality"
},
  "geometry": {"coordinates":[140.55151000000001,38.72283],"type":"Point"}
}