{
  "type": "Feature",
  "properties": {
    "gn:admin1_code":"26.0",
    "gn:admin2_code":"1856209.0",
    "gn:asciiname":"Minaminagano",
    "gn:country_code":"JP",
    "gn:dem":377,
    "gn:feature_class":"P",
    "gn:feature_code":"PPL",
    "gn:name":"Minaminagano",
    "gn:population":0,
    "gn:timezone":"Asia/Tokyo",
    "iso:country":"JP",
    "name:jpn_x_preferred":[
        "\u5357\u9577\u91ce"
    ],
    "wof:name":"Minaminagano",
    "wof:placetype":"locality"
},
  "geometry": {"coordinates":[138.17930000000001,36.65241],"type":"Point"}
}