{
  "type": "Feature",
  "properties": {
    "gn:admin1_code":"3.0",
    "gn:admin2_code":"2130056.0",
    "gn:asciiname":"Subaru",
    "gn:country_code":"JP",
    "gn:dem":58,
    "gn:feature_class":"P",
    "gn:feature_code":"PPL",
    "gn:name":"Subaru",
    "gn:population":0,
    "gn:timezone":"Asia/Tokyo",
    "iso:country":"JP",
    "name:ara_x_preferred":[
        "\u0633\u0648\u0628\u0627\u0631\u0648"
    ],
    "name:ast_x_preferred":[
        "Subaru"
    ],
    "name:azb_x_preferred":[
        "\u0633\u0648\u0628\u0627\u0631\u0648"
    ],
    "name:aze_x_preferred":[
        "Subaru"
    ],
    "name:bel_x_preferred":[
        "Subaru"
    ],
    "name:cat_x_preferred":[
        "Subaru"
    ],
    "name:ces_x_preferred":[
        "Subaru"
    ],
    "name:dan_x_preferred":[
        "Subaru"
    ],
    "name:deu_x_preferred":[
        "Subaru"
    ],
    "name:ell_x_preferred":[
        "Subaru"
    ],
    "name:est_x_preferred":[
        "Subaru"
    ],
    "name:eus_x_preferred":[
        "Subaru"
    ],
    "name:fas_x_preferred":[
        "\u0633\u0648\u0628\u0627\u0631\u0648"
    ],
    "name:fin_x_preferred":[
        "Subaru"
    ],
    "name:fra_x_preferred":[
        "Subaru"
    ],
    "name:heb_x_preferred":[
        "\u05e1\u05d5\u05d1\u05d0\u05e8\u05d5"
    ],
    "name:hrv_x_preferred":[
        "Subaru"
    ],
    "name:hun_x_preferred":[
        "Subaru"
    ],
    "name:hye_x_preferred":[
        "\u054d\u0578\u0582\u0562\u0561\u0580\u0578\u0582"
    ],
    "name:ind_x_preferred":[
        "Subaru"
    ],
    "name:isl_x_preferred":[
        "Subaru"
    ],
    "name:ita_x_preferred":[
        "Subaru"
    ],
    "name:jpn_x_preferred":[
        "\u6634"
    ],
    "name:jpn_x_variant":[
        "\u3059\u3070\u308b",
        "\u30b9\u30d0\u30eb"
    ],
    "name:kor_x_preferred":[
        "\uc2a4\ubc14\ub8e8"
    ],
    "name:lav_x_preferred":[
        "Subaru"
    ],
    "name:lin_x_preferred":[
        "Subaru"
    ],
    "name:lit_x_preferred":[
        "Subaru"
    ],
    "name:msa_x_preferred":[
        "Subaru"
    ],
    "name:nld_x_preferred":[
        "Subaru"
    ],
    "name:nor_x_preferred":[
        "Subaru"
    ],
    "name:pms_x_preferred":[
        "Subaru"
    ],
    "name:pol_x_preferred":[
        "Subaru"
    ],
    "name:por_x_preferred":[
        "Subaru"
    ],
    "name:ron_x_preferred":[
        "Subaru"
    ],
    "name:rus_x_preferred":[
        "Subaru"
    ],
    "name:sco_x_preferred":[
        "Subaru"
    ],
    "name:slk_x_preferred":[
        "Subaru"
    ],
    "name:slv_x_preferred":[
        "Subaru"
    ],
    "name:spa_x_preferred":[
        "Subaru"
    ],
    "name:sqi_x_preferred":[
        "Subaru"
    ],
    "name:srp_x_preferred":[
        "\u0421\u0443\u0431\u0430\u0440\u0443"
    ],
    "name:swa_x_preferred":[
        "Subaru"
    ],
    "name:swe_x_preferred":[
        "Subaru"
    ],
    "name:tha_x_preferred":[
        "\u0e0b\u0e39\u0e1a\u0e32\u0e23\u0e38"
    ],
    "name:tur_x_preferred":[
        "Subaru"
    ],
    "name:ukr_x_preferred":[
        "Subaru"
    ],
    "name:vie_x_preferred":[
        "Subaru"
    ],
    "name:zho_x_preferred":[
        "\u901f\u9738\u9678\u6c7d\u8eca"
    ],
    "wof:name":"Subaru",
    "wof:placetype":"locality"
},
  "geometry": {"coordinates":[140.40823999999998,40.58795],"type":"Point"}
}