{
  "type": "Feature",
  "properties": {
    "gn:admin1_code":"3.0",
    "gn:admin2_code":"2130056.0",
    "gn:asciiname":"Subaru",
    "gn:country_code":"JP",
    "gn:dem":58,
    "gn:feature_class":"P",
    "gn:feature_code":"PPL",
    "gn:name":"Subaru",
    "gn:population":0,
    "gn:timezone":"Asia/Tokyo",
    "iso:country":"JP",
    "name:jpn_x_preferred":[
        "\u6634"
    ],
    "name:jpn_x_variant":[
        "\u3059\u3070\u308b",
        "\u30b9\u30d0\u30eb"
    ],
    "wof:name":"Subaru",
    "wof:placetype":"locality"
},
  "geometry": {"coordinates":[140.40823999999998,40.58795],"type":"Point"}
}