{
  "type": "Feature",
  "properties": {
    "gn:admin1_code":"36.0",
    "gn:admin2_code":"1854361.0",
    "gn:admin3_code":"32528.0",
    "gn:asciiname":"Araki",
    "gn:country_code":"JP",
    "gn:dem":40,
    "gn:feature_class":"P",
    "gn:feature_code":"PPL",
    "gn:name":"Araki",
    "gn:population":0,
    "gn:timezone":"Asia/Tokyo",
    "iso:country":"JP",
    "name:ceb_x_preferred":[
        "Araki"
    ],
    "name:deu_x_preferred":[
        "Araki"
    ],
    "name:fra_x_preferred":[
        "Araki"
    ],
    "name:ita_x_preferred":[
        "Araki"
    ],
    "name:jpn_x_preferred":[
        "\u6709\u6728"
    ],
    "name:nld_x_preferred":[
        "Araki"
    ],
    "name:por_x_preferred":[
        "Araki"
    ],
    "name:rus_x_preferred":[
        "\u0410\u0440\u0430\u043a\u0438"
    ],
    "name:ukr_x_preferred":[
        "\u0410\u0440\u0430\u043a\u0456"
    ],
    "name:vie_x_preferred":[
        "Araki"
    ],
    "wof:name":"Araki",
    "wof:placetype":"locality"
},
  "geometry": {"coordinates":[133.31735,36.22549],"type":"Point"}
}