{
  "type": "Feature",
  "properties": {
    "gn:admin1_code":"8.0",
    "gn:admin2_code":"2112139.0",
    "gn:asciiname":"Fukuyamamachi-fukuhara",
    "gn:country_code":"JP",
    "gn:dem":226,
    "gn:feature_class":"P",
    "gn:feature_code":"PPL",
    "gn:name":"Fukuyamamachi-fukuhara",
    "gn:population":0,
    "gn:timezone":"Asia/Tokyo",
    "iso:country":"JP",
    "name:jpn_x_preferred":[
        "\u5bcc\u4e45\u5c71\u753a\u798f\u539f"
    ],
    "name:und_x_variant":[
        "Fukuhara",
        "Fukuwara",
        "Fukuyamamachi-fukuhara"
    ],
    "wof:name":"Fukuyamamachi-fukuhara",
    "wof:placetype":"locality"
},
  "geometry": {"coordinates":[140.39861999999999,37.42048],"type":"Point"}
}