{
  "type": "Feature",
  "properties": {
    "gn:admin1_code":"25",
    "gn:admin2_code":"1855473.0",
    "gn:asciiname":"Yowara",
    "gn:cc2":"JP",
    "gn:country_code":"JP",
    "gn:dem":38,
    "gn:feature_class":"P",
    "gn:feature_code":"PPL",
    "gn:name":"Yowara",
    "gn:population":0,
    "gn:timezone":"Asia/Tokyo",
    "iso:country":"JP",
    "name:und_x_variant":[
        "Hashinokuchi",
        "Yohara",
        "Yowara"
    ],
    "wof:name":"Yowara",
    "wof:placetype":"locality"
},
  "geometry": {"coordinates":[131.31666999999999,31.53333],"type":"Point"}
}