{
  "type": "Feature",
  "properties": {
    "gn:admin1_code":"4.0",
    "gn:admin2_code":"1859468.0",
    "gn:asciiname":"Utsubo",
    "gn:country_code":"JP",
    "gn:dem":61,
    "gn:feature_class":"P",
    "gn:feature_code":"PPLL",
    "gn:name":"Utsubo",
    "gn:population":0,
    "gn:timezone":"Asia/Tokyo",
    "iso:country":"JP",
    "name:jpn_x_preferred":[
        "\u5b87\u576a"
    ],
    "name:jpn_x_variant":[
        "\u3046\u3064\u307c",
        "\u30a6\u30c4\u30dc"
    ],
    "wof:name":"Utsubo",
    "wof:placetype":"locality"
},
  "geometry": {"coordinates":[140.06599,35.26824000000001],"type":"Point"}
}