{
  "type": "Feature",
  "properties": {
    "gn:admin1_code":"32",
    "gn:admin2_code":"1852642.0",
    "gn:asciiname":"Settsu",
    "gn:country_code":"JP",
    "gn:dem":11,
    "gn:feature_class":"P",
    "gn:feature_code":"PPLA2",
    "gn:name":"Settsu",
    "gn:population":0,
    "gn:timezone":"Asia/Tokyo",
    "iso:country":"JP",
    "name:jpn_x_preferred":[
        "\u651d\u6d25"
    ],
    "name:jpn_x_variant":[
        "\u6442\u6d25"
    ],
    "name:und_x_variant":[
        "Settsu-no-kuni",
        "Settsu"
    ],
    "wof:name":"Settsu",
    "wof:placetype":"locality"
},
  "geometry": {"coordinates":[135.59512000000001,34.77819],"type":"Point"}
}