{
  "type": "Feature",
  "properties": {
    "gn:admin1_code":"22",
    "gn:admin2_code":"1851574.0",
    "gn:admin3_code":"26364.0",
    "gn:asciiname":"Minamikasagi",
    "gn:country_code":"JP",
    "gn:dem":57,
    "gn:feature_class":"P",
    "gn:feature_code":"PPL",
    "gn:name":"Minamikasagi",
    "gn:population":0,
    "gn:timezone":"Asia/Tokyo",
    "iso:country":"JP",
    "name:jpn_x_preferred":[
        "\u5357\u7b20\u7f6e"
    ],
    "name:und_x_variant":[
        "Kasagi",
        "Minami-kasagi",
        "Minamikasagi"
    ],
    "wof:name":"Minamikasagi",
    "wof:placetype":"locality"
},
  "geometry": {"coordinates":[135.93607,34.75396],"type":"Point"}
}