{
  "type": "Feature",
  "properties": {
    "gn:admin1_code":"36",
    "gn:admin2_code":"1854750.0",
    "gn:asciiname":"Oshirocho-oe",
    "gn:country_code":"JP",
    "gn:dem":260,
    "gn:feature_class":"P",
    "gn:feature_code":"PPL",
    "gn:name":"\u014cshiroch\u014d-\u014de",
    "gn:population":0,
    "gn:timezone":"Asia/Tokyo",
    "iso:country":"JP",
    "name:jpn_x_preferred":[
        "\u5927\u4ee3\u753a\u5927\u5bb6"
    ],
    "name:und_x_variant":[
        "\u014ce-hongo",
        "\u014ce",
        "\u014cshiroch\u014d-\u014de"
    ],
    "wof:name":"Oshirocho-oe",
    "wof:placetype":"locality"
},
  "geometry": {"coordinates":[132.40983,35.03021],"type":"Point"}
}