{
  "type": "Feature",
  "properties": {
    "gn:admin1_code":"18.0",
    "gn:admin2_code":"7383999.0",
    "gn:admin3_code":"46490.0",
    "gn:asciiname":"Uebai",
    "gn:country_code":"JP",
    "gn:dem":156,
    "gn:feature_class":"P",
    "gn:feature_code":"PPLL",
    "gn:name":"Uebai",
    "gn:population":0,
    "gn:timezone":"Asia/Tokyo",
    "iso:country":"JP",
    "name:jpn_x_preferred":[
        "\u4e0a\u539f"
    ],
    "name:und_x_variant":[
        "Uehara"
    ],
    "wof:name":"Uebai",
    "wof:placetype":"locality"
},
  "geometry": {"coordinates":[130.83337,31.18679],"type":"Point"}
}